{
  "type": "Feature",
  "properties": {
    "gn:admin1_code":"15",
    "gn:admin2_code":"PA",
    "gn:admin3_code":"82072.0",
    "gn:asciiname":"Rosa",
    "gn:country_code":"IT",
    "gn:dem":135,
    "gn:feature_class":"P",
    "gn:feature_code":"PPL",
    "gn:name":"Rosa",
    "gn:population":68,
    "gn:timezone":"Europe/Rome",
    "iso:country":"IT",
    "wof:name":"Rosa",
    "wof:placetype":"locality",
    "wof:population":68
},
  "geometry": {"coordinates":[13.21249,38.14224],"type":"Point"}
}