{
  "type": "Feature",
  "properties": {
    "gn:admin1_code":"12",
    "gn:admin2_code":"CN",
    "gn:admin3_code":"4130.0",
    "gn:asciiname":"Manei",
    "gn:country_code":"IT",
    "gn:dem":401,
    "gn:feature_class":"P",
    "gn:feature_code":"PPL",
    "gn:name":"Manei",
    "gn:population":82,
    "gn:timezone":"Europe/Rome",
    "iso:country":"IT",
    "wof:name":"Manei",
    "wof:placetype":"locality",
    "wof:population":82
},
  "geometry": {"coordinates":[7.8091,44.43074],"type":"Point"}
}