{
  "type": "Feature",
  "properties": {
    "gn:admin1_code":"16",
    "gn:admin2_code":"AR",
    "gn:admin3_code":"51002.0",
    "gn:asciiname":"Tregozzano",
    "gn:country_code":"IT",
    "gn:dem":270,
    "gn:feature_class":"P",
    "gn:feature_code":"PPL",
    "gn:name":"Tregozzano",
    "gn:population":32,
    "gn:timezone":"Europe/Rome",
    "iso:country":"IT",
    "wof:name":"Tregozzano",
    "wof:placetype":"locality",
    "wof:population":32
},
  "geometry": {"coordinates":[11.84361,43.40555],"type":"Point"}
}