{
  "type": "Feature",
  "properties": {
    "gn:admin1_code":"12",
    "gn:admin2_code":"CN",
    "gn:admin3_code":"4180.0",
    "gn:asciiname":"Borgo Po",
    "gn:country_code":"IT",
    "gn:dem":324,
    "gn:feature_class":"P",
    "gn:feature_code":"PPL",
    "gn:name":"Borgo Po",
    "gn:population":22,
    "gn:timezone":"Europe/Rome",
    "iso:country":"IT",
    "wof:name":"Borgo Po",
    "wof:placetype":"locality",
    "wof:population":22
},
  "geometry": {"coordinates":[7.43255,44.63701],"type":"Point"}
}