{
  "type": "Feature",
  "properties": {
    "gn:admin1_code":"1",
    "gn:admin2_code":"TE",
    "gn:admin3_code":"67018.0",
    "gn:asciiname":"Pizzicato",
    "gn:country_code":"IT",
    "gn:dem":221,
    "gn:feature_class":"P",
    "gn:feature_code":"PPL",
    "gn:name":"Pizzicato",
    "gn:population":83,
    "gn:timezone":"Europe/Rome",
    "iso:country":"IT",
    "wof:name":"Pizzicato",
    "wof:placetype":"locality",
    "wof:population":83
},
  "geometry": {"coordinates":[13.72147,42.58427],"type":"Point"}
}