{
  "type": "Feature",
  "properties": {
    "gn:admin1_code":"1",
    "gn:admin2_code":"TE",
    "gn:admin3_code":"67018.0",
    "gn:asciiname":"Pizzicato",
    "gn:country_code":"IT",
    "gn:dem":221,
    "gn:feature_class":"P",
    "gn:feature_code":"PPL",
    "gn:name":"Pizzicato",
    "gn:population":83,
    "gn:timezone":"Europe/Rome",
    "iso:country":"IT",
    "name:cat_x_preferred":[
        "Pizzicato"
    ],
    "name:ces_x_preferred":[
        "Pizzicato"
    ],
    "name:deu_x_preferred":[
        "Pizzicato"
    ],
    "name:ell_x_preferred":[
        "\u03a0\u03b9\u03c4\u03c3\u03b9\u03ba\u03ac\u03c4\u03bf"
    ],
    "name:epo_x_preferred":[
        "Pizzicato"
    ],
    "name:est_x_preferred":[
        "Pizzicato"
    ],
    "name:fas_x_preferred":[
        "\u067e\u06cc\u062a\u0632\u06cc\u06a9\u0627\u062a\u0648"
    ],
    "name:fin_x_preferred":[
        "Pizzicato"
    ],
    "name:fra_x_preferred":[
        "Pizzicato"
    ],
    "name:glg_x_preferred":[
        "Pizzicato"
    ],
    "name:heb_x_preferred":[
        "\u05e4\u05d9\u05e6\u05d9\u05e7\u05d8\u05d5"
    ],
    "name:hun_x_preferred":[
        "Pizzicato"
    ],
    "name:hye_x_preferred":[
        "\u054a\u056b\u0581\u0581\u056b\u056f\u0561\u057f\u0578"
    ],
    "name:ita_x_preferred":[
        "Pizzicato"
    ],
    "name:jpn_x_preferred":[
        "\u30d4\u30c3\u30c4\u30a3\u30ab\u30fc\u30c8"
    ],
    "name:kat_x_preferred":[
        "\u10de\u10d8\u10ea\u10d8\u10d9\u10d0\u10e2\u10dd"
    ],
    "name:kaz_x_preferred":[
        "\u041f\u0438\u0446\u0446\u0438\u043a\u0430\u0442\u043e"
    ],
    "name:kor_x_preferred":[
        "\ud53c\uce58\uce74\ud1a0"
    ],
    "name:nld_x_preferred":[
        "Pizzicato"
    ],
    "name:nno_x_preferred":[
        "Pizzicato"
    ],
    "name:nor_x_preferred":[
        "Pizzicato"
    ],
    "name:oci_x_preferred":[
        "Pizzicato"
    ],
    "name:pol_x_preferred":[
        "Pizzicato"
    ],
    "name:por_x_preferred":[
        "Pizzicato"
    ],
    "name:rus_x_preferred":[
        "\u041f\u0438\u0446\u0446\u0438\u043a\u0430\u0442\u043e"
    ],
    "name:slk_x_preferred":[
        "Pizzicato"
    ],
    "name:slv_x_preferred":[
        "Pizzicato"
    ],
    "name:spa_x_preferred":[
        "Pizzicato"
    ],
    "name:swe_x_preferred":[
        "Pizzicato"
    ],
    "name:ukr_x_preferred":[
        "\u041f\u0456\u0446\u0438\u043a\u0430\u0442\u043e"
    ],
    "wof:name":"Pizzicato",
    "wof:placetype":"locality",
    "wof:population":83
},
  "geometry": {"coordinates":[13.72147,42.58427],"type":"Point"}
}