{
  "type": "Feature",
  "properties": {
    "gn:admin1_code":"15.0",
    "gn:admin2_code":"ME",
    "gn:admin3_code":"83099.0",
    "gn:asciiname":"Moira",
    "gn:country_code":"IT",
    "gn:dem":868,
    "gn:feature_class":"P",
    "gn:feature_code":"PPL",
    "gn:name":"Moira",
    "gn:population":445,
    "gn:timezone":"Europe/Rome",
    "iso:country":"IT",
    "name:ceb_x_preferred":[
        "Moira"
    ],
    "name:ces_x_preferred":[
        "Moira"
    ],
    "name:deu_x_preferred":[
        "Moira"
    ],
    "name:ell_x_preferred":[
        "\u039c\u03bf\u03af\u03c1\u03b1"
    ],
    "name:fra_x_preferred":[
        "Moira"
    ],
    "name:ita_x_preferred":[
        "Moira"
    ],
    "name:jpn_x_preferred":[
        "\u30e2\u30a4\u30e9"
    ],
    "name:lit_x_preferred":[
        "Moira"
    ],
    "name:nld_x_preferred":[
        "Moira"
    ],
    "name:pol_x_preferred":[
        "Moira"
    ],
    "name:por_x_preferred":[
        "Moira"
    ],
    "name:rus_x_preferred":[
        "\u041c\u043e\u0439\u0440\u0430"
    ],
    "name:swe_x_preferred":[
        "Moira"
    ],
    "wof:name":"Moira",
    "wof:placetype":"locality",
    "wof:population":445
},
  "geometry": {"coordinates":[14.84484,38.03133],"type":"Point"}
}