{
  "type": "Feature",
  "properties": {
    "gn:admin1_code":"9",
    "gn:admin2_code":"BG",
    "gn:admin3_code":"16072.0",
    "gn:asciiname":"Rota-Bonasio-Locatelli",
    "gn:country_code":"IT",
    "gn:dem":219,
    "gn:feature_class":"P",
    "gn:feature_code":"PPL",
    "gn:name":"Rota-Bonasio-Locatelli",
    "gn:population":26,
    "gn:timezone":"Europe/Rome",
    "iso:country":"IT",
    "wof:name":"Rota-Bonasio-Locatelli",
    "wof:placetype":"locality",
    "wof:population":26
},
  "geometry": {"coordinates":[9.53337,45.6759],"type":"Point"}
}