{
  "type": "Feature",
  "properties": {
    "gn:admin1_code":"5",
    "gn:admin2_code":"PR",
    "gn:admin3_code":"34017.0",
    "gn:asciiname":"Vizzola",
    "gn:country_code":"IT",
    "gn:dem":203,
    "gn:feature_class":"P",
    "gn:feature_code":"PPL",
    "gn:name":"Vizzola",
    "gn:population":37,
    "gn:timezone":"Europe/Rome",
    "iso:country":"IT",
    "wof:name":"Vizzola",
    "wof:placetype":"locality",
    "wof:population":37
},
  "geometry": {"coordinates":[10.13171,44.69895],"type":"Point"}
}