{
  "type": "Feature",
  "properties": {
    "gn:admin1_code":"1.0",
    "gn:admin2_code":"AQ",
    "gn:admin3_code":"66020.0",
    "gn:asciiname":"Corcumello",
    "gn:country_code":"IT",
    "gn:dem":782,
    "gn:elevation":"744.0",
    "gn:feature_class":"P",
    "gn:feature_code":"PPL",
    "gn:name":"Corcumello",
    "gn:population":239,
    "gn:timezone":"Europe/Rome",
    "iso:country":"IT",
    "wof:name":"Corcumello",
    "wof:placetype":"locality",
    "wof:population":239
},
  "geometry": {"coordinates":[13.34645,42.00831],"type":"Point"}
}