{
  "type": "Feature",
  "properties": {
    "gn:admin1_code":"9",
    "gn:admin2_code":"LC",
    "gn:admin3_code":"97033.0",
    "gn:asciiname":"Marconaga",
    "gn:country_code":"IT",
    "gn:dem":424,
    "gn:feature_class":"P",
    "gn:feature_code":"PPL",
    "gn:name":"Marconaga",
    "gn:population":127,
    "gn:timezone":"Europe/Rome",
    "iso:country":"IT",
    "wof:name":"Marconaga",
    "wof:placetype":"locality",
    "wof:population":127
},
  "geometry": {"coordinates":[9.35925,45.77705],"type":"Point"}
}