{
  "type": "Feature",
  "properties": {
    "gn:admin1_code":"16",
    "gn:admin2_code":"PT",
    "gn:admin3_code":"47023.0",
    "gn:asciiname":"Rivoreta",
    "gn:country_code":"IT",
    "gn:dem":901,
    "gn:feature_class":"P",
    "gn:feature_code":"PPL",
    "gn:name":"Rivoreta",
    "gn:population":33,
    "gn:timezone":"Europe/Rome",
    "iso:country":"IT",
    "wof:name":"Rivoreta",
    "wof:placetype":"locality",
    "wof:population":33
},
  "geometry": {"coordinates":[10.71938,44.13077],"type":"Point"}
}