{
  "type": "Feature",
  "properties": {
    "gn:admin1_code":"1.0",
    "gn:admin2_code":"CH",
    "gn:admin3_code":"69043.0",
    "gn:asciiname":"Caporosso",
    "gn:country_code":"IT",
    "gn:dem":423,
    "gn:feature_class":"P",
    "gn:feature_code":"PPL",
    "gn:name":"Caporosso",
    "gn:population":421,
    "gn:timezone":"Europe/Rome",
    "iso:country":"IT",
    "wof:name":"Caporosso",
    "wof:placetype":"locality",
    "wof:population":421
},
  "geometry": {"coordinates":[14.20698,42.20189],"type":"Point"}
}