{
  "type": "Feature",
  "properties": {
    "gn:admin1_code":"11.0",
    "gn:admin2_code":"IS",
    "gn:admin3_code":"94019.0",
    "gn:asciiname":"Mennella",
    "gn:country_code":"IT",
    "gn:dem":601,
    "gn:feature_class":"P",
    "gn:feature_code":"PPL",
    "gn:name":"Mennella",
    "gn:population":21,
    "gn:timezone":"Europe/Rome",
    "iso:country":"IT",
    "wof:name":"Mennella",
    "wof:placetype":"locality",
    "wof:population":21
},
  "geometry": {"coordinates":[14.05162,41.57669],"type":"Point"}
}