{
  "type": "Feature",
  "properties": {
    "gn:admin1_code":"16",
    "gn:admin2_code":"LU",
    "gn:admin3_code":"46022.0",
    "gn:asciiname":"Ville",
    "gn:country_code":"IT",
    "gn:dem":422,
    "gn:feature_class":"P",
    "gn:feature_code":"PPL",
    "gn:name":"Ville",
    "gn:population":24,
    "gn:timezone":"Europe/Rome",
    "iso:country":"IT",
    "wof:name":"Ville",
    "wof:placetype":"locality",
    "wof:population":24
},
  "geometry": {"coordinates":[10.47412,43.9811],"type":"Point"}
}