{
  "type": "Feature",
  "properties": {
    "gn:elevation":23,
    "gn:population":1229,
    "iso:country":"IT",
    "name:ita_x_preferred":[
        "Migliarina"
    ],
    "name:ita_x_variant":[
        "Migliorina"
    ],
    "name:unk_x_variant":[
        "Migliorina"
    ],
    "qs:a0":"Italia",
    "qs:a1":"*Modena",
    "qs:a1r":"0Emilia-Romagna",
    "qs:adm0":"Italia",
    "qs:la_lc":"*",
    "qs:level":"locality",
    "qs:loc":"Migliarina",
    "qs:loc_alt":"Migliarina",
    "qs:pop":0,
    "qs:type":"buffered point",
    "wof:lang":[
        "ita"
    ],
    "wof:name":"Migliarina",
    "wof:placetype":"locality",
    "wof:population":1229
},
  "geometry": {"coordinates":[10.83595,44.805309],"type":"Point"}
}