{
  "type": "Feature",
  "properties": {
    "gn:elevation":23,
    "gn:population":1229,
    "iso:country":"IT",
    "name:cat_x_preferred":[
        "Migliarina"
    ],
    "name:ceb_x_preferred":[
        "Migliarina"
    ],
    "name:ces_x_preferred":[
        "Migliarina"
    ],
    "name:dan_x_preferred":[
        "Migliarina"
    ],
    "name:eng_x_preferred":[
        "Migliarina"
    ],
    "name:eus_x_preferred":[
        "Migliarina"
    ],
    "name:fin_x_preferred":[
        "Migliarina"
    ],
    "name:fra_x_preferred":[
        "Migliarina"
    ],
    "name:ind_x_preferred":[
        "Migliarina"
    ],
    "name:ita_x_preferred":[
        "Migliarina"
    ],
    "name:ita_x_variant":[
        "Migliorina"
    ],
    "name:nld_x_preferred":[
        "Migliarina"
    ],
    "name:nno_x_preferred":[
        "Migliarina"
    ],
    "name:nob_x_preferred":[
        "Migliarina"
    ],
    "name:oci_x_preferred":[
        "Migliarina"
    ],
    "name:pol_x_preferred":[
        "Migliarina"
    ],
    "name:por_x_preferred":[
        "Migliarina"
    ],
    "name:ron_x_preferred":[
        "Migliarina"
    ],
    "name:slk_x_preferred":[
        "Migliarina"
    ],
    "name:slv_x_preferred":[
        "Migliarina"
    ],
    "name:spa_x_preferred":[
        "Migliarina"
    ],
    "name:srp_x_preferred":[
        "Migliarina"
    ],
    "name:swe_x_preferred":[
        "Migliarina"
    ],
    "name:tgl_x_preferred":[
        "Migliarina"
    ],
    "name:tur_x_preferred":[
        "Migliarina"
    ],
    "name:war_x_preferred":[
        "Migliarina"
    ],
    "qs:a0":"Italia",
    "qs:a1":"*Modena",
    "qs:a1r":"0Emilia-Romagna",
    "qs:adm0":"Italia",
    "qs:la_lc":"*",
    "qs:level":"locality",
    "qs:loc":"Migliarina",
    "qs:loc_alt":"Migliarina",
    "qs:pop":0,
    "qs:type":"buffered point",
    "wof:name":"Migliarina",
    "wof:placetype":"locality",
    "wof:population":1229
},
  "geometry": {"coordinates":[10.83595,44.805309],"type":"Point"}
}