{
  "type": "Feature",
  "properties": {
    "gn:admin1_code":"8.0",
    "gn:admin2_code":"GE",
    "gn:admin3_code":"10066.0",
    "gn:asciiname":"Costaclavarezza",
    "gn:country_code":"IT",
    "gn:dem":724,
    "gn:feature_class":"P",
    "gn:feature_code":"PPL",
    "gn:name":"Costaclavarezza",
    "gn:population":2,
    "gn:timezone":"Europe/Rome",
    "iso:country":"IT",
    "wof:name":"Costaclavarezza",
    "wof:placetype":"locality",
    "wof:population":2
},
  "geometry": {"coordinates":[9.06106,44.57646],"type":"Point"}
}