{
  "type": "Feature",
  "properties": {
    "gn:admin1_code":"7",
    "gn:admin2_code":"FR",
    "gn:admin3_code":"60018.0",
    "gn:asciiname":"Serravoglia",
    "gn:country_code":"IT",
    "gn:dem":405,
    "gn:feature_class":"P",
    "gn:feature_code":"PPL",
    "gn:name":"Serravoglia",
    "gn:population":84,
    "gn:timezone":"Europe/Rome",
    "iso:country":"IT",
    "wof:name":"Serravoglia",
    "wof:placetype":"locality",
    "wof:population":84
},
  "geometry": {"coordinates":[13.7259,41.65826],"type":"Point"}
}