{
  "type": "Feature",
  "properties": {
    "gn:admin1_code":"6.0",
    "gn:admin2_code":"UD",
    "gn:admin3_code":"30036.0",
    "gn:asciiname":"Colloredo",
    "gn:country_code":"IT",
    "gn:dem":267,
    "gn:elevation":"272.0",
    "gn:feature_class":"P",
    "gn:feature_code":"PPL",
    "gn:name":"Colloredo",
    "gn:population":16,
    "gn:timezone":"Europe/Rome",
    "iso:country":"IT",
    "name:ces_x_preferred":[
        "Colloredo"
    ],
    "name:ita_x_preferred":[
        "Colloredo"
    ],
    "name:swe_x_preferred":[
        "Colloredo"
    ],
    "wof:name":"Colloredo",
    "wof:placetype":"locality",
    "wof:population":16
},
  "geometry": {"coordinates":[13.38342,46.13463],"type":"Point"}
}