{
  "type": "Feature",
  "properties": {
    "gn:admin1_code":"7.0",
    "gn:admin2_code":"FR",
    "gn:admin3_code":"60010.0",
    "gn:asciiname":"Forleta",
    "gn:country_code":"IT",
    "gn:dem":758,
    "gn:feature_class":"P",
    "gn:feature_code":"PPL",
    "gn:name":"Forleta",
    "gn:population":0,
    "gn:timezone":"Europe/Rome",
    "iso:country":"IT",
    "wof:name":"Forleta",
    "wof:placetype":"locality"
},
  "geometry": {"coordinates":[13.66667,41.63333],"type":"Point"}
}