{
  "type": "Feature",
  "properties": {
    "gn:admin1_code":"20",
    "gn:admin2_code":"VI",
    "gn:admin3_code":"24063.0",
    "gn:asciiname":"Giovanni Xxiii",
    "gn:country_code":"IT",
    "gn:dem":123,
    "gn:feature_class":"P",
    "gn:feature_code":"PPL",
    "gn:name":"Giovanni Xxiii",
    "gn:population":231,
    "gn:timezone":"Europe/Rome",
    "iso:country":"IT",
    "wof:name":"Giovanni Xxiii",
    "wof:placetype":"locality",
    "wof:population":231
},
  "geometry": {"coordinates":[11.38831,45.65247],"type":"Point"}
}