{
  "type": "Feature",
  "properties": {
    "gn:admin1_code":"9",
    "gn:admin2_code":"PV",
    "gn:admin3_code":"18133.0",
    "gn:asciiname":"Coste",
    "gn:country_code":"IT",
    "gn:dem":58,
    "gn:feature_class":"P",
    "gn:feature_code":"PPL",
    "gn:name":"Coste",
    "gn:population":26,
    "gn:timezone":"Europe/Rome",
    "iso:country":"IT",
    "wof:name":"Coste",
    "wof:placetype":"locality",
    "wof:population":26
},
  "geometry": {"coordinates":[9.28918,45.1063],"type":"Point"}
}