{
  "type": "Feature",
  "properties": {
    "gn:admin1_code":"12",
    "gn:admin2_code":"TO",
    "gn:admin3_code":"1294.0",
    "gn:asciiname":"Case Cocetti",
    "gn:country_code":"IT",
    "gn:dem":154,
    "gn:feature_class":"P",
    "gn:feature_code":"PPL",
    "gn:name":"Case Cocetti",
    "gn:population":67,
    "gn:timezone":"Europe/Rome",
    "iso:country":"IT",
    "wof:name":"Case Cocetti",
    "wof:placetype":"locality",
    "wof:population":67
},
  "geometry": {"coordinates":[8.13166,45.15835],"type":"Point"}
}