{
  "type": "Feature",
  "properties": {
    "gn:admin1_code":"3.0",
    "gn:admin2_code":"RC",
    "gn:admin3_code":"80085.0",
    "gn:asciiname":"Castagnarella",
    "gn:country_code":"IT",
    "gn:dem":726,
    "gn:feature_class":"P",
    "gn:feature_code":"PPL",
    "gn:name":"Castagnarella",
    "gn:population":0,
    "gn:timezone":"Europe/Rome",
    "iso:country":"IT",
    "wof:name":"Castagnarella",
    "wof:placetype":"locality"
},
  "geometry": {"coordinates":[15.78333,38.23333],"type":"Point"}
}