{
  "type": "Feature",
  "properties": {
    "gn:admin1_code":"16",
    "gn:admin2_code":"LU",
    "gn:admin3_code":"46005.0",
    "gn:asciiname":"Migliano",
    "gn:country_code":"IT",
    "gn:dem":357,
    "gn:feature_class":"P",
    "gn:feature_code":"PPL",
    "gn:name":"Migliano",
    "gn:population":67,
    "gn:timezone":"Europe/Rome",
    "iso:country":"IT",
    "wof:name":"Migliano",
    "wof:placetype":"locality",
    "wof:population":67
},
  "geometry": {"coordinates":[10.38047,43.90997],"type":"Point"}
}