{
  "type": "Feature",
  "properties": {
    "gn:admin1_code":"9.0",
    "gn:admin2_code":"CO",
    "gn:admin3_code":"13085.0",
    "gn:asciiname":"Cavia",
    "gn:cc2":"IT",
    "gn:country_code":"IT",
    "gn:dem":1306,
    "gn:feature_class":"P",
    "gn:feature_code":"PPL",
    "gn:name":"Cavia",
    "gn:population":0,
    "gn:timezone":"Europe/Rome",
    "iso:country":"IT",
    "name:und_x_variant":[
        "Cama",
        "Cavia"
    ],
    "wof:name":"Cavia",
    "wof:placetype":"locality"
},
  "geometry": {"coordinates":[9.16667,46.06667],"type":"Point"}
}