{
  "type": "Feature",
  "properties": {
    "gn:admin1_code":"5",
    "gn:admin2_code":"MO",
    "gn:admin3_code":"36027.0",
    "gn:asciiname":"Rubbiara",
    "gn:country_code":"IT",
    "gn:dem":30,
    "gn:feature_class":"P",
    "gn:feature_code":"PPL",
    "gn:name":"Rubbiara",
    "gn:population":58,
    "gn:timezone":"Europe/Rome",
    "iso:country":"IT",
    "wof:name":"Rubbiara",
    "wof:placetype":"locality",
    "wof:population":58
},
  "geometry": {"coordinates":[11.03961,44.64944000000001],"type":"Point"}
}