{
  "type": "Feature",
  "properties": {
    "gn:admin1_code":"5",
    "gn:admin2_code":"PR",
    "gn:admin3_code":"34049.0",
    "gn:asciiname":"Palasone",
    "gn:country_code":"IT",
    "gn:dem":34,
    "gn:feature_class":"P",
    "gn:feature_code":"PPL",
    "gn:name":"Palasone",
    "gn:population":51,
    "gn:timezone":"Europe/Rome",
    "iso:country":"IT",
    "wof:name":"Palasone",
    "wof:placetype":"locality",
    "wof:population":51
},
  "geometry": {"coordinates":[10.2418,44.95807],"type":"Point"}
}