{
  "type": "Feature",
  "properties": {
    "gn:admin1_code":"16",
    "gn:admin2_code":"GR",
    "gn:admin3_code":"53013.0",
    "gn:asciiname":"Podere Corso",
    "gn:country_code":"IT",
    "gn:dem":255,
    "gn:feature_class":"P",
    "gn:feature_code":"PPL",
    "gn:name":"Podere Corso",
    "gn:population":12,
    "gn:timezone":"Europe/Rome",
    "iso:country":"IT",
    "wof:name":"Podere Corso",
    "wof:placetype":"locality",
    "wof:population":12
},
  "geometry": {"coordinates":[11.25655,42.66367],"type":"Point"}
}