{
  "type": "Feature",
  "properties": {
    "gn:admin1_code":"20",
    "gn:admin2_code":"RO",
    "gn:admin3_code":"29049.0",
    "gn:asciiname":"Preguerre",
    "gn:country_code":"IT",
    "gn:dem":3,
    "gn:feature_class":"P",
    "gn:feature_code":"PPL",
    "gn:name":"Preguerre",
    "gn:population":19,
    "gn:timezone":"Europe/Rome",
    "iso:country":"IT",
    "wof:name":"Preguerre",
    "wof:placetype":"locality",
    "wof:population":19
},
  "geometry": {"coordinates":[11.70699,45.02279],"type":"Point"}
}