{
  "type": "Feature",
  "properties": {
    "gn:admin1_code":"20",
    "gn:admin2_code":"VE",
    "gn:admin3_code":"27034.0",
    "gn:asciiname":"Cavarzerani",
    "gn:country_code":"IT",
    "gn:dem":1,
    "gn:feature_class":"P",
    "gn:feature_code":"PPL",
    "gn:name":"Cavarzerani",
    "gn:population":45,
    "gn:timezone":"Europe/Rome",
    "iso:country":"IT",
    "wof:name":"Cavarzerani",
    "wof:placetype":"locality",
    "wof:population":45
},
  "geometry": {"coordinates":[12.97345,45.7573],"type":"Point"}
}