{
  "type": "Feature",
  "properties": {
    "gn:admin1_code":"3.0",
    "gn:admin2_code":"CS",
    "gn:admin3_code":"78002.0",
    "gn:asciiname":"Marina",
    "gn:country_code":"IT",
    "gn:dem":7,
    "gn:feature_class":"P",
    "gn:feature_code":"PPL",
    "gn:name":"Marina",
    "gn:population":362,
    "gn:timezone":"Europe/Rome",
    "iso:country":"IT",
    "wof:name":"Marina",
    "wof:placetype":"locality",
    "wof:population":362
},
  "geometry": {"coordinates":[15.95184,39.49325],"type":"Point"}
}