{
  "type": "Feature",
  "properties": {
    "gn:admin1_code":"6.0",
    "gn:admin2_code":"TS",
    "gn:admin3_code":"32004.0",
    "gn:asciiname":"San Giuseppe della Chiusa",
    "gn:cc2":"IT",
    "gn:country_code":"IT",
    "gn:dem":159,
    "gn:elevation":"164.0",
    "gn:feature_class":"P",
    "gn:feature_code":"PPL",
    "gn:name":"San Giuseppe della Chiusa",
    "gn:population":405,
    "gn:timezone":"Europe/Rome",
    "iso:country":"IT",
    "name:und_x_variant":[
        "Ricmanje",
        "San Giuseppe della Chiusa",
        "San Giuseppe"
    ],
    "wof:name":"San Giuseppe della Chiusa",
    "wof:placetype":"locality",
    "wof:population":405
},
  "geometry": {"coordinates":[13.84075,45.62622],"type":"Point"}
}