{
  "type": "Feature",
  "properties": {
    "gn:admin1_code":"5",
    "gn:admin2_code":"PR",
    "gn:admin3_code":"34046.0",
    "gn:asciiname":"Scortichiere",
    "gn:country_code":"IT",
    "gn:dem":618,
    "gn:feature_class":"P",
    "gn:feature_code":"PPLL",
    "gn:name":"Scortichiere",
    "gn:population":10,
    "gn:timezone":"Europe/Rome",
    "iso:country":"IT",
    "wof:name":"Scortichiere",
    "wof:placetype":"locality",
    "wof:population":10
},
  "geometry": {"coordinates":[9.83124,44.61875],"type":"Point"}
}