{
  "type": "Feature",
  "properties": {
    "gn:admin1_code":"3",
    "gn:admin2_code":"CS",
    "gn:admin3_code":"78125.0",
    "gn:asciiname":"Tufo",
    "gn:country_code":"IT",
    "gn:dem":100,
    "gn:feature_class":"P",
    "gn:feature_code":"PPL",
    "gn:name":"Tufo",
    "gn:population":13,
    "gn:timezone":"Europe/Rome",
    "iso:country":"IT",
    "name:azb_x_preferred":[
        "\u062a\u0648\u0641\u0648"
    ],
    "name:bel_x_preferred":[
        "\u0422\u0443\u0444\u0430"
    ],
    "name:bul_x_preferred":[
        "\u0422\u0443\u0444\u043e"
    ],
    "name:ceb_x_preferred":[
        "Tufo"
    ],
    "name:deu_x_preferred":[
        "Tufo"
    ],
    "name:epo_x_preferred":[
        "Tufo"
    ],
    "name:eus_x_preferred":[
        "Tufo"
    ],
    "name:fas_x_preferred":[
        "\u062a\u0648\u0641\u0648"
    ],
    "name:fra_x_preferred":[
        "Tufo"
    ],
    "name:hun_x_preferred":[
        "Tufo"
    ],
    "name:hye_x_preferred":[
        "\u054f\u0578\u0582\u0586\u0578"
    ],
    "name:ina_x_preferred":[
        "Tufo"
    ],
    "name:ita_x_preferred":[
        "Tufo"
    ],
    "name:jpn_x_preferred":[
        "\u30c8\u30a5\u30fc\u30d5\u30a9"
    ],
    "name:kaz_x_preferred":[
        "\u0422\u0443\u0444\u043e"
    ],
    "name:lat_x_preferred":[
        "Tufus"
    ],
    "name:lmo_x_preferred":[
        "Tufo"
    ],
    "name:mkd_x_preferred":[
        "\u0422\u0443\u0444\u043e"
    ],
    "name:msa_x_preferred":[
        "Tufo"
    ],
    "name:nap_x_preferred":[
        "Tufo"
    ],
    "name:nld_x_preferred":[
        "Tufo"
    ],
    "name:pms_x_preferred":[
        "Tufo"
    ],
    "name:pol_x_preferred":[
        "Tufo"
    ],
    "name:por_x_preferred":[
        "Tufo"
    ],
    "name:ron_x_preferred":[
        "Tufo"
    ],
    "name:rus_x_preferred":[
        "\u0422\u0443\u0444\u043e"
    ],
    "name:scn_x_preferred":[
        "Tufu"
    ],
    "name:spa_x_preferred":[
        "Tufo"
    ],
    "name:srp_x_preferred":[
        "\u0422\u0443\u0444\u043e"
    ],
    "name:tgl_x_preferred":[
        "Tufo"
    ],
    "name:ukr_x_preferred":[
        "\u0422\u0443\u0444\u043e"
    ],
    "name:uzb_x_preferred":[
        "Tufo"
    ],
    "name:vec_x_preferred":[
        "Tufo"
    ],
    "name:vol_x_preferred":[
        "Tufo"
    ],
    "name:war_x_preferred":[
        "Tufo"
    ],
    "wof:name":"Tufo",
    "wof:placetype":"locality",
    "wof:population":13
},
  "geometry": {"coordinates":[15.77973,39.83652],"type":"Point"}
}