{
  "type": "Feature",
  "properties": {
    "gn:admin1_code":"3",
    "gn:admin2_code":"CS",
    "gn:admin3_code":"78125.0",
    "gn:asciiname":"Tufo",
    "gn:country_code":"IT",
    "gn:dem":100,
    "gn:feature_class":"P",
    "gn:feature_code":"PPL",
    "gn:name":"Tufo",
    "gn:population":13,
    "gn:timezone":"Europe/Rome",
    "iso:country":"IT",
    "wof:name":"Tufo",
    "wof:placetype":"locality",
    "wof:population":13
},
  "geometry": {"coordinates":[15.77973,39.83652],"type":"Point"}
}