{
  "type": "Feature",
  "properties": {
    "gn:admin1_code":"12.0",
    "gn:admin2_code":"VB",
    "gn:admin3_code":"103041.0",
    "gn:asciiname":"Alpe Campo di Sotto",
    "gn:cc2":"IT",
    "gn:country_code":"IT",
    "gn:dem":1576,
    "gn:feature_class":"P",
    "gn:feature_code":"PPL",
    "gn:name":"Alpe Campo di Sotto",
    "gn:population":0,
    "gn:timezone":"Europe/Rome",
    "iso:country":"IT",
    "name:und_x_variant":[
        "Alpe Campo",
        "Alpe Campo di Sotto"
    ],
    "wof:name":"Alpe Campo di Sotto",
    "wof:placetype":"locality"
},
  "geometry": {"coordinates":[8.45,46.05],"type":"Point"}
}