{
  "type": "Feature",
  "properties": {
    "gn:admin1_code":"8.0",
    "gn:admin2_code":"GE",
    "gn:admin3_code":"10031.0",
    "gn:asciiname":"Tasso",
    "gn:country_code":"IT",
    "gn:dem":413,
    "gn:elevation":"388.0",
    "gn:feature_class":"P",
    "gn:feature_code":"PPL",
    "gn:name":"Tasso",
    "gn:population":55,
    "gn:timezone":"Europe/Rome",
    "iso:country":"IT",
    "wof:name":"Tasso",
    "wof:placetype":"locality",
    "wof:population":55
},
  "geometry": {"coordinates":[9.13629,44.45026],"type":"Point"}
}