{
  "type": "Feature",
  "properties": {
    "gn:admin1_code":"5.0",
    "gn:admin2_code":"FC",
    "gn:admin3_code":"40001.0",
    "gn:asciiname":"Montegranelli",
    "gn:country_code":"IT",
    "gn:dem":709,
    "gn:elevation":"730.0",
    "gn:feature_class":"P",
    "gn:feature_code":"PPL",
    "gn:name":"Montegranelli",
    "gn:population":11,
    "gn:timezone":"Europe/Rome",
    "iso:country":"IT",
    "wof:name":"Montegranelli",
    "wof:placetype":"locality",
    "wof:population":11
},
  "geometry": {"coordinates":[11.97639,43.87958],"type":"Point"}
}