{
  "type": "Feature",
  "properties": {
    "gn:admin1_code":"12",
    "gn:admin2_code":"BI",
    "gn:admin3_code":"96028.0",
    "gn:asciiname":"Angio",
    "gn:country_code":"IT",
    "gn:dem":478,
    "gn:feature_class":"P",
    "gn:feature_code":"PPL",
    "gn:name":"Angio",
    "gn:population":24,
    "gn:timezone":"Europe/Rome",
    "iso:country":"IT",
    "wof:name":"Angio",
    "wof:placetype":"locality",
    "wof:population":24
},
  "geometry": {"coordinates":[7.97281,45.53984000000001],"type":"Point"}
}