{
  "type": "Feature",
  "properties": {
    "gn:admin1_code":"20",
    "gn:admin2_code":"PD",
    "gn:admin3_code":"28088.0",
    "gn:asciiname":"Correzzo",
    "gn:country_code":"IT",
    "gn:dem":3,
    "gn:feature_class":"P",
    "gn:feature_code":"PPL",
    "gn:name":"Correzzo",
    "gn:population":90,
    "gn:timezone":"Europe/Rome",
    "iso:country":"IT",
    "wof:name":"Correzzo",
    "wof:placetype":"locality",
    "wof:population":90
},
  "geometry": {"coordinates":[11.77012,45.15452],"type":"Point"}
}