{
  "type": "Feature",
  "properties": {
    "gn:admin1_code":"7.0",
    "gn:admin2_code":"RI",
    "gn:admin3_code":"57016.0",
    "gn:asciiname":"Calcariola",
    "gn:country_code":"IT",
    "gn:dem":745,
    "gn:elevation":"776.0",
    "gn:feature_class":"P",
    "gn:feature_code":"PPL",
    "gn:name":"Calcariola",
    "gn:population":57,
    "gn:timezone":"Europe/Rome",
    "iso:country":"IT",
    "wof:name":"Calcariola",
    "wof:placetype":"locality",
    "wof:population":57
},
  "geometry": {"coordinates":[12.97305,42.35695],"type":"Point"}
}