{
  "type": "Feature",
  "properties": {
    "gn:admin1_code":"18",
    "gn:admin2_code":"TR",
    "gn:admin3_code":"55010.0",
    "gn:asciiname":"Localita Cornale",
    "gn:country_code":"IT",
    "gn:dem":550,
    "gn:feature_class":"P",
    "gn:feature_code":"PPL",
    "gn:name":"Localit\u00e0 Cornale",
    "gn:population":21,
    "gn:timezone":"Europe/Rome",
    "iso:country":"IT",
    "name:und_x_variant":[
        "Localit\u00e0 Cornale"
    ],
    "wof:name":"Localita Cornale",
    "wof:placetype":"locality",
    "wof:population":21
},
  "geometry": {"coordinates":[11.98548,42.75084],"type":"Point"}
}