{
  "type": "Feature",
  "properties": {
    "gn:elevation":644,
    "gn:population":546,
    "iso:country":"IT",
    "name:ara_x_preferred":[
        "\u0641\u0648\u0633\u0627"
    ],
    "name:azb_x_preferred":[
        "\u0641\u0648\u0633\u0627"
    ],
    "name:bcl_x_preferred":[
        "Fossa"
    ],
    "name:bul_x_preferred":[
        "\u0424\u043e\u0441\u0430"
    ],
    "name:ceb_x_preferred":[
        "Fossa"
    ],
    "name:deu_x_preferred":[
        "Fossa"
    ],
    "name:eng_x_preferred":[
        "Fossa"
    ],
    "name:epo_x_preferred":[
        "Fossa"
    ],
    "name:eus_x_preferred":[
        "Fossa"
    ],
    "name:fas_x_preferred":[
        "\u0641\u0648\u0633\u0627"
    ],
    "name:fra_x_preferred":[
        "Fossa"
    ],
    "name:hun_x_preferred":[
        "Fossa"
    ],
    "name:hye_x_preferred":[
        "\u0556\u0578\u057d\u057d\u0561"
    ],
    "name:ina_x_preferred":[
        "Fossa"
    ],
    "name:ita_x_preferred":[
        "Fossa"
    ],
    "name:jpn_x_preferred":[
        "\u30d5\u30a9\u30c3\u30b5"
    ],
    "name:kor_x_preferred":[
        "\ud3ec\uc0ac"
    ],
    "name:lat_x_preferred":[
        "Fossa"
    ],
    "name:lmo_x_preferred":[
        "Fossa"
    ],
    "name:msa_x_preferred":[
        "Fossa"
    ],
    "name:nan_x_preferred":[
        "Fossa"
    ],
    "name:nap_x_preferred":[
        "Fossa"
    ],
    "name:nld_x_preferred":[
        "Fossa"
    ],
    "name:pms_x_preferred":[
        "Fossa"
    ],
    "name:pol_x_preferred":[
        "Fossa"
    ],
    "name:por_x_preferred":[
        "Fossa"
    ],
    "name:ron_x_preferred":[
        "Fossa"
    ],
    "name:rus_x_preferred":[
        "\u0424\u043e\u0441\u0441\u0430"
    ],
    "name:scn_x_preferred":[
        "Fossa"
    ],
    "name:spa_x_preferred":[
        "Fossa"
    ],
    "name:srp_x_preferred":[
        "Fossa"
    ],
    "name:swe_x_preferred":[
        "Fossa"
    ],
    "name:ukr_x_preferred":[
        "\u0424\u043e\u0441\u0441\u0430"
    ],
    "name:uzb_x_preferred":[
        "Fossa"
    ],
    "name:vie_x_preferred":[
        "Fossa"
    ],
    "name:vol_x_preferred":[
        "Fossa"
    ],
    "name:war_x_preferred":[
        "Fossa"
    ],
    "name:zho_x_preferred":[
        "\u798f\u8428"
    ],
    "qs:a0":"Italia",
    "qs:a1":"*L'Aquila",
    "qs:a1r":"0Abruzzo",
    "qs:adm0":"Italia",
    "qs:la_lc":"*",
    "qs:level":"locality",
    "qs:loc":"Fossa",
    "qs:loc_alt":"Fossa",
    "qs:pop":0,
    "qs:type":"buffered point",
    "wof:lang":[
        "ita"
    ],
    "wof:name":"Fossa",
    "wof:placetype":"locality",
    "wof:population":546
},
  "geometry": {"coordinates":[13.48847,42.298321],"type":"Point"}
}