{
  "type": "Feature",
  "properties": {
    "gn:admin1_code":"17",
    "gn:admin2_code":"BZ",
    "gn:admin3_code":"21087.0",
    "gn:asciiname":"Leiter",
    "gn:country_code":"IT",
    "gn:dem":427,
    "gn:feature_class":"P",
    "gn:feature_code":"PPL",
    "gn:name":"Leiter",
    "gn:population":25,
    "gn:timezone":"Europe/Rome",
    "iso:country":"IT",
    "wof:name":"Leiter",
    "wof:placetype":"locality",
    "wof:population":25
},
  "geometry": {"coordinates":[11.18228,46.68545],"type":"Point"}
}