{
  "type": "Feature",
  "properties": {
    "gn:admin1_code":"20",
    "gn:admin2_code":"TV",
    "gn:admin3_code":"26078.0",
    "gn:asciiname":"Loc. Bardiere",
    "gn:country_code":"IT",
    "gn:dem":81,
    "gn:feature_class":"P",
    "gn:feature_code":"PPL",
    "gn:name":"Loc. Bardiere",
    "gn:population":17,
    "gn:timezone":"Europe/Rome",
    "iso:country":"IT",
    "wof:name":"Loc. Bardiere",
    "wof:placetype":"locality",
    "wof:population":17
},
  "geometry": {"coordinates":[12.39487,45.97063],"type":"Point"}
}