{
  "type": "Feature",
  "properties": {
    "gn:admin1_code":"7.0",
    "gn:admin2_code":"RI",
    "gn:admin3_code":"57033.0",
    "gn:asciiname":"Case Nuove",
    "gn:country_code":"IT",
    "gn:dem":930,
    "gn:feature_class":"P",
    "gn:feature_code":"PPL",
    "gn:name":"Case Nuove",
    "gn:population":0,
    "gn:timezone":"Europe/Rome",
    "iso:country":"IT",
    "wof:name":"Case Nuove",
    "wof:placetype":"locality"
},
  "geometry": {"coordinates":[12.98333,42.56667],"type":"Point"}
}