{
  "type": "Feature",
  "properties": {
    "gn:admin1_code":"20",
    "gn:admin2_code":"VR",
    "gn:admin3_code":"23078.0",
    "gn:asciiname":"Cona",
    "gn:country_code":"IT",
    "gn:dem":873,
    "gn:feature_class":"P",
    "gn:feature_code":"PPL",
    "gn:name":"Cona",
    "gn:population":63,
    "gn:timezone":"Europe/Rome",
    "iso:country":"IT",
    "name:ceb_x_preferred":[
        "Cona"
    ],
    "name:glg_x_preferred":[
        "Cona"
    ],
    "name:hye_x_preferred":[
        "\u053f\u0578\u0576\u0561"
    ],
    "name:ita_x_preferred":[
        "Cona"
    ],
    "name:nld_x_preferred":[
        "Cona"
    ],
    "name:rus_x_preferred":[
        "\u041a\u043e\u043d\u0430"
    ],
    "name:scn_x_preferred":[
        "Cona"
    ],
    "name:srp_x_preferred":[
        "\u041a\u043e\u043d\u0430"
    ],
    "name:swe_x_preferred":[
        "Cona"
    ],
    "name:ukr_x_preferred":[
        "\u041a\u043e\u043d\u0430"
    ],
    "name:vie_x_preferred":[
        "Cona"
    ],
    "wof:name":"Cona",
    "wof:placetype":"locality",
    "wof:population":63
},
  "geometry": {"coordinates":[10.94164,45.62306],"type":"Point"}
}