{
  "type": "Feature",
  "properties": {
    "gn:admin1_code":"20",
    "gn:admin2_code":"VR",
    "gn:admin3_code":"23078.0",
    "gn:asciiname":"Cona",
    "gn:country_code":"IT",
    "gn:dem":873,
    "gn:feature_class":"P",
    "gn:feature_code":"PPL",
    "gn:name":"Cona",
    "gn:population":63,
    "gn:timezone":"Europe/Rome",
    "iso:country":"IT",
    "wof:name":"Cona",
    "wof:placetype":"locality",
    "wof:population":63
},
  "geometry": {"coordinates":[10.94164,45.62306],"type":"Point"}
}