{
  "type": "Feature",
  "properties": {
    "iso:country":"IT",
    "name:fra_x_preferred":[
        "Oltrarno"
    ],
    "name:ita_x_preferred":[
        "Oltrarno"
    ],
    "name:rus_x_preferred":[
        "\u041e\u043b\u044c\u0442\u0440\u0430\u0440\u043d\u043e"
    ],
    "name:spa_x_preferred":[
        "Oltrarno"
    ],
    "name:zho_x_preferred":[
        "\u5965\u7279\u62c9\u8bfa\u533a"
    ],
    "wof:name":"Oltrarno",
    "wof:placetype":"neighbourhood"
},
  "geometry": {"coordinates":[11.24247297719904,43.76788024997487],"type":"Point"}
}