{
  "type": "Feature",
  "properties": {
    "gn:admin1_code":"1",
    "gn:admin2_code":"TE",
    "gn:admin3_code":"67007.0",
    "gn:asciiname":"Scipione",
    "gn:country_code":"IT",
    "gn:dem":570,
    "gn:feature_class":"P",
    "gn:feature_code":"PPL",
    "gn:name":"Scipione",
    "gn:population":32,
    "gn:timezone":"Europe/Rome",
    "iso:country":"IT",
    "name:cat_x_preferred":[
        "Scipione"
    ],
    "name:fra_x_preferred":[
        "Scipione"
    ],
    "name:ita_x_preferred":[
        "Scipione"
    ],
    "name:spa_x_preferred":[
        "Scipione"
    ],
    "name:swe_x_preferred":[
        "Scipione"
    ],
    "wof:name":"Scipione",
    "wof:placetype":"locality",
    "wof:population":32
},
  "geometry": {"coordinates":[13.77578,42.55017],"type":"Point"}
}