{
  "type": "Feature",
  "properties": {
    "gn:admin1_code":"12.0",
    "gn:admin2_code":"TO",
    "gn:admin3_code":"1216.0",
    "gn:asciiname":"Borgata Montiglio",
    "gn:country_code":"IT",
    "gn:dem":411,
    "gn:feature_class":"P",
    "gn:feature_code":"PPL",
    "gn:name":"Borgata Montiglio",
    "gn:population":15,
    "gn:timezone":"Europe/Rome",
    "iso:country":"IT",
    "wof:name":"Borgata Montiglio",
    "wof:placetype":"locality",
    "wof:population":15
},
  "geometry": {"coordinates":[7.62129,45.32842],"type":"Point"}
}