{
  "type": "Feature",
  "properties": {
    "gn:admin1_code":"12",
    "gn:admin2_code":"TO",
    "gn:admin3_code":"1163.0",
    "gn:asciiname":"Bausone",
    "gn:country_code":"IT",
    "gn:dem":298,
    "gn:feature_class":"P",
    "gn:feature_code":"PPL",
    "gn:name":"Bausone",
    "gn:population":233,
    "gn:timezone":"Europe/Rome",
    "iso:country":"IT",
    "wof:name":"Bausone",
    "wof:placetype":"locality",
    "wof:population":233
},
  "geometry": {"coordinates":[7.92491,45.02682],"type":"Point"}
}