{
  "type": "Feature",
  "properties": {
    "gn:admin1_code":"16",
    "gn:admin2_code":"LI",
    "gn:admin3_code":"49015.0",
    "gn:asciiname":"La Chiusa",
    "gn:country_code":"IT",
    "gn:dem":74,
    "gn:feature_class":"P",
    "gn:feature_code":"PPL",
    "gn:name":"La Chiusa",
    "gn:population":14,
    "gn:timezone":"Europe/Rome",
    "iso:country":"IT",
    "wof:name":"La Chiusa",
    "wof:placetype":"locality",
    "wof:population":14
},
  "geometry": {"coordinates":[10.41372,42.81741],"type":"Point"}
}