{
  "type": "Feature",
  "properties": {
    "gn:admin1_code":"17",
    "gn:admin2_code":"TN",
    "gn:admin3_code":"22058.0",
    "gn:asciiname":"Pietra",
    "gn:country_code":"IT",
    "gn:dem":702,
    "gn:feature_class":"P",
    "gn:feature_code":"PPL",
    "gn:name":"Pietra",
    "gn:population":64,
    "gn:timezone":"Europe/Rome",
    "iso:country":"IT",
    "name:ceb_x_preferred":[
        "Pietra"
    ],
    "name:deu_x_preferred":[
        "Pietra"
    ],
    "name:ita_x_preferred":[
        "Pietra"
    ],
    "name:por_x_preferred":[
        "Pietra"
    ],
    "name:srp_x_preferred":[
        "Pjetra"
    ],
    "name:swe_x_preferred":[
        "Pietra"
    ],
    "name:ukr_x_preferred":[
        "\u041f'\u0454\u0442\u0440\u0430"
    ],
    "wof:name":"Pietra",
    "wof:placetype":"locality",
    "wof:population":64
},
  "geometry": {"coordinates":[11.06449,45.98105],"type":"Point"}
}