{
  "type": "Feature",
  "properties": {
    "gn:admin1_code":"1",
    "gn:admin2_code":"CH",
    "gn:admin3_code":"69075.0",
    "gn:asciiname":"Colle Buono",
    "gn:country_code":"IT",
    "gn:dem":402,
    "gn:feature_class":"P",
    "gn:feature_code":"PPL",
    "gn:name":"Colle Buono",
    "gn:population":132,
    "gn:timezone":"Europe/Rome",
    "iso:country":"IT",
    "wof:name":"Colle Buono",
    "wof:placetype":"locality",
    "wof:population":132
},
  "geometry": {"coordinates":[14.32618,42.05582],"type":"Point"}
}