{
  "type": "Feature",
  "properties": {
    "gn:admin1_code":"20",
    "gn:admin2_code":"TV",
    "gn:admin3_code":"26040.0",
    "gn:asciiname":"Cascina Lazzaris",
    "gn:country_code":"IT",
    "gn:dem":25,
    "gn:feature_class":"P",
    "gn:feature_code":"PPL",
    "gn:name":"Cascina Lazzaris",
    "gn:population":67,
    "gn:timezone":"Europe/Rome",
    "iso:country":"IT",
    "wof:name":"Cascina Lazzaris",
    "wof:placetype":"locality",
    "wof:population":67
},
  "geometry": {"coordinates":[12.34368,45.74783],"type":"Point"}
}