{
  "type": "Feature",
  "properties": {
    "gn:admin1_code":"5",
    "gn:admin2_code":"FC",
    "gn:admin3_code":"40012.0",
    "gn:asciiname":"Volpina",
    "gn:country_code":"IT",
    "gn:dem":52,
    "gn:feature_class":"P",
    "gn:feature_code":"PPL",
    "gn:name":"Volpina",
    "gn:population":51,
    "gn:timezone":"Europe/Rome",
    "iso:country":"IT",
    "wof:name":"Volpina",
    "wof:placetype":"locality",
    "wof:population":51
},
  "geometry": {"coordinates":[11.97083,44.19824000000001],"type":"Point"}
}