{
  "type": "Feature",
  "properties": {
    "gn:admin1_code":"20",
    "gn:admin2_code":"TV",
    "gn:admin3_code":"26056.0",
    "gn:asciiname":"Vitipan-Logaro-Mazzocca",
    "gn:country_code":"IT",
    "gn:dem":181,
    "gn:feature_class":"P",
    "gn:feature_code":"PPL",
    "gn:name":"Vitipan-Logaro-Mazzocca",
    "gn:population":244,
    "gn:timezone":"Europe/Rome",
    "iso:country":"IT",
    "wof:name":"Vitipan-Logaro-Mazzocca",
    "wof:placetype":"locality",
    "wof:population":244
},
  "geometry": {"coordinates":[11.97282,45.86347],"type":"Point"}
}