{
  "type": "Feature",
  "properties": {
    "gn:admin1_code":"5",
    "gn:admin2_code":"FE",
    "gn:admin3_code":"38020.0",
    "gn:asciiname":"Recchi",
    "gn:country_code":"IT",
    "gn:dem":4,
    "gn:feature_class":"P",
    "gn:feature_code":"PPL",
    "gn:name":"Recchi",
    "gn:population":16,
    "gn:timezone":"Europe/Rome",
    "iso:country":"IT",
    "wof:name":"Recchi",
    "wof:placetype":"locality",
    "wof:population":16
},
  "geometry": {"coordinates":[11.82306,44.9591],"type":"Point"}
}