{
  "type": "Feature",
  "properties": {
    "gn:admin1_code":"3",
    "gn:admin2_code":"CS",
    "gn:admin3_code":"78040.0",
    "gn:asciiname":"Dattilo",
    "gn:country_code":"IT",
    "gn:dem":251,
    "gn:feature_class":"P",
    "gn:feature_code":"PPL",
    "gn:name":"Dattilo",
    "gn:population":65,
    "gn:timezone":"Europe/Rome",
    "iso:country":"IT",
    "wof:name":"Dattilo",
    "wof:placetype":"locality",
    "wof:population":65
},
  "geometry": {"coordinates":[15.91986,39.54122],"type":"Point"}
}