{
  "type": "Feature",
  "properties": {
    "gn:admin1_code":"6",
    "gn:admin2_code":"PN",
    "gn:admin3_code":"93040.0",
    "gn:asciiname":"Fregona",
    "gn:country_code":"IT",
    "gn:dem":54,
    "gn:feature_class":"P",
    "gn:feature_code":"PPL",
    "gn:name":"Fregona",
    "gn:population":44,
    "gn:timezone":"Europe/Rome",
    "iso:country":"IT",
    "name:azb_x_preferred":[
        "\u0641\u0631\u0642\u0648\u0646\u0627"
    ],
    "name:bul_x_preferred":[
        "\u0424\u0440\u0435\u0433\u043e\u043d\u0430"
    ],
    "name:cat_x_preferred":[
        "Fregona"
    ],
    "name:ceb_x_preferred":[
        "Fregona"
    ],
    "name:deu_x_preferred":[
        "Fregona"
    ],
    "name:epo_x_preferred":[
        "Fregona"
    ],
    "name:eus_x_preferred":[
        "Fregona"
    ],
    "name:fas_x_preferred":[
        "\u0641\u0631\u06af\u0648\u0646\u0627"
    ],
    "name:fra_x_preferred":[
        "Fregona"
    ],
    "name:hun_x_preferred":[
        "Fregona"
    ],
    "name:hye_x_preferred":[
        "\u0556\u0580\u0565\u0563\u0578\u0576\u0561"
    ],
    "name:ita_x_preferred":[
        "Fregona"
    ],
    "name:jpn_x_preferred":[
        "\u30d5\u30ec\u30b4\u30fc\u30ca"
    ],
    "name:kaz_x_preferred":[
        "\u0424\u0440\u0435\u0433\u043e\u043d\u0430"
    ],
    "name:lat_x_preferred":[
        "Frigonia"
    ],
    "name:lmo_x_preferred":[
        "Fregona"
    ],
    "name:msa_x_preferred":[
        "Fregona"
    ],
    "name:nap_x_preferred":[
        "Fregona"
    ],
    "name:nld_x_preferred":[
        "Fregona"
    ],
    "name:pms_x_preferred":[
        "Fregona"
    ],
    "name:pol_x_preferred":[
        "Fregona"
    ],
    "name:por_x_preferred":[
        "Fregona"
    ],
    "name:ron_x_preferred":[
        "Fregona"
    ],
    "name:rus_x_preferred":[
        "\u0424\u0440\u0435\u0433\u043e\u043d\u0430"
    ],
    "name:scn_x_preferred":[
        "Fregona"
    ],
    "name:spa_x_preferred":[
        "Fregona"
    ],
    "name:srp_x_preferred":[
        "\u0424\u0440\u0435\u0433\u043e\u043d\u0430"
    ],
    "name:tgl_x_preferred":[
        "Fregona"
    ],
    "name:ukr_x_preferred":[
        "\u0424\u0440\u0435\u0433\u043e\u043d\u0430"
    ],
    "name:uzb_x_preferred":[
        "Fregona"
    ],
    "name:vec_x_preferred":[
        "Fregona"
    ],
    "name:vie_x_preferred":[
        "Fregona"
    ],
    "name:vol_x_preferred":[
        "Fregona"
    ],
    "name:war_x_preferred":[
        "Fregona"
    ],
    "name:zho_x_preferred":[
        "\u5f17\u96f7\u6208\u7eb3"
    ],
    "wof:name":"Fregona",
    "wof:placetype":"locality",
    "wof:population":44
},
  "geometry": {"coordinates":[12.65569,45.98473],"type":"Point"}
}