{
  "type": "Feature",
  "properties": {
    "gn:admin1_code":"6",
    "gn:admin2_code":"PN",
    "gn:admin3_code":"93040.0",
    "gn:asciiname":"Fregona",
    "gn:country_code":"IT",
    "gn:dem":54,
    "gn:feature_class":"P",
    "gn:feature_code":"PPL",
    "gn:name":"Fregona",
    "gn:population":44,
    "gn:timezone":"Europe/Rome",
    "iso:country":"IT",
    "wof:name":"Fregona",
    "wof:placetype":"locality",
    "wof:population":44
},
  "geometry": {"coordinates":[12.65569,45.98473],"type":"Point"}
}