{
  "type": "Feature",
  "properties": {
    "gn:admin1_code":"5.0",
    "gn:admin2_code":"RA",
    "gn:admin3_code":"39007.0",
    "gn:asciiname":"Castiglione di Cervia",
    "gn:country_code":"IT",
    "gn:dem":0,
    "gn:feature_class":"P",
    "gn:feature_code":"PPL",
    "gn:name":"Castiglione di Cervia",
    "gn:population":0,
    "gn:timezone":"Europe/Rome",
    "iso:country":"IT",
    "wof:name":"Castiglione di Cervia",
    "wof:placetype":"locality"
},
  "geometry": {"coordinates":[12.28,44.26917],"type":"Point"}
}