{
  "type": "Feature",
  "properties": {
    "gn:admin1_code":"20",
    "gn:admin2_code":"VI",
    "gn:admin3_code":"24100.0",
    "gn:asciiname":"Sarego",
    "gn:country_code":"IT",
    "gn:dem":488,
    "gn:feature_class":"P",
    "gn:feature_code":"PPL",
    "gn:name":"Sarego",
    "gn:population":22,
    "gn:timezone":"Europe/Rome",
    "iso:country":"IT",
    "wof:name":"Sarego",
    "wof:placetype":"locality",
    "wof:population":22
},
  "geometry": {"coordinates":[11.33198,45.67853],"type":"Point"}
}