{
  "type": "Feature",
  "properties": {
    "gn:admin1_code":"20",
    "gn:admin2_code":"VI",
    "gn:admin3_code":"24100.0",
    "gn:asciiname":"Sarego",
    "gn:country_code":"IT",
    "gn:dem":488,
    "gn:feature_class":"P",
    "gn:feature_code":"PPL",
    "gn:name":"Sarego",
    "gn:population":22,
    "gn:timezone":"Europe/Rome",
    "iso:country":"IT",
    "name:azb_x_preferred":[
        "\u0633\u0627\u0631\u0642\u0648"
    ],
    "name:bul_x_preferred":[
        "\u0421\u0430\u0440\u0435\u0433\u043e"
    ],
    "name:ceb_x_preferred":[
        "Sarego"
    ],
    "name:deu_x_preferred":[
        "Sarego"
    ],
    "name:epo_x_preferred":[
        "Sarego"
    ],
    "name:eus_x_preferred":[
        "Sarego"
    ],
    "name:fas_x_preferred":[
        "\u0633\u0627\u0631\u06af\u0648"
    ],
    "name:fra_x_preferred":[
        "Sarego"
    ],
    "name:hun_x_preferred":[
        "Sarego"
    ],
    "name:hye_x_preferred":[
        "\u054d\u0561\u0580\u0565\u0563\u0578"
    ],
    "name:ita_x_preferred":[
        "Sarego"
    ],
    "name:jpn_x_preferred":[
        "\u30b5\u30ec\u30fc\u30b4"
    ],
    "name:kaz_x_preferred":[
        "\u0421\u0430\u0440\u0435\u0433\u043e"
    ],
    "name:lat_x_preferred":[
        "Seraticum"
    ],
    "name:lmo_x_preferred":[
        "Sarego"
    ],
    "name:msa_x_preferred":[
        "Sarego"
    ],
    "name:nap_x_preferred":[
        "Sarego"
    ],
    "name:nld_x_preferred":[
        "Sarego"
    ],
    "name:nor_x_preferred":[
        "Sarego"
    ],
    "name:pms_x_preferred":[
        "Sarego"
    ],
    "name:pol_x_preferred":[
        "Sarego"
    ],
    "name:por_x_preferred":[
        "Sarego"
    ],
    "name:ron_x_preferred":[
        "Sarego"
    ],
    "name:rus_x_preferred":[
        "\u0421\u0430\u0440\u0435\u0433\u043e"
    ],
    "name:scn_x_preferred":[
        "Sarego"
    ],
    "name:spa_x_preferred":[
        "Sarego"
    ],
    "name:srp_x_preferred":[
        "\u0421\u0430\u0440\u0435\u0433\u043e"
    ],
    "name:tgl_x_preferred":[
        "Sarego"
    ],
    "name:ukr_x_preferred":[
        "\u0421\u0430\u0440\u0435\u0433\u043e"
    ],
    "name:uzb_x_preferred":[
        "Sarego"
    ],
    "name:vec_x_preferred":[
        "Sar\u00e8go"
    ],
    "name:vol_x_preferred":[
        "Sarego"
    ],
    "name:war_x_preferred":[
        "Sarego"
    ],
    "name:zho_x_preferred":[
        "\u8428\u96f7\u6208"
    ],
    "wof:name":"Sarego",
    "wof:placetype":"locality",
    "wof:population":22
},
  "geometry": {"coordinates":[11.33198,45.67853],"type":"Point"}
}