{
  "type": "Feature",
  "properties": {
    "gn:admin1_code":"12",
    "gn:admin2_code":"TO",
    "gn:admin3_code":"1066.0",
    "gn:asciiname":"Case Rantano",
    "gn:country_code":"IT",
    "gn:dem":315,
    "gn:feature_class":"P",
    "gn:feature_code":"PPL",
    "gn:name":"Case Rantano",
    "gn:population":39,
    "gn:timezone":"Europe/Rome",
    "iso:country":"IT",
    "wof:name":"Case Rantano",
    "wof:placetype":"locality",
    "wof:population":39
},
  "geometry": {"coordinates":[7.72426,45.35989],"type":"Point"}
}