{
  "type": "Feature",
  "properties": {
    "gn:admin1_code":"20.0",
    "gn:admin2_code":"VE",
    "gn:admin3_code":"27042.0",
    "gn:asciiname":"Quattro Fontane",
    "gn:country_code":"IT",
    "gn:dem":5,
    "gn:feature_class":"P",
    "gn:feature_code":"PPL",
    "gn:name":"Quattro Fontane",
    "gn:population":0,
    "gn:timezone":"Europe/Rome",
    "iso:country":"IT",
    "name:bel_x_preferred":[
        "\u0427\u0430\u0442\u044b\u0440\u044b \u0444\u0430\u043d\u0442\u0430\u043d\u044b"
    ],
    "name:deu_x_preferred":[
        "Die Vier Brunnen"
    ],
    "name:ell_x_preferred":[
        "\u03a4\u03ad\u03c3\u03c3\u03b5\u03c1\u03b5\u03b9\u03c2 \u039a\u03c1\u03ae\u03bd\u03b5\u03c2"
    ],
    "name:hye_x_preferred":[
        "\u0549\u0578\u0580\u057d \u0577\u0561\u057f\u0580\u057e\u0561\u0576"
    ],
    "name:ita_x_preferred":[
        "Quattro Fontane"
    ],
    "name:kor_x_preferred":[
        "\ucf70\ud2b8\ub85c \ud3f0\ud0c0\ub124 \ubd84\uc218"
    ],
    "name:nld_x_preferred":[
        "Quattro Fontane"
    ],
    "name:por_x_preferred":[
        "Quattro Fontane"
    ],
    "name:rus_x_preferred":[
        "\u0427\u0435\u0442\u044b\u0440\u0435 \u0444\u043e\u043d\u0442\u0430\u043d\u0430"
    ],
    "name:spa_x_preferred":[
        "Quattro Fontane"
    ],
    "name:ukr_x_preferred":[
        "\u0427\u043e\u0442\u0438\u0440\u0438 \u0444\u043e\u043d\u0442\u0430\u043d\u0438"
    ],
    "name:zho_x_preferred":[
        "\u56db\u55b7\u6cc9"
    ],
    "wof:name":"Quattro Fontane",
    "wof:placetype":"locality"
},
  "geometry": {"coordinates":[12.36667,45.40833],"type":"Point"}
}