{
  "type": "Feature",
  "properties": {
    "gn:admin1_code":"20.0",
    "gn:admin2_code":"VE",
    "gn:admin3_code":"27042.0",
    "gn:asciiname":"Quattro Fontane",
    "gn:country_code":"IT",
    "gn:dem":5,
    "gn:feature_class":"P",
    "gn:feature_code":"PPL",
    "gn:name":"Quattro Fontane",
    "gn:population":0,
    "gn:timezone":"Europe/Rome",
    "iso:country":"IT",
    "wof:name":"Quattro Fontane",
    "wof:placetype":"locality"
},
  "geometry": {"coordinates":[12.36667,45.40833],"type":"Point"}
}