{
  "type": "Feature",
  "properties": {
    "gn:admin1_code":"5.0",
    "gn:admin2_code":"PC",
    "gn:admin3_code":"33020.0",
    "gn:asciiname":"Cerreto",
    "gn:country_code":"IT",
    "gn:dem":744,
    "gn:feature_class":"P",
    "gn:feature_code":"PPL",
    "gn:name":"Cerreto",
    "gn:population":21,
    "gn:timezone":"Europe/Rome",
    "iso:country":"IT",
    "wof:name":"Cerreto",
    "wof:placetype":"locality",
    "wof:population":21
},
  "geometry": {"coordinates":[9.49117,44.65189],"type":"Point"}
}