{
  "type": "Feature",
  "properties": {
    "gn:admin1_code":"9",
    "gn:admin2_code":"PV",
    "gn:admin3_code":"18126.0",
    "gn:asciiname":"Gaminara",
    "gn:country_code":"IT",
    "gn:dem":352,
    "gn:feature_class":"P",
    "gn:feature_code":"PPL",
    "gn:name":"Gaminara",
    "gn:population":18,
    "gn:timezone":"Europe/Rome",
    "iso:country":"IT",
    "wof:name":"Gaminara",
    "wof:placetype":"locality",
    "wof:population":18
},
  "geometry": {"coordinates":[9.10918,44.92754],"type":"Point"}
}