{
  "type": "Feature",
  "properties": {
    "gn:admin1_code":"9",
    "gn:admin2_code":"VA",
    "gn:admin3_code":"12035.0",
    "gn:asciiname":"Sasso",
    "gn:country_code":"IT",
    "gn:dem":338,
    "gn:feature_class":"P",
    "gn:feature_code":"PPL",
    "gn:name":"Sasso",
    "gn:population":41,
    "gn:timezone":"Europe/Rome",
    "iso:country":"IT",
    "wof:name":"Sasso",
    "wof:placetype":"locality",
    "wof:population":41
},
  "geometry": {"coordinates":[8.8209,45.73011],"type":"Point"}
}