{
  "type": "Feature",
  "properties": {
    "gn:admin1_code":"5",
    "gn:admin2_code":"BO",
    "gn:admin3_code":"37047.0",
    "gn:asciiname":"Guzzano",
    "gn:country_code":"IT",
    "gn:dem":337,
    "gn:feature_class":"P",
    "gn:feature_code":"PPL",
    "gn:name":"Guzzano",
    "gn:population":19,
    "gn:timezone":"Europe/Rome",
    "iso:country":"IT",
    "wof:name":"Guzzano",
    "wof:placetype":"locality",
    "wof:population":19
},
  "geometry": {"coordinates":[11.32226,44.37069],"type":"Point"}
}