{
  "type": "Feature",
  "properties": {
    "gn:admin1_code":"12",
    "gn:admin2_code":"CN",
    "gn:admin3_code":"4163.0",
    "gn:asciiname":"Borello",
    "gn:country_code":"IT",
    "gn:dem":514,
    "gn:feature_class":"P",
    "gn:feature_code":"PPL",
    "gn:name":"Borello",
    "gn:population":116,
    "gn:timezone":"Europe/Rome",
    "iso:country":"IT",
    "wof:name":"Borello",
    "wof:placetype":"locality",
    "wof:population":116
},
  "geometry": {"coordinates":[7.60622,44.37572],"type":"Point"}
}