{
  "type": "Feature",
  "properties": {
    "gn:admin1_code":"9",
    "gn:admin2_code":"PV",
    "gn:admin3_code":"18117.0",
    "gn:asciiname":"Molino del Conte",
    "gn:country_code":"IT",
    "gn:dem":281,
    "gn:feature_class":"P",
    "gn:feature_code":"PPL",
    "gn:name":"Molino del Conte",
    "gn:population":61,
    "gn:timezone":"Europe/Rome",
    "iso:country":"IT",
    "wof:name":"Molino del Conte",
    "wof:placetype":"locality",
    "wof:population":61
},
  "geometry": {"coordinates":[9.10389,44.8458],"type":"Point"}
}