{
  "type": "Feature",
  "properties": {
    "gn:admin1_code":"4.0",
    "gn:admin3_code":"63049.0",
    "gn:asciiname":"Agnano Terme",
    "gn:country_code":"IT",
    "gn:dem":21,
    "gn:feature_class":"P",
    "gn:feature_code":"PPL",
    "gn:name":"Agnano Terme",
    "gn:population":0,
    "gn:timezone":"Europe/Rome",
    "iso:country":"IT",
    "wof:name":"Agnano Terme",
    "wof:placetype":"locality"
},
  "geometry": {"coordinates":[14.15932,40.83433],"type":"Point"}
}