{
  "type": "Feature",
  "properties": {
    "gn:admin1_code":"9",
    "gn:admin2_code":"BG",
    "gn:admin3_code":"16148.0",
    "gn:asciiname":"Chignolo d'Oneta",
    "gn:country_code":"IT",
    "gn:dem":826,
    "gn:feature_class":"P",
    "gn:feature_code":"PPL",
    "gn:name":"Chignolo d'Oneta",
    "gn:population":104,
    "gn:timezone":"Europe/Rome",
    "iso:country":"IT",
    "wof:name":"Chignolo d'Oneta",
    "wof:placetype":"locality",
    "wof:population":104
},
  "geometry": {"coordinates":[9.82861,45.85963],"type":"Point"}
}