{
  "type": "Feature",
  "properties": {
    "gn:admin1_code":"9",
    "gn:admin2_code":"BS",
    "gn:admin3_code":"17024.0",
    "gn:asciiname":"Zigole",
    "gn:country_code":"IT",
    "gn:dem":612,
    "gn:feature_class":"P",
    "gn:feature_code":"PPL",
    "gn:name":"Zigole",
    "gn:population":71,
    "gn:timezone":"Europe/Rome",
    "iso:country":"IT",
    "wof:name":"Zigole",
    "wof:placetype":"locality",
    "wof:population":71
},
  "geometry": {"coordinates":[10.26495,45.7788],"type":"Point"}
}