{
  "type": "Feature",
  "properties": {
    "gn:admin1_code":"18.0",
    "gn:admin2_code":"PG",
    "gn:admin3_code":"54012.0",
    "gn:asciiname":"San Biagio",
    "gn:country_code":"IT",
    "gn:dem":385,
    "gn:elevation":"260.0",
    "gn:feature_class":"P",
    "gn:feature_code":"PPL",
    "gn:name":"San Biagio",
    "gn:population":27,
    "gn:timezone":"Europe/Rome",
    "iso:country":"IT",
    "wof:name":"San Biagio",
    "wof:placetype":"locality",
    "wof:population":27
},
  "geometry": {"coordinates":[12.02011,42.9868],"type":"Point"}
}