{
  "type": "Feature",
  "properties": {
    "gn:admin1_code":"1",
    "gn:admin2_code":"CH",
    "gn:admin3_code":"69022.0",
    "gn:asciiname":"Fasoli",
    "gn:country_code":"IT",
    "gn:dem":200,
    "gn:feature_class":"P",
    "gn:feature_code":"PPL",
    "gn:name":"Fasoli",
    "gn:population":53,
    "gn:timezone":"Europe/Rome",
    "iso:country":"IT",
    "wof:name":"Fasoli",
    "wof:placetype":"locality",
    "wof:population":53
},
  "geometry": {"coordinates":[14.15147,42.33671],"type":"Point"}
}