{
  "type": "Feature",
  "properties": {
    "gn:admin1_code":"12",
    "gn:admin2_code":"TO",
    "gn:admin3_code":"1082.0",
    "gn:asciiname":"Pichi",
    "gn:country_code":"IT",
    "gn:dem":198,
    "gn:feature_class":"P",
    "gn:feature_code":"PPL",
    "gn:name":"Pichi",
    "gn:population":275,
    "gn:timezone":"Europe/Rome",
    "iso:country":"IT",
    "wof:name":"Pichi",
    "wof:placetype":"locality",
    "wof:population":275
},
  "geometry": {"coordinates":[7.89398,45.20741],"type":"Point"}
}