{
  "type": "Feature",
  "properties": {
    "gn:admin1_code":"12",
    "gn:admin2_code":"TO",
    "gn:admin3_code":"1082.0",
    "gn:asciiname":"Pichi",
    "gn:country_code":"IT",
    "gn:dem":198,
    "gn:feature_class":"P",
    "gn:feature_code":"PPL",
    "gn:name":"Pichi",
    "gn:population":275,
    "gn:timezone":"Europe/Rome",
    "iso:country":"IT",
    "name:ara_x_preferred":[
        "\u0645\u062f\u0631\u0639 \u0628\u064a\u0634\u064a"
    ],
    "name:bre_x_preferred":[
        "Tatou Patagonia"
    ],
    "name:bul_x_preferred":[
        "\u041c\u0430\u043b\u044a\u043a \u0431\u0440\u043e\u043d\u0435\u043d\u043e\u0441\u0435\u0446"
    ],
    "name:ceb_x_preferred":[
        "Zaedyus pichiy"
    ],
    "name:deu_x_preferred":[
        "Zwergg\u00fcrteltier"
    ],
    "name:eus_x_preferred":[
        "Zaedyus pichiy"
    ],
    "name:fas_x_preferred":[
        "\u0622\u0631\u0645\u0627\u062f\u06cc\u0644\u0648\u06cc \u06a9\u0648\u062a\u0648\u0644\u0647"
    ],
    "name:fin_x_preferred":[
        "K\u00e4\u00e4pi\u00f6vy\u00f6ti\u00e4inen"
    ],
    "name:fra_x_preferred":[
        "Zaedyus pichiy"
    ],
    "name:glg_x_preferred":[
        "Zaedyus pichiy"
    ],
    "name:heb_x_preferred":[
        "\u05d0\u05e8\u05de\u05d3\u05d9\u05dc \u05d0\u05e8\u05d2\u05e0\u05d8\u05d9\u05e0\u05d0\u05d9"
    ],
    "name:hun_x_preferred":[
        "T\u00f6rpe tatu"
    ],
    "name:ita_x_preferred":[
        "Zaedyus pichiy"
    ],
    "name:jpn_x_preferred":[
        "\u30d4\u30c1\u30a2\u30eb\u30de\u30b8\u30ed"
    ],
    "name:kor_x_preferred":[
        "\ud53c\uce58\uc544\ub974\ub9c8\ub51c\ub85c"
    ],
    "name:nld_x_preferred":[
        "Dwerggordeldier"
    ],
    "name:por_x_preferred":[
        "Zaedyus pichiy"
    ],
    "name:rus_x_preferred":[
        "\u041a\u0430\u0440\u043b\u0438\u043a\u043e\u0432\u044b\u0439 \u0431\u0440\u043e\u043d\u0435\u043d\u043e\u0441\u0435\u0446"
    ],
    "name:spa_x_preferred":[
        "Zaedyus pichiy"
    ],
    "name:swe_x_preferred":[
        "Dv\u00e4rgb\u00e4lta"
    ],
    "name:tha_x_preferred":[
        "\u0e1b\u0e35\u0e0a\u0e35"
    ],
    "name:vie_x_preferred":[
        "Pichi"
    ],
    "name:war_x_preferred":[
        "Zaedyus pichiy"
    ],
    "name:zho_x_preferred":[
        "\u5c0f\u72b0\u72f3"
    ],
    "wof:name":"Pichi",
    "wof:placetype":"locality",
    "wof:population":275
},
  "geometry": {"coordinates":[7.89398,45.20741],"type":"Point"}
}