{
  "type": "Feature",
  "properties": {
    "gn:admin1_code":"5",
    "gn:admin2_code":"RE",
    "gn:admin3_code":"35046.0",
    "gn:asciiname":"Masere",
    "gn:country_code":"IT",
    "gn:dem":756,
    "gn:feature_class":"P",
    "gn:feature_code":"PPL",
    "gn:name":"Masere",
    "gn:population":41,
    "gn:timezone":"Europe/Rome",
    "iso:country":"IT",
    "wof:name":"Masere",
    "wof:placetype":"locality",
    "wof:population":41
},
  "geometry": {"coordinates":[10.28069,44.41397],"type":"Point"}
}