{
  "type": "Feature",
  "properties": {
    "gn:admin1_code":"4",
    "gn:admin3_code":"63072.0",
    "gn:asciiname":"Sellaro",
    "gn:country_code":"IT",
    "gn:dem":53,
    "gn:feature_class":"P",
    "gn:feature_code":"PPL",
    "gn:name":"Sellaro",
    "gn:population":54,
    "gn:timezone":"Europe/Rome",
    "iso:country":"IT",
    "wof:name":"Sellaro",
    "wof:placetype":"locality",
    "wof:population":54
},
  "geometry": {"coordinates":[14.37395,40.88409],"type":"Point"}
}