{
  "type": "Feature",
  "properties": {
    "gn:admin1_code":"8",
    "gn:admin2_code":"SV",
    "gn:admin3_code":"9055.0",
    "gn:asciiname":"Maddalena",
    "gn:country_code":"IT",
    "gn:dem":348,
    "gn:feature_class":"P",
    "gn:feature_code":"PPL",
    "gn:name":"Maddalena",
    "gn:population":54,
    "gn:timezone":"Europe/Rome",
    "iso:country":"IT",
    "name:bre_x_preferred":[
        "Maddalena"
    ],
    "name:ceb_x_preferred":[
        "Maddalena"
    ],
    "name:deu_x_preferred":[
        "Maddalena"
    ],
    "name:fra_x_preferred":[
        "Maddalena"
    ],
    "name:ita_x_preferred":[
        "Maddalena"
    ],
    "name:pol_x_preferred":[
        "Maddalena"
    ],
    "name:rus_x_preferred":[
        "\u041c\u0430\u0434\u0434\u0430\u043b\u0435\u043d\u0430"
    ],
    "name:srp_x_preferred":[
        "Maddalena"
    ],
    "name:swe_x_preferred":[
        "Maddalena"
    ],
    "wof:name":"Maddalena",
    "wof:placetype":"locality",
    "wof:population":54
},
  "geometry": {"coordinates":[8.48845,44.50091],"type":"Point"}
}