{
  "type": "Feature",
  "properties": {
    "gn:admin1_code":"8",
    "gn:admin2_code":"SV",
    "gn:admin3_code":"9055.0",
    "gn:asciiname":"Maddalena",
    "gn:country_code":"IT",
    "gn:dem":348,
    "gn:feature_class":"P",
    "gn:feature_code":"PPL",
    "gn:name":"Maddalena",
    "gn:population":54,
    "gn:timezone":"Europe/Rome",
    "iso:country":"IT",
    "wof:name":"Maddalena",
    "wof:placetype":"locality",
    "wof:population":54
},
  "geometry": {"coordinates":[8.48845,44.50091],"type":"Point"}
}