{
  "type": "Feature",
  "properties": {
    "gn:admin1_code":"1",
    "gn:admin2_code":"PE",
    "gn:admin3_code":"68021.0",
    "gn:asciiname":"Passocordone",
    "gn:country_code":"IT",
    "gn:dem":181,
    "gn:feature_class":"P",
    "gn:feature_code":"PPL",
    "gn:name":"Passocordone",
    "gn:population":265,
    "gn:timezone":"Europe/Rome",
    "iso:country":"IT",
    "wof:name":"Passocordone",
    "wof:placetype":"locality",
    "wof:population":265
},
  "geometry": {"coordinates":[13.9611,42.40112],"type":"Point"}
}