{
  "type": "Feature",
  "properties": {
    "gn:gn_country":"IT",
    "gn:gn_fcode":"PPL",
    "gn:gn_pop":0,
    "iso:country":"IT",
    "name:dut_x_preferred":[
        "Melezet"
    ],
    "name:eng_x_preferred":[
        "Melezet"
    ],
    "name:fre_x_preferred":[
        "M\u00e9lezet"
    ],
    "name:hun_x_preferred":[
        "Melezet"
    ],
    "name:ita_x_preferred":[
        "Melezet"
    ],
    "name:spa_x_preferred":[
        "Melezet"
    ],
    "qs_pg:aaroncc":"IT",
    "qs_pg:gn_country":"IT",
    "qs_pg:gn_fcode":"PPL",
    "qs_pg:gn_pop":0,
    "qs_pg:name":"Melezet",
    "qs_pg:name_adm0":"Italia",
    "qs_pg:name_adm1":"Piemonte",
    "qs_pg:photos":186,
    "qs_pg:photos_1k":38,
    "qs_pg:photos_9k":1,
    "qs_pg:photos_9r":4,
    "qs_pg:photos_all":186,
    "qs_pg:photos_sr":4,
    "qs_pg:pop_sr":0,
    "qs_pg:qs_pg_placetype":"locality",
    "qs_pg:qs_pg_placetype_gp":"Town",
    "qs_pg:woe_adm0":23424853,
    "woe:adm0_id":23424853,
    "woe:name_adm0":"Italia",
    "woe:name_adm1":"Piemonte",
    "woe:placetype":"Town",
    "wof:name":"Melezet",
    "wof:placetype":"locality"
},
  "geometry": {"coordinates":[6.68333,45.06667],"type":"Point"}
}