{
  "type": "Feature",
  "properties": {
    "gn:admin1_code":"9.0",
    "gn:admin2_code":"SO",
    "gn:admin3_code":"14077.0",
    "gn:asciiname":"Villa di Chiavenna",
    "gn:cc2":"IT",
    "gn:country_code":"IT",
    "gn:dem":618,
    "gn:feature_class":"P",
    "gn:feature_code":"PPLA3",
    "gn:name":"Villa di Chiavenna",
    "gn:population":1116,
    "gn:timezone":"Europe/Rome",
    "iso:country":"IT",
    "name:deu_x_preferred":[
        "Villa di Chiavenna"
    ],
    "name:eng_x_preferred":[
        "Villa di Chiavenna"
    ],
    "name:epo_x_preferred":[
        "Villa di Chiavenna"
    ],
    "name:fra_x_preferred":[
        "Villa di Chiavenna"
    ],
    "name:ita_x_preferred":[
        "Villa di Chiavenna"
    ],
    "name:nap_x_preferred":[
        "Villa di Chiavenna"
    ],
    "name:nld_x_preferred":[
        "Villa di Chiavenna"
    ],
    "name:pol_x_preferred":[
        "Villa di Chiavenna"
    ],
    "name:por_x_preferred":[
        "Villa di Chiavenna"
    ],
    "name:und_x_variant":[
        "Villa Chiavenna"
    ],
    "wof:name":"Villa di Chiavenna",
    "wof:placetype":"locality",
    "wof:population":1116
},
  "geometry": {"coordinates":[9.48114,46.33069],"type":"Point"}
}