{
  "type": "Feature",
  "properties": {
    "gn:admin1_code":"9.0",
    "gn:admin2_code":"SO",
    "gn:admin3_code":"14077.0",
    "gn:asciiname":"Villa di Chiavenna",
    "gn:cc2":"IT",
    "gn:country_code":"IT",
    "gn:dem":618,
    "gn:feature_class":"P",
    "gn:feature_code":"PPLA3",
    "gn:name":"Villa di Chiavenna",
    "gn:population":1116,
    "gn:timezone":"Europe/Rome",
    "iso:country":"IT",
    "name:azb_x_preferred":[
        "\u0648\u06cc\u0644\u0627 \u062f\u06cc \u06a9\u06cc\u0627\u0648\u0646\u0627"
    ],
    "name:bel_x_preferred":[
        "\u0412\u0456\u043b\u0430-\u0434\u0437\u0456-\u041a\u2019\u044f\u0432\u0435\u043d\u0430"
    ],
    "name:bul_x_preferred":[
        "\u0412\u0438\u043b\u0430 \u0434\u0438 \u041a\u0438\u0430\u0432\u0435\u043d\u0430"
    ],
    "name:deu_x_preferred":[
        "Villa di Chiavenna"
    ],
    "name:eng_x_preferred":[
        "Villa di Chiavenna"
    ],
    "name:epo_x_preferred":[
        "Villa di Chiavenna"
    ],
    "name:fas_x_preferred":[
        "\u0648\u06cc\u0644\u0627 \u062f\u06cc \u06a9\u06cc\u0627\u0648\u0646\u0627"
    ],
    "name:fra_x_preferred":[
        "Villa di Chiavenna"
    ],
    "name:hye_x_preferred":[
        "\u054e\u056b\u056c\u0561 \u0564\u056b \u053f\u056b\u0561\u057e\u0565\u0576\u0561"
    ],
    "name:ita_x_preferred":[
        "Villa di Chiavenna"
    ],
    "name:jpn_x_preferred":[
        "\u30f4\u30a3\u30c3\u30e9\u30fb\u30c7\u30a3\u30fb\u30ad\u30a2\u30f4\u30a7\u30f3\u30ca"
    ],
    "name:kaz_x_preferred":[
        "\u0412\u0438\u043b\u043b\u0430-\u0434\u0438-\u041a\u044c\u044f\u0432\u0435\u043d\u043d\u0430"
    ],
    "name:lat_x_preferred":[
        "Villa Clavennae"
    ],
    "name:nap_x_preferred":[
        "Villa di Chiavenna"
    ],
    "name:nld_x_preferred":[
        "Villa di Chiavenna"
    ],
    "name:pol_x_preferred":[
        "Villa di Chiavenna"
    ],
    "name:por_x_preferred":[
        "Villa di Chiavenna"
    ],
    "name:rus_x_preferred":[
        "\u0412\u0438\u043b\u043b\u0430-\u0434\u0438-\u041a\u044c\u044f\u0432\u0435\u043d\u043d\u0430"
    ],
    "name:srp_x_preferred":[
        "\u0412\u0438\u043b\u0430 \u0434\u0438 \u041a\u0458\u0430\u0432\u0435\u043d\u0430"
    ],
    "name:ukr_x_preferred":[
        "\u0412\u0456\u043b\u043b\u0430-\u0434\u0456-\u041a'\u044f\u0432\u0435\u043d\u043d\u0430"
    ],
    "name:und_x_variant":[
        "Villa Chiavenna"
    ],
    "name:zho_x_preferred":[
        "\u7ef4\u62c9\u8fea\u57fa\u4e9a\u6587\u7eb3"
    ],
    "wof:name":"Villa di Chiavenna",
    "wof:placetype":"locality",
    "wof:population":1116
},
  "geometry": {"coordinates":[9.48114,46.33069],"type":"Point"}
}