{
  "type": "Feature",
  "properties": {
    "gn:admin1_code":"9",
    "gn:admin2_code":"MI",
    "gn:admin3_code":"15242.0",
    "gn:asciiname":"Cascina Metalino",
    "gn:country_code":"IT",
    "gn:dem":128,
    "gn:feature_class":"P",
    "gn:feature_code":"PPL",
    "gn:name":"Cascina Metalino",
    "gn:population":34,
    "gn:timezone":"Europe/Rome",
    "iso:country":"IT",
    "wof:name":"Cascina Metalino",
    "wof:placetype":"locality",
    "wof:population":34
},
  "geometry": {"coordinates":[9.26906,45.51742],"type":"Point"}
}