{
  "type": "Feature",
  "properties": {
    "gn:admin1_code":"3",
    "gn:admin2_code":"CS",
    "gn:admin3_code":"78081.0",
    "gn:asciiname":"Telesio",
    "gn:country_code":"IT",
    "gn:dem":186,
    "gn:feature_class":"P",
    "gn:feature_code":"PPL",
    "gn:name":"Telesio",
    "gn:population":126,
    "gn:timezone":"Europe/Rome",
    "iso:country":"IT",
    "name:ita_x_preferred":[
        "Telesio"
    ],
    "name:rus_x_preferred":[
        "\u0422\u0435\u043b\u0435\u0437\u0438\u043e"
    ],
    "name:srp_x_preferred":[
        "Telezio"
    ],
    "wof:name":"Telesio",
    "wof:placetype":"locality",
    "wof:population":126
},
  "geometry": {"coordinates":[16.21883,39.39859000000001],"type":"Point"}
}