{
  "type": "Feature",
  "properties": {
    "iso:country":"IT",
    "wof:name":"Marianella",
    "wof:placetype":"neighbourhood"
},
  "geometry": {"coordinates":[14.23468822724617,40.87966642652503],"type":"Point"}
}