{
  "type": "Feature",
  "properties": {
    "gn:admin1_code":"14.0",
    "gn:admin2_code":"CA",
    "gn:admin3_code":"92080.0",
    "gn:asciiname":"Monte Cresia",
    "gn:country_code":"IT",
    "gn:dem":635,
    "gn:feature_class":"P",
    "gn:feature_code":"PPLL",
    "gn:name":"Monte Cresia",
    "gn:population":0,
    "gn:timezone":"Europe/Rome",
    "iso:country":"IT",
    "wof:name":"Monte Cresia",
    "wof:placetype":"locality"
},
  "geometry": {"coordinates":[9.38725,39.28119],"type":"Point"}
}