{
  "type": "Feature",
  "properties": {
    "gn:admin1_code":"17",
    "gn:admin2_code":"BZ",
    "gn:admin3_code":"21097.0",
    "gn:asciiname":"Kuhn",
    "gn:country_code":"IT",
    "gn:dem":251,
    "gn:feature_class":"P",
    "gn:feature_code":"PPL",
    "gn:name":"Kuhn",
    "gn:population":21,
    "gn:timezone":"Europe/Rome",
    "iso:country":"IT",
    "name:deu_x_preferred":[
        "Kuhn"
    ],
    "name:fas_x_preferred":[
        "\u06a9\u0648\u0646"
    ],
    "wof:name":"Kuhn",
    "wof:placetype":"locality",
    "wof:population":21
},
  "geometry": {"coordinates":[11.28005,46.50824],"type":"Point"}
}