{
  "type": "Feature",
  "properties": {
    "gn:admin1_code":"9.0",
    "gn:admin2_code":"SO",
    "gn:admin3_code":"14012.0",
    "gn:asciiname":"Splughetta",
    "gn:country_code":"IT",
    "gn:dem":1361,
    "gn:feature_class":"P",
    "gn:feature_code":"PPLL",
    "gn:name":"Splughetta",
    "gn:population":5,
    "gn:timezone":"Europe/Rome",
    "iso:country":"IT",
    "wof:name":"Splughetta",
    "wof:placetype":"locality",
    "wof:population":5
},
  "geometry": {"coordinates":[9.33718,46.41139],"type":"Point"}
}