{
  "type": "Feature",
  "properties": {
    "gn:elevation":606,
    "gn:population":511,
    "iso:country":"IT",
    "name:azb_x_preferred":[
        "\u0646\u062a\u0631\u0648"
    ],
    "name:bel_x_preferred":[
        "\u041d\u0435\u0442\u0440\u0430"
    ],
    "name:bul_x_preferred":[
        "\u041d\u0435\u0442\u0440\u043e"
    ],
    "name:ceb_x_preferred":[
        "Netro"
    ],
    "name:deu_x_preferred":[
        "Netro"
    ],
    "name:eng_x_preferred":[
        "Netro"
    ],
    "name:epo_x_preferred":[
        "Netro"
    ],
    "name:eus_x_preferred":[
        "Netro"
    ],
    "name:fas_x_preferred":[
        "\u0646\u062a\u0631\u0648"
    ],
    "name:fra_x_preferred":[
        "Netro"
    ],
    "name:hun_x_preferred":[
        "Netro"
    ],
    "name:hye_x_preferred":[
        "\u0546\u0565\u057f\u0580\u0578"
    ],
    "name:ind_x_preferred":[
        "Netro"
    ],
    "name:ita_x_preferred":[
        "Netro"
    ],
    "name:jpn_x_preferred":[
        "\u30cd\u30c8\u30ed"
    ],
    "name:kaz_x_preferred":[
        "\u041d\u0435\u0442\u0440\u043e"
    ],
    "name:lat_x_preferred":[
        "Netrum"
    ],
    "name:lmo_x_preferred":[
        "Netro"
    ],
    "name:msa_x_preferred":[
        "Netro"
    ],
    "name:nan_x_preferred":[
        "Netro"
    ],
    "name:nap_x_preferred":[
        "Netro"
    ],
    "name:nld_x_preferred":[
        "Netro"
    ],
    "name:pms_x_preferred":[
        "Netro"
    ],
    "name:pol_x_preferred":[
        "Netro"
    ],
    "name:por_x_preferred":[
        "Netro"
    ],
    "name:ron_x_preferred":[
        "Netro"
    ],
    "name:rus_x_preferred":[
        "\u041d\u0435\u0442\u0440\u043e"
    ],
    "name:scn_x_preferred":[
        "Netro"
    ],
    "name:spa_x_preferred":[
        "Netro"
    ],
    "name:srp_x_preferred":[
        "Netro"
    ],
    "name:tgl_x_preferred":[
        "Netro"
    ],
    "name:ukr_x_preferred":[
        "\u041d\u0435\u0442\u0440\u043e"
    ],
    "name:uzb_x_preferred":[
        "Netro"
    ],
    "name:vie_x_preferred":[
        "Netro"
    ],
    "name:vol_x_preferred":[
        "Netro"
    ],
    "name:war_x_preferred":[
        "Netro"
    ],
    "name:zho_x_preferred":[
        "\u5185\u7279\u7f57"
    ],
    "qs:a0":"Italia",
    "qs:a1":"*Biella",
    "qs:a1r":"0Piemonte",
    "qs:adm0":"Italia",
    "qs:la_lc":"*",
    "qs:level":"locality",
    "qs:loc":"Netro",
    "qs:loc_alt":"Netro",
    "qs:pop":0,
    "qs:type":"buffered point",
    "wof:lang":[
        "ita"
    ],
    "wof:name":"Netro",
    "wof:placetype":"locality",
    "wof:population":511
},
  "geometry": {"coordinates":[7.94639,45.538891],"type":"Point"}
}