{
  "type": "Feature",
  "properties": {
    "gn:admin1_code":"18",
    "gn:admin2_code":"TR",
    "gn:admin3_code":"55001.0",
    "gn:asciiname":"Firenzuola",
    "gn:country_code":"IT",
    "gn:dem":493,
    "gn:feature_class":"P",
    "gn:feature_code":"PPL",
    "gn:name":"Firenzuola",
    "gn:population":94,
    "gn:timezone":"Europe/Rome",
    "iso:country":"IT",
    "name:azb_x_preferred":[
        "\u0641\u06cc\u0631\u0646\u062a\u0632\u0648\u0626\u0648\u0644\u0627"
    ],
    "name:bcl_x_preferred":[
        "Firenzuola"
    ],
    "name:bel_x_preferred":[
        "\u0424\u0456\u0440\u044d\u043d\u0446\u0443\u043e\u043b\u0430"
    ],
    "name:bul_x_preferred":[
        "\u0424\u0438\u0440\u0435\u043d\u0446\u0443\u043e\u043b\u0430"
    ],
    "name:cat_x_preferred":[
        "Firenzuola"
    ],
    "name:ceb_x_preferred":[
        "Firenzuola"
    ],
    "name:cos_x_preferred":[
        "Firenzuola"
    ],
    "name:deu_x_preferred":[
        "Firenzuola"
    ],
    "name:epo_x_preferred":[
        "Firenzuola"
    ],
    "name:eus_x_preferred":[
        "Firenzuola"
    ],
    "name:fas_x_preferred":[
        "\u0641\u06cc\u0631\u0646\u062a\u0632\u0648\u0626\u0648\u0644\u0627"
    ],
    "name:fra_x_preferred":[
        "Firenzuola"
    ],
    "name:hun_x_preferred":[
        "Firenzuola"
    ],
    "name:hye_x_preferred":[
        "\u0556\u056b\u0580\u0565\u0576\u0581\u0578\u0582\u0578\u056c\u0561"
    ],
    "name:ita_x_preferred":[
        "Firenzuola"
    ],
    "name:jpn_x_preferred":[
        "\u30d5\u30a3\u30ec\u30f3\u30c4\u30aa\u30fc\u30e9"
    ],
    "name:kor_x_preferred":[
        "\ud53c\ub80c\ucd94\uc62c\ub77c"
    ],
    "name:lat_x_preferred":[
        "Florentiola"
    ],
    "name:lmo_x_preferred":[
        "Firenzuola"
    ],
    "name:msa_x_preferred":[
        "Firenzuola"
    ],
    "name:nap_x_preferred":[
        "Firenzuola"
    ],
    "name:nld_x_preferred":[
        "Firenzuola"
    ],
    "name:pms_x_preferred":[
        "Firenzuola"
    ],
    "name:pol_x_preferred":[
        "Firenzuola"
    ],
    "name:por_x_preferred":[
        "Firenzuola"
    ],
    "name:ron_x_preferred":[
        "Firenzuola"
    ],
    "name:rus_x_preferred":[
        "\u0424\u0438\u0440\u0435\u043d\u0446\u0443\u043e\u043b\u0430"
    ],
    "name:scn_x_preferred":[
        "Firinzuola"
    ],
    "name:spa_x_preferred":[
        "Firenzuola"
    ],
    "name:srp_x_preferred":[
        "\u0424\u0438\u0440\u0435\u043d\u0446\u0443\u043e\u043b\u0430"
    ],
    "name:tur_x_preferred":[
        "Firenzuola"
    ],
    "name:ukr_x_preferred":[
        "\u0424\u0456\u0440\u0435\u043d\u0446\u0443\u043e\u043b\u0430"
    ],
    "name:uzb_x_preferred":[
        "Firenzuola"
    ],
    "name:vec_x_preferred":[
        "Firensuo\u0142a"
    ],
    "name:vol_x_preferred":[
        "Firenzuola"
    ],
    "name:war_x_preferred":[
        "Firenzuola"
    ],
    "name:zho_x_preferred":[
        "\u83f2\u4f26\u4f50\u62c9"
    ],
    "wof:name":"Firenzuola",
    "wof:placetype":"locality",
    "wof:population":94
},
  "geometry": {"coordinates":[12.61084,42.71041],"type":"Point"}
}