{
  "type": "Feature",
  "properties": {
    "gn:gn_country":"IT",
    "gn:gn_fcode":"PPL",
    "gn:gn_pop":0,
    "gn:population":564,
    "iso:country":"IT",
    "name:bar_x_preferred":[
        "Tornavento"
    ],
    "name:bul_x_preferred":[
        "\u0422\u043e\u0440\u043d\u0430\u0432\u0435\u043d\u0442\u043e"
    ],
    "name:cat_x_preferred":[
        "Tornavento"
    ],
    "name:ceb_x_preferred":[
        "Tornavento"
    ],
    "name:ces_x_preferred":[
        "Tornavento"
    ],
    "name:dan_x_preferred":[
        "Tornavento"
    ],
    "name:deu_x_preferred":[
        "Tornavento"
    ],
    "name:eng_x_preferred":[
        "Tornavento"
    ],
    "name:eus_x_preferred":[
        "Tornavento"
    ],
    "name:fin_x_preferred":[
        "Tornavento"
    ],
    "name:fra_x_preferred":[
        "Tornavento"
    ],
    "name:hun_x_preferred":[
        "Tornavento"
    ],
    "name:ind_x_preferred":[
        "Tornavento"
    ],
    "name:ita_x_preferred":[
        "Tornavento"
    ],
    "name:lmo_x_preferred":[
        "Tornavent"
    ],
    "name:nld_x_preferred":[
        "Tornavento"
    ],
    "name:nno_x_preferred":[
        "Tornavento"
    ],
    "name:nob_x_preferred":[
        "Tornavento"
    ],
    "name:oci_x_preferred":[
        "Tornavento"
    ],
    "name:pol_x_preferred":[
        "Tornavento"
    ],
    "name:por_x_preferred":[
        "Tornavento"
    ],
    "name:ron_x_preferred":[
        "Tornavento"
    ],
    "name:slk_x_preferred":[
        "Tornavento"
    ],
    "name:slv_x_preferred":[
        "Tornavento"
    ],
    "name:spa_x_preferred":[
        "Tornavento"
    ],
    "name:srp_x_preferred":[
        "Tornavento"
    ],
    "name:swe_x_preferred":[
        "Tornavento"
    ],
    "name:tgl_x_preferred":[
        "Tornavento"
    ],
    "name:tur_x_preferred":[
        "Tornavento"
    ],
    "name:war_x_preferred":[
        "Tornavento"
    ],
    "qs_pg:aaroncc":"IT",
    "qs_pg:gn_country":"IT",
    "qs_pg:gn_fcode":"PPL",
    "qs_pg:gn_pop":0,
    "qs_pg:name":"Tornavento",
    "qs_pg:name_adm0":"Italia",
    "qs_pg:name_adm1":"Lombardia",
    "qs_pg:photos":217,
    "qs_pg:photos_1k":44,
    "qs_pg:photos_9k":1,
    "qs_pg:photos_9r":4,
    "qs_pg:photos_all":217,
    "qs_pg:photos_sr":4,
    "qs_pg:pop_sr":0,
    "qs_pg:qs_pg_placetype":"locality",
    "qs_pg:qs_pg_placetype_gp":"Town",
    "qs_pg:woe_adm0":23424853,
    "woe:adm0_id":23424853,
    "woe:name_adm0":"Italia",
    "woe:name_adm1":"Lombardia",
    "woe:placetype":"Town",
    "wof:name":"Tornavento",
    "wof:placetype":"locality",
    "wof:population":564
},
  "geometry": {"coordinates":[8.71667,45.58333],"type":"Point"}
}