{
  "type": "Feature",
  "properties": {
    "gn:admin1_code":"3",
    "gn:admin2_code":"RC",
    "gn:admin3_code":"80084.0",
    "gn:asciiname":"Santa Giorgia",
    "gn:country_code":"IT",
    "gn:dem":362,
    "gn:feature_class":"P",
    "gn:feature_code":"PPL",
    "gn:name":"Santa Giorgia",
    "gn:population":42,
    "gn:timezone":"Europe/Rome",
    "iso:country":"IT",
    "wof:name":"Santa Giorgia",
    "wof:placetype":"locality",
    "wof:population":42
},
  "geometry": {"coordinates":[15.93638,38.25461],"type":"Point"}
}