{
  "type": "Feature",
  "properties": {
    "gn:admin1_code":"8",
    "gn:admin2_code":"SP",
    "gn:admin3_code":"11028.0",
    "gn:asciiname":"Oradoro",
    "gn:country_code":"IT",
    "gn:dem":495,
    "gn:feature_class":"P",
    "gn:feature_code":"PPLL",
    "gn:name":"Oradoro",
    "gn:population":6,
    "gn:timezone":"Europe/Rome",
    "iso:country":"IT",
    "wof:name":"Oradoro",
    "wof:placetype":"locality",
    "wof:population":6
},
  "geometry": {"coordinates":[9.72462,44.29885],"type":"Point"}
}