{
  "type": "Feature",
  "properties": {
    "gn:admin1_code":"12",
    "gn:admin2_code":"TO",
    "gn:admin3_code":"1035.0",
    "gn:asciiname":"Corbarano",
    "gn:country_code":"IT",
    "gn:dem":365,
    "gn:feature_class":"P",
    "gn:feature_code":"PPLL",
    "gn:name":"Corbarano",
    "gn:population":7,
    "gn:timezone":"Europe/Rome",
    "iso:country":"IT",
    "wof:name":"Corbarano",
    "wof:placetype":"locality",
    "wof:population":7
},
  "geometry": {"coordinates":[7.30639,44.83427],"type":"Point"}
}