{
  "type": "Feature",
  "properties": {
    "gn:admin1_code":"20",
    "gn:admin2_code":"VI",
    "gn:admin3_code":"24036.0",
    "gn:asciiname":"Fusine",
    "gn:country_code":"IT",
    "gn:dem":149,
    "gn:feature_class":"P",
    "gn:feature_code":"PPL",
    "gn:name":"Fusine",
    "gn:population":38,
    "gn:timezone":"Europe/Rome",
    "iso:country":"IT",
    "wof:name":"Fusine",
    "wof:placetype":"locality",
    "wof:population":38
},
  "geometry": {"coordinates":[11.47014,45.54472],"type":"Point"}
}