{
  "type": "Feature",
  "properties": {
    "gn:admin1_code":"20",
    "gn:admin2_code":"VI",
    "gn:admin3_code":"24036.0",
    "gn:asciiname":"Fusine",
    "gn:country_code":"IT",
    "gn:dem":149,
    "gn:feature_class":"P",
    "gn:feature_code":"PPL",
    "gn:name":"Fusine",
    "gn:population":38,
    "gn:timezone":"Europe/Rome",
    "iso:country":"IT",
    "name:azb_x_preferred":[
        "\u0641\u0648\u0632\u06cc\u0646\u0647"
    ],
    "name:bel_x_preferred":[
        "\u0424\u0443\u0437\u0456\u043d\u044d"
    ],
    "name:bul_x_preferred":[
        "\u0424\u0443\u0437\u0438\u043d\u0435"
    ],
    "name:ceb_x_preferred":[
        "Fusine"
    ],
    "name:deu_x_preferred":[
        "Fusine"
    ],
    "name:epo_x_preferred":[
        "Fusine"
    ],
    "name:est_x_preferred":[
        "Fusine"
    ],
    "name:eus_x_preferred":[
        "Fusine"
    ],
    "name:fas_x_preferred":[
        "\u0641\u0648\u0632\u06cc\u0646\u0647"
    ],
    "name:fra_x_preferred":[
        "Fusine"
    ],
    "name:hun_x_preferred":[
        "Fusine"
    ],
    "name:hye_x_preferred":[
        "\u0556\u0578\u0582\u0566\u056b\u0576\u0565"
    ],
    "name:ind_x_preferred":[
        "Fusine"
    ],
    "name:ita_x_preferred":[
        "Fusine"
    ],
    "name:jpn_x_preferred":[
        "\u30d5\u30b8\u30fc\u30cd"
    ],
    "name:kaz_x_preferred":[
        "\u0424\u0443\u0437\u0438\u043d\u0435"
    ],
    "name:lat_x_preferred":[
        "Fucinae"
    ],
    "name:lmo_x_preferred":[
        "F\u00fcsini"
    ],
    "name:msa_x_preferred":[
        "Fusine"
    ],
    "name:nap_x_preferred":[
        "Fusine"
    ],
    "name:nld_x_preferred":[
        "Fusine"
    ],
    "name:pms_x_preferred":[
        "Fusine"
    ],
    "name:pol_x_preferred":[
        "Fusine"
    ],
    "name:por_x_preferred":[
        "Fusine"
    ],
    "name:ron_x_preferred":[
        "Fusine"
    ],
    "name:rus_x_preferred":[
        "\u0424\u0443\u0437\u0438\u043d\u0435"
    ],
    "name:scn_x_preferred":[
        "Fusine"
    ],
    "name:spa_x_preferred":[
        "Fusine"
    ],
    "name:srp_x_preferred":[
        "\u0424\u0443\u0437\u0438\u043d\u0435"
    ],
    "name:tgl_x_preferred":[
        "Fusine"
    ],
    "name:ukr_x_preferred":[
        "\u0424\u0443\u0437\u0456\u043d\u0435"
    ],
    "name:uzb_x_preferred":[
        "Fusine"
    ],
    "name:vie_x_preferred":[
        "Fusine"
    ],
    "name:vol_x_preferred":[
        "Fusine"
    ],
    "name:war_x_preferred":[
        "Fusine"
    ],
    "name:zho_x_preferred":[
        "\u5bcc\u897f\u5185"
    ],
    "wof:name":"Fusine",
    "wof:placetype":"locality",
    "wof:population":38
},
  "geometry": {"coordinates":[11.47014,45.54472],"type":"Point"}
}