{
  "type": "Feature",
  "properties": {
    "gn:admin1_code":"4",
    "gn:admin2_code":"BN",
    "gn:admin3_code":"62008.0",
    "gn:asciiname":"Sciabacca",
    "gn:country_code":"IT",
    "gn:dem":133,
    "gn:feature_class":"P",
    "gn:feature_code":"PPL",
    "gn:name":"Sciabacca",
    "gn:population":29,
    "gn:timezone":"Europe/Rome",
    "iso:country":"IT",
    "wof:name":"Sciabacca",
    "wof:placetype":"locality",
    "wof:population":29
},
  "geometry": {"coordinates":[14.73933,41.13579],"type":"Point"}
}