{
  "type": "Feature",
  "properties": {
    "gn:admin1_code":"7",
    "gn:admin2_code":"FR",
    "gn:admin3_code":"60045.0",
    "gn:asciiname":"Farneto-La Torre",
    "gn:country_code":"IT",
    "gn:dem":170,
    "gn:feature_class":"P",
    "gn:feature_code":"PPL",
    "gn:name":"Farneto-La Torre",
    "gn:population":71,
    "gn:timezone":"Europe/Rome",
    "iso:country":"IT",
    "wof:name":"Farneto-La Torre",
    "wof:placetype":"locality",
    "wof:population":71
},
  "geometry": {"coordinates":[13.20392,41.65178],"type":"Point"}
}