{
  "type": "Feature",
  "properties": {
    "gn:admin1_code":"4.0",
    "gn:admin2_code":"SA",
    "gn:admin3_code":"65126.0",
    "gn:asciiname":"Fontana Vaglio",
    "gn:country_code":"IT",
    "gn:dem":475,
    "gn:feature_class":"P",
    "gn:feature_code":"PPL",
    "gn:name":"Fontana Vaglio",
    "gn:population":538,
    "gn:timezone":"Europe/Rome",
    "iso:country":"IT",
    "wof:name":"Fontana Vaglio",
    "wof:placetype":"locality",
    "wof:population":538
},
  "geometry": {"coordinates":[15.48893,40.41571],"type":"Point"}
}