{
  "type": "Feature",
  "properties": {
    "gn:admin1_code":"15.0",
    "gn:admin2_code":"ME",
    "gn:admin3_code":"83041.0",
    "gn:asciiname":"Chiesa Vetusa",
    "gn:country_code":"IT",
    "gn:dem":159,
    "gn:feature_class":"P",
    "gn:feature_code":"PPL",
    "gn:name":"Chiesa Vetusa",
    "gn:population":0,
    "gn:timezone":"Europe/Rome",
    "iso:country":"IT",
    "wof:name":"Chiesa Vetusa",
    "wof:placetype":"locality"
},
  "geometry": {"coordinates":[14.93333,38.51667],"type":"Point"}
}