{
  "type": "Feature",
  "properties": {
    "gn:admin1_code":"11.0",
    "gn:admin2_code":"CB",
    "gn:admin3_code":"70081.0",
    "gn:asciiname":"Codacchio IV",
    "gn:country_code":"IT",
    "gn:dem":727,
    "gn:feature_class":"P",
    "gn:feature_code":"PPL",
    "gn:name":"Codacchio IV",
    "gn:population":20,
    "gn:timezone":"Europe/Rome",
    "iso:country":"IT",
    "wof:name":"Codacchio IV",
    "wof:placetype":"locality",
    "wof:population":20
},
  "geometry": {"coordinates":[14.61415,41.74847000000001],"type":"Point"}
}