{
  "type": "Feature",
  "properties": {
    "gn:admin1_code":"16",
    "gn:admin2_code":"MS",
    "gn:admin3_code":"45015.0",
    "gn:asciiname":"Pera",
    "gn:country_code":"IT",
    "gn:dem":375,
    "gn:feature_class":"P",
    "gn:feature_code":"PPL",
    "gn:name":"Pera",
    "gn:population":25,
    "gn:timezone":"Europe/Rome",
    "iso:country":"IT",
    "wof:name":"Pera",
    "wof:placetype":"locality",
    "wof:population":25
},
  "geometry": {"coordinates":[9.87572,44.25236],"type":"Point"}
}