{
  "type": "Feature",
  "properties": {
    "gn:admin1_code":"6",
    "gn:admin2_code":"PN",
    "gn:admin3_code":"93012.0",
    "gn:asciiname":"Petrucco",
    "gn:country_code":"IT",
    "gn:dem":355,
    "gn:feature_class":"P",
    "gn:feature_code":"PPLL",
    "gn:name":"Petrucco",
    "gn:population":10,
    "gn:timezone":"Europe/Rome",
    "iso:country":"IT",
    "wof:name":"Petrucco",
    "wof:placetype":"locality",
    "wof:population":10
},
  "geometry": {"coordinates":[12.76211,46.19093],"type":"Point"}
}