{
  "type": "Feature",
  "properties": {
    "gn:admin1_code":"20",
    "gn:admin2_code":"VR",
    "gn:admin3_code":"23076.0",
    "gn:asciiname":"Ossan",
    "gn:country_code":"IT",
    "gn:dem":131,
    "gn:feature_class":"P",
    "gn:feature_code":"PPL",
    "gn:name":"Ossan",
    "gn:population":44,
    "gn:timezone":"Europe/Rome",
    "iso:country":"IT",
    "name:ara_x_preferred":[
        "\u0623\u0648\u0633\u0627\u0646"
    ],
    "name:mal_x_preferred":[
        "\u0d12\u0d38\u0d4d\u0d38\u0d3e\u0d7b\u200c"
    ],
    "wof:name":"Ossan",
    "wof:placetype":"locality",
    "wof:population":44
},
  "geometry": {"coordinates":[10.89135,45.51032],"type":"Point"}
}