{
  "type": "Feature",
  "properties": {
    "gn:admin1_code":"9",
    "gn:admin2_code":"PV",
    "gn:admin3_code":"18098.0",
    "gn:asciiname":"Cencerate",
    "gn:country_code":"IT",
    "gn:dem":224,
    "gn:feature_class":"P",
    "gn:feature_code":"PPLL",
    "gn:name":"Cencerate",
    "gn:population":10,
    "gn:timezone":"Europe/Rome",
    "iso:country":"IT",
    "wof:name":"Cencerate",
    "wof:placetype":"locality",
    "wof:population":10
},
  "geometry": {"coordinates":[9.12797,44.92871],"type":"Point"}
}