{
  "type": "Feature",
  "properties": {
    "gn:admin1_code":"7",
    "gn:admin2_code":"RM",
    "gn:admin3_code":"58081.0",
    "gn:asciiname":"Valle Braccia",
    "gn:country_code":"IT",
    "gn:dem":154,
    "gn:feature_class":"P",
    "gn:feature_code":"PPL",
    "gn:name":"Valle Braccia",
    "gn:population":52,
    "gn:timezone":"Europe/Rome",
    "iso:country":"IT",
    "wof:name":"Valle Braccia",
    "wof:placetype":"locality",
    "wof:population":52
},
  "geometry": {"coordinates":[12.52801,42.09778],"type":"Point"}
}