{
  "type": "Feature",
  "properties": {
    "gn:admin1_code":"7.0",
    "gn:admin2_code":"FR",
    "gn:admin3_code":"60008.0",
    "gn:asciiname":"Isoletta I",
    "gn:country_code":"IT",
    "gn:dem":96,
    "gn:feature_class":"P",
    "gn:feature_code":"PPL",
    "gn:name":"Isoletta I",
    "gn:population":466,
    "gn:timezone":"Europe/Rome",
    "iso:country":"IT",
    "wof:name":"Isoletta I",
    "wof:placetype":"locality",
    "wof:population":466
},
  "geometry": {"coordinates":[13.54518,41.52788],"type":"Point"}
}