{
  "type": "Feature",
  "properties": {
    "gn:admin1_code":"16",
    "gn:admin2_code":"LU",
    "gn:admin3_code":"46004.0",
    "gn:asciiname":"Pedogna",
    "gn:country_code":"IT",
    "gn:dem":114,
    "gn:feature_class":"P",
    "gn:feature_code":"PPL",
    "gn:name":"Pedogna",
    "gn:population":120,
    "gn:timezone":"Europe/Rome",
    "iso:country":"IT",
    "wof:name":"Pedogna",
    "wof:placetype":"locality",
    "wof:population":120
},
  "geometry": {"coordinates":[10.48958,43.97034],"type":"Point"}
}