{
  "type": "Feature",
  "properties": {
    "gn:admin1_code":"10",
    "gn:admin2_code":"MC",
    "gn:admin3_code":"43041.0",
    "gn:asciiname":"Giannandrea",
    "gn:country_code":"IT",
    "gn:dem":270,
    "gn:feature_class":"P",
    "gn:feature_code":"PPL",
    "gn:name":"Giannandrea",
    "gn:population":21,
    "gn:timezone":"Europe/Rome",
    "iso:country":"IT",
    "wof:name":"Giannandrea",
    "wof:placetype":"locality",
    "wof:population":21
},
  "geometry": {"coordinates":[13.33205,43.2667],"type":"Point"}
}