{
  "type": "Feature",
  "properties": {
    "gn:admin1_code":"20",
    "gn:admin2_code":"VR",
    "gn:admin3_code":"23027.0",
    "gn:asciiname":"Stra",
    "gn:country_code":"IT",
    "gn:dem":23,
    "gn:feature_class":"P",
    "gn:feature_code":"PPL",
    "gn:name":"Str\u00e0",
    "gn:population":110,
    "gn:timezone":"Europe/Rome",
    "iso:country":"IT",
    "name:und_x_variant":[
        "Str\u00e0"
    ],
    "wof:name":"Stra",
    "wof:placetype":"locality",
    "wof:population":110
},
  "geometry": {"coordinates":[11.33081,45.32242],"type":"Point"}
}