{
  "type": "Feature",
  "properties": {
    "gn:admin1_code":"20",
    "gn:admin2_code":"VR",
    "gn:admin3_code":"23027.0",
    "gn:asciiname":"Stra",
    "gn:country_code":"IT",
    "gn:dem":23,
    "gn:feature_class":"P",
    "gn:feature_code":"PPL",
    "gn:name":"Str\u00e0",
    "gn:population":110,
    "gn:timezone":"Europe/Rome",
    "iso:country":"IT",
    "name:azb_x_preferred":[
        "\u0627\u0633\u062a\u0631\u0627"
    ],
    "name:bul_x_preferred":[
        "\u0421\u0442\u0440\u0430"
    ],
    "name:cat_x_preferred":[
        "Stra"
    ],
    "name:ceb_x_preferred":[
        "Stra"
    ],
    "name:ces_x_preferred":[
        "Str\u00e0"
    ],
    "name:deu_x_preferred":[
        "Stra"
    ],
    "name:epo_x_preferred":[
        "Stra"
    ],
    "name:eus_x_preferred":[
        "Stra"
    ],
    "name:fas_x_preferred":[
        "\u0627\u0633\u062a\u0631\u0627"
    ],
    "name:fra_x_preferred":[
        "Stra"
    ],
    "name:hun_x_preferred":[
        "Stra"
    ],
    "name:hye_x_preferred":[
        "\u054d\u057f\u0580\u0561"
    ],
    "name:ind_x_preferred":[
        "Stra"
    ],
    "name:ita_x_preferred":[
        "Stra"
    ],
    "name:jpn_x_preferred":[
        "\u30b9\u30c8\u30e9"
    ],
    "name:kaz_x_preferred":[
        "\u0421\u0442\u0440\u0430"
    ],
    "name:lat_x_preferred":[
        "Strata"
    ],
    "name:lmo_x_preferred":[
        "Stra"
    ],
    "name:msa_x_preferred":[
        "Stra"
    ],
    "name:nap_x_preferred":[
        "Stra"
    ],
    "name:nld_x_preferred":[
        "Stra"
    ],
    "name:pms_x_preferred":[
        "Stra"
    ],
    "name:pol_x_preferred":[
        "Stra"
    ],
    "name:por_x_preferred":[
        "Stra"
    ],
    "name:ron_x_preferred":[
        "Stra"
    ],
    "name:rus_x_preferred":[
        "\u0421\u0442\u0440\u0430"
    ],
    "name:scn_x_preferred":[
        "Stra"
    ],
    "name:spa_x_preferred":[
        "Stra"
    ],
    "name:srp_x_preferred":[
        "\u0421\u0442\u0440\u0430"
    ],
    "name:tgl_x_preferred":[
        "Stra"
    ],
    "name:ukr_x_preferred":[
        "\u0421\u0442\u0440\u0430"
    ],
    "name:und_x_variant":[
        "Str\u00e0"
    ],
    "name:uzb_x_preferred":[
        "Stra"
    ],
    "name:vec_x_preferred":[
        "Stra"
    ],
    "name:vol_x_preferred":[
        "Stra"
    ],
    "name:war_x_preferred":[
        "Str\u00e0"
    ],
    "name:zho_x_preferred":[
        "\u65af\u7279\u62c9"
    ],
    "wof:name":"Stra",
    "wof:placetype":"locality",
    "wof:population":110
},
  "geometry": {"coordinates":[11.33081,45.32242],"type":"Point"}
}