{
  "type": "Feature",
  "properties": {
    "gn:admin1_code":"16",
    "gn:admin2_code":"MS",
    "gn:admin3_code":"45014.0",
    "gn:asciiname":"Pietra Piccata",
    "gn:country_code":"IT",
    "gn:dem":858,
    "gn:feature_class":"P",
    "gn:feature_code":"PPL",
    "gn:name":"Pietra Piccata",
    "gn:population":23,
    "gn:timezone":"Europe/Rome",
    "iso:country":"IT",
    "wof:name":"Pietra Piccata",
    "wof:placetype":"locality",
    "wof:population":23
},
  "geometry": {"coordinates":[9.83837,44.33887],"type":"Point"}
}