{
  "type": "Feature",
  "properties": {
    "gn:admin1_code":"9",
    "gn:admin2_code":"LO",
    "gn:admin3_code":"98019.0",
    "gn:asciiname":"Maiocca",
    "gn:country_code":"IT",
    "gn:dem":64,
    "gn:feature_class":"P",
    "gn:feature_code":"PPL",
    "gn:name":"Maiocca",
    "gn:population":205,
    "gn:timezone":"Europe/Rome",
    "iso:country":"IT",
    "wof:name":"Maiocca",
    "wof:placetype":"locality",
    "wof:population":205
},
  "geometry": {"coordinates":[9.68257,45.1783],"type":"Point"}
}