{
  "type": "Feature",
  "properties": {
    "gn:admin1_code":"5",
    "gn:admin2_code":"PC",
    "gn:admin3_code":"33026.0",
    "gn:asciiname":"Fondo",
    "gn:country_code":"IT",
    "gn:dem":274,
    "gn:feature_class":"P",
    "gn:feature_code":"PPL",
    "gn:name":"Fondo",
    "gn:population":16,
    "gn:timezone":"Europe/Rome",
    "iso:country":"IT",
    "wof:name":"Fondo",
    "wof:placetype":"locality",
    "wof:population":16
},
  "geometry": {"coordinates":[9.81135,44.85559],"type":"Point"}
}