{
  "type": "Feature",
  "properties": {
    "gn:admin1_code":"5",
    "gn:admin2_code":"PC",
    "gn:admin3_code":"33026.0",
    "gn:asciiname":"Fondo",
    "gn:country_code":"IT",
    "gn:dem":274,
    "gn:feature_class":"P",
    "gn:feature_code":"PPL",
    "gn:name":"Fondo",
    "gn:population":16,
    "gn:timezone":"Europe/Rome",
    "iso:country":"IT",
    "name:cat_x_preferred":[
        "Fondo"
    ],
    "name:ceb_x_preferred":[
        "Fondo"
    ],
    "name:deu_x_preferred":[
        "Fondo"
    ],
    "name:epo_x_preferred":[
        "Fondo"
    ],
    "name:est_x_preferred":[
        "Fondo"
    ],
    "name:eus_x_preferred":[
        "Fondo"
    ],
    "name:fra_x_preferred":[
        "Fondo"
    ],
    "name:hun_x_preferred":[
        "Fondo"
    ],
    "name:hye_x_preferred":[
        "\u0556\u0578\u0576\u0564\u0578"
    ],
    "name:ind_x_preferred":[
        "Fondo"
    ],
    "name:ita_x_preferred":[
        "Fondo"
    ],
    "name:jpn_x_preferred":[
        "\u30d5\u30a9\u30f3\u30c9"
    ],
    "name:kaz_x_preferred":[
        "\u0424\u043e\u043d\u0434\u043e"
    ],
    "name:lat_x_preferred":[
        "Fondum"
    ],
    "name:lmo_x_preferred":[
        "Fondo"
    ],
    "name:msa_x_preferred":[
        "Fondo"
    ],
    "name:nap_x_preferred":[
        "Fondo"
    ],
    "name:nld_x_preferred":[
        "Fondo"
    ],
    "name:pms_x_preferred":[
        "Fondo"
    ],
    "name:pol_x_preferred":[
        "Fondo"
    ],
    "name:por_x_preferred":[
        "Fondo"
    ],
    "name:ron_x_preferred":[
        "Fondo"
    ],
    "name:rus_x_preferred":[
        "\u0424\u043e\u043d\u0434\u043e"
    ],
    "name:scn_x_preferred":[
        "Fondo"
    ],
    "name:spa_x_preferred":[
        "Fondo"
    ],
    "name:srp_x_preferred":[
        "\u0424\u043e\u043d\u0434\u043e"
    ],
    "name:tgl_x_preferred":[
        "Fondo"
    ],
    "name:ukr_x_preferred":[
        "\u0424\u043e\u043d\u0434\u043e"
    ],
    "name:uzb_x_preferred":[
        "Fondo"
    ],
    "name:vie_x_preferred":[
        "Fondo"
    ],
    "name:vol_x_preferred":[
        "Fondo"
    ],
    "name:war_x_preferred":[
        "Fondo"
    ],
    "wof:name":"Fondo",
    "wof:placetype":"locality",
    "wof:population":16
},
  "geometry": {"coordinates":[9.81135,44.85559],"type":"Point"}
}