{
  "type": "Feature",
  "properties": {
    "gn:admin1_code":"7",
    "gn:admin2_code":"FR",
    "gn:admin3_code":"60050.0",
    "gn:asciiname":"Serre",
    "gn:country_code":"IT",
    "gn:dem":495,
    "gn:feature_class":"P",
    "gn:feature_code":"PPL",
    "gn:name":"Serre",
    "gn:population":62,
    "gn:timezone":"Europe/Rome",
    "iso:country":"IT",
    "name:bel_x_preferred":[
        "\u0421\u0435\u0440\u044d"
    ],
    "name:ceb_x_preferred":[
        "Serre"
    ],
    "name:deu_x_preferred":[
        "Serre"
    ],
    "name:fra_x_preferred":[
        "Serre"
    ],
    "name:ita_x_preferred":[
        "Serre"
    ],
    "name:kaz_x_preferred":[
        "\u0421\u0435\u0440\u0440\u0435"
    ],
    "name:nds_x_preferred":[
        "Serre"
    ],
    "name:nld_x_preferred":[
        "Serre"
    ],
    "name:pol_x_preferred":[
        "Serre"
    ],
    "name:rus_x_preferred":[
        "\u0421\u0435\u0440\u0440\u0435"
    ],
    "name:srp_x_preferred":[
        "Sere"
    ],
    "name:swe_x_preferred":[
        "Serre"
    ],
    "wof:name":"Serre",
    "wof:placetype":"locality",
    "wof:population":62
},
  "geometry": {"coordinates":[13.85949,41.62758],"type":"Point"}
}