{
  "type": "Feature",
  "properties": {
    "gn:admin1_code":"4",
    "gn:admin2_code":"BN",
    "gn:admin3_code":"62044.0",
    "gn:asciiname":"Case Senzamici",
    "gn:country_code":"IT",
    "gn:dem":432,
    "gn:feature_class":"P",
    "gn:feature_code":"PPL",
    "gn:name":"Case Senzamici",
    "gn:population":30,
    "gn:timezone":"Europe/Rome",
    "iso:country":"IT",
    "wof:name":"Case Senzamici",
    "wof:placetype":"locality",
    "wof:population":30
},
  "geometry": {"coordinates":[14.71176,41.35311],"type":"Point"}
}