{
  "type": "Feature",
  "properties": {
    "gn:admin1_code":"12.0",
    "gn:admin2_code":"TO",
    "gn:admin3_code":"1311.0",
    "gn:asciiname":"Cascina Ova",
    "gn:country_code":"IT",
    "gn:dem":218,
    "gn:feature_class":"P",
    "gn:feature_code":"PPL",
    "gn:name":"Cascina Ova",
    "gn:population":19,
    "gn:timezone":"Europe/Rome",
    "iso:country":"IT",
    "wof:name":"Cascina Ova",
    "wof:placetype":"locality",
    "wof:population":19
},
  "geometry": {"coordinates":[7.93311,45.34225],"type":"Point"}
}