{
  "type": "Feature",
  "properties": {
    "gn:admin1_code":"12",
    "gn:admin2_code":"TO",
    "gn:admin3_code":"1049.0",
    "gn:asciiname":"Cascina Peiretti",
    "gn:country_code":"IT",
    "gn:dem":352,
    "gn:feature_class":"P",
    "gn:feature_code":"PPL",
    "gn:name":"Cascina Peiretti",
    "gn:population":57,
    "gn:timezone":"Europe/Rome",
    "iso:country":"IT",
    "wof:name":"Cascina Peiretti",
    "wof:placetype":"locality",
    "wof:population":57
},
  "geometry": {"coordinates":[7.33624,44.80432],"type":"Point"}
}