{
  "type": "Feature",
  "properties": {
    "gn:admin1_code":"10",
    "gn:admin2_code":"AN",
    "gn:admin3_code":"42043.0",
    "gn:asciiname":"Pradellona",
    "gn:country_code":"IT",
    "gn:dem":142,
    "gn:feature_class":"P",
    "gn:feature_code":"PPL",
    "gn:name":"Pradellona",
    "gn:population":24,
    "gn:timezone":"Europe/Rome",
    "iso:country":"IT",
    "wof:name":"Pradellona",
    "wof:placetype":"locality",
    "wof:population":24
},
  "geometry": {"coordinates":[13.31173,43.47008],"type":"Point"}
}