{
  "type": "Feature",
  "properties": {
    "gn:country":"IT",
    "gn:fcode":"PPL",
    "gn:population":0,
    "iso:country":"IT",
    "name:cat_x_preferred":[
        "Spiaggia di Fetovaia"
    ],
    "name:ces_x_preferred":[
        "Spiaggia di Fetovaia"
    ],
    "name:dan_x_preferred":[
        "Spiaggia di Fetovaia"
    ],
    "name:eng_x_preferred":[
        "Spiaggia di Fetovaia"
    ],
    "name:eus_x_preferred":[
        "Spiaggia di Fetovaia"
    ],
    "name:fin_x_preferred":[
        "Spiaggia di Fetovaia"
    ],
    "name:fra_x_preferred":[
        "Spiaggia di Fetovaia"
    ],
    "name:ind_x_preferred":[
        "Spiaggia di Fetovaia"
    ],
    "name:ita_x_preferred":[
        "Spiaggia di Fetovaia"
    ],
    "name:nld_x_preferred":[
        "Spiaggia di Fetovaia"
    ],
    "name:nno_x_preferred":[
        "Spiaggia di Fetovaia"
    ],
    "name:nob_x_preferred":[
        "Spiaggia di Fetovaia"
    ],
    "name:oci_x_preferred":[
        "Spiaggia di Fetovaia"
    ],
    "name:pol_x_preferred":[
        "Spiaggia di Fetovaia"
    ],
    "name:por_x_preferred":[
        "Spiaggia di Fetovaia"
    ],
    "name:ron_x_preferred":[
        "Spiaggia di Fetovaia"
    ],
    "name:slk_x_preferred":[
        "Spiaggia di Fetovaia"
    ],
    "name:slv_x_preferred":[
        "Spiaggia di Fetovaia"
    ],
    "name:spa_x_preferred":[
        "Spiaggia di Fetovaia"
    ],
    "name:srp_x_preferred":[
        "Fetovaia"
    ],
    "name:swe_x_preferred":[
        "Spiaggia di Fetovaia"
    ],
    "name:tgl_x_preferred":[
        "Spiaggia di Fetovaia"
    ],
    "name:tur_x_preferred":[
        "Spiaggia di Fetovaia"
    ],
    "name:und_x_variant":[
        "Felovaja"
    ],
    "name:war_x_preferred":[
        "Spiaggia di Fetovaia"
    ],
    "qs_pg:aaroncc":"IT",
    "qs_pg:gn_country":"IT",
    "qs_pg:gn_fcode":"PPL",
    "qs_pg:gn_pop":0,
    "qs_pg:name":"Fetovaia",
    "qs_pg:name_adm0":"Italia",
    "qs_pg:name_adm1":"Toscana",
    "qs_pg:photos":399,
    "qs_pg:photos_1k":81,
    "qs_pg:photos_9k":2,
    "qs_pg:photos_9r":5,
    "qs_pg:photos_all":399,
    "qs_pg:photos_sr":6,
    "qs_pg:pop_sr":0,
    "qs_pg:qs_pg_placetype":"locality",
    "qs_pg:qs_pg_placetype_gp":"Town",
    "qs_pg:woe_adm0":23424853,
    "woe:adm0_id":23424853,
    "woe:name_adm0":"Italia",
    "woe:name_adm1":"Toscana",
    "woe:placetype":"Town",
    "wof:name":"Fetovaia",
    "wof:placetype":"locality",
    "wof:population":67
},
  "geometry": {"coordinates":[10.15265,42.73491],"type":"Point"}
}