{
  "type": "Feature",
  "properties": {
    "gn:admin1_code":"5",
    "gn:admin2_code":"PC",
    "gn:admin3_code":"33045.0",
    "gn:asciiname":"Case della Chiesa",
    "gn:country_code":"IT",
    "gn:dem":157,
    "gn:feature_class":"P",
    "gn:feature_code":"PPL",
    "gn:name":"Case della Chiesa",
    "gn:population":30,
    "gn:timezone":"Europe/Rome",
    "iso:country":"IT",
    "wof:name":"Case della Chiesa",
    "wof:placetype":"locality",
    "wof:population":30
},
  "geometry": {"coordinates":[9.67859,44.91712],"type":"Point"}
}