{
  "type": "Feature",
  "properties": {
    "gn:admin1_code":"16",
    "gn:admin2_code":"FI",
    "gn:admin3_code":"48021.0",
    "gn:asciiname":"Il Piano",
    "gn:country_code":"IT",
    "gn:dem":601,
    "gn:feature_class":"P",
    "gn:feature_code":"PPL",
    "gn:name":"Il Piano",
    "gn:population":12,
    "gn:timezone":"Europe/Rome",
    "iso:country":"IT",
    "wof:name":"Il Piano",
    "wof:placetype":"locality",
    "wof:population":12
},
  "geometry": {"coordinates":[11.35839,43.54671],"type":"Point"}
}