{
  "type": "Feature",
  "properties": {
    "gn:admin1_code":"12",
    "gn:admin2_code":"AL",
    "gn:admin3_code":"6169.0",
    "gn:asciiname":"Gambina",
    "gn:country_code":"IT",
    "gn:dem":242,
    "gn:feature_class":"P",
    "gn:feature_code":"PPL",
    "gn:name":"Gambina",
    "gn:population":33,
    "gn:timezone":"Europe/Rome",
    "iso:country":"IT",
    "wof:name":"Gambina",
    "wof:placetype":"locality",
    "wof:population":33
},
  "geometry": {"coordinates":[8.68849,44.63467],"type":"Point"}
}