{
  "type": "Feature",
  "properties": {
    "gn:admin1_code":"16.0",
    "gn:admin2_code":"MS",
    "gn:admin3_code":"45003.0",
    "gn:asciiname":"Miseglia",
    "gn:country_code":"IT",
    "gn:dem":232,
    "gn:elevation":"240.0",
    "gn:feature_class":"P",
    "gn:feature_code":"PPL",
    "gn:name":"Miseglia",
    "gn:population":449,
    "gn:timezone":"Europe/Rome",
    "iso:country":"IT",
    "name:azb_x_preferred":[
        "\u0645\u06cc\u0632\u0644\u06cc\u0627"
    ],
    "name:ceb_x_preferred":[
        "Miseglia"
    ],
    "name:fas_x_preferred":[
        "\u0645\u06cc\u0632\u0644\u06cc\u0627"
    ],
    "name:ita_x_preferred":[
        "Miseglia"
    ],
    "name:srp_x_preferred":[
        "\u041c\u0438\u0437\u0435\u0459\u0438\u0458\u0430"
    ],
    "wof:name":"Miseglia",
    "wof:placetype":"locality",
    "wof:population":449
},
  "geometry": {"coordinates":[10.11565,44.08354],"type":"Point"}
}