{
  "type": "Feature",
  "properties": {
    "gn:admin1_code":"9.0",
    "gn:admin2_code":"BS",
    "gn:admin3_code":"17014.0",
    "gn:asciiname":"Campagnola",
    "gn:country_code":"IT",
    "gn:dem":141,
    "gn:feature_class":"P",
    "gn:feature_code":"PPL",
    "gn:name":"Campagnola",
    "gn:population":800,
    "gn:timezone":"Europe/Rome",
    "iso:country":"IT",
    "wof:name":"Campagnola",
    "wof:placetype":"locality",
    "wof:population":800
},
  "geometry": {"coordinates":[10.40723,45.48463],"type":"Point"}
}