{
  "type": "Feature",
  "properties": {
    "gn:admin1_code":"1",
    "gn:admin2_code":"AQ",
    "gn:admin3_code":"66098.0",
    "gn:asciiname":"Case Comunali Forma Torta",
    "gn:country_code":"IT",
    "gn:dem":453,
    "gn:feature_class":"P",
    "gn:feature_code":"PPL",
    "gn:name":"Case Comunali Forma Torta",
    "gn:population":104,
    "gn:timezone":"Europe/Rome",
    "iso:country":"IT",
    "wof:name":"Case Comunali Forma Torta",
    "wof:placetype":"locality",
    "wof:population":104
},
  "geometry": {"coordinates":[13.93259,42.02476],"type":"Point"}
}