{
  "type": "Feature",
  "properties": {
    "gn:admin1_code":"12",
    "gn:admin2_code":"BI",
    "gn:admin3_code":"96065.0",
    "gn:asciiname":"Deila-Donno",
    "gn:country_code":"IT",
    "gn:dem":376,
    "gn:feature_class":"P",
    "gn:feature_code":"PPL",
    "gn:name":"Deila-Donno",
    "gn:population":17,
    "gn:timezone":"Europe/Rome",
    "iso:country":"IT",
    "wof:name":"Deila-Donno",
    "wof:placetype":"locality",
    "wof:population":17
},
  "geometry": {"coordinates":[8.16718,45.61243],"type":"Point"}
}