{
  "type": "Feature",
  "properties": {
    "gn:admin1_code":"16.0",
    "gn:admin2_code":"GR",
    "gn:admin3_code":"53011.0",
    "gn:asciiname":"Pianetto",
    "gn:country_code":"IT",
    "gn:dem":3,
    "gn:feature_class":"P",
    "gn:feature_code":"PPL",
    "gn:name":"Pianetto",
    "gn:population":0,
    "gn:timezone":"Europe/Rome",
    "iso:country":"IT",
    "wof:name":"Pianetto",
    "wof:placetype":"locality"
},
  "geometry": {"coordinates":[11.07396,42.74563],"type":"Point"}
}