{
  "type": "Feature",
  "properties": {
    "gn:admin1_code":"5.0",
    "gn:admin2_code":"MO",
    "gn:admin3_code":"36022.0",
    "gn:asciiname":"Gavello",
    "gn:country_code":"IT",
    "gn:dem":11,
    "gn:elevation":"14.0",
    "gn:feature_class":"P",
    "gn:feature_code":"PPL",
    "gn:name":"Gavello",
    "gn:population":293,
    "gn:timezone":"Europe/Rome",
    "iso:country":"IT",
    "wof:name":"Gavello",
    "wof:placetype":"locality",
    "wof:population":293
},
  "geometry": {"coordinates":[11.18036,44.92562],"type":"Point"}
}