{
  "type": "Feature",
  "properties": {
    "gn:admin1_code":"5.0",
    "gn:admin2_code":"MO",
    "gn:admin3_code":"36022.0",
    "gn:asciiname":"Gavello",
    "gn:country_code":"IT",
    "gn:dem":11,
    "gn:elevation":"14.0",
    "gn:feature_class":"P",
    "gn:feature_code":"PPL",
    "gn:name":"Gavello",
    "gn:population":293,
    "gn:timezone":"Europe/Rome",
    "iso:country":"IT",
    "name:azb_x_preferred":[
        "\u062c\u0627\u0648\u0644\u0648"
    ],
    "name:bul_x_preferred":[
        "\u0413\u0430\u0432\u0435\u043b\u043e"
    ],
    "name:ceb_x_preferred":[
        "Gavello"
    ],
    "name:deu_x_preferred":[
        "Gavello"
    ],
    "name:epo_x_preferred":[
        "Gavello"
    ],
    "name:eus_x_preferred":[
        "Gavello"
    ],
    "name:fas_x_preferred":[
        "\u062c\u0627\u0648\u0644\u0648"
    ],
    "name:fra_x_preferred":[
        "Gavello"
    ],
    "name:hun_x_preferred":[
        "Gavello"
    ],
    "name:hye_x_preferred":[
        "\u0533\u0561\u057e\u0565\u056c\u0578"
    ],
    "name:ita_x_preferred":[
        "Gavello"
    ],
    "name:jpn_x_preferred":[
        "\u30ac\u30f4\u30a7\u30c3\u30ed"
    ],
    "name:kaz_x_preferred":[
        "\u0413\u0430\u0432\u0435\u043b\u043b\u043e"
    ],
    "name:lat_x_preferred":[
        "Gabellum"
    ],
    "name:lmo_x_preferred":[
        "Gavello"
    ],
    "name:msa_x_preferred":[
        "Gavello"
    ],
    "name:nap_x_preferred":[
        "Gavello"
    ],
    "name:nld_x_preferred":[
        "Gavello"
    ],
    "name:pms_x_preferred":[
        "Gavello"
    ],
    "name:pol_x_preferred":[
        "Gavello"
    ],
    "name:por_x_preferred":[
        "Gavello"
    ],
    "name:ron_x_preferred":[
        "Gavello"
    ],
    "name:rus_x_preferred":[
        "\u0413\u0430\u0432\u0435\u043b\u043b\u043e"
    ],
    "name:scn_x_preferred":[
        "Gavello"
    ],
    "name:spa_x_preferred":[
        "Gavello"
    ],
    "name:srp_x_preferred":[
        "\u0413\u0430\u0432\u0435\u043b\u043e"
    ],
    "name:tgl_x_preferred":[
        "Gavello"
    ],
    "name:ukr_x_preferred":[
        "\u0413\u0430\u0432\u0435\u043b\u043b\u043e"
    ],
    "name:uzb_x_preferred":[
        "Gavello"
    ],
    "name:vec_x_preferred":[
        "Gave\u0142o"
    ],
    "name:vie_x_preferred":[
        "Gavello"
    ],
    "name:vol_x_preferred":[
        "Gavello"
    ],
    "name:war_x_preferred":[
        "Gavello"
    ],
    "name:zho_x_preferred":[
        "\u52a0\u97e6\u6d1b"
    ],
    "wof:name":"Gavello",
    "wof:placetype":"locality",
    "wof:population":293
},
  "geometry": {"coordinates":[11.18036,44.92562],"type":"Point"}
}