{
  "type": "Feature",
  "properties": {
    "gn:admin1_code":"16",
    "gn:admin2_code":"AR",
    "gn:admin3_code":"51002.0",
    "gn:asciiname":"Il Busco",
    "gn:country_code":"IT",
    "gn:dem":374,
    "gn:feature_class":"P",
    "gn:feature_code":"PPL",
    "gn:name":"Il Busco",
    "gn:population":20,
    "gn:timezone":"Europe/Rome",
    "iso:country":"IT",
    "wof:name":"Il Busco",
    "wof:placetype":"locality",
    "wof:population":20
},
  "geometry": {"coordinates":[11.92163,43.437],"type":"Point"}
}