{
  "type": "Feature",
  "properties": {
    "gn:admin1_code":"1.0",
    "gn:admin2_code":"PE",
    "gn:admin3_code":"68042.0",
    "gn:asciiname":"Osservanza",
    "gn:country_code":"IT",
    "gn:dem":384,
    "gn:feature_class":"P",
    "gn:feature_code":"PPLL",
    "gn:name":"Osservanza",
    "gn:population":4,
    "gn:timezone":"Europe/Rome",
    "iso:country":"IT",
    "wof:name":"Osservanza",
    "wof:placetype":"locality",
    "wof:population":4
},
  "geometry": {"coordinates":[13.90769,42.20361],"type":"Point"}
}