{
  "type": "Feature",
  "properties": {
    "gn:admin1_code":"7.0",
    "gn:admin2_code":"RI",
    "gn:admin3_code":"57034.0",
    "gn:asciiname":"San Silvestro",
    "gn:country_code":"IT",
    "gn:dem":755,
    "gn:elevation":"742.0",
    "gn:feature_class":"P",
    "gn:feature_code":"PPL",
    "gn:name":"San Silvestro",
    "gn:population":98,
    "gn:timezone":"Europe/Rome",
    "iso:country":"IT",
    "name:ceb_x_preferred":[
        "San Silvestro"
    ],
    "name:deu_x_preferred":[
        "San Silvestro"
    ],
    "name:ita_x_preferred":[
        "San Silvestro"
    ],
    "name:srp_x_preferred":[
        "San Silvestro"
    ],
    "name:swe_x_preferred":[
        "San Silvestro"
    ],
    "wof:name":"San Silvestro",
    "wof:placetype":"locality",
    "wof:population":98
},
  "geometry": {"coordinates":[12.9449,42.31652],"type":"Point"}
}