{
  "type": "Feature",
  "properties": {
    "gn:admin1_code":"9",
    "gn:admin2_code":"SO",
    "gn:admin3_code":"14028.0",
    "gn:asciiname":"Campilunghi",
    "gn:country_code":"IT",
    "gn:dem":297,
    "gn:feature_class":"P",
    "gn:feature_code":"PPL",
    "gn:name":"Campilunghi",
    "gn:population":27,
    "gn:timezone":"Europe/Rome",
    "iso:country":"IT",
    "wof:name":"Campilunghi",
    "wof:placetype":"locality",
    "wof:population":27
},
  "geometry": {"coordinates":[9.90039,46.15879],"type":"Point"}
}