{
  "type": "Feature",
  "properties": {
    "gn:admin1_code":"15",
    "gn:admin2_code":"ME",
    "gn:admin3_code":"83007.0",
    "gn:asciiname":"Jannello",
    "gn:country_code":"IT",
    "gn:dem":283,
    "gn:feature_class":"P",
    "gn:feature_code":"PPL",
    "gn:name":"Jannello",
    "gn:population":188,
    "gn:timezone":"Europe/Rome",
    "iso:country":"IT",
    "wof:name":"Jannello",
    "wof:placetype":"locality",
    "wof:population":188
},
  "geometry": {"coordinates":[14.84208,38.14732],"type":"Point"}
}