{
  "type": "Feature",
  "properties": {
    "gn:admin1_code":"6",
    "gn:admin2_code":"UD",
    "gn:admin3_code":"30030.0",
    "gn:asciiname":"Noax",
    "gn:country_code":"IT",
    "gn:dem":97,
    "gn:feature_class":"P",
    "gn:feature_code":"PPL",
    "gn:name":"Noax",
    "gn:population":68,
    "gn:timezone":"Europe/Rome",
    "iso:country":"IT",
    "wof:name":"Noax",
    "wof:placetype":"locality",
    "wof:population":68
},
  "geometry": {"coordinates":[13.43221,46.01091],"type":"Point"}
}