{
  "type": "Feature",
  "properties": {
    "gn:admin1_code":"12",
    "gn:admin2_code":"NO",
    "gn:admin3_code":"3100.0",
    "gn:asciiname":"Cascina Nuova",
    "gn:country_code":"IT",
    "gn:dem":209,
    "gn:feature_class":"P",
    "gn:feature_code":"PPL",
    "gn:name":"Cascina Nuova",
    "gn:population":18,
    "gn:timezone":"Europe/Rome",
    "iso:country":"IT",
    "wof:name":"Cascina Nuova",
    "wof:placetype":"locality",
    "wof:population":18
},
  "geometry": {"coordinates":[8.54538,45.57385],"type":"Point"}
}