{
  "type": "Feature",
  "properties": {
    "gn:admin1_code":"11.0",
    "gn:admin2_code":"CB",
    "gn:admin3_code":"70075.0",
    "gn:asciiname":"Altilia II",
    "gn:country_code":"IT",
    "gn:dem":557,
    "gn:feature_class":"P",
    "gn:feature_code":"PPL",
    "gn:name":"Altilia II",
    "gn:population":13,
    "gn:timezone":"Europe/Rome",
    "iso:country":"IT",
    "wof:name":"Altilia II",
    "wof:placetype":"locality",
    "wof:population":13
},
  "geometry": {"coordinates":[14.62271,41.43243],"type":"Point"}
}