{
  "type": "Feature",
  "properties": {
    "gn:admin1_code":"9",
    "gn:admin2_code":"BG",
    "gn:admin3_code":"16022.0",
    "gn:asciiname":"Catoi",
    "gn:country_code":"IT",
    "gn:dem":537,
    "gn:feature_class":"P",
    "gn:feature_code":"PPL",
    "gn:name":"Catoi",
    "gn:population":20,
    "gn:timezone":"Europe/Rome",
    "iso:country":"IT",
    "wof:name":"Catoi",
    "wof:placetype":"locality",
    "wof:population":20
},
  "geometry": {"coordinates":[9.55843,45.78919000000001],"type":"Point"}
}