{
  "type": "Feature",
  "properties": {
    "gn:admin1_code":"10",
    "gn:admin2_code":"PU",
    "gn:admin3_code":"41065.0",
    "gn:asciiname":"Madonna del Monte",
    "gn:country_code":"IT",
    "gn:dem":200,
    "gn:feature_class":"P",
    "gn:feature_code":"PPL",
    "gn:name":"Madonna del Monte",
    "gn:population":19,
    "gn:timezone":"Europe/Rome",
    "iso:country":"IT",
    "wof:name":"Madonna del Monte",
    "wof:placetype":"locality",
    "wof:population":19
},
  "geometry": {"coordinates":[12.76588,43.89597],"type":"Point"}
}