{
  "type": "Feature",
  "properties": {
    "gn:admin1_code":"20",
    "gn:admin2_code":"PD",
    "gn:admin3_code":"28013.0",
    "gn:asciiname":"Caccin",
    "gn:country_code":"IT",
    "gn:dem":16,
    "gn:feature_class":"P",
    "gn:feature_code":"PPL",
    "gn:name":"Caccin",
    "gn:population":74,
    "gn:timezone":"Europe/Rome",
    "iso:country":"IT",
    "wof:name":"Caccin",
    "wof:placetype":"locality",
    "wof:population":74
},
  "geometry": {"coordinates":[11.99307,45.53598],"type":"Point"}
}