{
  "type": "Feature",
  "properties": {
    "iso:country":"IT",
    "qs:a0":"Italia",
    "qs:a1":"*Teramo",
    "qs:a1r":"0Abruzzo",
    "qs:adm0":"Italia",
    "qs:la_lc":"*",
    "qs:level":"locality",
    "qs:loc":"Pianura Vomano",
    "qs:loc_alt":"Pianura Vomano",
    "qs:pop":0,
    "qs:type":"buffered point",
    "wof:name":"Pianura Vomano",
    "wof:placetype":"locality"
},
  "geometry": {"coordinates":[13.901689,42.63221],"type":"Point"}
}