{
  "type": "Feature",
  "properties": {
    "gn:admin1_code":"9",
    "gn:admin2_code":"MI",
    "gn:admin3_code":"15085.0",
    "gn:asciiname":"Cascina Preloreto",
    "gn:country_code":"IT",
    "gn:dem":133,
    "gn:feature_class":"P",
    "gn:feature_code":"PPL",
    "gn:name":"Cascina Preloreto",
    "gn:population":61,
    "gn:timezone":"Europe/Rome",
    "iso:country":"IT",
    "wof:name":"Cascina Preloreto",
    "wof:placetype":"locality",
    "wof:population":61
},
  "geometry": {"coordinates":[8.90814,45.45451],"type":"Point"}
}