{
  "type": "Feature",
  "properties": {
    "gn:admin1_code":"14",
    "gn:admin2_code":"OR",
    "gn:admin3_code":"95047.0",
    "gn:asciiname":"Corte Baccas",
    "gn:country_code":"IT",
    "gn:dem":10,
    "gn:feature_class":"P",
    "gn:feature_code":"PPL",
    "gn:name":"Corte Baccas",
    "gn:population":84,
    "gn:timezone":"Europe/Rome",
    "iso:country":"IT",
    "wof:name":"Corte Baccas",
    "wof:placetype":"locality",
    "wof:population":84
},
  "geometry": {"coordinates":[8.61063,39.89135],"type":"Point"}
}