{
  "type": "Feature",
  "properties": {
    "gn:admin1_code":"18",
    "gn:admin2_code":"PG",
    "gn:admin3_code":"54051.0",
    "gn:asciiname":"Scuola di San Nicolo",
    "gn:country_code":"IT",
    "gn:dem":276,
    "gn:feature_class":"P",
    "gn:feature_code":"PPL",
    "gn:name":"Scuola di San Nicol\u00f2",
    "gn:population":94,
    "gn:timezone":"Europe/Rome",
    "iso:country":"IT",
    "name:und_x_variant":[
        "Scuola di San Nicol\u00f2"
    ],
    "wof:name":"Scuola di San Nicolo",
    "wof:placetype":"locality",
    "wof:population":94
},
  "geometry": {"coordinates":[12.70915,42.75525],"type":"Point"}
}