{
  "type": "Feature",
  "properties": {
    "gn:admin1_code":"10",
    "gn:admin2_code":"AN",
    "gn:admin3_code":"42005.0",
    "gn:asciiname":"Fornace",
    "gn:country_code":"IT",
    "gn:dem":189,
    "gn:feature_class":"P",
    "gn:feature_code":"PPL",
    "gn:name":"Fornace",
    "gn:population":171,
    "gn:timezone":"Europe/Rome",
    "iso:country":"IT",
    "wof:name":"Fornace",
    "wof:placetype":"locality",
    "wof:population":171
},
  "geometry": {"coordinates":[13.14219,43.55923],"type":"Point"}
}