{
  "type": "Feature",
  "properties": {
    "gn:admin1_code":"12.0",
    "gn:admin2_code":"TO",
    "gn:admin3_code":"1030.0",
    "gn:asciiname":"Grangia/Spinetto",
    "gn:country_code":"IT",
    "gn:dem":258,
    "gn:feature_class":"P",
    "gn:feature_code":"PPLL",
    "gn:name":"Grangia/Spinetto",
    "gn:population":0,
    "gn:timezone":"Europe/Rome",
    "iso:country":"IT",
    "wof:name":"Grangia/Spinetto",
    "wof:placetype":"locality"
},
  "geometry": {"coordinates":[7.84202,45.52493],"type":"Point"}
}