{
  "type": "Feature",
  "properties": {
    "gn:admin1_code":"4.0",
    "gn:admin3_code":"63034.0",
    "gn:asciiname":"Masseria Vecchia Est",
    "gn:country_code":"IT",
    "gn:dem":41,
    "gn:feature_class":"P",
    "gn:feature_code":"PPL",
    "gn:name":"Masseria Vecchia Est",
    "gn:population":148,
    "gn:timezone":"Europe/Rome",
    "iso:country":"IT",
    "wof:name":"Masseria Vecchia Est",
    "wof:placetype":"locality",
    "wof:population":148
},
  "geometry": {"coordinates":[14.07964,40.89788],"type":"Point"}
}