{
  "type": "Feature",
  "properties": {
    "gn:admin1_code":"10",
    "gn:admin2_code":"AP",
    "gn:admin3_code":"44011.0",
    "gn:asciiname":"Cabbiano",
    "gn:country_code":"IT",
    "gn:dem":135,
    "gn:feature_class":"P",
    "gn:feature_code":"PPL",
    "gn:name":"Cabbiano",
    "gn:population":57,
    "gn:timezone":"Europe/Rome",
    "iso:country":"IT",
    "wof:name":"Cabbiano",
    "wof:placetype":"locality",
    "wof:population":57
},
  "geometry": {"coordinates":[13.70544,42.87804000000001],"type":"Point"}
}