{
  "type": "Feature",
  "properties": {
    "gn:admin1_code":"3",
    "gn:admin2_code":"CZ",
    "gn:admin3_code":"79095.0",
    "gn:asciiname":"Macchie",
    "gn:country_code":"IT",
    "gn:dem":779,
    "gn:feature_class":"P",
    "gn:feature_code":"PPL",
    "gn:name":"Macchie",
    "gn:population":44,
    "gn:timezone":"Europe/Rome",
    "iso:country":"IT",
    "wof:name":"Macchie",
    "wof:placetype":"locality",
    "wof:population":44
},
  "geometry": {"coordinates":[16.76647,39.04127],"type":"Point"}
}