{
  "type": "Feature",
  "properties": {
    "gn:admin1_code":"12",
    "gn:admin2_code":"TO",
    "gn:admin3_code":"1149.0",
    "gn:asciiname":"Borgata Bassa Meana",
    "gn:country_code":"IT",
    "gn:dem":549,
    "gn:feature_class":"P",
    "gn:feature_code":"PPL",
    "gn:name":"Borgata Bassa Meana",
    "gn:population":24,
    "gn:timezone":"Europe/Rome",
    "iso:country":"IT",
    "wof:name":"Borgata Bassa Meana",
    "wof:placetype":"locality",
    "wof:population":24
},
  "geometry": {"coordinates":[7.06171,45.12718],"type":"Point"}
}