{
  "type": "Feature",
  "properties": {
    "gn:admin1_code":"17",
    "gn:admin2_code":"BZ",
    "gn:admin3_code":"21047.0",
    "gn:asciiname":"Fordora",
    "gn:country_code":"IT",
    "gn:dem":1489,
    "gn:feature_class":"P",
    "gn:feature_code":"PPL",
    "gn:name":"Fordora",
    "gn:population":26,
    "gn:timezone":"Europe/Rome",
    "iso:country":"IT",
    "wof:name":"Fordora",
    "wof:placetype":"locality",
    "wof:population":26
},
  "geometry": {"coordinates":[11.92942,46.72858],"type":"Point"}
}