{
  "type": "Feature",
  "properties": {
    "gn:admin1_code":"3",
    "gn:admin2_code":"CS",
    "gn:admin3_code":"78064.0",
    "gn:asciiname":"San Nicola",
    "gn:country_code":"IT",
    "gn:dem":466,
    "gn:feature_class":"P",
    "gn:feature_code":"PPL",
    "gn:name":"San Nicola",
    "gn:population":28,
    "gn:timezone":"Europe/Rome",
    "iso:country":"IT",
    "name:ceb_x_preferred":[
        "San Nicola"
    ],
    "name:deu_x_preferred":[
        "San Nicola"
    ],
    "name:ita_x_preferred":[
        "San Nicola"
    ],
    "name:scn_x_preferred":[
        "San Nicola"
    ],
    "name:srp_x_preferred":[
        "San Nikola"
    ],
    "name:swe_x_preferred":[
        "San Nicola"
    ],
    "wof:name":"San Nicola",
    "wof:placetype":"locality",
    "wof:population":28
},
  "geometry": {"coordinates":[15.98577,39.92386],"type":"Point"}
}