{
  "type": "Feature",
  "properties": {
    "gn:admin1_code":"16.0",
    "gn:admin2_code":"GR",
    "gn:admin3_code":"53010.0",
    "gn:asciiname":"Collacchia",
    "gn:cc2":"IT",
    "gn:country_code":"IT",
    "gn:dem":86,
    "gn:elevation":"91.0",
    "gn:feature_class":"P",
    "gn:feature_code":"PPL",
    "gn:name":"Collacchia",
    "gn:population":8,
    "gn:timezone":"Europe/Rome",
    "iso:country":"IT",
    "name:und_x_variant":[
        "San Benedetta"
    ],
    "wof:name":"Collacchia",
    "wof:placetype":"locality",
    "wof:population":8
},
  "geometry": {"coordinates":[11.01474,42.97891],"type":"Point"}
}