{
  "type": "Feature",
  "properties": {
    "gn:admin1_code":"8",
    "gn:admin2_code":"GE",
    "gn:admin3_code":"10023.0",
    "gn:asciiname":"Monta-Rocca-Fava",
    "gn:country_code":"IT",
    "gn:dem":405,
    "gn:feature_class":"P",
    "gn:feature_code":"PPL",
    "gn:name":"Mont\u00e0-Rocca-Fava",
    "gn:population":17,
    "gn:timezone":"Europe/Rome",
    "iso:country":"IT",
    "name:und_x_variant":[
        "Mont\u00e0-Rocca-Fava"
    ],
    "wof:name":"Monta-Rocca-Fava",
    "wof:placetype":"locality",
    "wof:population":17
},
  "geometry": {"coordinates":[9.25622,44.45311],"type":"Point"}
}