{
  "type": "Feature",
  "properties": {
    "gn:admin1_code":"1.0",
    "gn:admin2_code":"AQ",
    "gn:admin3_code":"66049.0",
    "gn:asciiname":"Nucleo Industriale di Bazzano",
    "gn:country_code":"IT",
    "gn:dem":594,
    "gn:feature_class":"P",
    "gn:feature_code":"PPL",
    "gn:name":"Nucleo Industriale di Bazzano",
    "gn:population":2619,
    "gn:timezone":"Europe/Rome",
    "iso:country":"IT",
    "wof:name":"Nucleo Industriale di Bazzano",
    "wof:placetype":"locality",
    "wof:population":2619
},
  "geometry": {"coordinates":[13.46755,42.33623],"type":"Point"}
}