{
  "type": "Feature",
  "properties": {
    "gn:admin1_code":"9.0",
    "gn:admin2_code":"BS",
    "gn:admin3_code":"17131.0",
    "gn:asciiname":"Paisco",
    "gn:country":"IT",
    "gn:country_code":"IT",
    "gn:dem":871,
    "gn:fcode":"PPLA3",
    "gn:feature_class":"P",
    "gn:feature_code":"PPL",
    "gn:name":"Paisco",
    "gn:population":257,
    "gn:timezone":"Europe/Rome",
    "iso:country":"IT",
    "qs_pg:aaroncc":"IT",
    "qs_pg:gn_country":"IT",
    "qs_pg:gn_fcode":"PPLA3",
    "qs_pg:gn_pop":257,
    "qs_pg:name":"Paisco",
    "qs_pg:name_adm0":"Italia",
    "qs_pg:name_adm1":"Lombardia",
    "qs_pg:photos_9k":1,
    "qs_pg:photos_9r":1,
    "qs_pg:photos_all":1,
    "qs_pg:photos_sr":0,
    "qs_pg:pop_sr":2,
    "qs_pg:qs_pg_placetype":"locality",
    "qs_pg:qs_pg_placetype_gp":"Town",
    "qs_pg:woe_adm0":23424853,
    "woe:adm0_id":23424853,
    "woe:name_adm0":"Italia",
    "woe:name_adm1":"Lombardia",
    "woe:placetype":"Town",
    "wof:name":"Paisco",
    "wof:placetype":"locality",
    "wof:population":257
},
  "geometry": {"coordinates":[10.29256,46.0791],"type":"Point"}
}