{
  "type": "Feature",
  "properties": {
    "gn:admin1_code":"9",
    "gn:admin2_code":"BS",
    "gn:admin3_code":"17009.0",
    "gn:asciiname":"Colombaie Averoldi",
    "gn:country_code":"IT",
    "gn:dem":78,
    "gn:feature_class":"P",
    "gn:feature_code":"PPL",
    "gn:name":"Colombaie Averoldi",
    "gn:population":21,
    "gn:timezone":"Europe/Rome",
    "iso:country":"IT",
    "wof:name":"Colombaie Averoldi",
    "wof:placetype":"locality",
    "wof:population":21
},
  "geometry": {"coordinates":[10.14209,45.40967],"type":"Point"}
}