{
  "type": "Feature",
  "properties": {
    "gn:admin1_code":"12.0",
    "gn:admin2_code":"CN",
    "gn:admin3_code":"4248.0",
    "gn:asciiname":"Pianche",
    "gn:country_code":"IT",
    "gn:dem":966,
    "gn:elevation":"966.0",
    "gn:feature_class":"P",
    "gn:feature_code":"PPL",
    "gn:name":"Pianche",
    "gn:population":39,
    "gn:timezone":"Europe/Rome",
    "iso:country":"IT",
    "wof:name":"Pianche",
    "wof:placetype":"locality",
    "wof:population":39
},
  "geometry": {"coordinates":[7.11437,44.3024],"type":"Point"}
}