{
  "type": "Feature",
  "properties": {
    "gn:admin1_code":"9.0",
    "gn:admin2_code":"SO",
    "gn:admin3_code":"14032.0",
    "gn:asciiname":"Voga",
    "gn:country_code":"IT",
    "gn:dem":1027,
    "gn:elevation":"1057.0",
    "gn:feature_class":"P",
    "gn:feature_code":"PPL",
    "gn:name":"Voga",
    "gn:population":0,
    "gn:timezone":"Europe/Rome",
    "iso:country":"IT",
    "wof:name":"Voga",
    "wof:placetype":"locality"
},
  "geometry": {"coordinates":[9.34413,46.30443],"type":"Point"}
}