{
  "type": "Feature",
  "properties": {
    "gn:admin1_code":"9",
    "gn:admin2_code":"LC",
    "gn:admin3_code":"97082.0",
    "gn:asciiname":"Taiello",
    "gn:country_code":"IT",
    "gn:dem":310,
    "gn:feature_class":"P",
    "gn:feature_code":"PPL",
    "gn:name":"Taiello",
    "gn:population":86,
    "gn:timezone":"Europe/Rome",
    "iso:country":"IT",
    "wof:name":"Taiello",
    "wof:placetype":"locality",
    "wof:population":86
},
  "geometry": {"coordinates":[9.4202,45.75901],"type":"Point"}
}