{
  "type": "Feature",
  "properties": {
    "iso:country":"IT",
    "name:dut_x_preferred":[
        "Caionvico"
    ],
    "name:eng_x_preferred":[
        "Caionvico"
    ],
    "name:fre_x_preferred":[
        "Caionvico"
    ],
    "name:hun_x_preferred":[
        "Caionvico"
    ],
    "name:ita_x_preferred":[
        "Caionvico"
    ],
    "name:jpn_x_preferred":[
        "\u30ab\u30a4\u30aa\u30f3\u30f4\u30a3\u30b3"
    ],
    "name:lmo_x_preferred":[
        "Caiunv\u00ecch"
    ],
    "qs_pg:aaroncc":"IT",
    "qs_pg:name":"Caionvico",
    "qs_pg:name_adm0":"Italia",
    "qs_pg:name_adm1":"Lombardia",
    "qs_pg:photos":409,
    "qs_pg:photos_1k":83,
    "qs_pg:photos_9k":2,
    "qs_pg:photos_9r":5,
    "qs_pg:photos_all":409,
    "qs_pg:photos_sr":6,
    "qs_pg:pop_sr":0,
    "qs_pg:qs_pg_placetype":"locality",
    "qs_pg:qs_pg_placetype_gp":"Town",
    "qs_pg:woe_adm0":23424853,
    "woe:adm0_id":23424853,
    "woe:name_adm0":"Italia",
    "woe:name_adm1":"Lombardia",
    "woe:placetype":"Town",
    "wof:name":"Caionvico",
    "wof:placetype":"locality"
},
  "geometry": {"coordinates":[10.292472,45.52466],"type":"Point"}
}