{
  "type": "Feature",
  "properties": {
    "gn:admin1_code":"1",
    "gn:admin2_code":"TE",
    "gn:admin3_code":"67029.0",
    "gn:asciiname":"Piano Cesare",
    "gn:country_code":"IT",
    "gn:dem":151,
    "gn:feature_class":"P",
    "gn:feature_code":"PPL",
    "gn:name":"Piano Cesare",
    "gn:population":55,
    "gn:timezone":"Europe/Rome",
    "iso:country":"IT",
    "wof:name":"Piano Cesare",
    "wof:placetype":"locality",
    "wof:population":55
},
  "geometry": {"coordinates":[13.91985,42.65438],"type":"Point"}
}