{
  "type": "Feature",
  "properties": {
    "gn:admin1_code":"9.0",
    "gn:admin2_code":"LO",
    "gn:admin3_code":"98045.0",
    "gn:asciiname":"Viscolube",
    "gn:country_code":"IT",
    "gn:dem":77,
    "gn:feature_class":"P",
    "gn:feature_code":"PPLL",
    "gn:name":"Viscolube",
    "gn:population":0,
    "gn:timezone":"Europe/Rome",
    "iso:country":"IT",
    "wof:name":"Viscolube",
    "wof:placetype":"locality"
},
  "geometry": {"coordinates":[9.45221,45.27207],"type":"Point"}
}