{
  "type": "Feature",
  "properties": {
    "iso:country":"IT",
    "name:fin_x_preferred":[
        "San Marinon taistelu"
    ],
    "name:fra_x_preferred":[
        "Bataille de San Marino"
    ],
    "name:ita_x_preferred":[
        "Battaglia di Monte Pulito"
    ],
    "name:lit_x_preferred":[
        "San Marino m\u016b\u0161is"
    ],
    "name:rus_x_preferred":[
        "\u0421\u0440\u0430\u0436\u0435\u043d\u0438\u0435 \u043f\u0440\u0438 \u041c\u043e\u043d\u0442\u0435-\u041f\u0443\u043b\u0438\u0442\u043e"
    ],
    "name:swe_x_preferred":[
        "Slaget om San Marino"
    ],
    "name:vie_x_preferred":[
        "Tr\u1eadn San Marino"
    ],
    "qs:a0":"Italia",
    "qs:a1":"*Frosinone",
    "qs:a1r":"0Lazio",
    "qs:adm0":"Italia",
    "qs:la_lc":"*",
    "qs:level":"locality",
    "qs:loc":"Monte San Marino",
    "qs:loc_alt":"Monte San Marino",
    "qs:pop":0,
    "qs:type":"buffered point",
    "wd:wordcount":1889,
    "wof:name":"Monte San Marino",
    "wof:placetype":"locality"
},
  "geometry": {"coordinates":[13.31136,41.709622],"type":"Point"}
}