{
  "type": "Feature",
  "properties": {
    "gn:admin1_code":"19",
    "gn:admin2_code":"AO",
    "gn:admin3_code":"7023.0",
    "gn:asciiname":"Outrefer",
    "gn:country_code":"IT",
    "gn:dem":338,
    "gn:feature_class":"P",
    "gn:feature_code":"PPL",
    "gn:name":"Outrefer",
    "gn:population":73,
    "gn:timezone":"Europe/Rome",
    "iso:country":"IT",
    "wof:name":"Outrefer",
    "wof:placetype":"locality",
    "wof:population":73
},
  "geometry": {"coordinates":[7.75623,45.60001],"type":"Point"}
}