{
  "type": "Feature",
  "properties": {
    "gn:admin1_code":"9",
    "gn:admin2_code":"MI",
    "gn:admin3_code":"15191.0",
    "gn:asciiname":"Costa Cornaggia",
    "gn:country_code":"IT",
    "gn:dem":73,
    "gn:feature_class":"P",
    "gn:feature_code":"PPL",
    "gn:name":"Costa Cornaggia",
    "gn:population":52,
    "gn:timezone":"Europe/Rome",
    "iso:country":"IT",
    "wof:name":"Costa Cornaggia",
    "wof:placetype":"locality",
    "wof:population":52
},
  "geometry": {"coordinates":[9.49245,45.16336],"type":"Point"}
}