{
  "type": "Feature",
  "properties": {
    "gn:admin1_code":"3.0",
    "gn:admin2_code":"RC",
    "gn:admin3_code":"80073.0",
    "gn:asciiname":"San Lorenzo",
    "gn:country_code":"IT",
    "gn:dem":789,
    "gn:elevation":"787.0",
    "gn:feature_class":"P",
    "gn:feature_code":"PPLA3",
    "gn:name":"San Lorenzo",
    "gn:population":281,
    "gn:timezone":"Europe/Rome",
    "iso:country":"IT",
    "name:und_x_variant":[
        "San Lorenzo di Reggio Calabria"
    ],
    "wof:name":"San Lorenzo",
    "wof:placetype":"locality",
    "wof:population":281
},
  "geometry": {"coordinates":[15.8344,38.01097],"type":"Point"}
}