{
  "type": "Feature",
  "properties": {
    "gn:admin1_code":"7",
    "gn:admin2_code":"RM",
    "gn:admin3_code":"58093.0",
    "gn:asciiname":"Borgo Pineto I",
    "gn:country_code":"IT",
    "gn:dem":132,
    "gn:feature_class":"P",
    "gn:feature_code":"PPL",
    "gn:name":"Borgo Pineto I",
    "gn:population":119,
    "gn:timezone":"Europe/Rome",
    "iso:country":"IT",
    "wof:name":"Borgo Pineto I",
    "wof:placetype":"locality",
    "wof:population":119
},
  "geometry": {"coordinates":[12.45103,42.06606],"type":"Point"}
}