{
  "type": "Feature",
  "properties": {
    "gn:admin1_code":"5",
    "gn:admin2_code":"RN",
    "gn:admin3_code":"99003.0",
    "gn:asciiname":"Le Casacce",
    "gn:country_code":"IT",
    "gn:dem":152,
    "gn:feature_class":"P",
    "gn:feature_code":"PPL",
    "gn:name":"Le Casacce",
    "gn:population":35,
    "gn:timezone":"Europe/Rome",
    "iso:country":"IT",
    "wof:name":"Le Casacce",
    "wof:placetype":"locality",
    "wof:population":35
},
  "geometry": {"coordinates":[12.51814,43.97419],"type":"Point"}
}