{
  "type": "Feature",
  "properties": {
    "gn:admin1_code":"5",
    "gn:admin2_code":"MO",
    "gn:admin3_code":"36007.0",
    "gn:asciiname":"Cavidole",
    "gn:country_code":"IT",
    "gn:dem":55,
    "gn:feature_class":"P",
    "gn:feature_code":"PPL",
    "gn:name":"Cavidole",
    "gn:population":164,
    "gn:timezone":"Europe/Rome",
    "iso:country":"IT",
    "wof:name":"Cavidole",
    "wof:placetype":"locality",
    "wof:population":164
},
  "geometry": {"coordinates":[10.95886,44.5629],"type":"Point"}
}