{
  "type": "Feature",
  "properties": {
    "gn:admin1_code":"4.0",
    "gn:admin3_code":"63007.0",
    "gn:asciiname":"Lido di Maronti",
    "gn:country_code":"IT",
    "gn:dem":157,
    "gn:feature_class":"P",
    "gn:feature_code":"PPL",
    "gn:name":"Lido di Maronti",
    "gn:population":0,
    "gn:timezone":"Europe/Rome",
    "iso:country":"IT",
    "wof:name":"Lido di Maronti",
    "wof:placetype":"locality"
},
  "geometry": {"coordinates":[13.91914,40.70468],"type":"Point"}
}