{
  "type": "Feature",
  "properties": {
    "gn:admin1_code":"15.0",
    "gn:admin2_code":"TP",
    "gn:admin3_code":"81011.0",
    "gn:asciiname":"Baglio Manzo",
    "gn:cc2":"IT",
    "gn:country_code":"IT",
    "gn:dem":72,
    "gn:feature_class":"P",
    "gn:feature_code":"PPL",
    "gn:name":"Baglio Manzo",
    "gn:population":0,
    "gn:timezone":"Europe/Rome",
    "iso:country":"IT",
    "name:und_x_variant":[
        "Manzo",
        "Baglio Manzo"
    ],
    "wof:name":"Baglio Manzo",
    "wof:placetype":"locality"
},
  "geometry": {"coordinates":[12.51667,37.85],"type":"Point"}
}