{
  "type": "Feature",
  "properties": {
    "gn:admin1_code":"5.0",
    "gn:admin2_code":"RA",
    "gn:admin3_code":"39005.0",
    "gn:asciiname":"Frassineta",
    "gn:country_code":"IT",
    "gn:dem":649,
    "gn:feature_class":"P",
    "gn:feature_code":"PPLL",
    "gn:name":"Frassineta",
    "gn:population":2,
    "gn:timezone":"Europe/Rome",
    "iso:country":"IT",
    "wof:name":"Frassineta",
    "wof:placetype":"locality",
    "wof:population":2
},
  "geometry": {"coordinates":[11.53997,44.17235],"type":"Point"}
}