{
  "type": "Feature",
  "properties": {
    "gn:admin1_code":"9",
    "gn:admin2_code":"LC",
    "gn:admin3_code":"97049.0",
    "gn:asciiname":"Tegnoso",
    "gn:country_code":"IT",
    "gn:dem":322,
    "gn:feature_class":"P",
    "gn:feature_code":"PPL",
    "gn:name":"Tegnoso",
    "gn:population":28,
    "gn:timezone":"Europe/Rome",
    "iso:country":"IT",
    "wof:name":"Tegnoso",
    "wof:placetype":"locality",
    "wof:population":28
},
  "geometry": {"coordinates":[9.33176,45.69433],"type":"Point"}
}