{
  "type": "Feature",
  "properties": {
    "gn:admin1_code":"7.0",
    "gn:admin2_code":"FR",
    "gn:admin3_code":"60027.0",
    "gn:asciiname":"Coldragone",
    "gn:country_code":"IT",
    "gn:dem":149,
    "gn:elevation":"158.0",
    "gn:feature_class":"P",
    "gn:feature_code":"PPLA3",
    "gn:name":"Coldragone",
    "gn:population":544,
    "gn:timezone":"Europe/Rome",
    "iso:country":"IT",
    "wof:name":"Coldragone",
    "wof:placetype":"locality",
    "wof:population":544
},
  "geometry": {"coordinates":[13.60399,41.55458],"type":"Point"}
}