{
  "type": "Feature",
  "properties": {
    "gn:admin1_code":"20",
    "gn:admin2_code":"VR",
    "gn:admin3_code":"23006.0",
    "gn:asciiname":"Cristo-Spadi",
    "gn:country_code":"IT",
    "gn:dem":157,
    "gn:feature_class":"P",
    "gn:feature_code":"PPL",
    "gn:name":"Cristo-Spadi",
    "gn:population":78,
    "gn:timezone":"Europe/Rome",
    "iso:country":"IT",
    "wof:name":"Cristo-Spadi",
    "wof:placetype":"locality",
    "wof:population":78
},
  "geometry": {"coordinates":[10.76353,45.51568],"type":"Point"}
}