{
  "type": "Feature",
  "properties": {
    "gn:admin1_code":"12",
    "gn:admin2_code":"CN",
    "gn:admin3_code":"4208.0",
    "gn:asciiname":"Madonna di Loreto",
    "gn:country_code":"IT",
    "gn:dem":329,
    "gn:feature_class":"P",
    "gn:feature_code":"PPL",
    "gn:name":"Madonna di Loreto",
    "gn:population":51,
    "gn:timezone":"Europe/Rome",
    "iso:country":"IT",
    "wof:name":"Madonna di Loreto",
    "wof:placetype":"locality",
    "wof:population":51
},
  "geometry": {"coordinates":[7.81747,44.74962],"type":"Point"}
}