{
  "type": "Feature",
  "properties": {
    "gn:gn_country":"IT",
    "gn:gn_fcode":"PPLA3",
    "gn:gn_pop":3762,
    "gn:population":3762,
    "iso:country":"IT",
    "name:azb_x_preferred":[
        "\u0686\u0631\u0627\u0646\u0632\u06cc"
    ],
    "name:bel_x_preferred":[
        "\u0427\u044d\u0440\u0430\u043d\u0435\u0437\u0456"
    ],
    "name:bul_x_preferred":[
        "\u0427\u0435\u0440\u0430\u043d\u0435\u0437\u0438"
    ],
    "name:cat_x_preferred":[
        "Ceranesi"
    ],
    "name:ceb_x_preferred":[
        "Ceranesi"
    ],
    "name:deu_x_preferred":[
        "Ceranesi"
    ],
    "name:eng_x_preferred":[
        "Ceranesi"
    ],
    "name:epo_x_preferred":[
        "Ceranesi"
    ],
    "name:eus_x_preferred":[
        "Ceranesi"
    ],
    "name:fas_x_preferred":[
        "\u0686\u0631\u0627\u0646\u0632\u06cc"
    ],
    "name:fra_x_preferred":[
        "Ceranesi"
    ],
    "name:hun_x_preferred":[
        "Ceranesi"
    ],
    "name:hye_x_preferred":[
        "\u0549\u0565\u0580\u0561\u0576\u0565\u0566\u056b"
    ],
    "name:ina_x_preferred":[
        "Ceranesi"
    ],
    "name:ita_x_preferred":[
        "Ceranesi"
    ],
    "name:jpn_x_preferred":[
        "\u30c1\u30a7\u30e9\u30fc\u30cd\u30b8"
    ],
    "name:kaz_x_preferred":[
        "\u0427\u0435\u0440\u0430\u043d\u0435\u0437\u0438"
    ],
    "name:lat_x_preferred":[
        "Ceranesis"
    ],
    "name:lij_x_preferred":[
        "\u00c7eranexi"
    ],
    "name:lmo_x_preferred":[
        "Ceranesi"
    ],
    "name:ltz_x_preferred":[
        "Ceranesi"
    ],
    "name:msa_x_preferred":[
        "Ceranesi"
    ],
    "name:nan_x_preferred":[
        "Ceranesi"
    ],
    "name:nap_x_preferred":[
        "Ceranesi"
    ],
    "name:nld_x_preferred":[
        "Ceranesi"
    ],
    "name:pms_x_preferred":[
        "Ceranesi"
    ],
    "name:pol_x_preferred":[
        "Ceranesi"
    ],
    "name:por_x_preferred":[
        "Ceranesi"
    ],
    "name:ron_x_preferred":[
        "Ceranesi"
    ],
    "name:rus_x_preferred":[
        "\u0427\u0435\u0440\u0430\u043d\u0435\u0437\u0438"
    ],
    "name:scn_x_preferred":[
        "Ceranesi"
    ],
    "name:spa_x_preferred":[
        "Ceranesi"
    ],
    "name:srp_x_preferred":[
        "Ceranesi"
    ],
    "name:szl_x_preferred":[
        "Ceranesi"
    ],
    "name:ukr_x_preferred":[
        "\u0427\u0435\u0440\u0430\u043d\u0435\u0437\u0456"
    ],
    "name:uzb_x_preferred":[
        "Ceranesi"
    ],
    "name:vie_x_preferred":[
        "Ceranesi"
    ],
    "name:vol_x_preferred":[
        "Ceranesi"
    ],
    "name:war_x_preferred":[
        "Ceranesi"
    ],
    "name:zho_x_preferred":[
        "\u5207\u62c9\u5185\u897f"
    ],
    "qs_pg:aaroncc":"IT",
    "qs_pg:gn_country":"IT",
    "qs_pg:gn_fcode":"PPLA3",
    "qs_pg:gn_pop":3762,
    "qs_pg:name":"Ceranesi",
    "qs_pg:name_adm0":"Italia",
    "qs_pg:name_adm1":"Liguria",
    "qs_pg:photos_9r":0,
    "qs_pg:photos_sr":0,
    "qs_pg:pop_sr":4,
    "qs_pg:qs_pg_placetype":"locality",
    "qs_pg:qs_pg_placetype_gp":"Town",
    "qs_pg:woe_adm0":23424853,
    "woe:adm0_id":23424853,
    "woe:name_adm0":"Italia",
    "woe:name_adm1":"Liguria",
    "woe:placetype":"Town",
    "wof:name":"Ceranesi",
    "wof:placetype":"locality",
    "wof:population":3762
},
  "geometry": {"coordinates":[8.89343,44.50563],"type":"Point"}
}