{
  "type": "Feature",
  "properties": {
    "gn:admin1_code":"2",
    "gn:admin2_code":"PZ",
    "gn:admin3_code":"76001.0",
    "gn:asciiname":"Tintiera",
    "gn:country_code":"IT",
    "gn:dem":830,
    "gn:feature_class":"P",
    "gn:feature_code":"PPL",
    "gn:name":"Tintiera",
    "gn:population":78,
    "gn:timezone":"Europe/Rome",
    "iso:country":"IT",
    "wof:name":"Tintiera",
    "wof:placetype":"locality",
    "wof:population":78
},
  "geometry": {"coordinates":[15.77327,40.55681],"type":"Point"}
}