{
  "type": "Feature",
  "properties": {
    "gn:admin1_code":"7",
    "gn:admin2_code":"RM",
    "gn:admin3_code":"58117.0",
    "gn:asciiname":"Fosso di Torre Bruno",
    "gn:country_code":"IT",
    "gn:dem":107,
    "gn:feature_class":"P",
    "gn:feature_code":"PPL",
    "gn:name":"Fosso di Torre Bruno",
    "gn:population":102,
    "gn:timezone":"Europe/Rome",
    "iso:country":"IT",
    "wof:name":"Fosso di Torre Bruno",
    "wof:placetype":"locality",
    "wof:population":102
},
  "geometry": {"coordinates":[12.59689,41.66726],"type":"Point"}
}