{
  "type": "Feature",
  "properties": {
    "gn:admin1_code":"4",
    "gn:admin2_code":"AV",
    "gn:admin3_code":"64038.0",
    "gn:asciiname":"Conduttiello",
    "gn:country_code":"IT",
    "gn:dem":459,
    "gn:feature_class":"P",
    "gn:feature_code":"PPL",
    "gn:name":"Conduttiello",
    "gn:population":70,
    "gn:timezone":"Europe/Rome",
    "iso:country":"IT",
    "wof:name":"Conduttiello",
    "wof:placetype":"locality",
    "wof:population":70
},
  "geometry": {"coordinates":[15.03581,41.05608],"type":"Point"}
}