{
  "type": "Feature",
  "properties": {
    "gn:admin1_code":"4",
    "gn:admin2_code":"BN",
    "gn:admin3_code":"62044.0",
    "gn:asciiname":"Guadoschiavo",
    "gn:country_code":"IT",
    "gn:dem":839,
    "gn:feature_class":"P",
    "gn:feature_code":"PPL",
    "gn:name":"Guadoschiavo",
    "gn:population":43,
    "gn:timezone":"Europe/Rome",
    "iso:country":"IT",
    "wof:name":"Guadoschiavo",
    "wof:placetype":"locality",
    "wof:population":43
},
  "geometry": {"coordinates":[14.63318,41.35100000000001],"type":"Point"}
}