{
  "type": "Feature",
  "properties": {
    "gn:admin1_code":"14.0",
    "gn:admin2_code":"CA",
    "gn:admin3_code":"92074.0",
    "gn:asciiname":"Cortexandra",
    "gn:country_code":"IT",
    "gn:dem":50,
    "gn:feature_class":"P",
    "gn:feature_code":"PPL",
    "gn:name":"Cortexandra",
    "gn:population":679,
    "gn:timezone":"Europe/Rome",
    "iso:country":"IT",
    "wof:name":"Cortexandra",
    "wof:placetype":"locality",
    "wof:population":679
},
  "geometry": {"coordinates":[9.07054,39.29091],"type":"Point"}
}