{
  "type": "Feature",
  "properties": {
    "gn:admin1_code":"9.0",
    "gn:admin2_code":"MN",
    "gn:admin3_code":"20049.0",
    "gn:asciiname":"Stazione di Revere",
    "gn:country_code":"IT",
    "gn:dem":11,
    "gn:feature_class":"P",
    "gn:feature_code":"PPL",
    "gn:name":"Stazione di Revere",
    "gn:population":16,
    "gn:timezone":"Europe/Rome",
    "iso:country":"IT",
    "wof:name":"Stazione di Revere",
    "wof:placetype":"locality",
    "wof:population":16
},
  "geometry": {"coordinates":[11.12863,45.04147],"type":"Point"}
}