{
  "type": "Feature",
  "properties": {
    "gn:admin1_code":"20.0",
    "gn:admin2_code":"VE",
    "gn:admin3_code":"27031.0",
    "gn:asciiname":"Ca' Corner",
    "gn:country_code":"IT",
    "gn:dem":2,
    "gn:feature_class":"P",
    "gn:feature_code":"PPL",
    "gn:name":"Ca' Corner",
    "gn:population":548,
    "gn:timezone":"Europe/Rome",
    "iso:country":"IT",
    "wof:name":"Ca' Corner",
    "wof:placetype":"locality",
    "wof:population":548
},
  "geometry": {"coordinates":[12.43434,45.55899],"type":"Point"}
}