{
  "type": "Feature",
  "properties": {
    "gn:admin1_code":"17",
    "gn:admin2_code":"BZ",
    "gn:admin3_code":"21104.0",
    "gn:asciiname":"Durago di Dentro",
    "gn:country_code":"IT",
    "gn:dem":1409,
    "gn:feature_class":"P",
    "gn:feature_code":"PPL",
    "gn:name":"Durago di Dentro",
    "gn:population":31,
    "gn:timezone":"Europe/Rome",
    "iso:country":"IT",
    "wof:name":"Durago di Dentro",
    "wof:placetype":"locality",
    "wof:population":31
},
  "geometry": {"coordinates":[11.0041,46.5568],"type":"Point"}
}