{
  "type": "Feature",
  "properties": {
    "gn:admin1_code":"10",
    "gn:admin2_code":"AP",
    "gn:admin3_code":"44073.0",
    "gn:asciiname":"Arola",
    "gn:country_code":"IT",
    "gn:dem":403,
    "gn:feature_class":"P",
    "gn:feature_code":"PPL",
    "gn:name":"Arola",
    "gn:population":72,
    "gn:timezone":"Europe/Rome",
    "iso:country":"IT",
    "wof:name":"Arola",
    "wof:placetype":"locality",
    "wof:population":72
},
  "geometry": {"coordinates":[13.48192,42.86977],"type":"Point"}
}