{
  "type": "Feature",
  "properties": {
    "iso:country":"IT",
    "wof:name":"Val Cannuta",
    "wof:placetype":"neighbourhood"
},
  "geometry": {"coordinates":[12.4101587458821,41.89823672897464],"type":"Point"}
}