{
  "type": "Feature",
  "properties": {
    "gn:admin1_code":"5",
    "gn:admin2_code":"FC",
    "gn:admin3_code":"40012.0",
    "gn:asciiname":"Argine",
    "gn:country_code":"IT",
    "gn:dem":17,
    "gn:feature_class":"P",
    "gn:feature_code":"PPL",
    "gn:name":"Argine",
    "gn:population":25,
    "gn:timezone":"Europe/Rome",
    "iso:country":"IT",
    "wof:name":"Argine",
    "wof:placetype":"locality",
    "wof:population":25
},
  "geometry": {"coordinates":[12.00354,44.29685],"type":"Point"}
}