{
  "type": "Feature",
  "properties": {
    "gn:admin1_code":"7",
    "gn:admin2_code":"FR",
    "gn:admin3_code":"60018.0",
    "gn:asciiname":"Catallo",
    "gn:country_code":"IT",
    "gn:dem":419,
    "gn:feature_class":"P",
    "gn:feature_code":"PPL",
    "gn:name":"Catallo",
    "gn:population":32,
    "gn:timezone":"Europe/Rome",
    "iso:country":"IT",
    "wof:name":"Catallo",
    "wof:placetype":"locality",
    "wof:population":32
},
  "geometry": {"coordinates":[13.70591,41.6434],"type":"Point"}
}