{
  "type": "Feature",
  "properties": {
    "gn:admin1_code":"20",
    "gn:admin2_code":"PD",
    "gn:admin3_code":"28044.0",
    "gn:asciiname":"Pra",
    "gn:country_code":"IT",
    "gn:dem":5,
    "gn:feature_class":"P",
    "gn:feature_code":"PPL",
    "gn:name":"Pr\u00e0",
    "gn:population":83,
    "gn:timezone":"Europe/Rome",
    "iso:country":"IT",
    "name:und_x_variant":[
        "Pr\u00e0"
    ],
    "wof:name":"Pra",
    "wof:placetype":"locality",
    "wof:population":83
},
  "geometry": {"coordinates":[11.98225,45.354],"type":"Point"}
}