{
  "type": "Feature",
  "properties": {
    "gn:admin1_code":"1",
    "gn:admin2_code":"TE",
    "gn:admin3_code":"67029.0",
    "gn:asciiname":"Case Sacchetti",
    "gn:country_code":"IT",
    "gn:dem":169,
    "gn:feature_class":"P",
    "gn:feature_code":"PPL",
    "gn:name":"Case Sacchetti",
    "gn:population":38,
    "gn:timezone":"Europe/Rome",
    "iso:country":"IT",
    "wof:name":"Case Sacchetti",
    "wof:placetype":"locality",
    "wof:population":38
},
  "geometry": {"coordinates":[13.93659,42.66109],"type":"Point"}
}