{
  "type": "Feature",
  "properties": {
    "gn:admin1_code":"9.0",
    "gn:admin2_code":"PV",
    "gn:admin3_code":"18159.0",
    "gn:asciiname":"Casottole",
    "gn:country_code":"IT",
    "gn:dem":84,
    "gn:feature_class":"P",
    "gn:feature_code":"PPL",
    "gn:name":"Casottole",
    "gn:population":564,
    "gn:timezone":"Europe/Rome",
    "iso:country":"IT",
    "wof:name":"Casottole",
    "wof:placetype":"locality",
    "wof:population":564
},
  "geometry": {"coordinates":[9.06785,45.22805],"type":"Point"}
}