{
  "type": "Feature",
  "properties": {
    "gn:admin1_code":"12",
    "gn:admin2_code":"TO",
    "gn:admin3_code":"1180.0",
    "gn:asciiname":"Tetti Apra - San Defendente",
    "gn:country_code":"IT",
    "gn:dem":405,
    "gn:feature_class":"P",
    "gn:feature_code":"PPL",
    "gn:name":"Tetti Apr\u00e0 - San Defendente",
    "gn:population":109,
    "gn:timezone":"Europe/Rome",
    "iso:country":"IT",
    "name:und_x_variant":[
        "Tetti Apr\u00e0 - San Defendente"
    ],
    "wof:name":"Tetti Apra - San Defendente",
    "wof:placetype":"locality",
    "wof:population":109
},
  "geometry": {"coordinates":[7.83027,45.08346],"type":"Point"}
}