{
  "type": "Feature",
  "properties": {
    "gn:admin1_code":"6.0",
    "gn:admin2_code":"GO",
    "gn:admin3_code":"31017.0",
    "gn:asciiname":"San Martino del Carso",
    "gn:country_code":"IT",
    "gn:dem":163,
    "gn:elevation":"163.0",
    "gn:feature_class":"P",
    "gn:feature_code":"PPL",
    "gn:name":"San Martino del Carso",
    "gn:population":258,
    "gn:timezone":"Europe/Rome",
    "iso:country":"IT",
    "wof:name":"San Martino del Carso",
    "wof:placetype":"locality",
    "wof:population":258
},
  "geometry": {"coordinates":[13.53528,45.87583],"type":"Point"}
}