{
  "type": "Feature",
  "properties": {
    "gn:admin1_code":"11.0",
    "gn:admin2_code":"IS",
    "gn:admin3_code":"94014.0",
    "gn:asciiname":"Valloni-Rossi",
    "gn:country_code":"IT",
    "gn:dem":586,
    "gn:feature_class":"P",
    "gn:feature_code":"PPL",
    "gn:name":"Valloni-Rossi",
    "gn:population":178,
    "gn:timezone":"Europe/Rome",
    "iso:country":"IT",
    "wof:name":"Valloni-Rossi",
    "wof:placetype":"locality",
    "wof:population":178
},
  "geometry": {"coordinates":[14.11245,41.63982],"type":"Point"}
}