{
  "type": "Feature",
  "properties": {
    "gn:admin1_code":"12",
    "gn:admin2_code":"AL",
    "gn:admin3_code":"6165.0",
    "gn:asciiname":"Costabella",
    "gn:country_code":"IT",
    "gn:dem":435,
    "gn:feature_class":"P",
    "gn:feature_code":"PPL",
    "gn:name":"Costabella",
    "gn:population":18,
    "gn:timezone":"Europe/Rome",
    "iso:country":"IT",
    "wof:name":"Costabella",
    "wof:placetype":"locality",
    "wof:population":18
},
  "geometry": {"coordinates":[8.38147,44.54237],"type":"Point"}
}