{
  "type": "Feature",
  "properties": {
    "gn:admin1_code":"19",
    "gn:admin2_code":"AO",
    "gn:admin3_code":"7013.0",
    "gn:asciiname":"Tollegnaz",
    "gn:country_code":"IT",
    "gn:dem":1024,
    "gn:feature_class":"P",
    "gn:feature_code":"PPL",
    "gn:name":"Tollegnaz",
    "gn:population":37,
    "gn:timezone":"Europe/Rome",
    "iso:country":"IT",
    "wof:name":"Tollegnaz",
    "wof:placetype":"locality",
    "wof:population":37
},
  "geometry": {"coordinates":[7.74943,45.72042],"type":"Point"}
}