{
  "type": "Feature",
  "properties": {
    "gn:admin1_code":"12.0",
    "gn:admin2_code":"TO",
    "gn:admin3_code":"1234.0",
    "gn:asciiname":"Coppi",
    "gn:country_code":"IT",
    "gn:dem":1265,
    "gn:feature_class":"P",
    "gn:feature_code":"PPLL",
    "gn:name":"Coppi",
    "gn:population":4,
    "gn:timezone":"Europe/Rome",
    "iso:country":"IT",
    "wof:name":"Coppi",
    "wof:placetype":"locality",
    "wof:population":4
},
  "geometry": {"coordinates":[7.04856,44.93977],"type":"Point"}
}