{
  "type": "Feature",
  "properties": {
    "gn:admin1_code":"9",
    "gn:admin2_code":"MN",
    "gn:admin3_code":"20002.0",
    "gn:asciiname":"Camporegio",
    "gn:country_code":"IT",
    "gn:dem":33,
    "gn:feature_class":"P",
    "gn:feature_code":"PPL",
    "gn:name":"Camporegio",
    "gn:population":26,
    "gn:timezone":"Europe/Rome",
    "iso:country":"IT",
    "wof:name":"Camporegio",
    "wof:placetype":"locality",
    "wof:population":26
},
  "geometry": {"coordinates":[10.41575,45.20524],"type":"Point"}
}