{
  "type": "Feature",
  "properties": {
    "gn:admin1_code":"4.0",
    "gn:admin3_code":"63053.0",
    "gn:asciiname":"Colli di Fontanelle",
    "gn:country_code":"IT",
    "gn:dem":327,
    "gn:feature_class":"P",
    "gn:feature_code":"PPL",
    "gn:name":"Colli di Fontanelle",
    "gn:population":0,
    "gn:timezone":"Europe/Rome",
    "iso:country":"IT",
    "wof:name":"Colli di Fontanelle",
    "wof:placetype":"locality"
},
  "geometry": {"coordinates":[14.41423,40.6148],"type":"Point"}
}