{
  "type": "Feature",
  "properties": {
    "gn:admin1_code":"5.0",
    "gn:admin2_code":"MO",
    "gn:admin3_code":"36019.0",
    "gn:asciiname":"Il Poggio",
    "gn:country_code":"IT",
    "gn:dem":376,
    "gn:feature_class":"P",
    "gn:feature_code":"PPL",
    "gn:name":"Il Poggio",
    "gn:population":102,
    "gn:timezone":"Europe/Rome",
    "iso:country":"IT",
    "wof:name":"Il Poggio",
    "wof:placetype":"locality",
    "wof:population":102
},
  "geometry": {"coordinates":[10.84881,44.48974000000001],"type":"Point"}
}