{
  "type": "Feature",
  "properties": {
    "gn:admin1_code":"1",
    "gn:admin2_code":"CH",
    "gn:admin3_code":"69099.0",
    "gn:asciiname":"Collepizzuto",
    "gn:country_code":"IT",
    "gn:dem":97,
    "gn:feature_class":"P",
    "gn:feature_code":"PPL",
    "gn:name":"Collepizzuto",
    "gn:population":204,
    "gn:timezone":"Europe/Rome",
    "iso:country":"IT",
    "wof:name":"Collepizzuto",
    "wof:placetype":"locality",
    "wof:population":204
},
  "geometry": {"coordinates":[14.72696,42.06461],"type":"Point"}
}