{
  "type": "Feature",
  "properties": {
    "gn:admin1_code":"3",
    "gn:admin2_code":"CS",
    "gn:admin3_code":"78103.0",
    "gn:asciiname":"Tavolaro",
    "gn:country_code":"IT",
    "gn:dem":25,
    "gn:feature_class":"P",
    "gn:feature_code":"PPL",
    "gn:name":"Tavolaro",
    "gn:population":125,
    "gn:timezone":"Europe/Rome",
    "iso:country":"IT",
    "wof:name":"Tavolaro",
    "wof:placetype":"locality",
    "wof:population":125
},
  "geometry": {"coordinates":[16.60461,40.10365],"type":"Point"}
}