{
  "type": "Feature",
  "properties": {
    "gn:admin1_code":"14",
    "gn:admin2_code":"CA",
    "gn:admin3_code":"92108.0",
    "gn:asciiname":"Is. Arenas",
    "gn:country_code":"IT",
    "gn:dem":9,
    "gn:feature_class":"P",
    "gn:feature_code":"PPL",
    "gn:name":"Is. Arenas",
    "gn:population":42,
    "gn:timezone":"Europe/Rome",
    "iso:country":"IT",
    "wof:name":"Is. Arenas",
    "wof:placetype":"locality",
    "wof:population":42
},
  "geometry": {"coordinates":[9.05151,39.27422],"type":"Point"}
}