{
  "type": "Feature",
  "properties": {
    "gn:admin1_code":"3",
    "gn:admin2_code":"CS",
    "gn:admin3_code":"78070.0",
    "gn:asciiname":"Verduro",
    "gn:country_code":"IT",
    "gn:dem":210,
    "gn:feature_class":"P",
    "gn:feature_code":"PPL",
    "gn:name":"Verduro",
    "gn:population":136,
    "gn:timezone":"Europe/Rome",
    "iso:country":"IT",
    "wof:name":"Verduro",
    "wof:placetype":"locality",
    "wof:population":136
},
  "geometry": {"coordinates":[16.27069,39.43285],"type":"Point"}
}