{
  "type": "Feature",
  "properties": {
    "gn:admin1_code":"17",
    "gn:admin2_code":"TN",
    "gn:admin3_code":"22209.0",
    "gn:asciiname":"Dora",
    "gn:country_code":"IT",
    "gn:dem":1107,
    "gn:feature_class":"P",
    "gn:feature_code":"PPL",
    "gn:name":"Dor\u00e0",
    "gn:population":75,
    "gn:timezone":"Europe/Rome",
    "iso:country":"IT",
    "name:bre_x_preferred":[
        "Dora"
    ],
    "name:ceb_x_preferred":[
        "Dora"
    ],
    "name:ces_x_preferred":[
        "Dora"
    ],
    "name:deu_x_preferred":[
        "Dora"
    ],
    "name:est_x_preferred":[
        "Dora"
    ],
    "name:fin_x_preferred":[
        "Dora"
    ],
    "name:fra_x_preferred":[
        "Dora"
    ],
    "name:heb_x_preferred":[
        "\u05d3\u05d5\u05e8\u05d4"
    ],
    "name:hun_x_preferred":[
        "Dora"
    ],
    "name:ind_x_preferred":[
        "Dora"
    ],
    "name:ita_x_preferred":[
        "Dora"
    ],
    "name:nld_x_preferred":[
        "Dora"
    ],
    "name:pol_x_preferred":[
        "Dora"
    ],
    "name:por_x_preferred":[
        "Dora"
    ],
    "name:ron_x_preferred":[
        "Dora"
    ],
    "name:rus_x_preferred":[
        "\u0414\u043e\u0440\u0430"
    ],
    "name:slk_x_preferred":[
        "Dora"
    ],
    "name:spa_x_preferred":[
        "Dora"
    ],
    "name:swe_x_preferred":[
        "Dora"
    ],
    "name:ukr_x_preferred":[
        "\u0414\u043e\u0440\u0430"
    ],
    "name:und_x_variant":[
        "Dor\u00e0"
    ],
    "name:vol_x_preferred":[
        "Dora"
    ],
    "wof:name":"Dora",
    "wof:placetype":"locality",
    "wof:population":75
},
  "geometry": {"coordinates":[11.35647,46.25176],"type":"Point"}
}