{
  "type": "Feature",
  "properties": {
    "gn:admin1_code":"17",
    "gn:admin2_code":"TN",
    "gn:admin3_code":"22209.0",
    "gn:asciiname":"Dora",
    "gn:country_code":"IT",
    "gn:dem":1107,
    "gn:feature_class":"P",
    "gn:feature_code":"PPL",
    "gn:name":"Dor\u00e0",
    "gn:population":75,
    "gn:timezone":"Europe/Rome",
    "iso:country":"IT",
    "name:und_x_variant":[
        "Dor\u00e0"
    ],
    "wof:name":"Dora",
    "wof:placetype":"locality",
    "wof:population":75
},
  "geometry": {"coordinates":[11.35647,46.25176],"type":"Point"}
}