{
  "type": "Feature",
  "properties": {
    "gn:admin1_code":"12.0",
    "gn:admin2_code":"AT",
    "gn:admin3_code":"5031.0",
    "gn:asciiname":"Bardella",
    "gn:country_code":"IT",
    "gn:dem":289,
    "gn:feature_class":"P",
    "gn:feature_code":"PPL",
    "gn:name":"Bardella",
    "gn:population":90,
    "gn:timezone":"Europe/Rome",
    "iso:country":"IT",
    "wof:name":"Bardella",
    "wof:placetype":"locality",
    "wof:population":90
},
  "geometry": {"coordinates":[7.94913,45.06185],"type":"Point"}
}