{
  "type": "Feature",
  "properties": {
    "gn:admin1_code":"20",
    "gn:admin2_code":"VR",
    "gn:admin3_code":"23091.0",
    "gn:asciiname":"Trezzolano",
    "gn:country_code":"IT",
    "gn:dem":381,
    "gn:feature_class":"P",
    "gn:feature_code":"PPL",
    "gn:name":"Trezzolano",
    "gn:population":43,
    "gn:timezone":"Europe/Rome",
    "iso:country":"IT",
    "wof:name":"Trezzolano",
    "wof:placetype":"locality",
    "wof:population":43
},
  "geometry": {"coordinates":[11.08044,45.50156],"type":"Point"}
}