{
  "type": "Feature",
  "properties": {
    "gn:admin1_code":"1",
    "gn:admin2_code":"CH",
    "gn:admin3_code":"69013.0",
    "gn:asciiname":"Val di Foro",
    "gn:country_code":"IT",
    "gn:dem":187,
    "gn:feature_class":"P",
    "gn:feature_code":"PPL",
    "gn:name":"Val di Foro",
    "gn:population":214,
    "gn:timezone":"Europe/Rome",
    "iso:country":"IT",
    "wof:name":"Val di Foro",
    "wof:placetype":"locality",
    "wof:population":214
},
  "geometry": {"coordinates":[14.1965,42.26941],"type":"Point"}
}