{
  "type": "Feature",
  "properties": {
    "gn:admin1_code":"4",
    "gn:admin3_code":"63058.0",
    "gn:asciiname":"Chiesa della Giuliana",
    "gn:country_code":"IT",
    "gn:dem":50,
    "gn:feature_class":"P",
    "gn:feature_code":"PPL",
    "gn:name":"Chiesa della Giuliana",
    "gn:population":261,
    "gn:timezone":"Europe/Rome",
    "iso:country":"IT",
    "wof:name":"Chiesa della Giuliana",
    "wof:placetype":"locality",
    "wof:population":261
},
  "geometry": {"coordinates":[14.48171,40.75925],"type":"Point"}
}