{
  "type": "Feature",
  "properties": {
    "gn:admin1_code":"15.0",
    "gn:admin2_code":"ME",
    "gn:admin3_code":"83068.0",
    "gn:asciiname":"Colla",
    "gn:country_code":"IT",
    "gn:dem":487,
    "gn:feature_class":"P",
    "gn:feature_code":"PPL",
    "gn:name":"Colla",
    "gn:population":18,
    "gn:timezone":"Europe/Rome",
    "iso:country":"IT",
    "name:als_x_preferred":[
        "Colla"
    ],
    "name:ceb_x_preferred":[
        "Colla"
    ],
    "name:deu_x_preferred":[
        "Colla"
    ],
    "name:fra_x_preferred":[
        "Colla"
    ],
    "name:ita_x_preferred":[
        "Colla"
    ],
    "name:lat_x_preferred":[
        "Colla"
    ],
    "name:rus_x_preferred":[
        "\u041a\u043e\u043b\u043b\u0430"
    ],
    "name:spa_x_preferred":[
        "Colla"
    ],
    "name:srp_x_preferred":[
        "Colla"
    ],
    "name:swe_x_preferred":[
        "Colla"
    ],
    "name:ukr_x_preferred":[
        "\u041a\u043e\u043b\u043b\u0430"
    ],
    "wof:name":"Colla",
    "wof:placetype":"locality",
    "wof:population":18
},
  "geometry": {"coordinates":[14.88837,38.15397],"type":"Point"}
}