{
  "type": "Feature",
  "properties": {
    "gn:admin1_code":"15",
    "gn:admin2_code":"CL",
    "gn:admin3_code":"85005.0",
    "gn:asciiname":"Villaggio Faina",
    "gn:country_code":"IT",
    "gn:dem":176,
    "gn:feature_class":"P",
    "gn:feature_code":"PPL",
    "gn:name":"Villaggio Faina",
    "gn:population":40,
    "gn:timezone":"Europe/Rome",
    "iso:country":"IT",
    "wof:name":"Villaggio Faina",
    "wof:placetype":"locality",
    "wof:population":40
},
  "geometry": {"coordinates":[13.69743,37.51802],"type":"Point"}
}