{
  "type": "Feature",
  "properties": {
    "gn:admin1_code":"18",
    "gn:admin2_code":"PG",
    "gn:admin3_code":"54040.0",
    "gn:asciiname":"Vignaie",
    "gn:country_code":"IT",
    "gn:dem":485,
    "gn:feature_class":"P",
    "gn:feature_code":"PPL",
    "gn:name":"Vignaie",
    "gn:population":14,
    "gn:timezone":"Europe/Rome",
    "iso:country":"IT",
    "wof:name":"Vignaie",
    "wof:placetype":"locality",
    "wof:population":14
},
  "geometry": {"coordinates":[12.14064,42.96654],"type":"Point"}
}