{
  "type": "Feature",
  "properties": {
    "gn:admin1_code":"9",
    "gn:admin2_code":"BG",
    "gn:admin3_code":"16159.0",
    "gn:asciiname":"Portirone",
    "gn:country_code":"IT",
    "gn:dem":195,
    "gn:feature_class":"P",
    "gn:feature_code":"PPL",
    "gn:name":"Portirone",
    "gn:population":19,
    "gn:timezone":"Europe/Rome",
    "iso:country":"IT",
    "wof:name":"Portirone",
    "wof:placetype":"locality",
    "wof:population":19
},
  "geometry": {"coordinates":[10.0506,45.72972],"type":"Point"}
}