{
  "type": "Feature",
  "properties": {
    "gn:admin1_code":"14.0",
    "gn:admin2_code":"NU",
    "gn:admin3_code":"91011.0",
    "gn:asciiname":"Piano Insediamenti Produttivi",
    "gn:country_code":"IT",
    "gn:dem":428,
    "gn:feature_class":"P",
    "gn:feature_code":"PPLL",
    "gn:name":"Piano Insediamenti Produttivi",
    "gn:population":0,
    "gn:timezone":"Europe/Rome",
    "iso:country":"IT",
    "wof:name":"Piano Insediamenti Produttivi",
    "wof:placetype":"locality"
},
  "geometry": {"coordinates":[8.78002,40.22842],"type":"Point"}
}