{
  "type": "Feature",
  "properties": {
    "gn:admin1_code":"6.0",
    "gn:admin2_code":"UD",
    "gn:admin3_code":"30058.0",
    "gn:asciiname":"Tomba",
    "gn:country_code":"IT",
    "gn:dem":96,
    "gn:elevation":"96.0",
    "gn:feature_class":"P",
    "gn:feature_code":"PPL",
    "gn:name":"Tomba",
    "gn:population":439,
    "gn:timezone":"Europe/Rome",
    "iso:country":"IT",
    "wof:name":"Tomba",
    "wof:placetype":"locality",
    "wof:population":439
},
  "geometry": {"coordinates":[13.06583,46.04933],"type":"Point"}
}