{
  "type": "Feature",
  "properties": {
    "gn:admin1_code":"20",
    "gn:admin2_code":"TV",
    "gn:admin3_code":"26007.0",
    "gn:asciiname":"Case Tobero",
    "gn:country_code":"IT",
    "gn:dem":182,
    "gn:feature_class":"P",
    "gn:feature_code":"PPL",
    "gn:name":"Case Tobero",
    "gn:population":33,
    "gn:timezone":"Europe/Rome",
    "iso:country":"IT",
    "wof:name":"Case Tobero",
    "wof:placetype":"locality",
    "wof:population":33
},
  "geometry": {"coordinates":[12.33687,45.98701],"type":"Point"}
}