{
  "type": "Feature",
  "properties": {
    "gn:admin1_code":"5",
    "gn:admin2_code":"BO",
    "gn:admin3_code":"37022.0",
    "gn:asciiname":"Prediera Sopra",
    "gn:country_code":"IT",
    "gn:dem":594,
    "gn:feature_class":"P",
    "gn:feature_code":"PPL",
    "gn:name":"Prediera Sopra",
    "gn:population":32,
    "gn:timezone":"Europe/Rome",
    "iso:country":"IT",
    "wof:name":"Prediera Sopra",
    "wof:placetype":"locality",
    "wof:population":32
},
  "geometry": {"coordinates":[11.18843,44.1717],"type":"Point"}
}