{
  "type": "Feature",
  "properties": {
    "iso:country":"IT",
    "name:bre_x_preferred":[
        "Amata"
    ],
    "name:bul_x_preferred":[
        "\u0410\u043c\u0430\u0442\u0430"
    ],
    "name:cat_x_preferred":[
        "Amata"
    ],
    "name:dan_x_preferred":[
        "Amata"
    ],
    "name:deu_x_preferred":[
        "Amata"
    ],
    "name:diq_x_preferred":[
        "Amata"
    ],
    "name:ell_x_preferred":[
        "\u0391\u03bc\u03ac\u03c4\u03b1"
    ],
    "name:eng_x_preferred":[
        "Amata"
    ],
    "name:eus_x_preferred":[
        "Amata"
    ],
    "name:fas_x_preferred":[
        "\u0622\u0645\u0627\u062a\u0627"
    ],
    "name:fra_x_preferred":[
        "Amata"
    ],
    "name:gle_x_preferred":[
        "Amata"
    ],
    "name:ind_x_preferred":[
        "Amata"
    ],
    "name:ita_x_preferred":[
        "Amata"
    ],
    "name:jpn_x_preferred":[
        "\u30a2\u30de\u30bf"
    ],
    "name:kat_x_preferred":[
        "\u10d0\u10db\u10d0\u10e2\u10d0"
    ],
    "name:lat_x_preferred":[
        "Amata"
    ],
    "name:lit_x_preferred":[
        "Amata"
    ],
    "name:nld_x_preferred":[
        "Amata"
    ],
    "name:pol_x_preferred":[
        "Amata"
    ],
    "name:por_x_preferred":[
        "Amata"
    ],
    "name:rus_x_preferred":[
        "\u0410\u043c\u0430\u0442\u0430"
    ],
    "name:spa_x_preferred":[
        "Amata"
    ],
    "name:swe_x_preferred":[
        "Amata"
    ],
    "name:tur_x_preferred":[
        "Amata"
    ],
    "name:ukr_x_preferred":[
        "\u0410\u043c\u0430\u0442\u0430"
    ],
    "name:zho_x_preferred":[
        "\u9e7f\u86fe\u5c5e"
    ],
    "qs:gn_adm0_cc":"IT",
    "qs:gn_local":3171737,
    "qs:gn_nam_loc":"Paderno Dugnano, Paderno Dugnano, Milano, Lombardia, IT",
    "qs:gn_namadm1":"09",
    "qs:local_max":1137,
    "qs:local_sum":1137,
    "qs:localhoods":1,
    "qs:name":"Amata",
    "qs:name_adm0":"Italia",
    "qs:name_adm1":"Lombardia",
    "qs:name_adm2":"Milano",
    "qs:name_lau":"Paderno Dugnano",
    "qs:name_local":"Paderno Dugnano",
    "qs:photo_max":264,
    "qs:photo_sum":1137,
    "qs:placetype":"Suburb",
    "qs:quad_count":64,
    "qs:woe_adm0":23424853,
    "qs:woe_adm1":7153338,
    "qs:woe_adm2":12591813,
    "qs:woe_lau":12677172,
    "qs:woe_local":719746,
    "qs:woe_ver":"7.10.0",
    "wd:wordcount":198,
    "wof:lang":[
        "ita"
    ],
    "wof:name":"Amata",
    "wof:placetype":"neighbourhood"
},
  "geometry": {"coordinates":[9.148568,45.589776],"type":"Point"}
}