{
  "type": "Feature",
  "properties": {
    "gn:admin1_code":"5.0",
    "gn:admin2_code":"BO",
    "gn:admin3_code":"37011.0",
    "gn:asciiname":"Zona Industriale Via del Lavoro",
    "gn:country_code":"IT",
    "gn:dem":62,
    "gn:feature_class":"P",
    "gn:feature_code":"PPL",
    "gn:name":"Zona Industriale Via del Lavoro",
    "gn:population":184,
    "gn:timezone":"Europe/Rome",
    "iso:country":"IT",
    "wof:name":"Zona Industriale Via del Lavoro",
    "wof:placetype":"locality",
    "wof:population":184
},
  "geometry": {"coordinates":[11.25575,44.48899],"type":"Point"}
}