{
  "type": "Feature",
  "properties": {
    "gn:admin1_code":"4",
    "gn:admin2_code":"BN",
    "gn:admin3_code":"62003.0",
    "gn:asciiname":"Bordi",
    "gn:country_code":"IT",
    "gn:dem":166,
    "gn:feature_class":"P",
    "gn:feature_code":"PPL",
    "gn:name":"Bordi",
    "gn:population":39,
    "gn:timezone":"Europe/Rome",
    "iso:country":"IT",
    "wof:name":"Bordi",
    "wof:placetype":"locality",
    "wof:population":39
},
  "geometry": {"coordinates":[14.93201,41.14386],"type":"Point"}
}