{
  "type": "Feature",
  "properties": {
    "gn:admin1_code":"20",
    "gn:admin2_code":"TV",
    "gn:admin3_code":"26092.0",
    "gn:asciiname":"Borgo Fae",
    "gn:country_code":"IT",
    "gn:dem":304,
    "gn:feature_class":"P",
    "gn:feature_code":"PPL",
    "gn:name":"Borgo Fa\u00e8",
    "gn:population":23,
    "gn:timezone":"Europe/Rome",
    "iso:country":"IT",
    "name:und_x_variant":[
        "Borgo Fa\u00e8"
    ],
    "wof:name":"Borgo Fae",
    "wof:placetype":"locality",
    "wof:population":23
},
  "geometry": {"coordinates":[12.33191,46.07044000000001],"type":"Point"}
}