{
  "type": "Feature",
  "properties": {
    "gn:admin1_code":"5",
    "gn:admin2_code":"FC",
    "gn:admin3_code":"40049.0",
    "gn:asciiname":"Villaggio Monte Busca",
    "gn:country_code":"IT",
    "gn:dem":707,
    "gn:feature_class":"P",
    "gn:feature_code":"PPL",
    "gn:name":"Villaggio Monte Busca",
    "gn:population":17,
    "gn:timezone":"Europe/Rome",
    "iso:country":"IT",
    "wof:name":"Villaggio Monte Busca",
    "wof:placetype":"locality",
    "wof:population":17
},
  "geometry": {"coordinates":[11.77073,44.05478],"type":"Point"}
}