{
  "type": "Feature",
  "properties": {
    "gn:admin1_code":"20",
    "gn:admin2_code":"VI",
    "gn:admin3_code":"24048.0",
    "gn:asciiname":"Cervo",
    "gn:country_code":"IT",
    "gn:dem":178,
    "gn:feature_class":"P",
    "gn:feature_code":"PPL",
    "gn:name":"Cervo",
    "gn:population":42,
    "gn:timezone":"Europe/Rome",
    "iso:country":"IT",
    "wof:name":"Cervo",
    "wof:placetype":"locality",
    "wof:population":42
},
  "geometry": {"coordinates":[11.41502,45.62097],"type":"Point"}
}