{
  "type": "Feature",
  "properties": {
    "gn:admin1_code":"20",
    "gn:admin2_code":"VI",
    "gn:admin3_code":"24048.0",
    "gn:asciiname":"Cervo",
    "gn:country_code":"IT",
    "gn:dem":178,
    "gn:feature_class":"P",
    "gn:feature_code":"PPL",
    "gn:name":"Cervo",
    "gn:population":42,
    "gn:timezone":"Europe/Rome",
    "iso:country":"IT",
    "name:bel_x_preferred":[
        "\u0427\u044d\u0440\u0432\u0430"
    ],
    "name:cat_x_preferred":[
        "Cervo"
    ],
    "name:ceb_x_preferred":[
        "Cervo"
    ],
    "name:deu_x_preferred":[
        "Cervo"
    ],
    "name:eus_x_preferred":[
        "Cervo"
    ],
    "name:fra_x_preferred":[
        "Cervo"
    ],
    "name:glg_x_preferred":[
        "Cervo"
    ],
    "name:heb_x_preferred":[
        "\u05e6'\u05e8\u05d1\u05d5"
    ],
    "name:hun_x_preferred":[
        "Cervo"
    ],
    "name:ita_x_preferred":[
        "Cervo"
    ],
    "name:jpn_x_preferred":[
        "\u30bb\u30eb\u30dc"
    ],
    "name:lmo_x_preferred":[
        "Cervo"
    ],
    "name:msa_x_preferred":[
        "Cervo"
    ],
    "name:nld_x_preferred":[
        "Cervo"
    ],
    "name:pms_x_preferred":[
        "Cervo"
    ],
    "name:pol_x_preferred":[
        "Cervo"
    ],
    "name:por_x_preferred":[
        "Cervo"
    ],
    "name:spa_x_preferred":[
        "Cervo"
    ],
    "name:srp_x_preferred":[
        "\u010cervo"
    ],
    "name:swe_x_preferred":[
        "Cervo"
    ],
    "name:vie_x_preferred":[
        "Cervo"
    ],
    "name:war_x_preferred":[
        "Cervo"
    ],
    "wof:name":"Cervo",
    "wof:placetype":"locality",
    "wof:population":42
},
  "geometry": {"coordinates":[11.41502,45.62097],"type":"Point"}
}