{
  "type": "Feature",
  "properties": {
    "gn:admin1_code":"17",
    "gn:admin2_code":"TN",
    "gn:admin3_code":"22157.0",
    "gn:asciiname":"Bosco",
    "gn:country_code":"IT",
    "gn:dem":795,
    "gn:feature_class":"P",
    "gn:feature_code":"PPL",
    "gn:name":"Bosco",
    "gn:population":38,
    "gn:timezone":"Europe/Rome",
    "iso:country":"IT",
    "wof:name":"Bosco",
    "wof:placetype":"locality",
    "wof:population":38
},
  "geometry": {"coordinates":[11.43068,46.06583],"type":"Point"}
}