{
  "type": "Feature",
  "properties": {
    "gn:admin1_code":"17",
    "gn:admin2_code":"TN",
    "gn:admin3_code":"22157.0",
    "gn:asciiname":"Bosco",
    "gn:country_code":"IT",
    "gn:dem":795,
    "gn:feature_class":"P",
    "gn:feature_code":"PPL",
    "gn:name":"Bosco",
    "gn:population":38,
    "gn:timezone":"Europe/Rome",
    "iso:country":"IT",
    "name:ceb_x_preferred":[
        "Bosco"
    ],
    "name:ces_x_preferred":[
        "Bosco"
    ],
    "name:deu_x_preferred":[
        "Bosco"
    ],
    "name:epo_x_preferred":[
        "Bosco"
    ],
    "name:fra_x_preferred":[
        "Bosco"
    ],
    "name:ita_x_preferred":[
        "Bosco"
    ],
    "name:jpn_x_preferred":[
        "\u30dc\u30b9\u30b3"
    ],
    "name:nld_x_preferred":[
        "Bosco"
    ],
    "name:por_x_preferred":[
        "Bosco"
    ],
    "name:ron_x_preferred":[
        "Bosco"
    ],
    "name:rus_x_preferred":[
        "\u0411\u043e\u0441\u043a\u043e"
    ],
    "name:spa_x_preferred":[
        "Bosco"
    ],
    "name:srp_x_preferred":[
        "\u0411\u043e\u0441\u043a\u043e"
    ],
    "name:swe_x_preferred":[
        "Bosco"
    ],
    "wof:name":"Bosco",
    "wof:placetype":"locality",
    "wof:population":38
},
  "geometry": {"coordinates":[11.43068,46.06583],"type":"Point"}
}