{
  "type": "Feature",
  "properties": {
    "gn:admin1_code":"9",
    "gn:admin2_code":"SO",
    "gn:admin3_code":"14060.0",
    "gn:asciiname":"Migiondo",
    "gn:country_code":"IT",
    "gn:dem":923,
    "gn:feature_class":"P",
    "gn:feature_code":"PPL",
    "gn:name":"Migiondo",
    "gn:population":51,
    "gn:timezone":"Europe/Rome",
    "iso:country":"IT",
    "wof:name":"Migiondo",
    "wof:placetype":"locality",
    "wof:population":51
},
  "geometry": {"coordinates":[10.3053,46.32367],"type":"Point"}
}