{
  "type": "Feature",
  "properties": {
    "gn:admin1_code":"20",
    "gn:admin2_code":"PD",
    "gn:admin3_code":"28050.0",
    "gn:asciiname":"Case Olivi",
    "gn:country_code":"IT",
    "gn:dem":14,
    "gn:feature_class":"P",
    "gn:feature_code":"PPL",
    "gn:name":"Case Olivi",
    "gn:population":61,
    "gn:timezone":"Europe/Rome",
    "iso:country":"IT",
    "wof:name":"Case Olivi",
    "wof:placetype":"locality",
    "wof:population":61
},
  "geometry": {"coordinates":[12.02507,45.56209000000001],"type":"Point"}
}