{
  "type": "Feature",
  "properties": {
    "gn:admin1_code":"5",
    "gn:admin2_code":"BO",
    "gn:admin3_code":"37042.0",
    "gn:asciiname":"Borra",
    "gn:country_code":"IT",
    "gn:dem":538,
    "gn:feature_class":"P",
    "gn:feature_code":"PPL",
    "gn:name":"Borra",
    "gn:population":42,
    "gn:timezone":"Europe/Rome",
    "iso:country":"IT",
    "wof:name":"Borra",
    "wof:placetype":"locality",
    "wof:population":42
},
  "geometry": {"coordinates":[11.16096,44.37464],"type":"Point"}
}