{
  "type": "Feature",
  "properties": {
    "gn:admin1_code":"12",
    "gn:admin2_code":"AL",
    "gn:admin3_code":"6044.0",
    "gn:asciiname":"Vercellini",
    "gn:country_code":"IT",
    "gn:dem":536,
    "gn:feature_class":"P",
    "gn:feature_code":"PPL",
    "gn:name":"Vercellini",
    "gn:population":31,
    "gn:timezone":"Europe/Rome",
    "iso:country":"IT",
    "wof:name":"Vercellini",
    "wof:placetype":"locality",
    "wof:population":31
},
  "geometry": {"coordinates":[8.55845,44.57753],"type":"Point"}
}