{
  "type": "Feature",
  "properties": {
    "gn:admin1_code":"9",
    "gn:admin2_code":"LC",
    "gn:admin3_code":"97082.0",
    "gn:asciiname":"Biglio Inferiore",
    "gn:country_code":"IT",
    "gn:dem":477,
    "gn:feature_class":"P",
    "gn:feature_code":"PPLL",
    "gn:name":"Biglio Inferiore",
    "gn:population":8,
    "gn:timezone":"Europe/Rome",
    "iso:country":"IT",
    "wof:name":"Biglio Inferiore",
    "wof:placetype":"locality",
    "wof:population":8
},
  "geometry": {"coordinates":[9.40215,45.76877],"type":"Point"}
}