{
  "type": "Feature",
  "properties": {
    "gn:admin1_code":"7",
    "gn:admin2_code":"LT",
    "gn:admin3_code":"59005.0",
    "gn:asciiname":"Casale Nuovo",
    "gn:country_code":"IT",
    "gn:dem":26,
    "gn:feature_class":"P",
    "gn:feature_code":"PPL",
    "gn:name":"Casale Nuovo",
    "gn:population":50,
    "gn:timezone":"Europe/Rome",
    "iso:country":"IT",
    "wof:name":"Casale Nuovo",
    "wof:placetype":"locality",
    "wof:population":50
},
  "geometry": {"coordinates":[12.82867,41.49732],"type":"Point"}
}