{
  "type": "Feature",
  "properties": {
    "gn:admin1_code":"18",
    "gn:admin2_code":"PG",
    "gn:admin3_code":"54052.0",
    "gn:asciiname":"Case Basse",
    "gn:country_code":"IT",
    "gn:dem":146,
    "gn:feature_class":"P",
    "gn:feature_code":"PPL",
    "gn:name":"Case Basse",
    "gn:population":17,
    "gn:timezone":"Europe/Rome",
    "iso:country":"IT",
    "wof:name":"Case Basse",
    "wof:placetype":"locality",
    "wof:population":17
},
  "geometry": {"coordinates":[12.39638,42.80553],"type":"Point"}
}