{
  "type": "Feature",
  "properties": {
    "gn:admin1_code":"5",
    "gn:admin2_code":"BO",
    "gn:admin3_code":"37020.0",
    "gn:asciiname":"San Lorenzo",
    "gn:country_code":"IT",
    "gn:dem":44,
    "gn:feature_class":"P",
    "gn:feature_code":"PPL",
    "gn:name":"San Lorenzo",
    "gn:population":29,
    "gn:timezone":"Europe/Rome",
    "iso:country":"IT",
    "wof:name":"San Lorenzo",
    "wof:placetype":"locality",
    "wof:population":29
},
  "geometry": {"coordinates":[11.56395,44.44224000000001],"type":"Point"}
}