{
  "type": "Feature",
  "properties": {
    "gn:admin1_code":"12.0",
    "gn:admin2_code":"BI",
    "gn:admin3_code":"96058.0",
    "gn:asciiname":"Vigellio",
    "gn:country_code":"IT",
    "gn:dem":234,
    "gn:feature_class":"P",
    "gn:feature_code":"PPL",
    "gn:name":"Vigellio",
    "gn:population":521,
    "gn:timezone":"Europe/Rome",
    "iso:country":"IT",
    "wof:name":"Vigellio",
    "wof:placetype":"locality",
    "wof:population":521
},
  "geometry": {"coordinates":[8.11546,45.46109000000001],"type":"Point"}
}