{
  "type": "Feature",
  "properties": {
    "gn:admin1_code":"5.0",
    "gn:admin2_code":"PC",
    "gn:admin3_code":"33020.0",
    "gn:asciiname":"Boschi",
    "gn:country_code":"IT",
    "gn:dem":764,
    "gn:elevation":"748.0",
    "gn:feature_class":"P",
    "gn:feature_code":"PPL",
    "gn:name":"Boschi",
    "gn:population":22,
    "gn:timezone":"Europe/Rome",
    "iso:country":"IT",
    "wof:name":"Boschi",
    "wof:placetype":"locality",
    "wof:population":22
},
  "geometry": {"coordinates":[9.42421,44.58325],"type":"Point"}
}