{
  "type": "Feature",
  "properties": {
    "gn:admin1_code":"20",
    "gn:admin2_code":"PD",
    "gn:admin3_code":"28016.0",
    "gn:asciiname":"Semoin",
    "gn:country_code":"IT",
    "gn:dem":7,
    "gn:feature_class":"P",
    "gn:feature_code":"PPL",
    "gn:name":"Semoin",
    "gn:population":139,
    "gn:timezone":"Europe/Rome",
    "iso:country":"IT",
    "wof:name":"Semoin",
    "wof:placetype":"locality",
    "wof:population":139
},
  "geometry": {"coordinates":[11.94715,45.44841],"type":"Point"}
}