{
  "type": "Feature",
  "properties": {
    "gn:admin1_code":"16",
    "gn:admin2_code":"GR",
    "gn:admin3_code":"53020.0",
    "gn:asciiname":"Case Galli",
    "gn:country_code":"IT",
    "gn:dem":626,
    "gn:feature_class":"P",
    "gn:feature_code":"PPL",
    "gn:name":"Case Galli",
    "gn:population":13,
    "gn:timezone":"Europe/Rome",
    "iso:country":"IT",
    "wof:name":"Case Galli",
    "wof:placetype":"locality",
    "wof:population":13
},
  "geometry": {"coordinates":[11.48309,42.78789],"type":"Point"}
}