{
  "type": "Feature",
  "properties": {
    "gn:admin1_code":"12",
    "gn:admin2_code":"TO",
    "gn:admin3_code":"1089.0",
    "gn:asciiname":"Marini",
    "gn:country_code":"IT",
    "gn:dem":864,
    "gn:feature_class":"P",
    "gn:feature_code":"PPL",
    "gn:name":"Marini",
    "gn:population":13,
    "gn:timezone":"Europe/Rome",
    "iso:country":"IT",
    "wof:name":"Marini",
    "wof:placetype":"locality",
    "wof:population":13
},
  "geometry": {"coordinates":[7.29967,45.06482000000001],"type":"Point"}
}