{
  "type": "Feature",
  "properties": {
    "gn:admin1_code":"12",
    "gn:admin2_code":"VB",
    "gn:admin3_code":"103064.0",
    "gn:asciiname":"Campino",
    "gn:country_code":"IT",
    "gn:dem":398,
    "gn:feature_class":"P",
    "gn:feature_code":"PPL",
    "gn:name":"Campino",
    "gn:population":139,
    "gn:timezone":"Europe/Rome",
    "iso:country":"IT",
    "name:por_x_preferred":[
        "Campino"
    ],
    "wof:name":"Campino",
    "wof:placetype":"locality",
    "wof:population":139
},
  "geometry": {"coordinates":[8.50621,45.89504],"type":"Point"}
}