{
  "type": "Feature",
  "properties": {
    "gn:admin1_code":"10.0",
    "gn:admin2_code":"AP",
    "gn:admin3_code":"44001.0",
    "gn:asciiname":"Paggese-Santa Maria",
    "gn:country_code":"IT",
    "gn:dem":437,
    "gn:feature_class":"P",
    "gn:feature_code":"PPL",
    "gn:name":"Paggese-Santa Maria",
    "gn:population":917,
    "gn:timezone":"Europe/Rome",
    "iso:country":"IT",
    "wof:name":"Paggese-Santa Maria",
    "wof:placetype":"locality",
    "wof:population":917
},
  "geometry": {"coordinates":[13.4183,42.77796],"type":"Point"}
}