{
  "type": "Feature",
  "properties": {
    "gn:admin1_code":"19",
    "gn:admin2_code":"AO",
    "gn:admin3_code":"7071.0",
    "gn:asciiname":"Maen",
    "gn:country_code":"IT",
    "gn:dem":1329,
    "gn:feature_class":"P",
    "gn:feature_code":"PPL",
    "gn:name":"Maen",
    "gn:population":176,
    "gn:timezone":"Europe/Rome",
    "iso:country":"IT",
    "wof:name":"Maen",
    "wof:placetype":"locality",
    "wof:population":176
},
  "geometry": {"coordinates":[7.61382,45.86709000000001],"type":"Point"}
}