{
  "type": "Feature",
  "properties": {
    "gn:admin1_code":"1",
    "gn:admin2_code":"TE",
    "gn:admin3_code":"67015.0",
    "gn:asciiname":"Monteverde Basso",
    "gn:country_code":"IT",
    "gn:dem":89,
    "gn:feature_class":"P",
    "gn:feature_code":"PPL",
    "gn:name":"Monteverde Basso",
    "gn:population":147,
    "gn:timezone":"Europe/Rome",
    "iso:country":"IT",
    "wof:name":"Monteverde Basso",
    "wof:placetype":"locality",
    "wof:population":147
},
  "geometry": {"coordinates":[13.85116,42.61816],"type":"Point"}
}