{
  "type": "Feature",
  "properties": {
    "gn:admin1_code":"16",
    "gn:admin2_code":"LU",
    "gn:admin3_code":"46017.0",
    "gn:asciiname":"Ponte della Maddalena",
    "gn:country_code":"IT",
    "gn:dem":66,
    "gn:feature_class":"P",
    "gn:feature_code":"PPL",
    "gn:name":"Ponte della Maddalena",
    "gn:population":146,
    "gn:timezone":"Europe/Rome",
    "iso:country":"IT",
    "wof:name":"Ponte della Maddalena",
    "wof:placetype":"locality",
    "wof:population":146
},
  "geometry": {"coordinates":[10.46169,43.90068],"type":"Point"}
}