{
  "type": "Feature",
  "properties": {
    "gn:admin1_code":"20",
    "gn:admin2_code":"VR",
    "gn:admin3_code":"23061.0",
    "gn:asciiname":"San Francesco",
    "gn:country_code":"IT",
    "gn:dem":14,
    "gn:feature_class":"P",
    "gn:feature_code":"PPL",
    "gn:name":"San Francesco",
    "gn:population":34,
    "gn:timezone":"Europe/Rome",
    "iso:country":"IT",
    "wof:name":"San Francesco",
    "wof:placetype":"locality",
    "wof:population":34
},
  "geometry": {"coordinates":[11.4155,45.27377],"type":"Point"}
}