{
  "type": "Feature",
  "properties": {
    "gn:admin1_code":"16",
    "gn:admin2_code":"LU",
    "gn:admin3_code":"46008.0",
    "gn:asciiname":"Le Coste",
    "gn:country_code":"IT",
    "gn:dem":822,
    "gn:feature_class":"P",
    "gn:feature_code":"PPL",
    "gn:name":"Le Coste",
    "gn:population":26,
    "gn:timezone":"Europe/Rome",
    "iso:country":"IT",
    "wof:name":"Le Coste",
    "wof:placetype":"locality",
    "wof:population":26
},
  "geometry": {"coordinates":[10.34042,44.08716],"type":"Point"}
}