{
  "type": "Feature",
  "properties": {
    "gn:admin1_code":"19",
    "gn:admin2_code":"AO",
    "gn:admin3_code":"7074.0",
    "gn:asciiname":"Vereytaz",
    "gn:country_code":"IT",
    "gn:dem":749,
    "gn:feature_class":"P",
    "gn:feature_code":"PPL",
    "gn:name":"Vereytaz",
    "gn:population":26,
    "gn:timezone":"Europe/Rome",
    "iso:country":"IT",
    "wof:name":"Vereytaz",
    "wof:placetype":"locality",
    "wof:population":26
},
  "geometry": {"coordinates":[7.21589,45.7122],"type":"Point"}
}