{
  "type": "Feature",
  "properties": {
    "gn:admin1_code":"17",
    "gn:admin2_code":"TN",
    "gn:admin3_code":"22181.0",
    "gn:asciiname":"Maso Milano",
    "gn:country_code":"IT",
    "gn:dem":265,
    "gn:feature_class":"P",
    "gn:feature_code":"PPL",
    "gn:name":"Maso Milano",
    "gn:population":41,
    "gn:timezone":"Europe/Rome",
    "iso:country":"IT",
    "wof:name":"Maso Milano",
    "wof:placetype":"locality",
    "wof:population":41
},
  "geometry": {"coordinates":[11.05257,46.23702],"type":"Point"}
}