{
  "type": "Feature",
  "properties": {
    "gn:admin1_code":"9",
    "gn:admin2_code":"BG",
    "gn:admin3_code":"16043.0",
    "gn:asciiname":"Cascina Quattro Vie",
    "gn:country_code":"IT",
    "gn:dem":177,
    "gn:feature_class":"P",
    "gn:feature_code":"PPL",
    "gn:name":"Cascina Quattro Vie",
    "gn:population":24,
    "gn:timezone":"Europe/Rome",
    "iso:country":"IT",
    "wof:name":"Cascina Quattro Vie",
    "wof:placetype":"locality",
    "wof:population":24
},
  "geometry": {"coordinates":[9.79367,45.61088],"type":"Point"}
}