{
  "type": "Feature",
  "properties": {
    "gn:admin1_code":"12",
    "gn:admin2_code":"BI",
    "gn:admin3_code":"96035.0",
    "gn:asciiname":"Toso",
    "gn:country_code":"IT",
    "gn:dem":425,
    "gn:feature_class":"P",
    "gn:feature_code":"PPL",
    "gn:name":"Toso",
    "gn:population":22,
    "gn:timezone":"Europe/Rome",
    "iso:country":"IT",
    "wof:name":"Toso",
    "wof:placetype":"locality",
    "wof:population":22
},
  "geometry": {"coordinates":[7.9929,45.5211],"type":"Point"}
}