{
  "type": "Feature",
  "properties": {
    "gn:admin1_code":"12",
    "gn:admin2_code":"AT",
    "gn:admin3_code":"5104.0",
    "gn:asciiname":"Brallo",
    "gn:country_code":"IT",
    "gn:dem":632,
    "gn:feature_class":"P",
    "gn:feature_code":"PPL",
    "gn:name":"Brallo",
    "gn:population":32,
    "gn:timezone":"Europe/Rome",
    "iso:country":"IT",
    "wof:name":"Brallo",
    "wof:placetype":"locality",
    "wof:population":32
},
  "geometry": {"coordinates":[8.26602,44.54758],"type":"Point"}
}