{
  "type": "Feature",
  "properties": {
    "gn:admin1_code":"3.0",
    "gn:admin2_code":"KR",
    "gn:admin3_code":"101010.0",
    "gn:asciiname":"Villa Morelli",
    "gn:cc2":"IT",
    "gn:country_code":"IT",
    "gn:dem":23,
    "gn:feature_class":"P",
    "gn:feature_code":"PPL",
    "gn:name":"Villa Morelli",
    "gn:population":0,
    "gn:timezone":"Europe/Rome",
    "iso:country":"IT",
    "name:und_x_variant":[
        "Morelli",
        "Villa Morelli"
    ],
    "wof:name":"Villa Morelli",
    "wof:placetype":"locality"
},
  "geometry": {"coordinates":[17.08333,39.08333],"type":"Point"}
}