{
  "type": "Feature",
  "properties": {
    "gn:admin1_code":"18",
    "gn:admin2_code":"TR",
    "gn:admin3_code":"55032.0",
    "gn:asciiname":"Costanzoni",
    "gn:country_code":"IT",
    "gn:dem":268,
    "gn:feature_class":"P",
    "gn:feature_code":"PPL",
    "gn:name":"Costanzoni",
    "gn:population":28,
    "gn:timezone":"Europe/Rome",
    "iso:country":"IT",
    "wof:name":"Costanzoni",
    "wof:placetype":"locality",
    "wof:population":28
},
  "geometry": {"coordinates":[12.61566,42.52733],"type":"Point"}
}