{
  "type": "Feature",
  "properties": {
    "gn:admin1_code":"20",
    "gn:admin2_code":"VR",
    "gn:admin3_code":"23084.0",
    "gn:asciiname":"Santo",
    "gn:country_code":"IT",
    "gn:dem":19,
    "gn:feature_class":"P",
    "gn:feature_code":"PPL",
    "gn:name":"Santo",
    "gn:population":44,
    "gn:timezone":"Europe/Rome",
    "iso:country":"IT",
    "wof:name":"Santo",
    "wof:placetype":"locality",
    "wof:population":44
},
  "geometry": {"coordinates":[11.00472,45.17597],"type":"Point"}
}