{
  "type": "Feature",
  "properties": {
    "gn:admin1_code":"6.0",
    "gn:admin2_code":"UD",
    "gn:admin3_code":"30108.0",
    "gn:asciiname":"Cepletischis",
    "gn:country_code":"IT",
    "gn:dem":574,
    "gn:elevation":"568.0",
    "gn:feature_class":"P",
    "gn:feature_code":"PPL",
    "gn:name":"Cepletischis",
    "gn:population":63,
    "gn:timezone":"Europe/Rome",
    "iso:country":"IT",
    "wof:name":"Cepletischis",
    "wof:placetype":"locality",
    "wof:population":63
},
  "geometry": {"coordinates":[13.57058,46.1789],"type":"Point"}
}