{
  "type": "Feature",
  "properties": {
    "gn:admin1_code":"5.0",
    "gn:admin2_code":"RE",
    "gn:admin3_code":"35043.0",
    "gn:asciiname":"Paderna",
    "gn:country_code":"IT",
    "gn:dem":392,
    "gn:feature_class":"P",
    "gn:feature_code":"PPL",
    "gn:name":"Paderna",
    "gn:population":36,
    "gn:timezone":"Europe/Rome",
    "iso:country":"IT",
    "wof:name":"Paderna",
    "wof:placetype":"locality",
    "wof:population":36
},
  "geometry": {"coordinates":[10.51712,44.57101],"type":"Point"}
}