{
  "type": "Feature",
  "properties": {
    "gn:admin1_code":"5.0",
    "gn:admin2_code":"RE",
    "gn:admin3_code":"35043.0",
    "gn:asciiname":"Paderna",
    "gn:country_code":"IT",
    "gn:dem":392,
    "gn:feature_class":"P",
    "gn:feature_code":"PPL",
    "gn:name":"Paderna",
    "gn:population":36,
    "gn:timezone":"Europe/Rome",
    "iso:country":"IT",
    "name:ara_x_preferred":[
        "\u0628\u0627\u062f\u064a\u0631\u0646\u0627"
    ],
    "name:azb_x_preferred":[
        "\u067e\u0627\u062f\u0631\u0646\u0627"
    ],
    "name:bel_x_preferred":[
        "\u041f\u0430\u0434\u044d\u0440\u043d\u0430"
    ],
    "name:bul_x_preferred":[
        "\u041f\u0430\u0434\u0435\u0440\u043d\u0430"
    ],
    "name:cat_x_preferred":[
        "Paderna"
    ],
    "name:ceb_x_preferred":[
        "Paderna"
    ],
    "name:deu_x_preferred":[
        "Paderna"
    ],
    "name:epo_x_preferred":[
        "Paderna"
    ],
    "name:eus_x_preferred":[
        "Paderna"
    ],
    "name:fas_x_preferred":[
        "\u067e\u0627\u062f\u0631\u0646\u0627"
    ],
    "name:fra_x_preferred":[
        "Paderna"
    ],
    "name:hun_x_preferred":[
        "Paderna"
    ],
    "name:hye_x_preferred":[
        "\u054a\u0561\u0564\u0565\u0580\u0576\u0561"
    ],
    "name:ind_x_preferred":[
        "Paderna"
    ],
    "name:ita_x_preferred":[
        "Paderna"
    ],
    "name:jpn_x_preferred":[
        "\u30d1\u30c7\u30eb\u30ca"
    ],
    "name:kaz_x_preferred":[
        "\u041f\u0430\u0434\u0435\u0440\u043d\u0430"
    ],
    "name:lat_x_preferred":[
        "Padernum"
    ],
    "name:lmo_x_preferred":[
        "Paderna"
    ],
    "name:msa_x_preferred":[
        "Paderna"
    ],
    "name:nap_x_preferred":[
        "Paderna"
    ],
    "name:nld_x_preferred":[
        "Paderna"
    ],
    "name:pms_x_preferred":[
        "Paderna"
    ],
    "name:pol_x_preferred":[
        "Paderna"
    ],
    "name:por_x_preferred":[
        "Paderna"
    ],
    "name:ron_x_preferred":[
        "Paderna"
    ],
    "name:rus_x_preferred":[
        "\u041f\u0430\u0434\u0435\u0440\u043d\u0430"
    ],
    "name:scn_x_preferred":[
        "Paderna"
    ],
    "name:spa_x_preferred":[
        "Paderna"
    ],
    "name:srp_x_preferred":[
        "\u041f\u0430\u0434\u0435\u0440\u043d\u0430"
    ],
    "name:tgl_x_preferred":[
        "Paderna"
    ],
    "name:ukr_x_preferred":[
        "\u041f\u0430\u0434\u0435\u0440\u043d\u0430"
    ],
    "name:uzb_x_preferred":[
        "Paderna"
    ],
    "name:vie_x_preferred":[
        "Paderna"
    ],
    "name:vol_x_preferred":[
        "Paderna"
    ],
    "name:war_x_preferred":[
        "Paderna"
    ],
    "name:zho_x_preferred":[
        "\u5e15\u5fb7\u5c14\u7eb3"
    ],
    "wof:name":"Paderna",
    "wof:placetype":"locality",
    "wof:population":36
},
  "geometry": {"coordinates":[10.51712,44.57101],"type":"Point"}
}