{
  "type": "Feature",
  "properties": {
    "gn:admin1_code":"12",
    "gn:admin2_code":"TO",
    "gn:admin3_code":"1205.0",
    "gn:asciiname":"Collaretto",
    "gn:country_code":"IT",
    "gn:dem":718,
    "gn:feature_class":"P",
    "gn:feature_code":"PPL",
    "gn:name":"Collaretto",
    "gn:population":48,
    "gn:timezone":"Europe/Rome",
    "iso:country":"IT",
    "wof:name":"Collaretto",
    "wof:placetype":"locality",
    "wof:population":48
},
  "geometry": {"coordinates":[7.27199,44.87216],"type":"Point"}
}