{
  "type": "Feature",
  "properties": {
    "gn:admin1_code":"3",
    "gn:admin2_code":"CS",
    "gn:admin3_code":"78040.0",
    "gn:asciiname":"Sopralirto",
    "gn:country_code":"IT",
    "gn:dem":164,
    "gn:feature_class":"P",
    "gn:feature_code":"PPL",
    "gn:name":"Sopralirto",
    "gn:population":30,
    "gn:timezone":"Europe/Rome",
    "iso:country":"IT",
    "wof:name":"Sopralirto",
    "wof:placetype":"locality",
    "wof:population":30
},
  "geometry": {"coordinates":[15.93814,39.52456],"type":"Point"}
}