{
  "type": "Feature",
  "properties": {
    "gn:gn_country":"IT",
    "gn:gn_fcode":"PPL",
    "gn:gn_pop":0,
    "gn:population":317,
    "iso:country":"IT",
    "name:bul_x_preferred":[
        "\u041b\u0435\u043d\u0437\u0443\u043c\u043e"
    ],
    "name:cat_x_preferred":[
        "Lenzumo"
    ],
    "name:ceb_x_preferred":[
        "Lenzumo"
    ],
    "name:ces_x_preferred":[
        "Lenzumo"
    ],
    "name:dan_x_preferred":[
        "Lenzumo"
    ],
    "name:eng_x_preferred":[
        "Lenzumo"
    ],
    "name:eus_x_preferred":[
        "Lenzumo"
    ],
    "name:fin_x_preferred":[
        "Lenzumo"
    ],
    "name:fra_x_preferred":[
        "Lenzumo"
    ],
    "name:ind_x_preferred":[
        "Lenzumo"
    ],
    "name:ita_x_preferred":[
        "Lenzumo"
    ],
    "name:nld_x_preferred":[
        "Lenzumo"
    ],
    "name:nno_x_preferred":[
        "Lenzumo"
    ],
    "name:nob_x_preferred":[
        "Lenzumo"
    ],
    "name:oci_x_preferred":[
        "Lenzumo"
    ],
    "name:pol_x_preferred":[
        "Lenzumo"
    ],
    "name:por_x_preferred":[
        "Lenzumo"
    ],
    "name:ron_x_preferred":[
        "Lenzumo"
    ],
    "name:slk_x_preferred":[
        "Lenzumo"
    ],
    "name:slv_x_preferred":[
        "Lenzumo"
    ],
    "name:spa_x_preferred":[
        "Lenzumo"
    ],
    "name:srp_x_preferred":[
        "Lenzumo"
    ],
    "name:swe_x_preferred":[
        "Lenzumo"
    ],
    "name:tgl_x_preferred":[
        "Lenzumo"
    ],
    "name:tur_x_preferred":[
        "Lenzumo"
    ],
    "name:war_x_preferred":[
        "Lenzumo"
    ],
    "qs_pg:aaroncc":"IT",
    "qs_pg:gn_country":"IT",
    "qs_pg:gn_fcode":"PPL",
    "qs_pg:gn_pop":0,
    "qs_pg:name":"Lenzumo",
    "qs_pg:name_adm0":"Italia",
    "qs_pg:name_adm1":"Trentino-Alto Adige",
    "qs_pg:photos":20,
    "qs_pg:photos_1k":4,
    "qs_pg:photos_9k":1,
    "qs_pg:photos_9r":1,
    "qs_pg:photos_all":20,
    "qs_pg:photos_sr":1,
    "qs_pg:pop_sr":0,
    "qs_pg:qs_pg_placetype":"locality",
    "qs_pg:qs_pg_placetype_gp":"Town",
    "qs_pg:woe_adm0":23424853,
    "woe:adm0_id":23424853,
    "woe:name_adm0":"Italia",
    "woe:name_adm1":"Trentino-Alto Adige",
    "woe:placetype":"Town",
    "wof:name":"Lenzumo",
    "wof:placetype":"locality",
    "wof:population":317
},
  "geometry": {"coordinates":[10.72918,45.91199],"type":"Point"}
}