{
  "type": "Feature",
  "properties": {
    "gn:admin1_code":"19",
    "gn:admin2_code":"AO",
    "gn:admin3_code":"7033.0",
    "gn:asciiname":"Noversch",
    "gn:country_code":"IT",
    "gn:dem":1553,
    "gn:feature_class":"P",
    "gn:feature_code":"PPL",
    "gn:name":"Noversch",
    "gn:population":25,
    "gn:timezone":"Europe/Rome",
    "iso:country":"IT",
    "wof:name":"Noversch",
    "wof:placetype":"locality",
    "wof:population":25
},
  "geometry": {"coordinates":[7.82458,45.81255],"type":"Point"}
}