{
  "type": "Feature",
  "properties": {
    "gn:admin1_code":"18",
    "gn:admin2_code":"PG",
    "gn:admin3_code":"54055.0",
    "gn:asciiname":"La Cima",
    "gn:country_code":"IT",
    "gn:dem":585,
    "gn:feature_class":"P",
    "gn:feature_code":"PPL",
    "gn:name":"La Cima",
    "gn:population":33,
    "gn:timezone":"Europe/Rome",
    "iso:country":"IT",
    "wof:name":"La Cima",
    "wof:placetype":"locality",
    "wof:population":33
},
  "geometry": {"coordinates":[12.09119,43.22763],"type":"Point"}
}