{
  "type": "Feature",
  "properties": {
    "gn:admin1_code":"20",
    "gn:admin2_code":"VE",
    "gn:admin3_code":"27001.0",
    "gn:asciiname":"Comugna Larga",
    "gn:country_code":"IT",
    "gn:dem":2,
    "gn:feature_class":"P",
    "gn:feature_code":"PPL",
    "gn:name":"Comugna Larga",
    "gn:population":30,
    "gn:timezone":"Europe/Rome",
    "iso:country":"IT",
    "wof:name":"Comugna Larga",
    "wof:placetype":"locality",
    "wof:population":30
},
  "geometry": {"coordinates":[12.71172,45.77437000000001],"type":"Point"}
}