{
  "type": "Feature",
  "properties": {
    "gn:admin1_code":"16",
    "gn:admin2_code":"PI",
    "gn:admin3_code":"50041.0",
    "gn:asciiname":"Poggio al Tesoro",
    "gn:country_code":"IT",
    "gn:dem":85,
    "gn:feature_class":"P",
    "gn:feature_code":"PPL",
    "gn:name":"Poggio al Tesoro",
    "gn:population":17,
    "gn:timezone":"Europe/Rome",
    "iso:country":"IT",
    "wof:name":"Poggio al Tesoro",
    "wof:placetype":"locality",
    "wof:population":17
},
  "geometry": {"coordinates":[10.54993,43.57981],"type":"Point"}
}