{
  "type": "Feature",
  "properties": {
    "gn:admin1_code":"8",
    "gn:admin2_code":"GE",
    "gn:admin3_code":"10040.0",
    "gn:asciiname":"Antigastro",
    "gn:country_code":"IT",
    "gn:dem":242,
    "gn:feature_class":"P",
    "gn:feature_code":"PPL",
    "gn:name":"Antigastro",
    "gn:population":17,
    "gn:timezone":"Europe/Rome",
    "iso:country":"IT",
    "wof:name":"Antigastro",
    "wof:placetype":"locality",
    "wof:population":17
},
  "geometry": {"coordinates":[9.42458,44.35484],"type":"Point"}
}