{
  "type": "Feature",
  "properties": {
    "gn:admin1_code":"5.0",
    "gn:admin2_code":"FC",
    "gn:admin3_code":"40001.0",
    "gn:asciiname":"Larciano-Castello",
    "gn:country_code":"IT",
    "gn:dem":543,
    "gn:feature_class":"P",
    "gn:feature_code":"PPL",
    "gn:name":"Larciano-Castello",
    "gn:population":20,
    "gn:timezone":"Europe/Rome",
    "iso:country":"IT",
    "wof:name":"Larciano-Castello",
    "wof:placetype":"locality",
    "wof:population":20
},
  "geometry": {"coordinates":[11.97836,43.83812],"type":"Point"}
}