{
  "type": "Feature",
  "properties": {
    "gn:admin1_code":"9",
    "gn:admin2_code":"SO",
    "gn:admin3_code":"14022.0",
    "gn:asciiname":"Caspano",
    "gn:country_code":"IT",
    "gn:dem":853,
    "gn:feature_class":"P",
    "gn:feature_code":"PPL",
    "gn:name":"Caspano",
    "gn:population":216,
    "gn:timezone":"Europe/Rome",
    "iso:country":"IT",
    "wof:name":"Caspano",
    "wof:placetype":"locality",
    "wof:population":216
},
  "geometry": {"coordinates":[9.59999,46.16924],"type":"Point"}
}