{
  "type": "Feature",
  "properties": {
    "gn:admin1_code":"20",
    "gn:admin2_code":"VR",
    "gn:admin3_code":"23013.0",
    "gn:asciiname":"Ca' Vecchia",
    "gn:country_code":"IT",
    "gn:dem":125,
    "gn:feature_class":"P",
    "gn:feature_code":"PPL",
    "gn:name":"Ca' Vecchia",
    "gn:population":48,
    "gn:timezone":"Europe/Rome",
    "iso:country":"IT",
    "wof:name":"Ca' Vecchia",
    "wof:placetype":"locality",
    "wof:population":48
},
  "geometry": {"coordinates":[10.89421,45.66813],"type":"Point"}
}