{
  "type": "Feature",
  "properties": {
    "gn:admin1_code":"5.0",
    "gn:admin2_code":"RE",
    "gn:admin3_code":"35008.0",
    "gn:asciiname":"Case del Cantone",
    "gn:country_code":"IT",
    "gn:dem":27,
    "gn:feature_class":"P",
    "gn:feature_code":"PPL",
    "gn:name":"Case del Cantone",
    "gn:population":0,
    "gn:timezone":"Europe/Rome",
    "iso:country":"IT",
    "wof:name":"Case del Cantone",
    "wof:placetype":"locality"
},
  "geometry": {"coordinates":[10.63333,44.78333],"type":"Point"}
}