{
  "type": "Feature",
  "properties": {
    "gn:admin1_code":"4",
    "gn:admin2_code":"SA",
    "gn:admin3_code":"65109.0",
    "gn:asciiname":"Provitera",
    "gn:country_code":"IT",
    "gn:dem":548,
    "gn:feature_class":"P",
    "gn:feature_code":"PPL",
    "gn:name":"Provitera",
    "gn:population":30,
    "gn:timezone":"Europe/Rome",
    "iso:country":"IT",
    "wof:name":"Provitera",
    "wof:placetype":"locality",
    "wof:population":30
},
  "geometry": {"coordinates":[15.43625,40.2107],"type":"Point"}
}