{
  "type": "Feature",
  "properties": {
    "gn:admin1_code":"20",
    "gn:admin2_code":"VR",
    "gn:admin3_code":"23004.0",
    "gn:asciiname":"Motte Crosaron",
    "gn:country_code":"IT",
    "gn:dem":27,
    "gn:feature_class":"P",
    "gn:feature_code":"PPL",
    "gn:name":"Motte Crosaron",
    "gn:population":68,
    "gn:timezone":"Europe/Rome",
    "iso:country":"IT",
    "wof:name":"Motte Crosaron",
    "wof:placetype":"locality",
    "wof:population":68
},
  "geometry": {"coordinates":[11.30977,45.37041],"type":"Point"}
}