{
  "type": "Feature",
  "properties": {
    "gn:admin1_code":"7",
    "gn:admin2_code":"LT",
    "gn:admin3_code":"59001.0",
    "gn:asciiname":"Riserva Nuova",
    "gn:country_code":"IT",
    "gn:dem":79,
    "gn:feature_class":"P",
    "gn:feature_code":"PPL",
    "gn:name":"Riserva Nuova",
    "gn:population":267,
    "gn:timezone":"Europe/Rome",
    "iso:country":"IT",
    "wof:name":"Riserva Nuova",
    "wof:placetype":"locality",
    "wof:population":267
},
  "geometry": {"coordinates":[12.62497,41.58948],"type":"Point"}
}