{
  "type": "Feature",
  "properties": {
    "gn:admin1_code":"4",
    "gn:admin2_code":"CE",
    "gn:admin3_code":"61073.0",
    "gn:asciiname":"San Domenico",
    "gn:country_code":"IT",
    "gn:dem":109,
    "gn:feature_class":"P",
    "gn:feature_code":"PPL",
    "gn:name":"San Domenico",
    "gn:population":22,
    "gn:timezone":"Europe/Rome",
    "iso:country":"IT",
    "wof:name":"San Domenico",
    "wof:placetype":"locality",
    "wof:population":22
},
  "geometry": {"coordinates":[14.41254,41.24074],"type":"Point"}
}