{
  "type": "Feature",
  "properties": {
    "gn:admin1_code":"11",
    "gn:admin2_code":"IS",
    "gn:admin3_code":"94040.0",
    "gn:asciiname":"Masseria di Rio",
    "gn:country_code":"IT",
    "gn:dem":677,
    "gn:feature_class":"P",
    "gn:feature_code":"PPL",
    "gn:name":"Masseria di Rio",
    "gn:population":13,
    "gn:timezone":"Europe/Rome",
    "iso:country":"IT",
    "wof:name":"Masseria di Rio",
    "wof:placetype":"locality",
    "wof:population":13
},
  "geometry": {"coordinates":[14.37506,41.48751],"type":"Point"}
}