{
  "type": "Feature",
  "properties": {
    "gn:admin1_code":"15",
    "gn:admin2_code":"ME",
    "gn:admin3_code":"83088.0",
    "gn:asciiname":"Santa Domenica",
    "gn:country_code":"IT",
    "gn:dem":700,
    "gn:feature_class":"P",
    "gn:feature_code":"PPL",
    "gn:name":"Santa Domenica",
    "gn:population":52,
    "gn:timezone":"Europe/Rome",
    "iso:country":"IT",
    "wof:name":"Santa Domenica",
    "wof:placetype":"locality",
    "wof:population":52
},
  "geometry": {"coordinates":[14.898,38.1169],"type":"Point"}
}