{
  "type": "Feature",
  "properties": {
    "gn:admin1_code":"5",
    "gn:admin2_code":"PR",
    "gn:admin3_code":"34024.0",
    "gn:asciiname":"Le Rette",
    "gn:country_code":"IT",
    "gn:dem":339,
    "gn:feature_class":"P",
    "gn:feature_code":"PPL",
    "gn:name":"Le Rette",
    "gn:population":29,
    "gn:timezone":"Europe/Rome",
    "iso:country":"IT",
    "wof:name":"Le Rette",
    "wof:placetype":"locality",
    "wof:population":29
},
  "geometry": {"coordinates":[10.36577,44.55008],"type":"Point"}
}