{
  "type": "Feature",
  "properties": {
    "gn:admin1_code":"12.0",
    "gn:admin2_code":"CN",
    "gn:admin3_code":"4027.0",
    "gn:asciiname":"Bossolaschetto",
    "gn:country_code":"IT",
    "gn:dem":758,
    "gn:feature_class":"P",
    "gn:feature_code":"PPL",
    "gn:name":"Bossolaschetto",
    "gn:population":18,
    "gn:timezone":"Europe/Rome",
    "iso:country":"IT",
    "wof:name":"Bossolaschetto",
    "wof:placetype":"locality",
    "wof:population":18
},
  "geometry": {"coordinates":[8.06724,44.53915],"type":"Point"}
}