{
  "type": "Feature",
  "properties": {
    "gn:admin1_code":"20",
    "gn:admin2_code":"PD",
    "gn:admin3_code":"28004.0",
    "gn:asciiname":"Ca' Matte",
    "gn:country_code":"IT",
    "gn:dem":0,
    "gn:feature_class":"P",
    "gn:feature_code":"PPL",
    "gn:name":"Ca' Matte",
    "gn:population":203,
    "gn:timezone":"Europe/Rome",
    "iso:country":"IT",
    "wof:name":"Ca' Matte",
    "wof:placetype":"locality",
    "wof:population":203
},
  "geometry": {"coordinates":[11.91233,45.13936],"type":"Point"}
}