{
  "type": "Feature",
  "properties": {
    "gn:admin1_code":"5.0",
    "gn:admin2_code":"RA",
    "gn:asciiname":"La Valle",
    "gn:country_code":"IT",
    "gn:dem":512,
    "gn:feature_class":"P",
    "gn:feature_code":"PPL",
    "gn:name":"La Valle",
    "gn:population":0,
    "gn:timezone":"Europe/Rome",
    "iso:country":"IT",
    "wof:name":"La Valle",
    "wof:placetype":"locality"
},
  "geometry": {"coordinates":[11.61667,44.15],"type":"Point"}
}