{
  "type": "Feature",
  "properties": {
    "gn:admin1_code":"5.0",
    "gn:admin2_code":"PR",
    "gn:admin3_code":"34009.0",
    "gn:asciiname":"La Fattoria di Vigheffio",
    "gn:country_code":"IT",
    "gn:dem":90,
    "gn:feature_class":"P",
    "gn:feature_code":"PPL",
    "gn:name":"La Fattoria di Vigheffio",
    "gn:population":15,
    "gn:timezone":"Europe/Rome",
    "iso:country":"IT",
    "wof:name":"La Fattoria di Vigheffio",
    "wof:placetype":"locality",
    "wof:population":15
},
  "geometry": {"coordinates":[10.28333,44.76667],"type":"Point"}
}