{
  "type": "Feature",
  "properties": {
    "gn:admin1_code":"5",
    "gn:admin2_code":"MO",
    "gn:admin3_code":"36019.0",
    "gn:asciiname":"La Siberia",
    "gn:country_code":"IT",
    "gn:dem":170,
    "gn:feature_class":"P",
    "gn:feature_code":"PPL",
    "gn:name":"La Siberia",
    "gn:population":11,
    "gn:timezone":"Europe/Rome",
    "iso:country":"IT",
    "wof:name":"La Siberia",
    "wof:placetype":"locality",
    "wof:population":11
},
  "geometry": {"coordinates":[10.89287,44.50922],"type":"Point"}
}