{
  "type": "Feature",
  "properties": {
    "gn:admin1_code":"5",
    "gn:admin2_code":"MO",
    "gn:admin3_code":"36019.0",
    "gn:asciiname":"La Siberia",
    "gn:country_code":"IT",
    "gn:dem":170,
    "gn:feature_class":"P",
    "gn:feature_code":"PPL",
    "gn:name":"La Siberia",
    "gn:population":11,
    "gn:timezone":"Europe/Rome",
    "iso:country":"IT",
    "name:cat_x_preferred":[
        "La Siberia"
    ],
    "name:epo_x_preferred":[
        "La Siberia"
    ],
    "name:ext_x_preferred":[
        "La Siberia"
    ],
    "name:kaz_x_preferred":[
        "\u041b\u0430-\u0421\u0438\u0431\u0435\u0440\u0438\u044f"
    ],
    "name:pol_x_preferred":[
        "La Siberia"
    ],
    "name:por_x_preferred":[
        "La Siberia"
    ],
    "name:rus_x_preferred":[
        "\u041b\u0430-\u0421\u0438\u0431\u0435\u0440\u0438\u044f"
    ],
    "name:spa_x_preferred":[
        "La Siberia Extreme\u00f1a"
    ],
    "name:urd_x_preferred":[
        "\u0644\u0627 \u0633\u0627\u0626\u0628\u0631\u06cc\u0627"
    ],
    "name:uzb_x_preferred":[
        "La Siberia"
    ],
    "wof:name":"La Siberia",
    "wof:placetype":"locality",
    "wof:population":11
},
  "geometry": {"coordinates":[10.89287,44.50922],"type":"Point"}
}