{
  "type": "Feature",
  "properties": {
    "gn:admin1_code":"5",
    "gn:admin2_code":"PR",
    "gn:admin3_code":"34028.0",
    "gn:asciiname":"Ceriato Lobbia",
    "gn:country_code":"IT",
    "gn:dem":527,
    "gn:feature_class":"P",
    "gn:feature_code":"PPL",
    "gn:name":"Ceriato Lobbia",
    "gn:population":12,
    "gn:timezone":"Europe/Rome",
    "iso:country":"IT",
    "wof:name":"Ceriato Lobbia",
    "wof:placetype":"locality",
    "wof:population":12
},
  "geometry": {"coordinates":[9.89336,44.733],"type":"Point"}
}