{
  "type": "Feature",
  "properties": {
    "gn:admin1_code":"20",
    "gn:admin2_code":"VR",
    "gn:admin3_code":"23018.0",
    "gn:asciiname":"Braga",
    "gn:country_code":"IT",
    "gn:dem":588,
    "gn:feature_class":"P",
    "gn:feature_code":"PPL",
    "gn:name":"Braga",
    "gn:population":74,
    "gn:timezone":"Europe/Rome",
    "iso:country":"IT",
    "wof:name":"Braga",
    "wof:placetype":"locality",
    "wof:population":74
},
  "geometry": {"coordinates":[10.82519,45.62904],"type":"Point"}
}