{
  "type": "Feature",
  "properties": {
    "gn:admin1_code":"3.0",
    "gn:admin2_code":"RC",
    "gn:admin3_code":"80022.0",
    "gn:asciiname":"Contrada Rinazza",
    "gn:country_code":"IT",
    "gn:dem":995,
    "gn:feature_class":"P",
    "gn:feature_code":"PPL",
    "gn:name":"Contrada Rinazza",
    "gn:population":52,
    "gn:timezone":"Europe/Rome",
    "iso:country":"IT",
    "wof:name":"Contrada Rinazza",
    "wof:placetype":"locality",
    "wof:population":52
},
  "geometry": {"coordinates":[15.77789,38.07176],"type":"Point"}
}