{
  "type": "Feature",
  "properties": {
    "gn:admin1_code":"16",
    "gn:admin2_code":"LU",
    "gn:admin3_code":"46005.0",
    "gn:asciiname":"Acquaviva",
    "gn:country_code":"IT",
    "gn:dem":52,
    "gn:feature_class":"P",
    "gn:feature_code":"PPL",
    "gn:name":"Acquaviva",
    "gn:population":23,
    "gn:timezone":"Europe/Rome",
    "iso:country":"IT",
    "name:cat_x_preferred":[
        "Acquaviva"
    ],
    "name:ceb_x_preferred":[
        "Acquaviva"
    ],
    "name:deu_x_preferred":[
        "Acquaviva"
    ],
    "name:fra_x_preferred":[
        "Acquaviva"
    ],
    "name:ind_x_preferred":[
        "Acquaviva"
    ],
    "name:ita_x_preferred":[
        "Acquaviva"
    ],
    "name:nld_x_preferred":[
        "Acquaviva"
    ],
    "name:rus_x_preferred":[
        "\u0410\u043a\u0432\u0430\u0432\u0438\u0432\u0430"
    ],
    "name:srp_x_preferred":[
        "Akvaviva"
    ],
    "name:swe_x_preferred":[
        "Acquaviva"
    ],
    "wof:name":"Acquaviva",
    "wof:placetype":"locality",
    "wof:population":23
},
  "geometry": {"coordinates":[10.31098,43.92742],"type":"Point"}
}