{
  "type": "Feature",
  "properties": {
    "gn:admin1_code":"3",
    "gn:admin2_code":"RC",
    "gn:admin3_code":"80063.0",
    "gn:asciiname":"Case Catania",
    "gn:country_code":"IT",
    "gn:dem":391,
    "gn:feature_class":"P",
    "gn:feature_code":"PPL",
    "gn:name":"Case Catania",
    "gn:population":31,
    "gn:timezone":"Europe/Rome",
    "iso:country":"IT",
    "wof:name":"Case Catania",
    "wof:placetype":"locality",
    "wof:population":31
},
  "geometry": {"coordinates":[15.68921,38.02123],"type":"Point"}
}