{
  "type": "Feature",
  "properties": {
    "gn:admin1_code":"9.0",
    "gn:admin2_code":"CO",
    "gn:admin3_code":"13211.0",
    "gn:asciiname":"Manno",
    "gn:country_code":"IT",
    "gn:dem":839,
    "gn:feature_class":"P",
    "gn:feature_code":"PPLL",
    "gn:name":"Manno",
    "gn:population":1,
    "gn:timezone":"Europe/Rome",
    "iso:country":"IT",
    "name:als_x_preferred":[
        "Manno"
    ],
    "name:ceb_x_preferred":[
        "Manno"
    ],
    "name:deu_x_preferred":[
        "Manno"
    ],
    "name:epo_x_preferred":[
        "Manno"
    ],
    "name:eus_x_preferred":[
        "Manno"
    ],
    "name:fra_x_preferred":[
        "Manno"
    ],
    "name:ita_x_preferred":[
        "Manno"
    ],
    "name:lmo_x_preferred":[
        "Mann"
    ],
    "name:msa_x_preferred":[
        "Manno"
    ],
    "name:nld_x_preferred":[
        "Manno"
    ],
    "name:nno_x_preferred":[
        "Manno"
    ],
    "name:por_x_preferred":[
        "Manno"
    ],
    "name:roh_x_preferred":[
        "Manno"
    ],
    "name:spa_x_preferred":[
        "Manno"
    ],
    "name:sqi_x_preferred":[
        "Manno"
    ],
    "name:swe_x_preferred":[
        "Manno"
    ],
    "name:vol_x_preferred":[
        "Manno"
    ],
    "name:war_x_preferred":[
        "Manno"
    ],
    "wof:name":"Manno",
    "wof:placetype":"locality",
    "wof:population":1
},
  "geometry": {"coordinates":[9.09895,45.91691],"type":"Point"}
}