{
  "type": "Feature",
  "properties": {
    "gn:admin1_code":"9",
    "gn:admin2_code":"PV",
    "gn:admin3_code":"18150.0",
    "gn:asciiname":"Bonate",
    "gn:country_code":"IT",
    "gn:dem":86,
    "gn:feature_class":"P",
    "gn:feature_code":"PPL",
    "gn:name":"Bonate",
    "gn:population":40,
    "gn:timezone":"Europe/Rome",
    "iso:country":"IT",
    "name:ita_x_preferred":[
        "Bonate"
    ],
    "name:lmo_x_preferred":[
        "Bun\u00e0t"
    ],
    "name:pms_x_preferred":[
        "Bonate"
    ],
    "wof:name":"Bonate",
    "wof:placetype":"locality",
    "wof:population":40
},
  "geometry": {"coordinates":[9.20848,45.29327],"type":"Point"}
}