{
  "type": "Feature",
  "properties": {
    "gn:admin1_code":"12",
    "gn:admin2_code":"TO",
    "gn:admin3_code":"1097.0",
    "gn:asciiname":"Villar",
    "gn:country_code":"IT",
    "gn:dem":413,
    "gn:feature_class":"P",
    "gn:feature_code":"PPL",
    "gn:name":"Villar",
    "gn:population":94,
    "gn:timezone":"Europe/Rome",
    "iso:country":"IT",
    "wof:name":"Villar",
    "wof:placetype":"locality",
    "wof:population":94
},
  "geometry": {"coordinates":[7.37179,44.96294],"type":"Point"}
}