{
  "type": "Feature",
  "properties": {
    "gn:admin1_code":"9",
    "gn:admin2_code":"BG",
    "gn:admin3_code":"16183.0",
    "gn:asciiname":"Cascina Naviglio",
    "gn:country_code":"IT",
    "gn:dem":113,
    "gn:feature_class":"P",
    "gn:feature_code":"PPL",
    "gn:name":"Cascina Naviglio",
    "gn:population":30,
    "gn:timezone":"Europe/Rome",
    "iso:country":"IT",
    "wof:name":"Cascina Naviglio",
    "wof:placetype":"locality",
    "wof:population":30
},
  "geometry": {"coordinates":[9.73091,45.50546],"type":"Point"}
}