{
  "type": "Feature",
  "properties": {
    "gn:admin1_code":"8.0",
    "gn:admin2_code":"GE",
    "gn:admin3_code":"10059.0",
    "gn:asciiname":"San Bernardo",
    "gn:country_code":"IT",
    "gn:dem":165,
    "gn:elevation":"186.0",
    "gn:feature_class":"P",
    "gn:feature_code":"PPL",
    "gn:name":"San Bernardo",
    "gn:population":183,
    "gn:timezone":"Europe/Rome",
    "iso:country":"IT",
    "wof:name":"San Bernardo",
    "wof:placetype":"locality",
    "wof:population":183
},
  "geometry": {"coordinates":[9.41009,44.2869],"type":"Point"}
}