{
  "type": "Feature",
  "properties": {
    "gn:admin1_code":"8.0",
    "gn:admin2_code":"GE",
    "gn:admin3_code":"10059.0",
    "gn:asciiname":"San Bernardo",
    "gn:country_code":"IT",
    "gn:dem":165,
    "gn:elevation":"186.0",
    "gn:feature_class":"P",
    "gn:feature_code":"PPL",
    "gn:name":"San Bernardo",
    "gn:population":183,
    "gn:timezone":"Europe/Rome",
    "iso:country":"IT",
    "name:ceb_x_preferred":[
        "San Bernardo"
    ],
    "name:deu_x_preferred":[
        "San Bernardo"
    ],
    "name:epo_x_preferred":[
        "San Bernardo"
    ],
    "name:fin_x_preferred":[
        "San Bernardo"
    ],
    "name:fra_x_preferred":[
        "San Bernardo"
    ],
    "name:ita_x_preferred":[
        "San Bernardo"
    ],
    "name:nld_x_preferred":[
        "San Bernardo"
    ],
    "name:pol_x_preferred":[
        "San Bernardo"
    ],
    "name:por_x_preferred":[
        "San Bernardo"
    ],
    "name:ron_x_preferred":[
        "San Bernardo"
    ],
    "name:rus_x_preferred":[
        "\u0421\u0430\u043d-\u0411\u0435\u0440\u043d\u0430\u0440\u0434\u043e"
    ],
    "name:sco_x_preferred":[
        "San Bernardo"
    ],
    "name:spa_x_preferred":[
        "San Bernardo"
    ],
    "name:srp_x_preferred":[
        "San Bernardo"
    ],
    "name:swe_x_preferred":[
        "San Bernardo"
    ],
    "name:tgl_x_preferred":[
        "San Bernardo"
    ],
    "name:vie_x_preferred":[
        "San Bernardo"
    ],
    "name:war_x_preferred":[
        "San Bernardo"
    ],
    "wof:name":"San Bernardo",
    "wof:placetype":"locality",
    "wof:population":183
},
  "geometry": {"coordinates":[9.41009,44.2869],"type":"Point"}
}