{
  "type": "Feature",
  "properties": {
    "gn:admin1_code":"20",
    "gn:admin2_code":"PD",
    "gn:admin3_code":"28101.0",
    "gn:asciiname":"Del Morto",
    "gn:country_code":"IT",
    "gn:dem":28,
    "gn:feature_class":"P",
    "gn:feature_code":"PPL",
    "gn:name":"Del Morto",
    "gn:population":24,
    "gn:timezone":"Europe/Rome",
    "iso:country":"IT",
    "wof:name":"Del Morto",
    "wof:placetype":"locality",
    "wof:population":24
},
  "geometry": {"coordinates":[11.8706,45.59251],"type":"Point"}
}