{
  "type": "Feature",
  "properties": {
    "gn:admin1_code":"1.0",
    "gn:admin2_code":"AQ",
    "gn:admin3_code":"66095.0",
    "gn:asciiname":"Madonna della Strada",
    "gn:country_code":"IT",
    "gn:dem":720,
    "gn:feature_class":"P",
    "gn:feature_code":"PPL",
    "gn:name":"Madonna della Strada",
    "gn:population":303,
    "gn:timezone":"Europe/Rome",
    "iso:country":"IT",
    "wof:name":"Madonna della Strada",
    "wof:placetype":"locality",
    "wof:population":303
},
  "geometry": {"coordinates":[13.2587,42.34562],"type":"Point"}
}