{
  "type": "Feature",
  "properties": {
    "gn:admin1_code":"1.0",
    "gn:admin2_code":"AQ",
    "gn:admin3_code":"66095.0",
    "gn:asciiname":"Madonna della Strada",
    "gn:country_code":"IT",
    "gn:dem":720,
    "gn:feature_class":"P",
    "gn:feature_code":"PPL",
    "gn:name":"Madonna della Strada",
    "gn:population":303,
    "gn:timezone":"Europe/Rome",
    "iso:country":"IT",
    "name:ceb_x_preferred":[
        "Madonna della Strada"
    ],
    "name:srp_x_preferred":[
        "\u041c\u0430\u0434\u043e\u043d\u0430 \u0434\u0435\u043b\u0430 \u0421\u0442\u0440\u0430\u0434\u0430"
    ],
    "wof:name":"Madonna della Strada",
    "wof:placetype":"locality",
    "wof:population":303
},
  "geometry": {"coordinates":[13.2587,42.34562],"type":"Point"}
}