{
  "type": "Feature",
  "properties": {
    "gn:admin1_code":"9",
    "gn:admin2_code":"BS",
    "gn:admin3_code":"17066.0",
    "gn:asciiname":"Fenile Lombardo",
    "gn:country_code":"IT",
    "gn:dem":76,
    "gn:feature_class":"P",
    "gn:feature_code":"PPL",
    "gn:name":"Fenile Lombardo",
    "gn:population":20,
    "gn:timezone":"Europe/Rome",
    "iso:country":"IT",
    "wof:name":"Fenile Lombardo",
    "wof:placetype":"locality",
    "wof:population":20
},
  "geometry": {"coordinates":[10.08668,45.39913],"type":"Point"}
}