{
  "type": "Feature",
  "properties": {
    "gn:admin1_code":"5.0",
    "gn:admin2_code":"PR",
    "gn:admin3_code":"34022.0",
    "gn:asciiname":"Casarola",
    "gn:country_code":"IT",
    "gn:dem":992,
    "gn:elevation":"996.0",
    "gn:feature_class":"P",
    "gn:feature_code":"PPL",
    "gn:name":"Casarola",
    "gn:population":78,
    "gn:timezone":"Europe/Rome",
    "iso:country":"IT",
    "wof:name":"Casarola",
    "wof:placetype":"locality",
    "wof:population":78
},
  "geometry": {"coordinates":[10.09714,44.42429],"type":"Point"}
}