{
  "type": "Feature",
  "properties": {
    "gn:admin1_code":"12",
    "gn:admin2_code":"TO",
    "gn:admin3_code":"1098.0",
    "gn:asciiname":"Vena",
    "gn:country_code":"IT",
    "gn:dem":795,
    "gn:feature_class":"P",
    "gn:feature_code":"PPL",
    "gn:name":"Vena",
    "gn:population":25,
    "gn:timezone":"Europe/Rome",
    "iso:country":"IT",
    "name:arg_x_preferred":[
        "Vena"
    ],
    "name:ceb_x_preferred":[
        "Vena"
    ],
    "name:deu_x_preferred":[
        "Vena"
    ],
    "name:fin_x_preferred":[
        "Vena"
    ],
    "name:fra_x_preferred":[
        "Vena"
    ],
    "name:ita_x_preferred":[
        "Vena"
    ],
    "name:nld_x_preferred":[
        "Vena"
    ],
    "name:spa_x_preferred":[
        "Vena"
    ],
    "name:srp_x_preferred":[
        "\u0412\u0435\u043d\u0430"
    ],
    "name:swe_x_preferred":[
        "Vena"
    ],
    "name:uzb_x_preferred":[
        "Vena"
    ],
    "wof:name":"Vena",
    "wof:placetype":"locality",
    "wof:population":25
},
  "geometry": {"coordinates":[7.60264,45.40874],"type":"Point"}
}