{
  "type": "Feature",
  "properties": {
    "gn:admin1_code":"12",
    "gn:admin2_code":"TO",
    "gn:admin3_code":"1098.0",
    "gn:asciiname":"Vena",
    "gn:country_code":"IT",
    "gn:dem":795,
    "gn:feature_class":"P",
    "gn:feature_code":"PPL",
    "gn:name":"Vena",
    "gn:population":25,
    "gn:timezone":"Europe/Rome",
    "iso:country":"IT",
    "wof:name":"Vena",
    "wof:placetype":"locality",
    "wof:population":25
},
  "geometry": {"coordinates":[7.60264,45.40874],"type":"Point"}
}