{
  "type": "Feature",
  "properties": {
    "gn:admin1_code":"9",
    "gn:admin2_code":"LC",
    "gn:admin3_code":"97026.0",
    "gn:asciiname":"Canile",
    "gn:country_code":"IT",
    "gn:dem":260,
    "gn:feature_class":"P",
    "gn:feature_code":"PPL",
    "gn:name":"Canile",
    "gn:population":46,
    "gn:timezone":"Europe/Rome",
    "iso:country":"IT",
    "wof:name":"Canile",
    "wof:placetype":"locality",
    "wof:population":46
},
  "geometry": {"coordinates":[9.26618,45.77097],"type":"Point"}
}