{
  "type": "Feature",
  "properties": {
    "gn:admin1_code":"20",
    "gn:admin2_code":"PD",
    "gn:admin3_code":"28021.0",
    "gn:asciiname":"Antico",
    "gn:country_code":"IT",
    "gn:dem":-1,
    "gn:feature_class":"P",
    "gn:feature_code":"PPL",
    "gn:name":"Antico",
    "gn:population":21,
    "gn:timezone":"Europe/Rome",
    "iso:country":"IT",
    "name:fra_x_preferred":[
        "Antico"
    ],
    "name:ita_x_preferred":[
        "Antico"
    ],
    "name:srp_x_preferred":[
        "Antico"
    ],
    "wof:name":"Antico",
    "wof:placetype":"locality",
    "wof:population":21
},
  "geometry": {"coordinates":[11.96273,45.21072],"type":"Point"}
}