{
  "type": "Feature",
  "properties": {
    "gn:admin1_code":"5.0",
    "gn:admin2_code":"BO",
    "gn:admin3_code":"37022.0",
    "gn:asciiname":"Vizzarete",
    "gn:country_code":"IT",
    "gn:dem":708,
    "gn:feature_class":"P",
    "gn:feature_code":"PPL",
    "gn:name":"Vizzarete",
    "gn:population":0,
    "gn:timezone":"Europe/Rome",
    "iso:country":"IT",
    "wof:name":"Vizzarete",
    "wof:placetype":"locality"
},
  "geometry": {"coordinates":[11.21667,44.11667],"type":"Point"}
}