{
  "type": "Feature",
  "properties": {
    "gn:admin1_code":"20.0",
    "gn:admin2_code":"VE",
    "gn:admin3_code":"27025.0",
    "gn:asciiname":"Millepertiche",
    "gn:country_code":"IT",
    "gn:dem":-2,
    "gn:elevation":"1.0",
    "gn:feature_class":"P",
    "gn:feature_code":"PPL",
    "gn:name":"Millepertiche",
    "gn:population":487,
    "gn:timezone":"Europe/Rome",
    "iso:country":"IT",
    "wof:name":"Millepertiche",
    "wof:placetype":"locality",
    "wof:population":487
},
  "geometry": {"coordinates":[12.50609,45.59259],"type":"Point"}
}