{
  "type": "Feature",
  "properties": {
    "gn:admin1_code":"12",
    "gn:admin2_code":"AT",
    "gn:admin3_code":"5001.0",
    "gn:asciiname":"Goretta",
    "gn:country_code":"IT",
    "gn:dem":183,
    "gn:feature_class":"P",
    "gn:feature_code":"PPL",
    "gn:name":"Goretta",
    "gn:population":22,
    "gn:timezone":"Europe/Rome",
    "iso:country":"IT",
    "wof:name":"Goretta",
    "wof:placetype":"locality",
    "wof:population":22
},
  "geometry": {"coordinates":[8.23032,44.79767],"type":"Point"}
}