{
  "type": "Feature",
  "properties": {
    "gn:admin1_code":"6.0",
    "gn:admin2_code":"PN",
    "gn:admin3_code":"93022.0",
    "gn:asciiname":"Nave",
    "gn:country_code":"IT",
    "gn:dem":27,
    "gn:elevation":"29.0",
    "gn:feature_class":"P",
    "gn:feature_code":"PPLL",
    "gn:name":"Nave",
    "gn:population":818,
    "gn:timezone":"Europe/Rome",
    "iso:country":"IT",
    "wof:name":"Nave",
    "wof:placetype":"locality",
    "wof:population":818
},
  "geometry": {"coordinates":[12.5027,45.97901],"type":"Point"}
}