{
  "type": "Feature",
  "properties": {
    "gn:admin1_code":"6.0",
    "gn:admin2_code":"PN",
    "gn:admin3_code":"93022.0",
    "gn:asciiname":"Nave",
    "gn:country_code":"IT",
    "gn:dem":27,
    "gn:elevation":"29.0",
    "gn:feature_class":"P",
    "gn:feature_code":"PPLL",
    "gn:name":"Nave",
    "gn:population":818,
    "gn:timezone":"Europe/Rome",
    "iso:country":"IT",
    "name:ara_x_preferred":[
        "\u0635\u062d\u0646"
    ],
    "name:arg_x_preferred":[
        "Nau"
    ],
    "name:bel_x_preferred":[
        "\u041d\u0435\u0444"
    ],
    "name:bre_x_preferred":[
        "Nev"
    ],
    "name:bul_x_preferred":[
        "\u041d\u0435\u0444"
    ],
    "name:cat_x_preferred":[
        "Nau"
    ],
    "name:ces_x_preferred":[
        "Lo\u010f"
    ],
    "name:dan_x_preferred":[
        "Kirkeskib"
    ],
    "name:deu_x_preferred":[
        "Kirchenschiff"
    ],
    "name:ell_x_preferred":[
        "\u039a\u03c5\u03c1\u03af\u03c9\u03c2 \u03bd\u03b1\u03cc\u03c2"
    ],
    "name:epo_x_preferred":[
        "Navo"
    ],
    "name:est_x_preferred":[
        "L\u00f6\u00f6v"
    ],
    "name:eus_x_preferred":[
        "Habearte"
    ],
    "name:fas_x_preferred":[
        "\u0634\u0628\u0633\u062a\u0627\u0646"
    ],
    "name:fin_x_preferred":[
        "Laiva"
    ],
    "name:fra_x_preferred":[
        "Nef"
    ],
    "name:fry_x_preferred":[
        "Skip"
    ],
    "name:gle_x_preferred":[
        "Corp eaglaise"
    ],
    "name:glg_x_preferred":[
        "Nave"
    ],
    "name:heb_x_preferred":[
        "\u05e1\u05e4\u05d9\u05e0\u05d4"
    ],
    "name:hrv_x_preferred":[
        "Brod"
    ],
    "name:hun_x_preferred":[
        "F\u0151haj\u00f3"
    ],
    "name:hye_x_preferred":[
        "\u0546\u0561\u057e"
    ],
    "name:ido_x_preferred":[
        "Navo"
    ],
    "name:ind_x_preferred":[
        "Panti umat"
    ],
    "name:ita_x_preferred":[
        "Navata"
    ],
    "name:lav_x_preferred":[
        "Joms"
    ],
    "name:lim_x_preferred":[
        "Sjeep"
    ],
    "name:lit_x_preferred":[
        "Nava"
    ],
    "name:nld_x_preferred":[
        "Schip"
    ],
    "name:nno_x_preferred":[
        "Kyrkjeskip"
    ],
    "name:nor_x_preferred":[
        "Midtskip"
    ],
    "name:pol_x_preferred":[
        "Nawa"
    ],
    "name:por_x_preferred":[
        "Nave"
    ],
    "name:ron_x_preferred":[
        "Nav\u0103"
    ],
    "name:rue_x_preferred":[
        "\u041d\u0430\u0432\u0430"
    ],
    "name:rus_x_preferred":[
        "\u041d\u0435\u0444"
    ],
    "name:slk_x_preferred":[
        "Lo\u010f"
    ],
    "name:slv_x_preferred":[
        "Cerkvena ladja"
    ],
    "name:spa_x_preferred":[
        "Nave"
    ],
    "name:sqi_x_preferred":[
        "Nefi"
    ],
    "name:srp_x_preferred":[
        "\u0411\u0440\u043e\u0434"
    ],
    "name:swe_x_preferred":[
        "Skepp"
    ],
    "name:tha_x_preferred":[
        "\u0e1a\u0e23\u0e34\u0e40\u0e27\u0e13\u0e01\u0e25\u0e32\u0e07\u0e42\u0e1a\u0e2a\u0e16\u0e4c"
    ],
    "name:tur_x_preferred":[
        "Nef"
    ],
    "name:ukr_x_preferred":[
        "\u041d\u0430\u0432\u0430"
    ],
    "name:vls_x_preferred":[
        "Middnbeuke"
    ],
    "wof:name":"Nave",
    "wof:placetype":"locality",
    "wof:population":818
},
  "geometry": {"coordinates":[12.5027,45.97901],"type":"Point"}
}