{
  "type": "Feature",
  "properties": {
    "gn:admin1_code":"15",
    "gn:admin2_code":"ME",
    "gn:admin3_code":"83016.0",
    "gn:asciiname":"Caruso",
    "gn:country_code":"IT",
    "gn:dem":136,
    "gn:feature_class":"P",
    "gn:feature_code":"PPL",
    "gn:name":"Caruso",
    "gn:population":44,
    "gn:timezone":"Europe/Rome",
    "iso:country":"IT",
    "name:bul_x_preferred":[
        "\u041a\u0430\u0440\u0443\u0437\u043e"
    ],
    "name:cat_x_preferred":[
        "Caruso"
    ],
    "name:ces_x_preferred":[
        "Caruso"
    ],
    "name:deu_x_preferred":[
        "Caruso"
    ],
    "name:fas_x_preferred":[
        "\u06a9\u0627\u0631\u0648\u0633\u0648"
    ],
    "name:fin_x_preferred":[
        "Caruso"
    ],
    "name:fra_x_preferred":[
        "Caruso"
    ],
    "name:heb_x_preferred":[
        "\u05e7\u05e8\u05d5\u05d6\u05d5"
    ],
    "name:hun_x_preferred":[
        "Caruso"
    ],
    "name:ita_x_preferred":[
        "Caruso"
    ],
    "name:nld_x_preferred":[
        "Caruso"
    ],
    "name:pol_x_preferred":[
        "Caruso"
    ],
    "name:por_x_preferred":[
        "Caruso"
    ],
    "name:rus_x_preferred":[
        "\u041a\u0430\u0440\u0443\u0437\u043e"
    ],
    "name:spa_x_preferred":[
        "Caruso"
    ],
    "name:srp_x_preferred":[
        "\u041a\u0430\u0440\u0443\u0437\u043e"
    ],
    "wof:name":"Caruso",
    "wof:placetype":"locality",
    "wof:population":44
},
  "geometry": {"coordinates":[15.18992,38.10649],"type":"Point"}
}