{
  "type": "Feature",
  "properties": {
    "gn:admin1_code":"15",
    "gn:admin2_code":"ME",
    "gn:admin3_code":"83016.0",
    "gn:asciiname":"Caruso",
    "gn:country_code":"IT",
    "gn:dem":136,
    "gn:feature_class":"P",
    "gn:feature_code":"PPL",
    "gn:name":"Caruso",
    "gn:population":44,
    "gn:timezone":"Europe/Rome",
    "iso:country":"IT",
    "wof:name":"Caruso",
    "wof:placetype":"locality",
    "wof:population":44
},
  "geometry": {"coordinates":[15.18992,38.10649],"type":"Point"}
}