{
  "type": "Feature",
  "properties": {
    "gn:admin1_code":"20",
    "gn:admin2_code":"TV",
    "gn:admin3_code":"26082.0",
    "gn:asciiname":"Case Rigato",
    "gn:country_code":"IT",
    "gn:dem":56,
    "gn:feature_class":"P",
    "gn:feature_code":"PPL",
    "gn:name":"Case Rigato",
    "gn:population":56,
    "gn:timezone":"Europe/Rome",
    "iso:country":"IT",
    "wof:name":"Case Rigato",
    "wof:placetype":"locality",
    "wof:population":56
},
  "geometry": {"coordinates":[12.25417,45.79149],"type":"Point"}
}