{
  "type": "Feature",
  "properties": {
    "gn:admin1_code":"7",
    "gn:admin2_code":"FR",
    "gn:admin3_code":"60010.0",
    "gn:asciiname":"De Gasperi-Panaccio",
    "gn:country_code":"IT",
    "gn:dem":426,
    "gn:feature_class":"P",
    "gn:feature_code":"PPL",
    "gn:name":"De Gasperi-Panaccio",
    "gn:population":244,
    "gn:timezone":"Europe/Rome",
    "iso:country":"IT",
    "wof:name":"De Gasperi-Panaccio",
    "wof:placetype":"locality",
    "wof:population":244
},
  "geometry": {"coordinates":[13.60909,41.6394],"type":"Point"}
}