{
  "type": "Feature",
  "properties": {
    "gn:admin1_code":"20",
    "gn:admin2_code":"RO",
    "gn:admin3_code":"29043.0",
    "gn:asciiname":"Arginello",
    "gn:country_code":"IT",
    "gn:dem":5,
    "gn:feature_class":"P",
    "gn:feature_code":"PPL",
    "gn:name":"Arginello",
    "gn:population":37,
    "gn:timezone":"Europe/Rome",
    "iso:country":"IT",
    "wof:name":"Arginello",
    "wof:placetype":"locality",
    "wof:population":37
},
  "geometry": {"coordinates":[11.57223,45.01026],"type":"Point"}
}