{
  "type": "Feature",
  "properties": {
    "gn:admin1_code":"12.0",
    "gn:admin2_code":"AL",
    "gn:admin3_code":"6151.0",
    "gn:asciiname":"Cascina Viscarda",
    "gn:country_code":"IT",
    "gn:dem":102,
    "gn:feature_class":"P",
    "gn:feature_code":"PPL",
    "gn:name":"Cascina Viscarda",
    "gn:population":18,
    "gn:timezone":"Europe/Rome",
    "iso:country":"IT",
    "wof:name":"Cascina Viscarda",
    "wof:placetype":"locality",
    "wof:population":18
},
  "geometry": {"coordinates":[8.81636,44.93272],"type":"Point"}
}