{
  "type": "Feature",
  "properties": {
    "gn:admin1_code":"16",
    "gn:admin2_code":"AR",
    "gn:admin3_code":"51025.0",
    "gn:asciiname":"Ponte Esse",
    "gn:country_code":"IT",
    "gn:dem":264,
    "gn:feature_class":"P",
    "gn:feature_code":"PPL",
    "gn:name":"Ponte Esse",
    "gn:population":231,
    "gn:timezone":"Europe/Rome",
    "iso:country":"IT",
    "wof:name":"Ponte Esse",
    "wof:placetype":"locality",
    "wof:population":231
},
  "geometry": {"coordinates":[11.73816,43.33713],"type":"Point"}
}