{
  "type": "Feature",
  "properties": {
    "gn:admin1_code":"9",
    "gn:admin2_code":"VA",
    "gn:admin3_code":"12029.0",
    "gn:asciiname":"Villaggio Benedetto Croce",
    "gn:country_code":"IT",
    "gn:dem":272,
    "gn:feature_class":"P",
    "gn:feature_code":"PPL",
    "gn:name":"Villaggio Benedetto Croce",
    "gn:population":26,
    "gn:timezone":"Europe/Rome",
    "iso:country":"IT",
    "wof:name":"Villaggio Benedetto Croce",
    "wof:placetype":"locality",
    "wof:population":26
},
  "geometry": {"coordinates":[8.85116,45.68216],"type":"Point"}
}