{
  "type": "Feature",
  "properties": {
    "gn:admin1_code":"5",
    "gn:admin2_code":"PC",
    "gn:admin3_code":"33012.0",
    "gn:asciiname":"Doppi",
    "gn:country_code":"IT",
    "gn:dem":95,
    "gn:feature_class":"P",
    "gn:feature_code":"PPL",
    "gn:name":"Doppi",
    "gn:population":18,
    "gn:timezone":"Europe/Rome",
    "iso:country":"IT",
    "wof:name":"Doppi",
    "wof:placetype":"locality",
    "wof:population":18
},
  "geometry": {"coordinates":[9.86541,44.90233],"type":"Point"}
}