{
  "type": "Feature",
  "properties": {
    "gn:admin1_code":"12",
    "gn:admin2_code":"CN",
    "gn:admin3_code":"4054.0",
    "gn:asciiname":"Stevagni",
    "gn:country_code":"IT",
    "gn:dem":762,
    "gn:feature_class":"P",
    "gn:feature_code":"PPLL",
    "gn:name":"Stevagni",
    "gn:population":8,
    "gn:timezone":"Europe/Rome",
    "iso:country":"IT",
    "wof:name":"Stevagni",
    "wof:placetype":"locality",
    "wof:population":8
},
  "geometry": {"coordinates":[8.13106,44.35765],"type":"Point"}
}