{
  "type": "Feature",
  "properties": {
    "gn:admin1_code":"12.0",
    "gn:admin2_code":"AT",
    "gn:admin3_code":"5045.0",
    "gn:asciiname":"San Grato",
    "gn:country_code":"IT",
    "gn:dem":250,
    "gn:feature_class":"P",
    "gn:feature_code":"PPL",
    "gn:name":"San Grato",
    "gn:population":30,
    "gn:timezone":"Europe/Rome",
    "iso:country":"IT",
    "wof:name":"San Grato",
    "wof:placetype":"locality",
    "wof:population":30
},
  "geometry": {"coordinates":[8.04515,44.95411],"type":"Point"}
}