{
  "type": "Feature",
  "properties": {
    "gn:admin1_code":"3.0",
    "gn:admin2_code":"RC",
    "gn:admin3_code":"80042.0",
    "gn:asciiname":"Sant'Anna",
    "gn:country_code":"IT",
    "gn:dem":513,
    "gn:feature_class":"P",
    "gn:feature_code":"PPL",
    "gn:name":"Sant'Anna",
    "gn:population":354,
    "gn:timezone":"Europe/Rome",
    "iso:country":"IT",
    "name:bre_x_preferred":[
        "Sant'Anna"
    ],
    "name:ceb_x_preferred":[
        "Sant'Anna"
    ],
    "name:deu_x_preferred":[
        "Sant\u2019Anna"
    ],
    "name:epo_x_preferred":[
        "Sant'Anna"
    ],
    "name:ita_x_preferred":[
        "Sant'Anna"
    ],
    "name:nld_x_preferred":[
        "Sant'Anna"
    ],
    "name:por_x_preferred":[
        "Sant'Anna"
    ],
    "name:srp_x_preferred":[
        "Sant'Ana"
    ],
    "name:swe_x_preferred":[
        "Sant'Anna"
    ],
    "wof:name":"Sant'Anna",
    "wof:placetype":"locality",
    "wof:population":354
},
  "geometry": {"coordinates":[16.11031,38.49638],"type":"Point"}
}