{
  "type": "Feature",
  "properties": {
    "gn:admin1_code":"15",
    "gn:admin2_code":"ME",
    "gn:admin3_code":"83055.0",
    "gn:asciiname":"Larderia",
    "gn:country_code":"IT",
    "gn:dem":642,
    "gn:feature_class":"P",
    "gn:feature_code":"PPL",
    "gn:name":"Larderia",
    "gn:population":13,
    "gn:timezone":"Europe/Rome",
    "iso:country":"IT",
    "wof:name":"Larderia",
    "wof:placetype":"locality",
    "wof:population":13
},
  "geometry": {"coordinates":[15.24916,37.89249],"type":"Point"}
}