{
  "type": "Feature",
  "properties": {
    "gn:admin1_code":"20",
    "gn:admin2_code":"VI",
    "gn:admin3_code":"24019.0",
    "gn:asciiname":"Campora",
    "gn:country_code":"IT",
    "gn:dem":370,
    "gn:feature_class":"P",
    "gn:feature_code":"PPL",
    "gn:name":"Campora",
    "gn:population":33,
    "gn:timezone":"Europe/Rome",
    "iso:country":"IT",
    "wof:name":"Campora",
    "wof:placetype":"locality",
    "wof:population":33
},
  "geometry": {"coordinates":[11.47148,45.77314000000001],"type":"Point"}
}