{
  "type": "Feature",
  "properties": {
    "gn:admin1_code":"2",
    "gn:admin2_code":"PZ",
    "gn:admin3_code":"76042.0",
    "gn:asciiname":"Sant'Alfonso",
    "gn:country_code":"IT",
    "gn:dem":778,
    "gn:feature_class":"P",
    "gn:feature_code":"PPL",
    "gn:name":"Sant'Alfonso",
    "gn:population":47,
    "gn:timezone":"Europe/Rome",
    "iso:country":"IT",
    "wof:name":"Sant'Alfonso",
    "wof:placetype":"locality",
    "wof:population":47
},
  "geometry": {"coordinates":[15.92154,40.07338],"type":"Point"}
}