{
  "type": "Feature",
  "properties": {
    "gn:admin1_code":"12",
    "gn:admin2_code":"AT",
    "gn:admin3_code":"5112.0",
    "gn:asciiname":"Quarona",
    "gn:country_code":"IT",
    "gn:dem":323,
    "gn:feature_class":"P",
    "gn:feature_code":"PPL",
    "gn:name":"Quarona",
    "gn:population":77,
    "gn:timezone":"Europe/Rome",
    "iso:country":"IT",
    "wof:name":"Quarona",
    "wof:placetype":"locality",
    "wof:population":77
},
  "geometry": {"coordinates":[7.96156,44.86141],"type":"Point"}
}