{
  "type": "Feature",
  "properties": {
    "gn:admin1_code":"12",
    "gn:admin2_code":"AT",
    "gn:admin3_code":"5112.0",
    "gn:asciiname":"Quarona",
    "gn:country_code":"IT",
    "gn:dem":323,
    "gn:feature_class":"P",
    "gn:feature_code":"PPL",
    "gn:name":"Quarona",
    "gn:population":77,
    "gn:timezone":"Europe/Rome",
    "iso:country":"IT",
    "name:ara_x_preferred":[
        "\u0643\u0648\u0627\u0631\u0648\u0646\u0627"
    ],
    "name:azb_x_preferred":[
        "\u06a9\u0648\u0627\u0631\u0648\u0646\u0627"
    ],
    "name:bar_x_preferred":[
        "Quarona"
    ],
    "name:bel_x_preferred":[
        "\u041a\u0443\u0430\u0440\u043e\u043d\u0430"
    ],
    "name:bul_x_preferred":[
        "\u041a\u0443\u0430\u0440\u043e\u043d\u0430"
    ],
    "name:ceb_x_preferred":[
        "Quarona"
    ],
    "name:deu_x_preferred":[
        "Quarona"
    ],
    "name:epo_x_preferred":[
        "Quarona"
    ],
    "name:eus_x_preferred":[
        "Quarona"
    ],
    "name:fas_x_preferred":[
        "\u06a9\u0648\u0627\u0631\u0648\u0646\u0627"
    ],
    "name:fin_x_preferred":[
        "Quarona"
    ],
    "name:fra_x_preferred":[
        "Quarona"
    ],
    "name:hun_x_preferred":[
        "Quarona"
    ],
    "name:hye_x_preferred":[
        "\u053f\u0578\u0582\u0561\u0580\u0578\u0576\u0561"
    ],
    "name:ind_x_preferred":[
        "Quarona"
    ],
    "name:ita_x_preferred":[
        "Quarona"
    ],
    "name:jpn_x_preferred":[
        "\u30af\u30a2\u30ed\u30fc\u30ca"
    ],
    "name:kaz_x_preferred":[
        "\u041a\u0443\u0430\u0440\u043e\u043d\u0430"
    ],
    "name:lat_x_preferred":[
        "Quariona"
    ],
    "name:lmo_x_preferred":[
        "Quaruna"
    ],
    "name:msa_x_preferred":[
        "Quarona"
    ],
    "name:nap_x_preferred":[
        "Quarona"
    ],
    "name:nld_x_preferred":[
        "Quarona"
    ],
    "name:pms_x_preferred":[
        "Quaron-a"
    ],
    "name:pol_x_preferred":[
        "Quarona"
    ],
    "name:por_x_preferred":[
        "Quarona"
    ],
    "name:ron_x_preferred":[
        "Quarona"
    ],
    "name:rus_x_preferred":[
        "\u041a\u0443\u0430\u0440\u043e\u043d\u0430"
    ],
    "name:scn_x_preferred":[
        "Quarona"
    ],
    "name:spa_x_preferred":[
        "Quarona"
    ],
    "name:srp_x_preferred":[
        "\u041a\u0432\u0430\u0440\u043e\u043d\u0430"
    ],
    "name:swe_x_preferred":[
        "Quarona"
    ],
    "name:tgl_x_preferred":[
        "Quarona"
    ],
    "name:tur_x_preferred":[
        "Quarona"
    ],
    "name:ukr_x_preferred":[
        "\u041a\u0443\u0430\u0440\u043e\u043d\u0430"
    ],
    "name:uzb_x_preferred":[
        "Quarona"
    ],
    "name:vie_x_preferred":[
        "Quarona"
    ],
    "name:vol_x_preferred":[
        "Quarona"
    ],
    "name:war_x_preferred":[
        "Quarona"
    ],
    "name:zho_x_preferred":[
        "\u5938\u7f57\u7eb3"
    ],
    "wof:name":"Quarona",
    "wof:placetype":"locality",
    "wof:population":77
},
  "geometry": {"coordinates":[7.96156,44.86141],"type":"Point"}
}