{
  "type": "Feature",
  "properties": {
    "gn:admin1_code":"12.0",
    "gn:admin2_code":"AT",
    "gn:admin3_code":"5053.0",
    "gn:asciiname":"San Grato",
    "gn:country_code":"IT",
    "gn:dem":318,
    "gn:feature_class":"P",
    "gn:feature_code":"PPL",
    "gn:name":"San Grato",
    "gn:population":66,
    "gn:timezone":"Europe/Rome",
    "iso:country":"IT",
    "wof:name":"San Grato",
    "wof:placetype":"locality",
    "wof:population":66
},
  "geometry": {"coordinates":[7.96897,44.85744],"type":"Point"}
}