{
  "type": "Feature",
  "properties": {
    "gn:admin1_code":"16.0",
    "gn:admin2_code":"MS",
    "gn:admin3_code":"45014.0",
    "gn:asciiname":"Toplecca di Sopra",
    "gn:country_code":"IT",
    "gn:dem":586,
    "gn:feature_class":"P",
    "gn:feature_code":"PPL",
    "gn:name":"Toplecca di Sopra",
    "gn:population":6,
    "gn:timezone":"Europe/Rome",
    "iso:country":"IT",
    "wof:name":"Toplecca di Sopra",
    "wof:placetype":"locality",
    "wof:population":6
},
  "geometry": {"coordinates":[9.92381,44.40973],"type":"Point"}
}