{
  "type": "Feature",
  "properties": {
    "gn:admin1_code":"18",
    "gn:admin2_code":"PG",
    "gn:admin3_code":"54016.0",
    "gn:asciiname":"Pielarocca",
    "gn:country_code":"IT",
    "gn:dem":591,
    "gn:feature_class":"P",
    "gn:feature_code":"PPLL",
    "gn:name":"Pielarocca",
    "gn:population":10,
    "gn:timezone":"Europe/Rome",
    "iso:country":"IT",
    "wof:name":"Pielarocca",
    "wof:placetype":"locality",
    "wof:population":10
},
  "geometry": {"coordinates":[12.6916,43.38116],"type":"Point"}
}