{
  "type": "Feature",
  "properties": {
    "gn:admin1_code":"9",
    "gn:admin2_code":"MI",
    "gn:admin3_code":"15062.0",
    "gn:asciiname":"Cascina Saronna",
    "gn:country_code":"IT",
    "gn:dem":188,
    "gn:feature_class":"P",
    "gn:feature_code":"PPL",
    "gn:name":"Cascina Saronna",
    "gn:population":78,
    "gn:timezone":"Europe/Rome",
    "iso:country":"IT",
    "wof:name":"Cascina Saronna",
    "wof:placetype":"locality",
    "wof:population":78
},
  "geometry": {"coordinates":[8.79549,45.55496],"type":"Point"}
}