{
  "type": "Feature",
  "properties": {
    "gn:admin1_code":"16.0",
    "gn:admin2_code":"AR",
    "gn:admin3_code":"51001.0",
    "gn:asciiname":"Bagnolo I",
    "gn:country_code":"IT",
    "gn:dem":370,
    "gn:feature_class":"P",
    "gn:feature_code":"PPL",
    "gn:name":"Bagnolo I",
    "gn:population":14,
    "gn:timezone":"Europe/Rome",
    "iso:country":"IT",
    "wof:name":"Bagnolo I",
    "wof:placetype":"locality",
    "wof:population":14
},
  "geometry": {"coordinates":[12.02371,43.55724],"type":"Point"}
}