{
  "type": "Feature",
  "properties": {
    "gn:admin1_code":"5.0",
    "gn:admin2_code":"MO",
    "gn:admin3_code":"36037.0",
    "gn:asciiname":"Ponte di San Pellegrino",
    "gn:cc2":"IT",
    "gn:country_code":"IT",
    "gn:dem":13,
    "gn:feature_class":"P",
    "gn:feature_code":"PPL",
    "gn:name":"Ponte di San Pellegrino",
    "gn:population":0,
    "gn:timezone":"Europe/Rome",
    "iso:country":"IT",
    "name:und_x_variant":[
        "Ponte San Pellegrino",
        "Ponte di San Pellegrino"
    ],
    "wof:name":"Ponte di San Pellegrino",
    "wof:placetype":"locality"
},
  "geometry": {"coordinates":[11.15,44.86667],"type":"Point"}
}