{
  "type": "Feature",
  "properties": {
    "gn:admin1_code":"19",
    "gn:admin2_code":"AO",
    "gn:admin3_code":"7045.0",
    "gn:asciiname":"Tholaseche",
    "gn:country_code":"IT",
    "gn:dem":836,
    "gn:feature_class":"P",
    "gn:feature_code":"PPL",
    "gn:name":"Tholaseche",
    "gn:population":29,
    "gn:timezone":"Europe/Rome",
    "iso:country":"IT",
    "wof:name":"Tholaseche",
    "wof:placetype":"locality",
    "wof:population":29
},
  "geometry": {"coordinates":[7.48032,45.75345],"type":"Point"}
}