{
  "type": "Feature",
  "properties": {
    "gn:admin1_code":"5",
    "gn:admin2_code":"PC",
    "gn:admin3_code":"33029.0",
    "gn:asciiname":"Stadera",
    "gn:country_code":"IT",
    "gn:dem":545,
    "gn:feature_class":"P",
    "gn:feature_code":"PPL",
    "gn:name":"Stadera",
    "gn:population":36,
    "gn:timezone":"Europe/Rome",
    "iso:country":"IT",
    "wof:name":"Stadera",
    "wof:placetype":"locality",
    "wof:population":36
},
  "geometry": {"coordinates":[9.32044,44.93138],"type":"Point"}
}