{
  "type": "Feature",
  "properties": {
    "gn:admin1_code":"7",
    "gn:admin2_code":"LT",
    "gn:admin3_code":"59005.0",
    "gn:asciiname":"Madonna dell'Olmo",
    "gn:country_code":"IT",
    "gn:dem":51,
    "gn:feature_class":"P",
    "gn:feature_code":"PPL",
    "gn:name":"Madonna dell'Olmo",
    "gn:population":46,
    "gn:timezone":"Europe/Rome",
    "iso:country":"IT",
    "wof:name":"Madonna dell'Olmo",
    "wof:placetype":"locality",
    "wof:population":46
},
  "geometry": {"coordinates":[12.81356,41.55962],"type":"Point"}
}