{
  "type": "Feature",
  "properties": {
    "gn:admin1_code":"12",
    "gn:admin2_code":"TO",
    "gn:admin3_code":"1227.0",
    "gn:asciiname":"Vignal",
    "gn:country_code":"IT",
    "gn:dem":855,
    "gn:feature_class":"P",
    "gn:feature_code":"PPL",
    "gn:name":"Vignal",
    "gn:population":17,
    "gn:timezone":"Europe/Rome",
    "iso:country":"IT",
    "wof:name":"Vignal",
    "wof:placetype":"locality",
    "wof:population":17
},
  "geometry": {"coordinates":[7.142,44.99301],"type":"Point"}
}