{
  "type": "Feature",
  "properties": {
    "gn:admin1_code":"18.0",
    "gn:admin2_code":"PG",
    "gn:admin3_code":"54030.0",
    "gn:asciiname":"Borghetto",
    "gn:country_code":"IT",
    "gn:dem":232,
    "gn:elevation":"236.0",
    "gn:feature_class":"P",
    "gn:feature_code":"PPL",
    "gn:name":"Borghetto",
    "gn:population":34,
    "gn:timezone":"Europe/Rome",
    "iso:country":"IT",
    "name:ceb_x_preferred":[
        "Borghetto"
    ],
    "name:deu_x_preferred":[
        "Borghetto"
    ],
    "name:fra_x_preferred":[
        "Borghetto"
    ],
    "name:ita_x_preferred":[
        "Borghetto"
    ],
    "name:nld_x_preferred":[
        "Borghetto"
    ],
    "name:por_x_preferred":[
        "Borghetto"
    ],
    "name:srp_x_preferred":[
        "Borgeto"
    ],
    "name:swe_x_preferred":[
        "Borghetto"
    ],
    "wof:name":"Borghetto",
    "wof:placetype":"locality",
    "wof:population":34
},
  "geometry": {"coordinates":[12.6808,42.85223],"type":"Point"}
}