{
  "type": "Feature",
  "properties": {
    "iso:country":"IT",
    "name:arg_x_preferred":[
        "Is Pratzas"
    ],
    "name:bel_x_preferred":[
        "\u041b\u0430\u0441-\u041f\u043b\u0430\u0441\u0430\u0441"
    ],
    "name:bul_x_preferred":[
        "\u041b\u0430\u0441 \u041f\u043b\u0430\u0441\u0430\u0441"
    ],
    "name:cat_x_preferred":[
        "Las Plassas"
    ],
    "name:deu_x_preferred":[
        "Las Plassas"
    ],
    "name:eng_x_preferred":[
        "Las Plassas"
    ],
    "name:epo_x_preferred":[
        "Las Plassas"
    ],
    "name:eus_x_preferred":[
        "Las Plassas"
    ],
    "name:fas_x_preferred":[
        "\u0644\u0627\u0633 \u067e\u0644\u0627\u0633\u0627\u0633"
    ],
    "name:fra_x_preferred":[
        "Las Plassas"
    ],
    "name:hun_x_preferred":[
        "Las Plassas"
    ],
    "name:hye_x_preferred":[
        "\u053c\u0561\u057d \u054a\u056c\u0561\u057d\u0561\u057d"
    ],
    "name:ita_x_preferred":[
        "Las Plassas"
    ],
    "name:jpn_x_preferred":[
        "\u30e9\u30b9\u30fb\u30d7\u30e9\u30c3\u30b5\u30b9"
    ],
    "name:kaz_x_preferred":[
        "\u041b\u0430\u0441-\u041f\u043b\u0430\u0441\u0441\u0430\u0441"
    ],
    "name:lat_x_preferred":[
        "Plateae"
    ],
    "name:lmo_x_preferred":[
        "Las Plassas"
    ],
    "name:msa_x_preferred":[
        "Las Plassas"
    ],
    "name:nan_x_preferred":[
        "Las Plassas"
    ],
    "name:nap_x_preferred":[
        "Las Plassas"
    ],
    "name:nld_x_preferred":[
        "Las Plassas"
    ],
    "name:pms_x_preferred":[
        "Las Plassas"
    ],
    "name:pol_x_preferred":[
        "Las Plassas"
    ],
    "name:por_x_preferred":[
        "Las Plassas"
    ],
    "name:ron_x_preferred":[
        "Las Plassas"
    ],
    "name:rus_x_preferred":[
        "\u041b\u0430\u0441-\u041f\u043b\u0430\u0441\u0441\u0430\u0441"
    ],
    "name:scn_x_preferred":[
        "Las Plassas"
    ],
    "name:spa_x_preferred":[
        "Las Plassas"
    ],
    "name:srd_x_preferred":[
        "Is Pratzas"
    ],
    "name:srp_x_preferred":[
        "Las Plassas"
    ],
    "name:tgl_x_preferred":[
        "Las Plassas"
    ],
    "name:ukr_x_preferred":[
        "\u041b\u0430\u0441-\u041f\u043b\u0430\u0441\u0441\u0430\u0441"
    ],
    "name:uzb_x_preferred":[
        "Las Plassas"
    ],
    "name:vie_x_preferred":[
        "Las Plassas"
    ],
    "name:vol_x_preferred":[
        "Las Plassas"
    ],
    "name:war_x_preferred":[
        "Las Plassas"
    ],
    "name:zho_x_preferred":[
        "\u62c9\u65af\u666e\u62c9\u8428\u65af"
    ],
    "qs_pg:aaroncc":"IT",
    "qs_pg:name":"Lasplassas",
    "qs_pg:name_adm0":"Italia",
    "qs_pg:name_adm1":"Sardegna",
    "qs_pg:photos":20,
    "qs_pg:photos_1k":4,
    "qs_pg:photos_9k":1,
    "qs_pg:photos_9r":1,
    "qs_pg:photos_all":20,
    "qs_pg:photos_sr":1,
    "qs_pg:pop_sr":0,
    "qs_pg:qs_pg_placetype":"locality",
    "qs_pg:qs_pg_placetype_gp":"Town",
    "qs_pg:woe_adm0":23424853,
    "woe:adm0_id":23424853,
    "woe:name_adm0":"Italia",
    "woe:name_adm1":"Sardegna",
    "woe:placetype":"Town",
    "wof:name":"Lasplassas",
    "wof:placetype":"locality"
},
  "geometry": {"coordinates":[8.982782,39.680306],"type":"Point"}
}