{
  "type": "Feature",
  "properties": {
    "gn:admin1_code":"5",
    "gn:admin2_code":"PR",
    "gn:admin3_code":"34032.0",
    "gn:asciiname":"Rossi",
    "gn:country_code":"IT",
    "gn:dem":245,
    "gn:feature_class":"P",
    "gn:feature_code":"PPL",
    "gn:name":"Rossi",
    "gn:population":25,
    "gn:timezone":"Europe/Rome",
    "iso:country":"IT",
    "wof:name":"Rossi",
    "wof:placetype":"locality",
    "wof:population":25
},
  "geometry": {"coordinates":[9.95597,44.81179],"type":"Point"}
}