{
  "type": "Feature",
  "properties": {
    "gn:admin1_code":"13",
    "gn:admin2_code":"FG",
    "gn:admin3_code":"71022.0",
    "gn:asciiname":"Catenaccio",
    "gn:country_code":"IT",
    "gn:dem":231,
    "gn:feature_class":"P",
    "gn:feature_code":"PPL",
    "gn:name":"Catenaccio",
    "gn:population":43,
    "gn:timezone":"Europe/Rome",
    "iso:country":"IT",
    "name:ara_x_preferred":[
        "\u0643\u0627\u062a\u064a\u0646\u0627\u062a\u0634\u0648"
    ],
    "name:aze_x_preferred":[
        "Katena\u00e7\u00e7o"
    ],
    "name:cat_x_preferred":[
        "Catenaccio"
    ],
    "name:ces_x_preferred":[
        "Catenaccio"
    ],
    "name:ckb_x_preferred":[
        "\u06a9\u0627\u062a\u06cc\u0646\u0627\u0686\u06c6"
    ],
    "name:deu_x_preferred":[
        "Catenaccio"
    ],
    "name:ell_x_preferred":[
        "\u039a\u03b1\u03c4\u03b5\u03bd\u03ac\u03c4\u03c3\u03b9\u03bf"
    ],
    "name:fas_x_preferred":[
        "\u06a9\u0627\u062a\u0646\u0627\u0686\u06cc\u0648"
    ],
    "name:fin_x_preferred":[
        "Catenaccio"
    ],
    "name:fra_x_preferred":[
        "Catenaccio"
    ],
    "name:heb_x_preferred":[
        "\u05e7\u05d8\u05e0\u05d0\u05e6'\u05d5"
    ],
    "name:ind_x_preferred":[
        "Catenaccio"
    ],
    "name:ita_x_preferred":[
        "Catenaccio"
    ],
    "name:jpn_x_preferred":[
        "\u30ab\u30c6\u30ca\u30c1\u30aa"
    ],
    "name:kor_x_preferred":[
        "\uce74\ud14c\ub098\uce58\uc624"
    ],
    "name:mal_x_preferred":[
        "\u0d15\u0d3e\u0d31\u0d4d\u0d31\u0d28\u0d3e\u0d1a\u0d4d\u0d1a\u0d3f\u0d2f\u0d4b"
    ],
    "name:nld_x_preferred":[
        "Catenaccio"
    ],
    "name:nor_x_preferred":[
        "Catenaccio"
    ],
    "name:pol_x_preferred":[
        "Catenaccio"
    ],
    "name:por_x_preferred":[
        "Catenaccio"
    ],
    "name:rus_x_preferred":[
        "\u041a\u0430\u0442\u0435\u043d\u0430\u0447\u0447\u043e"
    ],
    "name:spa_x_preferred":[
        "Catenaccio"
    ],
    "name:swe_x_preferred":[
        "Catenaccio"
    ],
    "name:ukr_x_preferred":[
        "\u041a\u0430\u0442\u0435\u043d\u0430\u0447\u043e"
    ],
    "name:vie_x_preferred":[
        "Catenaccio"
    ],
    "name:zho_x_preferred":[
        "\u93c8\u5f0f\u9632\u5b88"
    ],
    "wof:name":"Catenaccio",
    "wof:placetype":"locality",
    "wof:population":43
},
  "geometry": {"coordinates":[15.4686,41.26288],"type":"Point"}
}