{
  "type": "Feature",
  "properties": {
    "gn:admin1_code":"13",
    "gn:admin2_code":"FG",
    "gn:admin3_code":"71022.0",
    "gn:asciiname":"Catenaccio",
    "gn:country_code":"IT",
    "gn:dem":231,
    "gn:feature_class":"P",
    "gn:feature_code":"PPL",
    "gn:name":"Catenaccio",
    "gn:population":43,
    "gn:timezone":"Europe/Rome",
    "iso:country":"IT",
    "wof:name":"Catenaccio",
    "wof:placetype":"locality",
    "wof:population":43
},
  "geometry": {"coordinates":[15.4686,41.26288],"type":"Point"}
}