{
  "type": "Feature",
  "properties": {
    "gn:admin1_code":"20.0",
    "gn:admin2_code":"VI",
    "gn:admin3_code":"24085.0",
    "gn:asciiname":"Dosso",
    "gn:country_code":"IT",
    "gn:dem":998,
    "gn:feature_class":"P",
    "gn:feature_code":"PPL",
    "gn:name":"Dosso",
    "gn:population":12,
    "gn:timezone":"Europe/Rome",
    "iso:country":"IT",
    "name:bul_x_preferred":[
        "\u0414\u043e\u0441\u043e"
    ],
    "name:cat_x_preferred":[
        "Dosso"
    ],
    "name:ceb_x_preferred":[
        "Dosso"
    ],
    "name:deu_x_preferred":[
        "Dosso"
    ],
    "name:fas_x_preferred":[
        "\u062f\u0648\u0633\u0648"
    ],
    "name:fra_x_preferred":[
        "Dosso"
    ],
    "name:heb_x_preferred":[
        "\u05d3\u05d5\u05e1\u05d5"
    ],
    "name:hun_x_preferred":[
        "Dosso"
    ],
    "name:ita_x_preferred":[
        "Dosso"
    ],
    "name:nld_x_preferred":[
        "Dosso"
    ],
    "name:pol_x_preferred":[
        "Dosso"
    ],
    "name:por_x_preferred":[
        "Dosso"
    ],
    "name:rus_x_preferred":[
        "\u0414\u043e\u0441\u043e"
    ],
    "name:srp_x_preferred":[
        "Dosso"
    ],
    "name:swe_x_preferred":[
        "Dosso"
    ],
    "name:ukr_x_preferred":[
        "\u0414\u043e\u0441\u043e"
    ],
    "wof:name":"Dosso",
    "wof:placetype":"locality",
    "wof:population":12
},
  "geometry": {"coordinates":[11.41092,45.84632],"type":"Point"}
}