{
  "type": "Feature",
  "properties": {
    "gn:admin1_code":"20.0",
    "gn:admin2_code":"VI",
    "gn:admin3_code":"24085.0",
    "gn:asciiname":"Dosso",
    "gn:country_code":"IT",
    "gn:dem":998,
    "gn:feature_class":"P",
    "gn:feature_code":"PPL",
    "gn:name":"Dosso",
    "gn:population":12,
    "gn:timezone":"Europe/Rome",
    "iso:country":"IT",
    "wof:name":"Dosso",
    "wof:placetype":"locality",
    "wof:population":12
},
  "geometry": {"coordinates":[11.41092,45.84632],"type":"Point"}
}