{
  "type": "Feature",
  "properties": {
    "gn:elevation":868,
    "gn:population":167,
    "iso:country":"IT",
    "name:bel_x_preferred":[
        "\u041c\u0430\u043b\u0456\u0437\u044d"
    ],
    "name:bul_x_preferred":[
        "\u041c\u043e\u043b\u0438\u0437\u0435"
    ],
    "name:deu_x_preferred":[
        "Molise"
    ],
    "name:eng_x_preferred":[
        "Molise"
    ],
    "name:epo_x_preferred":[
        "Molise"
    ],
    "name:est_x_preferred":[
        "Molise vald"
    ],
    "name:eus_x_preferred":[
        "Molise"
    ],
    "name:fra_x_preferred":[
        "Molise"
    ],
    "name:hbs_x_preferred":[
        "Molise"
    ],
    "name:hun_x_preferred":[
        "Molise"
    ],
    "name:hye_x_preferred":[
        "\u0544\u0578\u056c\u056b\u0566\u0565"
    ],
    "name:ina_x_preferred":[
        "Molise"
    ],
    "name:ita_x_preferred":[
        "Molise"
    ],
    "name:jpn_x_preferred":[
        "\u30e2\u30ea\u30fc\u30bc"
    ],
    "name:kor_x_preferred":[
        "\ubab0\ub9ac\uc138"
    ],
    "name:lat_x_preferred":[
        "Molisium"
    ],
    "name:lmo_x_preferred":[
        "Molise"
    ],
    "name:msa_x_preferred":[
        "Molise"
    ],
    "name:nan_x_preferred":[
        "Molise Campobasso"
    ],
    "name:nap_x_preferred":[
        "Molise"
    ],
    "name:nld_x_preferred":[
        "Molise"
    ],
    "name:pol_x_preferred":[
        "Molise"
    ],
    "name:por_x_preferred":[
        "Molise"
    ],
    "name:ron_x_preferred":[
        "Molise"
    ],
    "name:rus_x_preferred":[
        "\u041c\u043e\u043b\u0438\u0437\u0435"
    ],
    "name:scn_x_preferred":[
        "Mulisi"
    ],
    "name:spa_x_preferred":[
        "Molise"
    ],
    "name:srp_x_preferred":[
        "\u041c\u043e\u043b\u0438\u0437\u0435"
    ],
    "name:tgl_x_preferred":[
        "Molise"
    ],
    "name:ukr_x_preferred":[
        "\u041c\u043e\u043b\u0456\u0437\u0435"
    ],
    "name:uzb_x_preferred":[
        "Molise"
    ],
    "name:vie_x_preferred":[
        "Molise"
    ],
    "name:vol_x_preferred":[
        "Molise"
    ],
    "name:war_x_preferred":[
        "Molise"
    ],
    "name:zho_min_nan_x_preferred":[
        "Molise Campobasso"
    ],
    "name:zho_x_preferred":[
        "\u83ab\u5229\u585e"
    ],
    "qs:a0":"Italia",
    "qs:a1":"*Campobasso",
    "qs:a1r":"0Molise",
    "qs:adm0":"Italia",
    "qs:la_lc":"*",
    "qs:level":"locality",
    "qs:loc":"Molise",
    "qs:loc_alt":"Molise",
    "qs:pop":0,
    "qs:type":"buffered point",
    "wd:wordcount":66,
    "wof:name":"Molise",
    "wof:placetype":"locality",
    "wof:population":167
},
  "geometry": {"coordinates":[14.491629,41.63166],"type":"Point"}
}