{
  "type": "Feature",
  "properties": {
    "gn:admin1_code":"20",
    "gn:admin2_code":"VR",
    "gn:admin3_code":"23082.0",
    "gn:asciiname":"Montegodi",
    "gn:country_code":"IT",
    "gn:dem":110,
    "gn:feature_class":"P",
    "gn:feature_code":"PPL",
    "gn:name":"Montegodi",
    "gn:population":20,
    "gn:timezone":"Europe/Rome",
    "iso:country":"IT",
    "wof:name":"Montegodi",
    "wof:placetype":"locality",
    "wof:population":20
},
  "geometry": {"coordinates":[10.79942,45.39122],"type":"Point"}
}