{
  "type": "Feature",
  "properties": {
    "gn:admin1_code":"16.0",
    "gn:admin2_code":"FI",
    "gn:admin3_code":"48044.0",
    "gn:asciiname":"San Mauro",
    "gn:country_code":"IT",
    "gn:dem":37,
    "gn:elevation":"37.0",
    "gn:feature_class":"P",
    "gn:feature_code":"PPL",
    "gn:name":"San Mauro",
    "gn:population":3091,
    "gn:timezone":"Europe/Rome",
    "iso:country":"IT",
    "name:ita_x_colloquial":[
        "San Mauro a Signa"
    ],
    "name:ita_x_preferred":[
        "San Mauro a Signa"
    ],
    "wof:name":"San Mauro",
    "wof:placetype":"locality",
    "wof:population":3091
},
  "geometry": {"coordinates":[11.12499,43.79418],"type":"Point"}
}