{
  "type": "Feature",
  "properties": {
    "gn:admin1_code":"16.0",
    "gn:admin2_code":"FI",
    "gn:admin3_code":"48044.0",
    "gn:asciiname":"San Mauro",
    "gn:country_code":"IT",
    "gn:dem":37,
    "gn:elevation":"37.0",
    "gn:feature_class":"P",
    "gn:feature_code":"PPL",
    "gn:name":"San Mauro",
    "gn:population":3091,
    "gn:timezone":"Europe/Rome",
    "iso:country":"IT",
    "name:ceb_x_preferred":[
        "San Mauro"
    ],
    "name:deu_x_preferred":[
        "San Mauro"
    ],
    "name:glg_x_preferred":[
        "San Mauro"
    ],
    "name:ita_x_colloquial":[
        "San Mauro a Signa"
    ],
    "name:ita_x_preferred":[
        "San Mauro a Signa"
    ],
    "name:ita_x_variant":[
        "San Mauro"
    ],
    "name:nld_x_preferred":[
        "San Mauro"
    ],
    "name:por_x_preferred":[
        "San Mauro"
    ],
    "name:rus_x_preferred":[
        "\u0421\u0432\u044f\u0442\u043e\u0439 \u041c\u0430\u0432\u0440"
    ],
    "name:scn_x_preferred":[
        "Santu M\u00e0uru"
    ],
    "name:sco_x_preferred":[
        "San Mauro"
    ],
    "name:srp_x_preferred":[
        "San Mauro"
    ],
    "name:swe_x_preferred":[
        "San Mauro"
    ],
    "wof:name":"San Mauro",
    "wof:placetype":"locality",
    "wof:population":3091
},
  "geometry": {"coordinates":[11.12499,43.79418],"type":"Point"}
}