{
  "type": "Feature",
  "properties": {
    "gn:admin1_code":"12",
    "gn:admin2_code":"CN",
    "gn:admin3_code":"4089.0",
    "gn:asciiname":"Frola",
    "gn:country_code":"IT",
    "gn:dem":368,
    "gn:feature_class":"P",
    "gn:feature_code":"PPL",
    "gn:name":"Frola",
    "gn:population":40,
    "gn:timezone":"Europe/Rome",
    "iso:country":"IT",
    "wof:name":"Frola",
    "wof:placetype":"locality",
    "wof:population":40
},
  "geometry": {"coordinates":[7.73484,44.56631],"type":"Point"}
}