{
  "type": "Feature",
  "properties": {
    "gn:admin1_code":"16",
    "gn:admin2_code":"AR",
    "gn:admin3_code":"51015.0",
    "gn:asciiname":"Casenuove",
    "gn:country_code":"IT",
    "gn:dem":726,
    "gn:feature_class":"P",
    "gn:feature_code":"PPL",
    "gn:name":"Casenuove",
    "gn:population":16,
    "gn:timezone":"Europe/Rome",
    "iso:country":"IT",
    "wof:name":"Casenuove",
    "wof:placetype":"locality",
    "wof:population":16
},
  "geometry": {"coordinates":[11.89289,43.70217],"type":"Point"}
}