{
  "type": "Feature",
  "properties": {
    "gn:admin1_code":"1",
    "gn:admin2_code":"AQ",
    "gn:admin3_code":"66041.0",
    "gn:asciiname":"Localita Produttiva Sant'Ippolito",
    "gn:country_code":"IT",
    "gn:dem":292,
    "gn:feature_class":"P",
    "gn:feature_code":"PPLL",
    "gn:name":"Localit\u00e0 Produttiva Sant'Ippolito",
    "gn:population":10,
    "gn:timezone":"Europe/Rome",
    "iso:country":"IT",
    "name:und_x_variant":[
        "Localit\u00e0 Produttiva Sant'Ippolito"
    ],
    "wof:name":"Localita Produttiva Sant'Ippolito",
    "wof:placetype":"locality",
    "wof:population":10
},
  "geometry": {"coordinates":[13.85313,42.12885],"type":"Point"}
}