{
  "type": "Feature",
  "properties": {
    "gn:admin1_code":"5",
    "gn:admin2_code":"PR",
    "gn:admin3_code":"34015.0",
    "gn:asciiname":"Salso",
    "gn:country_code":"IT",
    "gn:dem":69,
    "gn:feature_class":"P",
    "gn:feature_code":"PPL",
    "gn:name":"Salso",
    "gn:population":36,
    "gn:timezone":"Europe/Rome",
    "iso:country":"IT",
    "wof:name":"Salso",
    "wof:placetype":"locality",
    "wof:population":36
},
  "geometry": {"coordinates":[10.11048,44.86194],"type":"Point"}
}