{
  "type": "Feature",
  "properties": {
    "gn:admin1_code":"5",
    "gn:admin2_code":"PR",
    "gn:admin3_code":"34015.0",
    "gn:asciiname":"Salso",
    "gn:country_code":"IT",
    "gn:dem":69,
    "gn:feature_class":"P",
    "gn:feature_code":"PPL",
    "gn:name":"Salso",
    "gn:population":36,
    "gn:timezone":"Europe/Rome",
    "iso:country":"IT",
    "name:ara_x_preferred":[
        "\u0646\u0647\u0631 \u0633\u0627\u0644\u0633\u0648"
    ],
    "name:bar_x_preferred":[
        "Imera Meridionale"
    ],
    "name:cat_x_preferred":[
        "Riu Salso"
    ],
    "name:ces_x_preferred":[
        "Salso"
    ],
    "name:chv_x_preferred":[
        "\u0421\u0430\u043b\u044c\u0441\u043e"
    ],
    "name:deu_x_preferred":[
        "Imera Meridionale"
    ],
    "name:epo_x_preferred":[
        "Salso"
    ],
    "name:fra_x_preferred":[
        "Imera m\u00e9ridionale"
    ],
    "name:ita_x_preferred":[
        "Imera meridionale"
    ],
    "name:lat_x_preferred":[
        "Hymera Australis"
    ],
    "name:nld_x_preferred":[
        "Imera meridionale"
    ],
    "name:pol_x_preferred":[
        "Salso"
    ],
    "name:rus_x_preferred":[
        "\u0421\u0430\u043b\u044c\u0441\u043e"
    ],
    "name:scn_x_preferred":[
        "Salsu"
    ],
    "name:spa_x_preferred":[
        "R\u00edo Salso"
    ],
    "name:zho_x_preferred":[
        "\u85a9\u723e\u7d22\u6cb3"
    ],
    "wof:name":"Salso",
    "wof:placetype":"locality",
    "wof:population":36
},
  "geometry": {"coordinates":[10.11048,44.86194],"type":"Point"}
}