{
  "type": "Feature",
  "properties": {
    "gn:admin1_code":"6.0",
    "gn:admin2_code":"UD",
    "gn:admin3_code":"30005.0",
    "gn:asciiname":"Cedarchis",
    "gn:country_code":"IT",
    "gn:dem":421,
    "gn:feature_class":"P",
    "gn:feature_code":"PPL",
    "gn:name":"Cedarchis",
    "gn:population":183,
    "gn:timezone":"Europe/Rome",
    "iso:country":"IT",
    "wof:name":"Cedarchis",
    "wof:placetype":"locality",
    "wof:population":183
},
  "geometry": {"coordinates":[13.03527,46.45793],"type":"Point"}
}