{
  "type": "Feature",
  "properties": {
    "gn:country":"IT",
    "gn:fcode":"PPL",
    "gn:population":0,
    "iso:country":"IT",
    "name:eng_x_preferred":[
        "Contovello"
    ],
    "name:fra_x_preferred":[
        "Contovello"
    ],
    "name:hun_x_preferred":[
        "Contovello"
    ],
    "name:ita_x_preferred":[
        "Contovello"
    ],
    "name:nld_x_preferred":[
        "Contovello"
    ],
    "name:slv_x_preferred":[
        "Kontovel"
    ],
    "qs_pg:aaroncc":"IT",
    "qs_pg:gn_country":"IT",
    "qs_pg:gn_fcode":"PPL",
    "qs_pg:gn_pop":0,
    "qs_pg:name":"Contovello",
    "qs_pg:name_adm0":"Italia",
    "qs_pg:name_adm1":"Friuli-Venezia Giulia",
    "qs_pg:photos":18,
    "qs_pg:photos_1k":4,
    "qs_pg:photos_9k":1,
    "qs_pg:photos_9r":1,
    "qs_pg:photos_all":18,
    "qs_pg:photos_sr":1,
    "qs_pg:pop_sr":0,
    "qs_pg:qs_pg_placetype":"locality",
    "qs_pg:qs_pg_placetype_gp":"Town",
    "qs_pg:woe_adm0":23424853,
    "woe:adm0_id":23424853,
    "woe:name_adm0":"Italia",
    "woe:name_adm1":"Friuli-Venezia Giulia",
    "woe:placetype":"Town",
    "wof:name":"Contovello",
    "wof:placetype":"locality"
},
  "geometry": {"coordinates":[13.73332,45.70172],"type":"Point"}
}