{
  "type": "Feature",
  "properties": {
    "gn:admin1_code":"1.0",
    "gn:admin2_code":"TE",
    "gn:admin3_code":"67030.0",
    "gn:asciiname":"Artigianale Ripoli",
    "gn:country_code":"IT",
    "gn:dem":80,
    "gn:feature_class":"P",
    "gn:feature_code":"PPL",
    "gn:name":"Artigianale Ripoli",
    "gn:population":57,
    "gn:timezone":"Europe/Rome",
    "iso:country":"IT",
    "wof:name":"Artigianale Ripoli",
    "wof:placetype":"locality",
    "wof:population":57
},
  "geometry": {"coordinates":[13.91046,42.72363],"type":"Point"}
}