{
  "type": "Feature",
  "properties": {
    "gn:admin1_code":"9",
    "gn:admin2_code":"PV",
    "gn:admin3_code":"18124.0",
    "gn:asciiname":"Sacchina",
    "gn:country_code":"IT",
    "gn:dem":76,
    "gn:feature_class":"P",
    "gn:feature_code":"PPL",
    "gn:name":"Sacchina",
    "gn:population":17,
    "gn:timezone":"Europe/Rome",
    "iso:country":"IT",
    "wof:name":"Sacchina",
    "wof:placetype":"locality",
    "wof:population":17
},
  "geometry": {"coordinates":[9.15026,45.03757],"type":"Point"}
}