{
  "type": "Feature",
  "properties": {
    "gn:admin1_code":"3",
    "gn:admin2_code":"CS",
    "gn:admin3_code":"78044.0",
    "gn:asciiname":"Bonia I",
    "gn:country_code":"IT",
    "gn:dem":884,
    "gn:feature_class":"P",
    "gn:feature_code":"PPL",
    "gn:name":"Bonia I",
    "gn:population":23,
    "gn:timezone":"Europe/Rome",
    "iso:country":"IT",
    "wof:name":"Bonia I",
    "wof:placetype":"locality",
    "wof:population":23
},
  "geometry": {"coordinates":[16.51924,39.51262],"type":"Point"}
}