{
  "type": "Feature",
  "properties": {
    "gn:admin1_code":"4",
    "gn:admin2_code":"AV",
    "gn:admin3_code":"64005.0",
    "gn:asciiname":"Cervo",
    "gn:country_code":"IT",
    "gn:dem":314,
    "gn:feature_class":"P",
    "gn:feature_code":"PPL",
    "gn:name":"Cervo",
    "gn:population":17,
    "gn:timezone":"Europe/Rome",
    "iso:country":"IT",
    "wof:name":"Cervo",
    "wof:placetype":"locality",
    "wof:population":17
},
  "geometry": {"coordinates":[15.01138,41.14478],"type":"Point"}
}