{
  "type": "Feature",
  "properties": {
    "gn:admin1_code":"17.0",
    "gn:admin2_code":"TN",
    "gn:admin3_code":"22092.0",
    "gn:asciiname":"Maso Roncador",
    "gn:country_code":"IT",
    "gn:dem":650,
    "gn:feature_class":"P",
    "gn:feature_code":"PPL",
    "gn:name":"Maso Roncador",
    "gn:population":16,
    "gn:timezone":"Europe/Rome",
    "iso:country":"IT",
    "wof:name":"Maso Roncador",
    "wof:placetype":"locality",
    "wof:population":16
},
  "geometry": {"coordinates":[11.14019,46.16156],"type":"Point"}
}