{
  "type": "Feature",
  "properties": {
    "gn:admin1_code":"1",
    "gn:admin2_code":"TE",
    "gn:admin3_code":"67029.0",
    "gn:asciiname":"Torrenera",
    "gn:country_code":"IT",
    "gn:dem":161,
    "gn:feature_class":"P",
    "gn:feature_code":"PPL",
    "gn:name":"Torrenera",
    "gn:population":45,
    "gn:timezone":"Europe/Rome",
    "iso:country":"IT",
    "wof:name":"Torrenera",
    "wof:placetype":"locality",
    "wof:population":45
},
  "geometry": {"coordinates":[13.95378,42.67141],"type":"Point"}
}