{
  "type": "Feature",
  "properties": {
    "gn:admin1_code":"5",
    "gn:admin2_code":"RA",
    "gn:admin3_code":"39001.0",
    "gn:asciiname":"Pianta",
    "gn:country_code":"IT",
    "gn:dem":4,
    "gn:feature_class":"P",
    "gn:feature_code":"PPL",
    "gn:name":"Pianta",
    "gn:population":18,
    "gn:timezone":"Europe/Rome",
    "iso:country":"IT",
    "wof:name":"Pianta",
    "wof:placetype":"locality",
    "wof:population":18
},
  "geometry": {"coordinates":[11.93224,44.55609000000001],"type":"Point"}
}