{
  "type": "Feature",
  "properties": {
    "gn:admin1_code":"4",
    "gn:admin2_code":"AV",
    "gn:admin3_code":"64035.0",
    "gn:asciiname":"Molara",
    "gn:country_code":"IT",
    "gn:dem":408,
    "gn:feature_class":"P",
    "gn:feature_code":"PPL",
    "gn:name":"Molara",
    "gn:population":26,
    "gn:timezone":"Europe/Rome",
    "iso:country":"IT",
    "wof:name":"Molara",
    "wof:placetype":"locality",
    "wof:population":26
},
  "geometry": {"coordinates":[15.11744,41.03757],"type":"Point"}
}