{
  "type": "Feature",
  "properties": {
    "gn:admin1_code":"20.0",
    "gn:admin2_code":"VI",
    "gn:admin3_code":"24017.0",
    "gn:asciiname":"Carlassara I",
    "gn:country_code":"IT",
    "gn:dem":299,
    "gn:feature_class":"P",
    "gn:feature_code":"PPL",
    "gn:name":"Carlassara I",
    "gn:population":22,
    "gn:timezone":"Europe/Rome",
    "iso:country":"IT",
    "wof:name":"Carlassara I",
    "wof:placetype":"locality",
    "wof:population":22
},
  "geometry": {"coordinates":[11.3441,45.59569000000001],"type":"Point"}
}