{
  "type": "Feature",
  "properties": {
    "gn:admin1_code":"5.0",
    "gn:admin2_code":"BO",
    "gn:admin3_code":"37009.0",
    "gn:asciiname":"Casa Donini",
    "gn:cc2":"IT",
    "gn:country_code":"IT",
    "gn:dem":19,
    "gn:feature_class":"P",
    "gn:feature_code":"PPL",
    "gn:name":"Casa Donini",
    "gn:population":0,
    "gn:timezone":"Europe/Rome",
    "iso:country":"IT",
    "name:und_x_variant":[
        "San Chiara",
        "Casa Donini"
    ],
    "wof:name":"Casa Donini",
    "wof:placetype":"locality"
},
  "geometry": {"coordinates":[11.28333,44.58333],"type":"Point"}
}