{
  "type": "Feature",
  "properties": {
    "gn:admin1_code":"18",
    "gn:admin2_code":"PG",
    "gn:admin3_code":"54051.0",
    "gn:asciiname":"Francocci",
    "gn:country_code":"IT",
    "gn:dem":385,
    "gn:feature_class":"P",
    "gn:feature_code":"PPL",
    "gn:name":"Francocci",
    "gn:population":37,
    "gn:timezone":"Europe/Rome",
    "iso:country":"IT",
    "wof:name":"Francocci",
    "wof:placetype":"locality",
    "wof:population":37
},
  "geometry": {"coordinates":[12.63995,42.80926],"type":"Point"}
}