{
  "type": "Feature",
  "properties": {
    "gn:admin1_code":"9",
    "gn:admin2_code":"BS",
    "gn:admin3_code":"17043.0",
    "gn:asciiname":"Santa Giustina",
    "gn:country_code":"IT",
    "gn:dem":120,
    "gn:feature_class":"P",
    "gn:feature_code":"PPL",
    "gn:name":"Santa Giustina",
    "gn:population":50,
    "gn:timezone":"Europe/Rome",
    "iso:country":"IT",
    "wof:name":"Santa Giustina",
    "wof:placetype":"locality",
    "wof:population":50
},
  "geometry": {"coordinates":[10.28591,45.45663],"type":"Point"}
}