{
  "type": "Feature",
  "properties": {
    "gn:admin1_code":"9",
    "gn:admin2_code":"LO",
    "gn:admin3_code":"98049.0",
    "gn:asciiname":"Campagna",
    "gn:country_code":"IT",
    "gn:dem":48,
    "gn:feature_class":"P",
    "gn:feature_code":"PPL",
    "gn:name":"Campagna",
    "gn:population":30,
    "gn:timezone":"Europe/Rome",
    "iso:country":"IT",
    "wof:name":"Campagna",
    "wof:placetype":"locality",
    "wof:population":30
},
  "geometry": {"coordinates":[9.69031,45.08764],"type":"Point"}
}