{
  "type": "Feature",
  "properties": {
    "gn:admin1_code":"12",
    "gn:admin2_code":"BI",
    "gn:admin3_code":"96020.0",
    "gn:asciiname":"Monteferrario I",
    "gn:country_code":"IT",
    "gn:dem":334,
    "gn:feature_class":"P",
    "gn:feature_code":"PPL",
    "gn:name":"Monteferrario I",
    "gn:population":95,
    "gn:timezone":"Europe/Rome",
    "iso:country":"IT",
    "wof:name":"Monteferrario I",
    "wof:placetype":"locality",
    "wof:population":95
},
  "geometry": {"coordinates":[8.17689,45.58358],"type":"Point"}
}