{
  "type": "Feature",
  "properties": {
    "gn:admin1_code":"5",
    "gn:admin2_code":"RE",
    "gn:admin3_code":"35020.0",
    "gn:asciiname":"Mandriolo Inferiore",
    "gn:country_code":"IT",
    "gn:dem":29,
    "gn:feature_class":"P",
    "gn:feature_code":"PPL",
    "gn:name":"Mandriolo Inferiore",
    "gn:population":26,
    "gn:timezone":"Europe/Rome",
    "iso:country":"IT",
    "wof:name":"Mandriolo Inferiore",
    "wof:placetype":"locality",
    "wof:population":26
},
  "geometry": {"coordinates":[10.78204,44.78412],"type":"Point"}
}