{
  "type": "Feature",
  "properties": {
    "gn:admin1_code":"20",
    "gn:admin2_code":"PD",
    "gn:admin3_code":"28096.0",
    "gn:asciiname":"Ceresone",
    "gn:country_code":"IT",
    "gn:dem":19,
    "gn:feature_class":"P",
    "gn:feature_code":"PPL",
    "gn:name":"Ceresone",
    "gn:population":48,
    "gn:timezone":"Europe/Rome",
    "iso:country":"IT",
    "wof:name":"Ceresone",
    "wof:placetype":"locality",
    "wof:population":48
},
  "geometry": {"coordinates":[11.73658,45.44881],"type":"Point"}
}