{
  "type": "Feature",
  "properties": {
    "gn:admin1_code":"7",
    "gn:admin2_code":"LT",
    "gn:admin3_code":"59027.0",
    "gn:asciiname":"Abbadia di Valvisciolo",
    "gn:country_code":"IT",
    "gn:dem":105,
    "gn:feature_class":"P",
    "gn:feature_code":"PPL",
    "gn:name":"Abbadia di Valvisciolo",
    "gn:population":32,
    "gn:timezone":"Europe/Rome",
    "iso:country":"IT",
    "wof:name":"Abbadia di Valvisciolo",
    "wof:placetype":"locality",
    "wof:population":32
},
  "geometry": {"coordinates":[12.98093,41.56761],"type":"Point"}
}