{
  "type": "Feature",
  "properties": {
    "gn:admin1_code":"20",
    "gn:admin2_code":"VR",
    "gn:admin3_code":"23009.0",
    "gn:asciiname":"Moggia-Stra",
    "gn:country_code":"IT",
    "gn:dem":18,
    "gn:feature_class":"P",
    "gn:feature_code":"PPL",
    "gn:name":"Moggia-Stra",
    "gn:population":59,
    "gn:timezone":"Europe/Rome",
    "iso:country":"IT",
    "wof:name":"Moggia-Stra",
    "wof:placetype":"locality",
    "wof:population":59
},
  "geometry": {"coordinates":[11.28492,45.26739],"type":"Point"}
}