{
  "type": "Feature",
  "properties": {
    "gn:admin1_code":"12",
    "gn:admin2_code":"NO",
    "gn:admin3_code":"3052.0",
    "gn:asciiname":"Cascina Boscarolo",
    "gn:country_code":"IT",
    "gn:dem":269,
    "gn:feature_class":"P",
    "gn:feature_code":"PPL",
    "gn:name":"Cascina Boscarolo",
    "gn:population":60,
    "gn:timezone":"Europe/Rome",
    "iso:country":"IT",
    "wof:name":"Cascina Boscarolo",
    "wof:placetype":"locality",
    "wof:population":60
},
  "geometry": {"coordinates":[8.55295,45.71947],"type":"Point"}
}