{
  "type": "Feature",
  "properties": {
    "gn:admin1_code":"6",
    "gn:admin2_code":"PN",
    "gn:admin3_code":"93029.0",
    "gn:asciiname":"Case Squarzalovo",
    "gn:country_code":"IT",
    "gn:dem":11,
    "gn:feature_class":"P",
    "gn:feature_code":"PPL",
    "gn:name":"Case Squarzalovo",
    "gn:population":37,
    "gn:timezone":"Europe/Rome",
    "iso:country":"IT",
    "wof:name":"Case Squarzalovo",
    "wof:placetype":"locality",
    "wof:population":37
},
  "geometry": {"coordinates":[12.59716,45.84699000000001],"type":"Point"}
}