{
  "type": "Feature",
  "properties": {
    "gn:admin1_code":"9",
    "gn:admin2_code":"PV",
    "gn:admin3_code":"18164.0",
    "gn:asciiname":"Strada per Ottobiano",
    "gn:country_code":"IT",
    "gn:dem":96,
    "gn:feature_class":"P",
    "gn:feature_code":"PPL",
    "gn:name":"Strada per Ottobiano",
    "gn:population":18,
    "gn:timezone":"Europe/Rome",
    "iso:country":"IT",
    "wof:name":"Strada per Ottobiano",
    "wof:placetype":"locality",
    "wof:population":18
},
  "geometry": {"coordinates":[8.86431,45.20306],"type":"Point"}
}