{
  "type": "Feature",
  "properties": {
    "gn:admin1_code":"4.0",
    "gn:admin2_code":"SA",
    "gn:admin3_code":"65106.0",
    "gn:asciiname":"Serra",
    "gn:country_code":"IT",
    "gn:dem":269,
    "gn:feature_class":"P",
    "gn:feature_code":"PPL",
    "gn:name":"Serra",
    "gn:population":340,
    "gn:timezone":"Europe/Rome",
    "iso:country":"IT",
    "wof:name":"Serra",
    "wof:placetype":"locality",
    "wof:population":340
},
  "geometry": {"coordinates":[15.16228,40.44393],"type":"Point"}
}