{
  "type": "Feature",
  "properties": {
    "gn:admin1_code":"6",
    "gn:admin2_code":"UD",
    "gn:admin3_code":"30068.0",
    "gn:asciiname":"Colombatti",
    "gn:country_code":"IT",
    "gn:dem":151,
    "gn:feature_class":"P",
    "gn:feature_code":"PPL",
    "gn:name":"Colombatti",
    "gn:population":14,
    "gn:timezone":"Europe/Rome",
    "iso:country":"IT",
    "wof:name":"Colombatti",
    "wof:placetype":"locality",
    "wof:population":14
},
  "geometry": {"coordinates":[13.19042,46.11485],"type":"Point"}
}