{
  "type": "Feature",
  "properties": {
    "gn:admin1_code":"12",
    "gn:admin2_code":"VB",
    "gn:admin3_code":"103028.0",
    "gn:asciiname":"Rogoledo",
    "gn:country_code":"IT",
    "gn:dem":354,
    "gn:feature_class":"P",
    "gn:feature_code":"PPL",
    "gn:name":"Rogoledo",
    "gn:population":19,
    "gn:timezone":"Europe/Rome",
    "iso:country":"IT",
    "wof:name":"Rogoledo",
    "wof:placetype":"locality",
    "wof:population":19
},
  "geometry": {"coordinates":[8.27648,46.09379000000001],"type":"Point"}
}