{
  "type": "Feature",
  "properties": {
    "gn:admin1_code":"12",
    "gn:admin2_code":"TO",
    "gn:admin3_code":"1284.0",
    "gn:asciiname":"Betulle",
    "gn:country_code":"IT",
    "gn:dem":442,
    "gn:feature_class":"P",
    "gn:feature_code":"PPL",
    "gn:name":"Betulle",
    "gn:population":89,
    "gn:timezone":"Europe/Rome",
    "iso:country":"IT",
    "wof:name":"Betulle",
    "wof:placetype":"locality",
    "wof:population":89
},
  "geometry": {"coordinates":[7.47038,45.13032000000001],"type":"Point"}
}