{
  "type": "Feature",
  "properties": {
    "gn:admin1_code":"5.0",
    "gn:admin2_code":"MO",
    "gn:admin3_code":"36005.0",
    "gn:asciiname":"Fossoli",
    "gn:country_code":"IT",
    "gn:dem":25,
    "gn:elevation":"22.0",
    "gn:feature_class":"P",
    "gn:feature_code":"PPLL",
    "gn:name":"Fossoli",
    "gn:population":3578,
    "gn:timezone":"Europe/Rome",
    "iso:country":"IT",
    "name:azb_x_preferred":[
        "\u0641\u0648\u0633\u0644\u06cc"
    ],
    "name:eml_x_preferred":[
        "F\u00f2sel"
    ],
    "name:fas_x_preferred":[
        "\u0641\u0648\u0633\u0644\u06cc"
    ],
    "name:ita_x_preferred":[
        "Fossoli"
    ],
    "name:nld_x_preferred":[
        "Fossoli"
    ],
    "name:srp_x_preferred":[
        "\u0424\u043e\u0441\u043e\u043b\u0438"
    ],
    "wof:name":"Fossoli",
    "wof:placetype":"locality",
    "wof:population":3578
},
  "geometry": {"coordinates":[10.88977,44.8216],"type":"Point"}
}