{
  "type": "Feature",
  "properties": {
    "gn:admin1_code":"20",
    "gn:admin2_code":"VR",
    "gn:admin3_code":"23085.0",
    "gn:asciiname":"Trami",
    "gn:country_code":"IT",
    "gn:dem":10,
    "gn:feature_class":"P",
    "gn:feature_code":"PPL",
    "gn:name":"Trami",
    "gn:population":67,
    "gn:timezone":"Europe/Rome",
    "iso:country":"IT",
    "wof:name":"Trami",
    "wof:placetype":"locality",
    "wof:population":67
},
  "geometry": {"coordinates":[11.41445,45.14341],"type":"Point"}
}