{
  "type": "Feature",
  "properties": {
    "gn:admin1_code":"7.0",
    "gn:admin2_code":"VT",
    "gn:admin3_code":"56059.0",
    "gn:asciiname":"Magugnano",
    "gn:country_code":"IT",
    "gn:dem":293,
    "gn:feature_class":"P",
    "gn:feature_code":"PPL",
    "gn:name":"Magugnano",
    "gn:population":0,
    "gn:timezone":"Europe/Rome",
    "iso:country":"IT",
    "wof:name":"Magugnano",
    "wof:placetype":"locality"
},
  "geometry": {"coordinates":[12.16667,42.51667],"type":"Point"}
}