{
  "type": "Feature",
  "properties": {
    "gn:admin1_code":"1",
    "gn:admin2_code":"CH",
    "gn:admin3_code":"69076.0",
    "gn:asciiname":"Chiuse",
    "gn:country_code":"IT",
    "gn:dem":612,
    "gn:feature_class":"P",
    "gn:feature_code":"PPL",
    "gn:name":"Chiuse",
    "gn:population":23,
    "gn:timezone":"Europe/Rome",
    "iso:country":"IT",
    "wof:name":"Chiuse",
    "wof:placetype":"locality",
    "wof:population":23
},
  "geometry": {"coordinates":[14.47972,41.94135],"type":"Point"}
}