{
  "type": "Feature",
  "properties": {
    "gn:admin1_code":"9",
    "gn:admin2_code":"MI",
    "gn:admin3_code":"15179.0",
    "gn:asciiname":"Cascina Fabriziana",
    "gn:country_code":"IT",
    "gn:dem":153,
    "gn:feature_class":"P",
    "gn:feature_code":"PPL",
    "gn:name":"Cascina Fabriziana",
    "gn:population":58,
    "gn:timezone":"Europe/Rome",
    "iso:country":"IT",
    "wof:name":"Cascina Fabriziana",
    "wof:placetype":"locality",
    "wof:population":58
},
  "geometry": {"coordinates":[9.02112,45.52225],"type":"Point"}
}