{
  "type": "Feature",
  "properties": {
    "gn:admin1_code":"6",
    "gn:admin2_code":"PN",
    "gn:admin3_code":"93053.0",
    "gn:asciiname":"Fornasini",
    "gn:country_code":"IT",
    "gn:dem":47,
    "gn:feature_class":"P",
    "gn:feature_code":"PPL",
    "gn:name":"Fornasini",
    "gn:population":35,
    "gn:timezone":"Europe/Rome",
    "iso:country":"IT",
    "wof:name":"Fornasini",
    "wof:placetype":"locality",
    "wof:population":35
},
  "geometry": {"coordinates":[12.87164,45.9695],"type":"Point"}
}