{
  "type": "Feature",
  "properties": {
    "gn:admin1_code":"17",
    "gn:admin2_code":"TN",
    "gn:admin3_code":"22172.0",
    "gn:asciiname":"Valcava",
    "gn:country_code":"IT",
    "gn:dem":942,
    "gn:feature_class":"P",
    "gn:feature_code":"PPL",
    "gn:name":"Valcava",
    "gn:population":43,
    "gn:timezone":"Europe/Rome",
    "iso:country":"IT",
    "wof:name":"Valcava",
    "wof:placetype":"locality",
    "wof:population":43
},
  "geometry": {"coordinates":[11.31186,46.2064],"type":"Point"}
}