{
  "type": "Feature",
  "properties": {
    "gn:admin1_code":"5.0",
    "gn:admin2_code":"PC",
    "gn:admin3_code":"33020.0",
    "gn:asciiname":"Grondone Sopra",
    "gn:country_code":"IT",
    "gn:dem":1030,
    "gn:feature_class":"P",
    "gn:feature_code":"PPL",
    "gn:name":"Grondone Sopra",
    "gn:population":33,
    "gn:timezone":"Europe/Rome",
    "iso:country":"IT",
    "wof:name":"Grondone Sopra",
    "wof:placetype":"locality",
    "wof:population":33
},
  "geometry": {"coordinates":[9.46075,44.66527],"type":"Point"}
}