{
  "type": "Feature",
  "properties": {
    "gn:admin1_code":"3",
    "gn:admin2_code":"CS",
    "gn:admin3_code":"78040.0",
    "gn:asciiname":"San Martino",
    "gn:country_code":"IT",
    "gn:dem":407,
    "gn:feature_class":"P",
    "gn:feature_code":"PPL",
    "gn:name":"San Martino",
    "gn:population":43,
    "gn:timezone":"Europe/Rome",
    "iso:country":"IT",
    "name:bre_x_preferred":[
        "San Marti\u00f1o"
    ],
    "name:ceb_x_preferred":[
        "San Martino"
    ],
    "name:ces_x_preferred":[
        "San Martino"
    ],
    "name:deu_x_preferred":[
        "San Martino"
    ],
    "name:epo_x_preferred":[
        "San Martino"
    ],
    "name:fas_x_preferred":[
        "\u0633\u0646 \u0645\u0627\u0631\u062a\u06cc\u0646\u0648"
    ],
    "name:fra_x_preferred":[
        "San Martino"
    ],
    "name:glg_x_preferred":[
        "San Marti\u00f1o"
    ],
    "name:ita_x_preferred":[
        "San Martino"
    ],
    "name:kor_x_preferred":[
        "\uc0b0 \ub9c8\ub974\ud2f0\ub178"
    ],
    "name:nld_x_preferred":[
        "San Martino"
    ],
    "name:pol_x_preferred":[
        "San Martino"
    ],
    "name:por_x_preferred":[
        "San Martino"
    ],
    "name:rus_x_preferred":[
        "\u0421\u0432\u044f\u0442\u043e\u0439 \u041c\u0430\u0440\u0442\u0438\u043d"
    ],
    "name:srp_x_preferred":[
        "San Martino"
    ],
    "name:swe_x_preferred":[
        "San Martino"
    ],
    "wof:name":"San Martino",
    "wof:placetype":"locality",
    "wof:population":43
},
  "geometry": {"coordinates":[15.96808,39.5124],"type":"Point"}
}