{
  "type": "Feature",
  "properties": {
    "gn:admin1_code":"14",
    "gn:admin2_code":"SU",
    "gn:admin3_code":"111074.0",
    "gn:asciiname":"Seuni",
    "gn:country_code":"IT",
    "gn:dem":334,
    "gn:feature_class":"P",
    "gn:feature_code":"PPL",
    "gn:name":"Seuni",
    "gn:population":158,
    "gn:timezone":"Europe/Rome",
    "iso:country":"IT",
    "wof:name":"Seuni",
    "wof:placetype":"locality",
    "wof:population":158
},
  "geometry": {"coordinates":[9.11883,39.58399],"type":"Point"}
}