{
  "type": "Feature",
  "properties": {
    "gn:admin1_code":"7",
    "gn:admin2_code":"FR",
    "gn:admin3_code":"60033.0",
    "gn:asciiname":"Terravalle",
    "gn:country_code":"IT",
    "gn:dem":268,
    "gn:feature_class":"P",
    "gn:feature_code":"PPL",
    "gn:name":"Terravalle",
    "gn:population":93,
    "gn:timezone":"Europe/Rome",
    "iso:country":"IT",
    "wof:name":"Terravalle",
    "wof:placetype":"locality",
    "wof:population":93
},
  "geometry": {"coordinates":[13.29035,41.69328],"type":"Point"}
}