{
  "type": "Feature",
  "properties": {
    "gn:admin1_code":"16.0",
    "gn:admin2_code":"FI",
    "gn:admin3_code":"48001.0",
    "gn:asciiname":"Paterno",
    "gn:country_code":"IT",
    "gn:dem":220,
    "gn:elevation":"211.0",
    "gn:feature_class":"P",
    "gn:feature_code":"PPL",
    "gn:name":"Paterno",
    "gn:population":29,
    "gn:timezone":"Europe/Rome",
    "iso:country":"IT",
    "wof:name":"Paterno",
    "wof:placetype":"locality",
    "wof:population":29
},
  "geometry": {"coordinates":[11.3464,43.74392],"type":"Point"}
}