{
  "type": "Feature",
  "properties": {
    "gn:admin1_code":"16.0",
    "gn:admin2_code":"FI",
    "gn:admin3_code":"48001.0",
    "gn:asciiname":"Paterno",
    "gn:country_code":"IT",
    "gn:dem":220,
    "gn:elevation":"211.0",
    "gn:feature_class":"P",
    "gn:feature_code":"PPL",
    "gn:name":"Paterno",
    "gn:population":29,
    "gn:timezone":"Europe/Rome",
    "iso:country":"IT",
    "name:ceb_x_preferred":[
        "Paterno"
    ],
    "name:deu_x_preferred":[
        "Paterno"
    ],
    "name:fas_x_preferred":[
        "\u067e\u0627\u062a\u0631\u0646\u0648"
    ],
    "name:ita_x_preferred":[
        "Paterno"
    ],
    "name:nld_x_preferred":[
        "Paterno"
    ],
    "name:por_x_preferred":[
        "Paterno"
    ],
    "name:srp_x_preferred":[
        "\u041f\u0430\u0442\u0435\u0440\u043d\u043e"
    ],
    "name:swe_x_preferred":[
        "Paterno"
    ],
    "wof:name":"Paterno",
    "wof:placetype":"locality",
    "wof:population":29
},
  "geometry": {"coordinates":[11.3464,43.74392],"type":"Point"}
}