{
  "type": "Feature",
  "properties": {
    "gn:admin1_code":"12.0",
    "gn:admin2_code":"CN",
    "gn:admin3_code":"4148.0",
    "gn:asciiname":"Neive-Borgonovo",
    "gn:country_code":"IT",
    "gn:dem":236,
    "gn:feature_class":"P",
    "gn:feature_code":"PPLA3",
    "gn:name":"Neive-Borgonovo",
    "gn:population":1806,
    "gn:timezone":"Europe/Rome",
    "iso:country":"IT",
    "wof:name":"Neive-Borgonovo",
    "wof:placetype":"locality",
    "wof:population":1806
},
  "geometry": {"coordinates":[8.1178,44.72397],"type":"Point"}
}