{
  "type": "Feature",
  "properties": {
    "gn:admin1_code":"12",
    "gn:admin2_code":"CN",
    "gn:admin3_code":"4072.0",
    "gn:asciiname":"Vaschetti",
    "gn:country_code":"IT",
    "gn:dem":221,
    "gn:feature_class":"P",
    "gn:feature_code":"PPL",
    "gn:name":"Vaschetti",
    "gn:population":23,
    "gn:timezone":"Europe/Rome",
    "iso:country":"IT",
    "wof:name":"Vaschetti",
    "wof:placetype":"locality",
    "wof:population":23
},
  "geometry": {"coordinates":[7.99396,44.74098],"type":"Point"}
}