{
  "type": "Feature",
  "properties": {
    "gn:admin1_code":"8",
    "gn:admin2_code":"GE",
    "gn:admin3_code":"10023.0",
    "gn:asciiname":"Alvari",
    "gn:country_code":"IT",
    "gn:dem":457,
    "gn:feature_class":"P",
    "gn:feature_code":"PPL",
    "gn:name":"Alvari",
    "gn:population":16,
    "gn:timezone":"Europe/Rome",
    "iso:country":"IT",
    "wof:name":"Alvari",
    "wof:placetype":"locality",
    "wof:population":16
},
  "geometry": {"coordinates":[9.266,44.45631],"type":"Point"}
}