{
  "type": "Feature",
  "properties": {
    "gn:admin1_code":"12",
    "gn:admin2_code":"TO",
    "gn:admin3_code":"1142.0",
    "gn:asciiname":"Faule",
    "gn:country_code":"IT",
    "gn:dem":294,
    "gn:feature_class":"P",
    "gn:feature_code":"PPL",
    "gn:name":"Faule",
    "gn:population":26,
    "gn:timezone":"Europe/Rome",
    "iso:country":"IT",
    "wof:name":"Faule",
    "wof:placetype":"locality",
    "wof:population":26
},
  "geometry": {"coordinates":[7.41607,44.84932],"type":"Point"}
}