{
  "type": "Feature",
  "properties": {
    "gn:admin1_code":"12",
    "gn:admin2_code":"TO",
    "gn:admin3_code":"1142.0",
    "gn:asciiname":"Faule",
    "gn:country_code":"IT",
    "gn:dem":294,
    "gn:feature_class":"P",
    "gn:feature_code":"PPL",
    "gn:name":"Faule",
    "gn:population":26,
    "gn:timezone":"Europe/Rome",
    "iso:country":"IT",
    "name:azb_x_preferred":[
        "\u0641\u0627\u0648\u0644\u0647"
    ],
    "name:bel_x_preferred":[
        "\u0424\u0430\u0443\u043b\u0435"
    ],
    "name:bul_x_preferred":[
        "\u0424\u0430\u0443\u043b\u0435"
    ],
    "name:ceb_x_preferred":[
        "Faule"
    ],
    "name:deu_x_preferred":[
        "Faule"
    ],
    "name:epo_x_preferred":[
        "Faule"
    ],
    "name:eus_x_preferred":[
        "Faule"
    ],
    "name:fas_x_preferred":[
        "\u0641\u0627\u0648\u0644\u0647"
    ],
    "name:fra_x_preferred":[
        "Faule"
    ],
    "name:hun_x_preferred":[
        "Faule"
    ],
    "name:hye_x_preferred":[
        "\u0556\u0561\u0578\u0582\u056c\u0565"
    ],
    "name:ind_x_preferred":[
        "Faule"
    ],
    "name:ita_x_preferred":[
        "Faule"
    ],
    "name:jpn_x_preferred":[
        "\u30d5\u30a1\u30a6\u30ec"
    ],
    "name:kaz_x_preferred":[
        "\u0424\u0430\u0443\u043b\u0435"
    ],
    "name:lat_x_preferred":[
        "Fagulae"
    ],
    "name:lmo_x_preferred":[
        "Faule"
    ],
    "name:msa_x_preferred":[
        "Faule"
    ],
    "name:nap_x_preferred":[
        "Faule"
    ],
    "name:nld_x_preferred":[
        "Faule"
    ],
    "name:pms_x_preferred":[
        "F\u00e0ule"
    ],
    "name:pol_x_preferred":[
        "Faule"
    ],
    "name:por_x_preferred":[
        "Faule"
    ],
    "name:ron_x_preferred":[
        "Faule"
    ],
    "name:rus_x_preferred":[
        "\u0424\u0430\u0443\u043b\u0435"
    ],
    "name:scn_x_preferred":[
        "Faule"
    ],
    "name:spa_x_preferred":[
        "Faule"
    ],
    "name:srd_x_preferred":[
        "Faule"
    ],
    "name:srp_x_preferred":[
        "\u0424\u0430\u0443\u043b\u0435"
    ],
    "name:tgl_x_preferred":[
        "Faule"
    ],
    "name:ukr_x_preferred":[
        "\u0424\u0430\u0443\u043b\u0435"
    ],
    "name:uzb_x_preferred":[
        "Faule"
    ],
    "name:vie_x_preferred":[
        "Faule"
    ],
    "name:vol_x_preferred":[
        "Faule"
    ],
    "name:war_x_preferred":[
        "Faule"
    ],
    "wof:name":"Faule",
    "wof:placetype":"locality",
    "wof:population":26
},
  "geometry": {"coordinates":[7.41607,44.84932],"type":"Point"}
}