{
  "type": "Feature",
  "properties": {
    "gn:admin1_code":"9",
    "gn:admin2_code":"PV",
    "gn:admin3_code":"18105.0",
    "gn:asciiname":"Rosso",
    "gn:country_code":"IT",
    "gn:dem":190,
    "gn:feature_class":"P",
    "gn:feature_code":"PPL",
    "gn:name":"Rosso",
    "gn:population":26,
    "gn:timezone":"Europe/Rome",
    "iso:country":"IT",
    "name:afr_x_preferred":[
        "Rosso"
    ],
    "name:ara_x_preferred":[
        "\u0631\u0648\u0635\u0648"
    ],
    "name:azb_x_preferred":[
        "\u0631\u0648\u0633\u0648"
    ],
    "name:ben_x_preferred":[
        "\u09b0\u09cb\u09b8\u09b8\u09cb"
    ],
    "name:ceb_x_preferred":[
        "Rosso"
    ],
    "name:dan_x_preferred":[
        "Rosso"
    ],
    "name:deu_x_preferred":[
        "Rosso"
    ],
    "name:ell_x_preferred":[
        "\u03a1\u03cc\u03c3\u03bf"
    ],
    "name:eus_x_preferred":[
        "Rosso"
    ],
    "name:fas_x_preferred":[
        "\u0631\u0648\u0633\u0648"
    ],
    "name:fra_x_preferred":[
        "Rosso"
    ],
    "name:frr_x_preferred":[
        "Rosso"
    ],
    "name:heb_x_preferred":[
        "\u05e8\u05d5\u05e1\u05d5"
    ],
    "name:hin_x_preferred":[
        "\u0930\u094b\u0938\u094b"
    ],
    "name:hun_x_preferred":[
        "Rosso"
    ],
    "name:ind_x_preferred":[
        "Rosso"
    ],
    "name:ita_x_preferred":[
        "Rosso"
    ],
    "name:jpn_x_preferred":[
        "\u30ed\u30c3\u30bd"
    ],
    "name:kaz_x_preferred":[
        "\u0420\u043e\u0441\u043e"
    ],
    "name:lit_x_preferred":[
        "Rosas"
    ],
    "name:msa_x_preferred":[
        "Rosso"
    ],
    "name:nld_x_preferred":[
        "Rosso"
    ],
    "name:pol_x_preferred":[
        "Rosso"
    ],
    "name:por_x_preferred":[
        "Rosso"
    ],
    "name:ron_x_preferred":[
        "Rosso"
    ],
    "name:rus_x_preferred":[
        "\u0420\u043e\u0441\u043e"
    ],
    "name:spa_x_preferred":[
        "Rosso"
    ],
    "name:swe_x_preferred":[
        "Rosso"
    ],
    "name:ukr_x_preferred":[
        "\u0420\u043e\u0441\u043e"
    ],
    "name:urd_x_preferred":[
        "\u0631\u0648\u0635\u0648"
    ],
    "name:vep_x_preferred":[
        "Roso"
    ],
    "name:vie_x_preferred":[
        "Rosso"
    ],
    "name:zho_x_preferred":[
        "\u7f85\u7d22"
    ],
    "wof:name":"Rosso",
    "wof:placetype":"locality",
    "wof:population":26
},
  "geometry": {"coordinates":[9.19346,45.00334],"type":"Point"}
}