{
  "type": "Feature",
  "properties": {
    "gn:admin1_code":"9",
    "gn:admin2_code":"PV",
    "gn:admin3_code":"18105.0",
    "gn:asciiname":"Rosso",
    "gn:country_code":"IT",
    "gn:dem":190,
    "gn:feature_class":"P",
    "gn:feature_code":"PPL",
    "gn:name":"Rosso",
    "gn:population":26,
    "gn:timezone":"Europe/Rome",
    "iso:country":"IT",
    "wof:name":"Rosso",
    "wof:placetype":"locality",
    "wof:population":26
},
  "geometry": {"coordinates":[9.19346,45.00334],"type":"Point"}
}