{
  "type": "Feature",
  "properties": {
    "gn:admin1_code":"5.0",
    "gn:admin2_code":"PC",
    "gn:admin3_code":"33038.0",
    "gn:asciiname":"Roveleto Landi",
    "gn:cc2":"IT",
    "gn:country_code":"IT",
    "gn:dem":126,
    "gn:elevation":"127.0",
    "gn:feature_class":"P",
    "gn:feature_code":"PPL",
    "gn:name":"Roveleto Landi",
    "gn:population":224,
    "gn:timezone":"Europe/Rome",
    "iso:country":"IT",
    "name:und_x_variant":[
        "Roveleto Lando",
        "Roveleto Landi"
    ],
    "wof:name":"Roveleto Landi",
    "wof:placetype":"locality",
    "wof:population":224
},
  "geometry": {"coordinates":[9.60608,44.93556],"type":"Point"}
}