{
  "type": "Feature",
  "properties": {
    "gn:admin1_code":"17",
    "gn:admin2_code":"TN",
    "gn:admin3_code":"22080.0",
    "gn:asciiname":"Barco",
    "gn:country_code":"IT",
    "gn:dem":301,
    "gn:feature_class":"P",
    "gn:feature_code":"PPL",
    "gn:name":"Barco",
    "gn:population":103,
    "gn:timezone":"Europe/Rome",
    "iso:country":"IT",
    "wof:name":"Barco",
    "wof:placetype":"locality",
    "wof:population":103
},
  "geometry": {"coordinates":[11.14352,46.19963],"type":"Point"}
}