{
  "type": "Feature",
  "properties": {
    "gn:admin1_code":"16",
    "gn:admin2_code":"FI",
    "gn:admin3_code":"48017.0",
    "gn:asciiname":"Ema I",
    "gn:country_code":"IT",
    "gn:dem":78,
    "gn:feature_class":"P",
    "gn:feature_code":"PPL",
    "gn:name":"Ema I",
    "gn:population":30,
    "gn:timezone":"Europe/Rome",
    "iso:country":"IT",
    "wof:name":"Ema I",
    "wof:placetype":"locality",
    "wof:population":30
},
  "geometry": {"coordinates":[11.27117,43.74227],"type":"Point"}
}