{
  "type": "Feature",
  "properties": {
    "gn:admin1_code":"12",
    "gn:admin2_code":"VB",
    "gn:admin3_code":"103042.0",
    "gn:asciiname":"Merro",
    "gn:country_code":"IT",
    "gn:dem":485,
    "gn:feature_class":"P",
    "gn:feature_code":"PPL",
    "gn:name":"Merro",
    "gn:population":48,
    "gn:timezone":"Europe/Rome",
    "iso:country":"IT",
    "wof:name":"Merro",
    "wof:placetype":"locality",
    "wof:population":48
},
  "geometry": {"coordinates":[8.33891,46.13054],"type":"Point"}
}