{
  "type": "Feature",
  "properties": {
    "gn:admin1_code":"5.0",
    "gn:admin2_code":"MO",
    "gn:admin3_code":"36007.0",
    "gn:asciiname":"Sapi",
    "gn:country_code":"IT",
    "gn:dem":92,
    "gn:feature_class":"P",
    "gn:feature_code":"PPLL",
    "gn:name":"Sapi",
    "gn:population":4,
    "gn:timezone":"Europe/Rome",
    "iso:country":"IT",
    "wof:name":"Sapi",
    "wof:placetype":"locality",
    "wof:population":4
},
  "geometry": {"coordinates":[10.92794,44.53982],"type":"Point"}
}