{
  "type": "Feature",
  "properties": {
    "gn:admin1_code":"6",
    "gn:admin2_code":"UD",
    "gn:admin3_code":"30082.0",
    "gn:asciiname":"Casali Bianchini",
    "gn:country_code":"IT",
    "gn:dem":2,
    "gn:feature_class":"P",
    "gn:feature_code":"PPL",
    "gn:name":"Casali Bianchini",
    "gn:population":20,
    "gn:timezone":"Europe/Rome",
    "iso:country":"IT",
    "wof:name":"Casali Bianchini",
    "wof:placetype":"locality",
    "wof:population":20
},
  "geometry": {"coordinates":[13.0573,45.76998],"type":"Point"}
}