{
  "type": "Feature",
  "properties": {
    "gn:admin1_code":"20",
    "gn:admin2_code":"PD",
    "gn:admin3_code":"28003.0",
    "gn:asciiname":"Case Melchiotti",
    "gn:country_code":"IT",
    "gn:dem":9,
    "gn:feature_class":"P",
    "gn:feature_code":"PPL",
    "gn:name":"Case Melchiotti",
    "gn:population":68,
    "gn:timezone":"Europe/Rome",
    "iso:country":"IT",
    "wof:name":"Case Melchiotti",
    "wof:placetype":"locality",
    "wof:population":68
},
  "geometry": {"coordinates":[11.87335,45.33456],"type":"Point"}
}