{
  "type": "Feature",
  "properties": {
    "gn:admin1_code":"5",
    "gn:admin2_code":"BO",
    "gn:admin3_code":"37053.0",
    "gn:asciiname":"Piolino",
    "gn:country_code":"IT",
    "gn:dem":17,
    "gn:feature_class":"P",
    "gn:feature_code":"PPL",
    "gn:name":"Piolino",
    "gn:population":255,
    "gn:timezone":"Europe/Rome",
    "iso:country":"IT",
    "wof:name":"Piolino",
    "wof:placetype":"locality",
    "wof:population":255
},
  "geometry": {"coordinates":[11.17325,44.66571],"type":"Point"}
}