{
  "type": "Feature",
  "properties": {
    "gn:admin1_code":"17",
    "gn:admin2_code":"BZ",
    "gn:admin3_code":"21011.0",
    "gn:asciiname":"Sarnes",
    "gn:country_code":"IT",
    "gn:dem":599,
    "gn:feature_class":"P",
    "gn:feature_code":"PPL",
    "gn:name":"Sarnes",
    "gn:population":221,
    "gn:timezone":"Europe/Rome",
    "iso:country":"IT",
    "wof:name":"Sarnes",
    "wof:placetype":"locality",
    "wof:population":221
},
  "geometry": {"coordinates":[11.64773,46.68758],"type":"Point"}
}