{
  "type": "Feature",
  "properties": {
    "gn:admin1_code":"4",
    "gn:admin2_code":"CE",
    "gn:admin3_code":"61007.0",
    "gn:asciiname":"Vigna",
    "gn:country_code":"IT",
    "gn:dem":49,
    "gn:feature_class":"P",
    "gn:feature_code":"PPL",
    "gn:name":"Vigna",
    "gn:population":53,
    "gn:timezone":"Europe/Rome",
    "iso:country":"IT",
    "wof:name":"Vigna",
    "wof:placetype":"locality",
    "wof:population":53
},
  "geometry": {"coordinates":[14.24559,41.14709000000001],"type":"Point"}
}