{
  "type": "Feature",
  "properties": {
    "gn:admin1_code":"4",
    "gn:admin2_code":"CE",
    "gn:admin3_code":"61007.0",
    "gn:asciiname":"Vigna",
    "gn:country_code":"IT",
    "gn:dem":49,
    "gn:feature_class":"P",
    "gn:feature_code":"PPL",
    "gn:name":"Vigna",
    "gn:population":53,
    "gn:timezone":"Europe/Rome",
    "iso:country":"IT",
    "name:ara_x_preferred":[
        "\u0644\u0648\u0628\u064a\u0627\u0621"
    ],
    "name:cat_x_preferred":[
        "Vigna"
    ],
    "name:ceb_x_preferred":[
        "Vigna"
    ],
    "name:ces_x_preferred":[
        "Vigna"
    ],
    "name:dan_x_preferred":[
        "B\u00f8nne"
    ],
    "name:deu_x_preferred":[
        "Vigna"
    ],
    "name:epo_x_preferred":[
        "Vigno"
    ],
    "name:est_x_preferred":[
        "Vigna"
    ],
    "name:fas_x_preferred":[
        "\u0645\u0627\u0634"
    ],
    "name:fra_x_preferred":[
        "Vigna"
    ],
    "name:hye_x_preferred":[
        "\u0544\u0561\u0577"
    ],
    "name:ita_x_preferred":[
        "Vigna"
    ],
    "name:jpn_x_preferred":[
        "\u30b5\u30b5\u30b2\u5c5e"
    ],
    "name:kaz_x_preferred":[
        "\u0421\u0438\u044b\u0440\u0431\u04b1\u0440\u0448\u0430\u049b"
    ],
    "name:kor_x_preferred":[
        "\ub3d9\ubd80\uc18d"
    ],
    "name:lat_x_preferred":[
        "Vigna"
    ],
    "name:lit_x_preferred":[
        "Pupuol\u0117"
    ],
    "name:nld_x_preferred":[
        "Vigna"
    ],
    "name:por_x_preferred":[
        "Vigna"
    ],
    "name:rus_x_preferred":[
        "\u0412\u0438\u0433\u043d\u0430"
    ],
    "name:spa_x_preferred":[
        "Vigna"
    ],
    "name:srp_x_preferred":[
        "Vigna"
    ],
    "name:swe_x_preferred":[
        "Vignab\u00f6nssl\u00e4ktet"
    ],
    "name:tel_x_preferred":[
        "\u0c35\u0c3f\u0c17\u0c4d\u0c28\u0c3e"
    ],
    "name:vie_x_preferred":[
        "Chi \u0110\u1eadu"
    ],
    "name:war_x_preferred":[
        "Vigna"
    ],
    "name:zho_x_preferred":[
        "\u8c47\u8c46\u5c5e"
    ],
    "wof:name":"Vigna",
    "wof:placetype":"locality",
    "wof:population":53
},
  "geometry": {"coordinates":[14.24559,41.14709000000001],"type":"Point"}
}