{
  "type": "Feature",
  "properties": {
    "gn:admin1_code":"9.0",
    "gn:admin2_code":"SO",
    "gn:admin3_code":"14058.0",
    "gn:asciiname":"Gallivaggio",
    "gn:country_code":"IT",
    "gn:dem":1279,
    "gn:feature_class":"P",
    "gn:feature_code":"PPL",
    "gn:name":"Gallivaggio",
    "gn:population":0,
    "gn:timezone":"Europe/Rome",
    "iso:country":"IT",
    "wof:name":"Gallivaggio",
    "wof:placetype":"locality"
},
  "geometry": {"coordinates":[9.35,46.35],"type":"Point"}
}