{
  "type": "Feature",
  "properties": {
    "gn:admin1_code":"9",
    "gn:admin2_code":"BS",
    "gn:admin3_code":"17149.0",
    "gn:asciiname":"Gauzza",
    "gn:country_code":"IT",
    "gn:dem":55,
    "gn:feature_class":"P",
    "gn:feature_code":"PPL",
    "gn:name":"Gauzza",
    "gn:population":67,
    "gn:timezone":"Europe/Rome",
    "iso:country":"IT",
    "wof:name":"Gauzza",
    "wof:placetype":"locality",
    "wof:population":67
},
  "geometry": {"coordinates":[10.11925,45.27764000000001],"type":"Point"}
}