{
  "type": "Feature",
  "properties": {
    "gn:admin1_code":"9",
    "gn:admin2_code":"BG",
    "gn:admin3_code":"16186.0",
    "gn:asciiname":"Casabelli",
    "gn:country_code":"IT",
    "gn:dem":662,
    "gn:feature_class":"P",
    "gn:feature_code":"PPL",
    "gn:name":"Casabelli",
    "gn:population":33,
    "gn:timezone":"Europe/Rome",
    "iso:country":"IT",
    "wof:name":"Casabelli",
    "wof:placetype":"locality",
    "wof:population":33
},
  "geometry": {"coordinates":[9.50854,45.84576],"type":"Point"}
}