{
  "type": "Feature",
  "properties": {
    "gn:admin1_code":"18.0",
    "gn:admin2_code":"TR",
    "gn:admin3_code":"55032.0",
    "gn:asciiname":"San Liberatore",
    "gn:country_code":"IT",
    "gn:dem":420,
    "gn:elevation":"420.0",
    "gn:feature_class":"P",
    "gn:feature_code":"PPL",
    "gn:name":"San Liberatore",
    "gn:population":42,
    "gn:timezone":"Europe/Rome",
    "iso:country":"IT",
    "wof:name":"San Liberatore",
    "wof:placetype":"locality",
    "wof:population":42
},
  "geometry": {"coordinates":[12.71075,42.57097],"type":"Point"}
}