{
  "type": "Feature",
  "properties": {
    "gn:admin1_code":"4",
    "gn:admin2_code":"SA",
    "gn:admin3_code":"65089.0",
    "gn:asciiname":"Perrazze",
    "gn:country_code":"IT",
    "gn:dem":396,
    "gn:feature_class":"P",
    "gn:feature_code":"PPL",
    "gn:name":"Perrazze",
    "gn:population":286,
    "gn:timezone":"Europe/Rome",
    "iso:country":"IT",
    "wof:name":"Perrazze",
    "wof:placetype":"locality",
    "wof:population":286
},
  "geometry": {"coordinates":[15.29237,40.68057],"type":"Point"}
}