{
  "type": "Feature",
  "properties": {
    "gn:admin1_code":"20",
    "gn:admin2_code":"VR",
    "gn:admin3_code":"23070.0",
    "gn:asciiname":"Panarotti",
    "gn:country_code":"IT",
    "gn:dem":254,
    "gn:feature_class":"P",
    "gn:feature_code":"PPL",
    "gn:name":"Panarotti",
    "gn:population":27,
    "gn:timezone":"Europe/Rome",
    "iso:country":"IT",
    "wof:name":"Panarotti",
    "wof:placetype":"locality",
    "wof:population":27
},
  "geometry": {"coordinates":[11.231,45.54224],"type":"Point"}
}