{
  "type": "Feature",
  "properties": {
    "gn:admin1_code":"8",
    "gn:admin2_code":"GE",
    "gn:admin3_code":"10031.0",
    "gn:asciiname":"Boasi",
    "gn:country_code":"IT",
    "gn:dem":534,
    "gn:feature_class":"P",
    "gn:feature_code":"PPL",
    "gn:name":"Boasi",
    "gn:population":58,
    "gn:timezone":"Europe/Rome",
    "iso:country":"IT",
    "wof:name":"Boasi",
    "wof:placetype":"locality",
    "wof:population":58
},
  "geometry": {"coordinates":[9.12466,44.46873],"type":"Point"}
}