{
  "type": "Feature",
  "properties": {
    "gn:admin1_code":"12",
    "gn:admin2_code":"AL",
    "gn:admin3_code":"6127.0",
    "gn:asciiname":"Bellaria",
    "gn:country_code":"IT",
    "gn:dem":208,
    "gn:feature_class":"P",
    "gn:feature_code":"PPL",
    "gn:name":"Bellaria",
    "gn:population":239,
    "gn:timezone":"Europe/Rome",
    "iso:country":"IT",
    "wof:name":"Bellaria",
    "wof:placetype":"locality",
    "wof:population":239
},
  "geometry": {"coordinates":[8.75612,44.75735],"type":"Point"}
}