{
  "type": "Feature",
  "properties": {
    "iso:country":"IT",
    "name:deu_x_preferred":[
        "Casale"
    ],
    "name:fra_x_preferred":[
        "Casale"
    ],
    "name:hbs_x_preferred":[
        "Casale"
    ],
    "name:ita_x_preferred":[
        "Casale"
    ],
    "name:pms_x_preferred":[
        "Casal"
    ],
    "name:por_x_preferred":[
        "Casale"
    ],
    "name:rus_x_preferred":[
        "\u041a\u0430\u0437\u0430\u043b\u0435"
    ],
    "name:spa_x_preferred":[
        "Casale"
    ],
    "name:srp_x_preferred":[
        "Kazale"
    ],
    "qs:a0":"Italia",
    "qs:a1":"*Reggio di Calabria",
    "qs:a1r":"0Calabria",
    "qs:adm0":"Italia",
    "qs:la_lc":"*",
    "qs:level":"locality",
    "qs:loc":"Casale",
    "qs:loc_alt":"Casale",
    "qs:pop":0,
    "qs:type":"buffered point",
    "wd:wordcount":347,
    "wof:name":"Casale",
    "wof:placetype":"locality"
},
  "geometry": {"coordinates":[15.72421,38.044288],"type":"Point"}
}