{
  "type": "Feature",
  "properties": {
    "gn:admin1_code":"9",
    "gn:admin2_code":"BS",
    "gn:admin3_code":"17133.0",
    "gn:asciiname":"Boscolevato",
    "gn:country_code":"IT",
    "gn:dem":158,
    "gn:feature_class":"P",
    "gn:feature_code":"PPL",
    "gn:name":"Boscolevato",
    "gn:population":36,
    "gn:timezone":"Europe/Rome",
    "iso:country":"IT",
    "wof:name":"Boscolevato",
    "wof:placetype":"locality",
    "wof:population":36
},
  "geometry": {"coordinates":[9.87938,45.5611],"type":"Point"}
}