{
  "type": "Feature",
  "properties": {
    "gn:admin1_code":"5",
    "gn:admin2_code":"PR",
    "gn:admin3_code":"34002.0",
    "gn:asciiname":"Dorbora",
    "gn:country_code":"IT",
    "gn:dem":601,
    "gn:feature_class":"P",
    "gn:feature_code":"PPL",
    "gn:name":"Dorbora",
    "gn:population":18,
    "gn:timezone":"Europe/Rome",
    "iso:country":"IT",
    "wof:name":"Dorbora",
    "wof:placetype":"locality",
    "wof:population":18
},
  "geometry": {"coordinates":[9.66578,44.63629],"type":"Point"}
}