{
  "type": "Feature",
  "properties": {
    "gn:admin1_code":"18",
    "gn:admin2_code":"PG",
    "gn:admin3_code":"54030.0",
    "gn:asciiname":"Colle San Clemente",
    "gn:country_code":"IT",
    "gn:dem":332,
    "gn:feature_class":"P",
    "gn:feature_code":"PPL",
    "gn:name":"Colle San Clemente",
    "gn:population":108,
    "gn:timezone":"Europe/Rome",
    "iso:country":"IT",
    "wof:name":"Colle San Clemente",
    "wof:placetype":"locality",
    "wof:population":108
},
  "geometry": {"coordinates":[12.6543,42.90169],"type":"Point"}
}