{
  "type": "Feature",
  "properties": {
    "gn:admin1_code":"16.0",
    "gn:admin2_code":"PT",
    "gn:admin3_code":"47014.0",
    "gn:asciiname":"Corbezzi",
    "gn:country_code":"IT",
    "gn:dem":445,
    "gn:elevation":"440.0",
    "gn:feature_class":"P",
    "gn:feature_code":"PPL",
    "gn:name":"Corbezzi",
    "gn:population":24,
    "gn:timezone":"Europe/Rome",
    "iso:country":"IT",
    "wof:name":"Corbezzi",
    "wof:placetype":"locality",
    "wof:population":24
},
  "geometry": {"coordinates":[10.92133,43.99397],"type":"Point"}
}