{
  "type": "Feature",
  "properties": {
    "gn:admin1_code":"16",
    "gn:admin2_code":"SI",
    "gn:admin3_code":"52022.0",
    "gn:asciiname":"Campostaggia",
    "gn:country_code":"IT",
    "gn:dem":125,
    "gn:feature_class":"P",
    "gn:feature_code":"PPL",
    "gn:name":"Campostaggia",
    "gn:population":28,
    "gn:timezone":"Europe/Rome",
    "iso:country":"IT",
    "wof:name":"Campostaggia",
    "wof:placetype":"locality",
    "wof:population":28
},
  "geometry": {"coordinates":[11.14815,43.44988],"type":"Point"}
}