{
  "type": "Feature",
  "properties": {
    "gn:admin1_code":"16",
    "gn:admin2_code":"FI",
    "gn:admin3_code":"48030.0",
    "gn:asciiname":"Momigiano",
    "gn:country_code":"IT",
    "gn:dem":180,
    "gn:feature_class":"P",
    "gn:feature_code":"PPL",
    "gn:name":"Momigiano",
    "gn:population":33,
    "gn:timezone":"Europe/Rome",
    "iso:country":"IT",
    "wof:name":"Momigiano",
    "wof:placetype":"locality",
    "wof:population":33
},
  "geometry": {"coordinates":[11.05177,43.59962],"type":"Point"}
}