{
  "type": "Feature",
  "properties": {
    "gn:admin1_code":"9",
    "gn:admin2_code":"BS",
    "gn:admin3_code":"17136.0",
    "gn:asciiname":"Al Ponte",
    "gn:country_code":"IT",
    "gn:dem":205,
    "gn:feature_class":"P",
    "gn:feature_code":"PPL",
    "gn:name":"Al Ponte",
    "gn:population":43,
    "gn:timezone":"Europe/Rome",
    "iso:country":"IT",
    "wof:name":"Al Ponte",
    "wof:placetype":"locality",
    "wof:population":43
},
  "geometry": {"coordinates":[10.08207,45.60527],"type":"Point"}
}