{
  "type": "Feature",
  "properties": {
    "gn:admin1_code":"8.0",
    "gn:admin2_code":"GE",
    "gn:admin3_code":"10005.0",
    "gn:asciiname":"Brizzolara",
    "gn:country_code":"IT",
    "gn:dem":330,
    "gn:elevation":"310.0",
    "gn:feature_class":"P",
    "gn:feature_code":"PPL",
    "gn:name":"Brizzolara",
    "gn:population":98,
    "gn:timezone":"Europe/Rome",
    "iso:country":"IT",
    "wof:name":"Brizzolara",
    "wof:placetype":"locality",
    "wof:population":98
},
  "geometry": {"coordinates":[9.36807,44.4368],"type":"Point"}
}