{
  "type": "Feature",
  "properties": {
    "gn:admin1_code":"6",
    "gn:admin2_code":"PN",
    "gn:admin3_code":"93017.0",
    "gn:asciiname":"Battistin",
    "gn:country_code":"IT",
    "gn:dem":29,
    "gn:feature_class":"P",
    "gn:feature_code":"PPL",
    "gn:name":"Battistin",
    "gn:population":28,
    "gn:timezone":"Europe/Rome",
    "iso:country":"IT",
    "wof:name":"Battistin",
    "wof:placetype":"locality",
    "wof:population":28
},
  "geometry": {"coordinates":[12.71642,45.97114000000001],"type":"Point"}
}