{
  "type": "Feature",
  "properties": {
    "gn:admin1_code":"14.0",
    "gn:admin2_code":"SS",
    "gn:admin3_code":"90091.0",
    "gn:asciiname":"Tamarispa",
    "gn:country_code":"IT",
    "gn:dem":162,
    "gn:elevation":"178.0",
    "gn:feature_class":"P",
    "gn:feature_code":"PPL",
    "gn:name":"Tamarispa",
    "gn:population":219,
    "gn:timezone":"Europe/Rome",
    "iso:country":"IT",
    "wof:name":"Tamarispa",
    "wof:placetype":"locality",
    "wof:population":219
},
  "geometry": {"coordinates":[9.66596,40.68049],"type":"Point"}
}