{
  "type": "Feature",
  "properties": {
    "iso:country":"IT",
    "qs:a0":"Italia",
    "qs:a1":"*Treviso",
    "qs:a1r":"0Veneto",
    "qs:adm0":"Italia",
    "qs:la_lc":"*",
    "qs:level":"locality",
    "qs:loc":"Covolo - Levada",
    "qs:loc_alt":"Covolo - Levada",
    "qs:pop":0,
    "qs:type":"buffered point",
    "wof:name":"Covolo - Levada",
    "wof:placetype":"locality"
},
  "geometry": {"coordinates":[12.025039,45.85458],"type":"Point"}
}