{
  "type": "Feature",
  "properties": {
    "gn:admin1_code":"18.0",
    "gn:admin2_code":"PG",
    "gn:admin3_code":"54019.0",
    "gn:asciiname":"Strada Statale Flaminia",
    "gn:country_code":"IT",
    "gn:dem":446,
    "gn:feature_class":"P",
    "gn:feature_code":"PPLL",
    "gn:name":"Strada Statale Flaminia",
    "gn:population":2,
    "gn:timezone":"Europe/Rome",
    "iso:country":"IT",
    "wof:name":"Strada Statale Flaminia",
    "wof:placetype":"locality",
    "wof:population":2
},
  "geometry": {"coordinates":[12.75295,43.2974],"type":"Point"}
}