{
  "type": "Feature",
  "properties": {
    "gn:admin1_code":"9",
    "gn:admin2_code":"SO",
    "gn:admin3_code":"14015.0",
    "gn:asciiname":"Piatta",
    "gn:country_code":"IT",
    "gn:dem":691,
    "gn:feature_class":"P",
    "gn:feature_code":"PPL",
    "gn:name":"Piatta",
    "gn:population":88,
    "gn:timezone":"Europe/Rome",
    "iso:country":"IT",
    "wof:name":"Piatta",
    "wof:placetype":"locality",
    "wof:population":88
},
  "geometry": {"coordinates":[9.82176,46.1716],"type":"Point"}
}