{
  "type": "Feature",
  "properties": {
    "gn:admin1_code":"7.0",
    "gn:admin2_code":"LT",
    "gn:admin3_code":"59001.0",
    "gn:asciiname":"Camilleri-Vallelata",
    "gn:country_code":"IT",
    "gn:dem":74,
    "gn:feature_class":"P",
    "gn:feature_code":"PPL",
    "gn:name":"Camilleri-Vallelata",
    "gn:population":1101,
    "gn:timezone":"Europe/Rome",
    "iso:country":"IT",
    "wof:name":"Camilleri-Vallelata",
    "wof:placetype":"locality",
    "wof:population":1101
},
  "geometry": {"coordinates":[12.61738,41.59848],"type":"Point"}
}