{
  "type": "Feature",
  "properties": {
    "gn:admin1_code":"16",
    "gn:admin2_code":"MS",
    "gn:admin3_code":"45012.0",
    "gn:asciiname":"Serla",
    "gn:country_code":"IT",
    "gn:dem":209,
    "gn:feature_class":"P",
    "gn:feature_code":"PPL",
    "gn:name":"Serla",
    "gn:population":21,
    "gn:timezone":"Europe/Rome",
    "iso:country":"IT",
    "wof:name":"Serla",
    "wof:placetype":"locality",
    "wof:population":21
},
  "geometry": {"coordinates":[9.91701,44.30837],"type":"Point"}
}