{
  "type": "Feature",
  "properties": {
    "gn:admin1_code":"12.0",
    "gn:admin2_code":"CN",
    "gn:admin3_code":"4046.0",
    "gn:asciiname":"Baraccone",
    "gn:country_code":"IT",
    "gn:dem":154,
    "gn:feature_class":"P",
    "gn:feature_code":"PPL",
    "gn:name":"Baraccone",
    "gn:population":778,
    "gn:timezone":"Europe/Rome",
    "iso:country":"IT",
    "wof:name":"Baraccone",
    "wof:placetype":"locality",
    "wof:population":778
},
  "geometry": {"coordinates":[8.06242,44.74633],"type":"Point"}
}