{
  "type": "Feature",
  "properties": {
    "gn:admin1_code":"20.0",
    "gn:admin2_code":"BL",
    "gn:admin3_code":"25072.0",
    "gn:asciiname":"Cornei",
    "gn:country_code":"IT",
    "gn:dem":456,
    "gn:feature_class":"P",
    "gn:feature_code":"PPL",
    "gn:name":"Cornei",
    "gn:population":661,
    "gn:timezone":"Europe/Rome",
    "iso:country":"IT",
    "wof:name":"Cornei",
    "wof:placetype":"locality",
    "wof:population":661
},
  "geometry": {"coordinates":[12.38097,46.14098],"type":"Point"}
}