{
  "type": "Feature",
  "properties": {
    "gn:admin1_code":"4",
    "gn:admin2_code":"BN",
    "gn:admin3_code":"62070.0",
    "gn:asciiname":"Mosielli",
    "gn:country_code":"IT",
    "gn:dem":182,
    "gn:feature_class":"P",
    "gn:feature_code":"PPL",
    "gn:name":"Mosielli",
    "gn:population":32,
    "gn:timezone":"Europe/Rome",
    "iso:country":"IT",
    "wof:name":"Mosielli",
    "wof:placetype":"locality",
    "wof:population":32
},
  "geometry": {"coordinates":[14.50866,41.11789],"type":"Point"}
}