{
  "type": "Feature",
  "properties": {
    "gn:admin1_code":"9",
    "gn:admin2_code":"MI",
    "gn:admin3_code":"15150.0",
    "gn:asciiname":"Cascina Ticinello",
    "gn:country_code":"IT",
    "gn:dem":107,
    "gn:feature_class":"P",
    "gn:feature_code":"PPL",
    "gn:name":"Cascina Ticinello",
    "gn:population":21,
    "gn:timezone":"Europe/Rome",
    "iso:country":"IT",
    "wof:name":"Cascina Ticinello",
    "wof:placetype":"locality",
    "wof:population":21
},
  "geometry": {"coordinates":[8.9757,45.36116],"type":"Point"}
}