{
  "type": "Feature",
  "properties": {
    "gn:admin1_code":"15",
    "gn:admin2_code":"PA",
    "gn:admin3_code":"82073.0",
    "gn:asciiname":"Golden Hill III",
    "gn:country_code":"IT",
    "gn:dem":283,
    "gn:feature_class":"P",
    "gn:feature_code":"PPLL",
    "gn:name":"Golden Hill III",
    "gn:population":8,
    "gn:timezone":"Europe/Rome",
    "iso:country":"IT",
    "wof:name":"Golden Hill III",
    "wof:placetype":"locality",
    "wof:population":8
},
  "geometry": {"coordinates":[13.61514,37.97051],"type":"Point"}
}