{
  "type": "Feature",
  "properties": {
    "gn:admin1_code":"4",
    "gn:admin2_code":"CE",
    "gn:admin3_code":"61009.0",
    "gn:asciiname":"Cesarano",
    "gn:country_code":"IT",
    "gn:dem":48,
    "gn:feature_class":"P",
    "gn:feature_code":"PPL",
    "gn:name":"Cesarano",
    "gn:population":233,
    "gn:timezone":"Europe/Rome",
    "iso:country":"IT",
    "wof:name":"Cesarano",
    "wof:placetype":"locality",
    "wof:population":233
},
  "geometry": {"coordinates":[14.36232,41.16688],"type":"Point"}
}