{
  "type": "Feature",
  "properties": {
    "gn:admin1_code":"9.0",
    "gn:admin2_code":"MI",
    "gn:admin3_code":"15044.0",
    "gn:asciiname":"Torrazza dei Mandelli",
    "gn:country_code":"IT",
    "gn:dem":158,
    "gn:feature_class":"P",
    "gn:feature_code":"PPL",
    "gn:name":"Torrazza dei Mandelli",
    "gn:population":1046,
    "gn:timezone":"Europe/Rome",
    "iso:country":"IT",
    "wof:name":"Torrazza dei Mandelli",
    "wof:placetype":"locality",
    "wof:population":1046
},
  "geometry": {"coordinates":[9.39921,45.56629],"type":"Point"}
}