{
  "type": "Feature",
  "properties": {
    "gn:admin1_code":"8",
    "gn:admin2_code":"SP",
    "gn:admin3_code":"11008.0",
    "gn:asciiname":"Tranci",
    "gn:country_code":"IT",
    "gn:dem":319,
    "gn:feature_class":"P",
    "gn:feature_code":"PPL",
    "gn:name":"Tranci",
    "gn:population":79,
    "gn:timezone":"Europe/Rome",
    "iso:country":"IT",
    "wof:name":"Tranci",
    "wof:placetype":"locality",
    "wof:population":79
},
  "geometry": {"coordinates":[9.85559,44.20787],"type":"Point"}
}