{
  "type": "Feature",
  "properties": {
    "gn:admin1_code":"18.0",
    "gn:admin2_code":"PG",
    "gn:admin3_code":"54009.0",
    "gn:asciiname":"Cantagallina",
    "gn:country_code":"IT",
    "gn:dem":364,
    "gn:feature_class":"P",
    "gn:feature_code":"PPL",
    "gn:name":"Cantagallina",
    "gn:population":34,
    "gn:timezone":"Europe/Rome",
    "iso:country":"IT",
    "wof:name":"Cantagallina",
    "wof:placetype":"locality",
    "wof:population":34
},
  "geometry": {"coordinates":[12.01124,43.03981],"type":"Point"}
}