{
  "type": "Feature",
  "properties": {
    "gn:admin1_code":"18.0",
    "gn:admin2_code":"PG",
    "gn:admin3_code":"54015.0",
    "gn:asciiname":"Fratte",
    "gn:cc2":"IT",
    "gn:country_code":"IT",
    "gn:dem":252,
    "gn:feature_class":"P",
    "gn:feature_code":"PPL",
    "gn:name":"Fratte",
    "gn:population":0,
    "gn:timezone":"Europe/Rome",
    "iso:country":"IT",
    "name:ceb_x_preferred":[
        "Fratte"
    ],
    "name:deu_x_preferred":[
        "Fratte"
    ],
    "name:ita_x_preferred":[
        "Fratte"
    ],
    "name:srp_x_preferred":[
        "Frate"
    ],
    "name:swe_x_preferred":[
        "Fratte"
    ],
    "name:und_x_variant":[
        "Le Fratte"
    ],
    "wof:name":"Fratte",
    "wof:placetype":"locality"
},
  "geometry": {"coordinates":[12.28333,43.16667],"type":"Point"}
}