{
  "type": "Feature",
  "properties": {
    "gn:admin1_code":"11",
    "gn:admin2_code":"IS",
    "gn:admin3_code":"94030.0",
    "gn:asciiname":"Campo Sant'Angelo",
    "gn:country_code":"IT",
    "gn:dem":307,
    "gn:feature_class":"P",
    "gn:feature_code":"PPL",
    "gn:name":"Campo Sant'Angelo",
    "gn:population":15,
    "gn:timezone":"Europe/Rome",
    "iso:country":"IT",
    "name:fra_x_preferred":[
        "Campo Sant'Angelo"
    ],
    "name:ita_x_preferred":[
        "Campo Sant'Angelo"
    ],
    "wof:name":"Campo Sant'Angelo",
    "wof:placetype":"locality",
    "wof:population":15
},
  "geometry": {"coordinates":[14.16905,41.5211],"type":"Point"}
}