{
  "type": "Feature",
  "properties": {
    "gn:admin1_code":"1.0",
    "gn:admin2_code":"TE",
    "gn:admin3_code":"67018.0",
    "gn:asciiname":"Cretara",
    "gn:country_code":"IT",
    "gn:dem":519,
    "gn:feature_class":"P",
    "gn:feature_code":"PPL",
    "gn:name":"Cretara",
    "gn:population":73,
    "gn:timezone":"Europe/Rome",
    "iso:country":"IT",
    "wof:name":"Cretara",
    "wof:placetype":"locality",
    "wof:population":73
},
  "geometry": {"coordinates":[13.65432,42.52618],"type":"Point"}
}