{
  "type": "Feature",
  "properties": {
    "gn:admin1_code":"10.0",
    "gn:admin2_code":"AP",
    "gn:admin3_code":"44015.0",
    "gn:asciiname":"Casale",
    "gn:country_code":"IT",
    "gn:dem":653,
    "gn:elevation":"665.0",
    "gn:feature_class":"P",
    "gn:feature_code":"PPL",
    "gn:name":"Casale",
    "gn:population":12,
    "gn:timezone":"Europe/Rome",
    "iso:country":"IT",
    "name:ceb_x_preferred":[
        "Casale"
    ],
    "name:deu_x_preferred":[
        "Casale"
    ],
    "name:fra_x_preferred":[
        "Casale"
    ],
    "name:ita_x_preferred":[
        "Casale"
    ],
    "name:lat_x_preferred":[
        "Casale"
    ],
    "name:pol_x_preferred":[
        "Casale"
    ],
    "name:por_x_preferred":[
        "Casale"
    ],
    "name:rus_x_preferred":[
        "\u041a\u0430\u0437\u0430\u043b\u0435"
    ],
    "name:spa_x_preferred":[
        "Casale"
    ],
    "name:srp_x_preferred":[
        "\u041a\u0430\u0437\u0430\u043b\u0435"
    ],
    "name:swe_x_preferred":[
        "Casale"
    ],
    "wof:name":"Casale",
    "wof:placetype":"locality",
    "wof:population":12
},
  "geometry": {"coordinates":[13.43414,42.8977],"type":"Point"}
}