{
  "type": "Feature",
  "properties": {
    "gn:admin1_code":"20",
    "gn:admin2_code":"VR",
    "gn:admin3_code":"23063.0",
    "gn:asciiname":"Banduani (Chiesuola)",
    "gn:country_code":"IT",
    "gn:dem":103,
    "gn:feature_class":"P",
    "gn:feature_code":"PPL",
    "gn:name":"Banduani (Chiesuola)",
    "gn:population":44,
    "gn:timezone":"Europe/Rome",
    "iso:country":"IT",
    "wof:name":"Banduani (Chiesuola)",
    "wof:placetype":"locality",
    "wof:population":44
},
  "geometry": {"coordinates":[11.31275,45.47468],"type":"Point"}
}