{
  "type": "Feature",
  "properties": {
    "gn:admin1_code":"4",
    "gn:admin2_code":"SA",
    "gn:admin3_code":"65119.0",
    "gn:asciiname":"Capolomonte",
    "gn:country_code":"IT",
    "gn:dem":302,
    "gn:feature_class":"P",
    "gn:feature_code":"PPL",
    "gn:name":"Capolomonte",
    "gn:population":45,
    "gn:timezone":"Europe/Rome",
    "iso:country":"IT",
    "wof:name":"Capolomonte",
    "wof:placetype":"locality",
    "wof:population":45
},
  "geometry": {"coordinates":[15.4671,40.07158],"type":"Point"}
}