{
  "type": "Feature",
  "properties": {
    "gn:admin1_code":"15",
    "gn:admin2_code":"RG",
    "gn:admin3_code":"88012.0",
    "gn:asciiname":"Borgo Micciche III",
    "gn:country_code":"IT",
    "gn:dem":182,
    "gn:feature_class":"P",
    "gn:feature_code":"PPL",
    "gn:name":"Borgo Miccich\u00e8 III",
    "gn:population":31,
    "gn:timezone":"Europe/Rome",
    "iso:country":"IT",
    "name:und_x_variant":[
        "Borgo Miccich\u00e8 III"
    ],
    "wof:name":"Borgo Micciche III",
    "wof:placetype":"locality",
    "wof:population":31
},
  "geometry": {"coordinates":[14.58193,36.9673],"type":"Point"}
}