{
  "type": "Feature",
  "properties": {
    "gn:admin1_code":"16.0",
    "gn:admin2_code":"LU",
    "gn:admin3_code":"46024.0",
    "gn:asciiname":"Fiumetto",
    "gn:cc2":"IT",
    "gn:country_code":"IT",
    "gn:dem":5,
    "gn:feature_class":"P",
    "gn:feature_code":"PPL",
    "gn:name":"Fiumetto",
    "gn:population":0,
    "gn:timezone":"Europe/Rome",
    "iso:country":"IT",
    "name:und_x_variant":[
        "Fiumello"
    ],
    "wof:name":"Fiumetto",
    "wof:placetype":"locality"
},
  "geometry": {"coordinates":[10.18484,43.94253],"type":"Point"}
}