{
  "type": "Feature",
  "properties": {
    "gn:admin1_code":"12",
    "gn:admin2_code":"AT",
    "gn:admin3_code":"5050.0",
    "gn:asciiname":"Alliere",
    "gn:country_code":"IT",
    "gn:dem":244,
    "gn:feature_class":"P",
    "gn:feature_code":"PPL",
    "gn:name":"Alliere",
    "gn:population":26,
    "gn:timezone":"Europe/Rome",
    "iso:country":"IT",
    "wof:name":"Alliere",
    "wof:placetype":"locality",
    "wof:population":26
},
  "geometry": {"coordinates":[8.17408,44.79363],"type":"Point"}
}