{
  "type": "Feature",
  "properties": {
    "gn:admin1_code":"12",
    "gn:admin2_code":"TO",
    "gn:admin3_code":"1313.0",
    "gn:asciiname":"Oldri",
    "gn:country_code":"IT",
    "gn:dem":788,
    "gn:feature_class":"P",
    "gn:feature_code":"PPL",
    "gn:name":"Oldr\u00ec",
    "gn:population":25,
    "gn:timezone":"Europe/Rome",
    "iso:country":"IT",
    "name:und_x_variant":[
        "Oldr\u00ec"
    ],
    "wof:name":"Oldri",
    "wof:placetype":"locality",
    "wof:population":25
},
  "geometry": {"coordinates":[7.38193,45.23967],"type":"Point"}
}