{
  "type": "Feature",
  "properties": {
    "gn:admin1_code":"3",
    "gn:admin2_code":"CS",
    "gn:admin3_code":"78014.0",
    "gn:asciiname":"Surda",
    "gn:country_code":"IT",
    "gn:dem":707,
    "gn:feature_class":"P",
    "gn:feature_code":"PPL",
    "gn:name":"Surda",
    "gn:population":46,
    "gn:timezone":"Europe/Rome",
    "iso:country":"IT",
    "wof:name":"Surda",
    "wof:placetype":"locality",
    "wof:population":46
},
  "geometry": {"coordinates":[16.28756,39.18345],"type":"Point"}
}