{
  "type": "Feature",
  "properties": {
    "gn:admin1_code":"3",
    "gn:admin2_code":"CS",
    "gn:admin3_code":"78014.0",
    "gn:asciiname":"Surda",
    "gn:country_code":"IT",
    "gn:dem":707,
    "gn:feature_class":"P",
    "gn:feature_code":"PPL",
    "gn:name":"Surda",
    "gn:population":46,
    "gn:timezone":"Europe/Rome",
    "iso:country":"IT",
    "name:ara_x_preferred":[
        "\u0633\u0631\u062f\u0627"
    ],
    "name:cat_x_preferred":[
        "Surda"
    ],
    "name:heb_x_preferred":[
        "\u05e1\u05d5\u05e8\u05d3\u05d0"
    ],
    "name:pol_x_preferred":[
        "Surda"
    ],
    "wof:name":"Surda",
    "wof:placetype":"locality",
    "wof:population":46
},
  "geometry": {"coordinates":[16.28756,39.18345],"type":"Point"}
}