{
  "type": "Feature",
  "properties": {
    "gn:admin1_code":"11",
    "gn:admin2_code":"CB",
    "gn:admin3_code":"70081.0",
    "gn:asciiname":"Montagna III",
    "gn:country_code":"IT",
    "gn:dem":502,
    "gn:feature_class":"P",
    "gn:feature_code":"PPL",
    "gn:name":"Montagna III",
    "gn:population":54,
    "gn:timezone":"Europe/Rome",
    "iso:country":"IT",
    "wof:name":"Montagna III",
    "wof:placetype":"locality",
    "wof:population":54
},
  "geometry": {"coordinates":[14.60341,41.79107],"type":"Point"}
}