{
  "type": "Feature",
  "properties": {
    "gn:admin1_code":"12.0",
    "gn:admin2_code":"CN",
    "gn:admin3_code":"4183.0",
    "gn:asciiname":"Tetto Malanoce",
    "gn:cc2":"IT",
    "gn:country_code":"IT",
    "gn:dem":1254,
    "gn:feature_class":"P",
    "gn:feature_code":"PPL",
    "gn:name":"Tetto Malanoce",
    "gn:population":0,
    "gn:timezone":"Europe/Rome",
    "iso:country":"IT",
    "name:und_x_variant":[
        "Malanoce",
        "Tetto Malanoce"
    ],
    "wof:name":"Tetto Malanoce",
    "wof:placetype":"locality"
},
  "geometry": {"coordinates":[7.46667,44.25],"type":"Point"}
}