{
  "type": "Feature",
  "properties": {
    "gn:admin1_code":"5",
    "gn:admin2_code":"MO",
    "gn:admin3_code":"36007.0",
    "gn:asciiname":"Balugola",
    "gn:country_code":"IT",
    "gn:dem":78,
    "gn:feature_class":"P",
    "gn:feature_code":"PPL",
    "gn:name":"Balugola",
    "gn:population":168,
    "gn:timezone":"Europe/Rome",
    "iso:country":"IT",
    "wof:name":"Balugola",
    "wof:placetype":"locality",
    "wof:population":168
},
  "geometry": {"coordinates":[10.946,44.54015],"type":"Point"}
}