{
  "type": "Feature",
  "properties": {
    "gn:elevation":56,
    "gn:population":45463,
    "iso:country":"IT",
    "name:ces_x_preferred":[
        "San Giorgio a Cremano"
    ],
    "name:eng_x_preferred":[
        "S.giorgio A Cremano"
    ],
    "name:eng_x_variant":[
        "San Giorgio a Cremano",
        "S.giorgio A Cremano"
    ],
    "name:epo_x_preferred":[
        "San Giorgio a Cremano"
    ],
    "name:fra_x_preferred":[
        "San Giorgio a Cremano"
    ],
    "name:ita_x_preferred":[
        "San Giorgio A Cremano"
    ],
    "name:ita_x_variant":[
        "S Giorgio A Cremano",
        "S. Giorgio A Cremano",
        "San Giorgio a Cremano"
    ],
    "name:jpn_x_preferred":[
        "\u30b5\u30f3\u30fb\u30b8\u30e7\u30eb\u30b8\u30e7\u30fb\u30a2\u30fb\u30af\u30ec\u30de\u30fc\u30ce"
    ],
    "name:nap_x_preferred":[
        "San Giorgio a Cremano"
    ],
    "name:nld_x_preferred":[
        "San Giorgio a Cremano"
    ],
    "name:pol_x_preferred":[
        "San Giorgio a Cremano"
    ],
    "name:por_x_preferred":[
        "San Giorgio a Cremano"
    ],
    "name:spa_x_preferred":[
        "San Giorgio a Cremano"
    ],
    "name:unk_x_variant":[
        "San Giorgio A Cremano"
    ],
    "qs:gn_adm0_cc":"IT",
    "qs:gn_fcode":"PPLA3",
    "qs:gn_local":6537348,
    "qs:gn_nam_loc":"San Giorgio a Cremano, Napoli, Campania, IT",
    "qs:gn_namadm1":"04",
    "qs:gn_name":"San Giorgio a Cremano",
    "qs:local_max":1716,
    "qs:local_sum":1716,
    "qs:localhoods":1,
    "qs:name":"San Giorgio A Cremano",
    "qs:name_adm0":"Italia",
    "qs:name_adm1":"Campania",
    "qs:name_adm2":"Napoli",
    "qs:name_en":"S.giorgio A Cremano",
    "qs:name_lau":"San Giorgio a Cremano",
    "qs:name_local":"San Giorgio a Cremano",
    "qs:photo_max":736,
    "qs:photo_sum":1716,
    "qs:placetype":"Suburb",
    "qs:quad_count":81,
    "qs:woe_adm0":23424853,
    "qs:woe_adm1":7153333,
    "qs:woe_adm2":12591829,
    "qs:woe_lau":12681637,
    "qs:woe_local":12681637,
    "qs:woe_ver":"7.10.0",
    "wof:name":"San Giorgio A Cremano",
    "wof:placetype":"neighbourhood",
    "wof:population":45463
},
  "geometry": {"coordinates":[14.35514,40.816516],"type":"Point"}
}