{
  "type": "Feature",
  "properties": {
    "gn:admin1_code":"9",
    "gn:admin2_code":"BS",
    "gn:admin3_code":"17198.0",
    "gn:asciiname":"Davena",
    "gn:country_code":"IT",
    "gn:dem":972,
    "gn:feature_class":"P",
    "gn:feature_code":"PPL",
    "gn:name":"Davena",
    "gn:population":99,
    "gn:timezone":"Europe/Rome",
    "iso:country":"IT",
    "wof:name":"Davena",
    "wof:placetype":"locality",
    "wof:population":99
},
  "geometry": {"coordinates":[10.37885,46.23234],"type":"Point"}
}