{
  "type": "Feature",
  "properties": {
    "gn:admin1_code":"20",
    "gn:admin2_code":"VR",
    "gn:admin3_code":"23002.0",
    "gn:asciiname":"Cadelsette",
    "gn:country_code":"IT",
    "gn:dem":23,
    "gn:feature_class":"P",
    "gn:feature_code":"PPL",
    "gn:name":"Cadelsette",
    "gn:population":75,
    "gn:timezone":"Europe/Rome",
    "iso:country":"IT",
    "wof:name":"Cadelsette",
    "wof:placetype":"locality",
    "wof:population":75
},
  "geometry": {"coordinates":[11.30089,45.30891],"type":"Point"}
}