{
  "type": "Feature",
  "properties": {
    "gn:admin1_code":"8.0",
    "gn:admin2_code":"GE",
    "gn:admin3_code":"10013.0",
    "gn:asciiname":"Santuario Loreto",
    "gn:country_code":"IT",
    "gn:dem":348,
    "gn:feature_class":"P",
    "gn:feature_code":"PPL",
    "gn:name":"Santuario Loreto",
    "gn:population":0,
    "gn:timezone":"Europe/Rome",
    "iso:country":"IT",
    "wof:name":"Santuario Loreto",
    "wof:placetype":"locality"
},
  "geometry": {"coordinates":[9.48978,44.27092],"type":"Point"}
}