{
  "type": "Feature",
  "properties": {
    "gn:admin1_code":"16",
    "gn:admin2_code":"MS",
    "gn:admin3_code":"45002.0",
    "gn:asciiname":"Valle-Montale",
    "gn:country_code":"IT",
    "gn:dem":448,
    "gn:feature_class":"P",
    "gn:feature_code":"PPL",
    "gn:name":"Valle-Montale",
    "gn:population":38,
    "gn:timezone":"Europe/Rome",
    "iso:country":"IT",
    "wof:name":"Valle-Montale",
    "wof:placetype":"locality",
    "wof:population":38
},
  "geometry": {"coordinates":[9.99937,44.34665],"type":"Point"}
}