{
  "type": "Feature",
  "properties": {
    "gn:admin1_code":"10",
    "gn:admin2_code":"AP",
    "gn:admin3_code":"44027.0",
    "gn:asciiname":"Bonifica",
    "gn:country_code":"IT",
    "gn:dem":71,
    "gn:feature_class":"P",
    "gn:feature_code":"PPLL",
    "gn:name":"Bonifica",
    "gn:population":9,
    "gn:timezone":"Europe/Rome",
    "iso:country":"IT",
    "wof:name":"Bonifica",
    "wof:placetype":"locality",
    "wof:population":9
},
  "geometry": {"coordinates":[13.67589,42.84597],"type":"Point"}
}