{
  "type": "Feature",
  "properties": {
    "gn:admin1_code":"5",
    "gn:admin2_code":"RE",
    "gn:admin3_code":"35046.0",
    "gn:asciiname":"Fornolo",
    "gn:country_code":"IT",
    "gn:dem":815,
    "gn:feature_class":"P",
    "gn:feature_code":"PPL",
    "gn:name":"Fornolo",
    "gn:population":29,
    "gn:timezone":"Europe/Rome",
    "iso:country":"IT",
    "wof:name":"Fornolo",
    "wof:placetype":"locality",
    "wof:population":29
},
  "geometry": {"coordinates":[10.22042,44.38373],"type":"Point"}
}