{
  "type": "Feature",
  "properties": {
    "gn:admin1_code":"13.0",
    "gn:admin2_code":"TA",
    "gn:admin3_code":"73010.0",
    "gn:asciiname":"Marina di Leporano",
    "gn:country_code":"IT",
    "gn:dem":9,
    "gn:feature_class":"P",
    "gn:feature_code":"PPLL",
    "gn:name":"Marina di Leporano",
    "gn:population":0,
    "gn:timezone":"Europe/Rome",
    "iso:country":"IT",
    "wof:name":"Marina di Leporano",
    "wof:placetype":"locality"
},
  "geometry": {"coordinates":[17.33939,40.36309],"type":"Point"}
}