{
  "type": "Feature",
  "properties": {
    "gn:admin1_code":"8",
    "gn:admin2_code":"GE",
    "gn:admin3_code":"10031.0",
    "gn:asciiname":"Forca",
    "gn:country_code":"IT",
    "gn:dem":432,
    "gn:feature_class":"P",
    "gn:feature_code":"PPLL",
    "gn:name":"Forca",
    "gn:population":8,
    "gn:timezone":"Europe/Rome",
    "iso:country":"IT",
    "wof:name":"Forca",
    "wof:placetype":"locality",
    "wof:population":8
},
  "geometry": {"coordinates":[9.12163,44.44058],"type":"Point"}
}