{
  "type": "Feature",
  "properties": {
    "gn:admin1_code":"12.0",
    "gn:admin2_code":"AL",
    "gn:admin3_code":"6136.0",
    "gn:asciiname":"Ciglione",
    "gn:country_code":"IT",
    "gn:dem":438,
    "gn:elevation":"439.0",
    "gn:feature_class":"P",
    "gn:feature_code":"PPL",
    "gn:name":"Ciglione",
    "gn:population":84,
    "gn:timezone":"Europe/Rome",
    "iso:country":"IT",
    "wof:name":"Ciglione",
    "wof:placetype":"locality",
    "wof:population":84
},
  "geometry": {"coordinates":[8.48605,44.60798],"type":"Point"}
}