{
  "type": "Feature",
  "properties": {
    "gn:admin1_code":"12",
    "gn:admin2_code":"TO",
    "gn:admin3_code":"1191.0",
    "gn:asciiname":"Cascina Pol",
    "gn:country_code":"IT",
    "gn:dem":567,
    "gn:feature_class":"P",
    "gn:feature_code":"PPL",
    "gn:name":"Cascina Pol",
    "gn:population":64,
    "gn:timezone":"Europe/Rome",
    "iso:country":"IT",
    "wof:name":"Cascina Pol",
    "wof:placetype":"locality",
    "wof:population":64
},
  "geometry": {"coordinates":[7.31379,44.91943],"type":"Point"}
}