{
  "type": "Feature",
  "properties": {
    "gn:admin1_code":"20",
    "gn:admin2_code":"TV",
    "gn:admin3_code":"26095.0",
    "gn:asciiname":"Corniani",
    "gn:country_code":"IT",
    "gn:dem":18,
    "gn:feature_class":"P",
    "gn:feature_code":"PPL",
    "gn:name":"Corniani",
    "gn:population":74,
    "gn:timezone":"Europe/Rome",
    "iso:country":"IT",
    "wof:name":"Corniani",
    "wof:placetype":"locality",
    "wof:population":74
},
  "geometry": {"coordinates":[12.12096,45.62057],"type":"Point"}
}