{
  "type": "Feature",
  "properties": {
    "gn:admin1_code":"20",
    "gn:admin2_code":"PD",
    "gn:admin3_code":"28046.0",
    "gn:asciiname":"Pierobon-Fornace",
    "gn:country_code":"IT",
    "gn:dem":23,
    "gn:feature_class":"P",
    "gn:feature_code":"PPL",
    "gn:name":"Pierobon-Fornace",
    "gn:population":95,
    "gn:timezone":"Europe/Rome",
    "iso:country":"IT",
    "wof:name":"Pierobon-Fornace",
    "wof:placetype":"locality",
    "wof:population":95
},
  "geometry": {"coordinates":[11.96444,45.58412],"type":"Point"}
}