{
  "type": "Feature",
  "properties": {
    "gn:admin1_code":"3",
    "gn:admin2_code":"CZ",
    "gn:admin3_code":"79099.0",
    "gn:asciiname":"Pietra",
    "gn:country_code":"IT",
    "gn:dem":972,
    "gn:feature_class":"P",
    "gn:feature_code":"PPL",
    "gn:name":"Pietra",
    "gn:population":17,
    "gn:timezone":"Europe/Rome",
    "iso:country":"IT",
    "name:ceb_x_preferred":[
        "Pietra"
    ],
    "name:deu_x_preferred":[
        "Pietra"
    ],
    "name:ita_x_preferred":[
        "Pietra"
    ],
    "name:por_x_preferred":[
        "Pietra"
    ],
    "name:srp_x_preferred":[
        "Pjetra"
    ],
    "name:swe_x_preferred":[
        "Pietra"
    ],
    "name:ukr_x_preferred":[
        "\u041f'\u0454\u0442\u0440\u0430"
    ],
    "wof:name":"Pietra",
    "wof:placetype":"locality",
    "wof:population":17
},
  "geometry": {"coordinates":[16.30005,39.02755],"type":"Point"}
}