{
  "type": "Feature",
  "properties": {
    "gn:gn_country":"IT",
    "gn:gn_fcode":"PPLA3",
    "gn:gn_pop":1432,
    "gn:population":288,
    "iso:country":"IT",
    "name:arm_x_preferred":[
        "\u054d\u057a\u056b\u0576\u0565\u057f\u0565"
    ],
    "name:baq_x_preferred":[
        "Spinete"
    ],
    "name:bel_x_preferred":[
        "\u0421\u043f\u0456\u043d\u0435\u0442\u044d"
    ],
    "name:bul_x_preferred":[
        "\u0421\u043f\u0438\u043d\u0435\u0442\u0435"
    ],
    "name:chi_x_preferred":[
        "\u65af\u76ae\u5185\u6cf0"
    ],
    "name:dut_x_preferred":[
        "Spinete"
    ],
    "name:eng_x_preferred":[
        "Spinete"
    ],
    "name:epo_x_preferred":[
        "Spinete"
    ],
    "name:fra_x_preferred":[
        "Spinete"
    ],
    "name:fre_x_preferred":[
        "Spinete"
    ],
    "name:ger_x_preferred":[
        "Spinete"
    ],
    "name:hun_x_preferred":[
        "Spinete"
    ],
    "name:ina_x_preferred":[
        "Spinete"
    ],
    "name:ita_x_preferred":[
        "Spinete"
    ],
    "name:jpn_x_preferred":[
        "\u30b9\u30d4\u30cd\u30fc\u30c6"
    ],
    "name:kaz_x_preferred":[
        "\u0421\u043f\u0438\u043d\u0435\u0442\u0435"
    ],
    "name:kor_x_preferred":[
        "\uc2a4\ud53c\ub124\ud14c"
    ],
    "name:lat_x_preferred":[
        "Spinetum"
    ],
    "name:lmo_x_preferred":[
        "Spinete"
    ],
    "name:may_x_preferred":[
        "Spinete"
    ],
    "name:nan_x_preferred":[
        "Spinete"
    ],
    "name:nap_x_preferred":[
        "Spinete"
    ],
    "name:nld_x_preferred":[
        "Spinete"
    ],
    "name:per_x_preferred":[
        "\u0633\u067e\u06cc\u0646\u062a\u0647"
    ],
    "name:pms_x_preferred":[
        "Spinete"
    ],
    "name:pol_x_preferred":[
        "Spinete"
    ],
    "name:por_x_preferred":[
        "Spinete"
    ],
    "name:rum_x_preferred":[
        "Spinete"
    ],
    "name:rus_x_preferred":[
        "\u0421\u043f\u0438\u043d\u0435\u0442\u0435"
    ],
    "name:scn_x_preferred":[
        "Spineti"
    ],
    "name:spa_x_preferred":[
        "Spinete"
    ],
    "name:srp_x_preferred":[
        "Spinete"
    ],
    "name:tgl_x_preferred":[
        "Spinete"
    ],
    "name:ukr_x_preferred":[
        "\u0421\u043f\u0456\u043d\u0435\u0442\u0435"
    ],
    "name:uzb_x_preferred":[
        "Spinete"
    ],
    "name:vie_x_preferred":[
        "Spinete"
    ],
    "name:vol_x_preferred":[
        "Spinete"
    ],
    "name:war_x_preferred":[
        "Spinete"
    ],
    "qs_pg:aaroncc":"IT",
    "qs_pg:gn_country":"IT",
    "qs_pg:gn_fcode":"PPLA3",
    "qs_pg:gn_pop":1432,
    "qs_pg:name":"Spinete",
    "qs_pg:name_adm0":"Italia",
    "qs_pg:name_adm1":"Molise",
    "qs_pg:photos_9k":1,
    "qs_pg:photos_9r":1,
    "qs_pg:photos_all":2,
    "qs_pg:photos_sr":0,
    "qs_pg:pop_sr":3,
    "qs_pg:qs_pg_placetype":"locality",
    "qs_pg:qs_pg_placetype_gp":"Town",
    "qs_pg:woe_adm0":23424853,
    "woe:adm0_id":23424853,
    "woe:name_adm0":"Italia",
    "woe:name_adm1":"Molise",
    "woe:placetype":"Town",
    "wof:name":"Spinete",
    "wof:placetype":"locality",
    "wof:population":288
},
  "geometry": {"coordinates":[14.48623,41.54493],"type":"Point"}
}