{
  "type": "Feature",
  "properties": {
    "gn:admin1_code":"4",
    "gn:admin2_code":"AV",
    "gn:admin3_code":"64074.0",
    "gn:asciiname":"Tavernanova",
    "gn:country_code":"IT",
    "gn:dem":299,
    "gn:feature_class":"P",
    "gn:feature_code":"PPL",
    "gn:name":"Tavernanova",
    "gn:population":289,
    "gn:timezone":"Europe/Rome",
    "iso:country":"IT",
    "wof:name":"Tavernanova",
    "wof:placetype":"locality",
    "wof:population":289
},
  "geometry": {"coordinates":[14.85599,40.99599],"type":"Point"}
}