{
  "type": "Feature",
  "properties": {
    "gn:admin1_code":"14",
    "gn:admin2_code":"CA",
    "gn:admin3_code":"92108.0",
    "gn:asciiname":"Is Punteddus",
    "gn:country_code":"IT",
    "gn:dem":3,
    "gn:feature_class":"P",
    "gn:feature_code":"PPL",
    "gn:name":"Is Punteddus",
    "gn:population":25,
    "gn:timezone":"Europe/Rome",
    "iso:country":"IT",
    "wof:name":"Is Punteddus",
    "wof:placetype":"locality",
    "wof:population":25
},
  "geometry": {"coordinates":[9.03469,39.27258],"type":"Point"}
}