{
  "type": "Feature",
  "properties": {
    "gn:admin1_code":"5",
    "gn:admin2_code":"FE",
    "gn:admin3_code":"38007.0",
    "gn:asciiname":"Forcello",
    "gn:country_code":"IT",
    "gn:dem":-1,
    "gn:feature_class":"P",
    "gn:feature_code":"PPL",
    "gn:name":"Forcello",
    "gn:population":16,
    "gn:timezone":"Europe/Rome",
    "iso:country":"IT",
    "wof:name":"Forcello",
    "wof:placetype":"locality",
    "wof:population":16
},
  "geometry": {"coordinates":[11.92224,44.93472],"type":"Point"}
}