{
  "type": "Feature",
  "properties": {
    "gn:admin1_code":"5",
    "gn:admin2_code":"PC",
    "gn:admin3_code":"33043.0",
    "gn:asciiname":"Vei",
    "gn:country_code":"IT",
    "gn:dem":370,
    "gn:feature_class":"P",
    "gn:feature_code":"PPL",
    "gn:name":"Vei",
    "gn:population":21,
    "gn:timezone":"Europe/Rome",
    "iso:country":"IT",
    "wof:name":"Vei",
    "wof:placetype":"locality",
    "wof:population":21
},
  "geometry": {"coordinates":[9.50706,44.84884],"type":"Point"}
}