{
  "type": "Feature",
  "properties": {
    "gn:admin1_code":"9.0",
    "gn:admin2_code":"BS",
    "gn:admin3_code":"17166.0",
    "gn:asciiname":"San Giuseppe",
    "gn:country_code":"IT",
    "gn:dem":140,
    "gn:feature_class":"P",
    "gn:feature_code":"PPL",
    "gn:name":"San Giuseppe",
    "gn:population":344,
    "gn:timezone":"Europe/Rome",
    "iso:country":"IT",
    "name:ceb_x_preferred":[
        "San Giuseppe"
    ],
    "name:deu_x_preferred":[
        "San Giuseppe"
    ],
    "name:fra_x_preferred":[
        "San Giuseppe"
    ],
    "name:ita_x_preferred":[
        "San Giuseppe"
    ],
    "name:nld_x_preferred":[
        "San Giuseppe"
    ],
    "name:pol_x_preferred":[
        "\u015awi\u0119ty J\u00f3zef"
    ],
    "name:por_x_preferred":[
        "San Giuseppe"
    ],
    "name:rus_x_preferred":[
        "\u0421\u0432\u044f\u0442\u043e\u0439 \u0414\u0436\u0443\u0437\u0435\u043f\u043f\u0435"
    ],
    "name:srp_x_preferred":[
        "San \u0110uzepe"
    ],
    "name:swe_x_preferred":[
        "San Giuseppe"
    ],
    "name:vie_x_preferred":[
        "Giuse"
    ],
    "wof:name":"San Giuseppe",
    "wof:placetype":"locality",
    "wof:population":344
},
  "geometry": {"coordinates":[9.98747,45.53176],"type":"Point"}
}