{
  "type": "Feature",
  "properties": {
    "gn:admin1_code":"20",
    "gn:admin2_code":"VR",
    "gn:admin3_code":"23063.0",
    "gn:asciiname":"Chiesuola",
    "gn:country_code":"IT",
    "gn:dem":89,
    "gn:feature_class":"P",
    "gn:feature_code":"PPL",
    "gn:name":"Chiesuola",
    "gn:population":50,
    "gn:timezone":"Europe/Rome",
    "iso:country":"IT",
    "wof:name":"Chiesuola",
    "wof:placetype":"locality",
    "wof:population":50
},
  "geometry": {"coordinates":[11.31429,45.47295],"type":"Point"}
}