{
  "type": "Feature",
  "properties": {
    "gn:admin1_code":"7",
    "gn:admin2_code":"RM",
    "gn:admin3_code":"58082.0",
    "gn:asciiname":"Santo Sisino",
    "gn:country_code":"IT",
    "gn:dem":293,
    "gn:feature_class":"P",
    "gn:feature_code":"PPL",
    "gn:name":"Santo Sisino",
    "gn:population":66,
    "gn:timezone":"Europe/Rome",
    "iso:country":"IT",
    "wof:name":"Santo Sisino",
    "wof:placetype":"locality",
    "wof:population":66
},
  "geometry": {"coordinates":[12.47981,42.21889],"type":"Point"}
}