{
  "type": "Feature",
  "properties": {
    "gn:admin1_code":"20.0",
    "gn:admin2_code":"BL",
    "gn:admin3_code":"25073.0",
    "gn:asciiname":"Villanova",
    "gn:country_code":"IT",
    "gn:dem":886,
    "gn:feature_class":"P",
    "gn:feature_code":"PPL",
    "gn:name":"Villanova",
    "gn:population":16,
    "gn:timezone":"Europe/Rome",
    "iso:country":"IT",
    "wof:name":"Villanova",
    "wof:placetype":"locality",
    "wof:population":16
},
  "geometry": {"coordinates":[12.19073,46.36009],"type":"Point"}
}