{
  "type": "Feature",
  "properties": {
    "gn:elevation":283,
    "gn:population":879,
    "iso:country":"IT",
    "name:azb_x_preferred":[
        "\u067e\u0648\u0641\u06cc"
    ],
    "name:bcl_x_preferred":[
        "Pofi"
    ],
    "name:bul_x_preferred":[
        "\u041f\u043e\u0444\u0438"
    ],
    "name:cat_x_preferred":[
        "Pofi"
    ],
    "name:ceb_x_preferred":[
        "Pofi"
    ],
    "name:deu_x_preferred":[
        "Pofi"
    ],
    "name:eng_x_preferred":[
        "Pofi"
    ],
    "name:epo_x_preferred":[
        "Pofi"
    ],
    "name:eus_x_preferred":[
        "Pofi"
    ],
    "name:fas_x_preferred":[
        "\u067e\u0648\u0641\u06cc"
    ],
    "name:fra_x_preferred":[
        "Pofi"
    ],
    "name:hbs_x_preferred":[
        "Pofi"
    ],
    "name:hun_x_preferred":[
        "Pofi"
    ],
    "name:hye_x_preferred":[
        "\u054a\u0578\u0586\u056b"
    ],
    "name:ina_x_preferred":[
        "Pofi"
    ],
    "name:ita_x_preferred":[
        "Pofi"
    ],
    "name:jpn_x_preferred":[
        "\u30dd\u30fc\u30d5\u30a3"
    ],
    "name:kaz_x_preferred":[
        "\u041f\u043e\u0444\u0438"
    ],
    "name:kor_x_preferred":[
        "\ud3ec\ud53c"
    ],
    "name:lat_x_preferred":[
        "Castrum Phofi"
    ],
    "name:lmo_x_preferred":[
        "Pofi"
    ],
    "name:msa_x_preferred":[
        "Pofi"
    ],
    "name:nan_x_preferred":[
        "Pofi"
    ],
    "name:nap_x_preferred":[
        "Pofi"
    ],
    "name:nld_x_preferred":[
        "Pofi"
    ],
    "name:oci_x_preferred":[
        "Pofi"
    ],
    "name:pms_x_preferred":[
        "Pofi"
    ],
    "name:pol_x_preferred":[
        "Pofi"
    ],
    "name:por_x_preferred":[
        "Pofi"
    ],
    "name:ron_x_preferred":[
        "Pofi"
    ],
    "name:rus_x_preferred":[
        "\u041f\u043e\u0444\u0438"
    ],
    "name:scn_x_preferred":[
        "Pofi"
    ],
    "name:spa_x_preferred":[
        "Pofi"
    ],
    "name:srp_x_preferred":[
        "\u041f\u043e\u0444\u0438"
    ],
    "name:srp_x_variant":[
        "Pofi"
    ],
    "name:swe_x_preferred":[
        "Pofi"
    ],
    "name:ukr_x_preferred":[
        "\u041f\u043e\u0444\u0456"
    ],
    "name:uzb_x_preferred":[
        "Pofi"
    ],
    "name:vie_x_preferred":[
        "Pofi"
    ],
    "name:vol_x_preferred":[
        "Pofi"
    ],
    "name:war_x_preferred":[
        "Pofi"
    ],
    "name:zho_min_nan_x_preferred":[
        "Pofi"
    ],
    "name:zho_x_preferred":[
        "\u6ce2\u83f2"
    ],
    "qs:a0":"Italia",
    "qs:a1":"*Frosinone",
    "qs:a1r":"0Lazio",
    "qs:adm0":"Italia",
    "qs:la_lc":"*",
    "qs:level":"locality",
    "qs:loc":"Pofi",
    "qs:loc_alt":"Pofi",
    "qs:pop":0,
    "qs:type":"buffered point",
    "wd:wordcount":80,
    "wof:lang":[
        "ita"
    ],
    "wof:name":"Pofi",
    "wof:placetype":"locality",
    "wof:population":879
},
  "geometry": {"coordinates":[13.415281,41.566391],"type":"Point"}
}