{
  "type": "Feature",
  "properties": {
    "gn:admin1_code":"15",
    "gn:admin2_code":"PA",
    "gn:admin3_code":"82071.0",
    "gn:asciiname":"Paterna",
    "gn:country_code":"IT",
    "gn:dem":121,
    "gn:feature_class":"P",
    "gn:feature_code":"PPL",
    "gn:name":"Paterna",
    "gn:population":88,
    "gn:timezone":"Europe/Rome",
    "iso:country":"IT",
    "name:arg_x_preferred":[
        "Paterna"
    ],
    "name:ast_x_preferred":[
        "Paterna"
    ],
    "name:cat_x_preferred":[
        "Paterna"
    ],
    "name:ceb_x_preferred":[
        "Paterna"
    ],
    "name:deu_x_preferred":[
        "Paterna"
    ],
    "name:eus_x_preferred":[
        "Paterna"
    ],
    "name:fra_x_preferred":[
        "Paterna"
    ],
    "name:glg_x_preferred":[
        "Paterna"
    ],
    "name:hun_x_preferred":[
        "Paterna"
    ],
    "name:hye_x_preferred":[
        "\u054a\u0561\u057f\u0565\u0580\u0576\u0561"
    ],
    "name:ita_x_preferred":[
        "Paterna"
    ],
    "name:jpn_x_preferred":[
        "\u30d1\u30c6\u30eb\u30ca"
    ],
    "name:kor_x_preferred":[
        "\ud30c\ud14c\ub974\ub098"
    ],
    "name:mlg_x_preferred":[
        "Paterna"
    ],
    "name:msa_x_preferred":[
        "Paterna"
    ],
    "name:nld_x_preferred":[
        "Paterna"
    ],
    "name:nno_x_preferred":[
        "Paterna"
    ],
    "name:oci_x_preferred":[
        "Paterna"
    ],
    "name:pol_x_preferred":[
        "Paterna"
    ],
    "name:por_x_preferred":[
        "Paterna"
    ],
    "name:rus_x_preferred":[
        "\u041f\u0430\u0442\u0435\u0440\u043d\u0430"
    ],
    "name:spa_x_preferred":[
        "Paterna"
    ],
    "name:sqi_x_preferred":[
        "Paterna"
    ],
    "name:srp_x_preferred":[
        "\u041f\u0430\u0442\u0435\u0440\u043d\u0430"
    ],
    "name:swe_x_preferred":[
        "Paterna"
    ],
    "name:tat_x_preferred":[
        "\u041f\u0430\u0442\u0435\u0440\u043d\u0430"
    ],
    "name:ukr_x_preferred":[
        "\u041f\u0430\u0442\u0435\u0440\u043d\u0430"
    ],
    "name:war_x_preferred":[
        "Paterna"
    ],
    "name:zho_x_preferred":[
        "\u5e15\u7279\u5c14\u7eb3"
    ],
    "wof:name":"Paterna",
    "wof:placetype":"locality",
    "wof:population":88
},
  "geometry": {"coordinates":[13.10266,38.08608],"type":"Point"}
}