{
  "type": "Feature",
  "properties": {
    "gn:admin1_code":"18.0",
    "gn:admin2_code":"PG",
    "gn:admin3_code":"54048.0",
    "gn:asciiname":"San Martino",
    "gn:country_code":"IT",
    "gn:dem":757,
    "gn:feature_class":"P",
    "gn:feature_code":"PPL",
    "gn:name":"San Martino",
    "gn:population":43,
    "gn:timezone":"Europe/Rome",
    "iso:country":"IT",
    "wof:name":"San Martino",
    "wof:placetype":"locality",
    "wof:population":43
},
  "geometry": {"coordinates":[12.90969,42.9033],"type":"Point"}
}