{
  "type": "Feature",
  "properties": {
    "gn:admin1_code":"20.0",
    "gn:admin2_code":"VE",
    "gn:admin3_code":"27008.0",
    "gn:asciiname":"Le Motte",
    "gn:country_code":"IT",
    "gn:dem":-2,
    "gn:feature_class":"P",
    "gn:feature_code":"PPL",
    "gn:name":"Le Motte",
    "gn:population":0,
    "gn:timezone":"Europe/Rome",
    "iso:country":"IT",
    "wof:name":"Le Motte",
    "wof:placetype":"locality"
},
  "geometry": {"coordinates":[12.23667,45.13667],"type":"Point"}
}