{
  "type": "Feature",
  "properties": {
    "gn:admin1_code":"20",
    "gn:admin2_code":"TV",
    "gn:admin3_code":"26028.0",
    "gn:asciiname":"Nucleo Baldessin",
    "gn:country_code":"IT",
    "gn:dem":18,
    "gn:feature_class":"P",
    "gn:feature_code":"PPL",
    "gn:name":"Nucleo Baldessin",
    "gn:population":43,
    "gn:timezone":"Europe/Rome",
    "iso:country":"IT",
    "wof:name":"Nucleo Baldessin",
    "wof:placetype":"locality",
    "wof:population":43
},
  "geometry": {"coordinates":[12.43728,45.83427],"type":"Point"}
}