{
  "type": "Feature",
  "properties": {
    "iso:country":"IT",
    "name:ceb_x_preferred":[
        "San Giusto"
    ],
    "name:deu_x_preferred":[
        "San Giusto"
    ],
    "name:fra_x_preferred":[
        "San Giusto"
    ],
    "name:ita_x_preferred":[
        "San Giusto"
    ],
    "name:ita_x_variant":[
        "S Giusto",
        "S. Giusto"
    ],
    "name:rus_x_preferred":[
        "\u0421\u0430\u043d-\u0414\u0436\u0443\u0441\u0442\u043e"
    ],
    "name:srp_x_preferred":[
        "San \u0110usto"
    ],
    "name:swe_x_preferred":[
        "San Giusto"
    ],
    "name:unk_x_variant":[
        "San Giusto"
    ],
    "qs:gn_adm0_cc":"IT",
    "qs:gn_fcode":"PPLX",
    "qs:gn_local":3165185,
    "qs:gn_nam_loc":"Trieste, Trieste, Trieste, Friuli Venezia Giulia, IT",
    "qs:gn_namadm1":"06",
    "qs:gn_name":"San Giusto",
    "qs:local_max":9211,
    "qs:local_sum":26825,
    "qs:localhoods":32,
    "qs:name":"San Giusto",
    "qs:name_adm0":"Italia",
    "qs:name_adm1":"Friuli-Venezia Giulia",
    "qs:name_adm2":"Trieste",
    "qs:name_lau":"Trieste",
    "qs:name_local":"Trieste",
    "qs:photo_max":36,
    "qs:photo_sum":125,
    "qs:placetype":"Suburb",
    "qs:quad_count":9,
    "qs:woe_adm0":23424853,
    "qs:woe_adm1":7153335,
    "qs:woe_adm2":12591892,
    "qs:woe_lau":12676517,
    "qs:woe_local":725300,
    "qs:woe_ver":"7.10.0",
    "wof:lang":[
        "ita"
    ],
    "wof:name":"San Giusto",
    "wof:placetype":"neighbourhood"
},
  "geometry": {"coordinates":[13.80467,45.643871],"type":"Point"}
}