{
  "type": "Feature",
  "properties": {
    "gn:admin1_code":"5",
    "gn:admin2_code":"RE",
    "gn:admin3_code":"35045.0",
    "gn:asciiname":"Sorba",
    "gn:country_code":"IT",
    "gn:dem":835,
    "gn:feature_class":"P",
    "gn:feature_code":"PPLL",
    "gn:name":"Sorba",
    "gn:population":6,
    "gn:timezone":"Europe/Rome",
    "iso:country":"IT",
    "wof:name":"Sorba",
    "wof:placetype":"locality",
    "wof:population":6
},
  "geometry": {"coordinates":[10.49891,44.33233],"type":"Point"}
}