{
  "type": "Feature",
  "properties": {
    "gn:admin1_code":"3.0",
    "gn:admin2_code":"CS",
    "gn:admin3_code":"78017.0",
    "gn:asciiname":"Localita Imperatore",
    "gn:country_code":"IT",
    "gn:dem":98,
    "gn:feature_class":"P",
    "gn:feature_code":"PPLL",
    "gn:name":"Localit\u00e0 Imperatore",
    "gn:population":0,
    "gn:timezone":"Europe/Rome",
    "iso:country":"IT",
    "name:und_x_variant":[
        "Localit\u00e0 Imperatore"
    ],
    "wof:name":"Localita Imperatore",
    "wof:placetype":"locality"
},
  "geometry": {"coordinates":[16.23013,39.49788],"type":"Point"}
}