{
  "type": "Feature",
  "properties": {
    "gn:admin1_code":"4",
    "gn:admin2_code":"AV",
    "gn:admin3_code":"64092.0",
    "gn:asciiname":"Montevergine",
    "gn:country_code":"IT",
    "gn:dem":820,
    "gn:feature_class":"P",
    "gn:feature_code":"PPL",
    "gn:name":"Montevergine",
    "gn:population":21,
    "gn:timezone":"Europe/Rome",
    "iso:country":"IT",
    "name:ita_x_preferred":[
        "Montevergine"
    ],
    "name:nor_x_preferred":[
        "Montevergine"
    ],
    "name:pol_x_preferred":[
        "Montevergine"
    ],
    "wof:name":"Montevergine",
    "wof:placetype":"locality",
    "wof:population":21
},
  "geometry": {"coordinates":[15.21941,40.93194],"type":"Point"}
}