{
  "type": "Feature",
  "properties": {
    "gn:admin1_code":"20.0",
    "gn:admin2_code":"PD",
    "gn:admin3_code":"28104.0",
    "gn:asciiname":"Mussolini",
    "gn:country_code":"IT",
    "gn:dem":13,
    "gn:feature_class":"P",
    "gn:feature_code":"PPL",
    "gn:name":"Mussolini",
    "gn:population":597,
    "gn:timezone":"Europe/Rome",
    "iso:country":"IT",
    "wof:name":"Mussolini",
    "wof:placetype":"locality",
    "wof:population":597
},
  "geometry": {"coordinates":[11.97627,45.50999],"type":"Point"}
}