{
  "type": "Feature",
  "properties": {
    "gn:admin1_code":"20",
    "gn:admin2_code":"VR",
    "gn:admin3_code":"23011.0",
    "gn:asciiname":"Colletta",
    "gn:country_code":"IT",
    "gn:dem":1111,
    "gn:feature_class":"P",
    "gn:feature_code":"PPL",
    "gn:name":"Colletta",
    "gn:population":25,
    "gn:timezone":"Europe/Rome",
    "iso:country":"IT",
    "name:fra_x_preferred":[
        "Colletta"
    ],
    "name:ita_x_preferred":[
        "Colletta"
    ],
    "name:srp_x_preferred":[
        "Colletta"
    ],
    "wof:name":"Colletta",
    "wof:placetype":"locality",
    "wof:population":25
},
  "geometry": {"coordinates":[11.02791,45.63147],"type":"Point"}
}