{
  "type": "Feature",
  "properties": {
    "gn:admin1_code":"9",
    "gn:admin2_code":"MN",
    "gn:admin3_code":"20068.0",
    "gn:asciiname":"Alberia",
    "gn:country_code":"IT",
    "gn:dem":17,
    "gn:feature_class":"P",
    "gn:feature_code":"PPL",
    "gn:name":"Alberia",
    "gn:population":33,
    "gn:timezone":"Europe/Rome",
    "iso:country":"IT",
    "wof:name":"Alberia",
    "wof:placetype":"locality",
    "wof:population":33
},
  "geometry": {"coordinates":[11.03045,45.13604],"type":"Point"}
}