{
  "type": "Feature",
  "properties": {
    "gn:admin1_code":"10.0",
    "gn:admin2_code":"AN",
    "gn:admin3_code":"42006.0",
    "gn:asciiname":"Cisterna",
    "gn:country_code":"IT",
    "gn:dem":27,
    "gn:feature_class":"P",
    "gn:feature_code":"PPLL",
    "gn:name":"Cisterna",
    "gn:population":2,
    "gn:timezone":"Europe/Rome",
    "iso:country":"IT",
    "name:ara_x_preferred":[
        "\u0635\u0647\u0631\u064a\u062c"
    ],
    "name:nld_x_preferred":[
        "Cistern"
    ],
    "wof:name":"Cisterna",
    "wof:placetype":"locality",
    "wof:population":2
},
  "geometry": {"coordinates":[13.53239,43.52682],"type":"Point"}
}