{
  "type": "Feature",
  "properties": {
    "gn:admin1_code":"14",
    "gn:admin2_code":"NU",
    "gn:admin3_code":"91063.0",
    "gn:asciiname":"Sas Linnas Siccas",
    "gn:country_code":"IT",
    "gn:dem":18,
    "gn:feature_class":"P",
    "gn:feature_code":"PPL",
    "gn:name":"Sas Linnas Siccas",
    "gn:population":35,
    "gn:timezone":"Europe/Rome",
    "iso:country":"IT",
    "wof:name":"Sas Linnas Siccas",
    "wof:placetype":"locality",
    "wof:population":35
},
  "geometry": {"coordinates":[9.77093,40.4236],"type":"Point"}
}