{
  "type": "Feature",
  "properties": {
    "gn:admin1_code":"5",
    "gn:admin2_code":"MO",
    "gn:admin3_code":"36012.0",
    "gn:asciiname":"Le Casette",
    "gn:country_code":"IT",
    "gn:dem":11,
    "gn:feature_class":"P",
    "gn:feature_code":"PPL",
    "gn:name":"Le Casette",
    "gn:population":23,
    "gn:timezone":"Europe/Rome",
    "iso:country":"IT",
    "wof:name":"Le Casette",
    "wof:placetype":"locality",
    "wof:population":23
},
  "geometry": {"coordinates":[11.33205,44.84141],"type":"Point"}
}