{
  "type": "Feature",
  "properties": {
    "gn:admin1_code":"9",
    "gn:admin2_code":"CO",
    "gn:admin3_code":"13041.0",
    "gn:asciiname":"Cascina Varenna",
    "gn:country_code":"IT",
    "gn:dem":370,
    "gn:feature_class":"P",
    "gn:feature_code":"PPL",
    "gn:name":"Cascina Varenna",
    "gn:population":46,
    "gn:timezone":"Europe/Rome",
    "iso:country":"IT",
    "wof:name":"Cascina Varenna",
    "wof:placetype":"locality",
    "wof:population":46
},
  "geometry": {"coordinates":[9.16393,45.74893],"type":"Point"}
}