{
  "type": "Feature",
  "properties": {
    "gn:admin1_code":"17.0",
    "gn:admin2_code":"TN",
    "gn:admin3_code":"22228.0",
    "gn:asciiname":"Cilla",
    "gn:country_code":"IT",
    "gn:dem":555,
    "gn:feature_class":"P",
    "gn:feature_code":"PPL",
    "gn:name":"Cill\u00e0",
    "gn:population":0,
    "gn:timezone":"Europe/Rome",
    "iso:country":"IT",
    "name:hun_x_preferred":[
        "Cilla"
    ],
    "wof:name":"Cilla",
    "wof:placetype":"locality"
},
  "geometry": {"coordinates":[10.84608,46.04272],"type":"Point"}
}