{
  "type": "Feature",
  "properties": {
    "gn:admin1_code":"16",
    "gn:admin2_code":"LU",
    "gn:admin3_code":"46021.0",
    "gn:asciiname":"Marcucci",
    "gn:country_code":"IT",
    "gn:dem":20,
    "gn:feature_class":"P",
    "gn:feature_code":"PPL",
    "gn:name":"Marcucci",
    "gn:population":41,
    "gn:timezone":"Europe/Rome",
    "iso:country":"IT",
    "wof:name":"Marcucci",
    "wof:placetype":"locality",
    "wof:population":41
},
  "geometry": {"coordinates":[10.70169,43.84596],"type":"Point"}
}