{
  "type": "Feature",
  "properties": {
    "gn:admin1_code":"12",
    "gn:admin2_code":"VC",
    "gn:admin3_code":"2152.0",
    "gn:asciiname":"Cantone",
    "gn:country_code":"IT",
    "gn:dem":543,
    "gn:feature_class":"P",
    "gn:feature_code":"PPL",
    "gn:name":"Cantone",
    "gn:population":39,
    "gn:timezone":"Europe/Rome",
    "iso:country":"IT",
    "wof:name":"Cantone",
    "wof:placetype":"locality",
    "wof:population":39
},
  "geometry": {"coordinates":[8.33364,45.71926],"type":"Point"}
}