{
  "type": "Feature",
  "properties": {
    "gn:admin1_code":"4",
    "gn:admin2_code":"SA",
    "gn:admin3_code":"65138.0",
    "gn:asciiname":"Pontone",
    "gn:country_code":"IT",
    "gn:dem":271,
    "gn:feature_class":"P",
    "gn:feature_code":"PPL",
    "gn:name":"Pontone",
    "gn:population":256,
    "gn:timezone":"Europe/Rome",
    "iso:country":"IT",
    "wof:name":"Pontone",
    "wof:placetype":"locality",
    "wof:population":256
},
  "geometry": {"coordinates":[14.6029,40.64321],"type":"Point"}
}