{
  "type": "Feature",
  "properties": {
    "gn:admin1_code":"9.0",
    "gn:admin2_code":"PV",
    "gn:admin3_code":"18171.0",
    "gn:asciiname":"Nivione",
    "gn:country_code":"IT",
    "gn:dem":502,
    "gn:feature_class":"P",
    "gn:feature_code":"PPL",
    "gn:name":"Nivione",
    "gn:population":32,
    "gn:timezone":"Europe/Rome",
    "iso:country":"IT",
    "wof:name":"Nivione",
    "wof:placetype":"locality",
    "wof:population":32
},
  "geometry": {"coordinates":[9.18175,44.80631],"type":"Point"}
}