{
  "type": "Feature",
  "properties": {
    "gn:admin1_code":"6.0",
    "gn:admin2_code":"PN",
    "gn:admin3_code":"93037.0",
    "gn:asciiname":"Santo Odorico",
    "gn:country_code":"IT",
    "gn:dem":24,
    "gn:feature_class":"P",
    "gn:feature_code":"PPLL",
    "gn:name":"Santo Odorico",
    "gn:population":0,
    "gn:timezone":"Europe/Rome",
    "iso:country":"IT",
    "wof:name":"Santo Odorico",
    "wof:placetype":"locality"
},
  "geometry": {"coordinates":[12.50596,45.94872],"type":"Point"}
}