{
  "type": "Feature",
  "properties": {
    "gn:admin1_code":"12",
    "gn:admin2_code":"TO",
    "gn:admin3_code":"1080.0",
    "gn:asciiname":"Sant'Antonio",
    "gn:country_code":"IT",
    "gn:dem":992,
    "gn:feature_class":"P",
    "gn:feature_code":"PPL",
    "gn:name":"Sant'Antonio",
    "gn:population":79,
    "gn:timezone":"Europe/Rome",
    "iso:country":"IT",
    "wof:name":"Sant'Antonio",
    "wof:placetype":"locality",
    "wof:population":79
},
  "geometry": {"coordinates":[6.97392,45.12469],"type":"Point"}
}