{
  "type": "Feature",
  "properties": {
    "gn:admin1_code":"10.0",
    "gn:admin2_code":"AN",
    "gn:admin3_code":"42019.0",
    "gn:asciiname":"Imbrecciata",
    "gn:country_code":"IT",
    "gn:dem":163,
    "gn:feature_class":"P",
    "gn:feature_code":"PPL",
    "gn:name":"Imbrecciata",
    "gn:population":379,
    "gn:timezone":"Europe/Rome",
    "iso:country":"IT",
    "wof:name":"Imbrecciata",
    "wof:placetype":"locality",
    "wof:population":379
},
  "geometry": {"coordinates":[13.35897,43.41783],"type":"Point"}
}