{
  "type": "Feature",
  "properties": {
    "gn:admin1_code":"9",
    "gn:admin2_code":"BG",
    "gn:admin3_code":"16076.0",
    "gn:asciiname":"Cascina Bosco",
    "gn:country_code":"IT",
    "gn:dem":129,
    "gn:feature_class":"P",
    "gn:feature_code":"PPL",
    "gn:name":"Cascina Bosco",
    "gn:population":24,
    "gn:timezone":"Europe/Rome",
    "iso:country":"IT",
    "wof:name":"Cascina Bosco",
    "wof:placetype":"locality",
    "wof:population":24
},
  "geometry": {"coordinates":[9.84524,45.53793],"type":"Point"}
}