{
  "type": "Feature",
  "properties": {
    "gn:admin1_code":"2.0",
    "gn:admin2_code":"MT",
    "gn:admin3_code":"77022.0",
    "gn:asciiname":"Ischia Basento",
    "gn:country_code":"IT",
    "gn:dem":75,
    "gn:feature_class":"P",
    "gn:feature_code":"PPLL",
    "gn:name":"Ischia Basento",
    "gn:population":0,
    "gn:timezone":"Europe/Rome",
    "iso:country":"IT",
    "wof:name":"Ischia Basento",
    "wof:placetype":"locality"
},
  "geometry": {"coordinates":[16.47781,40.5199],"type":"Point"}
}