{
  "type": "Feature",
  "properties": {
    "gn:admin1_code":"5",
    "gn:admin2_code":"PR",
    "gn:admin3_code":"34038.0",
    "gn:asciiname":"Puilio",
    "gn:country_code":"IT",
    "gn:dem":738,
    "gn:feature_class":"P",
    "gn:feature_code":"PPL",
    "gn:name":"Puilio",
    "gn:population":32,
    "gn:timezone":"Europe/Rome",
    "iso:country":"IT",
    "wof:name":"Puilio",
    "wof:placetype":"locality",
    "wof:population":32
},
  "geometry": {"coordinates":[10.08188,44.59483],"type":"Point"}
}