{
  "type": "Feature",
  "properties": {
    "gn:admin1_code":"15",
    "gn:admin2_code":"PA",
    "gn:admin3_code":"82027.0",
    "gn:asciiname":"Settefrati",
    "gn:country_code":"IT",
    "gn:dem":27,
    "gn:feature_class":"P",
    "gn:feature_code":"PPL",
    "gn:name":"Settefrati",
    "gn:population":19,
    "gn:timezone":"Europe/Rome",
    "iso:country":"IT",
    "name:azb_x_preferred":[
        "\u0633\u062a\u0641\u0631\u0627\u062a\u06cc"
    ],
    "name:bcl_x_preferred":[
        "Settefrati"
    ],
    "name:bel_x_preferred":[
        "\u0421\u0435\u0442\u044d\u0444\u0440\u0430\u0446\u0456"
    ],
    "name:bul_x_preferred":[
        "\u0421\u0435\u0442\u0435\u0444\u0440\u0430\u0442\u0438"
    ],
    "name:ceb_x_preferred":[
        "Settefrati"
    ],
    "name:cos_x_preferred":[
        "Settefrati"
    ],
    "name:deu_x_preferred":[
        "Settefrati"
    ],
    "name:epo_x_preferred":[
        "Settefrati"
    ],
    "name:eus_x_preferred":[
        "Settefrati"
    ],
    "name:fas_x_preferred":[
        "\u0633\u062a\u0641\u0631\u0627\u062a\u06cc"
    ],
    "name:fra_x_preferred":[
        "Settefrati"
    ],
    "name:hun_x_preferred":[
        "Settefrati"
    ],
    "name:hye_x_preferred":[
        "\u054d\u0565\u057f\u0565\u0586\u0580\u0561\u057f\u056b"
    ],
    "name:ina_x_preferred":[
        "Settefrati"
    ],
    "name:ita_x_preferred":[
        "Settefrati"
    ],
    "name:jpn_x_preferred":[
        "\u30bb\u30c3\u30c6\u30d5\u30e9\u30fc\u30c6\u30a3"
    ],
    "name:kaz_x_preferred":[
        "\u0421\u0435\u0442\u0442\u0435\u0444\u0440\u0430\u0442\u0438"
    ],
    "name:kor_x_preferred":[
        "\uc138\ud14c\ud504\ub77c\ud2f0"
    ],
    "name:lat_x_preferred":[
        "Septem Fratrum"
    ],
    "name:lmo_x_preferred":[
        "Settefrati"
    ],
    "name:msa_x_preferred":[
        "Settefrati"
    ],
    "name:nap_x_preferred":[
        "Settefrati"
    ],
    "name:nld_x_preferred":[
        "Settefrati"
    ],
    "name:pms_x_preferred":[
        "Settefrati"
    ],
    "name:pol_x_preferred":[
        "Settefrati"
    ],
    "name:por_x_preferred":[
        "Settefrati"
    ],
    "name:ron_x_preferred":[
        "Settefrati"
    ],
    "name:rus_x_preferred":[
        "\u0421\u0435\u0442\u0442\u0435\u0444\u0440\u0430\u0442\u0438"
    ],
    "name:scn_x_preferred":[
        "Sittifrati"
    ],
    "name:spa_x_preferred":[
        "Settefrati"
    ],
    "name:srp_x_preferred":[
        "\u0421\u0435\u0442\u0435\u0444\u0440\u0430\u0442\u0438"
    ],
    "name:ukr_x_preferred":[
        "\u0421\u0435\u0442\u0442\u0435\u0444\u0440\u0430\u0442\u0456"
    ],
    "name:uzb_x_preferred":[
        "Settefrati"
    ],
    "name:vie_x_preferred":[
        "Settefrati"
    ],
    "name:vol_x_preferred":[
        "Settefrati"
    ],
    "name:war_x_preferred":[
        "Settefrati"
    ],
    "name:zho_x_preferred":[
        "\u585e\u6cf0\u592b\u62c9\u8482"
    ],
    "wof:name":"Settefrati",
    "wof:placetype":"locality",
    "wof:population":19
},
  "geometry": {"coordinates":[13.96384,38.02686],"type":"Point"}
}