{
  "type": "Feature",
  "properties": {
    "gn:admin1_code":"15",
    "gn:admin2_code":"PA",
    "gn:admin3_code":"82027.0",
    "gn:asciiname":"Settefrati",
    "gn:country_code":"IT",
    "gn:dem":27,
    "gn:feature_class":"P",
    "gn:feature_code":"PPL",
    "gn:name":"Settefrati",
    "gn:population":19,
    "gn:timezone":"Europe/Rome",
    "iso:country":"IT",
    "wof:name":"Settefrati",
    "wof:placetype":"locality",
    "wof:population":19
},
  "geometry": {"coordinates":[13.96384,38.02686],"type":"Point"}
}