{
  "type": "Feature",
  "properties": {
    "gn:admin1_code":"10",
    "gn:admin2_code":"MC",
    "gn:admin3_code":"43028.0",
    "gn:asciiname":"Selve",
    "gn:country_code":"IT",
    "gn:dem":67,
    "gn:feature_class":"P",
    "gn:feature_code":"PPL",
    "gn:name":"Selve",
    "gn:population":22,
    "gn:timezone":"Europe/Rome",
    "iso:country":"IT",
    "wof:name":"Selve",
    "wof:placetype":"locality",
    "wof:population":22
},
  "geometry": {"coordinates":[13.63328,43.29119],"type":"Point"}
}