{
  "type": "Feature",
  "properties": {
    "gn:admin1_code":"20.0",
    "gn:admin2_code":"TV",
    "gn:admin3_code":"26046.0",
    "gn:asciiname":"Caonada",
    "gn:country_code":"IT",
    "gn:dem":117,
    "gn:feature_class":"P",
    "gn:feature_code":"PPL",
    "gn:name":"Caonada",
    "gn:population":0,
    "gn:timezone":"Europe/Rome",
    "iso:country":"IT",
    "wof:name":"Caonada",
    "wof:placetype":"locality"
},
  "geometry": {"coordinates":[12.07056,45.78528],"type":"Point"}
}