{
  "type": "Feature",
  "properties": {
    "gn:admin1_code":"20",
    "gn:admin2_code":"VI",
    "gn:admin3_code":"24053.0",
    "gn:asciiname":"Molan",
    "gn:country_code":"IT",
    "gn:dem":157,
    "gn:feature_class":"P",
    "gn:feature_code":"PPL",
    "gn:name":"Molan",
    "gn:population":70,
    "gn:timezone":"Europe/Rome",
    "iso:country":"IT",
    "wof:name":"Molan",
    "wof:placetype":"locality",
    "wof:population":70
},
  "geometry": {"coordinates":[11.5168,45.74844],"type":"Point"}
}