{
  "type": "Feature",
  "properties": {
    "gn:admin1_code":"20",
    "gn:admin2_code":"VE",
    "gn:admin3_code":"27013.0",
    "gn:asciiname":"Tabina",
    "gn:country_code":"IT",
    "gn:dem":0,
    "gn:feature_class":"P",
    "gn:feature_code":"PPL",
    "gn:name":"Tabina",
    "gn:population":50,
    "gn:timezone":"Europe/Rome",
    "iso:country":"IT",
    "wof:name":"Tabina",
    "wof:placetype":"locality",
    "wof:population":50
},
  "geometry": {"coordinates":[12.68316,45.59478],"type":"Point"}
}