{
  "type": "Feature",
  "properties": {
    "gn:admin1_code":"9",
    "gn:admin2_code":"BG",
    "gn:admin3_code":"16006.0",
    "gn:asciiname":"Carosso",
    "gn:country_code":"IT",
    "gn:dem":356,
    "gn:feature_class":"P",
    "gn:feature_code":"PPL",
    "gn:name":"Carosso",
    "gn:population":185,
    "gn:timezone":"Europe/Rome",
    "iso:country":"IT",
    "wof:name":"Carosso",
    "wof:placetype":"locality",
    "wof:population":185
},
  "geometry": {"coordinates":[9.54693,45.74987],"type":"Point"}
}