{
  "type": "Feature",
  "properties": {
    "gn:admin1_code":"5.0",
    "gn:admin2_code":"PR",
    "gn:admin3_code":"34022.0",
    "gn:asciiname":"Rimagna",
    "gn:cc2":"IT",
    "gn:country_code":"IT",
    "gn:dem":978,
    "gn:elevation":"963.0",
    "gn:feature_class":"P",
    "gn:feature_code":"PPL",
    "gn:name":"Rimagna",
    "gn:population":67,
    "gn:timezone":"Europe/Rome",
    "iso:country":"IT",
    "name:und_x_variant":[
        "Rimigna",
        "Rimagna"
    ],
    "wof:name":"Rimagna",
    "wof:placetype":"locality",
    "wof:population":67
},
  "geometry": {"coordinates":[10.1282,44.38711],"type":"Point"}
}