{
  "type": "Feature",
  "properties": {
    "gn:admin1_code":"11",
    "gn:admin2_code":"CB",
    "gn:admin3_code":"70008.0",
    "gn:asciiname":"San Silvestro",
    "gn:country_code":"IT",
    "gn:dem":549,
    "gn:feature_class":"P",
    "gn:feature_code":"PPL",
    "gn:name":"San Silvestro",
    "gn:population":25,
    "gn:timezone":"Europe/Rome",
    "iso:country":"IT",
    "wof:name":"San Silvestro",
    "wof:placetype":"locality",
    "wof:population":25
},
  "geometry": {"coordinates":[14.73165,41.54305],"type":"Point"}
}