{
  "type": "Feature",
  "properties": {
    "gn:admin1_code":"9",
    "gn:admin2_code":"MN",
    "gn:admin3_code":"20052.0",
    "gn:asciiname":"Due Madonne",
    "gn:country_code":"IT",
    "gn:dem":14,
    "gn:feature_class":"P",
    "gn:feature_code":"PPL",
    "gn:name":"Due Madonne",
    "gn:population":18,
    "gn:timezone":"Europe/Rome",
    "iso:country":"IT",
    "wof:name":"Due Madonne",
    "wof:placetype":"locality",
    "wof:population":18
},
  "geometry": {"coordinates":[10.93506,45.10029],"type":"Point"}
}