{
  "type": "Feature",
  "properties": {
    "gn:admin1_code":"6.0",
    "gn:admin2_code":"UD",
    "gn:admin3_code":"30086.0",
    "gn:asciiname":"Biacis",
    "gn:country_code":"IT",
    "gn:dem":182,
    "gn:elevation":"179.0",
    "gn:feature_class":"P",
    "gn:feature_code":"PPL",
    "gn:name":"Biacis",
    "gn:population":80,
    "gn:timezone":"Europe/Rome",
    "iso:country":"IT",
    "wof:name":"Biacis",
    "wof:placetype":"locality",
    "wof:population":80
},
  "geometry": {"coordinates":[13.48237,46.14909],"type":"Point"}
}