{
  "type": "Feature",
  "properties": {
    "gn:gn_country":"IT",
    "gn:gn_fcode":"PPLA3",
    "gn:gn_pop":149,
    "gn:population":149,
    "iso:country":"IT",
    "name:azb_x_preferred":[
        "\u0631\u06cc\u062a\u0627\u0646\u0627"
    ],
    "name:bel_x_preferred":[
        "\u0420\u044b\u0442\u0430\u043d\u0430"
    ],
    "name:bul_x_preferred":[
        "\u0420\u0438\u0442\u0430\u043d\u0430"
    ],
    "name:cat_x_preferred":[
        "Ritana"
    ],
    "name:ceb_x_preferred":[
        "Rittana"
    ],
    "name:deu_x_preferred":[
        "Rittana"
    ],
    "name:eng_x_preferred":[
        "Rittana"
    ],
    "name:epo_x_preferred":[
        "Rittana"
    ],
    "name:eus_x_preferred":[
        "Rittana"
    ],
    "name:fas_x_preferred":[
        "\u0631\u06cc\u062a\u0627\u0646\u0627"
    ],
    "name:fra_x_preferred":[
        "Rittana"
    ],
    "name:hun_x_preferred":[
        "Rittana"
    ],
    "name:hye_x_preferred":[
        "\u054c\u056b\u0569\u0561\u0576\u0561"
    ],
    "name:ind_x_preferred":[
        "Rittana"
    ],
    "name:ita_x_preferred":[
        "Rittana"
    ],
    "name:jpn_x_preferred":[
        "\u30ea\u30c3\u30bf\u30fc\u30ca"
    ],
    "name:kaz_x_preferred":[
        "\u0420\u0438\u0442\u0442\u0430\u043d\u0430"
    ],
    "name:lat_x_preferred":[
        "Ritana"
    ],
    "name:lmo_x_preferred":[
        "Rittana"
    ],
    "name:msa_x_preferred":[
        "Rittana"
    ],
    "name:nan_x_preferred":[
        "Rittana"
    ],
    "name:nap_x_preferred":[
        "Rittana"
    ],
    "name:nld_x_preferred":[
        "Rittana"
    ],
    "name:oci_x_preferred":[
        "Ritana"
    ],
    "name:pms_x_preferred":[
        "Ritan-a"
    ],
    "name:pol_x_preferred":[
        "Rittana"
    ],
    "name:por_x_preferred":[
        "Rittana"
    ],
    "name:ron_x_preferred":[
        "Rittana"
    ],
    "name:rus_x_preferred":[
        "\u0420\u0438\u0442\u0442\u0430\u043d\u0430"
    ],
    "name:scn_x_preferred":[
        "Rittana"
    ],
    "name:spa_x_preferred":[
        "Rittana"
    ],
    "name:srp_x_preferred":[
        "Rittana"
    ],
    "name:tgl_x_preferred":[
        "Rittana"
    ],
    "name:ukr_x_preferred":[
        "\u0420\u0456\u0442\u0442\u0430\u043d\u0430"
    ],
    "name:uzb_x_preferred":[
        "Rittana"
    ],
    "name:vie_x_preferred":[
        "Rittana"
    ],
    "name:vol_x_preferred":[
        "Rittana"
    ],
    "name:war_x_preferred":[
        "Rittana"
    ],
    "name:zho_x_preferred":[
        "\u91cc\u5854\u7eb3"
    ],
    "qs_pg:aaroncc":"IT",
    "qs_pg:gn_country":"IT",
    "qs_pg:gn_fcode":"PPLA3",
    "qs_pg:gn_pop":149,
    "qs_pg:name":"Rittana",
    "qs_pg:name_adm0":"Italia",
    "qs_pg:name_adm1":"Piemonte",
    "qs_pg:photos_9k":1,
    "qs_pg:photos_9r":1,
    "qs_pg:photos_all":4,
    "qs_pg:photos_sr":0,
    "qs_pg:pop_sr":1,
    "qs_pg:qs_pg_placetype":"locality",
    "qs_pg:qs_pg_placetype_gp":"Town",
    "qs_pg:woe_adm0":23424853,
    "woe:adm0_id":23424853,
    "woe:name_adm0":"Italia",
    "woe:name_adm1":"Piemonte",
    "woe:placetype":"Town",
    "wof:name":"Rittana",
    "wof:placetype":"locality",
    "wof:population":149
},
  "geometry": {"coordinates":[7.39843,44.35103],"type":"Point"}
}