{
  "type": "Feature",
  "properties": {
    "gn:admin1_code":"7",
    "gn:admin2_code":"VT",
    "gn:admin3_code":"56036.0",
    "gn:asciiname":"Paoletti",
    "gn:country_code":"IT",
    "gn:dem":410,
    "gn:feature_class":"P",
    "gn:feature_code":"PPL",
    "gn:name":"Paoletti",
    "gn:population":14,
    "gn:timezone":"Europe/Rome",
    "iso:country":"IT",
    "wof:name":"Paoletti",
    "wof:placetype":"locality",
    "wof:population":14
},
  "geometry": {"coordinates":[12.04284,42.51372],"type":"Point"}
}