{
  "type": "Feature",
  "properties": {
    "gn:admin1_code":"10",
    "gn:admin2_code":"PU",
    "gn:admin3_code":"41026.0",
    "gn:asciiname":"Ca' Merone",
    "gn:country_code":"IT",
    "gn:dem":404,
    "gn:feature_class":"P",
    "gn:feature_code":"PPL",
    "gn:name":"Ca' Merone",
    "gn:population":12,
    "gn:timezone":"Europe/Rome",
    "iso:country":"IT",
    "wof:name":"Ca' Merone",
    "wof:placetype":"locality",
    "wof:population":12
},
  "geometry": {"coordinates":[12.48624,43.87878],"type":"Point"}
}