{
  "type": "Feature",
  "properties": {
    "gn:admin1_code":"1",
    "gn:admin2_code":"CH",
    "gn:admin3_code":"69085.0",
    "gn:asciiname":"Brecciaio",
    "gn:country_code":"IT",
    "gn:dem":75,
    "gn:feature_class":"P",
    "gn:feature_code":"PPL",
    "gn:name":"Brecciaio",
    "gn:population":230,
    "gn:timezone":"Europe/Rome",
    "iso:country":"IT",
    "wof:name":"Brecciaio",
    "wof:placetype":"locality",
    "wof:population":230
},
  "geometry": {"coordinates":[14.39182,42.14006],"type":"Point"}
}