{
  "type": "Feature",
  "properties": {
    "gn:admin1_code":"9",
    "gn:admin2_code":"BS",
    "gn:admin3_code":"17122.0",
    "gn:asciiname":"Zona Artigianale",
    "gn:country_code":"IT",
    "gn:dem":70,
    "gn:feature_class":"P",
    "gn:feature_code":"PPL",
    "gn:name":"Zona Artigianale",
    "gn:population":33,
    "gn:timezone":"Europe/Rome",
    "iso:country":"IT",
    "wof:name":"Zona Artigianale",
    "wof:placetype":"locality",
    "wof:population":33
},
  "geometry": {"coordinates":[10.11956,45.3782],"type":"Point"}
}