{
  "type": "Feature",
  "properties": {
    "gn:admin1_code":"1.0",
    "gn:admin2_code":"AQ",
    "gn:admin3_code":"66065.0",
    "gn:asciiname":"Tre Nevi",
    "gn:country_code":"IT",
    "gn:dem":1806,
    "gn:feature_class":"P",
    "gn:feature_code":"PPL",
    "gn:name":"Tre Nevi",
    "gn:population":0,
    "gn:timezone":"Europe/Rome",
    "iso:country":"IT",
    "wof:name":"Tre Nevi",
    "wof:placetype":"locality"
},
  "geometry": {"coordinates":[13.478,42.14435],"type":"Point"}
}