{
  "type": "Feature",
  "properties": {
    "gn:admin1_code":"20",
    "gn:admin2_code":"VE",
    "gn:admin3_code":"27001.0",
    "gn:asciiname":"Oltrefossa",
    "gn:country_code":"IT",
    "gn:dem":5,
    "gn:feature_class":"P",
    "gn:feature_code":"PPL",
    "gn:name":"Oltrefossa",
    "gn:population":32,
    "gn:timezone":"Europe/Rome",
    "iso:country":"IT",
    "wof:name":"Oltrefossa",
    "wof:placetype":"locality",
    "wof:population":32
},
  "geometry": {"coordinates":[12.67817,45.7897],"type":"Point"}
}