{
  "type": "Feature",
  "properties": {
    "gn:admin1_code":"3.0",
    "gn:admin2_code":"RC",
    "gn:admin3_code":"80095.0",
    "gn:asciiname":"Oliva",
    "gn:country_code":"IT",
    "gn:dem":225,
    "gn:feature_class":"P",
    "gn:feature_code":"PPL",
    "gn:name":"Oliva",
    "gn:population":0,
    "gn:timezone":"Europe/Rome",
    "iso:country":"IT",
    "wof:name":"Oliva",
    "wof:placetype":"locality"
},
  "geometry": {"coordinates":[15.98333,38.31667],"type":"Point"}
}