{
  "type": "Feature",
  "properties": {
    "gn:admin1_code":"9.0",
    "gn:admin2_code":"MI",
    "gn:admin3_code":"15247.0",
    "gn:asciiname":"Casiglio",
    "gn:country_code":"IT",
    "gn:dem":101,
    "gn:feature_class":"P",
    "gn:feature_code":"PPL",
    "gn:name":"Casiglio",
    "gn:population":27,
    "gn:timezone":"Europe/Rome",
    "iso:country":"IT",
    "wof:name":"Casiglio",
    "wof:placetype":"locality",
    "wof:population":27
},
  "geometry": {"coordinates":[9.12087,45.35989],"type":"Point"}
}