{
  "type": "Feature",
  "properties": {
    "gn:admin1_code":"4",
    "gn:admin2_code":"AV",
    "gn:admin3_code":"64052.0",
    "gn:asciiname":"Santo Spirito",
    "gn:country_code":"IT",
    "gn:dem":392,
    "gn:feature_class":"P",
    "gn:feature_code":"PPL",
    "gn:name":"Santo Spirito",
    "gn:population":25,
    "gn:timezone":"Europe/Rome",
    "iso:country":"IT",
    "wof:name":"Santo Spirito",
    "wof:placetype":"locality",
    "wof:population":25
},
  "geometry": {"coordinates":[15.04501,41.21829],"type":"Point"}
}