{
  "type": "Feature",
  "properties": {
    "iso:country":"IT",
    "name:eng_x_preferred":[
        "Prato Centenaro"
    ],
    "name:fra_x_preferred":[
        "Prato Centenaro"
    ],
    "name:ita_x_preferred":[
        "Prato Centenaro"
    ],
    "name:lmo_x_preferred":[
        "Presciantenee"
    ],
    "name:nld_x_preferred":[
        "Prato Centenaro"
    ],
    "wof:name":"Prato Centenaro",
    "wof:placetype":"neighbourhood"
},
  "geometry": {"coordinates":[9.2005610578081,45.50964461886952],"type":"Point"}
}