{
  "type": "Feature",
  "properties": {
    "gn:admin1_code":"20",
    "gn:admin2_code":"VR",
    "gn:admin3_code":"23082.0",
    "gn:asciiname":"Rampa",
    "gn:country_code":"IT",
    "gn:dem":83,
    "gn:feature_class":"P",
    "gn:feature_code":"PPL",
    "gn:name":"Rampa",
    "gn:population":98,
    "gn:timezone":"Europe/Rome",
    "iso:country":"IT",
    "name:cat_x_preferred":[
        "Rampa"
    ],
    "name:ces_x_preferred":[
        "Rampa"
    ],
    "name:deu_x_preferred":[
        "Rampa"
    ],
    "name:kaz_x_preferred":[
        "\u0420\u0430\u043c\u043f\u0430"
    ],
    "name:pol_x_preferred":[
        "Rampa"
    ],
    "name:por_x_preferred":[
        "Rampa"
    ],
    "name:rus_x_preferred":[
        "\u0420\u0430\u043c\u043f\u0430"
    ],
    "name:srp_x_preferred":[
        "Rampa"
    ],
    "name:ukr_x_preferred":[
        "\u0420\u0430\u043c\u043f\u0430"
    ],
    "wof:name":"Rampa",
    "wof:placetype":"locality",
    "wof:population":98
},
  "geometry": {"coordinates":[10.90103,45.42503],"type":"Point"}
}