{
  "type": "Feature",
  "properties": {
    "gn:admin1_code":"2",
    "gn:admin2_code":"PZ",
    "gn:admin3_code":"76063.0",
    "gn:asciiname":"Macchia Capraia",
    "gn:country_code":"IT",
    "gn:dem":916,
    "gn:feature_class":"P",
    "gn:feature_code":"PPL",
    "gn:name":"Macchia Capraia",
    "gn:population":125,
    "gn:timezone":"Europe/Rome",
    "iso:country":"IT",
    "wof:name":"Macchia Capraia",
    "wof:placetype":"locality",
    "wof:population":125
},
  "geometry": {"coordinates":[15.81477,40.73068],"type":"Point"}
}