{
  "type": "Feature",
  "properties": {
    "gn:admin1_code":"20",
    "gn:admin2_code":"RO",
    "gn:admin3_code":"29021.0",
    "gn:asciiname":"Vallicella Bassa",
    "gn:country_code":"IT",
    "gn:dem":5,
    "gn:feature_class":"P",
    "gn:feature_code":"PPL",
    "gn:name":"Vallicella Bassa",
    "gn:population":103,
    "gn:timezone":"Europe/Rome",
    "iso:country":"IT",
    "wof:name":"Vallicella Bassa",
    "wof:placetype":"locality",
    "wof:population":103
},
  "geometry": {"coordinates":[11.44062,44.97197],"type":"Point"}
}