{
  "type": "Feature",
  "properties": {
    "gn:admin1_code":"3",
    "gn:admin2_code":"CS",
    "gn:admin3_code":"78036.0",
    "gn:asciiname":"Masseria Adduci",
    "gn:country_code":"IT",
    "gn:dem":79,
    "gn:feature_class":"P",
    "gn:feature_code":"PPL",
    "gn:name":"Masseria Adduci",
    "gn:population":15,
    "gn:timezone":"Europe/Rome",
    "iso:country":"IT",
    "wof:name":"Masseria Adduci",
    "wof:placetype":"locality",
    "wof:population":15
},
  "geometry": {"coordinates":[16.43437999999999,39.82464],"type":"Point"}
}