{
  "type": "Feature",
  "properties": {
    "gn:admin1_code":"5",
    "gn:admin2_code":"PR",
    "gn:admin3_code":"34002.0",
    "gn:asciiname":"Brugnoli",
    "gn:country_code":"IT",
    "gn:dem":583,
    "gn:feature_class":"P",
    "gn:feature_code":"PPLL",
    "gn:name":"Brugnoli",
    "gn:population":10,
    "gn:timezone":"Europe/Rome",
    "iso:country":"IT",
    "wof:name":"Brugnoli",
    "wof:placetype":"locality",
    "wof:population":10
},
  "geometry": {"coordinates":[9.76146,44.65319],"type":"Point"}
}