{
  "type": "Feature",
  "properties": {
    "gn:admin1_code":"20",
    "gn:admin2_code":"TV",
    "gn:admin3_code":"26038.0",
    "gn:asciiname":"Borgo Dall'Armellina I",
    "gn:country_code":"IT",
    "gn:dem":42,
    "gn:feature_class":"P",
    "gn:feature_code":"PPL",
    "gn:name":"Borgo Dall'Armellina I",
    "gn:population":27,
    "gn:timezone":"Europe/Rome",
    "iso:country":"IT",
    "wof:name":"Borgo Dall'Armellina I",
    "wof:placetype":"locality",
    "wof:population":27
},
  "geometry": {"coordinates":[12.33297,45.83518],"type":"Point"}
}