{
  "type": "Feature",
  "properties": {
    "gn:admin1_code":"5.0",
    "gn:admin2_code":"PC",
    "gn:admin3_code":"33011.0",
    "gn:asciiname":"Valle di Segola",
    "gn:country_code":"IT",
    "gn:dem":272,
    "gn:feature_class":"P",
    "gn:feature_code":"PPL",
    "gn:name":"Valle di Segola",
    "gn:population":16,
    "gn:timezone":"Europe/Rome",
    "iso:country":"IT",
    "wof:name":"Valle di Segola",
    "wof:placetype":"locality",
    "wof:population":16
},
  "geometry": {"coordinates":[9.79636,44.85245],"type":"Point"}
}