{
  "type": "Feature",
  "properties": {
    "gn:admin1_code":"7.0",
    "gn:admin2_code":"FR",
    "gn:admin3_code":"60019.0",
    "gn:asciiname":"San Nicola",
    "gn:country_code":"IT",
    "gn:dem":70,
    "gn:feature_class":"P",
    "gn:feature_code":"PPL",
    "gn:name":"San Nicola",
    "gn:population":340,
    "gn:timezone":"Europe/Rome",
    "iso:country":"IT",
    "wof:name":"San Nicola",
    "wof:placetype":"locality",
    "wof:population":340
},
  "geometry": {"coordinates":[13.80758,41.45847],"type":"Point"}
}