{
  "type": "Feature",
  "properties": {
    "gn:admin1_code":"5",
    "gn:admin2_code":"FE",
    "gn:admin3_code":"38024.0",
    "gn:asciiname":"La Grotta",
    "gn:country_code":"IT",
    "gn:dem":-1,
    "gn:feature_class":"P",
    "gn:feature_code":"PPL",
    "gn:name":"La Grotta",
    "gn:population":12,
    "gn:timezone":"Europe/Rome",
    "iso:country":"IT",
    "wof:name":"La Grotta",
    "wof:placetype":"locality",
    "wof:population":12
},
  "geometry": {"coordinates":[11.90626,44.82364000000001],"type":"Point"}
}