{
  "type": "Feature",
  "properties": {
    "gn:admin1_code":"5.0",
    "gn:admin2_code":"FC",
    "gn:admin3_code":"40001.0",
    "gn:asciiname":"La Lama",
    "gn:country_code":"IT",
    "gn:dem":824,
    "gn:feature_class":"P",
    "gn:feature_code":"PPL",
    "gn:name":"La Lama",
    "gn:population":0,
    "gn:timezone":"Europe/Rome",
    "iso:country":"IT",
    "wof:name":"La Lama",
    "wof:placetype":"locality"
},
  "geometry": {"coordinates":[11.83333,43.83333],"type":"Point"}
}