{
  "type": "Feature",
  "properties": {
    "gn:admin1_code":"5",
    "gn:admin2_code":"RN",
    "gn:admin3_code":"99005.0",
    "gn:asciiname":"Camilluccia-Ca' Gallo",
    "gn:country_code":"IT",
    "gn:dem":59,
    "gn:feature_class":"P",
    "gn:feature_code":"PPL",
    "gn:name":"Camilluccia-Ca' Gallo",
    "gn:population":208,
    "gn:timezone":"Europe/Rome",
    "iso:country":"IT",
    "wof:name":"Camilluccia-Ca' Gallo",
    "wof:placetype":"locality",
    "wof:population":208
},
  "geometry": {"coordinates":[12.66293,43.96734],"type":"Point"}
}