{
  "type": "Feature",
  "properties": {
    "gn:admin1_code":"13.0",
    "gn:admin2_code":"BA",
    "gn:admin3_code":"72044.0",
    "gn:asciiname":"Quasano",
    "gn:cc2":"IT",
    "gn:country_code":"IT",
    "gn:dem":357,
    "gn:elevation":"369.0",
    "gn:feature_class":"P",
    "gn:feature_code":"PPLA3",
    "gn:name":"Quasano",
    "gn:population":305,
    "gn:timezone":"Europe/Rome",
    "iso:country":"IT",
    "name:und_x_variant":[
        "Quasani"
    ],
    "wof:name":"Quasano",
    "wof:placetype":"locality",
    "wof:population":305
},
  "geometry": {"coordinates":[16.57354,40.96724],"type":"Point"}
}