{
  "type": "Feature",
  "properties": {
    "gn:admin1_code":"12",
    "gn:admin2_code":"BI",
    "gn:admin3_code":"96035.0",
    "gn:asciiname":"Granero",
    "gn:country_code":"IT",
    "gn:dem":428,
    "gn:feature_class":"P",
    "gn:feature_code":"PPL",
    "gn:name":"Granero",
    "gn:population":46,
    "gn:timezone":"Europe/Rome",
    "iso:country":"IT",
    "wof:name":"Granero",
    "wof:placetype":"locality",
    "wof:population":46
},
  "geometry": {"coordinates":[7.99736,45.52244],"type":"Point"}
}