{
  "type": "Feature",
  "properties": {
    "gn:admin1_code":"7",
    "gn:admin2_code":"FR",
    "gn:admin3_code":"60079.0",
    "gn:asciiname":"Colle Cannuccio",
    "gn:country_code":"IT",
    "gn:dem":262,
    "gn:feature_class":"P",
    "gn:feature_code":"PPL",
    "gn:name":"Colle Cannuccio",
    "gn:population":65,
    "gn:timezone":"Europe/Rome",
    "iso:country":"IT",
    "wof:name":"Colle Cannuccio",
    "wof:placetype":"locality",
    "wof:population":65
},
  "geometry": {"coordinates":[13.3831,41.64484],"type":"Point"}
}