{
  "type": "Feature",
  "properties": {
    "gn:admin1_code":"20",
    "gn:admin2_code":"VR",
    "gn:admin3_code":"23024.0",
    "gn:asciiname":"Pissolo di Sotto",
    "gn:country_code":"IT",
    "gn:dem":121,
    "gn:feature_class":"P",
    "gn:feature_code":"PPL",
    "gn:name":"Pissolo di Sotto",
    "gn:population":46,
    "gn:timezone":"Europe/Rome",
    "iso:country":"IT",
    "wof:name":"Pissolo di Sotto",
    "wof:placetype":"locality",
    "wof:population":46
},
  "geometry": {"coordinates":[11.21655,45.46895],"type":"Point"}
}