{
  "type": "Feature",
  "properties": {
    "gn:admin1_code":"12",
    "gn:admin2_code":"CN",
    "gn:admin3_code":"4166.0",
    "gn:asciiname":"Borgo San Giacomo",
    "gn:country_code":"IT",
    "gn:dem":526,
    "gn:feature_class":"P",
    "gn:feature_code":"PPL",
    "gn:name":"Borgo San Giacomo",
    "gn:population":26,
    "gn:timezone":"Europe/Rome",
    "iso:country":"IT",
    "name:azb_x_preferred":[
        "\u0628\u0648\u0631\u0642\u0648 \u0633\u0646 \u062c\u06cc\u0627\u06a9\u0648\u0645\u0648"
    ],
    "name:bul_x_preferred":[
        "\u0411\u043e\u0440\u0433\u043e \u0421\u0430\u043d \u0414\u0436\u0430\u043a\u043e\u043c\u043e"
    ],
    "name:cat_x_preferred":[
        "Borgo San Giacomo"
    ],
    "name:ceb_x_preferred":[
        "Borgo San Giacomo"
    ],
    "name:deu_x_preferred":[
        "Borgo San Giacomo"
    ],
    "name:epo_x_preferred":[
        "Borgo San Giacomo"
    ],
    "name:eus_x_preferred":[
        "Borgo San Giacomo"
    ],
    "name:fas_x_preferred":[
        "\u0628\u0648\u0631\u06af\u0648 \u0633\u0646 \u062c\u06cc\u0627\u06a9\u0648\u0645\u0648"
    ],
    "name:fra_x_preferred":[
        "Borgo San Giacomo"
    ],
    "name:hun_x_preferred":[
        "Borgo San Giacomo"
    ],
    "name:hye_x_preferred":[
        "\u0532\u0578\u0580\u0563\u0578 \u054d\u0561\u0576 \u054b\u0561\u056f\u0578\u0574\u0578"
    ],
    "name:ina_x_preferred":[
        "Borgo San Giacomo"
    ],
    "name:ind_x_preferred":[
        "Borgo San Giacomo"
    ],
    "name:ita_x_preferred":[
        "Borgo San Giacomo"
    ],
    "name:jpn_x_preferred":[
        "\u30dc\u30eb\u30b4\u30fb\u30b5\u30f3\u30fb\u30b8\u30e3\u30fc\u30b3\u30e2"
    ],
    "name:kaz_x_preferred":[
        "\u0411\u043e\u0440\u0433\u043e-\u0421\u0430\u043d-\u0414\u0436\u0430\u043a\u043e\u043c\u043e"
    ],
    "name:lat_x_preferred":[
        "Gabianum"
    ],
    "name:lmo_x_preferred":[
        "B\u00f3rch San Gi\u00e0com"
    ],
    "name:msa_x_preferred":[
        "Borgo San Giacomo"
    ],
    "name:nap_x_preferred":[
        "Borgo San Giacomo"
    ],
    "name:nld_x_preferred":[
        "Borgo San Giacomo"
    ],
    "name:pms_x_preferred":[
        "Borgo San Giacomo"
    ],
    "name:pol_x_preferred":[
        "Borgo San Giacomo"
    ],
    "name:por_x_preferred":[
        "Borgo San Giacomo"
    ],
    "name:ron_x_preferred":[
        "Borgo San Giacomo"
    ],
    "name:rus_x_preferred":[
        "\u0411\u043e\u0440\u0433\u043e-\u0421\u0430\u043d-\u0414\u0436\u0430\u043a\u043e\u043c\u043e"
    ],
    "name:scn_x_preferred":[
        "Borgo San Giacomo"
    ],
    "name:spa_x_preferred":[
        "Borgo San Giacomo"
    ],
    "name:srp_x_preferred":[
        "\u0411\u043e\u0440\u0433\u043e \u0421\u0430\u043d \u0402\u0430\u043a\u043e\u043c\u043e"
    ],
    "name:tgl_x_preferred":[
        "Borgo San Giacomo"
    ],
    "name:ukr_x_preferred":[
        "\u0411\u043e\u0440\u0433\u043e-\u0421\u0430\u043d-\u0414\u0436\u0430\u043a\u043e\u043c\u043e"
    ],
    "name:uzb_x_preferred":[
        "Borgo San Giacomo"
    ],
    "name:vie_x_preferred":[
        "Borgo San Giacomo"
    ],
    "name:vol_x_preferred":[
        "Borgo San Giacomo"
    ],
    "name:war_x_preferred":[
        "Borgo San Giacomo"
    ],
    "name:zho_x_preferred":[
        "\u535a\u5c14\u6208\u5723\u8d3e\u79d1\u83ab"
    ],
    "wof:name":"Borgo San Giacomo",
    "wof:placetype":"locality",
    "wof:population":26
},
  "geometry": {"coordinates":[7.43131,44.56132],"type":"Point"}
}