{
  "type": "Feature",
  "properties": {
    "gn:admin1_code":"12",
    "gn:admin2_code":"CN",
    "gn:admin3_code":"4166.0",
    "gn:asciiname":"Borgo San Giacomo",
    "gn:country_code":"IT",
    "gn:dem":526,
    "gn:feature_class":"P",
    "gn:feature_code":"PPL",
    "gn:name":"Borgo San Giacomo",
    "gn:population":26,
    "gn:timezone":"Europe/Rome",
    "iso:country":"IT",
    "wof:name":"Borgo San Giacomo",
    "wof:placetype":"locality",
    "wof:population":26
},
  "geometry": {"coordinates":[7.43131,44.56132],"type":"Point"}
}