{
  "type": "Feature",
  "properties": {
    "gn:admin1_code":"16",
    "gn:admin2_code":"PI",
    "gn:admin3_code":"50019.0",
    "gn:asciiname":"Gabella",
    "gn:country_code":"IT",
    "gn:dem":66,
    "gn:feature_class":"P",
    "gn:feature_code":"PPL",
    "gn:name":"Gabella",
    "gn:population":27,
    "gn:timezone":"Europe/Rome",
    "iso:country":"IT",
    "wof:name":"Gabella",
    "wof:placetype":"locality",
    "wof:population":27
},
  "geometry": {"coordinates":[10.70634,43.26817],"type":"Point"}
}