{
  "type": "Feature",
  "properties": {
    "gn:admin1_code":"16",
    "gn:admin2_code":"SI",
    "gn:admin3_code":"52018.0",
    "gn:asciiname":"Cerbaia",
    "gn:country_code":"IT",
    "gn:dem":453,
    "gn:feature_class":"P",
    "gn:feature_code":"PPL",
    "gn:name":"Cerbaia",
    "gn:population":42,
    "gn:timezone":"Europe/Rome",
    "iso:country":"IT",
    "wof:name":"Cerbaia",
    "wof:placetype":"locality",
    "wof:population":42
},
  "geometry": {"coordinates":[11.26071,43.09806],"type":"Point"}
}