{
  "type": "Feature",
  "properties": {
    "gn:admin1_code":"9",
    "gn:admin2_code":"CR",
    "gn:admin3_code":"19087.0",
    "gn:asciiname":"Albera",
    "gn:country_code":"IT",
    "gn:dem":78,
    "gn:feature_class":"P",
    "gn:feature_code":"PPL",
    "gn:name":"Albera",
    "gn:population":23,
    "gn:timezone":"Europe/Rome",
    "iso:country":"IT",
    "name:cat_x_preferred":[
        "Albera"
    ],
    "name:deu_x_preferred":[
        "Albera"
    ],
    "name:ita_x_preferred":[
        "Albera"
    ],
    "name:srp_x_preferred":[
        "Albera"
    ],
    "wof:name":"Albera",
    "wof:placetype":"locality",
    "wof:population":23
},
  "geometry": {"coordinates":[9.80482,45.36601],"type":"Point"}
}