{
  "type": "Feature",
  "properties": {
    "gn:admin1_code":"15",
    "gn:admin2_code":"RG",
    "gn:admin3_code":"88003.0",
    "gn:asciiname":"Quaglio",
    "gn:country_code":"IT",
    "gn:dem":253,
    "gn:feature_class":"P",
    "gn:feature_code":"PPL",
    "gn:name":"Quaglio",
    "gn:population":39,
    "gn:timezone":"Europe/Rome",
    "iso:country":"IT",
    "name:deu_x_preferred":[
        "Quaglio"
    ],
    "name:fra_x_preferred":[
        "Quaglio"
    ],
    "name:rus_x_preferred":[
        "\u041a\u0432\u0430\u043b\u044c\u043e"
    ],
    "name:slv_x_preferred":[
        "Quaglio"
    ],
    "name:swe_x_preferred":[
        "Quaglio"
    ],
    "wof:name":"Quaglio",
    "wof:placetype":"locality",
    "wof:population":39
},
  "geometry": {"coordinates":[14.60034,37.03798],"type":"Point"}
}