{
  "type": "Feature",
  "properties": {
    "gn:admin1_code":"20",
    "gn:admin2_code":"BL",
    "gn:admin3_code":"25006.0",
    "gn:asciiname":"Pra de Luni",
    "gn:country_code":"IT",
    "gn:dem":684,
    "gn:feature_class":"P",
    "gn:feature_code":"PPL",
    "gn:name":"Pra de Luni",
    "gn:population":17,
    "gn:timezone":"Europe/Rome",
    "iso:country":"IT",
    "wof:name":"Pra de Luni",
    "wof:placetype":"locality",
    "wof:population":17
},
  "geometry": {"coordinates":[12.194,46.18195],"type":"Point"}
}