{
  "type": "Feature",
  "properties": {
    "gn:admin1_code":"5",
    "gn:admin2_code":"FC",
    "gn:admin3_code":"40041.0",
    "gn:asciiname":"Cagnona",
    "gn:country_code":"IT",
    "gn:dem":1,
    "gn:feature_class":"P",
    "gn:feature_code":"PPL",
    "gn:name":"Cagnona",
    "gn:population":59,
    "gn:timezone":"Europe/Rome",
    "iso:country":"IT",
    "wof:name":"Cagnona",
    "wof:placetype":"locality",
    "wof:population":59
},
  "geometry": {"coordinates":[12.43149,44.15184],"type":"Point"}
}