{
  "type": "Feature",
  "properties": {
    "gn:admin1_code":"5.0",
    "gn:admin2_code":"RN",
    "gn:admin3_code":"99003.0",
    "gn:asciiname":"Vecciano",
    "gn:country_code":"IT",
    "gn:dem":74,
    "gn:feature_class":"P",
    "gn:feature_code":"PPL",
    "gn:name":"Vecciano",
    "gn:population":45,
    "gn:timezone":"Europe/Rome",
    "iso:country":"IT",
    "wof:name":"Vecciano",
    "wof:placetype":"locality",
    "wof:population":45
},
  "geometry": {"coordinates":[12.55649,43.95498],"type":"Point"}
}