{
  "type": "Feature",
  "properties": {
    "gn:admin1_code":"20",
    "gn:admin2_code":"VI",
    "gn:admin3_code":"24009.0",
    "gn:asciiname":"Buscar",
    "gn:country_code":"IT",
    "gn:dem":1094,
    "gn:feature_class":"P",
    "gn:feature_code":"PPL",
    "gn:name":"Buscar",
    "gn:population":46,
    "gn:timezone":"Europe/Rome",
    "iso:country":"IT",
    "wof:name":"Buscar",
    "wof:placetype":"locality",
    "wof:population":46
},
  "geometry": {"coordinates":[11.49116,45.8904],"type":"Point"}
}