{
  "type": "Feature",
  "properties": {
    "gn:admin1_code":"5",
    "gn:admin2_code":"BO",
    "gn:admin3_code":"37008.0",
    "gn:asciiname":"Case Lipparini",
    "gn:country_code":"IT",
    "gn:dem":14,
    "gn:feature_class":"P",
    "gn:feature_code":"PPL",
    "gn:name":"Case Lipparini",
    "gn:population":29,
    "gn:timezone":"Europe/Rome",
    "iso:country":"IT",
    "wof:name":"Case Lipparini",
    "wof:placetype":"locality",
    "wof:population":29
},
  "geometry": {"coordinates":[11.5788,44.59306],"type":"Point"}
}