{
  "type": "Feature",
  "properties": {
    "gn:admin1_code":"3",
    "gn:admin2_code":"RC",
    "gn:admin3_code":"80065.0",
    "gn:asciiname":"Stracozzi-Grasso",
    "gn:country_code":"IT",
    "gn:dem":127,
    "gn:feature_class":"P",
    "gn:feature_code":"PPL",
    "gn:name":"Stracozzi-Grasso",
    "gn:population":99,
    "gn:timezone":"Europe/Rome",
    "iso:country":"IT",
    "wof:name":"Stracozzi-Grasso",
    "wof:placetype":"locality",
    "wof:population":99
},
  "geometry": {"coordinates":[16.00652,38.40874],"type":"Point"}
}