{
  "type": "Feature",
  "properties": {
    "gn:admin1_code":"11",
    "gn:admin2_code":"CB",
    "gn:admin3_code":"70017.0",
    "gn:asciiname":"Petroccolo",
    "gn:country_code":"IT",
    "gn:dem":712,
    "gn:feature_class":"P",
    "gn:feature_code":"PPL",
    "gn:name":"Petroccolo",
    "gn:population":49,
    "gn:timezone":"Europe/Rome",
    "iso:country":"IT",
    "wof:name":"Petroccolo",
    "wof:placetype":"locality",
    "wof:population":49
},
  "geometry": {"coordinates":[14.7599,41.46979],"type":"Point"}
}