{
  "type": "Feature",
  "properties": {
    "gn:admin1_code":"20",
    "gn:admin2_code":"RO",
    "gn:admin3_code":"29001.0",
    "gn:asciiname":"Palazzon",
    "gn:country_code":"IT",
    "gn:dem":0,
    "gn:feature_class":"P",
    "gn:feature_code":"PPL",
    "gn:name":"Palazzon",
    "gn:population":138,
    "gn:timezone":"Europe/Rome",
    "iso:country":"IT",
    "wof:name":"Palazzon",
    "wof:placetype":"locality",
    "wof:population":138
},
  "geometry": {"coordinates":[12.032,45.0586],"type":"Point"}
}