{
  "type": "Feature",
  "properties": {
    "gn:admin1_code":"12",
    "gn:admin2_code":"NO",
    "gn:admin3_code":"3095.0",
    "gn:asciiname":"Silvera",
    "gn:country_code":"IT",
    "gn:dem":452,
    "gn:feature_class":"P",
    "gn:feature_code":"PPL",
    "gn:name":"Silvera",
    "gn:population":110,
    "gn:timezone":"Europe/Rome",
    "iso:country":"IT",
    "wof:name":"Silvera",
    "wof:placetype":"locality",
    "wof:population":110
},
  "geometry": {"coordinates":[8.49498,45.78205],"type":"Point"}
}