{
  "type": "Feature",
  "properties": {
    "gn:admin1_code":"20.0",
    "gn:admin2_code":"VE",
    "gn:admin3_code":"27034.0",
    "gn:asciiname":"Malafesta",
    "gn:country_code":"IT",
    "gn:dem":8,
    "gn:feature_class":"P",
    "gn:feature_code":"PPL",
    "gn:name":"Malafesta",
    "gn:population":259,
    "gn:timezone":"Europe/Rome",
    "iso:country":"IT",
    "wof:name":"Malafesta",
    "wof:placetype":"locality",
    "wof:population":259
},
  "geometry": {"coordinates":[12.96194,45.82611],"type":"Point"}
}