{
  "type": "Feature",
  "properties": {
    "gn:admin1_code":"12",
    "gn:admin2_code":"AL",
    "gn:admin3_code":"6049.0",
    "gn:asciiname":"Crebini",
    "gn:country_code":"IT",
    "gn:dem":209,
    "gn:feature_class":"P",
    "gn:feature_code":"PPL",
    "gn:name":"Crebini",
    "gn:population":275,
    "gn:timezone":"Europe/Rome",
    "iso:country":"IT",
    "wof:name":"Crebini",
    "wof:placetype":"locality",
    "wof:population":275
},
  "geometry": {"coordinates":[8.71969,44.69178],"type":"Point"}
}