{
  "type": "Feature",
  "properties": {
    "gn:admin1_code":"9.0",
    "gn:admin2_code":"CO",
    "gn:admin3_code":"13234.0",
    "gn:asciiname":"Puria",
    "gn:country_code":"IT",
    "gn:dem":512,
    "gn:elevation":"504.0",
    "gn:feature_class":"P",
    "gn:feature_code":"PPL",
    "gn:name":"Puria",
    "gn:population":314,
    "gn:timezone":"Europe/Rome",
    "iso:country":"IT",
    "wof:name":"Puria",
    "wof:placetype":"locality",
    "wof:population":314
},
  "geometry": {"coordinates":[9.05694,46.0324],"type":"Point"}
}