{
  "type": "Feature",
  "properties": {
    "gn:admin1_code":"3",
    "gn:admin2_code":"CS",
    "gn:admin3_code":"78071.0",
    "gn:asciiname":"Alorio",
    "gn:country_code":"IT",
    "gn:dem":315,
    "gn:feature_class":"P",
    "gn:feature_code":"PPL",
    "gn:name":"Alorio",
    "gn:population":223,
    "gn:timezone":"Europe/Rome",
    "iso:country":"IT",
    "wof:name":"Alorio",
    "wof:placetype":"locality",
    "wof:population":223
},
  "geometry": {"coordinates":[15.83972,39.71172],"type":"Point"}
}