{
  "type": "Feature",
  "properties": {
    "gn:admin1_code":"5",
    "gn:admin2_code":"RE",
    "gn:admin3_code":"35043.0",
    "gn:asciiname":"Signano",
    "gn:country_code":"IT",
    "gn:dem":349,
    "gn:feature_class":"P",
    "gn:feature_code":"PPL",
    "gn:name":"Signano",
    "gn:population":14,
    "gn:timezone":"Europe/Rome",
    "iso:country":"IT",
    "wof:name":"Signano",
    "wof:placetype":"locality",
    "wof:population":14
},
  "geometry": {"coordinates":[10.50993,44.57792],"type":"Point"}
}