{
  "type": "Feature",
  "properties": {
    "gn:admin1_code":"8",
    "gn:admin2_code":"SV",
    "gn:admin3_code":"9017.0",
    "gn:asciiname":"Miniera",
    "gn:country_code":"IT",
    "gn:dem":657,
    "gn:feature_class":"P",
    "gn:feature_code":"PPL",
    "gn:name":"Miniera",
    "gn:population":12,
    "gn:timezone":"Europe/Rome",
    "iso:country":"IT",
    "wof:name":"Miniera",
    "wof:placetype":"locality",
    "wof:population":12
},
  "geometry": {"coordinates":[8.11409,44.24712],"type":"Point"}
}