{
  "type": "Feature",
  "properties": {
    "gn:admin1_code":"3.0",
    "gn:admin2_code":"KR",
    "gn:admin3_code":"101021.0",
    "gn:asciiname":"Santa Domenica",
    "gn:country_code":"IT",
    "gn:dem":115,
    "gn:feature_class":"P",
    "gn:feature_code":"PPL",
    "gn:name":"Santa Domenica",
    "gn:population":0,
    "gn:timezone":"Europe/Rome",
    "iso:country":"IT",
    "wof:name":"Santa Domenica",
    "wof:placetype":"locality"
},
  "geometry": {"coordinates":[16.98333,39.26667],"type":"Point"}
}