{
  "type": "Feature",
  "properties": {
    "gn:admin1_code":"8",
    "gn:admin2_code":"SV",
    "gn:admin3_code":"9068.0",
    "gn:asciiname":"Marta",
    "gn:country_code":"IT",
    "gn:dem":169,
    "gn:feature_class":"P",
    "gn:feature_code":"PPL",
    "gn:name":"Marta",
    "gn:population":80,
    "gn:timezone":"Europe/Rome",
    "iso:country":"IT",
    "name:cat_x_preferred":[
        "Marta"
    ],
    "name:ceb_x_preferred":[
        "Marta"
    ],
    "name:deu_x_preferred":[
        "Marta"
    ],
    "name:epo_x_preferred":[
        "Marta"
    ],
    "name:est_x_preferred":[
        "Marta"
    ],
    "name:fas_x_preferred":[
        "\u0645\u0627\u0631\u062a\u0627"
    ],
    "name:fra_x_preferred":[
        "Marta"
    ],
    "name:glg_x_preferred":[
        "Marta"
    ],
    "name:hye_x_preferred":[
        "\u0544\u0561\u0580\u0569\u0561"
    ],
    "name:ita_x_preferred":[
        "Marta"
    ],
    "name:kor_x_preferred":[
        "\ub9c8\ub974\ud0c0"
    ],
    "name:lav_x_preferred":[
        "Marta"
    ],
    "name:nld_x_preferred":[
        "Marta"
    ],
    "name:pol_x_preferred":[
        "Marta"
    ],
    "name:por_x_preferred":[
        "Marta"
    ],
    "name:rus_x_preferred":[
        "\u041c\u0430\u0440\u0442\u0430"
    ],
    "name:scn_x_preferred":[
        "Marta"
    ],
    "name:slk_x_preferred":[
        "Marta"
    ],
    "name:slv_x_preferred":[
        "Marta"
    ],
    "name:spa_x_preferred":[
        "Marta"
    ],
    "name:srp_x_preferred":[
        "Marta"
    ],
    "name:swe_x_preferred":[
        "Marta"
    ],
    "name:tur_x_preferred":[
        "Marta"
    ],
    "name:ukr_x_preferred":[
        "\u041c\u0430\u0440\u0442\u0430"
    ],
    "wof:name":"Marta",
    "wof:placetype":"locality",
    "wof:population":80
},
  "geometry": {"coordinates":[8.12072,44.02514],"type":"Point"}
}