{
  "type": "Feature",
  "properties": {
    "gn:admin1_code":"8",
    "gn:admin2_code":"SV",
    "gn:admin3_code":"9068.0",
    "gn:asciiname":"Marta",
    "gn:country_code":"IT",
    "gn:dem":169,
    "gn:feature_class":"P",
    "gn:feature_code":"PPL",
    "gn:name":"Marta",
    "gn:population":80,
    "gn:timezone":"Europe/Rome",
    "iso:country":"IT",
    "wof:name":"Marta",
    "wof:placetype":"locality",
    "wof:population":80
},
  "geometry": {"coordinates":[8.12072,44.02514],"type":"Point"}
}