{
  "type": "Feature",
  "properties": {
    "gn:admin1_code":"6.0",
    "gn:admin2_code":"PN",
    "gn:admin3_code":"93022.0",
    "gn:asciiname":"La Croce",
    "gn:country_code":"IT",
    "gn:dem":29,
    "gn:elevation":"29.0",
    "gn:feature_class":"P",
    "gn:feature_code":"PPLL",
    "gn:name":"La Croce",
    "gn:population":158,
    "gn:timezone":"Europe/Rome",
    "iso:country":"IT",
    "wof:name":"La Croce",
    "wof:placetype":"locality",
    "wof:population":158
},
  "geometry": {"coordinates":[12.52544,45.9774],"type":"Point"}
}