{
  "type": "Feature",
  "properties": {
    "gn:admin1_code":"3",
    "gn:admin2_code":"RC",
    "gn:admin3_code":"80040.0",
    "gn:asciiname":"Farri-Barrici",
    "gn:country_code":"IT",
    "gn:dem":166,
    "gn:feature_class":"P",
    "gn:feature_code":"PPL",
    "gn:name":"Farri-Barrici",
    "gn:population":26,
    "gn:timezone":"Europe/Rome",
    "iso:country":"IT",
    "wof:name":"Farri-Barrici",
    "wof:placetype":"locality",
    "wof:population":26
},
  "geometry": {"coordinates":[16.26578,38.33902],"type":"Point"}
}