{
  "type": "Feature",
  "properties": {
    "gn:admin1_code":"20.0",
    "gn:admin2_code":"BL",
    "gn:admin3_code":"25029.0",
    "gn:asciiname":"Polentes",
    "gn:country_code":"IT",
    "gn:dem":437,
    "gn:feature_class":"P",
    "gn:feature_code":"PPL",
    "gn:name":"Polentes",
    "gn:population":94,
    "gn:timezone":"Europe/Rome",
    "iso:country":"IT",
    "wof:name":"Polentes",
    "wof:placetype":"locality",
    "wof:population":94
},
  "geometry": {"coordinates":[12.18583,46.08556],"type":"Point"}
}