{
  "type": "Feature",
  "properties": {
    "gn:admin1_code":"1.0",
    "gn:admin2_code":"TE",
    "gn:admin3_code":"67032.0",
    "gn:asciiname":"Colleluccio",
    "gn:country_code":"IT",
    "gn:dem":203,
    "gn:feature_class":"P",
    "gn:feature_code":"PPL",
    "gn:name":"Colleluccio",
    "gn:population":19,
    "gn:timezone":"Europe/Rome",
    "iso:country":"IT",
    "wof:name":"Colleluccio",
    "wof:placetype":"locality",
    "wof:population":19
},
  "geometry": {"coordinates":[13.87263,42.63963],"type":"Point"}
}