{
  "type": "Feature",
  "properties": {
    "gn:admin1_code":"6.0",
    "gn:admin2_code":"PN",
    "gn:admin3_code":"93038.0",
    "gn:asciiname":"Cosa",
    "gn:country_code":"IT",
    "gn:dem":83,
    "gn:elevation":"86.0",
    "gn:feature_class":"P",
    "gn:feature_code":"PPL",
    "gn:name":"Cosa",
    "gn:population":352,
    "gn:timezone":"Europe/Rome",
    "iso:country":"IT",
    "name:bul_x_preferred":[
        "\u041a\u043e\u0437\u0430"
    ],
    "name:cat_x_preferred":[
        "Cosa"
    ],
    "name:deu_x_preferred":[
        "Cosa"
    ],
    "name:heb_x_preferred":[
        "\u05e7\u05d5\u05e1\u05d4"
    ],
    "name:ita_x_preferred":[
        "Cosa"
    ],
    "name:lat_x_preferred":[
        "Cosa"
    ],
    "wof:name":"Cosa",
    "wof:placetype":"locality",
    "wof:population":352
},
  "geometry": {"coordinates":[12.8943,46.05601],"type":"Point"}
}