{
  "type": "Feature",
  "properties": {
    "gn:admin1_code":"7",
    "gn:admin2_code":"RM",
    "gn:admin3_code":"58120.0",
    "gn:asciiname":"Centro Tre Cannelle Barbabianca",
    "gn:country_code":"IT",
    "gn:dem":22,
    "gn:feature_class":"P",
    "gn:feature_code":"PPL",
    "gn:name":"Centro Tre Cannelle Barbabianca",
    "gn:population":37,
    "gn:timezone":"Europe/Rome",
    "iso:country":"IT",
    "wof:name":"Centro Tre Cannelle Barbabianca",
    "wof:placetype":"locality",
    "wof:population":37
},
  "geometry": {"coordinates":[12.2187,41.90404],"type":"Point"}
}