{
  "type": "Feature",
  "properties": {
    "gn:admin1_code":"16",
    "gn:admin2_code":"AR",
    "gn:admin3_code":"51023.0",
    "gn:asciiname":"Forcanasso",
    "gn:country_code":"IT",
    "gn:dem":711,
    "gn:feature_class":"P",
    "gn:feature_code":"PPLL",
    "gn:name":"Forcanasso",
    "gn:population":7,
    "gn:timezone":"Europe/Rome",
    "iso:country":"IT",
    "wof:name":"Forcanasso",
    "wof:placetype":"locality",
    "wof:population":7
},
  "geometry": {"coordinates":[11.62652,43.73746],"type":"Point"}
}