{
  "type": "Feature",
  "properties": {
    "gn:admin1_code":"16",
    "gn:admin2_code":"SI",
    "gn:admin3_code":"52013.0",
    "gn:asciiname":"Poggio San Polo",
    "gn:country_code":"IT",
    "gn:dem":523,
    "gn:feature_class":"P",
    "gn:feature_code":"PPL",
    "gn:name":"Poggio San Polo",
    "gn:population":29,
    "gn:timezone":"Europe/Rome",
    "iso:country":"IT",
    "wof:name":"Poggio San Polo",
    "wof:placetype":"locality",
    "wof:population":29
},
  "geometry": {"coordinates":[11.37815,43.44677],"type":"Point"}
}