{
  "type": "Feature",
  "properties": {
    "gn:admin1_code":"12",
    "gn:admin2_code":"TO",
    "gn:admin3_code":"1062.0",
    "gn:asciiname":"Grangiotto",
    "gn:country_code":"IT",
    "gn:dem":345,
    "gn:feature_class":"P",
    "gn:feature_code":"PPL",
    "gn:name":"Grangiotto",
    "gn:population":30,
    "gn:timezone":"Europe/Rome",
    "iso:country":"IT",
    "wof:name":"Grangiotto",
    "wof:placetype":"locality",
    "wof:population":30
},
  "geometry": {"coordinates":[7.45744,45.09836],"type":"Point"}
}