{
  "type": "Feature",
  "properties": {
    "gn:admin1_code":"20",
    "gn:admin2_code":"RO",
    "gn:admin3_code":"29001.0",
    "gn:asciiname":"Canareggio",
    "gn:country_code":"IT",
    "gn:dem":1,
    "gn:feature_class":"P",
    "gn:feature_code":"PPL",
    "gn:name":"Canareggio",
    "gn:population":68,
    "gn:timezone":"Europe/Rome",
    "iso:country":"IT",
    "wof:name":"Canareggio",
    "wof:placetype":"locality",
    "wof:population":68
},
  "geometry": {"coordinates":[12.05887,45.0742],"type":"Point"}
}