{
  "type": "Feature",
  "properties": {
    "gn:admin1_code":"20",
    "gn:admin2_code":"TV",
    "gn:admin3_code":"26008.0",
    "gn:asciiname":"Villa Maria",
    "gn:country_code":"IT",
    "gn:dem":21,
    "gn:feature_class":"P",
    "gn:feature_code":"PPL",
    "gn:name":"Villa Maria",
    "gn:population":22,
    "gn:timezone":"Europe/Rome",
    "iso:country":"IT",
    "name:cat_x_preferred":[
        "Villa Maria"
    ],
    "name:deu_x_preferred":[
        "Villa Maria"
    ],
    "name:fra_x_preferred":[
        "Villa-Maria"
    ],
    "name:ita_x_preferred":[
        "Villa Maria"
    ],
    "name:nld_x_preferred":[
        "Villa Maria"
    ],
    "name:por_x_preferred":[
        "Villa Mar\u00eda"
    ],
    "name:spa_x_preferred":[
        "Villa Mar\u00eda"
    ],
    "name:srp_x_preferred":[
        "Vila Marija"
    ],
    "wof:name":"Villa Maria",
    "wof:placetype":"locality",
    "wof:population":22
},
  "geometry": {"coordinates":[12.29024,45.69267],"type":"Point"}
}