{
  "type": "Feature",
  "properties": {
    "gn:admin1_code":"10.0",
    "gn:admin2_code":"MC",
    "gn:admin3_code":"43027.0",
    "gn:asciiname":"Pie' del Sasso",
    "gn:country_code":"IT",
    "gn:dem":672,
    "gn:feature_class":"P",
    "gn:feature_code":"PPLA3",
    "gn:name":"Pie' del Sasso",
    "gn:population":83,
    "gn:timezone":"Europe/Rome",
    "iso:country":"IT",
    "wof:name":"Pie' del Sasso",
    "wof:placetype":"locality",
    "wof:population":83
},
  "geometry": {"coordinates":[12.99889,42.99429],"type":"Point"}
}