{
  "type": "Feature",
  "properties": {
    "gn:admin1_code":"15.0",
    "gn:admin2_code":"PA",
    "gn:admin3_code":"82060.0",
    "gn:asciiname":"Filaga",
    "gn:country_code":"IT",
    "gn:dem":834,
    "gn:elevation":"828.0",
    "gn:feature_class":"P",
    "gn:feature_code":"PPL",
    "gn:name":"Filaga",
    "gn:population":220,
    "gn:timezone":"Europe/Rome",
    "iso:country":"IT",
    "wof:name":"Filaga",
    "wof:placetype":"locality",
    "wof:population":220
},
  "geometry": {"coordinates":[13.46759,37.69343],"type":"Point"}
}