{
  "type": "Feature",
  "properties": {
    "gn:admin1_code":"20.0",
    "gn:admin2_code":"VE",
    "gn:admin3_code":"27029.0",
    "gn:asciiname":"Lison",
    "gn:country_code":"IT",
    "gn:dem":3,
    "gn:elevation":"5.0",
    "gn:feature_class":"P",
    "gn:feature_code":"PPL",
    "gn:name":"Lison",
    "gn:population":209,
    "gn:timezone":"Europe/Rome",
    "iso:country":"IT",
    "name:bre_x_preferred":[
        "Lison"
    ],
    "name:cat_x_preferred":[
        "Lison"
    ],
    "name:ceb_x_preferred":[
        "Lison"
    ],
    "name:deu_x_preferred":[
        "Lison"
    ],
    "name:epo_x_preferred":[
        "Lison"
    ],
    "name:eus_x_preferred":[
        "Lison"
    ],
    "name:fra_x_preferred":[
        "Lison"
    ],
    "name:hun_x_preferred":[
        "Lison"
    ],
    "name:hye_x_preferred":[
        "\u053c\u056b\u0566\u0578\u0576"
    ],
    "name:ita_x_preferred":[
        "Lison"
    ],
    "name:kaz_x_preferred":[
        "\u041b\u0438\u0437\u043e\u043d"
    ],
    "name:lat_x_preferred":[
        "Lison"
    ],
    "name:msa_x_preferred":[
        "Lison"
    ],
    "name:nld_x_preferred":[
        "Lison"
    ],
    "name:oci_x_preferred":[
        "Lison"
    ],
    "name:pms_x_preferred":[
        "Lison"
    ],
    "name:pol_x_preferred":[
        "Lison"
    ],
    "name:por_x_preferred":[
        "Lison"
    ],
    "name:ron_x_preferred":[
        "Lison"
    ],
    "name:rus_x_preferred":[
        "\u041b\u0438\u0437\u043e\u043d"
    ],
    "name:slk_x_preferred":[
        "Lison"
    ],
    "name:spa_x_preferred":[
        "Lison"
    ],
    "name:swe_x_preferred":[
        "Lison"
    ],
    "name:ukr_x_preferred":[
        "\u041b\u0456\u0437\u043e\u043d"
    ],
    "name:uzb_x_preferred":[
        "Lison"
    ],
    "name:vie_x_preferred":[
        "Lison"
    ],
    "name:vol_x_preferred":[
        "Lison"
    ],
    "name:war_x_preferred":[
        "Lison"
    ],
    "wof:name":"Lison",
    "wof:placetype":"locality",
    "wof:population":209
},
  "geometry": {"coordinates":[12.7521,45.75656],"type":"Point"}
}