{
  "type": "Feature",
  "properties": {
    "gn:admin1_code":"20.0",
    "gn:admin2_code":"VE",
    "gn:admin3_code":"27029.0",
    "gn:asciiname":"Lison",
    "gn:country_code":"IT",
    "gn:dem":3,
    "gn:elevation":"5.0",
    "gn:feature_class":"P",
    "gn:feature_code":"PPL",
    "gn:name":"Lison",
    "gn:population":209,
    "gn:timezone":"Europe/Rome",
    "iso:country":"IT",
    "wof:name":"Lison",
    "wof:placetype":"locality",
    "wof:population":209
},
  "geometry": {"coordinates":[12.7521,45.75656],"type":"Point"}
}