{
  "type": "Feature",
  "properties": {
    "gn:admin1_code":"6",
    "gn:admin2_code":"UD",
    "gn:admin3_code":"30103.0",
    "gn:asciiname":"Cocevaro",
    "gn:country_code":"IT",
    "gn:dem":187,
    "gn:feature_class":"P",
    "gn:feature_code":"PPL",
    "gn:name":"Cocevaro",
    "gn:population":20,
    "gn:timezone":"Europe/Rome",
    "iso:country":"IT",
    "wof:name":"Cocevaro",
    "wof:placetype":"locality",
    "wof:population":20
},
  "geometry": {"coordinates":[13.51656,46.14753],"type":"Point"}
}