{
  "type": "Feature",
  "properties": {
    "gn:admin1_code":"1",
    "gn:admin2_code":"CH",
    "gn:admin3_code":"69099.0",
    "gn:asciiname":"Maddalena",
    "gn:country_code":"IT",
    "gn:dem":118,
    "gn:feature_class":"P",
    "gn:feature_code":"PPL",
    "gn:name":"Maddalena",
    "gn:population":31,
    "gn:timezone":"Europe/Rome",
    "iso:country":"IT",
    "name:bre_x_preferred":[
        "Maddalena"
    ],
    "name:ceb_x_preferred":[
        "Maddalena"
    ],
    "name:deu_x_preferred":[
        "Maddalena"
    ],
    "name:fra_x_preferred":[
        "Maddalena"
    ],
    "name:ita_x_preferred":[
        "Maddalena"
    ],
    "name:pol_x_preferred":[
        "Maddalena"
    ],
    "name:rus_x_preferred":[
        "\u041c\u0430\u0434\u0434\u0430\u043b\u0435\u043d\u0430"
    ],
    "name:srp_x_preferred":[
        "Maddalena"
    ],
    "name:swe_x_preferred":[
        "Maddalena"
    ],
    "wof:name":"Maddalena",
    "wof:placetype":"locality",
    "wof:population":31
},
  "geometry": {"coordinates":[14.68966,42.12699],"type":"Point"}
}