{
  "type": "Feature",
  "properties": {
    "gn:admin1_code":"1",
    "gn:admin2_code":"CH",
    "gn:admin3_code":"69099.0",
    "gn:asciiname":"Maddalena",
    "gn:country_code":"IT",
    "gn:dem":118,
    "gn:feature_class":"P",
    "gn:feature_code":"PPL",
    "gn:name":"Maddalena",
    "gn:population":31,
    "gn:timezone":"Europe/Rome",
    "iso:country":"IT",
    "wof:name":"Maddalena",
    "wof:placetype":"locality",
    "wof:population":31
},
  "geometry": {"coordinates":[14.68966,42.12699],"type":"Point"}
}