{
  "type": "Feature",
  "properties": {
    "gn:admin1_code":"18",
    "gn:admin2_code":"TR",
    "gn:admin3_code":"55018.0",
    "gn:asciiname":"Monastero",
    "gn:country_code":"IT",
    "gn:dem":398,
    "gn:feature_class":"P",
    "gn:feature_code":"PPLL",
    "gn:name":"Monastero",
    "gn:population":9,
    "gn:timezone":"Europe/Rome",
    "iso:country":"IT",
    "name:deu_x_preferred":[
        "Monastero"
    ],
    "name:epo_x_preferred":[
        "Monastero"
    ],
    "name:ita_x_preferred":[
        "Monastero"
    ],
    "name:pms_x_preferred":[
        "Monast\u00e9"
    ],
    "name:por_x_preferred":[
        "Monastero"
    ],
    "name:srp_x_preferred":[
        "Monastero"
    ],
    "wof:name":"Monastero",
    "wof:placetype":"locality",
    "wof:population":9
},
  "geometry": {"coordinates":[12.30152,42.65126],"type":"Point"}
}