{
  "type": "Feature",
  "properties": {
    "gn:admin1_code":"1.0",
    "gn:admin2_code":"AQ",
    "gn:admin3_code":"66021.0",
    "gn:asciiname":"Pago-Rovagnano",
    "gn:country_code":"IT",
    "gn:dem":848,
    "gn:feature_class":"P",
    "gn:feature_code":"PPL",
    "gn:name":"Pago-Rovagnano",
    "gn:population":46,
    "gn:timezone":"Europe/Rome",
    "iso:country":"IT",
    "name:und_x_variant":[
        "Pago",
        "Rovagnano"
    ],
    "wof:name":"Pago-Rovagnano",
    "wof:placetype":"locality",
    "wof:population":46
},
  "geometry": {"coordinates":[13.27359,42.52765],"type":"Point"}
}