{
  "type": "Feature",
  "properties": {
    "gn:admin1_code":"8.0",
    "gn:admin2_code":"GE",
    "gn:admin3_code":"10015.0",
    "gn:asciiname":"Sanguineto",
    "gn:country_code":"IT",
    "gn:dem":209,
    "gn:elevation":"203.0",
    "gn:feature_class":"P",
    "gn:feature_code":"PPL",
    "gn:name":"Sanguineto",
    "gn:population":67,
    "gn:timezone":"Europe/Rome",
    "iso:country":"IT",
    "wof:name":"Sanguineto",
    "wof:placetype":"locality",
    "wof:population":67
},
  "geometry": {"coordinates":[9.3043,44.33803],"type":"Point"}
}