{
  "type": "Feature",
  "properties": {
    "gn:admin1_code":"5",
    "gn:admin2_code":"RA",
    "gn:admin3_code":"39017.0",
    "gn:asciiname":"Chilometro 54",
    "gn:country_code":"IT",
    "gn:dem":11,
    "gn:feature_class":"P",
    "gn:feature_code":"PPL",
    "gn:name":"Chilometro 54",
    "gn:population":18,
    "gn:timezone":"Europe/Rome",
    "iso:country":"IT",
    "wof:name":"Chilometro 54",
    "wof:placetype":"locality",
    "wof:population":18
},
  "geometry": {"coordinates":[11.8763,44.45549000000001],"type":"Point"}
}