{
  "type": "Feature",
  "properties": {
    "gn:admin1_code":"4.0",
    "gn:admin2_code":"BN",
    "gn:admin3_code":"62029.0",
    "gn:asciiname":"San Pasquale",
    "gn:country_code":"IT",
    "gn:dem":327,
    "gn:feature_class":"P",
    "gn:feature_code":"PPLL",
    "gn:name":"San Pasquale",
    "gn:population":2,
    "gn:timezone":"Europe/Rome",
    "iso:country":"IT",
    "wof:name":"San Pasquale",
    "wof:placetype":"locality",
    "wof:population":2
},
  "geometry": {"coordinates":[14.47824,41.2834],"type":"Point"}
}