{
  "type": "Feature",
  "properties": {
    "gn:admin1_code":"7",
    "gn:admin2_code":"LT",
    "gn:admin3_code":"59029.0",
    "gn:asciiname":"Campo-Starza",
    "gn:country_code":"IT",
    "gn:dem":12,
    "gn:feature_class":"P",
    "gn:feature_code":"PPL",
    "gn:name":"Campo-Starza",
    "gn:population":51,
    "gn:timezone":"Europe/Rome",
    "iso:country":"IT",
    "wof:name":"Campo-Starza",
    "wof:placetype":"locality",
    "wof:population":51
},
  "geometry": {"coordinates":[13.19906,41.41262],"type":"Point"}
}