{
  "type": "Feature",
  "properties": {
    "gn:admin1_code":"3.0",
    "gn:admin2_code":"CS",
    "gn:admin3_code":"78078.0",
    "gn:asciiname":"Ischiaromana",
    "gn:cc2":"IT",
    "gn:country_code":"IT",
    "gn:dem":1018,
    "gn:feature_class":"P",
    "gn:feature_code":"PPL",
    "gn:name":"Ischiaromana",
    "gn:population":0,
    "gn:timezone":"Europe/Rome",
    "iso:country":"IT",
    "name:und_x_variant":[
        "Isca Romana",
        "Iscaramano",
        "Ischiaromana"
    ],
    "wof:name":"Ischiaromana",
    "wof:placetype":"locality"
},
  "geometry": {"coordinates":[16.36667000000001,39.15],"type":"Point"}
}