{
  "type": "Feature",
  "properties": {
    "gn:admin1_code":"17",
    "gn:admin2_code":"BZ",
    "gn:admin3_code":"21080.0",
    "gn:asciiname":"Valtina",
    "gn:country_code":"IT",
    "gn:dem":1280,
    "gn:feature_class":"P",
    "gn:feature_code":"PPL",
    "gn:name":"Valtina",
    "gn:population":73,
    "gn:timezone":"Europe/Rome",
    "iso:country":"IT",
    "name:deu_x_preferred":[
        "Walten"
    ],
    "name:ita_x_preferred":[
        "Valtina"
    ],
    "wof:name":"Valtina",
    "wof:placetype":"locality",
    "wof:population":73
},
  "geometry": {"coordinates":[11.28818,46.8255],"type":"Point"}
}