{
  "type": "Feature",
  "properties": {
    "gn:admin1_code":"17",
    "gn:admin2_code":"BZ",
    "gn:admin3_code":"21080.0",
    "gn:asciiname":"Valtina",
    "gn:country_code":"IT",
    "gn:dem":1280,
    "gn:feature_class":"P",
    "gn:feature_code":"PPL",
    "gn:name":"Valtina",
    "gn:population":73,
    "gn:timezone":"Europe/Rome",
    "iso:country":"IT",
    "name:ara_x_preferred":[
        "\u0641\u0627\u0644\u062a\u064a\u0646\u0627"
    ],
    "name:deu_x_preferred":[
        "Walten"
    ],
    "name:est_x_preferred":[
        "Valtina"
    ],
    "name:hye_x_preferred":[
        "\u054e\u0561\u056c\u057f\u056b\u0576\u0561"
    ],
    "name:ita_x_preferred":[
        "Valtina"
    ],
    "name:pol_x_preferred":[
        "Valtina"
    ],
    "name:spa_x_preferred":[
        "Valtina"
    ],
    "name:ukr_x_preferred":[
        "\u0412\u0430\u043b\u0442\u0456\u043d\u0430"
    ],
    "name:vol_x_preferred":[
        "Valtina"
    ],
    "wof:name":"Valtina",
    "wof:placetype":"locality",
    "wof:population":73
},
  "geometry": {"coordinates":[11.28818,46.8255],"type":"Point"}
}