{
  "type": "Feature",
  "properties": {
    "gn:admin1_code":"5.0",
    "gn:admin2_code":"MO",
    "gn:admin3_code":"36016.0",
    "gn:asciiname":"Spervara di Sopra",
    "gn:country_code":"IT",
    "gn:dem":893,
    "gn:feature_class":"P",
    "gn:feature_code":"PPL",
    "gn:name":"Spervara di Sopra",
    "gn:population":15,
    "gn:timezone":"Europe/Rome",
    "iso:country":"IT",
    "wof:name":"Spervara di Sopra",
    "wof:placetype":"locality",
    "wof:population":15
},
  "geometry": {"coordinates":[10.58047,44.2818],"type":"Point"}
}