{
  "type": "Feature",
  "properties": {
    "gn:admin1_code":"3.0",
    "gn:admin2_code":"RC",
    "gn:admin3_code":"80043.0",
    "gn:asciiname":"Casa La Rosa",
    "gn:country_code":"IT",
    "gn:dem":97,
    "gn:feature_class":"P",
    "gn:feature_code":"PPL",
    "gn:name":"Casa La Rosa",
    "gn:population":0,
    "gn:timezone":"Europe/Rome",
    "iso:country":"IT",
    "wof:name":"Casa La Rosa",
    "wof:placetype":"locality"
},
  "geometry": {"coordinates":[16.23333,38.25],"type":"Point"}
}