{
  "type": "Feature",
  "properties": {
    "gn:admin1_code":"5.0",
    "gn:admin2_code":"PC",
    "gn:admin3_code":"33001.0",
    "gn:asciiname":"Grintorto",
    "gn:country_code":"IT",
    "gn:dem":118,
    "gn:feature_class":"P",
    "gn:feature_code":"PPL",
    "gn:name":"Grintorto",
    "gn:population":0,
    "gn:timezone":"Europe/Rome",
    "iso:country":"IT",
    "wof:name":"Grintorto",
    "wof:placetype":"locality"
},
  "geometry": {"coordinates":[9.46667,44.98333],"type":"Point"}
}