{
  "type": "Feature",
  "properties": {
    "gn:admin1_code":"2",
    "gn:admin2_code":"PZ",
    "gn:admin3_code":"76045.0",
    "gn:asciiname":"Galaino",
    "gn:country_code":"IT",
    "gn:dem":626,
    "gn:feature_class":"P",
    "gn:feature_code":"PPL",
    "gn:name":"Galaino",
    "gn:population":243,
    "gn:timezone":"Europe/Rome",
    "iso:country":"IT",
    "wof:name":"Galaino",
    "wof:placetype":"locality",
    "wof:population":243
},
  "geometry": {"coordinates":[15.76152,40.38273],"type":"Point"}
}