{
  "type": "Feature",
  "properties": {
    "gn:admin1_code":"13",
    "gn:admin2_code":"BA",
    "gn:admin3_code":"72041.0",
    "gn:asciiname":"Alessandriello",
    "gn:country_code":"IT",
    "gn:dem":472,
    "gn:feature_class":"P",
    "gn:feature_code":"PPL",
    "gn:name":"Alessandriello",
    "gn:population":39,
    "gn:timezone":"Europe/Rome",
    "iso:country":"IT",
    "wof:name":"Alessandriello",
    "wof:placetype":"locality",
    "wof:population":39
},
  "geometry": {"coordinates":[16.73875,40.78636],"type":"Point"}
}