{
  "type": "Feature",
  "properties": {
    "gn:admin1_code":"20",
    "gn:admin2_code":"PD",
    "gn:admin3_code":"28022.0",
    "gn:asciiname":"Businari",
    "gn:country_code":"IT",
    "gn:dem":5,
    "gn:feature_class":"P",
    "gn:feature_code":"PPL",
    "gn:name":"Businari",
    "gn:population":19,
    "gn:timezone":"Europe/Rome",
    "iso:country":"IT",
    "wof:name":"Businari",
    "wof:placetype":"locality",
    "wof:population":19
},
  "geometry": {"coordinates":[11.63434,45.18712],"type":"Point"}
}