{
  "type": "Feature",
  "properties": {
    "gn:admin1_code":"17.0",
    "gn:admin2_code":"TN",
    "gn:admin3_code":"22230.0",
    "gn:asciiname":"Mollaro",
    "gn:country_code":"IT",
    "gn:dem":470,
    "gn:feature_class":"P",
    "gn:feature_code":"PPL",
    "gn:name":"Mollaro",
    "gn:population":382,
    "gn:timezone":"Europe/Rome",
    "iso:country":"IT",
    "wof:name":"Mollaro",
    "wof:placetype":"locality",
    "wof:population":382
},
  "geometry": {"coordinates":[11.07093,46.29419],"type":"Point"}
}