{
  "type": "Feature",
  "properties": {
    "gn:admin1_code":"20.0",
    "gn:admin2_code":"VR",
    "gn:admin3_code":"23073.0",
    "gn:asciiname":"Ortini",
    "gn:country_code":"IT",
    "gn:dem":42,
    "gn:feature_class":"P",
    "gn:feature_code":"PPL",
    "gn:name":"Ortini",
    "gn:population":13,
    "gn:timezone":"Europe/Rome",
    "iso:country":"IT",
    "wof:name":"Ortini",
    "wof:placetype":"locality",
    "wof:population":13
},
  "geometry": {"coordinates":[11.11527,45.41069],"type":"Point"}
}