{
  "type": "Feature",
  "properties": {
    "gn:admin1_code":"8.0",
    "gn:admin2_code":"GE",
    "gn:admin3_code":"10059.0",
    "gn:asciiname":"Balicca",
    "gn:country_code":"IT",
    "gn:dem":72,
    "gn:elevation":"80.0",
    "gn:feature_class":"P",
    "gn:feature_code":"PPL",
    "gn:name":"Balicca",
    "gn:population":29,
    "gn:timezone":"Europe/Rome",
    "iso:country":"IT",
    "wof:name":"Balicca",
    "wof:placetype":"locality",
    "wof:population":29
},
  "geometry": {"coordinates":[9.43377,44.30496],"type":"Point"}
}