{
  "type": "Feature",
  "properties": {
    "iso:country":"IT",
    "name:ita_x_preferred":[
        "Terravecchia"
    ],
    "name:unk_x_variant":[
        "Terravecchia"
    ],
    "qs:gn_fcode":"PPLX",
    "qs:gn_local":0,
    "qs:gn_namadm1":"15",
    "qs:gn_name":"Terravecchia",
    "qs:local_max":175,
    "qs:local_sum":175,
    "qs:localhoods":1,
    "qs:name":"Terravecchia",
    "qs:name_adm0":"Italia",
    "qs:name_adm1":"Sicilia",
    "qs:name_adm2":"Siracusa",
    "qs:name_lau":"Augusta",
    "qs:name_local":"Augusta",
    "qs:photo_max":23,
    "qs:photo_sum":175,
    "qs:placetype":"Suburb",
    "qs:quad_count":27,
    "qs:woe_adm0":23424853,
    "qs:woe_adm1":7153344,
    "qs:woe_adm2":12591894,
    "qs:woe_lau":12676336,
    "qs:woe_local":710422,
    "qs:woe_ver":"7.10.0",
    "wof:lang":[
        "ita"
    ],
    "wof:name":"Terravecchia",
    "wof:placetype":"neighbourhood"
},
  "geometry": {"coordinates":[15.223836,37.236615],"type":"Point"}
}