{
  "type": "Feature",
  "properties": {
    "gn:admin1_code":"18",
    "gn:admin2_code":"TR",
    "gn:admin3_code":"55023.0",
    "gn:asciiname":"Bivio Corsica",
    "gn:country_code":"IT",
    "gn:dem":492,
    "gn:feature_class":"P",
    "gn:feature_code":"PPL",
    "gn:name":"Bivio Corsica",
    "gn:population":47,
    "gn:timezone":"Europe/Rome",
    "iso:country":"IT",
    "wof:name":"Bivio Corsica",
    "wof:placetype":"locality",
    "wof:population":47
},
  "geometry": {"coordinates":[12.0668,42.67966],"type":"Point"}
}