{
  "type": "Feature",
  "properties": {
    "gn:admin1_code":"5",
    "gn:admin2_code":"MO",
    "gn:admin3_code":"36033.0",
    "gn:asciiname":"Le Are",
    "gn:country_code":"IT",
    "gn:dem":568,
    "gn:feature_class":"P",
    "gn:feature_code":"PPL",
    "gn:name":"Le Are",
    "gn:population":13,
    "gn:timezone":"Europe/Rome",
    "iso:country":"IT",
    "wof:name":"Le Are",
    "wof:placetype":"locality",
    "wof:population":13
},
  "geometry": {"coordinates":[10.68105,44.44929000000001],"type":"Point"}
}