{
  "type": "Feature",
  "properties": {
    "gn:admin1_code":"16.0",
    "gn:admin2_code":"PT",
    "gn:admin3_code":"47020.0",
    "gn:asciiname":"Ponte di Serravalle",
    "gn:country_code":"IT",
    "gn:dem":41,
    "gn:feature_class":"P",
    "gn:feature_code":"PPL",
    "gn:name":"Ponte di Serravalle",
    "gn:population":894,
    "gn:timezone":"Europe/Rome",
    "iso:country":"IT",
    "wof:name":"Ponte di Serravalle",
    "wof:placetype":"locality",
    "wof:population":894
},
  "geometry": {"coordinates":[10.82163,43.89574],"type":"Point"}
}