{
  "type": "Feature",
  "properties": {
    "gn:admin1_code":"9",
    "gn:admin2_code":"VA",
    "gn:admin3_code":"12092.0",
    "gn:asciiname":"Pianazzo",
    "gn:country_code":"IT",
    "gn:dem":414,
    "gn:feature_class":"P",
    "gn:feature_code":"PPL",
    "gn:name":"Pianazzo",
    "gn:population":110,
    "gn:timezone":"Europe/Rome",
    "iso:country":"IT",
    "wof:name":"Pianazzo",
    "wof:placetype":"locality",
    "wof:population":110
},
  "geometry": {"coordinates":[8.78476,45.9992],"type":"Point"}
}