{
  "type": "Feature",
  "properties": {
    "gn:admin1_code":"8.0",
    "gn:admin2_code":"SP",
    "gn:admin3_code":"11002.0",
    "gn:asciiname":"Pomara",
    "gn:country_code":"IT",
    "gn:dem":32,
    "gn:feature_class":"P",
    "gn:feature_code":"PPLL",
    "gn:name":"Pomara",
    "gn:population":3,
    "gn:timezone":"Europe/Rome",
    "iso:country":"IT",
    "wof:name":"Pomara",
    "wof:placetype":"locality",
    "wof:population":3
},
  "geometry": {"coordinates":[9.88837,44.10266],"type":"Point"}
}