{
  "type": "Feature",
  "properties": {
    "gn:admin1_code":"6.0",
    "gn:admin2_code":"UD",
    "gn:admin3_code":"30038.0",
    "gn:asciiname":"Papariano",
    "gn:country_code":"IT",
    "gn:dem":4,
    "gn:elevation":"11.0",
    "gn:feature_class":"P",
    "gn:feature_code":"PPL",
    "gn:name":"Papariano",
    "gn:population":892,
    "gn:timezone":"Europe/Rome",
    "iso:country":"IT",
    "wof:name":"Papariano",
    "wof:placetype":"locality",
    "wof:population":892
},
  "geometry": {"coordinates":[13.41638,45.80556],"type":"Point"}
}