{
  "type": "Feature",
  "properties": {
    "gn:admin1_code":"13",
    "gn:admin2_code":"LE",
    "gn:admin3_code":"75092.0",
    "gn:asciiname":"Saraceni",
    "gn:country_code":"IT",
    "gn:dem":40,
    "gn:feature_class":"P",
    "gn:feature_code":"PPL",
    "gn:name":"Saraceni",
    "gn:population":61,
    "gn:timezone":"Europe/Rome",
    "iso:country":"IT",
    "wof:name":"Saraceni",
    "wof:placetype":"locality",
    "wof:population":61
},
  "geometry": {"coordinates":[17.9584,40.31503],"type":"Point"}
}