{
  "type": "Feature",
  "properties": {
    "gn:admin1_code":"15",
    "gn:admin2_code":"ME",
    "gn:admin3_code":"83084.0",
    "gn:asciiname":"Sanguinera",
    "gn:country_code":"IT",
    "gn:dem":372,
    "gn:feature_class":"P",
    "gn:feature_code":"PPLL",
    "gn:name":"Sanguinera",
    "gn:population":10,
    "gn:timezone":"Europe/Rome",
    "iso:country":"IT",
    "wof:name":"Sanguinera",
    "wof:placetype":"locality",
    "wof:population":10
},
  "geometry": {"coordinates":[14.63004,38.01423],"type":"Point"}
}