{
  "type": "Feature",
  "properties": {
    "gn:admin1_code":"12.0",
    "gn:admin2_code":"TO",
    "gn:admin3_code":"1149.0",
    "gn:asciiname":"Borgata Assiere",
    "gn:country_code":"IT",
    "gn:dem":796,
    "gn:feature_class":"P",
    "gn:feature_code":"PPL",
    "gn:name":"Borgata Assiere",
    "gn:population":21,
    "gn:timezone":"Europe/Rome",
    "iso:country":"IT",
    "wof:name":"Borgata Assiere",
    "wof:placetype":"locality",
    "wof:population":21
},
  "geometry": {"coordinates":[7.0818,45.11553],"type":"Point"}
}