{
  "type": "Feature",
  "properties": {
    "gn:admin1_code":"10",
    "gn:admin2_code":"AP",
    "gn:admin3_code":"44015.0",
    "gn:asciiname":"Lisciano",
    "gn:country_code":"IT",
    "gn:dem":684,
    "gn:feature_class":"P",
    "gn:feature_code":"PPL",
    "gn:name":"Lisciano",
    "gn:population":13,
    "gn:timezone":"Europe/Rome",
    "iso:country":"IT",
    "wof:name":"Lisciano",
    "wof:placetype":"locality",
    "wof:population":13
},
  "geometry": {"coordinates":[13.43359,42.91308],"type":"Point"}
}