{
  "type": "Feature",
  "properties": {
    "gn:admin1_code":"13.0",
    "gn:admin2_code":"LE",
    "gn:admin3_code":"75039.0",
    "gn:asciiname":"Area Industriale",
    "gn:country_code":"IT",
    "gn:dem":87,
    "gn:feature_class":"P",
    "gn:feature_code":"PPLL",
    "gn:name":"Area Industriale",
    "gn:population":5,
    "gn:timezone":"Europe/Rome",
    "iso:country":"IT",
    "wof:name":"Area Industriale",
    "wof:placetype":"locality",
    "wof:population":5
},
  "geometry": {"coordinates":[18.29438,40.13799],"type":"Point"}
}