{
  "type": "Feature",
  "properties": {
    "gn:admin1_code":"6.0",
    "gn:admin2_code":"UD",
    "gn:admin3_code":"30110.0",
    "gn:asciiname":"Feltrone",
    "gn:country_code":"IT",
    "gn:dem":701,
    "gn:elevation":"716.0",
    "gn:feature_class":"P",
    "gn:feature_code":"PPL",
    "gn:name":"Feltrone",
    "gn:population":56,
    "gn:timezone":"Europe/Rome",
    "iso:country":"IT",
    "wof:name":"Feltrone",
    "wof:placetype":"locality",
    "wof:population":56
},
  "geometry": {"coordinates":[12.83465,46.41913],"type":"Point"}
}