{
  "type": "Feature",
  "properties": {
    "gn:admin1_code":"9",
    "gn:admin2_code":"LO",
    "gn:admin3_code":"98024.0",
    "gn:asciiname":"Ronchi",
    "gn:country_code":"IT",
    "gn:dem":68,
    "gn:feature_class":"P",
    "gn:feature_code":"PPL",
    "gn:name":"Ronchi",
    "gn:population":30,
    "gn:timezone":"Europe/Rome",
    "iso:country":"IT",
    "wof:name":"Ronchi",
    "wof:placetype":"locality",
    "wof:population":30
},
  "geometry": {"coordinates":[9.59312,45.33097],"type":"Point"}
}