{
  "type": "Feature",
  "properties": {
    "gn:admin1_code":"5",
    "gn:admin2_code":"RN",
    "gn:admin3_code":"99016.0",
    "gn:asciiname":"Casa del Marinaro",
    "gn:country_code":"IT",
    "gn:dem":147,
    "gn:feature_class":"P",
    "gn:feature_code":"PPL",
    "gn:name":"Casa del Marinaro",
    "gn:population":16,
    "gn:timezone":"Europe/Rome",
    "iso:country":"IT",
    "wof:name":"Casa del Marinaro",
    "wof:placetype":"locality",
    "wof:population":16
},
  "geometry": {"coordinates":[12.64043,43.9439],"type":"Point"}
}