{
  "type": "Feature",
  "properties": {
    "gn:gn_country":"IT",
    "gn:gn_fcode":"PPL",
    "gn:gn_pop":0,
    "gn:population":260,
    "iso:country":"IT",
    "name:bul_x_preferred":[
        "\u041f\u0438\u043e\u043f\u0438"
    ],
    "name:dut_x_preferred":[
        "Pioppi"
    ],
    "name:eng_x_preferred":[
        "Pioppi"
    ],
    "name:fre_x_preferred":[
        "Pioppi"
    ],
    "name:hun_x_preferred":[
        "Pioppi"
    ],
    "name:ita_x_preferred":[
        "Pioppi"
    ],
    "name:srp_x_preferred":[
        "Pioppi"
    ],
    "name:unk_x_variant":[
        "Marina dei Pioppi"
    ],
    "qs_pg:aaroncc":"IT",
    "qs_pg:gn_country":"IT",
    "qs_pg:gn_fcode":"PPL",
    "qs_pg:gn_pop":0,
    "qs_pg:name":"Pioppi",
    "qs_pg:name_adm0":"Italia",
    "qs_pg:name_adm1":"Campania",
    "qs_pg:photos":91,
    "qs_pg:photos_1k":18,
    "qs_pg:photos_9k":1,
    "qs_pg:photos_9r":3,
    "qs_pg:photos_all":91,
    "qs_pg:photos_sr":3,
    "qs_pg:pop_sr":0,
    "qs_pg:qs_pg_placetype":"locality",
    "qs_pg:qs_pg_placetype_gp":"Town",
    "qs_pg:woe_adm0":23424853,
    "woe:adm0_id":23424853,
    "woe:name_adm0":"Italia",
    "woe:name_adm1":"Campania",
    "woe:placetype":"Town",
    "wof:name":"Pioppi",
    "wof:placetype":"locality",
    "wof:population":260
},
  "geometry": {"coordinates":[15.08333,40.18333],"type":"Point"}
}