{
  "type": "Feature",
  "properties": {
    "gn:admin1_code":"12.0",
    "gn:admin2_code":"AL",
    "gn:admin3_code":"6165.0",
    "gn:asciiname":"Rocchetta",
    "gn:country_code":"IT",
    "gn:dem":422,
    "gn:feature_class":"P",
    "gn:feature_code":"PPLL",
    "gn:name":"Rocchetta",
    "gn:population":4,
    "gn:timezone":"Europe/Rome",
    "iso:country":"IT",
    "name:ceb_x_preferred":[
        "Rocchetta"
    ],
    "name:deu_x_preferred":[
        "Rocchetta"
    ],
    "name:fra_x_preferred":[
        "Rocchetta"
    ],
    "name:ita_x_preferred":[
        "Rocchetta"
    ],
    "name:por_x_preferred":[
        "Rocchetta"
    ],
    "name:srp_x_preferred":[
        "Roketa"
    ],
    "name:swe_x_preferred":[
        "Rocchetta"
    ],
    "wof:name":"Rocchetta",
    "wof:placetype":"locality",
    "wof:population":4
},
  "geometry": {"coordinates":[8.29786,44.54495],"type":"Point"}
}