{
  "type": "Feature",
  "properties": {
    "gn:admin1_code":"11",
    "gn:admin2_code":"IS",
    "gn:admin3_code":"94023.0",
    "gn:asciiname":"Breccelle I",
    "gn:country_code":"IT",
    "gn:dem":402,
    "gn:feature_class":"P",
    "gn:feature_code":"PPL",
    "gn:name":"Breccelle I",
    "gn:population":74,
    "gn:timezone":"Europe/Rome",
    "iso:country":"IT",
    "wof:name":"Breccelle I",
    "wof:placetype":"locality",
    "wof:population":74
},
  "geometry": {"coordinates":[14.20093,41.58532],"type":"Point"}
}