{
  "type": "Feature",
  "properties": {
    "gn:admin1_code":"9",
    "gn:admin2_code":"MN",
    "gn:admin3_code":"20066.0",
    "gn:asciiname":"Villa Grotta",
    "gn:country_code":"IT",
    "gn:dem":24,
    "gn:feature_class":"P",
    "gn:feature_code":"PPL",
    "gn:name":"Villa Grotta",
    "gn:population":43,
    "gn:timezone":"Europe/Rome",
    "iso:country":"IT",
    "wof:name":"Villa Grotta",
    "wof:placetype":"locality",
    "wof:population":43
},
  "geometry": {"coordinates":[10.54484,44.94114],"type":"Point"}
}