{
  "type": "Feature",
  "properties": {
    "gn:admin1_code":"10",
    "gn:admin2_code":"AN",
    "gn:admin3_code":"42003.0",
    "gn:asciiname":"Vado",
    "gn:country_code":"IT",
    "gn:dem":351,
    "gn:feature_class":"P",
    "gn:feature_code":"PPL",
    "gn:name":"Vado",
    "gn:population":13,
    "gn:timezone":"Europe/Rome",
    "iso:country":"IT",
    "wof:name":"Vado",
    "wof:placetype":"locality",
    "wof:population":13
},
  "geometry": {"coordinates":[12.97884,43.47755],"type":"Point"}
}