{
  "type": "Feature",
  "properties": {
    "gn:admin1_code":"10",
    "gn:admin2_code":"AN",
    "gn:admin3_code":"42003.0",
    "gn:asciiname":"Vado",
    "gn:country_code":"IT",
    "gn:dem":351,
    "gn:feature_class":"P",
    "gn:feature_code":"PPL",
    "gn:name":"Vado",
    "gn:population":13,
    "gn:timezone":"Europe/Rome",
    "iso:country":"IT",
    "name:ceb_x_preferred":[
        "Vado"
    ],
    "name:ita_x_preferred":[
        "Vado"
    ],
    "name:jpn_x_preferred":[
        "\u30f4\u30a1\u30fc\u30c9"
    ],
    "name:spa_x_preferred":[
        "Vado"
    ],
    "name:srp_x_preferred":[
        "Vado"
    ],
    "name:swe_x_preferred":[
        "Vado"
    ],
    "wof:name":"Vado",
    "wof:placetype":"locality",
    "wof:population":13
},
  "geometry": {"coordinates":[12.97884,43.47755],"type":"Point"}
}