{
  "type": "Feature",
  "properties": {
    "gn:admin1_code":"1",
    "gn:admin2_code":"CH",
    "gn:admin3_code":"69054.0",
    "gn:asciiname":"Fonticelle",
    "gn:country_code":"IT",
    "gn:dem":1004,
    "gn:feature_class":"P",
    "gn:feature_code":"PPL",
    "gn:name":"Fonticelle",
    "gn:population":87,
    "gn:timezone":"Europe/Rome",
    "iso:country":"IT",
    "wof:name":"Fonticelle",
    "wof:placetype":"locality",
    "wof:population":87
},
  "geometry": {"coordinates":[14.24834,41.99009],"type":"Point"}
}