{
  "type": "Feature",
  "properties": {
    "gn:admin1_code":"20",
    "gn:admin2_code":"PD",
    "gn:admin3_code":"28089.0",
    "gn:asciiname":"Fornace Laterizi",
    "gn:country_code":"IT",
    "gn:dem":11,
    "gn:feature_class":"P",
    "gn:feature_code":"PPL",
    "gn:name":"Fornace Laterizi",
    "gn:population":235,
    "gn:timezone":"Europe/Rome",
    "iso:country":"IT",
    "wof:name":"Fornace Laterizi",
    "wof:placetype":"locality",
    "wof:population":235
},
  "geometry": {"coordinates":[11.75053,45.34992],"type":"Point"}
}