{
  "type": "Feature",
  "properties": {
    "gn:admin1_code":"20.0",
    "gn:admin2_code":"VE",
    "gn:admin3_code":"27037.0",
    "gn:asciiname":"Fontane",
    "gn:country_code":"IT",
    "gn:dem":14,
    "gn:feature_class":"P",
    "gn:feature_code":"PPL",
    "gn:name":"Fontane",
    "gn:population":44,
    "gn:timezone":"Europe/Rome",
    "iso:country":"IT",
    "wof:name":"Fontane",
    "wof:placetype":"locality",
    "wof:population":44
},
  "geometry": {"coordinates":[12.10322,45.59659],"type":"Point"}
}