{
  "type": "Feature",
  "properties": {
    "gn:admin1_code":"5",
    "gn:admin2_code":"RN",
    "gn:admin3_code":"99014.0",
    "gn:asciiname":"Pozzi",
    "gn:country_code":"IT",
    "gn:dem":21,
    "gn:feature_class":"P",
    "gn:feature_code":"PPL",
    "gn:name":"Pozzi",
    "gn:population":64,
    "gn:timezone":"Europe/Rome",
    "iso:country":"IT",
    "wof:name":"Pozzi",
    "wof:placetype":"locality",
    "wof:population":64
},
  "geometry": {"coordinates":[12.60052,44.00448],"type":"Point"}
}