{
  "type": "Feature",
  "properties": {
    "gn:admin1_code":"1.0",
    "gn:admin2_code":"TE",
    "gn:admin3_code":"67009.0",
    "gn:asciiname":"Valle Canzano",
    "gn:country_code":"IT",
    "gn:dem":369,
    "gn:feature_class":"P",
    "gn:feature_code":"PPL",
    "gn:name":"Valle Canzano",
    "gn:population":109,
    "gn:timezone":"Europe/Rome",
    "iso:country":"IT",
    "wof:name":"Valle Canzano",
    "wof:placetype":"locality",
    "wof:population":109
},
  "geometry": {"coordinates":[13.79356,42.65894],"type":"Point"}
}