{
  "type": "Feature",
  "properties": {
    "gn:admin1_code":"5",
    "gn:admin2_code":"RE",
    "gn:admin3_code":"35041.0",
    "gn:asciiname":"Lignano",
    "gn:country_code":"IT",
    "gn:dem":702,
    "gn:feature_class":"P",
    "gn:feature_code":"PPL",
    "gn:name":"Lignano",
    "gn:population":19,
    "gn:timezone":"Europe/Rome",
    "iso:country":"IT",
    "wof:name":"Lignano",
    "wof:placetype":"locality",
    "wof:population":19
},
  "geometry": {"coordinates":[10.51477,44.3615],"type":"Point"}
}