{
  "type": "Feature",
  "properties": {
    "gn:admin1_code":"6.0",
    "gn:admin2_code":"TS",
    "gn:admin3_code":"32005.0",
    "gn:asciiname":"Baita",
    "gn:country_code":"IT",
    "gn:dem":245,
    "gn:feature_class":"P",
    "gn:feature_code":"PPL",
    "gn:name":"Baita",
    "gn:population":0,
    "gn:timezone":"Europe/Rome",
    "iso:country":"IT",
    "wof:name":"Baita",
    "wof:placetype":"locality"
},
  "geometry": {"coordinates":[13.71667,45.75],"type":"Point"}
}