{
  "type": "Feature",
  "properties": {
    "gn:admin1_code":"20",
    "gn:admin2_code":"VI",
    "gn:admin3_code":"24113.0",
    "gn:asciiname":"Chiumenti",
    "gn:country_code":"IT",
    "gn:dem":443,
    "gn:feature_class":"P",
    "gn:feature_code":"PPL",
    "gn:name":"Chiumenti",
    "gn:population":69,
    "gn:timezone":"Europe/Rome",
    "iso:country":"IT",
    "wof:name":"Chiumenti",
    "wof:placetype":"locality",
    "wof:population":69
},
  "geometry": {"coordinates":[11.23528,45.75053],"type":"Point"}
}