{
  "type": "Feature",
  "properties": {
    "gn:admin1_code":"12",
    "gn:admin2_code":"BI",
    "gn:admin3_code":"96042.0",
    "gn:asciiname":"Tappi Rosa",
    "gn:country_code":"IT",
    "gn:dem":766,
    "gn:feature_class":"P",
    "gn:feature_code":"PPL",
    "gn:name":"Tappi Rosa",
    "gn:population":51,
    "gn:timezone":"Europe/Rome",
    "iso:country":"IT",
    "wof:name":"Tappi Rosa",
    "wof:placetype":"locality",
    "wof:population":51
},
  "geometry": {"coordinates":[8.08698,45.61961],"type":"Point"}
}