{
  "type": "Feature",
  "properties": {
    "gn:admin1_code":"20",
    "gn:admin2_code":"VR",
    "gn:admin3_code":"23064.0",
    "gn:asciiname":"Corrubbioli",
    "gn:country_code":"IT",
    "gn:dem":19,
    "gn:feature_class":"P",
    "gn:feature_code":"PPL",
    "gn:name":"Corrubbioli",
    "gn:population":62,
    "gn:timezone":"Europe/Rome",
    "iso:country":"IT",
    "wof:name":"Corrubbioli",
    "wof:placetype":"locality",
    "wof:population":62
},
  "geometry": {"coordinates":[11.18594,45.34172],"type":"Point"}
}