{
  "type": "Feature",
  "properties": {
    "gn:admin1_code":"9",
    "gn:admin2_code":"CR",
    "gn:admin3_code":"19037.0",
    "gn:asciiname":"Localita San Benedetto",
    "gn:country_code":"IT",
    "gn:dem":79,
    "gn:feature_class":"P",
    "gn:feature_code":"PPL",
    "gn:name":"Localit\u00e0 San Benedetto",
    "gn:population":16,
    "gn:timezone":"Europe/Rome",
    "iso:country":"IT",
    "name:und_x_variant":[
        "Localit\u00e0 San Benedetto"
    ],
    "wof:name":"Localita San Benedetto",
    "wof:placetype":"locality",
    "wof:population":16
},
  "geometry": {"coordinates":[9.6517,45.37964],"type":"Point"}
}