{
  "type": "Feature",
  "properties": {
    "gn:admin1_code":"12",
    "gn:admin2_code":"TO",
    "gn:admin3_code":"1072.0",
    "gn:asciiname":"Chiampernotto",
    "gn:country_code":"IT",
    "gn:dem":841,
    "gn:feature_class":"P",
    "gn:feature_code":"PPL",
    "gn:name":"Chiampernotto",
    "gn:population":41,
    "gn:timezone":"Europe/Rome",
    "iso:country":"IT",
    "wof:name":"Chiampernotto",
    "wof:placetype":"locality",
    "wof:population":41
},
  "geometry": {"coordinates":[7.34388,45.32127],"type":"Point"}
}