{
  "type": "Feature",
  "properties": {
    "gn:admin1_code":"2",
    "gn:admin2_code":"PZ",
    "gn:admin3_code":"76045.0",
    "gn:asciiname":"San Vito",
    "gn:country_code":"IT",
    "gn:dem":962,
    "gn:feature_class":"P",
    "gn:feature_code":"PPL",
    "gn:name":"San Vito",
    "gn:population":55,
    "gn:timezone":"Europe/Rome",
    "iso:country":"IT",
    "wof:name":"San Vito",
    "wof:placetype":"locality",
    "wof:population":55
},
  "geometry": {"coordinates":[15.70828,40.43668],"type":"Point"}
}