{
  "type": "Feature",
  "properties": {
    "gn:admin1_code":"12",
    "gn:admin2_code":"TO",
    "gn:admin3_code":"1262.0",
    "gn:asciiname":"Tetti Garavaglia",
    "gn:country_code":"IT",
    "gn:dem":320,
    "gn:feature_class":"P",
    "gn:feature_code":"PPL",
    "gn:name":"Tetti Garavaglia",
    "gn:population":81,
    "gn:timezone":"Europe/Rome",
    "iso:country":"IT",
    "wof:name":"Tetti Garavaglia",
    "wof:placetype":"locality",
    "wof:population":81
},
  "geometry": {"coordinates":[7.86165,45.10872],"type":"Point"}
}