{
  "type": "Feature",
  "properties": {
    "gn:admin1_code":"7",
    "gn:admin2_code":"FR",
    "gn:admin3_code":"60053.0",
    "gn:asciiname":"Coce",
    "gn:country_code":"IT",
    "gn:dem":475,
    "gn:feature_class":"P",
    "gn:feature_code":"PPL",
    "gn:name":"Coce",
    "gn:population":34,
    "gn:timezone":"Europe/Rome",
    "iso:country":"IT",
    "wof:name":"Coce",
    "wof:placetype":"locality",
    "wof:population":34
},
  "geometry": {"coordinates":[13.1239,41.82316],"type":"Point"}
}