{
  "type": "Feature",
  "properties": {
    "gn:admin1_code":"5",
    "gn:admin2_code":"BO",
    "gn:admin3_code":"37062.0",
    "gn:asciiname":"Campoferraio",
    "gn:country_code":"IT",
    "gn:dem":787,
    "gn:feature_class":"P",
    "gn:feature_code":"PPL",
    "gn:name":"Campoferraio",
    "gn:population":27,
    "gn:timezone":"Europe/Rome",
    "iso:country":"IT",
    "wof:name":"Campoferraio",
    "wof:placetype":"locality",
    "wof:population":27
},
  "geometry": {"coordinates":[10.93154,44.15465],"type":"Point"}
}