{
  "type": "Feature",
  "properties": {
    "gn:admin1_code":"15",
    "gn:admin2_code":"CT",
    "gn:admin3_code":"87023.0",
    "gn:asciiname":"Montargano",
    "gn:country_code":"IT",
    "gn:dem":675,
    "gn:feature_class":"P",
    "gn:feature_code":"PPL",
    "gn:name":"Montargano",
    "gn:population":48,
    "gn:timezone":"Europe/Rome",
    "iso:country":"IT",
    "wof:name":"Montargano",
    "wof:placetype":"locality",
    "wof:population":48
},
  "geometry": {"coordinates":[15.14101,37.76887],"type":"Point"}
}