{
  "type": "Feature",
  "properties": {
    "gn:admin1_code":"9",
    "gn:admin2_code":"MN",
    "gn:admin3_code":"20041.0",
    "gn:asciiname":"Negrisoli",
    "gn:country_code":"IT",
    "gn:dem":39,
    "gn:feature_class":"P",
    "gn:feature_code":"PPL",
    "gn:name":"Negrisoli",
    "gn:population":22,
    "gn:timezone":"Europe/Rome",
    "iso:country":"IT",
    "wof:name":"Negrisoli",
    "wof:placetype":"locality",
    "wof:population":22
},
  "geometry": {"coordinates":[10.50766,45.228],"type":"Point"}
}