{
  "type": "Feature",
  "properties": {
    "gn:admin1_code":"5",
    "gn:admin2_code":"RE",
    "gn:admin3_code":"35020.0",
    "gn:asciiname":"Cesis",
    "gn:country_code":"IT",
    "gn:dem":29,
    "gn:feature_class":"P",
    "gn:feature_code":"PPL",
    "gn:name":"Cesis",
    "gn:population":27,
    "gn:timezone":"Europe/Rome",
    "iso:country":"IT",
    "wof:name":"Cesis",
    "wof:placetype":"locality",
    "wof:population":27
},
  "geometry": {"coordinates":[10.759,44.80836],"type":"Point"}
}