{
  "type": "Feature",
  "properties": {
    "gn:admin1_code":"16.0",
    "gn:admin2_code":"AR",
    "gn:admin3_code":"51039.0",
    "gn:asciiname":"Ville",
    "gn:country_code":"IT",
    "gn:dem":153,
    "gn:feature_class":"P",
    "gn:feature_code":"PPL",
    "gn:name":"Ville",
    "gn:population":542,
    "gn:timezone":"Europe/Rome",
    "iso:country":"IT",
    "wof:name":"Ville",
    "wof:placetype":"locality",
    "wof:population":542
},
  "geometry": {"coordinates":[11.57122,43.56628],"type":"Point"}
}