{
  "type": "Feature",
  "properties": {
    "gn:admin1_code":"7",
    "gn:admin2_code":"FR",
    "gn:admin3_code":"60089.0",
    "gn:asciiname":"Ponteromano II",
    "gn:country_code":"IT",
    "gn:dem":94,
    "gn:feature_class":"P",
    "gn:feature_code":"PPL",
    "gn:name":"Ponteromano II",
    "gn:population":26,
    "gn:timezone":"Europe/Rome",
    "iso:country":"IT",
    "wof:name":"Ponteromano II",
    "wof:placetype":"locality",
    "wof:population":26
},
  "geometry": {"coordinates":[13.77514,41.49475],"type":"Point"}
}