{
  "type": "Feature",
  "properties": {
    "gn:admin1_code":"5",
    "gn:admin2_code":"PR",
    "gn:admin3_code":"34019.0",
    "gn:asciiname":"La Porta",
    "gn:country_code":"IT",
    "gn:dem":392,
    "gn:feature_class":"P",
    "gn:feature_code":"PPL",
    "gn:name":"La Porta",
    "gn:population":15,
    "gn:timezone":"Europe/Rome",
    "iso:country":"IT",
    "name:ast_x_preferred":[
        "Portar"
    ],
    "name:cat_x_preferred":[
        "La Porta"
    ],
    "name:ceb_x_preferred":[
        "La Porta"
    ],
    "name:cos_x_preferred":[
        "A Porta d'Ampugnani"
    ],
    "name:deu_x_preferred":[
        "La Porta"
    ],
    "name:eus_x_preferred":[
        "La Porta"
    ],
    "name:fas_x_preferred":[
        "\u0644\u0627 \u067e\u0648\u0631\u062a\u0627"
    ],
    "name:fra_x_preferred":[
        "La Porta"
    ],
    "name:hun_x_preferred":[
        "La Porta"
    ],
    "name:ind_x_preferred":[
        "La Porta"
    ],
    "name:ita_x_preferred":[
        "La Porta"
    ],
    "name:kaz_x_preferred":[
        "\u041b\u0430-\u041f\u043e\u0440\u0442\u0430"
    ],
    "name:lat_x_preferred":[
        "La Porta"
    ],
    "name:lmo_x_preferred":[
        "La Porta"
    ],
    "name:msa_x_preferred":[
        "La Porta"
    ],
    "name:nld_x_preferred":[
        "La Porta"
    ],
    "name:oci_x_preferred":[
        "La Porta"
    ],
    "name:pol_x_preferred":[
        "La Porta"
    ],
    "name:por_x_preferred":[
        "La Porta"
    ],
    "name:rus_x_preferred":[
        "\u041b\u0430-\u041f\u043e\u0440\u0442\u0430"
    ],
    "name:slk_x_preferred":[
        "La Porta"
    ],
    "name:slv_x_preferred":[
        "La Porta"
    ],
    "name:spa_x_preferred":[
        "La Porta"
    ],
    "name:swe_x_preferred":[
        "La Porta"
    ],
    "name:ukr_x_preferred":[
        "\u041b\u0430-\u041f\u043e\u0440\u0442\u0430"
    ],
    "name:urd_x_preferred":[
        "\u0644\u0627 \u067e\u0648\u0631\u0679\u0627"
    ],
    "name:vie_x_preferred":[
        "La Porta"
    ],
    "name:vol_x_preferred":[
        "La Porta"
    ],
    "name:war_x_preferred":[
        "La Porta"
    ],
    "wof:name":"La Porta",
    "wof:placetype":"locality",
    "wof:population":15
},
  "geometry": {"coordinates":[10.31571,44.61305],"type":"Point"}
}