{
  "type": "Feature",
  "properties": {
    "gn:admin1_code":"16.0",
    "gn:admin2_code":"AR",
    "gn:admin3_code":"51008.0",
    "gn:asciiname":"Montanina",
    "gn:country_code":"IT",
    "gn:dem":322,
    "gn:feature_class":"P",
    "gn:feature_code":"PPLL",
    "gn:name":"Montanina",
    "gn:population":3,
    "gn:timezone":"Europe/Rome",
    "iso:country":"IT",
    "wof:name":"Montanina",
    "wof:placetype":"locality",
    "wof:population":3
},
  "geometry": {"coordinates":[11.847,43.62888],"type":"Point"}
}