{
  "type": "Feature",
  "properties": {
    "gn:admin1_code":"20",
    "gn:admin2_code":"PD",
    "gn:admin3_code":"28007.0",
    "gn:asciiname":"Pozzetto",
    "gn:country_code":"IT",
    "gn:dem":1,
    "gn:feature_class":"P",
    "gn:feature_code":"PPL",
    "gn:name":"Pozzetto",
    "gn:population":20,
    "gn:timezone":"Europe/Rome",
    "iso:country":"IT",
    "wof:name":"Pozzetto",
    "wof:placetype":"locality",
    "wof:population":20
},
  "geometry": {"coordinates":[12.03707,45.2745],"type":"Point"}
}