{
  "type": "Feature",
  "properties": {
    "gn:admin1_code":"12",
    "gn:admin2_code":"TO",
    "gn:admin3_code":"1266.0",
    "gn:asciiname":"Cornaley",
    "gn:country_code":"IT",
    "gn:dem":614,
    "gn:feature_class":"P",
    "gn:feature_code":"PPL",
    "gn:name":"Cornaley",
    "gn:population":27,
    "gn:timezone":"Europe/Rome",
    "iso:country":"IT",
    "wof:name":"Cornaley",
    "wof:placetype":"locality",
    "wof:population":27
},
  "geometry": {"coordinates":[7.84236,45.55901],"type":"Point"}
}