{
  "type": "Feature",
  "properties": {
    "gn:admin1_code":"9",
    "gn:admin2_code":"LO",
    "gn:admin3_code":"98010.0",
    "gn:asciiname":"Borasca e Boraschina",
    "gn:country_code":"IT",
    "gn:dem":59,
    "gn:feature_class":"P",
    "gn:feature_code":"PPL",
    "gn:name":"Borasca e Boraschina",
    "gn:population":79,
    "gn:timezone":"Europe/Rome",
    "iso:country":"IT",
    "wof:name":"Borasca e Boraschina",
    "wof:placetype":"locality",
    "wof:population":79
},
  "geometry": {"coordinates":[9.63305,45.18656],"type":"Point"}
}