{
  "type": "Feature",
  "properties": {
    "gn:admin1_code":"1.0",
    "gn:admin2_code":"CH",
    "gn:admin3_code":"69037.0",
    "gn:asciiname":"Guastameroli",
    "gn:cc2":"IT",
    "gn:country_code":"IT",
    "gn:dem":232,
    "gn:feature_class":"P",
    "gn:feature_code":"PPL",
    "gn:name":"Guastameroli",
    "gn:population":0,
    "gn:timezone":"Europe/Rome",
    "iso:country":"IT",
    "name:und_x_variant":[
        "Casone",
        "Guastameroli"
    ],
    "wof:name":"Guastameroli",
    "wof:placetype":"locality"
},
  "geometry": {"coordinates":[14.36667,42.26667],"type":"Point"}
}