{
  "type": "Feature",
  "properties": {
    "gn:admin1_code":"8",
    "gn:admin2_code":"GE",
    "gn:admin3_code":"10025.0",
    "gn:asciiname":"Cremeno",
    "gn:country_code":"IT",
    "gn:dem":149,
    "gn:feature_class":"P",
    "gn:feature_code":"PPL",
    "gn:name":"Cremeno",
    "gn:population":65,
    "gn:timezone":"Europe/Rome",
    "iso:country":"IT",
    "name:azb_x_preferred":[
        "\u06a9\u0631\u0645\u0646\u0648"
    ],
    "name:bar_x_preferred":[
        "Cremeno"
    ],
    "name:bel_x_preferred":[
        "\u041a\u0440\u044d\u043c\u0435\u043d\u0430"
    ],
    "name:bul_x_preferred":[
        "\u041a\u0440\u0435\u043c\u0435\u043d\u043e"
    ],
    "name:ceb_x_preferred":[
        "Cremeno"
    ],
    "name:deu_x_preferred":[
        "Cremeno"
    ],
    "name:epo_x_preferred":[
        "Cremeno"
    ],
    "name:eus_x_preferred":[
        "Cremeno"
    ],
    "name:fas_x_preferred":[
        "\u06a9\u0631\u0645\u0646\u0648"
    ],
    "name:fra_x_preferred":[
        "Cremeno"
    ],
    "name:hun_x_preferred":[
        "Cremeno"
    ],
    "name:hye_x_preferred":[
        "\u053f\u0580\u0565\u0574\u0565\u0576\u0578"
    ],
    "name:ita_x_preferred":[
        "Cremeno"
    ],
    "name:jpn_x_preferred":[
        "\u30af\u30ec\u30e1\u30fc\u30ce"
    ],
    "name:kaz_x_preferred":[
        "\u041a\u0440\u0435\u043c\u0435\u043d\u043e"
    ],
    "name:lat_x_preferred":[
        "Cremenum"
    ],
    "name:lmo_x_preferred":[
        "Cremee"
    ],
    "name:msa_x_preferred":[
        "Cremeno"
    ],
    "name:nap_x_preferred":[
        "Cremeno"
    ],
    "name:nld_x_preferred":[
        "Cremeno"
    ],
    "name:pms_x_preferred":[
        "Cremeno"
    ],
    "name:pol_x_preferred":[
        "Cremeno"
    ],
    "name:por_x_preferred":[
        "Cremeno"
    ],
    "name:ron_x_preferred":[
        "Cremeno"
    ],
    "name:rus_x_preferred":[
        "\u041a\u0440\u0435\u043c\u0435\u043d\u043e"
    ],
    "name:scn_x_preferred":[
        "Cremeno"
    ],
    "name:spa_x_preferred":[
        "Cremeno"
    ],
    "name:srp_x_preferred":[
        "\u041a\u0440\u0435\u043c\u0435\u043d\u043e"
    ],
    "name:tgl_x_preferred":[
        "Cremeno"
    ],
    "name:ukr_x_preferred":[
        "\u041a\u0440\u0435\u043c\u0435\u043d\u043e"
    ],
    "name:uzb_x_preferred":[
        "Cremeno"
    ],
    "name:vie_x_preferred":[
        "Cremeno"
    ],
    "name:vol_x_preferred":[
        "Cremeno"
    ],
    "name:war_x_preferred":[
        "Cremeno"
    ],
    "name:zho_x_preferred":[
        "\u514b\u96f7\u6885\u8bfa"
    ],
    "wof:name":"Cremeno",
    "wof:placetype":"locality",
    "wof:population":65
},
  "geometry": {"coordinates":[8.91926,44.47207],"type":"Point"}
}