{
  "type": "Feature",
  "properties": {
    "gn:admin1_code":"8",
    "gn:admin2_code":"GE",
    "gn:admin3_code":"10025.0",
    "gn:asciiname":"Cremeno",
    "gn:country_code":"IT",
    "gn:dem":149,
    "gn:feature_class":"P",
    "gn:feature_code":"PPL",
    "gn:name":"Cremeno",
    "gn:population":65,
    "gn:timezone":"Europe/Rome",
    "iso:country":"IT",
    "wof:name":"Cremeno",
    "wof:placetype":"locality",
    "wof:population":65
},
  "geometry": {"coordinates":[8.91926,44.47207],"type":"Point"}
}