{
  "type": "Feature",
  "properties": {
    "gn:admin1_code":"7",
    "gn:admin2_code":"FR",
    "gn:admin3_code":"60090.0",
    "gn:asciiname":"Acquaroni",
    "gn:country_code":"IT",
    "gn:dem":375,
    "gn:feature_class":"P",
    "gn:feature_code":"PPL",
    "gn:name":"Acquaroni",
    "gn:population":121,
    "gn:timezone":"Europe/Rome",
    "iso:country":"IT",
    "wof:name":"Acquaroni",
    "wof:placetype":"locality",
    "wof:population":121
},
  "geometry": {"coordinates":[13.33675,41.50425],"type":"Point"}
}