{
  "type": "Feature",
  "properties": {
    "iso:country":"IT",
    "name:ita_x_preferred":[
        "Paina"
    ],
    "name:mal_x_preferred":[
        "\u0d2a\u0d48\u0d28"
    ],
    "qs:gn_local":0,
    "qs:local_max":525,
    "qs:local_sum":837,
    "qs:localhoods":2,
    "qs:name":"Paina",
    "qs:name_adm0":"Italia",
    "qs:name_adm1":"Lombardia",
    "qs:name_adm2":"Monze e Brienza",
    "qs:name_lau":"Giussano",
    "qs:name_local":"Giussano",
    "qs:photo_max":77,
    "qs:photo_sum":525,
    "qs:placetype":"Suburb",
    "qs:quad_count":45,
    "qs:woe_adm0":23424853,
    "qs:woe_adm1":7153338,
    "qs:woe_adm2":56043515,
    "qs:woe_lau":12679610,
    "qs:woe_local":716231,
    "qs:woe_ver":"7.10.0",
    "wd:wordcount":317,
    "wof:lang":[
        "ita"
    ],
    "wof:name":"Paina",
    "wof:placetype":"neighbourhood"
},
  "geometry": {"coordinates":[9.206344,45.658879],"type":"Point"}
}