{
  "type": "Feature",
  "properties": {
    "gn:admin1_code":"12",
    "gn:admin2_code":"VC",
    "gn:admin3_code":"2078.0",
    "gn:asciiname":"Grampa",
    "gn:country_code":"IT",
    "gn:dem":948,
    "gn:feature_class":"P",
    "gn:feature_code":"PPLL",
    "gn:name":"Grampa",
    "gn:population":6,
    "gn:timezone":"Europe/Rome",
    "iso:country":"IT",
    "wof:name":"Grampa",
    "wof:placetype":"locality",
    "wof:population":6
},
  "geometry": {"coordinates":[8.03459,45.81362],"type":"Point"}
}