{
  "type": "Feature",
  "properties": {
    "gn:admin1_code":"11",
    "gn:admin2_code":"IS",
    "gn:admin3_code":"94043.0",
    "gn:asciiname":"Scalo Ferroviario",
    "gn:country_code":"IT",
    "gn:dem":926,
    "gn:feature_class":"P",
    "gn:feature_code":"PPL",
    "gn:name":"Scalo Ferroviario",
    "gn:population":26,
    "gn:timezone":"Europe/Rome",
    "iso:country":"IT",
    "wof:name":"Scalo Ferroviario",
    "wof:placetype":"locality",
    "wof:population":26
},
  "geometry": {"coordinates":[14.20004,41.77032],"type":"Point"}
}