{
  "type": "Feature",
  "properties": {
    "gn:admin1_code":"5.0",
    "gn:admin2_code":"PC",
    "gn:admin3_code":"33016.0",
    "gn:asciiname":"Ponte Sotto",
    "gn:country_code":"IT",
    "gn:dem":243,
    "gn:feature_class":"P",
    "gn:feature_code":"PPL",
    "gn:name":"Pont\u00e8 Sotto",
    "gn:population":29,
    "gn:timezone":"Europe/Rome",
    "iso:country":"IT",
    "wof:name":"Ponte Sotto",
    "wof:placetype":"locality",
    "wof:population":29
},
  "geometry": {"coordinates":[9.47821,44.81527],"type":"Point"}
}