{
  "type": "Feature",
  "properties": {
    "gn:admin1_code":"12.0",
    "gn:admin2_code":"NO",
    "gn:admin3_code":"3024.0",
    "gn:asciiname":"Cascina Fagnani",
    "gn:country_code":"IT",
    "gn:dem":294,
    "gn:feature_class":"P",
    "gn:feature_code":"PPL",
    "gn:name":"Cascina Fagnani",
    "gn:population":46,
    "gn:timezone":"Europe/Rome",
    "iso:country":"IT",
    "wof:name":"Cascina Fagnani",
    "wof:placetype":"locality",
    "wof:population":46
},
  "geometry": {"coordinates":[8.49429,45.67888],"type":"Point"}
}