{
  "type": "Feature",
  "properties": {
    "gn:admin1_code":"18.0",
    "gn:admin2_code":"TR",
    "gn:admin3_code":"55023.0",
    "gn:asciiname":"Corbara",
    "gn:country_code":"IT",
    "gn:dem":134,
    "gn:feature_class":"P",
    "gn:feature_code":"PPL",
    "gn:name":"Corbara",
    "gn:population":123,
    "gn:timezone":"Europe/Rome",
    "iso:country":"IT",
    "name:azb_x_preferred":[
        "\u06a9\u0648\u0631\u0628\u0627\u0631\u0627"
    ],
    "name:bul_x_preferred":[
        "\u041a\u043e\u0440\u0431\u0430\u0440\u0430"
    ],
    "name:ceb_x_preferred":[
        "Corbara"
    ],
    "name:deu_x_preferred":[
        "Corbara"
    ],
    "name:epo_x_preferred":[
        "Corbara"
    ],
    "name:eus_x_preferred":[
        "Corbara"
    ],
    "name:fas_x_preferred":[
        "\u06a9\u0648\u0631\u0628\u0627\u0631\u0627"
    ],
    "name:fin_x_preferred":[
        "Corbara"
    ],
    "name:fra_x_preferred":[
        "Corbara"
    ],
    "name:hun_x_preferred":[
        "Corbara"
    ],
    "name:hye_x_preferred":[
        "\u053f\u0578\u0580\u0562\u0561\u0580\u0561"
    ],
    "name:ina_x_preferred":[
        "Corbara"
    ],
    "name:ita_x_preferred":[
        "Corbara"
    ],
    "name:jpn_x_preferred":[
        "\u30b3\u30eb\u30d0\u30fc\u30e9"
    ],
    "name:kor_x_preferred":[
        "\ucf54\ub974\ubc14\ub77c"
    ],
    "name:lat_x_preferred":[
        "Corbaria"
    ],
    "name:lmo_x_preferred":[
        "Corbara"
    ],
    "name:msa_x_preferred":[
        "Corbara"
    ],
    "name:nap_x_preferred":[
        "Corbara"
    ],
    "name:nld_x_preferred":[
        "Corbara"
    ],
    "name:pms_x_preferred":[
        "Corbara"
    ],
    "name:pol_x_preferred":[
        "Corbara"
    ],
    "name:por_x_preferred":[
        "Corbara"
    ],
    "name:ron_x_preferred":[
        "Corbara"
    ],
    "name:rus_x_preferred":[
        "\u041a\u043e\u0440\u0431\u0430\u0440\u0430"
    ],
    "name:spa_x_preferred":[
        "Corbara"
    ],
    "name:srp_x_preferred":[
        "\u041a\u043e\u0440\u0431\u0430\u0440\u0430"
    ],
    "name:tgl_x_preferred":[
        "Corbara"
    ],
    "name:ukr_x_preferred":[
        "\u041a\u043e\u0440\u0431\u0430\u0440\u0430"
    ],
    "name:uzb_x_preferred":[
        "Corbara"
    ],
    "name:vec_x_preferred":[
        "Corbara"
    ],
    "name:vie_x_preferred":[
        "Corbara"
    ],
    "name:vol_x_preferred":[
        "Corbara"
    ],
    "name:war_x_preferred":[
        "Corbara"
    ],
    "name:zho_x_preferred":[
        "\u79d1\u5c14\u5df4\u62c9"
    ],
    "wof:name":"Corbara",
    "wof:placetype":"locality",
    "wof:population":123
},
  "geometry": {"coordinates":[12.22649,42.70427],"type":"Point"}
}