{
  "type": "Feature",
  "properties": {
    "gn:admin1_code":"18.0",
    "gn:admin2_code":"TR",
    "gn:admin3_code":"55023.0",
    "gn:asciiname":"Corbara",
    "gn:country_code":"IT",
    "gn:dem":134,
    "gn:feature_class":"P",
    "gn:feature_code":"PPL",
    "gn:name":"Corbara",
    "gn:population":123,
    "gn:timezone":"Europe/Rome",
    "iso:country":"IT",
    "wof:name":"Corbara",
    "wof:placetype":"locality",
    "wof:population":123
},
  "geometry": {"coordinates":[12.22649,42.70427],"type":"Point"}
}