{
  "type": "Feature",
  "properties": {
    "gn:admin1_code":"20",
    "gn:admin2_code":"VE",
    "gn:admin3_code":"27024.0",
    "gn:asciiname":"Fontana",
    "gn:country_code":"IT",
    "gn:dem":7,
    "gn:feature_class":"P",
    "gn:feature_code":"PPL",
    "gn:name":"Fontana",
    "gn:population":117,
    "gn:timezone":"Europe/Rome",
    "iso:country":"IT",
    "wof:name":"Fontana",
    "wof:placetype":"locality",
    "wof:population":117
},
  "geometry": {"coordinates":[12.07192,45.51137],"type":"Point"}
}