{
  "type": "Feature",
  "properties": {
    "iso:country":"IT",
    "wof:name":"Barca",
    "wof:placetype":"neighbourhood"
},
  "geometry": {"coordinates":[7.72956120387416,45.10491037460793],"type":"Point"}
}