{
  "type": "Feature",
  "properties": {
    "iso:country":"IT",
    "name:ara_x_preferred":[
        "\u0628\u0631\u0642\u0629"
    ],
    "name:bel_x_preferred":[
        "\u0411\u0430\u0440\u043a\u0430"
    ],
    "name:cat_x_preferred":[
        "Barca"
    ],
    "name:ceb_x_preferred":[
        "Barca"
    ],
    "name:ces_x_preferred":[
        "Barca"
    ],
    "name:deu_x_preferred":[
        "Barca"
    ],
    "name:epo_x_preferred":[
        "Barca"
    ],
    "name:eus_x_preferred":[
        "Barca"
    ],
    "name:ext_x_preferred":[
        "Barca"
    ],
    "name:fra_x_preferred":[
        "Barca"
    ],
    "name:glg_x_preferred":[
        "Barca"
    ],
    "name:heb_x_preferred":[
        "\u05d1\u05e8\u05e7\u05d4"
    ],
    "name:hun_x_preferred":[
        "Barca"
    ],
    "name:ita_x_preferred":[
        "Barca"
    ],
    "name:kor_x_preferred":[
        "\ubc14\ub974\uce74"
    ],
    "name:nld_x_preferred":[
        "Barca"
    ],
    "name:pol_x_preferred":[
        "Barca"
    ],
    "name:por_x_preferred":[
        "Barca"
    ],
    "name:slk_x_preferred":[
        "Barca"
    ],
    "name:spa_x_preferred":[
        "Barca"
    ],
    "name:srp_x_preferred":[
        "\u0411\u0430\u0440\u0446\u0430"
    ],
    "name:swe_x_preferred":[
        "Barca"
    ],
    "name:tur_x_preferred":[
        "Barca"
    ],
    "name:vie_x_preferred":[
        "Barca"
    ],
    "wof:name":"Barca",
    "wof:placetype":"neighbourhood"
},
  "geometry": {"coordinates":[7.72956120387416,45.10491037460793],"type":"Point"}
}