{
  "type": "Feature",
  "properties": {
    "gn:admin1_code":"9",
    "gn:admin2_code":"CR",
    "gn:admin3_code":"19025.0",
    "gn:asciiname":"Cavagnolo",
    "gn:country_code":"IT",
    "gn:dem":67,
    "gn:feature_class":"P",
    "gn:feature_code":"PPL",
    "gn:name":"Cavagnolo",
    "gn:population":16,
    "gn:timezone":"Europe/Rome",
    "iso:country":"IT",
    "name:azb_x_preferred":[
        "\u06a9\u0627\u0648\u0627\u0646\u06cc\u0648\u0644\u0648"
    ],
    "name:bel_x_preferred":[
        "\u041a\u0430\u0432\u0430\u043d\u044c\u0451\u043b\u0430"
    ],
    "name:bul_x_preferred":[
        "\u041a\u0430\u0432\u0430\u043d\u044c\u043e\u043b\u043e"
    ],
    "name:ceb_x_preferred":[
        "Cavagnolo"
    ],
    "name:deu_x_preferred":[
        "Cavagnolo"
    ],
    "name:epo_x_preferred":[
        "Cavagnolo"
    ],
    "name:eus_x_preferred":[
        "Cavagnolo"
    ],
    "name:fas_x_preferred":[
        "\u06a9\u0627\u0648\u0627\u0646\u06cc\u0648\u0644\u0648"
    ],
    "name:fra_x_preferred":[
        "Cavagnolo"
    ],
    "name:hun_x_preferred":[
        "Cavagnolo"
    ],
    "name:hye_x_preferred":[
        "\u053f\u0561\u057e\u0561\u0576\u0578\u056c\u0578"
    ],
    "name:ind_x_preferred":[
        "Cavagnolo"
    ],
    "name:ita_x_preferred":[
        "Cavagnolo"
    ],
    "name:jpn_x_preferred":[
        "\u30ab\u30f4\u30a1\u30cb\u30e7\u30fc\u30ed"
    ],
    "name:kaz_x_preferred":[
        "\u041a\u0430\u0432\u0430\u043d\u044c\u043e\u043b\u043e"
    ],
    "name:lat_x_preferred":[
        "Cabanniolum"
    ],
    "name:lmo_x_preferred":[
        "Cavagnolo"
    ],
    "name:msa_x_preferred":[
        "Cavagnolo"
    ],
    "name:nap_x_preferred":[
        "Cavagnolo"
    ],
    "name:nld_x_preferred":[
        "Cavagnolo"
    ],
    "name:pms_x_preferred":[
        "Cavagneul"
    ],
    "name:pol_x_preferred":[
        "Cavagnolo"
    ],
    "name:por_x_preferred":[
        "Cavagnolo"
    ],
    "name:ron_x_preferred":[
        "Cavagnolo"
    ],
    "name:rus_x_preferred":[
        "\u041a\u0430\u0432\u0430\u043d\u044c\u043e\u043b\u043e"
    ],
    "name:scn_x_preferred":[
        "Cavagnolo"
    ],
    "name:spa_x_preferred":[
        "Cavagnolo"
    ],
    "name:srp_x_preferred":[
        "\u041a\u0430\u0432\u0430\u045a\u043e\u043b\u043e"
    ],
    "name:swe_x_preferred":[
        "Cavagnolo"
    ],
    "name:tgl_x_preferred":[
        "Cavagnolo"
    ],
    "name:ukr_x_preferred":[
        "\u041a\u0430\u0432\u0430\u043d\u044c\u043e\u043b\u043e"
    ],
    "name:uzb_x_preferred":[
        "Cavagnolo"
    ],
    "name:vie_x_preferred":[
        "Cavagnolo"
    ],
    "name:vol_x_preferred":[
        "Cavagnolo"
    ],
    "name:war_x_preferred":[
        "Cavagnolo"
    ],
    "name:zho_x_preferred":[
        "\u5361\u74e6\u5c3c\u6d1b"
    ],
    "wof:name":"Cavagnolo",
    "wof:placetype":"locality",
    "wof:population":16
},
  "geometry": {"coordinates":[9.7517,45.33701],"type":"Point"}
}