{
  "type": "Feature",
  "properties": {
    "gn:admin1_code":"9",
    "gn:admin2_code":"CR",
    "gn:admin3_code":"19025.0",
    "gn:asciiname":"Cavagnolo",
    "gn:country_code":"IT",
    "gn:dem":67,
    "gn:feature_class":"P",
    "gn:feature_code":"PPL",
    "gn:name":"Cavagnolo",
    "gn:population":16,
    "gn:timezone":"Europe/Rome",
    "iso:country":"IT",
    "wof:name":"Cavagnolo",
    "wof:placetype":"locality",
    "wof:population":16
},
  "geometry": {"coordinates":[9.7517,45.33701],"type":"Point"}
}