{
  "type": "Feature",
  "properties": {
    "gn:admin1_code":"3.0",
    "gn:admin2_code":"CZ",
    "gn:admin3_code":"79130.0",
    "gn:asciiname":"Case di Grazia",
    "gn:country_code":"IT",
    "gn:dem":21,
    "gn:feature_class":"P",
    "gn:feature_code":"PPL",
    "gn:name":"Case di Grazia",
    "gn:population":0,
    "gn:timezone":"Europe/Rome",
    "iso:country":"IT",
    "wof:name":"Case di Grazia",
    "wof:placetype":"locality"
},
  "geometry": {"coordinates":[16.78333,38.91667],"type":"Point"}
}