{
  "type": "Feature",
  "properties": {
    "gn:admin1_code":"16",
    "gn:admin2_code":"LU",
    "gn:admin3_code":"46023.0",
    "gn:asciiname":"Colognola",
    "gn:country_code":"IT",
    "gn:dem":579,
    "gn:feature_class":"P",
    "gn:feature_code":"PPL",
    "gn:name":"Colognola",
    "gn:population":124,
    "gn:timezone":"Europe/Rome",
    "iso:country":"IT",
    "name:ita_x_preferred":[
        "Colognola"
    ],
    "name:lmo_x_preferred":[
        "Cologn\u00f6la"
    ],
    "wof:name":"Colognola",
    "wof:placetype":"locality",
    "wof:population":124
},
  "geometry": {"coordinates":[10.28135,44.19393],"type":"Point"}
}