{
  "type": "Feature",
  "properties": {
    "gn:admin1_code":"15",
    "gn:admin2_code":"ME",
    "gn:admin3_code":"83099.0",
    "gn:asciiname":"Lembo",
    "gn:country_code":"IT",
    "gn:dem":818,
    "gn:feature_class":"P",
    "gn:feature_code":"PPL",
    "gn:name":"Lembo",
    "gn:population":24,
    "gn:timezone":"Europe/Rome",
    "iso:country":"IT",
    "wof:name":"Lembo",
    "wof:placetype":"locality",
    "wof:population":24
},
  "geometry": {"coordinates":[14.84772,38.01696],"type":"Point"}
}