{
  "type": "Feature",
  "properties": {
    "gn:admin1_code":"4.0",
    "gn:admin2_code":"BN",
    "gn:admin3_code":"62068.0",
    "gn:asciiname":"Cese San Manno",
    "gn:country_code":"IT",
    "gn:dem":130,
    "gn:feature_class":"P",
    "gn:feature_code":"PPL",
    "gn:name":"Cese San Manno",
    "gn:population":499,
    "gn:timezone":"Europe/Rome",
    "iso:country":"IT",
    "wof:name":"Cese San Manno",
    "wof:placetype":"locality",
    "wof:population":499
},
  "geometry": {"coordinates":[14.48744,41.24336],"type":"Point"}
}