{
  "type": "Feature",
  "properties": {
    "gn:gn_country":"IT",
    "gn:gn_fcode":"PPLA3",
    "gn:gn_pop":445,
    "gn:population":148,
    "iso:country":"IT",
    "name:ara_x_preferred":[
        "\u0641\u064a\u0643\u0648\u0644\u064a"
    ],
    "name:bcl_x_preferred":[
        "Vicoli"
    ],
    "name:bel_x_preferred":[
        "\u0412\u0456\u043a\u043e\u043b\u0456"
    ],
    "name:bul_x_preferred":[
        "\u0412\u0438\u043a\u043e\u043b\u0438"
    ],
    "name:cat_x_preferred":[
        "Vicoli"
    ],
    "name:deu_x_preferred":[
        "Vicoli"
    ],
    "name:eng_x_preferred":[
        "Vicoli"
    ],
    "name:epo_x_preferred":[
        "Vicoli"
    ],
    "name:eus_x_preferred":[
        "Vicoli"
    ],
    "name:fas_x_preferred":[
        "\u0648\u06cc\u06a9\u0648\u0644\u06cc"
    ],
    "name:fra_x_preferred":[
        "Vicoli"
    ],
    "name:hun_x_preferred":[
        "Vicoli"
    ],
    "name:hye_x_preferred":[
        "\u054e\u056b\u056f\u0578\u056c\u056b"
    ],
    "name:ina_x_preferred":[
        "Vicoli"
    ],
    "name:ita_x_preferred":[
        "Vicoli"
    ],
    "name:jpn_x_preferred":[
        "\u30f4\u30a3\u30fc\u30b3\u30ea"
    ],
    "name:kaz_x_preferred":[
        "\u0412\u0438\u043a\u043e\u043b\u0438"
    ],
    "name:kor_x_preferred":[
        "\ube44\ucf5c\ub9ac"
    ],
    "name:lat_x_preferred":[
        "Vicolum"
    ],
    "name:lmo_x_preferred":[
        "Vicoli"
    ],
    "name:msa_x_preferred":[
        "Vicoli"
    ],
    "name:nan_x_preferred":[
        "Vicoli"
    ],
    "name:nap_x_preferred":[
        "Vicoli"
    ],
    "name:nld_x_preferred":[
        "Vicoli"
    ],
    "name:oci_x_preferred":[
        "Vicoli"
    ],
    "name:pms_x_preferred":[
        "Vicoli"
    ],
    "name:pol_x_preferred":[
        "Vicoli"
    ],
    "name:por_x_preferred":[
        "Vicoli"
    ],
    "name:ron_x_preferred":[
        "Vicoli"
    ],
    "name:rus_x_preferred":[
        "\u0412\u0438\u043a\u043e\u043b\u0438"
    ],
    "name:scn_x_preferred":[
        "Vicoli"
    ],
    "name:spa_x_preferred":[
        "Vicoli"
    ],
    "name:srp_x_preferred":[
        "Vicoli"
    ],
    "name:tgl_x_preferred":[
        "Vicoli"
    ],
    "name:ukr_x_preferred":[
        "\u0412\u0456\u043a\u043e\u043b\u0456"
    ],
    "name:uzb_x_preferred":[
        "Vicoli"
    ],
    "name:vie_x_preferred":[
        "Vicoli"
    ],
    "name:vol_x_preferred":[
        "Vicoli"
    ],
    "name:war_x_preferred":[
        "Vicoli"
    ],
    "name:zho_x_preferred":[
        "\u7ef4\u79d1\u5229"
    ],
    "qs_pg:aaroncc":"IT",
    "qs_pg:gn_country":"IT",
    "qs_pg:gn_fcode":"PPLA3",
    "qs_pg:gn_pop":445,
    "qs_pg:name":"Vicoli",
    "qs_pg:name_adm0":"Italia",
    "qs_pg:name_adm1":"Abruzzo",
    "qs_pg:photos_9k":1,
    "qs_pg:photos_9r":1,
    "qs_pg:photos_all":8,
    "qs_pg:photos_sr":0,
    "qs_pg:pop_sr":2,
    "qs_pg:qs_pg_placetype":"locality",
    "qs_pg:qs_pg_placetype_gp":"Town",
    "qs_pg:woe_adm0":23424853,
    "woe:adm0_id":23424853,
    "woe:name_adm0":"Italia",
    "woe:name_adm1":"Abruzzo",
    "woe:placetype":"Town",
    "wof:name":"Vicoli",
    "wof:placetype":"locality",
    "wof:population":148
},
  "geometry": {"coordinates":[13.8971,42.34144],"type":"Point"}
}