{
  "type": "Feature",
  "properties": {
    "gn:admin1_code":"1",
    "gn:admin2_code":"TE",
    "gn:admin3_code":"67035.0",
    "gn:asciiname":"Zona Artig.Ind.Commerc. Mercatone",
    "gn:country_code":"IT",
    "gn:dem":6,
    "gn:feature_class":"P",
    "gn:feature_code":"PPLL",
    "gn:name":"Zona Artig.Ind.Commerc. Mercatone",
    "gn:population":10,
    "gn:timezone":"Europe/Rome",
    "iso:country":"IT",
    "wof:name":"Zona Artig.Ind.Commerc. Mercatone",
    "wof:placetype":"locality",
    "wof:population":10
},
  "geometry": {"coordinates":[14.04443,42.63586],"type":"Point"}
}