{
  "type": "Feature",
  "properties": {
    "gn:admin1_code":"10",
    "gn:admin2_code":"MC",
    "gn:admin3_code":"43058.0",
    "gn:asciiname":"Alfi",
    "gn:country_code":"IT",
    "gn:dem":628,
    "gn:feature_class":"P",
    "gn:feature_code":"PPL",
    "gn:name":"Alfi",
    "gn:population":15,
    "gn:timezone":"Europe/Rome",
    "iso:country":"IT",
    "wof:name":"Alfi",
    "wof:placetype":"locality",
    "wof:population":15
},
  "geometry": {"coordinates":[13.09531,43.03314],"type":"Point"}
}