{
  "type": "Feature",
  "properties": {
    "gn:admin1_code":"6",
    "gn:admin2_code":"UD",
    "gn:admin3_code":"30111.0",
    "gn:asciiname":"Gnidovizza",
    "gn:country_code":"IT",
    "gn:dem":594,
    "gn:feature_class":"P",
    "gn:feature_code":"PPL",
    "gn:name":"Gnidovizza",
    "gn:population":31,
    "gn:timezone":"Europe/Rome",
    "iso:country":"IT",
    "wof:name":"Gnidovizza",
    "wof:placetype":"locality",
    "wof:population":31
},
  "geometry": {"coordinates":[13.61695,46.13402],"type":"Point"}
}