{
  "type": "Feature",
  "properties": {
    "gn:admin1_code":"3.0",
    "gn:admin2_code":"CS",
    "gn:admin3_code":"78029.0",
    "gn:asciiname":"Le Caselle",
    "gn:cc2":"IT",
    "gn:country_code":"IT",
    "gn:dem":11,
    "gn:elevation":"13.0",
    "gn:feature_class":"P",
    "gn:feature_code":"PPL",
    "gn:name":"Le Caselle",
    "gn:population":26,
    "gn:timezone":"Europe/Rome",
    "iso:country":"IT",
    "name:und_x_variant":[
        "La Casella",
        "Le Caselle"
    ],
    "wof:name":"Le Caselle",
    "wof:placetype":"locality",
    "wof:population":26
},
  "geometry": {"coordinates":[16.42104,39.72],"type":"Point"}
}