{
  "type": "Feature",
  "properties": {
    "gn:country":"IT",
    "gn:fcode":"PPL",
    "gn:population":1106,
    "iso:country":"IT",
    "name:bul_x_preferred":[
        "\u0421\u0430\u0440\u0434\u0430\u0433\u043d\u0430"
    ],
    "name:ceb_x_preferred":[
        "Sardagna"
    ],
    "name:eng_x_preferred":[
        "Sardagna"
    ],
    "name:fra_x_preferred":[
        "Sardagna"
    ],
    "name:hun_x_preferred":[
        "Sardagna"
    ],
    "name:ita_x_preferred":[
        "Sardagna"
    ],
    "name:nld_x_preferred":[
        "Sardagna"
    ],
    "name:srp_x_preferred":[
        "Sardagna"
    ],
    "qs_pg:aaroncc":"IT",
    "qs_pg:gn_country":"IT",
    "qs_pg:gn_fcode":"PPL",
    "qs_pg:gn_pop":1106,
    "qs_pg:name":"Sardagna",
    "qs_pg:name_adm0":"Italia",
    "qs_pg:name_adm1":"Trentino-Alto Adige",
    "qs_pg:photos":24,
    "qs_pg:photos_1k":5,
    "qs_pg:photos_9k":1,
    "qs_pg:photos_9r":1,
    "qs_pg:photos_all":24,
    "qs_pg:photos_sr":1,
    "qs_pg:pop_sr":3,
    "qs_pg:qs_pg_placetype":"locality",
    "qs_pg:qs_pg_placetype_gp":"Town",
    "qs_pg:woe_adm0":23424853,
    "woe:adm0_id":23424853,
    "woe:name_adm0":"Italia",
    "woe:name_adm1":"Trentino-Alto Adige",
    "woe:placetype":"Town",
    "wof:name":"Sardagna",
    "wof:placetype":"locality",
    "wof:population":903
},
  "geometry": {"coordinates":[11.09628,46.06406],"type":"Point"}
}