{
  "type": "Feature",
  "properties": {
    "gn:admin1_code":"17",
    "gn:admin2_code":"BZ",
    "gn:admin3_code":"21086.0",
    "gn:asciiname":"Sacco",
    "gn:country_code":"IT",
    "gn:dem":1506,
    "gn:feature_class":"P",
    "gn:feature_code":"PPL",
    "gn:name":"Sacco",
    "gn:population":27,
    "gn:timezone":"Europe/Rome",
    "iso:country":"IT",
    "wof:name":"Sacco",
    "wof:placetype":"locality",
    "wof:population":27
},
  "geometry": {"coordinates":[11.43401,46.78762],"type":"Point"}
}