{
  "type": "Feature",
  "properties": {
    "gn:admin1_code":"6.0",
    "gn:admin2_code":"PN",
    "gn:admin3_code":"93034.0",
    "gn:asciiname":"Case Corazza",
    "gn:country_code":"IT",
    "gn:dem":14,
    "gn:feature_class":"P",
    "gn:feature_code":"PPL",
    "gn:name":"Case Corazza",
    "gn:population":25,
    "gn:timezone":"Europe/Rome",
    "iso:country":"IT",
    "wof:name":"Case Corazza",
    "wof:placetype":"locality",
    "wof:population":25
},
  "geometry": {"coordinates":[12.597,45.88065],"type":"Point"}
}