{
  "type": "Feature",
  "properties": {
    "gn:admin1_code":"4.0",
    "gn:admin2_code":"CE",
    "gn:admin3_code":"61017.0",
    "gn:asciiname":"Casale",
    "gn:country_code":"IT",
    "gn:dem":178,
    "gn:feature_class":"P",
    "gn:feature_code":"PPL",
    "gn:name":"Casale",
    "gn:population":1363,
    "gn:timezone":"Europe/Rome",
    "iso:country":"IT",
    "wof:name":"Casale",
    "wof:placetype":"locality",
    "wof:population":1363
},
  "geometry": {"coordinates":[14.00231,41.21972],"type":"Point"}
}