{
  "type": "Feature",
  "properties": {
    "gn:admin1_code":"20.0",
    "gn:admin2_code":"VE",
    "gn:admin3_code":"27030.0",
    "gn:asciiname":"Belfiore",
    "gn:country_code":"IT",
    "gn:dem":2,
    "gn:elevation":"7.0",
    "gn:feature_class":"P",
    "gn:feature_code":"PPL",
    "gn:name":"Belfiore",
    "gn:population":624,
    "gn:timezone":"Europe/Rome",
    "iso:country":"IT",
    "wof:name":"Belfiore",
    "wof:placetype":"locality",
    "wof:population":624
},
  "geometry": {"coordinates":[12.72737,45.78374],"type":"Point"}
}