{
  "type": "Feature",
  "properties": {
    "gn:admin1_code":"20.0",
    "gn:admin2_code":"VE",
    "gn:admin3_code":"27030.0",
    "gn:asciiname":"Belfiore",
    "gn:country_code":"IT",
    "gn:dem":2,
    "gn:elevation":"7.0",
    "gn:feature_class":"P",
    "gn:feature_code":"PPL",
    "gn:name":"Belfiore",
    "gn:population":624,
    "gn:timezone":"Europe/Rome",
    "iso:country":"IT",
    "name:azb_x_preferred":[
        "\u0628\u0644\u0641\u06cc\u0648\u0631\u0647"
    ],
    "name:bul_x_preferred":[
        "\u0411\u0435\u043b\u0444\u0438\u043e\u0440\u0435"
    ],
    "name:ceb_x_preferred":[
        "Belfiore"
    ],
    "name:deu_x_preferred":[
        "Belfiore"
    ],
    "name:epo_x_preferred":[
        "Belfiore"
    ],
    "name:eus_x_preferred":[
        "Belfiore"
    ],
    "name:fas_x_preferred":[
        "\u0628\u0644\u0641\u06cc\u0648\u0631\u0647"
    ],
    "name:fra_x_preferred":[
        "Belfiore"
    ],
    "name:hun_x_preferred":[
        "Belfiore"
    ],
    "name:hye_x_preferred":[
        "\u0532\u0565\u056c\u0586\u056b\u0578\u0580\u0565"
    ],
    "name:ita_x_preferred":[
        "Belfiore"
    ],
    "name:jpn_x_preferred":[
        "\u30d9\u30eb\u30d5\u30a3\u30aa\u30fc\u30ec"
    ],
    "name:kaz_x_preferred":[
        "\u0411\u0435\u043b\u044c\u0444\u044c\u043e\u0440\u0435"
    ],
    "name:lat_x_preferred":[
        "Castrum Porcile"
    ],
    "name:lmo_x_preferred":[
        "Belfiore"
    ],
    "name:msa_x_preferred":[
        "Belfiore"
    ],
    "name:nap_x_preferred":[
        "Belfiore"
    ],
    "name:nld_x_preferred":[
        "Belfiore"
    ],
    "name:pms_x_preferred":[
        "Belfiore"
    ],
    "name:pol_x_preferred":[
        "Belfiore"
    ],
    "name:por_x_preferred":[
        "Belfiore"
    ],
    "name:ron_x_preferred":[
        "Belfiore"
    ],
    "name:rus_x_preferred":[
        "\u0411\u0435\u043b\u044c\u0444\u044c\u043e\u0440\u0435"
    ],
    "name:scn_x_preferred":[
        "Belfiore"
    ],
    "name:spa_x_preferred":[
        "Belfiore"
    ],
    "name:srp_x_preferred":[
        "\u0411\u0435\u043b\u0444\u0438\u043e\u0440\u0435"
    ],
    "name:tgl_x_preferred":[
        "Belfiore"
    ],
    "name:ukr_x_preferred":[
        "\u0411\u0435\u043b\u044c\u0444\u0456\u043e\u0440\u0435"
    ],
    "name:uzb_x_preferred":[
        "Belfiore"
    ],
    "name:vec_x_preferred":[
        "Belfiore"
    ],
    "name:vie_x_preferred":[
        "Belfiore"
    ],
    "name:vol_x_preferred":[
        "Belfiore"
    ],
    "name:war_x_preferred":[
        "Belfiore"
    ],
    "name:zho_x_preferred":[
        "\u8d1d\u5c14\u83f2\u5965\u96f7"
    ],
    "wof:name":"Belfiore",
    "wof:placetype":"locality",
    "wof:population":624
},
  "geometry": {"coordinates":[12.72737,45.78374],"type":"Point"}
}