{
  "type": "Feature",
  "properties": {
    "gn:admin1_code":"8",
    "gn:admin2_code":"SV",
    "gn:admin3_code":"9055.0",
    "gn:asciiname":"Alberola",
    "gn:country_code":"IT",
    "gn:dem":967,
    "gn:feature_class":"P",
    "gn:feature_code":"PPL",
    "gn:name":"Alberola",
    "gn:population":11,
    "gn:timezone":"Europe/Rome",
    "iso:country":"IT",
    "wof:name":"Alberola",
    "wof:placetype":"locality",
    "wof:population":11
},
  "geometry": {"coordinates":[8.55843,44.46855],"type":"Point"}
}