{
  "type": "Feature",
  "properties": {
    "gn:admin1_code":"15.0",
    "gn:admin2_code":"CT",
    "gn:admin3_code":"87013.0",
    "gn:asciiname":"Carrubbo",
    "gn:cc2":"IT",
    "gn:country_code":"IT",
    "gn:dem":400,
    "gn:elevation":"422.0",
    "gn:feature_class":"P",
    "gn:feature_code":"PPL",
    "gn:name":"Carrubbo",
    "gn:population":688,
    "gn:timezone":"Europe/Rome",
    "iso:country":"IT",
    "name:und_x_variant":[
        "Case Carubbo",
        "Carrubo",
        "Carrubbo"
    ],
    "wof:name":"Carrubbo",
    "wof:placetype":"locality",
    "wof:population":688
},
  "geometry": {"coordinates":[14.63456,37.49481],"type":"Point"}
}