{
  "type": "Feature",
  "properties": {
    "gn:admin1_code":"20.0",
    "gn:admin2_code":"RO",
    "gn:admin3_code":"29030.0",
    "gn:asciiname":"Ca' Negra",
    "gn:cc2":"IT",
    "gn:country_code":"IT",
    "gn:dem":-3,
    "gn:feature_class":"P",
    "gn:feature_code":"PPL",
    "gn:name":"Ca' Negra",
    "gn:population":17,
    "gn:timezone":"Europe/Rome",
    "iso:country":"IT",
    "name:und_x_variant":[
        "Ca Negra",
        "Ca Negra Bassa"
    ],
    "wof:name":"Ca' Negra",
    "wof:placetype":"locality",
    "wof:population":17
},
  "geometry": {"coordinates":[12.16583,45.08889],"type":"Point"}
}