{
  "type": "Feature",
  "properties": {
    "gn:admin1_code":"12",
    "gn:admin2_code":"TO",
    "gn:admin3_code":"1260.0",
    "gn:asciiname":"Infermera",
    "gn:country_code":"IT",
    "gn:dem":262,
    "gn:feature_class":"P",
    "gn:feature_code":"PPL",
    "gn:name":"Infermera",
    "gn:population":48,
    "gn:timezone":"Europe/Rome",
    "iso:country":"IT",
    "wof:name":"Infermera",
    "wof:placetype":"locality",
    "wof:population":48
},
  "geometry": {"coordinates":[7.48272,44.88705],"type":"Point"}
}