{
  "type": "Feature",
  "properties": {
    "gn:admin1_code":"5",
    "gn:admin2_code":"RN",
    "gn:admin3_code":"99011.0",
    "gn:asciiname":"Ghetto Cinque Quattrini",
    "gn:country_code":"IT",
    "gn:dem":59,
    "gn:feature_class":"P",
    "gn:feature_code":"PPL",
    "gn:name":"Ghetto Cinque Quattrini",
    "gn:population":85,
    "gn:timezone":"Europe/Rome",
    "iso:country":"IT",
    "wof:name":"Ghetto Cinque Quattrini",
    "wof:placetype":"locality",
    "wof:population":85
},
  "geometry": {"coordinates":[12.67489,43.92183],"type":"Point"}
}