{
  "type": "Feature",
  "properties": {
    "gn:admin1_code":"17",
    "gn:admin2_code":"TN",
    "gn:admin3_code":"22102.0",
    "gn:asciiname":"Oseli",
    "gn:country_code":"IT",
    "gn:dem":1121,
    "gn:feature_class":"P",
    "gn:feature_code":"PPL",
    "gn:name":"Oseli",
    "gn:population":14,
    "gn:timezone":"Europe/Rome",
    "iso:country":"IT",
    "wof:name":"Oseli",
    "wof:placetype":"locality",
    "wof:population":14
},
  "geometry": {"coordinates":[11.28291,45.92639000000001],"type":"Point"}
}