{
  "type": "Feature",
  "properties": {
    "gn:admin1_code":"3",
    "gn:admin2_code":"CS",
    "gn:admin3_code":"78097.0",
    "gn:asciiname":"Taverna Sottana",
    "gn:country_code":"IT",
    "gn:dem":607,
    "gn:feature_class":"P",
    "gn:feature_code":"PPL",
    "gn:name":"Taverna Sottana",
    "gn:population":52,
    "gn:timezone":"Europe/Rome",
    "iso:country":"IT",
    "wof:name":"Taverna Sottana",
    "wof:placetype":"locality",
    "wof:population":52
},
  "geometry": {"coordinates":[16.30475,39.22767],"type":"Point"}
}