{
  "type": "Feature",
  "properties": {
    "gn:admin1_code":"4.0",
    "gn:admin2_code":"SA",
    "gn:admin3_code":"65076.0",
    "gn:asciiname":"Prato Comune",
    "gn:country_code":"IT",
    "gn:dem":622,
    "gn:feature_class":"P",
    "gn:feature_code":"PPL",
    "gn:name":"Prato Comune",
    "gn:population":547,
    "gn:timezone":"Europe/Rome",
    "iso:country":"IT",
    "wof:name":"Prato Comune",
    "wof:placetype":"locality",
    "wof:population":547
},
  "geometry": {"coordinates":[15.6871,40.27717],"type":"Point"}
}