{
  "type": "Feature",
  "properties": {
    "gn:country":"IT",
    "gn:fcode":"PPL",
    "gn:population":0,
    "iso:country":"IT",
    "name:deu_x_historical":[
        "Uttenheim"
    ],
    "name:deu_x_preferred":[
        "Uttenheim"
    ],
    "name:ita_x_preferred":[
        "Villa Ottone"
    ],
    "qs_pg:aaroncc":"IT",
    "qs_pg:gn_country":"IT",
    "qs_pg:gn_fcode":"PPL",
    "qs_pg:gn_pop":0,
    "qs_pg:name":"Villa Ottone",
    "qs_pg:name_adm0":"Italia",
    "qs_pg:name_adm1":"Trentino-Alto Adige",
    "qs_pg:photos":33,
    "qs_pg:photos_1k":7,
    "qs_pg:photos_9k":1,
    "qs_pg:photos_9r":2,
    "qs_pg:photos_all":33,
    "qs_pg:photos_sr":2,
    "qs_pg:pop_sr":0,
    "qs_pg:qs_pg_placetype":"locality",
    "qs_pg:qs_pg_placetype_gp":"Town",
    "qs_pg:woe_adm0":23424853,
    "woe:adm0_id":23424853,
    "woe:name_adm0":"Italia",
    "woe:name_adm1":"Trentino-Alto Adige",
    "woe:placetype":"Town",
    "wof:name":"Villa Ottone",
    "wof:placetype":"locality",
    "wof:population":927
},
  "geometry": {"coordinates":[11.95,46.86667],"type":"Point"}
}