{
  "type": "Feature",
  "properties": {
    "gn:admin1_code":"8.0",
    "gn:admin2_code":"IM",
    "gn:admin3_code":"8043.0",
    "gn:asciiname":"Madonna Passoscio",
    "gn:cc2":"IT",
    "gn:country_code":"IT",
    "gn:dem":389,
    "gn:feature_class":"P",
    "gn:feature_code":"PPL",
    "gn:name":"Madonna Passoscio",
    "gn:population":0,
    "gn:timezone":"Europe/Rome",
    "iso:country":"IT",
    "name:und_x_variant":[
        "Madonna di Passascio",
        "Madonna Passoscio"
    ],
    "wof:name":"Madonna Passoscio",
    "wof:placetype":"locality"
},
  "geometry": {"coordinates":[7.65,43.93333],"type":"Point"}
}