{
  "type": "Feature",
  "properties": {
    "gn:admin1_code":"20",
    "gn:admin2_code":"PD",
    "gn:admin3_code":"28032.0",
    "gn:asciiname":"Sant'Antonio I",
    "gn:country_code":"IT",
    "gn:dem":52,
    "gn:feature_class":"P",
    "gn:feature_code":"PPL",
    "gn:name":"Sant'Antonio I",
    "gn:population":33,
    "gn:timezone":"Europe/Rome",
    "iso:country":"IT",
    "wof:name":"Sant'Antonio I",
    "wof:placetype":"locality",
    "wof:population":33
},
  "geometry": {"coordinates":[11.79318,45.66295],"type":"Point"}
}