{
  "type": "Feature",
  "properties": {
    "gn:admin1_code":"9.0",
    "gn:admin2_code":"PV",
    "gn:admin3_code":"18073.0",
    "gn:asciiname":"San Desiderio",
    "gn:country_code":"IT",
    "gn:dem":236,
    "gn:feature_class":"P",
    "gn:feature_code":"PPL",
    "gn:name":"San Desiderio",
    "gn:population":51,
    "gn:timezone":"Europe/Rome",
    "iso:country":"IT",
    "wof:name":"San Desiderio",
    "wof:placetype":"locality",
    "wof:population":51
},
  "geometry": {"coordinates":[9.06459,44.87861],"type":"Point"}
}