{
  "type": "Feature",
  "properties": {
    "gn:admin1_code":"5",
    "gn:admin2_code":"PR",
    "gn:admin3_code":"34006.0",
    "gn:asciiname":"Valleto",
    "gn:country_code":"IT",
    "gn:dem":583,
    "gn:feature_class":"P",
    "gn:feature_code":"PPL",
    "gn:name":"Valleto",
    "gn:population":27,
    "gn:timezone":"Europe/Rome",
    "iso:country":"IT",
    "wof:name":"Valleto",
    "wof:placetype":"locality",
    "wof:population":27
},
  "geometry": {"coordinates":[9.78494,44.46071],"type":"Point"}
}