{
  "type": "Feature",
  "properties": {
    "gn:admin1_code":"5",
    "gn:admin2_code":"PR",
    "gn:admin3_code":"34024.0",
    "gn:asciiname":"Montenero-Prada",
    "gn:country_code":"IT",
    "gn:dem":591,
    "gn:feature_class":"P",
    "gn:feature_code":"PPL",
    "gn:name":"Montenero-Prada",
    "gn:population":16,
    "gn:timezone":"Europe/Rome",
    "iso:country":"IT",
    "wof:name":"Montenero-Prada",
    "wof:placetype":"locality",
    "wof:population":16
},
  "geometry": {"coordinates":[10.24817,44.51300000000001],"type":"Point"}
}