{
  "type": "Feature",
  "properties": {
    "gn:admin1_code":"20",
    "gn:admin2_code":"VI",
    "gn:admin3_code":"24053.0",
    "gn:asciiname":"Valdellette",
    "gn:country_code":"IT",
    "gn:dem":273,
    "gn:feature_class":"P",
    "gn:feature_code":"PPL",
    "gn:name":"Valdellette",
    "gn:population":90,
    "gn:timezone":"Europe/Rome",
    "iso:country":"IT",
    "wof:name":"Valdellette",
    "wof:placetype":"locality",
    "wof:population":90
},
  "geometry": {"coordinates":[11.53163,45.75505],"type":"Point"}
}