{
  "type": "Feature",
  "properties": {
    "gn:admin1_code":"20",
    "gn:admin2_code":"TV",
    "gn:admin3_code":"26064.0",
    "gn:asciiname":"Cazzaro",
    "gn:country_code":"IT",
    "gn:dem":14,
    "gn:feature_class":"P",
    "gn:feature_code":"PPL",
    "gn:name":"Cazzaro",
    "gn:population":37,
    "gn:timezone":"Europe/Rome",
    "iso:country":"IT",
    "wof:name":"Cazzaro",
    "wof:placetype":"locality",
    "wof:population":37
},
  "geometry": {"coordinates":[12.17938,45.62254],"type":"Point"}
}