{
  "type": "Feature",
  "properties": {
    "gn:admin1_code":"20",
    "gn:admin2_code":"RO",
    "gn:admin3_code":"29039.0",
    "gn:asciiname":"Ca' Mora",
    "gn:country_code":"IT",
    "gn:dem":-5,
    "gn:feature_class":"P",
    "gn:feature_code":"PPL",
    "gn:name":"Ca' Mora",
    "gn:population":31,
    "gn:timezone":"Europe/Rome",
    "iso:country":"IT",
    "wof:name":"Ca' Mora",
    "wof:placetype":"locality",
    "wof:population":31
},
  "geometry": {"coordinates":[12.31602,44.90696],"type":"Point"}
}