{
  "type": "Feature",
  "properties": {
    "gn:admin1_code":"5",
    "gn:admin2_code":"MO",
    "gn:admin3_code":"36022.0",
    "gn:asciiname":"Tre Gobbi",
    "gn:country_code":"IT",
    "gn:dem":10,
    "gn:feature_class":"P",
    "gn:feature_code":"PPL",
    "gn:name":"Tre Gobbi",
    "gn:population":89,
    "gn:timezone":"Europe/Rome",
    "iso:country":"IT",
    "wof:name":"Tre Gobbi",
    "wof:placetype":"locality",
    "wof:population":89
},
  "geometry": {"coordinates":[11.20365,44.93045],"type":"Point"}
}