{
  "type": "Feature",
  "properties": {
    "iso:country":"IT",
    "wof:name":"Carraia",
    "wof:placetype":"neighbourhood"
},
  "geometry": {"coordinates":[11.19168979429877,43.7734377561253],"type":"Point"}
}