{
  "type": "Feature",
  "properties": {
    "gn:admin1_code":"3",
    "gn:admin2_code":"VV",
    "gn:admin3_code":"102012.0",
    "gn:asciiname":"Scaliti",
    "gn:country_code":"IT",
    "gn:dem":405,
    "gn:feature_class":"P",
    "gn:feature_code":"PPL",
    "gn:name":"Scaliti",
    "gn:population":245,
    "gn:timezone":"Europe/Rome",
    "iso:country":"IT",
    "wof:name":"Scaliti",
    "wof:placetype":"locality",
    "wof:population":245
},
  "geometry": {"coordinates":[16.04229,38.6133],"type":"Point"}
}