{
  "type": "Feature",
  "properties": {
    "gn:admin1_code":"20.0",
    "gn:admin2_code":"PD",
    "gn:admin3_code":"28023.0",
    "gn:asciiname":"Camazzole",
    "gn:country_code":"IT",
    "gn:dem":51,
    "gn:feature_class":"P",
    "gn:feature_code":"PPL",
    "gn:name":"Camazzole",
    "gn:population":508,
    "gn:timezone":"Europe/Rome",
    "iso:country":"IT",
    "wof:name":"Camazzole",
    "wof:placetype":"locality",
    "wof:population":508
},
  "geometry": {"coordinates":[11.69868,45.64674],"type":"Point"}
}