{
  "type": "Feature",
  "properties": {
    "gn:admin1_code":"8.0",
    "gn:admin2_code":"GE",
    "gn:admin3_code":"10010.0",
    "gn:asciiname":"Santa Maria di Sturla",
    "gn:country_code":"IT",
    "gn:dem":36,
    "gn:feature_class":"P",
    "gn:feature_code":"PPL",
    "gn:name":"Santa Maria di Sturla",
    "gn:population":51,
    "gn:timezone":"Europe/Rome",
    "iso:country":"IT",
    "wof:name":"Santa Maria di Sturla",
    "wof:placetype":"locality",
    "wof:population":51
},
  "geometry": {"coordinates":[9.35097,44.35898],"type":"Point"}
}