{
  "type": "Feature",
  "properties": {
    "gn:admin1_code":"18.0",
    "gn:admin2_code":"PG",
    "gn:admin3_code":"54052.0",
    "gn:asciiname":"Camerata",
    "gn:country_code":"IT",
    "gn:dem":512,
    "gn:elevation":"500.0",
    "gn:feature_class":"P",
    "gn:feature_code":"PPL",
    "gn:name":"Camerata",
    "gn:population":208,
    "gn:timezone":"Europe/Rome",
    "iso:country":"IT",
    "wof:name":"Camerata",
    "wof:placetype":"locality",
    "wof:population":208
},
  "geometry": {"coordinates":[12.38137,42.70392],"type":"Point"}
}