{
  "type": "Feature",
  "properties": {
    "gn:admin1_code":"6.0",
    "gn:admin2_code":"UD",
    "gn:admin3_code":"30059.0",
    "gn:asciiname":"Mogessa di Qua",
    "gn:cc2":"IT",
    "gn:country_code":"IT",
    "gn:dem":598,
    "gn:feature_class":"P",
    "gn:feature_code":"PPL",
    "gn:name":"Mogessa di Qu\u00e0",
    "gn:population":0,
    "gn:timezone":"Europe/Rome",
    "iso:country":"IT",
    "name:und_x_variant":[
        "Moggessa",
        "Moggessa di Qua",
        "Mogessa di Qu\u00e0"
    ],
    "wof:name":"Mogessa di Qua",
    "wof:placetype":"locality"
},
  "geometry": {"coordinates":[13.15556,46.42389],"type":"Point"}
}