{
  "type": "Feature",
  "properties": {
    "gn:admin1_code":"16",
    "gn:admin2_code":"AR",
    "gn:admin3_code":"51010.0",
    "gn:asciiname":"Cavolini",
    "gn:country_code":"IT",
    "gn:dem":487,
    "gn:feature_class":"P",
    "gn:feature_code":"PPL",
    "gn:name":"Cavolini",
    "gn:population":16,
    "gn:timezone":"Europe/Rome",
    "iso:country":"IT",
    "wof:name":"Cavolini",
    "wof:placetype":"locality",
    "wof:population":16
},
  "geometry": {"coordinates":[11.69519,43.74107],"type":"Point"}
}