{
  "type": "Feature",
  "properties": {
    "gn:admin1_code":"12",
    "gn:admin2_code":"CN",
    "gn:admin3_code":"4078.0",
    "gn:asciiname":"Tetti Milano",
    "gn:country_code":"IT",
    "gn:dem":524,
    "gn:feature_class":"P",
    "gn:feature_code":"PPL",
    "gn:name":"Tetti Milano",
    "gn:population":16,
    "gn:timezone":"Europe/Rome",
    "iso:country":"IT",
    "wof:name":"Tetti Milano",
    "wof:placetype":"locality",
    "wof:population":16
},
  "geometry": {"coordinates":[7.59754,44.36465],"type":"Point"}
}