{
  "type": "Feature",
  "properties": {
    "gn:admin1_code":"12.0",
    "gn:admin2_code":"AL",
    "gn:admin3_code":"6081.0",
    "gn:asciiname":"Pratolungo Superiore",
    "gn:country_code":"IT",
    "gn:dem":322,
    "gn:feature_class":"P",
    "gn:feature_code":"PPL",
    "gn:name":"Pratolungo Superiore",
    "gn:population":16,
    "gn:timezone":"Europe/Rome",
    "iso:country":"IT",
    "wof:name":"Pratolungo Superiore",
    "wof:placetype":"locality",
    "wof:population":16
},
  "geometry": {"coordinates":[8.86848,44.6716],"type":"Point"}
}