{
  "type": "Feature",
  "properties": {
    "gn:admin1_code":"13",
    "gn:admin2_code":"BR",
    "gn:admin3_code":"74001.0",
    "gn:asciiname":"Posticeddu",
    "gn:country_code":"IT",
    "gn:dem":2,
    "gn:feature_class":"P",
    "gn:feature_code":"PPL",
    "gn:name":"Posticeddu",
    "gn:population":19,
    "gn:timezone":"Europe/Rome",
    "iso:country":"IT",
    "wof:name":"Posticeddu",
    "wof:placetype":"locality",
    "wof:population":19
},
  "geometry": {"coordinates":[17.832,40.69334],"type":"Point"}
}