{
  "type": "Feature",
  "properties": {
    "gn:admin1_code":"6.0",
    "gn:admin2_code":"TS",
    "gn:admin3_code":"32001.0",
    "gn:asciiname":"Precenico Inferiore",
    "gn:cc2":"IT",
    "gn:country_code":"IT",
    "gn:dem":230,
    "gn:feature_class":"P",
    "gn:feature_code":"PPL",
    "gn:name":"Precenico Inferiore",
    "gn:population":56,
    "gn:timezone":"Europe/Rome",
    "iso:country":"IT",
    "name:und_x_variant":[
        "Precenico di Comeno",
        "Precenico"
    ],
    "wof:name":"Precenico Inferiore",
    "wof:placetype":"locality",
    "wof:population":56
},
  "geometry": {"coordinates":[13.68465,45.77623],"type":"Point"}
}