{
  "type": "Feature",
  "properties": {
    "gn:admin1_code":"12.0",
    "gn:admin2_code":"TO",
    "gn:admin3_code":"1252.0",
    "gn:asciiname":"San Raffaele",
    "gn:country_code":"IT",
    "gn:dem":423,
    "gn:feature_class":"P",
    "gn:feature_code":"PPL",
    "gn:name":"San Raffaele",
    "gn:population":118,
    "gn:timezone":"Europe/Rome",
    "iso:country":"IT",
    "name:ita_x_preferred":[
        "San Raffaele"
    ],
    "name:srp_x_preferred":[
        "San Rafaele"
    ],
    "wof:name":"San Raffaele",
    "wof:placetype":"locality",
    "wof:population":118
},
  "geometry": {"coordinates":[7.86374,45.15407],"type":"Point"}
}