{
  "type": "Feature",
  "properties": {
    "gn:admin1_code":"10.0",
    "gn:admin2_code":"PU",
    "gn:admin3_code":"41005.0",
    "gn:asciiname":"Torriola",
    "gn:country_code":"IT",
    "gn:dem":510,
    "gn:elevation":"525.0",
    "gn:feature_class":"P",
    "gn:feature_code":"PPL",
    "gn:name":"Torriola",
    "gn:population":34,
    "gn:timezone":"Europe/Rome",
    "iso:country":"IT",
    "wof:name":"Torriola",
    "wof:placetype":"locality",
    "wof:population":34
},
  "geometry": {"coordinates":[12.3574,43.73387],"type":"Point"}
}