{
  "type": "Feature",
  "properties": {
    "gn:admin1_code":"7",
    "gn:admin2_code":"LT",
    "gn:admin3_code":"59028.0",
    "gn:asciiname":"Forno",
    "gn:country_code":"IT",
    "gn:dem":5,
    "gn:feature_class":"P",
    "gn:feature_code":"PPL",
    "gn:name":"Forno",
    "gn:population":22,
    "gn:timezone":"Europe/Rome",
    "iso:country":"IT",
    "name:ceb_x_preferred":[
        "Forno"
    ],
    "name:deu_x_preferred":[
        "Forno"
    ],
    "name:ita_x_preferred":[
        "Forno"
    ],
    "name:nld_x_preferred":[
        "Forno"
    ],
    "name:por_x_preferred":[
        "Forno"
    ],
    "name:rus_x_preferred":[
        "\u0424\u043e\u0440\u043d\u043e"
    ],
    "name:sco_x_preferred":[
        "Forno"
    ],
    "name:srp_x_preferred":[
        "Forno"
    ],
    "name:swe_x_preferred":[
        "Forno"
    ],
    "wof:name":"Forno",
    "wof:placetype":"locality",
    "wof:population":22
},
  "geometry": {"coordinates":[13.04835,41.441],"type":"Point"}
}