{
  "type": "Feature",
  "properties": {
    "gn:admin1_code":"15.0",
    "gn:admin2_code":"CT",
    "gn:admin3_code":"87023.0",
    "gn:asciiname":"Giarre (Pagliara)",
    "gn:country_code":"IT",
    "gn:dem":30,
    "gn:feature_class":"P",
    "gn:feature_code":"PPL",
    "gn:name":"Giarre (Pagliara)",
    "gn:population":18,
    "gn:timezone":"Europe/Rome",
    "iso:country":"IT",
    "wof:name":"Giarre (Pagliara)",
    "wof:placetype":"locality",
    "wof:population":18
},
  "geometry": {"coordinates":[15.1879,37.74404000000001],"type":"Point"}
}