{
  "type": "Feature",
  "properties": {
    "gn:admin1_code":"7",
    "gn:admin2_code":"FR",
    "gn:admin3_code":"60044.0",
    "gn:asciiname":"Reggimento",
    "gn:country_code":"IT",
    "gn:dem":310,
    "gn:feature_class":"P",
    "gn:feature_code":"PPL",
    "gn:name":"Reggimento",
    "gn:population":187,
    "gn:timezone":"Europe/Rome",
    "iso:country":"IT",
    "wof:name":"Reggimento",
    "wof:placetype":"locality",
    "wof:population":187
},
  "geometry": {"coordinates":[13.49855,41.66921],"type":"Point"}
}