{
  "type": "Feature",
  "properties": {
    "gn:admin1_code":"20",
    "gn:admin2_code":"TV",
    "gn:admin3_code":"26008.0",
    "gn:asciiname":"Colonia Agricola",
    "gn:country_code":"IT",
    "gn:dem":25,
    "gn:feature_class":"P",
    "gn:feature_code":"PPL",
    "gn:name":"Colonia Agricola",
    "gn:population":99,
    "gn:timezone":"Europe/Rome",
    "iso:country":"IT",
    "wof:name":"Colonia Agricola",
    "wof:placetype":"locality",
    "wof:population":99
},
  "geometry": {"coordinates":[12.30251,45.72116],"type":"Point"}
}