{
  "type": "Feature",
  "properties": {
    "gn:admin1_code":"20.0",
    "gn:admin2_code":"VR",
    "gn:admin3_code":"23092.0",
    "gn:asciiname":"Giavone",
    "gn:country_code":"IT",
    "gn:dem":18,
    "gn:elevation":"17.0",
    "gn:feature_class":"P",
    "gn:feature_code":"PPL",
    "gn:name":"Giavone",
    "gn:population":67,
    "gn:timezone":"Europe/Rome",
    "iso:country":"IT",
    "wof:name":"Giavone",
    "wof:placetype":"locality",
    "wof:population":67
},
  "geometry": {"coordinates":[11.34182,45.28985],"type":"Point"}
}