{
  "type": "Feature",
  "properties": {
    "gn:admin1_code":"10.0",
    "gn:admin2_code":"PU",
    "gn:admin3_code":"41067.0",
    "gn:asciiname":"La Torre",
    "gn:cc2":"IT",
    "gn:country_code":"IT",
    "gn:dem":394,
    "gn:feature_class":"P",
    "gn:feature_code":"PPL",
    "gn:name":"La Torre",
    "gn:population":227,
    "gn:timezone":"Europe/Rome",
    "iso:country":"IT",
    "name:und_x_variant":[
        "La Torraccia",
        "La Torrazza"
    ],
    "wof:name":"La Torre",
    "wof:placetype":"locality",
    "wof:population":227
},
  "geometry": {"coordinates":[12.70141,43.74129],"type":"Point"}
}