{
  "type": "Feature",
  "properties": {
    "gn:admin1_code":"9",
    "gn:admin2_code":"BG",
    "gn:admin3_code":"16105.0",
    "gn:asciiname":"Avanzesca",
    "gn:country_code":"IT",
    "gn:dem":102,
    "gn:feature_class":"P",
    "gn:feature_code":"PPL",
    "gn:name":"Avanzesca",
    "gn:population":93,
    "gn:timezone":"Europe/Rome",
    "iso:country":"IT",
    "wof:name":"Avanzesca",
    "wof:placetype":"locality",
    "wof:population":93
},
  "geometry": {"coordinates":[9.67628,45.48781],"type":"Point"}
}