{
  "type": "Feature",
  "properties": {
    "gn:admin1_code":"9.0",
    "gn:admin2_code":"SO",
    "gn:admin3_code":"14022.0",
    "gn:asciiname":"Regolido",
    "gn:country_code":"IT",
    "gn:dem":548,
    "gn:feature_class":"P",
    "gn:feature_code":"PPLL",
    "gn:name":"Regolido",
    "gn:population":0,
    "gn:timezone":"Europe/Rome",
    "iso:country":"IT",
    "wof:name":"Regolido",
    "wof:placetype":"locality"
},
  "geometry": {"coordinates":[9.61668,46.16403],"type":"Point"}
}