{
  "type": "Feature",
  "properties": {
    "gn:admin1_code":"9",
    "gn:admin2_code":"MI",
    "gn:admin3_code":"15171.0",
    "gn:asciiname":"Mirazzano",
    "gn:country_code":"IT",
    "gn:dem":104,
    "gn:feature_class":"P",
    "gn:feature_code":"PPL",
    "gn:name":"Mirazzano",
    "gn:population":20,
    "gn:timezone":"Europe/Rome",
    "iso:country":"IT",
    "wof:name":"Mirazzano",
    "wof:placetype":"locality",
    "wof:population":20
},
  "geometry": {"coordinates":[9.32376,45.43698],"type":"Point"}
}