{
  "type": "Feature",
  "properties": {
    "gn:admin1_code":"8.0",
    "gn:admin2_code":"SP",
    "gn:admin3_code":"11029.0",
    "gn:asciiname":"Pizzolo",
    "gn:country_code":"IT",
    "gn:dem":523,
    "gn:feature_class":"P",
    "gn:feature_code":"PPL",
    "gn:name":"Pizzolo",
    "gn:population":0,
    "gn:timezone":"Europe/Rome",
    "iso:country":"IT",
    "wof:name":"Pizzolo",
    "wof:placetype":"locality"
},
  "geometry": {"coordinates":[9.61667,44.35],"type":"Point"}
}