{
  "type": "Feature",
  "properties": {
    "gn:admin1_code":"5",
    "gn:admin2_code":"FC",
    "gn:admin3_code":"40016.0",
    "gn:asciiname":"Casetti Rigossa",
    "gn:country_code":"IT",
    "gn:dem":14,
    "gn:feature_class":"P",
    "gn:feature_code":"PPL",
    "gn:name":"Casetti Rigossa",
    "gn:population":42,
    "gn:timezone":"Europe/Rome",
    "iso:country":"IT",
    "wof:name":"Casetti Rigossa",
    "wof:placetype":"locality",
    "wof:population":42
},
  "geometry": {"coordinates":[12.37452,44.12805],"type":"Point"}
}