{
  "type": "Feature",
  "properties": {
    "gn:admin1_code":"10",
    "gn:admin2_code":"AP",
    "gn:admin3_code":"44001.0",
    "gn:asciiname":"San Vito",
    "gn:country_code":"IT",
    "gn:dem":470,
    "gn:feature_class":"P",
    "gn:feature_code":"PPL",
    "gn:name":"San Vito",
    "gn:population":13,
    "gn:timezone":"Europe/Rome",
    "iso:country":"IT",
    "wof:name":"San Vito",
    "wof:placetype":"locality",
    "wof:population":13
},
  "geometry": {"coordinates":[13.40397,42.77161],"type":"Point"}
}