{
  "type": "Feature",
  "properties": {
    "gn:admin1_code":"5",
    "gn:admin2_code":"FE",
    "gn:admin3_code":"38008.0",
    "gn:asciiname":"Possessione Boschetto",
    "gn:country_code":"IT",
    "gn:dem":8,
    "gn:feature_class":"P",
    "gn:feature_code":"PPL",
    "gn:name":"Possessione Boschetto",
    "gn:population":21,
    "gn:timezone":"Europe/Rome",
    "iso:country":"IT",
    "wof:name":"Possessione Boschetto",
    "wof:placetype":"locality",
    "wof:population":21
},
  "geometry": {"coordinates":[11.64126,44.77418],"type":"Point"}
}