{
  "type": "Feature",
  "properties": {
    "gn:admin1_code":"12",
    "gn:admin2_code":"TO",
    "gn:admin3_code":"1201.0",
    "gn:asciiname":"Alleve",
    "gn:country_code":"IT",
    "gn:dem":1804,
    "gn:feature_class":"P",
    "gn:feature_code":"PPLL",
    "gn:name":"Allev\u00e8",
    "gn:population":10,
    "gn:timezone":"Europe/Rome",
    "iso:country":"IT",
    "name:und_x_variant":[
        "Allev\u00e8"
    ],
    "wof:name":"Alleve",
    "wof:placetype":"locality",
    "wof:population":10
},
  "geometry": {"coordinates":[6.92167,45.00691],"type":"Point"}
}