{
  "type": "Feature",
  "properties": {
    "gn:admin1_code":"18",
    "gn:admin2_code":"TR",
    "gn:admin3_code":"55029.0",
    "gn:asciiname":"Colle Ozio",
    "gn:country_code":"IT",
    "gn:dem":290,
    "gn:feature_class":"P",
    "gn:feature_code":"PPL",
    "gn:name":"Colle Ozio",
    "gn:population":20,
    "gn:timezone":"Europe/Rome",
    "iso:country":"IT",
    "wof:name":"Colle Ozio",
    "wof:placetype":"locality",
    "wof:population":20
},
  "geometry": {"coordinates":[12.52578,42.62047000000001],"type":"Point"}
}