{
  "type": "Feature",
  "properties": {
    "gn:admin1_code":"12",
    "gn:admin2_code":"CN",
    "gn:admin3_code":"4133.0",
    "gn:asciiname":"Gianoli",
    "gn:country_code":"IT",
    "gn:dem":349,
    "gn:feature_class":"P",
    "gn:feature_code":"PPL",
    "gn:name":"Gianoli",
    "gn:population":33,
    "gn:timezone":"Europe/Rome",
    "iso:country":"IT",
    "wof:name":"Gianoli",
    "wof:placetype":"locality",
    "wof:population":33
},
  "geometry": {"coordinates":[7.9549,44.84717],"type":"Point"}
}