{
  "type": "Feature",
  "properties": {
    "gn:admin1_code":"4.0",
    "gn:admin2_code":"AV",
    "gn:admin3_code":"64066.0",
    "gn:asciiname":"Macchia II",
    "gn:country_code":"IT",
    "gn:dem":726,
    "gn:feature_class":"P",
    "gn:feature_code":"PPL",
    "gn:name":"Macchia II",
    "gn:population":9,
    "gn:timezone":"Europe/Rome",
    "iso:country":"IT",
    "wof:name":"Macchia II",
    "wof:placetype":"locality",
    "wof:population":9
},
  "geometry": {"coordinates":[15.09698,40.86784],"type":"Point"}
}