{
  "type": "Feature",
  "properties": {
    "gn:admin1_code":"12.0",
    "gn:admin2_code":"CN",
    "gn:admin3_code":"4028.0",
    "gn:asciiname":"Rivoira",
    "gn:country_code":"IT",
    "gn:dem":626,
    "gn:feature_class":"P",
    "gn:feature_code":"PPL",
    "gn:name":"Rivoira",
    "gn:population":520,
    "gn:timezone":"Europe/Rome",
    "iso:country":"IT",
    "wof:name":"Rivoira",
    "wof:placetype":"locality",
    "wof:population":520
},
  "geometry": {"coordinates":[7.57129,44.32014],"type":"Point"}
}