{
  "type": "Feature",
  "properties": {
    "gn:admin1_code":"7.0",
    "gn:admin2_code":"RI",
    "gn:admin3_code":"57007.0",
    "gn:asciiname":"Ponte Civitella",
    "gn:country_code":"IT",
    "gn:dem":636,
    "gn:feature_class":"P",
    "gn:feature_code":"PPL",
    "gn:name":"Ponte Civitella",
    "gn:population":2,
    "gn:timezone":"Europe/Rome",
    "iso:country":"IT",
    "wof:name":"Ponte Civitella",
    "wof:placetype":"locality",
    "wof:population":2
},
  "geometry": {"coordinates":[13.18494,42.20964],"type":"Point"}
}