{
  "type": "Feature",
  "properties": {
    "gn:admin1_code":"18",
    "gn:admin2_code":"PG",
    "gn:admin3_code":"54026.0",
    "gn:asciiname":"Monte Sperello",
    "gn:country_code":"IT",
    "gn:dem":314,
    "gn:feature_class":"P",
    "gn:feature_code":"PPL",
    "gn:name":"Monte Sperello",
    "gn:population":24,
    "gn:timezone":"Europe/Rome",
    "iso:country":"IT",
    "wof:name":"Monte Sperello",
    "wof:placetype":"locality",
    "wof:population":24
},
  "geometry": {"coordinates":[12.22774,43.12255],"type":"Point"}
}