{
  "type": "Feature",
  "properties": {
    "gn:admin1_code":"12",
    "gn:admin2_code":"CN",
    "gn:admin3_code":"4207.0",
    "gn:asciiname":"Adrecchio",
    "gn:country_code":"IT",
    "gn:dem":799,
    "gn:feature_class":"P",
    "gn:feature_code":"PPL",
    "gn:name":"Adrecchio",
    "gn:population":16,
    "gn:timezone":"Europe/Rome",
    "iso:country":"IT",
    "wof:name":"Adrecchio",
    "wof:placetype":"locality",
    "wof:population":16
},
  "geometry": {"coordinates":[7.21703,44.49217],"type":"Point"}
}