{
  "type": "Feature",
  "properties": {
    "gn:admin1_code":"12",
    "gn:admin2_code":"BI",
    "gn:admin3_code":"96039.0",
    "gn:asciiname":"Cerea",
    "gn:country_code":"IT",
    "gn:dem":523,
    "gn:feature_class":"P",
    "gn:feature_code":"PPL",
    "gn:name":"Cerea",
    "gn:population":28,
    "gn:timezone":"Europe/Rome",
    "iso:country":"IT",
    "name:bul_x_preferred":[
        "\u0427\u0435\u0440\u0435\u0430"
    ],
    "name:ceb_x_preferred":[
        "Cerea"
    ],
    "name:deu_x_preferred":[
        "Cerea"
    ],
    "name:epo_x_preferred":[
        "Cerea"
    ],
    "name:eus_x_preferred":[
        "Cerea"
    ],
    "name:fra_x_preferred":[
        "Cerea"
    ],
    "name:hun_x_preferred":[
        "Cerea"
    ],
    "name:hye_x_preferred":[
        "\u0549\u0565\u0580\u0565\u0561"
    ],
    "name:ita_x_preferred":[
        "Cerea"
    ],
    "name:jpn_x_preferred":[
        "\u30c1\u30a7\u30ec\u30fc\u30a2"
    ],
    "name:kaz_x_preferred":[
        "\u0427\u0435\u0440\u0435\u0430"
    ],
    "name:lat_x_preferred":[
        "Cereta"
    ],
    "name:lmo_x_preferred":[
        "Cerea"
    ],
    "name:msa_x_preferred":[
        "Cerea"
    ],
    "name:nap_x_preferred":[
        "Cerea"
    ],
    "name:nld_x_preferred":[
        "Cerea"
    ],
    "name:pms_x_preferred":[
        "Cerea"
    ],
    "name:pol_x_preferred":[
        "Cerea"
    ],
    "name:por_x_preferred":[
        "Cerea"
    ],
    "name:ron_x_preferred":[
        "Cerea"
    ],
    "name:rus_x_preferred":[
        "\u0427\u0435\u0440\u0435\u0430"
    ],
    "name:scn_x_preferred":[
        "Cerea"
    ],
    "name:spa_x_preferred":[
        "Cerea"
    ],
    "name:srp_x_preferred":[
        "\u0427\u0435\u0440\u0435\u0430"
    ],
    "name:tgl_x_preferred":[
        "Cerea"
    ],
    "name:ukr_x_preferred":[
        "\u0427\u0435\u0440\u0435\u0430"
    ],
    "name:uzb_x_preferred":[
        "Cerea"
    ],
    "name:vec_x_preferred":[
        "Cerea"
    ],
    "name:vie_x_preferred":[
        "Cerea"
    ],
    "name:vol_x_preferred":[
        "Cerea"
    ],
    "name:war_x_preferred":[
        "Cerea"
    ],
    "name:zho_x_preferred":[
        "\u5207\u96f7\u4e9a"
    ],
    "wof:name":"Cerea",
    "wof:placetype":"locality",
    "wof:population":28
},
  "geometry": {"coordinates":[7.94344,45.53058],"type":"Point"}
}