{
  "type": "Feature",
  "properties": {
    "gn:admin1_code":"12",
    "gn:admin2_code":"BI",
    "gn:admin3_code":"96039.0",
    "gn:asciiname":"Cerea",
    "gn:country_code":"IT",
    "gn:dem":523,
    "gn:feature_class":"P",
    "gn:feature_code":"PPL",
    "gn:name":"Cerea",
    "gn:population":28,
    "gn:timezone":"Europe/Rome",
    "iso:country":"IT",
    "wof:name":"Cerea",
    "wof:placetype":"locality",
    "wof:population":28
},
  "geometry": {"coordinates":[7.94344,45.53058],"type":"Point"}
}