{
  "type": "Feature",
  "properties": {
    "gn:admin1_code":"5.0",
    "gn:admin2_code":"RN",
    "gn:admin3_code":"99002.0",
    "gn:asciiname":"Cattolica",
    "gn:country_code":"IT",
    "gn:dem":11,
    "gn:elevation":"12.0",
    "gn:feature_class":"P",
    "gn:feature_code":"PPLA3",
    "gn:name":"Cattolica",
    "gn:population":16189,
    "gn:timezone":"Europe/Rome",
    "iso:country":"IT",
    "name:deu_x_preferred":[
        "Cattolica"
    ],
    "name:eng_x_preferred":[
        "Cattolica"
    ],
    "name:epo_x_preferred":[
        "Cattolica"
    ],
    "name:fin_x_preferred":[
        "Cattolica"
    ],
    "name:fra_x_preferred":[
        "Cattolica"
    ],
    "name:ita_x_preferred":[
        "Cattolica"
    ],
    "name:jpn_x_preferred":[
        "\u30ab\u30c3\u30c8\u30fc\u30ea\u30ab"
    ],
    "name:nap_x_preferred":[
        "Cattolica"
    ],
    "name:nld_x_preferred":[
        "Cattolica"
    ],
    "name:nor_x_preferred":[
        "Cattolica"
    ],
    "name:pol_x_preferred":[
        "Cattolica"
    ],
    "name:por_x_preferred":[
        "Cattolica"
    ],
    "name:ron_x_preferred":[
        "Cattolica"
    ],
    "wof:name":"Cattolica",
    "wof:placetype":"locality",
    "wof:population":16189
},
  "geometry": {"coordinates":[12.73631,43.96182],"type":"Point"}
}