{
  "type": "Feature",
  "properties": {
    "gn:admin1_code":"5.0",
    "gn:admin2_code":"RN",
    "gn:admin3_code":"99002.0",
    "gn:asciiname":"Cattolica",
    "gn:country_code":"IT",
    "gn:dem":11,
    "gn:elevation":"12.0",
    "gn:feature_class":"P",
    "gn:feature_code":"PPLA3",
    "gn:name":"Cattolica",
    "gn:population":16189,
    "gn:timezone":"Europe/Rome",
    "iso:country":"IT",
    "name:ara_x_preferred":[
        "\u0643\u0627\u062a\u0648\u0644\u064a\u0643\u0627"
    ],
    "name:azb_x_preferred":[
        "\u06a9\u0627\u062a\u0648\u0644\u06cc\u06a9\u0627"
    ],
    "name:bre_x_preferred":[
        "Cattolica"
    ],
    "name:bul_x_preferred":[
        "\u041a\u0430\u0442\u043e\u043b\u0438\u043a\u0430"
    ],
    "name:ceb_x_preferred":[
        "Cattolica"
    ],
    "name:deu_x_preferred":[
        "Cattolica"
    ],
    "name:eml_x_preferred":[
        "Cat\u00f2lga"
    ],
    "name:eng_x_preferred":[
        "Cattolica"
    ],
    "name:epo_x_preferred":[
        "Cattolica"
    ],
    "name:eus_x_preferred":[
        "Cattolica"
    ],
    "name:fas_x_preferred":[
        "\u06a9\u0627\u062a\u0648\u0644\u06cc\u06a9\u0627"
    ],
    "name:fin_x_preferred":[
        "Cattolica"
    ],
    "name:fra_x_preferred":[
        "Cattolica"
    ],
    "name:hun_x_preferred":[
        "Cattolica"
    ],
    "name:hye_x_preferred":[
        "\u053f\u0561\u057f\u0578\u056c\u056b\u056f\u0561"
    ],
    "name:ina_x_preferred":[
        "Cattolica"
    ],
    "name:ind_x_preferred":[
        "Cattolica"
    ],
    "name:ita_x_preferred":[
        "Cattolica"
    ],
    "name:jpn_x_preferred":[
        "\u30ab\u30c3\u30c8\u30fc\u30ea\u30ab"
    ],
    "name:kaz_x_preferred":[
        "\u041a\u0430\u0442\u0442\u043e\u043b\u0438\u043a\u0430"
    ],
    "name:lat_x_preferred":[
        "Catholica"
    ],
    "name:lmo_x_preferred":[
        "Cattolica"
    ],
    "name:msa_x_preferred":[
        "Cattolica"
    ],
    "name:nap_x_preferred":[
        "Cattolica"
    ],
    "name:nld_x_preferred":[
        "Cattolica"
    ],
    "name:nor_x_preferred":[
        "Cattolica"
    ],
    "name:pms_x_preferred":[
        "Cattolica"
    ],
    "name:pol_x_preferred":[
        "Cattolica"
    ],
    "name:por_x_preferred":[
        "Cattolica"
    ],
    "name:ron_x_preferred":[
        "Cattolica"
    ],
    "name:rus_x_preferred":[
        "\u041a\u0430\u0442\u0442\u043e\u043b\u0438\u043a\u0430"
    ],
    "name:spa_x_preferred":[
        "Cattolica"
    ],
    "name:srd_x_preferred":[
        "Cattolica"
    ],
    "name:srp_x_preferred":[
        "\u041a\u0430\u0442\u043e\u043b\u0438\u043a\u0430"
    ],
    "name:swe_x_preferred":[
        "Cattolica"
    ],
    "name:tur_x_preferred":[
        "Cattolica"
    ],
    "name:ukr_x_preferred":[
        "\u041a\u0430\u0442\u0442\u043e\u043b\u0456\u043a\u0430"
    ],
    "name:uzb_x_preferred":[
        "Cattolica"
    ],
    "name:vec_x_preferred":[
        "Cato\u0142ica"
    ],
    "name:vie_x_preferred":[
        "Cattolica"
    ],
    "name:vol_x_preferred":[
        "Cattolica"
    ],
    "name:war_x_preferred":[
        "Cattolica"
    ],
    "name:zho_x_preferred":[
        "\u5361\u6258\u5229\u5361"
    ],
    "wof:name":"Cattolica",
    "wof:placetype":"locality",
    "wof:population":16189
},
  "geometry": {"coordinates":[12.73631,43.96182],"type":"Point"}
}