{
  "type": "Feature",
  "properties": {
    "gn:admin1_code":"16",
    "gn:admin2_code":"AR",
    "gn:admin3_code":"51035.0",
    "gn:asciiname":"Martigliano",
    "gn:country_code":"IT",
    "gn:dem":796,
    "gn:feature_class":"P",
    "gn:feature_code":"PPL",
    "gn:name":"Martigliano",
    "gn:population":19,
    "gn:timezone":"Europe/Rome",
    "iso:country":"IT",
    "wof:name":"Martigliano",
    "wof:placetype":"locality",
    "wof:population":19
},
  "geometry": {"coordinates":[12.32373,43.73505],"type":"Point"}
}