{
  "type": "Feature",
  "properties": {
    "gn:admin1_code":"15.0",
    "gn:admin2_code":"SR",
    "gn:admin3_code":"89017.0",
    "gn:asciiname":"Ciane",
    "gn:country_code":"IT",
    "gn:dem":10,
    "gn:feature_class":"P",
    "gn:feature_code":"PPL",
    "gn:name":"Ciane",
    "gn:population":0,
    "gn:timezone":"Europe/Rome",
    "iso:country":"IT",
    "name:chv_x_preferred":[
        "\u0427\u0430\u043d\u0435"
    ],
    "name:deu_x_preferred":[
        "Ciane"
    ],
    "name:fra_x_preferred":[
        "Ciane"
    ],
    "name:ita_x_preferred":[
        "Ciane"
    ],
    "name:rus_x_preferred":[
        "\u0427\u0430\u043d\u0435"
    ],
    "name:scn_x_preferred":[
        "Ciani"
    ],
    "wof:name":"Ciane",
    "wof:placetype":"locality"
},
  "geometry": {"coordinates":[15.2701,37.0549],"type":"Point"}
}