{
  "type": "Feature",
  "properties": {
    "gn:admin1_code":"1",
    "gn:admin2_code":"TE",
    "gn:admin3_code":"67021.0",
    "gn:asciiname":"Case Piccio",
    "gn:country_code":"IT",
    "gn:dem":87,
    "gn:feature_class":"P",
    "gn:feature_code":"PPL",
    "gn:name":"Case Picci\u00f2",
    "gn:population":21,
    "gn:timezone":"Europe/Rome",
    "iso:country":"IT",
    "name:und_x_variant":[
        "Case Picci\u00f2"
    ],
    "wof:name":"Case Piccio",
    "wof:placetype":"locality",
    "wof:population":21
},
  "geometry": {"coordinates":[13.83542,42.80847],"type":"Point"}
}