{
  "type": "Feature",
  "properties": {
    "gn:admin1_code":"20",
    "gn:admin2_code":"VI",
    "gn:admin3_code":"24033.0",
    "gn:asciiname":"Rubbietto",
    "gn:country_code":"IT",
    "gn:dem":1029,
    "gn:feature_class":"P",
    "gn:feature_code":"PPL",
    "gn:name":"Rubbietto",
    "gn:population":70,
    "gn:timezone":"Europe/Rome",
    "iso:country":"IT",
    "wof:name":"Rubbietto",
    "wof:placetype":"locality",
    "wof:population":70
},
  "geometry": {"coordinates":[11.64825,45.80006],"type":"Point"}
}