{
  "type": "Feature",
  "properties": {
    "gn:admin1_code":"10.0",
    "gn:admin2_code":"PU",
    "gn:admin3_code":"41013.0",
    "gn:asciiname":"L.P.Bellocchi",
    "gn:country_code":"IT",
    "gn:dem":20,
    "gn:feature_class":"P",
    "gn:feature_code":"PPL",
    "gn:name":"L.P.Bellocchi",
    "gn:population":266,
    "gn:timezone":"Europe/Rome",
    "iso:country":"IT",
    "wof:name":"L.P.Bellocchi",
    "wof:placetype":"locality",
    "wof:population":266
},
  "geometry": {"coordinates":[13.01861,43.79398],"type":"Point"}
}