{
  "type": "Feature",
  "properties": {
    "gn:admin1_code":"12",
    "gn:admin2_code":"CN",
    "gn:admin3_code":"4043.0",
    "gn:asciiname":"Guida",
    "gn:country_code":"IT",
    "gn:dem":368,
    "gn:feature_class":"P",
    "gn:feature_code":"PPLL",
    "gn:name":"Guida",
    "gn:population":8,
    "gn:timezone":"Europe/Rome",
    "iso:country":"IT",
    "wof:name":"Guida",
    "wof:placetype":"locality",
    "wof:population":8
},
  "geometry": {"coordinates":[7.84695,44.46972],"type":"Point"}
}