{
  "type": "Feature",
  "properties": {
    "gn:admin1_code":"12.0",
    "gn:admin2_code":"AL",
    "gn:admin3_code":"6059.0",
    "gn:asciiname":"Valle Cerrina",
    "gn:country_code":"IT",
    "gn:dem":176,
    "gn:feature_class":"P",
    "gn:feature_code":"PPL",
    "gn:name":"Valle Cerrina",
    "gn:population":559,
    "gn:timezone":"Europe/Rome",
    "iso:country":"IT",
    "wof:name":"Valle Cerrina",
    "wof:placetype":"locality",
    "wof:population":559
},
  "geometry": {"coordinates":[8.21186,45.11478],"type":"Point"}
}