{
  "type": "Feature",
  "properties": {
    "gn:admin1_code":"4",
    "gn:admin2_code":"SA",
    "gn:admin3_code":"65127.0",
    "gn:asciiname":"Contrada Lupinata",
    "gn:country_code":"IT",
    "gn:dem":234,
    "gn:feature_class":"P",
    "gn:feature_code":"PPL",
    "gn:name":"Contrada Lupinata",
    "gn:population":119,
    "gn:timezone":"Europe/Rome",
    "iso:country":"IT",
    "wof:name":"Contrada Lupinata",
    "wof:placetype":"locality",
    "wof:population":119
},
  "geometry": {"coordinates":[15.51505,40.09617],"type":"Point"}
}