{
  "type": "Feature",
  "properties": {
    "gn:admin1_code":"5",
    "gn:admin2_code":"PC",
    "gn:admin3_code":"33019.0",
    "gn:asciiname":"Guglieri",
    "gn:country_code":"IT",
    "gn:dem":598,
    "gn:feature_class":"P",
    "gn:feature_code":"PPL",
    "gn:name":"Guglieri",
    "gn:population":46,
    "gn:timezone":"Europe/Rome",
    "iso:country":"IT",
    "wof:name":"Guglieri",
    "wof:placetype":"locality",
    "wof:population":46
},
  "geometry": {"coordinates":[9.55567,44.70128],"type":"Point"}
}