{
  "type": "Feature",
  "properties": {
    "gn:admin1_code":"9",
    "gn:admin2_code":"BG",
    "gn:admin3_code":"16133.0",
    "gn:asciiname":"Gazzo Morale",
    "gn:country_code":"IT",
    "gn:dem":141,
    "gn:feature_class":"P",
    "gn:feature_code":"PPL",
    "gn:name":"Gazzo Morale",
    "gn:population":30,
    "gn:timezone":"Europe/Rome",
    "iso:country":"IT",
    "wof:name":"Gazzo Morale",
    "wof:placetype":"locality",
    "wof:population":30
},
  "geometry": {"coordinates":[9.79126,45.55118],"type":"Point"}
}