{
  "type": "Feature",
  "properties": {
    "gn:admin1_code":"15.0",
    "gn:admin2_code":"PA",
    "gn:admin3_code":"82056.0",
    "gn:asciiname":"Landro",
    "gn:country_code":"IT",
    "gn:dem":634,
    "gn:feature_class":"P",
    "gn:feature_code":"PPL",
    "gn:name":"Landro",
    "gn:population":0,
    "gn:timezone":"Europe/Rome",
    "iso:country":"IT",
    "wof:name":"Landro",
    "wof:placetype":"locality"
},
  "geometry": {"coordinates":[13.98333,37.66667],"type":"Point"}
}