{
  "type": "Feature",
  "properties": {
    "gn:admin1_code":"3.0",
    "gn:admin2_code":"CS",
    "gn:admin3_code":"78115.0",
    "gn:asciiname":"Ficara III",
    "gn:country_code":"IT",
    "gn:dem":282,
    "gn:feature_class":"P",
    "gn:feature_code":"PPL",
    "gn:name":"Ficara III",
    "gn:population":72,
    "gn:timezone":"Europe/Rome",
    "iso:country":"IT",
    "wof:name":"Ficara III",
    "wof:placetype":"locality",
    "wof:population":72
},
  "geometry": {"coordinates":[16.11563,39.66359],"type":"Point"}
}