{
  "type": "Feature",
  "properties": {
    "gn:admin1_code":"18",
    "gn:admin2_code":"PG",
    "gn:admin3_code":"54013.0",
    "gn:asciiname":"Ronti",
    "gn:country_code":"IT",
    "gn:dem":300,
    "gn:feature_class":"P",
    "gn:feature_code":"PPL",
    "gn:name":"Ronti",
    "gn:population":28,
    "gn:timezone":"Europe/Rome",
    "iso:country":"IT",
    "wof:name":"Ronti",
    "wof:placetype":"locality",
    "wof:population":28
},
  "geometry": {"coordinates":[12.15882,43.39254],"type":"Point"}
}