{
  "type": "Feature",
  "properties": {
    "gn:admin1_code":"7",
    "gn:admin2_code":"FR",
    "gn:admin3_code":"60084.0",
    "gn:asciiname":"Gesenette",
    "gn:country_code":"IT",
    "gn:dem":490,
    "gn:feature_class":"P",
    "gn:feature_code":"PPL",
    "gn:name":"Gesenette",
    "gn:population":40,
    "gn:timezone":"Europe/Rome",
    "iso:country":"IT",
    "wof:name":"Gesenette",
    "wof:placetype":"locality",
    "wof:population":40
},
  "geometry": {"coordinates":[13.89947,41.5369],"type":"Point"}
}