{
  "type": "Feature",
  "properties": {
    "iso:country":"IT",
    "name:cat_x_preferred":[
        "Frazione Chiesa"
    ],
    "name:ces_x_preferred":[
        "Frazione Chiesa"
    ],
    "name:dan_x_preferred":[
        "Frazione Chiesa"
    ],
    "name:eng_x_preferred":[
        "Frazione Chiesa"
    ],
    "name:eus_x_preferred":[
        "Frazione Chiesa"
    ],
    "name:fin_x_preferred":[
        "Frazione Chiesa"
    ],
    "name:fra_x_preferred":[
        "Frazione Chiesa"
    ],
    "name:ind_x_preferred":[
        "Frazione Chiesa"
    ],
    "name:ita_x_preferred":[
        "Frazione Chiesa"
    ],
    "name:nld_x_preferred":[
        "Frazione Chiesa"
    ],
    "name:nno_x_preferred":[
        "Frazione Chiesa"
    ],
    "name:nob_x_preferred":[
        "Frazione Chiesa"
    ],
    "name:oci_x_preferred":[
        "Frazione Chiesa"
    ],
    "name:pol_x_preferred":[
        "Frazione Chiesa"
    ],
    "name:por_x_preferred":[
        "Frazione Chiesa"
    ],
    "name:ron_x_preferred":[
        "Frazione Chiesa"
    ],
    "name:slk_x_preferred":[
        "Frazione Chiesa"
    ],
    "name:slv_x_preferred":[
        "Frazione Chiesa"
    ],
    "name:spa_x_preferred":[
        "Frazione Chiesa"
    ],
    "name:srp_x_preferred":[
        "Frazione Chiesa"
    ],
    "name:swe_x_preferred":[
        "Frazione Chiesa"
    ],
    "name:tgl_x_preferred":[
        "Frazione Chiesa"
    ],
    "name:tur_x_preferred":[
        "Frazione Chiesa"
    ],
    "name:war_x_preferred":[
        "Frazione Chiesa"
    ],
    "qs:a0":"Italia",
    "qs:a1":"*Biella",
    "qs:a1r":"0Piemonte",
    "qs:adm0":"Italia",
    "qs:la_lc":"*",
    "qs:level":"locality",
    "qs:loc":"Frazione Chiesa",
    "qs:loc_alt":"Frazione Chiesa",
    "qs:pop":0,
    "qs:type":"buffered point",
    "wof:name":"Frazione Chiesa",
    "wof:placetype":"locality"
},
  "geometry": {"coordinates":[8.21389,45.693611],"type":"Point"}
}