{
  "type": "Feature",
  "properties": {
    "gn:admin1_code":"20",
    "gn:admin2_code":"BL",
    "gn:admin3_code":"25053.0",
    "gn:asciiname":"Sommaval",
    "gn:country_code":"IT",
    "gn:dem":537,
    "gn:feature_class":"P",
    "gn:feature_code":"PPL",
    "gn:name":"Sommaval",
    "gn:population":67,
    "gn:timezone":"Europe/Rome",
    "iso:country":"IT",
    "wof:name":"Sommaval",
    "wof:placetype":"locality",
    "wof:population":67
},
  "geometry": {"coordinates":[12.14755,46.15526],"type":"Point"}
}