{
  "type": "Feature",
  "properties": {
    "gn:admin1_code":"5",
    "gn:admin2_code":"FE",
    "gn:admin3_code":"38027.0",
    "gn:asciiname":"Case Bersanetti",
    "gn:country_code":"IT",
    "gn:dem":-2,
    "gn:feature_class":"P",
    "gn:feature_code":"PPL",
    "gn:name":"Case Bersanetti",
    "gn:population":27,
    "gn:timezone":"Europe/Rome",
    "iso:country":"IT",
    "wof:name":"Case Bersanetti",
    "wof:placetype":"locality",
    "wof:population":27
},
  "geometry": {"coordinates":[11.9823,44.81097000000001],"type":"Point"}
}