{
  "type": "Feature",
  "properties": {
    "gn:admin1_code":"12.0",
    "gn:admin2_code":"BI",
    "gn:admin3_code":"96084.0",
    "gn:asciiname":"Bellaria",
    "gn:country_code":"IT",
    "gn:dem":611,
    "gn:feature_class":"P",
    "gn:feature_code":"PPL",
    "gn:name":"Bellaria",
    "gn:population":23,
    "gn:timezone":"Europe/Rome",
    "iso:country":"IT",
    "wof:name":"Bellaria",
    "wof:placetype":"locality",
    "wof:population":23
},
  "geometry": {"coordinates":[8.1453,45.64856],"type":"Point"}
}