{
  "type": "Feature",
  "properties": {
    "gn:admin1_code":"6.0",
    "gn:admin2_code":"UD",
    "gn:admin3_code":"30040.0",
    "gn:asciiname":"Casera di Casa Vecchia",
    "gn:country_code":"IT",
    "gn:dem":1754,
    "gn:feature_class":"P",
    "gn:feature_code":"PPL",
    "gn:name":"Casera di Casa Vecchia",
    "gn:population":0,
    "gn:timezone":"Europe/Rome",
    "iso:country":"IT",
    "wof:name":"Casera di Casa Vecchia",
    "wof:placetype":"locality"
},
  "geometry": {"coordinates":[12.73167,46.61667],"type":"Point"}
}