{
  "type": "Feature",
  "properties": {
    "gn:admin1_code":"5",
    "gn:admin2_code":"PC",
    "gn:admin3_code":"33005.0",
    "gn:asciiname":"Schiavi",
    "gn:country_code":"IT",
    "gn:dem":687,
    "gn:feature_class":"P",
    "gn:feature_code":"PPLL",
    "gn:name":"Schiavi",
    "gn:population":8,
    "gn:timezone":"Europe/Rome",
    "iso:country":"IT",
    "wof:name":"Schiavi",
    "wof:placetype":"locality",
    "wof:population":8
},
  "geometry": {"coordinates":[9.39439,44.83171],"type":"Point"}
}