{
  "type": "Feature",
  "properties": {
    "gn:admin1_code":"5.0",
    "gn:admin2_code":"RN",
    "gn:admin3_code":"99009.0",
    "gn:asciiname":"Trebbio di Montegridolfo",
    "gn:country_code":"IT",
    "gn:dem":127,
    "gn:feature_class":"P",
    "gn:feature_code":"PPL",
    "gn:name":"Trebbio di Montegridolfo",
    "gn:population":483,
    "gn:timezone":"Europe/Rome",
    "iso:country":"IT",
    "wof:name":"Trebbio di Montegridolfo",
    "wof:placetype":"locality",
    "wof:population":483
},
  "geometry": {"coordinates":[12.70481,43.86067],"type":"Point"}
}