{
  "type": "Feature",
  "properties": {
    "gn:admin1_code":"3",
    "gn:admin2_code":"VV",
    "gn:admin3_code":"102011.0",
    "gn:asciiname":"Dirupi",
    "gn:country_code":"IT",
    "gn:dem":395,
    "gn:feature_class":"P",
    "gn:feature_code":"PPL",
    "gn:name":"Dirupi",
    "gn:population":97,
    "gn:timezone":"Europe/Rome",
    "iso:country":"IT",
    "wof:name":"Dirupi",
    "wof:placetype":"locality",
    "wof:population":97
},
  "geometry": {"coordinates":[16.30541,38.77141],"type":"Point"}
}