{
  "type": "Feature",
  "properties": {
    "gn:admin1_code":"7.0",
    "gn:admin2_code":"RM",
    "gn:admin3_code":"58066.0",
    "gn:asciiname":"Monte Libretti",
    "gn:country_code":"IT",
    "gn:dem":285,
    "gn:feature_class":"P",
    "gn:feature_code":"PPL",
    "gn:name":"Monte Libretti",
    "gn:population":0,
    "gn:timezone":"Europe/Rome",
    "iso:country":"IT",
    "wof:name":"Monte Libretti",
    "wof:placetype":"locality"
},
  "geometry": {"coordinates":[12.78333,42.13333],"type":"Point"}
}