{
  "type": "Feature",
  "properties": {
    "gn:admin1_code":"5",
    "gn:admin2_code":"PR",
    "gn:admin3_code":"34019.0",
    "gn:asciiname":"Fossola",
    "gn:country_code":"IT",
    "gn:dem":346,
    "gn:feature_class":"P",
    "gn:feature_code":"PPL",
    "gn:name":"Fossola",
    "gn:population":38,
    "gn:timezone":"Europe/Rome",
    "iso:country":"IT",
    "wof:name":"Fossola",
    "wof:placetype":"locality",
    "wof:population":38
},
  "geometry": {"coordinates":[10.32916,44.63307],"type":"Point"}
}