{
  "type": "Feature",
  "properties": {
    "gn:admin1_code":"20.0",
    "gn:admin2_code":"BL",
    "gn:admin3_code":"25019.0",
    "gn:asciiname":"Caviola",
    "gn:country_code":"IT",
    "gn:dem":1092,
    "gn:feature_class":"P",
    "gn:feature_code":"PPL",
    "gn:name":"Caviola",
    "gn:population":591,
    "gn:timezone":"Europe/Rome",
    "iso:country":"IT",
    "wof:name":"Caviola",
    "wof:placetype":"locality",
    "wof:population":591
},
  "geometry": {"coordinates":[11.89644,46.36433],"type":"Point"}
}