{
  "type": "Feature",
  "properties": {
    "gn:admin1_code":"7",
    "gn:admin2_code":"LT",
    "gn:admin3_code":"59028.0",
    "gn:asciiname":"Maina",
    "gn:country_code":"IT",
    "gn:dem":5,
    "gn:feature_class":"P",
    "gn:feature_code":"PPL",
    "gn:name":"Maina",
    "gn:population":186,
    "gn:timezone":"Europe/Rome",
    "iso:country":"IT",
    "wof:name":"Maina",
    "wof:placetype":"locality",
    "wof:population":186
},
  "geometry": {"coordinates":[13.00413,41.4732],"type":"Point"}
}