{
  "type": "Feature",
  "properties": {
    "gn:admin1_code":"1.0",
    "gn:admin2_code":"AQ",
    "gn:admin3_code":"66021.0",
    "gn:asciiname":"Mopolino",
    "gn:country_code":"IT",
    "gn:dem":882,
    "gn:feature_class":"P",
    "gn:feature_code":"PPL",
    "gn:name":"Mopolino",
    "gn:population":0,
    "gn:timezone":"Europe/Rome",
    "iso:country":"IT",
    "wof:name":"Mopolino",
    "wof:placetype":"locality"
},
  "geometry": {"coordinates":[13.29951,42.51798],"type":"Point"}
}