{
  "type": "Feature",
  "properties": {
    "gn:admin1_code":"1.0",
    "gn:admin2_code":"CH",
    "gn:admin3_code":"69059.0",
    "gn:asciiname":"Saletti d'Intrione",
    "gn:country_code":"IT",
    "gn:dem":16,
    "gn:feature_class":"P",
    "gn:feature_code":"PPLL",
    "gn:name":"Saletti d'Intrione",
    "gn:population":0,
    "gn:timezone":"Europe/Rome",
    "iso:country":"IT",
    "wof:name":"Saletti d'Intrione",
    "wof:placetype":"locality"
},
  "geometry": {"coordinates":[14.50979,42.20778],"type":"Point"}
}