{
  "type": "Feature",
  "properties": {
    "gn:admin1_code":"16",
    "gn:admin2_code":"LU",
    "gn:admin3_code":"46009.0",
    "gn:asciiname":"Cerretoli",
    "gn:country_code":"IT",
    "gn:dem":537,
    "gn:feature_class":"P",
    "gn:feature_code":"PPL",
    "gn:name":"Cerretoli",
    "gn:population":72,
    "gn:timezone":"Europe/Rome",
    "iso:country":"IT",
    "wof:name":"Cerretoli",
    "wof:placetype":"locality",
    "wof:population":72
},
  "geometry": {"coordinates":[10.37714,44.11131],"type":"Point"}
}