{
  "type": "Feature",
  "properties": {
    "gn:admin1_code":"6.0",
    "gn:admin2_code":"UD",
    "gn:admin3_code":"30074.0",
    "gn:asciiname":"Ronchi",
    "gn:cc2":"IT",
    "gn:country_code":"IT",
    "gn:dem":51,
    "gn:elevation":"52.0",
    "gn:feature_class":"P",
    "gn:feature_code":"PPL",
    "gn:name":"Ronchi",
    "gn:population":14,
    "gn:timezone":"Europe/Rome",
    "iso:country":"IT",
    "name:ceb_x_preferred":[
        "Ronchi"
    ],
    "name:deu_x_preferred":[
        "Ronchi"
    ],
    "name:epo_x_preferred":[
        "Ronchi"
    ],
    "name:ita_x_preferred":[
        "Ronchi"
    ],
    "name:lat_x_preferred":[
        "Ronches"
    ],
    "name:por_x_preferred":[
        "Ronchi"
    ],
    "name:scn_x_preferred":[
        "Ronchi"
    ],
    "name:srp_x_preferred":[
        "Ronki"
    ],
    "name:swe_x_preferred":[
        "Ronchi"
    ],
    "name:und_x_variant":[
        "Ronchi-Popereacco",
        "Ronchi"
    ],
    "wof:name":"Ronchi",
    "wof:placetype":"locality",
    "wof:population":14
},
  "geometry": {"coordinates":[13.30827,45.96118],"type":"Point"}
}