{
  "type": "Feature",
  "properties": {
    "gn:admin1_code":"3",
    "gn:admin2_code":"CS",
    "gn:admin3_code":"78002.0",
    "gn:asciiname":"San Iorio",
    "gn:country_code":"IT",
    "gn:dem":296,
    "gn:feature_class":"P",
    "gn:feature_code":"PPL",
    "gn:name":"San Iorio",
    "gn:population":49,
    "gn:timezone":"Europe/Rome",
    "iso:country":"IT",
    "wof:name":"San Iorio",
    "wof:placetype":"locality",
    "wof:population":49
},
  "geometry": {"coordinates":[15.96785,39.49249],"type":"Point"}
}