{
  "type": "Feature",
  "properties": {
    "gn:admin1_code":"15.0",
    "gn:admin2_code":"ME",
    "gn:admin3_code":"83011.0",
    "gn:asciiname":"Marina di Caronia",
    "gn:cc2":"IT",
    "gn:country_code":"IT",
    "gn:dem":17,
    "gn:elevation":"20.0",
    "gn:feature_class":"P",
    "gn:feature_code":"PPL",
    "gn:name":"Marina di Caronia",
    "gn:population":1015,
    "gn:timezone":"Europe/Rome",
    "iso:country":"IT",
    "name:und_x_variant":[
        "Marina",
        "Marina di Caronia",
        "Caronia Marina"
    ],
    "wof:name":"Marina di Caronia",
    "wof:placetype":"locality",
    "wof:population":1015
},
  "geometry": {"coordinates":[14.44182,38.03545],"type":"Point"}
}