{
  "type": "Feature",
  "properties": {
    "gn:admin1_code":"7.0",
    "gn:admin2_code":"RI",
    "gn:admin3_code":"57007.0",
    "gn:asciiname":"Collemaggiore",
    "gn:country_code":"IT",
    "gn:dem":884,
    "gn:elevation":"903.0",
    "gn:feature_class":"P",
    "gn:feature_code":"PPL",
    "gn:name":"Collemaggiore",
    "gn:population":87,
    "gn:timezone":"Europe/Rome",
    "iso:country":"IT",
    "wof:name":"Collemaggiore",
    "wof:placetype":"locality",
    "wof:population":87
},
  "geometry": {"coordinates":[13.20833,42.22644],"type":"Point"}
}