{
  "type": "Feature",
  "properties": {
    "gn:admin1_code":"4.0",
    "gn:admin2_code":"CE",
    "gn:admin3_code":"61060.0",
    "gn:asciiname":"Taverna di Pignataro Maggiore",
    "gn:country_code":"IT",
    "gn:dem":53,
    "gn:feature_class":"P",
    "gn:feature_code":"PPL",
    "gn:name":"Taverna di Pignataro Maggiore",
    "gn:population":84,
    "gn:timezone":"Europe/Rome",
    "iso:country":"IT",
    "wof:name":"Taverna di Pignataro Maggiore",
    "wof:placetype":"locality",
    "wof:population":84
},
  "geometry": {"coordinates":[14.16014,41.17651],"type":"Point"}
}