{
  "type": "Feature",
  "properties": {
    "gn:admin1_code":"3",
    "gn:admin2_code":"RC",
    "gn:admin3_code":"80054.0",
    "gn:asciiname":"Paolia",
    "gn:country_code":"IT",
    "gn:dem":85,
    "gn:feature_class":"P",
    "gn:feature_code":"PPL",
    "gn:name":"Paolia",
    "gn:population":38,
    "gn:timezone":"Europe/Rome",
    "iso:country":"IT",
    "wof:name":"Paolia",
    "wof:placetype":"locality",
    "wof:population":38
},
  "geometry": {"coordinates":[15.67657,37.97394],"type":"Point"}
}