{
  "type": "Feature",
  "properties": {
    "gn:admin1_code":"19",
    "gn:admin2_code":"AO",
    "gn:admin3_code":"7003.0",
    "gn:asciiname":"Champailler",
    "gn:country_code":"IT",
    "gn:dem":852,
    "gn:feature_class":"P",
    "gn:feature_code":"PPL",
    "gn:name":"Champailler",
    "gn:population":27,
    "gn:timezone":"Europe/Rome",
    "iso:country":"IT",
    "wof:name":"Champailler",
    "wof:placetype":"locality",
    "wof:population":27
},
  "geometry": {"coordinates":[7.3009,45.74322],"type":"Point"}
}