{
  "type": "Feature",
  "properties": {
    "gn:admin1_code":"17.0",
    "gn:admin2_code":"TN",
    "gn:admin3_code":"22244.0",
    "gn:asciiname":"Verdesina",
    "gn:country_code":"IT",
    "gn:dem":649,
    "gn:elevation":"648.0",
    "gn:feature_class":"P",
    "gn:feature_code":"PPL",
    "gn:name":"Verdesina",
    "gn:population":160,
    "gn:timezone":"Europe/Rome",
    "iso:country":"IT",
    "wof:name":"Verdesina",
    "wof:placetype":"locality",
    "wof:population":160
},
  "geometry": {"coordinates":[10.71277,46.05561],"type":"Point"}
}