{
  "type": "Feature",
  "properties": {
    "gn:admin1_code":"7",
    "gn:admin2_code":"FR",
    "gn:admin3_code":"60058.0",
    "gn:asciiname":"Porroni",
    "gn:country_code":"IT",
    "gn:dem":186,
    "gn:feature_class":"P",
    "gn:feature_code":"PPL",
    "gn:name":"Porroni",
    "gn:population":221,
    "gn:timezone":"Europe/Rome",
    "iso:country":"IT",
    "wof:name":"Porroni",
    "wof:placetype":"locality",
    "wof:population":221
},
  "geometry": {"coordinates":[13.41437,41.59831],"type":"Point"}
}