{
  "type": "Feature",
  "properties": {
    "gn:admin1_code":"12",
    "gn:admin2_code":"CN",
    "gn:admin3_code":"4240.0",
    "gn:asciiname":"Case Nicolini",
    "gn:country_code":"IT",
    "gn:dem":408,
    "gn:feature_class":"P",
    "gn:feature_code":"PPL",
    "gn:name":"Case Nicolini",
    "gn:population":28,
    "gn:timezone":"Europe/Rome",
    "iso:country":"IT",
    "wof:name":"Case Nicolini",
    "wof:placetype":"locality",
    "wof:population":28
},
  "geometry": {"coordinates":[7.50253,44.59761],"type":"Point"}
}