{
  "type": "Feature",
  "properties": {
    "gn:admin1_code":"9.0",
    "gn:admin2_code":"MN",
    "gn:admin3_code":"20019.0",
    "gn:asciiname":"Tezze di Ceresara",
    "gn:country_code":"IT",
    "gn:dem":41,
    "gn:feature_class":"P",
    "gn:feature_code":"PPL",
    "gn:name":"Tezze di Ceresara",
    "gn:population":89,
    "gn:timezone":"Europe/Rome",
    "iso:country":"IT",
    "wof:name":"Tezze di Ceresara",
    "wof:placetype":"locality",
    "wof:population":89
},
  "geometry": {"coordinates":[10.58165,45.26597],"type":"Point"}
}