{
  "type": "Feature",
  "properties": {
    "gn:admin1_code":"3.0",
    "gn:admin2_code":"RC",
    "gn:admin3_code":"80063.0",
    "gn:asciiname":"Straorino",
    "gn:cc2":"IT",
    "gn:country_code":"IT",
    "gn:dem":566,
    "gn:elevation":"586.0",
    "gn:feature_class":"P",
    "gn:feature_code":"PPL",
    "gn:name":"Straorino",
    "gn:population":76,
    "gn:timezone":"Europe/Rome",
    "iso:country":"IT",
    "name:und_x_variant":[
        "Straorini"
    ],
    "wof:name":"Straorino",
    "wof:placetype":"locality",
    "wof:population":76
},
  "geometry": {"coordinates":[15.74643,38.13282],"type":"Point"}
}