{
  "type": "Feature",
  "properties": {
    "gn:admin1_code":"12",
    "gn:admin2_code":"TO",
    "gn:admin3_code":"1191.0",
    "gn:asciiname":"Borgata Orba",
    "gn:country_code":"IT",
    "gn:dem":326,
    "gn:feature_class":"P",
    "gn:feature_code":"PPL",
    "gn:name":"Borgata Orba",
    "gn:population":36,
    "gn:timezone":"Europe/Rome",
    "iso:country":"IT",
    "wof:name":"Borgata Orba",
    "wof:placetype":"locality",
    "wof:population":36
},
  "geometry": {"coordinates":[7.38061,44.90174],"type":"Point"}
}