{
  "type": "Feature",
  "properties": {
    "iso:country":"IT",
    "name:deu_x_preferred":[
        "Precotto"
    ],
    "name:eng_x_preferred":[
        "Precotto"
    ],
    "name:fra_x_preferred":[
        "Precotto"
    ],
    "name:ita_x_preferred":[
        "Precotto"
    ],
    "name:lat_x_preferred":[
        "Praecautum"
    ],
    "name:lmo_x_preferred":[
        "Prec\u00f2tt"
    ],
    "name:nld_x_preferred":[
        "Precotto"
    ],
    "name:por_x_preferred":[
        "Precotto"
    ],
    "name:spa_x_preferred":[
        "Precotto"
    ],
    "wof:name":"Precotto",
    "wof:placetype":"neighbourhood"
},
  "geometry": {"coordinates":[9.22569515706324,45.51480719264094],"type":"Point"}
}