{
  "type": "Feature",
  "properties": {
    "iso:country":"IT",
    "name:deu_x_preferred":[
        "Precotto"
    ],
    "name:eng_x_preferred":[
        "Precotto"
    ],
    "name:fra_x_preferred":[
        "Precotto"
    ],
    "name:ita_x_preferred":[
        "Precotto"
    ],
    "name:lat_x_preferred":[
        "Praecautum"
    ],
    "name:lmo_x_preferred":[
        "Prec\u00f2tt"
    ],
    "name:nld_x_preferred":[
        "Precotto"
    ],
    "name:por_x_preferred":[
        "Precotto"
    ],
    "name:spa_x_preferred":[
        "Precotto"
    ],
    "name:urd_x_preferred":[
        "\u067e\u0631\u06cc\u06a9\u0648\u062a\u0648"
    ],
    "wof:name":"Precotto",
    "wof:placetype":"neighbourhood"
},
  "geometry": {"coordinates":[9.225695,45.514807],"type":"Point"}
}