{
  "type": "Feature",
  "properties": {
    "gn:admin1_code":"9.0",
    "gn:admin2_code":"MI",
    "gn:admin3_code":"15236.0",
    "gn:asciiname":"Moncucco",
    "gn:country_code":"IT",
    "gn:dem":101,
    "gn:feature_class":"P",
    "gn:feature_code":"PPL",
    "gn:name":"Moncucco",
    "gn:population":1481,
    "gn:timezone":"Europe/Rome",
    "iso:country":"IT",
    "name:azb_x_preferred":[
        "\u0645\u0648\u0646\u06a9\u0648\u06a9\u0648"
    ],
    "name:fas_x_preferred":[
        "\u0645\u0648\u0646\u06a9\u0648\u06a9\u0648"
    ],
    "wof:name":"Moncucco",
    "wof:placetype":"locality",
    "wof:population":1481
},
  "geometry": {"coordinates":[9.0392,45.31032],"type":"Point"}
}