{
  "type": "Feature",
  "properties": {
    "gn:admin1_code":"17",
    "gn:admin2_code":"BZ",
    "gn:admin3_code":"21028.0",
    "gn:asciiname":"Monterota",
    "gn:country_code":"IT",
    "gn:dem":1598,
    "gn:feature_class":"P",
    "gn:feature_code":"PPL",
    "gn:name":"Monterota",
    "gn:population":32,
    "gn:timezone":"Europe/Rome",
    "iso:country":"IT",
    "wof:name":"Monterota",
    "wof:placetype":"locality",
    "wof:population":32
},
  "geometry": {"coordinates":[12.218,46.74733],"type":"Point"}
}