{
  "type": "Feature",
  "properties": {
    "gn:admin1_code":"12",
    "gn:admin2_code":"VC",
    "gn:admin3_code":"2150.0",
    "gn:asciiname":"Vianone",
    "gn:country_code":"IT",
    "gn:dem":191,
    "gn:feature_class":"P",
    "gn:feature_code":"PPL",
    "gn:name":"Vianone",
    "gn:population":16,
    "gn:timezone":"Europe/Rome",
    "iso:country":"IT",
    "wof:name":"Vianone",
    "wof:placetype":"locality",
    "wof:population":16
},
  "geometry": {"coordinates":[8.12994,45.3452],"type":"Point"}
}