{
  "type": "Feature",
  "properties": {
    "gn:country":"IT",
    "gn:fcode":"PPL",
    "gn:population":0,
    "iso:country":"IT",
    "name:cat_x_preferred":[
        "Campolo"
    ],
    "name:ceb_x_preferred":[
        "Campolo"
    ],
    "name:ces_x_preferred":[
        "Campolo"
    ],
    "name:che_x_preferred":[
        "\u041a\u0430\u043c\u043f\u043e\u043b\u043e"
    ],
    "name:dan_x_preferred":[
        "Campolo"
    ],
    "name:eng_x_preferred":[
        "Campolo"
    ],
    "name:eus_x_preferred":[
        "Campolo"
    ],
    "name:fin_x_preferred":[
        "Campolo"
    ],
    "name:fra_x_preferred":[
        "Campolo"
    ],
    "name:ind_x_preferred":[
        "Campolo"
    ],
    "name:ita_x_preferred":[
        "Campolo"
    ],
    "name:nld_x_preferred":[
        "Campolo"
    ],
    "name:nno_x_preferred":[
        "Campolo"
    ],
    "name:nob_x_preferred":[
        "Campolo"
    ],
    "name:oci_x_preferred":[
        "Campolo"
    ],
    "name:pol_x_preferred":[
        "Campolo"
    ],
    "name:por_x_preferred":[
        "Campolo"
    ],
    "name:ron_x_preferred":[
        "Campolo"
    ],
    "name:slk_x_preferred":[
        "Campolo"
    ],
    "name:slv_x_preferred":[
        "Campolo"
    ],
    "name:spa_x_preferred":[
        "Campolo"
    ],
    "name:srp_x_preferred":[
        "Campolo"
    ],
    "name:swe_x_preferred":[
        "Campolo"
    ],
    "name:tat_x_preferred":[
        "\u041a\u0430\u043c\u043f\u043e\u043b\u043e"
    ],
    "name:tgl_x_preferred":[
        "Campolo"
    ],
    "name:tur_x_preferred":[
        "Campolo"
    ],
    "name:war_x_preferred":[
        "Campolo"
    ],
    "qs_pg:aaroncc":"IT",
    "qs_pg:gn_country":"IT",
    "qs_pg:gn_fcode":"PPL",
    "qs_pg:gn_pop":0,
    "qs_pg:name":"Campolo",
    "qs_pg:name_adm0":"Italia",
    "qs_pg:name_adm1":"Emilia Romagna",
    "qs_pg:photos":187,
    "qs_pg:photos_1k":38,
    "qs_pg:photos_9k":1,
    "qs_pg:photos_9r":4,
    "qs_pg:photos_all":187,
    "qs_pg:photos_sr":4,
    "qs_pg:pop_sr":0,
    "qs_pg:qs_pg_placetype":"locality",
    "qs_pg:qs_pg_placetype_gp":"Town",
    "qs_pg:woe_adm0":23424853,
    "woe:adm0_id":23424853,
    "woe:name_adm0":"Italia",
    "woe:name_adm1":"Emilia Romagna",
    "woe:placetype":"Town",
    "wof:name":"Campolo",
    "wof:placetype":"locality",
    "wof:population":71
},
  "geometry": {"coordinates":[11.08333,44.21667],"type":"Point"}
}