{
  "type": "Feature",
  "properties": {
    "gn:admin1_code":"5",
    "gn:admin2_code":"MO",
    "gn:admin3_code":"36023.0",
    "gn:asciiname":"Paganine",
    "gn:country_code":"IT",
    "gn:dem":44,
    "gn:feature_class":"P",
    "gn:feature_code":"PPL",
    "gn:name":"Paganine",
    "gn:population":206,
    "gn:timezone":"Europe/Rome",
    "iso:country":"IT",
    "wof:name":"Paganine",
    "wof:placetype":"locality",
    "wof:population":206
},
  "geometry": {"coordinates":[10.94738,44.58813],"type":"Point"}
}