{
  "type": "Feature",
  "properties": {
    "gn:admin1_code":"12",
    "gn:admin2_code":"CN",
    "gn:admin3_code":"4240.0",
    "gn:asciiname":"Quaranta",
    "gn:country_code":"IT",
    "gn:dem":404,
    "gn:feature_class":"P",
    "gn:feature_code":"PPL",
    "gn:name":"Quaranta",
    "gn:population":30,
    "gn:timezone":"Europe/Rome",
    "iso:country":"IT",
    "wof:name":"Quaranta",
    "wof:placetype":"locality",
    "wof:population":30
},
  "geometry": {"coordinates":[7.51799,44.58895],"type":"Point"}
}