{
  "type": "Feature",
  "properties": {
    "gn:elevation":2,
    "gn:population":3062,
    "iso:country":"IT",
    "name:cat_x_preferred":[
        "Sant'Anna"
    ],
    "name:ceb_x_preferred":[
        "Sant'Anna"
    ],
    "name:ces_x_preferred":[
        "Sant'Anna"
    ],
    "name:dan_x_preferred":[
        "Sant'Anna"
    ],
    "name:deu_x_preferred":[
        "Sant'Anna"
    ],
    "name:eng_x_preferred":[
        "Sant'Anna"
    ],
    "name:eus_x_preferred":[
        "Sant'Anna"
    ],
    "name:fin_x_preferred":[
        "Sant'Anna"
    ],
    "name:fra_x_preferred":[
        "Sant'Anna"
    ],
    "name:hun_x_preferred":[
        "Sant'Anna"
    ],
    "name:ind_x_preferred":[
        "Sant'Anna"
    ],
    "name:ita_x_preferred":[
        "Sant'anna"
    ],
    "name:ita_x_variant":[
        "S Anna",
        "S. Anna",
        "Sant'Anna"
    ],
    "name:nld_x_preferred":[
        "Sant'Anna di Chioggia"
    ],
    "name:nno_x_preferred":[
        "Sant'Anna"
    ],
    "name:nob_x_preferred":[
        "Sant'Anna"
    ],
    "name:oci_x_preferred":[
        "Sant'Anna"
    ],
    "name:pol_x_preferred":[
        "Sant'Anna"
    ],
    "name:por_x_preferred":[
        "Sant'Anna"
    ],
    "name:ron_x_preferred":[
        "Sant'Anna"
    ],
    "name:slk_x_preferred":[
        "Sant'Anna"
    ],
    "name:slv_x_preferred":[
        "Sant'Anna"
    ],
    "name:spa_x_preferred":[
        "Sant'Anna"
    ],
    "name:srp_x_preferred":[
        "Sant'Anna"
    ],
    "name:swe_x_preferred":[
        "Sant'Anna"
    ],
    "name:tgl_x_preferred":[
        "Sant'Anna"
    ],
    "name:tur_x_preferred":[
        "Sant'Anna"
    ],
    "name:und_x_variant":[
        "Santa Andrea"
    ],
    "name:war_x_preferred":[
        "Sant'Anna"
    ],
    "qs:a0":"Italia",
    "qs:a1":"*Venezia",
    "qs:a1r":"0Veneto",
    "qs:adm0":"Italia",
    "qs:la_lc":"*",
    "qs:level":"locality",
    "qs:loc":"Sant'Anna",
    "qs:loc_alt":"Sant'Anna",
    "qs:pop":0,
    "qs:type":"buffered point",
    "wof:lang":[
        "ita"
    ],
    "wof:name":"Sant'Anna",
    "wof:placetype":"locality",
    "wof:population":3062
},
  "geometry": {"coordinates":[12.27378,45.157928],"type":"Point"}
}