{
  "type": "Feature",
  "properties": {
    "gn:admin1_code":"5.0",
    "gn:admin2_code":"BO",
    "gn:admin3_code":"37034.0",
    "gn:asciiname":"Bibulano",
    "gn:country_code":"IT",
    "gn:dem":505,
    "gn:feature_class":"P",
    "gn:feature_code":"PPL",
    "gn:name":"Bibulano",
    "gn:population":21,
    "gn:timezone":"Europe/Rome",
    "iso:country":"IT",
    "wof:name":"Bibulano",
    "wof:placetype":"locality",
    "wof:population":21
},
  "geometry": {"coordinates":[11.3014,44.27414],"type":"Point"}
}