{
  "type": "Feature",
  "properties": {
    "gn:admin1_code":"10.0",
    "gn:admin2_code":"FM",
    "gn:admin3_code":"109006.0",
    "gn:asciiname":"Molini di Tenna",
    "gn:country_code":"IT",
    "gn:dem":75,
    "gn:feature_class":"P",
    "gn:feature_code":"PPL",
    "gn:name":"Molini di Tenna",
    "gn:population":900,
    "gn:timezone":"Europe/Rome",
    "iso:country":"IT",
    "wof:name":"Molini di Tenna",
    "wof:placetype":"locality",
    "wof:population":900
},
  "geometry": {"coordinates":[13.67125,43.16662],"type":"Point"}
}