{
  "type": "Feature",
  "properties": {
    "gn:admin1_code":"20.0",
    "gn:admin2_code":"TV",
    "gn:admin3_code":"26013.0",
    "gn:asciiname":"Case Moro",
    "gn:country_code":"IT",
    "gn:dem":46,
    "gn:feature_class":"P",
    "gn:feature_code":"PPL",
    "gn:name":"Case Moro",
    "gn:population":15,
    "gn:timezone":"Europe/Rome",
    "iso:country":"IT",
    "wof:name":"Case Moro",
    "wof:placetype":"locality",
    "wof:population":15
},
  "geometry": {"coordinates":[11.8819,45.67921],"type":"Point"}
}