{
  "type": "Feature",
  "properties": {
    "gn:admin1_code":"4.0",
    "gn:admin3_code":"63086.0",
    "gn:asciiname":"Moiano",
    "gn:country_code":"IT",
    "gn:dem":503,
    "gn:feature_class":"P",
    "gn:feature_code":"PPL",
    "gn:name":"Moiano",
    "gn:population":2670,
    "gn:timezone":"Europe/Rome",
    "iso:country":"IT",
    "name:azb_x_preferred":[
        "\u0645\u0648\u0627\u06cc\u0627\u0646\u0648"
    ],
    "name:bul_x_preferred":[
        "\u041c\u043e\u044f\u043d\u043e"
    ],
    "name:ceb_x_preferred":[
        "Moiano"
    ],
    "name:deu_x_preferred":[
        "Moiano"
    ],
    "name:epo_x_preferred":[
        "Moiano"
    ],
    "name:est_x_preferred":[
        "Moiano"
    ],
    "name:eus_x_preferred":[
        "Moiano"
    ],
    "name:fas_x_preferred":[
        "\u0645\u0648\u0627\u06cc\u0627\u0646\u0648"
    ],
    "name:fra_x_preferred":[
        "Moiano"
    ],
    "name:hun_x_preferred":[
        "Moiano"
    ],
    "name:hye_x_preferred":[
        "\u0544\u0578\u056b\u0561\u0576\u0578"
    ],
    "name:ina_x_preferred":[
        "Moiano"
    ],
    "name:ita_x_preferred":[
        "Moiano"
    ],
    "name:jpn_x_preferred":[
        "\u30e2\u30a4\u30a2\u30fc\u30ce"
    ],
    "name:kaz_x_preferred":[
        "\u041c\u043e\u044f\u043d\u043e"
    ],
    "name:kor_x_preferred":[
        "\ubaa8\uc774\uc544\ub178"
    ],
    "name:lat_x_preferred":[
        "Muianus"
    ],
    "name:lmo_x_preferred":[
        "Moiano"
    ],
    "name:mkd_x_preferred":[
        "\u041c\u043e\u0458\u0430\u043d\u043e"
    ],
    "name:msa_x_preferred":[
        "Moiano"
    ],
    "name:nap_x_preferred":[
        "Moiano"
    ],
    "name:nld_x_preferred":[
        "Moiano"
    ],
    "name:pms_x_preferred":[
        "Moiano"
    ],
    "name:pol_x_preferred":[
        "Moiano"
    ],
    "name:por_x_preferred":[
        "Moiano"
    ],
    "name:ron_x_preferred":[
        "Moiano"
    ],
    "name:rus_x_preferred":[
        "\u041c\u043e\u044f\u043d\u043e"
    ],
    "name:scn_x_preferred":[
        "Moianu"
    ],
    "name:spa_x_preferred":[
        "Moiano"
    ],
    "name:srn_x_preferred":[
        "Moiano"
    ],
    "name:srp_x_preferred":[
        "\u041c\u043e\u0458\u0430\u043d\u043e"
    ],
    "name:tgl_x_preferred":[
        "Moiano"
    ],
    "name:tur_x_preferred":[
        "Moiano"
    ],
    "name:ukr_x_preferred":[
        "\u041c\u043e\u044f\u043d\u043e"
    ],
    "name:uzb_x_preferred":[
        "Moiano"
    ],
    "name:vie_x_preferred":[
        "Moiano"
    ],
    "name:vol_x_preferred":[
        "Moiano"
    ],
    "name:war_x_preferred":[
        "Moiano"
    ],
    "name:zho_x_preferred":[
        "\u83ab\u4e9a\u8bfa"
    ],
    "wof:name":"Moiano",
    "wof:placetype":"locality",
    "wof:population":2670
},
  "geometry": {"coordinates":[14.46601,40.65172000000001],"type":"Point"}
}