{
  "type": "Feature",
  "properties": {
    "gn:admin1_code":"4.0",
    "gn:admin3_code":"63086.0",
    "gn:asciiname":"Moiano",
    "gn:country_code":"IT",
    "gn:dem":503,
    "gn:feature_class":"P",
    "gn:feature_code":"PPL",
    "gn:name":"Moiano",
    "gn:population":2670,
    "gn:timezone":"Europe/Rome",
    "iso:country":"IT",
    "wof:name":"Moiano",
    "wof:placetype":"locality",
    "wof:population":2670
},
  "geometry": {"coordinates":[14.46601,40.65172000000001],"type":"Point"}
}