{
  "type": "Feature",
  "properties": {
    "gn:admin1_code":"12",
    "gn:admin2_code":"BI",
    "gn:admin3_code":"96010.0",
    "gn:asciiname":"Cascine Rosse",
    "gn:country_code":"IT",
    "gn:dem":401,
    "gn:feature_class":"P",
    "gn:feature_code":"PPL",
    "gn:name":"Cascine Rosse",
    "gn:population":332,
    "gn:timezone":"Europe/Rome",
    "iso:country":"IT",
    "wof:name":"Cascine Rosse",
    "wof:placetype":"locality",
    "wof:population":332
},
  "geometry": {"coordinates":[8.00867,45.5506],"type":"Point"}
}