{
  "type": "Feature",
  "properties": {
    "gn:admin1_code":"20",
    "gn:admin2_code":"VI",
    "gn:admin3_code":"24020.0",
    "gn:asciiname":"Chiossi",
    "gn:country_code":"IT",
    "gn:dem":228,
    "gn:feature_class":"P",
    "gn:feature_code":"PPL",
    "gn:name":"Chiossi",
    "gn:population":14,
    "gn:timezone":"Europe/Rome",
    "iso:country":"IT",
    "wof:name":"Chiossi",
    "wof:placetype":"locality",
    "wof:population":14
},
  "geometry": {"coordinates":[11.50451,45.75871],"type":"Point"}
}