{
  "type": "Feature",
  "properties": {
    "gn:admin1_code":"4",
    "gn:admin2_code":"AV",
    "gn:admin3_code":"64038.0",
    "gn:asciiname":"Pezza Stefano Assanti",
    "gn:country_code":"IT",
    "gn:dem":366,
    "gn:feature_class":"P",
    "gn:feature_code":"PPL",
    "gn:name":"Pezza Stefano Assanti",
    "gn:population":46,
    "gn:timezone":"Europe/Rome",
    "iso:country":"IT",
    "wof:name":"Pezza Stefano Assanti",
    "wof:placetype":"locality",
    "wof:population":46
},
  "geometry": {"coordinates":[15.06705,41.0793],"type":"Point"}
}