{
  "type": "Feature",
  "properties": {
    "gn:admin1_code":"5.0",
    "gn:admin2_code":"RA",
    "gn:admin3_code":"39017.0",
    "gn:asciiname":"Sant'Agata sul Santerno",
    "gn:cc2":"IT",
    "gn:country_code":"IT",
    "gn:dem":12,
    "gn:elevation":"14.0",
    "gn:feature_class":"P",
    "gn:feature_code":"PPLA3",
    "gn:name":"Sant'Agata sul Santerno",
    "gn:population":2404,
    "gn:timezone":"Europe/Rome",
    "iso:country":"IT",
    "name:eng_x_preferred":[
        "Sant'Agata sul Santerno"
    ],
    "name:epo_x_preferred":[
        "Sant'Agata sul Santerno"
    ],
    "name:fra_x_preferred":[
        "Sant'Agata sul Santerno"
    ],
    "name:ita_x_preferred":[
        "Sant'Agata sul Santerno"
    ],
    "name:jpn_x_preferred":[
        "\u30b5\u30f3\u30bf\u30ac\u30fc\u30bf\u30fb\u30b9\u30eb\u30fb\u30b5\u30f3\u30c6\u30eb\u30ce"
    ],
    "name:nap_x_preferred":[
        "Sant'Agata sul Santerno"
    ],
    "name:nld_x_preferred":[
        "Sant'Agata sul Santerno"
    ],
    "name:pol_x_preferred":[
        "Sant'Agata sul Santerno"
    ],
    "name:por_x_preferred":[
        "Sant'Agata sul Santerno"
    ],
    "name:und_x_variant":[
        "Sant'Agata"
    ],
    "wof:name":"Sant'Agata sul Santerno",
    "wof:placetype":"locality",
    "wof:population":2404
},
  "geometry": {"coordinates":[11.86112,44.44351],"type":"Point"}
}