{
  "type": "Feature",
  "properties": {
    "gn:admin1_code":"20",
    "gn:admin2_code":"BL",
    "gn:admin3_code":"25011.0",
    "gn:asciiname":"Toschian",
    "gn:country_code":"IT",
    "gn:dem":462,
    "gn:feature_class":"P",
    "gn:feature_code":"PPL",
    "gn:name":"Toschian",
    "gn:population":120,
    "gn:timezone":"Europe/Rome",
    "iso:country":"IT",
    "wof:name":"Toschian",
    "wof:placetype":"locality",
    "wof:population":120
},
  "geometry": {"coordinates":[11.95675,46.07818],"type":"Point"}
}