{
  "type": "Feature",
  "properties": {
    "gn:admin1_code":"7",
    "gn:admin2_code":"FR",
    "gn:admin3_code":"60004.0",
    "gn:asciiname":"Fontana Paurosa",
    "gn:country_code":"IT",
    "gn:dem":407,
    "gn:feature_class":"P",
    "gn:feature_code":"PPL",
    "gn:name":"Fontana Paurosa",
    "gn:population":35,
    "gn:timezone":"Europe/Rome",
    "iso:country":"IT",
    "wof:name":"Fontana Paurosa",
    "wof:placetype":"locality",
    "wof:population":35
},
  "geometry": {"coordinates":[13.75768,41.66914000000001],"type":"Point"}
}