{
  "type": "Feature",
  "properties": {
    "gn:admin1_code":"7.0",
    "gn:admin2_code":"LT",
    "gn:admin3_code":"59005.0",
    "gn:asciiname":"Sant'Angelo",
    "gn:country_code":"IT",
    "gn:dem":47,
    "gn:feature_class":"P",
    "gn:feature_code":"PPL",
    "gn:name":"Sant'Angelo",
    "gn:population":0,
    "gn:timezone":"Europe/Rome",
    "iso:country":"IT",
    "wof:name":"Sant'Angelo",
    "wof:placetype":"locality"
},
  "geometry": {"coordinates":[12.92627,41.59118],"type":"Point"}
}