{
  "type": "Feature",
  "properties": {
    "gn:gn_country":"IT",
    "gn:gn_fcode":"PPLA3",
    "gn:gn_pop":204,
    "gn:population":42,
    "iso:country":"IT",
    "name:ara_x_preferred":[
        "\u062f\u064a\u0646\u064a\u062a\u0634\u064a"
    ],
    "name:bel_x_preferred":[
        "\u0414\u044d\u043d\u0456\u0447\u044d"
    ],
    "name:bul_x_preferred":[
        "\u0414\u0435\u043d\u0438\u0447\u0435"
    ],
    "name:cat_x_preferred":[
        "Denice"
    ],
    "name:deu_x_preferred":[
        "Denice"
    ],
    "name:eng_x_preferred":[
        "Denice"
    ],
    "name:epo_x_preferred":[
        "Denice"
    ],
    "name:est_x_preferred":[
        "Denice"
    ],
    "name:eus_x_preferred":[
        "Denice"
    ],
    "name:fas_x_preferred":[
        "\u062f\u0646\u06cc\u0686\u0647"
    ],
    "name:fra_x_preferred":[
        "Denice"
    ],
    "name:hun_x_preferred":[
        "Denice"
    ],
    "name:hye_x_preferred":[
        "\u0534\u0565\u0576\u056b\u0579\u0565"
    ],
    "name:ind_x_preferred":[
        "Denice"
    ],
    "name:ita_x_preferred":[
        "Denice"
    ],
    "name:jpn_x_preferred":[
        "\u30c7\u30fc\u30cb\u30c1\u30a7"
    ],
    "name:kaz_x_preferred":[
        "\u0414\u0435\u043d\u0438\u0447\u0435"
    ],
    "name:lat_x_preferred":[
        "Denice"
    ],
    "name:lmo_x_preferred":[
        "Denice"
    ],
    "name:msa_x_preferred":[
        "Denice"
    ],
    "name:nan_x_preferred":[
        "Denice"
    ],
    "name:nap_x_preferred":[
        "Denice"
    ],
    "name:nld_x_preferred":[
        "Denice"
    ],
    "name:oci_x_preferred":[
        "Denice"
    ],
    "name:pms_x_preferred":[
        "Dens"
    ],
    "name:pol_x_preferred":[
        "Denice"
    ],
    "name:por_x_preferred":[
        "Denice"
    ],
    "name:ron_x_preferred":[
        "Denice"
    ],
    "name:rus_x_preferred":[
        "\u0414\u0435\u043d\u0438\u0447\u0435"
    ],
    "name:scn_x_preferred":[
        "Denice"
    ],
    "name:spa_x_preferred":[
        "Denice"
    ],
    "name:srp_x_preferred":[
        "Denice"
    ],
    "name:tgl_x_preferred":[
        "Denice"
    ],
    "name:ukr_x_preferred":[
        "\u0414\u0435\u043d\u0456\u0447\u0435"
    ],
    "name:uzb_x_preferred":[
        "Denice"
    ],
    "name:vie_x_preferred":[
        "Denice"
    ],
    "name:vol_x_preferred":[
        "Denice"
    ],
    "name:war_x_preferred":[
        "Denice"
    ],
    "name:zho_x_preferred":[
        "\u5fb7\u5c3c\u5207"
    ],
    "qs_pg:aaroncc":"IT",
    "qs_pg:gn_country":"IT",
    "qs_pg:gn_fcode":"PPLA3",
    "qs_pg:gn_pop":204,
    "qs_pg:name":"Denice",
    "qs_pg:name_adm0":"Italia",
    "qs_pg:name_adm1":"Piemonte",
    "qs_pg:photos_9k":1,
    "qs_pg:photos_9r":1,
    "qs_pg:photos_all":1,
    "qs_pg:photos_sr":0,
    "qs_pg:pop_sr":2,
    "qs_pg:qs_pg_placetype":"locality",
    "qs_pg:qs_pg_placetype_gp":"Town",
    "qs_pg:woe_adm0":23424853,
    "woe:adm0_id":23424853,
    "woe:name_adm0":"Italia",
    "woe:name_adm1":"Piemonte",
    "woe:placetype":"Town",
    "wof:name":"Denice",
    "wof:placetype":"locality",
    "wof:population":42
},
  "geometry": {"coordinates":[8.33314,44.59884],"type":"Point"}
}