{
  "type": "Feature",
  "properties": {
    "gn:admin1_code":"20",
    "gn:admin2_code":"TV",
    "gn:admin3_code":"26027.0",
    "gn:asciiname":"Sottoriva",
    "gn:country_code":"IT",
    "gn:dem":175,
    "gn:feature_class":"P",
    "gn:feature_code":"PPL",
    "gn:name":"Sottoriva",
    "gn:population":28,
    "gn:timezone":"Europe/Rome",
    "iso:country":"IT",
    "wof:name":"Sottoriva",
    "wof:placetype":"locality",
    "wof:population":28
},
  "geometry": {"coordinates":[12.13024,45.94201],"type":"Point"}
}