{
  "type": "Feature",
  "properties": {
    "gn:admin1_code":"4",
    "gn:admin2_code":"SA",
    "gn:admin3_code":"65136.0",
    "gn:asciiname":"Bagno",
    "gn:country_code":"IT",
    "gn:dem":467,
    "gn:feature_class":"P",
    "gn:feature_code":"PPL",
    "gn:name":"Bagno",
    "gn:population":77,
    "gn:timezone":"Europe/Rome",
    "iso:country":"IT",
    "name:ceb_x_preferred":[
        "Bagno"
    ],
    "name:deu_x_preferred":[
        "Bagno"
    ],
    "name:fra_x_preferred":[
        "Bagno"
    ],
    "name:ita_x_preferred":[
        "Bagno"
    ],
    "name:lit_x_preferred":[
        "Bagnas"
    ],
    "name:pol_x_preferred":[
        "Bagno"
    ],
    "name:rus_x_preferred":[
        "\u0411\u0430\u043d\u044c\u043e"
    ],
    "name:srp_x_preferred":[
        "Bagno"
    ],
    "name:swe_x_preferred":[
        "Bagno"
    ],
    "name:ukr_x_preferred":[
        "\u0411\u0430\u043d\u044c\u043e"
    ],
    "wof:name":"Bagno",
    "wof:placetype":"locality",
    "wof:population":77
},
  "geometry": {"coordinates":[15.61576,40.32258],"type":"Point"}
}