{
  "type": "Feature",
  "properties": {
    "gn:admin1_code":"7",
    "gn:admin2_code":"FR",
    "gn:admin3_code":"60046.0",
    "gn:asciiname":"Ponti-La Selva",
    "gn:country_code":"IT",
    "gn:dem":265,
    "gn:feature_class":"P",
    "gn:feature_code":"PPLL",
    "gn:name":"Ponti-La Selva",
    "gn:population":7,
    "gn:timezone":"Europe/Rome",
    "iso:country":"IT",
    "wof:name":"Ponti-La Selva",
    "wof:placetype":"locality",
    "wof:population":7
},
  "geometry": {"coordinates":[13.03273,41.78105],"type":"Point"}
}