{
  "type": "Feature",
  "properties": {
    "gn:admin1_code":"1.0",
    "gn:admin2_code":"PE",
    "gn:admin3_code":"68012.0",
    "gn:asciiname":"San Martino Bassa",
    "gn:country_code":"IT",
    "gn:dem":29,
    "gn:feature_class":"P",
    "gn:feature_code":"PPL",
    "gn:name":"San Martino Bassa",
    "gn:population":4678,
    "gn:timezone":"Europe/Rome",
    "iso:country":"IT",
    "wof:name":"San Martino Bassa",
    "wof:placetype":"locality",
    "wof:population":4678
},
  "geometry": {"coordinates":[14.13045,42.51827],"type":"Point"}
}