{
  "type": "Feature",
  "properties": {
    "gn:admin1_code":"20.0",
    "gn:admin2_code":"BL",
    "gn:admin3_code":"25030.0",
    "gn:asciiname":"Livine",
    "gn:country_code":"IT",
    "gn:dem":1481,
    "gn:feature_class":"P",
    "gn:feature_code":"PPL",
    "gn:name":"Livin\u00e8",
    "gn:population":43,
    "gn:timezone":"Europe/Rome",
    "iso:country":"IT",
    "name:und_x_variant":[
        "Livin\u00e8"
    ],
    "wof:name":"Livine",
    "wof:placetype":"locality",
    "wof:population":43
},
  "geometry": {"coordinates":[11.94006,46.48906],"type":"Point"}
}