{
  "type": "Feature",
  "properties": {
    "gn:admin1_code":"12.0",
    "gn:admin2_code":"VC",
    "gn:admin3_code":"2148.0",
    "gn:asciiname":"Localita Produttiva IV",
    "gn:country_code":"IT",
    "gn:dem":132,
    "gn:feature_class":"P",
    "gn:feature_code":"PPL",
    "gn:name":"Localit\u00e0 Produttiva IV",
    "gn:population":0,
    "gn:timezone":"Europe/Rome",
    "iso:country":"IT",
    "name:und_x_variant":[
        "Localit\u00e0 Produttiva IV"
    ],
    "wof:name":"Localita Produttiva IV",
    "wof:placetype":"locality"
},
  "geometry": {"coordinates":[8.30806,45.18719],"type":"Point"}
}