{
  "type": "Feature",
  "properties": {
    "gn:admin1_code":"3.0",
    "gn:admin2_code":"CS",
    "gn:admin3_code":"78079.0",
    "gn:asciiname":"Tivolille Pasquali-Merenzata",
    "gn:country_code":"IT",
    "gn:dem":422,
    "gn:feature_class":"P",
    "gn:feature_code":"PPL",
    "gn:name":"Tivolille Pasquali-Merenzata",
    "gn:population":4381,
    "gn:timezone":"Europe/Rome",
    "iso:country":"IT",
    "wof:name":"Tivolille Pasquali-Merenzata",
    "wof:placetype":"locality",
    "wof:population":4381
},
  "geometry": {"coordinates":[16.20738,39.27953],"type":"Point"}
}