{
  "type": "Feature",
  "properties": {
    "gn:admin1_code":"15.0",
    "gn:admin2_code":"ME",
    "gn:admin3_code":"83010.0",
    "gn:asciiname":"Rocca di Capri Leone",
    "gn:cc2":"IT",
    "gn:country_code":"IT",
    "gn:dem":44,
    "gn:feature_class":"P",
    "gn:feature_code":"PPL",
    "gn:name":"Rocca di Capri Leone",
    "gn:population":4248,
    "gn:timezone":"Europe/Rome",
    "iso:country":"IT",
    "name:und_x_variant":[
        "Rocca di Caprileone",
        "La Rocca"
    ],
    "wof:name":"Rocca di Capri Leone",
    "wof:placetype":"locality",
    "wof:population":4248
},
  "geometry": {"coordinates":[14.71032,38.10677],"type":"Point"}
}