{
  "type": "Feature",
  "properties": {
    "gn:elevation":675,
    "gn:population":208,
    "iso:country":"IT",
    "name:arm_x_preferred":[
        "\u053c\u056b\u057e\u0578"
    ],
    "name:baq_x_preferred":[
        "Livo"
    ],
    "name:cat_x_preferred":[
        "Livo"
    ],
    "name:dut_x_preferred":[
        "Livo"
    ],
    "name:eng_x_preferred":[
        "Livo"
    ],
    "name:epo_x_preferred":[
        "Livo"
    ],
    "name:fra_x_preferred":[
        "Livo"
    ],
    "name:fre_x_preferred":[
        "Livo"
    ],
    "name:ger_x_preferred":[
        "Livo"
    ],
    "name:hun_x_preferred":[
        "Livo"
    ],
    "name:ita_x_preferred":[
        "Livo"
    ],
    "name:jpn_x_preferred":[
        "\u30ea\u30fc\u30f4\u30a9"
    ],
    "name:kaz_x_preferred":[
        "\u041b\u0438\u0432\u043e"
    ],
    "name:kor_x_preferred":[
        "\ub9ac\ubcf4"
    ],
    "name:lat_x_preferred":[
        "Livum"
    ],
    "name:lmo_x_preferred":[
        "Liv"
    ],
    "name:may_x_preferred":[
        "Livo"
    ],
    "name:nap_x_preferred":[
        "Livo"
    ],
    "name:oci_x_preferred":[
        "Livo"
    ],
    "name:pms_x_preferred":[
        "Livo"
    ],
    "name:por_x_preferred":[
        "Livo"
    ],
    "name:rum_x_preferred":[
        "Livo"
    ],
    "name:rus_x_preferred":[
        "\u041b\u0438\u0432\u043e"
    ],
    "name:scn_x_preferred":[
        "Livo"
    ],
    "name:spa_x_preferred":[
        "Livo"
    ],
    "name:srp_x_preferred":[
        "Livo"
    ],
    "name:tgl_x_preferred":[
        "Livo"
    ],
    "name:ukr_x_preferred":[
        "\u041b\u0456\u0432\u043e"
    ],
    "name:uzb_x_preferred":[
        "Livo"
    ],
    "name:vie_x_preferred":[
        "Livo"
    ],
    "name:war_x_preferred":[
        "Livo"
    ],
    "qs:a0":"Italia",
    "qs:a1":"*Como",
    "qs:a1r":"0Lombardia",
    "qs:adm0":"Italia",
    "qs:la_lc":"*",
    "qs:level":"locality",
    "qs:loc":"Livo",
    "qs:loc_alt":"Livo",
    "qs:pop":0,
    "qs:type":"buffered point",
    "wd:wordcount":40,
    "wof:lang":[
        "ita"
    ],
    "wof:name":"Livo",
    "wof:placetype":"locality",
    "wof:population":208
},
  "geometry": {"coordinates":[9.305,46.16917],"type":"Point"}
}