{
  "type": "Feature",
  "properties": {
    "gn:admin1_code":"1",
    "gn:admin2_code":"AQ",
    "gn:admin3_code":"66002.0",
    "gn:asciiname":"Localita Produttiva Via Tiburtina",
    "gn:country_code":"IT",
    "gn:dem":692,
    "gn:feature_class":"P",
    "gn:feature_code":"PPL",
    "gn:name":"Localit\u00e0 Produttiva Via Tiburtina",
    "gn:population":73,
    "gn:timezone":"Europe/Rome",
    "iso:country":"IT",
    "name:und_x_variant":[
        "Localit\u00e0 Produttiva Via Tiburtina"
    ],
    "wof:name":"Localita Produttiva Via Tiburtina",
    "wof:placetype":"locality",
    "wof:population":73
},
  "geometry": {"coordinates":[13.56354,42.05733],"type":"Point"}
}