{
  "type": "Feature",
  "properties": {
    "gn:admin1_code":"7.0",
    "gn:admin2_code":"VT",
    "gn:admin3_code":"56014.0",
    "gn:asciiname":"Capranica-Scalo",
    "gn:country_code":"IT",
    "gn:dem":404,
    "gn:feature_class":"P",
    "gn:feature_code":"PPL",
    "gn:name":"Capranica-Scalo",
    "gn:population":314,
    "gn:timezone":"Europe/Rome",
    "iso:country":"IT",
    "wof:name":"Capranica-Scalo",
    "wof:placetype":"locality",
    "wof:population":314
},
  "geometry": {"coordinates":[12.15862,42.24784],"type":"Point"}
}