{
  "type": "Feature",
  "properties": {
    "gn:admin1_code":"12",
    "gn:admin2_code":"BI",
    "gn:admin3_code":"96042.0",
    "gn:asciiname":"Calunnia",
    "gn:country_code":"IT",
    "gn:dem":642,
    "gn:feature_class":"P",
    "gn:feature_code":"PPL",
    "gn:name":"Calunnia",
    "gn:population":13,
    "gn:timezone":"Europe/Rome",
    "iso:country":"IT",
    "name:ita_x_preferred":[
        "Calunnia"
    ],
    "wof:name":"Calunnia",
    "wof:placetype":"locality",
    "wof:population":13
},
  "geometry": {"coordinates":[8.07673,45.60385],"type":"Point"}
}