{
  "type": "Feature",
  "properties": {
    "gn:admin1_code":"12.0",
    "gn:admin2_code":"TO",
    "gn:admin3_code":"1186.0",
    "gn:asciiname":"Clot",
    "gn:country_code":"IT",
    "gn:dem":1013,
    "gn:feature_class":"P",
    "gn:feature_code":"PPL",
    "gn:name":"Clot",
    "gn:population":3,
    "gn:timezone":"Europe/Rome",
    "iso:country":"IT",
    "wof:name":"Clot",
    "wof:placetype":"locality",
    "wof:population":3
},
  "geometry": {"coordinates":[7.12537,44.92615],"type":"Point"}
}