{
  "type": "Feature",
  "properties": {
    "gn:admin1_code":"7",
    "gn:admin2_code":"LT",
    "gn:admin3_code":"59011.0",
    "gn:asciiname":"Macchia di San Giovanni",
    "gn:country_code":"IT",
    "gn:dem":45,
    "gn:feature_class":"P",
    "gn:feature_code":"PPL",
    "gn:name":"Macchia di San Giovanni",
    "gn:population":222,
    "gn:timezone":"Europe/Rome",
    "iso:country":"IT",
    "wof:name":"Macchia di San Giovanni",
    "wof:placetype":"locality",
    "wof:population":222
},
  "geometry": {"coordinates":[12.77524,41.54247],"type":"Point"}
}