{
  "type": "Feature",
  "properties": {
    "gn:admin1_code":"12",
    "gn:admin2_code":"NO",
    "gn:admin3_code":"3088.0",
    "gn:asciiname":"Fornaci",
    "gn:country_code":"IT",
    "gn:dem":343,
    "gn:feature_class":"P",
    "gn:feature_code":"PPL",
    "gn:name":"Fornaci",
    "gn:population":31,
    "gn:timezone":"Europe/Rome",
    "iso:country":"IT",
    "wof:name":"Fornaci",
    "wof:placetype":"locality",
    "wof:population":31
},
  "geometry": {"coordinates":[8.41748,45.69872],"type":"Point"}
}