{
  "type": "Feature",
  "properties": {
    "gn:admin1_code":"15",
    "gn:admin2_code":"AG",
    "gn:admin3_code":"84001.0",
    "gn:asciiname":"Gibisa",
    "gn:country_code":"IT",
    "gn:dem":58,
    "gn:feature_class":"P",
    "gn:feature_code":"PPL",
    "gn:name":"Gibisa",
    "gn:population":12,
    "gn:timezone":"Europe/Rome",
    "iso:country":"IT",
    "wof:name":"Gibisa",
    "wof:placetype":"locality",
    "wof:population":12
},
  "geometry": {"coordinates":[13.6575,37.25479],"type":"Point"}
}