{
  "type": "Feature",
  "properties": {
    "gn:admin1_code":"9",
    "gn:admin2_code":"CR",
    "gn:admin3_code":"19008.0",
    "gn:asciiname":"Casanova d'Offredi",
    "gn:country_code":"IT",
    "gn:dem":31,
    "gn:feature_class":"P",
    "gn:feature_code":"PPL",
    "gn:name":"Casanova d'Offredi",
    "gn:population":93,
    "gn:timezone":"Europe/Rome",
    "iso:country":"IT",
    "wof:name":"Casanova d'Offredi",
    "wof:placetype":"locality",
    "wof:population":93
},
  "geometry": {"coordinates":[10.28898,45.1057],"type":"Point"}
}