{
  "type": "Feature",
  "properties": {
    "gn:admin1_code":"3",
    "gn:admin2_code":"CZ",
    "gn:admin3_code":"79127.0",
    "gn:asciiname":"Pirainetto",
    "gn:country_code":"IT",
    "gn:dem":35,
    "gn:feature_class":"P",
    "gn:feature_code":"PPL",
    "gn:name":"Pirainetto",
    "gn:population":101,
    "gn:timezone":"Europe/Rome",
    "iso:country":"IT",
    "wof:name":"Pirainetto",
    "wof:placetype":"locality",
    "wof:population":101
},
  "geometry": {"coordinates":[16.72954,38.90645],"type":"Point"}
}