{
  "type": "Feature",
  "properties": {
    "gn:admin1_code":"16",
    "gn:admin2_code":"LU",
    "gn:admin3_code":"46004.0",
    "gn:asciiname":"Salita",
    "gn:country_code":"IT",
    "gn:dem":126,
    "gn:feature_class":"P",
    "gn:feature_code":"PPL",
    "gn:name":"Salita",
    "gn:population":81,
    "gn:timezone":"Europe/Rome",
    "iso:country":"IT",
    "wof:name":"Salita",
    "wof:placetype":"locality",
    "wof:population":81
},
  "geometry": {"coordinates":[10.52748,44.01754],"type":"Point"}
}