{
  "type": "Feature",
  "properties": {
    "iso:country":"IT",
    "name:ceb_x_preferred":[
        "Ponte Nuovo"
    ],
    "name:srp_x_preferred":[
        "\u041f\u043e\u043d\u0442\u0435 \u041d\u0443\u043e\u0432\u043e"
    ],
    "qs_pg:aaroncc":"IT",
    "qs_pg:name":"Ponte Nuovo",
    "qs_pg:name_adm0":"Italia",
    "qs_pg:name_adm1":"Campania",
    "qs_pg:photos":25,
    "qs_pg:photos_1k":5,
    "qs_pg:photos_9k":1,
    "qs_pg:photos_9r":1,
    "qs_pg:photos_all":25,
    "qs_pg:photos_sr":1,
    "qs_pg:pop_sr":0,
    "qs_pg:qs_pg_placetype":"locality",
    "qs_pg:qs_pg_placetype_gp":"Town",
    "qs_pg:woe_adm0":23424853,
    "woe:adm0_id":23424853,
    "woe:name_adm0":"Italia",
    "woe:name_adm1":"Campania",
    "woe:placetype":"Town",
    "wof:name":"Ponte Nuovo",
    "wof:placetype":"locality"
},
  "geometry": {"coordinates":[14.488359,40.748374],"type":"Point"}
}