{
  "type": "Feature",
  "properties": {
    "gn:admin1_code":"5.0",
    "gn:admin2_code":"MO",
    "gn:admin3_code":"36017.0",
    "gn:asciiname":"Monte Orsello",
    "gn:country_code":"IT",
    "gn:dem":397,
    "gn:feature_class":"P",
    "gn:feature_code":"PPL",
    "gn:name":"Monte Orsello",
    "gn:population":126,
    "gn:timezone":"Europe/Rome",
    "iso:country":"IT",
    "wof:name":"Monte Orsello",
    "wof:placetype":"locality",
    "wof:population":126
},
  "geometry": {"coordinates":[10.96667,44.41667],"type":"Point"}
}