{
  "type": "Feature",
  "properties": {
    "gn:admin1_code":"10",
    "gn:admin2_code":"AN",
    "gn:admin3_code":"42044.0",
    "gn:asciiname":"Sementana",
    "gn:country_code":"IT",
    "gn:dem":545,
    "gn:feature_class":"P",
    "gn:feature_code":"PPL",
    "gn:name":"Sementana",
    "gn:population":14,
    "gn:timezone":"Europe/Rome",
    "iso:country":"IT",
    "wof:name":"Sementana",
    "wof:placetype":"locality",
    "wof:population":14
},
  "geometry": {"coordinates":[12.84363,43.50096],"type":"Point"}
}