{
  "type": "Feature",
  "properties": {
    "gn:admin1_code":"5",
    "gn:admin2_code":"PC",
    "gn:admin3_code":"33022.0",
    "gn:asciiname":"Lisignano",
    "gn:country_code":"IT",
    "gn:dem":149,
    "gn:feature_class":"P",
    "gn:feature_code":"PPL",
    "gn:name":"Lisignano",
    "gn:population":20,
    "gn:timezone":"Europe/Rome",
    "iso:country":"IT",
    "wof:name":"Lisignano",
    "wof:placetype":"locality",
    "wof:population":20
},
  "geometry": {"coordinates":[9.53557,44.9502],"type":"Point"}
}