{
  "type": "Feature",
  "properties": {
    "gn:admin1_code":"12",
    "gn:admin2_code":"AT",
    "gn:admin3_code":"5017.0",
    "gn:asciiname":"Fello",
    "gn:country_code":"IT",
    "gn:dem":282,
    "gn:feature_class":"P",
    "gn:feature_code":"PPL",
    "gn:name":"Fello",
    "gn:population":15,
    "gn:timezone":"Europe/Rome",
    "iso:country":"IT",
    "wof:name":"Fello",
    "wof:placetype":"locality",
    "wof:population":15
},
  "geometry": {"coordinates":[8.28072,44.70095],"type":"Point"}
}