{
  "type": "Feature",
  "properties": {
    "gn:admin1_code":"20",
    "gn:admin2_code":"TV",
    "gn:admin3_code":"26077.0",
    "gn:asciiname":"Le Valli",
    "gn:country_code":"IT",
    "gn:dem":119,
    "gn:feature_class":"P",
    "gn:feature_code":"PPL",
    "gn:name":"Le Valli",
    "gn:population":21,
    "gn:timezone":"Europe/Rome",
    "iso:country":"IT",
    "wof:name":"Le Valli",
    "wof:placetype":"locality",
    "wof:population":21
},
  "geometry": {"coordinates":[11.84988,45.78791],"type":"Point"}
}