{
  "type": "Feature",
  "properties": {
    "gn:admin1_code":"1.0",
    "gn:admin2_code":"AQ",
    "gn:admin3_code":"66052.0",
    "gn:asciiname":"Vado Lucoli",
    "gn:country_code":"IT",
    "gn:dem":1129,
    "gn:elevation":"1111.0",
    "gn:feature_class":"P",
    "gn:feature_code":"PPL",
    "gn:name":"Vado Lucoli",
    "gn:population":9,
    "gn:timezone":"Europe/Rome",
    "iso:country":"IT",
    "wof:name":"Vado Lucoli",
    "wof:placetype":"locality",
    "wof:population":9
},
  "geometry": {"coordinates":[13.34809,42.29234],"type":"Point"}
}