{
  "type": "Feature",
  "properties": {
    "gn:admin1_code":"6",
    "gn:admin2_code":"PN",
    "gn:admin3_code":"93049.0",
    "gn:asciiname":"Valentins",
    "gn:country_code":"IT",
    "gn:dem":357,
    "gn:feature_class":"P",
    "gn:feature_code":"PPL",
    "gn:name":"Valentins",
    "gn:population":30,
    "gn:timezone":"Europe/Rome",
    "iso:country":"IT",
    "wof:name":"Valentins",
    "wof:placetype":"locality",
    "wof:population":30
},
  "geometry": {"coordinates":[12.92922,46.3047],"type":"Point"}
}