{
  "type": "Feature",
  "properties": {
    "gn:admin1_code":"5.0",
    "gn:admin2_code":"MO",
    "gn:admin3_code":"36012.0",
    "gn:asciiname":"Vallacquosa",
    "gn:country_code":"IT",
    "gn:dem":6,
    "gn:feature_class":"P",
    "gn:feature_code":"PPL",
    "gn:name":"Vallacquosa",
    "gn:population":0,
    "gn:timezone":"Europe/Rome",
    "iso:country":"IT",
    "wof:name":"Vallacquosa",
    "wof:placetype":"locality"
},
  "geometry": {"coordinates":[11.23333,44.88333],"type":"Point"}
}