{
  "type": "Feature",
  "properties": {
    "gn:admin1_code":"10.0",
    "gn:admin2_code":"AP",
    "gn:admin3_code":"44007.0",
    "gn:asciiname":"Ponte Pedana",
    "gn:country_code":"IT",
    "gn:dem":238,
    "gn:feature_class":"P",
    "gn:feature_code":"PPL",
    "gn:name":"Ponte Pedana",
    "gn:population":24,
    "gn:timezone":"Europe/Rome",
    "iso:country":"IT",
    "wof:name":"Ponte Pedana",
    "wof:placetype":"locality",
    "wof:population":24
},
  "geometry": {"coordinates":[13.49571,42.80984],"type":"Point"}
}