{
  "type": "Feature",
  "properties": {
    "gn:admin1_code":"7.0",
    "gn:admin2_code":"RM",
    "gn:admin3_code":"58075.0",
    "gn:asciiname":"Stazzano",
    "gn:cc2":"IT",
    "gn:country_code":"IT",
    "gn:dem":270,
    "gn:elevation":"277.0",
    "gn:feature_class":"P",
    "gn:feature_code":"PPL",
    "gn:name":"Stazzano",
    "gn:population":251,
    "gn:timezone":"Europe/Rome",
    "iso:country":"IT",
    "name:ara_x_preferred":[
        "\u0633\u062a\u0627\u062a\u0633\u0627\u0646\u0648"
    ],
    "name:azb_x_preferred":[
        "\u0627\u0633\u062a\u0627\u062a\u0632\u0627\u0646\u0648"
    ],
    "name:bel_x_preferred":[
        "\u0421\u0442\u0430\u0446\u0446\u0430\u043d\u0430"
    ],
    "name:bul_x_preferred":[
        "\u0421\u0442\u0430\u0446\u0430\u043d\u043e"
    ],
    "name:cat_x_preferred":[
        "Stazzano"
    ],
    "name:ceb_x_preferred":[
        "Stazzano"
    ],
    "name:deu_x_preferred":[
        "Stazzano"
    ],
    "name:epo_x_preferred":[
        "Stazzano"
    ],
    "name:eus_x_preferred":[
        "Stazzano"
    ],
    "name:fas_x_preferred":[
        "\u0627\u0633\u062a\u0627\u062a\u0632\u0627\u0646\u0648"
    ],
    "name:fra_x_preferred":[
        "Stazzano"
    ],
    "name:hun_x_preferred":[
        "Stazzano"
    ],
    "name:hye_x_preferred":[
        "\u054d\u057f\u0561\u0581\u0561\u0576\u0578"
    ],
    "name:ind_x_preferred":[
        "Stazzano"
    ],
    "name:ita_x_preferred":[
        "Stazzano"
    ],
    "name:jpn_x_preferred":[
        "\u30b9\u30bf\u30c3\u30c4\u30a1\u30fc\u30ce"
    ],
    "name:kaz_x_preferred":[
        "\u0421\u0442\u0430\u0446\u0446\u0430\u043d\u043e"
    ],
    "name:lat_x_preferred":[
        "Statianum"
    ],
    "name:lij_x_preferred":[
        "Stassan"
    ],
    "name:lmo_x_preferred":[
        "Stazzano"
    ],
    "name:msa_x_preferred":[
        "Stazzano"
    ],
    "name:nap_x_preferred":[
        "Stazzano"
    ],
    "name:nld_x_preferred":[
        "Stazzano"
    ],
    "name:pms_x_preferred":[
        "Stassan"
    ],
    "name:pol_x_preferred":[
        "Stazzano"
    ],
    "name:por_x_preferred":[
        "Stazzano"
    ],
    "name:ron_x_preferred":[
        "Stazzano"
    ],
    "name:rus_x_preferred":[
        "\u0421\u0442\u0430\u0446\u0446\u0430\u043d\u043e"
    ],
    "name:scn_x_preferred":[
        "Stazzano"
    ],
    "name:spa_x_preferred":[
        "Stazzano"
    ],
    "name:srp_x_preferred":[
        "\u0421\u0442\u0430\u0446\u0430\u043d\u043e"
    ],
    "name:tgl_x_preferred":[
        "Stazzano"
    ],
    "name:tur_x_preferred":[
        "Stazzano"
    ],
    "name:ukr_x_preferred":[
        "\u0421\u0442\u0430\u0446\u0446\u0430\u043d\u043e"
    ],
    "name:und_x_variant":[
        "Stazzano Nuovo"
    ],
    "name:uzb_x_preferred":[
        "Stazzano"
    ],
    "name:vie_x_preferred":[
        "Stazzano"
    ],
    "name:vol_x_preferred":[
        "Stazzano"
    ],
    "name:war_x_preferred":[
        "Stazzano"
    ],
    "name:zho_x_preferred":[
        "\u65af\u5854\u624e\u8bfa"
    ],
    "wof:name":"Stazzano",
    "wof:placetype":"locality",
    "wof:population":251
},
  "geometry": {"coordinates":[12.77306,42.0913],"type":"Point"}
}