{
  "type": "Feature",
  "properties": {
    "gn:admin1_code":"7.0",
    "gn:admin2_code":"RM",
    "gn:admin3_code":"58075.0",
    "gn:asciiname":"Stazzano",
    "gn:cc2":"IT",
    "gn:country_code":"IT",
    "gn:dem":270,
    "gn:elevation":"277.0",
    "gn:feature_class":"P",
    "gn:feature_code":"PPL",
    "gn:name":"Stazzano",
    "gn:population":251,
    "gn:timezone":"Europe/Rome",
    "iso:country":"IT",
    "name:und_x_variant":[
        "Stazzano Nuovo"
    ],
    "wof:name":"Stazzano",
    "wof:placetype":"locality",
    "wof:population":251
},
  "geometry": {"coordinates":[12.77306,42.0913],"type":"Point"}
}