{
  "type": "Feature",
  "properties": {
    "gn:admin1_code":"20",
    "gn:admin2_code":"PD",
    "gn:admin3_code":"28090.0",
    "gn:asciiname":"Madonna",
    "gn:country_code":"IT",
    "gn:dem":1,
    "gn:feature_class":"P",
    "gn:feature_code":"PPL",
    "gn:name":"Madonna",
    "gn:population":56,
    "gn:timezone":"Europe/Rome",
    "iso:country":"IT",
    "wof:name":"Madonna",
    "wof:placetype":"locality",
    "wof:population":56
},
  "geometry": {"coordinates":[11.91114,45.25133],"type":"Point"}
}