{
  "type": "Feature",
  "properties": {
    "gn:admin1_code":"20",
    "gn:admin2_code":"PD",
    "gn:admin3_code":"28090.0",
    "gn:asciiname":"Madonna",
    "gn:country_code":"IT",
    "gn:dem":1,
    "gn:feature_class":"P",
    "gn:feature_code":"PPL",
    "gn:name":"Madonna",
    "gn:population":56,
    "gn:timezone":"Europe/Rome",
    "iso:country":"IT",
    "name:ara_x_preferred":[
        "\u0645\u0627\u062f\u0648\u0646\u0627"
    ],
    "name:bel_x_preferred":[
        "\u041c\u0430\u0434\u043e\u043d\u043d\u0430"
    ],
    "name:bre_x_preferred":[
        "Madonna"
    ],
    "name:ceb_x_preferred":[
        "Madonna"
    ],
    "name:ces_x_preferred":[
        "Madonna"
    ],
    "name:cym_x_preferred":[
        "Madonna"
    ],
    "name:dan_x_preferred":[
        "Madonna"
    ],
    "name:deu_x_preferred":[
        "Madonna"
    ],
    "name:eml_x_preferred":[
        "Madonna"
    ],
    "name:eus_x_preferred":[
        "Madonna"
    ],
    "name:fas_x_preferred":[
        "\u0645\u062f\u0648\u0646\u0627"
    ],
    "name:fin_x_preferred":[
        "Madonna"
    ],
    "name:fra_x_preferred":[
        "Madonna"
    ],
    "name:heb_x_preferred":[
        "\u05de\u05d3\u05d5\u05e0\u05d4"
    ],
    "name:hun_x_preferred":[
        "Madonna"
    ],
    "name:ind_x_preferred":[
        "Madonna"
    ],
    "name:ita_x_preferred":[
        "Madonna"
    ],
    "name:jpn_x_preferred":[
        "\u30de\u30c9\u30f3\u30ca"
    ],
    "name:kor_x_preferred":[
        "\ub9c8\ub3c8\ub098"
    ],
    "name:lav_x_preferred":[
        "Madonna"
    ],
    "name:ltz_x_preferred":[
        "Madonna"
    ],
    "name:mal_x_preferred":[
        "\u0d2e\u0d21\u0d4b\u0d23"
    ],
    "name:nld_x_preferred":[
        "Madonna"
    ],
    "name:nno_x_preferred":[
        "Madonna"
    ],
    "name:nor_x_preferred":[
        "Madonna"
    ],
    "name:pol_x_preferred":[
        "Madonna"
    ],
    "name:por_x_preferred":[
        "Madonna"
    ],
    "name:rus_x_preferred":[
        "\u041c\u0430\u0434\u043e\u043d\u043d\u0430"
    ],
    "name:scn_x_preferred":[
        "Madonna"
    ],
    "name:slk_x_preferred":[
        "Madonna"
    ],
    "name:slv_x_preferred":[
        "Madonna"
    ],
    "name:spa_x_preferred":[
        "Madonna"
    ],
    "name:srp_x_preferred":[
        "\u041c\u0430\u0434\u043e\u043d\u0430"
    ],
    "name:swa_x_preferred":[
        "Madonna"
    ],
    "name:swe_x_preferred":[
        "Madonna"
    ],
    "name:tur_x_preferred":[
        "Madonna"
    ],
    "name:ukr_x_preferred":[
        "\u041c\u0430\u0434\u043e\u043d\u043d\u0430"
    ],
    "name:uzb_x_preferred":[
        "Madonna"
    ],
    "name:vie_x_preferred":[
        "Madonna"
    ],
    "name:vls_x_preferred":[
        "Madonna"
    ],
    "name:zho_x_preferred":[
        "Madonna"
    ],
    "wof:name":"Madonna",
    "wof:placetype":"locality",
    "wof:population":56
},
  "geometry": {"coordinates":[11.91114,45.25133],"type":"Point"}
}