{
  "type": "Feature",
  "properties": {
    "iso:country":"IT",
    "qs:a0":"Italia",
    "qs:a1":"*Firenze",
    "qs:a1r":"0Toscana",
    "qs:adm0":"Italia",
    "qs:la_lc":"*",
    "qs:level":"locality",
    "qs:loc":"San Jacopo al Girone",
    "qs:loc_alt":"San Jacopo al Girone",
    "qs:pop":0,
    "qs:type":"buffered point",
    "wof:name":"San Jacopo al Girone",
    "wof:placetype":"locality"
},
  "geometry": {"coordinates":[11.338666,43.776327],"type":"Point"}
}