{
  "type": "Feature",
  "properties": {
    "gn:admin1_code":"12",
    "gn:admin2_code":"CN",
    "gn:admin3_code":"4113.0",
    "gn:asciiname":"Cornale",
    "gn:country_code":"IT",
    "gn:dem":148,
    "gn:feature_class":"P",
    "gn:feature_code":"PPL",
    "gn:name":"Cornale",
    "gn:population":97,
    "gn:timezone":"Europe/Rome",
    "iso:country":"IT",
    "wof:name":"Cornale",
    "wof:placetype":"locality",
    "wof:population":97
},
  "geometry": {"coordinates":[8.0823,44.76761],"type":"Point"}
}