{
  "type": "Feature",
  "properties": {
    "gn:admin1_code":"12",
    "gn:admin2_code":"CN",
    "gn:admin3_code":"4113.0",
    "gn:asciiname":"Cornale",
    "gn:country_code":"IT",
    "gn:dem":148,
    "gn:feature_class":"P",
    "gn:feature_code":"PPL",
    "gn:name":"Cornale",
    "gn:population":97,
    "gn:timezone":"Europe/Rome",
    "iso:country":"IT",
    "name:ara_x_preferred":[
        "\u0643\u0648\u0631\u0646\u0627\u0644"
    ],
    "name:azb_x_preferred":[
        "\u06a9\u0648\u0631\u0646\u0627\u0644\u0647"
    ],
    "name:bel_x_preferred":[
        "\u041a\u0430\u0440\u043d\u0430\u043b\u0435"
    ],
    "name:ceb_x_preferred":[
        "Cornale"
    ],
    "name:deu_x_preferred":[
        "Cornale"
    ],
    "name:epo_x_preferred":[
        "Cornale"
    ],
    "name:eus_x_preferred":[
        "Cornale"
    ],
    "name:fas_x_preferred":[
        "\u06a9\u0648\u0631\u0646\u0627\u0644\u0647"
    ],
    "name:fra_x_preferred":[
        "Cornale"
    ],
    "name:hun_x_preferred":[
        "Cornale"
    ],
    "name:hye_x_preferred":[
        "\u053f\u0578\u0580\u0576\u0561\u056c\u0565"
    ],
    "name:ind_x_preferred":[
        "Cornale"
    ],
    "name:ita_x_preferred":[
        "Cornale"
    ],
    "name:jpn_x_preferred":[
        "\u30b3\u30eb\u30ca\u30fc\u30ec"
    ],
    "name:kaz_x_preferred":[
        "\u041a\u043e\u0440\u043d\u0430\u043b\u0435"
    ],
    "name:lat_x_preferred":[
        "Cornale"
    ],
    "name:lmo_x_preferred":[
        "Al Curn\u00e0"
    ],
    "name:msa_x_preferred":[
        "Cornale"
    ],
    "name:nap_x_preferred":[
        "Cornale"
    ],
    "name:nld_x_preferred":[
        "Cornale"
    ],
    "name:pms_x_preferred":[
        "Cornale"
    ],
    "name:pol_x_preferred":[
        "Cornale"
    ],
    "name:por_x_preferred":[
        "Cornale"
    ],
    "name:ron_x_preferred":[
        "Cornale"
    ],
    "name:rus_x_preferred":[
        "\u041a\u043e\u0440\u043d\u0430\u043b\u0435"
    ],
    "name:scn_x_preferred":[
        "Cornale"
    ],
    "name:spa_x_preferred":[
        "Cornale"
    ],
    "name:srp_x_preferred":[
        "\u041a\u043e\u0440\u043d\u0430\u043b\u0435"
    ],
    "name:tgl_x_preferred":[
        "Cornale"
    ],
    "name:ukr_x_preferred":[
        "\u041a\u043e\u0440\u043d\u0430\u043b\u0435"
    ],
    "name:uzb_x_preferred":[
        "Cornale"
    ],
    "name:vie_x_preferred":[
        "Cornale"
    ],
    "name:vol_x_preferred":[
        "Cornale"
    ],
    "name:war_x_preferred":[
        "Cornale"
    ],
    "name:zho_x_preferred":[
        "\u79d1\u5c14\u7eb3\u83b1"
    ],
    "wof:name":"Cornale",
    "wof:placetype":"locality",
    "wof:population":97
},
  "geometry": {"coordinates":[8.0823,44.76761],"type":"Point"}
}