{
  "type": "Feature",
  "properties": {
    "gn:admin1_code":"17",
    "gn:admin2_code":"TN",
    "gn:admin3_code":"22191.0",
    "gn:asciiname":"Piazze",
    "gn:country_code":"IT",
    "gn:dem":223,
    "gn:feature_class":"P",
    "gn:feature_code":"PPL",
    "gn:name":"Piazze",
    "gn:population":18,
    "gn:timezone":"Europe/Rome",
    "iso:country":"IT",
    "wof:name":"Piazze",
    "wof:placetype":"locality",
    "wof:population":18
},
  "geometry": {"coordinates":[10.85133,45.91668],"type":"Point"}
}