{
  "type": "Feature",
  "properties": {
    "gn:admin1_code":"16.0",
    "gn:admin2_code":"FI",
    "gn:admin3_code":"48026.0",
    "gn:asciiname":"Sant'Adriano",
    "gn:country_code":"IT",
    "gn:dem":265,
    "gn:elevation":"260.0",
    "gn:feature_class":"P",
    "gn:feature_code":"PPL",
    "gn:name":"Sant'Adriano",
    "gn:population":211,
    "gn:timezone":"Europe/Rome",
    "iso:country":"IT",
    "wof:name":"Sant'Adriano",
    "wof:placetype":"locality",
    "wof:population":211
},
  "geometry": {"coordinates":[11.65797,44.10283],"type":"Point"}
}