{
  "type": "Feature",
  "properties": {
    "gn:admin1_code":"5",
    "gn:admin2_code":"MO",
    "gn:admin3_code":"36019.0",
    "gn:asciiname":"La Bottega",
    "gn:country_code":"IT",
    "gn:dem":170,
    "gn:feature_class":"P",
    "gn:feature_code":"PPL",
    "gn:name":"La Bottega",
    "gn:population":24,
    "gn:timezone":"Europe/Rome",
    "iso:country":"IT",
    "wof:name":"La Bottega",
    "wof:placetype":"locality",
    "wof:population":24
},
  "geometry": {"coordinates":[10.87771,44.50188],"type":"Point"}
}