{
  "type": "Feature",
  "properties": {
    "gn:admin1_code":"19",
    "gn:admin2_code":"AO",
    "gn:admin3_code":"7038.0",
    "gn:asciiname":"Pompiod",
    "gn:country_code":"IT",
    "gn:dem":649,
    "gn:feature_class":"P",
    "gn:feature_code":"PPL",
    "gn:name":"Pompiod",
    "gn:population":94,
    "gn:timezone":"Europe/Rome",
    "iso:country":"IT",
    "wof:name":"Pompiod",
    "wof:placetype":"locality",
    "wof:population":94
},
  "geometry": {"coordinates":[7.26117,45.70938],"type":"Point"}
}