{
  "type": "Feature",
  "properties": {
    "gn:admin1_code":"5.0",
    "gn:admin2_code":"FC",
    "gn:admin3_code":"40012.0",
    "gn:asciiname":"San Giorgio",
    "gn:country_code":"IT",
    "gn:dem":15,
    "gn:feature_class":"P",
    "gn:feature_code":"PPL",
    "gn:name":"San Giorgio",
    "gn:population":0,
    "gn:timezone":"Europe/Rome",
    "iso:country":"IT",
    "wof:name":"San Giorgio",
    "wof:placetype":"locality"
},
  "geometry": {"coordinates":[12.08083,44.26028],"type":"Point"}
}