{
  "type": "Feature",
  "properties": {
    "gn:admin1_code":"12",
    "gn:admin2_code":"TO",
    "gn:admin3_code":"1115.0",
    "gn:asciiname":"Barola Colpastore",
    "gn:country_code":"IT",
    "gn:dem":480,
    "gn:feature_class":"P",
    "gn:feature_code":"PPL",
    "gn:name":"Barol\u00e0 Colpastore",
    "gn:population":36,
    "gn:timezone":"Europe/Rome",
    "iso:country":"IT",
    "name:und_x_variant":[
        "Barol\u00e0 Colpastore"
    ],
    "wof:name":"Barola Colpastore",
    "wof:placetype":"locality",
    "wof:population":36
},
  "geometry": {"coordinates":[7.37509,45.03648],"type":"Point"}
}