{
  "type": "Feature",
  "properties": {
    "gn:admin1_code":"9.0",
    "gn:admin2_code":"MN",
    "gn:admin3_code":"20039.0",
    "gn:asciiname":"Tabino-Finella",
    "gn:country_code":"IT",
    "gn:dem":16,
    "gn:feature_class":"P",
    "gn:feature_code":"PPL",
    "gn:name":"Tabino-Finella",
    "gn:population":23,
    "gn:timezone":"Europe/Rome",
    "iso:country":"IT",
    "wof:name":"Tabino-Finella",
    "wof:placetype":"locality",
    "wof:population":23
},
  "geometry": {"coordinates":[10.85924,45.00587],"type":"Point"}
}