{
  "type": "Feature",
  "properties": {
    "gn:admin1_code":"15.0",
    "gn:admin2_code":"ME",
    "gn:admin3_code":"83048.0",
    "gn:asciiname":"Altolia",
    "gn:country_code":"IT",
    "gn:dem":294,
    "gn:feature_class":"P",
    "gn:feature_code":"PPL",
    "gn:name":"Altolia",
    "gn:population":354,
    "gn:timezone":"Europe/Rome",
    "iso:country":"IT",
    "name:ceb_x_preferred":[
        "Altolia"
    ],
    "name:fas_x_preferred":[
        "\u0622\u0644\u062a\u0648\u0644\u06cc\u0627"
    ],
    "name:ita_x_preferred":[
        "Altolia"
    ],
    "name:srp_x_preferred":[
        "\u0410\u043b\u0442\u043e\u043b\u0438\u0458\u0430"
    ],
    "wof:name":"Altolia",
    "wof:placetype":"locality",
    "wof:population":354
},
  "geometry": {"coordinates":[15.44603,38.07616],"type":"Point"}
}