{
  "type": "Feature",
  "properties": {
    "gn:admin1_code":"8.0",
    "gn:admin2_code":"IM",
    "gn:admin3_code":"8011.0",
    "gn:asciiname":"Brunetti",
    "gn:country_code":"IT",
    "gn:dem":354,
    "gn:elevation":"326.0",
    "gn:feature_class":"P",
    "gn:feature_code":"PPL",
    "gn:name":"Brunetti",
    "gn:population":25,
    "gn:timezone":"Europe/Rome",
    "iso:country":"IT",
    "wof:name":"Brunetti",
    "wof:placetype":"locality",
    "wof:population":25
},
  "geometry": {"coordinates":[7.60743,43.8409],"type":"Point"}
}