{
  "type": "Feature",
  "properties": {
    "gn:admin1_code":"15",
    "gn:admin2_code":"EN",
    "gn:admin3_code":"86003.0",
    "gn:asciiname":"Cuticchi",
    "gn:country_code":"IT",
    "gn:dem":230,
    "gn:feature_class":"P",
    "gn:feature_code":"PPL",
    "gn:name":"Cuticchi",
    "gn:population":18,
    "gn:timezone":"Europe/Rome",
    "iso:country":"IT",
    "wof:name":"Cuticchi",
    "wof:placetype":"locality",
    "wof:population":18
},
  "geometry": {"coordinates":[14.51691,37.5454],"type":"Point"}
}