{
  "type": "Feature",
  "properties": {
    "gn:admin1_code":"8",
    "gn:admin2_code":"GE",
    "gn:admin3_code":"10012.0",
    "gn:asciiname":"Stabbio",
    "gn:country_code":"IT",
    "gn:dem":404,
    "gn:feature_class":"P",
    "gn:feature_code":"PPL",
    "gn:name":"Stabbio",
    "gn:population":158,
    "gn:timezone":"Europe/Rome",
    "iso:country":"IT",
    "wof:name":"Stabbio",
    "wof:placetype":"locality",
    "wof:population":158
},
  "geometry": {"coordinates":[8.98704,44.54304000000001],"type":"Point"}
}