{
  "type": "Feature",
  "properties": {
    "gn:admin1_code":"5",
    "gn:admin2_code":"FC",
    "gn:admin3_code":"40003.0",
    "gn:asciiname":"Valmorre",
    "gn:country_code":"IT",
    "gn:dem":17,
    "gn:feature_class":"P",
    "gn:feature_code":"PPL",
    "gn:name":"Valmorre",
    "gn:population":32,
    "gn:timezone":"Europe/Rome",
    "iso:country":"IT",
    "wof:name":"Valmorre",
    "wof:placetype":"locality",
    "wof:population":32
},
  "geometry": {"coordinates":[12.1767,44.20806],"type":"Point"}
}