{
  "type": "Feature",
  "properties": {
    "gn:admin1_code":"17.0",
    "gn:admin2_code":"TN",
    "gn:admin3_code":"22139.0",
    "gn:asciiname":"Madrano-Canzolino",
    "gn:country_code":"IT",
    "gn:dem":543,
    "gn:feature_class":"P",
    "gn:feature_code":"PPL",
    "gn:name":"Madrano-Canzolino",
    "gn:population":1113,
    "gn:timezone":"Europe/Rome",
    "iso:country":"IT",
    "wof:name":"Madrano-Canzolino",
    "wof:placetype":"locality",
    "wof:population":1113
},
  "geometry": {"coordinates":[11.21736,46.0844],"type":"Point"}
}