{
  "type": "Feature",
  "properties": {
    "gn:admin1_code":"7",
    "gn:admin2_code":"FR",
    "gn:admin3_code":"60024.0",
    "gn:asciiname":"Sacco",
    "gn:country_code":"IT",
    "gn:dem":128,
    "gn:feature_class":"P",
    "gn:feature_code":"PPL",
    "gn:name":"Sacco",
    "gn:population":33,
    "gn:timezone":"Europe/Rome",
    "iso:country":"IT",
    "wof:name":"Sacco",
    "wof:placetype":"locality",
    "wof:population":33
},
  "geometry": {"coordinates":[13.32571,41.58264000000001],"type":"Point"}
}