{
  "type": "Feature",
  "properties": {
    "gn:admin1_code":"12",
    "gn:admin2_code":"VC",
    "gn:admin3_code":"2158.0",
    "gn:asciiname":"Boarone",
    "gn:country_code":"IT",
    "gn:dem":121,
    "gn:feature_class":"P",
    "gn:feature_code":"PPL",
    "gn:name":"Boarone",
    "gn:population":29,
    "gn:timezone":"Europe/Rome",
    "iso:country":"IT",
    "wof:name":"Boarone",
    "wof:placetype":"locality",
    "wof:population":29
},
  "geometry": {"coordinates":[8.46157,45.32479],"type":"Point"}
}