{
  "type": "Feature",
  "properties": {
    "gn:admin1_code":"20.0",
    "gn:admin2_code":"VR",
    "gn:admin3_code":"23048.0",
    "gn:asciiname":"Le Comuni",
    "gn:country_code":"IT",
    "gn:dem":11,
    "gn:feature_class":"P",
    "gn:feature_code":"PPL",
    "gn:name":"Le Comuni",
    "gn:population":0,
    "gn:timezone":"Europe/Rome",
    "iso:country":"IT",
    "wof:name":"Le Comuni",
    "wof:placetype":"locality"
},
  "geometry": {"coordinates":[11.35,45.25],"type":"Point"}
}