{
  "type": "Feature",
  "properties": {
    "gn:admin1_code":"5",
    "gn:admin2_code":"FE",
    "gn:admin3_code":"38008.0",
    "gn:asciiname":"Villa Costabile",
    "gn:country_code":"IT",
    "gn:dem":5,
    "gn:feature_class":"P",
    "gn:feature_code":"PPL",
    "gn:name":"Villa Costabile",
    "gn:population":12,
    "gn:timezone":"Europe/Rome",
    "iso:country":"IT",
    "wof:name":"Villa Costabile",
    "wof:placetype":"locality",
    "wof:population":12
},
  "geometry": {"coordinates":[11.66235,44.89106],"type":"Point"}
}