{
  "type": "Feature",
  "properties": {
    "gn:admin1_code":"5",
    "gn:admin2_code":"FE",
    "gn:admin3_code":"38005.0",
    "gn:asciiname":"Tagliata II",
    "gn:country_code":"IT",
    "gn:dem":-4,
    "gn:feature_class":"P",
    "gn:feature_code":"PPL",
    "gn:name":"Tagliata II",
    "gn:population":29,
    "gn:timezone":"Europe/Rome",
    "iso:country":"IT",
    "wof:name":"Tagliata II",
    "wof:placetype":"locality",
    "wof:population":29
},
  "geometry": {"coordinates":[12.07118,44.8875],"type":"Point"}
}