{
  "type": "Feature",
  "properties": {
    "gn:admin1_code":"12.0",
    "gn:admin2_code":"TO",
    "gn:admin3_code":"1093.0",
    "gn:asciiname":"Sinette",
    "gn:country_code":"IT",
    "gn:dem":878,
    "gn:feature_class":"P",
    "gn:feature_code":"PPLL",
    "gn:name":"Sinette",
    "gn:population":3,
    "gn:timezone":"Europe/Rome",
    "iso:country":"IT",
    "wof:name":"Sinette",
    "wof:placetype":"locality",
    "wof:population":3
},
  "geometry": {"coordinates":[7.28357,45.13361],"type":"Point"}
}