{
  "type": "Feature",
  "properties": {
    "gn:admin1_code":"6",
    "gn:admin2_code":"UD",
    "gn:admin3_code":"30104.0",
    "gn:asciiname":"Via San Floreano",
    "gn:country_code":"IT",
    "gn:dem":34,
    "gn:feature_class":"P",
    "gn:feature_code":"PPL",
    "gn:name":"Via San Floreano",
    "gn:population":29,
    "gn:timezone":"Europe/Rome",
    "iso:country":"IT",
    "wof:name":"Via San Floreano",
    "wof:placetype":"locality",
    "wof:population":29
},
  "geometry": {"coordinates":[13.27388,45.92833],"type":"Point"}
}