{
  "type": "Feature",
  "properties": {
    "gn:admin1_code":"3",
    "gn:admin2_code":"RC",
    "gn:admin3_code":"80043.0",
    "gn:asciiname":"Gabella",
    "gn:country_code":"IT",
    "gn:dem":108,
    "gn:feature_class":"P",
    "gn:feature_code":"PPL",
    "gn:name":"Gabella",
    "gn:population":44,
    "gn:timezone":"Europe/Rome",
    "iso:country":"IT",
    "wof:name":"Gabella",
    "wof:placetype":"locality",
    "wof:population":44
},
  "geometry": {"coordinates":[16.23636,38.24243],"type":"Point"}
}