{
  "type": "Feature",
  "properties": {
    "gn:admin1_code":"20",
    "gn:admin2_code":"PD",
    "gn:admin3_code":"28102.0",
    "gn:asciiname":"Salmistraro",
    "gn:country_code":"IT",
    "gn:dem":7,
    "gn:feature_class":"P",
    "gn:feature_code":"PPL",
    "gn:name":"Salmistraro",
    "gn:population":16,
    "gn:timezone":"Europe/Rome",
    "iso:country":"IT",
    "wof:name":"Salmistraro",
    "wof:placetype":"locality",
    "wof:population":16
},
  "geometry": {"coordinates":[11.68173,45.18246],"type":"Point"}
}