{
  "type": "Feature",
  "properties": {
    "gn:admin1_code":"20.0",
    "gn:admin2_code":"VR",
    "gn:admin3_code":"23011.0",
    "gn:asciiname":"Valbusa",
    "gn:country_code":"IT",
    "gn:dem":963,
    "gn:feature_class":"P",
    "gn:feature_code":"PPL",
    "gn:name":"Valbusa",
    "gn:population":17,
    "gn:timezone":"Europe/Rome",
    "iso:country":"IT",
    "wof:name":"Valbusa",
    "wof:placetype":"locality",
    "wof:population":17
},
  "geometry": {"coordinates":[11.01249,45.6213],"type":"Point"}
}