{
  "type": "Feature",
  "properties": {
    "gn:admin1_code":"16.0",
    "gn:admin2_code":"LI",
    "gn:admin3_code":"49008.0",
    "gn:asciiname":"Marmigliaio",
    "gn:country_code":"IT",
    "gn:dem":88,
    "gn:feature_class":"P",
    "gn:feature_code":"PPL",
    "gn:name":"Marmigliaio",
    "gn:population":0,
    "gn:timezone":"Europe/Rome",
    "iso:country":"IT",
    "name:und_x_variant":[
        "Marmigliajo",
        "Marmigliaio"
    ],
    "wof:name":"Marmigliaio",
    "wof:placetype":"locality"
},
  "geometry": {"coordinates":[10.46378,43.50234],"type":"Point"}
}