{
  "type": "Feature",
  "properties": {
    "gn:admin1_code":"20",
    "gn:admin2_code":"VR",
    "gn:admin3_code":"23067.0",
    "gn:asciiname":"Gardun",
    "gn:country_code":"IT",
    "gn:dem":1016,
    "gn:feature_class":"P",
    "gn:feature_code":"PPL",
    "gn:name":"Gardun",
    "gn:population":32,
    "gn:timezone":"Europe/Rome",
    "iso:country":"IT",
    "name:bos_x_preferred":[
        "Gardun"
    ],
    "name:cat_x_preferred":[
        "Gardun"
    ],
    "name:hrv_x_preferred":[
        "Gardun"
    ],
    "name:hun_x_preferred":[
        "Gardun"
    ],
    "name:nld_x_preferred":[
        "Gardun"
    ],
    "name:slv_x_preferred":[
        "Gardun"
    ],
    "name:srp_x_preferred":[
        "\u0413\u0430\u0440\u0434\u0443\u043d"
    ],
    "name:ukr_x_preferred":[
        "\u0413\u0430\u0440\u0434\u0443\u043d"
    ],
    "wof:name":"Gardun",
    "wof:placetype":"locality",
    "wof:population":32
},
  "geometry": {"coordinates":[11.07532,45.6087],"type":"Point"}
}