{
  "type": "Feature",
  "properties": {
    "gn:admin1_code":"9",
    "gn:admin2_code":"PV",
    "gn:admin3_code":"18020.0",
    "gn:asciiname":"Lupa",
    "gn:country_code":"IT",
    "gn:dem":121,
    "gn:feature_class":"P",
    "gn:feature_code":"PPL",
    "gn:name":"Lupa",
    "gn:population":19,
    "gn:timezone":"Europe/Rome",
    "iso:country":"IT",
    "name:bul_x_preferred":[
        "\u041b\u0443\u043f\u0430"
    ],
    "name:ceb_x_preferred":[
        "Lupa"
    ],
    "name:ces_x_preferred":[
        "Lupa"
    ],
    "name:deu_x_preferred":[
        "Lupa"
    ],
    "name:ita_x_preferred":[
        "Lupa"
    ],
    "name:lit_x_preferred":[
        "L\u016bpa"
    ],
    "name:pol_x_preferred":[
        "Lupa"
    ],
    "name:rus_x_preferred":[
        "\u041b\u0443\u043f\u0430"
    ],
    "name:slk_x_preferred":[
        "Lupa"
    ],
    "name:srp_x_preferred":[
        "Lupa"
    ],
    "name:swe_x_preferred":[
        "Lupa"
    ],
    "name:tgl_x_preferred":[
        "Lupa"
    ],
    "name:tur_x_preferred":[
        "Lupa"
    ],
    "name:ukr_x_preferred":[
        "\u041b\u0443\u043f\u0430"
    ],
    "wof:name":"Lupa",
    "wof:placetype":"locality",
    "wof:population":19
},
  "geometry": {"coordinates":[9.3595,45.05806],"type":"Point"}
}