{
  "type": "Feature",
  "properties": {
    "gn:admin1_code":"5.0",
    "gn:admin2_code":"PC",
    "gn:admin3_code":"33033.0",
    "gn:asciiname":"Chiarone",
    "gn:country_code":"IT",
    "gn:dem":260,
    "gn:elevation":"256.0",
    "gn:feature_class":"P",
    "gn:feature_code":"PPL",
    "gn:name":"Chiarone",
    "gn:population":21,
    "gn:timezone":"Europe/Rome",
    "iso:country":"IT",
    "name:und_x_variant":[
        "Stazione Chiarone"
    ],
    "wof:name":"Chiarone",
    "wof:placetype":"locality",
    "wof:population":21
},
  "geometry": {"coordinates":[9.41245,44.90993],"type":"Point"}
}