{
  "type": "Feature",
  "properties": {
    "iso:country":"IT",
    "wof:name":"Centro Storico",
    "wof:placetype":"neighbourhood"
},
  "geometry": {"coordinates":[8.92079013816335,44.41226080769574],"type":"Point"}
}