{
  "type": "Feature",
  "properties": {
    "gn:admin1_code":"1",
    "gn:admin2_code":"CH",
    "gn:admin3_code":"69050.0",
    "gn:asciiname":"Ferrara",
    "gn:country_code":"IT",
    "gn:dem":23,
    "gn:feature_class":"P",
    "gn:feature_code":"PPL",
    "gn:name":"Ferrara",
    "gn:population":130,
    "gn:timezone":"Europe/Rome",
    "iso:country":"IT",
    "wof:name":"Ferrara",
    "wof:placetype":"locality",
    "wof:population":130
},
  "geometry": {"coordinates":[14.30655,42.37716],"type":"Point"}
}