{
  "type": "Feature",
  "properties": {
    "gn:admin1_code":"15",
    "gn:admin2_code":"ME",
    "gn:admin3_code":"83088.0",
    "gn:asciiname":"Cartelli",
    "gn:country_code":"IT",
    "gn:dem":597,
    "gn:feature_class":"P",
    "gn:feature_code":"PPL",
    "gn:name":"Cartelli",
    "gn:population":66,
    "gn:timezone":"Europe/Rome",
    "iso:country":"IT",
    "wof:name":"Cartelli",
    "wof:placetype":"locality",
    "wof:population":66
},
  "geometry": {"coordinates":[14.9077,38.08841],"type":"Point"}
}