{
  "type": "Feature",
  "properties": {
    "gn:admin1_code":"5",
    "gn:admin2_code":"RE",
    "gn:admin3_code":"35018.0",
    "gn:asciiname":"Compiano",
    "gn:country_code":"IT",
    "gn:dem":292,
    "gn:feature_class":"P",
    "gn:feature_code":"PPL",
    "gn:name":"Compiano",
    "gn:population":56,
    "gn:timezone":"Europe/Rome",
    "iso:country":"IT",
    "name:ara_x_preferred":[
        "\u0643\u0648\u0645\u0628\u064a\u0627\u0646\u0648"
    ],
    "name:azb_x_preferred":[
        "\u06a9\u0648\u0645\u067e\u06cc\u0627\u0646\u0648"
    ],
    "name:bel_x_preferred":[
        "\u041a\u043e\u043c\u043f\u2019\u044f\u043d\u0430"
    ],
    "name:bul_x_preferred":[
        "\u041a\u043e\u043c\u043f\u0438\u0430\u043d\u043e"
    ],
    "name:ceb_x_preferred":[
        "Compiano"
    ],
    "name:deu_x_preferred":[
        "Compiano"
    ],
    "name:eml_x_preferred":[
        "Cumpi\u00e0n"
    ],
    "name:epo_x_preferred":[
        "Compiano"
    ],
    "name:eus_x_preferred":[
        "Compiano"
    ],
    "name:fas_x_preferred":[
        "\u06a9\u0648\u0645\u067e\u06cc\u0627\u0646\u0648"
    ],
    "name:fra_x_preferred":[
        "Compiano"
    ],
    "name:hun_x_preferred":[
        "Compiano"
    ],
    "name:hye_x_preferred":[
        "\u053f\u0578\u0574\u057a\u056b\u0561\u0576\u0578"
    ],
    "name:ina_x_preferred":[
        "Compiano"
    ],
    "name:ita_x_preferred":[
        "Compiano"
    ],
    "name:jpn_x_preferred":[
        "\u30b3\u30f3\u30d4\u30a2\u30fc\u30ce"
    ],
    "name:kaz_x_preferred":[
        "\u041a\u043e\u043c\u043f\u044c\u044f\u043d\u043e"
    ],
    "name:lat_x_preferred":[
        "Conpianum"
    ],
    "name:lmo_x_preferred":[
        "Compiano"
    ],
    "name:msa_x_preferred":[
        "Compiano"
    ],
    "name:nap_x_preferred":[
        "Compiano"
    ],
    "name:nld_x_preferred":[
        "Compiano"
    ],
    "name:pms_x_preferred":[
        "Compiano"
    ],
    "name:pol_x_preferred":[
        "Compiano"
    ],
    "name:por_x_preferred":[
        "Compiano"
    ],
    "name:ron_x_preferred":[
        "Compiano"
    ],
    "name:rus_x_preferred":[
        "\u041a\u043e\u043c\u043f\u044c\u044f\u043d\u043e"
    ],
    "name:spa_x_preferred":[
        "Compiano"
    ],
    "name:srp_x_preferred":[
        "\u041a\u043e\u043c\u043f\u0438\u0458\u0430\u043d\u043e"
    ],
    "name:ukr_x_preferred":[
        "\u041a\u043e\u043c\u043f'\u044f\u043d\u043e"
    ],
    "name:uzb_x_preferred":[
        "Compiano"
    ],
    "name:vie_x_preferred":[
        "Compiano"
    ],
    "name:vol_x_preferred":[
        "Compiano"
    ],
    "name:war_x_preferred":[
        "Compiano"
    ],
    "name:zho_x_preferred":[
        "\u5b54\u76ae\u4e9a\u8bfa"
    ],
    "wof:name":"Compiano",
    "wof:placetype":"locality",
    "wof:population":56
},
  "geometry": {"coordinates":[10.3546,44.52776],"type":"Point"}
}