{
  "type": "Feature",
  "properties": {
    "gn:admin1_code":"5",
    "gn:admin2_code":"RE",
    "gn:admin3_code":"35018.0",
    "gn:asciiname":"Compiano",
    "gn:country_code":"IT",
    "gn:dem":292,
    "gn:feature_class":"P",
    "gn:feature_code":"PPL",
    "gn:name":"Compiano",
    "gn:population":56,
    "gn:timezone":"Europe/Rome",
    "iso:country":"IT",
    "wof:name":"Compiano",
    "wof:placetype":"locality",
    "wof:population":56
},
  "geometry": {"coordinates":[10.3546,44.52776],"type":"Point"}
}