{
  "type": "Feature",
  "properties": {
    "gn:admin1_code":"12",
    "gn:admin2_code":"CN",
    "gn:admin3_code":"4066.0",
    "gn:asciiname":"Pratolungo",
    "gn:country_code":"IT",
    "gn:dem":461,
    "gn:feature_class":"P",
    "gn:feature_code":"PPL",
    "gn:name":"Pratolungo",
    "gn:population":29,
    "gn:timezone":"Europe/Rome",
    "iso:country":"IT",
    "wof:name":"Pratolungo",
    "wof:placetype":"locality",
    "wof:population":29
},
  "geometry": {"coordinates":[7.99671,44.37674000000001],"type":"Point"}
}