{
  "type": "Feature",
  "properties": {
    "gn:admin1_code":"20.0",
    "gn:admin2_code":"PD",
    "gn:admin3_code":"28088.0",
    "gn:asciiname":"Case Bertazzo-Malachin",
    "gn:country_code":"IT",
    "gn:dem":3,
    "gn:feature_class":"P",
    "gn:feature_code":"PPL",
    "gn:name":"Case Bertazzo-Malachin",
    "gn:population":43,
    "gn:timezone":"Europe/Rome",
    "iso:country":"IT",
    "wof:name":"Case Bertazzo-Malachin",
    "wof:placetype":"locality",
    "wof:population":43
},
  "geometry": {"coordinates":[11.7696,45.1795],"type":"Point"}
}