{
  "type": "Feature",
  "properties": {
    "gn:admin1_code":"12",
    "gn:admin2_code":"CN",
    "gn:admin3_code":"4240.0",
    "gn:asciiname":"Nitte",
    "gn:country_code":"IT",
    "gn:dem":376,
    "gn:feature_class":"P",
    "gn:feature_code":"PPL",
    "gn:name":"Nitte",
    "gn:population":23,
    "gn:timezone":"Europe/Rome",
    "iso:country":"IT",
    "wof:name":"Nitte",
    "wof:placetype":"locality",
    "wof:population":23
},
  "geometry": {"coordinates":[7.54556,44.60063],"type":"Point"}
}