{
  "type": "Feature",
  "properties": {
    "gn:admin1_code":"14",
    "gn:admin2_code":"SS",
    "gn:admin3_code":"90064.0",
    "gn:asciiname":"San Quirico",
    "gn:country_code":"IT",
    "gn:dem":104,
    "gn:feature_class":"P",
    "gn:feature_code":"PPL",
    "gn:name":"San Quirico",
    "gn:population":110,
    "gn:timezone":"Europe/Rome",
    "iso:country":"IT",
    "wof:name":"San Quirico",
    "wof:placetype":"locality",
    "wof:population":110
},
  "geometry": {"coordinates":[8.50713,40.76987],"type":"Point"}
}