{
  "type": "Feature",
  "properties": {
    "iso:country":"IT",
    "wof:name":"Passo Marchese",
    "wof:placetype":"neighbourhood"
},
  "geometry": {"coordinates":[13.33781504496136,38.08419044154289],"type":"Point"}
}