{
  "type": "Feature",
  "properties": {
    "gn:admin1_code":"20",
    "gn:admin2_code":"BL",
    "gn:admin3_code":"25004.0",
    "gn:asciiname":"Villaggio Nuovo",
    "gn:country_code":"IT",
    "gn:dem":287,
    "gn:feature_class":"P",
    "gn:feature_code":"PPL",
    "gn:name":"Villaggio Nuovo",
    "gn:population":123,
    "gn:timezone":"Europe/Rome",
    "iso:country":"IT",
    "wof:name":"Villaggio Nuovo",
    "wof:placetype":"locality",
    "wof:population":123
},
  "geometry": {"coordinates":[11.75791,45.96592],"type":"Point"}
}