{
  "type": "Feature",
  "properties": {
    "gn:admin1_code":"5",
    "gn:admin2_code":"PR",
    "gn:admin3_code":"34039.0",
    "gn:asciiname":"Casola",
    "gn:country_code":"IT",
    "gn:dem":662,
    "gn:feature_class":"P",
    "gn:feature_code":"PPL",
    "gn:name":"Casola",
    "gn:population":38,
    "gn:timezone":"Europe/Rome",
    "iso:country":"IT",
    "wof:name":"Casola",
    "wof:placetype":"locality",
    "wof:population":38
},
  "geometry": {"coordinates":[10.16203,44.51989],"type":"Point"}
}