{
  "type": "Feature",
  "properties": {
    "gn:admin1_code":"12",
    "gn:admin2_code":"AL",
    "gn:admin3_code":"6160.0",
    "gn:asciiname":"Libarna",
    "gn:country_code":"IT",
    "gn:dem":224,
    "gn:feature_class":"P",
    "gn:feature_code":"PPL",
    "gn:name":"Libarna",
    "gn:population":130,
    "gn:timezone":"Europe/Rome",
    "iso:country":"IT",
    "wof:name":"Libarna",
    "wof:placetype":"locality",
    "wof:population":130
},
  "geometry": {"coordinates":[8.86067,44.70988],"type":"Point"}
}