{
  "type": "Feature",
  "properties": {
    "gn:admin1_code":"12",
    "gn:admin2_code":"TO",
    "gn:admin3_code":"1098.0",
    "gn:asciiname":"Raschiotti",
    "gn:country_code":"IT",
    "gn:dem":501,
    "gn:feature_class":"P",
    "gn:feature_code":"PPL",
    "gn:name":"Raschiotti",
    "gn:population":39,
    "gn:timezone":"Europe/Rome",
    "iso:country":"IT",
    "wof:name":"Raschiotti",
    "wof:placetype":"locality",
    "wof:population":39
},
  "geometry": {"coordinates":[7.63227,45.38765],"type":"Point"}
}