{
  "type": "Feature",
  "properties": {
    "gn:admin1_code":"12",
    "gn:admin2_code":"AL",
    "gn:admin3_code":"6024.0",
    "gn:asciiname":"Casa Tolone",
    "gn:country_code":"IT",
    "gn:dem":322,
    "gn:feature_class":"P",
    "gn:feature_code":"PPLL",
    "gn:name":"Casa Tolone",
    "gn:population":10,
    "gn:timezone":"Europe/Rome",
    "iso:country":"IT",
    "wof:name":"Casa Tolone",
    "wof:placetype":"locality",
    "wof:population":10
},
  "geometry": {"coordinates":[9.05361,44.79242],"type":"Point"}
}