{
  "type": "Feature",
  "properties": {
    "gn:admin1_code":"12",
    "gn:admin2_code":"BI",
    "gn:admin3_code":"96050.0",
    "gn:asciiname":"Flecchia",
    "gn:country_code":"IT",
    "gn:dem":552,
    "gn:feature_class":"P",
    "gn:feature_code":"PPL",
    "gn:name":"Flecchia",
    "gn:population":194,
    "gn:timezone":"Europe/Rome",
    "iso:country":"IT",
    "name:azb_x_preferred":[
        "\u0641\u0644\u0647\u200c\u06a9\u06cc\u0627"
    ],
    "name:ceb_x_preferred":[
        "Flecchia"
    ],
    "name:fas_x_preferred":[
        "\u0641\u0644\u0647\u200c\u06a9\u06cc\u0627"
    ],
    "name:ita_x_preferred":[
        "Flecchia"
    ],
    "name:srp_x_preferred":[
        "\u0424\u043b\u0435\u043a\u0438\u0458\u0430"
    ],
    "wof:name":"Flecchia",
    "wof:placetype":"locality",
    "wof:population":194
},
  "geometry": {"coordinates":[8.19402,45.66994],"type":"Point"}
}