{
  "type": "Feature",
  "properties": {
    "gn:admin1_code":"12",
    "gn:admin2_code":"BI",
    "gn:admin3_code":"96050.0",
    "gn:asciiname":"Flecchia",
    "gn:country_code":"IT",
    "gn:dem":552,
    "gn:feature_class":"P",
    "gn:feature_code":"PPL",
    "gn:name":"Flecchia",
    "gn:population":194,
    "gn:timezone":"Europe/Rome",
    "iso:country":"IT",
    "wof:name":"Flecchia",
    "wof:placetype":"locality",
    "wof:population":194
},
  "geometry": {"coordinates":[8.19402,45.66994],"type":"Point"}
}