{
  "type": "Feature",
  "properties": {
    "gn:admin1_code":"12.0",
    "gn:admin2_code":"CN",
    "gn:admin3_code":"4239.0",
    "gn:asciiname":"Tetto Castello",
    "gn:country_code":"IT",
    "gn:dem":884,
    "gn:feature_class":"P",
    "gn:feature_code":"PPL",
    "gn:name":"Tetto Castello",
    "gn:population":4,
    "gn:timezone":"Europe/Rome",
    "iso:country":"IT",
    "wof:name":"Tetto Castello",
    "wof:placetype":"locality",
    "wof:population":4
},
  "geometry": {"coordinates":[7.53476,44.25037],"type":"Point"}
}