{
  "type": "Feature",
  "properties": {
    "gn:admin1_code":"16",
    "gn:admin2_code":"LU",
    "gn:admin3_code":"46004.0",
    "gn:asciiname":"Tempagnano",
    "gn:country_code":"IT",
    "gn:dem":273,
    "gn:feature_class":"P",
    "gn:feature_code":"PPL",
    "gn:name":"Tempagnano",
    "gn:population":135,
    "gn:timezone":"Europe/Rome",
    "iso:country":"IT",
    "wof:name":"Tempagnano",
    "wof:placetype":"locality",
    "wof:population":135
},
  "geometry": {"coordinates":[10.4611,43.94137],"type":"Point"}
}