{
  "type": "Feature",
  "properties": {
    "gn:admin1_code":"8",
    "gn:admin2_code":"SP",
    "gn:admin3_code":"11005.0",
    "gn:asciiname":"Costella",
    "gn:country_code":"IT",
    "gn:dem":157,
    "gn:feature_class":"P",
    "gn:feature_code":"PPL",
    "gn:name":"Costella",
    "gn:population":35,
    "gn:timezone":"Europe/Rome",
    "iso:country":"IT",
    "wof:name":"Costella",
    "wof:placetype":"locality",
    "wof:population":35
},
  "geometry": {"coordinates":[9.58584,44.18802],"type":"Point"}
}