{
  "type": "Feature",
  "properties": {
    "gn:admin1_code":"3",
    "gn:admin2_code":"VV",
    "gn:admin3_code":"102014.0",
    "gn:asciiname":"Stazione di Francavilla",
    "gn:country_code":"IT",
    "gn:dem":6,
    "gn:feature_class":"P",
    "gn:feature_code":"PPL",
    "gn:name":"Stazione di Francavilla",
    "gn:population":16,
    "gn:timezone":"Europe/Rome",
    "iso:country":"IT",
    "wof:name":"Stazione di Francavilla",
    "wof:placetype":"locality",
    "wof:population":16
},
  "geometry": {"coordinates":[16.21682,38.77839],"type":"Point"}
}