{
  "type": "Feature",
  "properties": {
    "gn:admin1_code":"20",
    "gn:admin2_code":"VI",
    "gn:admin3_code":"24079.0",
    "gn:asciiname":"Conche",
    "gn:country_code":"IT",
    "gn:dem":17,
    "gn:feature_class":"P",
    "gn:feature_code":"PPL",
    "gn:name":"Conche",
    "gn:population":45,
    "gn:timezone":"Europe/Rome",
    "iso:country":"IT",
    "name:ara_x_preferred":[
        "\u0642\u062f\u0631 \u0635\u062f\u0641\u064a"
    ],
    "name:bul_x_preferred":[
        "\u041a\u043e\u043d\u0447\u0438\u043d\u0433"
    ],
    "name:deu_x_preferred":[
        "Conchiermaschine"
    ],
    "name:fra_x_preferred":[
        "Conchage"
    ],
    "name:jpn_x_preferred":[
        "\u30b3\u30f3\u30c1\u30a7"
    ],
    "name:nld_x_preferred":[
        "Conche"
    ],
    "name:pol_x_preferred":[
        "Konsza"
    ],
    "name:por_x_preferred":[
        "Conchagem"
    ],
    "name:spa_x_preferred":[
        "Conche"
    ],
    "name:swe_x_preferred":[
        "Conchning"
    ],
    "wof:name":"Conche",
    "wof:placetype":"locality",
    "wof:population":45
},
  "geometry": {"coordinates":[11.48109,45.31308],"type":"Point"}
}