{
  "type": "Feature",
  "properties": {
    "gn:admin1_code":"17",
    "gn:admin2_code":"BZ",
    "gn:admin3_code":"21081.0",
    "gn:asciiname":"Hurtmuhle",
    "gn:country_code":"IT",
    "gn:dem":908,
    "gn:feature_class":"P",
    "gn:feature_code":"PPL",
    "gn:name":"Hurtmuhle",
    "gn:population":56,
    "gn:timezone":"Europe/Rome",
    "iso:country":"IT",
    "wof:name":"Hurtmuhle",
    "wof:placetype":"locality",
    "wof:population":56
},
  "geometry": {"coordinates":[11.92044,46.776],"type":"Point"}
}