{
  "type": "Feature",
  "properties": {
    "gn:admin1_code":"20",
    "gn:admin2_code":"VI",
    "gn:admin3_code":"24072.0",
    "gn:asciiname":"Golini",
    "gn:country_code":"IT",
    "gn:dem":553,
    "gn:feature_class":"P",
    "gn:feature_code":"PPL",
    "gn:name":"Golini",
    "gn:population":17,
    "gn:timezone":"Europe/Rome",
    "iso:country":"IT",
    "wof:name":"Golini",
    "wof:placetype":"locality",
    "wof:population":17
},
  "geometry": {"coordinates":[11.30146,45.56894000000001],"type":"Point"}
}