{
  "type": "Feature",
  "properties": {
    "gn:admin1_code":"8.0",
    "gn:admin2_code":"GE",
    "gn:admin3_code":"10065.0",
    "gn:asciiname":"Nenno",
    "gn:country_code":"IT",
    "gn:dem":582,
    "gn:feature_class":"P",
    "gn:feature_code":"PPL",
    "gn:name":"Nenno",
    "gn:population":121,
    "gn:timezone":"Europe/Rome",
    "iso:country":"IT",
    "wof:name":"Nenno",
    "wof:placetype":"locality",
    "wof:population":121
},
  "geometry": {"coordinates":[9.02885,44.55956],"type":"Point"}
}