{
  "type": "Feature",
  "properties": {
    "gn:admin1_code":"17.0",
    "gn:admin2_code":"TN",
    "gn:admin3_code":"22103.0",
    "gn:asciiname":"Stazione di Lavis",
    "gn:country_code":"IT",
    "gn:dem":207,
    "gn:feature_class":"P",
    "gn:feature_code":"PPL",
    "gn:name":"Stazione di Lavis",
    "gn:population":201,
    "gn:timezone":"Europe/Rome",
    "iso:country":"IT",
    "wof:name":"Stazione di Lavis",
    "wof:placetype":"locality",
    "wof:population":201
},
  "geometry": {"coordinates":[11.09319,46.14537],"type":"Point"}
}