{
  "type": "Feature",
  "properties": {
    "gn:admin1_code":"12",
    "gn:admin2_code":"CN",
    "gn:admin3_code":"4009.0",
    "gn:asciiname":"Boaglio",
    "gn:country_code":"IT",
    "gn:dem":501,
    "gn:feature_class":"P",
    "gn:feature_code":"PPL",
    "gn:name":"Boaglio",
    "gn:population":29,
    "gn:timezone":"Europe/Rome",
    "iso:country":"IT",
    "wof:name":"Boaglio",
    "wof:placetype":"locality",
    "wof:population":29
},
  "geometry": {"coordinates":[7.2866,44.75236],"type":"Point"}
}