{
  "type": "Feature",
  "properties": {
    "gn:admin1_code":"7",
    "gn:admin2_code":"FR",
    "gn:admin3_code":"60026.0",
    "gn:asciiname":"Marandola",
    "gn:country_code":"IT",
    "gn:dem":61,
    "gn:feature_class":"P",
    "gn:feature_code":"PPL",
    "gn:name":"Marandola",
    "gn:population":97,
    "gn:timezone":"Europe/Rome",
    "iso:country":"IT",
    "wof:name":"Marandola",
    "wof:placetype":"locality",
    "wof:population":97
},
  "geometry": {"coordinates":[13.87862,41.44798],"type":"Point"}
}