{
  "type": "Feature",
  "properties": {
    "gn:admin1_code":"20",
    "gn:admin2_code":"PD",
    "gn:admin3_code":"28076.0",
    "gn:asciiname":"Ronco",
    "gn:country_code":"IT",
    "gn:dem":26,
    "gn:feature_class":"P",
    "gn:feature_code":"PPL",
    "gn:name":"Ronco",
    "gn:population":26,
    "gn:timezone":"Europe/Rome",
    "iso:country":"IT",
    "wof:name":"Ronco",
    "wof:placetype":"locality",
    "wof:population":26
},
  "geometry": {"coordinates":[11.81614,45.57103],"type":"Point"}
}