{
  "type": "Feature",
  "properties": {
    "gn:admin1_code":"13",
    "gn:admin2_code":"BA",
    "gn:admin3_code":"72017.0",
    "gn:asciiname":"Pozzo Cucu",
    "gn:country_code":"IT",
    "gn:dem":274,
    "gn:feature_class":"P",
    "gn:feature_code":"PPL",
    "gn:name":"Pozzo Cuc\u00f9",
    "gn:population":200,
    "gn:timezone":"Europe/Rome",
    "iso:country":"IT",
    "name:und_x_variant":[
        "Pozzo Cuc\u00f9"
    ],
    "wof:name":"Pozzo Cucu",
    "wof:placetype":"locality",
    "wof:population":200
},
  "geometry": {"coordinates":[17.16582,40.90128],"type":"Point"}
}