{
  "type": "Feature",
  "properties": {
    "gn:admin1_code":"18",
    "gn:admin2_code":"PG",
    "gn:admin3_code":"54051.0",
    "gn:asciiname":"Sant'Anastasio",
    "gn:country_code":"IT",
    "gn:dem":298,
    "gn:feature_class":"P",
    "gn:feature_code":"PPL",
    "gn:name":"Sant'Anastasio",
    "gn:population":135,
    "gn:timezone":"Europe/Rome",
    "iso:country":"IT",
    "wof:name":"Sant'Anastasio",
    "wof:placetype":"locality",
    "wof:population":135
},
  "geometry": {"coordinates":[12.71135,42.77982],"type":"Point"}
}