{
  "type": "Feature",
  "properties": {
    "gn:admin1_code":"5.0",
    "gn:admin2_code":"RA",
    "gn:admin3_code":"39001.0",
    "gn:asciiname":"Borghetto",
    "gn:country_code":"IT",
    "gn:dem":6,
    "gn:feature_class":"P",
    "gn:feature_code":"PPL",
    "gn:name":"Borghetto",
    "gn:population":0,
    "gn:timezone":"Europe/Rome",
    "iso:country":"IT",
    "name:ceb_x_preferred":[
        "Borghetto"
    ],
    "name:deu_x_preferred":[
        "Borghetto"
    ],
    "name:fra_x_preferred":[
        "Borghetto"
    ],
    "name:ita_x_preferred":[
        "Borghetto"
    ],
    "name:nld_x_preferred":[
        "Borghetto"
    ],
    "name:por_x_preferred":[
        "Borghetto"
    ],
    "name:srp_x_preferred":[
        "Borgeto"
    ],
    "name:swe_x_preferred":[
        "Borghetto"
    ],
    "wof:name":"Borghetto",
    "wof:placetype":"locality"
},
  "geometry": {"coordinates":[12.03917,44.50833],"type":"Point"}
}