{
  "type": "Feature",
  "properties": {
    "gn:admin1_code":"12",
    "gn:admin2_code":"CN",
    "gn:admin3_code":"4165.0",
    "gn:asciiname":"Blangetti",
    "gn:country_code":"IT",
    "gn:dem":475,
    "gn:feature_class":"P",
    "gn:feature_code":"PPL",
    "gn:name":"Blangetti",
    "gn:population":144,
    "gn:timezone":"Europe/Rome",
    "iso:country":"IT",
    "wof:name":"Blangetti",
    "wof:placetype":"locality",
    "wof:population":144
},
  "geometry": {"coordinates":[7.72994,44.38778],"type":"Point"}
}