{
  "type": "Feature",
  "properties": {
    "gn:admin1_code":"9",
    "gn:admin2_code":"MN",
    "gn:admin3_code":"20028.0",
    "gn:asciiname":"Sferza",
    "gn:country_code":"IT",
    "gn:dem":48,
    "gn:feature_class":"P",
    "gn:feature_code":"PPL",
    "gn:name":"Sferza",
    "gn:population":20,
    "gn:timezone":"Europe/Rome",
    "iso:country":"IT",
    "wof:name":"Sferza",
    "wof:placetype":"locality",
    "wof:population":20
},
  "geometry": {"coordinates":[10.55977,45.28957],"type":"Point"}
}