{
  "type": "Feature",
  "properties": {
    "gn:admin1_code":"5",
    "gn:admin2_code":"PC",
    "gn:admin3_code":"33019.0",
    "gn:asciiname":"Asse",
    "gn:country_code":"IT",
    "gn:dem":757,
    "gn:feature_class":"P",
    "gn:feature_code":"PPL",
    "gn:name":"Ass\u00e8",
    "gn:population":11,
    "gn:timezone":"Europe/Rome",
    "iso:country":"IT",
    "name:bre_x_preferred":[
        "Asse"
    ],
    "name:bul_x_preferred":[
        "\u0410\u0441\u0435"
    ],
    "name:cat_x_preferred":[
        "Asse"
    ],
    "name:ceb_x_preferred":[
        "Asse"
    ],
    "name:deu_x_preferred":[
        "Asse"
    ],
    "name:epo_x_preferred":[
        "Asse"
    ],
    "name:eus_x_preferred":[
        "Asse"
    ],
    "name:fas_x_preferred":[
        "\u0627\u0633"
    ],
    "name:fra_x_preferred":[
        "Asse"
    ],
    "name:gle_x_preferred":[
        "Asse"
    ],
    "name:ita_x_preferred":[
        "Asse"
    ],
    "name:kor_x_preferred":[
        "\uc544\uc11c"
    ],
    "name:nld_x_preferred":[
        "Asse"
    ],
    "name:nor_x_preferred":[
        "Asse"
    ],
    "name:oci_x_preferred":[
        "Asse"
    ],
    "name:pol_x_preferred":[
        "Asse"
    ],
    "name:por_x_preferred":[
        "Asse"
    ],
    "name:ron_x_preferred":[
        "Asse"
    ],
    "name:rus_x_preferred":[
        "\u0410\u0441\u0441\u0435"
    ],
    "name:slk_x_preferred":[
        "Asse"
    ],
    "name:spa_x_preferred":[
        "Asse"
    ],
    "name:swe_x_preferred":[
        "Asse"
    ],
    "name:tur_x_preferred":[
        "Asse"
    ],
    "name:und_x_variant":[
        "Ass\u00e8"
    ],
    "name:vie_x_preferred":[
        "Asse"
    ],
    "name:vol_x_preferred":[
        "Asse"
    ],
    "name:war_x_preferred":[
        "Asse"
    ],
    "wof:name":"Asse",
    "wof:placetype":"locality",
    "wof:population":11
},
  "geometry": {"coordinates":[9.56717,44.72695],"type":"Point"}
}