{
  "type": "Feature",
  "properties": {
    "iso:country":"IT",
    "name:fra_x_preferred":[
        "Ponte Galeria"
    ],
    "name:ita_x_preferred":[
        "Ponte Galeria"
    ],
    "wof:name":"Ponte Galeria",
    "wof:placetype":"neighbourhood"
},
  "geometry": {"coordinates":[12.34947641859659,41.8185418131803],"type":"Point"}
}