{
  "type": "Feature",
  "properties": {
    "gn:admin1_code":"17",
    "gn:admin2_code":"BZ",
    "gn:admin3_code":"21102.0",
    "gn:asciiname":"Molini",
    "gn:country_code":"IT",
    "gn:dem":858,
    "gn:feature_class":"P",
    "gn:feature_code":"PPL",
    "gn:name":"Molini",
    "gn:population":36,
    "gn:timezone":"Europe/Rome",
    "iso:country":"IT",
    "wof:name":"Molini",
    "wof:placetype":"locality",
    "wof:population":36
},
  "geometry": {"coordinates":[11.32647,46.31124000000001],"type":"Point"}
}