{
  "type": "Feature",
  "properties": {
    "gn:admin1_code":"20",
    "gn:admin2_code":"VE",
    "gn:admin3_code":"27037.0",
    "gn:asciiname":"Bragato",
    "gn:country_code":"IT",
    "gn:dem":10,
    "gn:feature_class":"P",
    "gn:feature_code":"PPL",
    "gn:name":"Bragato",
    "gn:population":31,
    "gn:timezone":"Europe/Rome",
    "iso:country":"IT",
    "wof:name":"Bragato",
    "wof:placetype":"locality",
    "wof:population":31
},
  "geometry": {"coordinates":[12.1432,45.57756],"type":"Point"}
}