{
  "type": "Feature",
  "properties": {
    "gn:admin1_code":"10.0",
    "gn:admin2_code":"PU",
    "gn:admin3_code":"41034.0",
    "gn:asciiname":"Fontecorniale",
    "gn:country_code":"IT",
    "gn:dem":458,
    "gn:elevation":"450.0",
    "gn:feature_class":"P",
    "gn:feature_code":"PPL",
    "gn:name":"Fontecorniale",
    "gn:population":26,
    "gn:timezone":"Europe/Rome",
    "iso:country":"IT",
    "wof:name":"Fontecorniale",
    "wof:placetype":"locality",
    "wof:population":26
},
  "geometry": {"coordinates":[12.8129,43.7654],"type":"Point"}
}