{
  "type": "Feature",
  "properties": {
    "gn:admin1_code":"5.0",
    "gn:admin2_code":"BO",
    "gn:admin3_code":"37061.0",
    "gn:asciiname":"Ruseghino",
    "gn:country_code":"IT",
    "gn:dem":199,
    "gn:feature_class":"P",
    "gn:feature_code":"PPLL",
    "gn:name":"Ruseghino",
    "gn:population":4,
    "gn:timezone":"Europe/Rome",
    "iso:country":"IT",
    "wof:name":"Ruseghino",
    "wof:placetype":"locality",
    "wof:population":4
},
  "geometry": {"coordinates":[11.05363,44.43419],"type":"Point"}
}