{
  "type": "Feature",
  "properties": {
    "gn:admin1_code":"3",
    "gn:admin2_code":"RC",
    "gn:admin3_code":"80063.0",
    "gn:asciiname":"Case Sant'Andrea",
    "gn:country_code":"IT",
    "gn:dem":443,
    "gn:feature_class":"P",
    "gn:feature_code":"PPL",
    "gn:name":"Case Sant'Andrea",
    "gn:population":50,
    "gn:timezone":"Europe/Rome",
    "iso:country":"IT",
    "wof:name":"Case Sant'Andrea",
    "wof:placetype":"locality",
    "wof:population":50
},
  "geometry": {"coordinates":[15.71341,38.06456],"type":"Point"}
}