{
  "type": "Feature",
  "properties": {
    "gn:country":"IT",
    "gn:fcode":"PPL",
    "gn:population":0,
    "iso:country":"IT",
    "name:ceb_x_preferred":[
        "Porto Rotondo"
    ],
    "name:eng_x_preferred":[
        "Porto Rotondo"
    ],
    "name:fra_x_preferred":[
        "Porto Rotondo"
    ],
    "name:hun_x_preferred":[
        "Porto Rotondo"
    ],
    "name:ita_x_preferred":[
        "Porto Rotondo"
    ],
    "name:nld_x_preferred":[
        "Porto Rotondo"
    ],
    "name:srp_x_preferred":[
        "Porto Rotondo"
    ],
    "qs_pg:aaroncc":"IT",
    "qs_pg:gn_country":"IT",
    "qs_pg:gn_fcode":"PPL",
    "qs_pg:gn_pop":0,
    "qs_pg:name":"Porto Rotondo",
    "qs_pg:name_adm0":"Italia",
    "qs_pg:name_adm1":"Sardegna",
    "qs_pg:photos":745,
    "qs_pg:photos_1k":151,
    "qs_pg:photos_9k":3,
    "qs_pg:photos_9r":5,
    "qs_pg:photos_all":745,
    "qs_pg:photos_sr":8,
    "qs_pg:pop_sr":0,
    "qs_pg:qs_pg_placetype":"locality",
    "qs_pg:qs_pg_placetype_gp":"Town",
    "qs_pg:woe_adm0":23424853,
    "woe:adm0_id":23424853,
    "woe:name_adm0":"Italia",
    "woe:name_adm1":"Sardegna",
    "woe:placetype":"Town",
    "wof:name":"Porto Rotondo",
    "wof:placetype":"locality",
    "wof:population":305
},
  "geometry": {"coordinates":[9.54378,41.02596],"type":"Point"}
}