{
  "type": "Feature",
  "properties": {
    "gn:admin1_code":"5",
    "gn:admin2_code":"PC",
    "gn:admin3_code":"33019.0",
    "gn:asciiname":"Russi",
    "gn:country_code":"IT",
    "gn:dem":894,
    "gn:feature_class":"P",
    "gn:feature_code":"PPL",
    "gn:name":"Russi",
    "gn:population":11,
    "gn:timezone":"Europe/Rome",
    "iso:country":"IT",
    "wof:name":"Russi",
    "wof:placetype":"locality",
    "wof:population":11
},
  "geometry": {"coordinates":[9.5231,44.70515],"type":"Point"}
}