{
  "type": "Feature",
  "properties": {
    "gn:admin1_code":"3",
    "gn:admin2_code":"RC",
    "gn:admin3_code":"80025.0",
    "gn:asciiname":"Carrubbara-Lisera",
    "gn:country_code":"IT",
    "gn:dem":68,
    "gn:feature_class":"P",
    "gn:feature_code":"PPL",
    "gn:name":"Carrubbara-Liser\u00e0",
    "gn:population":158,
    "gn:timezone":"Europe/Rome",
    "iso:country":"IT",
    "name:und_x_variant":[
        "Carrubbara-Liser\u00e0"
    ],
    "wof:name":"Carrubbara-Lisera",
    "wof:placetype":"locality",
    "wof:population":158
},
  "geometry": {"coordinates":[16.43104,38.37277],"type":"Point"}
}