{
  "type": "Feature",
  "properties": {
    "iso:country":"IT",
    "wof:name":"Selva Candida",
    "wof:placetype":"neighbourhood"
},
  "geometry": {"coordinates":[12.37871608784966,41.95430450009673],"type":"Point"}
}