{
  "type": "Feature",
  "properties": {
    "gn:admin1_code":"15",
    "gn:admin2_code":"RG",
    "gn:admin3_code":"88009.0",
    "gn:asciiname":"Serra Garofalo",
    "gn:country_code":"IT",
    "gn:dem":576,
    "gn:feature_class":"P",
    "gn:feature_code":"PPL",
    "gn:name":"Serra Garofalo",
    "gn:population":27,
    "gn:timezone":"Europe/Rome",
    "iso:country":"IT",
    "wof:name":"Serra Garofalo",
    "wof:placetype":"locality",
    "wof:population":27
},
  "geometry": {"coordinates":[14.68087,36.86879],"type":"Point"}
}