{
  "type": "Feature",
  "properties": {
    "iso:country":"IT",
    "name:eng_x_preferred":[
        "Latte"
    ],
    "name:fra_x_preferred":[
        "Latte"
    ],
    "name:hun_x_preferred":[
        "Latte"
    ],
    "name:ita_x_preferred":[
        "Latte"
    ],
    "name:nld_x_preferred":[
        "Latte"
    ],
    "name:srp_x_preferred":[
        "Latte"
    ],
    "qs:a0":"Italia",
    "qs:a1":"*Imperia",
    "qs:a1r":"0Liguria",
    "qs:adm0":"Italia",
    "qs:la_lc":"*",
    "qs:level":"locality",
    "qs:loc":"Latte",
    "qs:loc_alt":"Latte",
    "qs:pop":0,
    "qs:type":"buffered point",
    "wof:name":"Latte",
    "wof:placetype":"locality"
},
  "geometry": {"coordinates":[7.565436,43.799021],"type":"Point"}
}