{
  "type": "Feature",
  "properties": {
    "gn:admin1_code":"7",
    "gn:admin2_code":"FR",
    "gn:admin3_code":"60085.0",
    "gn:asciiname":"Case Ricci",
    "gn:country_code":"IT",
    "gn:dem":454,
    "gn:feature_class":"P",
    "gn:feature_code":"PPL",
    "gn:name":"Case Ricci",
    "gn:population":108,
    "gn:timezone":"Europe/Rome",
    "iso:country":"IT",
    "wof:name":"Case Ricci",
    "wof:placetype":"locality",
    "wof:population":108
},
  "geometry": {"coordinates":[13.45699,41.71361],"type":"Point"}
}