{
  "type": "Feature",
  "properties": {
    "gn:admin1_code":"13.0",
    "gn:admin2_code":"LE",
    "gn:admin3_code":"75068.0",
    "gn:asciiname":"Aria Sana",
    "gn:country_code":"IT",
    "gn:dem":47,
    "gn:feature_class":"P",
    "gn:feature_code":"PPL",
    "gn:name":"Aria Sana",
    "gn:population":793,
    "gn:timezone":"Europe/Rome",
    "iso:country":"IT",
    "wof:name":"Aria Sana",
    "wof:placetype":"locality",
    "wof:population":793
},
  "geometry": {"coordinates":[18.16602,40.32878],"type":"Point"}
}