{
  "type": "Feature",
  "properties": {
    "gn:admin1_code":"12",
    "gn:admin2_code":"BI",
    "gn:admin3_code":"96003.0",
    "gn:asciiname":"Zona Industriale Campogrande",
    "gn:country_code":"IT",
    "gn:dem":261,
    "gn:feature_class":"P",
    "gn:feature_code":"PPL",
    "gn:name":"Zona Industriale Campogrande",
    "gn:population":65,
    "gn:timezone":"Europe/Rome",
    "iso:country":"IT",
    "wof:name":"Zona Industriale Campogrande",
    "wof:placetype":"locality",
    "wof:population":65
},
  "geometry": {"coordinates":[8.13542,45.50076],"type":"Point"}
}