{
  "type": "Feature",
  "properties": {
    "gn:admin1_code":"5",
    "gn:admin2_code":"FE",
    "gn:admin3_code":"38022.0",
    "gn:asciiname":"Castello",
    "gn:country_code":"IT",
    "gn:dem":10,
    "gn:feature_class":"P",
    "gn:feature_code":"PPL",
    "gn:name":"Castello",
    "gn:population":35,
    "gn:timezone":"Europe/Rome",
    "iso:country":"IT",
    "wof:name":"Castello",
    "wof:placetype":"locality",
    "wof:population":35
},
  "geometry": {"coordinates":[11.51759,44.81397],"type":"Point"}
}