{
  "type": "Feature",
  "properties": {
    "gn:admin1_code":"4.0",
    "gn:admin3_code":"63031.0",
    "gn:asciiname":"Monterone",
    "gn:country_code":"IT",
    "gn:dem":36,
    "gn:feature_class":"P",
    "gn:feature_code":"PPL",
    "gn:name":"Monterone",
    "gn:population":0,
    "gn:timezone":"Europe/Rome",
    "iso:country":"IT",
    "wof:name":"Monterone",
    "wof:placetype":"locality"
},
  "geometry": {"coordinates":[13.86741,40.73677],"type":"Point"}
}