{
  "type": "Feature",
  "properties": {
    "gn:admin1_code":"15.0",
    "gn:admin2_code":"AG",
    "gn:admin3_code":"84001.0",
    "gn:asciiname":"Torcicuda",
    "gn:country_code":"IT",
    "gn:dem":237,
    "gn:elevation":"235.0",
    "gn:feature_class":"P",
    "gn:feature_code":"PPL",
    "gn:name":"Torcicuda",
    "gn:population":21,
    "gn:timezone":"Europe/Rome",
    "iso:country":"IT",
    "wof:name":"Torcicuda",
    "wof:placetype":"locality",
    "wof:population":21
},
  "geometry": {"coordinates":[13.60245,37.32711],"type":"Point"}
}