{
  "type": "Feature",
  "properties": {
    "gn:admin1_code":"8",
    "gn:admin2_code":"IM",
    "gn:admin3_code":"8064.0",
    "gn:asciiname":"Torretta",
    "gn:country_code":"IT",
    "gn:dem":391,
    "gn:feature_class":"P",
    "gn:feature_code":"PPLL",
    "gn:name":"Torretta",
    "gn:population":10,
    "gn:timezone":"Europe/Rome",
    "iso:country":"IT",
    "name:ara_x_preferred":[
        "\u062a\u0648\u0631\u064a\u062a\u0627"
    ],
    "name:azb_x_preferred":[
        "\u062a\u0648\u0631\u062a\u0627"
    ],
    "name:bul_x_preferred":[
        "\u0422\u043e\u0440\u0435\u0442\u0430"
    ],
    "name:cat_x_preferred":[
        "Torretta"
    ],
    "name:ceb_x_preferred":[
        "Torretta"
    ],
    "name:deu_x_preferred":[
        "Torretta"
    ],
    "name:epo_x_preferred":[
        "Torretta"
    ],
    "name:eus_x_preferred":[
        "Torretta"
    ],
    "name:fas_x_preferred":[
        "\u062a\u0648\u0631\u062a\u0627"
    ],
    "name:fra_x_preferred":[
        "Torretta"
    ],
    "name:hun_x_preferred":[
        "Torretta"
    ],
    "name:hye_x_preferred":[
        "\u054f\u0578\u0580\u0565\u057f\u0561"
    ],
    "name:ita_x_preferred":[
        "Torretta"
    ],
    "name:jpn_x_preferred":[
        "\u30c8\u30c3\u30ec\u30c3\u30bf"
    ],
    "name:kaz_x_preferred":[
        "\u0422\u043e\u0440\u0440\u0435\u0442\u0442\u0430"
    ],
    "name:lat_x_preferred":[
        "Turritta"
    ],
    "name:lmo_x_preferred":[
        "Torretta"
    ],
    "name:msa_x_preferred":[
        "Torretta"
    ],
    "name:nap_x_preferred":[
        "Torretta"
    ],
    "name:nld_x_preferred":[
        "Torretta"
    ],
    "name:pms_x_preferred":[
        "Torretta"
    ],
    "name:pol_x_preferred":[
        "Torretta"
    ],
    "name:por_x_preferred":[
        "Torretta"
    ],
    "name:ron_x_preferred":[
        "Torretta"
    ],
    "name:rus_x_preferred":[
        "\u0422\u043e\u0440\u0440\u0435\u0442\u0442\u0430"
    ],
    "name:scn_x_preferred":[
        "Turretta"
    ],
    "name:spa_x_preferred":[
        "Torretta"
    ],
    "name:srd_x_preferred":[
        "Torretta"
    ],
    "name:srp_x_preferred":[
        "\u0422\u043e\u0440\u0435\u0442\u0430"
    ],
    "name:swe_x_preferred":[
        "Torretta"
    ],
    "name:tgl_x_preferred":[
        "Torretta"
    ],
    "name:ukr_x_preferred":[
        "\u0422\u043e\u0440\u0440\u0435\u0442\u0442\u0430"
    ],
    "name:uzb_x_preferred":[
        "Torretta"
    ],
    "name:vol_x_preferred":[
        "Torretta"
    ],
    "name:war_x_preferred":[
        "Torretta"
    ],
    "name:zho_x_preferred":[
        "\u6258\u96f7\u5854"
    ],
    "wof:name":"Torretta",
    "wof:placetype":"locality",
    "wof:population":10
},
  "geometry": {"coordinates":[7.95004,43.94196],"type":"Point"}
}