{
  "type": "Feature",
  "properties": {
    "gn:admin1_code":"3.0",
    "gn:admin2_code":"CS",
    "gn:admin3_code":"78012.0",
    "gn:asciiname":"San Nicola II",
    "gn:country_code":"IT",
    "gn:dem":519,
    "gn:feature_class":"P",
    "gn:feature_code":"PPL",
    "gn:name":"San Nicola II",
    "gn:population":61,
    "gn:timezone":"Europe/Rome",
    "iso:country":"IT",
    "wof:name":"San Nicola II",
    "wof:placetype":"locality",
    "wof:population":61
},
  "geometry": {"coordinates":[16.31843,39.24091],"type":"Point"}
}