{
  "type": "Feature",
  "properties": {
    "gn:admin1_code":"20",
    "gn:admin2_code":"TV",
    "gn:admin3_code":"26074.0",
    "gn:asciiname":"Caminada",
    "gn:country_code":"IT",
    "gn:dem":25,
    "gn:feature_class":"P",
    "gn:feature_code":"PPL",
    "gn:name":"Caminada",
    "gn:population":29,
    "gn:timezone":"Europe/Rome",
    "iso:country":"IT",
    "wof:name":"Caminada",
    "wof:placetype":"locality",
    "wof:population":29
},
  "geometry": {"coordinates":[12.38094,45.79569],"type":"Point"}
}