{
  "type": "Feature",
  "properties": {
    "gn:admin1_code":"12",
    "gn:admin2_code":"CN",
    "gn:admin3_code":"4215.0",
    "gn:asciiname":"Apparizione",
    "gn:country_code":"IT",
    "gn:dem":324,
    "gn:feature_class":"P",
    "gn:feature_code":"PPL",
    "gn:name":"Apparizione",
    "gn:population":35,
    "gn:timezone":"Europe/Rome",
    "iso:country":"IT",
    "wof:name":"Apparizione",
    "wof:placetype":"locality",
    "wof:population":35
},
  "geometry": {"coordinates":[7.68935,44.61938],"type":"Point"}
}