{
  "type": "Feature",
  "properties": {
    "gn:admin1_code":"4",
    "gn:admin2_code":"AV",
    "gn:admin3_code":"64092.0",
    "gn:asciiname":"Barricella",
    "gn:country_code":"IT",
    "gn:dem":668,
    "gn:feature_class":"P",
    "gn:feature_code":"PPL",
    "gn:name":"Barricella",
    "gn:population":53,
    "gn:timezone":"Europe/Rome",
    "iso:country":"IT",
    "wof:name":"Barricella",
    "wof:placetype":"locality",
    "wof:population":53
},
  "geometry": {"coordinates":[15.17727,40.90397],"type":"Point"}
}