{
  "type": "Feature",
  "properties": {
    "gn:admin1_code":"6.0",
    "gn:admin2_code":"UD",
    "gn:admin3_code":"30059.0",
    "gn:asciiname":"Badaiuz",
    "gn:country_code":"IT",
    "gn:dem":805,
    "gn:feature_class":"P",
    "gn:feature_code":"PPL",
    "gn:name":"Badaiuz",
    "gn:population":0,
    "gn:timezone":"Europe/Rome",
    "iso:country":"IT",
    "wof:name":"Badaiuz",
    "wof:placetype":"locality"
},
  "geometry": {"coordinates":[13.1775,46.4425],"type":"Point"}
}