{
  "type": "Feature",
  "properties": {
    "gn:admin1_code":"9.0",
    "gn:admin2_code":"MI",
    "gn:admin3_code":"15062.0",
    "gn:asciiname":"Molino al Ponte",
    "gn:country_code":"IT",
    "gn:dem":141,
    "gn:feature_class":"P",
    "gn:feature_code":"PPL",
    "gn:name":"Molino al Ponte",
    "gn:population":30,
    "gn:timezone":"Europe/Rome",
    "iso:country":"IT",
    "wof:name":"Molino al Ponte",
    "wof:placetype":"locality",
    "wof:population":30
},
  "geometry": {"coordinates":[8.72285,45.54206],"type":"Point"}
}