{
  "type": "Feature",
  "properties": {
    "gn:admin1_code":"12",
    "gn:admin2_code":"AL",
    "gn:admin3_code":"6087.0",
    "gn:asciiname":"Capraglia",
    "gn:country_code":"IT",
    "gn:dem":77,
    "gn:feature_class":"P",
    "gn:feature_code":"PPL",
    "gn:name":"Capraglia",
    "gn:population":87,
    "gn:timezone":"Europe/Rome",
    "iso:country":"IT",
    "wof:name":"Capraglia",
    "wof:placetype":"locality",
    "wof:population":87
},
  "geometry": {"coordinates":[8.82825,45.02614000000001],"type":"Point"}
}