{
  "type": "Feature",
  "properties": {
    "gn:admin1_code":"1",
    "gn:admin2_code":"CH",
    "gn:admin3_code":"69088.0",
    "gn:asciiname":"Villaggio",
    "gn:country_code":"IT",
    "gn:dem":593,
    "gn:feature_class":"P",
    "gn:feature_code":"PPL",
    "gn:name":"Villaggio",
    "gn:population":22,
    "gn:timezone":"Europe/Rome",
    "iso:country":"IT",
    "name:deu_x_preferred":[
        "Villaggio"
    ],
    "name:fra_x_preferred":[
        "Villaggio"
    ],
    "name:ita_x_preferred":[
        "Villaggio"
    ],
    "name:srp_x_preferred":[
        "Vila\u0111o"
    ],
    "wof:name":"Villaggio",
    "wof:placetype":"locality",
    "wof:population":22
},
  "geometry": {"coordinates":[14.4878,41.79132],"type":"Point"}
}