{
  "type": "Feature",
  "properties": {
    "gn:admin1_code":"6.0",
    "gn:admin2_code":"UD",
    "gn:admin3_code":"30122.0",
    "gn:asciiname":"Prestento",
    "gn:country_code":"IT",
    "gn:dem":165,
    "gn:elevation":"175.0",
    "gn:feature_class":"P",
    "gn:feature_code":"PPL",
    "gn:name":"Prestento",
    "gn:population":243,
    "gn:timezone":"Europe/Rome",
    "iso:country":"IT",
    "wof:name":"Prestento",
    "wof:placetype":"locality",
    "wof:population":243
},
  "geometry": {"coordinates":[13.40351,46.12682],"type":"Point"}
}