{
  "type": "Feature",
  "properties": {
    "gn:admin1_code":"5",
    "gn:admin2_code":"PC",
    "gn:admin3_code":"33033.0",
    "gn:asciiname":"Vaie",
    "gn:country_code":"IT",
    "gn:dem":336,
    "gn:feature_class":"P",
    "gn:feature_code":"PPL",
    "gn:name":"Vaie",
    "gn:population":14,
    "gn:timezone":"Europe/Rome",
    "iso:country":"IT",
    "name:azb_x_preferred":[
        "\u0648\u0627\u06cc\u0647"
    ],
    "name:bel_x_preferred":[
        "\u0412\u0430\u0435"
    ],
    "name:bul_x_preferred":[
        "\u0412\u0430\u0439\u0435"
    ],
    "name:cat_x_preferred":[
        "Vaie"
    ],
    "name:ceb_x_preferred":[
        "Vaie"
    ],
    "name:deu_x_preferred":[
        "Vaie"
    ],
    "name:epo_x_preferred":[
        "Vaie"
    ],
    "name:eus_x_preferred":[
        "Vaie"
    ],
    "name:fas_x_preferred":[
        "\u0648\u0627\u06cc\u0647"
    ],
    "name:fra_x_preferred":[
        "Vaye"
    ],
    "name:hun_x_preferred":[
        "Vaie"
    ],
    "name:hye_x_preferred":[
        "\u054e\u0561\u0565"
    ],
    "name:ind_x_preferred":[
        "Vaie"
    ],
    "name:ita_x_preferred":[
        "Vaie"
    ],
    "name:jpn_x_preferred":[
        "\u30f4\u30a1\u30a4\u30a8"
    ],
    "name:kaz_x_preferred":[
        "\u0412\u0430\u0435"
    ],
    "name:lat_x_preferred":[
        "Vaga"
    ],
    "name:lmo_x_preferred":[
        "Vaie"
    ],
    "name:msa_x_preferred":[
        "Vaie"
    ],
    "name:nap_x_preferred":[
        "Vaie"
    ],
    "name:nld_x_preferred":[
        "Vaie"
    ],
    "name:pms_x_preferred":[
        "Vaje"
    ],
    "name:pol_x_preferred":[
        "Vaie"
    ],
    "name:por_x_preferred":[
        "Vaie"
    ],
    "name:ron_x_preferred":[
        "Vaie"
    ],
    "name:rus_x_preferred":[
        "\u0412\u0430\u0435"
    ],
    "name:scn_x_preferred":[
        "Vaie"
    ],
    "name:spa_x_preferred":[
        "Vaie"
    ],
    "name:srp_x_preferred":[
        "\u0412\u0430\u0458\u0435"
    ],
    "name:swe_x_preferred":[
        "Vaie"
    ],
    "name:tgl_x_preferred":[
        "Vaie"
    ],
    "name:ukr_x_preferred":[
        "\u0412\u0430\u0454"
    ],
    "name:uzb_x_preferred":[
        "Vaie"
    ],
    "name:vie_x_preferred":[
        "Vaie"
    ],
    "name:vol_x_preferred":[
        "Vaie"
    ],
    "name:war_x_preferred":[
        "Vaie"
    ],
    "name:zho_x_preferred":[
        "\u74e6\u4f0a\u57c3"
    ],
    "wof:name":"Vaie",
    "wof:placetype":"locality",
    "wof:population":14
},
  "geometry": {"coordinates":[9.39929,44.92262],"type":"Point"}
}