{
  "type": "Feature",
  "properties": {
    "gn:admin1_code":"5",
    "gn:admin2_code":"PC",
    "gn:admin3_code":"33033.0",
    "gn:asciiname":"Vaie",
    "gn:country_code":"IT",
    "gn:dem":336,
    "gn:feature_class":"P",
    "gn:feature_code":"PPL",
    "gn:name":"Vaie",
    "gn:population":14,
    "gn:timezone":"Europe/Rome",
    "iso:country":"IT",
    "wof:name":"Vaie",
    "wof:placetype":"locality",
    "wof:population":14
},
  "geometry": {"coordinates":[9.39929,44.92262],"type":"Point"}
}