{
  "type": "Feature",
  "properties": {
    "gn:gn_country":"IT",
    "gn:gn_fcode":"PPL",
    "gn:gn_pop":0,
    "gn:population":964,
    "iso:country":"IT",
    "name:ceb_x_preferred":[
        "Masano"
    ],
    "name:eng_x_preferred":[
        "Masano"
    ],
    "name:epo_x_preferred":[
        "Masano"
    ],
    "name:fra_x_preferred":[
        "Masano"
    ],
    "name:hun_x_preferred":[
        "Masano"
    ],
    "name:ita_x_preferred":[
        "Masano"
    ],
    "name:lmo_x_preferred":[
        "Mas\u00e0"
    ],
    "name:nld_x_preferred":[
        "Masano"
    ],
    "name:srp_x_preferred":[
        "Masano"
    ],
    "qs_pg:aaroncc":"IT",
    "qs_pg:gn_country":"IT",
    "qs_pg:gn_fcode":"PPL",
    "qs_pg:gn_pop":0,
    "qs_pg:name":"Masano",
    "qs_pg:name_adm0":"Italia",
    "qs_pg:name_adm1":"Lombardia",
    "qs_pg:photos":55,
    "qs_pg:photos_1k":11,
    "qs_pg:photos_9k":1,
    "qs_pg:photos_9r":2,
    "qs_pg:photos_all":55,
    "qs_pg:photos_sr":2,
    "qs_pg:pop_sr":0,
    "qs_pg:qs_pg_placetype":"locality",
    "qs_pg:qs_pg_placetype_gp":"Town",
    "qs_pg:woe_adm0":23424853,
    "woe:adm0_id":23424853,
    "woe:name_adm0":"Italia",
    "woe:name_adm1":"Lombardia",
    "woe:placetype":"Town",
    "wof:name":"Masano",
    "wof:placetype":"locality",
    "wof:population":964
},
  "geometry": {"coordinates":[9.67552,45.51417],"type":"Point"}
}