{
  "type": "Feature",
  "properties": {
    "gn:admin1_code":"12",
    "gn:admin2_code":"TO",
    "gn:admin3_code":"1070.0",
    "gn:asciiname":"Malano",
    "gn:country_code":"IT",
    "gn:dem":330,
    "gn:feature_class":"P",
    "gn:feature_code":"PPL",
    "gn:name":"Malano",
    "gn:population":60,
    "gn:timezone":"Europe/Rome",
    "iso:country":"IT",
    "wof:name":"Malano",
    "wof:placetype":"locality",
    "wof:population":60
},
  "geometry": {"coordinates":[7.35492,44.8154],"type":"Point"}
}