{
  "type": "Feature",
  "properties": {
    "gn:admin1_code":"9.0",
    "gn:admin2_code":"MI",
    "gn:admin3_code":"15247.0",
    "gn:asciiname":"Localita Badile",
    "gn:country_code":"IT",
    "gn:dem":98,
    "gn:feature_class":"P",
    "gn:feature_code":"PPL",
    "gn:name":"Localit\u00e0 Badile",
    "gn:population":13,
    "gn:timezone":"Europe/Rome",
    "iso:country":"IT",
    "name:und_x_variant":[
        "Localit\u00e0 Badile"
    ],
    "wof:name":"Localita Badile",
    "wof:placetype":"locality",
    "wof:population":13
},
  "geometry": {"coordinates":[9.11403,45.34012],"type":"Point"}
}