{
  "type": "Feature",
  "properties": {
    "gn:admin1_code":"20.0",
    "gn:admin2_code":"VI",
    "gn:admin3_code":"24054.0",
    "gn:asciiname":"Campomezzavia",
    "gn:cc2":"IT",
    "gn:country_code":"IT",
    "gn:dem":1029,
    "gn:feature_class":"P",
    "gn:feature_code":"PPL",
    "gn:name":"Campomezzavia",
    "gn:population":17,
    "gn:timezone":"Europe/Rome",
    "iso:country":"IT",
    "name:und_x_variant":[
        "Campidimezzavia",
        "Campo di Mezza Via"
    ],
    "wof:name":"Campomezzavia",
    "wof:placetype":"locality",
    "wof:population":17
},
  "geometry": {"coordinates":[11.57412,45.83367],"type":"Point"}
}