{
  "type": "Feature",
  "properties": {
    "gn:admin1_code":"16",
    "gn:admin2_code":"SI",
    "gn:admin3_code":"52005.0",
    "gn:asciiname":"Tregole",
    "gn:country_code":"IT",
    "gn:dem":504,
    "gn:feature_class":"P",
    "gn:feature_code":"PPL",
    "gn:name":"Tregole",
    "gn:population":21,
    "gn:timezone":"Europe/Rome",
    "iso:country":"IT",
    "wof:name":"Tregole",
    "wof:placetype":"locality",
    "wof:population":21
},
  "geometry": {"coordinates":[11.31617,43.44411],"type":"Point"}
}