{
  "type": "Feature",
  "properties": {
    "gn:admin1_code":"18.0",
    "gn:admin2_code":"PG",
    "gn:admin3_code":"54051.0",
    "gn:asciiname":"Frazione Castagnacupa",
    "gn:country_code":"IT",
    "gn:dem":758,
    "gn:feature_class":"P",
    "gn:feature_code":"PPLL",
    "gn:name":"Frazione Castagnacupa",
    "gn:population":0,
    "gn:timezone":"Europe/Rome",
    "iso:country":"IT",
    "wof:name":"Frazione Castagnacupa",
    "wof:placetype":"locality"
},
  "geometry": {"coordinates":[12.65554,42.67013],"type":"Point"}
}