{
  "type": "Feature",
  "properties": {
    "gn:admin1_code":"12.0",
    "gn:admin2_code":"CN",
    "gn:admin3_code":"4084.0",
    "gn:asciiname":"Tetti Violino",
    "gn:country_code":"IT",
    "gn:dem":1047,
    "gn:feature_class":"P",
    "gn:feature_code":"PPLL",
    "gn:name":"Tetti Violino",
    "gn:population":1,
    "gn:timezone":"Europe/Rome",
    "iso:country":"IT",
    "wof:name":"Tetti Violino",
    "wof:placetype":"locality",
    "wof:population":1
},
  "geometry": {"coordinates":[7.41712,44.23805],"type":"Point"}
}