{
  "type": "Feature",
  "properties": {
    "gn:admin1_code":"7",
    "gn:admin2_code":"FR",
    "gn:admin3_code":"60012.0",
    "gn:asciiname":"Cavone",
    "gn:country_code":"IT",
    "gn:dem":283,
    "gn:feature_class":"P",
    "gn:feature_code":"PPL",
    "gn:name":"Cavone",
    "gn:population":22,
    "gn:timezone":"Europe/Rome",
    "iso:country":"IT",
    "name:ceb_x_preferred":[
        "Fiume Cavone"
    ],
    "name:deu_x_preferred":[
        "Cavone"
    ],
    "name:hun_x_preferred":[
        "Cavone"
    ],
    "name:ita_x_preferred":[
        "Cavone"
    ],
    "name:lat_x_preferred":[
        "Acalandrus"
    ],
    "name:spa_x_preferred":[
        "Cavone"
    ],
    "name:zho_x_preferred":[
        "\u5361\u6c83\u5167\u6cb3"
    ],
    "wof:name":"Cavone",
    "wof:placetype":"locality",
    "wof:population":22
},
  "geometry": {"coordinates":[13.72816,41.35338],"type":"Point"}
}