{
  "type": "Feature",
  "properties": {
    "gn:admin1_code":"15",
    "gn:admin2_code":"TP",
    "gn:admin3_code":"81002.0",
    "gn:asciiname":"Luziano",
    "gn:country_code":"IT",
    "gn:dem":346,
    "gn:feature_class":"P",
    "gn:feature_code":"PPL",
    "gn:name":"Luziano",
    "gn:population":18,
    "gn:timezone":"Europe/Rome",
    "iso:country":"IT",
    "wof:name":"Luziano",
    "wof:placetype":"locality",
    "wof:population":18
},
  "geometry": {"coordinates":[12.70109,38.00634],"type":"Point"}
}