{
  "type": "Feature",
  "properties": {
    "gn:admin1_code":"9",
    "gn:admin2_code":"BS",
    "gn:admin3_code":"17141.0",
    "gn:asciiname":"Aiale",
    "gn:country_code":"IT",
    "gn:dem":535,
    "gn:feature_class":"P",
    "gn:feature_code":"PPL",
    "gn:name":"Aiale",
    "gn:population":59,
    "gn:timezone":"Europe/Rome",
    "iso:country":"IT",
    "wof:name":"Aiale",
    "wof:placetype":"locality",
    "wof:population":59
},
  "geometry": {"coordinates":[10.26052,45.76697],"type":"Point"}
}