{
  "type": "Feature",
  "properties": {
    "gn:admin1_code":"12",
    "gn:admin2_code":"TO",
    "gn:admin3_code":"1155.0",
    "gn:asciiname":"Benale",
    "gn:country_code":"IT",
    "gn:dem":1131,
    "gn:feature_class":"P",
    "gn:feature_code":"PPL",
    "gn:name":"Benale",
    "gn:population":30,
    "gn:timezone":"Europe/Rome",
    "iso:country":"IT",
    "wof:name":"Benale",
    "wof:placetype":"locality",
    "wof:population":30
},
  "geometry": {"coordinates":[7.41607,45.3025],"type":"Point"}
}