{
  "type": "Feature",
  "properties": {
    "gn:gn_country":"IT",
    "gn:gn_fcode":"PPLA3",
    "gn:gn_pop":585,
    "gn:population":361,
    "iso:country":"IT",
    "name:bel_x_preferred":[
        "\u041f\u0435\u0432\u044d-\u0434\u0437\u0456-\u041b\u0435\u0434\u0440\u0430"
    ],
    "name:cat_x_preferred":[
        "Pieve di Ledro"
    ],
    "name:ces_x_preferred":[
        "Pieve di Ledro"
    ],
    "name:deu_x_preferred":[
        "Pieve di Ledro"
    ],
    "name:eng_x_preferred":[
        "Pieve di Ledro"
    ],
    "name:epo_x_preferred":[
        "Pieve di Ledro"
    ],
    "name:fra_x_preferred":[
        "Pieve di Ledro"
    ],
    "name:hun_x_preferred":[
        "Pieve di Ledro"
    ],
    "name:hye_x_preferred":[
        "\u054a\u056b\u0587\u0565 \u0564\u056b \u053c\u0565\u0564\u0580\u0578"
    ],
    "name:ind_x_preferred":[
        "Pieve di Ledro"
    ],
    "name:ita_x_preferred":[
        "Pieve di Ledro"
    ],
    "name:jpn_x_preferred":[
        "\u30d4\u30a8\u30fc\u30f4\u30a7\u30fb\u30c7\u30a3\u30fb\u30ec\u30fc\u30c9\u30ed"
    ],
    "name:kaz_x_preferred":[
        "\u041f\u044c\u0435\u0432\u0435-\u0434\u0438-\u041b\u0435\u0434\u0440\u043e"
    ],
    "name:nap_x_preferred":[
        "Pieve di Ledro"
    ],
    "name:nld_x_preferred":[
        "Pieve di Ledro"
    ],
    "name:pms_x_preferred":[
        "Pieve di Ledro"
    ],
    "name:pol_x_preferred":[
        "Pieve di Ledro"
    ],
    "name:por_x_preferred":[
        "Pieve di Ledro"
    ],
    "name:rus_x_preferred":[
        "\u041f\u044c\u0435\u0432\u0435-\u0434\u0438-\u041b\u0435\u0434\u0440\u043e"
    ],
    "name:srp_x_preferred":[
        "Pieve di Ledro"
    ],
    "name:ukr_x_preferred":[
        "\u041f\u0454\u0432\u0435-\u0434\u0456-\u041b\u0435\u0434\u0440\u043e"
    ],
    "name:uzb_x_preferred":[
        "Pieve di Ledro"
    ],
    "name:vie_x_preferred":[
        "Pieve di Ledro"
    ],
    "name:vol_x_preferred":[
        "Pieve di Ledro"
    ],
    "name:war_x_preferred":[
        "Pieve di Ledro"
    ],
    "name:zho_x_preferred":[
        "\u76ae\u8036\u97e6\u8fea\u83b1\u5fb7\u7f57"
    ],
    "qs_pg:aaroncc":"IT",
    "qs_pg:gn_country":"IT",
    "qs_pg:gn_fcode":"PPLA3",
    "qs_pg:gn_pop":585,
    "qs_pg:name":"Pieve di Ledro",
    "qs_pg:name_adm0":"Italia",
    "qs_pg:name_adm1":"Trentino-Alto Adige",
    "qs_pg:photos":380,
    "qs_pg:photos_1k":77,
    "qs_pg:photos_9k":2,
    "qs_pg:photos_9r":5,
    "qs_pg:photos_all":380,
    "qs_pg:photos_sr":6,
    "qs_pg:pop_sr":2,
    "qs_pg:qs_pg_placetype":"locality",
    "qs_pg:qs_pg_placetype_gp":"Town",
    "qs_pg:woe_adm0":23424853,
    "woe:adm0_id":23424853,
    "woe:name_adm0":"Italia",
    "woe:name_adm1":"Trentino-Alto Adige",
    "woe:placetype":"Town",
    "wof:name":"Pieve di Ledro",
    "wof:placetype":"locality",
    "wof:population":361
},
  "geometry": {"coordinates":[10.73124,45.88848],"type":"Point"}
}