{
  "type": "Feature",
  "properties": {
    "gn:admin1_code":"16.0",
    "gn:admin2_code":"SI",
    "gn:admin3_code":"52028.0",
    "gn:asciiname":"Badia A Elmi",
    "gn:country_code":"IT",
    "gn:dem":78,
    "gn:feature_class":"P",
    "gn:feature_code":"PPL",
    "gn:name":"Badia A Elmi",
    "gn:population":908,
    "gn:timezone":"Europe/Rome",
    "iso:country":"IT",
    "wof:name":"Badia A Elmi",
    "wof:placetype":"locality",
    "wof:population":908
},
  "geometry": {"coordinates":[11.03236,43.53869],"type":"Point"}
}