{
  "type": "Feature",
  "properties": {
    "iso:country":"IT",
    "wof:name":"Fogaccia",
    "wof:placetype":"neighbourhood"
},
  "geometry": {"coordinates":[12.39187680003792,41.91514313561527],"type":"Point"}
}