{
  "type": "Feature",
  "properties": {
    "gn:admin1_code":"9.0",
    "gn:admin2_code":"BG",
    "gn:admin3_code":"16139.0",
    "gn:asciiname":"Zona Industriale Montello",
    "gn:country_code":"IT",
    "gn:dem":229,
    "gn:feature_class":"P",
    "gn:feature_code":"PPL",
    "gn:name":"Zona Industriale Montello",
    "gn:population":3,
    "gn:timezone":"Europe/Rome",
    "iso:country":"IT",
    "wof:name":"Zona Industriale Montello",
    "wof:placetype":"locality",
    "wof:population":3
},
  "geometry": {"coordinates":[9.79425,45.67563],"type":"Point"}
}