{
  "type": "Feature",
  "properties": {
    "gn:admin1_code":"20",
    "gn:admin2_code":"VR",
    "gn:admin3_code":"23098.0",
    "gn:asciiname":"Lavagno",
    "gn:country_code":"IT",
    "gn:dem":22,
    "gn:feature_class":"P",
    "gn:feature_code":"PPL",
    "gn:name":"Lavagno",
    "gn:population":28,
    "gn:timezone":"Europe/Rome",
    "iso:country":"IT",
    "name:azb_x_preferred":[
        "\u0644\u0627\u0648\u0627\u0646\u06cc\u0648"
    ],
    "name:bul_x_preferred":[
        "\u041b\u0430\u0432\u0430\u043d\u044c\u043e"
    ],
    "name:ceb_x_preferred":[
        "Lavagno"
    ],
    "name:deu_x_preferred":[
        "Lavagno"
    ],
    "name:epo_x_preferred":[
        "Lavagno"
    ],
    "name:eus_x_preferred":[
        "Lavagno"
    ],
    "name:fas_x_preferred":[
        "\u0644\u0627\u0648\u0627\u0646\u06cc\u0648"
    ],
    "name:fra_x_preferred":[
        "Lavagno"
    ],
    "name:hun_x_preferred":[
        "Lavagno"
    ],
    "name:hye_x_preferred":[
        "\u053c\u0561\u057e\u0561\u0576\u0578"
    ],
    "name:ita_x_preferred":[
        "Lavagno"
    ],
    "name:jpn_x_preferred":[
        "\u30e9\u30f4\u30a1\u30fc\u30cb\u30e7"
    ],
    "name:kaz_x_preferred":[
        "\u041b\u0430\u0432\u0430\u043d\u044c\u043e"
    ],
    "name:lat_x_preferred":[
        "Lavaneus"
    ],
    "name:lmo_x_preferred":[
        "Lavagno"
    ],
    "name:msa_x_preferred":[
        "Lavagno"
    ],
    "name:nap_x_preferred":[
        "Lavagno"
    ],
    "name:nld_x_preferred":[
        "Lavagno"
    ],
    "name:pms_x_preferred":[
        "Lavagno"
    ],
    "name:pol_x_preferred":[
        "Lavagno"
    ],
    "name:por_x_preferred":[
        "Lavagno"
    ],
    "name:ron_x_preferred":[
        "Lavagno"
    ],
    "name:rus_x_preferred":[
        "\u041b\u0430\u0432\u0430\u043d\u044c\u043e"
    ],
    "name:scn_x_preferred":[
        "Lavagno"
    ],
    "name:spa_x_preferred":[
        "Lavagno"
    ],
    "name:srp_x_preferred":[
        "\u041b\u0430\u0432\u0430\u045a\u043e"
    ],
    "name:tgl_x_preferred":[
        "Lavagno"
    ],
    "name:ukr_x_preferred":[
        "\u041b\u0430\u0432\u0430\u043d\u044c\u043e"
    ],
    "name:uzb_x_preferred":[
        "Lavagno"
    ],
    "name:vec_x_preferred":[
        "\u0141avagno"
    ],
    "name:vie_x_preferred":[
        "Lavagno"
    ],
    "name:vol_x_preferred":[
        "Lavagno"
    ],
    "name:war_x_preferred":[
        "Lavagno"
    ],
    "name:zho_x_preferred":[
        "\u62c9\u74e6\u5c3c\u5965"
    ],
    "wof:name":"Lavagno",
    "wof:placetype":"locality",
    "wof:population":28
},
  "geometry": {"coordinates":[11.35639,45.33604],"type":"Point"}
}