{
  "type": "Feature",
  "properties": {
    "gn:admin1_code":"5",
    "gn:admin2_code":"PR",
    "gn:admin3_code":"34024.0",
    "gn:asciiname":"Neviano-Molino",
    "gn:country_code":"IT",
    "gn:dem":453,
    "gn:feature_class":"P",
    "gn:feature_code":"PPL",
    "gn:name":"Neviano-Molino",
    "gn:population":14,
    "gn:timezone":"Europe/Rome",
    "iso:country":"IT",
    "wof:name":"Neviano-Molino",
    "wof:placetype":"locality",
    "wof:population":14
},
  "geometry": {"coordinates":[10.32337,44.58611],"type":"Point"}
}