{
  "type": "Feature",
  "properties": {
    "gn:admin1_code":"20",
    "gn:admin2_code":"VR",
    "gn:admin3_code":"23084.0",
    "gn:asciiname":"Corte Belgioioso",
    "gn:country_code":"IT",
    "gn:dem":21,
    "gn:feature_class":"P",
    "gn:feature_code":"PPL",
    "gn:name":"Corte Belgioioso",
    "gn:population":63,
    "gn:timezone":"Europe/Rome",
    "iso:country":"IT",
    "wof:name":"Corte Belgioioso",
    "wof:placetype":"locality",
    "wof:population":63
},
  "geometry": {"coordinates":[11.02123,45.16398],"type":"Point"}
}