{
  "type": "Feature",
  "properties": {
    "gn:admin1_code":"12",
    "gn:admin2_code":"VC",
    "gn:admin3_code":"2049.0",
    "gn:asciiname":"Galli",
    "gn:country_code":"IT",
    "gn:dem":155,
    "gn:feature_class":"P",
    "gn:feature_code":"PPL",
    "gn:name":"Galli",
    "gn:population":197,
    "gn:timezone":"Europe/Rome",
    "iso:country":"IT",
    "wof:name":"Galli",
    "wof:placetype":"locality",
    "wof:population":197
},
  "geometry": {"coordinates":[8.06884,45.18944000000001],"type":"Point"}
}