{
  "type": "Feature",
  "properties": {
    "gn:elevation":418,
    "gn:population":68,
    "iso:country":"IT",
    "name:cat_x_preferred":[
        "Zolla"
    ],
    "name:ceb_x_preferred":[
        "Zolla"
    ],
    "name:ces_x_preferred":[
        "Zolla"
    ],
    "name:dan_x_preferred":[
        "Zolla"
    ],
    "name:eng_x_preferred":[
        "Zolla"
    ],
    "name:eng_x_variant":[
        "Repentabor",
        "Zolla Monrupino"
    ],
    "name:eus_x_preferred":[
        "Zolla"
    ],
    "name:fin_x_preferred":[
        "Zolla"
    ],
    "name:fra_x_preferred":[
        "Zolla"
    ],
    "name:ind_x_preferred":[
        "Zolla"
    ],
    "name:ita_x_preferred":[
        "Zolla di Monrupino"
    ],
    "name:ita_x_variant":[
        "Col",
        "Zolla"
    ],
    "name:nld_x_preferred":[
        "Zolla"
    ],
    "name:nno_x_preferred":[
        "Zolla"
    ],
    "name:nob_x_preferred":[
        "Zolla"
    ],
    "name:oci_x_preferred":[
        "Zolla"
    ],
    "name:pol_x_preferred":[
        "Zolla"
    ],
    "name:por_x_preferred":[
        "Zolla"
    ],
    "name:ron_x_preferred":[
        "Zolla"
    ],
    "name:slk_x_preferred":[
        "Zolla"
    ],
    "name:slv_x_preferred":[
        "Zolla"
    ],
    "name:spa_x_preferred":[
        "Zolla"
    ],
    "name:srp_x_preferred":[
        "Zolla"
    ],
    "name:swe_x_preferred":[
        "Zolla"
    ],
    "name:tgl_x_preferred":[
        "Zolla"
    ],
    "name:tur_x_preferred":[
        "Zolla"
    ],
    "name:und_x_variant":[
        "Monrupino"
    ],
    "name:war_x_preferred":[
        "Zolla"
    ],
    "qs:a0":"Italia",
    "qs:a1":"*Trieste",
    "qs:a1r":"0Friuli-Venezia Giulia",
    "qs:adm0":"Italia",
    "qs:la_lc":"*",
    "qs:level":"locality",
    "qs:loc":"Zolla",
    "qs:loc_alt":"Zolla",
    "qs:pop":0,
    "qs:type":"buffered point",
    "wof:lang":[
        "ita"
    ],
    "wof:name":"Zolla",
    "wof:placetype":"locality",
    "wof:population":68
},
  "geometry": {"coordinates":[13.812267,45.717499],"type":"Point"}
}