{
  "type": "Feature",
  "properties": {
    "gn:elevation":418,
    "gn:population":68,
    "iso:country":"IT",
    "name:eng_x_preferred":[
        "Zolla"
    ],
    "name:eng_x_variant":[
        "Repentabor",
        "Zolla Monrupino"
    ],
    "name:ita_x_preferred":[
        "Zolla di Monrupino"
    ],
    "name:ita_x_variant":[
        "Col"
    ],
    "name:unk_x_variant":[
        "Monrupino"
    ],
    "qs:a0":"Italia",
    "qs:a1":"*Trieste",
    "qs:a1r":"0Friuli-Venezia Giulia",
    "qs:adm0":"Italia",
    "qs:la_lc":"*",
    "qs:level":"locality",
    "qs:loc":"Zolla",
    "qs:loc_alt":"Zolla",
    "qs:pop":0,
    "qs:type":"buffered point",
    "wof:lang":[
        "ita"
    ],
    "wof:name":"Zolla",
    "wof:placetype":"locality",
    "wof:population":68
},
  "geometry": {"coordinates":[13.812267,45.717499],"type":"Point"}
}