{
  "type": "Feature",
  "properties": {
    "gn:admin1_code":"7",
    "gn:admin2_code":"FR",
    "gn:admin3_code":"60070.0",
    "gn:asciiname":"Bivio-Casilina",
    "gn:country_code":"IT",
    "gn:dem":85,
    "gn:feature_class":"P",
    "gn:feature_code":"PPL",
    "gn:name":"Bivio-Casilina",
    "gn:population":259,
    "gn:timezone":"Europe/Rome",
    "iso:country":"IT",
    "wof:name":"Bivio-Casilina",
    "wof:placetype":"locality",
    "wof:population":259
},
  "geometry": {"coordinates":[13.91643,41.45032],"type":"Point"}
}