{
  "type": "Feature",
  "properties": {
    "gn:admin1_code":"20",
    "gn:admin2_code":"VI",
    "gn:admin3_code":"24084.0",
    "gn:asciiname":"Pintari",
    "gn:country_code":"IT",
    "gn:dem":587,
    "gn:feature_class":"P",
    "gn:feature_code":"PPL",
    "gn:name":"Pintari",
    "gn:population":25,
    "gn:timezone":"Europe/Rome",
    "iso:country":"IT",
    "wof:name":"Pintari",
    "wof:placetype":"locality",
    "wof:population":25
},
  "geometry": {"coordinates":[11.23447,45.70208],"type":"Point"}
}