{
  "type": "Feature",
  "properties": {
    "gn:admin1_code":"1",
    "gn:admin2_code":"TE",
    "gn:admin3_code":"67028.0",
    "gn:asciiname":"Tappone",
    "gn:country_code":"IT",
    "gn:dem":324,
    "gn:feature_class":"P",
    "gn:feature_code":"PPL",
    "gn:name":"Tappone",
    "gn:population":22,
    "gn:timezone":"Europe/Rome",
    "iso:country":"IT",
    "wof:name":"Tappone",
    "wof:placetype":"locality",
    "wof:population":22
},
  "geometry": {"coordinates":[13.65472,42.60847],"type":"Point"}
}