{
  "type": "Feature",
  "properties": {
    "gn:admin1_code":"12",
    "gn:admin2_code":"CN",
    "gn:admin3_code":"4214.0",
    "gn:asciiname":"Monfriggio",
    "gn:country_code":"IT",
    "gn:dem":340,
    "gn:feature_class":"P",
    "gn:feature_code":"PPL",
    "gn:name":"Monfriggio",
    "gn:population":33,
    "gn:timezone":"Europe/Rome",
    "iso:country":"IT",
    "wof:name":"Monfriggio",
    "wof:placetype":"locality",
    "wof:population":33
},
  "geometry": {"coordinates":[7.94682,44.79285],"type":"Point"}
}