{
  "type": "Feature",
  "properties": {
    "gn:admin1_code":"5",
    "gn:admin2_code":"RE",
    "gn:admin3_code":"35041.0",
    "gn:asciiname":"Ca' Casalotto",
    "gn:country_code":"IT",
    "gn:dem":817,
    "gn:feature_class":"P",
    "gn:feature_code":"PPL",
    "gn:name":"Ca' Casalotto",
    "gn:population":34,
    "gn:timezone":"Europe/Rome",
    "iso:country":"IT",
    "wof:name":"Ca' Casalotto",
    "wof:placetype":"locality",
    "wof:population":34
},
  "geometry": {"coordinates":[10.51645,44.37258],"type":"Point"}
}