{
  "type": "Feature",
  "properties": {
    "gn:admin1_code":"12.0",
    "gn:admin2_code":"NO",
    "gn:admin3_code":"3058.0",
    "gn:asciiname":"Cascine Enea",
    "gn:country_code":"IT",
    "gn:dem":346,
    "gn:feature_class":"P",
    "gn:feature_code":"PPL",
    "gn:name":"Cascine Enea",
    "gn:population":434,
    "gn:timezone":"Europe/Rome",
    "iso:country":"IT",
    "wof:name":"Cascine Enea",
    "wof:placetype":"locality",
    "wof:population":434
},
  "geometry": {"coordinates":[8.44517,45.66456],"type":"Point"}
}