{
  "type": "Feature",
  "properties": {
    "gn:admin1_code":"10.0",
    "gn:admin2_code":"AN",
    "gn:admin3_code":"42019.0",
    "gn:asciiname":"Mozzavinci",
    "gn:country_code":"IT",
    "gn:dem":144,
    "gn:feature_class":"P",
    "gn:feature_code":"PPL",
    "gn:name":"Mozzavinci",
    "gn:population":0,
    "gn:timezone":"Europe/Rome",
    "iso:country":"IT",
    "wof:name":"Mozzavinci",
    "wof:placetype":"locality"
},
  "geometry": {"coordinates":[13.38547,43.426],"type":"Point"}
}