{
  "type": "Feature",
  "properties": {
    "gn:admin1_code":"20",
    "gn:admin2_code":"TV",
    "gn:admin3_code":"26092.0",
    "gn:asciiname":"Sfadiga",
    "gn:country_code":"IT",
    "gn:dem":258,
    "gn:feature_class":"P",
    "gn:feature_code":"PPL",
    "gn:name":"Sfadig\u00e0",
    "gn:population":21,
    "gn:timezone":"Europe/Rome",
    "iso:country":"IT",
    "name:und_x_variant":[
        "Sfadig\u00e0"
    ],
    "wof:name":"Sfadiga",
    "wof:placetype":"locality",
    "wof:population":21
},
  "geometry": {"coordinates":[12.3022,46.00419],"type":"Point"}
}