{
  "type": "Feature",
  "properties": {
    "gn:admin1_code":"17.0",
    "gn:admin2_code":"TN",
    "gn:admin3_code":"22244.0",
    "gn:asciiname":"Santi di Daone",
    "gn:country_code":"IT",
    "gn:dem":1123,
    "gn:feature_class":"P",
    "gn:feature_code":"PPL",
    "gn:name":"Santi di Daone",
    "gn:population":0,
    "gn:timezone":"Europe/Rome",
    "iso:country":"IT",
    "wof:name":"Santi di Daone",
    "wof:placetype":"locality"
},
  "geometry": {"coordinates":[10.73333,46.06667],"type":"Point"}
}