{
  "type": "Feature",
  "properties": {
    "gn:admin1_code":"20",
    "gn:admin2_code":"VR",
    "gn:admin3_code":"23087.0",
    "gn:asciiname":"Morini",
    "gn:country_code":"IT",
    "gn:dem":487,
    "gn:feature_class":"P",
    "gn:feature_code":"PPL",
    "gn:name":"Morini",
    "gn:population":20,
    "gn:timezone":"Europe/Rome",
    "iso:country":"IT",
    "name:bre_x_preferred":[
        "Morini"
    ],
    "name:bul_x_preferred":[
        "\u041c\u043e\u0440\u0438\u043d\u0438"
    ],
    "name:cat_x_preferred":[
        "M\u00f2rins"
    ],
    "name:cym_x_preferred":[
        "Morini"
    ],
    "name:deu_x_preferred":[
        "Moriner"
    ],
    "name:fin_x_preferred":[
        "Morinit"
    ],
    "name:fra_x_preferred":[
        "Morins"
    ],
    "name:hun_x_preferred":[
        "Moriniak"
    ],
    "name:ita_x_preferred":[
        "Morini"
    ],
    "name:lat_x_preferred":[
        "Morini"
    ],
    "name:nld_x_preferred":[
        "Morini"
    ],
    "name:por_x_preferred":[
        "Morinos"
    ],
    "name:slv_x_preferred":[
        "Morini"
    ],
    "name:spa_x_preferred":[
        "M\u00f3rinos"
    ],
    "name:tur_x_preferred":[
        "Moriniler"
    ],
    "name:vls_x_preferred":[
        "Morini"
    ],
    "wof:name":"Morini",
    "wof:placetype":"locality",
    "wof:population":20
},
  "geometry": {"coordinates":[11.14483,45.52066],"type":"Point"}
}