{
  "type": "Feature",
  "properties": {
    "gn:admin1_code":"12",
    "gn:admin2_code":"TO",
    "gn:admin3_code":"1267.0",
    "gn:asciiname":"Appare",
    "gn:country_code":"IT",
    "gn:dem":531,
    "gn:feature_class":"P",
    "gn:feature_code":"PPL",
    "gn:name":"Appar\u00e8",
    "gn:population":61,
    "gn:timezone":"Europe/Rome",
    "iso:country":"IT",
    "name:und_x_variant":[
        "Appar\u00e8"
    ],
    "wof:name":"Appare",
    "wof:placetype":"locality",
    "wof:population":61
},
  "geometry": {"coordinates":[7.53252,45.40923],"type":"Point"}
}