{
  "type": "Feature",
  "properties": {
    "gn:admin1_code":"9",
    "gn:admin2_code":"BG",
    "gn:admin3_code":"16101.0",
    "gn:asciiname":"Marzuole di Sotto",
    "gn:country_code":"IT",
    "gn:dem":98,
    "gn:feature_class":"P",
    "gn:feature_code":"PPL",
    "gn:name":"Marzuole di Sotto",
    "gn:population":34,
    "gn:timezone":"Europe/Rome",
    "iso:country":"IT",
    "wof:name":"Marzuole di Sotto",
    "wof:placetype":"locality",
    "wof:population":34
},
  "geometry": {"coordinates":[9.81147,45.45333],"type":"Point"}
}