{
  "type": "Feature",
  "properties": {
    "gn:admin1_code":"20.0",
    "gn:admin2_code":"VI",
    "gn:admin3_code":"24084.0",
    "gn:asciiname":"Righi",
    "gn:country_code":"IT",
    "gn:dem":926,
    "gn:feature_class":"P",
    "gn:feature_code":"PPLL",
    "gn:name":"Righi",
    "gn:population":5,
    "gn:timezone":"Europe/Rome",
    "iso:country":"IT",
    "name:deu_x_preferred":[
        "Righi"
    ],
    "name:fra_x_preferred":[
        "Righi"
    ],
    "name:ita_x_preferred":[
        "Righi"
    ],
    "name:nld_x_preferred":[
        "Righi"
    ],
    "name:pol_x_preferred":[
        "Righi"
    ],
    "name:spa_x_preferred":[
        "Righi"
    ],
    "name:srp_x_preferred":[
        "Righi"
    ],
    "wof:name":"Righi",
    "wof:placetype":"locality",
    "wof:population":5
},
  "geometry": {"coordinates":[11.22381,45.67257],"type":"Point"}
}