{
  "type": "Feature",
  "properties": {
    "gn:admin1_code":"5.0",
    "gn:admin2_code":"MO",
    "gn:admin3_code":"36006.0",
    "gn:asciiname":"Panzano",
    "gn:country_code":"IT",
    "gn:dem":37,
    "gn:feature_class":"P",
    "gn:feature_code":"PPL",
    "gn:name":"Panzano",
    "gn:population":447,
    "gn:timezone":"Europe/Rome",
    "iso:country":"IT",
    "name:ceb_x_preferred":[
        "Panzano"
    ],
    "name:deu_x_preferred":[
        "Panzano"
    ],
    "name:ita_x_preferred":[
        "Panzano"
    ],
    "name:swe_x_preferred":[
        "Panzano"
    ],
    "wof:name":"Panzano",
    "wof:placetype":"locality",
    "wof:population":447
},
  "geometry": {"coordinates":[11.03995,44.6203],"type":"Point"}
}