{
  "type": "Feature",
  "properties": {
    "gn:admin1_code":"4.0",
    "gn:admin2_code":"SA",
    "gn:admin3_code":"65089.0",
    "gn:asciiname":"Bivio",
    "gn:country_code":"IT",
    "gn:dem":295,
    "gn:feature_class":"P",
    "gn:feature_code":"PPL",
    "gn:name":"Bivio",
    "gn:population":438,
    "gn:timezone":"Europe/Rome",
    "iso:country":"IT",
    "wof:name":"Bivio",
    "wof:placetype":"locality",
    "wof:population":438
},
  "geometry": {"coordinates":[15.29675,40.64018],"type":"Point"}
}