{
  "type": "Feature",
  "properties": {
    "gn:admin1_code":"4.0",
    "gn:admin2_code":"SA",
    "gn:admin3_code":"65089.0",
    "gn:asciiname":"Bivio",
    "gn:country_code":"IT",
    "gn:dem":295,
    "gn:feature_class":"P",
    "gn:feature_code":"PPL",
    "gn:name":"Bivio",
    "gn:population":438,
    "gn:timezone":"Europe/Rome",
    "iso:country":"IT",
    "name:cat_x_preferred":[
        "Bivio"
    ],
    "name:chv_x_preferred":[
        "\u0411\u0438\u0432\u0438\u043e"
    ],
    "name:deu_x_preferred":[
        "Bivio"
    ],
    "name:epo_x_preferred":[
        "Bivio"
    ],
    "name:fra_x_preferred":[
        "Bivio"
    ],
    "name:ind_x_preferred":[
        "Bivio"
    ],
    "name:ita_x_preferred":[
        "Bivio"
    ],
    "name:kaz_x_preferred":[
        "\u0411\u0438\u0432\u0438\u043e"
    ],
    "name:lat_x_preferred":[
        "Bivium"
    ],
    "name:lmo_x_preferred":[
        "Bivio"
    ],
    "name:msa_x_preferred":[
        "Bivio"
    ],
    "name:nld_x_preferred":[
        "Bivio"
    ],
    "name:nno_x_preferred":[
        "Bivio"
    ],
    "name:nor_x_preferred":[
        "Bivio"
    ],
    "name:pms_x_preferred":[
        "Bivio"
    ],
    "name:pol_x_preferred":[
        "Bivio"
    ],
    "name:por_x_preferred":[
        "Bivio"
    ],
    "name:roh_x_preferred":[
        "Beiva"
    ],
    "name:rus_x_preferred":[
        "\u0411\u0438\u0432\u0438\u043e"
    ],
    "name:spa_x_preferred":[
        "Bivio"
    ],
    "name:sqi_x_preferred":[
        "Bivio"
    ],
    "name:swe_x_preferred":[
        "Bivio"
    ],
    "name:uzb_x_preferred":[
        "Bivio"
    ],
    "name:vec_x_preferred":[
        "Bivio"
    ],
    "name:vol_x_preferred":[
        "Bivio"
    ],
    "name:war_x_preferred":[
        "Bivio"
    ],
    "name:zho_x_preferred":[
        "\u6bd4\u7dad\u5967"
    ],
    "wof:name":"Bivio",
    "wof:placetype":"locality",
    "wof:population":438
},
  "geometry": {"coordinates":[15.29675,40.64018],"type":"Point"}
}