{
  "type": "Feature",
  "properties": {
    "gn:admin1_code":"12",
    "gn:admin2_code":"VC",
    "gn:admin3_code":"2150.0",
    "gn:asciiname":"Salomino",
    "gn:country_code":"IT",
    "gn:dem":187,
    "gn:feature_class":"P",
    "gn:feature_code":"PPL",
    "gn:name":"Salomino",
    "gn:population":200,
    "gn:timezone":"Europe/Rome",
    "iso:country":"IT",
    "wof:name":"Salomino",
    "wof:placetype":"locality",
    "wof:population":200
},
  "geometry": {"coordinates":[8.14537,45.34427],"type":"Point"}
}