{
  "type": "Feature",
  "properties": {
    "gn:admin1_code":"12",
    "gn:admin2_code":"AL",
    "gn:admin3_code":"6142.0",
    "gn:asciiname":"Piepasso",
    "gn:country_code":"IT",
    "gn:dem":134,
    "gn:feature_class":"P",
    "gn:feature_code":"PPL",
    "gn:name":"Piepasso",
    "gn:population":198,
    "gn:timezone":"Europe/Rome",
    "iso:country":"IT",
    "wof:name":"Piepasso",
    "wof:placetype":"locality",
    "wof:population":198
},
  "geometry": {"coordinates":[8.3855,44.92389],"type":"Point"}
}