{
  "type": "Feature",
  "properties": {
    "gn:elevation":1176,
    "gn:population":114,
    "iso:country":"IT",
    "name:als_x_preferred":[
        "Doues"
    ],
    "name:azb_x_preferred":[
        "\u062f\u0648\u0648\u0633"
    ],
    "name:bar_x_preferred":[
        "Doues"
    ],
    "name:bel_x_preferred":[
        "\u0414\u0443\u044d"
    ],
    "name:bel_x_variant":[
        "\u0414\u0443\u0435"
    ],
    "name:bul_x_preferred":[
        "\u0414\u0443\u0435"
    ],
    "name:cat_x_preferred":[
        "Doues"
    ],
    "name:ceb_x_preferred":[
        "Doues"
    ],
    "name:deu_x_preferred":[
        "Doues"
    ],
    "name:eng_x_preferred":[
        "Doues"
    ],
    "name:epo_x_preferred":[
        "Doues"
    ],
    "name:eus_x_preferred":[
        "Doues"
    ],
    "name:fas_x_preferred":[
        "\u062f\u0648\u0648\u0633"
    ],
    "name:fra_x_preferred":[
        "Doues"
    ],
    "name:frp_x_preferred":[
        "Doues"
    ],
    "name:gsw_x_preferred":[
        "Doues"
    ],
    "name:hbs_x_preferred":[
        "Doues"
    ],
    "name:hun_x_preferred":[
        "Doues"
    ],
    "name:hye_x_preferred":[
        "\u0534\u0578\u0582\u0565"
    ],
    "name:ina_x_preferred":[
        "Doues"
    ],
    "name:ita_x_preferred":[
        "Doues"
    ],
    "name:kaz_x_preferred":[
        "\u0414\u0443\u044d"
    ],
    "name:lat_x_preferred":[
        "Dovesium"
    ],
    "name:lmo_x_preferred":[
        "Doues"
    ],
    "name:msa_x_preferred":[
        "Doues"
    ],
    "name:nap_x_preferred":[
        "Doues"
    ],
    "name:nld_x_preferred":[
        "Doues"
    ],
    "name:oci_x_preferred":[
        "Doues"
    ],
    "name:pms_x_preferred":[
        "Doues"
    ],
    "name:pol_x_preferred":[
        "Doues"
    ],
    "name:por_x_preferred":[
        "Doues"
    ],
    "name:ron_x_preferred":[
        "Doues"
    ],
    "name:rup_x_preferred":[
        "Doues"
    ],
    "name:rus_x_preferred":[
        "\u0414\u0443\u044d"
    ],
    "name:scn_x_preferred":[
        "Doues"
    ],
    "name:spa_x_preferred":[
        "Doues"
    ],
    "name:srp_x_preferred":[
        "\u0414\u0443"
    ],
    "name:srp_x_variant":[
        "Doues"
    ],
    "name:tgl_x_preferred":[
        "Doues"
    ],
    "name:ukr_x_preferred":[
        "\u0414\u0443\u0435"
    ],
    "name:uzb_x_preferred":[
        "Doues"
    ],
    "name:vie_x_preferred":[
        "Doues"
    ],
    "name:vol_x_preferred":[
        "Doues"
    ],
    "name:war_x_preferred":[
        "Doues"
    ],
    "name:zho_x_preferred":[
        "\u675c\u57c3\u65af"
    ],
    "qs:a0":"Italia",
    "qs:a1":"*Aosta#Aoste",
    "qs:a1r":"0Valle d'Aosta#Vall\u00e9e d'Aoste",
    "qs:adm0":"Italia",
    "qs:la_lc":"*",
    "qs:level":"locality",
    "qs:loc":"Doues",
    "qs:loc_alt":"Doues",
    "qs:pop":0,
    "qs:type":"buffered point",
    "wd:wordcount":15,
    "wof:lang":[
        "ita"
    ],
    "wof:name":"Doues",
    "wof:placetype":"locality",
    "wof:population":114
},
  "geometry": {"coordinates":[7.30714,45.818951],"type":"Point"}
}