{
  "type": "Feature",
  "properties": {
    "gn:admin1_code":"15",
    "gn:admin2_code":"PA",
    "gn:admin3_code":"82049.0",
    "gn:asciiname":"Cippi",
    "gn:country_code":"IT",
    "gn:dem":600,
    "gn:feature_class":"P",
    "gn:feature_code":"PPL",
    "gn:name":"Cippi",
    "gn:population":25,
    "gn:timezone":"Europe/Rome",
    "iso:country":"IT",
    "wof:name":"Cippi",
    "wof:placetype":"locality",
    "wof:population":25
},
  "geometry": {"coordinates":[13.22615,38.09999000000001],"type":"Point"}
}