{
  "type": "Feature",
  "properties": {
    "gn:admin1_code":"12",
    "gn:admin2_code":"CN",
    "gn:admin3_code":"4091.0",
    "gn:asciiname":"Chiazze",
    "gn:country_code":"IT",
    "gn:dem":618,
    "gn:feature_class":"P",
    "gn:feature_code":"PPL",
    "gn:name":"Chiazze",
    "gn:population":29,
    "gn:timezone":"Europe/Rome",
    "iso:country":"IT",
    "wof:name":"Chiazze",
    "wof:placetype":"locality",
    "wof:population":29
},
  "geometry": {"coordinates":[7.80054,44.31792],"type":"Point"}
}