{
  "type": "Feature",
  "properties": {
    "gn:admin1_code":"10.0",
    "gn:admin2_code":"PU",
    "gn:admin3_code":"41065.0",
    "gn:asciiname":"Rio Salso-Case Bernardi",
    "gn:country_code":"IT",
    "gn:dem":82,
    "gn:feature_class":"P",
    "gn:feature_code":"PPL",
    "gn:name":"Rio Salso-Case Bernardi",
    "gn:population":1425,
    "gn:timezone":"Europe/Rome",
    "iso:country":"IT",
    "wof:name":"Rio Salso-Case Bernardi",
    "wof:placetype":"locality",
    "wof:population":1425
},
  "geometry": {"coordinates":[12.69031,43.83439],"type":"Point"}
}