{
  "type": "Feature",
  "properties": {
    "gn:admin1_code":"1.0",
    "gn:admin2_code":"PE",
    "gn:admin3_code":"68012.0",
    "gn:asciiname":"Fagnani Vecchia",
    "gn:country_code":"IT",
    "gn:dem":105,
    "gn:feature_class":"P",
    "gn:feature_code":"PPL",
    "gn:name":"Fagnani Vecchia",
    "gn:population":15,
    "gn:timezone":"Europe/Rome",
    "iso:country":"IT",
    "wof:name":"Fagnani Vecchia",
    "wof:placetype":"locality",
    "wof:population":15
},
  "geometry": {"coordinates":[14.02191,42.49331],"type":"Point"}
}