{
  "type": "Feature",
  "properties": {
    "gn:admin1_code":"1",
    "gn:admin2_code":"PE",
    "gn:admin3_code":"68023.0",
    "gn:asciiname":"Tancanera",
    "gn:country_code":"IT",
    "gn:dem":515,
    "gn:feature_class":"P",
    "gn:feature_code":"PPL",
    "gn:name":"Tancanera",
    "gn:population":22,
    "gn:timezone":"Europe/Rome",
    "iso:country":"IT",
    "wof:name":"Tancanera",
    "wof:placetype":"locality",
    "wof:population":22
},
  "geometry": {"coordinates":[13.87925,42.41965],"type":"Point"}
}