{
  "type": "Feature",
  "properties": {
    "gn:admin1_code":"11",
    "gn:admin2_code":"IS",
    "gn:admin3_code":"94028.0",
    "gn:asciiname":"Mastroleoni",
    "gn:country_code":"IT",
    "gn:dem":355,
    "gn:feature_class":"P",
    "gn:feature_code":"PPL",
    "gn:name":"Mastroleoni",
    "gn:population":34,
    "gn:timezone":"Europe/Rome",
    "iso:country":"IT",
    "wof:name":"Mastroleoni",
    "wof:placetype":"locality",
    "wof:population":34
},
  "geometry": {"coordinates":[14.10032,41.54647],"type":"Point"}
}