{
  "type": "Feature",
  "properties": {
    "gn:admin1_code":"5.0",
    "gn:admin2_code":"PR",
    "gn:admin3_code":"34033.0",
    "gn:asciiname":"Ronchetti",
    "gn:country_code":"IT",
    "gn:dem":37,
    "gn:elevation":"39.0",
    "gn:feature_class":"P",
    "gn:feature_code":"PPL",
    "gn:name":"Ronchetti",
    "gn:population":27,
    "gn:timezone":"Europe/Rome",
    "iso:country":"IT",
    "wof:name":"Ronchetti",
    "wof:placetype":"locality",
    "wof:population":27
},
  "geometry": {"coordinates":[10.23675,44.89786],"type":"Point"}
}