{
  "type": "Feature",
  "properties": {
    "gn:admin1_code":"12",
    "gn:admin2_code":"AT",
    "gn:admin3_code":"5065.0",
    "gn:asciiname":"Casalotto",
    "gn:country_code":"IT",
    "gn:dem":229,
    "gn:feature_class":"P",
    "gn:feature_code":"PPL",
    "gn:name":"Casalotto",
    "gn:population":64,
    "gn:timezone":"Europe/Rome",
    "iso:country":"IT",
    "wof:name":"Casalotto",
    "wof:placetype":"locality",
    "wof:population":64
},
  "geometry": {"coordinates":[8.4126,44.76214],"type":"Point"}
}