{
  "type": "Feature",
  "properties": {
    "gn:admin1_code":"17",
    "gn:admin2_code":"TN",
    "gn:admin3_code":"22210.0",
    "gn:asciiname":"Martini",
    "gn:country_code":"IT",
    "gn:dem":882,
    "gn:feature_class":"P",
    "gn:feature_code":"PPL",
    "gn:name":"Martini",
    "gn:population":86,
    "gn:timezone":"Europe/Rome",
    "iso:country":"IT",
    "name:ara_x_preferred":[
        "\u0645\u0627\u0631\u062a\u064a\u0646\u064a"
    ],
    "name:bre_x_preferred":[
        "Martini"
    ],
    "name:bul_x_preferred":[
        "\u041c\u0430\u0440\u0442\u0438\u043d\u0438"
    ],
    "name:ceb_x_preferred":[
        "Martini"
    ],
    "name:ces_x_preferred":[
        "Martini"
    ],
    "name:deu_x_preferred":[
        "Martini"
    ],
    "name:fin_x_preferred":[
        "Martini"
    ],
    "name:fra_x_preferred":[
        "Martini"
    ],
    "name:heb_x_preferred":[
        "\u05de\u05e8\u05d8\u05d9\u05e0\u05d9"
    ],
    "name:hun_x_preferred":[
        "Martini"
    ],
    "name:hye_x_preferred":[
        "\u0544\u0561\u0580\u057f\u056b\u0576\u056b"
    ],
    "name:ind_x_preferred":[
        "Martini"
    ],
    "name:ita_x_preferred":[
        "Martini"
    ],
    "name:jpn_x_preferred":[
        "\u30de\u30eb\u30c6\u30a3\u30fc\u30cb"
    ],
    "name:nld_x_preferred":[
        "Martini"
    ],
    "name:nor_x_preferred":[
        "Martini"
    ],
    "name:pol_x_preferred":[
        "Martini"
    ],
    "name:rus_x_preferred":[
        "\u041c\u0430\u0440\u0442\u0438\u043d\u0438"
    ],
    "name:spa_x_preferred":[
        "Martini"
    ],
    "name:srp_x_preferred":[
        "Martini"
    ],
    "name:swe_x_preferred":[
        "Martini"
    ],
    "name:tur_x_preferred":[
        "Martini"
    ],
    "name:ukr_x_preferred":[
        "\u041c\u0430\u0440\u0442\u0456\u043d\u0456"
    ],
    "wof:name":"Martini",
    "wof:placetype":"locality",
    "wof:population":86
},
  "geometry": {"coordinates":[11.13314,45.77294000000001],"type":"Point"}
}