{
  "type": "Feature",
  "properties": {
    "gn:admin1_code":"17",
    "gn:admin2_code":"TN",
    "gn:admin3_code":"22210.0",
    "gn:asciiname":"Martini",
    "gn:country_code":"IT",
    "gn:dem":882,
    "gn:feature_class":"P",
    "gn:feature_code":"PPL",
    "gn:name":"Martini",
    "gn:population":86,
    "gn:timezone":"Europe/Rome",
    "iso:country":"IT",
    "wof:name":"Martini",
    "wof:placetype":"locality",
    "wof:population":86
},
  "geometry": {"coordinates":[11.13314,45.77294000000001],"type":"Point"}
}