{
  "type": "Feature",
  "properties": {
    "gn:admin1_code":"16",
    "gn:admin2_code":"SI",
    "gn:admin3_code":"52022.0",
    "gn:asciiname":"San Giorgio",
    "gn:country_code":"IT",
    "gn:dem":235,
    "gn:feature_class":"P",
    "gn:feature_code":"PPL",
    "gn:name":"San Giorgio",
    "gn:population":44,
    "gn:timezone":"Europe/Rome",
    "iso:country":"IT",
    "wof:name":"San Giorgio",
    "wof:placetype":"locality",
    "wof:population":44
},
  "geometry": {"coordinates":[11.17135,43.49768],"type":"Point"}
}