{
  "type": "Feature",
  "properties": {
    "gn:admin1_code":"12.0",
    "gn:admin2_code":"CN",
    "gn:admin3_code":"4028.0",
    "gn:asciiname":"Tetti Linda",
    "gn:country_code":"IT",
    "gn:dem":672,
    "gn:feature_class":"P",
    "gn:feature_code":"PPL",
    "gn:name":"Tetti Linda",
    "gn:population":27,
    "gn:timezone":"Europe/Rome",
    "iso:country":"IT",
    "wof:name":"Tetti Linda",
    "wof:placetype":"locality",
    "wof:population":27
},
  "geometry": {"coordinates":[7.57048,44.30878],"type":"Point"}
}