{
  "type": "Feature",
  "properties": {
    "gn:admin1_code":"7.0",
    "gn:admin2_code":"RM",
    "gn:admin3_code":"58050.0",
    "gn:asciiname":"Casale Nuovo Presciano",
    "gn:cc2":"IT",
    "gn:country_code":"IT",
    "gn:dem":98,
    "gn:feature_class":"P",
    "gn:feature_code":"PPL",
    "gn:name":"Casale Nuovo Presciano",
    "gn:population":0,
    "gn:timezone":"Europe/Rome",
    "iso:country":"IT",
    "name:und_x_variant":[
        "Casale Nuovo di Presciano"
    ],
    "wof:name":"Casale Nuovo Presciano",
    "wof:placetype":"locality"
},
  "geometry": {"coordinates":[12.71221,41.62443],"type":"Point"}
}