{
  "type": "Feature",
  "properties": {
    "gn:admin1_code":"9",
    "gn:admin2_code":"PV",
    "gn:admin3_code":"18047.0",
    "gn:asciiname":"San Gaudenzio",
    "gn:country_code":"IT",
    "gn:dem":74,
    "gn:feature_class":"P",
    "gn:feature_code":"PPL",
    "gn:name":"San Gaudenzio",
    "gn:population":61,
    "gn:timezone":"Europe/Rome",
    "iso:country":"IT",
    "wof:name":"San Gaudenzio",
    "wof:placetype":"locality",
    "wof:population":61
},
  "geometry": {"coordinates":[9.00503,45.04717],"type":"Point"}
}