{
  "type": "Feature",
  "properties": {
    "gn:admin1_code":"12.0",
    "gn:admin2_code":"NO",
    "gn:admin3_code":"3032.0",
    "gn:asciiname":"Due Fontane",
    "gn:country_code":"IT",
    "gn:dem":160,
    "gn:feature_class":"P",
    "gn:feature_code":"PPLL",
    "gn:name":"Due Fontane",
    "gn:population":2,
    "gn:timezone":"Europe/Rome",
    "iso:country":"IT",
    "wof:name":"Due Fontane",
    "wof:placetype":"locality",
    "wof:population":2
},
  "geometry": {"coordinates":[8.62952,45.49377],"type":"Point"}
}