{
  "type": "Feature",
  "properties": {
    "gn:admin1_code":"8",
    "gn:admin2_code":"SP",
    "gn:admin3_code":"11008.0",
    "gn:asciiname":"Ferdana",
    "gn:country_code":"IT",
    "gn:dem":144,
    "gn:feature_class":"P",
    "gn:feature_code":"PPL",
    "gn:name":"Ferdana",
    "gn:population":27,
    "gn:timezone":"Europe/Rome",
    "iso:country":"IT",
    "wof:name":"Ferdana",
    "wof:placetype":"locality",
    "wof:population":27
},
  "geometry": {"coordinates":[9.82634,44.22722],"type":"Point"}
}