{
  "type": "Feature",
  "properties": {
    "gn:admin1_code":"9",
    "gn:admin2_code":"LO",
    "gn:admin3_code":"98040.0",
    "gn:asciiname":"Arcagna",
    "gn:country_code":"IT",
    "gn:dem":82,
    "gn:feature_class":"P",
    "gn:feature_code":"PPL",
    "gn:name":"Arcagna",
    "gn:population":262,
    "gn:timezone":"Europe/Rome",
    "iso:country":"IT",
    "wof:name":"Arcagna",
    "wof:placetype":"locality",
    "wof:population":262
},
  "geometry": {"coordinates":[9.4517,45.34319],"type":"Point"}
}