{
  "type": "Feature",
  "properties": {
    "gn:admin1_code":"4",
    "gn:admin2_code":"AV",
    "gn:admin3_code":"64049.0",
    "gn:asciiname":"Serroni B",
    "gn:country_code":"IT",
    "gn:dem":431,
    "gn:feature_class":"P",
    "gn:feature_code":"PPL",
    "gn:name":"Serroni B",
    "gn:population":30,
    "gn:timezone":"Europe/Rome",
    "iso:country":"IT",
    "wof:name":"Serroni B",
    "wof:placetype":"locality",
    "wof:population":30
},
  "geometry": {"coordinates":[14.75659,40.91332],"type":"Point"}
}