{
  "type": "Feature",
  "properties": {
    "gn:admin1_code":"9",
    "gn:admin2_code":"MN",
    "gn:admin3_code":"20026.0",
    "gn:asciiname":"Calliera",
    "gn:country_code":"IT",
    "gn:dem":34,
    "gn:feature_class":"P",
    "gn:feature_code":"PPL",
    "gn:name":"Calliera",
    "gn:population":212,
    "gn:timezone":"Europe/Rome",
    "iso:country":"IT",
    "wof:name":"Calliera",
    "wof:placetype":"locality",
    "wof:population":212
},
  "geometry": {"coordinates":[10.6523,45.23617],"type":"Point"}
}