{
  "type": "Feature",
  "properties": {
    "gn:admin1_code":"18.0",
    "gn:admin2_code":"PG",
    "gn:admin3_code":"54015.0",
    "gn:asciiname":"La Trinita",
    "gn:country_code":"IT",
    "gn:dem":604,
    "gn:feature_class":"P",
    "gn:feature_code":"PPL",
    "gn:name":"La Trinit\u00e0",
    "gn:population":396,
    "gn:timezone":"Europe/Rome",
    "iso:country":"IT",
    "name:und_x_variant":[
        "La Trinit\u00e0"
    ],
    "wof:name":"La Trinita",
    "wof:placetype":"locality",
    "wof:population":396
},
  "geometry": {"coordinates":[12.30825,43.12215],"type":"Point"}
}