{
  "type": "Feature",
  "properties": {
    "gn:admin1_code":"18",
    "gn:admin2_code":"PG",
    "gn:admin3_code":"54051.0",
    "gn:asciiname":"Fabbreria",
    "gn:country_code":"IT",
    "gn:dem":276,
    "gn:feature_class":"P",
    "gn:feature_code":"PPL",
    "gn:name":"Fabbreria",
    "gn:population":49,
    "gn:timezone":"Europe/Rome",
    "iso:country":"IT",
    "wof:name":"Fabbreria",
    "wof:placetype":"locality",
    "wof:population":49
},
  "geometry": {"coordinates":[12.76926,42.77447],"type":"Point"}
}