{
  "type": "Feature",
  "properties": {
    "gn:admin1_code":"15",
    "gn:admin2_code":"TP",
    "gn:admin3_code":"81022.0",
    "gn:asciiname":"Iacono Pietro",
    "gn:country_code":"IT",
    "gn:dem":226,
    "gn:feature_class":"P",
    "gn:feature_code":"PPL",
    "gn:name":"Iacono Pietro",
    "gn:population":25,
    "gn:timezone":"Europe/Rome",
    "iso:country":"IT",
    "wof:name":"Iacono Pietro",
    "wof:placetype":"locality",
    "wof:population":25
},
  "geometry": {"coordinates":[12.63942,38.03228],"type":"Point"}
}