{
  "type": "Feature",
  "properties": {
    "gn:admin1_code":"5",
    "gn:admin2_code":"PR",
    "gn:admin3_code":"34008.0",
    "gn:asciiname":"Ronzano",
    "gn:country_code":"IT",
    "gn:dem":449,
    "gn:feature_class":"P",
    "gn:feature_code":"PPL",
    "gn:name":"Ronzano",
    "gn:population":25,
    "gn:timezone":"Europe/Rome",
    "iso:country":"IT",
    "wof:name":"Ronzano",
    "wof:placetype":"locality",
    "wof:population":25
},
  "geometry": {"coordinates":[10.15298,44.61373],"type":"Point"}
}