{
  "type": "Feature",
  "properties": {
    "gn:admin1_code":"5.0",
    "gn:admin2_code":"RA",
    "gn:admin3_code":"39010.0",
    "gn:asciiname":"Pila Sant'Andrea",
    "gn:country_code":"IT",
    "gn:dem":17,
    "gn:feature_class":"P",
    "gn:feature_code":"PPL",
    "gn:name":"Pila Sant'Andrea",
    "gn:population":30,
    "gn:timezone":"Europe/Rome",
    "iso:country":"IT",
    "wof:name":"Pila Sant'Andrea",
    "wof:placetype":"locality",
    "wof:population":30
},
  "geometry": {"coordinates":[11.91719,44.33561],"type":"Point"}
}