{
  "type": "Feature",
  "properties": {
    "gn:admin1_code":"1.0",
    "gn:admin2_code":"AQ",
    "gn:admin3_code":"66056.0",
    "gn:asciiname":"Verrico",
    "gn:country_code":"IT",
    "gn:dem":1196,
    "gn:elevation":"1202.0",
    "gn:feature_class":"P",
    "gn:feature_code":"PPL",
    "gn:name":"Verrico",
    "gn:population":77,
    "gn:timezone":"Europe/Rome",
    "iso:country":"IT",
    "wof:name":"Verrico",
    "wof:placetype":"locality",
    "wof:population":77
},
  "geometry": {"coordinates":[13.21009,42.56141],"type":"Point"}
}