{
  "type": "Feature",
  "properties": {
    "gn:admin1_code":"17.0",
    "gn:admin2_code":"BZ",
    "gn:admin3_code":"21034.0",
    "gn:asciiname":"Zona Industriale",
    "gn:country_code":"IT",
    "gn:dem":837,
    "gn:feature_class":"P",
    "gn:feature_code":"PPL",
    "gn:name":"Zona Industriale",
    "gn:population":11,
    "gn:timezone":"Europe/Rome",
    "iso:country":"IT",
    "name:deu_x_preferred":[
        "Zona Industriale"
    ],
    "name:fra_x_preferred":[
        "Zona Industriale"
    ],
    "name:ita_x_preferred":[
        "Zona Industriale"
    ],
    "name:nap_x_preferred":[
        "Zona Nnustriale"
    ],
    "wof:name":"Zona Industriale",
    "wof:placetype":"locality",
    "wof:population":11
},
  "geometry": {"coordinates":[11.95366,46.84568],"type":"Point"}
}