{
  "type": "Feature",
  "properties": {
    "gn:admin1_code":"12",
    "gn:admin2_code":"NO",
    "gn:admin3_code":"3082.0",
    "gn:asciiname":"Monticelli",
    "gn:country_code":"IT",
    "gn:dem":381,
    "gn:feature_class":"P",
    "gn:feature_code":"PPL",
    "gn:name":"Monticelli",
    "gn:population":44,
    "gn:timezone":"Europe/Rome",
    "iso:country":"IT",
    "wof:name":"Monticelli",
    "wof:placetype":"locality",
    "wof:population":44
},
  "geometry": {"coordinates":[8.46546,45.74918],"type":"Point"}
}