{
  "type": "Feature",
  "properties": {
    "gn:admin1_code":"12",
    "gn:admin2_code":"TO",
    "gn:admin3_code":"1186.0",
    "gn:asciiname":"Saretto",
    "gn:country_code":"IT",
    "gn:dem":1212,
    "gn:feature_class":"P",
    "gn:feature_code":"PPLL",
    "gn:name":"Saretto",
    "gn:population":9,
    "gn:timezone":"Europe/Rome",
    "iso:country":"IT",
    "wof:name":"Saretto",
    "wof:placetype":"locality",
    "wof:population":9
},
  "geometry": {"coordinates":[7.09352,44.95069],"type":"Point"}
}