{
  "type": "Feature",
  "properties": {
    "gn:admin1_code":"16",
    "gn:admin2_code":"PI",
    "gn:admin3_code":"50029.0",
    "gn:asciiname":"Contrada Martinelli",
    "gn:country_code":"IT",
    "gn:dem":11,
    "gn:feature_class":"P",
    "gn:feature_code":"PPLL",
    "gn:name":"Contrada Martinelli",
    "gn:population":8,
    "gn:timezone":"Europe/Rome",
    "iso:country":"IT",
    "wof:name":"Contrada Martinelli",
    "wof:placetype":"locality",
    "wof:population":8
},
  "geometry": {"coordinates":[10.5874,43.66465],"type":"Point"}
}