{
  "type": "Feature",
  "properties": {
    "gn:admin1_code":"7.0",
    "gn:admin2_code":"RI",
    "gn:admin3_code":"57040.0",
    "gn:asciiname":"Sargnano II",
    "gn:country_code":"IT",
    "gn:dem":261,
    "gn:feature_class":"P",
    "gn:feature_code":"PPL",
    "gn:name":"Sargnano II",
    "gn:population":34,
    "gn:timezone":"Europe/Rome",
    "iso:country":"IT",
    "wof:name":"Sargnano II",
    "wof:placetype":"locality",
    "wof:population":34
},
  "geometry": {"coordinates":[12.58344,42.36929],"type":"Point"}
}