{
  "type": "Feature",
  "properties": {
    "gn:admin1_code":"4.0",
    "gn:admin2_code":"CE",
    "gn:admin3_code":"61094.0",
    "gn:asciiname":"Trentola-Ducenta",
    "gn:country_code":"IT",
    "gn:dem":46,
    "gn:elevation":"42.0",
    "gn:feature_class":"P",
    "gn:feature_code":"PPLA3",
    "gn:name":"Trentola-Ducenta",
    "gn:population":17056,
    "gn:timezone":"Europe/Rome",
    "iso:country":"IT",
    "name:eng_x_preferred":[
        "Trentola-Ducenta"
    ],
    "name:epo_x_preferred":[
        "Trentola-Ducenta"
    ],
    "name:fra_x_preferred":[
        "Trentola-Ducenta"
    ],
    "name:ita_x_preferred":[
        "Trentola-Ducenta"
    ],
    "name:nap_x_preferred":[
        "Trentola-Ducenta"
    ],
    "name:nld_x_preferred":[
        "Trentola-Ducenta"
    ],
    "name:pol_x_preferred":[
        "Trentola-Ducenta"
    ],
    "name:por_x_preferred":[
        "Trentola-Ducenta"
    ],
    "name:und_x_variant":[
        "Tr\u00e9ntola-Ducenta"
    ],
    "wof:name":"Trentola-Ducenta",
    "wof:placetype":"locality",
    "wof:population":17056
},
  "geometry": {"coordinates":[14.1749,40.97517],"type":"Point"}
}