{
  "type": "Feature",
  "properties": {
    "gn:admin1_code":"16.0",
    "gn:admin2_code":"FI",
    "gn:admin3_code":"48018.0",
    "gn:asciiname":"Collino",
    "gn:country_code":"IT",
    "gn:dem":500,
    "gn:feature_class":"P",
    "gn:feature_code":"PPL",
    "gn:name":"Collino",
    "gn:population":0,
    "gn:timezone":"Europe/Rome",
    "iso:country":"IT",
    "wof:name":"Collino",
    "wof:placetype":"locality"
},
  "geometry": {"coordinates":[11.33333,44.11667],"type":"Point"}
}