{
  "type": "Feature",
  "properties": {
    "gn:admin1_code":"20",
    "gn:admin2_code":"VI",
    "gn:admin3_code":"24084.0",
    "gn:asciiname":"Branchi",
    "gn:country_code":"IT",
    "gn:dem":648,
    "gn:feature_class":"P",
    "gn:feature_code":"PPL",
    "gn:name":"Branchi",
    "gn:population":69,
    "gn:timezone":"Europe/Rome",
    "iso:country":"IT",
    "wof:name":"Branchi",
    "wof:placetype":"locality",
    "wof:population":69
},
  "geometry": {"coordinates":[11.25561,45.70871],"type":"Point"}
}