{
  "type": "Feature",
  "properties": {
    "gn:admin1_code":"12",
    "gn:admin2_code":"TO",
    "gn:admin3_code":"1300.0",
    "gn:asciiname":"Roncalermo",
    "gn:country_code":"IT",
    "gn:dem":260,
    "gn:feature_class":"P",
    "gn:feature_code":"PPL",
    "gn:name":"Roncalermo",
    "gn:population":17,
    "gn:timezone":"Europe/Rome",
    "iso:country":"IT",
    "wof:name":"Roncalermo",
    "wof:placetype":"locality",
    "wof:population":17
},
  "geometry": {"coordinates":[7.48527,44.80236],"type":"Point"}
}