{
  "type": "Feature",
  "properties": {
    "gn:admin1_code":"1",
    "gn:admin2_code":"CH",
    "gn:admin3_code":"69094.0",
    "gn:asciiname":"Fondo Valle Alento",
    "gn:country_code":"IT",
    "gn:dem":28,
    "gn:feature_class":"P",
    "gn:feature_code":"PPL",
    "gn:name":"Fondo Valle Alento",
    "gn:population":332,
    "gn:timezone":"Europe/Rome",
    "iso:country":"IT",
    "wof:name":"Fondo Valle Alento",
    "wof:placetype":"locality",
    "wof:population":332
},
  "geometry": {"coordinates":[14.25665,42.40174],"type":"Point"}
}