{
  "type": "Feature",
  "properties": {
    "gn:country":"IT",
    "gn:fcode":"PPLL",
    "gn:population":0,
    "iso:country":"IT",
    "qs_pg:aaroncc":"IT",
    "qs_pg:gn_country":"IT",
    "qs_pg:gn_fcode":"PPLL",
    "qs_pg:gn_pop":0,
    "qs_pg:name":"Vorno",
    "qs_pg:name_adm0":"Italia",
    "qs_pg:name_adm1":"Toscana",
    "qs_pg:photos":123,
    "qs_pg:photos_1k":25,
    "qs_pg:photos_9k":1,
    "qs_pg:photos_9r":3,
    "qs_pg:photos_all":123,
    "qs_pg:photos_sr":3,
    "qs_pg:pop_sr":0,
    "qs_pg:qs_pg_placetype":"locality",
    "qs_pg:qs_pg_placetype_gp":"Town",
    "qs_pg:woe_adm0":23424853,
    "woe:adm0_id":23424853,
    "woe:name_adm0":"Italia",
    "woe:name_adm1":"Toscana",
    "woe:placetype":"Town",
    "wof:name":"Vorno",
    "wof:placetype":"locality"
},
  "geometry": {"coordinates":[10.511,43.78998],"type":"Point"}
}