{
  "type": "Feature",
  "properties": {
    "gn:admin1_code":"5",
    "gn:admin2_code":"PR",
    "gn:admin3_code":"34005.0",
    "gn:asciiname":"Zermani",
    "gn:country_code":"IT",
    "gn:dem":654,
    "gn:feature_class":"P",
    "gn:feature_code":"PPL",
    "gn:name":"Zermani",
    "gn:population":14,
    "gn:timezone":"Europe/Rome",
    "iso:country":"IT",
    "wof:name":"Zermani",
    "wof:placetype":"locality",
    "wof:population":14
},
  "geometry": {"coordinates":[9.78876,44.70242],"type":"Point"}
}