{
  "type": "Feature",
  "properties": {
    "gn:admin1_code":"16",
    "gn:admin2_code":"SI",
    "gn:admin3_code":"52006.0",
    "gn:asciiname":"Guistrigona",
    "gn:country_code":"IT",
    "gn:dem":273,
    "gn:feature_class":"P",
    "gn:feature_code":"PPL",
    "gn:name":"Guistrigona",
    "gn:population":48,
    "gn:timezone":"Europe/Rome",
    "iso:country":"IT",
    "wof:name":"Guistrigona",
    "wof:placetype":"locality",
    "wof:population":48
},
  "geometry": {"coordinates":[11.48438,43.32317000000001],"type":"Point"}
}