{
  "type": "Feature",
  "properties": {
    "gn:admin1_code":"20",
    "gn:admin2_code":"BL",
    "gn:admin3_code":"25045.0",
    "gn:asciiname":"Velos",
    "gn:country_code":"IT",
    "gn:dem":364,
    "gn:feature_class":"P",
    "gn:feature_code":"PPL",
    "gn:name":"Velos",
    "gn:population":24,
    "gn:timezone":"Europe/Rome",
    "iso:country":"IT",
    "name:deu_x_preferred":[
        "Velos"
    ],
    "name:ell_x_preferred":[
        "\u0392\u03ad\u03bb\u03bf\u03c2"
    ],
    "name:pol_x_preferred":[
        "Velos"
    ],
    "wof:name":"Velos",
    "wof:placetype":"locality",
    "wof:population":24
},
  "geometry": {"coordinates":[12.02444,46.09255],"type":"Point"}
}