{
  "type": "Feature",
  "properties": {
    "gn:gn_country":"IT",
    "gn:gn_fcode":"PPLA3",
    "gn:gn_pop":195,
    "gn:population":140,
    "iso:country":"IT",
    "name:bel_x_preferred":[
        "\u041b\u0456\u0433\u0430\u0437\u0443\u043b\u0430"
    ],
    "name:bul_x_preferred":[
        "\u041b\u0438\u0433\u043e\u0437\u0443\u043b\u043e"
    ],
    "name:cat_x_preferred":[
        "Ligosullo"
    ],
    "name:deu_x_preferred":[
        "Ligosullo"
    ],
    "name:eng_x_preferred":[
        "Ligosullo"
    ],
    "name:epo_x_preferred":[
        "Ligosullo"
    ],
    "name:eus_x_preferred":[
        "Ligosullo"
    ],
    "name:fas_x_preferred":[
        "\u0644\u06cc\u06af\u0648\u0633\u0648\u0644\u0648"
    ],
    "name:fra_x_preferred":[
        "Ligosullo"
    ],
    "name:fur_x_preferred":[
        "Livussul"
    ],
    "name:hun_x_preferred":[
        "Ligosullo"
    ],
    "name:hye_x_preferred":[
        "\u053c\u056b\u0563\u0578\u057d\u0578\u0582\u056c\u0578"
    ],
    "name:ina_x_preferred":[
        "Ligosullo"
    ],
    "name:ind_x_preferred":[
        "Ligosullo"
    ],
    "name:ita_x_preferred":[
        "Ligosullo"
    ],
    "name:jpn_x_preferred":[
        "\u30ea\u30b4\u30b9\u30c3\u30ed"
    ],
    "name:kaz_x_preferred":[
        "\u041b\u0438\u0433\u043e\u0437\u0443\u043b\u043b\u043e"
    ],
    "name:lat_x_preferred":[
        "Ligosullum"
    ],
    "name:lmo_x_preferred":[
        "Ligosullo"
    ],
    "name:msa_x_preferred":[
        "Ligosullo"
    ],
    "name:nan_x_preferred":[
        "Ligosullo"
    ],
    "name:nap_x_preferred":[
        "Ligosullo"
    ],
    "name:nld_x_preferred":[
        "Ligosullo"
    ],
    "name:oci_x_preferred":[
        "Ligosullo"
    ],
    "name:pms_x_preferred":[
        "Ligosullo"
    ],
    "name:pol_x_preferred":[
        "Ligosullo"
    ],
    "name:por_x_preferred":[
        "Ligosullo"
    ],
    "name:ron_x_preferred":[
        "Ligosullo"
    ],
    "name:rus_x_preferred":[
        "\u041b\u0438\u0433\u043e\u0437\u0443\u043b\u043b\u043e"
    ],
    "name:scn_x_preferred":[
        "Ligosullo"
    ],
    "name:spa_x_preferred":[
        "Ligosullo"
    ],
    "name:srp_x_preferred":[
        "Ligosullo"
    ],
    "name:ukr_x_preferred":[
        "\u041b\u0456\u0433\u043e\u0437\u0443\u043b\u043b\u043e"
    ],
    "name:uzb_x_preferred":[
        "Ligosullo"
    ],
    "name:vie_x_preferred":[
        "Ligosullo"
    ],
    "name:vol_x_preferred":[
        "Ligosullo"
    ],
    "name:war_x_preferred":[
        "Ligosullo"
    ],
    "name:zho_x_preferred":[
        "\u5229\u6208\u82cf\u6d1b"
    ],
    "qs_pg:aaroncc":"IT",
    "qs_pg:gn_country":"IT",
    "qs_pg:gn_fcode":"PPLA3",
    "qs_pg:gn_pop":195,
    "qs_pg:name":"Ligosullo",
    "qs_pg:name_adm0":"Italia",
    "qs_pg:name_adm1":"Friuli-Venezia Giulia",
    "qs_pg:photos_9k":1,
    "qs_pg:photos_9r":1,
    "qs_pg:photos_all":1,
    "qs_pg:photos_sr":0,
    "qs_pg:pop_sr":1,
    "qs_pg:qs_pg_placetype":"locality",
    "qs_pg:qs_pg_placetype_gp":"Town",
    "qs_pg:woe_adm0":23424853,
    "woe:adm0_id":23424853,
    "woe:name_adm0":"Italia",
    "woe:name_adm1":"Friuli-Venezia Giulia",
    "woe:placetype":"Town",
    "wof:name":"Ligosullo",
    "wof:placetype":"locality",
    "wof:population":140
},
  "geometry": {"coordinates":[13.08028,46.54278],"type":"Point"}
}