{
  "type": "Feature",
  "properties": {
    "gn:admin1_code":"15",
    "gn:admin2_code":"TP",
    "gn:admin3_code":"81024.0",
    "gn:asciiname":"Torreggiani",
    "gn:country_code":"IT",
    "gn:dem":12,
    "gn:feature_class":"P",
    "gn:feature_code":"PPL",
    "gn:name":"Torreggiani",
    "gn:population":27,
    "gn:timezone":"Europe/Rome",
    "iso:country":"IT",
    "wof:name":"Torreggiani",
    "wof:placetype":"locality",
    "wof:population":27
},
  "geometry": {"coordinates":[12.49374,37.72998],"type":"Point"}
}