{
  "type": "Feature",
  "properties": {
    "gn:admin1_code":"20",
    "gn:admin2_code":"VR",
    "gn:admin3_code":"23078.0",
    "gn:asciiname":"Ronconi",
    "gn:country_code":"IT",
    "gn:dem":957,
    "gn:feature_class":"P",
    "gn:feature_code":"PPL",
    "gn:name":"Ronconi",
    "gn:population":93,
    "gn:timezone":"Europe/Rome",
    "iso:country":"IT",
    "wof:name":"Ronconi",
    "wof:placetype":"locality",
    "wof:population":93
},
  "geometry": {"coordinates":[10.96441,45.6388],"type":"Point"}
}