{
  "type": "Feature",
  "properties": {
    "iso:country":"IT",
    "name:arg_x_preferred":[
        "Centro"
    ],
    "name:cat_x_preferred":[
        "Centro"
    ],
    "name:ceb_x_preferred":[
        "Centro"
    ],
    "name:ces_x_preferred":[
        "Centro"
    ],
    "name:deu_x_preferred":[
        "Centro"
    ],
    "name:ell_x_preferred":[
        "\u039a\u03ad\u03bd\u03c4\u03c1\u03bf"
    ],
    "name:epo_x_preferred":[
        "Centro"
    ],
    "name:eus_x_preferred":[
        "Centro"
    ],
    "name:fra_x_preferred":[
        "Centro"
    ],
    "name:glg_x_preferred":[
        "Centro"
    ],
    "name:ido_x_preferred":[
        "Centro"
    ],
    "name:ita_x_preferred":[
        "Centro"
    ],
    "name:jpn_x_preferred":[
        "\u30bb\u30f3\u30c8\u30ed"
    ],
    "name:kor_x_preferred":[
        "\uc13c\ud2b8\ub85c"
    ],
    "name:nld_x_preferred":[
        "Centro"
    ],
    "name:pol_x_preferred":[
        "Centro"
    ],
    "name:por_x_preferred":[
        "Centro"
    ],
    "name:rus_x_preferred":[
        "\u0421\u0435\u043d\u0442\u0440\u043e"
    ],
    "name:sco_x_preferred":[
        "Centro"
    ],
    "name:slk_x_preferred":[
        "Centro"
    ],
    "name:spa_x_preferred":[
        "Centro"
    ],
    "name:srp_x_preferred":[
        "Centro"
    ],
    "name:swe_x_preferred":[
        "Centro"
    ],
    "name:vie_x_preferred":[
        "Centro"
    ],
    "wof:name":"Centro",
    "wof:placetype":"neighbourhood"
},
  "geometry": {"coordinates":[11.25457511036344,43.77211557099474],"type":"Point"}
}