{
  "type": "Feature",
  "properties": {
    "iso:country":"IT",
    "wof:name":"Centro",
    "wof:placetype":"neighbourhood"
},
  "geometry": {"coordinates":[11.25457511036344,43.77211557099474],"type":"Point"}
}