{
  "type": "Feature",
  "properties": {
    "gn:admin1_code":"7.0",
    "gn:admin2_code":"FR",
    "gn:admin3_code":"60020.0",
    "gn:asciiname":"Localita Aringo",
    "gn:country_code":"IT",
    "gn:dem":207,
    "gn:feature_class":"P",
    "gn:feature_code":"PPL",
    "gn:name":"Localit\u00e0 Aringo",
    "gn:population":34,
    "gn:timezone":"Europe/Rome",
    "iso:country":"IT",
    "name:und_x_variant":[
        "Localit\u00e0 Aringo"
    ],
    "wof:name":"Localita Aringo",
    "wof:placetype":"locality",
    "wof:population":34
},
  "geometry": {"coordinates":[13.55468,41.66467],"type":"Point"}
}