{
  "type": "Feature",
  "properties": {
    "gn:admin1_code":"20",
    "gn:admin2_code":"VI",
    "gn:admin3_code":"24090.0",
    "gn:asciiname":"Legato",
    "gn:country_code":"IT",
    "gn:dem":213,
    "gn:feature_class":"P",
    "gn:feature_code":"PPL",
    "gn:name":"Legato",
    "gn:population":27,
    "gn:timezone":"Europe/Rome",
    "iso:country":"IT",
    "wof:name":"Legato",
    "wof:placetype":"locality",
    "wof:population":27
},
  "geometry": {"coordinates":[11.59279,45.75859000000001],"type":"Point"}
}