{
  "type": "Feature",
  "properties": {
    "gn:admin1_code":"20",
    "gn:admin2_code":"VI",
    "gn:admin3_code":"24090.0",
    "gn:asciiname":"Legato",
    "gn:country_code":"IT",
    "gn:dem":213,
    "gn:feature_class":"P",
    "gn:feature_code":"PPL",
    "gn:name":"Legato",
    "gn:population":27,
    "gn:timezone":"Europe/Rome",
    "iso:country":"IT",
    "name:bel_x_preferred":[
        "\u041b\u0435\u0433\u0430\u0442\u0430"
    ],
    "name:cat_x_preferred":[
        "Legato"
    ],
    "name:ces_x_preferred":[
        "Legato"
    ],
    "name:deu_x_preferred":[
        "Legato"
    ],
    "name:epo_x_preferred":[
        "Legato"
    ],
    "name:est_x_preferred":[
        "Legaato"
    ],
    "name:fas_x_preferred":[
        "\u0644\u06af\u0627\u062a\u0648"
    ],
    "name:fin_x_preferred":[
        "Legato"
    ],
    "name:fra_x_preferred":[
        "Legato"
    ],
    "name:glg_x_preferred":[
        "Legato"
    ],
    "name:hun_x_preferred":[
        "Legato"
    ],
    "name:ind_x_preferred":[
        "Legato"
    ],
    "name:jpn_x_preferred":[
        "\u30ec\u30ac\u30fc\u30c8"
    ],
    "name:kat_x_preferred":[
        "\u10da\u10d4\u10d2\u10d0\u10e2\u10dd"
    ],
    "name:nld_x_preferred":[
        "Legato"
    ],
    "name:nor_x_preferred":[
        "Legato"
    ],
    "name:oci_x_preferred":[
        "Legato"
    ],
    "name:pol_x_preferred":[
        "Legato"
    ],
    "name:por_x_preferred":[
        "Legato"
    ],
    "name:rus_x_preferred":[
        "\u041b\u0435\u0433\u0430\u0442\u043e"
    ],
    "name:spa_x_preferred":[
        "Legato"
    ],
    "name:srp_x_preferred":[
        "\u041b\u0435\u0433\u0430\u0442\u043e"
    ],
    "name:swe_x_preferred":[
        "Legato"
    ],
    "name:tgl_x_preferred":[
        "Legato"
    ],
    "name:tur_x_preferred":[
        "Legato"
    ],
    "name:ukr_x_preferred":[
        "\u041b\u0435\u0433\u0430\u0442\u043e"
    ],
    "wof:name":"Legato",
    "wof:placetype":"locality",
    "wof:population":27
},
  "geometry": {"coordinates":[11.59279,45.75859000000001],"type":"Point"}
}