{
  "type": "Feature",
  "properties": {
    "gn:admin1_code":"9.0",
    "gn:admin2_code":"BS",
    "gn:admin3_code":"17161.0",
    "gn:asciiname":"Localitaproduttiva Rezzatesi",
    "gn:country_code":"IT",
    "gn:dem":129,
    "gn:feature_class":"P",
    "gn:feature_code":"PPLL",
    "gn:name":"Localit\u00e0produttiva Rezzatesi",
    "gn:population":3,
    "gn:timezone":"Europe/Rome",
    "iso:country":"IT",
    "name:und_x_variant":[
        "Localit\u00e0produttiva Rezzatesi"
    ],
    "wof:name":"Localitaproduttiva Rezzatesi",
    "wof:placetype":"locality",
    "wof:population":3
},
  "geometry": {"coordinates":[10.29538,45.49262],"type":"Point"}
}