{
  "type": "Feature",
  "properties": {
    "gn:admin1_code":"7",
    "gn:admin2_code":"FR",
    "gn:admin3_code":"60075.0",
    "gn:asciiname":"Frischetto",
    "gn:country_code":"IT",
    "gn:dem":172,
    "gn:feature_class":"P",
    "gn:feature_code":"PPL",
    "gn:name":"Frischetto",
    "gn:population":48,
    "gn:timezone":"Europe/Rome",
    "iso:country":"IT",
    "wof:name":"Frischetto",
    "wof:placetype":"locality",
    "wof:population":48
},
  "geometry": {"coordinates":[13.50377,41.588],"type":"Point"}
}