{
  "type": "Feature",
  "properties": {
    "gn:admin1_code":"16.0",
    "gn:admin2_code":"SI",
    "gn:admin3_code":"52013.0",
    "gn:asciiname":"San Vincenti",
    "gn:country_code":"IT",
    "gn:dem":512,
    "gn:elevation":"520.0",
    "gn:feature_class":"P",
    "gn:feature_code":"PPL",
    "gn:name":"San Vincenti",
    "gn:population":10,
    "gn:timezone":"Europe/Rome",
    "iso:country":"IT",
    "wof:name":"San Vincenti",
    "wof:placetype":"locality",
    "wof:population":10
},
  "geometry": {"coordinates":[11.53294,43.42384000000001],"type":"Point"}
}