{
  "type": "Feature",
  "properties": {
    "gn:admin1_code":"20.0",
    "gn:admin2_code":"BL",
    "gn:admin3_code":"25021.0",
    "gn:asciiname":"Tomo",
    "gn:country_code":"IT",
    "gn:dem":363,
    "gn:feature_class":"P",
    "gn:feature_code":"PPL",
    "gn:name":"Tomo",
    "gn:population":411,
    "gn:timezone":"Europe/Rome",
    "iso:country":"IT",
    "name:ceb_x_preferred":[
        "Tomo"
    ],
    "name:ita_x_preferred":[
        "Tomo"
    ],
    "name:nld_x_preferred":[
        "Tomo"
    ],
    "name:spa_x_preferred":[
        "Tomo"
    ],
    "name:swe_x_preferred":[
        "Tomo"
    ],
    "name:tgl_x_preferred":[
        "Tomo"
    ],
    "wof:name":"Tomo",
    "wof:placetype":"locality",
    "wof:population":411
},
  "geometry": {"coordinates":[11.89388,46.00424],"type":"Point"}
}