{
  "type": "Feature",
  "properties": {
    "gn:admin1_code":"9",
    "gn:admin2_code":"PV",
    "gn:admin3_code":"18089.0",
    "gn:asciiname":"Canova",
    "gn:country_code":"IT",
    "gn:dem":539,
    "gn:feature_class":"P",
    "gn:feature_code":"PPL",
    "gn:name":"Canova",
    "gn:population":40,
    "gn:timezone":"Europe/Rome",
    "iso:country":"IT",
    "wof:name":"Canova",
    "wof:placetype":"locality",
    "wof:population":40
},
  "geometry": {"coordinates":[9.24368,44.80067],"type":"Point"}
}