{
  "type": "Feature",
  "properties": {
    "gn:admin1_code":"9",
    "gn:admin2_code":"BS",
    "gn:admin3_code":"17116.0",
    "gn:asciiname":"Burago",
    "gn:country_code":"IT",
    "gn:dem":238,
    "gn:feature_class":"P",
    "gn:feature_code":"PPL",
    "gn:name":"Burago",
    "gn:population":78,
    "gn:timezone":"Europe/Rome",
    "iso:country":"IT",
    "wof:name":"Burago",
    "wof:placetype":"locality",
    "wof:population":78
},
  "geometry": {"coordinates":[10.44836,45.55185],"type":"Point"}
}