{
  "type": "Feature",
  "properties": {
    "gn:admin1_code":"12",
    "gn:admin2_code":"BI",
    "gn:admin3_code":"96077.0",
    "gn:asciiname":"Vigna",
    "gn:country_code":"IT",
    "gn:dem":435,
    "gn:feature_class":"P",
    "gn:feature_code":"PPL",
    "gn:name":"Vigna",
    "gn:population":47,
    "gn:timezone":"Europe/Rome",
    "iso:country":"IT",
    "wof:name":"Vigna",
    "wof:placetype":"locality",
    "wof:population":47
},
  "geometry": {"coordinates":[8.09813,45.57456],"type":"Point"}
}