{
  "type": "Feature",
  "properties": {
    "gn:admin1_code":"12",
    "gn:admin2_code":"CN",
    "gn:admin3_code":"4035.0",
    "gn:asciiname":"Isole",
    "gn:country_code":"IT",
    "gn:dem":370,
    "gn:feature_class":"P",
    "gn:feature_code":"PPL",
    "gn:name":"Isole",
    "gn:population":25,
    "gn:timezone":"Europe/Rome",
    "iso:country":"IT",
    "wof:name":"Isole",
    "wof:placetype":"locality",
    "wof:population":25
},
  "geometry": {"coordinates":[8.13188,44.44634],"type":"Point"}
}