{
  "type": "Feature",
  "properties": {
    "gn:admin1_code":"12",
    "gn:admin2_code":"CN",
    "gn:admin3_code":"4035.0",
    "gn:asciiname":"Isole",
    "gn:country_code":"IT",
    "gn:dem":370,
    "gn:feature_class":"P",
    "gn:feature_code":"PPL",
    "gn:name":"Isole",
    "gn:population":25,
    "gn:timezone":"Europe/Rome",
    "iso:country":"IT",
    "name:bre_x_preferred":[
        "Izol"
    ],
    "name:deu_x_preferred":[
        "Isole"
    ],
    "name:fas_x_preferred":[
        "\u0627\u06cc\u0632\u0648\u0644"
    ],
    "name:fra_x_preferred":[
        "Isole"
    ],
    "name:tgk_x_preferred":[
        "\u0418\u0437\u043e\u043b\u0435"
    ],
    "wof:name":"Isole",
    "wof:placetype":"locality",
    "wof:population":25
},
  "geometry": {"coordinates":[8.13188,44.44634],"type":"Point"}
}