{
  "type": "Feature",
  "properties": {
    "gn:admin1_code":"9",
    "gn:admin2_code":"MN",
    "gn:admin3_code":"20011.0",
    "gn:asciiname":"Squarzieri",
    "gn:country_code":"IT",
    "gn:dem":46,
    "gn:feature_class":"P",
    "gn:feature_code":"PPL",
    "gn:name":"Squarzieri",
    "gn:population":41,
    "gn:timezone":"Europe/Rome",
    "iso:country":"IT",
    "wof:name":"Squarzieri",
    "wof:placetype":"locality",
    "wof:population":41
},
  "geometry": {"coordinates":[10.48795,45.26708],"type":"Point"}
}