{
  "type": "Feature",
  "properties": {
    "iso:country":"IT",
    "name:cat_x_preferred":[
        "Fossaz"
    ],
    "name:ces_x_preferred":[
        "Fossaz"
    ],
    "name:dan_x_preferred":[
        "Fossaz"
    ],
    "name:eng_x_preferred":[
        "Fossaz"
    ],
    "name:eus_x_preferred":[
        "Fossaz"
    ],
    "name:fin_x_preferred":[
        "Fossaz"
    ],
    "name:fra_x_preferred":[
        "Fossaz"
    ],
    "name:ind_x_preferred":[
        "Fossaz"
    ],
    "name:ita_x_preferred":[
        "Fossaz"
    ],
    "name:nld_x_preferred":[
        "Fossaz"
    ],
    "name:nno_x_preferred":[
        "Fossaz"
    ],
    "name:nob_x_preferred":[
        "Fossaz"
    ],
    "name:oci_x_preferred":[
        "Fossaz"
    ],
    "name:pol_x_preferred":[
        "Fossaz"
    ],
    "name:por_x_preferred":[
        "Fossaz"
    ],
    "name:ron_x_preferred":[
        "Fossaz"
    ],
    "name:slk_x_preferred":[
        "Fossaz"
    ],
    "name:slv_x_preferred":[
        "Fossaz"
    ],
    "name:spa_x_preferred":[
        "Fossaz"
    ],
    "name:srp_x_preferred":[
        "Fossaz"
    ],
    "name:swe_x_preferred":[
        "Fossaz"
    ],
    "name:tgl_x_preferred":[
        "Fossaz"
    ],
    "name:tur_x_preferred":[
        "Fossaz"
    ],
    "name:war_x_preferred":[
        "Fossaz"
    ],
    "qs:a0":"Italia",
    "qs:a1":"*Aosta#Aoste",
    "qs:a1r":"0Valle d'Aosta#Vall\u00e9e d'Aoste",
    "qs:adm0":"Italia",
    "qs:la_lc":"*",
    "qs:level":"locality",
    "qs:loc":"Fossaz",
    "qs:loc_alt":"Fossaz",
    "qs:pop":0,
    "qs:type":"buffered point",
    "wof:name":"Fossaz",
    "wof:placetype":"locality"
},
  "geometry": {"coordinates":[7.167781,45.717499],"type":"Point"}
}