{
  "type": "Feature",
  "properties": {
    "gn:admin1_code":"16",
    "gn:admin2_code":"LU",
    "gn:admin3_code":"46002.0",
    "gn:asciiname":"Pieve di Monti di Villa",
    "gn:country_code":"IT",
    "gn:dem":516,
    "gn:feature_class":"P",
    "gn:feature_code":"PPL",
    "gn:name":"Pieve di Monti di Villa",
    "gn:population":63,
    "gn:timezone":"Europe/Rome",
    "iso:country":"IT",
    "wof:name":"Pieve di Monti di Villa",
    "wof:placetype":"locality",
    "wof:population":63
},
  "geometry": {"coordinates":[10.57028,44.02502],"type":"Point"}
}