{
  "type": "Feature",
  "properties": {
    "gn:admin1_code":"18",
    "gn:admin2_code":"PG",
    "gn:admin3_code":"54051.0",
    "gn:asciiname":"Fogliano",
    "gn:country_code":"IT",
    "gn:dem":602,
    "gn:feature_class":"P",
    "gn:feature_code":"PPL",
    "gn:name":"Fogliano",
    "gn:population":70,
    "gn:timezone":"Europe/Rome",
    "iso:country":"IT",
    "name:ceb_x_preferred":[
        "Fogliano"
    ],
    "name:ita_x_preferred":[
        "Fogliano"
    ],
    "name:nld_x_preferred":[
        "Fogliano"
    ],
    "name:srp_x_preferred":[
        "\u0424\u043e\u0459\u0438\u0458\u0430\u043d\u043e"
    ],
    "wof:name":"Fogliano",
    "wof:placetype":"locality",
    "wof:population":70
},
  "geometry": {"coordinates":[12.62326,42.69308],"type":"Point"}
}