{
  "type": "Feature",
  "properties": {
    "gn:admin1_code":"20",
    "gn:admin2_code":"PD",
    "gn:admin3_code":"28034.0",
    "gn:asciiname":"Marcolin",
    "gn:country_code":"IT",
    "gn:dem":7,
    "gn:feature_class":"P",
    "gn:feature_code":"PPL",
    "gn:name":"Marcolin",
    "gn:population":33,
    "gn:timezone":"Europe/Rome",
    "iso:country":"IT",
    "wof:name":"Marcolin",
    "wof:placetype":"locality",
    "wof:population":33
},
  "geometry": {"coordinates":[11.85666,45.24818],"type":"Point"}
}