{
  "type": "Feature",
  "properties": {
    "gn:admin1_code":"9",
    "gn:admin2_code":"BS",
    "gn:admin3_code":"17022.0",
    "gn:asciiname":"Ram",
    "gn:country_code":"IT",
    "gn:dem":813,
    "gn:feature_class":"P",
    "gn:feature_code":"PPL",
    "gn:name":"Ram",
    "gn:population":12,
    "gn:timezone":"Europe/Rome",
    "iso:country":"IT",
    "name:bre_x_preferred":[
        "Ram"
    ],
    "name:cat_x_preferred":[
        "Ram"
    ],
    "name:ceb_x_preferred":[
        "Ram"
    ],
    "name:ces_x_preferred":[
        "Ram"
    ],
    "name:cym_x_preferred":[
        "Ram"
    ],
    "name:ell_x_preferred":[
        "\u03a1\u03b1\u03bc"
    ],
    "name:est_x_preferred":[
        "Ram"
    ],
    "name:fin_x_preferred":[
        "Ram"
    ],
    "name:hun_x_preferred":[
        "Ram"
    ],
    "name:lmo_x_preferred":[
        "Ram"
    ],
    "name:nld_x_preferred":[
        "Ram"
    ],
    "name:nor_x_preferred":[
        "Ram"
    ],
    "name:pol_x_preferred":[
        "Ram"
    ],
    "name:ron_x_preferred":[
        "Ram"
    ],
    "name:rus_x_preferred":[
        "\u0420\u0430\u043c"
    ],
    "name:srp_x_preferred":[
        "\u0420\u0430\u043c"
    ],
    "name:swe_x_preferred":[
        "Ram"
    ],
    "name:tgl_x_preferred":[
        "Ram"
    ],
    "name:ukr_x_preferred":[
        "Ram"
    ],
    "wof:name":"Ram",
    "wof:placetype":"locality",
    "wof:population":12
},
  "geometry": {"coordinates":[10.22004,45.94487],"type":"Point"}
}