{
  "type": "Feature",
  "properties": {
    "gn:admin1_code":"9",
    "gn:admin2_code":"BG",
    "gn:admin3_code":"16247.0",
    "gn:asciiname":"Tassone Basso",
    "gn:country_code":"IT",
    "gn:dem":666,
    "gn:feature_class":"P",
    "gn:feature_code":"PPLL",
    "gn:name":"Tassone Basso",
    "gn:population":10,
    "gn:timezone":"Europe/Rome",
    "iso:country":"IT",
    "wof:name":"Tassone Basso",
    "wof:placetype":"locality",
    "wof:population":10
},
  "geometry": {"coordinates":[9.75194,45.81668],"type":"Point"}
}