{
  "type": "Feature",
  "properties": {
    "gn:admin1_code":"5",
    "gn:admin2_code":"MO",
    "gn:admin3_code":"36024.0",
    "gn:asciiname":"Ca' Busotto",
    "gn:country_code":"IT",
    "gn:dem":629,
    "gn:feature_class":"P",
    "gn:feature_code":"PPLL",
    "gn:name":"Ca' Busotto",
    "gn:population":8,
    "gn:timezone":"Europe/Rome",
    "iso:country":"IT",
    "wof:name":"Ca' Busotto",
    "wof:placetype":"locality",
    "wof:population":8
},
  "geometry": {"coordinates":[10.7677,44.28847],"type":"Point"}
}