{
  "type": "Feature",
  "properties": {
    "gn:admin1_code":"9",
    "gn:admin2_code":"BS",
    "gn:admin3_code":"17133.0",
    "gn:asciiname":"Meucci",
    "gn:country_code":"IT",
    "gn:dem":190,
    "gn:feature_class":"P",
    "gn:feature_code":"PPL",
    "gn:name":"Meucci",
    "gn:population":45,
    "gn:timezone":"Europe/Rome",
    "iso:country":"IT",
    "wof:name":"Meucci",
    "wof:placetype":"locality",
    "wof:population":45
},
  "geometry": {"coordinates":[9.88289,45.60723],"type":"Point"}
}