{
  "type": "Feature",
  "properties": {
    "gn:admin1_code":"10",
    "gn:admin2_code":"MC",
    "gn:admin3_code":"43002.0",
    "gn:asciiname":"Montalvello",
    "gn:country_code":"IT",
    "gn:dem":555,
    "gn:feature_class":"P",
    "gn:feature_code":"PPL",
    "gn:name":"Montalvello",
    "gn:population":50,
    "gn:timezone":"Europe/Rome",
    "iso:country":"IT",
    "wof:name":"Montalvello",
    "wof:placetype":"locality",
    "wof:population":50
},
  "geometry": {"coordinates":[13.14629,43.40407],"type":"Point"}
}