{
  "type": "Feature",
  "properties": {
    "gn:admin1_code":"12",
    "gn:admin2_code":"AL",
    "gn:admin3_code":"6036.0",
    "gn:asciiname":"Rivere",
    "gn:country_code":"IT",
    "gn:dem":197,
    "gn:feature_class":"P",
    "gn:feature_code":"PPL",
    "gn:name":"Rivere",
    "gn:population":30,
    "gn:timezone":"Europe/Rome",
    "iso:country":"IT",
    "wof:name":"Rivere",
    "wof:placetype":"locality",
    "wof:population":30
},
  "geometry": {"coordinates":[8.41123,44.61117],"type":"Point"}
}