{
  "type": "Feature",
  "properties": {
    "gn:admin1_code":"5",
    "gn:admin2_code":"MO",
    "gn:admin3_code":"36018.0",
    "gn:asciiname":"La Ca'",
    "gn:country_code":"IT",
    "gn:dem":1009,
    "gn:feature_class":"P",
    "gn:feature_code":"PPL",
    "gn:name":"La Ca'",
    "gn:population":13,
    "gn:timezone":"Europe/Rome",
    "iso:country":"IT",
    "wof:name":"La Ca'",
    "wof:placetype":"locality",
    "wof:population":13
},
  "geometry": {"coordinates":[10.67683,44.26703],"type":"Point"}
}