{
  "type": "Feature",
  "properties": {
    "gn:admin1_code":"16",
    "gn:admin2_code":"FI",
    "gn:admin3_code":"48035.0",
    "gn:asciiname":"Fornaci Incisa",
    "gn:country_code":"IT",
    "gn:dem":129,
    "gn:feature_class":"P",
    "gn:feature_code":"PPL",
    "gn:name":"Fornaci Incisa",
    "gn:population":83,
    "gn:timezone":"Europe/Rome",
    "iso:country":"IT",
    "wof:name":"Fornaci Incisa",
    "wof:placetype":"locality",
    "wof:population":83
},
  "geometry": {"coordinates":[11.45089,43.6615],"type":"Point"}
}