{
  "type": "Feature",
  "properties": {
    "gn:admin1_code":"5.0",
    "gn:admin2_code":"FE",
    "gn:admin3_code":"38014.0",
    "gn:asciiname":"Massenzatica",
    "gn:country_code":"IT",
    "gn:dem":-2,
    "gn:elevation":"1.0",
    "gn:feature_class":"P",
    "gn:feature_code":"PPL",
    "gn:name":"Massenzatica",
    "gn:population":235,
    "gn:timezone":"Europe/Rome",
    "iso:country":"IT",
    "wof:name":"Massenzatica",
    "wof:placetype":"locality",
    "wof:population":235
},
  "geometry": {"coordinates":[12.17254,44.92559],"type":"Point"}
}