{
  "type": "Feature",
  "properties": {
    "gn:admin1_code":"17",
    "gn:admin2_code":"BZ",
    "gn:admin3_code":"21063.0",
    "gn:asciiname":"Sopranessano",
    "gn:country_code":"IT",
    "gn:dem":1329,
    "gn:feature_class":"P",
    "gn:feature_code":"PPLL",
    "gn:name":"Sopranessano",
    "gn:population":10,
    "gn:timezone":"Europe/Rome",
    "iso:country":"IT",
    "wof:name":"Sopranessano",
    "wof:placetype":"locality",
    "wof:population":10
},
  "geometry": {"coordinates":[12.0169,46.79364],"type":"Point"}
}