{
  "type": "Feature",
  "properties": {
    "gn:admin1_code":"11",
    "gn:admin2_code":"IS",
    "gn:admin3_code":"94022.0",
    "gn:asciiname":"Masseria Franciosi",
    "gn:country_code":"IT",
    "gn:dem":878,
    "gn:feature_class":"P",
    "gn:feature_code":"PPL",
    "gn:name":"Masseria Franciosi",
    "gn:population":44,
    "gn:timezone":"Europe/Rome",
    "iso:country":"IT",
    "wof:name":"Masseria Franciosi",
    "wof:placetype":"locality",
    "wof:population":44
},
  "geometry": {"coordinates":[14.44881,41.614],"type":"Point"}
}