{
  "type": "Feature",
  "properties": {
    "gn:admin1_code":"13.0",
    "gn:admin2_code":"FG",
    "gn:admin3_code":"71024.0",
    "gn:asciiname":"Ovile Nazionale",
    "gn:country_code":"IT",
    "gn:dem":148,
    "gn:feature_class":"P",
    "gn:feature_code":"PPLL",
    "gn:name":"Ovile Nazionale",
    "gn:population":0,
    "gn:timezone":"Europe/Rome",
    "iso:country":"IT",
    "wof:name":"Ovile Nazionale",
    "wof:placetype":"locality"
},
  "geometry": {"coordinates":[15.4925,41.37721],"type":"Point"}
}