{
  "type": "Feature",
  "properties": {
    "gn:admin1_code":"20.0",
    "gn:admin2_code":"VI",
    "gn:admin3_code":"24084.0",
    "gn:asciiname":"Prenero",
    "gn:country_code":"IT",
    "gn:dem":790,
    "gn:feature_class":"P",
    "gn:feature_code":"PPLL",
    "gn:name":"Prenero",
    "gn:population":2,
    "gn:timezone":"Europe/Rome",
    "iso:country":"IT",
    "wof:name":"Prenero",
    "wof:placetype":"locality",
    "wof:population":2
},
  "geometry": {"coordinates":[11.23818,45.67349],"type":"Point"}
}