{
  "type": "Feature",
  "properties": {
    "gn:admin1_code":"20",
    "gn:admin2_code":"TV",
    "gn:admin3_code":"26071.0",
    "gn:asciiname":"Calbassa (Castello)",
    "gn:country_code":"IT",
    "gn:dem":11,
    "gn:feature_class":"P",
    "gn:feature_code":"PPL",
    "gn:name":"Calbassa (Castello)",
    "gn:population":56,
    "gn:timezone":"Europe/Rome",
    "iso:country":"IT",
    "wof:name":"Calbassa (Castello)",
    "wof:placetype":"locality",
    "wof:population":56
},
  "geometry": {"coordinates":[12.41842,45.71045],"type":"Point"}
}