{
  "type": "Feature",
  "properties": {
    "gn:admin1_code":"15",
    "gn:admin2_code":"PA",
    "gn:admin3_code":"82049.0",
    "gn:asciiname":"Pietrelunghe",
    "gn:country_code":"IT",
    "gn:dem":519,
    "gn:feature_class":"P",
    "gn:feature_code":"PPL",
    "gn:name":"Pietrelunghe",
    "gn:population":143,
    "gn:timezone":"Europe/Rome",
    "iso:country":"IT",
    "wof:name":"Pietrelunghe",
    "wof:placetype":"locality",
    "wof:population":143
},
  "geometry": {"coordinates":[13.25664,38.10063],"type":"Point"}
}