{
  "type": "Feature",
  "properties": {
    "gn:admin1_code":"9",
    "gn:admin2_code":"MN",
    "gn:admin3_code":"20017.0",
    "gn:asciiname":"Tezzole",
    "gn:country_code":"IT",
    "gn:dem":119,
    "gn:feature_class":"P",
    "gn:feature_code":"PPL",
    "gn:name":"Tezzole",
    "gn:population":29,
    "gn:timezone":"Europe/Rome",
    "iso:country":"IT",
    "wof:name":"Tezzole",
    "wof:placetype":"locality",
    "wof:population":29
},
  "geometry": {"coordinates":[10.48307,45.40964],"type":"Point"}
}