{
  "type": "Feature",
  "properties": {
    "gn:admin1_code":"5",
    "gn:admin2_code":"PC",
    "gn:admin3_code":"33004.0",
    "gn:asciiname":"Forlini",
    "gn:country_code":"IT",
    "gn:dem":832,
    "gn:feature_class":"P",
    "gn:feature_code":"PPLL",
    "gn:name":"Forlini",
    "gn:population":8,
    "gn:timezone":"Europe/Rome",
    "iso:country":"IT",
    "wof:name":"Forlini",
    "wof:placetype":"locality",
    "wof:population":8
},
  "geometry": {"coordinates":[9.63901,44.73419000000001],"type":"Point"}
}