{
  "type": "Feature",
  "properties": {
    "gn:admin1_code":"15",
    "gn:admin2_code":"RG",
    "gn:admin3_code":"88006.0",
    "gn:asciiname":"Ufra",
    "gn:country_code":"IT",
    "gn:dem":445,
    "gn:feature_class":"P",
    "gn:feature_code":"PPL",
    "gn:name":"Ufra",
    "gn:population":32,
    "gn:timezone":"Europe/Rome",
    "iso:country":"IT",
    "wof:name":"Ufra",
    "wof:placetype":"locality",
    "wof:population":32
},
  "geometry": {"coordinates":[14.76968,36.8552],"type":"Point"}
}