{
  "type": "Feature",
  "properties": {
    "gn:admin1_code":"17.0",
    "gn:admin2_code":"TN",
    "gn:admin3_code":"22033.0",
    "gn:asciiname":"Tozzaga",
    "gn:country_code":"IT",
    "gn:dem":667,
    "gn:feature_class":"P",
    "gn:feature_code":"PPL",
    "gn:name":"Tozzaga",
    "gn:population":71,
    "gn:timezone":"Europe/Rome",
    "iso:country":"IT",
    "wof:name":"Tozzaga",
    "wof:placetype":"locality",
    "wof:population":71
},
  "geometry": {"coordinates":[10.96992,46.38145],"type":"Point"}
}