{
  "type": "Feature",
  "properties": {
    "gn:admin1_code":"9",
    "gn:admin2_code":"PV",
    "gn:admin3_code":"18074.0",
    "gn:asciiname":"Casa Pegorini",
    "gn:country_code":"IT",
    "gn:dem":339,
    "gn:feature_class":"P",
    "gn:feature_code":"PPLL",
    "gn:name":"Casa Pegorini",
    "gn:population":9,
    "gn:timezone":"Europe/Rome",
    "iso:country":"IT",
    "wof:name":"Casa Pegorini",
    "wof:placetype":"locality",
    "wof:population":9
},
  "geometry": {"coordinates":[9.30129,44.96442],"type":"Point"}
}