{
  "type": "Feature",
  "properties": {
    "gn:admin1_code":"20",
    "gn:admin2_code":"PD",
    "gn:admin3_code":"28005.0",
    "gn:asciiname":"Corte Vigo",
    "gn:country_code":"IT",
    "gn:dem":51,
    "gn:feature_class":"P",
    "gn:feature_code":"PPL",
    "gn:name":"Corte Vigo",
    "gn:population":128,
    "gn:timezone":"Europe/Rome",
    "iso:country":"IT",
    "wof:name":"Corte Vigo",
    "wof:placetype":"locality",
    "wof:population":128
},
  "geometry": {"coordinates":[11.73603,45.28329],"type":"Point"}
}