{
  "type": "Feature",
  "properties": {
    "gn:admin1_code":"7.0",
    "gn:admin2_code":"FR",
    "gn:admin3_code":"60036.0",
    "gn:asciiname":"Collefontana-Fontana Liri Inferiore",
    "gn:country_code":"IT",
    "gn:dem":154,
    "gn:feature_class":"P",
    "gn:feature_code":"PPLA3",
    "gn:name":"Collefontana-Fontana Liri Inferiore",
    "gn:population":2532,
    "gn:timezone":"Europe/Rome",
    "iso:country":"IT",
    "wof:name":"Collefontana-Fontana Liri Inferiore",
    "wof:placetype":"locality",
    "wof:population":2532
},
  "geometry": {"coordinates":[13.54945,41.61166],"type":"Point"}
}