{
  "type": "Feature",
  "properties": {
    "gn:admin1_code":"5.0",
    "gn:admin2_code":"FC",
    "gn:admin3_code":"40028.0",
    "gn:asciiname":"Badia",
    "gn:country_code":"IT",
    "gn:dem":52,
    "gn:elevation":"50.0",
    "gn:feature_class":"P",
    "gn:feature_code":"PPL",
    "gn:name":"Badia",
    "gn:population":231,
    "gn:timezone":"Europe/Rome",
    "iso:country":"IT",
    "name:cat_x_preferred":[
        "Badia"
    ],
    "name:ceb_x_preferred":[
        "Badia"
    ],
    "name:deu_x_preferred":[
        "Badia"
    ],
    "name:fra_x_preferred":[
        "Badia"
    ],
    "name:ita_x_preferred":[
        "Badia"
    ],
    "name:nld_x_preferred":[
        "Badia"
    ],
    "name:pol_x_preferred":[
        "Badia"
    ],
    "name:por_x_preferred":[
        "Badia"
    ],
    "name:sco_x_preferred":[
        "Badia"
    ],
    "name:slv_x_preferred":[
        "Bad\u00eda"
    ],
    "name:spa_x_preferred":[
        "Bad\u00eda"
    ],
    "name:srp_x_preferred":[
        "Badija"
    ],
    "name:swe_x_preferred":[
        "Badia"
    ],
    "wof:name":"Badia",
    "wof:placetype":"locality",
    "wof:population":231
},
  "geometry": {"coordinates":[12.31318,44.09548],"type":"Point"}
}