{
  "type": "Feature",
  "properties": {
    "gn:admin1_code":"5.0",
    "gn:admin2_code":"FC",
    "gn:admin3_code":"40028.0",
    "gn:asciiname":"Badia",
    "gn:country_code":"IT",
    "gn:dem":52,
    "gn:elevation":"50.0",
    "gn:feature_class":"P",
    "gn:feature_code":"PPL",
    "gn:name":"Badia",
    "gn:population":231,
    "gn:timezone":"Europe/Rome",
    "iso:country":"IT",
    "wof:name":"Badia",
    "wof:placetype":"locality",
    "wof:population":231
},
  "geometry": {"coordinates":[12.31318,44.09548],"type":"Point"}
}