{
  "type": "Feature",
  "properties": {
    "gn:admin1_code":"17",
    "gn:admin2_code":"BZ",
    "gn:admin3_code":"21091.0",
    "gn:asciiname":"Santa Caterina",
    "gn:country_code":"IT",
    "gn:dem":1247,
    "gn:feature_class":"P",
    "gn:feature_code":"PPL",
    "gn:name":"Santa Caterina",
    "gn:population":159,
    "gn:timezone":"Europe/Rome",
    "iso:country":"IT",
    "wof:name":"Santa Caterina",
    "wof:placetype":"locality",
    "wof:population":159
},
  "geometry": {"coordinates":[10.9347,46.68906],"type":"Point"}
}