{
  "type": "Feature",
  "properties": {
    "gn:admin1_code":"20",
    "gn:admin2_code":"VR",
    "gn:admin3_code":"23091.0",
    "gn:asciiname":"Marescalche",
    "gn:country_code":"IT",
    "gn:dem":44,
    "gn:feature_class":"P",
    "gn:feature_code":"PPL",
    "gn:name":"Marescalche",
    "gn:population":47,
    "gn:timezone":"Europe/Rome",
    "iso:country":"IT",
    "wof:name":"Marescalche",
    "wof:placetype":"locality",
    "wof:population":47
},
  "geometry": {"coordinates":[11.01453,45.38083],"type":"Point"}
}