{
  "type": "Feature",
  "properties": {
    "gn:admin1_code":"9",
    "gn:admin2_code":"PV",
    "gn:admin3_code":"18097.0",
    "gn:asciiname":"Ca' Selvatico",
    "gn:country_code":"IT",
    "gn:dem":229,
    "gn:feature_class":"P",
    "gn:feature_code":"PPL",
    "gn:name":"Ca' Selvatico",
    "gn:population":24,
    "gn:timezone":"Europe/Rome",
    "iso:country":"IT",
    "wof:name":"Ca' Selvatico",
    "wof:placetype":"locality",
    "wof:population":24
},
  "geometry": {"coordinates":[9.28993,45.02584],"type":"Point"}
}