{
  "type": "Feature",
  "properties": {
    "gn:admin1_code":"4.0",
    "gn:admin2_code":"CE",
    "gn:admin3_code":"61069.0",
    "gn:asciiname":"Santa Maria di Mortola",
    "gn:country_code":"IT",
    "gn:dem":38,
    "gn:feature_class":"P",
    "gn:feature_code":"PPL",
    "gn:name":"Santa Maria di Mortola",
    "gn:population":0,
    "gn:timezone":"Europe/Rome",
    "iso:country":"IT",
    "wof:name":"Santa Maria di Mortola",
    "wof:placetype":"locality"
},
  "geometry": {"coordinates":[13.88333,41.35],"type":"Point"}
}