{
  "type": "Feature",
  "properties": {
    "gn:admin1_code":"12",
    "gn:admin2_code":"TO",
    "gn:admin3_code":"1058.0",
    "gn:asciiname":"Regione Ponte Po",
    "gn:country_code":"IT",
    "gn:dem":230,
    "gn:feature_class":"P",
    "gn:feature_code":"PPL",
    "gn:name":"Regione Ponte Po",
    "gn:population":31,
    "gn:timezone":"Europe/Rome",
    "iso:country":"IT",
    "wof:name":"Regione Ponte Po",
    "wof:placetype":"locality",
    "wof:population":31
},
  "geometry": {"coordinates":[7.68909,44.90761],"type":"Point"}
}