{
  "type": "Feature",
  "properties": {
    "gn:admin1_code":"16.0",
    "gn:admin2_code":"AR",
    "gn:admin3_code":"51005.0",
    "gn:asciiname":"Badia A Ruoti",
    "gn:country_code":"IT",
    "gn:dem":261,
    "gn:feature_class":"P",
    "gn:feature_code":"PPL",
    "gn:name":"Badia A Ruoti",
    "gn:population":209,
    "gn:timezone":"Europe/Rome",
    "iso:country":"IT",
    "wof:name":"Badia A Ruoti",
    "wof:placetype":"locality",
    "wof:population":209
},
  "geometry": {"coordinates":[11.6057,43.39735],"type":"Point"}
}