{
  "type": "Feature",
  "properties": {
    "gn:admin1_code":"15.0",
    "gn:admin2_code":"ME",
    "gn:admin3_code":"83085.0",
    "gn:asciiname":"Sant'Alessio Village",
    "gn:country_code":"IT",
    "gn:dem":74,
    "gn:feature_class":"P",
    "gn:feature_code":"PPL",
    "gn:name":"Sant'Alessio Village",
    "gn:population":16,
    "gn:timezone":"Europe/Rome",
    "iso:country":"IT",
    "wof:name":"Sant'Alessio Village",
    "wof:placetype":"locality",
    "wof:population":16
},
  "geometry": {"coordinates":[15.34191,37.91866],"type":"Point"}
}