{
  "type": "Feature",
  "properties": {
    "gn:admin1_code":"5.0",
    "gn:admin2_code":"RA",
    "gn:admin3_code":"39002.0",
    "gn:asciiname":"Localita Sottofiume Boncellino",
    "gn:country_code":"IT",
    "gn:dem":10,
    "gn:feature_class":"P",
    "gn:feature_code":"PPL",
    "gn:name":"Localit\u00e0 Sottofiume Boncellino",
    "gn:population":25,
    "gn:timezone":"Europe/Rome",
    "iso:country":"IT",
    "name:und_x_variant":[
        "Localit\u00e0 Sottofiume Boncellino"
    ],
    "wof:name":"Localita Sottofiume Boncellino",
    "wof:placetype":"locality",
    "wof:population":25
},
  "geometry": {"coordinates":[12.00409,44.38657],"type":"Point"}
}