{
  "type": "Feature",
  "properties": {
    "gn:admin1_code":"5",
    "gn:admin2_code":"RE",
    "gn:admin3_code":"35011.0",
    "gn:asciiname":"Ca' d'Orsini",
    "gn:country_code":"IT",
    "gn:dem":397,
    "gn:feature_class":"P",
    "gn:feature_code":"PPLL",
    "gn:name":"Ca' d'Orsini",
    "gn:population":9,
    "gn:timezone":"Europe/Rome",
    "iso:country":"IT",
    "wof:name":"Ca' d'Orsini",
    "wof:placetype":"locality",
    "wof:population":9
},
  "geometry": {"coordinates":[10.56172,44.48412],"type":"Point"}
}