{
  "type": "Feature",
  "properties": {
    "gn:admin1_code":"9.0",
    "gn:admin2_code":"LC",
    "gn:admin3_code":"97014.0",
    "gn:asciiname":"Forcella Alta",
    "gn:country_code":"IT",
    "gn:dem":1306,
    "gn:feature_class":"P",
    "gn:feature_code":"PPLL",
    "gn:name":"Forcella Alta",
    "gn:population":3,
    "gn:timezone":"Europe/Rome",
    "iso:country":"IT",
    "wof:name":"Forcella Alta",
    "wof:placetype":"locality",
    "wof:population":3
},
  "geometry": {"coordinates":[9.49314,45.80467],"type":"Point"}
}