{
  "type": "Feature",
  "properties": {
    "gn:admin1_code":"4.0",
    "gn:admin2_code":"AV",
    "gn:admin3_code":"64017.0",
    "gn:asciiname":"Piani",
    "gn:country_code":"IT",
    "gn:dem":482,
    "gn:feature_class":"P",
    "gn:feature_code":"PPL",
    "gn:name":"Piani",
    "gn:population":650,
    "gn:timezone":"Europe/Rome",
    "iso:country":"IT",
    "wof:name":"Piani",
    "wof:placetype":"locality",
    "wof:population":650
},
  "geometry": {"coordinates":[15.22932,40.81919],"type":"Point"}
}