{
  "type": "Feature",
  "properties": {
    "gn:admin1_code":"12",
    "gn:admin2_code":"TO",
    "gn:admin3_code":"1135.0",
    "gn:asciiname":"Bossole",
    "gn:country_code":"IT",
    "gn:dem":223,
    "gn:feature_class":"P",
    "gn:feature_code":"PPL",
    "gn:name":"Bossole",
    "gn:population":58,
    "gn:timezone":"Europe/Rome",
    "iso:country":"IT",
    "wof:name":"Bossole",
    "wof:placetype":"locality",
    "wof:population":58
},
  "geometry": {"coordinates":[7.74311,45.23987],"type":"Point"}
}