{
  "type": "Feature",
  "properties": {
    "gn:admin1_code":"15",
    "gn:admin2_code":"RG",
    "gn:admin3_code":"88001.0",
    "gn:asciiname":"Marina di Acate",
    "gn:country_code":"IT",
    "gn:dem":9,
    "gn:feature_class":"P",
    "gn:feature_code":"PPLL",
    "gn:name":"Marina di Acate",
    "gn:population":6,
    "gn:timezone":"Europe/Rome",
    "iso:country":"IT",
    "wof:name":"Marina di Acate",
    "wof:placetype":"locality",
    "wof:population":6
},
  "geometry": {"coordinates":[14.35929,36.98442],"type":"Point"}
}