{
  "type": "Feature",
  "properties": {
    "gn:admin1_code":"12",
    "gn:admin2_code":"AL",
    "gn:admin3_code":"6085.0",
    "gn:asciiname":"Torrotta",
    "gn:country_code":"IT",
    "gn:dem":307,
    "gn:feature_class":"P",
    "gn:feature_code":"PPL",
    "gn:name":"Torrotta",
    "gn:population":31,
    "gn:timezone":"Europe/Rome",
    "iso:country":"IT",
    "wof:name":"Torrotta",
    "wof:placetype":"locality",
    "wof:population":31
},
  "geometry": {"coordinates":[8.92559,44.68835],"type":"Point"}
}