{
  "type": "Feature",
  "properties": {
    "gn:admin1_code":"5",
    "gn:admin2_code":"BO",
    "gn:admin3_code":"37005.0",
    "gn:asciiname":"Case Santa Maria in Duno",
    "gn:country_code":"IT",
    "gn:dem":9,
    "gn:feature_class":"P",
    "gn:feature_code":"PPL",
    "gn:name":"Case Santa Maria in Duno",
    "gn:population":23,
    "gn:timezone":"Europe/Rome",
    "iso:country":"IT",
    "wof:name":"Case Santa Maria in Duno",
    "wof:placetype":"locality",
    "wof:population":23
},
  "geometry": {"coordinates":[11.48161,44.67633],"type":"Point"}
}