{
  "type": "Feature",
  "properties": {
    "gn:admin1_code":"17",
    "gn:admin2_code":"BZ",
    "gn:admin3_code":"21007.0",
    "gn:asciiname":"Colma",
    "gn:country_code":"IT",
    "gn:dem":502,
    "gn:feature_class":"P",
    "gn:feature_code":"PPL",
    "gn:name":"Colma",
    "gn:population":288,
    "gn:timezone":"Europe/Rome",
    "iso:country":"IT",
    "wof:name":"Colma",
    "wof:placetype":"locality",
    "wof:population":288
},
  "geometry": {"coordinates":[11.52397,46.5898],"type":"Point"}
}