{
  "type": "Feature",
  "properties": {
    "gn:admin1_code":"12",
    "gn:admin2_code":"TO",
    "gn:admin3_code":"1188.0",
    "gn:asciiname":"Laietto",
    "gn:country_code":"IT",
    "gn:dem":692,
    "gn:feature_class":"P",
    "gn:feature_code":"PPL",
    "gn:name":"Laietto",
    "gn:population":16,
    "gn:timezone":"Europe/Rome",
    "iso:country":"IT",
    "wof:name":"Laietto",
    "wof:placetype":"locality",
    "wof:population":16
},
  "geometry": {"coordinates":[7.40759,45.29105],"type":"Point"}
}