{
  "type": "Feature",
  "properties": {
    "gn:admin1_code":"12",
    "gn:admin2_code":"TO",
    "gn:admin3_code":"1088.0",
    "gn:asciiname":"Vauda",
    "gn:country_code":"IT",
    "gn:dem":681,
    "gn:feature_class":"P",
    "gn:feature_code":"PPL",
    "gn:name":"Vauda",
    "gn:population":309,
    "gn:timezone":"Europe/Rome",
    "iso:country":"IT",
    "wof:name":"Vauda",
    "wof:placetype":"locality",
    "wof:population":309
},
  "geometry": {"coordinates":[7.4908,45.29712],"type":"Point"}
}