{
  "type": "Feature",
  "properties": {
    "gn:admin1_code":"12.0",
    "gn:admin2_code":"CN",
    "gn:admin3_code":"4182.0",
    "gn:asciiname":"Bergia",
    "gn:country_code":"IT",
    "gn:dem":1093,
    "gn:feature_class":"P",
    "gn:feature_code":"PPLL",
    "gn:name":"Bergia",
    "gn:population":1,
    "gn:timezone":"Europe/Rome",
    "iso:country":"IT",
    "name:aze_x_preferred":[
        "Berqiya"
    ],
    "name:cat_x_preferred":[
        "Bergia"
    ],
    "name:fas_x_preferred":[
        "\u0633\u0631\u062e\u0627\u0628\u06cc"
    ],
    "name:pol_x_preferred":[
        "Bergia"
    ],
    "name:por_x_preferred":[
        "Bergia"
    ],
    "name:rus_x_preferred":[
        "\u0411\u0435\u0440\u0433\u0438\u044f"
    ],
    "name:spa_x_preferred":[
        "Bergia"
    ],
    "name:zho_x_preferred":[
        "\u7530\u7e41\u7f15\u5c5e"
    ],
    "wof:name":"Bergia",
    "wof:placetype":"locality",
    "wof:population":1
},
  "geometry": {"coordinates":[7.38391,44.36553],"type":"Point"}
}