{
  "type": "Feature",
  "properties": {
    "gn:admin1_code":"15",
    "gn:admin2_code":"CT",
    "gn:admin3_code":"87007.0",
    "gn:asciiname":"Pietra Forcella",
    "gn:country_code":"IT",
    "gn:dem":685,
    "gn:feature_class":"P",
    "gn:feature_code":"PPL",
    "gn:name":"Pietra Forcella",
    "gn:population":230,
    "gn:timezone":"Europe/Rome",
    "iso:country":"IT",
    "wof:name":"Pietra Forcella",
    "wof:placetype":"locality",
    "wof:population":230
},
  "geometry": {"coordinates":[15.00084,37.60819],"type":"Point"}
}