{
  "type": "Feature",
  "properties": {
    "gn:admin1_code":"18.0",
    "gn:admin2_code":"PG",
    "gn:admin3_code":"54037.0",
    "gn:asciiname":"Tavernelle di Panicale",
    "gn:country_code":"IT",
    "gn:dem":487,
    "gn:feature_class":"P",
    "gn:feature_code":"PPL",
    "gn:name":"Tavernelle di Panicale",
    "gn:population":0,
    "gn:timezone":"Europe/Rome",
    "iso:country":"IT",
    "wof:name":"Tavernelle di Panicale",
    "wof:placetype":"locality"
},
  "geometry": {"coordinates":[12.168,43.06501],"type":"Point"}
}