{
  "type": "Feature",
  "properties": {
    "gn:admin1_code":"20",
    "gn:admin2_code":"PD",
    "gn:admin3_code":"28054.0",
    "gn:asciiname":"Marafon",
    "gn:country_code":"IT",
    "gn:dem":20,
    "gn:feature_class":"P",
    "gn:feature_code":"PPL",
    "gn:name":"Marafon",
    "gn:population":48,
    "gn:timezone":"Europe/Rome",
    "iso:country":"IT",
    "wof:name":"Marafon",
    "wof:placetype":"locality",
    "wof:population":48
},
  "geometry": {"coordinates":[11.75118,45.47301],"type":"Point"}
}