{
  "type": "Feature",
  "properties": {
    "gn:admin1_code":"9",
    "gn:admin2_code":"BS",
    "gn:admin3_code":"17204.0",
    "gn:asciiname":"Corona",
    "gn:country_code":"IT",
    "gn:dem":231,
    "gn:feature_class":"P",
    "gn:feature_code":"PPL",
    "gn:name":"Corona",
    "gn:population":48,
    "gn:timezone":"Europe/Rome",
    "iso:country":"IT",
    "wof:name":"Corona",
    "wof:placetype":"locality",
    "wof:population":48
},
  "geometry": {"coordinates":[10.50176,45.62904],"type":"Point"}
}