{
  "type": "Feature",
  "properties": {
    "gn:admin1_code":"4",
    "gn:admin2_code":"CE",
    "gn:admin3_code":"61009.0",
    "gn:asciiname":"San Pietro",
    "gn:country_code":"IT",
    "gn:dem":161,
    "gn:feature_class":"P",
    "gn:feature_code":"PPL",
    "gn:name":"San Pietro",
    "gn:population":58,
    "gn:timezone":"Europe/Rome",
    "iso:country":"IT",
    "name:ceb_x_preferred":[
        "San Pietro"
    ],
    "name:deu_x_preferred":[
        "San Pietro"
    ],
    "name:epo_x_preferred":[
        "San Pietro"
    ],
    "name:fra_x_preferred":[
        "San Pietro"
    ],
    "name:ita_x_preferred":[
        "San Pietro"
    ],
    "name:pol_x_preferred":[
        "San Pietro"
    ],
    "name:por_x_preferred":[
        "San Pietro"
    ],
    "name:sco_x_preferred":[
        "San Pietro"
    ],
    "name:srp_x_preferred":[
        "San Pjetro"
    ],
    "name:swe_x_preferred":[
        "San Pietro"
    ],
    "wof:name":"San Pietro",
    "wof:placetype":"locality",
    "wof:population":58
},
  "geometry": {"coordinates":[14.35542,41.19614],"type":"Point"}
}