{
  "type": "Feature",
  "properties": {
    "gn:admin1_code":"20.0",
    "gn:admin2_code":"VR",
    "gn:admin3_code":"23087.0",
    "gn:asciiname":"Calavena",
    "gn:country_code":"IT",
    "gn:dem":380,
    "gn:feature_class":"P",
    "gn:feature_code":"PPL",
    "gn:name":"Calavena",
    "gn:population":22,
    "gn:timezone":"Europe/Rome",
    "iso:country":"IT",
    "wof:name":"Calavena",
    "wof:placetype":"locality",
    "wof:population":22
},
  "geometry": {"coordinates":[11.1729,45.53198],"type":"Point"}
}