{
  "type": "Feature",
  "properties": {
    "gn:admin1_code":"9",
    "gn:admin2_code":"LC",
    "gn:admin3_code":"97090.0",
    "gn:asciiname":"Molere",
    "gn:country_code":"IT",
    "gn:dem":419,
    "gn:feature_class":"P",
    "gn:feature_code":"PPL",
    "gn:name":"Molere",
    "gn:population":23,
    "gn:timezone":"Europe/Rome",
    "iso:country":"IT",
    "wof:name":"Molere",
    "wof:placetype":"locality",
    "wof:population":23
},
  "geometry": {"coordinates":[9.33307,45.71959],"type":"Point"}
}