{
  "type": "Feature",
  "properties": {
    "gn:admin1_code":"9",
    "gn:admin2_code":"PV",
    "gn:admin3_code":"18143.0",
    "gn:asciiname":"Donelasco",
    "gn:country_code":"IT",
    "gn:dem":271,
    "gn:feature_class":"P",
    "gn:feature_code":"PPL",
    "gn:name":"Donelasco",
    "gn:population":81,
    "gn:timezone":"Europe/Rome",
    "iso:country":"IT",
    "wof:name":"Donelasco",
    "wof:placetype":"locality",
    "wof:population":81
},
  "geometry": {"coordinates":[9.30687,44.99897],"type":"Point"}
}