{
  "type": "Feature",
  "properties": {
    "gn:admin1_code":"4",
    "gn:admin2_code":"AV",
    "gn:admin3_code":"64023.0",
    "gn:asciiname":"Valle",
    "gn:country_code":"IT",
    "gn:dem":431,
    "gn:feature_class":"P",
    "gn:feature_code":"PPL",
    "gn:name":"Valle",
    "gn:population":34,
    "gn:timezone":"Europe/Rome",
    "iso:country":"IT",
    "name:ast_x_preferred":[
        "Valle"
    ],
    "name:cat_x_preferred":[
        "Valle"
    ],
    "name:ceb_x_preferred":[
        "Valle"
    ],
    "name:dan_x_preferred":[
        "Valle"
    ],
    "name:deu_x_preferred":[
        "Valle"
    ],
    "name:epo_x_preferred":[
        "Valle"
    ],
    "name:est_x_preferred":[
        "Valle"
    ],
    "name:eus_x_preferred":[
        "Valle"
    ],
    "name:fin_x_preferred":[
        "Valle"
    ],
    "name:fra_x_preferred":[
        "Valle"
    ],
    "name:heb_x_preferred":[
        "\u05d5\u05d0\u05dc\u05d4"
    ],
    "name:hrv_x_preferred":[
        "Valle"
    ],
    "name:ita_x_preferred":[
        "Valle"
    ],
    "name:nld_x_preferred":[
        "Valle"
    ],
    "name:nor_x_preferred":[
        "Valle"
    ],
    "name:pol_x_preferred":[
        "Valle"
    ],
    "name:ron_x_preferred":[
        "Valle"
    ],
    "name:rus_x_preferred":[
        "\u0412\u0430\u043b\u044c\u0435"
    ],
    "name:spa_x_preferred":[
        "Valle"
    ],
    "name:srp_x_preferred":[
        "\u0412\u0430\u043b\u0435"
    ],
    "name:swe_x_preferred":[
        "Valle"
    ],
    "wof:name":"Valle",
    "wof:placetype":"locality",
    "wof:population":34
},
  "geometry": {"coordinates":[15.04202,40.9217],"type":"Point"}
}