{
  "type": "Feature",
  "properties": {
    "gn:admin1_code":"4",
    "gn:admin2_code":"AV",
    "gn:admin3_code":"64116.0",
    "gn:asciiname":"Ilici 1",
    "gn:country_code":"IT",
    "gn:dem":350,
    "gn:feature_class":"P",
    "gn:feature_code":"PPL",
    "gn:name":"Ilici 1",
    "gn:population":37,
    "gn:timezone":"Europe/Rome",
    "iso:country":"IT",
    "wof:name":"Ilici 1",
    "wof:placetype":"locality",
    "wof:population":37
},
  "geometry": {"coordinates":[14.90626,41.04973],"type":"Point"}
}