{
  "type": "Feature",
  "properties": {
    "gn:admin1_code":"20.0",
    "gn:admin2_code":"VI",
    "gn:admin3_code":"24029.0",
    "gn:asciiname":"Vandinei",
    "gn:country_code":"IT",
    "gn:dem":370,
    "gn:feature_class":"P",
    "gn:feature_code":"PPL",
    "gn:name":"Vandinei",
    "gn:population":20,
    "gn:timezone":"Europe/Rome",
    "iso:country":"IT",
    "wof:name":"Vandinei",
    "wof:placetype":"locality",
    "wof:population":20
},
  "geometry": {"coordinates":[11.26528,45.54155],"type":"Point"}
}