{
  "type": "Feature",
  "properties": {
    "gn:admin1_code":"20",
    "gn:admin2_code":"VI",
    "gn:admin3_code":"24021.0",
    "gn:asciiname":"Vanzo Vecchio",
    "gn:country_code":"IT",
    "gn:dem":23,
    "gn:feature_class":"P",
    "gn:feature_code":"PPL",
    "gn:name":"Vanzo Vecchio",
    "gn:population":45,
    "gn:timezone":"Europe/Rome",
    "iso:country":"IT",
    "wof:name":"Vanzo Vecchio",
    "wof:placetype":"locality",
    "wof:population":45
},
  "geometry": {"coordinates":[11.72372,45.50054],"type":"Point"}
}