{
  "type": "Feature",
  "properties": {
    "gn:admin1_code":"5.0",
    "gn:admin2_code":"PR",
    "gn:admin3_code":"34018.0",
    "gn:asciiname":"Valle di Castrignano",
    "gn:country_code":"IT",
    "gn:dem":490,
    "gn:feature_class":"P",
    "gn:feature_code":"PPL",
    "gn:name":"Valle di Castrignano",
    "gn:population":50,
    "gn:timezone":"Europe/Rome",
    "iso:country":"IT",
    "wof:name":"Valle di Castrignano",
    "wof:placetype":"locality",
    "wof:population":50
},
  "geometry": {"coordinates":[10.21242,44.59933],"type":"Point"}
}