{
  "type": "Feature",
  "properties": {
    "gn:admin1_code":"9",
    "gn:admin2_code":"BS",
    "gn:admin3_code":"17076.0",
    "gn:asciiname":"Mignone",
    "gn:country_code":"IT",
    "gn:dem":786,
    "gn:feature_class":"P",
    "gn:feature_code":"PPL",
    "gn:name":"Mignone",
    "gn:population":18,
    "gn:timezone":"Europe/Rome",
    "iso:country":"IT",
    "wof:name":"Mignone",
    "wof:placetype":"locality",
    "wof:population":18
},
  "geometry": {"coordinates":[10.63686,45.73129],"type":"Point"}
}