{
  "type": "Feature",
  "properties": {
    "gn:admin1_code":"9.0",
    "gn:admin2_code":"MN",
    "gn:admin3_code":"20044.0",
    "gn:asciiname":"Marchino",
    "gn:country_code":"IT",
    "gn:dem":86,
    "gn:feature_class":"P",
    "gn:feature_code":"PPLL",
    "gn:name":"Marchino",
    "gn:population":0,
    "gn:timezone":"Europe/Rome",
    "iso:country":"IT",
    "wof:name":"Marchino",
    "wof:placetype":"locality"
},
  "geometry": {"coordinates":[10.69704,45.40119],"type":"Point"}
}