{
  "type": "Feature",
  "properties": {
    "gn:admin1_code":"4",
    "gn:admin2_code":"BN",
    "gn:admin3_code":"62017.0",
    "gn:asciiname":"Masseria Ciccoporcari",
    "gn:country_code":"IT",
    "gn:dem":717,
    "gn:feature_class":"P",
    "gn:feature_code":"PPL",
    "gn:name":"Masseria Ciccoporcari",
    "gn:population":32,
    "gn:timezone":"Europe/Rome",
    "iso:country":"IT",
    "wof:name":"Masseria Ciccoporcari",
    "wof:placetype":"locality",
    "wof:population":32
},
  "geometry": {"coordinates":[14.81687,41.40203],"type":"Point"}
}