{
  "type": "Feature",
  "properties": {
    "gn:admin1_code":"15",
    "gn:admin2_code":"TP",
    "gn:admin3_code":"81013.0",
    "gn:asciiname":"Murana",
    "gn:country_code":"IT",
    "gn:dem":5,
    "gn:feature_class":"P",
    "gn:feature_code":"PPL",
    "gn:name":"Murana",
    "gn:population":27,
    "gn:timezone":"Europe/Rome",
    "iso:country":"IT",
    "wof:name":"Murana",
    "wof:placetype":"locality",
    "wof:population":27
},
  "geometry": {"coordinates":[12.5105,37.9855],"type":"Point"}
}