{
  "type": "Feature",
  "properties": {
    "gn:admin1_code":"10",
    "gn:admin2_code":"AN",
    "gn:admin3_code":"42020.0",
    "gn:asciiname":"Ponte Chiaradovo",
    "gn:country_code":"IT",
    "gn:dem":191,
    "gn:feature_class":"P",
    "gn:feature_code":"PPL",
    "gn:name":"Ponte Chiaradovo",
    "gn:population":18,
    "gn:timezone":"Europe/Rome",
    "iso:country":"IT",
    "wof:name":"Ponte Chiaradovo",
    "wof:placetype":"locality",
    "wof:population":18
},
  "geometry": {"coordinates":[12.98982,43.41928],"type":"Point"}
}