{
  "type": "Feature",
  "properties": {
    "gn:admin1_code":"9",
    "gn:admin2_code":"LC",
    "gn:admin3_code":"97058.0",
    "gn:asciiname":"Brughe",
    "gn:country_code":"IT",
    "gn:dem":304,
    "gn:feature_class":"P",
    "gn:feature_code":"PPL",
    "gn:name":"Brugh\u00e8",
    "gn:population":32,
    "gn:timezone":"Europe/Rome",
    "iso:country":"IT",
    "name:und_x_variant":[
        "Brugh\u00e8"
    ],
    "wof:name":"Brughe",
    "wof:placetype":"locality",
    "wof:population":32
},
  "geometry": {"coordinates":[9.38913,45.70857],"type":"Point"}
}