{
  "type": "Feature",
  "properties": {
    "gn:admin1_code":"1",
    "gn:admin2_code":"TE",
    "gn:admin3_code":"67027.0",
    "gn:asciiname":"Crocetta Santa Maria",
    "gn:country_code":"IT",
    "gn:dem":372,
    "gn:feature_class":"P",
    "gn:feature_code":"PPL",
    "gn:name":"Crocetta Santa Maria",
    "gn:population":77,
    "gn:timezone":"Europe/Rome",
    "iso:country":"IT",
    "wof:name":"Crocetta Santa Maria",
    "wof:placetype":"locality",
    "wof:population":77
},
  "geometry": {"coordinates":[13.88786,42.55448],"type":"Point"}
}