{
  "type": "Feature",
  "properties": {
    "gn:admin1_code":"7",
    "gn:admin2_code":"RM",
    "gn:admin3_code":"58015.0",
    "gn:asciiname":"Monte Sarleo",
    "gn:country_code":"IT",
    "gn:dem":200,
    "gn:feature_class":"P",
    "gn:feature_code":"PPL",
    "gn:name":"Monte Sarleo",
    "gn:population":223,
    "gn:timezone":"Europe/Rome",
    "iso:country":"IT",
    "wof:name":"Monte Sarleo",
    "wof:placetype":"locality",
    "wof:population":223
},
  "geometry": {"coordinates":[12.35242,42.15962],"type":"Point"}
}