{
  "type": "Feature",
  "properties": {
    "gn:admin1_code":"4",
    "gn:admin2_code":"BN",
    "gn:admin3_code":"62046.0",
    "gn:asciiname":"Cerzoccole",
    "gn:country_code":"IT",
    "gn:dem":537,
    "gn:feature_class":"P",
    "gn:feature_code":"PPL",
    "gn:name":"Cerzoccole",
    "gn:population":50,
    "gn:timezone":"Europe/Rome",
    "iso:country":"IT",
    "wof:name":"Cerzoccole",
    "wof:placetype":"locality",
    "wof:population":50
},
  "geometry": {"coordinates":[14.87393,41.24076],"type":"Point"}
}