{
  "type": "Feature",
  "properties": {
    "gn:admin1_code":"17",
    "gn:admin2_code":"TN",
    "gn:admin3_code":"22080.0",
    "gn:asciiname":"Canazzi",
    "gn:country_code":"IT",
    "gn:dem":337,
    "gn:feature_class":"P",
    "gn:feature_code":"PPL",
    "gn:name":"Canazzi",
    "gn:population":16,
    "gn:timezone":"Europe/Rome",
    "iso:country":"IT",
    "wof:name":"Canazzi",
    "wof:placetype":"locality",
    "wof:population":16
},
  "geometry": {"coordinates":[11.14434,46.19313],"type":"Point"}
}