{
  "type": "Feature",
  "properties": {
    "gn:admin1_code":"5",
    "gn:admin2_code":"BO",
    "gn:admin3_code":"37010.0",
    "gn:asciiname":"La Piana",
    "gn:country_code":"IT",
    "gn:dem":634,
    "gn:feature_class":"P",
    "gn:feature_code":"PPL",
    "gn:name":"La Piana",
    "gn:population":38,
    "gn:timezone":"Europe/Rome",
    "iso:country":"IT",
    "wof:name":"La Piana",
    "wof:placetype":"locality",
    "wof:population":38
},
  "geometry": {"coordinates":[11.05887,44.12881],"type":"Point"}
}