{
  "type": "Feature",
  "properties": {
    "gn:admin1_code":"10.0",
    "gn:admin2_code":"AN",
    "gn:admin3_code":"42045.0",
    "gn:asciiname":"Montignano-Marzocca",
    "gn:country_code":"IT",
    "gn:dem":5,
    "gn:elevation":"4.0",
    "gn:feature_class":"P",
    "gn:feature_code":"PPL",
    "gn:name":"Montignano-Marzocca",
    "gn:population":4590,
    "gn:timezone":"Europe/Rome",
    "iso:country":"IT",
    "wof:name":"Montignano-Marzocca",
    "wof:placetype":"locality",
    "wof:population":4590
},
  "geometry": {"coordinates":[13.29093,43.67451],"type":"Point"}
}