{
  "type": "Feature",
  "properties": {
    "gn:admin1_code":"16",
    "gn:admin2_code":"MS",
    "gn:admin3_code":"45007.0",
    "gn:asciiname":"Piano di Collecchia",
    "gn:country_code":"IT",
    "gn:dem":115,
    "gn:feature_class":"P",
    "gn:feature_code":"PPL",
    "gn:name":"Piano di Collecchia",
    "gn:population":118,
    "gn:timezone":"Europe/Rome",
    "iso:country":"IT",
    "wof:name":"Piano di Collecchia",
    "wof:placetype":"locality",
    "wof:population":118
},
  "geometry": {"coordinates":[10.04101,44.21467],"type":"Point"}
}