{
  "type": "Feature",
  "properties": {
    "gn:admin1_code":"6",
    "gn:admin2_code":"UD",
    "gn:admin3_code":"30034.0",
    "gn:asciiname":"Lase",
    "gn:country_code":"IT",
    "gn:dem":763,
    "gn:feature_class":"P",
    "gn:feature_code":"PPL",
    "gn:name":"Lase",
    "gn:population":11,
    "gn:timezone":"Europe/Rome",
    "iso:country":"IT",
    "wof:name":"Lase",
    "wof:placetype":"locality",
    "wof:population":11
},
  "geometry": {"coordinates":[13.62686,46.18299],"type":"Point"}
}