{
  "type": "Feature",
  "properties": {
    "gn:admin1_code":"10",
    "gn:admin2_code":"MC",
    "gn:admin3_code":"43013.0",
    "gn:asciiname":"Zona Industriale",
    "gn:country_code":"IT",
    "gn:dem":21,
    "gn:feature_class":"P",
    "gn:feature_code":"PPLL",
    "gn:name":"Zona Industriale",
    "gn:population":7,
    "gn:timezone":"Europe/Rome",
    "iso:country":"IT",
    "wof:name":"Zona Industriale",
    "wof:placetype":"locality",
    "wof:population":7
},
  "geometry": {"coordinates":[13.68115,43.28458],"type":"Point"}
}