{
  "type": "Feature",
  "properties": {
    "gn:admin1_code":"16.0",
    "gn:admin2_code":"AR",
    "gn:admin3_code":"51040.0",
    "gn:asciiname":"Fornello",
    "gn:country_code":"IT",
    "gn:dem":1247,
    "gn:feature_class":"P",
    "gn:feature_code":"PPL",
    "gn:name":"Fornello",
    "gn:population":0,
    "gn:timezone":"Europe/Rome",
    "iso:country":"IT",
    "wof:name":"Fornello",
    "wof:placetype":"locality"
},
  "geometry": {"coordinates":[11.61667,43.66667],"type":"Point"}
}