{
  "type": "Feature",
  "properties": {
    "gn:admin1_code":"2",
    "gn:admin2_code":"PZ",
    "gn:admin3_code":"76006.0",
    "gn:asciiname":"Contrada Casale di Sotto",
    "gn:country_code":"IT",
    "gn:dem":749,
    "gn:feature_class":"P",
    "gn:feature_code":"PPL",
    "gn:name":"Contrada Casale di Sotto",
    "gn:population":13,
    "gn:timezone":"Europe/Rome",
    "iso:country":"IT",
    "wof:name":"Contrada Casale di Sotto",
    "wof:placetype":"locality",
    "wof:population":13
},
  "geometry": {"coordinates":[15.66867,40.79611],"type":"Point"}
}