{
  "type": "Feature",
  "properties": {
    "gn:admin1_code":"20.0",
    "gn:admin2_code":"BL",
    "gn:admin3_code":"25012.0",
    "gn:asciiname":"Montanes",
    "gn:country_code":"IT",
    "gn:dem":869,
    "gn:feature_class":"P",
    "gn:feature_code":"PPL",
    "gn:name":"Montanes",
    "gn:population":0,
    "gn:timezone":"Europe/Rome",
    "iso:country":"IT",
    "wof:name":"Montanes",
    "wof:placetype":"locality"
},
  "geometry": {"coordinates":[12.39139,46.18472],"type":"Point"}
}