{
  "type": "Feature",
  "properties": {
    "gn:admin1_code":"6.0",
    "gn:admin2_code":"UD",
    "gn:admin3_code":"30063.0",
    "gn:asciiname":"Brazzacco",
    "gn:country_code":"IT",
    "gn:dem":211,
    "gn:elevation":"202.0",
    "gn:feature_class":"P",
    "gn:feature_code":"PPL",
    "gn:name":"Brazzacco",
    "gn:population":762,
    "gn:timezone":"Europe/Rome",
    "iso:country":"IT",
    "wof:name":"Brazzacco",
    "wof:placetype":"locality",
    "wof:population":762
},
  "geometry": {"coordinates":[13.15917,46.12133],"type":"Point"}
}