{
  "type": "Feature",
  "properties": {
    "gn:admin1_code":"9",
    "gn:admin2_code":"BG",
    "gn:admin3_code":"16246.0",
    "gn:asciiname":"Sottoripa",
    "gn:country_code":"IT",
    "gn:dem":510,
    "gn:feature_class":"P",
    "gn:feature_code":"PPL",
    "gn:name":"Sottoripa",
    "gn:population":71,
    "gn:timezone":"Europe/Rome",
    "iso:country":"IT",
    "wof:name":"Sottoripa",
    "wof:placetype":"locality",
    "wof:population":71
},
  "geometry": {"coordinates":[9.68125,45.81674],"type":"Point"}
}