{
  "type": "Feature",
  "properties": {
    "gn:admin1_code":"20",
    "gn:admin2_code":"RO",
    "gn:admin3_code":"29001.0",
    "gn:asciiname":"Montefalche",
    "gn:country_code":"IT",
    "gn:dem":-2,
    "gn:feature_class":"P",
    "gn:feature_code":"PPL",
    "gn:name":"Montefalche",
    "gn:population":26,
    "gn:timezone":"Europe/Rome",
    "iso:country":"IT",
    "wof:name":"Montefalche",
    "wof:placetype":"locality",
    "wof:population":26
},
  "geometry": {"coordinates":[12.01668,45.08256],"type":"Point"}
}