{
  "type": "Feature",
  "properties": {
    "gn:admin1_code":"8",
    "gn:admin2_code":"GE",
    "gn:admin3_code":"10040.0",
    "gn:asciiname":"La Costa",
    "gn:country_code":"IT",
    "gn:dem":375,
    "gn:feature_class":"P",
    "gn:feature_code":"PPL",
    "gn:name":"La Costa",
    "gn:population":19,
    "gn:timezone":"Europe/Rome",
    "iso:country":"IT",
    "wof:name":"La Costa",
    "wof:placetype":"locality",
    "wof:population":19
},
  "geometry": {"coordinates":[9.44174,44.34163],"type":"Point"}
}