{
  "type": "Feature",
  "properties": {
    "gn:admin1_code":"19",
    "gn:admin2_code":"AO",
    "gn:admin3_code":"7002.0",
    "gn:asciiname":"Cerian-Epaillon",
    "gn:country_code":"IT",
    "gn:dem":1032,
    "gn:feature_class":"P",
    "gn:feature_code":"PPL",
    "gn:name":"Cerian-Epaillon",
    "gn:population":56,
    "gn:timezone":"Europe/Rome",
    "iso:country":"IT",
    "wof:name":"Cerian-Epaillon",
    "wof:placetype":"locality",
    "wof:population":56
},
  "geometry": {"coordinates":[7.58677,45.79663],"type":"Point"}
}