{
  "type": "Feature",
  "properties": {
    "gn:admin1_code":"8",
    "gn:admin2_code":"IM",
    "gn:admin3_code":"8046.0",
    "gn:asciiname":"Ponti",
    "gn:country_code":"IT",
    "gn:dem":390,
    "gn:feature_class":"P",
    "gn:feature_code":"PPL",
    "gn:name":"Ponti",
    "gn:population":107,
    "gn:timezone":"Europe/Rome",
    "iso:country":"IT",
    "name:ceb_x_preferred":[
        "Ponti"
    ],
    "name:deu_x_preferred":[
        "Ponti"
    ],
    "name:fas_x_preferred":[
        "\u067e\u0648\u0646\u062a\u06cc"
    ],
    "name:fra_x_preferred":[
        "Ponti"
    ],
    "name:ita_x_preferred":[
        "Ponti"
    ],
    "name:srp_x_preferred":[
        "Ponti"
    ],
    "name:swe_x_preferred":[
        "Ponti"
    ],
    "name:ukr_x_preferred":[
        "\u041f\u043e\u043d\u0442\u0456"
    ],
    "wof:name":"Ponti",
    "wof:placetype":"locality",
    "wof:population":107
},
  "geometry": {"coordinates":[7.85566,44.06491],"type":"Point"}
}