{
  "type": "Feature",
  "properties": {
    "gn:admin1_code":"20",
    "gn:admin2_code":"TV",
    "gn:admin3_code":"26013.0",
    "gn:asciiname":"Battistini",
    "gn:country_code":"IT",
    "gn:dem":43,
    "gn:feature_class":"P",
    "gn:feature_code":"PPL",
    "gn:name":"Battistini",
    "gn:population":15,
    "gn:timezone":"Europe/Rome",
    "iso:country":"IT",
    "wof:name":"Battistini",
    "wof:placetype":"locality",
    "wof:population":15
},
  "geometry": {"coordinates":[11.88343,45.67616],"type":"Point"}
}