{
  "type": "Feature",
  "properties": {
    "gn:admin1_code":"20",
    "gn:admin2_code":"TV",
    "gn:admin3_code":"26087.0",
    "gn:asciiname":"Case Polit",
    "gn:country_code":"IT",
    "gn:dem":349,
    "gn:feature_class":"P",
    "gn:feature_code":"PPL",
    "gn:name":"Case Polit",
    "gn:population":36,
    "gn:timezone":"Europe/Rome",
    "iso:country":"IT",
    "wof:name":"Case Polit",
    "wof:placetype":"locality",
    "wof:population":36
},
  "geometry": {"coordinates":[12.0237,45.903],"type":"Point"}
}