{
  "type": "Feature",
  "properties": {
    "gn:admin1_code":"5",
    "gn:admin2_code":"PC",
    "gn:admin3_code":"33030.0",
    "gn:asciiname":"Cabosa",
    "gn:country_code":"IT",
    "gn:dem":738,
    "gn:feature_class":"P",
    "gn:feature_code":"PPLL",
    "gn:name":"Cabosa",
    "gn:population":8,
    "gn:timezone":"Europe/Rome",
    "iso:country":"IT",
    "wof:name":"Cabosa",
    "wof:placetype":"locality",
    "wof:population":8
},
  "geometry": {"coordinates":[9.31384,44.62097],"type":"Point"}
}