{
  "type": "Feature",
  "properties": {
    "gn:admin1_code":"11.0",
    "gn:admin2_code":"CB",
    "gn:admin3_code":"70078.0",
    "gn:asciiname":"Colle della Torre",
    "gn:country_code":"IT",
    "gn:dem":48,
    "gn:feature_class":"P",
    "gn:feature_code":"PPL",
    "gn:name":"Colle della Torre",
    "gn:population":680,
    "gn:timezone":"Europe/Rome",
    "iso:country":"IT",
    "wof:name":"Colle della Torre",
    "wof:placetype":"locality",
    "wof:population":680
},
  "geometry": {"coordinates":[14.94959,42.00628],"type":"Point"}
}