{
  "type": "Feature",
  "properties": {
    "gn:admin1_code":"12",
    "gn:admin2_code":"CN",
    "gn:admin3_code":"4009.0",
    "gn:asciiname":"Fenoglio",
    "gn:country_code":"IT",
    "gn:dem":414,
    "gn:feature_class":"P",
    "gn:feature_code":"PPL",
    "gn:name":"Fenoglio",
    "gn:population":29,
    "gn:timezone":"Europe/Rome",
    "iso:country":"IT",
    "wof:name":"Fenoglio",
    "wof:placetype":"locality",
    "wof:population":29
},
  "geometry": {"coordinates":[7.29616,44.77247],"type":"Point"}
}