{
  "type": "Feature",
  "properties": {
    "gn:admin1_code":"4",
    "gn:admin2_code":"AV",
    "gn:admin3_code":"64008.0",
    "gn:asciiname":"Cardalani",
    "gn:country_code":"IT",
    "gn:dem":359,
    "gn:feature_class":"P",
    "gn:feature_code":"PPL",
    "gn:name":"Cardalani",
    "gn:population":25,
    "gn:timezone":"Europe/Rome",
    "iso:country":"IT",
    "wof:name":"Cardalani",
    "wof:placetype":"locality",
    "wof:population":25
},
  "geometry": {"coordinates":[14.79375,40.93509],"type":"Point"}
}