{
  "type": "Feature",
  "properties": {
    "gn:admin1_code":"4",
    "gn:admin2_code":"SA",
    "gn:admin3_code":"65028.0",
    "gn:asciiname":"Carullo",
    "gn:country_code":"IT",
    "gn:dem":321,
    "gn:feature_class":"P",
    "gn:feature_code":"PPL",
    "gn:name":"Carullo",
    "gn:population":96,
    "gn:timezone":"Europe/Rome",
    "iso:country":"IT",
    "wof:name":"Carullo",
    "wof:placetype":"locality",
    "wof:population":96
},
  "geometry": {"coordinates":[15.12581,40.21991],"type":"Point"}
}