{
  "type": "Feature",
  "properties": {
    "gn:admin1_code":"4",
    "gn:admin2_code":"AV",
    "gn:admin3_code":"64073.0",
    "gn:asciiname":"Starza",
    "gn:country_code":"IT",
    "gn:dem":264,
    "gn:feature_class":"P",
    "gn:feature_code":"PPL",
    "gn:name":"Starza",
    "gn:population":60,
    "gn:timezone":"Europe/Rome",
    "iso:country":"IT",
    "name:ceb_x_preferred":[
        "Starza"
    ],
    "name:pol_x_preferred":[
        "Starza"
    ],
    "name:vie_x_preferred":[
        "Starza"
    ],
    "wof:name":"Starza",
    "wof:placetype":"locality",
    "wof:population":60
},
  "geometry": {"coordinates":[14.75583,41.00678],"type":"Point"}
}