{
  "type": "Feature",
  "properties": {
    "gn:admin1_code":"1.0",
    "gn:admin2_code":"TE",
    "gn:admin3_code":"67030.0",
    "gn:asciiname":"Notaresco Stazione",
    "gn:country_code":"IT",
    "gn:dem":78,
    "gn:feature_class":"P",
    "gn:feature_code":"PPL",
    "gn:name":"Notaresco Stazione",
    "gn:population":446,
    "gn:timezone":"Europe/Rome",
    "iso:country":"IT",
    "wof:name":"Notaresco Stazione",
    "wof:placetype":"locality",
    "wof:population":446
},
  "geometry": {"coordinates":[13.87768,42.70747],"type":"Point"}
}