{
  "type": "Feature",
  "properties": {
    "gn:admin1_code":"20",
    "gn:admin2_code":"PD",
    "gn:admin3_code":"28046.0",
    "gn:asciiname":"Salvalajo",
    "gn:country_code":"IT",
    "gn:dem":19,
    "gn:feature_class":"P",
    "gn:feature_code":"PPL",
    "gn:name":"Salvalajo",
    "gn:population":39,
    "gn:timezone":"Europe/Rome",
    "iso:country":"IT",
    "wof:name":"Salvalajo",
    "wof:placetype":"locality",
    "wof:population":39
},
  "geometry": {"coordinates":[11.96384,45.57436],"type":"Point"}
}