{
  "type": "Feature",
  "properties": {
    "gn:admin1_code":"4.0",
    "gn:admin2_code":"BN",
    "gn:admin3_code":"62070.0",
    "gn:asciiname":"Paolini",
    "gn:country_code":"IT",
    "gn:dem":308,
    "gn:elevation":"310.0",
    "gn:feature_class":"P",
    "gn:feature_code":"PPL",
    "gn:name":"Paolini",
    "gn:population":70,
    "gn:timezone":"Europe/Rome",
    "iso:country":"IT",
    "name:cos_x_preferred":[
        "Paolini"
    ],
    "wof:name":"Paolini",
    "wof:placetype":"locality",
    "wof:population":70
},
  "geometry": {"coordinates":[14.53826,41.10426],"type":"Point"}
}