{
  "type": "Feature",
  "properties": {
    "iso:country":"IT",
    "wof:name":"La Fontana",
    "wof:placetype":"neighbourhood"
},
  "geometry": {"coordinates":[9.18791533000983,45.49233902527335],"type":"Point"}
}