{
  "type": "Feature",
  "properties": {
    "gn:admin1_code":"8.0",
    "gn:admin2_code":"GE",
    "gn:admin3_code":"10034.0",
    "gn:asciiname":"Porciletto",
    "gn:country_code":"IT",
    "gn:dem":268,
    "gn:elevation":"280.0",
    "gn:feature_class":"P",
    "gn:feature_code":"PPL",
    "gn:name":"Porciletto",
    "gn:population":43,
    "gn:timezone":"Europe/Rome",
    "iso:country":"IT",
    "wof:name":"Porciletto",
    "wof:placetype":"locality",
    "wof:population":43
},
  "geometry": {"coordinates":[9.38935,44.38966],"type":"Point"}
}