{
  "type": "Feature",
  "properties": {
    "gn:admin1_code":"12",
    "gn:admin2_code":"TO",
    "gn:admin3_code":"1011.0",
    "gn:asciiname":"Marchetti",
    "gn:country_code":"IT",
    "gn:dem":910,
    "gn:feature_class":"P",
    "gn:feature_code":"PPLL",
    "gn:name":"Marchetti",
    "gn:population":7,
    "gn:timezone":"Europe/Rome",
    "iso:country":"IT",
    "name:cos_x_preferred":[
        "Marchetti"
    ],
    "name:ita_x_preferred":[
        "Marchetti"
    ],
    "wof:name":"Marchetti",
    "wof:placetype":"locality",
    "wof:population":7
},
  "geometry": {"coordinates":[7.22533,44.84986],"type":"Point"}
}