{
  "type": "Feature",
  "properties": {
    "gn:admin1_code":"9",
    "gn:admin2_code":"BS",
    "gn:admin3_code":"17043.0",
    "gn:asciiname":"Macina",
    "gn:country_code":"IT",
    "gn:dem":131,
    "gn:feature_class":"P",
    "gn:feature_code":"PPL",
    "gn:name":"Macina",
    "gn:population":304,
    "gn:timezone":"Europe/Rome",
    "iso:country":"IT",
    "name:ceb_x_preferred":[
        "Macina"
    ],
    "name:deu_x_preferred":[
        "Macina"
    ],
    "name:fra_x_preferred":[
        "Macina"
    ],
    "name:ind_x_preferred":[
        "Macina"
    ],
    "name:ita_x_preferred":[
        "Macina"
    ],
    "name:swe_x_preferred":[
        "Macina"
    ],
    "wof:name":"Macina",
    "wof:placetype":"locality",
    "wof:population":304
},
  "geometry": {"coordinates":[10.32035,45.47069000000001],"type":"Point"}
}