{
  "type": "Feature",
  "properties": {
    "gn:admin1_code":"12",
    "gn:admin2_code":"TO",
    "gn:admin3_code":"1204.0",
    "gn:asciiname":"Bocchiardi",
    "gn:country_code":"IT",
    "gn:dem":1190,
    "gn:feature_class":"P",
    "gn:feature_code":"PPLL",
    "gn:name":"Bocchiardi",
    "gn:population":8,
    "gn:timezone":"Europe/Rome",
    "iso:country":"IT",
    "wof:name":"Bocchiardi",
    "wof:placetype":"locality",
    "wof:population":8
},
  "geometry": {"coordinates":[7.18832,44.91139],"type":"Point"}
}