{
  "type": "Feature",
  "properties": {
    "gn:admin1_code":"18",
    "gn:admin2_code":"TR",
    "gn:admin3_code":"55033.0",
    "gn:asciiname":"Palombara-Palazzo",
    "gn:country_code":"IT",
    "gn:dem":412,
    "gn:feature_class":"P",
    "gn:feature_code":"PPL",
    "gn:name":"Palombara-Palazzo",
    "gn:population":138,
    "gn:timezone":"Europe/Rome",
    "iso:country":"IT",
    "wof:name":"Palombara-Palazzo",
    "wof:placetype":"locality",
    "wof:population":138
},
  "geometry": {"coordinates":[12.44079,42.67983],"type":"Point"}
}