{
  "type": "Feature",
  "properties": {
    "gn:admin1_code":"9",
    "gn:admin2_code":"LC",
    "gn:admin3_code":"97016.0",
    "gn:asciiname":"Verdura",
    "gn:country_code":"IT",
    "gn:dem":301,
    "gn:feature_class":"P",
    "gn:feature_code":"PPL",
    "gn:name":"Verdura",
    "gn:population":98,
    "gn:timezone":"Europe/Rome",
    "iso:country":"IT",
    "name:ceb_x_preferred":[
        "Fiume Verdura"
    ],
    "name:chv_x_preferred":[
        "\u0412\u0435\u0440\u0434\u0443\u0440\u0430"
    ],
    "name:ita_x_preferred":[
        "Verdura"
    ],
    "name:pol_x_preferred":[
        "Verdura"
    ],
    "name:zho_x_preferred":[
        "\u97cb\u723e\u675c\u62c9\u6cb3"
    ],
    "wof:name":"Verdura",
    "wof:placetype":"locality",
    "wof:population":98
},
  "geometry": {"coordinates":[9.32235,45.68191],"type":"Point"}
}