{
  "type": "Feature",
  "properties": {
    "gn:admin1_code":"4.0",
    "gn:admin2_code":"AV",
    "gn:admin3_code":"64014.0",
    "gn:asciiname":"Quaglietta",
    "gn:country_code":"IT",
    "gn:dem":271,
    "gn:elevation":"260.0",
    "gn:feature_class":"P",
    "gn:feature_code":"PPL",
    "gn:name":"Quaglietta",
    "gn:population":443,
    "gn:timezone":"Europe/Rome",
    "iso:country":"IT",
    "wof:name":"Quaglietta",
    "wof:placetype":"locality",
    "wof:population":443
},
  "geometry": {"coordinates":[15.23434,40.74531],"type":"Point"}
}