{
  "type": "Feature",
  "properties": {
    "gn:admin1_code":"19.0",
    "gn:admin2_code":"AO",
    "gn:admin3_code":"7022.0",
    "gn:asciiname":"Montita",
    "gn:country_code":"IT",
    "gn:dem":1641,
    "gn:feature_class":"P",
    "gn:feature_code":"PPL",
    "gn:name":"Montita",
    "gn:population":0,
    "gn:timezone":"Europe/Rome",
    "iso:country":"IT",
    "wof:name":"Montita",
    "wof:placetype":"locality"
},
  "geometry": {"coordinates":[6.98333,45.83333],"type":"Point"}
}