{
  "type": "Feature",
  "properties": {
    "gn:country":"IT",
    "gn:fcode":"PPL",
    "gn:population":444,
    "iso:country":"IT",
    "name:arg_x_preferred":[
        "Borda"
    ],
    "name:ceb_x_preferred":[
        "Borda"
    ],
    "name:deu_x_preferred":[
        "Borda"
    ],
    "name:fas_x_preferred":[
        "\u0628\u0631\u062f\u0627"
    ],
    "name:fra_x_preferred":[
        "Borda"
    ],
    "name:ita_x_preferred":[
        "Borda"
    ],
    "name:nds_x_preferred":[
        "Borda"
    ],
    "name:pol_x_preferred":[
        "Borda"
    ],
    "name:por_x_preferred":[
        "Borda"
    ],
    "name:spa_x_preferred":[
        "Borda"
    ],
    "name:srp_x_preferred":[
        "Borda"
    ],
    "name:swe_x_preferred":[
        "Borda"
    ],
    "qs_pg:aaroncc":"IT",
    "qs_pg:gn_country":"IT",
    "qs_pg:gn_fcode":"PPL",
    "qs_pg:gn_pop":444,
    "qs_pg:name":"Borda",
    "qs_pg:name_adm0":"Italia",
    "qs_pg:name_adm1":"Liguria",
    "qs_pg:photos_9r":0,
    "qs_pg:photos_sr":0,
    "qs_pg:pop_sr":2,
    "qs_pg:qs_pg_placetype":"locality",
    "qs_pg:qs_pg_placetype_gp":"Town",
    "qs_pg:woe_adm0":23424853,
    "woe:adm0_id":23424853,
    "woe:name_adm0":"Italia",
    "woe:name_adm1":"Liguria",
    "woe:placetype":"Town",
    "wof:name":"Borda",
    "wof:placetype":"locality",
    "wof:population":22
},
  "geometry": {"coordinates":[8.15,44.43333],"type":"Point"}
}