{
  "type": "Feature",
  "properties": {
    "gn:admin1_code":"8",
    "gn:admin2_code":"SV",
    "gn:admin3_code":"9056.0",
    "gn:asciiname":"Case Crocetta",
    "gn:country_code":"IT",
    "gn:dem":168,
    "gn:feature_class":"P",
    "gn:feature_code":"PPL",
    "gn:name":"Case Crocetta",
    "gn:population":22,
    "gn:timezone":"Europe/Rome",
    "iso:country":"IT",
    "wof:name":"Case Crocetta",
    "wof:placetype":"locality",
    "wof:population":22
},
  "geometry": {"coordinates":[8.4794,44.32671],"type":"Point"}
}