{
  "type": "Feature",
  "properties": {
    "gn:admin1_code":"6",
    "gn:admin2_code":"PN",
    "gn:admin3_code":"93028.0",
    "gn:asciiname":"Poiana",
    "gn:country_code":"IT",
    "gn:dem":12,
    "gn:feature_class":"P",
    "gn:feature_code":"PPL",
    "gn:name":"Poiana",
    "gn:population":22,
    "gn:timezone":"Europe/Rome",
    "iso:country":"IT",
    "name:ceb_x_preferred":[
        "Poiana"
    ],
    "name:deu_x_preferred":[
        "Poiana"
    ],
    "name:epo_x_preferred":[
        "Poiana"
    ],
    "name:hun_x_preferred":[
        "Poiana"
    ],
    "name:ita_x_preferred":[
        "Poiana"
    ],
    "name:ron_x_preferred":[
        "Poiana"
    ],
    "name:rus_x_preferred":[
        "\u041f\u043e\u044f\u043d\u0430"
    ],
    "name:srp_x_preferred":[
        "\u041f\u043e\u0458\u0430\u043d\u0430"
    ],
    "name:swe_x_preferred":[
        "Poiana"
    ],
    "name:ukr_x_preferred":[
        "\u041f\u043e\u044f\u043d\u0430"
    ],
    "name:vie_x_preferred":[
        "Poiana"
    ],
    "name:vol_x_preferred":[
        "Poiana"
    ],
    "wof:name":"Poiana",
    "wof:placetype":"locality",
    "wof:population":22
},
  "geometry": {"coordinates":[12.96835,45.8545],"type":"Point"}
}