{
  "type": "Feature",
  "properties": {
    "gn:admin1_code":"6",
    "gn:admin2_code":"PN",
    "gn:admin3_code":"93028.0",
    "gn:asciiname":"Poiana",
    "gn:country_code":"IT",
    "gn:dem":12,
    "gn:feature_class":"P",
    "gn:feature_code":"PPL",
    "gn:name":"Poiana",
    "gn:population":22,
    "gn:timezone":"Europe/Rome",
    "iso:country":"IT",
    "wof:name":"Poiana",
    "wof:placetype":"locality",
    "wof:population":22
},
  "geometry": {"coordinates":[12.96835,45.8545],"type":"Point"}
}