{
  "type": "Feature",
  "properties": {
    "gn:admin1_code":"20.0",
    "gn:admin2_code":"BL",
    "gn:admin3_code":"25022.0",
    "gn:asciiname":"San Niccolo",
    "gn:cc2":"IT",
    "gn:country_code":"IT",
    "gn:dem":494,
    "gn:feature_class":"P",
    "gn:feature_code":"PPL",
    "gn:name":"San Niccolo",
    "gn:population":0,
    "gn:timezone":"Europe/Rome",
    "iso:country":"IT",
    "name:und_x_variant":[
        "Niccolo",
        "San Nicolo",
        "San Niccolo"
    ],
    "wof:name":"San Niccolo",
    "wof:placetype":"locality"
},
  "geometry": {"coordinates":[11.83333,46.01667],"type":"Point"}
}