{
  "type": "Feature",
  "properties": {
    "gn:admin1_code":"5",
    "gn:admin2_code":"BO",
    "gn:admin3_code":"37027.0",
    "gn:asciiname":"Capanna Foresta",
    "gn:country_code":"IT",
    "gn:dem":479,
    "gn:feature_class":"P",
    "gn:feature_code":"PPL",
    "gn:name":"Capanna Foresta",
    "gn:population":15,
    "gn:timezone":"Europe/Rome",
    "iso:country":"IT",
    "wof:name":"Capanna Foresta",
    "wof:placetype":"locality",
    "wof:population":15
},
  "geometry": {"coordinates":[10.96656,44.19601],"type":"Point"}
}