{
  "type": "Feature",
  "properties": {
    "gn:admin1_code":"16",
    "gn:admin2_code":"FI",
    "gn:admin3_code":"48035.0",
    "gn:asciiname":"Ostina",
    "gn:country_code":"IT",
    "gn:dem":263,
    "gn:feature_class":"P",
    "gn:feature_code":"PPL",
    "gn:name":"Ostina",
    "gn:population":32,
    "gn:timezone":"Europe/Rome",
    "iso:country":"IT",
    "wof:name":"Ostina",
    "wof:placetype":"locality",
    "wof:population":32
},
  "geometry": {"coordinates":[11.51336,43.65389],"type":"Point"}
}