{
  "type": "Feature",
  "properties": {
    "gn:gn_country":"IT",
    "iso:country":"IT",
    "name:eng_x_preferred":[
        "Molo"
    ],
    "name:ita_x_preferred":[
        "Molo"
    ],
    "name:nld_x_preferred":[
        "Molo"
    ],
    "qs_pg:aaroncc":"IT",
    "qs_pg:gn_country":"IT",
    "qs_pg:name":"Molo",
    "qs_pg:name_adm0":"Italia",
    "qs_pg:name_adm1":"Liguria",
    "qs_pg:photos":102,
    "qs_pg:photos_1k":21,
    "qs_pg:photos_9k":1,
    "qs_pg:photos_9r":3,
    "qs_pg:photos_all":102,
    "qs_pg:photos_sr":3,
    "qs_pg:pop_sr":0,
    "qs_pg:qs_pg_placetype":"locality",
    "qs_pg:qs_pg_placetype_gp":"Town",
    "qs_pg:woe_adm0":23424853,
    "woe:adm0_id":23424853,
    "woe:name_adm0":"Italia",
    "woe:name_adm1":"Liguria",
    "woe:placetype":"Town",
    "wof:name":"Molo",
    "wof:placetype":"locality"
},
  "geometry": {"coordinates":[8.930983,44.404272],"type":"Point"}
}