{
  "type": "Feature",
  "properties": {
    "gn:admin1_code":"7",
    "gn:admin2_code":"FR",
    "gn:admin3_code":"60004.0",
    "gn:asciiname":"Serre di Conca",
    "gn:country_code":"IT",
    "gn:dem":430,
    "gn:feature_class":"P",
    "gn:feature_code":"PPL",
    "gn:name":"Serre di Conca",
    "gn:population":76,
    "gn:timezone":"Europe/Rome",
    "iso:country":"IT",
    "wof:name":"Serre di Conca",
    "wof:placetype":"locality",
    "wof:population":76
},
  "geometry": {"coordinates":[13.75158,41.67265],"type":"Point"}
}