{
  "type": "Feature",
  "properties": {
    "gn:admin1_code":"5.0",
    "gn:admin2_code":"RN",
    "gn:admin3_code":"99014.0",
    "gn:asciiname":"Ghetto Tamagnino",
    "gn:country_code":"IT",
    "gn:dem":40,
    "gn:feature_class":"P",
    "gn:feature_code":"PPL",
    "gn:name":"Ghetto Tamagnino",
    "gn:population":45,
    "gn:timezone":"Europe/Rome",
    "iso:country":"IT",
    "wof:name":"Ghetto Tamagnino",
    "wof:placetype":"locality",
    "wof:population":45
},
  "geometry": {"coordinates":[12.56664,43.99307],"type":"Point"}
}