{
  "type": "Feature",
  "properties": {
    "gn:admin1_code":"20.0",
    "gn:admin2_code":"VI",
    "gn:admin3_code":"24123.0",
    "gn:asciiname":"Pederiva",
    "gn:country_code":"IT",
    "gn:dem":46,
    "gn:feature_class":"P",
    "gn:feature_code":"PPLA3",
    "gn:name":"Pederiva",
    "gn:population":771,
    "gn:timezone":"Europe/Rome",
    "iso:country":"IT",
    "wof:name":"Pederiva",
    "wof:placetype":"locality",
    "wof:population":771
},
  "geometry": {"coordinates":[11.46568,45.42254000000001],"type":"Point"}
}