{
  "type": "Feature",
  "properties": {
    "gn:admin1_code":"12",
    "gn:admin2_code":"AL",
    "gn:admin3_code":"6067.0",
    "gn:asciiname":"La Gioia",
    "gn:country_code":"IT",
    "gn:dem":1087,
    "gn:feature_class":"P",
    "gn:feature_code":"PPL",
    "gn:name":"La Gioia",
    "gn:population":41,
    "gn:timezone":"Europe/Rome",
    "iso:country":"IT",
    "wof:name":"La Gioia",
    "wof:placetype":"locality",
    "wof:population":41
},
  "geometry": {"coordinates":[9.15029,44.72295],"type":"Point"}
}