{
  "type": "Feature",
  "properties": {
    "gn:admin1_code":"18",
    "gn:admin2_code":"PG",
    "gn:admin3_code":"54018.0",
    "gn:asciiname":"Lie",
    "gn:country_code":"IT",
    "gn:dem":419,
    "gn:feature_class":"P",
    "gn:feature_code":"PPL",
    "gn:name":"Li\u00e8",
    "gn:population":32,
    "gn:timezone":"Europe/Rome",
    "iso:country":"IT",
    "name:und_x_variant":[
        "Li\u00e8"
    ],
    "wof:name":"Lie",
    "wof:placetype":"locality",
    "wof:population":32
},
  "geometry": {"coordinates":[12.75724,42.98865],"type":"Point"}
}