{
  "type": "Feature",
  "properties": {
    "gn:admin1_code":"8",
    "gn:admin2_code":"IM",
    "gn:admin3_code":"8046.0",
    "gn:asciiname":"Case Rosse",
    "gn:country_code":"IT",
    "gn:dem":745,
    "gn:feature_class":"P",
    "gn:feature_code":"PPL",
    "gn:name":"Case Rosse",
    "gn:population":100,
    "gn:timezone":"Europe/Rome",
    "iso:country":"IT",
    "wof:name":"Case Rosse",
    "wof:placetype":"locality",
    "wof:population":100
},
  "geometry": {"coordinates":[7.86249,44.07744],"type":"Point"}
}