{
  "type": "Feature",
  "properties": {
    "gn:admin1_code":"16.0",
    "gn:admin2_code":"SI",
    "gn:admin3_code":"52034.0",
    "gn:asciiname":"Valacchio",
    "gn:country_code":"IT",
    "gn:dem":230,
    "gn:elevation":"229.0",
    "gn:feature_class":"P",
    "gn:feature_code":"PPL",
    "gn:name":"Valacchio",
    "gn:population":9,
    "gn:timezone":"Europe/Rome",
    "iso:country":"IT",
    "wof:name":"Valacchio",
    "wof:placetype":"locality",
    "wof:population":9
},
  "geometry": {"coordinates":[11.23239,43.29962],"type":"Point"}
}