{
  "type": "Feature",
  "properties": {
    "gn:admin1_code":"9",
    "gn:admin2_code":"BS",
    "gn:admin3_code":"17115.0",
    "gn:asciiname":"Posico",
    "gn:country_code":"IT",
    "gn:dem":652,
    "gn:feature_class":"P",
    "gn:feature_code":"PPL",
    "gn:name":"Posico",
    "gn:population":125,
    "gn:timezone":"Europe/Rome",
    "iso:country":"IT",
    "wof:name":"Posico",
    "wof:placetype":"locality",
    "wof:population":125
},
  "geometry": {"coordinates":[10.33038,45.70538],"type":"Point"}
}