{
  "type": "Feature",
  "properties": {
    "gn:admin1_code":"1",
    "gn:admin2_code":"TE",
    "gn:admin3_code":"67021.0",
    "gn:asciiname":"Frattari",
    "gn:country_code":"IT",
    "gn:dem":93,
    "gn:feature_class":"P",
    "gn:feature_code":"PPL",
    "gn:name":"Frattari",
    "gn:population":154,
    "gn:timezone":"Europe/Rome",
    "iso:country":"IT",
    "wof:name":"Frattari",
    "wof:placetype":"locality",
    "wof:population":154
},
  "geometry": {"coordinates":[13.83467,42.81358],"type":"Point"}
}