{
  "type": "Feature",
  "properties": {
    "gn:admin1_code":"9.0",
    "gn:admin2_code":"BG",
    "gn:admin3_code":"16176.0",
    "gn:asciiname":"Marzole",
    "gn:country_code":"IT",
    "gn:dem":242,
    "gn:feature_class":"P",
    "gn:feature_code":"PPLL",
    "gn:name":"Marzole",
    "gn:population":1,
    "gn:timezone":"Europe/Rome",
    "iso:country":"IT",
    "wof:name":"Marzole",
    "wof:placetype":"locality",
    "wof:population":1
},
  "geometry": {"coordinates":[9.55871,45.69801],"type":"Point"}
}