{
  "type": "Feature",
  "properties": {
    "gn:admin1_code":"1",
    "gn:admin2_code":"CH",
    "gn:admin3_code":"69005.0",
    "gn:asciiname":"Saletti II",
    "gn:country_code":"IT",
    "gn:dem":58,
    "gn:feature_class":"P",
    "gn:feature_code":"PPL",
    "gn:name":"Saletti II",
    "gn:population":161,
    "gn:timezone":"Europe/Rome",
    "iso:country":"IT",
    "wof:name":"Saletti II",
    "wof:placetype":"locality",
    "wof:population":161
},
  "geometry": {"coordinates":[14.44229,42.14491],"type":"Point"}
}