{
  "type": "Feature",
  "properties": {
    "gn:admin1_code":"20",
    "gn:admin2_code":"VR",
    "gn:admin3_code":"23067.0",
    "gn:asciiname":"Squarantello",
    "gn:country_code":"IT",
    "gn:dem":992,
    "gn:feature_class":"P",
    "gn:feature_code":"PPLL",
    "gn:name":"Squarantello",
    "gn:population":10,
    "gn:timezone":"Europe/Rome",
    "iso:country":"IT",
    "wof:name":"Squarantello",
    "wof:placetype":"locality",
    "wof:population":10
},
  "geometry": {"coordinates":[11.0618,45.63703],"type":"Point"}
}