{
  "type": "Feature",
  "properties": {
    "gn:admin1_code":"6.0",
    "gn:admin2_code":"UD",
    "gn:admin3_code":"30101.0",
    "gn:asciiname":"Zona Industriale Cascina Rinaldi",
    "gn:country_code":"IT",
    "gn:dem":62,
    "gn:feature_class":"P",
    "gn:feature_code":"PPL",
    "gn:name":"Zona Industriale Cascina Rinaldi",
    "gn:population":0,
    "gn:timezone":"Europe/Rome",
    "iso:country":"IT",
    "wof:name":"Zona Industriale Cascina Rinaldi",
    "wof:placetype":"locality"
},
  "geometry": {"coordinates":[13.42082,45.97365],"type":"Point"}
}