{
  "type": "Feature",
  "properties": {
    "gn:admin1_code":"20.0",
    "gn:admin2_code":"TV",
    "gn:admin3_code":"26076.0",
    "gn:asciiname":"San Vendemiano-Fossamerlo",
    "gn:country_code":"IT",
    "gn:dem":54,
    "gn:elevation":"51.0",
    "gn:feature_class":"P",
    "gn:feature_code":"PPLA3",
    "gn:name":"San Vendemiano-Fossamerlo",
    "gn:population":6034,
    "gn:timezone":"Europe/Rome",
    "iso:country":"IT",
    "wof:name":"San Vendemiano-Fossamerlo",
    "wof:placetype":"locality",
    "wof:population":6034
},
  "geometry": {"coordinates":[12.32992,45.8918],"type":"Point"}
}