{
  "type": "Feature",
  "properties": {
    "gn:admin1_code":"12.0",
    "gn:admin2_code":"AL",
    "gn:admin3_code":"6001.0",
    "gn:asciiname":"Bagnoli",
    "gn:country_code":"IT",
    "gn:dem":244,
    "gn:feature_class":"P",
    "gn:feature_code":"PPL",
    "gn:name":"Bagnoli",
    "gn:population":20,
    "gn:timezone":"Europe/Rome",
    "iso:country":"IT",
    "wof:name":"Bagnoli",
    "wof:placetype":"locality",
    "wof:population":20
},
  "geometry": {"coordinates":[8.4774,44.66128],"type":"Point"}
}