{
  "type": "Feature",
  "properties": {
    "gn:admin1_code":"18",
    "gn:admin2_code":"PG",
    "gn:admin3_code":"54022.0",
    "gn:asciiname":"Case Bacci",
    "gn:country_code":"IT",
    "gn:dem":375,
    "gn:feature_class":"P",
    "gn:feature_code":"PPL",
    "gn:name":"Case Bacci",
    "gn:population":33,
    "gn:timezone":"Europe/Rome",
    "iso:country":"IT",
    "wof:name":"Case Bacci",
    "wof:placetype":"locality",
    "wof:population":33
},
  "geometry": {"coordinates":[12.51431,42.89783],"type":"Point"}
}