{
  "type": "Feature",
  "properties": {
    "gn:admin1_code":"5",
    "gn:admin2_code":"MO",
    "gn:admin3_code":"36027.0",
    "gn:asciiname":"Case Ponte Fossa",
    "gn:country_code":"IT",
    "gn:dem":21,
    "gn:feature_class":"P",
    "gn:feature_code":"PPL",
    "gn:name":"Case Ponte Fossa",
    "gn:population":117,
    "gn:timezone":"Europe/Rome",
    "iso:country":"IT",
    "wof:name":"Case Ponte Fossa",
    "wof:placetype":"locality",
    "wof:population":117
},
  "geometry": {"coordinates":[11.05427,44.69525],"type":"Point"}
}