{
  "type": "Feature",
  "properties": {
    "gn:admin1_code":"8",
    "gn:admin2_code":"SV",
    "gn:admin3_code":"9008.0",
    "gn:asciiname":"Bergalla",
    "gn:country_code":"IT",
    "gn:dem":415,
    "gn:feature_class":"P",
    "gn:feature_code":"PPL",
    "gn:name":"Bergalla",
    "gn:population":60,
    "gn:timezone":"Europe/Rome",
    "iso:country":"IT",
    "wof:name":"Bergalla",
    "wof:placetype":"locality",
    "wof:population":60
},
  "geometry": {"coordinates":[8.15763,44.12136],"type":"Point"}
}