{
  "type": "Feature",
  "properties": {
    "gn:admin1_code":"10.0",
    "gn:admin2_code":"MC",
    "gn:admin3_code":"43047.0",
    "gn:asciiname":"Stigliano Piede",
    "gn:country_code":"IT",
    "gn:dem":487,
    "gn:feature_class":"P",
    "gn:feature_code":"PPL",
    "gn:name":"Stigliano Piede",
    "gn:population":53,
    "gn:timezone":"Europe/Rome",
    "iso:country":"IT",
    "wof:name":"Stigliano Piede",
    "wof:placetype":"locality",
    "wof:population":53
},
  "geometry": {"coordinates":[13.14022,43.25817],"type":"Point"}
}