{
  "type": "Feature",
  "properties": {
    "gn:admin1_code":"12.0",
    "gn:admin2_code":"VB",
    "gn:admin3_code":"103057.0",
    "gn:asciiname":"Alpe Lagarasc",
    "gn:cc2":"IT",
    "gn:country_code":"IT",
    "gn:dem":726,
    "gn:feature_class":"P",
    "gn:feature_code":"PPL",
    "gn:name":"Alpe Lagarasc",
    "gn:population":0,
    "gn:timezone":"Europe/Rome",
    "iso:country":"IT",
    "name:und_x_variant":[
        "Alpe Lagarsc",
        "Alpe Lagarasc"
    ],
    "wof:name":"Alpe Lagarasc",
    "wof:placetype":"locality"
},
  "geometry": {"coordinates":[8.33333,46.01667],"type":"Point"}
}