{
  "type": "Feature",
  "properties": {
    "gn:admin1_code":"17.0",
    "gn:admin2_code":"BZ",
    "gn:admin3_code":"21082.0",
    "gn:asciiname":"Zona Artigianale Alfur",
    "gn:country_code":"IT",
    "gn:dem":1077,
    "gn:feature_class":"P",
    "gn:feature_code":"PPLL",
    "gn:name":"Zona Artigianale Alfur",
    "gn:population":0,
    "gn:timezone":"Europe/Rome",
    "iso:country":"IT",
    "wof:name":"Zona Artigianale Alfur",
    "wof:placetype":"locality"
},
  "geometry": {"coordinates":[11.89135,46.69053],"type":"Point"}
}