{
  "type": "Feature",
  "properties": {
    "gn:admin1_code":"15.0",
    "gn:admin2_code":"ME",
    "gn:admin3_code":"83023.0",
    "gn:asciiname":"Fantina",
    "gn:country_code":"IT",
    "gn:dem":439,
    "gn:feature_class":"P",
    "gn:feature_code":"PPL",
    "gn:name":"Fantina",
    "gn:population":78,
    "gn:timezone":"Europe/Rome",
    "iso:country":"IT",
    "wof:name":"Fantina",
    "wof:placetype":"locality",
    "wof:population":78
},
  "geometry": {"coordinates":[15.17675,38.02596],"type":"Point"}
}