{
  "type": "Feature",
  "properties": {
    "gn:admin1_code":"20.0",
    "gn:admin2_code":"VE",
    "gn:admin3_code":"27008.0",
    "gn:asciiname":"Sant'Anna",
    "gn:country_code":"IT",
    "gn:dem":-1,
    "gn:elevation":"2.0",
    "gn:feature_class":"P",
    "gn:feature_code":"PPL",
    "gn:name":"Sant'Anna",
    "gn:population":3062,
    "gn:timezone":"Europe/Rome",
    "iso:country":"IT",
    "name:bre_x_preferred":[
        "Sant'Anna"
    ],
    "name:ceb_x_preferred":[
        "Sant'Anna"
    ],
    "name:deu_x_preferred":[
        "Sant\u2019Anna"
    ],
    "name:epo_x_preferred":[
        "Sant'Anna"
    ],
    "name:ita_x_preferred":[
        "Sant'Anna"
    ],
    "name:nld_x_preferred":[
        "Sant'Anna"
    ],
    "name:por_x_preferred":[
        "Sant'Anna"
    ],
    "name:srp_x_preferred":[
        "Sant'Ana"
    ],
    "name:swe_x_preferred":[
        "Sant'Anna"
    ],
    "wof:name":"Sant'Anna",
    "wof:placetype":"locality",
    "wof:population":3062
},
  "geometry": {"coordinates":[12.27355,45.1661],"type":"Point"}
}