{
  "type": "Feature",
  "properties": {
    "gn:admin1_code":"5.0",
    "gn:admin2_code":"RA",
    "gn:admin3_code":"39014.0",
    "gn:asciiname":"San Marco",
    "gn:country_code":"IT",
    "gn:dem":2,
    "gn:elevation":"5.0",
    "gn:feature_class":"P",
    "gn:feature_code":"PPL",
    "gn:name":"San Marco",
    "gn:population":232,
    "gn:timezone":"Europe/Rome",
    "iso:country":"IT",
    "wof:name":"San Marco",
    "wof:placetype":"locality",
    "wof:population":232
},
  "geometry": {"coordinates":[12.13936,44.37131],"type":"Point"}
}