{
  "type": "Feature",
  "properties": {
    "gn:admin1_code":"15",
    "gn:admin2_code":"ME",
    "gn:admin3_code":"83088.0",
    "gn:asciiname":"Russo",
    "gn:country_code":"IT",
    "gn:dem":271,
    "gn:feature_class":"P",
    "gn:feature_code":"PPL",
    "gn:name":"Russo",
    "gn:population":28,
    "gn:timezone":"Europe/Rome",
    "iso:country":"IT",
    "name:ces_x_preferred":[
        "Russo"
    ],
    "name:deu_x_preferred":[
        "Russo"
    ],
    "name:fra_x_preferred":[
        "Russo"
    ],
    "name:ita_x_preferred":[
        "Russo"
    ],
    "name:jpn_x_preferred":[
        "\u30eb\u30c3\u30bd"
    ],
    "name:ron_x_preferred":[
        "Russo"
    ],
    "name:rus_x_preferred":[
        "\u0420\u0443\u0441\u0441\u043e"
    ],
    "name:slv_x_preferred":[
        "Russo"
    ],
    "name:ukr_x_preferred":[
        "\u0420\u0443\u0441\u0441\u043e"
    ],
    "wof:name":"Russo",
    "wof:placetype":"locality",
    "wof:population":28
},
  "geometry": {"coordinates":[14.88057,38.13479],"type":"Point"}
}