{
  "type": "Feature",
  "properties": {
    "gn:admin1_code":"16.0",
    "gn:admin2_code":"PO",
    "gn:admin3_code":"100001.0",
    "gn:asciiname":"La Villa",
    "gn:country_code":"IT",
    "gn:dem":363,
    "gn:elevation":"363.0",
    "gn:feature_class":"P",
    "gn:feature_code":"PPL",
    "gn:name":"La Villa",
    "gn:population":29,
    "gn:timezone":"Europe/Rome",
    "iso:country":"IT",
    "name:ceb_x_preferred":[
        "La Villa"
    ],
    "name:fra_x_preferred":[
        "La Villa"
    ],
    "name:ita_x_preferred":[
        "La Villa"
    ],
    "name:nld_x_preferred":[
        "La Villa"
    ],
    "name:srp_x_preferred":[
        "La Villa"
    ],
    "name:swe_x_preferred":[
        "La Villa"
    ],
    "wof:name":"La Villa",
    "wof:placetype":"locality",
    "wof:population":29
},
  "geometry": {"coordinates":[11.11739,44.03225],"type":"Point"}
}