{
  "type": "Feature",
  "properties": {
    "gn:gn_country":"IT",
    "gn:gn_fcode":"PPL",
    "gn:gn_pop":0,
    "gn:population":1098,
    "iso:country":"IT",
    "name:cat_x_preferred":[
        "Brucoli"
    ],
    "name:ceb_x_preferred":[
        "Brucoli"
    ],
    "name:ces_x_preferred":[
        "Brucoli"
    ],
    "name:dan_x_preferred":[
        "Brucoli"
    ],
    "name:deu_x_preferred":[
        "Brucoli"
    ],
    "name:eng_x_preferred":[
        "Brucoli"
    ],
    "name:eus_x_preferred":[
        "Brucoli"
    ],
    "name:fin_x_preferred":[
        "Brucoli"
    ],
    "name:fra_x_preferred":[
        "Brucoli"
    ],
    "name:hun_x_preferred":[
        "Brucoli"
    ],
    "name:ind_x_preferred":[
        "Brucoli"
    ],
    "name:ita_x_preferred":[
        "Brucoli"
    ],
    "name:nld_x_preferred":[
        "Brucoli"
    ],
    "name:nno_x_preferred":[
        "Brucoli"
    ],
    "name:nob_x_preferred":[
        "Brucoli"
    ],
    "name:oci_x_preferred":[
        "Brucoli"
    ],
    "name:pol_x_preferred":[
        "Brucoli"
    ],
    "name:por_x_preferred":[
        "Brucoli"
    ],
    "name:ron_x_preferred":[
        "Brucoli"
    ],
    "name:scn_x_preferred":[
        "Bruculi"
    ],
    "name:slk_x_preferred":[
        "Brucoli"
    ],
    "name:slv_x_preferred":[
        "Brucoli"
    ],
    "name:spa_x_preferred":[
        "Brucoli"
    ],
    "name:srp_x_preferred":[
        "Brucoli"
    ],
    "name:swe_x_preferred":[
        "Brucoli"
    ],
    "name:tgl_x_preferred":[
        "Brucoli"
    ],
    "name:tur_x_preferred":[
        "Brucoli"
    ],
    "name:unk_x_variant":[
        "Brugoli"
    ],
    "name:war_x_preferred":[
        "Brucoli"
    ],
    "qs_pg:aaroncc":"IT",
    "qs_pg:gn_country":"IT",
    "qs_pg:gn_fcode":"PPL",
    "qs_pg:gn_pop":0,
    "qs_pg:name":"Brucoli",
    "qs_pg:name_adm0":"Italia",
    "qs_pg:name_adm1":"Sicilia",
    "qs_pg:photos":98,
    "qs_pg:photos_1k":20,
    "qs_pg:photos_9k":1,
    "qs_pg:photos_9r":3,
    "qs_pg:photos_all":98,
    "qs_pg:photos_sr":3,
    "qs_pg:pop_sr":0,
    "qs_pg:qs_pg_placetype":"locality",
    "qs_pg:qs_pg_placetype_gp":"Town",
    "qs_pg:woe_adm0":23424853,
    "woe:adm0_id":23424853,
    "woe:name_adm0":"Italia",
    "woe:name_adm1":"Sicilia",
    "woe:placetype":"Town",
    "wof:name":"Brucoli",
    "wof:placetype":"locality",
    "wof:population":1098
},
  "geometry": {"coordinates":[15.18333,37.28333],"type":"Point"}
}