{
  "type": "Feature",
  "properties": {
    "gn:admin1_code":"16",
    "gn:admin2_code":"LU",
    "gn:admin3_code":"46003.0",
    "gn:asciiname":"Stefanetti",
    "gn:country_code":"IT",
    "gn:dem":271,
    "gn:feature_class":"P",
    "gn:feature_code":"PPL",
    "gn:name":"Stefanetti",
    "gn:population":47,
    "gn:timezone":"Europe/Rome",
    "iso:country":"IT",
    "wof:name":"Stefanetti",
    "wof:placetype":"locality",
    "wof:population":47
},
  "geometry": {"coordinates":[10.46573,44.07718],"type":"Point"}
}