{
  "type": "Feature",
  "properties": {
    "gn:admin1_code":"5",
    "gn:admin2_code":"MO",
    "gn:admin3_code":"36005.0",
    "gn:asciiname":"Lancellotti",
    "gn:country_code":"IT",
    "gn:dem":27,
    "gn:feature_class":"P",
    "gn:feature_code":"PPL",
    "gn:name":"Lancellotti",
    "gn:population":64,
    "gn:timezone":"Europe/Rome",
    "iso:country":"IT",
    "wof:name":"Lancellotti",
    "wof:placetype":"locality",
    "wof:population":64
},
  "geometry": {"coordinates":[10.86206,44.74805],"type":"Point"}
}