{
  "type": "Feature",
  "properties": {
    "gn:admin1_code":"8",
    "gn:admin2_code":"GE",
    "gn:admin3_code":"10041.0",
    "gn:asciiname":"Roccatagliata",
    "gn:country_code":"IT",
    "gn:dem":582,
    "gn:feature_class":"P",
    "gn:feature_code":"PPL",
    "gn:name":"Roccatagliata",
    "gn:population":53,
    "gn:timezone":"Europe/Rome",
    "iso:country":"IT",
    "wof:name":"Roccatagliata",
    "wof:placetype":"locality",
    "wof:population":53
},
  "geometry": {"coordinates":[9.19911,44.47232],"type":"Point"}
}