{
  "type": "Feature",
  "properties": {
    "gn:admin1_code":"1.0",
    "gn:admin2_code":"CH",
    "gn:admin3_code":"69084.0",
    "gn:asciiname":"Borgata Fattore I",
    "gn:country_code":"IT",
    "gn:dem":129,
    "gn:feature_class":"P",
    "gn:feature_code":"PPL",
    "gn:name":"Borgata Fattore I",
    "gn:population":25,
    "gn:timezone":"Europe/Rome",
    "iso:country":"IT",
    "wof:name":"Borgata Fattore I",
    "wof:placetype":"locality",
    "wof:population":25
},
  "geometry": {"coordinates":[14.45952,42.21341],"type":"Point"}
}