{
  "type": "Feature",
  "properties": {
    "gn:admin1_code":"14.0",
    "gn:admin2_code":"SU",
    "gn:admin3_code":"111011.0",
    "gn:asciiname":"L'Annunziata",
    "gn:country_code":"IT",
    "gn:dem":62,
    "gn:feature_class":"P",
    "gn:feature_code":"PPL",
    "gn:name":"L'Annunziata",
    "gn:population":119,
    "gn:timezone":"Europe/Rome",
    "iso:country":"IT",
    "wof:name":"L'Annunziata",
    "wof:placetype":"locality",
    "wof:population":119
},
  "geometry": {"coordinates":[9.50528,39.30222],"type":"Point"}
}