{
  "type": "Feature",
  "properties": {
    "gn:admin1_code":"12",
    "gn:admin2_code":"TO",
    "gn:admin3_code":"1270.0",
    "gn:asciiname":"Traduerivi",
    "gn:country_code":"IT",
    "gn:dem":486,
    "gn:feature_class":"P",
    "gn:feature_code":"PPL",
    "gn:name":"Traduerivi",
    "gn:population":109,
    "gn:timezone":"Europe/Rome",
    "iso:country":"IT",
    "wof:name":"Traduerivi",
    "wof:placetype":"locality",
    "wof:population":109
},
  "geometry": {"coordinates":[7.09097,45.13198],"type":"Point"}
}