{
  "type": "Feature",
  "properties": {
    "gn:admin1_code":"5.0",
    "gn:admin2_code":"RN",
    "gn:admin3_code":"99014.0",
    "gn:asciiname":"Ghetto Casale",
    "gn:country_code":"IT",
    "gn:dem":22,
    "gn:feature_class":"P",
    "gn:feature_code":"PPL",
    "gn:name":"Ghetto Casale",
    "gn:population":76,
    "gn:timezone":"Europe/Rome",
    "iso:country":"IT",
    "wof:name":"Ghetto Casale",
    "wof:placetype":"locality",
    "wof:population":76
},
  "geometry": {"coordinates":[12.56893,44.01736],"type":"Point"}
}