{
  "type": "Feature",
  "properties": {
    "gn:admin1_code":"13",
    "gn:admin2_code":"LE",
    "gn:admin3_code":"75059.0",
    "gn:asciiname":"Carbone",
    "gn:country_code":"IT",
    "gn:dem":58,
    "gn:feature_class":"P",
    "gn:feature_code":"PPLL",
    "gn:name":"Carbone",
    "gn:population":6,
    "gn:timezone":"Europe/Rome",
    "iso:country":"IT",
    "wof:name":"Carbone",
    "wof:placetype":"locality",
    "wof:population":6
},
  "geometry": {"coordinates":[18.08856,40.04881],"type":"Point"}
}