{
  "type": "Feature",
  "properties": {
    "gn:admin1_code":"20.0",
    "gn:admin2_code":"VE",
    "gn:admin3_code":"27019.0",
    "gn:asciiname":"Ca' Pirami",
    "gn:cc2":"IT",
    "gn:country_code":"IT",
    "gn:dem":2,
    "gn:feature_class":"P",
    "gn:feature_code":"PPL",
    "gn:name":"Ca' Pirami",
    "gn:population":216,
    "gn:timezone":"Europe/Rome",
    "iso:country":"IT",
    "name:und_x_variant":[
        "Casa Pirami",
        "Ca Pirami"
    ],
    "wof:name":"Ca' Pirami",
    "wof:placetype":"locality",
    "wof:population":216
},
  "geometry": {"coordinates":[12.64222,45.55964],"type":"Point"}
}