{
  "type": "Feature",
  "properties": {
    "gn:admin1_code":"20",
    "gn:admin2_code":"BL",
    "gn:admin3_code":"25034.0",
    "gn:asciiname":"Conzago",
    "gn:country_code":"IT",
    "gn:dem":387,
    "gn:feature_class":"P",
    "gn:feature_code":"PPL",
    "gn:name":"Conzago",
    "gn:population":173,
    "gn:timezone":"Europe/Rome",
    "iso:country":"IT",
    "wof:name":"Conzago",
    "wof:placetype":"locality",
    "wof:population":173
},
  "geometry": {"coordinates":[12.07897,46.05144],"type":"Point"}
}