{
  "type": "Feature",
  "properties": {
    "gn:admin1_code":"20",
    "gn:admin2_code":"TV",
    "gn:admin3_code":"26016.0",
    "gn:asciiname":"Carbonere Nuove",
    "gn:country_code":"IT",
    "gn:dem":6,
    "gn:feature_class":"P",
    "gn:feature_code":"PPL",
    "gn:name":"Carbonere Nuove",
    "gn:population":30,
    "gn:timezone":"Europe/Rome",
    "iso:country":"IT",
    "wof:name":"Carbonere Nuove",
    "wof:placetype":"locality",
    "wof:population":30
},
  "geometry": {"coordinates":[12.54952,45.74574000000001],"type":"Point"}
}