{
  "type": "Feature",
  "properties": {
    "gn:admin1_code":"14.0",
    "gn:admin2_code":"SS",
    "gn:admin3_code":"90091.0",
    "gn:asciiname":"Berruiles",
    "gn:country_code":"IT",
    "gn:dem":67,
    "gn:elevation":"71.0",
    "gn:feature_class":"P",
    "gn:feature_code":"PPLL",
    "gn:name":"Berruiles",
    "gn:population":219,
    "gn:timezone":"Europe/Rome",
    "iso:country":"IT",
    "wof:name":"Berruiles",
    "wof:placetype":"locality",
    "wof:population":219
},
  "geometry": {"coordinates":[9.66292,40.72723],"type":"Point"}
}