{
  "type": "Feature",
  "properties": {
    "iso:country":"IT",
    "wof:name":"Montalbino",
    "wof:placetype":"neighbourhood"
},
  "geometry": {"coordinates":[9.19089079537413,45.49827526273561],"type":"Point"}
}