{
  "type": "Feature",
  "properties": {
    "gn:country":"IT",
    "gn:fcode":"PPL",
    "gn:population":0,
    "iso:country":"IT",
    "name:cat_x_preferred":[
        "Prodo"
    ],
    "name:ceb_x_preferred":[
        "Prodo"
    ],
    "name:ces_x_preferred":[
        "Prodo"
    ],
    "name:dan_x_preferred":[
        "Prodo"
    ],
    "name:eng_x_preferred":[
        "Prodo"
    ],
    "name:eus_x_preferred":[
        "Prodo"
    ],
    "name:fin_x_preferred":[
        "Prodo"
    ],
    "name:fra_x_preferred":[
        "Prodo"
    ],
    "name:hun_x_preferred":[
        "Prodo"
    ],
    "name:ind_x_preferred":[
        "Prodo"
    ],
    "name:ita_x_preferred":[
        "Prodo"
    ],
    "name:nld_x_preferred":[
        "Prodo"
    ],
    "name:nno_x_preferred":[
        "Prodo"
    ],
    "name:nob_x_preferred":[
        "Prodo"
    ],
    "name:oci_x_preferred":[
        "Prodo"
    ],
    "name:pol_x_preferred":[
        "Prodo"
    ],
    "name:por_x_preferred":[
        "Prodo"
    ],
    "name:ron_x_preferred":[
        "Prodo"
    ],
    "name:slk_x_preferred":[
        "Prodo"
    ],
    "name:slv_x_preferred":[
        "Prodo"
    ],
    "name:spa_x_preferred":[
        "Prodo"
    ],
    "name:srp_x_preferred":[
        "Prodo"
    ],
    "name:swe_x_preferred":[
        "Prodo"
    ],
    "name:tgl_x_preferred":[
        "Prodo"
    ],
    "name:tur_x_preferred":[
        "Prodo"
    ],
    "name:war_x_preferred":[
        "Prodo"
    ],
    "qs_pg:aaroncc":"IT",
    "qs_pg:gn_country":"IT",
    "qs_pg:gn_fcode":"PPL",
    "qs_pg:gn_pop":0,
    "qs_pg:name":"Prodo",
    "qs_pg:name_adm0":"Italia",
    "qs_pg:name_adm1":"Umbria",
    "qs_pg:photos":29,
    "qs_pg:photos_1k":6,
    "qs_pg:photos_9k":1,
    "qs_pg:photos_9r":2,
    "qs_pg:photos_all":29,
    "qs_pg:photos_sr":2,
    "qs_pg:pop_sr":0,
    "qs_pg:qs_pg_placetype":"locality",
    "qs_pg:qs_pg_placetype_gp":"Town",
    "qs_pg:woe_adm0":23424853,
    "woe:adm0_id":23424853,
    "woe:name_adm0":"Italia",
    "woe:name_adm1":"Umbria",
    "woe:placetype":"Town",
    "wof:name":"Prodo",
    "wof:placetype":"locality",
    "wof:population":49
},
  "geometry": {"coordinates":[12.23333,42.76667],"type":"Point"}
}