{
  "type": "Feature",
  "properties": {
    "gn:admin1_code":"3",
    "gn:admin2_code":"RC",
    "gn:admin3_code":"80063.0",
    "gn:asciiname":"Amendolea",
    "gn:country_code":"IT",
    "gn:dem":288,
    "gn:feature_class":"P",
    "gn:feature_code":"PPL",
    "gn:name":"Amendolea",
    "gn:population":92,
    "gn:timezone":"Europe/Rome",
    "iso:country":"IT",
    "name:hun_x_preferred":[
        "Amendolea"
    ],
    "name:ita_x_preferred":[
        "Fiumara Amendolea"
    ],
    "name:zho_x_preferred":[
        "\u963f\u9580\u591a\u840a\u4e9e\u6cb3"
    ],
    "wof:name":"Amendolea",
    "wof:placetype":"locality",
    "wof:population":92
},
  "geometry": {"coordinates":[15.69511,38.04282],"type":"Point"}
}