{
  "type": "Feature",
  "properties": {
    "gn:admin1_code":"9",
    "gn:admin2_code":"PV",
    "gn:admin3_code":"18177.0",
    "gn:asciiname":"Pescatora",
    "gn:country_code":"IT",
    "gn:dem":108,
    "gn:feature_class":"P",
    "gn:feature_code":"PPL",
    "gn:name":"Pescatora",
    "gn:population":87,
    "gn:timezone":"Europe/Rome",
    "iso:country":"IT",
    "wof:name":"Pescatora",
    "wof:placetype":"locality",
    "wof:population":87
},
  "geometry": {"coordinates":[8.84904,45.33868],"type":"Point"}
}