{
  "type": "Feature",
  "properties": {
    "gn:admin1_code":"5",
    "gn:admin2_code":"PR",
    "gn:admin3_code":"34012.0",
    "gn:asciiname":"Mossale",
    "gn:country_code":"IT",
    "gn:dem":591,
    "gn:feature_class":"P",
    "gn:feature_code":"PPL",
    "gn:name":"Mossale",
    "gn:population":78,
    "gn:timezone":"Europe/Rome",
    "iso:country":"IT",
    "wof:name":"Mossale",
    "wof:placetype":"locality",
    "wof:population":78
},
  "geometry": {"coordinates":[10.15534,44.54343],"type":"Point"}
}