{
  "type": "Feature",
  "properties": {
    "gn:admin1_code":"1.0",
    "gn:admin2_code":"CH",
    "gn:admin3_code":"69095.0",
    "gn:asciiname":"Fallascoso",
    "gn:country_code":"IT",
    "gn:dem":903,
    "gn:elevation":"923.0",
    "gn:feature_class":"P",
    "gn:feature_code":"PPL",
    "gn:name":"Fallascoso",
    "gn:population":83,
    "gn:timezone":"Europe/Rome",
    "iso:country":"IT",
    "name:fas_x_preferred":[
        "\u0641\u0627\u0644\u0627\u0633\u06a9\u0648\u0633\u0648"
    ],
    "name:ita_x_preferred":[
        "Fallascoso"
    ],
    "name:srp_x_preferred":[
        "\u0424\u0430\u043b\u0430\u0437\u043a\u043e\u0437\u043e"
    ],
    "name:urd_x_preferred":[
        "\u0641\u0627\u0644\u0627\u0633\u06a9\u0648\u0633\u0648"
    ],
    "wof:name":"Fallascoso",
    "wof:placetype":"locality",
    "wof:population":83
},
  "geometry": {"coordinates":[14.24204,42.0044],"type":"Point"}
}