{
  "type": "Feature",
  "properties": {
    "gn:admin1_code":"8",
    "gn:admin2_code":"GE",
    "gn:admin3_code":"10014.0",
    "gn:asciiname":"Santa Marta",
    "gn:country_code":"IT",
    "gn:dem":120,
    "gn:feature_class":"P",
    "gn:feature_code":"PPLA3",
    "gn:name":"Santa Marta",
    "gn:population":272,
    "gn:timezone":"Europe/Rome",
    "iso:country":"IT",
    "wof:name":"Santa Marta",
    "wof:placetype":"locality",
    "wof:population":272
},
  "geometry": {"coordinates":[8.89268,44.50401],"type":"Point"}
}