{
  "type": "Feature",
  "properties": {
    "gn:admin1_code":"19",
    "gn:admin2_code":"AO",
    "gn:admin3_code":"7007.0",
    "gn:asciiname":"Bisous",
    "gn:country_code":"IT",
    "gn:dem":1725,
    "gn:feature_class":"P",
    "gn:feature_code":"PPL",
    "gn:name":"Bisous",
    "gn:population":20,
    "gn:timezone":"Europe/Rome",
    "iso:country":"IT",
    "wof:name":"Bisous",
    "wof:placetype":"locality",
    "wof:population":20
},
  "geometry": {"coordinates":[7.69803,45.82184],"type":"Point"}
}