{
  "type": "Feature",
  "properties": {
    "gn:admin1_code":"9.0",
    "gn:admin2_code":"CR",
    "gn:admin3_code":"19032.0",
    "gn:asciiname":"Corte de' Cortesi",
    "gn:country_code":"IT",
    "gn:dem":62,
    "gn:feature_class":"P",
    "gn:feature_code":"PPLA3",
    "gn:name":"Corte de' Cortesi",
    "gn:population":408,
    "gn:timezone":"Europe/Rome",
    "iso:country":"IT",
    "wof:name":"Corte de' Cortesi",
    "wof:placetype":"locality",
    "wof:population":408
},
  "geometry": {"coordinates":[10.00738,45.27265],"type":"Point"}
}