{
  "type": "Feature",
  "properties": {
    "gn:admin1_code":"20.0",
    "gn:admin2_code":"PD",
    "gn:admin3_code":"28089.0",
    "gn:asciiname":"Zona Produttiva Selve",
    "gn:country_code":"IT",
    "gn:dem":15,
    "gn:feature_class":"P",
    "gn:feature_code":"PPL",
    "gn:name":"Zona Produttiva Selve",
    "gn:population":48,
    "gn:timezone":"Europe/Rome",
    "iso:country":"IT",
    "wof:name":"Zona Produttiva Selve",
    "wof:placetype":"locality",
    "wof:population":48
},
  "geometry": {"coordinates":[11.71692,45.39033],"type":"Point"}
}