{
  "type": "Feature",
  "properties": {
    "gn:admin1_code":"4",
    "gn:admin2_code":"SA",
    "gn:admin3_code":"65027.0",
    "gn:asciiname":"Vallennora",
    "gn:country_code":"IT",
    "gn:dem":689,
    "gn:feature_class":"P",
    "gn:feature_code":"PPL",
    "gn:name":"Vallennora",
    "gn:population":21,
    "gn:timezone":"Europe/Rome",
    "iso:country":"IT",
    "wof:name":"Vallennora",
    "wof:placetype":"locality",
    "wof:population":21
},
  "geometry": {"coordinates":[15.67932,40.16211],"type":"Point"}
}