{
  "type": "Feature",
  "properties": {
    "gn:admin1_code":"5.0",
    "gn:admin2_code":"BO",
    "gn:admin3_code":"37040.0",
    "gn:asciiname":"La Martina",
    "gn:country_code":"IT",
    "gn:dem":687,
    "gn:elevation":"700.0",
    "gn:feature_class":"P",
    "gn:feature_code":"PPL",
    "gn:name":"La Martina",
    "gn:population":8,
    "gn:timezone":"Europe/Rome",
    "iso:country":"IT",
    "wof:name":"La Martina",
    "wof:placetype":"locality",
    "wof:population":8
},
  "geometry": {"coordinates":[11.37739,44.21592],"type":"Point"}
}