{
  "type": "Feature",
  "properties": {
    "gn:admin1_code":"5",
    "gn:admin2_code":"FC",
    "gn:admin3_code":"40016.0",
    "gn:asciiname":"Case Zanotti",
    "gn:country_code":"IT",
    "gn:dem":22,
    "gn:feature_class":"P",
    "gn:feature_code":"PPL",
    "gn:name":"Case Zanotti",
    "gn:population":79,
    "gn:timezone":"Europe/Rome",
    "iso:country":"IT",
    "wof:name":"Case Zanotti",
    "wof:placetype":"locality",
    "wof:population":79
},
  "geometry": {"coordinates":[12.37257,44.10634],"type":"Point"}
}