{
  "type": "Feature",
  "properties": {
    "gn:admin1_code":"7",
    "gn:admin2_code":"FR",
    "gn:admin3_code":"60069.0",
    "gn:asciiname":"Le Poste",
    "gn:country_code":"IT",
    "gn:dem":347,
    "gn:feature_class":"P",
    "gn:feature_code":"PPL",
    "gn:name":"Le Poste",
    "gn:population":25,
    "gn:timezone":"Europe/Rome",
    "iso:country":"IT",
    "wof:name":"Le Poste",
    "wof:placetype":"locality",
    "wof:population":25
},
  "geometry": {"coordinates":[13.6583,41.58577],"type":"Point"}
}