{
  "type": "Feature",
  "properties": {
    "gn:admin1_code":"12",
    "gn:admin2_code":"AT",
    "gn:admin3_code":"5005.0",
    "gn:asciiname":"Ghirlandina",
    "gn:country_code":"IT",
    "gn:dem":210,
    "gn:feature_class":"P",
    "gn:feature_code":"PPL",
    "gn:name":"Ghirlandina",
    "gn:population":22,
    "gn:timezone":"Europe/Rome",
    "iso:country":"IT",
    "wof:name":"Ghirlandina",
    "wof:placetype":"locality",
    "wof:population":22
},
  "geometry": {"coordinates":[8.24892,44.85652],"type":"Point"}
}