{
  "type": "Feature",
  "properties": {
    "gn:admin1_code":"15",
    "gn:admin2_code":"PA",
    "gn:admin3_code":"82005.0",
    "gn:asciiname":"Localita' Seggio",
    "gn:country_code":"IT",
    "gn:dem":395,
    "gn:feature_class":"P",
    "gn:feature_code":"PPL",
    "gn:name":"Localita' Seggio",
    "gn:population":252,
    "gn:timezone":"Europe/Rome",
    "iso:country":"IT",
    "wof:name":"Localita' Seggio",
    "wof:placetype":"locality",
    "wof:population":252
},
  "geometry": {"coordinates":[13.27134,38.04414000000001],"type":"Point"}
}