{
  "type": "Feature",
  "properties": {
    "gn:admin1_code":"3",
    "gn:admin2_code":"CS",
    "gn:admin3_code":"78015.0",
    "gn:asciiname":"Serluca-Calabaia Isola Polazza",
    "gn:country_code":"IT",
    "gn:dem":8,
    "gn:feature_class":"P",
    "gn:feature_code":"PPL",
    "gn:name":"Serluca-Calabaia Isola Polazza",
    "gn:population":153,
    "gn:timezone":"Europe/Rome",
    "iso:country":"IT",
    "wof:name":"Serluca-Calabaia Isola Polazza",
    "wof:placetype":"locality",
    "wof:population":153
},
  "geometry": {"coordinates":[15.86066,39.60049],"type":"Point"}
}