{
  "type": "Feature",
  "properties": {
    "gn:admin1_code":"5",
    "gn:admin2_code":"RE",
    "gn:admin3_code":"35016.0",
    "gn:asciiname":"Case Perizzi",
    "gn:country_code":"IT",
    "gn:dem":614,
    "gn:feature_class":"P",
    "gn:feature_code":"PPL",
    "gn:name":"Case Perizzi",
    "gn:population":68,
    "gn:timezone":"Europe/Rome",
    "iso:country":"IT",
    "wof:name":"Case Perizzi",
    "wof:placetype":"locality",
    "wof:population":68
},
  "geometry": {"coordinates":[10.47487,44.45428],"type":"Point"}
}