{
  "type": "Feature",
  "properties": {
    "gn:admin1_code":"20",
    "gn:admin2_code":"PD",
    "gn:admin3_code":"28073.0",
    "gn:asciiname":"Argine Sinistro I",
    "gn:country_code":"IT",
    "gn:dem":17,
    "gn:feature_class":"P",
    "gn:feature_code":"PPL",
    "gn:name":"Argine Sinistro I",
    "gn:population":41,
    "gn:timezone":"Europe/Rome",
    "iso:country":"IT",
    "wof:name":"Argine Sinistro I",
    "wof:placetype":"locality",
    "wof:population":41
},
  "geometry": {"coordinates":[11.74897,45.42095],"type":"Point"}
}