{
  "type": "Feature",
  "properties": {
    "gn:admin1_code":"6",
    "gn:admin2_code":"GO",
    "gn:admin3_code":"31006.0",
    "gn:asciiname":"Zona Artigianale",
    "gn:country_code":"IT",
    "gn:dem":18,
    "gn:feature_class":"P",
    "gn:feature_code":"PPLL",
    "gn:name":"Zona Artigianale",
    "gn:population":10,
    "gn:timezone":"Europe/Rome",
    "iso:country":"IT",
    "wof:name":"Zona Artigianale",
    "wof:placetype":"locality",
    "wof:population":10
},
  "geometry": {"coordinates":[13.47564,45.85811],"type":"Point"}
}