{
  "type": "Feature",
  "properties": {
    "gn:admin1_code":"6.0",
    "gn:admin2_code":"UD",
    "gn:admin3_code":"30041.0",
    "gn:asciiname":"Casera Tragonia",
    "gn:country_code":"IT",
    "gn:dem":1781,
    "gn:feature_class":"P",
    "gn:feature_code":"PPL",
    "gn:name":"Casera Tragonia",
    "gn:population":0,
    "gn:timezone":"Europe/Rome",
    "iso:country":"IT",
    "wof:name":"Casera Tragonia",
    "wof:placetype":"locality"
},
  "geometry": {"coordinates":[12.60265,46.45542],"type":"Point"}
}