{
  "type": "Feature",
  "properties": {
    "gn:admin1_code":"5",
    "gn:admin2_code":"FE",
    "gn:admin3_code":"38009.0",
    "gn:asciiname":"Zona Artigianale",
    "gn:country_code":"IT",
    "gn:dem":2,
    "gn:feature_class":"P",
    "gn:feature_code":"PPL",
    "gn:name":"Zona Artigianale",
    "gn:population":28,
    "gn:timezone":"Europe/Rome",
    "iso:country":"IT",
    "wof:name":"Zona Artigianale",
    "wof:placetype":"locality",
    "wof:population":28
},
  "geometry": {"coordinates":[11.84685,44.84478],"type":"Point"}
}