{
  "type": "Feature",
  "properties": {
    "gn:admin1_code":"16",
    "gn:admin2_code":"LI",
    "gn:admin3_code":"49009.0",
    "gn:asciiname":"Ghiandaie",
    "gn:country_code":"IT",
    "gn:dem":120,
    "gn:feature_class":"P",
    "gn:feature_code":"PPL",
    "gn:name":"Ghiandaie",
    "gn:population":41,
    "gn:timezone":"Europe/Rome",
    "iso:country":"IT",
    "wof:name":"Ghiandaie",
    "wof:placetype":"locality",
    "wof:population":41
},
  "geometry": {"coordinates":[10.36642,43.52457],"type":"Point"}
}