{
  "type": "Feature",
  "properties": {
    "gn:admin1_code":"5",
    "gn:admin2_code":"RE",
    "gn:admin3_code":"35003.0",
    "gn:asciiname":"Sasso Gattone",
    "gn:country_code":"IT",
    "gn:dem":233,
    "gn:feature_class":"P",
    "gn:feature_code":"PPL",
    "gn:name":"Sasso Gattone",
    "gn:population":11,
    "gn:timezone":"Europe/Rome",
    "iso:country":"IT",
    "wof:name":"Sasso Gattone",
    "wof:placetype":"locality",
    "wof:population":11
},
  "geometry": {"coordinates":[10.64961,44.48116],"type":"Point"}
}