{
  "type": "Feature",
  "properties": {
    "gn:admin1_code":"12",
    "gn:admin2_code":"AL",
    "gn:admin3_code":"6148.0",
    "gn:asciiname":"Sant'Ambrogio",
    "gn:country_code":"IT",
    "gn:dem":609,
    "gn:feature_class":"P",
    "gn:feature_code":"PPL",
    "gn:name":"Sant'Ambrogio",
    "gn:population":15,
    "gn:timezone":"Europe/Rome",
    "iso:country":"IT",
    "wof:name":"Sant'Ambrogio",
    "wof:placetype":"locality",
    "wof:population":15
},
  "geometry": {"coordinates":[9.06108,44.6769],"type":"Point"}
}