{
  "type": "Feature",
  "properties": {
    "gn:admin1_code":"10",
    "gn:admin2_code":"AN",
    "gn:admin3_code":"42017.0",
    "gn:asciiname":"Nazzano",
    "gn:country_code":"IT",
    "gn:dem":376,
    "gn:feature_class":"P",
    "gn:feature_code":"PPL",
    "gn:name":"Nazzano",
    "gn:population":37,
    "gn:timezone":"Europe/Rome",
    "iso:country":"IT",
    "name:azb_x_preferred":[
        "\u0646\u0627\u062a\u0632\u0627\u0646\u0648"
    ],
    "name:bcl_x_preferred":[
        "Nazzano"
    ],
    "name:bel_x_preferred":[
        "\u041d\u0430\u0446\u0446\u0430\u043d\u0430"
    ],
    "name:bul_x_preferred":[
        "\u041d\u0430\u0446\u0430\u043d\u043e"
    ],
    "name:cat_x_preferred":[
        "Nazzano"
    ],
    "name:ceb_x_preferred":[
        "Nazzano"
    ],
    "name:deu_x_preferred":[
        "Nazzano"
    ],
    "name:epo_x_preferred":[
        "Nazzano"
    ],
    "name:eus_x_preferred":[
        "Nazzano"
    ],
    "name:fas_x_preferred":[
        "\u0646\u0627\u062a\u0632\u0627\u0646\u0648"
    ],
    "name:fra_x_preferred":[
        "Nazzano"
    ],
    "name:hun_x_preferred":[
        "Nazzano"
    ],
    "name:hye_x_preferred":[
        "\u0546\u0561\u0581\u0561\u0576\u0578"
    ],
    "name:ina_x_preferred":[
        "Nazzano"
    ],
    "name:ita_x_preferred":[
        "Nazzano"
    ],
    "name:jpn_x_preferred":[
        "\u30ca\u30c3\u30c4\u30a1\u30fc\u30ce"
    ],
    "name:kaz_x_preferred":[
        "\u041d\u0430\u0446\u0446\u0430\u043d\u043e"
    ],
    "name:kor_x_preferred":[
        "\ub098\ucc28\ub178"
    ],
    "name:lat_x_preferred":[
        "Natianum"
    ],
    "name:lmo_x_preferred":[
        "Nazzano"
    ],
    "name:msa_x_preferred":[
        "Nazzano"
    ],
    "name:nap_x_preferred":[
        "Nazzano"
    ],
    "name:nld_x_preferred":[
        "Nazzano"
    ],
    "name:pms_x_preferred":[
        "Nazzano"
    ],
    "name:pol_x_preferred":[
        "Nazzano"
    ],
    "name:por_x_preferred":[
        "Nazzano"
    ],
    "name:ron_x_preferred":[
        "Nazzano"
    ],
    "name:rus_x_preferred":[
        "\u041d\u0430\u0446\u0446\u0430\u043d\u043e"
    ],
    "name:scn_x_preferred":[
        "Nazzanu"
    ],
    "name:sco_x_preferred":[
        "Nazzano"
    ],
    "name:spa_x_preferred":[
        "Nazzano"
    ],
    "name:srp_x_preferred":[
        "\u041d\u0430\u0446\u0430\u043d\u043e"
    ],
    "name:ukr_x_preferred":[
        "\u041d\u0430\u0446\u0446\u0430\u043d\u043e"
    ],
    "name:uzb_x_preferred":[
        "Nazzano"
    ],
    "name:vie_x_preferred":[
        "Nazzano"
    ],
    "name:vol_x_preferred":[
        "Nazzano"
    ],
    "name:war_x_preferred":[
        "Nazzano"
    ],
    "name:zho_x_preferred":[
        "\u7eb3\u624e\u8bfa"
    ],
    "wof:name":"Nazzano",
    "wof:placetype":"locality",
    "wof:population":37
},
  "geometry": {"coordinates":[12.89428,43.35833],"type":"Point"}
}