{
  "type": "Feature",
  "properties": {
    "gn:admin1_code":"10",
    "gn:admin2_code":"AN",
    "gn:admin3_code":"42045.0",
    "gn:asciiname":"Ferretti",
    "gn:country_code":"IT",
    "gn:dem":20,
    "gn:feature_class":"P",
    "gn:feature_code":"PPL",
    "gn:name":"Ferretti",
    "gn:population":62,
    "gn:timezone":"Europe/Rome",
    "iso:country":"IT",
    "name:deu_x_preferred":[
        "Ferretti"
    ],
    "name:fra_x_preferred":[
        "Ferretti"
    ],
    "name:ita_x_preferred":[
        "Ferretti"
    ],
    "name:nds_x_preferred":[
        "Ferretti"
    ],
    "name:rus_x_preferred":[
        "\u0424\u0435\u0440\u0440\u0435\u0442\u0442\u0438"
    ],
    "name:srp_x_preferred":[
        "Ferretti"
    ],
    "name:swe_x_preferred":[
        "Ferretti"
    ],
    "wof:name":"Ferretti",
    "wof:placetype":"locality",
    "wof:population":62
},
  "geometry": {"coordinates":[13.20984,43.69985],"type":"Point"}
}