{
  "type": "Feature",
  "properties": {
    "gn:admin1_code":"15.0",
    "gn:admin2_code":"PA",
    "gn:admin3_code":"82034.0",
    "gn:asciiname":"Contrada Giammaria",
    "gn:country_code":"IT",
    "gn:dem":463,
    "gn:feature_class":"P",
    "gn:feature_code":"PPLL",
    "gn:name":"Contrada Giammaria",
    "gn:population":0,
    "gn:timezone":"Europe/Rome",
    "iso:country":"IT",
    "wof:name":"Contrada Giammaria",
    "wof:placetype":"locality"
},
  "geometry": {"coordinates":[13.20762,37.78809],"type":"Point"}
}