{
  "type": "Feature",
  "properties": {
    "gn:admin1_code":"8.0",
    "gn:admin2_code":"SV",
    "gn:admin3_code":"9015.0",
    "gn:asciiname":"Montenotte Inferiore",
    "gn:country_code":"IT",
    "gn:dem":565,
    "gn:feature_class":"P",
    "gn:feature_code":"PPL",
    "gn:name":"Montenotte Inferiore",
    "gn:population":6,
    "gn:timezone":"Europe/Rome",
    "iso:country":"IT",
    "wof:name":"Montenotte Inferiore",
    "wof:placetype":"locality",
    "wof:population":6
},
  "geometry": {"coordinates":[8.41313,44.41188],"type":"Point"}
}