{
  "type": "Feature",
  "properties": {
    "gn:admin1_code":"9",
    "gn:admin2_code":"SO",
    "gn:admin3_code":"14020.0",
    "gn:asciiname":"Vallone",
    "gn:country_code":"IT",
    "gn:dem":358,
    "gn:feature_class":"P",
    "gn:feature_code":"PPL",
    "gn:name":"Vallone",
    "gn:population":12,
    "gn:timezone":"Europe/Rome",
    "iso:country":"IT",
    "wof:name":"Vallone",
    "wof:placetype":"locality",
    "wof:population":12
},
  "geometry": {"coordinates":[9.99653,46.16474],"type":"Point"}
}