{
  "type": "Feature",
  "properties": {
    "gn:admin1_code":"9",
    "gn:admin2_code":"PV",
    "gn:admin3_code":"18117.0",
    "gn:asciiname":"Panzini",
    "gn:country_code":"IT",
    "gn:dem":725,
    "gn:feature_class":"P",
    "gn:feature_code":"PPL",
    "gn:name":"Panzini",
    "gn:population":36,
    "gn:timezone":"Europe/Rome",
    "iso:country":"IT",
    "wof:name":"Panzini",
    "wof:placetype":"locality",
    "wof:population":36
},
  "geometry": {"coordinates":[9.15097,44.85201],"type":"Point"}
}