{
  "type": "Feature",
  "properties": {
    "gn:admin1_code":"1.0",
    "gn:admin2_code":"AQ",
    "gn:admin3_code":"66056.0",
    "gn:asciiname":"Ville di Fano",
    "gn:country_code":"IT",
    "gn:dem":868,
    "gn:feature_class":"P",
    "gn:feature_code":"PPL",
    "gn:name":"Ville di Fano",
    "gn:population":0,
    "gn:timezone":"Europe/Rome",
    "iso:country":"IT",
    "name:azb_x_preferred":[
        "\u0648\u06cc\u0644\u0647 \u062f\u06cc \u0641\u0627\u0646\u0648"
    ],
    "name:fas_x_preferred":[
        "\u0648\u06cc\u0644\u0647 \u062f\u06cc \u0641\u0627\u0646\u0648"
    ],
    "name:srp_x_preferred":[
        "\u041b\u043e\u043d\u0430\u0440\u043e-\u0412\u0438\u043b\u0435 \u0434\u0438 \u0424\u0430\u043d\u043e"
    ],
    "wof:name":"Ville di Fano",
    "wof:placetype":"locality"
},
  "geometry": {"coordinates":[13.18643,42.5248],"type":"Point"}
}