{
  "type": "Feature",
  "properties": {
    "gn:admin1_code":"15.0",
    "gn:admin2_code":"TP",
    "gn:admin3_code":"81018.0",
    "gn:asciiname":"Chiesa di Pusillesi",
    "gn:country_code":"IT",
    "gn:dem":289,
    "gn:feature_class":"P",
    "gn:feature_code":"PPL",
    "gn:name":"Chiesa di Pusillesi",
    "gn:population":0,
    "gn:timezone":"Europe/Rome",
    "iso:country":"IT",
    "wof:name":"Chiesa di Pusillesi",
    "wof:placetype":"locality"
},
  "geometry": {"coordinates":[12.75,37.81667],"type":"Point"}
}