{
  "type": "Feature",
  "properties": {
    "gn:admin1_code":"9",
    "gn:admin2_code":"PV",
    "gn:admin3_code":"18005.0",
    "gn:asciiname":"Plessa",
    "gn:country_code":"IT",
    "gn:dem":93,
    "gn:feature_class":"P",
    "gn:feature_code":"PPL",
    "gn:name":"Plessa",
    "gn:population":37,
    "gn:timezone":"Europe/Rome",
    "iso:country":"IT",
    "name:cat_x_preferred":[
        "Plessa"
    ],
    "name:dan_x_preferred":[
        "Plessa"
    ],
    "name:deu_x_preferred":[
        "Plessa"
    ],
    "name:epo_x_preferred":[
        "Plessa"
    ],
    "name:eus_x_preferred":[
        "Plessa"
    ],
    "name:fas_x_preferred":[
        "\u067e\u0644\u0633\u0627"
    ],
    "name:fra_x_preferred":[
        "Plessa"
    ],
    "name:hsb_x_preferred":[
        "Plesow"
    ],
    "name:hun_x_preferred":[
        "Plessa"
    ],
    "name:hye_x_preferred":[
        "\u054a\u056c\u0565\u057d\u0561"
    ],
    "name:ita_x_preferred":[
        "Plessa"
    ],
    "name:mkd_x_preferred":[
        "\u041f\u043b\u0435\u0441\u0430"
    ],
    "name:msa_x_preferred":[
        "Plessa"
    ],
    "name:nld_x_preferred":[
        "Plessa"
    ],
    "name:pol_x_preferred":[
        "Plessa"
    ],
    "name:ron_x_preferred":[
        "Plessa"
    ],
    "name:rus_x_preferred":[
        "\u041f\u043b\u0435\u0441\u0441\u0430"
    ],
    "name:spa_x_preferred":[
        "Plessa"
    ],
    "name:srp_x_preferred":[
        "\u041f\u043b\u0435\u0441\u0430"
    ],
    "name:swe_x_preferred":[
        "Plessa"
    ],
    "name:ukr_x_preferred":[
        "\u041f\u043b\u0435\u0441\u0441\u0430"
    ],
    "name:uzb_x_preferred":[
        "Plessa"
    ],
    "name:vol_x_preferred":[
        "Plessa"
    ],
    "name:war_x_preferred":[
        "Plessa"
    ],
    "name:zho_x_preferred":[
        "\u666e\u83b1\u8428"
    ],
    "wof:name":"Plessa",
    "wof:placetype":"locality",
    "wof:population":37
},
  "geometry": {"coordinates":[9.34313,45.07289],"type":"Point"}
}