{
  "type": "Feature",
  "properties": {
    "gn:admin1_code":"9",
    "gn:admin2_code":"PV",
    "gn:admin3_code":"18005.0",
    "gn:asciiname":"Plessa",
    "gn:country_code":"IT",
    "gn:dem":93,
    "gn:feature_class":"P",
    "gn:feature_code":"PPL",
    "gn:name":"Plessa",
    "gn:population":37,
    "gn:timezone":"Europe/Rome",
    "iso:country":"IT",
    "wof:name":"Plessa",
    "wof:placetype":"locality",
    "wof:population":37
},
  "geometry": {"coordinates":[9.34313,45.07289],"type":"Point"}
}