{
  "type": "Feature",
  "properties": {
    "gn:admin1_code":"9",
    "gn:admin2_code":"CO",
    "gn:admin3_code":"13107.0",
    "gn:asciiname":"Stallone Venini",
    "gn:country_code":"IT",
    "gn:dem":199,
    "gn:feature_class":"P",
    "gn:feature_code":"PPL",
    "gn:name":"Stallone Venini",
    "gn:population":19,
    "gn:timezone":"Europe/Rome",
    "iso:country":"IT",
    "wof:name":"Stallone Venini",
    "wof:placetype":"locality",
    "wof:population":19
},
  "geometry": {"coordinates":[9.40205,46.16128],"type":"Point"}
}