{
  "type": "Feature",
  "properties": {
    "gn:admin1_code":"20",
    "gn:admin2_code":"VR",
    "gn:admin3_code":"23089.0",
    "gn:asciiname":"Gobbini",
    "gn:country_code":"IT",
    "gn:dem":92,
    "gn:feature_class":"P",
    "gn:feature_code":"PPL",
    "gn:name":"Gobbini",
    "gn:population":46,
    "gn:timezone":"Europe/Rome",
    "iso:country":"IT",
    "wof:name":"Gobbini",
    "wof:placetype":"locality",
    "wof:population":46
},
  "geometry": {"coordinates":[10.70105,45.35053],"type":"Point"}
}