{
  "type": "Feature",
  "properties": {
    "gn:admin1_code":"3",
    "gn:admin2_code":"CS",
    "gn:admin3_code":"78139.0",
    "gn:asciiname":"Lupia",
    "gn:country_code":"IT",
    "gn:dem":556,
    "gn:feature_class":"P",
    "gn:feature_code":"PPL",
    "gn:name":"Lupia",
    "gn:population":255,
    "gn:timezone":"Europe/Rome",
    "iso:country":"IT",
    "wof:name":"Lupia",
    "wof:placetype":"locality",
    "wof:population":255
},
  "geometry": {"coordinates":[16.29427,39.12766],"type":"Point"}
}