{
  "type": "Feature",
  "properties": {
    "gn:admin1_code":"9",
    "gn:admin2_code":"LC",
    "gn:admin3_code":"97060.0",
    "gn:asciiname":"Palaino",
    "gn:country_code":"IT",
    "gn:dem":649,
    "gn:feature_class":"P",
    "gn:feature_code":"PPL",
    "gn:name":"Palaino",
    "gn:population":24,
    "gn:timezone":"Europe/Rome",
    "iso:country":"IT",
    "wof:name":"Palaino",
    "wof:placetype":"locality",
    "wof:population":24
},
  "geometry": {"coordinates":[9.25801,45.94965],"type":"Point"}
}