{
  "type": "Feature",
  "properties": {
    "gn:admin1_code":"9",
    "gn:admin2_code":"VA",
    "gn:admin3_code":"12092.0",
    "gn:asciiname":"Cascina Cattaneo",
    "gn:country_code":"IT",
    "gn:dem":202,
    "gn:feature_class":"P",
    "gn:feature_code":"PPL",
    "gn:name":"Cascina Cattaneo",
    "gn:population":111,
    "gn:timezone":"Europe/Rome",
    "iso:country":"IT",
    "wof:name":"Cascina Cattaneo",
    "wof:placetype":"locality",
    "wof:population":111
},
  "geometry": {"coordinates":[8.73509,45.99216],"type":"Point"}
}