{
  "type": "Feature",
  "properties": {
    "gn:admin1_code":"9",
    "gn:admin2_code":"SO",
    "gn:admin3_code":"14027.0",
    "gn:asciiname":"Bocca d'Adda",
    "gn:country_code":"IT",
    "gn:dem":199,
    "gn:feature_class":"P",
    "gn:feature_code":"PPL",
    "gn:name":"Bocca d'Adda",
    "gn:population":98,
    "gn:timezone":"Europe/Rome",
    "iso:country":"IT",
    "wof:name":"Bocca d'Adda",
    "wof:placetype":"locality",
    "wof:population":98
},
  "geometry": {"coordinates":[9.43844,46.18192],"type":"Point"}
}