{
  "type": "Feature",
  "properties": {
    "gn:admin1_code":"20",
    "gn:admin2_code":"RO",
    "gn:admin3_code":"29014.0",
    "gn:asciiname":"Facchina",
    "gn:country_code":"IT",
    "gn:dem":8,
    "gn:feature_class":"P",
    "gn:feature_code":"PPL",
    "gn:name":"Facchina",
    "gn:population":32,
    "gn:timezone":"Europe/Rome",
    "iso:country":"IT",
    "wof:name":"Facchina",
    "wof:placetype":"locality",
    "wof:population":32
},
  "geometry": {"coordinates":[11.38284,45.02255],"type":"Point"}
}