{
  "type": "Feature",
  "properties": {
    "gn:admin1_code":"12.0",
    "gn:admin2_code":"VB",
    "gn:admin3_code":"103056.0",
    "gn:asciiname":"Cadarese",
    "gn:country_code":"IT",
    "gn:dem":750,
    "gn:elevation":"749.0",
    "gn:feature_class":"P",
    "gn:feature_code":"PPL",
    "gn:name":"Cadarese",
    "gn:population":39,
    "gn:timezone":"Europe/Rome",
    "iso:country":"IT",
    "wof:name":"Cadarese",
    "wof:placetype":"locality",
    "wof:population":39
},
  "geometry": {"coordinates":[8.36078,46.29744],"type":"Point"}
}