{
  "type": "Feature",
  "properties": {
    "gn:admin1_code":"13.0",
    "gn:admin2_code":"LE",
    "gn:admin3_code":"75095.0",
    "gn:asciiname":"Zona P.I.P.",
    "gn:country_code":"IT",
    "gn:dem":98,
    "gn:feature_class":"P",
    "gn:feature_code":"PPLL",
    "gn:name":"Zona P.I.P.",
    "gn:population":0,
    "gn:timezone":"Europe/Rome",
    "iso:country":"IT",
    "wof:name":"Zona P.I.P.",
    "wof:placetype":"locality"
},
  "geometry": {"coordinates":[18.31857,40.05429],"type":"Point"}
}