{
  "type": "Feature",
  "properties": {
    "gn:admin1_code":"6.0",
    "gn:admin2_code":"PN",
    "gn:admin3_code":"93049.0",
    "gn:asciiname":"Battaias",
    "gn:country_code":"IT",
    "gn:dem":515,
    "gn:feature_class":"P",
    "gn:feature_code":"PPL",
    "gn:name":"Battaias",
    "gn:population":0,
    "gn:timezone":"Europe/Rome",
    "iso:country":"IT",
    "wof:name":"Battaias",
    "wof:placetype":"locality"
},
  "geometry": {"coordinates":[12.93861,46.26389],"type":"Point"}
}