{
  "type": "Feature",
  "properties": {
    "gn:admin1_code":"12",
    "gn:admin2_code":"AL",
    "gn:admin3_code":"6108.0",
    "gn:asciiname":"Zebedassi",
    "gn:country_code":"IT",
    "gn:dem":331,
    "gn:feature_class":"P",
    "gn:feature_code":"PPL",
    "gn:name":"Zebedassi",
    "gn:population":31,
    "gn:timezone":"Europe/Rome",
    "iso:country":"IT",
    "wof:name":"Zebedassi",
    "wof:placetype":"locality",
    "wof:population":31
},
  "geometry": {"coordinates":[9.00978,44.86249],"type":"Point"}
}