{
  "type": "Feature",
  "properties": {
    "gn:admin1_code":"15.0",
    "gn:admin2_code":"ME",
    "gn:admin3_code":"83076.0",
    "gn:asciiname":"Gimello",
    "gn:country_code":"IT",
    "gn:dem":484,
    "gn:feature_class":"P",
    "gn:feature_code":"PPL",
    "gn:name":"Gimello",
    "gn:population":246,
    "gn:timezone":"Europe/Rome",
    "iso:country":"IT",
    "wof:name":"Gimello",
    "wof:placetype":"locality",
    "wof:population":246
},
  "geometry": {"coordinates":[15.41988,38.15806],"type":"Point"}
}