{
  "type": "Feature",
  "properties": {
    "gn:admin1_code":"4",
    "gn:admin2_code":"AV",
    "gn:admin3_code":"64115.0",
    "gn:asciiname":"Serro d'Annunzio",
    "gn:country_code":"IT",
    "gn:dem":725,
    "gn:feature_class":"P",
    "gn:feature_code":"PPL",
    "gn:name":"Serro d'Annunzio",
    "gn:population":74,
    "gn:timezone":"Europe/Rome",
    "iso:country":"IT",
    "wof:name":"Serro d'Annunzio",
    "wof:placetype":"locality",
    "wof:population":74
},
  "geometry": {"coordinates":[15.26137,41.05903],"type":"Point"}
}