{
  "type": "Feature",
  "properties": {
    "gn:admin1_code":"10.0",
    "gn:admin2_code":"AN",
    "gn:admin3_code":"42017.0",
    "gn:asciiname":"Rucce",
    "gn:country_code":"IT",
    "gn:dem":561,
    "gn:feature_class":"P",
    "gn:feature_code":"PPL",
    "gn:name":"Rucce",
    "gn:population":38,
    "gn:timezone":"Europe/Rome",
    "iso:country":"IT",
    "wof:name":"Rucce",
    "wof:placetype":"locality",
    "wof:population":38
},
  "geometry": {"coordinates":[12.7905,43.37356],"type":"Point"}
}