{
  "type": "Feature",
  "properties": {
    "gn:admin1_code":"12",
    "gn:admin2_code":"CN",
    "gn:admin3_code":"4095.0",
    "gn:asciiname":"Regione Penoni Sottani Borgata Carrara",
    "gn:country_code":"IT",
    "gn:dem":697,
    "gn:feature_class":"P",
    "gn:feature_code":"PPLL",
    "gn:name":"Regione Penoni Sottani Borgata Carrara",
    "gn:population":7,
    "gn:timezone":"Europe/Rome",
    "iso:country":"IT",
    "wof:name":"Regione Penoni Sottani Borgata Carrara",
    "wof:placetype":"locality",
    "wof:population":7
},
  "geometry": {"coordinates":[7.99578,44.19006],"type":"Point"}
}