{
  "type": "Feature",
  "properties": {
    "gn:admin1_code":"20",
    "gn:admin2_code":"RO",
    "gn:admin3_code":"29034.0",
    "gn:asciiname":"Borgata Romani",
    "gn:country_code":"IT",
    "gn:dem":1,
    "gn:feature_class":"P",
    "gn:feature_code":"PPL",
    "gn:name":"Borgata Romani",
    "gn:population":15,
    "gn:timezone":"Europe/Rome",
    "iso:country":"IT",
    "wof:name":"Borgata Romani",
    "wof:placetype":"locality",
    "wof:population":15
},
  "geometry": {"coordinates":[12.03771,44.98953],"type":"Point"}
}