{
  "type": "Feature",
  "properties": {
    "gn:admin1_code":"20.0",
    "gn:admin2_code":"VR",
    "gn:admin3_code":"23070.0",
    "gn:asciiname":"Lovati",
    "gn:country_code":"IT",
    "gn:dem":473,
    "gn:feature_class":"P",
    "gn:feature_code":"PPL",
    "gn:name":"Lovati",
    "gn:population":33,
    "gn:timezone":"Europe/Rome",
    "iso:country":"IT",
    "wof:name":"Lovati",
    "wof:placetype":"locality",
    "wof:population":33
},
  "geometry": {"coordinates":[11.26638,45.52887],"type":"Point"}
}