{
  "type": "Feature",
  "properties": {
    "gn:admin1_code":"17",
    "gn:admin2_code":"TN",
    "gn:admin3_code":"22163.0",
    "gn:asciiname":"Marcena",
    "gn:country_code":"IT",
    "gn:dem":936,
    "gn:feature_class":"P",
    "gn:feature_code":"PPL",
    "gn:name":"Marcena",
    "gn:population":182,
    "gn:timezone":"Europe/Rome",
    "iso:country":"IT",
    "wof:name":"Marcena",
    "wof:placetype":"locality",
    "wof:population":182
},
  "geometry": {"coordinates":[11.0188,46.44121],"type":"Point"}
}