{
  "type": "Feature",
  "properties": {
    "gn:admin1_code":"4",
    "gn:admin2_code":"SA",
    "gn:admin3_code":"65025.0",
    "gn:asciiname":"Podere San Bernardo",
    "gn:country_code":"IT",
    "gn:dem":17,
    "gn:feature_class":"P",
    "gn:feature_code":"PPL",
    "gn:name":"Podere San Bernardo",
    "gn:population":25,
    "gn:timezone":"Europe/Rome",
    "iso:country":"IT",
    "wof:name":"Podere San Bernardo",
    "wof:placetype":"locality",
    "wof:population":25
},
  "geometry": {"coordinates":[14.9956,40.46677],"type":"Point"}
}