{
  "type": "Feature",
  "properties": {
    "gn:admin1_code":"12",
    "gn:admin2_code":"VB",
    "gn:admin3_code":"103077.0",
    "gn:asciiname":"Prata",
    "gn:country_code":"IT",
    "gn:dem":231,
    "gn:feature_class":"P",
    "gn:feature_code":"PPL",
    "gn:name":"Prata",
    "gn:population":236,
    "gn:timezone":"Europe/Rome",
    "iso:country":"IT",
    "wof:name":"Prata",
    "wof:placetype":"locality",
    "wof:population":236
},
  "geometry": {"coordinates":[8.28041,46.03788],"type":"Point"}
}