{
  "type": "Feature",
  "properties": {
    "gn:admin1_code":"12",
    "gn:admin2_code":"VB",
    "gn:admin3_code":"103077.0",
    "gn:asciiname":"Prata",
    "gn:country_code":"IT",
    "gn:dem":231,
    "gn:feature_class":"P",
    "gn:feature_code":"PPL",
    "gn:name":"Prata",
    "gn:population":236,
    "gn:timezone":"Europe/Rome",
    "iso:country":"IT",
    "name:ceb_x_preferred":[
        "Prata"
    ],
    "name:deu_x_preferred":[
        "Prata"
    ],
    "name:fra_x_preferred":[
        "Prata"
    ],
    "name:ita_x_preferred":[
        "Prata"
    ],
    "name:lat_x_preferred":[
        "Prata"
    ],
    "name:nld_x_preferred":[
        "Prata"
    ],
    "name:nor_x_preferred":[
        "Prata"
    ],
    "name:por_x_preferred":[
        "Prata"
    ],
    "name:rus_x_preferred":[
        "\u041f\u0440\u0430\u0442\u0430"
    ],
    "name:srp_x_preferred":[
        "\u041f\u0440\u0430\u0442\u0430"
    ],
    "name:swe_x_preferred":[
        "Prata"
    ],
    "name:vie_x_preferred":[
        "Prata"
    ],
    "name:vol_x_preferred":[
        "Prata"
    ],
    "wof:name":"Prata",
    "wof:placetype":"locality",
    "wof:population":236
},
  "geometry": {"coordinates":[8.28041,46.03788],"type":"Point"}
}