{
  "type": "Feature",
  "properties": {
    "gn:country":"IT",
    "gn:fcode":"PPLX",
    "gn:population":22,
    "iso:country":"IT",
    "qs_pg:aaroncc":"IT",
    "qs_pg:gn_country":"IT",
    "qs_pg:gn_fcode":"PPLX",
    "qs_pg:gn_pop":22,
    "qs_pg:name":"Castagnoli",
    "qs_pg:photos_9r":0,
    "qs_pg:photos_sr":0,
    "qs_pg:pop_sr":1,
    "qs_pg:qs_pg_placetype":"neighbourhood",
    "wof:name":"Castagnoli",
    "wof:placetype":"neighbourhood",
    "wof:population":22
},
  "geometry": {"coordinates":[11.85695,43.63088],"type":"Point"}
}