{
  "type": "Feature",
  "properties": {
    "gn:admin1_code":"14.0",
    "gn:admin2_code":"SS",
    "gn:admin3_code":"90041.0",
    "gn:asciiname":"La Palazzina",
    "gn:country_code":"IT",
    "gn:dem":79,
    "gn:elevation":"92.0",
    "gn:feature_class":"P",
    "gn:feature_code":"PPL",
    "gn:name":"La Palazzina",
    "gn:population":214,
    "gn:timezone":"Europe/Rome",
    "iso:country":"IT",
    "wof:name":"La Palazzina",
    "wof:placetype":"locality",
    "wof:population":214
},
  "geometry": {"coordinates":[9.40129,40.84258],"type":"Point"}
}