{
  "type": "Feature",
  "properties": {
    "gn:admin1_code":"17",
    "gn:admin2_code":"TN",
    "gn:admin3_code":"22064.0",
    "gn:asciiname":"Mestriago",
    "gn:country_code":"IT",
    "gn:dem":809,
    "gn:feature_class":"P",
    "gn:feature_code":"PPL",
    "gn:name":"Mestriago",
    "gn:population":143,
    "gn:timezone":"Europe/Rome",
    "iso:country":"IT",
    "wof:name":"Mestriago",
    "wof:placetype":"locality",
    "wof:population":143
},
  "geometry": {"coordinates":[10.84019,46.32185],"type":"Point"}
}