{
  "type": "Feature",
  "properties": {
    "gn:admin1_code":"4",
    "gn:admin2_code":"SA",
    "gn:admin3_code":"65022.0",
    "gn:asciiname":"Vallegrini",
    "gn:country_code":"IT",
    "gn:dem":172,
    "gn:feature_class":"P",
    "gn:feature_code":"PPL",
    "gn:name":"Vallegrini",
    "gn:population":144,
    "gn:timezone":"Europe/Rome",
    "iso:country":"IT",
    "wof:name":"Vallegrini",
    "wof:placetype":"locality",
    "wof:population":144
},
  "geometry": {"coordinates":[15.1248,40.63845],"type":"Point"}
}