{
  "type": "Feature",
  "properties": {
    "gn:admin1_code":"9.0",
    "gn:admin2_code":"CR",
    "gn:admin3_code":"19050.0",
    "gn:asciiname":"Levata",
    "gn:country_code":"IT",
    "gn:dem":44,
    "gn:feature_class":"P",
    "gn:feature_code":"PPL",
    "gn:name":"Levata",
    "gn:population":465,
    "gn:timezone":"Europe/Rome",
    "iso:country":"IT",
    "wof:name":"Levata",
    "wof:placetype":"locality",
    "wof:population":465
},
  "geometry": {"coordinates":[10.13653,45.19962],"type":"Point"}
}