{
  "type": "Feature",
  "properties": {
    "gn:admin1_code":"4",
    "gn:admin2_code":"AV",
    "gn:admin3_code":"64078.0",
    "gn:asciiname":"Barbati",
    "gn:country_code":"IT",
    "gn:dem":438,
    "gn:feature_class":"P",
    "gn:feature_code":"PPL",
    "gn:name":"Barbati",
    "gn:population":76,
    "gn:timezone":"Europe/Rome",
    "iso:country":"IT",
    "wof:name":"Barbati",
    "wof:placetype":"locality",
    "wof:population":76
},
  "geometry": {"coordinates":[14.7317,41.01353],"type":"Point"}
}