{
  "type": "Feature",
  "properties": {
    "gn:admin1_code":"18.0",
    "gn:admin2_code":"PG",
    "gn:admin3_code":"54023.0",
    "gn:asciiname":"Palazzo Mancinelli-Vaccara",
    "gn:country_code":"IT",
    "gn:dem":438,
    "gn:feature_class":"P",
    "gn:feature_code":"PPL",
    "gn:name":"Palazzo Mancinelli-Vaccara",
    "gn:population":718,
    "gn:timezone":"Europe/Rome",
    "iso:country":"IT",
    "wof:name":"Palazzo Mancinelli-Vaccara",
    "wof:placetype":"locality",
    "wof:population":718
},
  "geometry": {"coordinates":[12.76281,43.25899999999999],"type":"Point"}
}