{
  "type": "Feature",
  "properties": {
    "gn:admin1_code":"20",
    "gn:admin2_code":"RO",
    "gn:admin3_code":"29013.0",
    "gn:asciiname":"Case Arella",
    "gn:country_code":"IT",
    "gn:dem":7,
    "gn:feature_class":"P",
    "gn:feature_code":"PPL",
    "gn:name":"Case Arella",
    "gn:population":25,
    "gn:timezone":"Europe/Rome",
    "iso:country":"IT",
    "wof:name":"Case Arella",
    "wof:placetype":"locality",
    "wof:population":25
},
  "geometry": {"coordinates":[11.27805,45.07643],"type":"Point"}
}