{
  "type": "Feature",
  "properties": {
    "gn:admin1_code":"20.0",
    "gn:admin2_code":"VR",
    "gn:admin3_code":"23078.0",
    "gn:asciiname":"Fosse",
    "gn:country_code":"IT",
    "gn:dem":933,
    "gn:feature_class":"P",
    "gn:feature_code":"PPL",
    "gn:name":"Fosse",
    "gn:population":346,
    "gn:timezone":"Europe/Rome",
    "iso:country":"IT",
    "wof:name":"Fosse",
    "wof:placetype":"locality",
    "wof:population":346
},
  "geometry": {"coordinates":[10.93788,45.64545],"type":"Point"}
}