{
  "type": "Feature",
  "properties": {
    "gn:admin1_code":"20.0",
    "gn:admin2_code":"VR",
    "gn:admin3_code":"23078.0",
    "gn:asciiname":"Fosse",
    "gn:country_code":"IT",
    "gn:dem":933,
    "gn:feature_class":"P",
    "gn:feature_code":"PPL",
    "gn:name":"Fosse",
    "gn:population":346,
    "gn:timezone":"Europe/Rome",
    "iso:country":"IT",
    "name:ceb_x_preferred":[
        "Fosse"
    ],
    "name:deu_x_preferred":[
        "Fosse"
    ],
    "name:fra_x_preferred":[
        "Fosse"
    ],
    "name:heb_x_preferred":[
        "\u05e4\u05d5\u05e1\u05d9"
    ],
    "name:ita_x_preferred":[
        "Fosse"
    ],
    "name:nds_x_preferred":[
        "Fosse"
    ],
    "name:nld_x_preferred":[
        "Fosse"
    ],
    "name:nor_x_preferred":[
        "Fosse"
    ],
    "name:rus_x_preferred":[
        "\u0424\u043e\u0441\u0441"
    ],
    "name:srp_x_preferred":[
        "Fosse"
    ],
    "name:swe_x_preferred":[
        "Fosse"
    ],
    "name:ukr_x_preferred":[
        "\u0424\u043e\u0441\u0441"
    ],
    "name:wln_x_preferred":[
        "Fosse"
    ],
    "wof:name":"Fosse",
    "wof:placetype":"locality",
    "wof:population":346
},
  "geometry": {"coordinates":[10.93788,45.64545],"type":"Point"}
}