{
  "type": "Feature",
  "properties": {
    "gn:admin1_code":"9",
    "gn:admin2_code":"LC",
    "gn:admin3_code":"97052.0",
    "gn:asciiname":"Piudizzo",
    "gn:country_code":"IT",
    "gn:dem":480,
    "gn:feature_class":"P",
    "gn:feature_code":"PPL",
    "gn:name":"Piudizzo",
    "gn:population":46,
    "gn:timezone":"Europe/Rome",
    "iso:country":"IT",
    "wof:name":"Piudizzo",
    "wof:placetype":"locality",
    "wof:population":46
},
  "geometry": {"coordinates":[9.46218,45.76811],"type":"Point"}
}