{
  "type": "Feature",
  "properties": {
    "gn:admin1_code":"9",
    "gn:admin2_code":"BG",
    "gn:admin3_code":"16188.0",
    "gn:asciiname":"Oneta",
    "gn:country_code":"IT",
    "gn:dem":473,
    "gn:feature_class":"P",
    "gn:feature_code":"PPL",
    "gn:name":"Oneta",
    "gn:population":62,
    "gn:timezone":"Europe/Rome",
    "iso:country":"IT",
    "name:ast_x_preferred":[
        "Oneta"
    ],
    "name:ceb_x_preferred":[
        "Oneta"
    ],
    "name:spa_x_preferred":[
        "Oneta"
    ],
    "name:srp_x_preferred":[
        "Oneta"
    ],
    "name:swe_x_preferred":[
        "Oneta"
    ],
    "name:vol_x_preferred":[
        "Oneta"
    ],
    "wof:name":"Oneta",
    "wof:placetype":"locality",
    "wof:population":62
},
  "geometry": {"coordinates":[9.65053,45.88257],"type":"Point"}
}