{
  "type": "Feature",
  "properties": {
    "gn:admin1_code":"5.0",
    "gn:admin2_code":"BO",
    "gn:admin3_code":"37041.0",
    "gn:asciiname":"Fornace",
    "gn:country_code":"IT",
    "gn:dem":173,
    "gn:feature_class":"P",
    "gn:feature_code":"PPL",
    "gn:name":"Fornace",
    "gn:population":37,
    "gn:timezone":"Europe/Rome",
    "iso:country":"IT",
    "wof:name":"Fornace",
    "wof:placetype":"locality",
    "wof:population":37
},
  "geometry": {"coordinates":[11.47962,44.31783],"type":"Point"}
}