{
  "type": "Feature",
  "properties": {
    "gn:admin1_code":"12",
    "gn:admin2_code":"CN",
    "gn:admin3_code":"4082.0",
    "gn:asciiname":"Borgetto",
    "gn:country_code":"IT",
    "gn:dem":678,
    "gn:feature_class":"P",
    "gn:feature_code":"PPL",
    "gn:name":"Borgetto",
    "gn:population":67,
    "gn:timezone":"Europe/Rome",
    "iso:country":"IT",
    "name:ara_x_preferred":[
        "\u0628\u0648\u0631\u063a\u064a\u062a\u0648"
    ],
    "name:azb_x_preferred":[
        "\u0628\u0648\u0631\u0642\u062a\u0648"
    ],
    "name:bul_x_preferred":[
        "\u0411\u043e\u0440\u0434\u0436\u0435\u0442\u043e"
    ],
    "name:cat_x_preferred":[
        "Borgetto"
    ],
    "name:ceb_x_preferred":[
        "Borgetto"
    ],
    "name:deu_x_preferred":[
        "Borgetto"
    ],
    "name:epo_x_preferred":[
        "Borgetto"
    ],
    "name:eus_x_preferred":[
        "Borgetto"
    ],
    "name:fas_x_preferred":[
        "\u0628\u0648\u0631\u06af\u062a\u0648"
    ],
    "name:fra_x_preferred":[
        "Borgetto"
    ],
    "name:hun_x_preferred":[
        "Borgetto"
    ],
    "name:hye_x_preferred":[
        "\u0532\u0578\u0580\u057b\u0565\u057f\u0578"
    ],
    "name:ita_x_preferred":[
        "Borgetto"
    ],
    "name:jpn_x_preferred":[
        "\u30dc\u30eb\u30b8\u30a7\u30c3\u30c8"
    ],
    "name:kaz_x_preferred":[
        "\u0411\u043e\u0440\u0434\u0436\u0435\u0442\u0442\u043e"
    ],
    "name:lat_x_preferred":[
        "Burgettum"
    ],
    "name:lmo_x_preferred":[
        "Borgetto"
    ],
    "name:msa_x_preferred":[
        "Borgetto"
    ],
    "name:nap_x_preferred":[
        "Borgetto"
    ],
    "name:nld_x_preferred":[
        "Borgetto"
    ],
    "name:pms_x_preferred":[
        "Borgetto"
    ],
    "name:pol_x_preferred":[
        "Borgetto"
    ],
    "name:por_x_preferred":[
        "Borgetto"
    ],
    "name:ron_x_preferred":[
        "Borgetto"
    ],
    "name:rus_x_preferred":[
        "\u0411\u043e\u0440\u0434\u0436\u0435\u0442\u0442\u043e"
    ],
    "name:scn_x_preferred":[
        "Lu Burgettu"
    ],
    "name:sco_x_preferred":[
        "Borgetto"
    ],
    "name:spa_x_preferred":[
        "Borgetto"
    ],
    "name:srd_x_preferred":[
        "Borgetto"
    ],
    "name:srp_x_preferred":[
        "\u0411\u043e\u0440\u0433\u0435\u0442\u043e"
    ],
    "name:tgl_x_preferred":[
        "Borgetto"
    ],
    "name:ukr_x_preferred":[
        "\u0411\u043e\u0440\u0434\u0436\u0435\u0442\u0442\u043e"
    ],
    "name:uzb_x_preferred":[
        "Borgetto"
    ],
    "name:vol_x_preferred":[
        "Borgetto"
    ],
    "name:war_x_preferred":[
        "Borgetto"
    ],
    "name:zho_x_preferred":[
        "\u535a\u5c14\u6770\u6258"
    ],
    "wof:name":"Borgetto",
    "wof:placetype":"locality",
    "wof:population":67
},
  "geometry": {"coordinates":[7.30755,44.46654],"type":"Point"}
}