{
  "type": "Feature",
  "properties": {
    "gn:admin1_code":"12",
    "gn:admin2_code":"CN",
    "gn:admin3_code":"4082.0",
    "gn:asciiname":"Borgetto",
    "gn:country_code":"IT",
    "gn:dem":678,
    "gn:feature_class":"P",
    "gn:feature_code":"PPL",
    "gn:name":"Borgetto",
    "gn:population":67,
    "gn:timezone":"Europe/Rome",
    "iso:country":"IT",
    "wof:name":"Borgetto",
    "wof:placetype":"locality",
    "wof:population":67
},
  "geometry": {"coordinates":[7.30755,44.46654],"type":"Point"}
}