{
  "type": "Feature",
  "properties": {
    "gn:admin1_code":"17",
    "gn:admin2_code":"TN",
    "gn:admin3_code":"22087.0",
    "gn:asciiname":"San Sebastiano",
    "gn:country_code":"IT",
    "gn:dem":1286,
    "gn:feature_class":"P",
    "gn:feature_code":"PPL",
    "gn:name":"San Sebastiano",
    "gn:population":228,
    "gn:timezone":"Europe/Rome",
    "iso:country":"IT",
    "wof:name":"San Sebastiano",
    "wof:placetype":"locality",
    "wof:population":228
},
  "geometry": {"coordinates":[11.21352,45.92516],"type":"Point"}
}