{
  "type": "Feature",
  "properties": {
    "iso:country":"IT",
    "name:deu_x_preferred":[
        "Pogerola"
    ],
    "name:eng_x_preferred":[
        "Pogerola"
    ],
    "name:ita_x_preferred":[
        "Pogerola"
    ],
    "qs_pg:aaroncc":"IT",
    "qs_pg:name":"Pogerola",
    "qs_pg:name_adm0":"Italia",
    "qs_pg:name_adm1":"Campania",
    "qs_pg:photos":36,
    "qs_pg:photos_1k":7,
    "qs_pg:photos_9k":1,
    "qs_pg:photos_9r":2,
    "qs_pg:photos_all":36,
    "qs_pg:photos_sr":2,
    "qs_pg:pop_sr":0,
    "qs_pg:qs_pg_placetype":"locality",
    "qs_pg:qs_pg_placetype_gp":"Town",
    "qs_pg:woe_adm0":23424853,
    "woe:adm0_id":23424853,
    "woe:name_adm0":"Italia",
    "woe:name_adm1":"Campania",
    "woe:placetype":"Town",
    "wof:name":"Pogerola",
    "wof:placetype":"locality"
},
  "geometry": {"coordinates":[14.5928095,40.637429],"type":"Point"}
}