{
  "type": "Feature",
  "properties": {
    "gn:admin1_code":"7",
    "gn:admin2_code":"RI",
    "gn:admin3_code":"57009.0",
    "gn:asciiname":"Lasca",
    "gn:country_code":"IT",
    "gn:dem":483,
    "gn:feature_class":"P",
    "gn:feature_code":"PPL",
    "gn:name":"Lasca",
    "gn:population":220,
    "gn:timezone":"Europe/Rome",
    "iso:country":"IT",
    "name:deu_x_preferred":[
        "Laska"
    ],
    "name:fin_x_preferred":[
        "Lasca"
    ],
    "name:nld_x_preferred":[
        "Laska"
    ],
    "name:pol_x_preferred":[
        "Laska"
    ],
    "name:rus_x_preferred":[
        "\u041b\u0430\u0441\u043a\u0430"
    ],
    "name:spa_x_preferred":[
        "Lasca"
    ],
    "name:zho_x_preferred":[
        "\u62c9\u65af\u514b\u758a\u8df3\u68cb"
    ],
    "wof:name":"Lasca",
    "wof:placetype":"locality",
    "wof:population":220
},
  "geometry": {"coordinates":[12.87806,42.46345],"type":"Point"}
}