{
  "type": "Feature",
  "properties": {
    "gn:admin1_code":"10.0",
    "gn:admin2_code":"MC",
    "gn:admin3_code":"43025.0",
    "gn:asciiname":"Bagliano",
    "gn:country_code":"IT",
    "gn:dem":217,
    "gn:feature_class":"P",
    "gn:feature_code":"PPL",
    "gn:name":"Bagliano",
    "gn:population":57,
    "gn:timezone":"Europe/Rome",
    "iso:country":"IT",
    "wof:name":"Bagliano",
    "wof:placetype":"locality",
    "wof:population":57
},
  "geometry": {"coordinates":[13.48352,43.17575],"type":"Point"}
}