{
  "type": "Feature",
  "properties": {
    "gn:admin1_code":"4",
    "gn:admin2_code":"CE",
    "gn:admin3_code":"61083.0",
    "gn:asciiname":"Istituto Penitenziario N.C.C.",
    "gn:country_code":"IT",
    "gn:dem":19,
    "gn:feature_class":"P",
    "gn:feature_code":"PPL",
    "gn:name":"Istituto Penitenziario N.C.C.",
    "gn:population":292,
    "gn:timezone":"Europe/Rome",
    "iso:country":"IT",
    "wof:name":"Istituto Penitenziario N.C.C.",
    "wof:placetype":"locality",
    "wof:population":292
},
  "geometry": {"coordinates":[14.23754,41.0449],"type":"Point"}
}