{
  "type": "Feature",
  "properties": {
    "gn:admin1_code":"12",
    "gn:admin2_code":"TO",
    "gn:admin3_code":"1113.0",
    "gn:asciiname":"Borgo",
    "gn:country_code":"IT",
    "gn:dem":613,
    "gn:feature_class":"P",
    "gn:feature_code":"PPL",
    "gn:name":"Borgo",
    "gn:population":19,
    "gn:timezone":"Europe/Rome",
    "iso:country":"IT",
    "wof:name":"Borgo",
    "wof:placetype":"locality",
    "wof:population":19
},
  "geometry": {"coordinates":[7.43603,45.23967],"type":"Point"}
}