{
  "type": "Feature",
  "properties": {
    "gn:admin1_code":"12",
    "gn:admin2_code":"TO",
    "gn:admin3_code":"1113.0",
    "gn:asciiname":"Borgo",
    "gn:country_code":"IT",
    "gn:dem":613,
    "gn:feature_class":"P",
    "gn:feature_code":"PPL",
    "gn:name":"Borgo",
    "gn:population":19,
    "gn:timezone":"Europe/Rome",
    "iso:country":"IT",
    "name:ceb_x_preferred":[
        "Borgo"
    ],
    "name:deu_x_preferred":[
        "Borgo"
    ],
    "name:fra_x_preferred":[
        "Borgo"
    ],
    "name:heb_x_preferred":[
        "\u05d1\u05d5\u05e8\u05d2\u05d5"
    ],
    "name:hun_x_preferred":[
        "Borgo"
    ],
    "name:ita_x_preferred":[
        "Borgo"
    ],
    "name:nld_x_preferred":[
        "Borgo"
    ],
    "name:nor_x_preferred":[
        "Borgo"
    ],
    "name:pol_x_preferred":[
        "Borgo"
    ],
    "name:por_x_preferred":[
        "Borgo"
    ],
    "name:rus_x_preferred":[
        "\u0411\u043e\u0440\u0433\u043e"
    ],
    "name:sco_x_preferred":[
        "Borgo"
    ],
    "name:slk_x_preferred":[
        "Borgo"
    ],
    "name:srp_x_preferred":[
        "Borgo"
    ],
    "name:swe_x_preferred":[
        "Borgo"
    ],
    "wof:name":"Borgo",
    "wof:placetype":"locality",
    "wof:population":19
},
  "geometry": {"coordinates":[7.43603,45.23967],"type":"Point"}
}