{
  "type": "Feature",
  "properties": {
    "gn:admin1_code":"15",
    "gn:admin2_code":"PA",
    "gn:admin3_code":"82048.0",
    "gn:asciiname":"Montagna Grande",
    "gn:country_code":"IT",
    "gn:dem":280,
    "gn:feature_class":"P",
    "gn:feature_code":"PPL",
    "gn:name":"Montagna Grande",
    "gn:population":64,
    "gn:timezone":"Europe/Rome",
    "iso:country":"IT",
    "wof:name":"Montagna Grande",
    "wof:placetype":"locality",
    "wof:population":64
},
  "geometry": {"coordinates":[13.44865,38.04647],"type":"Point"}
}