{
  "type": "Feature",
  "properties": {
    "gn:admin1_code":"9",
    "gn:admin2_code":"CO",
    "gn:admin3_code":"13227.0",
    "gn:asciiname":"Cascina Piatti",
    "gn:country_code":"IT",
    "gn:dem":259,
    "gn:feature_class":"P",
    "gn:feature_code":"PPL",
    "gn:name":"Cascina Piatti",
    "gn:population":88,
    "gn:timezone":"Europe/Rome",
    "iso:country":"IT",
    "wof:name":"Cascina Piatti",
    "wof:placetype":"locality",
    "wof:population":88
},
  "geometry": {"coordinates":[8.99724,45.67342],"type":"Point"}
}