{
  "type": "Feature",
  "properties": {
    "gn:admin1_code":"4",
    "gn:admin2_code":"AV",
    "gn:admin3_code":"64005.0",
    "gn:asciiname":"Ficucelle",
    "gn:country_code":"IT",
    "gn:dem":590,
    "gn:feature_class":"P",
    "gn:feature_code":"PPL",
    "gn:name":"Ficucelle",
    "gn:population":32,
    "gn:timezone":"Europe/Rome",
    "iso:country":"IT",
    "wof:name":"Ficucelle",
    "wof:placetype":"locality",
    "wof:population":32
},
  "geometry": {"coordinates":[15.08031,41.18541],"type":"Point"}
}