{
  "type": "Feature",
  "properties": {
    "gn:admin1_code":"9",
    "gn:admin2_code":"PV",
    "gn:admin3_code":"18089.0",
    "gn:asciiname":"Vigomarito",
    "gn:country_code":"IT",
    "gn:dem":728,
    "gn:feature_class":"P",
    "gn:feature_code":"PPL",
    "gn:name":"Vigomarito",
    "gn:population":18,
    "gn:timezone":"Europe/Rome",
    "iso:country":"IT",
    "wof:name":"Vigomarito",
    "wof:placetype":"locality",
    "wof:population":18
},
  "geometry": {"coordinates":[9.27802,44.8025],"type":"Point"}
}