{
  "type": "Feature",
  "properties": {
    "gn:admin1_code":"20",
    "gn:admin2_code":"TV",
    "gn:admin3_code":"26064.0",
    "gn:asciiname":"Toscan",
    "gn:country_code":"IT",
    "gn:dem":18,
    "gn:feature_class":"P",
    "gn:feature_code":"PPL",
    "gn:name":"Toscan",
    "gn:population":27,
    "gn:timezone":"Europe/Rome",
    "iso:country":"IT",
    "wof:name":"Toscan",
    "wof:placetype":"locality",
    "wof:population":27
},
  "geometry": {"coordinates":[12.1461,45.65083],"type":"Point"}
}