{
  "type": "Feature",
  "properties": {
    "gn:admin1_code":"4",
    "gn:admin2_code":"SA",
    "gn:admin3_code":"65050.0",
    "gn:asciiname":"Torre dei Rai",
    "gn:country_code":"IT",
    "gn:dem":46,
    "gn:feature_class":"P",
    "gn:feature_code":"PPL",
    "gn:name":"Torre dei Rai",
    "gn:population":79,
    "gn:timezone":"Europe/Rome",
    "iso:country":"IT",
    "wof:name":"Torre dei Rai",
    "wof:placetype":"locality",
    "wof:population":79
},
  "geometry": {"coordinates":[14.98996,40.58487],"type":"Point"}
}