{
  "type": "Feature",
  "properties": {
    "gn:admin1_code":"12",
    "gn:admin2_code":"TO",
    "gn:admin3_code":"1075.0",
    "gn:asciiname":"Gabbi",
    "gn:country_code":"IT",
    "gn:dem":844,
    "gn:feature_class":"P",
    "gn:feature_code":"PPL",
    "gn:name":"Gabbi",
    "gn:population":28,
    "gn:timezone":"Europe/Rome",
    "iso:country":"IT",
    "wof:name":"Gabbi",
    "wof:placetype":"locality",
    "wof:population":28
},
  "geometry": {"coordinates":[7.35104,45.35735],"type":"Point"}
}