{
  "type": "Feature",
  "properties": {
    "gn:admin1_code":"16",
    "gn:admin2_code":"FI",
    "gn:admin3_code":"48027.0",
    "gn:asciiname":"Palagio",
    "gn:country_code":"IT",
    "gn:dem":333,
    "gn:feature_class":"P",
    "gn:feature_code":"PPL",
    "gn:name":"Palagio",
    "gn:population":25,
    "gn:timezone":"Europe/Rome",
    "iso:country":"IT",
    "wof:name":"Palagio",
    "wof:placetype":"locality",
    "wof:population":25
},
  "geometry": {"coordinates":[10.88163,43.49751],"type":"Point"}
}