{
  "type": "Feature",
  "properties": {
    "gn:admin1_code":"20",
    "gn:admin2_code":"VE",
    "gn:admin3_code":"27029.0",
    "gn:asciiname":"Gardissere",
    "gn:country_code":"IT",
    "gn:dem":-1,
    "gn:feature_class":"P",
    "gn:feature_code":"PPL",
    "gn:name":"Gardissere",
    "gn:population":31,
    "gn:timezone":"Europe/Rome",
    "iso:country":"IT",
    "wof:name":"Gardissere",
    "wof:placetype":"locality",
    "wof:population":31
},
  "geometry": {"coordinates":[12.8729,45.75129],"type":"Point"}
}