{
  "type": "Feature",
  "properties": {
    "gn:admin1_code":"5",
    "gn:admin2_code":"BO",
    "gn:admin3_code":"37022.0",
    "gn:asciiname":"Ca di Fabbiani",
    "gn:country_code":"IT",
    "gn:dem":555,
    "gn:feature_class":"P",
    "gn:feature_code":"PPL",
    "gn:name":"C\u00e0 di Fabbiani",
    "gn:population":15,
    "gn:timezone":"Europe/Rome",
    "iso:country":"IT",
    "name:und_x_variant":[
        "C\u00e0 di Fabbiani"
    ],
    "wof:name":"Ca di Fabbiani",
    "wof:placetype":"locality",
    "wof:population":15
},
  "geometry": {"coordinates":[11.22475,44.11943],"type":"Point"}
}