{
  "type": "Feature",
  "properties": {
    "gn:admin1_code":"3",
    "gn:admin2_code":"CS",
    "gn:admin3_code":"78029.0",
    "gn:asciiname":"Olmo Torto",
    "gn:country_code":"IT",
    "gn:dem":9,
    "gn:feature_class":"P",
    "gn:feature_code":"PPL",
    "gn:name":"Olmo Torto",
    "gn:population":16,
    "gn:timezone":"Europe/Rome",
    "iso:country":"IT",
    "wof:name":"Olmo Torto",
    "wof:placetype":"locality",
    "wof:population":16
},
  "geometry": {"coordinates":[16.42433,39.72585],"type":"Point"}
}