{
  "type": "Feature",
  "properties": {
    "gn:admin1_code":"16",
    "gn:admin2_code":"MS",
    "gn:admin3_code":"45006.0",
    "gn:asciiname":"Canale",
    "gn:country_code":"IT",
    "gn:dem":216,
    "gn:feature_class":"P",
    "gn:feature_code":"PPL",
    "gn:name":"Canale",
    "gn:population":98,
    "gn:timezone":"Europe/Rome",
    "iso:country":"IT",
    "wof:name":"Canale",
    "wof:placetype":"locality",
    "wof:population":98
},
  "geometry": {"coordinates":[9.91864,44.35057000000001],"type":"Point"}
}