{
  "type": "Feature",
  "properties": {
    "gn:admin1_code":"16.0",
    "gn:admin2_code":"SI",
    "gn:admin3_code":"52019.0",
    "gn:asciiname":"Miniera di Murlo",
    "gn:country_code":"IT",
    "gn:dem":206,
    "gn:feature_class":"P",
    "gn:feature_code":"PPL",
    "gn:name":"Miniera di Murlo",
    "gn:population":33,
    "gn:timezone":"Europe/Rome",
    "iso:country":"IT",
    "wof:name":"Miniera di Murlo",
    "wof:placetype":"locality",
    "wof:population":33
},
  "geometry": {"coordinates":[11.38081,43.14858],"type":"Point"}
}