{
  "type": "Feature",
  "properties": {
    "gn:admin1_code":"16",
    "gn:admin2_code":"LI",
    "gn:admin3_code":"49017.0",
    "gn:asciiname":"Polveroni",
    "gn:country_code":"IT",
    "gn:dem":10,
    "gn:feature_class":"P",
    "gn:feature_code":"PPL",
    "gn:name":"Polveroni",
    "gn:population":306,
    "gn:timezone":"Europe/Rome",
    "iso:country":"IT",
    "wof:name":"Polveroni",
    "wof:placetype":"locality",
    "wof:population":306
},
  "geometry": {"coordinates":[10.46159,43.37086],"type":"Point"}
}