{
  "type": "Feature",
  "properties": {
    "gn:admin1_code":"1",
    "gn:admin2_code":"AQ",
    "gn:admin3_code":"66098.0",
    "gn:asciiname":"Tratturo II",
    "gn:country_code":"IT",
    "gn:dem":389,
    "gn:feature_class":"P",
    "gn:feature_code":"PPL",
    "gn:name":"Tratturo II",
    "gn:population":39,
    "gn:timezone":"Europe/Rome",
    "iso:country":"IT",
    "wof:name":"Tratturo II",
    "wof:placetype":"locality",
    "wof:population":39
},
  "geometry": {"coordinates":[13.89913,42.05524000000001],"type":"Point"}
}