{
  "type": "Feature",
  "properties": {
    "gn:admin1_code":"5.0",
    "gn:admin2_code":"RN",
    "gn:admin3_code":"99017.0",
    "gn:asciiname":"Villaggio Fontemaggi",
    "gn:country_code":"IT",
    "gn:dem":15,
    "gn:feature_class":"P",
    "gn:feature_code":"PPL",
    "gn:name":"Villaggio Fontemaggi",
    "gn:population":488,
    "gn:timezone":"Europe/Rome",
    "iso:country":"IT",
    "wof:name":"Villaggio Fontemaggi",
    "wof:placetype":"locality",
    "wof:population":488
},
  "geometry": {"coordinates":[12.72508,43.96083],"type":"Point"}
}