{
  "type": "Feature",
  "properties": {
    "gn:admin1_code":"5",
    "gn:admin2_code":"PR",
    "gn:admin3_code":"34017.0",
    "gn:asciiname":"Neviano De' Rossi",
    "gn:country_code":"IT",
    "gn:dem":401,
    "gn:feature_class":"P",
    "gn:feature_code":"PPL",
    "gn:name":"Neviano De' Rossi",
    "gn:population":16,
    "gn:timezone":"Europe/Rome",
    "iso:country":"IT",
    "wof:name":"Neviano De' Rossi",
    "wof:placetype":"locality",
    "wof:population":16
},
  "geometry": {"coordinates":[10.15833,44.66615],"type":"Point"}
}