{
  "type": "Feature",
  "properties": {
    "gn:admin1_code":"3",
    "gn:admin2_code":"VV",
    "gn:admin3_code":"102014.0",
    "gn:asciiname":"Carcarella",
    "gn:country_code":"IT",
    "gn:dem":34,
    "gn:feature_class":"P",
    "gn:feature_code":"PPL",
    "gn:name":"Carcarella",
    "gn:population":17,
    "gn:timezone":"Europe/Rome",
    "iso:country":"IT",
    "name:nap_x_preferred":[
        "Carcarella"
    ],
    "name:srp_x_preferred":[
        "\u041a\u0430\u0440\u043a\u0430\u0440\u0435\u043b\u0430"
    ],
    "wof:name":"Carcarella",
    "wof:placetype":"locality",
    "wof:population":17
},
  "geometry": {"coordinates":[16.22031,38.78364000000001],"type":"Point"}
}