{
  "type": "Feature",
  "properties": {
    "gn:admin1_code":"8.0",
    "gn:admin2_code":"SV",
    "gn:admin3_code":"9023.0",
    "gn:asciiname":"Pianrocchetta",
    "gn:country_code":"IT",
    "gn:dem":404,
    "gn:feature_class":"P",
    "gn:feature_code":"PPLL",
    "gn:name":"Pianrocchetta",
    "gn:population":0,
    "gn:timezone":"Europe/Rome",
    "iso:country":"IT",
    "wof:name":"Pianrocchetta",
    "wof:placetype":"locality"
},
  "geometry": {"coordinates":[8.17991,44.39737],"type":"Point"}
}