{
  "type": "Feature",
  "properties": {
    "gn:admin1_code":"7",
    "gn:admin2_code":"FR",
    "gn:admin3_code":"60033.0",
    "gn:asciiname":"Monte Trave",
    "gn:country_code":"IT",
    "gn:dem":217,
    "gn:feature_class":"P",
    "gn:feature_code":"PPL",
    "gn:name":"Monte Trave",
    "gn:population":77,
    "gn:timezone":"Europe/Rome",
    "iso:country":"IT",
    "wof:name":"Monte Trave",
    "wof:placetype":"locality",
    "wof:population":77
},
  "geometry": {"coordinates":[13.21645,41.66593],"type":"Point"}
}