{
  "type": "Feature",
  "properties": {
    "gn:admin1_code":"3.0",
    "gn:admin2_code":"CZ",
    "gn:admin3_code":"79160.0",
    "gn:asciiname":"Acquafredda",
    "gn:country_code":"IT",
    "gn:dem":861,
    "gn:elevation":"860.0",
    "gn:feature_class":"P",
    "gn:feature_code":"PPL",
    "gn:name":"Acquafredda",
    "gn:population":437,
    "gn:timezone":"Europe/Rome",
    "iso:country":"IT",
    "wof:name":"Acquafredda",
    "wof:placetype":"locality",
    "wof:population":437
},
  "geometry": {"coordinates":[16.24012,38.98999],"type":"Point"}
}