{
  "type": "Feature",
  "properties": {
    "gn:admin1_code":"3.0",
    "gn:admin2_code":"CZ",
    "gn:admin3_code":"79160.0",
    "gn:asciiname":"Acquafredda",
    "gn:country_code":"IT",
    "gn:dem":861,
    "gn:elevation":"860.0",
    "gn:feature_class":"P",
    "gn:feature_code":"PPL",
    "gn:name":"Acquafredda",
    "gn:population":437,
    "gn:timezone":"Europe/Rome",
    "iso:country":"IT",
    "name:azb_x_preferred":[
        "\u0627\u06a9\u0648\u0627\u0641\u0631\u062f\u0627"
    ],
    "name:bel_x_preferred":[
        "\u0410\u043a\u0443\u0430\u0444\u0440\u044d\u0434\u0430"
    ],
    "name:bul_x_preferred":[
        "\u0410\u043a\u0443\u0430\u0444\u0440\u0435\u0434\u0430"
    ],
    "name:cat_x_preferred":[
        "Acquafredda"
    ],
    "name:ceb_x_preferred":[
        "Acquafredda"
    ],
    "name:deu_x_preferred":[
        "Acquafredda"
    ],
    "name:epo_x_preferred":[
        "Acquafredda"
    ],
    "name:eus_x_preferred":[
        "Acquafredda"
    ],
    "name:fas_x_preferred":[
        "\u0627\u06a9\u0648\u0627\u0641\u0631\u062f\u0627"
    ],
    "name:fra_x_preferred":[
        "Acquafredda"
    ],
    "name:hun_x_preferred":[
        "Acquafredda"
    ],
    "name:hye_x_preferred":[
        "\u0531\u056f\u057e\u0561\u0586\u0580\u0565\u0564\u0564\u0561"
    ],
    "name:ina_x_preferred":[
        "Acquafredda"
    ],
    "name:ind_x_preferred":[
        "Acquafredda"
    ],
    "name:ita_x_preferred":[
        "Acquafredda"
    ],
    "name:jpn_x_preferred":[
        "\u30a2\u30c3\u30af\u30a2\u30d5\u30ec\u30c3\u30c0"
    ],
    "name:kaz_x_preferred":[
        "\u0410\u043a\u043a\u0443\u0430\u0444\u0440\u0435\u0434\u0434\u0430"
    ],
    "name:lat_x_preferred":[
        "Aquafrigida"
    ],
    "name:lmo_x_preferred":[
        "Aquafr\u00e8da"
    ],
    "name:msa_x_preferred":[
        "Acquafredda"
    ],
    "name:nap_x_preferred":[
        "Acquafredda"
    ],
    "name:nld_x_preferred":[
        "Acquafredda"
    ],
    "name:pms_x_preferred":[
        "Acquafredda"
    ],
    "name:pol_x_preferred":[
        "Acquafredda"
    ],
    "name:por_x_preferred":[
        "Acquafredda"
    ],
    "name:ron_x_preferred":[
        "Acquafredda"
    ],
    "name:rus_x_preferred":[
        "\u0410\u043a\u043a\u0443\u0430\u0444\u0440\u0435\u0434\u0434\u0430"
    ],
    "name:scn_x_preferred":[
        "Acquafredda"
    ],
    "name:spa_x_preferred":[
        "Acquafredda"
    ],
    "name:srp_x_preferred":[
        "\u0410\u043a\u0432\u0430\u0444\u0440\u0435\u0434\u0430"
    ],
    "name:tgl_x_preferred":[
        "Acquafredda"
    ],
    "name:ukr_x_preferred":[
        "\u0410\u043a\u043a\u0443\u0430\u0444\u0440\u0435\u0434\u0434\u0430"
    ],
    "name:uzb_x_preferred":[
        "Acquafredda"
    ],
    "name:vec_x_preferred":[
        "Aquafreda"
    ],
    "name:vie_x_preferred":[
        "Acquafredda"
    ],
    "name:vol_x_preferred":[
        "Acquafredda"
    ],
    "name:war_x_preferred":[
        "Acquafredda"
    ],
    "name:zho_x_preferred":[
        "\u963f\u5938\u592b\u96f7\u8fbe"
    ],
    "wof:name":"Acquafredda",
    "wof:placetype":"locality",
    "wof:population":437
},
  "geometry": {"coordinates":[16.24012,38.98999],"type":"Point"}
}