{
  "type": "Feature",
  "properties": {
    "gn:admin1_code":"5",
    "gn:admin2_code":"BO",
    "gn:admin3_code":"37015.0",
    "gn:asciiname":"Marzolara",
    "gn:country_code":"IT",
    "gn:dem":736,
    "gn:feature_class":"P",
    "gn:feature_code":"PPL",
    "gn:name":"Marzolara",
    "gn:population":29,
    "gn:timezone":"Europe/Rome",
    "iso:country":"IT",
    "wof:name":"Marzolara",
    "wof:placetype":"locality",
    "wof:population":29
},
  "geometry": {"coordinates":[11.02581,44.17313],"type":"Point"}
}