{
  "type": "Feature",
  "properties": {
    "gn:admin1_code":"20",
    "gn:admin2_code":"VI",
    "gn:admin3_code":"24106.0",
    "gn:asciiname":"Via",
    "gn:country_code":"IT",
    "gn:dem":1043,
    "gn:feature_class":"P",
    "gn:feature_code":"PPL",
    "gn:name":"Via",
    "gn:population":75,
    "gn:timezone":"Europe/Rome",
    "iso:country":"IT",
    "name:fin_x_preferred":[
        "Via"
    ],
    "name:nld_x_preferred":[
        "Via"
    ],
    "name:swe_x_preferred":[
        "Via"
    ],
    "wof:name":"Via",
    "wof:placetype":"locality",
    "wof:population":75
},
  "geometry": {"coordinates":[11.34073,45.86175],"type":"Point"}
}