{
  "type": "Feature",
  "properties": {
    "gn:admin1_code":"17",
    "gn:admin2_code":"TN",
    "gn:admin3_code":"22009.0",
    "gn:asciiname":"Valt",
    "gn:country_code":"IT",
    "gn:dem":950,
    "gn:feature_class":"P",
    "gn:feature_code":"PPL",
    "gn:name":"Valt",
    "gn:population":180,
    "gn:timezone":"Europe/Rome",
    "iso:country":"IT",
    "wof:name":"Valt",
    "wof:placetype":"locality",
    "wof:population":180
},
  "geometry": {"coordinates":[11.23674,46.10682],"type":"Point"}
}