{
  "type": "Feature",
  "properties": {
    "gn:admin1_code":"14",
    "gn:admin2_code":"SS",
    "gn:admin3_code":"90074.0",
    "gn:asciiname":"Paduledda",
    "gn:country_code":"IT",
    "gn:dem":194,
    "gn:feature_class":"P",
    "gn:feature_code":"PPL",
    "gn:name":"Paduledda",
    "gn:population":204,
    "gn:timezone":"Europe/Rome",
    "iso:country":"IT",
    "wof:name":"Paduledda",
    "wof:placetype":"locality",
    "wof:population":204
},
  "geometry": {"coordinates":[8.89711,40.99907],"type":"Point"}
}