{
  "type": "Feature",
  "properties": {
    "gn:admin1_code":"12",
    "gn:admin2_code":"TO",
    "gn:admin3_code":"1018.0",
    "gn:asciiname":"Tetti None",
    "gn:country_code":"IT",
    "gn:dem":472,
    "gn:feature_class":"P",
    "gn:feature_code":"PPL",
    "gn:name":"Tetti None",
    "gn:population":242,
    "gn:timezone":"Europe/Rome",
    "iso:country":"IT",
    "wof:name":"Tetti None",
    "wof:placetype":"locality",
    "wof:population":242
},
  "geometry": {"coordinates":[7.79622,45.08696],"type":"Point"}
}