{
  "type": "Feature",
  "properties": {
    "gn:admin1_code":"15",
    "gn:admin2_code":"CT",
    "gn:admin3_code":"87030.0",
    "gn:asciiname":"Villaggio degli Ulivi",
    "gn:country_code":"IT",
    "gn:dem":67,
    "gn:feature_class":"P",
    "gn:feature_code":"PPL",
    "gn:name":"Villaggio degli Ulivi",
    "gn:population":284,
    "gn:timezone":"Europe/Rome",
    "iso:country":"IT",
    "wof:name":"Villaggio degli Ulivi",
    "wof:placetype":"locality",
    "wof:population":284
},
  "geometry": {"coordinates":[14.96216,37.4651],"type":"Point"}
}