{
  "type": "Feature",
  "properties": {
    "gn:admin1_code":"8.0",
    "gn:admin2_code":"SV",
    "gn:admin3_code":"9064.0",
    "gn:asciiname":"Cavatrevo",
    "gn:country_code":"IT",
    "gn:dem":141,
    "gn:feature_class":"P",
    "gn:feature_code":"PPLL",
    "gn:name":"Cavatrevo",
    "gn:population":0,
    "gn:timezone":"Europe/Rome",
    "iso:country":"IT",
    "wof:name":"Cavatrevo",
    "wof:placetype":"locality"
},
  "geometry": {"coordinates":[8.40741,44.2488],"type":"Point"}
}