{
  "type": "Feature",
  "properties": {
    "gn:admin1_code":"2",
    "gn:admin2_code":"PZ",
    "gn:admin3_code":"76053.0",
    "gn:asciiname":"Casale San Giuliano",
    "gn:country_code":"IT",
    "gn:dem":781,
    "gn:feature_class":"P",
    "gn:feature_code":"PPL",
    "gn:name":"Casale San Giuliano",
    "gn:population":32,
    "gn:timezone":"Europe/Rome",
    "iso:country":"IT",
    "wof:name":"Casale San Giuliano",
    "wof:placetype":"locality",
    "wof:population":32
},
  "geometry": {"coordinates":[15.46974,40.69238],"type":"Point"}
}