{
  "type": "Feature",
  "properties": {
    "gn:admin1_code":"16",
    "gn:admin2_code":"FI",
    "gn:admin3_code":"48019.0",
    "gn:asciiname":"Tacchio",
    "gn:country_code":"IT",
    "gn:dem":54,
    "gn:feature_class":"P",
    "gn:feature_code":"PPL",
    "gn:name":"Tacchio",
    "gn:population":63,
    "gn:timezone":"Europe/Rome",
    "iso:country":"IT",
    "wof:name":"Tacchio",
    "wof:placetype":"locality",
    "wof:population":63
},
  "geometry": {"coordinates":[10.79184,43.78507000000001],"type":"Point"}
}