{
  "type": "Feature",
  "properties": {
    "gn:admin1_code":"16.0",
    "gn:admin2_code":"PT",
    "gn:admin3_code":"47007.0",
    "gn:asciiname":"Pianigioli",
    "gn:country_code":"IT",
    "gn:dem":795,
    "gn:feature_class":"P",
    "gn:feature_code":"PPLL",
    "gn:name":"Pianigioli",
    "gn:population":4,
    "gn:timezone":"Europe/Rome",
    "iso:country":"IT",
    "wof:name":"Pianigioli",
    "wof:placetype":"locality",
    "wof:population":4
},
  "geometry": {"coordinates":[10.76104,43.951],"type":"Point"}
}