{
  "type": "Feature",
  "properties": {
    "gn:admin1_code":"9",
    "gn:admin2_code":"CR",
    "gn:admin3_code":"19014.0",
    "gn:asciiname":"Cansero",
    "gn:country_code":"IT",
    "gn:dem":39,
    "gn:feature_class":"P",
    "gn:feature_code":"PPL",
    "gn:name":"Cansero",
    "gn:population":37,
    "gn:timezone":"Europe/Rome",
    "iso:country":"IT",
    "wof:name":"Cansero",
    "wof:placetype":"locality",
    "wof:population":37
},
  "geometry": {"coordinates":[10.25307,45.15142],"type":"Point"}
}