{
  "type": "Feature",
  "properties": {
    "gn:admin1_code":"20",
    "gn:admin2_code":"TV",
    "gn:admin3_code":"26086.0",
    "gn:asciiname":"Case Semenzini",
    "gn:country_code":"IT",
    "gn:dem":18,
    "gn:feature_class":"P",
    "gn:feature_code":"PPL",
    "gn:name":"Case Semenzini",
    "gn:population":16,
    "gn:timezone":"Europe/Rome",
    "iso:country":"IT",
    "wof:name":"Case Semenzini",
    "wof:placetype":"locality",
    "wof:population":16
},
  "geometry": {"coordinates":[12.19401,45.66405],"type":"Point"}
}