{
  "type": "Feature",
  "properties": {
    "gn:admin1_code":"3",
    "gn:admin2_code":"RC",
    "gn:admin3_code":"80050.0",
    "gn:asciiname":"Giachindi-Placanica",
    "gn:country_code":"IT",
    "gn:dem":151,
    "gn:feature_class":"P",
    "gn:feature_code":"PPL",
    "gn:name":"Giachindi-Placanica",
    "gn:population":22,
    "gn:timezone":"Europe/Rome",
    "iso:country":"IT",
    "wof:name":"Giachindi-Placanica",
    "wof:placetype":"locality",
    "wof:population":22
},
  "geometry": {"coordinates":[15.76287,37.94422],"type":"Point"}
}