{
  "type": "Feature",
  "properties": {
    "gn:admin1_code":"4",
    "gn:admin2_code":"SA",
    "gn:admin3_code":"65037.0",
    "gn:asciiname":"Pregiatello",
    "gn:country_code":"IT",
    "gn:dem":297,
    "gn:feature_class":"P",
    "gn:feature_code":"PPL",
    "gn:name":"Pregiatello",
    "gn:population":97,
    "gn:timezone":"Europe/Rome",
    "iso:country":"IT",
    "wof:name":"Pregiatello",
    "wof:placetype":"locality",
    "wof:population":97
},
  "geometry": {"coordinates":[14.71499,40.71148],"type":"Point"}
}