{
  "type": "Feature",
  "properties": {
    "gn:admin1_code":"9",
    "gn:admin2_code":"PV",
    "gn:admin3_code":"18171.0",
    "gn:asciiname":"Casa Ien",
    "gn:country_code":"IT",
    "gn:dem":444,
    "gn:feature_class":"P",
    "gn:feature_code":"PPL",
    "gn:name":"Casa Ien",
    "gn:population":14,
    "gn:timezone":"Europe/Rome",
    "iso:country":"IT",
    "wof:name":"Casa Ien",
    "wof:placetype":"locality",
    "wof:population":14
},
  "geometry": {"coordinates":[9.21264,44.81802],"type":"Point"}
}