{
  "type": "Feature",
  "properties": {
    "gn:admin1_code":"12",
    "gn:admin2_code":"VC",
    "gn:admin3_code":"2048.0",
    "gn:asciiname":"Bocciolaro",
    "gn:country_code":"IT",
    "gn:dem":564,
    "gn:feature_class":"P",
    "gn:feature_code":"PPLL",
    "gn:name":"Bocciolaro",
    "gn:population":9,
    "gn:timezone":"Europe/Rome",
    "iso:country":"IT",
    "wof:name":"Bocciolaro",
    "wof:placetype":"locality",
    "wof:population":9
},
  "geometry": {"coordinates":[8.23828,45.85315],"type":"Point"}
}