{
  "type": "Feature",
  "properties": {
    "gn:admin1_code":"9",
    "gn:admin2_code":"LC",
    "gn:admin3_code":"97016.0",
    "gn:asciiname":"Gemella",
    "gn:country_code":"IT",
    "gn:dem":305,
    "gn:feature_class":"P",
    "gn:feature_code":"PPL",
    "gn:name":"Gemella",
    "gn:population":40,
    "gn:timezone":"Europe/Rome",
    "iso:country":"IT",
    "name:deu_x_preferred":[
        "Gemella"
    ],
    "name:glg_x_preferred":[
        "Gemella"
    ],
    "name:isl_x_preferred":[
        "Gemella"
    ],
    "name:pol_x_preferred":[
        "Gemella"
    ],
    "name:tgl_x_preferred":[
        "Gemella"
    ],
    "wof:name":"Gemella",
    "wof:placetype":"locality",
    "wof:population":40
},
  "geometry": {"coordinates":[9.3119,45.68213],"type":"Point"}
}