{
  "type": "Feature",
  "properties": {
    "gn:admin1_code":"9",
    "gn:admin2_code":"BG",
    "gn:admin3_code":"16073.0",
    "gn:asciiname":"Gromolevate",
    "gn:country_code":"IT",
    "gn:dem":199,
    "gn:feature_class":"P",
    "gn:feature_code":"PPL",
    "gn:name":"Gromolevate",
    "gn:population":39,
    "gn:timezone":"Europe/Rome",
    "iso:country":"IT",
    "wof:name":"Gromolevate",
    "wof:placetype":"locality",
    "wof:population":39
},
  "geometry": {"coordinates":[9.85565,45.63916],"type":"Point"}
}