{
  "type": "Feature",
  "properties": {
    "gn:admin1_code":"12",
    "gn:admin2_code":"NO",
    "gn:admin3_code":"3164.0",
    "gn:asciiname":"Cascinotti Corona",
    "gn:country_code":"IT",
    "gn:dem":118,
    "gn:feature_class":"P",
    "gn:feature_code":"PPL",
    "gn:name":"Cascinotti Corona",
    "gn:population":46,
    "gn:timezone":"Europe/Rome",
    "iso:country":"IT",
    "wof:name":"Cascinotti Corona",
    "wof:placetype":"locality",
    "wof:population":46
},
  "geometry": {"coordinates":[8.49605,45.31532],"type":"Point"}
}