{
  "type": "Feature",
  "properties": {
    "gn:admin1_code":"20.0",
    "gn:admin2_code":"PD",
    "gn:admin3_code":"28033.0",
    "gn:asciiname":"Casa Boschettona",
    "gn:country_code":"IT",
    "gn:dem":-1,
    "gn:feature_class":"P",
    "gn:feature_code":"PPL",
    "gn:name":"Casa Boschettona",
    "gn:population":0,
    "gn:timezone":"Europe/Rome",
    "iso:country":"IT",
    "wof:name":"Casa Boschettona",
    "wof:placetype":"locality"
},
  "geometry": {"coordinates":[12.13556,45.25611],"type":"Point"}
}