{
  "type": "Feature",
  "properties": {
    "gn:admin1_code":"16",
    "gn:admin2_code":"FI",
    "gn:admin3_code":"48014.0",
    "gn:asciiname":"La Casetta",
    "gn:country_code":"IT",
    "gn:dem":58,
    "gn:feature_class":"P",
    "gn:feature_code":"PPL",
    "gn:name":"La Casetta",
    "gn:population":17,
    "gn:timezone":"Europe/Rome",
    "iso:country":"IT",
    "wof:name":"La Casetta",
    "wof:placetype":"locality",
    "wof:population":17
},
  "geometry": {"coordinates":[10.95159,43.69373],"type":"Point"}
}