{
  "type": "Feature",
  "properties": {
    "gn:admin1_code":"20",
    "gn:admin2_code":"VR",
    "gn:admin3_code":"23023.0",
    "gn:asciiname":"Pelizzara",
    "gn:country_code":"IT",
    "gn:dem":190,
    "gn:feature_class":"P",
    "gn:feature_code":"PPL",
    "gn:name":"Pelizzara",
    "gn:population":48,
    "gn:timezone":"Europe/Rome",
    "iso:country":"IT",
    "wof:name":"Pelizzara",
    "wof:placetype":"locality",
    "wof:population":48
},
  "geometry": {"coordinates":[10.79361,45.52909],"type":"Point"}
}