{
  "type": "Feature",
  "properties": {
    "gn:country":"IT",
    "gn:fcode":"PPL",
    "gn:population":0,
    "iso:country":"IT",
    "name:ben_x_preferred":[
        "\u0995\u09be\u09a4\u09cb\u09a8\u09be"
    ],
    "name:eml_x_preferred":[
        "Catona"
    ],
    "name:epo_x_preferred":[
        "Catona"
    ],
    "name:fra_x_preferred":[
        "Catona"
    ],
    "name:ita_x_preferred":[
        "Catona"
    ],
    "name:kat_x_preferred":[
        "\u10d9\u10d0\u10e2\u10dd\u10dc\u10d0"
    ],
    "name:lat_x_preferred":[
        "Catona"
    ],
    "name:lmo_x_preferred":[
        "Catona"
    ],
    "name:mwl_x_preferred":[
        "Catona"
    ],
    "name:por_x_preferred":[
        "Catona"
    ],
    "name:rus_x_preferred":[
        "\u041a\u0430\u0442\u043e\u043d\u0430"
    ],
    "name:scn_x_preferred":[
        "A Catuna"
    ],
    "name:und_x_variant":[
        "Dorrecatona"
    ],
    "qs_pg:aaroncc":"IT",
    "qs_pg:gn_country":"IT",
    "qs_pg:gn_fcode":"PPL",
    "qs_pg:gn_pop":0,
    "qs_pg:name":"Catona",
    "qs_pg:name_adm0":"Italia",
    "qs_pg:name_adm1":"Calabria",
    "qs_pg:photos":84,
    "qs_pg:photos_1k":17,
    "qs_pg:photos_9k":1,
    "qs_pg:photos_9r":3,
    "qs_pg:photos_all":84,
    "qs_pg:photos_sr":3,
    "qs_pg:pop_sr":0,
    "qs_pg:qs_pg_placetype":"locality",
    "qs_pg:qs_pg_placetype_gp":"Town",
    "qs_pg:woe_adm0":23424853,
    "woe:adm0_id":23424853,
    "woe:name_adm0":"Italia",
    "woe:name_adm1":"Calabria",
    "woe:placetype":"Town",
    "wof:name":"Catona",
    "wof:placetype":"locality"
},
  "geometry": {"coordinates":[15.63333,38.18333],"type":"Point"}
}