{
  "type": "Feature",
  "properties": {
    "gn:admin1_code":"4",
    "gn:admin2_code":"BN",
    "gn:admin3_code":"62070.0",
    "gn:asciiname":"Masseria Izzo",
    "gn:country_code":"IT",
    "gn:dem":87,
    "gn:feature_class":"P",
    "gn:feature_code":"PPL",
    "gn:name":"Masseria Izzo",
    "gn:population":42,
    "gn:timezone":"Europe/Rome",
    "iso:country":"IT",
    "wof:name":"Masseria Izzo",
    "wof:placetype":"locality",
    "wof:population":42
},
  "geometry": {"coordinates":[14.46047,41.09701],"type":"Point"}
}