{
  "type": "Feature",
  "properties": {
    "gn:admin1_code":"10.0",
    "gn:admin2_code":"PU",
    "gn:admin3_code":"41068.0",
    "gn:asciiname":"Capponello",
    "gn:country_code":"IT",
    "gn:dem":86,
    "gn:feature_class":"P",
    "gn:feature_code":"PPL",
    "gn:name":"Capponello",
    "gn:population":48,
    "gn:timezone":"Europe/Rome",
    "iso:country":"IT",
    "wof:name":"Capponello",
    "wof:placetype":"locality",
    "wof:population":48
},
  "geometry": {"coordinates":[12.7352,43.8213],"type":"Point"}
}