{
  "type": "Feature",
  "properties": {
    "gn:admin1_code":"18",
    "gn:admin2_code":"PG",
    "gn:admin3_code":"54007.0",
    "gn:asciiname":"Sciedi",
    "gn:country_code":"IT",
    "gn:dem":719,
    "gn:feature_class":"P",
    "gn:feature_code":"PPL",
    "gn:name":"Sciedi",
    "gn:population":23,
    "gn:timezone":"Europe/Rome",
    "iso:country":"IT",
    "wof:name":"Sciedi",
    "wof:placetype":"locality",
    "wof:population":23
},
  "geometry": {"coordinates":[13.02996,42.70483],"type":"Point"}
}