{
  "type": "Feature",
  "properties": {
    "gn:admin1_code":"16",
    "gn:admin2_code":"LU",
    "gn:admin3_code":"46001.0",
    "gn:asciiname":"Ponte alla Ciliegia",
    "gn:country_code":"IT",
    "gn:dem":25,
    "gn:feature_class":"P",
    "gn:feature_code":"PPL",
    "gn:name":"Ponte alla Ciliegia",
    "gn:population":94,
    "gn:timezone":"Europe/Rome",
    "iso:country":"IT",
    "wof:name":"Ponte alla Ciliegia",
    "wof:placetype":"locality",
    "wof:population":94
},
  "geometry": {"coordinates":[10.70202,43.83403],"type":"Point"}
}