{
  "type": "Feature",
  "properties": {
    "gn:admin1_code":"8",
    "gn:admin2_code":"GE",
    "gn:admin3_code":"10040.0",
    "gn:asciiname":"Osti di San Michele",
    "gn:country_code":"IT",
    "gn:dem":366,
    "gn:feature_class":"P",
    "gn:feature_code":"PPL",
    "gn:name":"Osti di San Michele",
    "gn:population":15,
    "gn:timezone":"Europe/Rome",
    "iso:country":"IT",
    "wof:name":"Osti di San Michele",
    "wof:placetype":"locality",
    "wof:population":15
},
  "geometry": {"coordinates":[9.42989,44.35545],"type":"Point"}
}