{
  "type": "Feature",
  "properties": {
    "gn:admin1_code":"5",
    "gn:admin2_code":"RA",
    "gn:admin3_code":"39006.0",
    "gn:asciiname":"Ponte del Castello",
    "gn:country_code":"IT",
    "gn:dem":37,
    "gn:feature_class":"P",
    "gn:feature_code":"PPL",
    "gn:name":"Ponte del Castello",
    "gn:population":79,
    "gn:timezone":"Europe/Rome",
    "iso:country":"IT",
    "wof:name":"Ponte del Castello",
    "wof:placetype":"locality",
    "wof:population":79
},
  "geometry": {"coordinates":[11.82254,44.31075],"type":"Point"}
}