{
  "type": "Feature",
  "properties": {
    "gn:admin1_code":"9.0",
    "gn:admin2_code":"SO",
    "gn:admin3_code":"14054.0",
    "gn:asciiname":"Prata Centro",
    "gn:country_code":"IT",
    "gn:dem":302,
    "gn:feature_class":"P",
    "gn:feature_code":"PPLA3",
    "gn:name":"Prata Centro",
    "gn:population":1224,
    "gn:timezone":"Europe/Rome",
    "iso:country":"IT",
    "wof:name":"Prata Centro",
    "wof:placetype":"locality",
    "wof:population":1224
},
  "geometry": {"coordinates":[9.39625,46.30847],"type":"Point"}
}