{
  "type": "Feature",
  "properties": {
    "gn:admin1_code":"1",
    "gn:admin2_code":"CH",
    "gn:admin3_code":"69040.0",
    "gn:asciiname":"Coccioli",
    "gn:country_code":"IT",
    "gn:dem":580,
    "gn:feature_class":"P",
    "gn:feature_code":"PPL",
    "gn:name":"Coccioli",
    "gn:population":20,
    "gn:timezone":"Europe/Rome",
    "iso:country":"IT",
    "wof:name":"Coccioli",
    "wof:placetype":"locality",
    "wof:population":20
},
  "geometry": {"coordinates":[14.29112,42.04414000000001],"type":"Point"}
}