{
  "type": "Feature",
  "properties": {
    "gn:admin1_code":"7",
    "gn:admin2_code":"FR",
    "gn:admin3_code":"60066.0",
    "gn:asciiname":"Conventi",
    "gn:country_code":"IT",
    "gn:dem":44,
    "gn:feature_class":"P",
    "gn:feature_code":"PPL",
    "gn:name":"Conventi",
    "gn:population":33,
    "gn:timezone":"Europe/Rome",
    "iso:country":"IT",
    "wof:name":"Conventi",
    "wof:placetype":"locality",
    "wof:population":33
},
  "geometry": {"coordinates":[13.8599,41.35818],"type":"Point"}
}