{
  "type": "Feature",
  "properties": {
    "gn:admin1_code":"8.0",
    "gn:admin2_code":"SP",
    "gn:admin3_code":"11015.0",
    "gn:asciiname":"Isola",
    "gn:country_code":"IT",
    "gn:dem":282,
    "gn:elevation":"275.0",
    "gn:feature_class":"P",
    "gn:feature_code":"PPL",
    "gn:name":"Isola",
    "gn:population":29,
    "gn:timezone":"Europe/Rome",
    "iso:country":"IT",
    "wof:name":"Isola",
    "wof:placetype":"locality",
    "wof:population":29
},
  "geometry": {"coordinates":[9.83644,44.13879],"type":"Point"}
}