{
  "type": "Feature",
  "properties": {
    "gn:admin1_code":"10",
    "gn:admin2_code":"PU",
    "gn:admin3_code":"41061.0",
    "gn:asciiname":"Pianello",
    "gn:country_code":"IT",
    "gn:dem":478,
    "gn:feature_class":"P",
    "gn:feature_code":"PPL",
    "gn:name":"Pianello",
    "gn:population":42,
    "gn:timezone":"Europe/Rome",
    "iso:country":"IT",
    "wof:name":"Pianello",
    "wof:placetype":"locality",
    "wof:population":42
},
  "geometry": {"coordinates":[12.75276,43.50391],"type":"Point"}
}