{
  "type": "Feature",
  "properties": {
    "iso:country":"IT",
    "wof:name":"Castel di Decima",
    "wof:placetype":"neighbourhood"
},
  "geometry": {"coordinates":[12.47724261523731,41.73240140509216],"type":"Point"}
}