{
  "type": "Feature",
  "properties": {
    "gn:admin1_code":"12",
    "gn:admin2_code":"NO",
    "gn:admin3_code":"3103.0",
    "gn:asciiname":"Tapigliano",
    "gn:country_code":"IT",
    "gn:dem":502,
    "gn:feature_class":"P",
    "gn:feature_code":"PPL",
    "gn:name":"Tapigliano",
    "gn:population":208,
    "gn:timezone":"Europe/Rome",
    "iso:country":"IT",
    "wof:name":"Tapigliano",
    "wof:placetype":"locality",
    "wof:population":208
},
  "geometry": {"coordinates":[8.51568,45.80377],"type":"Point"}
}