{
  "type": "Feature",
  "properties": {
    "gn:admin1_code":"3.0",
    "gn:admin2_code":"CS",
    "gn:admin3_code":"78155.0",
    "gn:asciiname":"Rovella",
    "gn:cc2":"IT",
    "gn:country_code":"IT",
    "gn:dem":384,
    "gn:feature_class":"P",
    "gn:feature_code":"PPL",
    "gn:name":"Rovella",
    "gn:population":268,
    "gn:timezone":"Europe/Rome",
    "iso:country":"IT",
    "name:und_x_variant":[
        "Rovello",
        "Rovella"
    ],
    "wof:name":"Rovella",
    "wof:placetype":"locality",
    "wof:population":268
},
  "geometry": {"coordinates":[16.28695,39.30398],"type":"Point"}
}