{
  "type": "Feature",
  "properties": {
    "gn:admin1_code":"16",
    "gn:admin2_code":"SI",
    "gn:admin3_code":"52022.0",
    "gn:asciiname":"Vivaia",
    "gn:country_code":"IT",
    "gn:dem":207,
    "gn:feature_class":"P",
    "gn:feature_code":"PPL",
    "gn:name":"Vivaia",
    "gn:population":25,
    "gn:timezone":"Europe/Rome",
    "iso:country":"IT",
    "wof:name":"Vivaia",
    "wof:placetype":"locality",
    "wof:population":25
},
  "geometry": {"coordinates":[11.19967,43.41345],"type":"Point"}
}