{
  "type": "Feature",
  "properties": {
    "gn:admin1_code":"5",
    "gn:admin2_code":"FE",
    "gn:admin3_code":"38023.0",
    "gn:asciiname":"Sellarino",
    "gn:country_code":"IT",
    "gn:dem":1,
    "gn:feature_class":"P",
    "gn:feature_code":"PPL",
    "gn:name":"Sellarino",
    "gn:population":23,
    "gn:timezone":"Europe/Rome",
    "iso:country":"IT",
    "wof:name":"Sellarino",
    "wof:placetype":"locality",
    "wof:population":23
},
  "geometry": {"coordinates":[11.74736,44.74371],"type":"Point"}
}