{
  "type": "Feature",
  "properties": {
    "gn:admin1_code":"10",
    "gn:admin2_code":"AN",
    "gn:admin3_code":"42017.0",
    "gn:asciiname":"Case Ciampeo",
    "gn:country_code":"IT",
    "gn:dem":317,
    "gn:feature_class":"P",
    "gn:feature_code":"PPL",
    "gn:name":"Case Ciampeo",
    "gn:population":24,
    "gn:timezone":"Europe/Rome",
    "iso:country":"IT",
    "wof:name":"Case Ciampeo",
    "wof:placetype":"locality",
    "wof:population":24
},
  "geometry": {"coordinates":[12.96242,43.32666],"type":"Point"}
}