{
  "type": "Feature",
  "properties": {
    "gn:admin1_code":"10",
    "gn:admin2_code":"MC",
    "gn:admin3_code":"43057.0",
    "gn:asciiname":"Rasenna",
    "gn:country_code":"IT",
    "gn:dem":927,
    "gn:feature_class":"P",
    "gn:feature_code":"PPL",
    "gn:name":"Rasenna",
    "gn:population":23,
    "gn:timezone":"Europe/Rome",
    "iso:country":"IT",
    "wof:name":"Rasenna",
    "wof:placetype":"locality",
    "wof:population":23
},
  "geometry": {"coordinates":[12.95667,42.93511],"type":"Point"}
}