{
  "type": "Feature",
  "properties": {
    "gn:admin1_code":"20.0",
    "gn:admin2_code":"PD",
    "gn:admin3_code":"28049.0",
    "gn:asciiname":"Masi",
    "gn:country_code":"IT",
    "gn:dem":9,
    "gn:elevation":"11.0",
    "gn:feature_class":"P",
    "gn:feature_code":"PPLA3",
    "gn:name":"Masi",
    "gn:population":1036,
    "gn:timezone":"Europe/Rome",
    "iso:country":"IT",
    "name:bel_x_preferred":[
        "\u0413\u043e\u0440\u0430\u0434 \u041c\u0430\u0437\u0456"
    ],
    "name:hye_x_preferred":[
        "\u0544\u0561\u0566\u056b"
    ],
    "name:jpn_x_preferred":[
        "\u30de\u30fc\u30b8"
    ],
    "name:rus_x_preferred":[
        "\u041c\u0430\u0437\u0438"
    ],
    "name:ukr_x_preferred":[
        "\u041c\u0430\u0437\u0456"
    ],
    "name:vec_x_preferred":[
        "Maxi"
    ],
    "wof:name":"Masi",
    "wof:placetype":"locality",
    "wof:population":1036
},
  "geometry": {"coordinates":[11.48921,45.10888],"type":"Point"}
}