{
  "type": "Feature",
  "properties": {
    "gn:admin1_code":"20.0",
    "gn:admin2_code":"PD",
    "gn:admin3_code":"28049.0",
    "gn:asciiname":"Masi",
    "gn:country_code":"IT",
    "gn:dem":9,
    "gn:elevation":"11.0",
    "gn:feature_class":"P",
    "gn:feature_code":"PPLA3",
    "gn:name":"Masi",
    "gn:population":1036,
    "gn:timezone":"Europe/Rome",
    "iso:country":"IT",
    "name:azb_x_preferred":[
        "\u0645\u0627\u0633\u06cc"
    ],
    "name:bel_x_preferred":[
        "\u0413\u043e\u0440\u0430\u0434 \u041c\u0430\u0437\u0456"
    ],
    "name:bel_x_variant":[
        "\u041c\u0430\u0437\u0456"
    ],
    "name:bul_x_preferred":[
        "\u041c\u0430\u0437\u0438"
    ],
    "name:ceb_x_preferred":[
        "Masi"
    ],
    "name:deu_x_preferred":[
        "Masi"
    ],
    "name:epo_x_preferred":[
        "Masi"
    ],
    "name:eus_x_preferred":[
        "Masi"
    ],
    "name:fas_x_preferred":[
        "\u0645\u0627\u0633\u06cc"
    ],
    "name:fra_x_preferred":[
        "Masi"
    ],
    "name:hun_x_preferred":[
        "Masi"
    ],
    "name:hye_x_preferred":[
        "\u0544\u0561\u0566\u056b"
    ],
    "name:ind_x_preferred":[
        "Masi"
    ],
    "name:ita_x_preferred":[
        "Masi"
    ],
    "name:jpn_x_preferred":[
        "\u30de\u30fc\u30b8"
    ],
    "name:lat_x_preferred":[
        "Masi"
    ],
    "name:lmo_x_preferred":[
        "Masi"
    ],
    "name:msa_x_preferred":[
        "Masi"
    ],
    "name:nap_x_preferred":[
        "Masi"
    ],
    "name:nld_x_preferred":[
        "Masi"
    ],
    "name:pms_x_preferred":[
        "Masi"
    ],
    "name:pol_x_preferred":[
        "Masi"
    ],
    "name:por_x_preferred":[
        "Masi"
    ],
    "name:ron_x_preferred":[
        "Masi"
    ],
    "name:rus_x_preferred":[
        "\u041c\u0430\u0437\u0438"
    ],
    "name:scn_x_preferred":[
        "Masi"
    ],
    "name:spa_x_preferred":[
        "Masi"
    ],
    "name:srp_x_preferred":[
        "\u041c\u0430\u0437\u0438"
    ],
    "name:swe_x_preferred":[
        "Masi"
    ],
    "name:tgl_x_preferred":[
        "Masi"
    ],
    "name:ukr_x_preferred":[
        "\u041c\u0430\u0437\u0456"
    ],
    "name:uzb_x_preferred":[
        "Masi"
    ],
    "name:vec_x_preferred":[
        "Maxi"
    ],
    "name:vie_x_preferred":[
        "Masi"
    ],
    "name:vol_x_preferred":[
        "Masi"
    ],
    "name:war_x_preferred":[
        "Masi"
    ],
    "wof:name":"Masi",
    "wof:placetype":"locality",
    "wof:population":1036
},
  "geometry": {"coordinates":[11.48921,45.10888],"type":"Point"}
}