{
  "type": "Feature",
  "properties": {
    "gn:admin1_code":"15",
    "gn:admin2_code":"TP",
    "gn:admin3_code":"81021.0",
    "gn:asciiname":"Pietretagliate",
    "gn:country_code":"IT",
    "gn:dem":30,
    "gn:feature_class":"P",
    "gn:feature_code":"PPL",
    "gn:name":"Pietretagliate",
    "gn:population":162,
    "gn:timezone":"Europe/Rome",
    "iso:country":"IT",
    "wof:name":"Pietretagliate",
    "wof:placetype":"locality",
    "wof:population":162
},
  "geometry": {"coordinates":[12.52872,37.95683],"type":"Point"}
}