{
  "type": "Feature",
  "properties": {
    "gn:admin1_code":"12",
    "gn:admin2_code":"CN",
    "gn:admin3_code":"4009.0",
    "gn:asciiname":"San Maurizio",
    "gn:country_code":"IT",
    "gn:dem":425,
    "gn:feature_class":"P",
    "gn:feature_code":"PPL",
    "gn:name":"San Maurizio",
    "gn:population":48,
    "gn:timezone":"Europe/Rome",
    "iso:country":"IT",
    "name:ceb_x_preferred":[
        "San Maurizio"
    ],
    "name:ita_x_preferred":[
        "San Maurizio"
    ],
    "name:rus_x_preferred":[
        "\u0421\u0430\u043d-\u041c\u0430\u0443\u0440\u0438\u0446\u0438\u043e"
    ],
    "name:srp_x_preferred":[
        "San Maurizio"
    ],
    "name:swe_x_preferred":[
        "San Maurizio"
    ],
    "wof:name":"San Maurizio",
    "wof:placetype":"locality",
    "wof:population":48
},
  "geometry": {"coordinates":[7.31098,44.74569],"type":"Point"}
}