{
  "type": "Feature",
  "properties": {
    "gn:admin1_code":"12",
    "gn:admin2_code":"CN",
    "gn:admin3_code":"4009.0",
    "gn:asciiname":"San Maurizio",
    "gn:country_code":"IT",
    "gn:dem":425,
    "gn:feature_class":"P",
    "gn:feature_code":"PPL",
    "gn:name":"San Maurizio",
    "gn:population":48,
    "gn:timezone":"Europe/Rome",
    "iso:country":"IT",
    "wof:name":"San Maurizio",
    "wof:placetype":"locality",
    "wof:population":48
},
  "geometry": {"coordinates":[7.31098,44.74569],"type":"Point"}
}