{
  "type": "Feature",
  "properties": {
    "gn:admin1_code":"9.0",
    "gn:admin2_code":"BG",
    "gn:admin3_code":"16132.0",
    "gn:asciiname":"Valtrighe",
    "gn:country_code":"IT",
    "gn:dem":238,
    "gn:feature_class":"P",
    "gn:feature_code":"PPL",
    "gn:name":"Valtrighe",
    "gn:population":661,
    "gn:timezone":"Europe/Rome",
    "iso:country":"IT",
    "wof:name":"Valtrighe",
    "wof:placetype":"locality",
    "wof:population":661
},
  "geometry": {"coordinates":[9.5367,45.69571],"type":"Point"}
}