{
  "type": "Feature",
  "properties": {
    "iso:country":"IT",
    "name:eng_x_preferred":[
        "Madonna di Dossobuono"
    ],
    "name:ita_x_preferred":[
        "Madonna di Dossobuono"
    ],
    "wof:name":"Madonna di Dossobuono",
    "wof:placetype":"neighbourhood"
},
  "geometry": {"coordinates":[10.93044694844392,45.40746207818779],"type":"Point"}
}