{
  "type": "Feature",
  "properties": {
    "gn:admin1_code":"12",
    "gn:admin2_code":"AL",
    "gn:admin3_code":"6100.0",
    "gn:asciiname":"Vergagni",
    "gn:country_code":"IT",
    "gn:dem":659,
    "gn:feature_class":"P",
    "gn:feature_code":"PPL",
    "gn:name":"Vergagni",
    "gn:population":16,
    "gn:timezone":"Europe/Rome",
    "iso:country":"IT",
    "wof:name":"Vergagni",
    "wof:placetype":"locality",
    "wof:population":16
},
  "geometry": {"coordinates":[9.06138,44.66023],"type":"Point"}
}