{
  "type": "Feature",
  "properties": {
    "gn:admin1_code":"8.0",
    "gn:admin2_code":"SV",
    "gn:admin3_code":"9062.0",
    "gn:asciiname":"Bardino Vecchio",
    "gn:country_code":"IT",
    "gn:dem":236,
    "gn:elevation":"233.0",
    "gn:feature_class":"P",
    "gn:feature_code":"PPL",
    "gn:name":"Bardino Vecchio",
    "gn:population":90,
    "gn:timezone":"Europe/Rome",
    "iso:country":"IT",
    "wof:name":"Bardino Vecchio",
    "wof:placetype":"locality",
    "wof:population":90
},
  "geometry": {"coordinates":[8.27076,44.18785],"type":"Point"}
}