{
  "type": "Feature",
  "properties": {
    "gn:admin1_code":"16",
    "gn:admin2_code":"FI",
    "gn:admin3_code":"48053.0",
    "gn:asciiname":"Petrona",
    "gn:country_code":"IT",
    "gn:dem":201,
    "gn:feature_class":"P",
    "gn:feature_code":"PPL",
    "gn:name":"Petrona",
    "gn:population":19,
    "gn:timezone":"Europe/Rome",
    "iso:country":"IT",
    "wof:name":"Petrona",
    "wof:placetype":"locality",
    "wof:population":19
},
  "geometry": {"coordinates":[11.34807,43.96166],"type":"Point"}
}