{
  "type": "Feature",
  "properties": {
    "gn:admin1_code":"5.0",
    "gn:admin2_code":"PC",
    "gn:admin3_code":"33020.0",
    "gn:asciiname":"Gambaro",
    "gn:country_code":"IT",
    "gn:dem":874,
    "gn:elevation":"864.0",
    "gn:feature_class":"P",
    "gn:feature_code":"PPL",
    "gn:name":"Gambaro",
    "gn:population":42,
    "gn:timezone":"Europe/Rome",
    "iso:country":"IT",
    "wof:name":"Gambaro",
    "wof:placetype":"locality",
    "wof:population":42
},
  "geometry": {"coordinates":[9.48197,44.61485],"type":"Point"}
}