{
  "type": "Feature",
  "properties": {
    "iso:country":"IT",
    "wof:name":"Prato Fiorito",
    "wof:placetype":"neighbourhood"
},
  "geometry": {"coordinates":[12.66232228294573,41.88634739681014],"type":"Point"}
}