{
  "type": "Feature",
  "properties": {
    "gn:admin1_code":"16",
    "gn:admin2_code":"LU",
    "gn:admin3_code":"46022.0",
    "gn:asciiname":"Molinetto",
    "gn:country_code":"IT",
    "gn:dem":300,
    "gn:feature_class":"P",
    "gn:feature_code":"PPL",
    "gn:name":"Molinetto",
    "gn:population":32,
    "gn:timezone":"Europe/Rome",
    "iso:country":"IT",
    "wof:name":"Molinetto",
    "wof:placetype":"locality",
    "wof:population":32
},
  "geometry": {"coordinates":[10.43198,43.95505],"type":"Point"}
}