{
  "type": "Feature",
  "properties": {
    "gn:admin1_code":"3.0",
    "gn:admin2_code":"CZ",
    "gn:admin3_code":"79036.0",
    "gn:asciiname":"Marraglione",
    "gn:country_code":"IT",
    "gn:dem":314,
    "gn:feature_class":"P",
    "gn:feature_code":"PPL",
    "gn:name":"Marraglione",
    "gn:population":0,
    "gn:timezone":"Europe/Rome",
    "iso:country":"IT",
    "wof:name":"Marraglione",
    "wof:placetype":"locality"
},
  "geometry": {"coordinates":[16.75,38.96667],"type":"Point"}
}