{
  "type": "Feature",
  "properties": {
    "gn:admin1_code":"15.0",
    "gn:admin2_code":"ME",
    "gn:admin3_code":"83096.0",
    "gn:asciiname":"San Martino",
    "gn:country_code":"IT",
    "gn:dem":248,
    "gn:elevation":"245.0",
    "gn:feature_class":"P",
    "gn:feature_code":"PPL",
    "gn:name":"San Martino",
    "gn:population":335,
    "gn:timezone":"Europe/Rome",
    "iso:country":"IT",
    "wof:name":"San Martino",
    "wof:placetype":"locality",
    "wof:population":335
},
  "geometry": {"coordinates":[15.39106,38.20626],"type":"Point"}
}