{
  "type": "Feature",
  "properties": {
    "gn:admin1_code":"6.0",
    "gn:admin2_code":"PN",
    "gn:admin3_code":"93014.0",
    "gn:asciiname":"Casera la Fontana",
    "gn:country_code":"IT",
    "gn:dem":966,
    "gn:feature_class":"P",
    "gn:feature_code":"PPL",
    "gn:name":"Casera la Fontana",
    "gn:population":0,
    "gn:timezone":"Europe/Rome",
    "iso:country":"IT",
    "wof:name":"Casera la Fontana",
    "wof:placetype":"locality"
},
  "geometry": {"coordinates":[12.46667,46.35],"type":"Point"}
}