{
  "type": "Feature",
  "properties": {
    "gn:admin1_code":"7",
    "gn:admin2_code":"FR",
    "gn:admin3_code":"60058.0",
    "gn:asciiname":"Cesalonga",
    "gn:country_code":"IT",
    "gn:dem":187,
    "gn:feature_class":"P",
    "gn:feature_code":"PPL",
    "gn:name":"Cesalonga",
    "gn:population":31,
    "gn:timezone":"Europe/Rome",
    "iso:country":"IT",
    "wof:name":"Cesalonga",
    "wof:placetype":"locality",
    "wof:population":31
},
  "geometry": {"coordinates":[13.45363,41.60972],"type":"Point"}
}