{
  "type": "Feature",
  "properties": {
    "gn:admin1_code":"15.0",
    "gn:admin2_code":"SR",
    "gn:admin3_code":"89013.0",
    "gn:asciiname":"Lido di Noto",
    "gn:cc2":"IT",
    "gn:country_code":"IT",
    "gn:dem":21,
    "gn:feature_class":"P",
    "gn:feature_code":"PPL",
    "gn:name":"Lido di Noto",
    "gn:population":741,
    "gn:timezone":"Europe/Rome",
    "iso:country":"IT",
    "name:und_x_variant":[
        "Colonia Marina",
        "Lido di Noto",
        "Noto Marina"
    ],
    "wof:name":"Lido di Noto",
    "wof:placetype":"locality",
    "wof:population":741
},
  "geometry": {"coordinates":[15.11445,36.85907],"type":"Point"}
}