{
  "type": "Feature",
  "properties": {
    "gn:admin1_code":"16",
    "gn:admin2_code":"LU",
    "gn:admin3_code":"46035.0",
    "gn:asciiname":"Le Piane",
    "gn:country_code":"IT",
    "gn:dem":535,
    "gn:feature_class":"P",
    "gn:feature_code":"PPL",
    "gn:name":"Le Piane",
    "gn:population":32,
    "gn:timezone":"Europe/Rome",
    "iso:country":"IT",
    "wof:name":"Le Piane",
    "wof:placetype":"locality",
    "wof:population":32
},
  "geometry": {"coordinates":[10.3924,44.16127],"type":"Point"}
}