{
  "type": "Feature",
  "properties": {
    "gn:admin1_code":"9.0",
    "gn:admin2_code":"BG",
    "gn:admin3_code":"16243.0",
    "gn:asciiname":"Vilminore",
    "gn:country_code":"IT",
    "gn:dem":1032,
    "gn:feature_class":"P",
    "gn:feature_code":"PPLA3",
    "gn:name":"Vilminore",
    "gn:population":610,
    "gn:timezone":"Europe/Rome",
    "iso:country":"IT",
    "wof:name":"Vilminore",
    "wof:placetype":"locality",
    "wof:population":610
},
  "geometry": {"coordinates":[10.09531,45.99795],"type":"Point"}
}