{
  "type": "Feature",
  "properties": {
    "gn:admin1_code":"5",
    "gn:admin2_code":"MO",
    "gn:admin3_code":"36022.0",
    "gn:asciiname":"Stazione Ferroviaria",
    "gn:country_code":"IT",
    "gn:dem":13,
    "gn:feature_class":"P",
    "gn:feature_code":"PPL",
    "gn:name":"Stazione Ferroviaria",
    "gn:population":72,
    "gn:timezone":"Europe/Rome",
    "iso:country":"IT",
    "wof:name":"Stazione Ferroviaria",
    "wof:placetype":"locality",
    "wof:population":72
},
  "geometry": {"coordinates":[11.11017,44.89231],"type":"Point"}
}