{
  "type": "Feature",
  "properties": {
    "gn:admin1_code":"5.0",
    "gn:admin2_code":"RA",
    "gn:admin3_code":"39010.0",
    "gn:asciiname":"Sarna",
    "gn:country_code":"IT",
    "gn:dem":86,
    "gn:feature_class":"P",
    "gn:feature_code":"PPLL",
    "gn:name":"Sarna",
    "gn:population":4,
    "gn:timezone":"Europe/Rome",
    "iso:country":"IT",
    "name:deu_x_preferred":[
        "Sarna"
    ],
    "name:fra_x_preferred":[
        "Sarna"
    ],
    "name:ita_x_preferred":[
        "Sarna"
    ],
    "name:pol_x_preferred":[
        "Sarna"
    ],
    "name:spa_x_preferred":[
        "Sarna"
    ],
    "name:srp_x_preferred":[
        "Sarna"
    ],
    "wof:name":"Sarna",
    "wof:placetype":"locality",
    "wof:population":4
},
  "geometry": {"coordinates":[11.83149,44.24001],"type":"Point"}
}