{
  "type": "Feature",
  "properties": {
    "gn:admin1_code":"1",
    "gn:admin2_code":"CH",
    "gn:admin3_code":"69035.0",
    "gn:asciiname":"Pujese",
    "gn:country_code":"IT",
    "gn:dem":19,
    "gn:feature_class":"P",
    "gn:feature_code":"PPL",
    "gn:name":"Pujese",
    "gn:population":220,
    "gn:timezone":"Europe/Rome",
    "iso:country":"IT",
    "wof:name":"Pujese",
    "wof:placetype":"locality",
    "wof:population":220
},
  "geometry": {"coordinates":[14.31127,42.39725],"type":"Point"}
}