{
  "type": "Feature",
  "properties": {
    "gn:admin1_code":"20.0",
    "gn:admin2_code":"VI",
    "gn:admin3_code":"24084.0",
    "gn:asciiname":"Fantoni",
    "gn:country_code":"IT",
    "gn:dem":906,
    "gn:feature_class":"P",
    "gn:feature_code":"PPLL",
    "gn:name":"Fantoni",
    "gn:population":3,
    "gn:timezone":"Europe/Rome",
    "iso:country":"IT",
    "wof:name":"Fantoni",
    "wof:placetype":"locality",
    "wof:population":3
},
  "geometry": {"coordinates":[11.23103,45.68118],"type":"Point"}
}