{
  "type": "Feature",
  "properties": {
    "gn:admin1_code":"4.0",
    "gn:admin2_code":"AV",
    "gn:admin3_code":"64121.0",
    "gn:asciiname":"Misciano",
    "gn:country_code":"IT",
    "gn:dem":235,
    "gn:feature_class":"P",
    "gn:feature_code":"PPL",
    "gn:name":"Misciano",
    "gn:population":504,
    "gn:timezone":"Europe/Rome",
    "iso:country":"IT",
    "wof:name":"Misciano",
    "wof:placetype":"locality",
    "wof:population":504
},
  "geometry": {"coordinates":[14.7864,40.81516],"type":"Point"}
}