{
  "type": "Feature",
  "properties": {
    "gn:admin1_code":"4",
    "gn:admin2_code":"SA",
    "gn:admin3_code":"65002.0",
    "gn:asciiname":"Principe",
    "gn:country_code":"IT",
    "gn:dem":109,
    "gn:feature_class":"P",
    "gn:feature_code":"PPL",
    "gn:name":"Principe",
    "gn:population":34,
    "gn:timezone":"Europe/Rome",
    "iso:country":"IT",
    "name:hun_x_preferred":[
        "Pr\u00edncipe"
    ],
    "wof:name":"Principe",
    "wof:placetype":"locality",
    "wof:population":34
},
  "geometry": {"coordinates":[14.99017,40.32422],"type":"Point"}
}