{
  "type": "Feature",
  "properties": {
    "gn:admin1_code":"12",
    "gn:admin2_code":"AL",
    "gn:admin3_code":"6044.0",
    "gn:asciiname":"Galanti",
    "gn:country_code":"IT",
    "gn:dem":374,
    "gn:feature_class":"P",
    "gn:feature_code":"PPL",
    "gn:name":"Galanti",
    "gn:population":15,
    "gn:timezone":"Europe/Rome",
    "iso:country":"IT",
    "wof:name":"Galanti",
    "wof:placetype":"locality",
    "wof:population":15
},
  "geometry": {"coordinates":[8.55173,44.5911],"type":"Point"}
}