{
  "type": "Feature",
  "properties": {
    "gn:admin1_code":"12.0",
    "gn:admin2_code":"TO",
    "gn:admin3_code":"1175.0",
    "gn:asciiname":"Gouthier",
    "gn:country_code":"IT",
    "gn:dem":1977,
    "gn:feature_class":"P",
    "gn:feature_code":"PPL",
    "gn:name":"Gouthier",
    "gn:population":0,
    "gn:timezone":"Europe/Rome",
    "iso:country":"IT",
    "wof:name":"Gouthier",
    "wof:placetype":"locality"
},
  "geometry": {"coordinates":[6.78333,45.06667],"type":"Point"}
}