{
  "type": "Feature",
  "properties": {
    "gn:admin1_code":"14.0",
    "gn:admin2_code":"SU",
    "gn:admin3_code":"111073.0",
    "gn:asciiname":"Segariu",
    "gn:country_code":"IT",
    "gn:dem":114,
    "gn:elevation":"117.0",
    "gn:feature_class":"P",
    "gn:feature_code":"PPLA3",
    "gn:name":"Segariu",
    "gn:population":1139,
    "gn:timezone":"Europe/Rome",
    "iso:country":"IT",
    "name:arg_x_preferred":[
        "Segariu"
    ],
    "name:azb_x_preferred":[
        "\u0633\u0642\u0627\u0631\u06cc\u0648"
    ],
    "name:bel_x_preferred":[
        "\u0421\u0435\u0433\u0430\u0440\u044b\u0443"
    ],
    "name:bul_x_preferred":[
        "\u0421\u0435\u0433\u0430\u0440\u0438\u0443"
    ],
    "name:cat_x_preferred":[
        "Segariu"
    ],
    "name:ceb_x_preferred":[
        "Segariu"
    ],
    "name:ces_x_preferred":[
        "Segariu"
    ],
    "name:dan_x_preferred":[
        "Segariu"
    ],
    "name:deu_x_preferred":[
        "Segariu"
    ],
    "name:eng_x_preferred":[
        "Segariu"
    ],
    "name:epo_x_preferred":[
        "Segariu"
    ],
    "name:eus_x_preferred":[
        "Segariu"
    ],
    "name:fas_x_preferred":[
        "\u0633\u06af\u0627\u0631\u06cc\u0648"
    ],
    "name:fin_x_preferred":[
        "Segariu"
    ],
    "name:fra_x_preferred":[
        "Segariu"
    ],
    "name:hrv_x_preferred":[
        "Segariu"
    ],
    "name:hun_x_preferred":[
        "Segariu"
    ],
    "name:hye_x_preferred":[
        "\u054d\u0565\u0563\u0561\u0580\u056b\u0578\u0582"
    ],
    "name:ind_x_preferred":[
        "Segariu"
    ],
    "name:ita_x_preferred":[
        "Segariu"
    ],
    "name:jpn_x_preferred":[
        "\u30bb\u30ac\u30ea\u30fc\u30a6"
    ],
    "name:kaz_x_preferred":[
        "\u0421\u0435\u0433\u0430\u0440\u0438\u0443"
    ],
    "name:lat_x_preferred":[
        "Seguarius"
    ],
    "name:lmo_x_preferred":[
        "Segariu"
    ],
    "name:msa_x_preferred":[
        "Segariu"
    ],
    "name:nap_x_preferred":[
        "Segariu"
    ],
    "name:nld_x_preferred":[
        "Segariu"
    ],
    "name:nno_x_preferred":[
        "Segariu"
    ],
    "name:nor_x_preferred":[
        "Segariu"
    ],
    "name:pms_x_preferred":[
        "Segariu"
    ],
    "name:pol_x_preferred":[
        "Segariu"
    ],
    "name:por_x_preferred":[
        "Segariu"
    ],
    "name:ron_x_preferred":[
        "Segariu"
    ],
    "name:rus_x_preferred":[
        "\u0421\u0435\u0433\u0430\u0440\u0438\u0443"
    ],
    "name:scn_x_preferred":[
        "Segariu"
    ],
    "name:spa_x_preferred":[
        "Segariu"
    ],
    "name:sqi_x_preferred":[
        "Segariu"
    ],
    "name:srd_x_preferred":[
        "Segariu"
    ],
    "name:srp_x_preferred":[
        "\u0421\u0435\u0433\u0430\u0440\u0438\u0458\u0443"
    ],
    "name:tur_x_preferred":[
        "Segariu"
    ],
    "name:ukr_x_preferred":[
        "\u0421\u0435\u0433\u0430\u0440\u0456\u0443"
    ],
    "name:uzb_x_preferred":[
        "Segariu"
    ],
    "name:vec_x_preferred":[
        "Segariu"
    ],
    "name:vie_x_preferred":[
        "Segariu"
    ],
    "name:vol_x_preferred":[
        "Segariu"
    ],
    "name:war_x_preferred":[
        "Segariu"
    ],
    "name:zho_x_preferred":[
        "\u585e\u52a0\u7559"
    ],
    "wof:name":"Segariu",
    "wof:placetype":"locality",
    "wof:population":1139
},
  "geometry": {"coordinates":[8.98163,39.56403],"type":"Point"}
}