{
  "type": "Feature",
  "properties": {
    "gn:admin1_code":"14.0",
    "gn:admin2_code":"SU",
    "gn:admin3_code":"111073.0",
    "gn:asciiname":"Segariu",
    "gn:country_code":"IT",
    "gn:dem":114,
    "gn:elevation":"117.0",
    "gn:feature_class":"P",
    "gn:feature_code":"PPLA3",
    "gn:name":"Segariu",
    "gn:population":1139,
    "gn:timezone":"Europe/Rome",
    "iso:country":"IT",
    "name:eng_x_preferred":[
        "Segariu"
    ],
    "name:epo_x_preferred":[
        "Segariu"
    ],
    "name:eus_x_preferred":[
        "Segariu"
    ],
    "name:fra_x_preferred":[
        "Segariu"
    ],
    "name:ita_x_preferred":[
        "Segariu"
    ],
    "name:nap_x_preferred":[
        "Segariu"
    ],
    "name:nld_x_preferred":[
        "Segariu"
    ],
    "name:pol_x_preferred":[
        "Segariu"
    ],
    "name:por_x_preferred":[
        "Segariu"
    ],
    "wof:name":"Segariu",
    "wof:placetype":"locality",
    "wof:population":1139
},
  "geometry": {"coordinates":[8.98163,39.56403],"type":"Point"}
}