{
  "type": "Feature",
  "properties": {
    "gn:admin1_code":"8",
    "gn:admin2_code":"GE",
    "gn:admin3_code":"10016.0",
    "gn:asciiname":"Chichizzola",
    "gn:country_code":"IT",
    "gn:dem":203,
    "gn:feature_class":"P",
    "gn:feature_code":"PPL",
    "gn:name":"Chichizzola",
    "gn:population":11,
    "gn:timezone":"Europe/Rome",
    "iso:country":"IT",
    "wof:name":"Chichizzola",
    "wof:placetype":"locality",
    "wof:population":11
},
  "geometry": {"coordinates":[9.21508,44.40687],"type":"Point"}
}