{
  "type": "Feature",
  "properties": {
    "gn:admin1_code":"9",
    "gn:admin2_code":"BG",
    "gn:admin3_code":"16246.0",
    "gn:asciiname":"Camissinone",
    "gn:country_code":"IT",
    "gn:dem":794,
    "gn:feature_class":"P",
    "gn:feature_code":"PPL",
    "gn:name":"Camissinone",
    "gn:population":29,
    "gn:timezone":"Europe/Rome",
    "iso:country":"IT",
    "wof:name":"Camissinone",
    "wof:placetype":"locality",
    "wof:population":29
},
  "geometry": {"coordinates":[9.64586,45.80544],"type":"Point"}
}