{
  "type": "Feature",
  "properties": {
    "gn:admin1_code":"15",
    "gn:admin2_code":"ME",
    "gn:admin3_code":"83020.0",
    "gn:asciiname":"Crocevia-Novello",
    "gn:country_code":"IT",
    "gn:dem":593,
    "gn:feature_class":"P",
    "gn:feature_code":"PPL",
    "gn:name":"Crocevia-Novello",
    "gn:population":77,
    "gn:timezone":"Europe/Rome",
    "iso:country":"IT",
    "wof:name":"Crocevia-Novello",
    "wof:placetype":"locality",
    "wof:population":77
},
  "geometry": {"coordinates":[14.84259,38.11502],"type":"Point"}
}