{
  "type": "Feature",
  "properties": {
    "gn:admin1_code":"19",
    "gn:admin2_code":"AO",
    "gn:admin3_code":"7065.0",
    "gn:asciiname":"Cillian",
    "gn:country_code":"IT",
    "gn:dem":617,
    "gn:feature_class":"P",
    "gn:feature_code":"PPL",
    "gn:name":"Cillian",
    "gn:population":102,
    "gn:timezone":"Europe/Rome",
    "iso:country":"IT",
    "wof:name":"Cillian",
    "wof:placetype":"locality",
    "wof:population":102
},
  "geometry": {"coordinates":[7.66029,45.74292],"type":"Point"}
}