{
  "type": "Feature",
  "properties": {
    "gn:admin1_code":"20",
    "gn:admin2_code":"VR",
    "gn:admin3_code":"23071.0",
    "gn:asciiname":"Comotto",
    "gn:country_code":"IT",
    "gn:dem":42,
    "gn:feature_class":"P",
    "gn:feature_code":"PPL",
    "gn:name":"Comotto",
    "gn:population":76,
    "gn:timezone":"Europe/Rome",
    "iso:country":"IT",
    "wof:name":"Comotto",
    "wof:placetype":"locality",
    "wof:population":76
},
  "geometry": {"coordinates":[11.01847,45.38277],"type":"Point"}
}