{
  "type": "Feature",
  "properties": {
    "iso:country":"IT",
    "name:eng_x_preferred":[
        "Valtesse"
    ],
    "name:ita_x_preferred":[
        "Valtesse"
    ],
    "qs:gn_adm0_cc":"IT",
    "qs:gn_fcode":"PPLX",
    "qs:gn_local":3182164,
    "qs:gn_nam_loc":"Bergamo, Bergamo, Bergamo, Lombardia, IT",
    "qs:gn_namadm1":"09",
    "qs:gn_name":"Valtesse",
    "qs:local_max":6952,
    "qs:local_sum":6952,
    "qs:localhoods":1,
    "qs:name":"Valtesse",
    "qs:name_adm0":"Italia",
    "qs:name_adm1":"Lombardia",
    "qs:name_adm2":"Bergamo",
    "qs:name_lau":"Bergamo",
    "qs:name_local":"Bergamo",
    "qs:photo_max":901,
    "qs:photo_sum":6952,
    "qs:placetype":"Suburb",
    "qs:quad_count":140,
    "qs:woe_adm0":23424853,
    "qs:woe_adm1":7153338,
    "qs:woe_adm2":12591880,
    "qs:woe_lau":12676717,
    "qs:woe_local":710893,
    "qs:woe_ver":"7.10.0",
    "wd:wordcount":92,
    "wof:name":"Valtesse",
    "wof:placetype":"neighbourhood"
},
  "geometry": {"coordinates":[9.663154,45.703552],"type":"Point"}
}