{
  "type": "Feature",
  "properties": {
    "gn:admin1_code":"16.0",
    "gn:admin2_code":"FI",
    "gn:admin3_code":"48014.0",
    "gn:asciiname":"Pozzale-Case Nuove",
    "gn:country_code":"IT",
    "gn:dem":35,
    "gn:feature_class":"P",
    "gn:feature_code":"PPL",
    "gn:name":"Pozzale-Case Nuove",
    "gn:population":1665,
    "gn:timezone":"Europe/Rome",
    "iso:country":"IT",
    "wof:name":"Pozzale-Case Nuove",
    "wof:placetype":"locality",
    "wof:population":1665
},
  "geometry": {"coordinates":[10.95651,43.69584],"type":"Point"}
}