{
  "type": "Feature",
  "properties": {
    "gn:admin1_code":"9",
    "gn:admin2_code":"CR",
    "gn:admin3_code":"19033.0",
    "gn:asciiname":"San Sillo",
    "gn:country_code":"IT",
    "gn:dem":50,
    "gn:feature_class":"P",
    "gn:feature_code":"PPL",
    "gn:name":"San Sillo",
    "gn:population":11,
    "gn:timezone":"Europe/Rome",
    "iso:country":"IT",
    "wof:name":"San Sillo",
    "wof:placetype":"locality",
    "wof:population":11
},
  "geometry": {"coordinates":[10.1014,45.20709],"type":"Point"}
}