{
  "type": "Feature",
  "properties": {
    "gn:admin1_code":"3",
    "gn:admin2_code":"CS",
    "gn:admin3_code":"78070.0",
    "gn:asciiname":"Calderotto",
    "gn:country_code":"IT",
    "gn:dem":752,
    "gn:feature_class":"P",
    "gn:feature_code":"PPL",
    "gn:name":"Calderotto",
    "gn:population":40,
    "gn:timezone":"Europe/Rome",
    "iso:country":"IT",
    "wof:name":"Calderotto",
    "wof:placetype":"locality",
    "wof:population":40
},
  "geometry": {"coordinates":[16.31448,39.45669],"type":"Point"}
}