{
  "type": "Feature",
  "properties": {
    "gn:admin1_code":"9",
    "gn:admin2_code":"LO",
    "gn:admin3_code":"98030.0",
    "gn:asciiname":"Pantigliate",
    "gn:country_code":"IT",
    "gn:dem":61,
    "gn:feature_class":"P",
    "gn:feature_code":"PPL",
    "gn:name":"Pantigliate",
    "gn:population":142,
    "gn:timezone":"Europe/Rome",
    "iso:country":"IT",
    "wof:name":"Pantigliate",
    "wof:placetype":"locality",
    "wof:population":142
},
  "geometry": {"coordinates":[9.53474,45.17447],"type":"Point"}
}