{
  "type": "Feature",
  "properties": {
    "gn:admin1_code":"9",
    "gn:admin2_code":"LO",
    "gn:admin3_code":"98030.0",
    "gn:asciiname":"Pantigliate",
    "gn:country_code":"IT",
    "gn:dem":61,
    "gn:feature_class":"P",
    "gn:feature_code":"PPL",
    "gn:name":"Pantigliate",
    "gn:population":142,
    "gn:timezone":"Europe/Rome",
    "iso:country":"IT",
    "name:azb_x_preferred":[
        "\u067e\u0627\u0646\u062a\u06cc\u0644\u06cc\u0627\u062a\u0647"
    ],
    "name:bul_x_preferred":[
        "\u041f\u0430\u043d\u0442\u0438\u043b\u044f\u0442\u0435"
    ],
    "name:ceb_x_preferred":[
        "Pantigliate"
    ],
    "name:deu_x_preferred":[
        "Pantigliate"
    ],
    "name:epo_x_preferred":[
        "Pantigliate"
    ],
    "name:eus_x_preferred":[
        "Pantigliate"
    ],
    "name:fas_x_preferred":[
        "\u067e\u0627\u0646\u062a\u06cc\u0644\u06cc\u0627\u062a\u0647"
    ],
    "name:fra_x_preferred":[
        "Pantigliate"
    ],
    "name:hun_x_preferred":[
        "Pantigliate"
    ],
    "name:hye_x_preferred":[
        "\u054a\u0561\u0576\u057f\u056b\u056c\u056b\u0561\u057f\u0565"
    ],
    "name:ita_x_preferred":[
        "Pantigliate"
    ],
    "name:jpn_x_preferred":[
        "\u30d1\u30f3\u30c6\u30a3\u30ea\u30a2\u30fc\u30c6"
    ],
    "name:kaz_x_preferred":[
        "\u041f\u0430\u043d\u0442\u0438\u043b\u044c\u044f\u0442\u0435"
    ],
    "name:lat_x_preferred":[
        "Pantelliatum"
    ],
    "name:lmo_x_preferred":[
        "Pantijaa"
    ],
    "name:msa_x_preferred":[
        "Pantigliate"
    ],
    "name:nap_x_preferred":[
        "Pantigliate"
    ],
    "name:nld_x_preferred":[
        "Pantigliate"
    ],
    "name:pms_x_preferred":[
        "Pantigliate"
    ],
    "name:pol_x_preferred":[
        "Pantigliate"
    ],
    "name:por_x_preferred":[
        "Pantigliate"
    ],
    "name:ron_x_preferred":[
        "Pantigliate"
    ],
    "name:rus_x_preferred":[
        "\u041f\u0430\u043d\u0442\u0438\u043b\u044c\u044f\u0442\u0435"
    ],
    "name:scn_x_preferred":[
        "Pantigliate"
    ],
    "name:spa_x_preferred":[
        "Pantigliate"
    ],
    "name:srp_x_preferred":[
        "\u041f\u0430\u043d\u0442\u0438\u0459\u0430\u0442\u0435"
    ],
    "name:tgl_x_preferred":[
        "Pantigliate"
    ],
    "name:ukr_x_preferred":[
        "\u041f\u0430\u043d\u0442\u0456\u043b\u044c\u044f\u0442\u0435"
    ],
    "name:uzb_x_preferred":[
        "Pantigliate"
    ],
    "name:vie_x_preferred":[
        "Pantigliate"
    ],
    "name:vol_x_preferred":[
        "Pantigliate"
    ],
    "name:war_x_preferred":[
        "Pantigliate"
    ],
    "name:zho_x_preferred":[
        "\u6f58\u8482\u5229\u4e9a\u6cf0"
    ],
    "wof:name":"Pantigliate",
    "wof:placetype":"locality",
    "wof:population":142
},
  "geometry": {"coordinates":[9.53474,45.17447],"type":"Point"}
}