{
  "type": "Feature",
  "properties": {
    "gn:admin1_code":"12",
    "gn:admin2_code":"CN",
    "gn:admin3_code":"4029.0",
    "gn:asciiname":"Ronchi",
    "gn:country_code":"IT",
    "gn:dem":276,
    "gn:feature_class":"P",
    "gn:feature_code":"PPL",
    "gn:name":"Ronchi",
    "gn:population":66,
    "gn:timezone":"Europe/Rome",
    "iso:country":"IT",
    "wof:name":"Ronchi",
    "wof:placetype":"locality",
    "wof:population":66
},
  "geometry": {"coordinates":[7.80749,44.74554000000001],"type":"Point"}
}