{
  "type": "Feature",
  "properties": {
    "gn:admin1_code":"14.0",
    "gn:admin2_code":"SS",
    "gn:admin3_code":"90063.0",
    "gn:asciiname":"Ruoni",
    "gn:country_code":"IT",
    "gn:dem":77,
    "gn:elevation":"98.0",
    "gn:feature_class":"P",
    "gn:feature_code":"PPL",
    "gn:name":"Ruoni",
    "gn:population":375,
    "gn:timezone":"Europe/Rome",
    "iso:country":"IT",
    "wof:name":"Ruoni",
    "wof:placetype":"locality",
    "wof:population":375
},
  "geometry": {"coordinates":[9.22088,41.22547],"type":"Point"}
}