{
  "type": "Feature",
  "properties": {
    "gn:admin1_code":"9",
    "gn:admin2_code":"PV",
    "gn:admin3_code":"18016.0",
    "gn:asciiname":"Staghiglione",
    "gn:country_code":"IT",
    "gn:dem":262,
    "gn:feature_class":"P",
    "gn:feature_code":"PPL",
    "gn:name":"Staghiglione",
    "gn:population":54,
    "gn:timezone":"Europe/Rome",
    "iso:country":"IT",
    "wof:name":"Staghiglione",
    "wof:placetype":"locality",
    "wof:population":54
},
  "geometry": {"coordinates":[9.16686,44.9632],"type":"Point"}
}