{
  "type": "Feature",
  "properties": {
    "gn:admin1_code":"15",
    "gn:admin2_code":"EN",
    "gn:admin3_code":"86013.0",
    "gn:asciiname":"Contrada Perciata",
    "gn:country_code":"IT",
    "gn:dem":719,
    "gn:feature_class":"P",
    "gn:feature_code":"PPLL",
    "gn:name":"Contrada Perciata",
    "gn:population":9,
    "gn:timezone":"Europe/Rome",
    "iso:country":"IT",
    "wof:name":"Contrada Perciata",
    "wof:placetype":"locality",
    "wof:population":9
},
  "geometry": {"coordinates":[14.4207,37.64649],"type":"Point"}
}