{
  "type": "Feature",
  "properties": {
    "gn:admin1_code":"1",
    "gn:admin2_code":"TE",
    "gn:admin3_code":"67045.0",
    "gn:asciiname":"Tozzanella",
    "gn:country_code":"IT",
    "gn:dem":558,
    "gn:feature_class":"P",
    "gn:feature_code":"PPL",
    "gn:name":"Tozzanella",
    "gn:population":43,
    "gn:timezone":"Europe/Rome",
    "iso:country":"IT",
    "wof:name":"Tozzanella",
    "wof:placetype":"locality",
    "wof:population":43
},
  "geometry": {"coordinates":[13.632,42.54244],"type":"Point"}
}