{
  "type": "Feature",
  "properties": {
    "gn:admin1_code":"12.0",
    "gn:admin2_code":"BI",
    "gn:admin3_code":"96018.0",
    "gn:asciiname":"Cascina Galanta",
    "gn:country_code":"IT",
    "gn:dem":278,
    "gn:feature_class":"P",
    "gn:feature_code":"PPL",
    "gn:name":"Cascina Galanta",
    "gn:population":22,
    "gn:timezone":"Europe/Rome",
    "iso:country":"IT",
    "wof:name":"Cascina Galanta",
    "wof:placetype":"locality",
    "wof:population":22
},
  "geometry": {"coordinates":[8.05864,45.49023],"type":"Point"}
}