{
  "type": "Feature",
  "properties": {
    "gn:admin1_code":"12",
    "gn:admin2_code":"TO",
    "gn:admin3_code":"1262.0",
    "gn:asciiname":"Torre",
    "gn:country_code":"IT",
    "gn:dem":242,
    "gn:feature_class":"P",
    "gn:feature_code":"PPL",
    "gn:name":"Torre",
    "gn:population":56,
    "gn:timezone":"Europe/Rome",
    "iso:country":"IT",
    "wof:name":"Torre",
    "wof:placetype":"locality",
    "wof:population":56
},
  "geometry": {"coordinates":[7.86407,45.11522],"type":"Point"}
}