{
  "type": "Feature",
  "properties": {
    "gn:admin1_code":"14",
    "gn:admin2_code":"CA",
    "gn:admin3_code":"92011.0",
    "gn:asciiname":"Sa Perda Su Gattu",
    "gn:country_code":"IT",
    "gn:dem":63,
    "gn:feature_class":"P",
    "gn:feature_code":"PPL",
    "gn:name":"Sa Perda Su Gattu",
    "gn:population":136,
    "gn:timezone":"Europe/Rome",
    "iso:country":"IT",
    "wof:name":"Sa Perda Su Gattu",
    "wof:placetype":"locality",
    "wof:population":136
},
  "geometry": {"coordinates":[8.96679,39.16392000000001],"type":"Point"}
}