{
  "type": "Feature",
  "properties": {
    "gn:admin1_code":"7.0",
    "gn:admin2_code":"RI",
    "gn:admin3_code":"57057.0",
    "gn:asciiname":"Favischio",
    "gn:country_code":"IT",
    "gn:dem":805,
    "gn:elevation":"808.0",
    "gn:feature_class":"P",
    "gn:feature_code":"PPL",
    "gn:name":"Favischio",
    "gn:population":24,
    "gn:timezone":"Europe/Rome",
    "iso:country":"IT",
    "wof:name":"Favischio",
    "wof:placetype":"locality",
    "wof:population":24
},
  "geometry": {"coordinates":[13.08209,42.52898],"type":"Point"}
}