{
  "type": "Feature",
  "properties": {
    "gn:admin1_code":"9",
    "gn:admin2_code":"LO",
    "gn:admin3_code":"98031.0",
    "gn:asciiname":"Riolo",
    "gn:country_code":"IT",
    "gn:dem":72,
    "gn:feature_class":"P",
    "gn:feature_code":"PPL",
    "gn:name":"Riolo",
    "gn:population":203,
    "gn:timezone":"Europe/Rome",
    "iso:country":"IT",
    "wof:name":"Riolo",
    "wof:placetype":"locality",
    "wof:population":203
},
  "geometry": {"coordinates":[9.51996,45.33677],"type":"Point"}
}