{
  "type": "Feature",
  "properties": {
    "gn:admin1_code":"12",
    "gn:admin2_code":"AL",
    "gn:admin3_code":"6102.0",
    "gn:asciiname":"Poldini",
    "gn:country_code":"IT",
    "gn:dem":359,
    "gn:feature_class":"P",
    "gn:feature_code":"PPL",
    "gn:name":"Poldini",
    "gn:population":16,
    "gn:timezone":"Europe/Rome",
    "iso:country":"IT",
    "wof:name":"Poldini",
    "wof:placetype":"locality",
    "wof:population":16
},
  "geometry": {"coordinates":[9.07139,44.77491],"type":"Point"}
}