{
  "type": "Feature",
  "properties": {
    "gn:admin1_code":"12",
    "gn:admin2_code":"BI",
    "gn:admin3_code":"96035.0",
    "gn:asciiname":"Aral Grande",
    "gn:country_code":"IT",
    "gn:dem":439,
    "gn:feature_class":"P",
    "gn:feature_code":"PPL",
    "gn:name":"Aral Grande",
    "gn:population":31,
    "gn:timezone":"Europe/Rome",
    "iso:country":"IT",
    "wof:name":"Aral Grande",
    "wof:placetype":"locality",
    "wof:population":31
},
  "geometry": {"coordinates":[7.98453,45.53371],"type":"Point"}
}