{
  "type": "Feature",
  "properties": {
    "iso:country":"IT",
    "name:ita_x_preferred":[
        "Trenno"
    ],
    "name:lmo_x_preferred":[
        "Trenn"
    ],
    "wof:name":"Trenno",
    "wof:placetype":"neighbourhood"
},
  "geometry": {"coordinates":[9.10142656273795,45.49233902527335],"type":"Point"}
}