{
  "type": "Feature",
  "properties": {
    "gn:admin1_code":"20",
    "gn:admin2_code":"TV",
    "gn:admin3_code":"26013.0",
    "gn:asciiname":"Vallo",
    "gn:country_code":"IT",
    "gn:dem":45,
    "gn:feature_class":"P",
    "gn:feature_code":"PPL",
    "gn:name":"Vallo",
    "gn:population":106,
    "gn:timezone":"Europe/Rome",
    "iso:country":"IT",
    "name:ceb_x_preferred":[
        "Vallo"
    ],
    "name:deu_x_preferred":[
        "Vallo"
    ],
    "name:fra_x_preferred":[
        "Vallo"
    ],
    "name:glg_x_preferred":[
        "Vallo"
    ],
    "name:ita_x_preferred":[
        "Vallo"
    ],
    "name:por_x_preferred":[
        "Vallo"
    ],
    "name:rus_x_preferred":[
        "\u0412\u0430\u043b\u043b\u043e"
    ],
    "name:spa_x_preferred":[
        "Vallo"
    ],
    "name:srp_x_preferred":[
        "Valo"
    ],
    "name:swe_x_preferred":[
        "Vallo"
    ],
    "wof:name":"Vallo",
    "wof:placetype":"locality",
    "wof:population":106
},
  "geometry": {"coordinates":[11.86561,45.67401],"type":"Point"}
}