{
  "type": "Feature",
  "properties": {
    "gn:elevation":736,
    "gn:population":337,
    "iso:country":"IT",
    "name:bel_x_preferred":[
        "\u041a\u043e\u0440\u043d\u0430-\u0406\u043c\u0430\u043d\u044c\u044f"
    ],
    "name:deu_x_preferred":[
        "Corna Imagna"
    ],
    "name:epo_x_preferred":[
        "Corna Imagna"
    ],
    "name:eus_x_preferred":[
        "Corna Imagna"
    ],
    "name:fra_x_preferred":[
        "Corna Imagna"
    ],
    "name:hbs_x_preferred":[
        "Corna Imagna"
    ],
    "name:hun_x_preferred":[
        "Corna Imagna"
    ],
    "name:hye_x_preferred":[
        "\u053f\u0578\u0580\u0576\u0561 \u053b\u0574\u0561\u0576\u0575\u0561"
    ],
    "name:ina_x_preferred":[
        "Corna Imagna"
    ],
    "name:ita_x_preferred":[
        "Corna Imagna"
    ],
    "name:jpn_x_preferred":[
        "\u30b3\u30eb\u30ca\u30fb\u30a4\u30de\u30fc\u30cb\u30e3"
    ],
    "name:kaz_x_preferred":[
        "\u041a\u043e\u0440\u043d\u0430-\u0418\u043c\u0430\u043d\u044c\u044f"
    ],
    "name:lat_x_preferred":[
        "Corna"
    ],
    "name:lmo_x_preferred":[
        "C\u00f2rna"
    ],
    "name:msa_x_preferred":[
        "Corna Imagna"
    ],
    "name:nap_x_preferred":[
        "Corna Imagna"
    ],
    "name:nld_x_preferred":[
        "Corna Imagna"
    ],
    "name:pms_x_preferred":[
        "Corna Imagna"
    ],
    "name:pol_x_preferred":[
        "Corna Imagna"
    ],
    "name:por_x_preferred":[
        "Corna Imagna"
    ],
    "name:ron_x_preferred":[
        "Corna Imagna"
    ],
    "name:rus_x_preferred":[
        "\u041a\u043e\u0440\u043d\u0430-\u0418\u043c\u0430\u043d\u044c\u044f"
    ],
    "name:scn_x_preferred":[
        "Corna Imagna"
    ],
    "name:spa_x_preferred":[
        "Corna Imagna"
    ],
    "name:srp_x_preferred":[
        "\u041a\u043e\u0440\u043d\u0430 \u0418\u043c\u0430\u045a\u0430"
    ],
    "name:tgl_x_preferred":[
        "Corna Imagna"
    ],
    "name:ukr_x_preferred":[
        "\u041a\u043e\u0440\u043d\u0430-\u0406\u043c\u0430\u043d\u044c\u044f"
    ],
    "name:uzb_x_preferred":[
        "Corna Imagna"
    ],
    "name:vie_x_preferred":[
        "Corna Imagna"
    ],
    "name:vol_x_preferred":[
        "Corna Imagna"
    ],
    "name:war_x_preferred":[
        "Corna Imagna"
    ],
    "name:zho_x_preferred":[
        "\u79d1\u5c14\u7eb3\u4f0a\u9a6c\u5c3c\u4e9a"
    ],
    "qs:a0":"Italia",
    "qs:a1":"*Bergamo",
    "qs:a1r":"0Lombardia",
    "qs:adm0":"Italia",
    "qs:la_lc":"*",
    "qs:level":"locality",
    "qs:loc":"Corna Imagna",
    "qs:loc_alt":"Corna Imagna",
    "qs:pop":0,
    "qs:type":"buffered point",
    "wd:wordcount":84,
    "wof:lang":[
        "ita"
    ],
    "wof:name":"Corna Imagna",
    "wof:placetype":"locality",
    "wof:population":337
},
  "geometry": {"coordinates":[9.54583,45.83139],"type":"Point"}
}