{
  "type": "Feature",
  "properties": {
    "gn:admin1_code":"7",
    "gn:admin2_code":"FR",
    "gn:admin3_code":"60008.0",
    "gn:asciiname":"Tramonti I",
    "gn:country_code":"IT",
    "gn:dem":213,
    "gn:feature_class":"P",
    "gn:feature_code":"PPL",
    "gn:name":"Tramonti I",
    "gn:population":64,
    "gn:timezone":"Europe/Rome",
    "iso:country":"IT",
    "wof:name":"Tramonti I",
    "wof:placetype":"locality",
    "wof:population":64
},
  "geometry": {"coordinates":[13.58349,41.56351],"type":"Point"}
}