{
  "type": "Feature",
  "properties": {
    "gn:admin1_code":"4",
    "gn:admin2_code":"SA",
    "gn:admin3_code":"65154.0",
    "gn:asciiname":"Spinacelli",
    "gn:country_code":"IT",
    "gn:dem":216,
    "gn:feature_class":"P",
    "gn:feature_code":"PPL",
    "gn:name":"Spinacelli",
    "gn:population":30,
    "gn:timezone":"Europe/Rome",
    "iso:country":"IT",
    "wof:name":"Spinacelli",
    "wof:placetype":"locality",
    "wof:population":30
},
  "geometry": {"coordinates":[15.24255,40.22786],"type":"Point"}
}