{
  "type": "Feature",
  "properties": {
    "gn:admin1_code":"5.0",
    "gn:admin2_code":"PR",
    "gn:admin3_code":"34009.0",
    "gn:asciiname":"Stradella",
    "gn:country_code":"IT",
    "gn:dem":103,
    "gn:feature_class":"P",
    "gn:feature_code":"PPL",
    "gn:name":"Stradella",
    "gn:population":88,
    "gn:timezone":"Europe/Rome",
    "iso:country":"IT",
    "wof:name":"Stradella",
    "wof:placetype":"locality",
    "wof:population":88
},
  "geometry": {"coordinates":[10.24774,44.76267],"type":"Point"}
}