{
  "type": "Feature",
  "properties": {
    "gn:admin1_code":"11",
    "gn:admin2_code":"IS",
    "gn:admin3_code":"94051.0",
    "gn:asciiname":"Villa San Michele",
    "gn:country_code":"IT",
    "gn:dem":920,
    "gn:feature_class":"P",
    "gn:feature_code":"PPL",
    "gn:name":"Villa San Michele",
    "gn:population":224,
    "gn:timezone":"Europe/Rome",
    "iso:country":"IT",
    "name:cat_x_preferred":[
        "Villa San Michele"
    ],
    "name:deu_x_preferred":[
        "Villa San Michele"
    ],
    "name:fra_x_preferred":[
        "Villa San Michele"
    ],
    "name:hun_x_preferred":[
        "Villa San Michele"
    ],
    "name:ita_x_preferred":[
        "Villa San Michele"
    ],
    "name:kor_x_preferred":[
        "\ube4c\ub77c \uc0b0 \ubbf8\ucf08\ub808"
    ],
    "name:nor_x_preferred":[
        "Villa San Michele"
    ],
    "name:ron_x_preferred":[
        "Villa San Michele"
    ],
    "name:swe_x_preferred":[
        "San Michele"
    ],
    "name:zho_x_preferred":[
        "\u5723\u5f25\u989d\u5c14\u522b\u5885"
    ],
    "wof:name":"Villa San Michele",
    "wof:placetype":"locality",
    "wof:population":224
},
  "geometry": {"coordinates":[14.2359,41.74098],"type":"Point"}
}