{
  "type": "Feature",
  "properties": {
    "iso:country":"IT",
    "qs_pg:aaroncc":"IT",
    "qs_pg:name":"Poggio Azzuano",
    "qs_pg:name_adm0":"Italia",
    "qs_pg:name_adm1":"Umbria",
    "qs_pg:photos":255,
    "qs_pg:photos_1k":52,
    "qs_pg:photos_9k":1,
    "qs_pg:photos_9r":4,
    "qs_pg:photos_all":255,
    "qs_pg:photos_sr":5,
    "qs_pg:pop_sr":0,
    "qs_pg:qs_pg_placetype":"locality",
    "qs_pg:qs_pg_placetype_gp":"Town",
    "qs_pg:woe_adm0":23424853,
    "woe:adm0_id":23424853,
    "woe:name_adm0":"Italia",
    "woe:name_adm1":"Umbria",
    "woe:placetype":"Town",
    "wof:name":"Poggio Azzuano",
    "wof:placetype":"locality"
},
  "geometry": {"coordinates":[12.557548,42.634779],"type":"Point"}
}