{
  "type": "Feature",
  "properties": {
    "gn:admin1_code":"11.0",
    "gn:admin2_code":"IS",
    "gn:admin3_code":"94037.0",
    "gn:asciiname":"Casteldicroce (Vuttaro)",
    "gn:country_code":"IT",
    "gn:dem":628,
    "gn:feature_class":"P",
    "gn:feature_code":"PPL",
    "gn:name":"Casteldicroce (Vuttaro)",
    "gn:population":20,
    "gn:timezone":"Europe/Rome",
    "iso:country":"IT",
    "wof:name":"Casteldicroce (Vuttaro)",
    "wof:placetype":"locality",
    "wof:population":20
},
  "geometry": {"coordinates":[14.45594,41.7583],"type":"Point"}
}