{
  "type": "Feature",
  "properties": {
    "gn:country":"IT",
    "gn:fcode":"PPL",
    "gn:population":0,
    "iso:country":"IT",
    "name:cat_x_preferred":[
        "Viboldone"
    ],
    "name:ceb_x_preferred":[
        "Viboldone"
    ],
    "name:ces_x_preferred":[
        "Viboldone"
    ],
    "name:che_x_preferred":[
        "\u0412\u0438\u0431\u043e\u043b\u0434\u043e\u043d\u0435"
    ],
    "name:dan_x_preferred":[
        "Viboldone"
    ],
    "name:deu_x_preferred":[
        "Viboldone"
    ],
    "name:eng_x_preferred":[
        "Viboldone"
    ],
    "name:eus_x_preferred":[
        "Viboldone"
    ],
    "name:fin_x_preferred":[
        "Viboldone"
    ],
    "name:fra_x_preferred":[
        "Viboldone"
    ],
    "name:hun_x_preferred":[
        "Viboldone"
    ],
    "name:ind_x_preferred":[
        "Viboldone"
    ],
    "name:ita_x_preferred":[
        "Viboldone"
    ],
    "name:lmo_x_preferred":[
        "Viboldon"
    ],
    "name:nld_x_preferred":[
        "Viboldone"
    ],
    "name:nno_x_preferred":[
        "Viboldone"
    ],
    "name:nob_x_preferred":[
        "Viboldone"
    ],
    "name:oci_x_preferred":[
        "Viboldone"
    ],
    "name:pol_x_preferred":[
        "Viboldone"
    ],
    "name:por_x_preferred":[
        "Viboldone"
    ],
    "name:ron_x_preferred":[
        "Viboldone"
    ],
    "name:slk_x_preferred":[
        "Viboldone"
    ],
    "name:slv_x_preferred":[
        "Viboldone"
    ],
    "name:spa_x_preferred":[
        "Viboldone"
    ],
    "name:srp_x_preferred":[
        "Viboldone"
    ],
    "name:swe_x_preferred":[
        "Viboldone"
    ],
    "name:tat_x_preferred":[
        "\u0412\u0438\u0431\u043e\u043b\u0434\u043e\u043d\u0435"
    ],
    "name:tgl_x_preferred":[
        "Viboldone"
    ],
    "name:tur_x_preferred":[
        "Viboldone"
    ],
    "name:war_x_preferred":[
        "Viboldone"
    ],
    "qs_pg:aaroncc":"IT",
    "qs_pg:gn_country":"IT",
    "qs_pg:gn_fcode":"PPL",
    "qs_pg:gn_pop":0,
    "qs_pg:name":"Viboldone",
    "qs_pg:name_adm0":"Italia",
    "qs_pg:name_adm1":"Lombardia",
    "qs_pg:photos":47,
    "qs_pg:photos_1k":10,
    "qs_pg:photos_9k":1,
    "qs_pg:photos_9r":2,
    "qs_pg:photos_all":47,
    "qs_pg:photos_sr":2,
    "qs_pg:pop_sr":0,
    "qs_pg:qs_pg_placetype":"locality",
    "qs_pg:qs_pg_placetype_gp":"Town",
    "qs_pg:woe_adm0":23424853,
    "woe:adm0_id":23424853,
    "woe:name_adm0":"Italia",
    "woe:name_adm1":"Lombardia",
    "woe:placetype":"Town",
    "wof:name":"Viboldone",
    "wof:placetype":"locality",
    "wof:population":87
},
  "geometry": {"coordinates":[9.27744,45.38555],"type":"Point"}
}