{
  "type": "Feature",
  "properties": {
    "gn:admin1_code":"12",
    "gn:admin2_code":"CN",
    "gn:admin3_code":"4095.0",
    "gn:asciiname":"Regione Porenca",
    "gn:country_code":"IT",
    "gn:dem":718,
    "gn:feature_class":"P",
    "gn:feature_code":"PPLL",
    "gn:name":"Regione Porenca",
    "gn:population":10,
    "gn:timezone":"Europe/Rome",
    "iso:country":"IT",
    "wof:name":"Regione Porenca",
    "wof:placetype":"locality",
    "wof:population":10
},
  "geometry": {"coordinates":[8.00949,44.24089],"type":"Point"}
}