{
  "type": "Feature",
  "properties": {
    "gn:admin1_code":"16",
    "gn:admin2_code":"AR",
    "gn:admin3_code":"51026.0",
    "gn:asciiname":"Acquaborra-Caselle",
    "gn:country_code":"IT",
    "gn:dem":155,
    "gn:feature_class":"P",
    "gn:feature_code":"PPL",
    "gn:name":"Acquaborra-Caselle",
    "gn:population":54,
    "gn:timezone":"Europe/Rome",
    "iso:country":"IT",
    "wof:name":"Acquaborra-Caselle",
    "wof:placetype":"locality",
    "wof:population":54
},
  "geometry": {"coordinates":[11.62621,43.51073],"type":"Point"}
}