{
  "type": "Feature",
  "properties": {
    "iso:country":"IT",
    "name:ara_x_preferred":[
        "\u0627\u0644\u0645\u0627\u0631\u0646"
    ],
    "name:bel_x_preferred":[
        "\u041c\u0430\u0440\u043d\u0430"
    ],
    "name:bre_x_preferred":[
        "Marne"
    ],
    "name:cat_x_preferred":[
        "Marne"
    ],
    "name:ceb_x_preferred":[
        "Marne"
    ],
    "name:ces_x_preferred":[
        "Marne"
    ],
    "name:chv_x_preferred":[
        "\u041c\u0430\u0440\u043d\u0430"
    ],
    "name:cym_x_preferred":[
        "Marne"
    ],
    "name:deu_x_preferred":[
        "Marne"
    ],
    "name:epo_x_preferred":[
        "Marne"
    ],
    "name:fin_x_preferred":[
        "Marne"
    ],
    "name:fra_x_preferred":[
        "Marne"
    ],
    "name:fry_x_preferred":[
        "Marne"
    ],
    "name:hun_x_preferred":[
        "Marne"
    ],
    "name:ita_x_preferred":[
        "Marne"
    ],
    "name:jpn_x_preferred":[
        "\u30de\u30eb\u30cc"
    ],
    "name:lav_x_preferred":[
        "Marne"
    ],
    "name:lim_x_preferred":[
        "Marne"
    ],
    "name:ltz_x_preferred":[
        "Marne"
    ],
    "name:nds_x_preferred":[
        "Marne"
    ],
    "name:nld_x_preferred":[
        "Marne"
    ],
    "name:nor_x_preferred":[
        "Marne"
    ],
    "name:pol_x_preferred":[
        "Marne"
    ],
    "name:por_x_preferred":[
        "Marne"
    ],
    "name:rus_x_preferred":[
        "\u041c\u0430\u0440\u043d\u0430"
    ],
    "name:spa_x_preferred":[
        "Marne"
    ],
    "name:srp_x_preferred":[
        "\u041c\u0430\u0440\u043d"
    ],
    "name:swe_x_preferred":[
        "Marne"
    ],
    "name:tur_x_preferred":[
        "Marne"
    ],
    "name:ukr_x_preferred":[
        "\u041c\u0430\u0440\u043d\u0430"
    ],
    "name:vol_x_preferred":[
        "Marne"
    ],
    "qs_pg:aaroncc":"IT",
    "qs_pg:name":"Marne",
    "qs_pg:name_adm0":"Italia",
    "qs_pg:name_adm1":"Lombardia",
    "qs_pg:photos":45,
    "qs_pg:photos_1k":9,
    "qs_pg:photos_9k":1,
    "qs_pg:photos_9r":2,
    "qs_pg:photos_all":45,
    "qs_pg:photos_sr":2,
    "qs_pg:pop_sr":0,
    "qs_pg:qs_pg_placetype":"locality",
    "qs_pg:qs_pg_placetype_gp":"Town",
    "qs_pg:woe_adm0":23424853,
    "woe:adm0_id":23424853,
    "woe:name_adm0":"Italia",
    "woe:name_adm1":"Lombardia",
    "woe:placetype":"Town",
    "wof:name":"Marne",
    "wof:placetype":"locality"
},
  "geometry": {"coordinates":[9.559521,45.624843],"type":"Point"}
}