{
  "type": "Feature",
  "properties": {
    "gn:admin1_code":"12",
    "gn:admin2_code":"CN",
    "gn:admin3_code":"4081.0",
    "gn:asciiname":"Pian del Troglio",
    "gn:country_code":"IT",
    "gn:dem":284,
    "gn:feature_class":"P",
    "gn:feature_code":"PPL",
    "gn:name":"Pian del Troglio",
    "gn:population":25,
    "gn:timezone":"Europe/Rome",
    "iso:country":"IT",
    "wof:name":"Pian del Troglio",
    "wof:placetype":"locality",
    "wof:population":25
},
  "geometry": {"coordinates":[7.92683,44.53477],"type":"Point"}
}