{
  "type": "Feature",
  "properties": {
    "gn:admin1_code":"8",
    "gn:admin2_code":"SP",
    "gn:admin3_code":"11023.0",
    "gn:asciiname":"Montecapri",
    "gn:country_code":"IT",
    "gn:dem":255,
    "gn:feature_class":"P",
    "gn:feature_code":"PPL",
    "gn:name":"Montecapri",
    "gn:population":26,
    "gn:timezone":"Europe/Rome",
    "iso:country":"IT",
    "wof:name":"Montecapri",
    "wof:placetype":"locality",
    "wof:population":26
},
  "geometry": {"coordinates":[9.79244,44.14748],"type":"Point"}
}