{
  "type": "Feature",
  "properties": {
    "gn:admin1_code":"13.0",
    "gn:admin2_code":"LE",
    "gn:admin3_code":"75048.0",
    "gn:asciiname":"Area Industriale",
    "gn:country_code":"IT",
    "gn:dem":38,
    "gn:feature_class":"P",
    "gn:feature_code":"PPLL",
    "gn:name":"Area Industriale",
    "gn:population":0,
    "gn:timezone":"Europe/Rome",
    "iso:country":"IT",
    "wof:name":"Area Industriale",
    "wof:placetype":"locality"
},
  "geometry": {"coordinates":[18.06534,40.31957],"type":"Point"}
}