{
  "type": "Feature",
  "properties": {
    "gn:admin1_code":"9.0",
    "gn:admin2_code":"MI",
    "gn:admin3_code":"15139.0",
    "gn:asciiname":"San Martino Olearo",
    "gn:country_code":"IT",
    "gn:dem":97,
    "gn:elevation":"97.0",
    "gn:feature_class":"P",
    "gn:feature_code":"PPL",
    "gn:name":"San Martino Olearo",
    "gn:population":333,
    "gn:timezone":"Europe/Rome",
    "iso:country":"IT",
    "wof:name":"San Martino Olearo",
    "wof:placetype":"locality",
    "wof:population":333
},
  "geometry": {"coordinates":[9.34786,45.41695],"type":"Point"}
}