{
  "type": "Feature",
  "properties": {
    "gn:admin1_code":"12",
    "gn:admin2_code":"TO",
    "gn:admin3_code":"1265.0",
    "gn:asciiname":"Mezzi Po",
    "gn:country_code":"IT",
    "gn:dem":193,
    "gn:feature_class":"P",
    "gn:feature_code":"PPL",
    "gn:name":"Mezzi Po",
    "gn:population":318,
    "gn:timezone":"Europe/Rome",
    "iso:country":"IT",
    "wof:name":"Mezzi Po",
    "wof:placetype":"locality",
    "wof:population":318
},
  "geometry": {"coordinates":[7.81329,45.14758],"type":"Point"}
}