{
  "type": "Feature",
  "properties": {
    "gn:admin1_code":"1.0",
    "gn:admin2_code":"TE",
    "gn:admin3_code":"67041.0",
    "gn:asciiname":"Valle San Giovanni",
    "gn:country_code":"IT",
    "gn:dem":458,
    "gn:elevation":"320.0",
    "gn:feature_class":"P",
    "gn:feature_code":"PPL",
    "gn:name":"Valle San Giovanni",
    "gn:population":805,
    "gn:timezone":"Europe/Rome",
    "iso:country":"IT",
    "name:ceb_x_preferred":[
        "Valle San Giovanni"
    ],
    "name:deu_x_preferred":[
        "Valle San Giovanni"
    ],
    "name:fas_x_preferred":[
        "\u0648\u0627\u0644\u0647 \u0633\u0646 \u062c\u06cc\u0648\u0627\u0646\u06cc"
    ],
    "name:fra_x_preferred":[
        "Valle San Giovanni"
    ],
    "name:ita_x_preferred":[
        "Valle San Giovanni"
    ],
    "name:nld_x_preferred":[
        "Valle San Giovanni"
    ],
    "name:spa_x_preferred":[
        "Valle San Giovanni"
    ],
    "name:srp_x_preferred":[
        "\u0412\u0430\u043b\u0435 \u0421\u0430\u043d \u0402\u043e\u0432\u0430\u043d\u0438"
    ],
    "name:swe_x_preferred":[
        "Valle San Giovanni"
    ],
    "wof:name":"Valle San Giovanni",
    "wof:placetype":"locality",
    "wof:population":805
},
  "geometry": {"coordinates":[13.61807,42.6215],"type":"Point"}
}