{
  "type": "Feature",
  "properties": {
    "gn:admin1_code":"1.0",
    "gn:admin2_code":"TE",
    "gn:admin3_code":"67041.0",
    "gn:asciiname":"Valle San Giovanni",
    "gn:country_code":"IT",
    "gn:dem":458,
    "gn:elevation":"320.0",
    "gn:feature_class":"P",
    "gn:feature_code":"PPL",
    "gn:name":"Valle San Giovanni",
    "gn:population":805,
    "gn:timezone":"Europe/Rome",
    "iso:country":"IT",
    "wof:name":"Valle San Giovanni",
    "wof:placetype":"locality",
    "wof:population":805
},
  "geometry": {"coordinates":[13.61807,42.6215],"type":"Point"}
}