{
  "type": "Feature",
  "properties": {
    "gn:admin1_code":"5",
    "gn:admin2_code":"RA",
    "gn:admin3_code":"39013.0",
    "gn:asciiname":"Possessione Serraioli",
    "gn:country_code":"IT",
    "gn:dem":9,
    "gn:feature_class":"P",
    "gn:feature_code":"PPL",
    "gn:name":"Possessione Serraioli",
    "gn:population":24,
    "gn:timezone":"Europe/Rome",
    "iso:country":"IT",
    "wof:name":"Possessione Serraioli",
    "wof:placetype":"locality",
    "wof:population":24
},
  "geometry": {"coordinates":[11.8355,44.45386],"type":"Point"}
}