{
  "type": "Feature",
  "properties": {
    "gn:admin1_code":"11.0",
    "gn:admin2_code":"IS",
    "gn:admin3_code":"94026.0",
    "gn:asciiname":"Santo Ianni Narducci",
    "gn:country_code":"IT",
    "gn:dem":616,
    "gn:feature_class":"P",
    "gn:feature_code":"PPL",
    "gn:name":"Santo Ianni Narducci",
    "gn:population":13,
    "gn:timezone":"Europe/Rome",
    "iso:country":"IT",
    "wof:name":"Santo Ianni Narducci",
    "wof:placetype":"locality",
    "wof:population":13
},
  "geometry": {"coordinates":[14.40864,41.54693],"type":"Point"}
}