{
  "type": "Feature",
  "properties": {
    "gn:admin1_code":"15.0",
    "gn:admin2_code":"CT",
    "gn:admin3_code":"87038.0",
    "gn:asciiname":"Montelaguardia",
    "gn:country_code":"IT",
    "gn:dem":731,
    "gn:elevation":"730.0",
    "gn:feature_class":"P",
    "gn:feature_code":"PPL",
    "gn:name":"Montelaguardia",
    "gn:population":108,
    "gn:timezone":"Europe/Rome",
    "iso:country":"IT",
    "wof:name":"Montelaguardia",
    "wof:placetype":"locality",
    "wof:population":108
},
  "geometry": {"coordinates":[14.99537,37.8739],"type":"Point"}
}