{
  "type": "Feature",
  "properties": {
    "gn:admin1_code":"10.0",
    "gn:admin2_code":"AP",
    "gn:admin3_code":"44015.0",
    "gn:asciiname":"Illice",
    "gn:country_code":"IT",
    "gn:dem":749,
    "gn:elevation":"750.0",
    "gn:feature_class":"P",
    "gn:feature_code":"PPL",
    "gn:name":"Illice",
    "gn:population":25,
    "gn:timezone":"Europe/Rome",
    "iso:country":"IT",
    "wof:name":"Illice",
    "wof:placetype":"locality",
    "wof:population":25
},
  "geometry": {"coordinates":[13.4009,42.90273],"type":"Point"}
}