{
  "type": "Feature",
  "properties": {
    "gn:gn_country":"IT",
    "gn:gn_fcode":"PPLA3",
    "gn:gn_pop":256,
    "gn:population":239,
    "iso:country":"IT",
    "name:ara_x_preferred":[
        "\u0633\u064a\u0645\u064a\u0627\u0646\u0627"
    ],
    "name:azb_x_preferred":[
        "\u0633\u0645\u06cc\u0627\u0646\u0627"
    ],
    "name:bel_x_preferred":[
        "\u0421\u0435\u043c'\u044f\u043d\u0430"
    ],
    "name:cat_x_preferred":[
        "Semiana"
    ],
    "name:ceb_x_preferred":[
        "Semiana"
    ],
    "name:ces_x_preferred":[
        "Semiana"
    ],
    "name:deu_x_preferred":[
        "Semiana"
    ],
    "name:eng_x_preferred":[
        "Semiana"
    ],
    "name:epo_x_preferred":[
        "Semiana"
    ],
    "name:eus_x_preferred":[
        "Semiana"
    ],
    "name:fas_x_preferred":[
        "\u0633\u0645\u06cc\u0627\u0646\u0627"
    ],
    "name:fra_x_preferred":[
        "Semiana"
    ],
    "name:hun_x_preferred":[
        "Semiana"
    ],
    "name:hye_x_preferred":[
        "\u054d\u0565\u0574\u056b\u0561\u0576\u0561"
    ],
    "name:ind_x_preferred":[
        "Semiana"
    ],
    "name:ita_x_preferred":[
        "Semiana"
    ],
    "name:jpn_x_preferred":[
        "\u30bb\u30df\u30a2\u30fc\u30ca"
    ],
    "name:kaz_x_preferred":[
        "\u0421\u0435\u043c\u044c\u044f\u043d\u0430"
    ],
    "name:lat_x_preferred":[
        "Semiana"
    ],
    "name:lmo_x_preferred":[
        "Semi\u00e4na"
    ],
    "name:msa_x_preferred":[
        "Semiana"
    ],
    "name:nan_x_preferred":[
        "Semiana"
    ],
    "name:nap_x_preferred":[
        "Semiana"
    ],
    "name:nld_x_preferred":[
        "Semiana"
    ],
    "name:oci_x_preferred":[
        "Semiana"
    ],
    "name:pms_x_preferred":[
        "Semiana"
    ],
    "name:pol_x_preferred":[
        "Semiana"
    ],
    "name:por_x_preferred":[
        "Semiana"
    ],
    "name:ron_x_preferred":[
        "Semiana"
    ],
    "name:rus_x_preferred":[
        "\u0421\u0435\u043c\u044c\u044f\u043d\u0430"
    ],
    "name:scn_x_preferred":[
        "Semiana"
    ],
    "name:spa_x_preferred":[
        "Semiana"
    ],
    "name:srp_x_preferred":[
        "\u0421\u0435\u043c\u0438\u0458\u0430\u043d\u0430"
    ],
    "name:tgl_x_preferred":[
        "Semiana"
    ],
    "name:ukr_x_preferred":[
        "\u0421\u0435\u043c'\u044f\u043d\u0430"
    ],
    "name:uzb_x_preferred":[
        "Semiana"
    ],
    "name:vie_x_preferred":[
        "Semiana"
    ],
    "name:vol_x_preferred":[
        "Semiana"
    ],
    "name:war_x_preferred":[
        "Semiana"
    ],
    "name:zho_x_preferred":[
        "\u585e\u7c73\u4e9a\u7eb3"
    ],
    "qs_pg:aaroncc":"IT",
    "qs_pg:gn_country":"IT",
    "qs_pg:gn_fcode":"PPLA3",
    "qs_pg:gn_pop":256,
    "qs_pg:name":"Semiana",
    "qs_pg:name_adm0":"Italia",
    "qs_pg:name_adm1":"Lombardia",
    "qs_pg:photos_9r":0,
    "qs_pg:photos_sr":0,
    "qs_pg:pop_sr":2,
    "qs_pg:qs_pg_placetype":"locality",
    "qs_pg:qs_pg_placetype_gp":"Town",
    "qs_pg:woe_adm0":23424853,
    "woe:adm0_id":23424853,
    "woe:name_adm0":"Italia",
    "woe:name_adm1":"Lombardia",
    "woe:placetype":"Town",
    "wof:name":"Semiana",
    "wof:placetype":"locality",
    "wof:population":239
},
  "geometry": {"coordinates":[8.73264,45.13746],"type":"Point"}
}