{
  "type": "Feature",
  "properties": {
    "gn:admin1_code":"8.0",
    "gn:admin2_code":"SV",
    "gn:admin3_code":"9060.0",
    "gn:asciiname":"Costa",
    "gn:country_code":"IT",
    "gn:dem":445,
    "gn:feature_class":"P",
    "gn:feature_code":"PPL",
    "gn:name":"Costa",
    "gn:population":20,
    "gn:timezone":"Europe/Rome",
    "iso:country":"IT",
    "wof:name":"Costa",
    "wof:placetype":"locality",
    "wof:population":20
},
  "geometry": {"coordinates":[8.00939,44.01139000000001],"type":"Point"}
}