{
  "type": "Feature",
  "properties": {
    "gn:admin1_code":"17",
    "gn:admin2_code":"BZ",
    "gn:admin3_code":"21115.0",
    "gn:asciiname":"Mazzes",
    "gn:country_code":"IT",
    "gn:dem":1272,
    "gn:feature_class":"P",
    "gn:feature_code":"PPL",
    "gn:name":"Mazzes",
    "gn:population":45,
    "gn:timezone":"Europe/Rome",
    "iso:country":"IT",
    "wof:name":"Mazzes",
    "wof:placetype":"locality",
    "wof:population":45
},
  "geometry": {"coordinates":[11.4271,46.9162],"type":"Point"}
}