{
  "type": "Feature",
  "properties": {
    "gn:admin1_code":"3.0",
    "gn:admin2_code":"RC",
    "gn:admin3_code":"80063.0",
    "gn:asciiname":"Archi",
    "gn:country_code":"IT",
    "gn:dem":58,
    "gn:feature_class":"P",
    "gn:feature_code":"PPL",
    "gn:name":"Archi",
    "gn:population":0,
    "gn:timezone":"Europe/Rome",
    "iso:country":"IT",
    "name:ceb_x_preferred":[
        "Archi"
    ],
    "name:deu_x_preferred":[
        "Archi"
    ],
    "name:ita_x_preferred":[
        "Archi"
    ],
    "name:rus_x_preferred":[
        "\u0410\u0440\u0447\u0438"
    ],
    "name:scn_x_preferred":[
        "Archi"
    ],
    "name:sqi_x_preferred":[
        "Archi"
    ],
    "name:swe_x_preferred":[
        "Archi"
    ],
    "wof:name":"Archi",
    "wof:placetype":"locality"
},
  "geometry": {"coordinates":[15.66127,38.14296],"type":"Point"}
}