{
  "type": "Feature",
  "properties": {
    "gn:admin1_code":"16",
    "gn:admin2_code":"MS",
    "gn:admin3_code":"45014.0",
    "gn:asciiname":"Braia",
    "gn:country_code":"IT",
    "gn:dem":705,
    "gn:feature_class":"P",
    "gn:feature_code":"PPLL",
    "gn:name":"Braia",
    "gn:population":7,
    "gn:timezone":"Europe/Rome",
    "iso:country":"IT",
    "wof:name":"Braia",
    "wof:placetype":"locality",
    "wof:population":7
},
  "geometry": {"coordinates":[9.84497,44.44472],"type":"Point"}
}