{
  "type": "Feature",
  "properties": {
    "gn:admin1_code":"3.0",
    "gn:admin2_code":"RC",
    "gn:admin3_code":"80055.0",
    "gn:asciiname":"Piminoro",
    "gn:country_code":"IT",
    "gn:dem":715,
    "gn:feature_class":"P",
    "gn:feature_code":"PPL",
    "gn:name":"Piminoro",
    "gn:population":467,
    "gn:timezone":"Europe/Rome",
    "iso:country":"IT",
    "wof:name":"Piminoro",
    "wof:placetype":"locality",
    "wof:population":467
},
  "geometry": {"coordinates":[16.00823,38.27026],"type":"Point"}
}