{
  "type": "Feature",
  "properties": {
    "gn:admin1_code":"16",
    "gn:admin2_code":"PI",
    "gn:admin3_code":"50032.0",
    "gn:asciiname":"Alberaccio",
    "gn:country_code":"IT",
    "gn:dem":18,
    "gn:feature_class":"P",
    "gn:feature_code":"PPL",
    "gn:name":"Alberaccio",
    "gn:population":30,
    "gn:timezone":"Europe/Rome",
    "iso:country":"IT",
    "wof:name":"Alberaccio",
    "wof:placetype":"locality",
    "wof:population":30
},
  "geometry": {"coordinates":[10.76964,43.6957],"type":"Point"}
}