{
  "type": "Feature",
  "properties": {
    "gn:admin1_code":"4",
    "gn:admin2_code":"CE",
    "gn:admin3_code":"61002.0",
    "gn:asciiname":"Masseria Panella",
    "gn:country_code":"IT",
    "gn:dem":143,
    "gn:feature_class":"P",
    "gn:feature_code":"PPL",
    "gn:name":"Masseria Panella",
    "gn:population":142,
    "gn:timezone":"Europe/Rome",
    "iso:country":"IT",
    "wof:name":"Masseria Panella",
    "wof:placetype":"locality",
    "wof:population":142
},
  "geometry": {"coordinates":[14.34936,41.33973],"type":"Point"}
}