{
  "type": "Feature",
  "properties": {
    "gn:admin1_code":"8",
    "gn:admin2_code":"SP",
    "gn:admin3_code":"11017.0",
    "gn:asciiname":"Pastine",
    "gn:country_code":"IT",
    "gn:dem":178,
    "gn:feature_class":"P",
    "gn:feature_code":"PPL",
    "gn:name":"Pastine",
    "gn:population":79,
    "gn:timezone":"Europe/Rome",
    "iso:country":"IT",
    "wof:name":"Pastine",
    "wof:placetype":"locality",
    "wof:population":79
},
  "geometry": {"coordinates":[9.63755,44.18629],"type":"Point"}
}