{
  "type": "Feature",
  "properties": {
    "gn:admin1_code":"8",
    "gn:admin2_code":"SP",
    "gn:admin3_code":"11023.0",
    "gn:asciiname":"Porcale",
    "gn:country_code":"IT",
    "gn:dem":326,
    "gn:feature_class":"P",
    "gn:feature_code":"PPL",
    "gn:name":"Porcale",
    "gn:population":55,
    "gn:timezone":"Europe/Rome",
    "iso:country":"IT",
    "wof:name":"Porcale",
    "wof:placetype":"locality",
    "wof:population":55
},
  "geometry": {"coordinates":[9.77097,44.12235],"type":"Point"}
}