{
  "type": "Feature",
  "properties": {
    "gn:admin1_code":"16",
    "gn:admin2_code":"LU",
    "gn:admin3_code":"46003.0",
    "gn:asciiname":"Biagi",
    "gn:country_code":"IT",
    "gn:dem":249,
    "gn:feature_class":"P",
    "gn:feature_code":"PPL",
    "gn:name":"Biagi",
    "gn:population":23,
    "gn:timezone":"Europe/Rome",
    "iso:country":"IT",
    "name:spa_x_preferred":[
        "Biagi"
    ],
    "wof:name":"Biagi",
    "wof:placetype":"locality",
    "wof:population":23
},
  "geometry": {"coordinates":[10.46039,44.07596],"type":"Point"}
}