{
  "type": "Feature",
  "properties": {
    "gn:admin1_code":"20",
    "gn:admin2_code":"VE",
    "gn:admin3_code":"27018.0",
    "gn:asciiname":"Case Giometro",
    "gn:country_code":"IT",
    "gn:dem":4,
    "gn:feature_class":"P",
    "gn:feature_code":"PPL",
    "gn:name":"Case Giometro",
    "gn:population":14,
    "gn:timezone":"Europe/Rome",
    "iso:country":"IT",
    "wof:name":"Case Giometro",
    "wof:placetype":"locality",
    "wof:population":14
},
  "geometry": {"coordinates":[12.82865,45.81287],"type":"Point"}
}