{
  "type": "Feature",
  "properties": {
    "gn:admin1_code":"6.0",
    "gn:admin2_code":"UD",
    "gn:admin3_code":"30033.0",
    "gn:asciiname":"Chiutdipupe",
    "gn:cc2":"IT",
    "gn:country_code":"IT",
    "gn:dem":497,
    "gn:feature_class":"P",
    "gn:feature_code":"PPL",
    "gn:name":"Chiutdipupe",
    "gn:population":21,
    "gn:timezone":"Europe/Rome",
    "iso:country":"IT",
    "name:und_x_variant":[
        "Chiout",
        "Chiout di Puppe"
    ],
    "wof:name":"Chiutdipupe",
    "wof:placetype":"locality",
    "wof:population":21
},
  "geometry": {"coordinates":[13.3316,46.44971],"type":"Point"}
}