{
  "type": "Feature",
  "properties": {
    "gn:admin1_code":"9",
    "gn:admin2_code":"LO",
    "gn:admin3_code":"98040.0",
    "gn:asciiname":"Pantanasco",
    "gn:country_code":"IT",
    "gn:dem":86,
    "gn:feature_class":"P",
    "gn:feature_code":"PPL",
    "gn:name":"Pantanasco",
    "gn:population":20,
    "gn:timezone":"Europe/Rome",
    "iso:country":"IT",
    "wof:name":"Pantanasco",
    "wof:placetype":"locality",
    "wof:population":20
},
  "geometry": {"coordinates":[9.43769,45.33957],"type":"Point"}
}