{
  "type": "Feature",
  "properties": {
    "gn:admin1_code":"9",
    "gn:admin2_code":"PV",
    "gn:admin3_code":"18008.0",
    "gn:asciiname":"Casale Raggia",
    "gn:country_code":"IT",
    "gn:dem":64,
    "gn:feature_class":"P",
    "gn:feature_code":"PPL",
    "gn:name":"Casale Raggia",
    "gn:population":22,
    "gn:timezone":"Europe/Rome",
    "iso:country":"IT",
    "wof:name":"Casale Raggia",
    "wof:placetype":"locality",
    "wof:population":22
},
  "geometry": {"coordinates":[9.22963,45.08669],"type":"Point"}
}