{
  "type": "Feature",
  "properties": {
    "gn:gn_country":"IT",
    "gn:gn_fcode":"PPLL",
    "gn:gn_pop":0,
    "gn:population":52,
    "iso:country":"IT",
    "name:dut_x_preferred":[
        "Pievasciata"
    ],
    "name:eng_x_preferred":[
        "Pievasciata"
    ],
    "name:fre_x_preferred":[
        "Pievasciata"
    ],
    "name:ita_x_preferred":[
        "Pievasciata"
    ],
    "name:srp_x_preferred":[
        "Pievasciata"
    ],
    "qs_pg:aaroncc":"IT",
    "qs_pg:gn_country":"IT",
    "qs_pg:gn_fcode":"PPLL",
    "qs_pg:gn_pop":0,
    "qs_pg:name":"Pievasciata",
    "qs_pg:name_adm0":"Italia",
    "qs_pg:name_adm1":"Toscana",
    "qs_pg:photos":138,
    "qs_pg:photos_1k":28,
    "qs_pg:photos_9k":1,
    "qs_pg:photos_9r":3,
    "qs_pg:photos_all":138,
    "qs_pg:photos_sr":3,
    "qs_pg:pop_sr":0,
    "qs_pg:qs_pg_placetype":"locality",
    "qs_pg:qs_pg_placetype_gp":"Town",
    "qs_pg:woe_adm0":23424853,
    "woe:adm0_id":23424853,
    "woe:name_adm0":"Italia",
    "woe:name_adm1":"Toscana",
    "woe:placetype":"Town",
    "wof:name":"Pievasciata",
    "wof:placetype":"locality",
    "wof:population":52
},
  "geometry": {"coordinates":[11.38548,43.38924],"type":"Point"}
}