{
  "type": "Feature",
  "properties": {
    "gn:admin1_code":"12",
    "gn:admin2_code":"CN",
    "gn:admin3_code":"4180.0",
    "gn:asciiname":"Piglionasso",
    "gn:country_code":"IT",
    "gn:dem":296,
    "gn:feature_class":"P",
    "gn:feature_code":"PPL",
    "gn:name":"Piglionasso",
    "gn:population":20,
    "gn:timezone":"Europe/Rome",
    "iso:country":"IT",
    "wof:name":"Piglionasso",
    "wof:placetype":"locality",
    "wof:population":20
},
  "geometry": {"coordinates":[7.41255,44.68087],"type":"Point"}
}