{
  "type": "Feature",
  "properties": {
    "gn:admin1_code":"20",
    "gn:admin2_code":"TV",
    "gn:admin3_code":"26081.0",
    "gn:asciiname":"Case Massarotto",
    "gn:country_code":"IT",
    "gn:dem":11,
    "gn:feature_class":"P",
    "gn:feature_code":"PPL",
    "gn:name":"Case Massarotto",
    "gn:population":27,
    "gn:timezone":"Europe/Rome",
    "iso:country":"IT",
    "wof:name":"Case Massarotto",
    "wof:placetype":"locality",
    "wof:population":27
},
  "geometry": {"coordinates":[12.31506,45.65356],"type":"Point"}
}