{
  "type": "Feature",
  "properties": {
    "gn:admin1_code":"9",
    "gn:admin2_code":"MN",
    "gn:admin3_code":"20064.0",
    "gn:asciiname":"Malcantone",
    "gn:country_code":"IT",
    "gn:dem":16,
    "gn:feature_class":"P",
    "gn:feature_code":"PPL",
    "gn:name":"Malcantone",
    "gn:population":22,
    "gn:timezone":"Europe/Rome",
    "iso:country":"IT",
    "wof:name":"Malcantone",
    "wof:placetype":"locality",
    "wof:population":22
},
  "geometry": {"coordinates":[10.9885,45.07165],"type":"Point"}
}