{
  "type": "Feature",
  "properties": {
    "gn:admin1_code":"1",
    "gn:admin2_code":"CH",
    "gn:admin3_code":"69086.0",
    "gn:asciiname":"Cese",
    "gn:country_code":"IT",
    "gn:dem":50,
    "gn:feature_class":"P",
    "gn:feature_code":"PPL",
    "gn:name":"Cese",
    "gn:population":73,
    "gn:timezone":"Europe/Rome",
    "iso:country":"IT",
    "wof:name":"Cese",
    "wof:placetype":"locality",
    "wof:population":73
},
  "geometry": {"coordinates":[14.43864,42.29348],"type":"Point"}
}