{
  "type": "Feature",
  "properties": {
    "gn:admin1_code":"3",
    "gn:admin2_code":"CZ",
    "gn:admin3_code":"79160.0",
    "gn:asciiname":"Case Valenzi II",
    "gn:country_code":"IT",
    "gn:dem":1039,
    "gn:feature_class":"P",
    "gn:feature_code":"PPL",
    "gn:name":"Case Valenzi II",
    "gn:population":16,
    "gn:timezone":"Europe/Rome",
    "iso:country":"IT",
    "wof:name":"Case Valenzi II",
    "wof:placetype":"locality",
    "wof:population":16
},
  "geometry": {"coordinates":[16.22834,39.00724],"type":"Point"}
}