{
  "type": "Feature",
  "properties": {
    "gn:admin1_code":"4",
    "gn:admin3_code":"63044.0",
    "gn:asciiname":"Villazzano II",
    "gn:country_code":"IT",
    "gn:dem":123,
    "gn:feature_class":"P",
    "gn:feature_code":"PPL",
    "gn:name":"Villazzano II",
    "gn:population":27,
    "gn:timezone":"Europe/Rome",
    "iso:country":"IT",
    "wof:name":"Villazzano II",
    "wof:placetype":"locality",
    "wof:population":27
},
  "geometry": {"coordinates":[14.34581,40.61908],"type":"Point"}
}