{
  "type": "Feature",
  "properties": {
    "iso:country":"IT",
    "name:azb_x_preferred":[
        "\u0641\u0627\u0626\u062f\u0648"
    ],
    "name:bel_x_preferred":[
        "\u0424\u0430\u0435\u0434\u0430"
    ],
    "name:cat_x_preferred":[
        "Faedo"
    ],
    "name:ceb_x_preferred":[
        "Faedo"
    ],
    "name:deu_x_preferred":[
        "Faedo"
    ],
    "name:epo_x_preferred":[
        "Faedo"
    ],
    "name:est_x_preferred":[
        "Faedo"
    ],
    "name:eus_x_preferred":[
        "Faedo"
    ],
    "name:fas_x_preferred":[
        "\u0641\u0627\u0626\u062f\u0648"
    ],
    "name:fra_x_preferred":[
        "Faedo"
    ],
    "name:hun_x_preferred":[
        "Faedo"
    ],
    "name:hye_x_preferred":[
        "\u0556\u0561\u0565\u0564\u0578"
    ],
    "name:ind_x_preferred":[
        "Faedo"
    ],
    "name:ita_x_preferred":[
        "Faedo"
    ],
    "name:jpn_x_preferred":[
        "\u30d5\u30a1\u30a8\u30fc\u30c9"
    ],
    "name:kaz_x_preferred":[
        "\u0424\u0430\u0435\u0434\u043e"
    ],
    "name:lat_x_preferred":[
        "Faedum"
    ],
    "name:lmo_x_preferred":[
        "Faedo"
    ],
    "name:msa_x_preferred":[
        "Faedo"
    ],
    "name:nap_x_preferred":[
        "Faedo"
    ],
    "name:nld_x_preferred":[
        "Faedo"
    ],
    "name:pms_x_preferred":[
        "Faedo"
    ],
    "name:pol_x_preferred":[
        "Faedo"
    ],
    "name:por_x_preferred":[
        "Faedo"
    ],
    "name:ron_x_preferred":[
        "Faedo"
    ],
    "name:rus_x_preferred":[
        "\u0424\u0430\u044d\u0434\u043e"
    ],
    "name:scn_x_preferred":[
        "Faedo"
    ],
    "name:spa_x_preferred":[
        "Faedo"
    ],
    "name:srp_x_preferred":[
        "\u0424\u0430\u0435\u0434\u043e"
    ],
    "name:szl_x_preferred":[
        "Faedo"
    ],
    "name:tgl_x_preferred":[
        "Faedo"
    ],
    "name:ukr_x_preferred":[
        "\u0424\u0430\u0435\u0434\u043e"
    ],
    "name:urd_x_preferred":[
        "\u0641\u06cc\u0688\u0648"
    ],
    "name:uzb_x_preferred":[
        "Faedo"
    ],
    "name:vie_x_preferred":[
        "Faedo"
    ],
    "name:vol_x_preferred":[
        "Faedo"
    ],
    "name:war_x_preferred":[
        "Faedo"
    ],
    "name:zho_x_preferred":[
        "\u6cd5\u57c3\u591a"
    ],
    "qs_pg:aaroncc":"IT",
    "qs_pg:name":"Faedo",
    "qs_pg:name_adm0":"Italia",
    "qs_pg:name_adm1":"Veneto",
    "qs_pg:photos":151,
    "qs_pg:photos_1k":31,
    "qs_pg:photos_9k":1,
    "qs_pg:photos_9r":4,
    "qs_pg:photos_all":151,
    "qs_pg:photos_sr":4,
    "qs_pg:pop_sr":0,
    "qs_pg:qs_pg_placetype":"locality",
    "qs_pg:qs_pg_placetype_gp":"Town",
    "qs_pg:woe_adm0":23424853,
    "woe:adm0_id":23424853,
    "woe:name_adm0":"Italia",
    "woe:name_adm1":"Veneto",
    "woe:placetype":"Town",
    "wof:name":"Faedo",
    "wof:placetype":"locality"
},
  "geometry": {"coordinates":[11.692543,45.304565],"type":"Point"}
}