{
  "type": "Feature",
  "properties": {
    "gn:admin1_code":"17",
    "gn:admin2_code":"BZ",
    "gn:admin3_code":"21008.0",
    "gn:asciiname":"Ponte Adige",
    "gn:country_code":"IT",
    "gn:dem":240,
    "gn:feature_class":"P",
    "gn:feature_code":"PPL",
    "gn:name":"Ponte Adige",
    "gn:population":78,
    "gn:timezone":"Europe/Rome",
    "iso:country":"IT",
    "wof:name":"Ponte Adige",
    "wof:placetype":"locality",
    "wof:population":78
},
  "geometry": {"coordinates":[11.29882,46.4856],"type":"Point"}
}