{
  "type": "Feature",
  "properties": {
    "gn:admin1_code":"2",
    "gn:admin2_code":"PZ",
    "gn:admin3_code":"76007.0",
    "gn:asciiname":"Bruciate di Sotto",
    "gn:country_code":"IT",
    "gn:dem":912,
    "gn:feature_class":"P",
    "gn:feature_code":"PPL",
    "gn:name":"Bruciate di Sotto",
    "gn:population":37,
    "gn:timezone":"Europe/Rome",
    "iso:country":"IT",
    "wof:name":"Bruciate di Sotto",
    "wof:placetype":"locality",
    "wof:population":37
},
  "geometry": {"coordinates":[15.73452,40.71272],"type":"Point"}
}