{
  "type": "Feature",
  "properties": {
    "gn:admin1_code":"20.0",
    "gn:admin2_code":"TV",
    "gn:admin3_code":"26049.0",
    "gn:asciiname":"Ponte Redigole",
    "gn:country_code":"IT",
    "gn:dem":2,
    "gn:feature_class":"P",
    "gn:feature_code":"PPL",
    "gn:name":"Ponte Redigole",
    "gn:population":55,
    "gn:timezone":"Europe/Rome",
    "iso:country":"IT",
    "wof:name":"Ponte Redigole",
    "wof:placetype":"locality",
    "wof:population":55
},
  "geometry": {"coordinates":[12.59142,45.76833],"type":"Point"}
}