{
  "type": "Feature",
  "properties": {
    "gn:admin1_code":"17",
    "gn:admin2_code":"BZ",
    "gn:admin3_code":"21028.0",
    "gn:asciiname":"Seghe",
    "gn:country_code":"IT",
    "gn:dem":1229,
    "gn:feature_class":"P",
    "gn:feature_code":"PPL",
    "gn:name":"Seghe",
    "gn:population":17,
    "gn:timezone":"Europe/Rome",
    "iso:country":"IT",
    "wof:name":"Seghe",
    "wof:placetype":"locality",
    "wof:population":17
},
  "geometry": {"coordinates":[12.22161,46.71487],"type":"Point"}
}