{
  "type": "Feature",
  "properties": {
    "iso:country":"IT",
    "qs:a0":"Italia",
    "qs:a1":"*Brescia",
    "qs:a1r":"0Lombardia",
    "qs:adm0":"Italia",
    "qs:la_lc":"*",
    "qs:level":"locality",
    "qs:loc":"Costa-Barco",
    "qs:loc_alt":"Costa-Barco",
    "qs:pop":0,
    "qs:type":"buffered point",
    "wof:name":"Costa-Barco",
    "wof:placetype":"locality"
},
  "geometry": {"coordinates":[10.04784,45.576489],"type":"Point"}
}