{
  "type": "Feature",
  "properties": {
    "gn:admin1_code":"20",
    "gn:admin2_code":"VI",
    "gn:admin3_code":"24012.0",
    "gn:asciiname":"Baggi",
    "gn:country_code":"IT",
    "gn:dem":102,
    "gn:feature_class":"P",
    "gn:feature_code":"PPL",
    "gn:name":"Baggi",
    "gn:population":25,
    "gn:timezone":"Europe/Rome",
    "iso:country":"IT",
    "wof:name":"Baggi",
    "wof:placetype":"locality",
    "wof:population":25
},
  "geometry": {"coordinates":[11.73085,45.73997],"type":"Point"}
}