{
  "type": "Feature",
  "properties": {
    "gn:admin1_code":"16.0",
    "gn:admin2_code":"AR",
    "gn:admin3_code":"51017.0",
    "gn:asciiname":"Montanare",
    "gn:country_code":"IT",
    "gn:dem":306,
    "gn:elevation":"315.0",
    "gn:feature_class":"P",
    "gn:feature_code":"PPL",
    "gn:name":"Montanare",
    "gn:population":13,
    "gn:timezone":"Europe/Rome",
    "iso:country":"IT",
    "wof:name":"Montanare",
    "wof:placetype":"locality",
    "wof:population":13
},
  "geometry": {"coordinates":[12.05555,43.26085],"type":"Point"}
}