{
  "type": "Feature",
  "properties": {
    "gn:admin1_code":"17",
    "gn:admin2_code":"TN",
    "gn:admin3_code":"22127.0",
    "gn:asciiname":"Noarna",
    "gn:country_code":"IT",
    "gn:dem":391,
    "gn:feature_class":"P",
    "gn:feature_code":"PPL",
    "gn:name":"Noarna",
    "gn:population":285,
    "gn:timezone":"Europe/Rome",
    "iso:country":"IT",
    "wof:name":"Noarna",
    "wof:placetype":"locality",
    "wof:population":285
},
  "geometry": {"coordinates":[11.01262,45.91103],"type":"Point"}
}