{
  "type": "Feature",
  "properties": {
    "gn:admin1_code":"3",
    "gn:admin2_code":"RC",
    "gn:admin3_code":"80093.0",
    "gn:asciiname":"Sacchinella",
    "gn:country_code":"IT",
    "gn:dem":191,
    "gn:feature_class":"P",
    "gn:feature_code":"PPL",
    "gn:name":"Sacchinella",
    "gn:population":30,
    "gn:timezone":"Europe/Rome",
    "iso:country":"IT",
    "wof:name":"Sacchinella",
    "wof:placetype":"locality",
    "wof:population":30
},
  "geometry": {"coordinates":[16.02895,38.38909],"type":"Point"}
}