{
  "type": "Feature",
  "properties": {
    "gn:admin1_code":"15.0",
    "gn:admin2_code":"PA",
    "gn:admin3_code":"82079.0",
    "gn:asciiname":"Ficarazzelli-Bagni Italia",
    "gn:country_code":"IT",
    "gn:dem":28,
    "gn:feature_class":"P",
    "gn:feature_code":"PPL",
    "gn:name":"Ficarazzelli-Bagni Italia",
    "gn:population":757,
    "gn:timezone":"Europe/Rome",
    "iso:country":"IT",
    "wof:name":"Ficarazzelli-Bagni Italia",
    "wof:placetype":"locality",
    "wof:population":757
},
  "geometry": {"coordinates":[13.44811,38.08639],"type":"Point"}
}