{
  "type": "Feature",
  "properties": {
    "gn:admin1_code":"3.0",
    "gn:admin2_code":"CS",
    "gn:admin3_code":"78003.0",
    "gn:asciiname":"Foresta",
    "gn:country_code":"IT",
    "gn:dem":423,
    "gn:feature_class":"P",
    "gn:feature_code":"PPL",
    "gn:name":"Foresta",
    "gn:population":657,
    "gn:timezone":"Europe/Rome",
    "iso:country":"IT",
    "wof:name":"Foresta",
    "wof:placetype":"locality",
    "wof:population":657
},
  "geometry": {"coordinates":[16.49658,39.56448],"type":"Point"}
}