{
  "type": "Feature",
  "properties": {
    "gn:admin1_code":"4.0",
    "gn:admin3_code":"63086.0",
    "gn:asciiname":"Montechiaro",
    "gn:country_code":"IT",
    "gn:dem":241,
    "gn:feature_class":"P",
    "gn:feature_code":"PPL",
    "gn:name":"Montechiaro",
    "gn:population":575,
    "gn:timezone":"Europe/Rome",
    "iso:country":"IT",
    "wof:name":"Montechiaro",
    "wof:placetype":"locality",
    "wof:population":575
},
  "geometry": {"coordinates":[14.40995,40.65408],"type":"Point"}
}