{
  "type": "Feature",
  "properties": {
    "gn:admin1_code":"8",
    "gn:admin2_code":"IM",
    "gn:admin3_code":"8017.0",
    "gn:asciiname":"Capo Mimosa-Rollo",
    "gn:country_code":"IT",
    "gn:dem":64,
    "gn:feature_class":"P",
    "gn:feature_code":"PPL",
    "gn:name":"Capo Mimosa-Rollo",
    "gn:population":66,
    "gn:timezone":"Europe/Rome",
    "iso:country":"IT",
    "wof:name":"Capo Mimosa-Rollo",
    "wof:placetype":"locality",
    "wof:population":66
},
  "geometry": {"coordinates":[8.13148,43.93373],"type":"Point"}
}