{
  "type": "Feature",
  "properties": {
    "gn:admin1_code":"16",
    "gn:admin2_code":"GR",
    "gn:admin3_code":"53003.0",
    "gn:asciiname":"Centro C",
    "gn:country_code":"IT",
    "gn:dem":11,
    "gn:feature_class":"P",
    "gn:feature_code":"PPL",
    "gn:name":"Centro C",
    "gn:population":45,
    "gn:timezone":"Europe/Rome",
    "iso:country":"IT",
    "wof:name":"Centro C",
    "wof:placetype":"locality",
    "wof:population":45
},
  "geometry": {"coordinates":[11.42712,42.40983],"type":"Point"}
}