{
  "type": "Feature",
  "properties": {
    "gn:admin1_code":"5",
    "gn:admin2_code":"MO",
    "gn:admin3_code":"36046.0",
    "gn:asciiname":"Zona Mercato Ortofrutticolo",
    "gn:country_code":"IT",
    "gn:dem":110,
    "gn:feature_class":"P",
    "gn:feature_code":"PPL",
    "gn:name":"Zona Mercato Ortofrutticolo",
    "gn:population":72,
    "gn:timezone":"Europe/Rome",
    "iso:country":"IT",
    "wof:name":"Zona Mercato Ortofrutticolo",
    "wof:placetype":"locality",
    "wof:population":72
},
  "geometry": {"coordinates":[10.99218,44.506],"type":"Point"}
}