{
  "type": "Feature",
  "properties": {
    "gn:admin1_code":"5.0",
    "gn:admin2_code":"FE",
    "gn:admin3_code":"38008.0",
    "gn:asciiname":"Porporana",
    "gn:country_code":"IT",
    "gn:dem":9,
    "gn:elevation":"9.0",
    "gn:feature_class":"P",
    "gn:feature_code":"PPL",
    "gn:name":"Porporana",
    "gn:population":194,
    "gn:timezone":"Europe/Rome",
    "iso:country":"IT",
    "wof:name":"Porporana",
    "wof:placetype":"locality",
    "wof:population":194
},
  "geometry": {"coordinates":[11.47333,44.92458],"type":"Point"}
}