{
  "type": "Feature",
  "properties": {
    "gn:admin1_code":"3",
    "gn:admin2_code":"VV",
    "gn:admin3_code":"102011.0",
    "gn:asciiname":"Montesoro",
    "gn:country_code":"IT",
    "gn:dem":334,
    "gn:feature_class":"P",
    "gn:feature_code":"PPL",
    "gn:name":"Montesoro",
    "gn:population":282,
    "gn:timezone":"Europe/Rome",
    "iso:country":"IT",
    "wof:name":"Montesoro",
    "wof:placetype":"locality",
    "wof:population":282
},
  "geometry": {"coordinates":[16.29471,38.81571],"type":"Point"}
}