{
  "type": "Feature",
  "properties": {
    "gn:admin1_code":"9",
    "gn:admin2_code":"BS",
    "gn:admin3_code":"17174.0",
    "gn:asciiname":"Cagnaghe",
    "gn:country_code":"IT",
    "gn:dem":444,
    "gn:feature_class":"P",
    "gn:feature_code":"PPL",
    "gn:name":"Cagnaghe",
    "gn:population":62,
    "gn:timezone":"Europe/Rome",
    "iso:country":"IT",
    "wof:name":"Cagnaghe",
    "wof:placetype":"locality",
    "wof:population":62
},
  "geometry": {"coordinates":[10.21874,45.65565],"type":"Point"}
}