{
  "type": "Feature",
  "properties": {
    "gn:admin1_code":"10.0",
    "gn:admin2_code":"FM",
    "gn:admin3_code":"109017.0",
    "gn:asciiname":"Piane di Monteverde I",
    "gn:country_code":"IT",
    "gn:dem":195,
    "gn:feature_class":"P",
    "gn:feature_code":"PPL",
    "gn:name":"Piane di Monteverde I",
    "gn:population":226,
    "gn:timezone":"Europe/Rome",
    "iso:country":"IT",
    "wof:name":"Piane di Monteverde I",
    "wof:placetype":"locality",
    "wof:population":226
},
  "geometry": {"coordinates":[13.5159,43.10342],"type":"Point"}
}