{
  "type": "Feature",
  "properties": {
    "gn:admin1_code":"3",
    "gn:admin2_code":"CS",
    "gn:admin3_code":"78058.0",
    "gn:asciiname":"Torretta",
    "gn:country_code":"IT",
    "gn:dem":54,
    "gn:feature_class":"P",
    "gn:feature_code":"PPL",
    "gn:name":"Torretta",
    "gn:population":140,
    "gn:timezone":"Europe/Rome",
    "iso:country":"IT",
    "wof:name":"Torretta",
    "wof:placetype":"locality",
    "wof:population":140
},
  "geometry": {"coordinates":[16.0141,39.41851],"type":"Point"}
}