{
  "type": "Feature",
  "properties": {
    "gn:admin1_code":"18",
    "gn:admin2_code":"PG",
    "gn:admin3_code":"54007.0",
    "gn:asciiname":"Padule",
    "gn:country_code":"IT",
    "gn:dem":602,
    "gn:feature_class":"P",
    "gn:feature_code":"PPL",
    "gn:name":"Padule",
    "gn:population":45,
    "gn:timezone":"Europe/Rome",
    "iso:country":"IT",
    "wof:name":"Padule",
    "wof:placetype":"locality",
    "wof:population":45
},
  "geometry": {"coordinates":[13.02893,42.72067],"type":"Point"}
}