{
  "type": "Feature",
  "properties": {
    "gn:admin1_code":"20",
    "gn:admin2_code":"TV",
    "gn:admin3_code":"26086.0",
    "gn:asciiname":"Moncini",
    "gn:country_code":"IT",
    "gn:dem":14,
    "gn:feature_class":"P",
    "gn:feature_code":"PPL",
    "gn:name":"Moncini",
    "gn:population":21,
    "gn:timezone":"Europe/Rome",
    "iso:country":"IT",
    "wof:name":"Moncini",
    "wof:placetype":"locality",
    "wof:population":21
},
  "geometry": {"coordinates":[12.2203,45.64145],"type":"Point"}
}