{
  "type": "Feature",
  "properties": {
    "gn:admin1_code":"16.0",
    "gn:admin2_code":"FI",
    "gn:admin3_code":"48030.0",
    "gn:asciiname":"Montagnana",
    "gn:country_code":"IT",
    "gn:dem":214,
    "gn:elevation":"229.0",
    "gn:feature_class":"P",
    "gn:feature_code":"PPL",
    "gn:name":"Montagnana",
    "gn:population":374,
    "gn:timezone":"Europe/Rome",
    "iso:country":"IT",
    "wof:name":"Montagnana",
    "wof:placetype":"locality",
    "wof:population":374
},
  "geometry": {"coordinates":[11.10744,43.67414],"type":"Point"}
}