{
  "type": "Feature",
  "properties": {
    "gn:admin1_code":"4.0",
    "gn:admin2_code":"SA",
    "gn:admin3_code":"65087.0",
    "gn:asciiname":"Contrada Fiumicello",
    "gn:country_code":"IT",
    "gn:dem":481,
    "gn:feature_class":"P",
    "gn:feature_code":"PPL",
    "gn:name":"Contrada Fiumicello",
    "gn:population":82,
    "gn:timezone":"Europe/Rome",
    "iso:country":"IT",
    "wof:name":"Contrada Fiumicello",
    "wof:placetype":"locality",
    "wof:population":82
},
  "geometry": {"coordinates":[15.65359,40.30582],"type":"Point"}
}