{
  "type": "Feature",
  "properties": {
    "gn:admin1_code":"20",
    "gn:admin2_code":"RO",
    "gn:admin3_code":"29003.0",
    "gn:asciiname":"Valmolin Inferiore",
    "gn:country_code":"IT",
    "gn:dem":2,
    "gn:feature_class":"P",
    "gn:feature_code":"PPL",
    "gn:name":"Valmolin Inferiore",
    "gn:population":91,
    "gn:timezone":"Europe/Rome",
    "iso:country":"IT",
    "wof:name":"Valmolin Inferiore",
    "wof:placetype":"locality",
    "wof:population":91
},
  "geometry": {"coordinates":[11.77274,45.01139000000001],"type":"Point"}
}