{
  "type": "Feature",
  "properties": {
    "gn:admin1_code":"12",
    "gn:admin2_code":"TO",
    "gn:admin3_code":"1186.0",
    "gn:asciiname":"Traverse",
    "gn:country_code":"IT",
    "gn:dem":1091,
    "gn:feature_class":"P",
    "gn:feature_code":"PPL",
    "gn:name":"Traverse",
    "gn:population":27,
    "gn:timezone":"Europe/Rome",
    "iso:country":"IT",
    "name:ceb_x_preferred":[
        "Traverse"
    ],
    "name:ces_x_preferred":[
        "Traverz"
    ],
    "name:chv_x_preferred":[
        "\u0422\u0440\u0430\u0432\u0435\u0440\u0441"
    ],
    "name:deu_x_preferred":[
        "Traverse"
    ],
    "name:fin_x_preferred":[
        "Traverssi"
    ],
    "name:fra_x_preferred":[
        "Traverse"
    ],
    "name:jpn_x_preferred":[
        "\u30c8\u30e9\u30d0\u30fc\u30b9"
    ],
    "name:lit_x_preferred":[
        "Traversas"
    ],
    "name:nld_x_preferred":[
        "Traverse"
    ],
    "name:pol_x_preferred":[
        "Traverse"
    ],
    "name:rus_x_preferred":[
        "\u0422\u0440\u0430\u0432\u0435\u0440\u0441"
    ],
    "name:spa_x_preferred":[
        "Traverse"
    ],
    "wof:name":"Traverse",
    "wof:placetype":"locality",
    "wof:population":27
},
  "geometry": {"coordinates":[7.11722,44.94275],"type":"Point"}
}