{
  "type": "Feature",
  "properties": {
    "gn:admin1_code":"12",
    "gn:admin2_code":"TO",
    "gn:admin3_code":"1186.0",
    "gn:asciiname":"Traverse",
    "gn:country_code":"IT",
    "gn:dem":1091,
    "gn:feature_class":"P",
    "gn:feature_code":"PPL",
    "gn:name":"Traverse",
    "gn:population":27,
    "gn:timezone":"Europe/Rome",
    "iso:country":"IT",
    "wof:name":"Traverse",
    "wof:placetype":"locality",
    "wof:population":27
},
  "geometry": {"coordinates":[7.11722,44.94275],"type":"Point"}
}