{
  "type": "Feature",
  "properties": {
    "gn:admin1_code":"5",
    "gn:admin2_code":"FE",
    "gn:admin3_code":"38019.0",
    "gn:asciiname":"Cirelli",
    "gn:country_code":"IT",
    "gn:dem":3,
    "gn:feature_class":"P",
    "gn:feature_code":"PPL",
    "gn:name":"Cirelli",
    "gn:population":30,
    "gn:timezone":"Europe/Rome",
    "iso:country":"IT",
    "name:ltz_x_preferred":[
        "Cirelli"
    ],
    "wof:name":"Cirelli",
    "wof:placetype":"locality",
    "wof:population":30
},
  "geometry": {"coordinates":[11.77516,44.73537],"type":"Point"}
}