{
  "type": "Feature",
  "properties": {
    "gn:admin1_code":"12",
    "gn:admin2_code":"CN",
    "gn:admin3_code":"4203.0",
    "gn:asciiname":"Colombaro Rossi",
    "gn:country_code":"IT",
    "gn:dem":351,
    "gn:feature_class":"P",
    "gn:feature_code":"PPL",
    "gn:name":"Colombaro Rossi",
    "gn:population":19,
    "gn:timezone":"Europe/Rome",
    "iso:country":"IT",
    "wof:name":"Colombaro Rossi",
    "wof:placetype":"locality",
    "wof:population":19
},
  "geometry": {"coordinates":[7.51889,44.63803],"type":"Point"}
}