{
  "type": "Feature",
  "properties": {
    "gn:admin1_code":"3.0",
    "gn:admin2_code":"CZ",
    "gn:admin3_code":"79033.0",
    "gn:asciiname":"San Mazzeo-Stranges I",
    "gn:cc2":"IT",
    "gn:country_code":"IT",
    "gn:dem":869,
    "gn:feature_class":"P",
    "gn:feature_code":"PPL",
    "gn:name":"San Mazzeo-Stranges I",
    "gn:population":100,
    "gn:timezone":"Europe/Rome",
    "iso:country":"IT",
    "name:und_x_variant":[
        "Casa San Mazzeo",
        "San Mazzeo"
    ],
    "wof:name":"San Mazzeo-Stranges I",
    "wof:placetype":"locality",
    "wof:population":100
},
  "geometry": {"coordinates":[16.2667,39.03968],"type":"Point"}
}