{
  "type": "Feature",
  "properties": {
    "gn:admin1_code":"1",
    "gn:admin2_code":"PE",
    "gn:admin3_code":"68004.0",
    "gn:asciiname":"Cerqueglio",
    "gn:country_code":"IT",
    "gn:dem":534,
    "gn:feature_class":"P",
    "gn:feature_code":"PPL",
    "gn:name":"Cerqueglio",
    "gn:population":42,
    "gn:timezone":"Europe/Rome",
    "iso:country":"IT",
    "wof:name":"Cerqueglio",
    "wof:placetype":"locality",
    "wof:population":42
},
  "geometry": {"coordinates":[13.87323,42.30874],"type":"Point"}
}