{
  "type": "Feature",
  "properties": {
    "gn:admin1_code":"20",
    "gn:admin2_code":"VI",
    "gn:admin3_code":"24038.0",
    "gn:asciiname":"Rozzola",
    "gn:country_code":"IT",
    "gn:dem":50,
    "gn:feature_class":"P",
    "gn:feature_code":"PPL",
    "gn:name":"Rozzola",
    "gn:population":52,
    "gn:timezone":"Europe/Rome",
    "iso:country":"IT",
    "wof:name":"Rozzola",
    "wof:placetype":"locality",
    "wof:population":52
},
  "geometry": {"coordinates":[11.5837,45.63026],"type":"Point"}
}