{
  "type": "Feature",
  "properties": {
    "gn:admin1_code":"1",
    "gn:admin2_code":"TE",
    "gn:admin3_code":"67029.0",
    "gn:asciiname":"Case Merluzzo",
    "gn:country_code":"IT",
    "gn:dem":68,
    "gn:feature_class":"P",
    "gn:feature_code":"PPL",
    "gn:name":"Case Merluzzo",
    "gn:population":90,
    "gn:timezone":"Europe/Rome",
    "iso:country":"IT",
    "wof:name":"Case Merluzzo",
    "wof:placetype":"locality",
    "wof:population":90
},
  "geometry": {"coordinates":[13.93383,42.64116],"type":"Point"}
}