{
  "type": "Feature",
  "properties": {
    "gn:admin1_code":"16",
    "gn:admin2_code":"PI",
    "gn:admin3_code":"50041.0",
    "gn:asciiname":"Botteghino",
    "gn:country_code":"IT",
    "gn:dem":34,
    "gn:feature_class":"P",
    "gn:feature_code":"PPL",
    "gn:name":"Botteghino",
    "gn:population":45,
    "gn:timezone":"Europe/Rome",
    "iso:country":"IT",
    "wof:name":"Botteghino",
    "wof:placetype":"locality",
    "wof:population":45
},
  "geometry": {"coordinates":[10.53981,43.57171],"type":"Point"}
}