{
  "type": "Feature",
  "properties": {
    "gn:admin1_code":"16",
    "gn:admin2_code":"PI",
    "gn:admin3_code":"50031.0",
    "gn:asciiname":"Gatano",
    "gn:country_code":"IT",
    "gn:dem":1,
    "gn:feature_class":"P",
    "gn:feature_code":"PPL",
    "gn:name":"Gatano",
    "gn:population":38,
    "gn:timezone":"Europe/Rome",
    "iso:country":"IT",
    "wof:name":"Gatano",
    "wof:placetype":"locality",
    "wof:population":38
},
  "geometry": {"coordinates":[10.40404,43.74942],"type":"Point"}
}