{
  "type": "Feature",
  "properties": {
    "gn:admin1_code":"16",
    "gn:admin2_code":"PT",
    "gn:admin3_code":"47016.0",
    "gn:asciiname":"Bassetti",
    "gn:country_code":"IT",
    "gn:dem":18,
    "gn:feature_class":"P",
    "gn:feature_code":"PPL",
    "gn:name":"Bassetti",
    "gn:population":21,
    "gn:timezone":"Europe/Rome",
    "iso:country":"IT",
    "name:ita_x_preferred":[
        "Bassetti"
    ],
    "wof:name":"Bassetti",
    "wof:placetype":"locality",
    "wof:population":21
},
  "geometry": {"coordinates":[10.74669,43.82985],"type":"Point"}
}