{
  "type": "Feature",
  "properties": {
    "gn:admin1_code":"7.0",
    "gn:admin2_code":"RM",
    "gn:admin3_code":"58091.0",
    "gn:admin4_code":"5809111.0",
    "gn:asciiname":"Monte Stallonara",
    "gn:country_code":"IT",
    "gn:dem":43,
    "gn:feature_class":"P",
    "gn:feature_code":"PPL",
    "gn:name":"Monte Stallonara",
    "gn:population":437,
    "gn:timezone":"Europe/Rome",
    "iso:country":"IT",
    "wof:name":"Monte Stallonara",
    "wof:placetype":"locality",
    "wof:population":437
},
  "geometry": {"coordinates":[12.34664,41.83693],"type":"Point"}
}