{
  "type": "Feature",
  "properties": {
    "gn:admin1_code":"3.0",
    "gn:admin2_code":"RC",
    "gn:admin3_code":"80060.0",
    "gn:asciiname":"Cirella",
    "gn:country_code":"IT",
    "gn:dem":271,
    "gn:elevation":"266.0",
    "gn:feature_class":"P",
    "gn:feature_code":"PPL",
    "gn:name":"Cirella",
    "gn:population":382,
    "gn:timezone":"Europe/Rome",
    "iso:country":"IT",
    "wof:name":"Cirella",
    "wof:placetype":"locality",
    "wof:population":382
},
  "geometry": {"coordinates":[16.1004,38.23265],"type":"Point"}
}