{
  "type": "Feature",
  "properties": {
    "gn:admin1_code":"16.0",
    "gn:admin2_code":"PI",
    "gn:admin3_code":"50009.0",
    "gn:asciiname":"Nardi-Palandri",
    "gn:country_code":"IT",
    "gn:dem":25,
    "gn:feature_class":"P",
    "gn:feature_code":"PPL",
    "gn:name":"Nardi-Palandri",
    "gn:population":32,
    "gn:timezone":"Europe/Rome",
    "iso:country":"IT",
    "wof:name":"Nardi-Palandri",
    "wof:placetype":"locality",
    "wof:population":32
},
  "geometry": {"coordinates":[10.69109,43.80338],"type":"Point"}
}