{
  "type": "Feature",
  "properties": {
    "gn:admin1_code":"9.0",
    "gn:admin2_code":"LO",
    "gn:admin3_code":"98043.0",
    "gn:asciiname":"Viale Europa",
    "gn:country_code":"IT",
    "gn:dem":66,
    "gn:feature_class":"P",
    "gn:feature_code":"PPLL",
    "gn:name":"Viale Europa",
    "gn:population":0,
    "gn:timezone":"Europe/Rome",
    "iso:country":"IT",
    "wof:name":"Viale Europa",
    "wof:placetype":"locality"
},
  "geometry": {"coordinates":[9.59957,45.1701],"type":"Point"}
}