{
  "type": "Feature",
  "properties": {
    "gn:admin1_code":"20",
    "gn:admin2_code":"VR",
    "gn:admin3_code":"23089.0",
    "gn:asciiname":"Sfrizzera",
    "gn:country_code":"IT",
    "gn:dem":65,
    "gn:feature_class":"P",
    "gn:feature_code":"PPL",
    "gn:name":"Sfrizzera",
    "gn:population":30,
    "gn:timezone":"Europe/Rome",
    "iso:country":"IT",
    "wof:name":"Sfrizzera",
    "wof:placetype":"locality",
    "wof:population":30
},
  "geometry": {"coordinates":[10.7443,45.3119],"type":"Point"}
}