{
  "type": "Feature",
  "properties": {
    "gn:admin1_code":"20.0",
    "gn:admin2_code":"VE",
    "gn:admin3_code":"27044.0",
    "gn:asciiname":"Piave Vecchia",
    "gn:cc2":"IT",
    "gn:country_code":"IT",
    "gn:dem":0,
    "gn:feature_class":"P",
    "gn:feature_code":"PPL",
    "gn:name":"Piave Vecchia",
    "gn:population":0,
    "gn:timezone":"Europe/Rome",
    "iso:country":"IT",
    "name:und_x_variant":[
        "Casa Piave V\u00e9cchia",
        "Porto di Piave Vecchia",
        "Piave Vecchia"
    ],
    "wof:name":"Piave Vecchia",
    "wof:placetype":"locality"
},
  "geometry": {"coordinates":[12.57972,45.47972],"type":"Point"}
}