{
  "type": "Feature",
  "properties": {
    "gn:admin1_code":"9",
    "gn:admin2_code":"MN",
    "gn:admin3_code":"20003.0",
    "gn:asciiname":"Correggio Micheli",
    "gn:country_code":"IT",
    "gn:dem":17,
    "gn:feature_class":"P",
    "gn:feature_code":"PPL",
    "gn:name":"Correggio Micheli",
    "gn:population":243,
    "gn:timezone":"Europe/Rome",
    "iso:country":"IT",
    "wof:name":"Correggio Micheli",
    "wof:placetype":"locality",
    "wof:population":243
},
  "geometry": {"coordinates":[10.94729,45.07382],"type":"Point"}
}