{
  "type": "Feature",
  "properties": {
    "gn:admin1_code":"9",
    "gn:admin2_code":"MI",
    "gn:admin3_code":"15165.0",
    "gn:asciiname":"Soria Vecchia",
    "gn:country_code":"IT",
    "gn:dem":95,
    "gn:feature_class":"P",
    "gn:feature_code":"PPL",
    "gn:name":"Soria Vecchia",
    "gn:population":85,
    "gn:timezone":"Europe/Rome",
    "iso:country":"IT",
    "wof:name":"Soria Vecchia",
    "wof:placetype":"locality",
    "wof:population":85
},
  "geometry": {"coordinates":[8.91071,45.35993],"type":"Point"}
}