{
  "type": "Feature",
  "properties": {
    "gn:admin1_code":"10.0",
    "gn:admin2_code":"FM",
    "gn:admin3_code":"109031.0",
    "gn:asciiname":"Valmir",
    "gn:country_code":"IT",
    "gn:dem":136,
    "gn:feature_class":"P",
    "gn:feature_code":"PPL",
    "gn:name":"Valmir",
    "gn:population":424,
    "gn:timezone":"Europe/Rome",
    "iso:country":"IT",
    "wof:name":"Valmir",
    "wof:placetype":"locality",
    "wof:population":424
},
  "geometry": {"coordinates":[13.67925,43.04876],"type":"Point"}
}