{
  "type": "Feature",
  "properties": {
    "gn:admin1_code":"16",
    "gn:admin2_code":"GR",
    "gn:admin3_code":"53026.0",
    "gn:asciiname":"Valle Castagneta",
    "gn:country_code":"IT",
    "gn:dem":468,
    "gn:feature_class":"P",
    "gn:feature_code":"PPL",
    "gn:name":"Valle Castagneta",
    "gn:population":23,
    "gn:timezone":"Europe/Rome",
    "iso:country":"IT",
    "wof:name":"Valle Castagneta",
    "wof:placetype":"locality",
    "wof:population":23
},
  "geometry": {"coordinates":[11.71861,42.70884],"type":"Point"}
}