{
  "type": "Feature",
  "properties": {
    "gn:admin1_code":"12.0",
    "gn:admin2_code":"VB",
    "gn:admin3_code":"103021.0",
    "gn:asciiname":"Ceppo Morelli",
    "gn:country_code":"IT",
    "gn:dem":897,
    "gn:feature_class":"P",
    "gn:feature_code":"PPL",
    "gn:name":"Ceppo Morelli",
    "gn:population":0,
    "gn:timezone":"Europe/Rome",
    "iso:country":"IT",
    "name:bel_x_preferred":[
        "\u0427\u044d\u043f\u0430-\u041c\u0430\u0440\u044d\u043b\u0456"
    ],
    "name:hye_x_preferred":[
        "\u0549\u0565\u057a\u0578 \u0544\u0578\u0580\u0565\u056c\u056b"
    ],
    "name:jpn_x_preferred":[
        "\u30c1\u30a7\u30c3\u30dd\u30fb\u30e2\u30ec\u30c3\u30ea"
    ],
    "name:kaz_x_preferred":[
        "\u0427\u0435\u043f\u043f\u043e-\u041c\u043e\u0440\u0435\u043b\u043b\u0438"
    ],
    "name:lat_x_preferred":[
        "Cippus Maurellus"
    ],
    "name:lmo_x_preferred":[
        "C\u00e9ch Muril"
    ],
    "name:pms_x_preferred":[
        "Ciach Moril"
    ],
    "name:rus_x_preferred":[
        "\u0427\u0435\u043f\u043f\u043e-\u041c\u043e\u0440\u0435\u043b\u043b\u0438"
    ],
    "name:srp_x_preferred":[
        "\u0427\u0435\u043f\u043e \u041c\u043e\u0440\u0435\u043b\u0438"
    ],
    "name:ukr_x_preferred":[
        "\u0427\u0435\u043f\u043f\u043e-\u041c\u043e\u0440\u0435\u043b\u043b\u0456"
    ],
    "name:zho_x_preferred":[
        "\u5207\u6ce2\u83ab\u96f7\u5229"
    ],
    "wof:name":"Ceppo Morelli",
    "wof:placetype":"locality"
},
  "geometry": {"coordinates":[8.06667,45.96667],"type":"Point"}
}