{
  "type": "Feature",
  "properties": {
    "gn:admin1_code":"9.0",
    "gn:admin2_code":"BS",
    "gn:admin3_code":"17081.0",
    "gn:asciiname":"Ronco",
    "gn:country_code":"IT",
    "gn:dem":169,
    "gn:feature_class":"P",
    "gn:feature_code":"PPL",
    "gn:name":"Ronco",
    "gn:population":1508,
    "gn:timezone":"Europe/Rome",
    "iso:country":"IT",
    "wof:name":"Ronco",
    "wof:placetype":"locality",
    "wof:population":1508
},
  "geometry": {"coordinates":[10.13531,45.59611],"type":"Point"}
}