{
  "type": "Feature",
  "properties": {
    "iso:country":"IT",
    "qs:a0":"Italia",
    "qs:a1":"*Parma",
    "qs:a1r":"0Emilia-Romagna",
    "qs:adm0":"Italia",
    "qs:la_lc":"*",
    "qs:level":"locality",
    "qs:loc":"Gaiano",
    "qs:loc_alt":"Gaiano",
    "qs:pop":0,
    "qs:type":"buffered point",
    "wof:name":"Gaiano",
    "wof:placetype":"locality"
},
  "geometry": {"coordinates":[10.175102,44.724751],"type":"Point"}
}