{
  "type": "Feature",
  "properties": {
    "gn:admin1_code":"16.0",
    "gn:admin2_code":"SI",
    "gn:admin3_code":"52034.0",
    "gn:asciiname":"La Macchia",
    "gn:country_code":"IT",
    "gn:dem":204,
    "gn:feature_class":"P",
    "gn:feature_code":"PPLL",
    "gn:name":"La Macchia",
    "gn:population":0,
    "gn:timezone":"Europe/Rome",
    "iso:country":"IT",
    "wof:name":"La Macchia",
    "wof:placetype":"locality"
},
  "geometry": {"coordinates":[11.24822,43.27687],"type":"Point"}
}