{
  "type": "Feature",
  "properties": {
    "gn:admin1_code":"20",
    "gn:admin2_code":"VR",
    "gn:admin3_code":"23003.0",
    "gn:asciiname":"Possessione",
    "gn:country_code":"IT",
    "gn:dem":15,
    "gn:feature_class":"P",
    "gn:feature_code":"PPL",
    "gn:name":"Possessione",
    "gn:population":31,
    "gn:timezone":"Europe/Rome",
    "iso:country":"IT",
    "wof:name":"Possessione",
    "wof:placetype":"locality",
    "wof:population":31
},
  "geometry": {"coordinates":[11.24073,45.23498],"type":"Point"}
}