{
  "type": "Feature",
  "properties": {
    "gn:admin1_code":"18",
    "gn:admin2_code":"PG",
    "gn:admin3_code":"54005.0",
    "gn:asciiname":"Carvello",
    "gn:country_code":"IT",
    "gn:dem":489,
    "gn:feature_class":"P",
    "gn:feature_code":"PPL",
    "gn:name":"Carvello",
    "gn:population":18,
    "gn:timezone":"Europe/Rome",
    "iso:country":"IT",
    "wof:name":"Carvello",
    "wof:placetype":"locality",
    "wof:population":18
},
  "geometry": {"coordinates":[12.78982,42.82061],"type":"Point"}
}