{
  "type": "Feature",
  "properties": {
    "iso:country":"IT",
    "wof:name":"San Luigi",
    "wof:placetype":"neighbourhood"
},
  "geometry": {"coordinates":[9.2100167434129,45.44395342323877],"type":"Point"}
}