{
  "type": "Feature",
  "properties": {
    "gn:admin1_code":"9.0",
    "gn:admin2_code":"LC",
    "gn:admin3_code":"97065.0",
    "gn:asciiname":"Costa",
    "gn:country_code":"IT",
    "gn:dem":1367,
    "gn:feature_class":"P",
    "gn:feature_code":"PPLL",
    "gn:name":"Costa",
    "gn:population":0,
    "gn:timezone":"Europe/Rome",
    "iso:country":"IT",
    "wof:name":"Costa",
    "wof:placetype":"locality"
},
  "geometry": {"coordinates":[9.41598,45.94563],"type":"Point"}
}