{
  "type": "Feature",
  "properties": {
    "gn:admin1_code":"20",
    "gn:admin2_code":"TV",
    "gn:admin3_code":"26036.0",
    "gn:asciiname":"Verdi",
    "gn:country_code":"IT",
    "gn:dem":78,
    "gn:feature_class":"P",
    "gn:feature_code":"PPL",
    "gn:name":"Verdi",
    "gn:population":49,
    "gn:timezone":"Europe/Rome",
    "iso:country":"IT",
    "wof:name":"Verdi",
    "wof:placetype":"locality",
    "wof:population":49
},
  "geometry": {"coordinates":[11.82298,45.72463],"type":"Point"}
}