{
  "type": "Feature",
  "properties": {
    "gn:admin1_code":"20.0",
    "gn:admin2_code":"BL",
    "gn:admin3_code":"25029.0",
    "gn:asciiname":"Pieve di Limana",
    "gn:country_code":"IT",
    "gn:dem":320,
    "gn:feature_class":"P",
    "gn:feature_code":"PPL",
    "gn:name":"Pieve di Limana",
    "gn:population":107,
    "gn:timezone":"Europe/Rome",
    "iso:country":"IT",
    "wof:name":"Pieve di Limana",
    "wof:placetype":"locality",
    "wof:population":107
},
  "geometry": {"coordinates":[12.14412,46.08994000000001],"type":"Point"}
}