{
  "type": "Feature",
  "properties": {
    "gn:admin1_code":"10.0",
    "gn:admin2_code":"MC",
    "gn:admin3_code":"43002.0",
    "gn:asciiname":"Casarini II",
    "gn:country_code":"IT",
    "gn:dem":399,
    "gn:elevation":"401.0",
    "gn:feature_class":"P",
    "gn:feature_code":"PPL",
    "gn:name":"Casarini II",
    "gn:population":24,
    "gn:timezone":"Europe/Rome",
    "iso:country":"IT",
    "wof:name":"Casarini II",
    "wof:placetype":"locality",
    "wof:population":24
},
  "geometry": {"coordinates":[13.1142,43.37176],"type":"Point"}
}