{
  "type": "Feature",
  "properties": {
    "gn:admin1_code":"9",
    "gn:admin2_code":"LO",
    "gn:admin3_code":"98010.0",
    "gn:asciiname":"Buongodere",
    "gn:country_code":"IT",
    "gn:dem":67,
    "gn:feature_class":"P",
    "gn:feature_code":"PPL",
    "gn:name":"Buongodere",
    "gn:population":22,
    "gn:timezone":"Europe/Rome",
    "iso:country":"IT",
    "wof:name":"Buongodere",
    "wof:placetype":"locality",
    "wof:population":22
},
  "geometry": {"coordinates":[9.62539,45.22362],"type":"Point"}
}