{
  "type": "Feature",
  "properties": {
    "gn:admin1_code":"20",
    "gn:admin2_code":"RO",
    "gn:admin3_code":"29050.0",
    "gn:asciiname":"Zona Industriale",
    "gn:country_code":"IT",
    "gn:dem":6,
    "gn:feature_class":"P",
    "gn:feature_code":"PPL",
    "gn:name":"Zona Industriale",
    "gn:population":44,
    "gn:timezone":"Europe/Rome",
    "iso:country":"IT",
    "name:deu_x_preferred":[
        "Zona Industriale"
    ],
    "name:fra_x_preferred":[
        "Zona Industriale"
    ],
    "name:ita_x_preferred":[
        "Zona Industriale"
    ],
    "name:nap_x_preferred":[
        "Zona Nnustriale"
    ],
    "wof:name":"Zona Industriale",
    "wof:placetype":"locality",
    "wof:population":44
},
  "geometry": {"coordinates":[11.67556,45.07652],"type":"Point"}
}