{
  "type": "Feature",
  "properties": {
    "gn:admin1_code":"2.0",
    "gn:admin2_code":"PZ",
    "gn:admin3_code":"76078.0",
    "gn:asciiname":"Sorgenti di Frido",
    "gn:cc2":"IT",
    "gn:country_code":"IT",
    "gn:dem":1473,
    "gn:feature_class":"P",
    "gn:feature_code":"PPL",
    "gn:name":"Sorgenti di Frido",
    "gn:population":0,
    "gn:timezone":"Europe/Rome",
    "iso:country":"IT",
    "name:und_x_variant":[
        "Sorgenti Frido",
        "Sorgenti di Frido"
    ],
    "wof:name":"Sorgenti di Frido",
    "wof:placetype":"locality"
},
  "geometry": {"coordinates":[16.18333,39.95],"type":"Point"}
}