{
  "type": "Feature",
  "properties": {
    "gn:admin1_code":"20.0",
    "gn:admin2_code":"BL",
    "gn:admin3_code":"25048.0",
    "gn:asciiname":"San Gregorio nelle Aloi",
    "gn:country_code":"IT",
    "gn:dem":306,
    "gn:feature_class":"P",
    "gn:feature_code":"PPL",
    "gn:name":"San Gregorio nelle Aloi",
    "gn:population":0,
    "gn:timezone":"Europe/Rome",
    "iso:country":"IT",
    "wof:name":"San Gregorio nelle Aloi",
    "wof:placetype":"locality"
},
  "geometry": {"coordinates":[12.06278,46.10083],"type":"Point"}
}