{
  "type": "Feature",
  "properties": {
    "gn:admin1_code":"16.0",
    "gn:admin2_code":"MS",
    "gn:admin3_code":"45013.0",
    "gn:asciiname":"Bagni",
    "gn:country_code":"IT",
    "gn:dem":115,
    "gn:feature_class":"P",
    "gn:feature_code":"PPL",
    "gn:name":"Bagni",
    "gn:population":397,
    "gn:timezone":"Europe/Rome",
    "iso:country":"IT",
    "name:ceb_x_preferred":[
        "Bagni"
    ],
    "name:deu_x_preferred":[
        "Bagni"
    ],
    "name:ita_x_preferred":[
        "Bagni"
    ],
    "name:nld_x_preferred":[
        "Bagni"
    ],
    "name:srp_x_preferred":[
        "Banji"
    ],
    "name:swe_x_preferred":[
        "Bagni"
    ],
    "wof:name":"Bagni",
    "wof:placetype":"locality",
    "wof:population":397
},
  "geometry": {"coordinates":[9.96104,44.20563],"type":"Point"}
}