{
  "type": "Feature",
  "properties": {
    "gn:admin1_code":"5.0",
    "gn:admin2_code":"BO",
    "gn:admin3_code":"37016.0",
    "gn:asciiname":"Picchio",
    "gn:country_code":"IT",
    "gn:dem":38,
    "gn:feature_class":"P",
    "gn:feature_code":"PPL",
    "gn:name":"Picchio",
    "gn:population":30,
    "gn:timezone":"Europe/Rome",
    "iso:country":"IT",
    "wof:name":"Picchio",
    "wof:placetype":"locality",
    "wof:population":30
},
  "geometry": {"coordinates":[11.63219,44.44196],"type":"Point"}
}