{
  "type": "Feature",
  "properties": {
    "gn:admin1_code":"17",
    "gn:admin2_code":"BZ",
    "gn:admin3_code":"21070.0",
    "gn:asciiname":"Braunhofe",
    "gn:country_code":"IT",
    "gn:dem":1336,
    "gn:feature_class":"P",
    "gn:feature_code":"PPL",
    "gn:name":"Braunhofe",
    "gn:population":168,
    "gn:timezone":"Europe/Rome",
    "iso:country":"IT",
    "wof:name":"Braunhofe",
    "wof:placetype":"locality",
    "wof:population":168
},
  "geometry": {"coordinates":[11.29616,46.91923],"type":"Point"}
}