{
  "type": "Feature",
  "properties": {
    "gn:admin1_code":"9",
    "gn:admin2_code":"VA",
    "gn:admin3_code":"12096.0",
    "gn:asciiname":"Molini di Gurone",
    "gn:country_code":"IT",
    "gn:dem":288,
    "gn:feature_class":"P",
    "gn:feature_code":"PPL",
    "gn:name":"Molini di Gurone",
    "gn:population":19,
    "gn:timezone":"Europe/Rome",
    "iso:country":"IT",
    "wof:name":"Molini di Gurone",
    "wof:placetype":"locality",
    "wof:population":19
},
  "geometry": {"coordinates":[8.8572,45.78881],"type":"Point"}
}