{
  "type": "Feature",
  "properties": {
    "gn:admin1_code":"16",
    "gn:admin2_code":"LU",
    "gn:admin3_code":"46027.0",
    "gn:asciiname":"Sillicagnana",
    "gn:country_code":"IT",
    "gn:dem":507,
    "gn:feature_class":"P",
    "gn:feature_code":"PPL",
    "gn:name":"Sillicagnana",
    "gn:population":318,
    "gn:timezone":"Europe/Rome",
    "iso:country":"IT",
    "wof:name":"Sillicagnana",
    "wof:placetype":"locality",
    "wof:population":318
},
  "geometry": {"coordinates":[10.3553,44.16233],"type":"Point"}
}