{
  "type": "Feature",
  "properties": {
    "gn:admin1_code":"16",
    "gn:admin2_code":"LU",
    "gn:admin3_code":"46023.0",
    "gn:asciiname":"Cortia",
    "gn:country_code":"IT",
    "gn:dem":651,
    "gn:feature_class":"P",
    "gn:feature_code":"PPL",
    "gn:name":"Cortia",
    "gn:population":66,
    "gn:timezone":"Europe/Rome",
    "iso:country":"IT",
    "wof:name":"Cortia",
    "wof:placetype":"locality",
    "wof:population":66
},
  "geometry": {"coordinates":[10.26988,44.18195],"type":"Point"}
}