{
  "type": "Feature",
  "properties": {
    "gn:admin1_code":"10.0",
    "gn:admin2_code":"MC",
    "gn:admin3_code":"43007.0",
    "gn:asciiname":"Campolarzo",
    "gn:country_code":"IT",
    "gn:dem":321,
    "gn:feature_class":"P",
    "gn:feature_code":"PPL",
    "gn:name":"Campolarzo",
    "gn:population":0,
    "gn:timezone":"Europe/Rome",
    "iso:country":"IT",
    "wof:name":"Campolarzo",
    "wof:placetype":"locality"
},
  "geometry": {"coordinates":[13.15,43.13333],"type":"Point"}
}