{
  "type": "Feature",
  "properties": {
    "gn:admin1_code":"10",
    "gn:admin2_code":"PU",
    "gn:admin3_code":"41033.0",
    "gn:asciiname":"Cisterna",
    "gn:country_code":"IT",
    "gn:dem":957,
    "gn:feature_class":"P",
    "gn:feature_code":"PPL",
    "gn:name":"Cisterna",
    "gn:population":24,
    "gn:timezone":"Europe/Rome",
    "iso:country":"IT",
    "name:ara_x_preferred":[
        "\u0635\u0647\u0631\u064a\u062c"
    ],
    "name:nld_x_preferred":[
        "Cistern"
    ],
    "wof:name":"Cisterna",
    "wof:placetype":"locality",
    "wof:population":24
},
  "geometry": {"coordinates":[12.34491,43.81769],"type":"Point"}
}