{
  "type": "Feature",
  "properties": {
    "gn:admin1_code":"8",
    "gn:admin2_code":"SP",
    "gn:admin3_code":"11015.0",
    "gn:asciiname":"Proffiano",
    "gn:country_code":"IT",
    "gn:dem":107,
    "gn:feature_class":"P",
    "gn:feature_code":"PPL",
    "gn:name":"Proffiano",
    "gn:population":22,
    "gn:timezone":"Europe/Rome",
    "iso:country":"IT",
    "wof:name":"Proffiano",
    "wof:placetype":"locality",
    "wof:population":22
},
  "geometry": {"coordinates":[9.79719,44.11438],"type":"Point"}
}