{
  "type": "Feature",
  "properties": {
    "gn:admin1_code":"15.0",
    "gn:admin2_code":"AG",
    "gn:admin3_code":"84027.0",
    "gn:asciiname":"Punta Bianca",
    "gn:country_code":"IT",
    "gn:dem":62,
    "gn:feature_class":"P",
    "gn:feature_code":"PPL",
    "gn:name":"Punta Bianca",
    "gn:population":0,
    "gn:timezone":"Europe/Rome",
    "iso:country":"IT",
    "wof:name":"Punta Bianca",
    "wof:placetype":"locality"
},
  "geometry": {"coordinates":[13.66922,37.20436],"type":"Point"}
}