{
  "type": "Feature",
  "properties": {
    "gn:admin1_code":"2",
    "gn:admin2_code":"PZ",
    "gn:admin3_code":"76007.0",
    "gn:asciiname":"Masseria Bozzelli",
    "gn:country_code":"IT",
    "gn:dem":850,
    "gn:feature_class":"P",
    "gn:feature_code":"PPL",
    "gn:name":"Masseria Bozzelli",
    "gn:population":41,
    "gn:timezone":"Europe/Rome",
    "iso:country":"IT",
    "wof:name":"Masseria Bozzelli",
    "wof:placetype":"locality",
    "wof:population":41
},
  "geometry": {"coordinates":[15.77132,40.81579],"type":"Point"}
}