{
  "type": "Feature",
  "properties": {
    "gn:admin1_code":"7",
    "gn:admin2_code":"FR",
    "gn:admin3_code":"60038.0",
    "gn:asciiname":"Capo Barile Nicolia",
    "gn:country_code":"IT",
    "gn:dem":241,
    "gn:feature_class":"P",
    "gn:feature_code":"PPL",
    "gn:name":"Capo Barile Nicolia",
    "gn:population":21,
    "gn:timezone":"Europe/Rome",
    "iso:country":"IT",
    "wof:name":"Capo Barile Nicolia",
    "wof:placetype":"locality",
    "wof:population":21
},
  "geometry": {"coordinates":[13.37353,41.6241],"type":"Point"}
}