{
  "type": "Feature",
  "properties": {
    "gn:admin1_code":"13.0",
    "gn:admin2_code":"TA",
    "gn:admin3_code":"73015.0",
    "gn:asciiname":"Parco di Guerra",
    "gn:country_code":"IT",
    "gn:dem":121,
    "gn:feature_class":"P",
    "gn:feature_code":"PPL",
    "gn:name":"Parco di Guerra",
    "gn:population":526,
    "gn:timezone":"Europe/Rome",
    "iso:country":"IT",
    "wof:name":"Parco di Guerra",
    "wof:placetype":"locality",
    "wof:population":526
},
  "geometry": {"coordinates":[17.15038,40.57707],"type":"Point"}
}