{
  "type": "Feature",
  "properties": {
    "gn:admin1_code":"20",
    "gn:admin2_code":"PD",
    "gn:admin3_code":"28106.0",
    "gn:asciiname":"Autostrada",
    "gn:country_code":"IT",
    "gn:dem":4,
    "gn:feature_class":"P",
    "gn:feature_code":"PPL",
    "gn:name":"Autostrada",
    "gn:population":23,
    "gn:timezone":"Europe/Rome",
    "iso:country":"IT",
    "wof:name":"Autostrada",
    "wof:placetype":"locality",
    "wof:population":23
},
  "geometry": {"coordinates":[11.79772,45.28298],"type":"Point"}
}