{
  "type": "Feature",
  "properties": {
    "gn:admin1_code":"1",
    "gn:admin2_code":"PE",
    "gn:admin3_code":"68012.0",
    "gn:asciiname":"Annunziata",
    "gn:country_code":"IT",
    "gn:dem":260,
    "gn:feature_class":"P",
    "gn:feature_code":"PPL",
    "gn:name":"Annunziata",
    "gn:population":213,
    "gn:timezone":"Europe/Rome",
    "iso:country":"IT",
    "wof:name":"Annunziata",
    "wof:placetype":"locality",
    "wof:population":213
},
  "geometry": {"coordinates":[14.05124,42.51565],"type":"Point"}
}