{
  "type": "Feature",
  "properties": {
    "gn:admin1_code":"20",
    "gn:admin2_code":"VI",
    "gn:admin3_code":"24101.0",
    "gn:asciiname":"Torre",
    "gn:country_code":"IT",
    "gn:dem":123,
    "gn:feature_class":"P",
    "gn:feature_code":"PPL",
    "gn:name":"Torre",
    "gn:population":42,
    "gn:timezone":"Europe/Rome",
    "iso:country":"IT",
    "wof:name":"Torre",
    "wof:placetype":"locality",
    "wof:population":42
},
  "geometry": {"coordinates":[11.7171,45.80655],"type":"Point"}
}