{
  "type": "Feature",
  "properties": {
    "gn:admin1_code":"9",
    "gn:admin2_code":"BG",
    "gn:admin3_code":"16219.0",
    "gn:asciiname":"Cascina Dotti",
    "gn:country_code":"IT",
    "gn:dem":127,
    "gn:feature_class":"P",
    "gn:feature_code":"PPL",
    "gn:name":"Cascina Dotti",
    "gn:population":86,
    "gn:timezone":"Europe/Rome",
    "iso:country":"IT",
    "wof:name":"Cascina Dotti",
    "wof:placetype":"locality",
    "wof:population":86
},
  "geometry": {"coordinates":[9.61646,45.53065],"type":"Point"}
}