{
  "type": "Feature",
  "properties": {
    "gn:admin1_code":"3.0",
    "gn:admin2_code":"CS",
    "gn:admin3_code":"78127.0",
    "gn:asciiname":"Casa la Fontana",
    "gn:country_code":"IT",
    "gn:dem":206,
    "gn:feature_class":"P",
    "gn:feature_code":"PPL",
    "gn:name":"Casa la Fontana",
    "gn:population":0,
    "gn:timezone":"Europe/Rome",
    "iso:country":"IT",
    "wof:name":"Casa la Fontana",
    "wof:placetype":"locality"
},
  "geometry": {"coordinates":[16.26667,39.35],"type":"Point"}
}