{
  "type": "Feature",
  "properties": {
    "gn:admin1_code":"20",
    "gn:admin2_code":"VR",
    "gn:admin3_code":"23082.0",
    "gn:asciiname":"Pirlar",
    "gn:country_code":"IT",
    "gn:dem":87,
    "gn:feature_class":"P",
    "gn:feature_code":"PPL",
    "gn:name":"Pirlar",
    "gn:population":34,
    "gn:timezone":"Europe/Rome",
    "iso:country":"IT",
    "wof:name":"Pirlar",
    "wof:placetype":"locality",
    "wof:population":34
},
  "geometry": {"coordinates":[10.85816,45.41642],"type":"Point"}
}