{
  "type": "Feature",
  "properties": {
    "gn:admin1_code":"4",
    "gn:admin2_code":"BN",
    "gn:admin3_code":"62071.0",
    "gn:asciiname":"Fratese",
    "gn:country_code":"IT",
    "gn:dem":211,
    "gn:feature_class":"P",
    "gn:feature_code":"PPL",
    "gn:name":"Fratese",
    "gn:population":55,
    "gn:timezone":"Europe/Rome",
    "iso:country":"IT",
    "wof:name":"Fratese",
    "wof:placetype":"locality",
    "wof:population":55
},
  "geometry": {"coordinates":[14.78877,41.07431],"type":"Point"}
}