{
  "type": "Feature",
  "properties": {
    "gn:admin1_code":"9",
    "gn:admin2_code":"BG",
    "gn:admin3_code":"16109.0",
    "gn:asciiname":"Fanti",
    "gn:country_code":"IT",
    "gn:dem":335,
    "gn:feature_class":"P",
    "gn:feature_code":"PPL",
    "gn:name":"Fanti",
    "gn:population":142,
    "gn:timezone":"Europe/Rome",
    "iso:country":"IT",
    "wof:name":"Fanti",
    "wof:placetype":"locality",
    "wof:population":142
},
  "geometry": {"coordinates":[9.89226,45.66486],"type":"Point"}
}