{
  "type": "Feature",
  "properties": {
    "gn:admin1_code":"10",
    "gn:admin2_code":"MC",
    "gn:admin3_code":"43007.0",
    "gn:asciiname":"Sfercia",
    "gn:country_code":"IT",
    "gn:dem":354,
    "gn:feature_class":"P",
    "gn:feature_code":"PPL",
    "gn:name":"Sfercia",
    "gn:population":52,
    "gn:timezone":"Europe/Rome",
    "iso:country":"IT",
    "wof:name":"Sfercia",
    "wof:placetype":"locality",
    "wof:population":52
},
  "geometry": {"coordinates":[13.12783,43.10947],"type":"Point"}
}