{
  "type": "Feature",
  "properties": {
    "gn:admin1_code":"2",
    "gn:admin2_code":"PZ",
    "gn:admin3_code":"76063.0",
    "gn:asciiname":"Case Scafarelli",
    "gn:country_code":"IT",
    "gn:dem":827,
    "gn:feature_class":"P",
    "gn:feature_code":"PPL",
    "gn:name":"Case Scafarelli",
    "gn:population":20,
    "gn:timezone":"Europe/Rome",
    "iso:country":"IT",
    "wof:name":"Case Scafarelli",
    "wof:placetype":"locality",
    "wof:population":20
},
  "geometry": {"coordinates":[15.78269,40.70492],"type":"Point"}
}