{
  "type": "Feature",
  "properties": {
    "gn:admin1_code":"12",
    "gn:admin2_code":"CN",
    "gn:admin3_code":"4085.0",
    "gn:asciiname":"Mondino",
    "gn:country_code":"IT",
    "gn:dem":399,
    "gn:feature_class":"P",
    "gn:feature_code":"PPL",
    "gn:name":"Mondino",
    "gn:population":24,
    "gn:timezone":"Europe/Rome",
    "iso:country":"IT",
    "wof:name":"Mondino",
    "wof:placetype":"locality",
    "wof:population":24
},
  "geometry": {"coordinates":[7.36374,44.68295],"type":"Point"}
}