{
  "type": "Feature",
  "properties": {
    "gn:admin1_code":"3",
    "gn:admin2_code":"CZ",
    "gn:admin3_code":"79080.0",
    "gn:asciiname":"Basile",
    "gn:country_code":"IT",
    "gn:dem":69,
    "gn:feature_class":"P",
    "gn:feature_code":"PPL",
    "gn:name":"Basile",
    "gn:population":27,
    "gn:timezone":"Europe/Rome",
    "iso:country":"IT",
    "name:bul_x_preferred":[
        "\u0412\u0430\u0441\u0438\u043b\u0438\u0439"
    ],
    "name:deu_x_preferred":[
        "Basile"
    ],
    "name:fra_x_preferred":[
        "Basile"
    ],
    "name:ita_x_preferred":[
        "Basile"
    ],
    "name:jpn_x_preferred":[
        "\u30d0\u30b8\u30fc\u30ec"
    ],
    "name:por_x_preferred":[
        "Basile"
    ],
    "name:rus_x_preferred":[
        "\u0411\u0430\u0437\u0438\u043b\u0435"
    ],
    "name:slv_x_preferred":[
        "Basile"
    ],
    "name:spa_x_preferred":[
        "Basile"
    ],
    "wof:name":"Basile",
    "wof:placetype":"locality",
    "wof:population":27
},
  "geometry": {"coordinates":[16.53264,38.73403],"type":"Point"}
}