{
  "type": "Feature",
  "properties": {
    "gn:admin1_code":"12",
    "gn:admin2_code":"CN",
    "gn:admin3_code":"4206.0",
    "gn:asciiname":"Monastero",
    "gn:country_code":"IT",
    "gn:dem":578,
    "gn:feature_class":"P",
    "gn:feature_code":"PPL",
    "gn:name":"Monastero",
    "gn:population":25,
    "gn:timezone":"Europe/Rome",
    "iso:country":"IT",
    "name:deu_x_preferred":[
        "Monastero"
    ],
    "name:epo_x_preferred":[
        "Monastero"
    ],
    "name:ita_x_preferred":[
        "Monastero"
    ],
    "name:pms_x_preferred":[
        "Monast\u00e9"
    ],
    "name:por_x_preferred":[
        "Monastero"
    ],
    "name:srp_x_preferred":[
        "Monastero"
    ],
    "wof:name":"Monastero",
    "wof:placetype":"locality",
    "wof:population":25
},
  "geometry": {"coordinates":[8.05641,44.48782],"type":"Point"}
}