{
  "type": "Feature",
  "properties": {
    "gn:admin1_code":"5",
    "gn:admin2_code":"BO",
    "gn:admin3_code":"37046.0",
    "gn:asciiname":"Cavaliera",
    "gn:country_code":"IT",
    "gn:dem":114,
    "gn:feature_class":"P",
    "gn:feature_code":"PPL",
    "gn:name":"Cavaliera",
    "gn:population":62,
    "gn:timezone":"Europe/Rome",
    "iso:country":"IT",
    "wof:name":"Cavaliera",
    "wof:placetype":"locality",
    "wof:population":62
},
  "geometry": {"coordinates":[11.42634,44.40512],"type":"Point"}
}