{
  "type": "Feature",
  "properties": {
    "gn:admin1_code":"20.0",
    "gn:admin2_code":"BL",
    "gn:admin3_code":"25015.0",
    "gn:asciiname":"Sopalu",
    "gn:country_code":"IT",
    "gn:dem":1041,
    "gn:elevation":"1016.0",
    "gn:feature_class":"P",
    "gn:feature_code":"PPL",
    "gn:name":"Sopal\u00f9",
    "gn:population":12,
    "gn:timezone":"Europe/Rome",
    "iso:country":"IT",
    "wof:name":"Sopalu",
    "wof:placetype":"locality",
    "wof:population":12
},
  "geometry": {"coordinates":[12.50459,46.58848],"type":"Point"}
}