{
  "type": "Feature",
  "properties": {
    "gn:admin1_code":"9",
    "gn:admin2_code":"BS",
    "gn:admin3_code":"17024.0",
    "gn:asciiname":"Predondo",
    "gn:country_code":"IT",
    "gn:dem":587,
    "gn:feature_class":"P",
    "gn:feature_code":"PPL",
    "gn:name":"Predondo",
    "gn:population":113,
    "gn:timezone":"Europe/Rome",
    "iso:country":"IT",
    "wof:name":"Predondo",
    "wof:placetype":"locality",
    "wof:population":113
},
  "geometry": {"coordinates":[10.26208,45.78045],"type":"Point"}
}