{
  "type": "Feature",
  "properties": {
    "gn:admin1_code":"10.0",
    "gn:admin2_code":"PU",
    "gn:admin3_code":"41033.0",
    "gn:asciiname":"Pugliano",
    "gn:country_code":"IT",
    "gn:dem":731,
    "gn:elevation":"731.0",
    "gn:feature_class":"P",
    "gn:feature_code":"PPL",
    "gn:name":"Pugliano",
    "gn:population":13,
    "gn:timezone":"Europe/Rome",
    "iso:country":"IT",
    "wof:name":"Pugliano",
    "wof:placetype":"locality",
    "wof:population":13
},
  "geometry": {"coordinates":[12.3664,43.86717],"type":"Point"}
}