{
  "type": "Feature",
  "properties": {
    "gn:admin1_code":"12",
    "gn:admin2_code":"BI",
    "gn:admin3_code":"96028.0",
    "gn:asciiname":"Vagliumina",
    "gn:country_code":"IT",
    "gn:dem":473,
    "gn:feature_class":"P",
    "gn:feature_code":"PPL",
    "gn:name":"Vagliumina",
    "gn:population":46,
    "gn:timezone":"Europe/Rome",
    "iso:country":"IT",
    "wof:name":"Vagliumina",
    "wof:placetype":"locality",
    "wof:population":46
},
  "geometry": {"coordinates":[7.9764,45.53933],"type":"Point"}
}