{
  "type": "Feature",
  "properties": {
    "gn:admin1_code":"20.0",
    "gn:admin2_code":"VI",
    "gn:admin3_code":"24071.0",
    "gn:asciiname":"Bosco di Nanto",
    "gn:country_code":"IT",
    "gn:dem":19,
    "gn:feature_class":"P",
    "gn:feature_code":"PPL",
    "gn:name":"Bosco di Nanto",
    "gn:population":431,
    "gn:timezone":"Europe/Rome",
    "iso:country":"IT",
    "wof:name":"Bosco di Nanto",
    "wof:placetype":"locality",
    "wof:population":431
},
  "geometry": {"coordinates":[11.61524,45.4124],"type":"Point"}
}