{
  "type": "Feature",
  "properties": {
    "gn:admin1_code":"5",
    "gn:admin2_code":"BO",
    "gn:admin3_code":"37033.0",
    "gn:asciiname":"Gabba",
    "gn:country_code":"IT",
    "gn:dem":704,
    "gn:feature_class":"P",
    "gn:feature_code":"PPL",
    "gn:name":"Gabba",
    "gn:population":45,
    "gn:timezone":"Europe/Rome",
    "iso:country":"IT",
    "wof:name":"Gabba",
    "wof:placetype":"locality",
    "wof:population":45
},
  "geometry": {"coordinates":[10.91568,44.18526],"type":"Point"}
}