{
  "type": "Feature",
  "properties": {
    "gn:admin1_code":"12",
    "gn:admin2_code":"TO",
    "gn:admin3_code":"1253.0",
    "gn:asciiname":"Nosma",
    "gn:country_code":"IT",
    "gn:dem":318,
    "gn:feature_class":"P",
    "gn:feature_code":"PPL",
    "gn:name":"Nosma",
    "gn:population":12,
    "gn:timezone":"Europe/Rome",
    "iso:country":"IT",
    "wof:name":"Nosma",
    "wof:placetype":"locality",
    "wof:population":12
},
  "geometry": {"coordinates":[7.91019,45.16575],"type":"Point"}
}