{
  "type": "Feature",
  "properties": {
    "gn:admin1_code":"20",
    "gn:admin2_code":"PD",
    "gn:admin3_code":"28064.0",
    "gn:asciiname":"Condotta",
    "gn:country_code":"IT",
    "gn:dem":24,
    "gn:feature_class":"P",
    "gn:feature_code":"PPL",
    "gn:name":"Condotta",
    "gn:population":23,
    "gn:timezone":"Europe/Rome",
    "iso:country":"IT",
    "wof:name":"Condotta",
    "wof:placetype":"locality",
    "wof:population":23
},
  "geometry": {"coordinates":[12.04976,45.63523],"type":"Point"}
}