{
  "type": "Feature",
  "properties": {
    "gn:admin1_code":"10.0",
    "gn:admin2_code":"AN",
    "gn:admin3_code":"42017.0",
    "gn:asciiname":"Collamato",
    "gn:country_code":"IT",
    "gn:dem":492,
    "gn:elevation":"500.0",
    "gn:feature_class":"P",
    "gn:feature_code":"PPL",
    "gn:name":"Collamato",
    "gn:population":341,
    "gn:timezone":"Europe/Rome",
    "iso:country":"IT",
    "wof:name":"Collamato",
    "wof:placetype":"locality",
    "wof:population":341
},
  "geometry": {"coordinates":[12.94918,43.29143],"type":"Point"}
}