{
  "type": "Feature",
  "properties": {
    "gn:admin1_code":"3.0",
    "gn:admin2_code":"CZ",
    "gn:admin3_code":"79002.0",
    "gn:asciiname":"Capanne",
    "gn:country_code":"IT",
    "gn:dem":1458,
    "gn:feature_class":"P",
    "gn:feature_code":"PPL",
    "gn:name":"Capanne",
    "gn:population":0,
    "gn:timezone":"Europe/Rome",
    "iso:country":"IT",
    "name:deu_x_preferred":[
        "Capanne"
    ],
    "name:ltz_x_preferred":[
        "Capanne"
    ],
    "name:srp_x_preferred":[
        "Kapane"
    ],
    "wof:name":"Capanne",
    "wof:placetype":"locality"
},
  "geometry": {"coordinates":[16.63332999999999,39.06667],"type":"Point"}
}