{
  "type": "Feature",
  "properties": {
    "gn:admin1_code":"20",
    "gn:admin2_code":"TV",
    "gn:admin3_code":"26020.0",
    "gn:asciiname":"D'Annunzio",
    "gn:country_code":"IT",
    "gn:dem":94,
    "gn:feature_class":"P",
    "gn:feature_code":"PPL",
    "gn:name":"D'Annunzio",
    "gn:population":93,
    "gn:timezone":"Europe/Rome",
    "iso:country":"IT",
    "wof:name":"D'Annunzio",
    "wof:placetype":"locality",
    "wof:population":93
},
  "geometry": {"coordinates":[12.32843,45.94857],"type":"Point"}
}