{
  "type": "Feature",
  "properties": {
    "gn:admin1_code":"9",
    "gn:admin2_code":"PV",
    "gn:admin3_code":"18156.0",
    "gn:asciiname":"Castellaro de' Giorgi",
    "gn:country_code":"IT",
    "gn:dem":91,
    "gn:feature_class":"P",
    "gn:feature_code":"PPL",
    "gn:name":"Castellaro de' Giorgi",
    "gn:population":98,
    "gn:timezone":"Europe/Rome",
    "iso:country":"IT",
    "wof:name":"Castellaro de' Giorgi",
    "wof:placetype":"locality",
    "wof:population":98
},
  "geometry": {"coordinates":[8.70705,45.0753],"type":"Point"}
}