{
  "type": "Feature",
  "properties": {
    "gn:admin1_code":"8",
    "gn:admin2_code":"GE",
    "gn:admin3_code":"10037.0",
    "gn:asciiname":"Camposoprano",
    "gn:country_code":"IT",
    "gn:dem":159,
    "gn:feature_class":"P",
    "gn:feature_code":"PPL",
    "gn:name":"Camposoprano",
    "gn:population":41,
    "gn:timezone":"Europe/Rome",
    "iso:country":"IT",
    "wof:name":"Camposoprano",
    "wof:placetype":"locality",
    "wof:population":41
},
  "geometry": {"coordinates":[9.49683,44.25235],"type":"Point"}
}