{
  "type": "Feature",
  "properties": {
    "gn:admin1_code":"1",
    "gn:admin2_code":"TE",
    "gn:admin3_code":"67009.0",
    "gn:asciiname":"Maciera",
    "gn:country_code":"IT",
    "gn:dem":128,
    "gn:feature_class":"P",
    "gn:feature_code":"PPL",
    "gn:name":"Maciera",
    "gn:population":35,
    "gn:timezone":"Europe/Rome",
    "iso:country":"IT",
    "wof:name":"Maciera",
    "wof:placetype":"locality",
    "wof:population":35
},
  "geometry": {"coordinates":[13.82802,42.62991],"type":"Point"}
}