{
  "type": "Feature",
  "properties": {
    "gn:admin1_code":"6",
    "gn:admin2_code":"PN",
    "gn:admin3_code":"93026.0",
    "gn:asciiname":"Romaniz",
    "gn:country_code":"IT",
    "gn:dem":302,
    "gn:feature_class":"P",
    "gn:feature_code":"PPL",
    "gn:name":"Romaniz",
    "gn:population":18,
    "gn:timezone":"Europe/Rome",
    "iso:country":"IT",
    "wof:name":"Romaniz",
    "wof:placetype":"locality",
    "wof:population":18
},
  "geometry": {"coordinates":[12.76004,46.22784],"type":"Point"}
}