{
  "type": "Feature",
  "properties": {
    "gn:admin1_code":"16.0",
    "gn:admin2_code":"PT",
    "gn:admin3_code":"47017.0",
    "gn:asciiname":"Santonuovo",
    "gn:country_code":"IT",
    "gn:dem":49,
    "gn:feature_class":"P",
    "gn:feature_code":"PPL",
    "gn:name":"Santonuovo",
    "gn:population":901,
    "gn:timezone":"Europe/Rome",
    "iso:country":"IT",
    "wof:name":"Santonuovo",
    "wof:placetype":"locality",
    "wof:population":901
},
  "geometry": {"coordinates":[10.94394,43.86496],"type":"Point"}
}