{
  "type": "Feature",
  "properties": {
    "gn:admin1_code":"12.0",
    "gn:admin2_code":"CN",
    "gn:admin3_code":"4040.0",
    "gn:asciiname":"Roata Chiabo",
    "gn:country_code":"IT",
    "gn:dem":597,
    "gn:feature_class":"P",
    "gn:feature_code":"PPL",
    "gn:name":"Roata Chiab\u00f2",
    "gn:population":27,
    "gn:timezone":"Europe/Rome",
    "iso:country":"IT",
    "name:und_x_variant":[
        "Roata Chiab\u00f2"
    ],
    "wof:name":"Roata Chiabo",
    "wof:placetype":"locality",
    "wof:population":27
},
  "geometry": {"coordinates":[7.41743,44.4001],"type":"Point"}
}