{
  "type": "Feature",
  "properties": {
    "gn:admin1_code":"6",
    "gn:admin2_code":"PN",
    "gn:admin3_code":"93025.0",
    "gn:asciiname":"Case Filipuzzi",
    "gn:country_code":"IT",
    "gn:dem":245,
    "gn:feature_class":"P",
    "gn:feature_code":"PPL",
    "gn:name":"Case Filipuzzi",
    "gn:population":32,
    "gn:timezone":"Europe/Rome",
    "iso:country":"IT",
    "wof:name":"Case Filipuzzi",
    "wof:placetype":"locality",
    "wof:population":32
},
  "geometry": {"coordinates":[12.73726,46.14107],"type":"Point"}
}