{
  "type": "Feature",
  "properties": {
    "gn:admin1_code":"9",
    "gn:admin2_code":"MI",
    "gn:admin3_code":"15050.0",
    "gn:asciiname":"Cascina Longora",
    "gn:country_code":"IT",
    "gn:dem":92,
    "gn:feature_class":"P",
    "gn:feature_code":"PPL",
    "gn:name":"Cascina Longora",
    "gn:population":205,
    "gn:timezone":"Europe/Rome",
    "iso:country":"IT",
    "wof:name":"Cascina Longora",
    "wof:placetype":"locality",
    "wof:population":205
},
  "geometry": {"coordinates":[9.27399,45.32885],"type":"Point"}
}