{
  "type": "Feature",
  "properties": {
    "gn:admin1_code":"12",
    "gn:admin2_code":"TO",
    "gn:admin3_code":"1078.0",
    "gn:asciiname":"Mosi",
    "gn:country_code":"IT",
    "gn:dem":256,
    "gn:feature_class":"P",
    "gn:feature_code":"PPL",
    "gn:name":"Mosi",
    "gn:population":63,
    "gn:timezone":"Europe/Rome",
    "iso:country":"IT",
    "wof:name":"Mosi",
    "wof:placetype":"locality",
    "wof:population":63
},
  "geometry": {"coordinates":[7.79975,44.96979],"type":"Point"}
}