{
  "type": "Feature",
  "properties": {
    "gn:admin1_code":"14",
    "gn:admin2_code":"SS",
    "gn:admin3_code":"90023.0",
    "gn:asciiname":"Punta Tramontana",
    "gn:country_code":"IT",
    "gn:dem":31,
    "gn:feature_class":"P",
    "gn:feature_code":"PPL",
    "gn:name":"Punta Tramontana",
    "gn:population":14,
    "gn:timezone":"Europe/Rome",
    "iso:country":"IT",
    "wof:name":"Punta Tramontana",
    "wof:placetype":"locality",
    "wof:population":14
},
  "geometry": {"coordinates":[8.63439,40.87849],"type":"Point"}
}