{
  "type": "Feature",
  "properties": {
    "gn:admin1_code":"10",
    "gn:admin2_code":"AN",
    "gn:admin3_code":"42044.0",
    "gn:asciiname":"Felcine",
    "gn:country_code":"IT",
    "gn:dem":374,
    "gn:feature_class":"P",
    "gn:feature_code":"PPL",
    "gn:name":"Felcine",
    "gn:population":25,
    "gn:timezone":"Europe/Rome",
    "iso:country":"IT",
    "wof:name":"Felcine",
    "wof:placetype":"locality",
    "wof:population":25
},
  "geometry": {"coordinates":[12.86963,43.49816],"type":"Point"}
}