{
  "type": "Feature",
  "properties": {
    "gn:admin1_code":"5",
    "gn:admin2_code":"MO",
    "gn:admin3_code":"36016.0",
    "gn:asciiname":"Pian degli Ontani",
    "gn:country_code":"IT",
    "gn:dem":1075,
    "gn:feature_class":"P",
    "gn:feature_code":"PPLL",
    "gn:name":"Pian degli Ontani",
    "gn:population":8,
    "gn:timezone":"Europe/Rome",
    "iso:country":"IT",
    "wof:name":"Pian degli Ontani",
    "wof:placetype":"locality",
    "wof:population":8
},
  "geometry": {"coordinates":[10.53545,44.21761],"type":"Point"}
}