{
  "type": "Feature",
  "properties": {
    "gn:admin1_code":"7",
    "gn:admin2_code":"FR",
    "gn:admin3_code":"60019.0",
    "gn:asciiname":"Cocciuto",
    "gn:country_code":"IT",
    "gn:dem":61,
    "gn:feature_class":"P",
    "gn:feature_code":"PPL",
    "gn:name":"Cocciuto",
    "gn:population":52,
    "gn:timezone":"Europe/Rome",
    "iso:country":"IT",
    "wof:name":"Cocciuto",
    "wof:placetype":"locality",
    "wof:population":52
},
  "geometry": {"coordinates":[13.81444,41.46656],"type":"Point"}
}