{
  "type": "Feature",
  "properties": {
    "gn:admin1_code":"4",
    "gn:admin2_code":"BN",
    "gn:admin3_code":"62029.0",
    "gn:asciiname":"Russi",
    "gn:country_code":"IT",
    "gn:dem":206,
    "gn:feature_class":"P",
    "gn:feature_code":"PPL",
    "gn:name":"Russi",
    "gn:population":57,
    "gn:timezone":"Europe/Rome",
    "iso:country":"IT",
    "name:afr_x_preferred":[
        "Russi"
    ],
    "name:ara_x_preferred":[
        "\u0631\u0648\u0633\u064a"
    ],
    "name:azb_x_preferred":[
        "\u0631\u0648\u0633\u06cc"
    ],
    "name:bul_x_preferred":[
        "\u0420\u0443\u0441\u0438"
    ],
    "name:ceb_x_preferred":[
        "Russi"
    ],
    "name:ces_x_preferred":[
        "Russi"
    ],
    "name:deu_x_preferred":[
        "Russi"
    ],
    "name:eml_x_preferred":[
        "R\u00f3s"
    ],
    "name:epo_x_preferred":[
        "Russi"
    ],
    "name:eus_x_preferred":[
        "Russi"
    ],
    "name:fas_x_preferred":[
        "\u0631\u0648\u0633\u06cc"
    ],
    "name:fra_x_preferred":[
        "Russi"
    ],
    "name:hun_x_preferred":[
        "Russi"
    ],
    "name:hye_x_preferred":[
        "\u054c\u0578\u0582\u057d\u056b"
    ],
    "name:ina_x_preferred":[
        "Russi"
    ],
    "name:ita_x_preferred":[
        "Russi"
    ],
    "name:jpn_x_preferred":[
        "\u30eb\u30c3\u30b7"
    ],
    "name:kaz_x_preferred":[
        "\u0420\u0443\u0441\u0441\u0438"
    ],
    "name:lat_x_preferred":[
        "Russi"
    ],
    "name:lmo_x_preferred":[
        "Russi"
    ],
    "name:msa_x_preferred":[
        "Russi"
    ],
    "name:nap_x_preferred":[
        "Russi"
    ],
    "name:nld_x_preferred":[
        "Russi"
    ],
    "name:pms_x_preferred":[
        "Russi"
    ],
    "name:pol_x_preferred":[
        "Russi"
    ],
    "name:por_x_preferred":[
        "Russi"
    ],
    "name:ron_x_preferred":[
        "Russi"
    ],
    "name:rus_x_preferred":[
        "\u0420\u0443\u0441\u0441\u0438"
    ],
    "name:sco_x_preferred":[
        "Russi"
    ],
    "name:spa_x_preferred":[
        "Russi"
    ],
    "name:srp_x_preferred":[
        "\u0420\u0443\u0441\u0438"
    ],
    "name:tur_x_preferred":[
        "Russi"
    ],
    "name:ukr_x_preferred":[
        "\u0420\u0443\u0441\u0441\u0456"
    ],
    "name:uzb_x_preferred":[
        "Russi"
    ],
    "name:vec_x_preferred":[
        "Russi"
    ],
    "name:vie_x_preferred":[
        "Russi"
    ],
    "name:vol_x_preferred":[
        "Russi"
    ],
    "name:war_x_preferred":[
        "Russi"
    ],
    "name:zho_x_preferred":[
        "\u9c81\u897f"
    ],
    "wof:name":"Russi",
    "wof:placetype":"locality",
    "wof:population":57
},
  "geometry": {"coordinates":[14.46139,41.28353],"type":"Point"}
}