{
  "type": "Feature",
  "properties": {
    "gn:admin1_code":"4",
    "gn:admin2_code":"BN",
    "gn:admin3_code":"62029.0",
    "gn:asciiname":"Russi",
    "gn:country_code":"IT",
    "gn:dem":206,
    "gn:feature_class":"P",
    "gn:feature_code":"PPL",
    "gn:name":"Russi",
    "gn:population":57,
    "gn:timezone":"Europe/Rome",
    "iso:country":"IT",
    "wof:name":"Russi",
    "wof:placetype":"locality",
    "wof:population":57
},
  "geometry": {"coordinates":[14.46139,41.28353],"type":"Point"}
}