{
  "type": "Feature",
  "properties": {
    "gn:admin1_code":"16.0",
    "gn:admin2_code":"PO",
    "gn:admin3_code":"100001.0",
    "gn:asciiname":"Carmignanello",
    "gn:country_code":"IT",
    "gn:dem":188,
    "gn:elevation":"183.0",
    "gn:feature_class":"P",
    "gn:feature_code":"PPL",
    "gn:name":"Carmignanello",
    "gn:population":645,
    "gn:timezone":"Europe/Rome",
    "iso:country":"IT",
    "wof:name":"Carmignanello",
    "wof:placetype":"locality",
    "wof:population":645
},
  "geometry": {"coordinates":[11.14061,44.00044000000001],"type":"Point"}
}