{
  "type": "Feature",
  "properties": {
    "gn:admin1_code":"4",
    "gn:admin2_code":"CE",
    "gn:admin3_code":"61091.0",
    "gn:asciiname":"Borgonuovo",
    "gn:country_code":"IT",
    "gn:dem":183,
    "gn:feature_class":"P",
    "gn:feature_code":"PPL",
    "gn:name":"Borgonuovo",
    "gn:population":259,
    "gn:timezone":"Europe/Rome",
    "iso:country":"IT",
    "wof:name":"Borgonuovo",
    "wof:placetype":"locality",
    "wof:population":259
},
  "geometry": {"coordinates":[14.08916,41.27893],"type":"Point"}
}