{
  "type": "Feature",
  "properties": {
    "gn:admin1_code":"3.0",
    "gn:admin2_code":"CZ",
    "gn:admin3_code":"79160.0",
    "gn:asciiname":"Bellafemmina II",
    "gn:country_code":"IT",
    "gn:dem":26,
    "gn:feature_class":"P",
    "gn:feature_code":"PPL",
    "gn:name":"Bellafemmina II",
    "gn:population":6,
    "gn:timezone":"Europe/Rome",
    "iso:country":"IT",
    "wof:name":"Bellafemmina II",
    "wof:placetype":"locality",
    "wof:population":6
},
  "geometry": {"coordinates":[16.26333,38.91504000000001],"type":"Point"}
}