{
  "type": "Feature",
  "properties": {
    "gn:admin1_code":"10.0",
    "gn:admin2_code":"MC",
    "gn:admin3_code":"43045.0",
    "gn:asciiname":"Le Case",
    "gn:country_code":"IT",
    "gn:dem":311,
    "gn:feature_class":"P",
    "gn:feature_code":"PPL",
    "gn:name":"Le Case",
    "gn:population":27,
    "gn:timezone":"Europe/Rome",
    "iso:country":"IT",
    "wof:name":"Le Case",
    "wof:placetype":"locality",
    "wof:population":27
},
  "geometry": {"coordinates":[13.37776,43.13836],"type":"Point"}
}