{
  "type": "Feature",
  "properties": {
    "gn:admin1_code":"5.0",
    "gn:admin2_code":"FE",
    "gn:admin3_code":"38003.0",
    "gn:asciiname":"Ponte Rodoni",
    "gn:country_code":"IT",
    "gn:dem":10,
    "gn:feature_class":"P",
    "gn:feature_code":"PPL",
    "gn:name":"Ponte Rodoni",
    "gn:population":372,
    "gn:timezone":"Europe/Rome",
    "iso:country":"IT",
    "wof:name":"Ponte Rodoni",
    "wof:placetype":"locality",
    "wof:population":372
},
  "geometry": {"coordinates":[11.44515,44.86809],"type":"Point"}
}