{
  "type": "Feature",
  "properties": {
    "gn:admin1_code":"20",
    "gn:admin2_code":"RO",
    "gn:admin3_code":"29001.0",
    "gn:asciiname":"Forcarigoli",
    "gn:country_code":"IT",
    "gn:dem":1,
    "gn:feature_class":"P",
    "gn:feature_code":"PPL",
    "gn:name":"Forcarigoli",
    "gn:population":19,
    "gn:timezone":"Europe/Rome",
    "iso:country":"IT",
    "wof:name":"Forcarigoli",
    "wof:placetype":"locality",
    "wof:population":19
},
  "geometry": {"coordinates":[12.12576,45.05593],"type":"Point"}
}