{
  "type": "Feature",
  "properties": {
    "iso:country":"IT",
    "wof:name":"Sestiere di Porta Comacina",
    "wof:placetype":"neighbourhood"
},
  "geometry": {"coordinates":[9.18508734403263,45.46801286328726],"type":"Point"}
}