{
  "type": "Feature",
  "properties": {
    "gn:admin1_code":"12",
    "gn:admin2_code":"CN",
    "gn:admin3_code":"4025.0",
    "gn:asciiname":"Via Don Minzoni",
    "gn:country_code":"IT",
    "gn:dem":613,
    "gn:feature_class":"P",
    "gn:feature_code":"PPL",
    "gn:name":"Via Don Minzoni",
    "gn:population":62,
    "gn:timezone":"Europe/Rome",
    "iso:country":"IT",
    "wof:name":"Via Don Minzoni",
    "wof:placetype":"locality",
    "wof:population":62
},
  "geometry": {"coordinates":[7.49751,44.32924000000001],"type":"Point"}
}