{
  "type": "Feature",
  "properties": {
    "gn:admin1_code":"20",
    "gn:admin2_code":"TV",
    "gn:admin3_code":"26031.0",
    "gn:asciiname":"Bruna",
    "gn:country_code":"IT",
    "gn:dem":15,
    "gn:feature_class":"P",
    "gn:feature_code":"PPL",
    "gn:name":"Bruna",
    "gn:population":31,
    "gn:timezone":"Europe/Rome",
    "iso:country":"IT",
    "wof:name":"Bruna",
    "wof:placetype":"locality",
    "wof:population":31
},
  "geometry": {"coordinates":[12.48776,45.90032],"type":"Point"}
}