{
  "type": "Feature",
  "properties": {
    "gn:admin1_code":"20",
    "gn:admin2_code":"TV",
    "gn:admin3_code":"26031.0",
    "gn:asciiname":"Bruna",
    "gn:country_code":"IT",
    "gn:dem":15,
    "gn:feature_class":"P",
    "gn:feature_code":"PPL",
    "gn:name":"Bruna",
    "gn:population":31,
    "gn:timezone":"Europe/Rome",
    "iso:country":"IT",
    "name:bre_x_preferred":[
        "Bruna"
    ],
    "name:ceb_x_preferred":[
        "Bruna"
    ],
    "name:deu_x_preferred":[
        "Bruna"
    ],
    "name:fra_x_preferred":[
        "Bruna"
    ],
    "name:heb_x_preferred":[
        "\u05d1\u05e8\u05d5\u05e0\u05d0"
    ],
    "name:ita_x_preferred":[
        "Bruna"
    ],
    "name:nld_x_preferred":[
        "Bruna"
    ],
    "name:rus_x_preferred":[
        "\u0411\u0440\u0443\u043d\u0430"
    ],
    "name:spa_x_preferred":[
        "Bruna"
    ],
    "name:srp_x_preferred":[
        "Bruna"
    ],
    "name:ukr_x_preferred":[
        "\u0411\u0440\u0443\u043d\u0430"
    ],
    "wof:name":"Bruna",
    "wof:placetype":"locality",
    "wof:population":31
},
  "geometry": {"coordinates":[12.48776,45.90032],"type":"Point"}
}