{
  "type": "Feature",
  "properties": {
    "gn:admin1_code":"8",
    "gn:admin2_code":"SV",
    "gn:admin3_code":"9024.0",
    "gn:asciiname":"Faro",
    "gn:country_code":"IT",
    "gn:dem":84,
    "gn:feature_class":"P",
    "gn:feature_code":"PPL",
    "gn:name":"Faro",
    "gn:population":107,
    "gn:timezone":"Europe/Rome",
    "iso:country":"IT",
    "name:arg_x_preferred":[
        "Faro"
    ],
    "name:ceb_x_preferred":[
        "Faro"
    ],
    "name:deu_x_preferred":[
        "Faro"
    ],
    "name:epo_x_preferred":[
        "Faro"
    ],
    "name:fas_x_preferred":[
        "\u0641\u0627\u0631\u0648"
    ],
    "name:fin_x_preferred":[
        "Faro"
    ],
    "name:fra_x_preferred":[
        "Faro"
    ],
    "name:glg_x_preferred":[
        "Faro"
    ],
    "name:ita_x_preferred":[
        "Faro"
    ],
    "name:jpn_x_preferred":[
        "\u30d5\u30a1\u30ed"
    ],
    "name:ltz_x_preferred":[
        "Faro"
    ],
    "name:nld_x_preferred":[
        "Faro"
    ],
    "name:nor_x_preferred":[
        "Faro"
    ],
    "name:pnb_x_preferred":[
        "\u0641\u0627\u0631\u0648"
    ],
    "name:pol_x_preferred":[
        "Faro"
    ],
    "name:por_x_preferred":[
        "Faro"
    ],
    "name:rus_x_preferred":[
        "\u0424\u0430\u0440\u043e"
    ],
    "name:scn_x_preferred":[
        "Faro"
    ],
    "name:sco_x_preferred":[
        "Faro"
    ],
    "name:slk_x_preferred":[
        "Faro"
    ],
    "name:spa_x_preferred":[
        "Faro"
    ],
    "name:srp_x_preferred":[
        "Faro"
    ],
    "name:swe_x_preferred":[
        "Faro"
    ],
    "name:vol_x_preferred":[
        "Faro"
    ],
    "wof:name":"Faro",
    "wof:placetype":"locality",
    "wof:population":107
},
  "geometry": {"coordinates":[8.20835,44.09177],"type":"Point"}
}