{
  "type": "Feature",
  "properties": {
    "gn:admin1_code":"9.0",
    "gn:admin2_code":"SO",
    "gn:admin3_code":"14005.0",
    "gn:asciiname":"Lotto",
    "gn:country_code":"IT",
    "gn:dem":969,
    "gn:feature_class":"P",
    "gn:feature_code":"PPLL",
    "gn:name":"Lotto",
    "gn:population":0,
    "gn:timezone":"Europe/Rome",
    "iso:country":"IT",
    "name:dan_x_preferred":[
        "Lotto"
    ],
    "name:deu_x_preferred":[
        "Lotto"
    ],
    "name:fra_x_preferred":[
        "Lotto"
    ],
    "name:glg_x_preferred":[
        "Lotto"
    ],
    "name:ita_x_preferred":[
        "Lotto"
    ],
    "name:pol_x_preferred":[
        "Lotto"
    ],
    "name:rus_x_preferred":[
        "\u041b\u043e\u0442\u0442\u043e"
    ],
    "name:ukr_x_preferred":[
        "\u041b\u043e\u0442\u0442\u043e"
    ],
    "wof:name":"Lotto",
    "wof:placetype":"locality"
},
  "geometry": {"coordinates":[9.63532,46.17921],"type":"Point"}
}