{
  "type": "Feature",
  "properties": {
    "gn:admin1_code":"7",
    "gn:admin2_code":"RI",
    "gn:admin3_code":"57038.0",
    "gn:asciiname":"Vocabolo Collericcio",
    "gn:country_code":"IT",
    "gn:dem":310,
    "gn:feature_class":"P",
    "gn:feature_code":"PPL",
    "gn:name":"Vocabolo Collericcio",
    "gn:population":20,
    "gn:timezone":"Europe/Rome",
    "iso:country":"IT",
    "wof:name":"Vocabolo Collericcio",
    "wof:placetype":"locality",
    "wof:population":20
},
  "geometry": {"coordinates":[12.7806,42.24896],"type":"Point"}
}