{
  "type": "Feature",
  "properties": {
    "gn:admin1_code":"9",
    "gn:admin2_code":"BG",
    "gn:admin3_code":"16068.0",
    "gn:asciiname":"Piazze",
    "gn:country_code":"IT",
    "gn:dem":468,
    "gn:feature_class":"P",
    "gn:feature_code":"PPL",
    "gn:name":"Piazze",
    "gn:population":27,
    "gn:timezone":"Europe/Rome",
    "iso:country":"IT",
    "wof:name":"Piazze",
    "wof:placetype":"locality",
    "wof:population":27
},
  "geometry": {"coordinates":[9.80167,45.71803],"type":"Point"}
}