{
  "type": "Feature",
  "properties": {
    "gn:admin1_code":"1.0",
    "gn:admin2_code":"TE",
    "gn:admin3_code":"67030.0",
    "gn:asciiname":"Collepietro",
    "gn:country_code":"IT",
    "gn:dem":217,
    "gn:feature_class":"P",
    "gn:feature_code":"PPL",
    "gn:name":"Collepietro",
    "gn:population":61,
    "gn:timezone":"Europe/Rome",
    "iso:country":"IT",
    "wof:name":"Collepietro",
    "wof:placetype":"locality",
    "wof:population":61
},
  "geometry": {"coordinates":[13.86349,42.74123],"type":"Point"}
}