{
  "type": "Feature",
  "properties": {
    "gn:admin1_code":"1.0",
    "gn:admin2_code":"TE",
    "gn:admin3_code":"67030.0",
    "gn:asciiname":"Collepietro",
    "gn:country_code":"IT",
    "gn:dem":217,
    "gn:feature_class":"P",
    "gn:feature_code":"PPL",
    "gn:name":"Collepietro",
    "gn:population":61,
    "gn:timezone":"Europe/Rome",
    "iso:country":"IT",
    "name:ara_x_preferred":[
        "\u0643\u0648\u0644\u064a\u0628\u064a\u062a\u0631\u0648"
    ],
    "name:azb_x_preferred":[
        "\u06a9\u0648\u0644\u067e\u06cc\u062a\u0631\u0648"
    ],
    "name:bar_x_preferred":[
        "Collepietro"
    ],
    "name:bcl_x_preferred":[
        "Collepietro"
    ],
    "name:bel_x_preferred":[
        "\u041a\u0430\u043b\u0435\u043f\u2019\u0435\u0442\u0440\u0430"
    ],
    "name:bul_x_preferred":[
        "\u041a\u043e\u043b\u0435\u043f\u0438\u0435\u0442\u0440\u043e"
    ],
    "name:ceb_x_preferred":[
        "Collepietro"
    ],
    "name:deu_x_preferred":[
        "Collepietro"
    ],
    "name:epo_x_preferred":[
        "Collepietro"
    ],
    "name:eus_x_preferred":[
        "Collepietro"
    ],
    "name:fas_x_preferred":[
        "\u06a9\u0648\u0644\u067e\u06cc\u062a\u0631\u0648"
    ],
    "name:fra_x_preferred":[
        "Collepietro"
    ],
    "name:hun_x_preferred":[
        "Collepietro"
    ],
    "name:hye_x_preferred":[
        "\u053f\u0578\u056c\u0565\u057a\u056b\u0565\u057f\u0580\u0578"
    ],
    "name:ina_x_preferred":[
        "Collepietro"
    ],
    "name:ita_x_preferred":[
        "Collepietro"
    ],
    "name:jpn_x_preferred":[
        "\u30b3\u30c3\u30ec\u30d4\u30a8\u30c8\u30ed"
    ],
    "name:kaz_x_preferred":[
        "\u041a\u043e\u043b\u043b\u0435\u043f\u044c\u0435\u0442\u0440\u043e"
    ],
    "name:kor_x_preferred":[
        "\ucf5c\ub808\ud53c\uc5d0\ud2b8\ub85c"
    ],
    "name:lat_x_preferred":[
        "Collis Petrae"
    ],
    "name:lmo_x_preferred":[
        "Collepietro"
    ],
    "name:msa_x_preferred":[
        "Collepietro"
    ],
    "name:nap_x_preferred":[
        "Collepietro"
    ],
    "name:nld_x_preferred":[
        "Collepietro"
    ],
    "name:pms_x_preferred":[
        "Collepietro"
    ],
    "name:pol_x_preferred":[
        "Collepietro"
    ],
    "name:por_x_preferred":[
        "Collepietro"
    ],
    "name:ron_x_preferred":[
        "Collepietro"
    ],
    "name:rus_x_preferred":[
        "\u041a\u043e\u043b\u043b\u0435\u043f\u044c\u0435\u0442\u0440\u043e"
    ],
    "name:scn_x_preferred":[
        "Collipietru"
    ],
    "name:spa_x_preferred":[
        "Collepietro"
    ],
    "name:srp_x_preferred":[
        "\u041a\u043e\u043b\u0435\u043f\u0438\u0458\u0435\u0442\u0440\u043e"
    ],
    "name:tgl_x_preferred":[
        "Collepietro"
    ],
    "name:ukr_x_preferred":[
        "\u041a\u043e\u043b\u043b\u0435\u043f'\u0454\u0442\u0440\u043e"
    ],
    "name:uzb_x_preferred":[
        "Collepietro"
    ],
    "name:vie_x_preferred":[
        "Collepietro"
    ],
    "name:vol_x_preferred":[
        "Collepietro"
    ],
    "name:war_x_preferred":[
        "Collepietro"
    ],
    "name:zho_x_preferred":[
        "\u79d1\u83b1\u76ae\u8036\u7279\u7f57"
    ],
    "wof:name":"Collepietro",
    "wof:placetype":"locality",
    "wof:population":61
},
  "geometry": {"coordinates":[13.86349,42.74123],"type":"Point"}
}