{
  "type": "Feature",
  "properties": {
    "gn:admin1_code":"8",
    "gn:admin2_code":"SP",
    "gn:admin3_code":"11032.0",
    "gn:asciiname":"Valgiuncata",
    "gn:country_code":"IT",
    "gn:dem":451,
    "gn:feature_class":"P",
    "gn:feature_code":"PPL",
    "gn:name":"Valgiuncata",
    "gn:population":29,
    "gn:timezone":"Europe/Rome",
    "iso:country":"IT",
    "wof:name":"Valgiuncata",
    "wof:placetype":"locality",
    "wof:population":29
},
  "geometry": {"coordinates":[9.73573,44.30614],"type":"Point"}
}