{
  "type": "Feature",
  "properties": {
    "gn:admin1_code":"20",
    "gn:admin2_code":"VR",
    "gn:admin3_code":"23054.0",
    "gn:asciiname":"Salette",
    "gn:country_code":"IT",
    "gn:dem":34,
    "gn:feature_class":"P",
    "gn:feature_code":"PPL",
    "gn:name":"Salette",
    "gn:population":19,
    "gn:timezone":"Europe/Rome",
    "iso:country":"IT",
    "wof:name":"Salette",
    "wof:placetype":"locality",
    "wof:population":19
},
  "geometry": {"coordinates":[10.91158,45.29777],"type":"Point"}
}