{
  "type": "Feature",
  "properties": {
    "gn:admin1_code":"3.0",
    "gn:admin2_code":"RC",
    "gn:admin3_code":"80042.0",
    "gn:asciiname":"Plaesano",
    "gn:country_code":"IT",
    "gn:dem":260,
    "gn:feature_class":"P",
    "gn:feature_code":"PPL",
    "gn:name":"Plaesano",
    "gn:population":0,
    "gn:timezone":"Europe/Rome",
    "iso:country":"IT",
    "wof:name":"Plaesano",
    "wof:placetype":"locality"
},
  "geometry": {"coordinates":[16.08333,38.48333],"type":"Point"}
}