{
  "type": "Feature",
  "properties": {
    "gn:admin1_code":"11",
    "gn:admin2_code":"IS",
    "gn:admin3_code":"94021.0",
    "gn:asciiname":"Chiuselle",
    "gn:country_code":"IT",
    "gn:dem":398,
    "gn:feature_class":"P",
    "gn:feature_code":"PPL",
    "gn:name":"Chiuselle",
    "gn:population":103,
    "gn:timezone":"Europe/Rome",
    "iso:country":"IT",
    "wof:name":"Chiuselle",
    "wof:placetype":"locality",
    "wof:population":103
},
  "geometry": {"coordinates":[14.14555,41.59838],"type":"Point"}
}