{
  "type": "Feature",
  "properties": {
    "gn:admin1_code":"16.0",
    "gn:admin2_code":"FI",
    "gn:admin3_code":"48018.0",
    "gn:asciiname":"Osteto",
    "gn:country_code":"IT",
    "gn:dem":569,
    "gn:elevation":"585.0",
    "gn:feature_class":"P",
    "gn:feature_code":"PPL",
    "gn:name":"Osteto",
    "gn:population":12,
    "gn:timezone":"Europe/Rome",
    "iso:country":"IT",
    "wof:name":"Osteto",
    "wof:placetype":"locality",
    "wof:population":12
},
  "geometry": {"coordinates":[11.41654,44.06967],"type":"Point"}
}