{
  "type": "Feature",
  "properties": {
    "gn:admin1_code":"4.0",
    "gn:admin2_code":"SA",
    "gn:admin3_code":"65022.0",
    "gn:asciiname":"Folcata",
    "gn:country_code":"IT",
    "gn:dem":222,
    "gn:feature_class":"P",
    "gn:feature_code":"PPL",
    "gn:name":"Folcata",
    "gn:population":481,
    "gn:timezone":"Europe/Rome",
    "iso:country":"IT",
    "wof:name":"Folcata",
    "wof:placetype":"locality",
    "wof:population":481
},
  "geometry": {"coordinates":[15.11624,40.6498],"type":"Point"}
}