{
  "type": "Feature",
  "properties": {
    "gn:admin1_code":"20",
    "gn:admin2_code":"TV",
    "gn:admin3_code":"26002.0",
    "gn:asciiname":"Madonnetta",
    "gn:country_code":"IT",
    "gn:dem":61,
    "gn:feature_class":"P",
    "gn:feature_code":"PPL",
    "gn:name":"Madonnetta",
    "gn:population":223,
    "gn:timezone":"Europe/Rome",
    "iso:country":"IT",
    "wof:name":"Madonnetta",
    "wof:placetype":"locality",
    "wof:population":223
},
  "geometry": {"coordinates":[12.23157,45.79222],"type":"Point"}
}