{
  "type": "Feature",
  "properties": {
    "gn:admin1_code":"8.0",
    "gn:admin2_code":"IM",
    "gn:admin3_code":"8035.0",
    "gn:asciiname":"Rataira",
    "gn:country_code":"IT",
    "gn:dem":358,
    "gn:feature_class":"P",
    "gn:feature_code":"PPL",
    "gn:name":"Rataira",
    "gn:population":0,
    "gn:timezone":"Europe/Rome",
    "iso:country":"IT",
    "wof:name":"Rataira",
    "wof:placetype":"locality"
},
  "geometry": {"coordinates":[7.81667,43.96667],"type":"Point"}
}