{
  "type": "Feature",
  "properties": {
    "gn:admin1_code":"8",
    "gn:admin2_code":"GE",
    "gn:admin3_code":"10031.0",
    "gn:asciiname":"Tolara",
    "gn:country_code":"IT",
    "gn:dem":503,
    "gn:feature_class":"P",
    "gn:feature_code":"PPL",
    "gn:name":"Tolara",
    "gn:population":13,
    "gn:timezone":"Europe/Rome",
    "iso:country":"IT",
    "wof:name":"Tolara",
    "wof:placetype":"locality",
    "wof:population":13
},
  "geometry": {"coordinates":[9.11497,44.45059000000001],"type":"Point"}
}