{
  "type": "Feature",
  "properties": {
    "gn:admin1_code":"4",
    "gn:admin2_code":"AV",
    "gn:admin3_code":"64047.0",
    "gn:asciiname":"Torre",
    "gn:country_code":"IT",
    "gn:dem":87,
    "gn:feature_class":"P",
    "gn:feature_code":"PPL",
    "gn:name":"Torre",
    "gn:population":32,
    "gn:timezone":"Europe/Rome",
    "iso:country":"IT",
    "wof:name":"Torre",
    "wof:placetype":"locality",
    "wof:population":32
},
  "geometry": {"coordinates":[14.57529,40.90024],"type":"Point"}
}