{
  "type": "Feature",
  "properties": {
    "gn:gn_country":"IT",
    "gn:gn_fcode":"PPL",
    "gn:gn_pop":0,
    "gn:population":36,
    "iso:country":"IT",
    "name:deu_x_preferred":[
        "La Piazza"
    ],
    "name:eng_x_preferred":[
        "La Piazza"
    ],
    "name:ita_x_preferred":[
        "La Piazza"
    ],
    "name:nld_x_preferred":[
        "Piazza"
    ],
    "name:srp_x_preferred":[
        "Piazza"
    ],
    "qs_pg:aaroncc":"IT",
    "qs_pg:gn_country":"IT",
    "qs_pg:gn_fcode":"PPL",
    "qs_pg:gn_pop":0,
    "qs_pg:name":"La Piazza",
    "qs_pg:name_adm0":"Italia",
    "qs_pg:name_adm1":"Toscana",
    "qs_pg:photos":9,
    "qs_pg:photos_1k":2,
    "qs_pg:photos_9k":1,
    "qs_pg:photos_9r":1,
    "qs_pg:photos_all":9,
    "qs_pg:photos_sr":1,
    "qs_pg:pop_sr":0,
    "qs_pg:qs_pg_placetype":"locality",
    "qs_pg:qs_pg_placetype_gp":"Town",
    "qs_pg:woe_adm0":23424853,
    "woe:adm0_id":23424853,
    "woe:name_adm0":"Italia",
    "woe:name_adm1":"Toscana",
    "woe:placetype":"Town",
    "wof:name":"La Piazza",
    "wof:placetype":"locality",
    "wof:population":36
},
  "geometry": {"coordinates":[11.28517,43.52967],"type":"Point"}
}