{
  "type": "Feature",
  "properties": {
    "gn:admin1_code":"8",
    "gn:admin2_code":"SV",
    "gn:admin3_code":"9067.0",
    "gn:asciiname":"Campei",
    "gn:country_code":"IT",
    "gn:dem":276,
    "gn:feature_class":"P",
    "gn:feature_code":"PPL",
    "gn:name":"Campei",
    "gn:population":23,
    "gn:timezone":"Europe/Rome",
    "iso:country":"IT",
    "wof:name":"Campei",
    "wof:placetype":"locality",
    "wof:population":23
},
  "geometry": {"coordinates":[8.35426,44.23527],"type":"Point"}
}