{
  "type": "Feature",
  "properties": {
    "gn:admin1_code":"20.0",
    "gn:admin2_code":"RO",
    "gn:admin3_code":"29009.0",
    "gn:asciiname":"Paviole",
    "gn:country_code":"IT",
    "gn:dem":5,
    "gn:elevation":"8.0",
    "gn:feature_class":"P",
    "gn:feature_code":"PPL",
    "gn:name":"Paviole",
    "gn:population":49,
    "gn:timezone":"Europe/Rome",
    "iso:country":"IT",
    "wof:name":"Paviole",
    "wof:placetype":"locality",
    "wof:population":49
},
  "geometry": {"coordinates":[11.66422,44.915],"type":"Point"}
}