{
  "type": "Feature",
  "properties": {
    "gn:admin1_code":"16",
    "gn:admin2_code":"FI",
    "gn:admin3_code":"48011.0",
    "gn:asciiname":"Lotti-Sant'Anna",
    "gn:country_code":"IT",
    "gn:dem":99,
    "gn:feature_class":"P",
    "gn:feature_code":"PPL",
    "gn:name":"Lotti-Sant'Anna",
    "gn:population":32,
    "gn:timezone":"Europe/Rome",
    "iso:country":"IT",
    "wof:name":"Lotti-Sant'Anna",
    "wof:placetype":"locality",
    "wof:population":32
},
  "geometry": {"coordinates":[10.88444,43.74709],"type":"Point"}
}