{
  "type": "Feature",
  "properties": {
    "gn:admin1_code":"9",
    "gn:admin2_code":"VA",
    "gn:admin3_code":"12133.0",
    "gn:asciiname":"Dei Boderi",
    "gn:country_code":"IT",
    "gn:dem":268,
    "gn:feature_class":"P",
    "gn:feature_code":"PPL",
    "gn:name":"Dei Boderi",
    "gn:population":16,
    "gn:timezone":"Europe/Rome",
    "iso:country":"IT",
    "wof:name":"Dei Boderi",
    "wof:placetype":"locality",
    "wof:population":16
},
  "geometry": {"coordinates":[8.81763,45.80248],"type":"Point"}
}