{
  "type": "Feature",
  "properties": {
    "gn:admin1_code":"8",
    "gn:admin2_code":"SV",
    "gn:admin3_code":"9037.0",
    "gn:asciiname":"Muraglia",
    "gn:country_code":"IT",
    "gn:dem":658,
    "gn:feature_class":"P",
    "gn:feature_code":"PPLL",
    "gn:name":"Muraglia",
    "gn:population":7,
    "gn:timezone":"Europe/Rome",
    "iso:country":"IT",
    "wof:name":"Muraglia",
    "wof:placetype":"locality",
    "wof:population":7
},
  "geometry": {"coordinates":[8.08476,44.301],"type":"Point"}
}