{
  "type": "Feature",
  "properties": {
    "gn:admin1_code":"17",
    "gn:admin2_code":"TN",
    "gn:admin3_code":"22248.0",
    "gn:asciiname":"Pin-Vallene",
    "gn:country_code":"IT",
    "gn:dem":726,
    "gn:feature_class":"P",
    "gn:feature_code":"PPL",
    "gn:name":"Pin-Vallene",
    "gn:population":101,
    "gn:timezone":"Europe/Rome",
    "iso:country":"IT",
    "wof:name":"Pin-Vallene",
    "wof:placetype":"locality",
    "wof:population":101
},
  "geometry": {"coordinates":[11.04561,46.10916],"type":"Point"}
}