{
  "type": "Feature",
  "properties": {
    "gn:admin1_code":"6",
    "gn:admin2_code":"UD",
    "gn:admin3_code":"30085.0",
    "gn:asciiname":"Bordon",
    "gn:country_code":"IT",
    "gn:dem":280,
    "gn:feature_class":"P",
    "gn:feature_code":"PPL",
    "gn:name":"Bordon",
    "gn:population":17,
    "gn:timezone":"Europe/Rome",
    "iso:country":"IT",
    "wof:name":"Bordon",
    "wof:placetype":"locality",
    "wof:population":17
},
  "geometry": {"coordinates":[13.59459,46.10658],"type":"Point"}
}