{
  "type": "Feature",
  "properties": {
    "gn:admin1_code":"4",
    "gn:admin2_code":"AV",
    "gn:admin3_code":"64050.0",
    "gn:asciiname":"San Francesco",
    "gn:country_code":"IT",
    "gn:dem":511,
    "gn:feature_class":"P",
    "gn:feature_code":"PPL",
    "gn:name":"San Francesco",
    "gn:population":11,
    "gn:timezone":"Europe/Rome",
    "iso:country":"IT",
    "wof:name":"San Francesco",
    "wof:placetype":"locality",
    "wof:population":11
},
  "geometry": {"coordinates":[15.0174,41.03554000000001],"type":"Point"}
}