{
  "type": "Feature",
  "properties": {
    "gn:admin1_code":"5",
    "gn:admin2_code":"MO",
    "gn:admin3_code":"36033.0",
    "gn:asciiname":"Castelvecchio",
    "gn:country_code":"IT",
    "gn:dem":445,
    "gn:feature_class":"P",
    "gn:feature_code":"PPL",
    "gn:name":"Castelvecchio",
    "gn:population":76,
    "gn:timezone":"Europe/Rome",
    "iso:country":"IT",
    "name:ceb_x_preferred":[
        "Castelvecchio"
    ],
    "name:deu_x_preferred":[
        "Castelvecchio"
    ],
    "name:ita_x_preferred":[
        "Castelvecchio"
    ],
    "name:pol_x_preferred":[
        "Castelvecchio"
    ],
    "name:srp_x_preferred":[
        "Kastelvekio"
    ],
    "name:swe_x_preferred":[
        "Castelvecchio"
    ],
    "name:ukr_x_preferred":[
        "\u041a\u0430\u0441\u0442\u0435\u043b\u044c\u0432\u0435\u043a\u043a\u0456\u043e"
    ],
    "wof:name":"Castelvecchio",
    "wof:placetype":"locality",
    "wof:population":76
},
  "geometry": {"coordinates":[10.67173,44.44819],"type":"Point"}
}