{
  "type": "Feature",
  "properties": {
    "gn:admin1_code":"9",
    "gn:admin2_code":"LC",
    "gn:admin3_code":"97092.0",
    "gn:asciiname":"Mulino",
    "gn:country_code":"IT",
    "gn:dem":331,
    "gn:feature_class":"P",
    "gn:feature_code":"PPL",
    "gn:name":"Mulino",
    "gn:population":15,
    "gn:timezone":"Europe/Rome",
    "iso:country":"IT",
    "name:ceb_x_preferred":[
        "Mulino"
    ],
    "name:hun_x_preferred":[
        "Mulino"
    ],
    "name:hye_x_preferred":[
        "\u0544\u0578\u0582\u056c\u056b\u0576\u0578"
    ],
    "name:ita_x_preferred":[
        "Mulino"
    ],
    "name:rus_x_preferred":[
        "\u041c\u0443\u043b\u0438\u043d\u043e"
    ],
    "name:srp_x_preferred":[
        "Mulino"
    ],
    "name:swe_x_preferred":[
        "Mulino"
    ],
    "wof:name":"Mulino",
    "wof:placetype":"locality",
    "wof:population":15
},
  "geometry": {"coordinates":[9.36657,45.74458],"type":"Point"}
}