{
  "type": "Feature",
  "properties": {
    "gn:admin1_code":"7",
    "gn:admin2_code":"VT",
    "gn:admin3_code":"56045.0",
    "gn:asciiname":"Chianello di Sopra",
    "gn:country_code":"IT",
    "gn:dem":486,
    "gn:feature_class":"P",
    "gn:feature_code":"PPL",
    "gn:name":"Chianello di Sopra",
    "gn:population":32,
    "gn:timezone":"Europe/Rome",
    "iso:country":"IT",
    "wof:name":"Chianello di Sopra",
    "wof:placetype":"locality",
    "wof:population":32
},
  "geometry": {"coordinates":[12.19964,42.29088],"type":"Point"}
}