{
  "type": "Feature",
  "properties": {
    "gn:admin1_code":"6",
    "gn:admin2_code":"GO",
    "gn:admin3_code":"31019.0",
    "gn:asciiname":"Giasbana I",
    "gn:country_code":"IT",
    "gn:dem":78,
    "gn:feature_class":"P",
    "gn:feature_code":"PPL",
    "gn:name":"Giasbana I",
    "gn:population":68,
    "gn:timezone":"Europe/Rome",
    "iso:country":"IT",
    "wof:name":"Giasbana I",
    "wof:placetype":"locality",
    "wof:population":68
},
  "geometry": {"coordinates":[13.5604,45.96492],"type":"Point"}
}