{
  "type": "Feature",
  "properties": {
    "gn:admin1_code":"9",
    "gn:admin2_code":"MN",
    "gn:admin3_code":"20013.0",
    "gn:asciiname":"Le Truzze",
    "gn:country_code":"IT",
    "gn:dem":29,
    "gn:feature_class":"P",
    "gn:feature_code":"PPL",
    "gn:name":"Le Truzze",
    "gn:population":29,
    "gn:timezone":"Europe/Rome",
    "iso:country":"IT",
    "wof:name":"Le Truzze",
    "wof:placetype":"locality",
    "wof:population":29
},
  "geometry": {"coordinates":[10.87987,45.21035],"type":"Point"}
}