{
  "type": "Feature",
  "properties": {
    "gn:admin1_code":"16",
    "gn:admin2_code":"PI",
    "gn:admin3_code":"50033.0",
    "gn:asciiname":"Baldacci",
    "gn:country_code":"IT",
    "gn:dem":34,
    "gn:feature_class":"P",
    "gn:feature_code":"PPL",
    "gn:name":"Baldacci",
    "gn:population":47,
    "gn:timezone":"Europe/Rome",
    "iso:country":"IT",
    "wof:name":"Baldacci",
    "wof:placetype":"locality",
    "wof:population":47
},
  "geometry": {"coordinates":[10.71413,43.77459],"type":"Point"}
}