{
  "type": "Feature",
  "properties": {
    "gn:admin1_code":"16",
    "gn:admin2_code":"AR",
    "gn:admin3_code":"51027.0",
    "gn:asciiname":"San Piero",
    "gn:country_code":"IT",
    "gn:dem":357,
    "gn:feature_class":"P",
    "gn:feature_code":"PPL",
    "gn:name":"San Piero",
    "gn:population":261,
    "gn:timezone":"Europe/Rome",
    "iso:country":"IT",
    "wof:name":"San Piero",
    "wof:placetype":"locality",
    "wof:population":261
},
  "geometry": {"coordinates":[11.76419,43.6879],"type":"Point"}
}