{
  "type": "Feature",
  "properties": {
    "gn:admin1_code":"13",
    "gn:admin2_code":"LE",
    "gn:admin3_code":"75031.0",
    "gn:asciiname":"Perez",
    "gn:country_code":"IT",
    "gn:dem":20,
    "gn:feature_class":"P",
    "gn:feature_code":"PPL",
    "gn:name":"Perez",
    "gn:population":83,
    "gn:timezone":"Europe/Rome",
    "iso:country":"IT",
    "wof:name":"Perez",
    "wof:placetype":"locality",
    "wof:population":83
},
  "geometry": {"coordinates":[18.01182,40.06311],"type":"Point"}
}