{
  "type": "Feature",
  "properties": {
    "gn:admin1_code":"20",
    "gn:admin2_code":"RO",
    "gn:admin3_code":"29014.0",
    "gn:asciiname":"Case Chilanti",
    "gn:country_code":"IT",
    "gn:dem":8,
    "gn:feature_class":"P",
    "gn:feature_code":"PPL",
    "gn:name":"Case Chilanti",
    "gn:population":77,
    "gn:timezone":"Europe/Rome",
    "iso:country":"IT",
    "wof:name":"Case Chilanti",
    "wof:placetype":"locality",
    "wof:population":77
},
  "geometry": {"coordinates":[11.37835,45.01445],"type":"Point"}
}