{
  "type": "Feature",
  "properties": {
    "gn:admin1_code":"3",
    "gn:admin2_code":"RC",
    "gn:admin3_code":"80088.0",
    "gn:asciiname":"Larone",
    "gn:country_code":"IT",
    "gn:dem":157,
    "gn:feature_class":"P",
    "gn:feature_code":"PPL",
    "gn:name":"Larone",
    "gn:population":43,
    "gn:timezone":"Europe/Rome",
    "iso:country":"IT",
    "wof:name":"Larone",
    "wof:placetype":"locality",
    "wof:population":43
},
  "geometry": {"coordinates":[16.26188,38.29349000000001],"type":"Point"}
}