{
  "type": "Feature",
  "properties": {
    "gn:admin1_code":"4",
    "gn:admin2_code":"AV",
    "gn:admin3_code":"64003.0",
    "gn:asciiname":"Pisciolo",
    "gn:country_code":"IT",
    "gn:dem":810,
    "gn:feature_class":"P",
    "gn:feature_code":"PPL",
    "gn:name":"Pisciolo",
    "gn:population":46,
    "gn:timezone":"Europe/Rome",
    "iso:country":"IT",
    "wof:name":"Pisciolo",
    "wof:placetype":"locality",
    "wof:population":46
},
  "geometry": {"coordinates":[15.33439,40.95121],"type":"Point"}
}