{
  "type": "Feature",
  "properties": {
    "gn:admin1_code":"17",
    "gn:admin2_code":"BZ",
    "gn:admin3_code":"21013.0",
    "gn:asciiname":"Villa Santa Caterina",
    "gn:country_code":"IT",
    "gn:dem":854,
    "gn:feature_class":"P",
    "gn:feature_code":"PPL",
    "gn:name":"Villa Santa Caterina",
    "gn:population":284,
    "gn:timezone":"Europe/Rome",
    "iso:country":"IT",
    "wof:name":"Villa Santa Caterina",
    "wof:placetype":"locality",
    "wof:population":284
},
  "geometry": {"coordinates":[11.94633,46.8138],"type":"Point"}
}