{
  "type": "Feature",
  "properties": {
    "gn:admin1_code":"15.0",
    "gn:admin2_code":"ME",
    "gn:admin3_code":"83005.0",
    "gn:asciiname":"La Gala",
    "gn:cc2":"IT",
    "gn:country_code":"IT",
    "gn:dem":220,
    "gn:elevation":"193.0",
    "gn:feature_class":"P",
    "gn:feature_code":"PPL",
    "gn:name":"La Gala",
    "gn:population":844,
    "gn:timezone":"Europe/Rome",
    "iso:country":"IT",
    "name:und_x_variant":[
        "Gala",
        "La Gala"
    ],
    "wof:name":"La Gala",
    "wof:placetype":"locality",
    "wof:population":844
},
  "geometry": {"coordinates":[15.23089,38.11802],"type":"Point"}
}