{
  "type": "Feature",
  "properties": {
    "gn:admin1_code":"7",
    "gn:admin2_code":"FR",
    "gn:admin3_code":"60024.0",
    "gn:asciiname":"Ficone",
    "gn:country_code":"IT",
    "gn:dem":140,
    "gn:feature_class":"P",
    "gn:feature_code":"PPL",
    "gn:name":"Ficone",
    "gn:population":161,
    "gn:timezone":"Europe/Rome",
    "iso:country":"IT",
    "wof:name":"Ficone",
    "wof:placetype":"locality",
    "wof:population":161
},
  "geometry": {"coordinates":[13.30133,41.57888],"type":"Point"}
}