{
  "type": "Feature",
  "properties": {
    "gn:admin1_code":"20",
    "gn:admin2_code":"VI",
    "gn:admin3_code":"24113.0",
    "gn:asciiname":"Corzati",
    "gn:country_code":"IT",
    "gn:dem":568,
    "gn:feature_class":"P",
    "gn:feature_code":"PPL",
    "gn:name":"Corzati",
    "gn:population":13,
    "gn:timezone":"Europe/Rome",
    "iso:country":"IT",
    "wof:name":"Corzati",
    "wof:placetype":"locality",
    "wof:population":13
},
  "geometry": {"coordinates":[11.27023,45.75222],"type":"Point"}
}