{
  "type": "Feature",
  "properties": {
    "gn:admin1_code":"5",
    "gn:admin2_code":"BO",
    "gn:admin3_code":"37032.0",
    "gn:asciiname":"Il Casino",
    "gn:country_code":"IT",
    "gn:dem":53,
    "gn:feature_class":"P",
    "gn:feature_code":"PPL",
    "gn:name":"Il Casino",
    "gn:population":45,
    "gn:timezone":"Europe/Rome",
    "iso:country":"IT",
    "wof:name":"Il Casino",
    "wof:placetype":"locality",
    "wof:population":45
},
  "geometry": {"coordinates":[11.6731,44.3225],"type":"Point"}
}