{
  "type": "Feature",
  "properties": {
    "gn:admin1_code":"12.0",
    "gn:admin2_code":"TO",
    "gn:admin3_code":"1267.0",
    "gn:asciiname":"Torre Antigliera",
    "gn:country_code":"IT",
    "gn:dem":505,
    "gn:feature_class":"P",
    "gn:feature_code":"PPL",
    "gn:name":"Torre Antigliera",
    "gn:population":3,
    "gn:timezone":"Europe/Rome",
    "iso:country":"IT",
    "wof:name":"Torre Antigliera",
    "wof:placetype":"locality",
    "wof:population":3
},
  "geometry": {"coordinates":[7.55926,45.4186],"type":"Point"}
}