{
  "type": "Feature",
  "properties": {
    "gn:admin1_code":"20",
    "gn:admin2_code":"VI",
    "gn:admin3_code":"24067.0",
    "gn:asciiname":"Barausse",
    "gn:country_code":"IT",
    "gn:dem":43,
    "gn:feature_class":"P",
    "gn:feature_code":"PPL",
    "gn:name":"Barausse",
    "gn:population":25,
    "gn:timezone":"Europe/Rome",
    "iso:country":"IT",
    "wof:name":"Barausse",
    "wof:placetype":"locality",
    "wof:population":25
},
  "geometry": {"coordinates":[11.59718,45.61115],"type":"Point"}
}