{
  "type": "Feature",
  "properties": {
    "gn:admin1_code":"15",
    "gn:admin2_code":"ME",
    "gn:admin3_code":"83080.0",
    "gn:asciiname":"Pirrera",
    "gn:country_code":"IT",
    "gn:dem":144,
    "gn:feature_class":"P",
    "gn:feature_code":"PPL",
    "gn:name":"Pirrera",
    "gn:population":23,
    "gn:timezone":"Europe/Rome",
    "iso:country":"IT",
    "wof:name":"Pirrera",
    "wof:placetype":"locality",
    "wof:population":23
},
  "geometry": {"coordinates":[15.33838,38.17718],"type":"Point"}
}