{
  "type": "Feature",
  "properties": {
    "gn:admin1_code":"3.0",
    "gn:admin2_code":"RC",
    "gn:admin3_code":"80052.0",
    "gn:asciiname":"Casa Petrusa",
    "gn:country_code":"IT",
    "gn:dem":115,
    "gn:feature_class":"P",
    "gn:feature_code":"PPL",
    "gn:name":"Casa Petrusa",
    "gn:population":0,
    "gn:timezone":"Europe/Rome",
    "iso:country":"IT",
    "wof:name":"Casa Petrusa",
    "wof:placetype":"locality"
},
  "geometry": {"coordinates":[16.55,38.45],"type":"Point"}
}