{
  "type": "Feature",
  "properties": {
    "gn:admin1_code":"10",
    "gn:admin2_code":"AN",
    "gn:admin3_code":"42029.0",
    "gn:asciiname":"Ponte Pio",
    "gn:country_code":"IT",
    "gn:dem":70,
    "gn:feature_class":"P",
    "gn:feature_code":"PPL",
    "gn:name":"Ponte Pio",
    "gn:population":98,
    "gn:timezone":"Europe/Rome",
    "iso:country":"IT",
    "wof:name":"Ponte Pio",
    "wof:placetype":"locality",
    "wof:population":98
},
  "geometry": {"coordinates":[13.21372,43.49837],"type":"Point"}
}