{
  "type": "Feature",
  "properties": {
    "gn:admin1_code":"6",
    "gn:admin2_code":"PN",
    "gn:admin3_code":"93017.0",
    "gn:asciiname":"Lotti",
    "gn:country_code":"IT",
    "gn:dem":27,
    "gn:feature_class":"P",
    "gn:feature_code":"PPL",
    "gn:name":"Lotti",
    "gn:population":44,
    "gn:timezone":"Europe/Rome",
    "iso:country":"IT",
    "wof:name":"Lotti",
    "wof:placetype":"locality",
    "wof:population":44
},
  "geometry": {"coordinates":[12.70354,45.97193],"type":"Point"}
}