{
  "type": "Feature",
  "properties": {
    "gn:admin1_code":"1",
    "gn:admin2_code":"TE",
    "gn:admin3_code":"67026.0",
    "gn:asciiname":"Collalto-Frisoni",
    "gn:country_code":"IT",
    "gn:dem":424,
    "gn:feature_class":"P",
    "gn:feature_code":"PPL",
    "gn:name":"Collalto-Frisoni",
    "gn:population":105,
    "gn:timezone":"Europe/Rome",
    "iso:country":"IT",
    "wof:name":"Collalto-Frisoni",
    "wof:placetype":"locality",
    "wof:population":105
},
  "geometry": {"coordinates":[13.67002,42.52693],"type":"Point"}
}