{
  "type": "Feature",
  "properties": {
    "gn:admin1_code":"7.0",
    "gn:admin2_code":"VT",
    "gn:admin3_code":"56039.0",
    "gn:asciiname":"Colle Farnese",
    "gn:country_code":"IT",
    "gn:dem":225,
    "gn:elevation":"238.0",
    "gn:feature_class":"P",
    "gn:feature_code":"PPL",
    "gn:name":"Colle Farnese",
    "gn:population":603,
    "gn:timezone":"Europe/Rome",
    "iso:country":"IT",
    "wof:name":"Colle Farnese",
    "wof:placetype":"locality",
    "wof:population":603
},
  "geometry": {"coordinates":[12.31207,42.22394],"type":"Point"}
}