{
  "type": "Feature",
  "properties": {
    "gn:admin1_code":"10.0",
    "gn:admin2_code":"AP",
    "gn:admin3_code":"44054.0",
    "gn:asciiname":"Stalla Sociale",
    "gn:country_code":"IT",
    "gn:dem":196,
    "gn:feature_class":"P",
    "gn:feature_code":"PPLL",
    "gn:name":"Stalla Sociale",
    "gn:population":0,
    "gn:timezone":"Europe/Rome",
    "iso:country":"IT",
    "wof:name":"Stalla Sociale",
    "wof:placetype":"locality"
},
  "geometry": {"coordinates":[13.71017,42.95771],"type":"Point"}
}