{
  "type": "Feature",
  "properties": {
    "gn:admin1_code":"12",
    "gn:admin2_code":"AL",
    "gn:admin3_code":"6039.0",
    "gn:asciiname":"Rolasco",
    "gn:country_code":"IT",
    "gn:dem":251,
    "gn:feature_class":"P",
    "gn:feature_code":"PPL",
    "gn:name":"Rolasco",
    "gn:population":53,
    "gn:timezone":"Europe/Rome",
    "iso:country":"IT",
    "wof:name":"Rolasco",
    "wof:placetype":"locality",
    "wof:population":53
},
  "geometry": {"coordinates":[8.39128,45.12625],"type":"Point"}
}