{
  "type": "Feature",
  "properties": {
    "gn:admin1_code":"16",
    "gn:admin2_code":"MS",
    "gn:admin3_code":"45008.0",
    "gn:asciiname":"Vercalda",
    "gn:country_code":"IT",
    "gn:dem":381,
    "gn:feature_class":"P",
    "gn:feature_code":"PPL",
    "gn:name":"Vercalda",
    "gn:population":27,
    "gn:timezone":"Europe/Rome",
    "iso:country":"IT",
    "wof:name":"Vercalda",
    "wof:placetype":"locality",
    "wof:population":27
},
  "geometry": {"coordinates":[10.00983,44.12809],"type":"Point"}
}