{
  "type": "Feature",
  "properties": {
    "gn:admin1_code":"4",
    "gn:admin3_code":"63052.0",
    "gn:asciiname":"Pozzoceravolo",
    "gn:country_code":"IT",
    "gn:dem":51,
    "gn:feature_class":"P",
    "gn:feature_code":"PPL",
    "gn:name":"Pozzoceravolo",
    "gn:population":165,
    "gn:timezone":"Europe/Rome",
    "iso:country":"IT",
    "wof:name":"Pozzoceravolo",
    "wof:placetype":"locality",
    "wof:population":165
},
  "geometry": {"coordinates":[14.5298,40.87801],"type":"Point"}
}