{
  "type": "Feature",
  "properties": {
    "gn:admin1_code":"6.0",
    "gn:admin2_code":"UD",
    "gn:admin3_code":"30094.0",
    "gn:asciiname":"Vuezzis",
    "gn:country_code":"IT",
    "gn:dem":888,
    "gn:elevation":"878.0",
    "gn:feature_class":"P",
    "gn:feature_code":"PPL",
    "gn:name":"Vuezzis",
    "gn:population":17,
    "gn:timezone":"Europe/Rome",
    "iso:country":"IT",
    "wof:name":"Vuezzis",
    "wof:placetype":"locality",
    "wof:population":17
},
  "geometry": {"coordinates":[12.86229,46.55417],"type":"Point"}
}