{
  "type": "Feature",
  "properties": {
    "gn:admin1_code":"16.0",
    "gn:admin2_code":"PT",
    "gn:admin3_code":"47023.0",
    "gn:asciiname":"Conio",
    "gn:country_code":"IT",
    "gn:dem":1062,
    "gn:feature_class":"P",
    "gn:feature_code":"PPLL",
    "gn:name":"Conio",
    "gn:population":0,
    "gn:timezone":"Europe/Rome",
    "iso:country":"IT",
    "name:und_x_variant":[
        "Koni"
    ],
    "wof:name":"Conio",
    "wof:placetype":"locality"
},
  "geometry": {"coordinates":[10.74592,44.12817],"type":"Point"}
}