{
  "type": "Feature",
  "properties": {
    "gn:admin1_code":"20",
    "gn:admin2_code":"PD",
    "gn:admin3_code":"28082.0",
    "gn:asciiname":"Magro",
    "gn:country_code":"IT",
    "gn:dem":5,
    "gn:feature_class":"P",
    "gn:feature_code":"PPL",
    "gn:name":"Magro",
    "gn:population":84,
    "gn:timezone":"Europe/Rome",
    "iso:country":"IT",
    "wof:name":"Magro",
    "wof:placetype":"locality",
    "wof:population":84
},
  "geometry": {"coordinates":[12.01242,45.34779],"type":"Point"}
}