{
  "type": "Feature",
  "properties": {
    "gn:admin1_code":"15.0",
    "gn:admin2_code":"ME",
    "gn:admin3_code":"83016.0",
    "gn:asciiname":"Bafia",
    "gn:country_code":"IT",
    "gn:dem":500,
    "gn:elevation":"488.0",
    "gn:feature_class":"P",
    "gn:feature_code":"PPL",
    "gn:name":"Bafia",
    "gn:population":643,
    "gn:timezone":"Europe/Rome",
    "iso:country":"IT",
    "wof:name":"Bafia",
    "wof:placetype":"locality",
    "wof:population":643
},
  "geometry": {"coordinates":[15.20529,38.07447],"type":"Point"}
}