{
  "type": "Feature",
  "properties": {
    "gn:admin1_code":"15.0",
    "gn:admin2_code":"ME",
    "gn:admin3_code":"83016.0",
    "gn:asciiname":"Bafia",
    "gn:country_code":"IT",
    "gn:dem":500,
    "gn:elevation":"488.0",
    "gn:feature_class":"P",
    "gn:feature_code":"PPL",
    "gn:name":"Bafia",
    "gn:population":643,
    "gn:timezone":"Europe/Rome",
    "iso:country":"IT",
    "name:bul_x_preferred":[
        "\u0411\u0430\u0444\u0438\u0430"
    ],
    "name:ceb_x_preferred":[
        "Bafia"
    ],
    "name:deu_x_preferred":[
        "Bafia"
    ],
    "name:fra_x_preferred":[
        "Bafia"
    ],
    "name:heb_x_preferred":[
        "\u05d1\u05d0\u05e4\u05d9\u05d4"
    ],
    "name:ita_x_preferred":[
        "Bafia"
    ],
    "name:msa_x_preferred":[
        "Bafia"
    ],
    "name:pol_x_preferred":[
        "Bafia"
    ],
    "name:por_x_preferred":[
        "Bafia"
    ],
    "name:ron_x_preferred":[
        "Bafia"
    ],
    "name:rus_x_preferred":[
        "\u0411\u0430\u0444\u0438\u0430"
    ],
    "name:slv_x_preferred":[
        "Bafia"
    ],
    "name:spa_x_preferred":[
        "Bafia"
    ],
    "name:zho_x_preferred":[
        "\u5df4\u83f2\u4e9e"
    ],
    "wof:name":"Bafia",
    "wof:placetype":"locality",
    "wof:population":643
},
  "geometry": {"coordinates":[15.20529,38.07447],"type":"Point"}
}