{
  "type": "Feature",
  "properties": {
    "gn:admin1_code":"16",
    "gn:admin2_code":"PT",
    "gn:admin3_code":"47017.0",
    "gn:asciiname":"Case Ferretti",
    "gn:country_code":"IT",
    "gn:dem":79,
    "gn:feature_class":"P",
    "gn:feature_code":"PPL",
    "gn:name":"Case Ferretti",
    "gn:population":44,
    "gn:timezone":"Europe/Rome",
    "iso:country":"IT",
    "wof:name":"Case Ferretti",
    "wof:placetype":"locality",
    "wof:population":44
},
  "geometry": {"coordinates":[10.95753,43.85059],"type":"Point"}
}