{
  "type": "Feature",
  "properties": {
    "gn:admin1_code":"12",
    "gn:admin2_code":"TO",
    "gn:admin3_code":"1097.0",
    "gn:asciiname":"Ardissoni",
    "gn:country_code":"IT",
    "gn:dem":346,
    "gn:feature_class":"P",
    "gn:feature_code":"PPL",
    "gn:name":"Ardissoni",
    "gn:population":14,
    "gn:timezone":"Europe/Rome",
    "iso:country":"IT",
    "wof:name":"Ardissoni",
    "wof:placetype":"locality",
    "wof:population":14
},
  "geometry": {"coordinates":[7.39177,44.99069],"type":"Point"}
}