{
  "type": "Feature",
  "properties": {
    "gn:admin1_code":"2.0",
    "gn:admin2_code":"PZ",
    "gn:admin3_code":"76063.0",
    "gn:asciiname":"Masseria Colucci",
    "gn:country_code":"IT",
    "gn:dem":824,
    "gn:feature_class":"P",
    "gn:feature_code":"PPL",
    "gn:name":"Masseria Colucci",
    "gn:population":29,
    "gn:timezone":"Europe/Rome",
    "iso:country":"IT",
    "wof:name":"Masseria Colucci",
    "wof:placetype":"locality",
    "wof:population":29
},
  "geometry": {"coordinates":[15.84041,40.6796],"type":"Point"}
}