{
  "type": "Feature",
  "properties": {
    "gn:admin1_code":"17",
    "gn:admin2_code":"TN",
    "gn:admin3_code":"22247.0",
    "gn:asciiname":"Cort",
    "gn:country_code":"IT",
    "gn:dem":837,
    "gn:feature_class":"P",
    "gn:feature_code":"PPL",
    "gn:name":"Cort",
    "gn:population":65,
    "gn:timezone":"Europe/Rome",
    "iso:country":"IT",
    "name:arg_x_preferred":[
        "Cort"
    ],
    "name:cat_x_preferred":[
        "Cort"
    ],
    "name:deu_x_preferred":[
        "Cort"
    ],
    "name:fra_x_preferred":[
        "Cort"
    ],
    "name:spa_x_preferred":[
        "Cort"
    ],
    "name:srp_x_preferred":[
        "Cort"
    ],
    "wof:name":"Cort",
    "wof:placetype":"locality",
    "wof:population":65
},
  "geometry": {"coordinates":[10.75318,46.052],"type":"Point"}
}