{
  "type": "Feature",
  "properties": {
    "gn:gn_country":"IT",
    "iso:country":"IT",
    "name:cat_x_preferred":[
        "Colle di Palombaia"
    ],
    "name:ces_x_preferred":[
        "Colle di Palombaia"
    ],
    "name:dan_x_preferred":[
        "Colle di Palombaia"
    ],
    "name:eng_x_preferred":[
        "Colle di Palombaia"
    ],
    "name:eus_x_preferred":[
        "Colle di Palombaia"
    ],
    "name:fin_x_preferred":[
        "Colle di Palombaia"
    ],
    "name:fra_x_preferred":[
        "Colle di Palombaia"
    ],
    "name:ind_x_preferred":[
        "Colle di Palombaia"
    ],
    "name:ita_x_preferred":[
        "Colle di Palombaia"
    ],
    "name:nld_x_preferred":[
        "Colle di Palombaia"
    ],
    "name:nno_x_preferred":[
        "Colle di Palombaia"
    ],
    "name:nob_x_preferred":[
        "Colle di Palombaia"
    ],
    "name:oci_x_preferred":[
        "Colle di Palombaia"
    ],
    "name:pol_x_preferred":[
        "Colle di Palombaia"
    ],
    "name:por_x_preferred":[
        "Colle di Palombaia"
    ],
    "name:ron_x_preferred":[
        "Colle di Palombaia"
    ],
    "name:slk_x_preferred":[
        "Colle di Palombaia"
    ],
    "name:slv_x_preferred":[
        "Colle di Palombaia"
    ],
    "name:spa_x_preferred":[
        "Colle di Palombaia"
    ],
    "name:srp_x_preferred":[
        "Colle di Palombaia"
    ],
    "name:swe_x_preferred":[
        "Colle di Palombaia"
    ],
    "name:tgl_x_preferred":[
        "Colle di Palombaia"
    ],
    "name:tur_x_preferred":[
        "Colle di Palombaia"
    ],
    "name:war_x_preferred":[
        "Colle di Palombaia"
    ],
    "qs_pg:aaroncc":"IT",
    "qs_pg:gn_country":"IT",
    "qs_pg:name":"Colle di Palombaia",
    "qs_pg:name_adm0":"Italia",
    "qs_pg:name_adm1":"Toscana",
    "qs_pg:photos":61,
    "qs_pg:photos_1k":12,
    "qs_pg:photos_9k":1,
    "qs_pg:photos_9r":2,
    "qs_pg:photos_all":61,
    "qs_pg:photos_sr":2,
    "qs_pg:pop_sr":0,
    "qs_pg:qs_pg_placetype":"locality",
    "qs_pg:qs_pg_placetype_gp":"Town",
    "qs_pg:woe_adm0":23424853,
    "woe:adm0_id":23424853,
    "woe:name_adm0":"Italia",
    "woe:name_adm1":"Toscana",
    "woe:placetype":"Town",
    "wof:name":"Colle di Palombaia",
    "wof:placetype":"locality"
},
  "geometry": {"coordinates":[10.202779,42.735886],"type":"Point"}
}