{
  "type": "Feature",
  "properties": {
    "gn:admin1_code":"16",
    "gn:admin2_code":"SI",
    "gn:admin3_code":"52013.0",
    "gn:asciiname":"Galenda",
    "gn:country_code":"IT",
    "gn:dem":476,
    "gn:feature_class":"P",
    "gn:feature_code":"PPL",
    "gn:name":"Galenda",
    "gn:population":12,
    "gn:timezone":"Europe/Rome",
    "iso:country":"IT",
    "wof:name":"Galenda",
    "wof:placetype":"locality",
    "wof:population":12
},
  "geometry": {"coordinates":[11.37749,43.45461],"type":"Point"}
}