{
  "type": "Feature",
  "properties": {
    "gn:admin1_code":"9",
    "gn:admin2_code":"CO",
    "gn:admin3_code":"13097.0",
    "gn:asciiname":"Cascina Gera",
    "gn:country_code":"IT",
    "gn:dem":265,
    "gn:feature_class":"P",
    "gn:feature_code":"PPL",
    "gn:name":"Cascina Gera",
    "gn:population":11,
    "gn:timezone":"Europe/Rome",
    "iso:country":"IT",
    "wof:name":"Cascina Gera",
    "wof:placetype":"locality",
    "wof:population":11
},
  "geometry": {"coordinates":[9.25009,45.80305],"type":"Point"}
}