{
  "type": "Feature",
  "properties": {
    "gn:admin1_code":"5.0",
    "gn:admin2_code":"RE",
    "gn:admin3_code":"35015.0",
    "gn:asciiname":"Meletole",
    "gn:country_code":"IT",
    "gn:dem":20,
    "gn:feature_class":"P",
    "gn:feature_code":"PPL",
    "gn:name":"Meletole",
    "gn:population":591,
    "gn:timezone":"Europe/Rome",
    "iso:country":"IT",
    "wof:name":"Meletole",
    "wof:placetype":"locality",
    "wof:population":591
},
  "geometry": {"coordinates":[10.58217,44.84881],"type":"Point"}
}