{
  "type": "Feature",
  "properties": {
    "gn:admin1_code":"9",
    "gn:admin2_code":"PV",
    "gn:admin3_code":"18155.0",
    "gn:asciiname":"Cadelazzi",
    "gn:country_code":"IT",
    "gn:dem":227,
    "gn:feature_class":"P",
    "gn:feature_code":"PPL",
    "gn:name":"Cadelazzi",
    "gn:population":27,
    "gn:timezone":"Europe/Rome",
    "iso:country":"IT",
    "wof:name":"Cadelazzi",
    "wof:placetype":"locality",
    "wof:population":27
},
  "geometry": {"coordinates":[9.09034,44.96584],"type":"Point"}
}