{
  "type": "Feature",
  "properties": {
    "gn:admin1_code":"13.0",
    "gn:admin2_code":"BA",
    "gn:admin3_code":"72025.0",
    "gn:asciiname":"Le Lamie di Olimpe",
    "gn:cc2":"IT",
    "gn:country_code":"IT",
    "gn:dem":371,
    "gn:feature_class":"P",
    "gn:feature_code":"PPL",
    "gn:name":"Le Lamie di Olimpe",
    "gn:population":0,
    "gn:timezone":"Europe/Rome",
    "iso:country":"IT",
    "name:und_x_variant":[
        "Le Lame di Olimpe",
        "Le Lamie di Olimpe"
    ],
    "wof:name":"Le Lamie di Olimpe",
    "wof:placetype":"locality"
},
  "geometry": {"coordinates":[17.36372,40.78577],"type":"Point"}
}