{
  "type": "Feature",
  "properties": {
    "gn:admin1_code":"11",
    "gn:admin2_code":"CB",
    "gn:admin3_code":"70076.0",
    "gn:asciiname":"Iacovantuono",
    "gn:country_code":"IT",
    "gn:dem":700,
    "gn:feature_class":"P",
    "gn:feature_code":"PPL",
    "gn:name":"Iacovantuono",
    "gn:population":49,
    "gn:timezone":"Europe/Rome",
    "iso:country":"IT",
    "wof:name":"Iacovantuono",
    "wof:placetype":"locality",
    "wof:population":49
},
  "geometry": {"coordinates":[14.49569,41.53573],"type":"Point"}
}