{
  "type": "Feature",
  "properties": {
    "gn:admin1_code":"7",
    "gn:admin2_code":"FR",
    "gn:admin3_code":"60033.0",
    "gn:asciiname":"Pinelli",
    "gn:country_code":"IT",
    "gn:dem":215,
    "gn:feature_class":"P",
    "gn:feature_code":"PPL",
    "gn:name":"Pinelli",
    "gn:population":111,
    "gn:timezone":"Europe/Rome",
    "iso:country":"IT",
    "wof:name":"Pinelli",
    "wof:placetype":"locality",
    "wof:population":111
},
  "geometry": {"coordinates":[13.26272,41.6724],"type":"Point"}
}