{
  "type": "Feature",
  "properties": {
    "gn:admin1_code":"20",
    "gn:admin2_code":"VI",
    "gn:admin3_code":"24093.0",
    "gn:asciiname":"Lanari",
    "gn:country_code":"IT",
    "gn:dem":155,
    "gn:feature_class":"P",
    "gn:feature_code":"PPL",
    "gn:name":"Lanari",
    "gn:population":44,
    "gn:timezone":"Europe/Rome",
    "iso:country":"IT",
    "wof:name":"Lanari",
    "wof:placetype":"locality",
    "wof:population":44
},
  "geometry": {"coordinates":[11.69829,45.83442],"type":"Point"}
}