{
  "type": "Feature",
  "properties": {
    "gn:admin1_code":"8.0",
    "gn:admin2_code":"SV",
    "gn:admin3_code":"9047.0",
    "gn:asciiname":"Biestro",
    "gn:country_code":"IT",
    "gn:dem":650,
    "gn:elevation":"626.0",
    "gn:feature_class":"P",
    "gn:feature_code":"PPL",
    "gn:name":"Biestro",
    "gn:population":68,
    "gn:timezone":"Europe/Rome",
    "iso:country":"IT",
    "wof:name":"Biestro",
    "wof:placetype":"locality",
    "wof:population":68
},
  "geometry": {"coordinates":[8.24362,44.33198],"type":"Point"}
}