{
  "type": "Feature",
  "properties": {
    "gn:admin1_code":"16",
    "gn:admin2_code":"PI",
    "gn:admin3_code":"50029.0",
    "gn:asciiname":"Le Cantine",
    "gn:country_code":"IT",
    "gn:dem":15,
    "gn:feature_class":"P",
    "gn:feature_code":"PPL",
    "gn:name":"Le Cantine",
    "gn:population":63,
    "gn:timezone":"Europe/Rome",
    "iso:country":"IT",
    "wof:name":"Le Cantine",
    "wof:placetype":"locality",
    "wof:population":63
},
  "geometry": {"coordinates":[10.64644,43.6568],"type":"Point"}
}