{
  "type": "Feature",
  "properties": {
    "gn:admin1_code":"15",
    "gn:admin2_code":"ME",
    "gn:admin3_code":"83004.0",
    "gn:asciiname":"Morzulli",
    "gn:country_code":"IT",
    "gn:dem":449,
    "gn:feature_class":"P",
    "gn:feature_code":"PPL",
    "gn:name":"Morzulli",
    "gn:population":32,
    "gn:timezone":"Europe/Rome",
    "iso:country":"IT",
    "wof:name":"Morzulli",
    "wof:placetype":"locality",
    "wof:population":32
},
  "geometry": {"coordinates":[15.25498,37.96989],"type":"Point"}
}