{
  "type": "Feature",
  "properties": {
    "gn:admin1_code":"16",
    "gn:admin2_code":"MS",
    "gn:admin3_code":"45017.0",
    "gn:asciiname":"Piagna",
    "gn:country_code":"IT",
    "gn:dem":773,
    "gn:feature_class":"P",
    "gn:feature_code":"PPL",
    "gn:name":"Piagna",
    "gn:population":55,
    "gn:timezone":"Europe/Rome",
    "iso:country":"IT",
    "wof:name":"Piagna",
    "wof:placetype":"locality",
    "wof:population":55
},
  "geometry": {"coordinates":[9.79418,44.33039],"type":"Point"}
}