{
  "type": "Feature",
  "properties": {
    "gn:admin1_code":"13",
    "gn:admin2_code":"LE",
    "gn:admin3_code":"75035.0",
    "gn:asciiname":"Mezzagrande",
    "gn:country_code":"IT",
    "gn:dem":34,
    "gn:feature_class":"P",
    "gn:feature_code":"PPL",
    "gn:name":"Mezzagrande",
    "gn:population":224,
    "gn:timezone":"Europe/Rome",
    "iso:country":"IT",
    "wof:name":"Mezzagrande",
    "wof:placetype":"locality",
    "wof:population":224
},
  "geometry": {"coordinates":[18.23701,40.37213],"type":"Point"}
}