{
  "type": "Feature",
  "properties": {
    "gn:admin1_code":"12",
    "gn:admin2_code":"VB",
    "gn:admin3_code":"103015.0",
    "gn:asciiname":"Ramello",
    "gn:country_code":"IT",
    "gn:dem":320,
    "gn:feature_class":"P",
    "gn:feature_code":"PPL",
    "gn:name":"Ramello",
    "gn:population":234,
    "gn:timezone":"Europe/Rome",
    "iso:country":"IT",
    "wof:name":"Ramello",
    "wof:placetype":"locality",
    "wof:population":234
},
  "geometry": {"coordinates":[8.55648,45.97064],"type":"Point"}
}