{
  "type": "Feature",
  "properties": {
    "gn:admin1_code":"14.0",
    "gn:admin2_code":"SS",
    "gn:admin3_code":"90008.0",
    "gn:asciiname":"Terme Aurora",
    "gn:country_code":"IT",
    "gn:dem":261,
    "gn:feature_class":"P",
    "gn:feature_code":"PPLL",
    "gn:name":"Terme Aurora",
    "gn:population":0,
    "gn:timezone":"Europe/Rome",
    "iso:country":"IT",
    "wof:name":"Terme Aurora",
    "wof:placetype":"locality"
},
  "geometry": {"coordinates":[9.12975,40.42696],"type":"Point"}
}