{
  "type": "Feature",
  "properties": {
    "gn:admin1_code":"19",
    "gn:admin2_code":"AO",
    "gn:admin3_code":"7029.0",
    "gn:asciiname":"Pont Trenta",
    "gn:country_code":"IT",
    "gn:dem":1175,
    "gn:feature_class":"P",
    "gn:feature_code":"PPL",
    "gn:name":"Pont Trenta",
    "gn:population":16,
    "gn:timezone":"Europe/Rome",
    "iso:country":"IT",
    "wof:name":"Pont Trenta",
    "wof:placetype":"locality",
    "wof:population":16
},
  "geometry": {"coordinates":[7.86243,45.72801],"type":"Point"}
}