{
  "type": "Feature",
  "properties": {
    "gn:admin1_code":"12",
    "gn:admin2_code":"TO",
    "gn:admin3_code":"1012.0",
    "gn:asciiname":"Moano",
    "gn:country_code":"IT",
    "gn:dem":300,
    "gn:feature_class":"P",
    "gn:feature_code":"PPL",
    "gn:name":"Moano",
    "gn:population":52,
    "gn:timezone":"Europe/Rome",
    "iso:country":"IT",
    "wof:name":"Moano",
    "wof:placetype":"locality",
    "wof:population":52
},
  "geometry": {"coordinates":[7.88593,45.02779],"type":"Point"}
}