{
  "type": "Feature",
  "properties": {
    "gn:admin1_code":"11",
    "gn:admin2_code":"IS",
    "gn:admin3_code":"94048.0",
    "gn:asciiname":"Cannine",
    "gn:country_code":"IT",
    "gn:dem":515,
    "gn:feature_class":"P",
    "gn:feature_code":"PPL",
    "gn:name":"Cannine",
    "gn:population":51,
    "gn:timezone":"Europe/Rome",
    "iso:country":"IT",
    "wof:name":"Cannine",
    "wof:placetype":"locality",
    "wof:population":51
},
  "geometry": {"coordinates":[14.04938,41.60017],"type":"Point"}
}