{
  "type": "Feature",
  "properties": {
    "gn:admin1_code":"17.0",
    "gn:admin2_code":"TN",
    "gn:admin3_code":"22209.0",
    "gn:asciiname":"Barcatta",
    "gn:country_code":"IT",
    "gn:dem":930,
    "gn:feature_class":"P",
    "gn:feature_code":"PPL",
    "gn:name":"Barcatta",
    "gn:population":41,
    "gn:timezone":"Europe/Rome",
    "iso:country":"IT",
    "wof:name":"Barcatta",
    "wof:placetype":"locality",
    "wof:population":41
},
  "geometry": {"coordinates":[11.35062,46.25122],"type":"Point"}
}