{
  "type": "Feature",
  "properties": {
    "gn:admin1_code":"5",
    "gn:admin2_code":"RE",
    "gn:admin3_code":"35016.0",
    "gn:asciiname":"Vezzolo",
    "gn:country_code":"IT",
    "gn:dem":571,
    "gn:feature_class":"P",
    "gn:feature_code":"PPL",
    "gn:name":"Vezzolo",
    "gn:population":16,
    "gn:timezone":"Europe/Rome",
    "iso:country":"IT",
    "wof:name":"Vezzolo",
    "wof:placetype":"locality",
    "wof:population":16
},
  "geometry": {"coordinates":[10.39209,44.45354],"type":"Point"}
}