{
  "type": "Feature",
  "properties": {
    "gn:admin1_code":"5",
    "gn:admin2_code":"PR",
    "gn:admin3_code":"34038.0",
    "gn:asciiname":"Villa",
    "gn:country_code":"IT",
    "gn:dem":424,
    "gn:feature_class":"P",
    "gn:feature_code":"PPL",
    "gn:name":"Villa",
    "gn:population":35,
    "gn:timezone":"Europe/Rome",
    "iso:country":"IT",
    "wof:name":"Villa",
    "wof:placetype":"locality",
    "wof:population":35
},
  "geometry": {"coordinates":[9.99904,44.60358],"type":"Point"}
}