{
  "type": "Feature",
  "properties": {
    "gn:admin1_code":"14.0",
    "gn:admin2_code":"SS",
    "gn:admin3_code":"90092.0",
    "gn:asciiname":"Lu Lioni",
    "gn:country_code":"IT",
    "gn:dem":67,
    "gn:feature_class":"P",
    "gn:feature_code":"PPL",
    "gn:name":"Lu Lioni",
    "gn:population":0,
    "gn:timezone":"Europe/Rome",
    "iso:country":"IT",
    "wof:name":"Lu Lioni",
    "wof:placetype":"locality"
},
  "geometry": {"coordinates":[9.63333,40.78333],"type":"Point"}
}