{
  "type": "Feature",
  "properties": {
    "gn:admin1_code":"12",
    "gn:admin2_code":"AL",
    "gn:admin3_code":"6147.0",
    "gn:asciiname":"Carrara",
    "gn:country_code":"IT",
    "gn:dem":226,
    "gn:feature_class":"P",
    "gn:feature_code":"PPL",
    "gn:name":"Carrara",
    "gn:population":13,
    "gn:timezone":"Europe/Rome",
    "iso:country":"IT",
    "wof:name":"Carrara",
    "wof:placetype":"locality",
    "wof:population":13
},
  "geometry": {"coordinates":[8.6369,44.68659],"type":"Point"}
}