{
  "type": "Feature",
  "properties": {
    "gn:admin1_code":"20",
    "gn:admin2_code":"VI",
    "gn:admin3_code":"24080.0",
    "gn:asciiname":"Rader",
    "gn:country_code":"IT",
    "gn:dem":666,
    "gn:feature_class":"P",
    "gn:feature_code":"PPL",
    "gn:name":"Rader",
    "gn:population":18,
    "gn:timezone":"Europe/Rome",
    "iso:country":"IT",
    "wof:name":"Rader",
    "wof:placetype":"locality",
    "wof:population":18
},
  "geometry": {"coordinates":[11.23926,45.79599],"type":"Point"}
}