{
  "type": "Feature",
  "properties": {
    "gn:admin1_code":"7.0",
    "gn:admin2_code":"RM",
    "gn:admin3_code":"58005.0",
    "gn:asciiname":"Ponton dell'Elce",
    "gn:country_code":"IT",
    "gn:dem":166,
    "gn:feature_class":"P",
    "gn:feature_code":"PPL",
    "gn:name":"Ponton dell'Elce",
    "gn:population":1736,
    "gn:timezone":"Europe/Rome",
    "iso:country":"IT",
    "wof:name":"Ponton dell'Elce",
    "wof:placetype":"locality",
    "wof:population":1736
},
  "geometry": {"coordinates":[12.23505,42.0227],"type":"Point"}
}