{
  "type": "Feature",
  "properties": {
    "gn:admin1_code":"5.0",
    "gn:admin2_code":"BO",
    "gn:admin3_code":"37015.0",
    "gn:asciiname":"Poggio di Badi",
    "gn:country_code":"IT",
    "gn:dem":634,
    "gn:feature_class":"P",
    "gn:feature_code":"PPL",
    "gn:name":"Poggio di Badi",
    "gn:population":14,
    "gn:timezone":"Europe/Rome",
    "iso:country":"IT",
    "wof:name":"Poggio di Badi",
    "wof:placetype":"locality",
    "wof:population":14
},
  "geometry": {"coordinates":[11.00888,44.11261],"type":"Point"}
}