{
  "type": "Feature",
  "properties": {
    "gn:admin1_code":"20.0",
    "gn:admin2_code":"VE",
    "gn:admin3_code":"27008.0",
    "gn:asciiname":"Cavanella d'Adige",
    "gn:country_code":"IT",
    "gn:dem":1,
    "gn:feature_class":"P",
    "gn:feature_code":"PPL",
    "gn:name":"Cavanella d'Adige",
    "gn:population":327,
    "gn:timezone":"Europe/Rome",
    "iso:country":"IT",
    "name:und_x_variant":[
        "Cavanella",
        "Cavanella d'Adige"
    ],
    "wof:name":"Cavanella d'Adige",
    "wof:placetype":"locality",
    "wof:population":327
},
  "geometry": {"coordinates":[12.24452,45.10991],"type":"Point"}
}