{
  "type": "Feature",
  "properties": {
    "gn:admin1_code":"1.0",
    "gn:admin2_code":"CH",
    "gn:admin3_code":"69059.0",
    "gn:asciiname":"Sevel",
    "gn:country_code":"IT",
    "gn:dem":53,
    "gn:feature_class":"P",
    "gn:feature_code":"PPLL",
    "gn:name":"Sevel",
    "gn:population":0,
    "gn:timezone":"Europe/Rome",
    "iso:country":"IT",
    "wof:name":"Sevel",
    "wof:placetype":"locality"
},
  "geometry": {"coordinates":[14.46087,42.15122],"type":"Point"}
}