{
  "type": "Feature",
  "properties": {
    "gn:admin1_code":"1.0",
    "gn:admin2_code":"CH",
    "gn:admin3_code":"69059.0",
    "gn:asciiname":"Sevel",
    "gn:country_code":"IT",
    "gn:dem":53,
    "gn:feature_class":"P",
    "gn:feature_code":"PPLL",
    "gn:name":"Sevel",
    "gn:population":0,
    "gn:timezone":"Europe/Rome",
    "iso:country":"IT",
    "name:deu_x_preferred":[
        "Sevel Uruguay"
    ],
    "name:fas_x_preferred":[
        "\u0633\u06cc\u0648\u06cc\u0644"
    ],
    "name:fin_x_preferred":[
        "Sevel"
    ],
    "name:fra_x_preferred":[
        "Sevel"
    ],
    "name:ita_x_preferred":[
        "Sevel"
    ],
    "name:pol_x_preferred":[
        "Sevel"
    ],
    "name:por_x_preferred":[
        "Sevel Van"
    ],
    "name:rus_x_preferred":[
        "Sevel"
    ],
    "name:slk_x_preferred":[
        "Sevel"
    ],
    "wof:name":"Sevel",
    "wof:placetype":"locality"
},
  "geometry": {"coordinates":[14.46087,42.15122],"type":"Point"}
}