{
  "type": "Feature",
  "properties": {
    "gn:admin1_code":"6.0",
    "gn:admin2_code":"PN",
    "gn:admin3_code":"93002.0",
    "gn:asciiname":"Colle",
    "gn:country_code":"IT",
    "gn:dem":227,
    "gn:elevation":"225.0",
    "gn:feature_class":"P",
    "gn:feature_code":"PPL",
    "gn:name":"Colle",
    "gn:population":223,
    "gn:timezone":"Europe/Rome",
    "iso:country":"IT",
    "name:ceb_x_preferred":[
        "Colle"
    ],
    "name:deu_x_preferred":[
        "Colle"
    ],
    "name:fra_x_preferred":[
        "Colle"
    ],
    "name:ita_x_preferred":[
        "Colle"
    ],
    "name:nld_x_preferred":[
        "Colle"
    ],
    "name:por_x_preferred":[
        "Colle"
    ],
    "name:swe_x_preferred":[
        "Colle"
    ],
    "wof:name":"Colle",
    "wof:placetype":"locality",
    "wof:population":223
},
  "geometry": {"coordinates":[12.80859,46.16307000000001],"type":"Point"}
}