{
  "type": "Feature",
  "properties": {
    "gn:admin1_code":"9",
    "gn:admin2_code":"BS",
    "gn:admin3_code":"17034.0",
    "gn:asciiname":"Via Brescia",
    "gn:country_code":"IT",
    "gn:dem":71,
    "gn:feature_class":"P",
    "gn:feature_code":"PPL",
    "gn:name":"Via Brescia",
    "gn:population":31,
    "gn:timezone":"Europe/Rome",
    "iso:country":"IT",
    "wof:name":"Via Brescia",
    "wof:placetype":"locality",
    "wof:population":31
},
  "geometry": {"coordinates":[10.33884,45.36046],"type":"Point"}
}