{
  "type": "Feature",
  "properties": {
    "gn:admin1_code":"12",
    "gn:admin2_code":"TO",
    "gn:admin3_code":"1088.0",
    "gn:asciiname":"Airola",
    "gn:country_code":"IT",
    "gn:dem":656,
    "gn:feature_class":"P",
    "gn:feature_code":"PPL",
    "gn:name":"Airola",
    "gn:population":41,
    "gn:timezone":"Europe/Rome",
    "iso:country":"IT",
    "name:azb_x_preferred":[
        "\u0627\u06cc\u0631\u0648\u0644\u0627"
    ],
    "name:bul_x_preferred":[
        "\u0410\u0439\u0440\u043e\u043b\u0430"
    ],
    "name:ceb_x_preferred":[
        "Airola"
    ],
    "name:deu_x_preferred":[
        "Airola"
    ],
    "name:epo_x_preferred":[
        "Airola"
    ],
    "name:eus_x_preferred":[
        "Airola"
    ],
    "name:fas_x_preferred":[
        "\u0627\u06cc\u0631\u0648\u0644\u0627"
    ],
    "name:fra_x_preferred":[
        "Airola"
    ],
    "name:hun_x_preferred":[
        "Airola"
    ],
    "name:hye_x_preferred":[
        "\u0531\u056b\u0580\u0578\u056c\u0561"
    ],
    "name:ina_x_preferred":[
        "Airola"
    ],
    "name:ind_x_preferred":[
        "Airola"
    ],
    "name:ita_x_preferred":[
        "Airola"
    ],
    "name:jav_x_preferred":[
        "Airola"
    ],
    "name:jpn_x_preferred":[
        "\u30a2\u30a4\u30ed\u30fc\u30e9"
    ],
    "name:kaz_x_preferred":[
        "\u0410\u0439\u0440\u043e\u043b\u0430"
    ],
    "name:kor_x_preferred":[
        "\uc544\uc774\ub864\ub77c"
    ],
    "name:lat_x_preferred":[
        "Airola"
    ],
    "name:lmo_x_preferred":[
        "Airola"
    ],
    "name:mkd_x_preferred":[
        "\u0410\u0458\u0440\u043e\u043b\u0430"
    ],
    "name:msa_x_preferred":[
        "Airola"
    ],
    "name:nap_x_preferred":[
        "Airola"
    ],
    "name:nld_x_preferred":[
        "Airola"
    ],
    "name:pms_x_preferred":[
        "Airola"
    ],
    "name:pol_x_preferred":[
        "Airola"
    ],
    "name:por_x_preferred":[
        "Airola"
    ],
    "name:ron_x_preferred":[
        "Airola"
    ],
    "name:rus_x_preferred":[
        "\u0410\u0439\u0440\u043e\u043b\u0430"
    ],
    "name:scn_x_preferred":[
        "Airola"
    ],
    "name:spa_x_preferred":[
        "Airola"
    ],
    "name:srn_x_preferred":[
        "Airola"
    ],
    "name:srp_x_preferred":[
        "\u0410\u0458\u0440\u043e\u043b\u0430"
    ],
    "name:tgl_x_preferred":[
        "Airola"
    ],
    "name:tur_x_preferred":[
        "Airola"
    ],
    "name:ukr_x_preferred":[
        "\u0410\u0457\u0440\u043e\u043b\u0430"
    ],
    "name:uzb_x_preferred":[
        "Airola"
    ],
    "name:vie_x_preferred":[
        "Airola"
    ],
    "name:vol_x_preferred":[
        "Airola"
    ],
    "name:war_x_preferred":[
        "Airola"
    ],
    "name:zho_x_preferred":[
        "\u827e\u7f57\u62c9"
    ],
    "wof:name":"Airola",
    "wof:placetype":"locality",
    "wof:population":41
},
  "geometry": {"coordinates":[7.47841,45.2953],"type":"Point"}
}