{
  "type": "Feature",
  "properties": {
    "gn:admin1_code":"12",
    "gn:admin2_code":"TO",
    "gn:admin3_code":"1088.0",
    "gn:asciiname":"Airola",
    "gn:country_code":"IT",
    "gn:dem":656,
    "gn:feature_class":"P",
    "gn:feature_code":"PPL",
    "gn:name":"Airola",
    "gn:population":41,
    "gn:timezone":"Europe/Rome",
    "iso:country":"IT",
    "wof:name":"Airola",
    "wof:placetype":"locality",
    "wof:population":41
},
  "geometry": {"coordinates":[7.47841,45.2953],"type":"Point"}
}