{
  "type": "Feature",
  "properties": {
    "gn:admin1_code":"16.0",
    "gn:admin2_code":"GR",
    "gn:admin3_code":"53015.0",
    "gn:asciiname":"Pian dei Mucini",
    "gn:country_code":"IT",
    "gn:dem":370,
    "gn:elevation":"372.0",
    "gn:feature_class":"P",
    "gn:feature_code":"PPLL",
    "gn:name":"Pian dei Mucini",
    "gn:population":0,
    "gn:timezone":"Europe/Rome",
    "iso:country":"IT",
    "name:und_x_variant":[
        "Pian Mucini",
        "Podere Pian Mucini"
    ],
    "wof:name":"Pian dei Mucini",
    "wof:placetype":"locality"
},
  "geometry": {"coordinates":[10.91656,43.07359],"type":"Point"}
}