{
  "type": "Feature",
  "properties": {
    "gn:gn_country":"IT",
    "gn:gn_fcode":"PPLA3",
    "gn:gn_pop":678,
    "gn:population":267,
    "iso:country":"IT",
    "name:ara_x_preferred":[
        "\u0641\u064a\u0633\u064a\u0645\u064a"
    ],
    "name:azb_x_preferred":[
        "\u0648\u0633\u06cc\u0645\u0647"
    ],
    "name:bel_x_preferred":[
        "\u0412\u0435\u0437\u0456\u043c\u044d"
    ],
    "name:bul_x_preferred":[
        "\u0412\u0435\u0437\u0438\u043c\u0435"
    ],
    "name:cat_x_preferred":[
        "Vesime"
    ],
    "name:ceb_x_preferred":[
        "Vesime"
    ],
    "name:deu_x_preferred":[
        "Vesime"
    ],
    "name:eng_x_preferred":[
        "Vesime"
    ],
    "name:epo_x_preferred":[
        "Vesime"
    ],
    "name:est_x_preferred":[
        "Vesime"
    ],
    "name:eus_x_preferred":[
        "Vesime"
    ],
    "name:fas_x_preferred":[
        "\u0648\u0633\u06cc\u0645\u0647"
    ],
    "name:fra_x_preferred":[
        "Vesime"
    ],
    "name:hun_x_preferred":[
        "Vesime"
    ],
    "name:hye_x_preferred":[
        "\u054e\u0565\u0566\u056b\u0574\u0565"
    ],
    "name:ind_x_preferred":[
        "Vesime"
    ],
    "name:ita_x_preferred":[
        "Vesime"
    ],
    "name:jpn_x_preferred":[
        "\u30f4\u30a7\u30fc\u30b8\u30e1"
    ],
    "name:kaz_x_preferred":[
        "\u0412\u0435\u0437\u0438\u043c\u0435"
    ],
    "name:lat_x_preferred":[
        "Vesimum"
    ],
    "name:lmo_x_preferred":[
        "Vesime"
    ],
    "name:msa_x_preferred":[
        "Vesime"
    ],
    "name:nan_x_preferred":[
        "Vesime"
    ],
    "name:nap_x_preferred":[
        "Vesime"
    ],
    "name:nld_x_preferred":[
        "Vesime"
    ],
    "name:oci_x_preferred":[
        "Vesime"
    ],
    "name:pms_x_preferred":[
        "Vesme"
    ],
    "name:pol_x_preferred":[
        "Vesime"
    ],
    "name:por_x_preferred":[
        "Vesime"
    ],
    "name:ron_x_preferred":[
        "Vesime"
    ],
    "name:rus_x_preferred":[
        "\u0412\u0435\u0437\u0438\u043c\u0435"
    ],
    "name:scn_x_preferred":[
        "Vesime"
    ],
    "name:spa_x_preferred":[
        "Vesime"
    ],
    "name:srp_x_preferred":[
        "Vesime"
    ],
    "name:tgl_x_preferred":[
        "Vesime"
    ],
    "name:ukr_x_preferred":[
        "\u0412\u0435\u0437\u0456\u043c\u0435"
    ],
    "name:uzb_x_preferred":[
        "Vesime"
    ],
    "name:vie_x_preferred":[
        "Vesime"
    ],
    "name:vol_x_preferred":[
        "Vesime"
    ],
    "name:war_x_preferred":[
        "Vesime"
    ],
    "name:zho_x_preferred":[
        "\u97e6\u897f\u6885"
    ],
    "qs_pg:aaroncc":"IT",
    "qs_pg:gn_country":"IT",
    "qs_pg:gn_fcode":"PPLA3",
    "qs_pg:gn_pop":678,
    "qs_pg:name":"Vesime",
    "qs_pg:name_adm0":"Italia",
    "qs_pg:name_adm1":"Piemonte",
    "qs_pg:photos_9k":1,
    "qs_pg:photos_9r":1,
    "qs_pg:photos_all":3,
    "qs_pg:photos_sr":0,
    "qs_pg:pop_sr":2,
    "qs_pg:qs_pg_placetype":"locality",
    "qs_pg:qs_pg_placetype_gp":"Town",
    "qs_pg:woe_adm0":23424853,
    "woe:adm0_id":23424853,
    "woe:name_adm0":"Italia",
    "woe:name_adm1":"Piemonte",
    "woe:placetype":"Town",
    "wof:name":"Vesime",
    "wof:placetype":"locality",
    "wof:population":267
},
  "geometry": {"coordinates":[8.22724,44.63574],"type":"Point"}
}