{
  "type": "Feature",
  "properties": {
    "gn:admin1_code":"5",
    "gn:admin2_code":"BO",
    "gn:admin3_code":"37057.0",
    "gn:asciiname":"Figatello",
    "gn:country_code":"IT",
    "gn:dem":253,
    "gn:feature_class":"P",
    "gn:feature_code":"PPL",
    "gn:name":"Figatello",
    "gn:population":52,
    "gn:timezone":"Europe/Rome",
    "iso:country":"IT",
    "wof:name":"Figatello",
    "wof:placetype":"locality",
    "wof:population":52
},
  "geometry": {"coordinates":[11.18991,44.43427],"type":"Point"}
}