{
  "type": "Feature",
  "properties": {
    "gn:admin1_code":"15.0",
    "gn:admin2_code":"TP",
    "gn:admin3_code":"81022.0",
    "gn:asciiname":"Rione la Sala",
    "gn:country_code":"IT",
    "gn:dem":22,
    "gn:feature_class":"P",
    "gn:feature_code":"PPL",
    "gn:name":"Rione la Sala",
    "gn:population":23,
    "gn:timezone":"Europe/Rome",
    "iso:country":"IT",
    "wof:name":"Rione la Sala",
    "wof:placetype":"locality",
    "wof:population":23
},
  "geometry": {"coordinates":[12.6221,38.06143],"type":"Point"}
}