{
  "type": "Feature",
  "properties": {
    "gn:admin1_code":"5",
    "gn:admin2_code":"MO",
    "gn:admin3_code":"36035.0",
    "gn:asciiname":"Pra di Sotto",
    "gn:country_code":"IT",
    "gn:dem":1117,
    "gn:feature_class":"P",
    "gn:feature_code":"PPL",
    "gn:name":"Pra di Sotto",
    "gn:population":16,
    "gn:timezone":"Europe/Rome",
    "iso:country":"IT",
    "wof:name":"Pra di Sotto",
    "wof:placetype":"locality",
    "wof:population":16
},
  "geometry": {"coordinates":[10.64095,44.25832],"type":"Point"}
}