{
  "type": "Feature",
  "properties": {
    "gn:admin1_code":"13",
    "gn:admin2_code":"BR",
    "gn:admin3_code":"74001.0",
    "gn:asciiname":"Lobia",
    "gn:country_code":"IT",
    "gn:dem":18,
    "gn:feature_class":"P",
    "gn:feature_code":"PPL",
    "gn:name":"Lobia",
    "gn:population":56,
    "gn:timezone":"Europe/Rome",
    "iso:country":"IT",
    "wof:name":"Lobia",
    "wof:placetype":"locality",
    "wof:population":56
},
  "geometry": {"coordinates":[17.89494,40.6669],"type":"Point"}
}