{
  "type": "Feature",
  "properties": {
    "gn:admin1_code":"7",
    "gn:admin2_code":"FR",
    "gn:admin3_code":"60050.0",
    "gn:asciiname":"Colle Posta II",
    "gn:country_code":"IT",
    "gn:dem":494,
    "gn:feature_class":"P",
    "gn:feature_code":"PPL",
    "gn:name":"Colle Posta II",
    "gn:population":74,
    "gn:timezone":"Europe/Rome",
    "iso:country":"IT",
    "wof:name":"Colle Posta II",
    "wof:placetype":"locality",
    "wof:population":74
},
  "geometry": {"coordinates":[13.84654,41.63349],"type":"Point"}
}