{
  "type": "Feature",
  "properties": {
    "gn:admin1_code":"20",
    "gn:admin2_code":"PD",
    "gn:admin3_code":"28081.0",
    "gn:asciiname":"Caduti",
    "gn:country_code":"IT",
    "gn:dem":6,
    "gn:feature_class":"P",
    "gn:feature_code":"PPL",
    "gn:name":"Caduti",
    "gn:population":16,
    "gn:timezone":"Europe/Rome",
    "iso:country":"IT",
    "wof:name":"Caduti",
    "wof:placetype":"locality",
    "wof:population":16
},
  "geometry": {"coordinates":[11.56366,45.18979],"type":"Point"}
}