{
  "type": "Feature",
  "properties": {
    "gn:admin1_code":"9.0",
    "gn:admin2_code":"SO",
    "gn:admin3_code":"14071.0",
    "gn:asciiname":"Degola",
    "gn:country_code":"IT",
    "gn:dem":1455,
    "gn:elevation":"1370.0",
    "gn:feature_class":"P",
    "gn:feature_code":"PPL",
    "gn:name":"Degola",
    "gn:population":59,
    "gn:timezone":"Europe/Rome",
    "iso:country":"IT",
    "wof:name":"Degola",
    "wof:placetype":"locality",
    "wof:population":59
},
  "geometry": {"coordinates":[10.31659,46.48897],"type":"Point"}
}