{
  "type": "Feature",
  "properties": {
    "gn:admin1_code":"16",
    "gn:admin2_code":"AR",
    "gn:admin3_code":"51012.0",
    "gn:asciiname":"Pieve di Chio",
    "gn:country_code":"IT",
    "gn:dem":299,
    "gn:feature_class":"P",
    "gn:feature_code":"PPL",
    "gn:name":"Pieve di Chio",
    "gn:population":29,
    "gn:timezone":"Europe/Rome",
    "iso:country":"IT",
    "wof:name":"Pieve di Chio",
    "wof:placetype":"locality",
    "wof:population":29
},
  "geometry": {"coordinates":[11.98901,43.35009],"type":"Point"}
}