{
  "type": "Feature",
  "properties": {
    "gn:admin1_code":"7",
    "gn:admin2_code":"FR",
    "gn:admin3_code":"60012.0",
    "gn:asciiname":"Orfanotrofio",
    "gn:country_code":"IT",
    "gn:dem":60,
    "gn:feature_class":"P",
    "gn:feature_code":"PPL",
    "gn:name":"Orfanotrofio",
    "gn:population":113,
    "gn:timezone":"Europe/Rome",
    "iso:country":"IT",
    "wof:name":"Orfanotrofio",
    "wof:placetype":"locality",
    "wof:population":113
},
  "geometry": {"coordinates":[13.75164,41.3475],"type":"Point"}
}