{
  "type": "Feature",
  "properties": {
    "gn:admin1_code":"7",
    "gn:admin2_code":"RM",
    "gn:admin3_code":"58107.0",
    "gn:asciiname":"Cala Pianorum",
    "gn:country_code":"IT",
    "gn:dem":181,
    "gn:feature_class":"P",
    "gn:feature_code":"PPL",
    "gn:name":"Cala Pianorum",
    "gn:population":66,
    "gn:timezone":"Europe/Rome",
    "iso:country":"IT",
    "wof:name":"Cala Pianorum",
    "wof:placetype":"locality",
    "wof:population":66
},
  "geometry": {"coordinates":[12.27391,42.15063],"type":"Point"}
}