{
  "type": "Feature",
  "properties": {
    "gn:admin1_code":"18",
    "gn:admin2_code":"PG",
    "gn:admin3_code":"54036.0",
    "gn:asciiname":"Caselle",
    "gn:country_code":"IT",
    "gn:dem":340,
    "gn:feature_class":"P",
    "gn:feature_code":"PPL",
    "gn:name":"Caselle",
    "gn:population":21,
    "gn:timezone":"Europe/Rome",
    "iso:country":"IT",
    "name:ceb_x_preferred":[
        "Caselle"
    ],
    "name:deu_x_preferred":[
        "Caselle"
    ],
    "name:ita_x_preferred":[
        "Caselle"
    ],
    "name:pol_x_preferred":[
        "Caselle"
    ],
    "name:por_x_preferred":[
        "Caselle"
    ],
    "name:srp_x_preferred":[
        "Kazele"
    ],
    "name:swe_x_preferred":[
        "Caselle"
    ],
    "wof:name":"Caselle",
    "wof:placetype":"locality",
    "wof:population":21
},
  "geometry": {"coordinates":[12.07007,43.02672000000001],"type":"Point"}
}