{
  "type": "Feature",
  "properties": {
    "gn:admin1_code":"6.0",
    "gn:admin2_code":"UD",
    "gn:admin3_code":"30013.0",
    "gn:asciiname":"Urbignacco",
    "gn:country_code":"IT",
    "gn:dem":204,
    "gn:feature_class":"P",
    "gn:feature_code":"PPL",
    "gn:name":"Urbignacco",
    "gn:population":0,
    "gn:timezone":"Europe/Rome",
    "iso:country":"IT",
    "wof:name":"Urbignacco",
    "wof:placetype":"locality"
},
  "geometry": {"coordinates":[13.13433,46.21856],"type":"Point"}
}