{
  "type": "Feature",
  "properties": {
    "gn:admin1_code":"9",
    "gn:admin2_code":"BS",
    "gn:admin3_code":"17179.0",
    "gn:asciiname":"Palazzo",
    "gn:country_code":"IT",
    "gn:dem":70,
    "gn:feature_class":"P",
    "gn:feature_code":"PPL",
    "gn:name":"Palazzo",
    "gn:population":57,
    "gn:timezone":"Europe/Rome",
    "iso:country":"IT",
    "wof:name":"Palazzo",
    "wof:placetype":"locality",
    "wof:population":57
},
  "geometry": {"coordinates":[10.61936,45.44935],"type":"Point"}
}