{
  "type": "Feature",
  "properties": {
    "gn:admin1_code":"18",
    "gn:admin2_code":"PG",
    "gn:admin3_code":"54051.0",
    "gn:asciiname":"Sant'Angelo in Mercole",
    "gn:country_code":"IT",
    "gn:dem":411,
    "gn:feature_class":"P",
    "gn:feature_code":"PPL",
    "gn:name":"Sant'Angelo in Mercole",
    "gn:population":42,
    "gn:timezone":"Europe/Rome",
    "iso:country":"IT",
    "wof:name":"Sant'Angelo in Mercole",
    "wof:placetype":"locality",
    "wof:population":42
},
  "geometry": {"coordinates":[12.68707,42.7501],"type":"Point"}
}