{
  "type": "Feature",
  "properties": {
    "gn:admin1_code":"20.0",
    "gn:admin2_code":"PD",
    "gn:admin3_code":"28080.0",
    "gn:asciiname":"Reato",
    "gn:country_code":"IT",
    "gn:dem":26,
    "gn:feature_class":"P",
    "gn:feature_code":"PPL",
    "gn:name":"Reato",
    "gn:population":20,
    "gn:timezone":"Europe/Rome",
    "iso:country":"IT",
    "wof:name":"Reato",
    "wof:placetype":"locality",
    "wof:population":20
},
  "geometry": {"coordinates":[11.88953,45.58863],"type":"Point"}
}