{
  "type": "Feature",
  "properties": {
    "gn:admin1_code":"7.0",
    "gn:admin2_code":"LT",
    "gn:admin3_code":"59001.0",
    "gn:asciiname":"Vallelata Centrale",
    "gn:country_code":"IT",
    "gn:dem":99,
    "gn:feature_class":"P",
    "gn:feature_code":"PPL",
    "gn:name":"Vallelata Centrale",
    "gn:population":140,
    "gn:timezone":"Europe/Rome",
    "iso:country":"IT",
    "wof:name":"Vallelata Centrale",
    "wof:placetype":"locality",
    "wof:population":140
},
  "geometry": {"coordinates":[12.64096,41.61399],"type":"Point"}
}