{
  "type": "Feature",
  "properties": {
    "gn:admin1_code":"16",
    "gn:admin2_code":"LU",
    "gn:admin3_code":"46033.0",
    "gn:asciiname":"Manone",
    "gn:country_code":"IT",
    "gn:dem":1,
    "gn:feature_class":"P",
    "gn:feature_code":"PPL",
    "gn:name":"Manone",
    "gn:population":21,
    "gn:timezone":"Europe/Rome",
    "iso:country":"IT",
    "wof:name":"Manone",
    "wof:placetype":"locality",
    "wof:population":21
},
  "geometry": {"coordinates":[10.27625,43.8352],"type":"Point"}
}