{
  "type": "Feature",
  "properties": {
    "gn:admin1_code":"4",
    "gn:admin2_code":"AV",
    "gn:admin3_code":"64030.0",
    "gn:asciiname":"Aree Industriali",
    "gn:country_code":"IT",
    "gn:dem":444,
    "gn:feature_class":"P",
    "gn:feature_code":"PPL",
    "gn:name":"Aree Industriali",
    "gn:population":11,
    "gn:timezone":"Europe/Rome",
    "iso:country":"IT",
    "wof:name":"Aree Industriali",
    "wof:placetype":"locality",
    "wof:population":11
},
  "geometry": {"coordinates":[15.29228,40.8793],"type":"Point"}
}