{
  "type": "Feature",
  "properties": {
    "gn:admin1_code":"7",
    "gn:admin2_code":"FR",
    "gn:admin3_code":"60089.0",
    "gn:asciiname":"Colle San Francesco",
    "gn:country_code":"IT",
    "gn:dem":90,
    "gn:feature_class":"P",
    "gn:feature_code":"PPLL",
    "gn:name":"Colle San Francesco",
    "gn:population":6,
    "gn:timezone":"Europe/Rome",
    "iso:country":"IT",
    "wof:name":"Colle San Francesco",
    "wof:placetype":"locality",
    "wof:population":6
},
  "geometry": {"coordinates":[13.75858,41.45096],"type":"Point"}
}