{
  "type": "Feature",
  "properties": {
    "gn:admin1_code":"20",
    "gn:admin2_code":"BL",
    "gn:admin3_code":"25021.0",
    "gn:asciiname":"Villapaiera",
    "gn:country_code":"IT",
    "gn:dem":241,
    "gn:feature_class":"P",
    "gn:feature_code":"PPL",
    "gn:name":"Villapaiera",
    "gn:population":223,
    "gn:timezone":"Europe/Rome",
    "iso:country":"IT",
    "wof:name":"Villapaiera",
    "wof:placetype":"locality",
    "wof:population":223
},
  "geometry": {"coordinates":[11.95688,46.02042],"type":"Point"}
}