{
  "type": "Feature",
  "properties": {
    "gn:admin1_code":"8",
    "gn:admin2_code":"GE",
    "gn:admin3_code":"10016.0",
    "gn:asciiname":"Quartaie",
    "gn:country_code":"IT",
    "gn:dem":125,
    "gn:feature_class":"P",
    "gn:feature_code":"PPL",
    "gn:name":"Quartaie",
    "gn:population":53,
    "gn:timezone":"Europe/Rome",
    "iso:country":"IT",
    "wof:name":"Quartaie",
    "wof:placetype":"locality",
    "wof:population":53
},
  "geometry": {"coordinates":[9.21581,44.4156],"type":"Point"}
}