{
  "type": "Feature",
  "properties": {
    "gn:admin1_code":"6",
    "gn:admin2_code":"UD",
    "gn:admin3_code":"30061.0",
    "gn:asciiname":"Zampariul",
    "gn:country_code":"IT",
    "gn:dem":406,
    "gn:feature_class":"P",
    "gn:feature_code":"PPL",
    "gn:name":"Zampariul",
    "gn:population":238,
    "gn:timezone":"Europe/Rome",
    "iso:country":"IT",
    "wof:name":"Zampariul",
    "wof:placetype":"locality",
    "wof:population":238
},
  "geometry": {"coordinates":[13.16837,46.25399],"type":"Point"}
}