{
  "type": "Feature",
  "properties": {
    "gn:admin1_code":"12",
    "gn:admin2_code":"NO",
    "gn:admin3_code":"3071.0",
    "gn:asciiname":"Cascina Scella",
    "gn:country_code":"IT",
    "gn:dem":405,
    "gn:feature_class":"P",
    "gn:feature_code":"PPL",
    "gn:name":"Cascina Scella",
    "gn:population":25,
    "gn:timezone":"Europe/Rome",
    "iso:country":"IT",
    "wof:name":"Cascina Scella",
    "wof:placetype":"locality",
    "wof:population":25
},
  "geometry": {"coordinates":[8.50501,45.71991],"type":"Point"}
}