{
  "type": "Feature",
  "properties": {
    "gn:admin1_code":"8",
    "gn:admin2_code":"GE",
    "gn:admin3_code":"10042.0",
    "gn:asciiname":"Pianmegorino",
    "gn:country_code":"IT",
    "gn:dem":294,
    "gn:feature_class":"P",
    "gn:feature_code":"PPL",
    "gn:name":"Pianmegorino",
    "gn:population":44,
    "gn:timezone":"Europe/Rome",
    "iso:country":"IT",
    "wof:name":"Pianmegorino",
    "wof:placetype":"locality",
    "wof:population":44
},
  "geometry": {"coordinates":[9.28376,44.4158],"type":"Point"}
}