{
  "type": "Feature",
  "properties": {
    "gn:admin1_code":"9",
    "gn:admin2_code":"LO",
    "gn:admin3_code":"98030.0",
    "gn:asciiname":"Cascina de Liuraghi",
    "gn:country_code":"IT",
    "gn:dem":64,
    "gn:feature_class":"P",
    "gn:feature_code":"PPL",
    "gn:name":"Cascina de Liuraghi",
    "gn:population":22,
    "gn:timezone":"Europe/Rome",
    "iso:country":"IT",
    "wof:name":"Cascina de Liuraghi",
    "wof:placetype":"locality",
    "wof:population":22
},
  "geometry": {"coordinates":[9.56262,45.17555],"type":"Point"}
}