{
  "type": "Feature",
  "properties": {
    "gn:admin1_code":"17.0",
    "gn:admin2_code":"BZ",
    "gn:admin3_code":"21109.0",
    "gn:asciiname":"San Martino in Casies Vallalta",
    "gn:country_code":"IT",
    "gn:dem":1508,
    "gn:feature_class":"P",
    "gn:feature_code":"PPL",
    "gn:name":"San Martino in Casies Vallalta",
    "gn:population":0,
    "gn:timezone":"Europe/Rome",
    "iso:country":"IT",
    "wof:name":"San Martino in Casies Vallalta",
    "wof:placetype":"locality"
},
  "geometry": {"coordinates":[12.245,46.84417],"type":"Point"}
}