{
  "type": "Feature",
  "properties": {
    "gn:admin1_code":"5",
    "gn:admin2_code":"PR",
    "gn:admin3_code":"34045.0",
    "gn:asciiname":"Vianino",
    "gn:country_code":"IT",
    "gn:dem":306,
    "gn:feature_class":"P",
    "gn:feature_code":"PPL",
    "gn:name":"Vianino",
    "gn:population":82,
    "gn:timezone":"Europe/Rome",
    "iso:country":"IT",
    "wof:name":"Vianino",
    "wof:placetype":"locality",
    "wof:population":82
},
  "geometry": {"coordinates":[9.93362,44.68367],"type":"Point"}
}