{
  "type": "Feature",
  "properties": {
    "gn:admin1_code":"9.0",
    "gn:admin2_code":"BG",
    "gn:admin3_code":"16171.0",
    "gn:asciiname":"Riviera",
    "gn:country_code":"IT",
    "gn:dem":428,
    "gn:feature_class":"P",
    "gn:feature_code":"PPL",
    "gn:name":"Riviera",
    "gn:population":375,
    "gn:timezone":"Europe/Rome",
    "iso:country":"IT",
    "wof:name":"Riviera",
    "wof:placetype":"locality",
    "wof:population":375
},
  "geometry": {"coordinates":[9.51073,45.74025],"type":"Point"}
}