{
  "type": "Feature",
  "properties": {
    "gn:admin1_code":"19",
    "gn:admin2_code":"AO",
    "gn:admin3_code":"7060.0",
    "gn:asciiname":"Lillaz",
    "gn:country_code":"IT",
    "gn:dem":526,
    "gn:feature_class":"P",
    "gn:feature_code":"PPL",
    "gn:name":"Lillaz",
    "gn:population":33,
    "gn:timezone":"Europe/Rome",
    "iso:country":"IT",
    "wof:name":"Lillaz",
    "wof:placetype":"locality",
    "wof:population":33
},
  "geometry": {"coordinates":[7.44126,45.73816],"type":"Point"}
}