{
  "type": "Feature",
  "properties": {
    "gn:admin1_code":"5.0",
    "gn:admin2_code":"MO",
    "gn:admin3_code":"36016.0",
    "gn:asciiname":"Casa Abbadina",
    "gn:country_code":"IT",
    "gn:dem":935,
    "gn:feature_class":"P",
    "gn:feature_code":"PPLL",
    "gn:name":"Casa Abbadina",
    "gn:population":2,
    "gn:timezone":"Europe/Rome",
    "iso:country":"IT",
    "wof:name":"Casa Abbadina",
    "wof:placetype":"locality",
    "wof:population":2
},
  "geometry": {"coordinates":[10.58328,44.26469],"type":"Point"}
}