{
  "type": "Feature",
  "properties": {
    "gn:admin1_code":"16",
    "gn:admin2_code":"PI",
    "gn:admin3_code":"50038.0",
    "gn:asciiname":"Sarzanese Valdera",
    "gn:country_code":"IT",
    "gn:dem":11,
    "gn:feature_class":"P",
    "gn:feature_code":"PPL",
    "gn:name":"Sarzanese Valdera",
    "gn:population":25,
    "gn:timezone":"Europe/Rome",
    "iso:country":"IT",
    "wof:name":"Sarzanese Valdera",
    "wof:placetype":"locality",
    "wof:population":25
},
  "geometry": {"coordinates":[10.61686,43.72053],"type":"Point"}
}