{
  "type": "Feature",
  "properties": {
    "gn:admin1_code":"15.0",
    "gn:admin2_code":"PA",
    "gn:admin3_code":"82053.0",
    "gn:asciiname":"Villagrazia",
    "gn:country_code":"IT",
    "gn:dem":91,
    "gn:feature_class":"P",
    "gn:feature_code":"PPL",
    "gn:name":"Villagrazia",
    "gn:population":0,
    "gn:timezone":"Europe/Rome",
    "iso:country":"IT",
    "wof:name":"Villagrazia",
    "wof:placetype":"locality"
},
  "geometry": {"coordinates":[13.33333,38.08333],"type":"Point"}
}