{
  "type": "Feature",
  "properties": {
    "gn:admin1_code":"4",
    "gn:admin2_code":"SA",
    "gn:admin3_code":"65084.0",
    "gn:asciiname":"Coste",
    "gn:country_code":"IT",
    "gn:dem":160,
    "gn:feature_class":"P",
    "gn:feature_code":"PPL",
    "gn:name":"Coste",
    "gn:population":30,
    "gn:timezone":"Europe/Rome",
    "iso:country":"IT",
    "wof:name":"Coste",
    "wof:placetype":"locality",
    "wof:population":30
},
  "geometry": {"coordinates":[15.11258,40.25075],"type":"Point"}
}