{
  "type": "Feature",
  "properties": {
    "gn:gn_country":"IT",
    "gn:gn_fcode":"PPL",
    "gn:gn_pop":0,
    "gn:population":874,
    "iso:country":"IT",
    "name:ceb_x_preferred":[
        "Nugola"
    ],
    "name:ita_x_preferred":[
        "Nugola"
    ],
    "name:nld_x_preferred":[
        "Nugola"
    ],
    "name:srp_x_preferred":[
        "\u041d\u0443\u0433\u043e\u043b\u0430"
    ],
    "qs_pg:aaroncc":"IT",
    "qs_pg:gn_country":"IT",
    "qs_pg:gn_fcode":"PPL",
    "qs_pg:gn_pop":0,
    "qs_pg:name":"Nugola",
    "qs_pg:name_adm0":"Italia",
    "qs_pg:name_adm1":"Toscana",
    "qs_pg:photos":42,
    "qs_pg:photos_1k":9,
    "qs_pg:photos_9k":1,
    "qs_pg:photos_9r":2,
    "qs_pg:photos_all":42,
    "qs_pg:photos_sr":2,
    "qs_pg:pop_sr":0,
    "qs_pg:qs_pg_placetype":"locality",
    "qs_pg:qs_pg_placetype_gp":"Town",
    "qs_pg:woe_adm0":23424853,
    "woe:adm0_id":23424853,
    "woe:name_adm0":"Italia",
    "woe:name_adm1":"Toscana",
    "woe:placetype":"Town",
    "wof:name":"Nugola",
    "wof:placetype":"locality",
    "wof:population":874
},
  "geometry": {"coordinates":[10.43333,43.58333],"type":"Point"}
}