{
  "type": "Feature",
  "properties": {
    "gn:admin1_code":"8.0",
    "gn:admin2_code":"IM",
    "gn:admin3_code":"8041.0",
    "gn:asciiname":"Boscomare",
    "gn:country_code":"IT",
    "gn:dem":370,
    "gn:elevation":"380.0",
    "gn:feature_class":"P",
    "gn:feature_code":"PPL",
    "gn:name":"Boscomare",
    "gn:population":91,
    "gn:timezone":"Europe/Rome",
    "iso:country":"IT",
    "wof:name":"Boscomare",
    "wof:placetype":"locality",
    "wof:population":91
},
  "geometry": {"coordinates":[7.90661,43.87838],"type":"Point"}
}