{
  "type": "Feature",
  "properties": {
    "iso:country":"IT",
    "wof:name":"Colle Prenestion",
    "wof:placetype":"neighbourhood"
},
  "geometry": {"coordinates":[12.63073657369389,41.89171464208572],"type":"Point"}
}