{
  "type": "Feature",
  "properties": {
    "gn:admin1_code":"20.0",
    "gn:admin2_code":"BL",
    "gn:admin3_code":"25005.0",
    "gn:asciiname":"Santa Caterina",
    "gn:country_code":"IT",
    "gn:dem":883,
    "gn:feature_class":"P",
    "gn:feature_code":"PPL",
    "gn:name":"Santa Caterina",
    "gn:population":0,
    "gn:timezone":"Europe/Rome",
    "iso:country":"IT",
    "name:cat_x_preferred":[
        "Santa Caterina"
    ],
    "name:ceb_x_preferred":[
        "Santa Caterina"
    ],
    "name:deu_x_preferred":[
        "Santa Caterina"
    ],
    "name:ita_x_preferred":[
        "Santa Caterina"
    ],
    "name:nld_x_preferred":[
        "Santa Caterina"
    ],
    "name:srp_x_preferred":[
        "\u0421\u0430\u043d\u0442\u0430 \u041a\u0430\u0442\u0435\u0440\u0438\u043d\u0430"
    ],
    "name:swe_x_preferred":[
        "Santa Caterina"
    ],
    "wof:name":"Santa Caterina",
    "wof:placetype":"locality"
},
  "geometry": {"coordinates":[12.46417,46.54306],"type":"Point"}
}