{
  "type": "Feature",
  "properties": {
    "gn:admin1_code":"9",
    "gn:admin2_code":"BS",
    "gn:admin3_code":"17185.0",
    "gn:asciiname":"Prabione",
    "gn:country_code":"IT",
    "gn:dem":526,
    "gn:feature_class":"P",
    "gn:feature_code":"PPL",
    "gn:name":"Prabione",
    "gn:population":147,
    "gn:timezone":"Europe/Rome",
    "iso:country":"IT",
    "wof:name":"Prabione",
    "wof:placetype":"locality",
    "wof:population":147
},
  "geometry": {"coordinates":[10.73255,45.75345],"type":"Point"}
}