{
  "type": "Feature",
  "properties": {
    "gn:admin1_code":"17",
    "gn:admin2_code":"BZ",
    "gn:admin3_code":"21070.0",
    "gn:asciiname":"Calice",
    "gn:country_code":"IT",
    "gn:dem":1434,
    "gn:feature_class":"P",
    "gn:feature_code":"PPL",
    "gn:name":"Calice",
    "gn:population":23,
    "gn:timezone":"Europe/Rome",
    "iso:country":"IT",
    "wof:name":"Calice",
    "wof:placetype":"locality",
    "wof:population":23
},
  "geometry": {"coordinates":[11.3638,46.86808],"type":"Point"}
}