{
  "type": "Feature",
  "properties": {
    "gn:admin1_code":"12",
    "gn:admin2_code":"CN",
    "gn:admin3_code":"4035.0",
    "gn:asciiname":"Gaudini",
    "gn:country_code":"IT",
    "gn:dem":437,
    "gn:feature_class":"P",
    "gn:feature_code":"PPL",
    "gn:name":"Gaudini",
    "gn:population":23,
    "gn:timezone":"Europe/Rome",
    "iso:country":"IT",
    "wof:name":"Gaudini",
    "wof:placetype":"locality",
    "wof:population":23
},
  "geometry": {"coordinates":[8.14633,44.43057],"type":"Point"}
}