{
  "type": "Feature",
  "properties": {
    "gn:admin1_code":"20.0",
    "gn:admin2_code":"TV",
    "gn:admin3_code":"26033.0",
    "gn:asciiname":"Zoppe",
    "gn:country_code":"IT",
    "gn:dem":33,
    "gn:feature_class":"P",
    "gn:feature_code":"PPL",
    "gn:name":"Zoppe",
    "gn:population":0,
    "gn:timezone":"Europe/Rome",
    "iso:country":"IT",
    "wof:name":"Zoppe",
    "wof:placetype":"locality"
},
  "geometry": {"coordinates":[12.40583,45.88806],"type":"Point"}
}