{
  "type": "Feature",
  "properties": {
    "gn:admin1_code":"13",
    "gn:admin2_code":"BR",
    "gn:admin3_code":"74012.0",
    "gn:asciiname":"Specchiaruzzo",
    "gn:country_code":"IT",
    "gn:dem":321,
    "gn:feature_class":"P",
    "gn:feature_code":"PPL",
    "gn:name":"Specchiaruzzo",
    "gn:population":74,
    "gn:timezone":"Europe/Rome",
    "iso:country":"IT",
    "wof:name":"Specchiaruzzo",
    "wof:placetype":"locality",
    "wof:population":74
},
  "geometry": {"coordinates":[17.42379,40.72341],"type":"Point"}
}