{
  "type": "Feature",
  "properties": {
    "gn:admin1_code":"5.0",
    "gn:admin2_code":"BO",
    "gn:admin3_code":"37022.0",
    "gn:asciiname":"Rasora",
    "gn:country_code":"IT",
    "gn:dem":787,
    "gn:elevation":"775.0",
    "gn:feature_class":"P",
    "gn:feature_code":"PPL",
    "gn:name":"Rasora",
    "gn:population":106,
    "gn:timezone":"Europe/Rome",
    "iso:country":"IT",
    "wof:name":"Rasora",
    "wof:placetype":"locality",
    "wof:population":106
},
  "geometry": {"coordinates":[11.15663,44.11574],"type":"Point"}
}