{
  "type": "Feature",
  "properties": {
    "gn:admin1_code":"16",
    "gn:admin2_code":"LI",
    "gn:admin3_code":"49008.0",
    "gn:asciiname":"Aiaccia",
    "gn:country_code":"IT",
    "gn:dem":15,
    "gn:feature_class":"P",
    "gn:feature_code":"PPL",
    "gn:name":"Aiaccia",
    "gn:population":47,
    "gn:timezone":"Europe/Rome",
    "iso:country":"IT",
    "wof:name":"Aiaccia",
    "wof:placetype":"locality",
    "wof:population":47
},
  "geometry": {"coordinates":[10.36934,43.57806],"type":"Point"}
}