{
  "type": "Feature",
  "properties": {
    "gn:admin1_code":"10.0",
    "gn:admin2_code":"MC",
    "gn:admin3_code":"43019.0",
    "gn:asciiname":"Forcatura",
    "gn:country_code":"IT",
    "gn:dem":723,
    "gn:elevation":"721.0",
    "gn:feature_class":"P",
    "gn:feature_code":"PPL",
    "gn:name":"Forcatura",
    "gn:population":13,
    "gn:timezone":"Europe/Rome",
    "iso:country":"IT",
    "wof:name":"Forcatura",
    "wof:placetype":"locality",
    "wof:population":13
},
  "geometry": {"coordinates":[12.88261,43.14514000000001],"type":"Point"}
}