{
  "type": "Feature",
  "properties": {
    "gn:admin1_code":"17.0",
    "gn:admin2_code":"BZ",
    "gn:admin3_code":"21092.0",
    "gn:asciiname":"Bagni",
    "gn:cc2":"IT",
    "gn:country_code":"IT",
    "gn:dem":1415,
    "gn:feature_class":"P",
    "gn:feature_code":"PPL",
    "gn:name":"Bagni",
    "gn:population":0,
    "gn:timezone":"Europe/Rome",
    "iso:country":"IT",
    "name:und_x_variant":[
        "Bagni di Sesto",
        "Bagni di Moso",
        "Bagni"
    ],
    "wof:name":"Bagni",
    "wof:placetype":"locality"
},
  "geometry": {"coordinates":[12.36917,46.68139],"type":"Point"}
}