{
  "type": "Feature",
  "properties": {
    "gn:admin1_code":"12.0",
    "gn:admin2_code":"TO",
    "gn:admin3_code":"1225.0",
    "gn:asciiname":"Zona Industriale Strada della Mandria",
    "gn:country_code":"IT",
    "gn:dem":212,
    "gn:feature_class":"P",
    "gn:feature_code":"PPL",
    "gn:name":"Zona Industriale Strada della Mandria",
    "gn:population":8,
    "gn:timezone":"Europe/Rome",
    "iso:country":"IT",
    "wof:name":"Zona Industriale Strada della Mandria",
    "wof:placetype":"locality",
    "wof:population":8
},
  "geometry": {"coordinates":[7.95532,45.24406],"type":"Point"}
}