{
  "type": "Feature",
  "properties": {
    "gn:admin1_code":"13",
    "gn:admin2_code":"BR",
    "gn:admin3_code":"74007.0",
    "gn:asciiname":"Occhio Piccolo",
    "gn:country_code":"IT",
    "gn:dem":71,
    "gn:feature_class":"P",
    "gn:feature_code":"PPL",
    "gn:name":"Occhio Piccolo",
    "gn:population":26,
    "gn:timezone":"Europe/Rome",
    "iso:country":"IT",
    "wof:name":"Occhio Piccolo",
    "wof:placetype":"locality",
    "wof:population":26
},
  "geometry": {"coordinates":[17.4845,40.78514000000001],"type":"Point"}
}