{
  "type": "Feature",
  "properties": {
    "gn:admin1_code":"4.0",
    "gn:admin2_code":"SA",
    "gn:admin3_code":"65037.0",
    "gn:asciiname":"San Giuseppe al Pennino Iv",
    "gn:country_code":"IT",
    "gn:dem":367,
    "gn:feature_class":"P",
    "gn:feature_code":"PPL",
    "gn:name":"San Giuseppe al Pennino Iv",
    "gn:population":30,
    "gn:timezone":"Europe/Rome",
    "iso:country":"IT",
    "wof:name":"San Giuseppe al Pennino Iv",
    "wof:placetype":"locality",
    "wof:population":30
},
  "geometry": {"coordinates":[14.72496,40.71748],"type":"Point"}
}