{
  "type": "Feature",
  "properties": {
    "gn:admin1_code":"7.0",
    "gn:admin2_code":"RI",
    "gn:admin3_code":"57002.0",
    "gn:asciiname":"Petrana",
    "gn:country_code":"IT",
    "gn:dem":920,
    "gn:elevation":"921.0",
    "gn:feature_class":"P",
    "gn:feature_code":"PPL",
    "gn:name":"Petrana",
    "gn:population":11,
    "gn:timezone":"Europe/Rome",
    "iso:country":"IT",
    "wof:name":"Petrana",
    "wof:placetype":"locality",
    "wof:population":11
},
  "geometry": {"coordinates":[13.29088,42.64927],"type":"Point"}
}