{
  "type": "Feature",
  "properties": {
    "gn:admin1_code":"7",
    "gn:admin2_code":"FR",
    "gn:admin3_code":"60018.0",
    "gn:asciiname":"Vitello",
    "gn:country_code":"IT",
    "gn:dem":342,
    "gn:feature_class":"P",
    "gn:feature_code":"PPL",
    "gn:name":"Vitello",
    "gn:population":21,
    "gn:timezone":"Europe/Rome",
    "iso:country":"IT",
    "wof:name":"Vitello",
    "wof:placetype":"locality",
    "wof:population":21
},
  "geometry": {"coordinates":[13.71446,41.62736],"type":"Point"}
}