{
  "type": "Feature",
  "properties": {
    "gn:admin1_code":"7",
    "gn:admin2_code":"FR",
    "gn:admin3_code":"60018.0",
    "gn:asciiname":"Vitello",
    "gn:country_code":"IT",
    "gn:dem":342,
    "gn:feature_class":"P",
    "gn:feature_code":"PPL",
    "gn:name":"Vitello",
    "gn:population":21,
    "gn:timezone":"Europe/Rome",
    "iso:country":"IT",
    "name:ara_x_preferred":[
        "\u0648\u064a\u062a\u0644\u0648"
    ],
    "name:ces_x_preferred":[
        "Witelo"
    ],
    "name:deu_x_preferred":[
        "Witelo"
    ],
    "name:epo_x_preferred":[
        "Vitelono"
    ],
    "name:fra_x_preferred":[
        "Vitellion"
    ],
    "name:ind_x_preferred":[
        "Witelo"
    ],
    "name:ita_x_preferred":[
        "Witelo"
    ],
    "name:jpn_x_preferred":[
        "\u30a6\u30a3\u30c6\u30ed"
    ],
    "name:kat_x_preferred":[
        "\u10d4\u10e0\u10d0\u10d6\u10db \u10d5\u10d8\u10e2\u10d4\u10da\u10dd"
    ],
    "name:nno_x_preferred":[
        "Vitelo"
    ],
    "name:nor_x_preferred":[
        "Vitelo"
    ],
    "name:pol_x_preferred":[
        "Witelon"
    ],
    "name:rus_x_preferred":[
        "\u0412\u0438\u0442\u0435\u043b\u043e"
    ],
    "name:slk_x_preferred":[
        "Vitelo"
    ],
    "name:spa_x_preferred":[
        "Witelo"
    ],
    "name:swe_x_preferred":[
        "Witelo"
    ],
    "name:ukr_x_preferred":[
        "\u0412\u0456\u0442\u0435\u043b\u043e"
    ],
    "name:zho_x_preferred":[
        "\u5a01\u7279\u7f85"
    ],
    "wof:name":"Vitello",
    "wof:placetype":"locality",
    "wof:population":21
},
  "geometry": {"coordinates":[13.71446,41.62736],"type":"Point"}
}