{
  "type": "Feature",
  "properties": {
    "gn:admin1_code":"6",
    "gn:admin2_code":"PN",
    "gn:admin3_code":"93007.0",
    "gn:asciiname":"Broch",
    "gn:country_code":"IT",
    "gn:dem":15,
    "gn:feature_class":"P",
    "gn:feature_code":"PPL",
    "gn:name":"Broch",
    "gn:population":39,
    "gn:timezone":"Europe/Rome",
    "iso:country":"IT",
    "name:cat_x_preferred":[
        "Broch"
    ],
    "name:ces_x_preferred":[
        "Broch"
    ],
    "name:cym_x_preferred":[
        "Broch"
    ],
    "name:deu_x_preferred":[
        "Broch"
    ],
    "name:epo_x_preferred":[
        "Broch"
    ],
    "name:eus_x_preferred":[
        "Broch"
    ],
    "name:fas_x_preferred":[
        "\u0633\u0646\u06af\u200c\u062f\u0698"
    ],
    "name:fin_x_preferred":[
        "Broch"
    ],
    "name:fra_x_preferred":[
        "Broch"
    ],
    "name:gla_x_preferred":[
        "Borg"
    ],
    "name:gle_x_preferred":[
        "Brugh"
    ],
    "name:ita_x_preferred":[
        "Broch"
    ],
    "name:kor_x_preferred":[
        "\ube0c\ub77c\ud750"
    ],
    "name:nld_x_preferred":[
        "Broch"
    ],
    "name:nor_x_preferred":[
        "Broch"
    ],
    "name:pol_x_preferred":[
        "Broch"
    ],
    "name:rus_x_preferred":[
        "\u0411\u0440\u043e\u0445"
    ],
    "name:spa_x_preferred":[
        "Broch"
    ],
    "name:swe_x_preferred":[
        "Broch"
    ],
    "name:ukr_x_preferred":[
        "\u0411\u0440\u043e\u0445"
    ],
    "wof:name":"Broch",
    "wof:placetype":"locality",
    "wof:population":39
},
  "geometry": {"coordinates":[12.58858,45.92039000000001],"type":"Point"}
}