{
  "type": "Feature",
  "properties": {
    "gn:admin1_code":"6.0",
    "gn:admin2_code":"UD",
    "gn:admin3_code":"30127.0",
    "gn:asciiname":"Leonacco",
    "gn:country_code":"IT",
    "gn:dem":183,
    "gn:elevation":"182.0",
    "gn:feature_class":"P",
    "gn:feature_code":"PPL",
    "gn:name":"Leonacco",
    "gn:population":278,
    "gn:timezone":"Europe/Rome",
    "iso:country":"IT",
    "wof:name":"Leonacco",
    "wof:placetype":"locality",
    "wof:population":278
},
  "geometry": {"coordinates":[13.20205,46.14315],"type":"Point"}
}