{
  "type": "Feature",
  "properties": {
    "gn:admin1_code":"5",
    "gn:admin2_code":"RE",
    "gn:admin3_code":"35004.0",
    "gn:asciiname":"Casale di Sopra",
    "gn:country_code":"IT",
    "gn:dem":128,
    "gn:feature_class":"P",
    "gn:feature_code":"PPL",
    "gn:name":"Casale di Sopra",
    "gn:population":88,
    "gn:timezone":"Europe/Rome",
    "iso:country":"IT",
    "wof:name":"Casale di Sopra",
    "wof:placetype":"locality",
    "wof:population":88
},
  "geometry": {"coordinates":[10.4486,44.66187],"type":"Point"}
}