{
  "type": "Feature",
  "properties": {
    "gn:admin1_code":"5.0",
    "gn:admin2_code":"PR",
    "gn:admin3_code":"34040.0",
    "gn:asciiname":"Casoni",
    "gn:country_code":"IT",
    "gn:dem":872,
    "gn:feature_class":"P",
    "gn:feature_code":"PPL",
    "gn:name":"Casoni",
    "gn:population":15,
    "gn:timezone":"Europe/Rome",
    "iso:country":"IT",
    "wof:name":"Casoni",
    "wof:placetype":"locality",
    "wof:population":15
},
  "geometry": {"coordinates":[9.47697,44.43848],"type":"Point"}
}