{
  "type": "Feature",
  "properties": {
    "gn:admin1_code":"12",
    "gn:admin2_code":"CN",
    "gn:admin3_code":"4030.0",
    "gn:asciiname":"Tetti Ellero",
    "gn:country_code":"IT",
    "gn:dem":342,
    "gn:feature_class":"P",
    "gn:feature_code":"PPL",
    "gn:name":"Tetti Ellero",
    "gn:population":51,
    "gn:timezone":"Europe/Rome",
    "iso:country":"IT",
    "wof:name":"Tetti Ellero",
    "wof:placetype":"locality",
    "wof:population":51
},
  "geometry": {"coordinates":[7.86252,44.41194],"type":"Point"}
}