{
  "type": "Feature",
  "properties": {
    "gn:admin1_code":"5",
    "gn:admin2_code":"RN",
    "gn:admin3_code":"99017.0",
    "gn:asciiname":"Pozzo Conca Vecchia",
    "gn:country_code":"IT",
    "gn:dem":28,
    "gn:feature_class":"P",
    "gn:feature_code":"PPL",
    "gn:name":"Pozzo Conca Vecchia",
    "gn:population":17,
    "gn:timezone":"Europe/Rome",
    "iso:country":"IT",
    "wof:name":"Pozzo Conca Vecchia",
    "wof:placetype":"locality",
    "wof:population":17
},
  "geometry": {"coordinates":[12.70346,43.94761],"type":"Point"}
}