{
  "type": "Feature",
  "properties": {
    "gn:admin1_code":"20",
    "gn:admin2_code":"RO",
    "gn:admin3_code":"29030.0",
    "gn:asciiname":"Pilastro",
    "gn:country_code":"IT",
    "gn:dem":-2,
    "gn:feature_class":"P",
    "gn:feature_code":"PPL",
    "gn:name":"Pilastro",
    "gn:population":87,
    "gn:timezone":"Europe/Rome",
    "iso:country":"IT",
    "wof:name":"Pilastro",
    "wof:placetype":"locality",
    "wof:population":87
},
  "geometry": {"coordinates":[12.2102,45.05369],"type":"Point"}
}