{
  "type": "Feature",
  "properties": {
    "gn:admin1_code":"19",
    "gn:admin2_code":"AO",
    "gn:admin3_code":"7049.0",
    "gn:asciiname":"Autoporto",
    "gn:country_code":"IT",
    "gn:dem":545,
    "gn:feature_class":"P",
    "gn:feature_code":"PPL",
    "gn:name":"Autoporto",
    "gn:population":57,
    "gn:timezone":"Europe/Rome",
    "iso:country":"IT",
    "wof:name":"Autoporto",
    "wof:placetype":"locality",
    "wof:population":57
},
  "geometry": {"coordinates":[7.36775,45.73615],"type":"Point"}
}