{
  "type": "Feature",
  "properties": {
    "gn:admin1_code":"12",
    "gn:admin2_code":"NO",
    "gn:admin3_code":"3114.0",
    "gn:asciiname":"Borgo Agnello",
    "gn:country_code":"IT",
    "gn:dem":346,
    "gn:feature_class":"P",
    "gn:feature_code":"PPL",
    "gn:name":"Borgo Agnello",
    "gn:population":11,
    "gn:timezone":"Europe/Rome",
    "iso:country":"IT",
    "wof:name":"Borgo Agnello",
    "wof:placetype":"locality",
    "wof:population":11
},
  "geometry": {"coordinates":[8.50966,45.7386],"type":"Point"}
}