{
  "type": "Feature",
  "properties": {
    "gn:admin1_code":"16",
    "gn:admin2_code":"FI",
    "gn:admin3_code":"48010.0",
    "gn:asciiname":"Pesciola",
    "gn:country_code":"IT",
    "gn:dem":55,
    "gn:feature_class":"P",
    "gn:feature_code":"PPL",
    "gn:name":"Pesciola",
    "gn:population":22,
    "gn:timezone":"Europe/Rome",
    "iso:country":"IT",
    "wof:name":"Pesciola",
    "wof:placetype":"locality",
    "wof:population":22
},
  "geometry": {"coordinates":[10.98474,43.59351],"type":"Point"}
}