{
  "type": "Feature",
  "properties": {
    "gn:admin1_code":"15.0",
    "gn:admin2_code":"TP",
    "gn:admin3_code":"81011.0",
    "gn:asciiname":"Arini",
    "gn:country_code":"IT",
    "gn:dem":17,
    "gn:feature_class":"P",
    "gn:feature_code":"PPL",
    "gn:name":"Arini",
    "gn:population":0,
    "gn:timezone":"Europe/Rome",
    "iso:country":"IT",
    "name:ceb_x_preferred":[
        "Arini"
    ],
    "name:deu_x_preferred":[
        "Arini"
    ],
    "name:epo_x_preferred":[
        "Arini"
    ],
    "name:hun_x_preferred":[
        "Arini"
    ],
    "name:ron_x_preferred":[
        "Arini"
    ],
    "name:swe_x_preferred":[
        "Arini"
    ],
    "wof:name":"Arini",
    "wof:placetype":"locality"
},
  "geometry": {"coordinates":[12.48333,37.81667],"type":"Point"}
}