{
  "type": "Feature",
  "properties": {
    "gn:admin1_code":"3",
    "gn:admin2_code":"RC",
    "gn:admin3_code":"80029.0",
    "gn:asciiname":"Carcara",
    "gn:country_code":"IT",
    "gn:dem":241,
    "gn:feature_class":"P",
    "gn:feature_code":"PPL",
    "gn:name":"Carcara",
    "gn:population":83,
    "gn:timezone":"Europe/Rome",
    "iso:country":"IT",
    "wof:name":"Carcara",
    "wof:placetype":"locality",
    "wof:population":83
},
  "geometry": {"coordinates":[15.87388,37.99479],"type":"Point"}
}