{
  "type": "Feature",
  "properties": {
    "gn:admin1_code":"9",
    "gn:admin2_code":"PV",
    "gn:admin3_code":"18167.0",
    "gn:asciiname":"Regina",
    "gn:country_code":"IT",
    "gn:dem":94,
    "gn:feature_class":"P",
    "gn:feature_code":"PPL",
    "gn:name":"Regina",
    "gn:population":18,
    "gn:timezone":"Europe/Rome",
    "iso:country":"IT",
    "name:azb_x_preferred":[
        "\u0631\u062c\u0627\u06cc\u0646\u0627"
    ],
    "name:bre_x_preferred":[
        "Regina"
    ],
    "name:cat_x_preferred":[
        "Regina"
    ],
    "name:ceb_x_preferred":[
        "Regina"
    ],
    "name:ces_x_preferred":[
        "Regina"
    ],
    "name:dan_x_preferred":[
        "Regina"
    ],
    "name:deu_x_preferred":[
        "Regina"
    ],
    "name:ell_x_preferred":[
        "\u03a1\u03b5\u03b3\u03b3\u03af\u03bd\u03b1"
    ],
    "name:est_x_preferred":[
        "Regina"
    ],
    "name:fas_x_preferred":[
        "\u0631\u062c\u06cc\u0646\u0627"
    ],
    "name:fin_x_preferred":[
        "Regina"
    ],
    "name:fra_x_preferred":[
        "R\u00e9gina"
    ],
    "name:heb_x_preferred":[
        "\u05e8\u05d2'\u05d9\u05e0\u05d4"
    ],
    "name:hun_x_preferred":[
        "Regina"
    ],
    "name:ita_x_preferred":[
        "Regina"
    ],
    "name:jpn_x_preferred":[
        "Regina"
    ],
    "name:kor_x_preferred":[
        "\ub808\uc9c0\ub098"
    ],
    "name:lit_x_preferred":[
        "Regina"
    ],
    "name:nld_x_preferred":[
        "Regina"
    ],
    "name:nor_x_preferred":[
        "Regina"
    ],
    "name:pol_x_preferred":[
        "Regina"
    ],
    "name:por_x_preferred":[
        "Regina"
    ],
    "name:rus_x_preferred":[
        "\u0420\u0435\u0433\u0438\u043d\u0430"
    ],
    "name:slk_x_preferred":[
        "Regina"
    ],
    "name:slv_x_preferred":[
        "Regina"
    ],
    "name:spa_x_preferred":[
        "Regina"
    ],
    "name:srp_x_preferred":[
        "\u0420\u0435\u0433\u0438\u043d\u0430"
    ],
    "name:swe_x_preferred":[
        "Regina"
    ],
    "name:vol_x_preferred":[
        "Regina"
    ],
    "name:zho_x_preferred":[
        "Regina"
    ],
    "wof:name":"Regina",
    "wof:placetype":"locality",
    "wof:population":18
},
  "geometry": {"coordinates":[8.8549,45.1538],"type":"Point"}
}