{
  "type": "Feature",
  "properties": {
    "gn:admin1_code":"9",
    "gn:admin2_code":"PV",
    "gn:admin3_code":"18167.0",
    "gn:asciiname":"Regina",
    "gn:country_code":"IT",
    "gn:dem":94,
    "gn:feature_class":"P",
    "gn:feature_code":"PPL",
    "gn:name":"Regina",
    "gn:population":18,
    "gn:timezone":"Europe/Rome",
    "iso:country":"IT",
    "wof:name":"Regina",
    "wof:placetype":"locality",
    "wof:population":18
},
  "geometry": {"coordinates":[8.8549,45.1538],"type":"Point"}
}