{
  "type": "Feature",
  "properties": {
    "gn:admin1_code":"9.0",
    "gn:admin2_code":"MI",
    "gn:admin3_code":"15051.0",
    "gn:asciiname":"Zona Industriale",
    "gn:country_code":"IT",
    "gn:dem":153,
    "gn:feature_class":"P",
    "gn:feature_code":"PPL",
    "gn:name":"Zona Industriale",
    "gn:population":13,
    "gn:timezone":"Europe/Rome",
    "iso:country":"IT",
    "name:deu_x_preferred":[
        "Zona Industriale"
    ],
    "name:fra_x_preferred":[
        "Zona Industriale"
    ],
    "name:ita_x_preferred":[
        "Zona Industriale"
    ],
    "name:nap_x_preferred":[
        "Zona Nnustriale"
    ],
    "wof:name":"Zona Industriale",
    "wof:placetype":"locality",
    "wof:population":13
},
  "geometry": {"coordinates":[9.34235,45.55906],"type":"Point"}
}