{
  "type": "Feature",
  "properties": {
    "gn:admin1_code":"20",
    "gn:admin2_code":"TV",
    "gn:admin3_code":"26092.0",
    "gn:asciiname":"Borgo Olivi",
    "gn:country_code":"IT",
    "gn:dem":664,
    "gn:feature_class":"P",
    "gn:feature_code":"PPL",
    "gn:name":"Borgo Olivi",
    "gn:population":17,
    "gn:timezone":"Europe/Rome",
    "iso:country":"IT",
    "wof:name":"Borgo Olivi",
    "wof:placetype":"locality",
    "wof:population":17
},
  "geometry": {"coordinates":[12.27531,46.02811],"type":"Point"}
}