{
  "type": "Feature",
  "properties": {
    "gn:admin1_code":"20",
    "gn:admin2_code":"PD",
    "gn:admin3_code":"28087.0",
    "gn:asciiname":"Sottopra",
    "gn:country_code":"IT",
    "gn:dem":3,
    "gn:feature_class":"P",
    "gn:feature_code":"PPL",
    "gn:name":"Sottopr\u00e0",
    "gn:population":15,
    "gn:timezone":"Europe/Rome",
    "iso:country":"IT",
    "name:und_x_variant":[
        "Sottopr\u00e0"
    ],
    "wof:name":"Sottopra",
    "wof:placetype":"locality",
    "wof:population":15
},
  "geometry": {"coordinates":[11.7381,45.17243],"type":"Point"}
}