{
  "type": "Feature",
  "properties": {
    "gn:admin1_code":"18",
    "gn:admin2_code":"PG",
    "gn:admin3_code":"54023.0",
    "gn:asciiname":"Poggio Sant'Ercolano",
    "gn:country_code":"IT",
    "gn:dem":667,
    "gn:feature_class":"P",
    "gn:feature_code":"PPL",
    "gn:name":"Poggio Sant'Ercolano",
    "gn:population":86,
    "gn:timezone":"Europe/Rome",
    "iso:country":"IT",
    "wof:name":"Poggio Sant'Ercolano",
    "wof:placetype":"locality",
    "wof:population":86
},
  "geometry": {"coordinates":[12.70526,43.23667],"type":"Point"}
}