{
  "type": "Feature",
  "properties": {
    "gn:admin1_code":"16",
    "gn:admin2_code":"LI",
    "gn:admin3_code":"49014.0",
    "gn:asciiname":"Acquabona",
    "gn:country_code":"IT",
    "gn:dem":70,
    "gn:feature_class":"P",
    "gn:feature_code":"PPL",
    "gn:name":"Acquabona",
    "gn:population":32,
    "gn:timezone":"Europe/Rome",
    "iso:country":"IT",
    "wof:name":"Acquabona",
    "wof:placetype":"locality",
    "wof:population":32
},
  "geometry": {"coordinates":[10.34066,42.78358],"type":"Point"}
}