{
  "type": "Feature",
  "properties": {
    "gn:admin1_code":"16",
    "gn:admin2_code":"LI",
    "gn:admin3_code":"49002.0",
    "gn:asciiname":"Campalto",
    "gn:country_code":"IT",
    "gn:dem":100,
    "gn:feature_class":"P",
    "gn:feature_code":"PPL",
    "gn:name":"Campalto",
    "gn:population":38,
    "gn:timezone":"Europe/Rome",
    "iso:country":"IT",
    "wof:name":"Campalto",
    "wof:placetype":"locality",
    "wof:population":38
},
  "geometry": {"coordinates":[10.5813,43.06379],"type":"Point"}
}