{
  "type": "Feature",
  "properties": {
    "gn:admin1_code":"16",
    "gn:admin2_code":"MS",
    "gn:admin3_code":"45013.0",
    "gn:asciiname":"Metti",
    "gn:country_code":"IT",
    "gn:dem":327,
    "gn:feature_class":"P",
    "gn:feature_code":"PPL",
    "gn:name":"Metti",
    "gn:population":25,
    "gn:timezone":"Europe/Rome",
    "iso:country":"IT",
    "wof:name":"Metti",
    "wof:placetype":"locality",
    "wof:population":25
},
  "geometry": {"coordinates":[9.92874,44.20741],"type":"Point"}
}