{
  "type": "Feature",
  "properties": {
    "gn:admin1_code":"10",
    "gn:admin2_code":"MC",
    "gn:admin3_code":"43044.0",
    "gn:asciiname":"Spaccio Bagnolo",
    "gn:country_code":"IT",
    "gn:dem":148,
    "gn:feature_class":"P",
    "gn:feature_code":"PPL",
    "gn:name":"Spaccio Bagnolo",
    "gn:population":93,
    "gn:timezone":"Europe/Rome",
    "iso:country":"IT",
    "wof:name":"Spaccio Bagnolo",
    "wof:placetype":"locality",
    "wof:population":93
},
  "geometry": {"coordinates":[13.50415,43.42177],"type":"Point"}
}