{
  "type": "Feature",
  "properties": {
    "gn:admin1_code":"20",
    "gn:admin2_code":"VE",
    "gn:admin3_code":"27021.0",
    "gn:asciiname":"Ca' Errera",
    "gn:country_code":"IT",
    "gn:dem":7,
    "gn:feature_class":"P",
    "gn:feature_code":"PPL",
    "gn:name":"Ca' Errera",
    "gn:population":34,
    "gn:timezone":"Europe/Rome",
    "iso:country":"IT",
    "wof:name":"Ca' Errera",
    "wof:placetype":"locality",
    "wof:population":34
},
  "geometry": {"coordinates":[12.14642,45.55527],"type":"Point"}
}