{
  "type": "Feature",
  "properties": {
    "gn:admin1_code":"20",
    "gn:admin2_code":"VR",
    "gn:admin3_code":"23062.0",
    "gn:asciiname":"Valdoneghe di Sotto",
    "gn:country_code":"IT",
    "gn:dem":210,
    "gn:feature_class":"P",
    "gn:feature_code":"PPL",
    "gn:name":"Valdoneghe di Sotto",
    "gn:population":27,
    "gn:timezone":"Europe/Rome",
    "iso:country":"IT",
    "wof:name":"Valdoneghe di Sotto",
    "wof:placetype":"locality",
    "wof:population":27
},
  "geometry": {"coordinates":[10.76761,45.57717],"type":"Point"}
}