{
  "type": "Feature",
  "properties": {
    "gn:admin1_code":"1",
    "gn:admin2_code":"PE",
    "gn:admin3_code":"68027.0",
    "gn:asciiname":"Mallo",
    "gn:country_code":"IT",
    "gn:dem":382,
    "gn:feature_class":"P",
    "gn:feature_code":"PPL",
    "gn:name":"Mallo",
    "gn:population":61,
    "gn:timezone":"Europe/Rome",
    "iso:country":"IT",
    "wof:name":"Mallo",
    "wof:placetype":"locality",
    "wof:population":61
},
  "geometry": {"coordinates":[13.89401,42.46508],"type":"Point"}
}