{
  "type": "Feature",
  "properties": {
    "gn:admin1_code":"7",
    "gn:admin2_code":"FR",
    "gn:admin3_code":"60009.0",
    "gn:asciiname":"Colle Mola",
    "gn:country_code":"IT",
    "gn:dem":178,
    "gn:feature_class":"P",
    "gn:feature_code":"PPL",
    "gn:name":"Colle Mola",
    "gn:population":90,
    "gn:timezone":"Europe/Rome",
    "iso:country":"IT",
    "wof:name":"Colle Mola",
    "wof:placetype":"locality",
    "wof:population":90
},
  "geometry": {"coordinates":[13.38552,41.56569],"type":"Point"}
}