{
  "type": "Feature",
  "properties": {
    "gn:admin1_code":"3.0",
    "gn:admin2_code":"RC",
    "gn:admin3_code":"80022.0",
    "gn:asciiname":"Contrada Castanea",
    "gn:country_code":"IT",
    "gn:dem":997,
    "gn:feature_class":"P",
    "gn:feature_code":"PPL",
    "gn:name":"Contrada Castanea",
    "gn:population":57,
    "gn:timezone":"Europe/Rome",
    "iso:country":"IT",
    "wof:name":"Contrada Castanea",
    "wof:placetype":"locality",
    "wof:population":57
},
  "geometry": {"coordinates":[15.81504,38.09458],"type":"Point"}
}