{
  "type": "Feature",
  "properties": {
    "gn:admin1_code":"17",
    "gn:admin2_code":"TN",
    "gn:admin3_code":"22048.0",
    "gn:asciiname":"Lissa",
    "gn:country_code":"IT",
    "gn:dem":905,
    "gn:feature_class":"P",
    "gn:feature_code":"PPLL",
    "gn:name":"Lissa",
    "gn:population":8,
    "gn:timezone":"Europe/Rome",
    "iso:country":"IT",
    "wof:name":"Lissa",
    "wof:placetype":"locality",
    "wof:population":8
},
  "geometry": {"coordinates":[11.62695,46.07397],"type":"Point"}
}