{
  "type": "Feature",
  "properties": {
    "gn:admin1_code":"1.0",
    "gn:admin2_code":"AQ",
    "gn:admin3_code":"66094.0",
    "gn:asciiname":"Loc. Campo Dragone",
    "gn:country_code":"IT",
    "gn:dem":822,
    "gn:feature_class":"P",
    "gn:feature_code":"PPLL",
    "gn:name":"Loc. Campo Dragone",
    "gn:population":0,
    "gn:timezone":"Europe/Rome",
    "iso:country":"IT",
    "wof:name":"Loc. Campo Dragone",
    "wof:placetype":"locality"
},
  "geometry": {"coordinates":[14.08835,41.74549],"type":"Point"}
}