{
  "type": "Feature",
  "properties": {
    "gn:admin1_code":"15.0",
    "gn:admin2_code":"ME",
    "gn:admin3_code":"83075.0",
    "gn:asciiname":"Milici",
    "gn:country_code":"IT",
    "gn:dem":252,
    "gn:elevation":"234.0",
    "gn:feature_class":"P",
    "gn:feature_code":"PPL",
    "gn:name":"Milici",
    "gn:population":382,
    "gn:timezone":"Europe/Rome",
    "iso:country":"IT",
    "wof:name":"Milici",
    "wof:placetype":"locality",
    "wof:population":382
},
  "geometry": {"coordinates":[15.16877,38.08349000000001],"type":"Point"}
}