{
  "type": "Feature",
  "properties": {
    "gn:admin1_code":"13",
    "gn:admin2_code":"LE",
    "gn:admin3_code":"75029.0",
    "gn:asciiname":"Contrada San Giuseppe",
    "gn:country_code":"IT",
    "gn:dem":68,
    "gn:feature_class":"P",
    "gn:feature_code":"PPL",
    "gn:name":"Contrada San Giuseppe",
    "gn:population":29,
    "gn:timezone":"Europe/Rome",
    "iso:country":"IT",
    "wof:name":"Contrada San Giuseppe",
    "wof:placetype":"locality",
    "wof:population":29
},
  "geometry": {"coordinates":[18.17454,40.18835],"type":"Point"}
}