{
  "type": "Feature",
  "properties": {
    "gn:admin1_code":"20",
    "gn:admin2_code":"TV",
    "gn:admin3_code":"26045.0",
    "gn:asciiname":"Farnea",
    "gn:country_code":"IT",
    "gn:dem":166,
    "gn:feature_class":"P",
    "gn:feature_code":"PPL",
    "gn:name":"Farnea",
    "gn:population":34,
    "gn:timezone":"Europe/Rome",
    "iso:country":"IT",
    "wof:name":"Farnea",
    "wof:placetype":"locality",
    "wof:population":34
},
  "geometry": {"coordinates":[11.90997,45.83583],"type":"Point"}
}