{
  "type": "Feature",
  "properties": {
    "gn:admin1_code":"9.0",
    "gn:admin2_code":"SO",
    "gn:admin3_code":"14004.0",
    "gn:asciiname":"Mavigna",
    "gn:country_code":"IT",
    "gn:dem":1096,
    "gn:feature_class":"P",
    "gn:feature_code":"PPL",
    "gn:name":"Mavigna",
    "gn:population":0,
    "gn:timezone":"Europe/Rome",
    "iso:country":"IT",
    "wof:name":"Mavigna",
    "wof:placetype":"locality"
},
  "geometry": {"coordinates":[10.13333,46.15],"type":"Point"}
}