{
  "type": "Feature",
  "properties": {
    "gn:admin1_code":"4",
    "gn:admin2_code":"SA",
    "gn:admin3_code":"65043.0",
    "gn:asciiname":"Macchia Grande",
    "gn:country_code":"IT",
    "gn:dem":201,
    "gn:feature_class":"P",
    "gn:feature_code":"PPL",
    "gn:name":"Macchia Grande",
    "gn:population":276,
    "gn:timezone":"Europe/Rome",
    "iso:country":"IT",
    "wof:name":"Macchia Grande",
    "wof:placetype":"locality",
    "wof:population":276
},
  "geometry": {"coordinates":[15.26051,40.70973],"type":"Point"}
}