{
  "type": "Feature",
  "properties": {
    "gn:country":"IT",
    "gn:fcode":"PPL",
    "gn:population":0,
    "iso:country":"IT",
    "name:cat_x_preferred":[
        "Borgata Sestriere"
    ],
    "name:ceb_x_preferred":[
        "Borgata Sestriere"
    ],
    "name:ces_x_preferred":[
        "Borgata Sestriere"
    ],
    "name:dan_x_preferred":[
        "Borgata Sestriere"
    ],
    "name:eng_x_preferred":[
        "Borgata Sestriere"
    ],
    "name:eus_x_preferred":[
        "Borgata Sestriere"
    ],
    "name:fin_x_preferred":[
        "Borgata Sestriere"
    ],
    "name:fra_x_preferred":[
        "Borgata Sestriere"
    ],
    "name:ind_x_preferred":[
        "Borgata Sestriere"
    ],
    "name:ita_x_preferred":[
        "Borgata Sestriere"
    ],
    "name:nld_x_preferred":[
        "Borgata Sestriere"
    ],
    "name:nld_x_variant":[
        "Sestriere Borgata"
    ],
    "name:nno_x_preferred":[
        "Borgata Sestriere"
    ],
    "name:nob_x_preferred":[
        "Borgata Sestriere"
    ],
    "name:oci_x_preferred":[
        "Borgata Sestriere"
    ],
    "name:pol_x_preferred":[
        "Borgata Sestriere"
    ],
    "name:por_x_preferred":[
        "Borgata Sestriere"
    ],
    "name:ron_x_preferred":[
        "Borgata Sestriere"
    ],
    "name:slk_x_preferred":[
        "Borgata Sestriere"
    ],
    "name:slv_x_preferred":[
        "Borgata Sestriere"
    ],
    "name:spa_x_preferred":[
        "Borgata Sestriere"
    ],
    "name:srp_x_preferred":[
        "Borgata Sestriere"
    ],
    "name:swe_x_preferred":[
        "Borgata Sestriere"
    ],
    "name:tgl_x_preferred":[
        "Borgata Sestriere"
    ],
    "name:tur_x_preferred":[
        "Borgata Sestriere"
    ],
    "name:und_x_variant":[
        "Sestriere Vecchio"
    ],
    "name:war_x_preferred":[
        "Borgata Sestriere"
    ],
    "qs_pg:aaroncc":"IT",
    "qs_pg:gn_country":"IT",
    "qs_pg:gn_fcode":"PPL",
    "qs_pg:gn_pop":0,
    "qs_pg:name":"Borgata Sestriere",
    "qs_pg:name_adm0":"Italia",
    "qs_pg:name_adm1":"Piemonte",
    "qs_pg:photos_9r":0,
    "qs_pg:photos_sr":0,
    "qs_pg:pop_sr":0,
    "qs_pg:qs_pg_placetype":"locality",
    "qs_pg:qs_pg_placetype_gp":"Town",
    "qs_pg:woe_adm0":23424853,
    "woe:adm0_id":23424853,
    "woe:name_adm0":"Italia",
    "woe:name_adm1":"Piemonte",
    "woe:placetype":"Town",
    "wof:name":"Borgata Sestriere",
    "wof:placetype":"locality",
    "wof:population":74
},
  "geometry": {"coordinates":[6.89637,44.97281],"type":"Point"}
}