{
  "type": "Feature",
  "properties": {
    "gn:admin1_code":"8",
    "gn:admin2_code":"GE",
    "gn:admin3_code":"10018.0",
    "gn:asciiname":"Monticelli",
    "gn:country_code":"IT",
    "gn:dem":144,
    "gn:feature_class":"P",
    "gn:feature_code":"PPL",
    "gn:name":"Monticelli",
    "gn:population":31,
    "gn:timezone":"Europe/Rome",
    "iso:country":"IT",
    "name:ceb_x_preferred":[
        "Monticelli"
    ],
    "name:deu_x_preferred":[
        "Monticelli"
    ],
    "name:fra_x_preferred":[
        "Monticelli"
    ],
    "name:ita_x_preferred":[
        "Monticelli"
    ],
    "name:por_x_preferred":[
        "Monticelli"
    ],
    "name:rus_x_preferred":[
        "\u041c\u043e\u043d\u0442\u0438\u0447\u0435\u043b\u043b\u0438"
    ],
    "name:srp_x_preferred":[
        "Monti\u010deli"
    ],
    "name:swe_x_preferred":[
        "Monticelli"
    ],
    "wof:name":"Monticelli",
    "wof:placetype":"locality",
    "wof:population":31
},
  "geometry": {"coordinates":[9.36276,44.34139],"type":"Point"}
}