{
  "type": "Feature",
  "properties": {
    "gn:admin1_code":"8",
    "gn:admin2_code":"SV",
    "gn:admin3_code":"9052.0",
    "gn:asciiname":"Montagna",
    "gn:country_code":"IT",
    "gn:dem":341,
    "gn:feature_class":"P",
    "gn:feature_code":"PPL",
    "gn:name":"Montagna",
    "gn:population":138,
    "gn:timezone":"Europe/Rome",
    "iso:country":"IT",
    "wof:name":"Montagna",
    "wof:placetype":"locality",
    "wof:population":138
},
  "geometry": {"coordinates":[8.36784,44.28073],"type":"Point"}
}