{
  "type": "Feature",
  "properties": {
    "gn:admin1_code":"16",
    "gn:admin2_code":"FI",
    "gn:admin3_code":"48001.0",
    "gn:asciiname":"Taiano",
    "gn:country_code":"IT",
    "gn:dem":259,
    "gn:feature_class":"P",
    "gn:feature_code":"PPL",
    "gn:name":"Taiano",
    "gn:population":102,
    "gn:timezone":"Europe/Rome",
    "iso:country":"IT",
    "wof:name":"Taiano",
    "wof:placetype":"locality",
    "wof:population":102
},
  "geometry": {"coordinates":[11.35916,43.7311],"type":"Point"}
}