{
  "type": "Feature",
  "properties": {
    "gn:admin1_code":"15",
    "gn:admin2_code":"ME",
    "gn:admin3_code":"83066.0",
    "gn:asciiname":"Gallo",
    "gn:country_code":"IT",
    "gn:dem":211,
    "gn:feature_class":"P",
    "gn:feature_code":"PPL",
    "gn:name":"Gallo",
    "gn:population":171,
    "gn:timezone":"Europe/Rome",
    "iso:country":"IT",
    "name:ceb_x_preferred":[
        "Gallo"
    ],
    "name:ces_x_preferred":[
        "Gallo"
    ],
    "name:deu_x_preferred":[
        "Gallo"
    ],
    "name:fra_x_preferred":[
        "Gallo"
    ],
    "name:ita_x_preferred":[
        "Gallo"
    ],
    "name:nld_x_preferred":[
        "Gallo"
    ],
    "name:por_x_preferred":[
        "Gallo"
    ],
    "name:rus_x_preferred":[
        "\u0413\u0430\u043b\u043b\u043e"
    ],
    "name:slk_x_preferred":[
        "Gallo"
    ],
    "name:spa_x_preferred":[
        "Gallo"
    ],
    "name:srp_x_preferred":[
        "Galo"
    ],
    "name:swe_x_preferred":[
        "Gallo"
    ],
    "wof:name":"Gallo",
    "wof:placetype":"locality",
    "wof:population":171
},
  "geometry": {"coordinates":[14.96501,38.11944],"type":"Point"}
}