{
  "type": "Feature",
  "properties": {
    "gn:admin1_code":"20",
    "gn:admin2_code":"RO",
    "gn:admin3_code":"29047.0",
    "gn:asciiname":"Vallalta sul Tartaro",
    "gn:country_code":"IT",
    "gn:dem":8,
    "gn:feature_class":"P",
    "gn:feature_code":"PPL",
    "gn:name":"Vallalta sul Tartaro",
    "gn:population":38,
    "gn:timezone":"Europe/Rome",
    "iso:country":"IT",
    "wof:name":"Vallalta sul Tartaro",
    "wof:placetype":"locality",
    "wof:population":38
},
  "geometry": {"coordinates":[11.47923,45.02836],"type":"Point"}
}