{
  "type": "Feature",
  "properties": {
    "gn:admin1_code":"4.0",
    "gn:admin2_code":"SA",
    "gn:admin3_code":"65124.0",
    "gn:asciiname":"Stazione di San Mauro la Bruca",
    "gn:country_code":"IT",
    "gn:dem":80,
    "gn:feature_class":"P",
    "gn:feature_code":"PPL",
    "gn:name":"Stazione di San Mauro la Bruca",
    "gn:population":5,
    "gn:timezone":"Europe/Rome",
    "iso:country":"IT",
    "wof:name":"Stazione di San Mauro la Bruca",
    "wof:placetype":"locality",
    "wof:population":5
},
  "geometry": {"coordinates":[15.2997,40.09735],"type":"Point"}
}