{
  "type": "Feature",
  "properties": {
    "gn:admin1_code":"8.0",
    "gn:admin2_code":"GE",
    "gn:admin3_code":"10046.0",
    "gn:asciiname":"Pagana",
    "gn:country_code":"IT",
    "gn:dem":7,
    "gn:feature_class":"P",
    "gn:feature_code":"PPL",
    "gn:name":"Pagana",
    "gn:population":0,
    "gn:timezone":"Europe/Rome",
    "iso:country":"IT",
    "wof:name":"Pagana",
    "wof:placetype":"locality"
},
  "geometry": {"coordinates":[9.22488,44.33897],"type":"Point"}
}