{
  "type": "Feature",
  "properties": {
    "gn:admin1_code":"9.0",
    "gn:admin2_code":"BS",
    "gn:admin3_code":"17173.0",
    "gn:asciiname":"San Zeno Due",
    "gn:country_code":"IT",
    "gn:dem":105,
    "gn:feature_class":"P",
    "gn:feature_code":"PPLL",
    "gn:name":"San Zeno Due",
    "gn:population":0,
    "gn:timezone":"Europe/Rome",
    "iso:country":"IT",
    "wof:name":"San Zeno Due",
    "wof:placetype":"locality"
},
  "geometry": {"coordinates":[10.21106,45.47853],"type":"Point"}
}