{
  "type": "Feature",
  "properties": {
    "gn:admin1_code":"8.0",
    "gn:admin2_code":"GE",
    "gn:admin3_code":"10059.0",
    "gn:asciiname":"Montedomenico",
    "gn:country_code":"IT",
    "gn:dem":227,
    "gn:elevation":"198.0",
    "gn:feature_class":"P",
    "gn:feature_code":"PPL",
    "gn:name":"Montedomenico",
    "gn:population":222,
    "gn:timezone":"Europe/Rome",
    "iso:country":"IT",
    "wof:name":"Montedomenico",
    "wof:placetype":"locality",
    "wof:population":222
},
  "geometry": {"coordinates":[9.4365,44.3114],"type":"Point"}
}