{
  "type": "Feature",
  "properties": {
    "gn:admin1_code":"6",
    "gn:admin2_code":"PN",
    "gn:admin3_code":"93029.0",
    "gn:asciiname":"Case Zanella",
    "gn:country_code":"IT",
    "gn:dem":14,
    "gn:feature_class":"P",
    "gn:feature_code":"PPL",
    "gn:name":"Case Zanella",
    "gn:population":16,
    "gn:timezone":"Europe/Rome",
    "iso:country":"IT",
    "wof:name":"Case Zanella",
    "wof:placetype":"locality",
    "wof:population":16
},
  "geometry": {"coordinates":[12.62759,45.89874],"type":"Point"}
}