{
  "type": "Feature",
  "properties": {
    "gn:admin1_code":"20",
    "gn:admin2_code":"PD",
    "gn:admin3_code":"28019.0",
    "gn:asciiname":"Ferro",
    "gn:country_code":"IT",
    "gn:dem":19,
    "gn:feature_class":"P",
    "gn:feature_code":"PPL",
    "gn:name":"Ferro",
    "gn:population":74,
    "gn:timezone":"Europe/Rome",
    "iso:country":"IT",
    "name:ceb_x_preferred":[
        "Ferro"
    ],
    "name:ces_x_preferred":[
        "Ferro"
    ],
    "name:deu_x_preferred":[
        "Ferro"
    ],
    "name:fin_x_preferred":[
        "Ferro"
    ],
    "name:fra_x_preferred":[
        "Ferro"
    ],
    "name:ina_x_preferred":[
        "Ferro"
    ],
    "name:ita_x_preferred":[
        "Ferro"
    ],
    "name:nld_x_preferred":[
        "Ferro"
    ],
    "name:pol_x_preferred":[
        "Ferro"
    ],
    "name:por_x_preferred":[
        "Ferro"
    ],
    "name:swe_x_preferred":[
        "Ferro"
    ],
    "name:ukr_x_preferred":[
        "\u0424\u0435\u0440\u0440\u043e"
    ],
    "wof:name":"Ferro",
    "wof:placetype":"locality",
    "wof:population":74
},
  "geometry": {"coordinates":[11.94663,45.56392],"type":"Point"}
}