{
  "type": "Feature",
  "properties": {
    "gn:admin1_code":"19",
    "gn:admin2_code":"AO",
    "gn:admin3_code":"7003.0",
    "gn:asciiname":"Vignole",
    "gn:country_code":"IT",
    "gn:dem":896,
    "gn:feature_class":"P",
    "gn:feature_code":"PPL",
    "gn:name":"Vignole",
    "gn:population":36,
    "gn:timezone":"Europe/Rome",
    "iso:country":"IT",
    "name:ceb_x_preferred":[
        "Le Vignole"
    ],
    "name:deu_x_preferred":[
        "Vignole"
    ],
    "name:fra_x_preferred":[
        "Vignole"
    ],
    "name:hrv_x_preferred":[
        "Vignole"
    ],
    "name:hun_x_preferred":[
        "Le Vignole-sziget"
    ],
    "name:ita_x_preferred":[
        "Vignole"
    ],
    "name:lat_x_preferred":[
        "Biniola"
    ],
    "name:pol_x_preferred":[
        "Vignole"
    ],
    "name:spa_x_preferred":[
        "Vignole"
    ],
    "name:vec_x_preferred":[
        "Vigno\u0142e"
    ],
    "wof:name":"Vignole",
    "wof:placetype":"locality",
    "wof:population":36
},
  "geometry": {"coordinates":[7.29701,45.74323],"type":"Point"}
}