{
  "type": "Feature",
  "properties": {
    "iso:country":"IT",
    "name:ita_x_preferred":[
        "Porta Vigentina"
    ],
    "name:lmo_x_preferred":[
        "Porta Vigentina"
    ],
    "wof:name":"Porta Vigentina",
    "wof:placetype":"neighbourhood"
},
  "geometry": {"coordinates":[9.1951394165914,45.45045674466252],"type":"Point"}
}