{
  "type": "Feature",
  "properties": {
    "gn:admin1_code":"10",
    "gn:admin2_code":"PU",
    "gn:admin3_code":"41026.0",
    "gn:asciiname":"Trebbio",
    "gn:country_code":"IT",
    "gn:dem":516,
    "gn:feature_class":"P",
    "gn:feature_code":"PPL",
    "gn:name":"Trebbio",
    "gn:population":34,
    "gn:timezone":"Europe/Rome",
    "iso:country":"IT",
    "wof:name":"Trebbio",
    "wof:placetype":"locality",
    "wof:population":34
},
  "geometry": {"coordinates":[12.50892,43.85624],"type":"Point"}
}