{
  "type": "Feature",
  "properties": {
    "gn:admin1_code":"20",
    "gn:admin2_code":"TV",
    "gn:admin3_code":"26093.0",
    "gn:asciiname":"Madonna della Salute",
    "gn:country_code":"IT",
    "gn:dem":74,
    "gn:feature_class":"P",
    "gn:feature_code":"PPL",
    "gn:name":"Madonna della Salute",
    "gn:population":31,
    "gn:timezone":"Europe/Rome",
    "iso:country":"IT",
    "wof:name":"Madonna della Salute",
    "wof:placetype":"locality",
    "wof:population":31
},
  "geometry": {"coordinates":[12.13494,45.76058],"type":"Point"}
}