{
  "type": "Feature",
  "properties": {
    "gn:admin1_code":"20",
    "gn:admin2_code":"PD",
    "gn:admin3_code":"28062.0",
    "gn:asciiname":"Barchessa",
    "gn:country_code":"IT",
    "gn:dem":5,
    "gn:feature_class":"P",
    "gn:feature_code":"PPL",
    "gn:name":"Barchessa",
    "gn:population":30,
    "gn:timezone":"Europe/Rome",
    "iso:country":"IT",
    "wof:name":"Barchessa",
    "wof:placetype":"locality",
    "wof:population":30
},
  "geometry": {"coordinates":[11.55972,45.14437],"type":"Point"}
}