{
  "type": "Feature",
  "properties": {
    "gn:admin1_code":"12",
    "gn:admin2_code":"TO",
    "gn:admin3_code":"1184.0",
    "gn:asciiname":"Bressi",
    "gn:country_code":"IT",
    "gn:dem":784,
    "gn:feature_class":"P",
    "gn:feature_code":"PPLL",
    "gn:name":"Bressi",
    "gn:population":9,
    "gn:timezone":"Europe/Rome",
    "iso:country":"IT",
    "wof:name":"Bressi",
    "wof:placetype":"locality",
    "wof:population":9
},
  "geometry": {"coordinates":[7.1976,44.96938],"type":"Point"}
}