{
  "type": "Feature",
  "properties": {
    "gn:admin1_code":"4",
    "gn:admin2_code":"SA",
    "gn:admin3_code":"65146.0",
    "gn:asciiname":"Cappello",
    "gn:country_code":"IT",
    "gn:dem":491,
    "gn:feature_class":"P",
    "gn:feature_code":"PPL",
    "gn:name":"Cappello",
    "gn:population":104,
    "gn:timezone":"Europe/Rome",
    "iso:country":"IT",
    "wof:name":"Cappello",
    "wof:placetype":"locality",
    "wof:population":104
},
  "geometry": {"coordinates":[15.49998,40.39443],"type":"Point"}
}