{
  "type": "Feature",
  "properties": {
    "gn:admin1_code":"18",
    "gn:admin2_code":"PG",
    "gn:admin3_code":"54045.0",
    "gn:asciiname":"Caso",
    "gn:country_code":"IT",
    "gn:dem":703,
    "gn:feature_class":"P",
    "gn:feature_code":"PPL",
    "gn:name":"Caso",
    "gn:population":34,
    "gn:timezone":"Europe/Rome",
    "iso:country":"IT",
    "name:ara_x_preferred":[
        "\u0643\u0627\u0633\u0648"
    ],
    "name:arg_x_preferred":[
        "Casu"
    ],
    "name:ast_x_preferred":[
        "Casu"
    ],
    "name:cat_x_preferred":[
        "Casu"
    ],
    "name:ceb_x_preferred":[
        "Caso"
    ],
    "name:deu_x_preferred":[
        "Caso"
    ],
    "name:eus_x_preferred":[
        "Caso"
    ],
    "name:fas_x_preferred":[
        "\u06a9\u0627\u0633\u0648"
    ],
    "name:fra_x_preferred":[
        "Caso"
    ],
    "name:glg_x_preferred":[
        "Casu"
    ],
    "name:hun_x_preferred":[
        "Caso"
    ],
    "name:ina_x_preferred":[
        "Caso"
    ],
    "name:ita_x_preferred":[
        "Caso"
    ],
    "name:msa_x_preferred":[
        "Caso"
    ],
    "name:nld_x_preferred":[
        "Caso"
    ],
    "name:oci_x_preferred":[
        "Caso"
    ],
    "name:pam_x_preferred":[
        "Caso"
    ],
    "name:pol_x_preferred":[
        "Caso"
    ],
    "name:por_x_preferred":[
        "Caso"
    ],
    "name:ron_x_preferred":[
        "Caso"
    ],
    "name:rus_x_preferred":[
        "\u041a\u0430\u0441\u043e"
    ],
    "name:spa_x_preferred":[
        "Caso"
    ],
    "name:sqi_x_preferred":[
        "Caso"
    ],
    "name:tur_x_preferred":[
        "Caso"
    ],
    "name:ukr_x_preferred":[
        "\u041a\u0430\u0441\u043e"
    ],
    "name:uzb_x_preferred":[
        "Caso"
    ],
    "name:vie_x_preferred":[
        "Caso"
    ],
    "name:war_x_preferred":[
        "Caso"
    ],
    "wof:name":"Caso",
    "wof:placetype":"locality",
    "wof:population":34
},
  "geometry": {"coordinates":[12.85682,42.70831],"type":"Point"}
}