{
  "type": "Feature",
  "properties": {
    "gn:gn_country":"IT",
    "gn:gn_fcode":"PPLA3",
    "gn:gn_pop":1005,
    "gn:population":278,
    "iso:country":"IT",
    "name:ara_x_preferred":[
        "\u0643\u0648\u0646\u0632\u0627\u0646\u0648"
    ],
    "name:bel_x_preferred":[
        "\u041a\u0430\u043d\u0446\u0430\u043d\u0430"
    ],
    "name:bul_x_preferred":[
        "\u041a\u043e\u043d\u0446\u0430\u043d\u043e"
    ],
    "name:cat_x_preferred":[
        "Conzano"
    ],
    "name:deu_x_preferred":[
        "Conzano"
    ],
    "name:eng_x_preferred":[
        "Conzano"
    ],
    "name:epo_x_preferred":[
        "Conzano"
    ],
    "name:eus_x_preferred":[
        "Conzano"
    ],
    "name:fas_x_preferred":[
        "\u06a9\u0648\u0646\u062a\u0633\u0627\u0646\u0648"
    ],
    "name:fra_x_preferred":[
        "Conzano"
    ],
    "name:hun_x_preferred":[
        "Conzano"
    ],
    "name:hye_x_preferred":[
        "\u053f\u0578\u0576\u0581\u0561\u0576\u0578"
    ],
    "name:ind_x_preferred":[
        "Conzano"
    ],
    "name:ita_x_preferred":[
        "Conzano"
    ],
    "name:jav_x_preferred":[
        "Conzano"
    ],
    "name:jpn_x_preferred":[
        "\u30b3\u30f3\u30c4\u30a1\u30fc\u30ce"
    ],
    "name:kaz_x_preferred":[
        "\u041a\u043e\u043d\u0446\u0430\u043d\u043e"
    ],
    "name:lat_x_preferred":[
        "Contianum"
    ],
    "name:lmo_x_preferred":[
        "Conzano"
    ],
    "name:msa_x_preferred":[
        "Conzano"
    ],
    "name:nan_x_preferred":[
        "Conzano"
    ],
    "name:nap_x_preferred":[
        "Conzano"
    ],
    "name:nld_x_preferred":[
        "Conzano"
    ],
    "name:oci_x_preferred":[
        "Conzano"
    ],
    "name:pms_x_preferred":[
        "Consan"
    ],
    "name:pol_x_preferred":[
        "Conzano"
    ],
    "name:por_x_preferred":[
        "Conzano"
    ],
    "name:ron_x_preferred":[
        "Conzano"
    ],
    "name:rus_x_preferred":[
        "\u041a\u043e\u043d\u0446\u0430\u043d\u043e"
    ],
    "name:scn_x_preferred":[
        "Conzano"
    ],
    "name:spa_x_preferred":[
        "Conzano"
    ],
    "name:srp_x_preferred":[
        "Conzano"
    ],
    "name:tgl_x_preferred":[
        "Conzano"
    ],
    "name:ukr_x_preferred":[
        "\u041a\u043e\u043d\u0446\u0430\u043d\u043e"
    ],
    "name:uzb_x_preferred":[
        "Conzano"
    ],
    "name:vie_x_preferred":[
        "Conzano"
    ],
    "name:vol_x_preferred":[
        "Conzano"
    ],
    "name:war_x_preferred":[
        "Conzano"
    ],
    "name:zho_x_preferred":[
        "\u5b54\u624e\u8bfa"
    ],
    "qs_pg:aaroncc":"IT",
    "qs_pg:gn_country":"IT",
    "qs_pg:gn_fcode":"PPLA3",
    "qs_pg:gn_pop":1005,
    "qs_pg:name":"Conzano",
    "qs_pg:name_adm0":"Italia",
    "qs_pg:name_adm1":"Piemonte",
    "qs_pg:photos":48,
    "qs_pg:photos_1k":10,
    "qs_pg:photos_9k":1,
    "qs_pg:photos_9r":2,
    "qs_pg:photos_all":48,
    "qs_pg:photos_sr":2,
    "qs_pg:pop_sr":3,
    "qs_pg:qs_pg_placetype":"locality",
    "qs_pg:qs_pg_placetype_gp":"Town",
    "qs_pg:woe_adm0":23424853,
    "woe:adm0_id":23424853,
    "woe:name_adm0":"Italia",
    "woe:name_adm1":"Piemonte",
    "woe:placetype":"Town",
    "wof:name":"Conzano",
    "wof:placetype":"locality",
    "wof:population":278
},
  "geometry": {"coordinates":[8.45394,45.02045],"type":"Point"}
}