{
  "type": "Feature",
  "properties": {
    "gn:admin1_code":"15",
    "gn:admin2_code":"ME",
    "gn:admin3_code":"83081.0",
    "gn:asciiname":"Spaditta",
    "gn:country_code":"IT",
    "gn:dem":626,
    "gn:feature_class":"P",
    "gn:feature_code":"PPL",
    "gn:name":"Spaditta",
    "gn:population":30,
    "gn:timezone":"Europe/Rome",
    "iso:country":"IT",
    "wof:name":"Spaditta",
    "wof:placetype":"locality",
    "wof:population":30
},
  "geometry": {"coordinates":[14.96366,38.02684],"type":"Point"}
}