{
  "type": "Feature",
  "properties": {
    "gn:admin1_code":"5.0",
    "gn:admin2_code":"RN",
    "gn:admin3_code":"99011.0",
    "gn:asciiname":"Ca' Fabbro II",
    "gn:country_code":"IT",
    "gn:dem":67,
    "gn:feature_class":"P",
    "gn:feature_code":"PPL",
    "gn:name":"Ca' Fabbro II",
    "gn:population":37,
    "gn:timezone":"Europe/Rome",
    "iso:country":"IT",
    "wof:name":"Ca' Fabbro II",
    "wof:placetype":"locality",
    "wof:population":37
},
  "geometry": {"coordinates":[12.6645,43.9128],"type":"Point"}
}