{
  "type": "Feature",
  "properties": {
    "gn:admin1_code":"10.0",
    "gn:admin2_code":"PU",
    "gn:admin3_code":"41059.0",
    "gn:asciiname":"Zona Produttiva Mercatale",
    "gn:country_code":"IT",
    "gn:dem":211,
    "gn:feature_class":"P",
    "gn:feature_code":"PPL",
    "gn:name":"Zona Produttiva Mercatale",
    "gn:population":51,
    "gn:timezone":"Europe/Rome",
    "iso:country":"IT",
    "wof:name":"Zona Produttiva Mercatale",
    "wof:placetype":"locality",
    "wof:population":51
},
  "geometry": {"coordinates":[12.49318,43.79297],"type":"Point"}
}