{
  "type": "Feature",
  "properties": {
    "gn:admin1_code":"7",
    "gn:admin2_code":"RI",
    "gn:admin3_code":"57042.0",
    "gn:asciiname":"Capitignano",
    "gn:country_code":"IT",
    "gn:dem":702,
    "gn:feature_class":"P",
    "gn:feature_code":"PPL",
    "gn:name":"Capitignano",
    "gn:population":21,
    "gn:timezone":"Europe/Rome",
    "iso:country":"IT",
    "name:ara_x_preferred":[
        "\u0643\u0627\u0628\u064a\u062a\u0646\u064a\u0627\u0646\u0648"
    ],
    "name:azb_x_preferred":[
        "\u06a9\u0627\u067e\u06cc\u062a\u06cc\u0646\u06cc\u0627\u0646\u0648"
    ],
    "name:bcl_x_preferred":[
        "Capitignano"
    ],
    "name:bel_x_preferred":[
        "\u041a\u0430\u043f\u0456\u0446\u0456\u043d\u2019\u044f\u043d\u0430"
    ],
    "name:bul_x_preferred":[
        "\u041a\u0430\u043f\u0438\u0442\u0438\u043d\u044f\u043d\u043e"
    ],
    "name:ceb_x_preferred":[
        "Capitignano"
    ],
    "name:deu_x_preferred":[
        "Capitignano"
    ],
    "name:epo_x_preferred":[
        "Capitignano"
    ],
    "name:eus_x_preferred":[
        "Capitignano"
    ],
    "name:fas_x_preferred":[
        "\u06a9\u0627\u067e\u06cc\u062a\u06cc\u0646\u06cc\u0627\u0646\u0648"
    ],
    "name:fra_x_preferred":[
        "Capitignano"
    ],
    "name:hun_x_preferred":[
        "Capitignano"
    ],
    "name:hye_x_preferred":[
        "\u053f\u0561\u057a\u056b\u057f\u056b\u0576\u0575\u0561\u0576\u0578"
    ],
    "name:ina_x_preferred":[
        "Capitignano"
    ],
    "name:ita_x_preferred":[
        "Capitignano"
    ],
    "name:jpn_x_preferred":[
        "\u30ab\u30d4\u30c6\u30a3\u30cb\u30e3\u30fc\u30ce"
    ],
    "name:kaz_x_preferred":[
        "\u041a\u0430\u043f\u0438\u0442\u0438\u043d\u044c\u044f\u043d\u043e"
    ],
    "name:kor_x_preferred":[
        "\uce74\ud53c\ud2f0\ub0d0\ub178"
    ],
    "name:lat_x_preferred":[
        "Capitignanum"
    ],
    "name:lmo_x_preferred":[
        "Capitignano"
    ],
    "name:msa_x_preferred":[
        "Capitignano"
    ],
    "name:nap_x_preferred":[
        "Capitignano"
    ],
    "name:nld_x_preferred":[
        "Capitignano"
    ],
    "name:pms_x_preferred":[
        "Capitignano"
    ],
    "name:pol_x_preferred":[
        "Capitignano"
    ],
    "name:por_x_preferred":[
        "Capitignano"
    ],
    "name:ron_x_preferred":[
        "Capitignano"
    ],
    "name:rus_x_preferred":[
        "\u041a\u0430\u043f\u0438\u0442\u0438\u043d\u044c\u044f\u043d\u043e"
    ],
    "name:scn_x_preferred":[
        "Capitignanu"
    ],
    "name:spa_x_preferred":[
        "Capitignano"
    ],
    "name:srp_x_preferred":[
        "\u041a\u0430\u043f\u0438\u0442\u0438\u045a\u0430\u043d\u043e"
    ],
    "name:ukr_x_preferred":[
        "\u041a\u0430\u043f\u0456\u0442\u0456\u043d\u044c\u044f\u043d\u043e"
    ],
    "name:uzb_x_preferred":[
        "Capitignano"
    ],
    "name:vie_x_preferred":[
        "Capitignano"
    ],
    "name:vol_x_preferred":[
        "Capitignano"
    ],
    "name:war_x_preferred":[
        "Capitignano"
    ],
    "name:zho_x_preferred":[
        "\u5361\u76ae\u8482\u5c3c\u4e9a\u8bfa"
    ],
    "wof:name":"Capitignano",
    "wof:placetype":"locality",
    "wof:population":21
},
  "geometry": {"coordinates":[12.82687,42.28346],"type":"Point"}
}