{
  "type": "Feature",
  "properties": {
    "gn:admin1_code":"16",
    "gn:admin2_code":"FI",
    "gn:admin3_code":"48036.0",
    "gn:asciiname":"Bombone",
    "gn:country_code":"IT",
    "gn:dem":287,
    "gn:feature_class":"P",
    "gn:feature_code":"PPL",
    "gn:name":"Bombone",
    "gn:population":323,
    "gn:timezone":"Europe/Rome",
    "iso:country":"IT",
    "wof:name":"Bombone",
    "wof:placetype":"locality",
    "wof:population":323
},
  "geometry": {"coordinates":[11.43881,43.72913],"type":"Point"}
}