{
  "type": "Feature",
  "properties": {
    "gn:admin1_code":"10.0",
    "gn:admin2_code":"FM",
    "gn:admin3_code":"109037.0",
    "gn:asciiname":"Cascinare",
    "gn:country_code":"IT",
    "gn:dem":127,
    "gn:feature_class":"P",
    "gn:feature_code":"PPL",
    "gn:name":"Cascinare",
    "gn:population":1089,
    "gn:timezone":"Europe/Rome",
    "iso:country":"IT",
    "wof:name":"Cascinare",
    "wof:placetype":"locality",
    "wof:population":1089
},
  "geometry": {"coordinates":[13.71181,43.26434],"type":"Point"}
}