{
  "type": "Feature",
  "properties": {
    "gn:admin1_code":"1.0",
    "gn:admin2_code":"AQ",
    "gn:admin3_code":"66101.0",
    "gn:asciiname":"Pie la Costa",
    "gn:country_code":"IT",
    "gn:dem":785,
    "gn:feature_class":"P",
    "gn:feature_code":"PPL",
    "gn:name":"Pi\u00e8 la Costa",
    "gn:population":254,
    "gn:timezone":"Europe/Rome",
    "iso:country":"IT",
    "name:ceb_x_preferred":[
        "Pi\u00e8 la Costa"
    ],
    "name:ita_x_preferred":[
        "Pi\u00e9 La Costa"
    ],
    "name:nld_x_preferred":[
        "Pi\u00e9 La Costa"
    ],
    "name:srp_x_preferred":[
        "\u041f\u0458\u0435 \u043b\u0430 \u041a\u043e\u0437\u0442\u0430"
    ],
    "wof:name":"Pie la Costa",
    "wof:placetype":"locality",
    "wof:population":254
},
  "geometry": {"coordinates":[13.27251,42.31864],"type":"Point"}
}