{
  "type": "Feature",
  "properties": {
    "gn:admin1_code":"9",
    "gn:admin2_code":"MN",
    "gn:admin3_code":"20064.0",
    "gn:asciiname":"Vela",
    "gn:country_code":"IT",
    "gn:dem":13,
    "gn:feature_class":"P",
    "gn:feature_code":"PPL",
    "gn:name":"Vela",
    "gn:population":22,
    "gn:timezone":"Europe/Rome",
    "iso:country":"IT",
    "name:ara_x_preferred":[
        "\u0641\u064a\u0644\u0627"
    ],
    "name:arg_x_preferred":[
        "Vela"
    ],
    "name:ast_x_preferred":[
        "Vela"
    ],
    "name:bul_x_preferred":[
        "\u0412\u0435\u043b\u0430"
    ],
    "name:cat_x_preferred":[
        "Vela"
    ],
    "name:ceb_x_preferred":[
        "Vela"
    ],
    "name:ces_x_preferred":[
        "Vela"
    ],
    "name:deu_x_preferred":[
        "Vela"
    ],
    "name:fas_x_preferred":[
        "\u0628\u0627\u062f\u0628\u0627\u0646"
    ],
    "name:fin_x_preferred":[
        "Vela"
    ],
    "name:fra_x_preferred":[
        "Vela"
    ],
    "name:glg_x_preferred":[
        "Vela"
    ],
    "name:hrv_x_preferred":[
        "Vela"
    ],
    "name:hun_x_preferred":[
        "Vela"
    ],
    "name:ita_x_preferred":[
        "Vela"
    ],
    "name:nld_x_preferred":[
        "Vela"
    ],
    "name:nor_x_preferred":[
        "Vela"
    ],
    "name:pol_x_preferred":[
        "Vela"
    ],
    "name:por_x_preferred":[
        "Vela"
    ],
    "name:que_x_preferred":[
        "Vela"
    ],
    "name:rus_x_preferred":[
        "\u0412\u0435\u043b\u0430"
    ],
    "name:spa_x_preferred":[
        "Vela"
    ],
    "name:srp_x_preferred":[
        "Vela"
    ],
    "name:swe_x_preferred":[
        "Vela"
    ],
    "wof:name":"Vela",
    "wof:placetype":"locality",
    "wof:population":22
},
  "geometry": {"coordinates":[11.03664,45.07441],"type":"Point"}
}