{
  "type": "Feature",
  "properties": {
    "gn:admin1_code":"9",
    "gn:admin2_code":"MN",
    "gn:admin3_code":"20064.0",
    "gn:asciiname":"Vela",
    "gn:country_code":"IT",
    "gn:dem":13,
    "gn:feature_class":"P",
    "gn:feature_code":"PPL",
    "gn:name":"Vela",
    "gn:population":22,
    "gn:timezone":"Europe/Rome",
    "iso:country":"IT",
    "wof:name":"Vela",
    "wof:placetype":"locality",
    "wof:population":22
},
  "geometry": {"coordinates":[11.03664,45.07441],"type":"Point"}
}