{
  "type": "Feature",
  "properties": {
    "gn:admin1_code":"12",
    "gn:admin2_code":"AL",
    "gn:admin3_code":"6101.0",
    "gn:asciiname":"Corso Roma",
    "gn:country_code":"IT",
    "gn:dem":186,
    "gn:feature_class":"P",
    "gn:feature_code":"PPL",
    "gn:name":"Corso Roma",
    "gn:population":208,
    "gn:timezone":"Europe/Rome",
    "iso:country":"IT",
    "wof:name":"Corso Roma",
    "wof:placetype":"locality",
    "wof:population":208
},
  "geometry": {"coordinates":[8.98251,44.88584],"type":"Point"}
}