{
  "type": "Feature",
  "properties": {
    "gn:admin1_code":"16.0",
    "gn:admin2_code":"GR",
    "gn:admin3_code":"53020.0",
    "gn:asciiname":"Vallerona",
    "gn:country_code":"IT",
    "gn:dem":574,
    "gn:elevation":"569.0",
    "gn:feature_class":"P",
    "gn:feature_code":"PPL",
    "gn:name":"Vallerona",
    "gn:population":243,
    "gn:timezone":"Europe/Rome",
    "iso:country":"IT",
    "name:ceb_x_preferred":[
        "Vallerona"
    ],
    "name:ita_x_preferred":[
        "Vallerona"
    ],
    "name:nld_x_preferred":[
        "Vallerona"
    ],
    "name:srp_x_preferred":[
        "\u0412\u0430\u043b\u0435\u0440\u043e\u043d\u0430"
    ],
    "wof:name":"Vallerona",
    "wof:placetype":"locality",
    "wof:population":243
},
  "geometry": {"coordinates":[11.47041,42.79276],"type":"Point"}
}