{
  "type": "Feature",
  "properties": {
    "gn:admin1_code":"16.0",
    "gn:admin2_code":"GR",
    "gn:admin3_code":"53020.0",
    "gn:asciiname":"Vallerona",
    "gn:country_code":"IT",
    "gn:dem":574,
    "gn:elevation":"569.0",
    "gn:feature_class":"P",
    "gn:feature_code":"PPL",
    "gn:name":"Vallerona",
    "gn:population":243,
    "gn:timezone":"Europe/Rome",
    "iso:country":"IT",
    "wof:name":"Vallerona",
    "wof:placetype":"locality",
    "wof:population":243
},
  "geometry": {"coordinates":[11.47041,42.79276],"type":"Point"}
}