{
  "type": "Feature",
  "properties": {
    "gn:admin1_code":"12",
    "gn:admin2_code":"VB",
    "gn:admin3_code":"103017.0",
    "gn:asciiname":"Socraggio",
    "gn:country_code":"IT",
    "gn:dem":515,
    "gn:feature_class":"P",
    "gn:feature_code":"PPLL",
    "gn:name":"Socraggio",
    "gn:population":9,
    "gn:timezone":"Europe/Rome",
    "iso:country":"IT",
    "wof:name":"Socraggio",
    "wof:placetype":"locality",
    "wof:population":9
},
  "geometry": {"coordinates":[8.62263,46.06447],"type":"Point"}
}