{
  "type": "Feature",
  "properties": {
    "gn:admin1_code":"12",
    "gn:admin2_code":"NO",
    "gn:admin3_code":"3154.0",
    "gn:asciiname":"Cascina Chisvoi",
    "gn:country_code":"IT",
    "gn:dem":256,
    "gn:feature_class":"P",
    "gn:feature_code":"PPL",
    "gn:name":"Cascina Chisvoi",
    "gn:population":42,
    "gn:timezone":"Europe/Rome",
    "iso:country":"IT",
    "wof:name":"Cascina Chisvoi",
    "wof:placetype":"locality",
    "wof:population":42
},
  "geometry": {"coordinates":[8.65149,45.66977],"type":"Point"}
}