{
  "type": "Feature",
  "properties": {
    "gn:admin1_code":"16.0",
    "gn:admin2_code":"PI",
    "gn:admin3_code":"50040.0",
    "gn:asciiname":"Gello",
    "gn:country_code":"IT",
    "gn:dem":98,
    "gn:feature_class":"P",
    "gn:feature_code":"PPL",
    "gn:name":"Gello",
    "gn:population":0,
    "gn:timezone":"Europe/Rome",
    "iso:country":"IT",
    "name:deu_x_preferred":[
        "Gello"
    ],
    "name:ita_x_preferred":[
        "Gell\u00f2"
    ],
    "name:rus_x_preferred":[
        "\u0413\u0435\u043b\u043b\u043e"
    ],
    "name:ukr_x_preferred":[
        "\u0413\u0435\u043b\u043b\u043e"
    ],
    "wof:name":"Gello",
    "wof:placetype":"locality"
},
  "geometry": {"coordinates":[10.56667,43.51667],"type":"Point"}
}