{
  "type": "Feature",
  "properties": {
    "gn:admin1_code":"3",
    "gn:admin2_code":"CS",
    "gn:admin3_code":"78062.0",
    "gn:asciiname":"Fontanella",
    "gn:country_code":"IT",
    "gn:dem":658,
    "gn:feature_class":"P",
    "gn:feature_code":"PPL",
    "gn:name":"Fontanella",
    "gn:population":57,
    "gn:timezone":"Europe/Rome",
    "iso:country":"IT",
    "name:bel_x_preferred":[
        "\u0424\u0430\u043d\u0442\u0430\u043d\u0435\u043b\u0430"
    ],
    "name:cat_x_preferred":[
        "Fontanella"
    ],
    "name:ceb_x_preferred":[
        "Fontanella"
    ],
    "name:deu_x_preferred":[
        "Fontanella"
    ],
    "name:epo_x_preferred":[
        "Fontanella"
    ],
    "name:fra_x_preferred":[
        "Fontanella"
    ],
    "name:hun_x_preferred":[
        "Fontanella"
    ],
    "name:ita_x_preferred":[
        "Fontanella"
    ],
    "name:lmo_x_preferred":[
        "Fontan\u00e8la"
    ],
    "name:nds_x_preferred":[
        "Fontanella"
    ],
    "name:nld_x_preferred":[
        "Fontanella"
    ],
    "name:pol_x_preferred":[
        "Fontanella"
    ],
    "name:slk_x_preferred":[
        "Fontanella"
    ],
    "name:srp_x_preferred":[
        "Fontanela"
    ],
    "name:swe_x_preferred":[
        "Fontanella"
    ],
    "name:vol_x_preferred":[
        "Fontanella"
    ],
    "wof:name":"Fontanella",
    "wof:placetype":"locality",
    "wof:population":57
},
  "geometry": {"coordinates":[16.15864,39.16022],"type":"Point"}
}