{
  "type": "Feature",
  "properties": {
    "gn:country":"IT",
    "gn:fcode":"PPL",
    "gn:population":0,
    "iso:country":"IT",
    "name:cat_x_preferred":[
        "Savoulx"
    ],
    "name:ceb_x_preferred":[
        "Savoulx"
    ],
    "name:ces_x_preferred":[
        "Savoulx"
    ],
    "name:dan_x_preferred":[
        "Savoulx"
    ],
    "name:eng_x_preferred":[
        "Savoulx"
    ],
    "name:eus_x_preferred":[
        "Savoulx"
    ],
    "name:fin_x_preferred":[
        "Savoulx"
    ],
    "name:fra_x_preferred":[
        "Savoulx"
    ],
    "name:hun_x_preferred":[
        "Savoulx"
    ],
    "name:ind_x_preferred":[
        "Savoulx"
    ],
    "name:ita_x_preferred":[
        "Savoulx"
    ],
    "name:jpn_x_preferred":[
        "\u30b5\u30f4\u30a9\u30fc\u30eb\u30af\u30b9"
    ],
    "name:nld_x_preferred":[
        "Savoulx"
    ],
    "name:nno_x_preferred":[
        "Savoulx"
    ],
    "name:nob_x_preferred":[
        "Savoulx"
    ],
    "name:oci_x_preferred":[
        "Savoulx"
    ],
    "name:pol_x_preferred":[
        "Savoulx"
    ],
    "name:por_x_preferred":[
        "Savoulx"
    ],
    "name:ron_x_preferred":[
        "Savoulx"
    ],
    "name:slk_x_preferred":[
        "Savoulx"
    ],
    "name:slv_x_preferred":[
        "Savoulx"
    ],
    "name:spa_x_preferred":[
        "Savoulx"
    ],
    "name:srp_x_preferred":[
        "Savoulx"
    ],
    "name:swe_x_preferred":[
        "Savoulx"
    ],
    "name:tgl_x_preferred":[
        "Savoulx"
    ],
    "name:tur_x_preferred":[
        "Savoulx"
    ],
    "name:und_x_variant":[
        "Savoule"
    ],
    "name:war_x_preferred":[
        "Savoulx"
    ],
    "qs_pg:aaroncc":"IT",
    "qs_pg:gn_country":"IT",
    "qs_pg:gn_fcode":"PPL",
    "qs_pg:gn_pop":0,
    "qs_pg:name":"Savoulx",
    "qs_pg:name_adm0":"Italia",
    "qs_pg:name_adm1":"Piemonte",
    "qs_pg:photos":16,
    "qs_pg:photos_1k":3,
    "qs_pg:photos_9k":1,
    "qs_pg:photos_9r":1,
    "qs_pg:photos_all":16,
    "qs_pg:photos_sr":1,
    "qs_pg:pop_sr":0,
    "qs_pg:qs_pg_placetype":"locality",
    "qs_pg:qs_pg_placetype_gp":"Town",
    "qs_pg:woe_adm0":23424853,
    "woe:adm0_id":23424853,
    "woe:name_adm0":"Italia",
    "woe:name_adm1":"Piemonte",
    "woe:placetype":"Town",
    "wof:name":"Savoulx",
    "wof:placetype":"locality",
    "wof:population":392
},
  "geometry": {"coordinates":[6.78333,45.05],"type":"Point"}
}