{
  "type": "Feature",
  "properties": {
    "gn:admin1_code":"16",
    "gn:admin2_code":"PT",
    "gn:admin3_code":"47014.0",
    "gn:asciiname":"Fabbiana",
    "gn:country_code":"IT",
    "gn:dem":393,
    "gn:feature_class":"P",
    "gn:feature_code":"PPL",
    "gn:name":"Fabbiana",
    "gn:population":52,
    "gn:timezone":"Europe/Rome",
    "iso:country":"IT",
    "wof:name":"Fabbiana",
    "wof:placetype":"locality",
    "wof:population":52
},
  "geometry": {"coordinates":[10.90291,44.00203],"type":"Point"}
}