{
  "type": "Feature",
  "properties": {
    "gn:admin1_code":"12",
    "gn:admin2_code":"NO",
    "gn:admin3_code":"3103.0",
    "gn:asciiname":"Poggio Alto",
    "gn:country_code":"IT",
    "gn:dem":710,
    "gn:feature_class":"P",
    "gn:feature_code":"PPLL",
    "gn:name":"Poggio Alto",
    "gn:population":6,
    "gn:timezone":"Europe/Rome",
    "iso:country":"IT",
    "wof:name":"Poggio Alto",
    "wof:placetype":"locality",
    "wof:population":6
},
  "geometry": {"coordinates":[8.5141,45.82287],"type":"Point"}
}