{
  "type": "Feature",
  "properties": {
    "gn:admin1_code":"5.0",
    "gn:admin2_code":"MO",
    "gn:admin3_code":"36012.0",
    "gn:asciiname":"Villa Magri",
    "gn:country_code":"IT",
    "gn:dem":8,
    "gn:feature_class":"P",
    "gn:feature_code":"PPL",
    "gn:name":"Villa Magri",
    "gn:population":0,
    "gn:timezone":"Europe/Rome",
    "iso:country":"IT",
    "wof:name":"Villa Magri",
    "wof:placetype":"locality"
},
  "geometry": {"coordinates":[11.28333,44.86667],"type":"Point"}
}