{
  "type": "Feature",
  "properties": {
    "gn:admin1_code":"6.0",
    "gn:admin2_code":"UD",
    "gn:admin3_code":"30004.0",
    "gn:asciiname":"Beligna",
    "gn:country_code":"IT",
    "gn:dem":-1,
    "gn:elevation":"1.0",
    "gn:feature_class":"P",
    "gn:feature_code":"PPL",
    "gn:name":"Beligna",
    "gn:population":29,
    "gn:timezone":"Europe/Rome",
    "iso:country":"IT",
    "wof:name":"Beligna",
    "wof:placetype":"locality",
    "wof:population":29
},
  "geometry": {"coordinates":[13.3756,45.75689000000001],"type":"Point"}
}