{
  "type": "Feature",
  "properties": {
    "gn:admin1_code":"3.0",
    "gn:admin2_code":"RC",
    "gn:admin3_code":"80082.0",
    "gn:asciiname":"Marina di Sant'Ilario dello Ionio",
    "gn:country_code":"IT",
    "gn:dem":9,
    "gn:feature_class":"P",
    "gn:feature_code":"PPL",
    "gn:name":"Marina di Sant'Ilario dello Ionio",
    "gn:population":538,
    "gn:timezone":"Europe/Rome",
    "iso:country":"IT",
    "wof:name":"Marina di Sant'Ilario dello Ionio",
    "wof:placetype":"locality",
    "wof:population":538
},
  "geometry": {"coordinates":[16.22639,38.19818],"type":"Point"}
}