{
  "type": "Feature",
  "properties": {
    "gn:admin1_code":"20",
    "gn:admin2_code":"TV",
    "gn:admin3_code":"26023.0",
    "gn:asciiname":"Zona Industriale Sud",
    "gn:country_code":"IT",
    "gn:dem":140,
    "gn:feature_class":"P",
    "gn:feature_code":"PPL",
    "gn:name":"Zona Industriale Sud",
    "gn:population":147,
    "gn:timezone":"Europe/Rome",
    "iso:country":"IT",
    "wof:name":"Zona Industriale Sud",
    "wof:placetype":"locality",
    "wof:population":147
},
  "geometry": {"coordinates":[12.00963,45.81161],"type":"Point"}
}