{
  "type": "Feature",
  "properties": {
    "gn:admin1_code":"9",
    "gn:admin2_code":"BG",
    "gn:admin3_code":"16159.0",
    "gn:asciiname":"Casarola",
    "gn:country_code":"IT",
    "gn:dem":548,
    "gn:feature_class":"P",
    "gn:feature_code":"PPLL",
    "gn:name":"Casarola",
    "gn:population":10,
    "gn:timezone":"Europe/Rome",
    "iso:country":"IT",
    "wof:name":"Casarola",
    "wof:placetype":"locality",
    "wof:population":10
},
  "geometry": {"coordinates":[10.03566,45.73254],"type":"Point"}
}