{
  "type": "Feature",
  "properties": {
    "gn:admin1_code":"16",
    "gn:admin2_code":"FI",
    "gn:admin3_code":"48036.0",
    "gn:asciiname":"La Felce",
    "gn:country_code":"IT",
    "gn:dem":261,
    "gn:feature_class":"P",
    "gn:feature_code":"PPL",
    "gn:name":"La Felce",
    "gn:population":79,
    "gn:timezone":"Europe/Rome",
    "iso:country":"IT",
    "wof:name":"La Felce",
    "wof:placetype":"locality",
    "wof:population":79
},
  "geometry": {"coordinates":[11.41004,43.70068],"type":"Point"}
}