{
  "type": "Feature",
  "properties": {
    "gn:admin1_code":"20",
    "gn:admin2_code":"PD",
    "gn:admin3_code":"28009.0",
    "gn:asciiname":"San Biagio",
    "gn:country_code":"IT",
    "gn:dem":48,
    "gn:feature_class":"P",
    "gn:feature_code":"PPL",
    "gn:name":"San Biagio",
    "gn:population":32,
    "gn:timezone":"Europe/Rome",
    "iso:country":"IT",
    "name:bre_x_preferred":[
        "San Biagio"
    ],
    "name:ceb_x_preferred":[
        "San Biagio"
    ],
    "name:fra_x_preferred":[
        "San Biagio"
    ],
    "name:ita_x_preferred":[
        "San Biagio"
    ],
    "name:nap_x_preferred":[
        "San Biagio"
    ],
    "name:pms_x_preferred":[
        "San Biagio"
    ],
    "name:por_x_preferred":[
        "San Biagio"
    ],
    "name:srp_x_preferred":[
        "San Bja\u0111o"
    ],
    "name:swe_x_preferred":[
        "San Biagio"
    ],
    "wof:name":"San Biagio",
    "wof:placetype":"locality",
    "wof:population":32
},
  "geometry": {"coordinates":[11.69084,45.27445],"type":"Point"}
}