{
  "type": "Feature",
  "properties": {
    "gn:admin1_code":"19",
    "gn:admin2_code":"AO",
    "gn:admin3_code":"7014.0",
    "gn:asciiname":"Sizan",
    "gn:country_code":"IT",
    "gn:dem":685,
    "gn:feature_class":"P",
    "gn:feature_code":"PPL",
    "gn:name":"Sizan",
    "gn:population":22,
    "gn:timezone":"Europe/Rome",
    "iso:country":"IT",
    "name:ara_x_preferred":[
        "\u0633\u064a\u0632\u0627\u0646"
    ],
    "name:ceb_x_preferred":[
        "S\u012bz\u0101n"
    ],
    "name:fas_x_preferred":[
        "\u0633\u06cc\u0632\u0627\u0646"
    ],
    "name:swe_x_preferred":[
        "S\u012bz\u0101n"
    ],
    "wof:name":"Sizan",
    "wof:placetype":"locality",
    "wof:population":22
},
  "geometry": {"coordinates":[7.71308,45.69195],"type":"Point"}
}