{
  "type": "Feature",
  "properties": {
    "gn:admin1_code":"12",
    "gn:admin2_code":"AL",
    "gn:admin3_code":"6172.0",
    "gn:asciiname":"Ronchetti",
    "gn:country_code":"IT",
    "gn:dem":198,
    "gn:feature_class":"P",
    "gn:feature_code":"PPL",
    "gn:name":"Ronchetti",
    "gn:population":13,
    "gn:timezone":"Europe/Rome",
    "iso:country":"IT",
    "wof:name":"Ronchetti",
    "wof:placetype":"locality",
    "wof:population":13
},
  "geometry": {"coordinates":[8.42862,44.67778],"type":"Point"}
}