{
  "type": "Feature",
  "properties": {
    "gn:gn_country":"IT",
    "gn:gn_fcode":"PPLA3",
    "gn:gn_pop":272,
    "gn:population":268,
    "iso:country":"IT",
    "name:arg_x_preferred":[
        "Tinnura"
    ],
    "name:bel_x_preferred":[
        "\u0422\u044b\u043d\u0443\u0440\u0430"
    ],
    "name:bul_x_preferred":[
        "\u0422\u0438\u043d\u0443\u0440\u0430"
    ],
    "name:cat_x_preferred":[
        "Tinnura"
    ],
    "name:deu_x_preferred":[
        "Tinnura"
    ],
    "name:eng_x_preferred":[
        "Tinnura"
    ],
    "name:epo_x_preferred":[
        "Tinnura"
    ],
    "name:eus_x_preferred":[
        "Tinnura"
    ],
    "name:fas_x_preferred":[
        "\u062a\u06cc\u0646\u0648\u0631\u0627"
    ],
    "name:fra_x_preferred":[
        "Tinnura"
    ],
    "name:hun_x_preferred":[
        "Tinnura"
    ],
    "name:hye_x_preferred":[
        "\u054f\u056b\u0576\u0576\u0578\u0582\u0580\u0561"
    ],
    "name:ita_x_preferred":[
        "Tinnura"
    ],
    "name:jpn_x_preferred":[
        "\u30c6\u30a3\u30f3\u30cc\u30fc\u30e9"
    ],
    "name:kaz_x_preferred":[
        "\u0422\u0438\u043d\u043d\u0443\u0440\u0430"
    ],
    "name:lat_x_preferred":[
        "Tinnura"
    ],
    "name:lmo_x_preferred":[
        "Tinnura"
    ],
    "name:msa_x_preferred":[
        "Tinnura"
    ],
    "name:nan_x_preferred":[
        "Tinnura"
    ],
    "name:nap_x_preferred":[
        "Tinnura"
    ],
    "name:nld_x_preferred":[
        "Tinnura"
    ],
    "name:pms_x_preferred":[
        "Tinnura"
    ],
    "name:pol_x_preferred":[
        "Tinnura"
    ],
    "name:por_x_preferred":[
        "Tinnura"
    ],
    "name:ron_x_preferred":[
        "Tinnura"
    ],
    "name:rus_x_preferred":[
        "\u0422\u0438\u043d\u043d\u0443\u0440\u0430"
    ],
    "name:scn_x_preferred":[
        "Tinnura"
    ],
    "name:spa_x_preferred":[
        "Tinnura"
    ],
    "name:srd_x_preferred":[
        "Tinnura"
    ],
    "name:srp_x_preferred":[
        "Tinnura"
    ],
    "name:tgl_x_preferred":[
        "Tinnura"
    ],
    "name:ukr_x_preferred":[
        "\u0422\u0456\u043d\u043d\u0443\u0440\u0430"
    ],
    "name:uzb_x_preferred":[
        "Tinnura"
    ],
    "name:vie_x_preferred":[
        "Tinnura"
    ],
    "name:vol_x_preferred":[
        "Tinnura"
    ],
    "name:war_x_preferred":[
        "Tinnura"
    ],
    "name:zho_x_preferred":[
        "\u5ef7\u52aa\u62c9"
    ],
    "qs_pg:aaroncc":"IT",
    "qs_pg:gn_country":"IT",
    "qs_pg:gn_fcode":"PPLA3",
    "qs_pg:gn_pop":272,
    "qs_pg:name":"Tinnura",
    "qs_pg:name_adm0":"Italia",
    "qs_pg:name_adm1":"Sardegna",
    "qs_pg:photos":135,
    "qs_pg:photos_1k":27,
    "qs_pg:photos_9k":1,
    "qs_pg:photos_9r":3,
    "qs_pg:photos_all":135,
    "qs_pg:photos_sr":3,
    "qs_pg:pop_sr":2,
    "qs_pg:qs_pg_placetype":"locality",
    "qs_pg:qs_pg_placetype_gp":"Town",
    "qs_pg:woe_adm0":23424853,
    "woe:adm0_id":23424853,
    "woe:name_adm0":"Italia",
    "woe:name_adm1":"Sardegna",
    "woe:placetype":"Town",
    "wof:name":"Tinnura",
    "wof:placetype":"locality",
    "wof:population":268
},
  "geometry": {"coordinates":[8.54952,40.27015],"type":"Point"}
}