{
  "type": "Feature",
  "properties": {
    "gn:admin1_code":"12",
    "gn:admin2_code":"CN",
    "gn:admin3_code":"4197.0",
    "gn:asciiname":"Madonna delle Grazie",
    "gn:country_code":"IT",
    "gn:dem":691,
    "gn:feature_class":"P",
    "gn:feature_code":"PPLL",
    "gn:name":"Madonna delle Grazie",
    "gn:population":8,
    "gn:timezone":"Europe/Rome",
    "iso:country":"IT",
    "wof:name":"Madonna delle Grazie",
    "wof:placetype":"locality",
    "wof:population":8
},
  "geometry": {"coordinates":[7.4066,44.52466],"type":"Point"}
}