{
  "type": "Feature",
  "properties": {
    "iso:country":"IT",
    "name:eng_x_preferred":[
        "Entr\u00e8ves"
    ],
    "name:fra_x_preferred":[
        "Entr\u00e8ves"
    ],
    "name:hun_x_preferred":[
        "Entr\u00e8ves"
    ],
    "name:ita_x_preferred":[
        "Entr\u00e8ves"
    ],
    "name:lmo_x_preferred":[
        "Entr\u00e8ves"
    ],
    "name:nld_x_preferred":[
        "Entr\u00e8ves"
    ],
    "qs_pg:aaroncc":"IT",
    "qs_pg:name":"Entr\u00e8ves",
    "qs_pg:name_adm0":"Italia",
    "qs_pg:name_adm1":"Valle d'Aosta",
    "qs_pg:photos":82,
    "qs_pg:photos_1k":17,
    "qs_pg:photos_9k":1,
    "qs_pg:photos_9r":3,
    "qs_pg:photos_all":82,
    "qs_pg:photos_sr":3,
    "qs_pg:pop_sr":0,
    "qs_pg:qs_pg_placetype":"locality",
    "qs_pg:qs_pg_placetype_gp":"Town",
    "qs_pg:woe_adm0":23424853,
    "woe:adm0_id":23424853,
    "woe:name_adm0":"Italia",
    "woe:name_adm1":"Valle d'Aosta",
    "woe:placetype":"Town",
    "wof:name":"Entr\u00e8ves",
    "wof:placetype":"locality"
},
  "geometry": {"coordinates":[6.963036,45.814383],"type":"Point"}
}