{
  "type": "Feature",
  "properties": {
    "iso:country":"IT",
    "qs_pg:aaroncc":"IT",
    "qs_pg:name":"Santa Maria Della Carruba",
    "qs_pg:name_adm0":"Italia",
    "qs_pg:name_adm1":"Sicilia",
    "qs_pg:photos":396,
    "qs_pg:photos_1k":80,
    "qs_pg:photos_9k":2,
    "qs_pg:photos_9r":5,
    "qs_pg:photos_all":396,
    "qs_pg:photos_sr":6,
    "qs_pg:pop_sr":0,
    "qs_pg:qs_pg_placetype":"locality",
    "qs_pg:qs_pg_placetype_gp":"Town",
    "qs_pg:woe_adm0":23424853,
    "woe:adm0_id":23424853,
    "woe:name_adm0":"Italia",
    "woe:name_adm1":"Sicilia",
    "woe:placetype":"Town",
    "wof:name":"Santa Maria Della Carruba",
    "wof:placetype":"locality"
},
  "geometry": {"coordinates":[15.115288,37.5251535],"type":"Point"}
}