{
  "type": "Feature",
  "properties": {
    "gn:admin1_code":"15",
    "gn:admin2_code":"ME",
    "gn:admin3_code":"83015.0",
    "gn:asciiname":"Trupiano",
    "gn:country_code":"IT",
    "gn:dem":336,
    "gn:feature_class":"P",
    "gn:feature_code":"PPL",
    "gn:name":"Trupiano",
    "gn:population":21,
    "gn:timezone":"Europe/Rome",
    "iso:country":"IT",
    "wof:name":"Trupiano",
    "wof:placetype":"locality",
    "wof:population":21
},
  "geometry": {"coordinates":[15.2524,37.85202],"type":"Point"}
}