{
  "type": "Feature",
  "properties": {
    "gn:admin1_code":"1.0",
    "gn:admin2_code":"CH",
    "gn:admin3_code":"69086.0",
    "gn:asciiname":"Sant'Apollinare",
    "gn:country_code":"IT",
    "gn:dem":150,
    "gn:elevation":"149.0",
    "gn:feature_class":"P",
    "gn:feature_code":"PPL",
    "gn:name":"Sant'Apollinare",
    "gn:population":765,
    "gn:timezone":"Europe/Rome",
    "iso:country":"IT",
    "wof:name":"Sant'Apollinare",
    "wof:placetype":"locality",
    "wof:population":765
},
  "geometry": {"coordinates":[14.40969,42.29657],"type":"Point"}
}