{
  "type": "Feature",
  "properties": {
    "gn:admin1_code":"1.0",
    "gn:admin2_code":"CH",
    "gn:admin3_code":"69086.0",
    "gn:asciiname":"Sant'Apollinare",
    "gn:country_code":"IT",
    "gn:dem":150,
    "gn:elevation":"149.0",
    "gn:feature_class":"P",
    "gn:feature_code":"PPL",
    "gn:name":"Sant'Apollinare",
    "gn:population":765,
    "gn:timezone":"Europe/Rome",
    "iso:country":"IT",
    "name:bcl_x_preferred":[
        "Sant'Apollinare"
    ],
    "name:bul_x_preferred":[
        "\u0421\u0430\u043d\u0442'\u0410\u043f\u043e\u043b\u0438\u043d\u0430\u0440\u0435"
    ],
    "name:ceb_x_preferred":[
        "Sant'Apollinare"
    ],
    "name:deu_x_preferred":[
        "Sant\u2019Apollinare"
    ],
    "name:epo_x_preferred":[
        "Sant'Apollinare"
    ],
    "name:eus_x_preferred":[
        "Sant'Apollinare"
    ],
    "name:fra_x_preferred":[
        "Sant'Apollinare"
    ],
    "name:hun_x_preferred":[
        "Sant\u2019Apollinare"
    ],
    "name:hye_x_preferred":[
        "\u054d\u0561\u0576\u057f \u0531\u057a\u0578\u056c\u056b\u0576\u0561\u0580\u0565"
    ],
    "name:ina_x_preferred":[
        "Sant'Apollinare"
    ],
    "name:ita_x_preferred":[
        "Sant'Apollinare"
    ],
    "name:jpn_x_preferred":[
        "\u30b5\u30f3\u30bf\u30dd\u30c3\u30ea\u30ca\u30fc\u30ec"
    ],
    "name:kaz_x_preferred":[
        "\u0421\u0430\u043d\u0442'\u0410\u043f\u043e\u043b\u043b\u0438\u043d\u0430\u0440\u0435"
    ],
    "name:kor_x_preferred":[
        "\uc0b0\ud0c0\ud3f4\ub9ac\ub098\ub808"
    ],
    "name:lmo_x_preferred":[
        "Sant'Apollinare"
    ],
    "name:msa_x_preferred":[
        "Sant'Apollinare"
    ],
    "name:nap_x_preferred":[
        "Sant'Apollinare"
    ],
    "name:nld_x_preferred":[
        "Sant'Apollinare"
    ],
    "name:pms_x_preferred":[
        "Sant'Apollinare"
    ],
    "name:pol_x_preferred":[
        "Sant\u2019Apollinare"
    ],
    "name:por_x_preferred":[
        "Sant'Apollinare"
    ],
    "name:ron_x_preferred":[
        "Sant'Apollinare"
    ],
    "name:rus_x_preferred":[
        "\u0421\u0430\u043d\u0442-\u0410\u043f\u043e\u043b\u043b\u0438\u043d\u0430\u0440\u0435"
    ],
    "name:spa_x_preferred":[
        "Sant'Apollinare"
    ],
    "name:srp_x_preferred":[
        "\u0421\u0430\u043d\u0442'\u0410\u043f\u043e\u043b\u0438\u043d\u0430\u0440\u0435"
    ],
    "name:ukr_x_preferred":[
        "\u0421\u0430\u043d\u0442'\u0410\u043f\u043e\u043b\u043b\u0456\u043d\u0430\u0440\u0435"
    ],
    "name:uzb_x_preferred":[
        "Sant'Apollinare"
    ],
    "name:vie_x_preferred":[
        "Sant'Apollinare"
    ],
    "name:vol_x_preferred":[
        "Sant'Apollinare"
    ],
    "name:war_x_preferred":[
        "Sant'Apollinare"
    ],
    "name:zho_x_preferred":[
        "\u5723\u963f\u6ce2\u5229\u7eb3\u96f7"
    ],
    "wof:name":"Sant'Apollinare",
    "wof:placetype":"locality",
    "wof:population":765
},
  "geometry": {"coordinates":[14.40969,42.29657],"type":"Point"}
}