{
  "type": "Feature",
  "properties": {
    "gn:admin1_code":"14",
    "gn:admin2_code":"NU",
    "gn:admin3_code":"91044.0",
    "gn:asciiname":"Zona Industriale Tossilo",
    "gn:country_code":"IT",
    "gn:dem":417,
    "gn:feature_class":"P",
    "gn:feature_code":"PPLL",
    "gn:name":"Zona Industriale Tossilo",
    "gn:population":8,
    "gn:timezone":"Europe/Rome",
    "iso:country":"IT",
    "wof:name":"Zona Industriale Tossilo",
    "wof:placetype":"locality",
    "wof:population":8
},
  "geometry": {"coordinates":[8.77982,40.23637],"type":"Point"}
}