{
  "type": "Feature",
  "properties": {
    "gn:admin1_code":"5.0",
    "gn:admin2_code":"RE",
    "gn:admin3_code":"35033.0",
    "gn:asciiname":"San Maurizio",
    "gn:country_code":"IT",
    "gn:dem":53,
    "gn:feature_class":"P",
    "gn:feature_code":"PPL",
    "gn:name":"San Maurizio",
    "gn:population":0,
    "gn:timezone":"Europe/Rome",
    "iso:country":"IT",
    "name:ceb_x_preferred":[
        "San Maurizio"
    ],
    "name:ita_x_preferred":[
        "San Maurizio"
    ],
    "name:rus_x_preferred":[
        "\u0421\u0430\u043d-\u041c\u0430\u0443\u0440\u0438\u0446\u0438\u043e"
    ],
    "name:srp_x_preferred":[
        "San Maurizio"
    ],
    "name:swe_x_preferred":[
        "San Maurizio"
    ],
    "wof:name":"San Maurizio",
    "wof:placetype":"locality"
},
  "geometry": {"coordinates":[10.66996,44.68458],"type":"Point"}
}