{
  "type": "Feature",
  "properties": {
    "gn:admin1_code":"17",
    "gn:admin2_code":"BZ",
    "gn:admin3_code":"21117.0",
    "gn:asciiname":"Tolpei",
    "gn:country_code":"IT",
    "gn:dem":1508,
    "gn:feature_class":"P",
    "gn:feature_code":"PPL",
    "gn:name":"Tolpei",
    "gn:population":30,
    "gn:timezone":"Europe/Rome",
    "iso:country":"IT",
    "wof:name":"Tolpei",
    "wof:placetype":"locality",
    "wof:population":30
},
  "geometry": {"coordinates":[11.93387,46.66011],"type":"Point"}
}