{
  "type": "Feature",
  "properties": {
    "iso:country":"IT",
    "qs:a0":"Italia",
    "qs:a1":"*Verbano-Cusio-Ossola",
    "qs:a1r":"0Piemonte",
    "qs:adm0":"Italia",
    "qs:la_lc":"*",
    "qs:level":"locality",
    "qs:loc":"Antrogna",
    "qs:loc_alt":"Antrogna",
    "qs:pop":0,
    "qs:type":"buffered point",
    "wof:name":"Antrogna",
    "wof:placetype":"locality"
},
  "geometry": {"coordinates":[8.17,46.004169],"type":"Point"}
}