{
  "type": "Feature",
  "properties": {
    "gn:admin1_code":"18.0",
    "gn:admin2_code":"PG",
    "gn:admin3_code":"54035.0",
    "gn:asciiname":"Biselli",
    "gn:cc2":"IT",
    "gn:country_code":"IT",
    "gn:dem":581,
    "gn:feature_class":"P",
    "gn:feature_code":"PPL",
    "gn:name":"Biselli",
    "gn:population":0,
    "gn:timezone":"Europe/Rome",
    "iso:country":"IT",
    "name:und_x_variant":[
        "Biselli Argentigli",
        "Biselli"
    ],
    "wof:name":"Biselli",
    "wof:placetype":"locality"
},
  "geometry": {"coordinates":[12.97975,42.79065],"type":"Point"}
}