{
  "type": "Feature",
  "properties": {
    "gn:admin1_code":"4",
    "gn:admin2_code":"BN",
    "gn:admin3_code":"62008.0",
    "gn:asciiname":"Mosti",
    "gn:country_code":"IT",
    "gn:dem":360,
    "gn:feature_class":"P",
    "gn:feature_code":"PPL",
    "gn:name":"Mosti",
    "gn:population":37,
    "gn:timezone":"Europe/Rome",
    "iso:country":"IT",
    "wof:name":"Mosti",
    "wof:placetype":"locality",
    "wof:population":37
},
  "geometry": {"coordinates":[14.79779,41.18022],"type":"Point"}
}