{
  "type": "Feature",
  "properties": {
    "gn:admin1_code":"7",
    "gn:admin2_code":"VT",
    "gn:admin3_code":"56039.0",
    "gn:asciiname":"Colle Salomonio",
    "gn:country_code":"IT",
    "gn:dem":244,
    "gn:feature_class":"P",
    "gn:feature_code":"PPL",
    "gn:name":"Colle Salomonio",
    "gn:population":92,
    "gn:timezone":"Europe/Rome",
    "iso:country":"IT",
    "wof:name":"Colle Salomonio",
    "wof:placetype":"locality",
    "wof:population":92
},
  "geometry": {"coordinates":[12.31047,42.23209],"type":"Point"}
}