{
  "type": "Feature",
  "properties": {
    "gn:admin1_code":"5",
    "gn:admin2_code":"PR",
    "gn:admin3_code":"34026.0",
    "gn:asciiname":"Pratopiano",
    "gn:country_code":"IT",
    "gn:dem":702,
    "gn:feature_class":"P",
    "gn:feature_code":"PPL",
    "gn:name":"Pratopiano",
    "gn:population":48,
    "gn:timezone":"Europe/Rome",
    "iso:country":"IT",
    "wof:name":"Pratopiano",
    "wof:placetype":"locality",
    "wof:population":48
},
  "geometry": {"coordinates":[10.22928,44.45113],"type":"Point"}
}