{
  "type": "Feature",
  "properties": {
    "gn:admin1_code":"20",
    "gn:admin2_code":"PD",
    "gn:admin3_code":"28040.0",
    "gn:asciiname":"Grottarole",
    "gn:country_code":"IT",
    "gn:dem":7,
    "gn:feature_class":"P",
    "gn:feature_code":"PPL",
    "gn:name":"Grottarole",
    "gn:population":61,
    "gn:timezone":"Europe/Rome",
    "iso:country":"IT",
    "wof:name":"Grottarole",
    "wof:placetype":"locality",
    "wof:population":61
},
  "geometry": {"coordinates":[11.76247,45.29612],"type":"Point"}
}