{
  "type": "Feature",
  "properties": {
    "gn:admin1_code":"9",
    "gn:admin2_code":"SO",
    "gn:admin3_code":"14015.0",
    "gn:asciiname":"Vendolo",
    "gn:country_code":"IT",
    "gn:dem":482,
    "gn:feature_class":"P",
    "gn:feature_code":"PPL",
    "gn:name":"Vendolo",
    "gn:population":70,
    "gn:timezone":"Europe/Rome",
    "iso:country":"IT",
    "wof:name":"Vendolo",
    "wof:placetype":"locality",
    "wof:population":70
},
  "geometry": {"coordinates":[9.7927,46.17392],"type":"Point"}
}