{
  "type": "Feature",
  "properties": {
    "gn:admin1_code":"16.0",
    "gn:admin2_code":"FI",
    "gn:admin3_code":"48033.0",
    "gn:asciiname":"L'Opaco",
    "gn:country_code":"IT",
    "gn:dem":306,
    "gn:feature_class":"P",
    "gn:feature_code":"PPL",
    "gn:name":"L'Opaco",
    "gn:population":0,
    "gn:timezone":"Europe/Rome",
    "iso:country":"IT",
    "wof:name":"L'Opaco",
    "wof:placetype":"locality"
},
  "geometry": {"coordinates":[11.36667,43.85],"type":"Point"}
}