{
  "type": "Feature",
  "properties": {
    "gn:admin1_code":"9",
    "gn:admin2_code":"CR",
    "gn:admin3_code":"19071.0",
    "gn:asciiname":"San Paolo Ripa d'Oglio",
    "gn:country_code":"IT",
    "gn:dem":32,
    "gn:feature_class":"P",
    "gn:feature_code":"PPL",
    "gn:name":"San Paolo Ripa d'Oglio",
    "gn:population":69,
    "gn:timezone":"Europe/Rome",
    "iso:country":"IT",
    "wof:name":"San Paolo Ripa d'Oglio",
    "wof:placetype":"locality",
    "wof:population":69
},
  "geometry": {"coordinates":[10.40453,45.13156],"type":"Point"}
}