{
  "type": "Feature",
  "properties": {
    "gn:admin1_code":"6.0",
    "gn:admin2_code":"UD",
    "gn:admin3_code":"30083.0",
    "gn:asciiname":"Firmano",
    "gn:country_code":"IT",
    "gn:dem":118,
    "gn:elevation":"114.0",
    "gn:feature_class":"P",
    "gn:feature_code":"PPL",
    "gn:name":"Firmano",
    "gn:population":244,
    "gn:timezone":"Europe/Rome",
    "iso:country":"IT",
    "wof:name":"Firmano",
    "wof:placetype":"locality",
    "wof:population":244
},
  "geometry": {"coordinates":[13.40644,46.06197],"type":"Point"}
}