{
  "type": "Feature",
  "properties": {
    "gn:admin1_code":"5",
    "gn:admin2_code":"PR",
    "gn:admin3_code":"34035.0",
    "gn:asciiname":"Case Martini",
    "gn:country_code":"IT",
    "gn:dem":386,
    "gn:feature_class":"P",
    "gn:feature_code":"PPL",
    "gn:name":"Case Martini",
    "gn:population":16,
    "gn:timezone":"Europe/Rome",
    "iso:country":"IT",
    "wof:name":"Case Martini",
    "wof:placetype":"locality",
    "wof:population":16
},
  "geometry": {"coordinates":[9.96309,44.61496],"type":"Point"}
}