{
  "type": "Feature",
  "properties": {
    "gn:admin1_code":"12",
    "gn:admin2_code":"TO",
    "gn:admin3_code":"1208.0",
    "gn:asciiname":"Piana",
    "gn:country_code":"IT",
    "gn:dem":375,
    "gn:feature_class":"P",
    "gn:feature_code":"PPL",
    "gn:name":"Piana",
    "gn:population":25,
    "gn:timezone":"Europe/Rome",
    "iso:country":"IT",
    "name:ceb_x_preferred":[
        "Piana"
    ],
    "name:deu_x_preferred":[
        "Piana"
    ],
    "name:fra_x_preferred":[
        "Piana"
    ],
    "name:ita_x_preferred":[
        "Piana"
    ],
    "name:nld_x_preferred":[
        "Piana"
    ],
    "name:pol_x_preferred":[
        "Piana"
    ],
    "name:rus_x_preferred":[
        "\u041f\u044c\u044f\u043d\u0430"
    ],
    "name:spa_x_preferred":[
        "Piana"
    ],
    "name:srp_x_preferred":[
        "Pjana"
    ],
    "name:swe_x_preferred":[
        "Piana"
    ],
    "name:ukr_x_preferred":[
        "\u041f'\u044f\u043d\u0430"
    ],
    "wof:name":"Piana",
    "wof:placetype":"locality",
    "wof:population":25
},
  "geometry": {"coordinates":[7.78309,45.41407],"type":"Point"}
}