{
  "type": "Feature",
  "properties": {
    "gn:admin1_code":"20.0",
    "gn:admin2_code":"PD",
    "gn:admin3_code":"28086.0",
    "gn:asciiname":"Montecchia",
    "gn:country_code":"IT",
    "gn:dem":14,
    "gn:feature_class":"P",
    "gn:feature_code":"PPL",
    "gn:name":"Montecchia",
    "gn:population":0,
    "gn:timezone":"Europe/Rome",
    "iso:country":"IT",
    "wof:name":"Montecchia",
    "wof:placetype":"locality"
},
  "geometry": {"coordinates":[11.76667,45.38333],"type":"Point"}
}