{
  "type": "Feature",
  "properties": {
    "gn:admin1_code":"9",
    "gn:admin2_code":"PV",
    "gn:admin3_code":"18034.0",
    "gn:asciiname":"Cascina dell'Acqua",
    "gn:country_code":"IT",
    "gn:dem":102,
    "gn:feature_class":"P",
    "gn:feature_code":"PPL",
    "gn:name":"Cascina dell'Acqua",
    "gn:population":14,
    "gn:timezone":"Europe/Rome",
    "iso:country":"IT",
    "wof:name":"Cascina dell'Acqua",
    "wof:placetype":"locality",
    "wof:population":14
},
  "geometry": {"coordinates":[8.99289,45.31754],"type":"Point"}
}