{
  "type": "Feature",
  "properties": {
    "gn:admin1_code":"12",
    "gn:admin2_code":"TO",
    "gn:admin3_code":"1078.0",
    "gn:asciiname":"Fortemaggiore",
    "gn:country_code":"IT",
    "gn:dem":254,
    "gn:feature_class":"P",
    "gn:feature_code":"PPL",
    "gn:name":"Fortemaggiore",
    "gn:population":31,
    "gn:timezone":"Europe/Rome",
    "iso:country":"IT",
    "wof:name":"Fortemaggiore",
    "wof:placetype":"locality",
    "wof:population":31
},
  "geometry": {"coordinates":[7.8218,44.96717],"type":"Point"}
}