{
  "type": "Feature",
  "properties": {
    "gn:admin1_code":"1.0",
    "gn:admin2_code":"TE",
    "gn:admin3_code":"67014.0",
    "gn:asciiname":"Contrada Cancelli Zona Industriale N.2",
    "gn:country_code":"IT",
    "gn:dem":121,
    "gn:feature_class":"P",
    "gn:feature_code":"PPL",
    "gn:name":"Contrada Cancelli Zona Industriale N.2",
    "gn:population":25,
    "gn:timezone":"Europe/Rome",
    "iso:country":"IT",
    "wof:name":"Contrada Cancelli Zona Industriale N.2",
    "wof:placetype":"locality",
    "wof:population":25
},
  "geometry": {"coordinates":[13.93681,42.51429],"type":"Point"}
}