{
  "type": "Feature",
  "properties": {
    "gn:admin1_code":"20",
    "gn:admin2_code":"VR",
    "gn:admin3_code":"23018.0",
    "gn:asciiname":"Coliel",
    "gn:country_code":"IT",
    "gn:dem":751,
    "gn:feature_class":"P",
    "gn:feature_code":"PPL",
    "gn:name":"Coliel",
    "gn:population":26,
    "gn:timezone":"Europe/Rome",
    "iso:country":"IT",
    "wof:name":"Coliel",
    "wof:placetype":"locality",
    "wof:population":26
},
  "geometry": {"coordinates":[10.84536,45.64621],"type":"Point"}
}