{
  "type": "Feature",
  "properties": {
    "gn:admin1_code":"8",
    "gn:admin2_code":"SV",
    "gn:admin3_code":"9043.0",
    "gn:asciiname":"Varavo Superiore",
    "gn:country_code":"IT",
    "gn:dem":367,
    "gn:feature_class":"P",
    "gn:feature_code":"PPL",
    "gn:name":"Varavo Superiore",
    "gn:population":18,
    "gn:timezone":"Europe/Rome",
    "iso:country":"IT",
    "wof:name":"Varavo Superiore",
    "wof:placetype":"locality",
    "wof:population":18
},
  "geometry": {"coordinates":[8.05636,44.07324000000001],"type":"Point"}
}