{
  "type": "Feature",
  "properties": {
    "gn:admin1_code":"20",
    "gn:admin2_code":"VI",
    "gn:admin3_code":"24084.0",
    "gn:asciiname":"Alpe",
    "gn:country_code":"IT",
    "gn:dem":638,
    "gn:feature_class":"P",
    "gn:feature_code":"PPL",
    "gn:name":"Alpe",
    "gn:population":51,
    "gn:timezone":"Europe/Rome",
    "iso:country":"IT",
    "wof:name":"Alpe",
    "wof:placetype":"locality",
    "wof:population":51
},
  "geometry": {"coordinates":[11.24378,45.71023],"type":"Point"}
}