{
  "type": "Feature",
  "properties": {
    "gn:admin1_code":"9.0",
    "gn:admin2_code":"CO",
    "gn:admin3_code":"13187.0",
    "gn:asciiname":"Ponna di Mezzo",
    "gn:country_code":"IT",
    "gn:dem":764,
    "gn:elevation":"765.0",
    "gn:feature_class":"P",
    "gn:feature_code":"PPL",
    "gn:name":"Ponna di Mezzo",
    "gn:population":13,
    "gn:timezone":"Europe/Rome",
    "iso:country":"IT",
    "wof:name":"Ponna di Mezzo",
    "wof:placetype":"locality",
    "wof:population":13
},
  "geometry": {"coordinates":[9.08908,45.99028],"type":"Point"}
}