{
  "type": "Feature",
  "properties": {
    "gn:admin1_code":"9.0",
    "gn:admin2_code":"PV",
    "gn:admin3_code":"18086.0",
    "gn:asciiname":"Localita Rera",
    "gn:country_code":"IT",
    "gn:dem":88,
    "gn:feature_class":"P",
    "gn:feature_code":"PPL",
    "gn:name":"Localit\u00e0 Rera",
    "gn:population":349,
    "gn:timezone":"Europe/Rome",
    "iso:country":"IT",
    "name:und_x_variant":[
        "Localit\u00e0 Rera"
    ],
    "wof:name":"Localita Rera",
    "wof:placetype":"locality",
    "wof:population":349
},
  "geometry": {"coordinates":[9.07559,45.26024],"type":"Point"}
}