{
  "type": "Feature",
  "properties": {
    "gn:admin1_code":"6",
    "gn:admin2_code":"GO",
    "gn:admin3_code":"31018.0",
    "gn:asciiname":"Terranova",
    "gn:country_code":"IT",
    "gn:dem":-1,
    "gn:feature_class":"P",
    "gn:feature_code":"PPL",
    "gn:name":"Terranova",
    "gn:population":87,
    "gn:timezone":"Europe/Rome",
    "iso:country":"IT",
    "wof:name":"Terranova",
    "wof:placetype":"locality",
    "wof:population":87
},
  "geometry": {"coordinates":[13.46968,45.75762],"type":"Point"}
}