{
  "type": "Feature",
  "properties": {
    "gn:population":28,
    "iso:country":"IT",
    "name:fra_x_preferred":[
        "Piaggia"
    ],
    "name:hun_x_preferred":[
        "Piaggia"
    ],
    "name:ita_x_preferred":[
        "Piaggia"
    ],
    "name:nld_x_preferred":[
        "Piaggia"
    ],
    "name:srp_x_preferred":[
        "Piaggia"
    ],
    "qs:a0":"Italia",
    "qs:a1":"*Cuneo",
    "qs:a1r":"0Piemonte",
    "qs:adm0":"Italia",
    "qs:la_lc":"*",
    "qs:level":"locality",
    "qs:loc":"Piaggia",
    "qs:loc_alt":"Piaggia",
    "qs:pop":0,
    "qs:type":"buffered point",
    "wof:name":"Piaggia",
    "wof:placetype":"locality",
    "wof:population":28
},
  "geometry": {"coordinates":[7.75018,44.082679],"type":"Point"}
}