{
  "type": "Feature",
  "properties": {
    "gn:admin1_code":"8",
    "gn:admin2_code":"SV",
    "gn:admin3_code":"9056.0",
    "gn:asciiname":"Botta",
    "gn:country_code":"IT",
    "gn:dem":137,
    "gn:feature_class":"P",
    "gn:feature_code":"PPL",
    "gn:name":"Botta",
    "gn:population":69,
    "gn:timezone":"Europe/Rome",
    "iso:country":"IT",
    "wof:name":"Botta",
    "wof:placetype":"locality",
    "wof:population":69
},
  "geometry": {"coordinates":[8.41678,44.34475],"type":"Point"}
}