{
  "type": "Feature",
  "properties": {
    "gn:admin1_code":"16",
    "gn:admin2_code":"AR",
    "gn:admin3_code":"51037.0",
    "gn:asciiname":"Vogognano",
    "gn:country_code":"IT",
    "gn:dem":548,
    "gn:feature_class":"P",
    "gn:feature_code":"PPL",
    "gn:name":"Vogognano",
    "gn:population":51,
    "gn:timezone":"Europe/Rome",
    "iso:country":"IT",
    "wof:name":"Vogognano",
    "wof:placetype":"locality",
    "wof:population":51
},
  "geometry": {"coordinates":[11.88804,43.61096],"type":"Point"}
}