{
  "type": "Feature",
  "properties": {
    "gn:admin1_code":"3",
    "gn:admin2_code":"RC",
    "gn:admin3_code":"80024.0",
    "gn:asciiname":"Nucleo Palazzi",
    "gn:country_code":"IT",
    "gn:dem":16,
    "gn:feature_class":"P",
    "gn:feature_code":"PPL",
    "gn:name":"Nucleo Palazzi",
    "gn:population":41,
    "gn:timezone":"Europe/Rome",
    "iso:country":"IT",
    "wof:name":"Nucleo Palazzi",
    "wof:placetype":"locality",
    "wof:population":41
},
  "geometry": {"coordinates":[16.15781,38.12146],"type":"Point"}
}