{
  "type": "Feature",
  "properties": {
    "gn:admin1_code":"2",
    "gn:admin2_code":"PZ",
    "gn:admin3_code":"76076.0",
    "gn:asciiname":"Pierno",
    "gn:country_code":"IT",
    "gn:dem":959,
    "gn:feature_class":"P",
    "gn:feature_code":"PPL",
    "gn:name":"Pierno",
    "gn:population":67,
    "gn:timezone":"Europe/Rome",
    "iso:country":"IT",
    "wof:name":"Pierno",
    "wof:placetype":"locality",
    "wof:population":67
},
  "geometry": {"coordinates":[15.60489,40.79286],"type":"Point"}
}