{
  "type": "Feature",
  "properties": {
    "gn:admin1_code":"20",
    "gn:admin2_code":"VI",
    "gn:admin3_code":"24028.0",
    "gn:asciiname":"Brunetti",
    "gn:country_code":"IT",
    "gn:dem":60,
    "gn:feature_class":"P",
    "gn:feature_code":"PPL",
    "gn:name":"Brunetti",
    "gn:population":18,
    "gn:timezone":"Europe/Rome",
    "iso:country":"IT",
    "wof:name":"Brunetti",
    "wof:placetype":"locality",
    "wof:population":18
},
  "geometry": {"coordinates":[11.4208,45.57337],"type":"Point"}
}