{
  "type": "Feature",
  "properties": {
    "gn:admin1_code":"15",
    "gn:admin2_code":"PA",
    "gn:admin3_code":"82049.0",
    "gn:asciiname":"Celsa",
    "gn:country_code":"IT",
    "gn:dem":376,
    "gn:feature_class":"P",
    "gn:feature_code":"PPL",
    "gn:name":"Celsa",
    "gn:population":292,
    "gn:timezone":"Europe/Rome",
    "iso:country":"IT",
    "wof:name":"Celsa",
    "wof:placetype":"locality",
    "wof:population":292
},
  "geometry": {"coordinates":[13.26647,38.04694],"type":"Point"}
}