{
  "type": "Feature",
  "properties": {
    "gn:admin1_code":"6.0",
    "gn:admin2_code":"UD",
    "gn:admin3_code":"30092.0",
    "gn:asciiname":"Uccea",
    "gn:country_code":"IT",
    "gn:dem":655,
    "gn:elevation":"645.0",
    "gn:feature_class":"P",
    "gn:feature_code":"PPL",
    "gn:name":"Uccea",
    "gn:population":31,
    "gn:timezone":"Europe/Rome",
    "iso:country":"IT",
    "wof:name":"Uccea",
    "wof:placetype":"locality",
    "wof:population":31
},
  "geometry": {"coordinates":[13.39761,46.30722],"type":"Point"}
}