{
  "type": "Feature",
  "properties": {
    "gn:country":"IT",
    "gn:fcode":"PPL",
    "gn:population":0,
    "iso:country":"IT",
    "name:ceb_x_preferred":[
        "Pomonte"
    ],
    "name:eng_x_preferred":[
        "Pomonte"
    ],
    "name:fra_x_preferred":[
        "Pomonte"
    ],
    "name:hun_x_preferred":[
        "Pomonte"
    ],
    "name:ita_x_preferred":[
        "Pomonte"
    ],
    "name:nld_x_preferred":[
        "Pomonte"
    ],
    "name:spa_x_preferred":[
        "Pomonte"
    ],
    "name:srp_x_preferred":[
        "Pomonte"
    ],
    "name:und_x_variant":[
        "Poinonte"
    ],
    "qs_pg:aaroncc":"IT",
    "qs_pg:gn_country":"IT",
    "qs_pg:gn_fcode":"PPL",
    "qs_pg:gn_pop":0,
    "qs_pg:name":"Pomonte",
    "qs_pg:name_adm0":"Italia",
    "qs_pg:name_adm1":"Toscana",
    "qs_pg:photos":195,
    "qs_pg:photos_1k":40,
    "qs_pg:photos_9k":1,
    "qs_pg:photos_9r":4,
    "qs_pg:photos_all":195,
    "qs_pg:photos_sr":4,
    "qs_pg:pop_sr":0,
    "qs_pg:qs_pg_placetype":"locality",
    "qs_pg:qs_pg_placetype_gp":"Town",
    "qs_pg:woe_adm0":23424853,
    "woe:adm0_id":23424853,
    "woe:name_adm0":"Italia",
    "woe:name_adm1":"Toscana",
    "woe:placetype":"Town",
    "wof:name":"Pomonte",
    "wof:placetype":"locality",
    "wof:population":299
},
  "geometry": {"coordinates":[10.12115,42.74846],"type":"Point"}
}