{
  "type": "Feature",
  "properties": {
    "gn:admin1_code":"7.0",
    "gn:admin2_code":"FR",
    "gn:admin3_code":"60008.0",
    "gn:asciiname":"Tramonti II",
    "gn:country_code":"IT",
    "gn:dem":172,
    "gn:feature_class":"P",
    "gn:feature_code":"PPL",
    "gn:name":"Tramonti II",
    "gn:population":54,
    "gn:timezone":"Europe/Rome",
    "iso:country":"IT",
    "wof:name":"Tramonti II",
    "wof:placetype":"locality",
    "wof:population":54
},
  "geometry": {"coordinates":[13.58309,41.55767],"type":"Point"}
}