{
  "type": "Feature",
  "properties": {
    "gn:admin1_code":"20",
    "gn:admin2_code":"VR",
    "gn:admin3_code":"23093.0",
    "gn:asciiname":"Rigoni",
    "gn:country_code":"IT",
    "gn:dem":656,
    "gn:feature_class":"P",
    "gn:feature_code":"PPL",
    "gn:name":"Rigoni",
    "gn:population":18,
    "gn:timezone":"Europe/Rome",
    "iso:country":"IT",
    "wof:name":"Rigoni",
    "wof:placetype":"locality",
    "wof:population":18
},
  "geometry": {"coordinates":[11.21515,45.60303],"type":"Point"}
}