{
  "type": "Feature",
  "properties": {
    "gn:admin1_code":"6.0",
    "gn:admin2_code":"UD",
    "gn:admin3_code":"30015.0",
    "gn:asciiname":"Gorizzo",
    "gn:country_code":"IT",
    "gn:dem":31,
    "gn:elevation":"33.0",
    "gn:feature_class":"P",
    "gn:feature_code":"PPL",
    "gn:name":"Gorizzo",
    "gn:population":78,
    "gn:timezone":"Europe/Rome",
    "iso:country":"IT",
    "wof:name":"Gorizzo",
    "wof:placetype":"locality",
    "wof:population":78
},
  "geometry": {"coordinates":[12.95669,45.9309],"type":"Point"}
}