{
  "type": "Feature",
  "properties": {
    "gn:admin1_code":"9",
    "gn:admin2_code":"LO",
    "gn:admin3_code":"98050.0",
    "gn:asciiname":"Ranera",
    "gn:country_code":"IT",
    "gn:dem":72,
    "gn:feature_class":"P",
    "gn:feature_code":"PPL",
    "gn:name":"Ranera",
    "gn:population":233,
    "gn:timezone":"Europe/Rome",
    "iso:country":"IT",
    "wof:name":"Ranera",
    "wof:placetype":"locality",
    "wof:population":233
},
  "geometry": {"coordinates":[9.40758,45.21715],"type":"Point"}
}