{
  "type": "Feature",
  "properties": {
    "gn:admin1_code":"17.0",
    "gn:admin2_code":"BZ",
    "gn:admin3_code":"21086.0",
    "gn:asciiname":"San Martino",
    "gn:country_code":"IT",
    "gn:dem":1511,
    "gn:feature_class":"P",
    "gn:feature_code":"PPL",
    "gn:name":"San Martino",
    "gn:population":271,
    "gn:timezone":"Europe/Rome",
    "iso:country":"IT",
    "wof:name":"San Martino",
    "wof:placetype":"locality",
    "wof:population":271
},
  "geometry": {"coordinates":[11.41733,46.68884],"type":"Point"}
}