{
  "type": "Feature",
  "properties": {
    "gn:admin1_code":"12",
    "gn:admin2_code":"CN",
    "gn:admin3_code":"4029.0",
    "gn:asciiname":"Scatoleri",
    "gn:country_code":"IT",
    "gn:dem":287,
    "gn:feature_class":"P",
    "gn:feature_code":"PPL",
    "gn:name":"Scatoleri",
    "gn:population":41,
    "gn:timezone":"Europe/Rome",
    "iso:country":"IT",
    "wof:name":"Scatoleri",
    "wof:placetype":"locality",
    "wof:population":41
},
  "geometry": {"coordinates":[7.80306,44.68677],"type":"Point"}
}