{
  "type": "Feature",
  "properties": {
    "gn:admin1_code":"19",
    "gn:admin2_code":"AO",
    "gn:admin3_code":"7031.0",
    "gn:asciiname":"Pila",
    "gn:country_code":"IT",
    "gn:dem":1821,
    "gn:feature_class":"P",
    "gn:feature_code":"PPL",
    "gn:name":"Pila",
    "gn:population":79,
    "gn:timezone":"Europe/Rome",
    "iso:country":"IT",
    "name:bos_x_preferred":[
        "Pila"
    ],
    "name:cat_x_preferred":[
        "Pila"
    ],
    "name:ceb_x_preferred":[
        "Pila"
    ],
    "name:ces_x_preferred":[
        "Pila"
    ],
    "name:dan_x_preferred":[
        "Pila"
    ],
    "name:deu_x_preferred":[
        "Pila"
    ],
    "name:epo_x_preferred":[
        "Pila"
    ],
    "name:fin_x_preferred":[
        "Pila"
    ],
    "name:fra_x_preferred":[
        "Pila"
    ],
    "name:glg_x_preferred":[
        "Pila"
    ],
    "name:hun_x_preferred":[
        "Pila"
    ],
    "name:hye_x_preferred":[
        "\u054a\u056b\u056c\u0561"
    ],
    "name:ita_x_preferred":[
        "Pila"
    ],
    "name:lat_x_preferred":[
        "Pila"
    ],
    "name:nld_x_preferred":[
        "Pila"
    ],
    "name:nor_x_preferred":[
        "Pila"
    ],
    "name:pol_x_preferred":[
        "Pila"
    ],
    "name:por_x_preferred":[
        "Pila"
    ],
    "name:rus_x_preferred":[
        "\u041f\u0438\u043b\u0430"
    ],
    "name:sco_x_preferred":[
        "Pila"
    ],
    "name:slv_x_preferred":[
        "Pila"
    ],
    "name:spa_x_preferred":[
        "Pila"
    ],
    "name:srp_x_preferred":[
        "\u041f\u0438\u043b\u0430"
    ],
    "name:swe_x_preferred":[
        "Pila"
    ],
    "name:ukr_x_preferred":[
        "\u041f\u0456\u043b\u0430"
    ],
    "name:und_x_variant":[
        "Pila-Ciel Blu"
    ],
    "name:war_x_preferred":[
        "Pila"
    ],
    "wof:name":"Pila",
    "wof:placetype":"locality",
    "wof:population":79
},
  "geometry": {"coordinates":[7.30944,45.68487],"type":"Point"}
}