{
  "type": "Feature",
  "properties": {
    "gn:admin1_code":"19",
    "gn:admin2_code":"AO",
    "gn:admin3_code":"7031.0",
    "gn:asciiname":"Pila",
    "gn:country_code":"IT",
    "gn:dem":1821,
    "gn:feature_class":"P",
    "gn:feature_code":"PPL",
    "gn:name":"Pila",
    "gn:population":79,
    "gn:timezone":"Europe/Rome",
    "iso:country":"IT",
    "name:und_x_variant":[
        "Pila-Ciel Blu"
    ],
    "wof:name":"Pila",
    "wof:placetype":"locality",
    "wof:population":79
},
  "geometry": {"coordinates":[7.30944,45.68487],"type":"Point"}
}