{
  "type": "Feature",
  "properties": {
    "gn:admin1_code":"5",
    "gn:admin2_code":"MO",
    "gn:admin3_code":"36023.0",
    "gn:asciiname":"Ponte della Perlina",
    "gn:country_code":"IT",
    "gn:dem":29,
    "gn:feature_class":"P",
    "gn:feature_code":"PPL",
    "gn:name":"Ponte della Perlina",
    "gn:population":25,
    "gn:timezone":"Europe/Rome",
    "iso:country":"IT",
    "wof:name":"Ponte della Perlina",
    "wof:placetype":"locality",
    "wof:population":25
},
  "geometry": {"coordinates":[10.98085,44.66504000000001],"type":"Point"}
}