{
  "type": "Feature",
  "properties": {
    "gn:admin1_code":"9",
    "gn:admin2_code":"BG",
    "gn:admin3_code":"16133.0",
    "gn:asciiname":"Le Case",
    "gn:country_code":"IT",
    "gn:dem":146,
    "gn:feature_class":"P",
    "gn:feature_code":"PPL",
    "gn:name":"Le Case",
    "gn:population":23,
    "gn:timezone":"Europe/Rome",
    "iso:country":"IT",
    "wof:name":"Le Case",
    "wof:placetype":"locality",
    "wof:population":23
},
  "geometry": {"coordinates":[9.79563,45.56226],"type":"Point"}
}