{
  "type": "Feature",
  "properties": {
    "gn:admin1_code":"15",
    "gn:admin2_code":"AG",
    "gn:admin3_code":"84021.0",
    "gn:asciiname":"Nicolizia",
    "gn:country_code":"IT",
    "gn:dem":94,
    "gn:feature_class":"P",
    "gn:feature_code":"PPL",
    "gn:name":"Nicolizia",
    "gn:population":54,
    "gn:timezone":"Europe/Rome",
    "iso:country":"IT",
    "wof:name":"Nicolizia",
    "wof:placetype":"locality",
    "wof:population":54
},
  "geometry": {"coordinates":[13.90818,37.1013],"type":"Point"}
}