{
  "type": "Feature",
  "properties": {
    "gn:admin1_code":"4",
    "gn:admin2_code":"SA",
    "gn:admin3_code":"65146.0",
    "gn:asciiname":"Ischia",
    "gn:country_code":"IT",
    "gn:dem":469,
    "gn:feature_class":"P",
    "gn:feature_code":"PPL",
    "gn:name":"Ischia",
    "gn:population":35,
    "gn:timezone":"Europe/Rome",
    "iso:country":"IT",
    "wof:name":"Ischia",
    "wof:placetype":"locality",
    "wof:population":35
},
  "geometry": {"coordinates":[15.50488,40.40362],"type":"Point"}
}