{
  "type": "Feature",
  "properties": {
    "gn:admin1_code":"4",
    "gn:admin2_code":"SA",
    "gn:admin3_code":"65146.0",
    "gn:asciiname":"Ischia",
    "gn:country_code":"IT",
    "gn:dem":469,
    "gn:feature_class":"P",
    "gn:feature_code":"PPL",
    "gn:name":"Ischia",
    "gn:population":35,
    "gn:timezone":"Europe/Rome",
    "iso:country":"IT",
    "name:afr_x_preferred":[
        "Ischia"
    ],
    "name:ara_x_preferred":[
        "\u0625\u0633\u0643\u064a\u0627"
    ],
    "name:aze_x_preferred":[
        "\u0130skya"
    ],
    "name:bel_x_preferred":[
        "\u0413\u0440\u0430\u043d\u2019\u044f\u043d\u0430"
    ],
    "name:cat_x_preferred":[
        "Ischia"
    ],
    "name:ceb_x_preferred":[
        "Isola d'Ischia"
    ],
    "name:ces_x_preferred":[
        "Ischia"
    ],
    "name:dan_x_preferred":[
        "Ischia"
    ],
    "name:deu_x_preferred":[
        "Ischia"
    ],
    "name:ell_x_preferred":[
        "\u038a\u03c3\u03ba\u03b9\u03b1"
    ],
    "name:epo_x_preferred":[
        "Insulo Ischia"
    ],
    "name:est_x_preferred":[
        "Ischia saar"
    ],
    "name:eus_x_preferred":[
        "Ischia"
    ],
    "name:fas_x_preferred":[
        "\u0627\u06cc\u0633\u06a9\u06cc\u0627"
    ],
    "name:fin_x_preferred":[
        "Ischia"
    ],
    "name:fra_x_preferred":[
        "Ischia"
    ],
    "name:glg_x_preferred":[
        "Ischia"
    ],
    "name:heb_x_preferred":[
        "\u05d0\u05d9\u05e1\u05e7\u05d9\u05d4"
    ],
    "name:hun_x_preferred":[
        "Ischia"
    ],
    "name:ind_x_preferred":[
        "Ischia"
    ],
    "name:ita_x_preferred":[
        "Isola d'Ischia"
    ],
    "name:jpn_x_preferred":[
        "\u30a4\u30b9\u30ad\u30a2\u5cf6"
    ],
    "name:kaz_x_preferred":[
        "\u0418\u0441\u043a\u044c\u044f"
    ],
    "name:kor_x_preferred":[
        "\uc774\uc2a4\ud0a4\uc544\uc12c"
    ],
    "name:lat_x_preferred":[
        "Aenaria"
    ],
    "name:lit_x_preferred":[
        "Iskija"
    ],
    "name:mkd_x_preferred":[
        "\u0418\u0441\u043a\u0458\u0430"
    ],
    "name:nld_x_preferred":[
        "Ischia"
    ],
    "name:nno_x_preferred":[
        "Ischia"
    ],
    "name:nor_x_preferred":[
        "Ischia"
    ],
    "name:oss_x_preferred":[
        "\u0418\u0441\u043a\u044c\u044f"
    ],
    "name:pol_x_preferred":[
        "Ischia"
    ],
    "name:por_x_preferred":[
        "\u00cdsquia"
    ],
    "name:ron_x_preferred":[
        "Insula Ischia"
    ],
    "name:rus_x_preferred":[
        "\u0418\u0441\u043a\u044c\u044f"
    ],
    "name:scn_x_preferred":[
        "Ischia"
    ],
    "name:sco_x_preferred":[
        "Ischia"
    ],
    "name:slk_x_preferred":[
        "Ischia"
    ],
    "name:spa_x_preferred":[
        "Isquia"
    ],
    "name:swe_x_preferred":[
        "Ischia"
    ],
    "name:ukr_x_preferred":[
        "\u0406\u0441\u043a\u0456\u044f"
    ],
    "name:urd_x_preferred":[
        "\u0627\u0633\u06a9\u06cc\u0627"
    ],
    "name:zho_x_preferred":[
        "\u4f0a\u65af\u57fa\u4e9a"
    ],
    "wof:name":"Ischia",
    "wof:placetype":"locality",
    "wof:population":35
},
  "geometry": {"coordinates":[15.50488,40.40362],"type":"Point"}
}