{
  "type": "Feature",
  "properties": {
    "gn:admin1_code":"17.0",
    "gn:admin2_code":"BZ",
    "gn:admin3_code":"21111.0",
    "gn:asciiname":"Scaleres",
    "gn:country_code":"IT",
    "gn:dem":1182,
    "gn:elevation":"1166.0",
    "gn:feature_class":"P",
    "gn:feature_code":"PPL",
    "gn:name":"Scaleres",
    "gn:population":59,
    "gn:timezone":"Europe/Rome",
    "iso:country":"IT",
    "wof:name":"Scaleres",
    "wof:placetype":"locality",
    "wof:population":59
},
  "geometry": {"coordinates":[11.59549,46.73963],"type":"Point"}
}