{
  "type": "Feature",
  "properties": {
    "gn:admin1_code":"4.0",
    "gn:admin2_code":"SA",
    "gn:admin3_code":"65073.0",
    "gn:asciiname":"Gauro",
    "gn:country_code":"IT",
    "gn:dem":319,
    "gn:feature_class":"P",
    "gn:feature_code":"PPL",
    "gn:name":"Gauro",
    "gn:population":807,
    "gn:timezone":"Europe/Rome",
    "iso:country":"IT",
    "wof:name":"Gauro",
    "wof:placetype":"locality",
    "wof:population":807
},
  "geometry": {"coordinates":[14.96365,40.71398],"type":"Point"}
}