{
  "type": "Feature",
  "properties": {
    "gn:admin1_code":"12",
    "gn:admin2_code":"TO",
    "gn:admin3_code":"1243.0",
    "gn:asciiname":"Tetti Negri",
    "gn:country_code":"IT",
    "gn:dem":337,
    "gn:feature_class":"P",
    "gn:feature_code":"PPL",
    "gn:name":"Tetti Negri",
    "gn:population":19,
    "gn:timezone":"Europe/Rome",
    "iso:country":"IT",
    "wof:name":"Tetti Negri",
    "wof:placetype":"locality",
    "wof:population":19
},
  "geometry": {"coordinates":[7.50982,45.1325],"type":"Point"}
}