{
  "type": "Feature",
  "properties": {
    "gn:admin1_code":"20",
    "gn:admin2_code":"BL",
    "gn:admin3_code":"25034.0",
    "gn:asciiname":"Pascoi",
    "gn:country_code":"IT",
    "gn:dem":337,
    "gn:feature_class":"P",
    "gn:feature_code":"PPL",
    "gn:name":"Pascoi",
    "gn:population":17,
    "gn:timezone":"Europe/Rome",
    "iso:country":"IT",
    "wof:name":"Pascoi",
    "wof:placetype":"locality",
    "wof:population":17
},
  "geometry": {"coordinates":[12.10339,46.07489],"type":"Point"}
}