{
  "type": "Feature",
  "properties": {
    "gn:admin1_code":"20",
    "gn:admin2_code":"VI",
    "gn:admin3_code":"24105.0",
    "gn:asciiname":"Quarta Zona Industriale Artigianale",
    "gn:country_code":"IT",
    "gn:dem":119,
    "gn:feature_class":"P",
    "gn:feature_code":"PPL",
    "gn:name":"Quarta Zona Industriale Artigianale",
    "gn:population":28,
    "gn:timezone":"Europe/Rome",
    "iso:country":"IT",
    "wof:name":"Quarta Zona Industriale Artigianale",
    "wof:placetype":"locality",
    "wof:population":28
},
  "geometry": {"coordinates":[11.46556,45.68871],"type":"Point"}
}