{
  "type": "Feature",
  "properties": {
    "gn:admin1_code":"19.0",
    "gn:admin2_code":"AO",
    "gn:admin3_code":"7053.0",
    "gn:asciiname":"Mollie",
    "gn:country_code":"IT",
    "gn:dem":1592,
    "gn:feature_class":"P",
    "gn:feature_code":"PPL",
    "gn:name":"Molli\u00e9",
    "gn:population":0,
    "gn:timezone":"Europe/Rome",
    "iso:country":"IT",
    "wof:name":"Mollie",
    "wof:placetype":"locality"
},
  "geometry": {"coordinates":[6.98333,45.75],"type":"Point"}
}