{
  "type": "Feature",
  "properties": {
    "gn:admin1_code":"20.0",
    "gn:admin2_code":"PD",
    "gn:admin3_code":"28033.0",
    "gn:asciiname":"P.I.P. Codevigo",
    "gn:country_code":"IT",
    "gn:dem":0,
    "gn:feature_class":"P",
    "gn:feature_code":"PPL",
    "gn:name":"P.I.P. Codevigo",
    "gn:population":48,
    "gn:timezone":"Europe/Rome",
    "iso:country":"IT",
    "wof:name":"P.I.P. Codevigo",
    "wof:placetype":"locality",
    "wof:population":48
},
  "geometry": {"coordinates":[12.09243,45.2723],"type":"Point"}
}