{
  "type": "Feature",
  "properties": {
    "gn:admin1_code":"1.0",
    "gn:admin2_code":"AQ",
    "gn:admin3_code":"66095.0",
    "gn:asciiname":"Stazione di Vigliano",
    "gn:country_code":"IT",
    "gn:dem":855,
    "gn:feature_class":"P",
    "gn:feature_code":"PPL",
    "gn:name":"Stazione di Vigliano",
    "gn:population":72,
    "gn:timezone":"Europe/Rome",
    "iso:country":"IT",
    "wof:name":"Stazione di Vigliano",
    "wof:placetype":"locality",
    "wof:population":72
},
  "geometry": {"coordinates":[13.22912,42.3421],"type":"Point"}
}