{
  "type": "Feature",
  "properties": {
    "gn:admin1_code":"5.0",
    "gn:admin2_code":"RA",
    "gn:admin3_code":"39001.0",
    "gn:asciiname":"Taglio Corelli",
    "gn:country_code":"IT",
    "gn:dem":4,
    "gn:elevation":"6.0",
    "gn:feature_class":"P",
    "gn:feature_code":"PPL",
    "gn:name":"Taglio Corelli",
    "gn:population":64,
    "gn:timezone":"Europe/Rome",
    "iso:country":"IT",
    "wof:name":"Taglio Corelli",
    "wof:placetype":"locality",
    "wof:population":64
},
  "geometry": {"coordinates":[12.00147,44.53892000000001],"type":"Point"}
}