{
  "type": "Feature",
  "properties": {
    "gn:admin1_code":"9.0",
    "gn:admin2_code":"PV",
    "gn:admin3_code":"18101.0",
    "gn:asciiname":"Losana",
    "gn:country_code":"IT",
    "gn:dem":139,
    "gn:feature_class":"P",
    "gn:feature_code":"PPL",
    "gn:name":"Losana",
    "gn:population":112,
    "gn:timezone":"Europe/Rome",
    "iso:country":"IT",
    "wof:name":"Losana",
    "wof:placetype":"locality",
    "wof:population":112
},
  "geometry": {"coordinates":[9.18976,45.00823],"type":"Point"}
}