{
  "type": "Feature",
  "properties": {
    "gn:admin1_code":"20",
    "gn:admin2_code":"VI",
    "gn:admin3_code":"24021.0",
    "gn:asciiname":"Traverso",
    "gn:country_code":"IT",
    "gn:dem":30,
    "gn:feature_class":"P",
    "gn:feature_code":"PPL",
    "gn:name":"Traverso",
    "gn:population":24,
    "gn:timezone":"Europe/Rome",
    "iso:country":"IT",
    "wof:name":"Traverso",
    "wof:placetype":"locality",
    "wof:population":24
},
  "geometry": {"coordinates":[11.72505,45.55832],"type":"Point"}
}