{
  "type": "Feature",
  "properties": {
    "gn:admin1_code":"1.0",
    "gn:admin2_code":"CH",
    "gn:admin3_code":"69002.0",
    "gn:asciiname":"Fara",
    "gn:country_code":"IT",
    "gn:dem":291,
    "gn:feature_class":"P",
    "gn:feature_code":"PPL",
    "gn:name":"Fara",
    "gn:population":78,
    "gn:timezone":"Europe/Rome",
    "iso:country":"IT",
    "name:bos_x_preferred":[
        "Fara"
    ],
    "name:ceb_x_preferred":[
        "Fara"
    ],
    "name:deu_x_preferred":[
        "Fara"
    ],
    "name:fin_x_preferred":[
        "Fara"
    ],
    "name:fra_x_preferred":[
        "Fara"
    ],
    "name:gla_x_preferred":[
        "Fara"
    ],
    "name:hrv_x_preferred":[
        "Fara"
    ],
    "name:ita_x_preferred":[
        "Fara"
    ],
    "name:lat_x_preferred":[
        "Fara"
    ],
    "name:lmo_x_preferred":[
        "Fara"
    ],
    "name:nld_x_preferred":[
        "Fara"
    ],
    "name:nor_x_preferred":[
        "Fara"
    ],
    "name:pms_x_preferred":[
        "Fara"
    ],
    "name:pol_x_preferred":[
        "Fara"
    ],
    "name:por_x_preferred":[
        "Fara"
    ],
    "name:rus_x_preferred":[
        "\u0424\u0430\u0440\u0430"
    ],
    "name:sco_x_preferred":[
        "Fara"
    ],
    "name:slv_x_preferred":[
        "Fara"
    ],
    "name:spa_x_preferred":[
        "Fara"
    ],
    "name:srp_x_preferred":[
        "\u0424\u0430\u0440\u0430"
    ],
    "name:swe_x_preferred":[
        "Fara"
    ],
    "name:ukr_x_preferred":[
        "\u0424\u0430\u0440\u0430"
    ],
    "wof:name":"Fara",
    "wof:placetype":"locality",
    "wof:population":78
},
  "geometry": {"coordinates":[14.36208,42.07861],"type":"Point"}
}