{
  "type": "Feature",
  "properties": {
    "gn:admin1_code":"1.0",
    "gn:admin2_code":"CH",
    "gn:admin3_code":"69002.0",
    "gn:asciiname":"Fara",
    "gn:country_code":"IT",
    "gn:dem":291,
    "gn:feature_class":"P",
    "gn:feature_code":"PPL",
    "gn:name":"Fara",
    "gn:population":78,
    "gn:timezone":"Europe/Rome",
    "iso:country":"IT",
    "wof:name":"Fara",
    "wof:placetype":"locality",
    "wof:population":78
},
  "geometry": {"coordinates":[14.36208,42.07861],"type":"Point"}
}