{
  "type": "Feature",
  "properties": {
    "gn:admin1_code":"5.0",
    "gn:admin2_code":"RE",
    "gn:admin3_code":"35033.0",
    "gn:asciiname":"Castello di Pratofontana",
    "gn:country_code":"IT",
    "gn:dem":35,
    "gn:feature_class":"P",
    "gn:feature_code":"PPL",
    "gn:name":"Castello di Pratofontana",
    "gn:population":508,
    "gn:timezone":"Europe/Rome",
    "iso:country":"IT",
    "wof:name":"Castello di Pratofontana",
    "wof:placetype":"locality",
    "wof:population":508
},
  "geometry": {"coordinates":[10.6706,44.73952],"type":"Point"}
}