{
  "type": "Feature",
  "properties": {
    "gn:admin1_code":"15.0",
    "gn:admin2_code":"ME",
    "gn:admin3_code":"83066.0",
    "gn:asciiname":"Case Nuove Russo",
    "gn:country_code":"IT",
    "gn:dem":31,
    "gn:feature_class":"P",
    "gn:feature_code":"PPL",
    "gn:name":"Case Nuove Russo",
    "gn:population":969,
    "gn:timezone":"Europe/Rome",
    "iso:country":"IT",
    "wof:name":"Case Nuove Russo",
    "wof:placetype":"locality",
    "wof:population":969
},
  "geometry": {"coordinates":[14.98877,38.14052],"type":"Point"}
}