{
  "type": "Feature",
  "properties": {
    "gn:admin1_code":"16",
    "gn:admin2_code":"MS",
    "gn:admin3_code":"45015.0",
    "gn:asciiname":"Meredo",
    "gn:country_code":"IT",
    "gn:dem":369,
    "gn:feature_class":"P",
    "gn:feature_code":"PPL",
    "gn:name":"Meredo",
    "gn:population":17,
    "gn:timezone":"Europe/Rome",
    "iso:country":"IT",
    "name:ast_x_preferred":[
        "Meredo"
    ],
    "name:cat_x_preferred":[
        "Meredo"
    ],
    "name:deu_x_preferred":[
        "Meredo"
    ],
    "name:spa_x_preferred":[
        "Meredo"
    ],
    "wof:name":"Meredo",
    "wof:placetype":"locality",
    "wof:population":17
},
  "geometry": {"coordinates":[9.90996,44.21732],"type":"Point"}
}