{
  "type": "Feature",
  "properties": {
    "gn:gn_country":"IT",
    "gn:gn_fcode":"PPLA3",
    "gn:gn_pop":1841,
    "gn:population":1021,
    "iso:country":"IT",
    "name:bel_x_preferred":[
        "\u0422\u043e\u0440\u044d-\u0434\u044d'-\u041f\u0456\u0447\u044d\u043d\u0430\u0440\u0434\u0437\u0456"
    ],
    "name:bul_x_preferred":[
        "\u0422\u043e\u0440\u0435 \u0434\u0435' \u041f\u0438\u0447\u0435\u043d\u0430\u0440\u0434\u0438"
    ],
    "name:cat_x_preferred":[
        "Torre de' Picenardi"
    ],
    "name:deu_x_preferred":[
        "Torre de\u2019 Picenardi"
    ],
    "name:eng_x_preferred":[
        "Torre de' Picenardi"
    ],
    "name:epo_x_preferred":[
        "Torre de' Picenardi"
    ],
    "name:est_x_preferred":[
        "Torre de' Picenardi vald"
    ],
    "name:eus_x_preferred":[
        "Torre de' Picenardi"
    ],
    "name:fra_x_preferred":[
        "Torre de' Picenardi"
    ],
    "name:hun_x_preferred":[
        "Torre de\u2019 Picenardi"
    ],
    "name:hye_x_preferred":[
        "\u054f\u0578\u0580\u0565 \u0564\u0565 \u054a\u056b\u0579\u0565\u0576\u0561\u0580\u0564\u056b"
    ],
    "name:ita_x_preferred":[
        "Torre de' Picenardi"
    ],
    "name:jpn_x_preferred":[
        "\u30c8\u30c3\u30ec\u30fb\u30c7\u30fb\u30d4\u30c1\u30a7\u30ca\u30eb\u30c7\u30a3"
    ],
    "name:kaz_x_preferred":[
        "\u0422\u043e\u0440\u0440\u0435-\u0434\u0435-\u041f\u0438\u0447\u0435\u043d\u0430\u0440\u0434\u0438"
    ],
    "name:lat_x_preferred":[
        "Turris de Madalbertis"
    ],
    "name:lmo_x_preferred":[
        "Li Tur"
    ],
    "name:msa_x_preferred":[
        "Torre de' Picenardi"
    ],
    "name:nan_x_preferred":[
        "Torre de' Picenardi"
    ],
    "name:nap_x_preferred":[
        "Torre de' Picenardi"
    ],
    "name:nld_x_preferred":[
        "Torre de' Picenardi"
    ],
    "name:oci_x_preferred":[
        "Torre de' Picenardi"
    ],
    "name:pms_x_preferred":[
        "Torre de' Picenardi"
    ],
    "name:pol_x_preferred":[
        "Torre de' Picenardi"
    ],
    "name:por_x_preferred":[
        "Torre de' Picenardi"
    ],
    "name:ron_x_preferred":[
        "Torre de' Picenardi"
    ],
    "name:rus_x_preferred":[
        "\u0422\u043e\u0440\u0440\u0435-\u0434\u0435-\u041f\u0438\u0447\u0435\u043d\u0430\u0440\u0434\u0438"
    ],
    "name:scn_x_preferred":[
        "Torre de' Picenardi"
    ],
    "name:spa_x_preferred":[
        "Torre de' Picenardi"
    ],
    "name:srp_x_preferred":[
        "Torre de' Picenardi"
    ],
    "name:ukr_x_preferred":[
        "\u0422\u043e\u0440\u0440\u0435-\u0434\u0435'-\u041f\u0456\u0447\u0435\u043d\u0430\u0440\u0434\u0456"
    ],
    "name:uzb_x_preferred":[
        "Torre de' Picenardi"
    ],
    "name:vie_x_preferred":[
        "Torre de' Picenardi"
    ],
    "name:vol_x_preferred":[
        "Torre de' Picenardi"
    ],
    "name:war_x_preferred":[
        "Torre de' Picenardi"
    ],
    "name:zho_x_preferred":[
        "\u6258\u96f7\u5fb7\u76ae\u5207\u7eb3\u5c14\u8fea"
    ],
    "qs_pg:aaroncc":"IT",
    "qs_pg:gn_country":"IT",
    "qs_pg:gn_fcode":"PPLA3",
    "qs_pg:gn_pop":1841,
    "qs_pg:name":"Torre de'Picenardi",
    "qs_pg:photos_9r":0,
    "qs_pg:photos_sr":0,
    "qs_pg:pop_sr":3,
    "qs_pg:qs_pg_placetype":"locality",
    "wof:name":"Torre de'Picenardi",
    "wof:placetype":"locality",
    "wof:population":1021
},
  "geometry": {"coordinates":[10.28688,45.14357],"type":"Point"}
}