{
  "type": "Feature",
  "properties": {
    "gn:admin1_code":"20.0",
    "gn:admin2_code":"VR",
    "gn:admin3_code":"23026.0",
    "gn:asciiname":"Lonico",
    "gn:country_code":"IT",
    "gn:dem":606,
    "gn:feature_class":"P",
    "gn:feature_code":"PPL",
    "gn:name":"Lonico",
    "gn:population":30,
    "gn:timezone":"Europe/Rome",
    "iso:country":"IT",
    "wof:name":"Lonico",
    "wof:placetype":"locality",
    "wof:population":30
},
  "geometry": {"coordinates":[11.02816,45.56803],"type":"Point"}
}