{
  "type": "Feature",
  "properties": {
    "gn:admin1_code":"20.0",
    "gn:admin2_code":"TV",
    "gn:admin3_code":"26005.0",
    "gn:asciiname":"Vacil",
    "gn:country_code":"IT",
    "gn:dem":22,
    "gn:elevation":"22.0",
    "gn:feature_class":"P",
    "gn:feature_code":"PPL",
    "gn:name":"Vacil",
    "gn:population":994,
    "gn:timezone":"Europe/Rome",
    "iso:country":"IT",
    "wof:name":"Vacil",
    "wof:placetype":"locality",
    "wof:population":994
},
  "geometry": {"coordinates":[12.30906,45.70981],"type":"Point"}
}