{
  "type": "Feature",
  "properties": {
    "gn:admin1_code":"20",
    "gn:admin2_code":"VI",
    "gn:admin3_code":"24028.0",
    "gn:asciiname":"Carletti (Montepulgo)",
    "gn:country_code":"IT",
    "gn:dem":394,
    "gn:feature_class":"P",
    "gn:feature_code":"PPL",
    "gn:name":"Carletti (Montepulgo)",
    "gn:population":19,
    "gn:timezone":"Europe/Rome",
    "iso:country":"IT",
    "wof:name":"Carletti (Montepulgo)",
    "wof:placetype":"locality",
    "wof:population":19
},
  "geometry": {"coordinates":[11.40014,45.61115],"type":"Point"}
}