{
  "type": "Feature",
  "properties": {
    "gn:admin1_code":"5",
    "gn:admin2_code":"RN",
    "gn:admin3_code":"99016.0",
    "gn:asciiname":"Casa Ferri",
    "gn:country_code":"IT",
    "gn:dem":63,
    "gn:feature_class":"P",
    "gn:feature_code":"PPL",
    "gn:name":"Casa Ferri",
    "gn:population":50,
    "gn:timezone":"Europe/Rome",
    "iso:country":"IT",
    "wof:name":"Casa Ferri",
    "wof:placetype":"locality",
    "wof:population":50
},
  "geometry": {"coordinates":[12.66765,43.93407],"type":"Point"}
}