{
  "type": "Feature",
  "properties": {
    "gn:admin1_code":"6",
    "gn:admin2_code":"UD",
    "gn:admin3_code":"30018.0",
    "gn:asciiname":"Zavattina",
    "gn:country_code":"IT",
    "gn:dem":7,
    "gn:feature_class":"P",
    "gn:feature_code":"PPL",
    "gn:name":"Zavattina",
    "gn:population":43,
    "gn:timezone":"Europe/Rome",
    "iso:country":"IT",
    "wof:name":"Zavattina",
    "wof:placetype":"locality",
    "wof:population":43
},
  "geometry": {"coordinates":[13.15889,45.81731],"type":"Point"}
}