{
  "type": "Feature",
  "properties": {
    "gn:admin1_code":"9.0",
    "gn:admin2_code":"SO",
    "gn:admin3_code":"14020.0",
    "gn:asciiname":"Contrada Maffina",
    "gn:country_code":"IT",
    "gn:dem":654,
    "gn:feature_class":"P",
    "gn:feature_code":"PPL",
    "gn:name":"Contrada Maffina",
    "gn:population":23,
    "gn:timezone":"Europe/Rome",
    "iso:country":"IT",
    "wof:name":"Contrada Maffina",
    "wof:placetype":"locality",
    "wof:population":23
},
  "geometry": {"coordinates":[10.0017,46.18024000000001],"type":"Point"}
}