{
  "type": "Feature",
  "properties": {
    "gn:admin1_code":"3",
    "gn:admin2_code":"CS",
    "gn:admin3_code":"78035.0",
    "gn:asciiname":"Contrada Riposo",
    "gn:country_code":"IT",
    "gn:dem":808,
    "gn:feature_class":"P",
    "gn:feature_code":"PPL",
    "gn:name":"Contrada Riposo",
    "gn:population":30,
    "gn:timezone":"Europe/Rome",
    "iso:country":"IT",
    "wof:name":"Contrada Riposo",
    "wof:placetype":"locality",
    "wof:population":30
},
  "geometry": {"coordinates":[16.33948,39.21488],"type":"Point"}
}