{
  "type": "Feature",
  "properties": {
    "gn:admin1_code":"9",
    "gn:admin2_code":"MN",
    "gn:admin3_code":"20055.0",
    "gn:asciiname":"Zara",
    "gn:country_code":"IT",
    "gn:dem":19,
    "gn:feature_class":"P",
    "gn:feature_code":"PPL",
    "gn:name":"Zara",
    "gn:population":28,
    "gn:timezone":"Europe/Rome",
    "iso:country":"IT",
    "wof:name":"Zara",
    "wof:placetype":"locality",
    "wof:population":28
},
  "geometry": {"coordinates":[10.85684,45.03051],"type":"Point"}
}