{
  "type": "Feature",
  "properties": {
    "iso:country":"IT",
    "wof:name":"Barriera di Milano",
    "wof:placetype":"neighbourhood"
},
  "geometry": {"coordinates":[7.70095095998667,45.0944492225639],"type":"Point"}
}