{
  "type": "Feature",
  "properties": {
    "gn:admin1_code":"5",
    "gn:admin2_code":"RN",
    "gn:admin3_code":"99029.0",
    "gn:asciiname":"Mandrio",
    "gn:country_code":"IT",
    "gn:dem":180,
    "gn:feature_class":"P",
    "gn:feature_code":"PPL",
    "gn:name":"Mandrio",
    "gn:population":12,
    "gn:timezone":"Europe/Rome",
    "iso:country":"IT",
    "wof:name":"Mandrio",
    "wof:placetype":"locality",
    "wof:population":12
},
  "geometry": {"coordinates":[12.50736,43.92364],"type":"Point"}
}