{
  "type": "Feature",
  "properties": {
    "gn:admin1_code":"9",
    "gn:admin2_code":"BG",
    "gn:admin3_code":"16083.0",
    "gn:asciiname":"Area Artigianale Galeazze",
    "gn:country_code":"IT",
    "gn:dem":129,
    "gn:feature_class":"P",
    "gn:feature_code":"PPL",
    "gn:name":"Area Artigianale Galeazze",
    "gn:population":44,
    "gn:timezone":"Europe/Rome",
    "iso:country":"IT",
    "wof:name":"Area Artigianale Galeazze",
    "wof:placetype":"locality",
    "wof:population":44
},
  "geometry": {"coordinates":[9.77444,45.53591],"type":"Point"}
}