{
  "type": "Feature",
  "properties": {
    "gn:admin1_code":"7",
    "gn:admin2_code":"FR",
    "gn:admin3_code":"60085.0",
    "gn:asciiname":"Madonna degli Angeli",
    "gn:country_code":"IT",
    "gn:dem":432,
    "gn:feature_class":"P",
    "gn:feature_code":"PPL",
    "gn:name":"Madonna degli Angeli",
    "gn:population":169,
    "gn:timezone":"Europe/Rome",
    "iso:country":"IT",
    "wof:name":"Madonna degli Angeli",
    "wof:placetype":"locality",
    "wof:population":169
},
  "geometry": {"coordinates":[13.42228,41.68349],"type":"Point"}
}