{
  "type": "Feature",
  "properties": {
    "gn:admin1_code":"20",
    "gn:admin2_code":"VI",
    "gn:admin3_code":"24110.0",
    "gn:asciiname":"Nori",
    "gn:country_code":"IT",
    "gn:dem":533,
    "gn:feature_class":"P",
    "gn:feature_code":"PPL",
    "gn:name":"Nori",
    "gn:population":21,
    "gn:timezone":"Europe/Rome",
    "iso:country":"IT",
    "name:ara_x_preferred":[
        "\u0646\u0648\u0631\u064a"
    ],
    "name:aze_x_preferred":[
        "Nori"
    ],
    "name:cat_x_preferred":[
        "Nori"
    ],
    "name:cdo_x_preferred":[
        "Ci\u0113-ch\u00e1i"
    ],
    "name:ces_x_preferred":[
        "Nori"
    ],
    "name:deu_x_preferred":[
        "Nori"
    ],
    "name:epo_x_preferred":[
        "Nori"
    ],
    "name:eus_x_preferred":[
        "Nori"
    ],
    "name:fas_x_preferred":[
        "\u0646\u0648\u0631\u06cc"
    ],
    "name:fin_x_preferred":[
        "Nori"
    ],
    "name:fra_x_preferred":[
        "Nori"
    ],
    "name:gla_x_preferred":[
        "Nori"
    ],
    "name:glg_x_preferred":[
        "Nori"
    ],
    "name:heb_x_preferred":[
        "\u05e0\u05d5\u05e8\u05d9"
    ],
    "name:hun_x_preferred":[
        "Nori"
    ],
    "name:ind_x_preferred":[
        "Nori"
    ],
    "name:ita_x_preferred":[
        "Nori"
    ],
    "name:jav_x_preferred":[
        "Nori"
    ],
    "name:kir_x_preferred":[
        "\u041d\u043e\u0440\u0438"
    ],
    "name:msa_x_preferred":[
        "Nori"
    ],
    "name:nep_x_preferred":[
        "\u0928\u094b\u0930\u0940"
    ],
    "name:nld_x_preferred":[
        "Nori"
    ],
    "name:pol_x_preferred":[
        "Nori"
    ],
    "name:por_x_preferred":[
        "Nori"
    ],
    "name:rus_x_preferred":[
        "\u041d\u043e\u0440\u0438"
    ],
    "name:spa_x_preferred":[
        "Nori"
    ],
    "name:srp_x_preferred":[
        "\u041d\u043e\u0440\u0438"
    ],
    "name:swe_x_preferred":[
        "Nori"
    ],
    "name:tur_x_preferred":[
        "Nori"
    ],
    "name:ukr_x_preferred":[
        "\u041d\u043e\u0440\u0456"
    ],
    "name:vie_x_preferred":[
        "Nori"
    ],
    "wof:name":"Nori",
    "wof:placetype":"locality",
    "wof:population":21
},
  "geometry": {"coordinates":[11.30796,45.57714],"type":"Point"}
}