{
  "type": "Feature",
  "properties": {
    "gn:admin1_code":"3.0",
    "gn:admin2_code":"RC",
    "gn:admin3_code":"80092.0",
    "gn:asciiname":"Casetta Tre Ponticelli",
    "gn:country_code":"IT",
    "gn:dem":1291,
    "gn:feature_class":"P",
    "gn:feature_code":"PPL",
    "gn:name":"Casetta Tre Ponticelli",
    "gn:population":0,
    "gn:timezone":"Europe/Rome",
    "iso:country":"IT",
    "wof:name":"Casetta Tre Ponticelli",
    "wof:placetype":"locality"
},
  "geometry": {"coordinates":[16.36667000000001,38.55],"type":"Point"}
}