{
  "type": "Feature",
  "properties": {
    "gn:admin1_code":"20",
    "gn:admin2_code":"VI",
    "gn:admin3_code":"24105.0",
    "gn:asciiname":"Manea",
    "gn:country_code":"IT",
    "gn:dem":127,
    "gn:feature_class":"P",
    "gn:feature_code":"PPL",
    "gn:name":"Manea",
    "gn:population":23,
    "gn:timezone":"Europe/Rome",
    "iso:country":"IT",
    "wof:name":"Manea",
    "wof:placetype":"locality",
    "wof:population":23
},
  "geometry": {"coordinates":[11.47252,45.69547],"type":"Point"}
}