{
  "type": "Feature",
  "properties": {
    "gn:admin1_code":"20",
    "gn:admin2_code":"VI",
    "gn:admin3_code":"24105.0",
    "gn:asciiname":"Manea",
    "gn:country_code":"IT",
    "gn:dem":127,
    "gn:feature_class":"P",
    "gn:feature_code":"PPL",
    "gn:name":"Manea",
    "gn:population":23,
    "gn:timezone":"Europe/Rome",
    "iso:country":"IT",
    "name:ceb_x_preferred":[
        "Manea"
    ],
    "name:deu_x_preferred":[
        "Manea"
    ],
    "name:fra_x_preferred":[
        "Manea"
    ],
    "name:hye_x_preferred":[
        "\u0544\u0561\u0576\u0575\u0561"
    ],
    "name:pol_x_preferred":[
        "Manea"
    ],
    "name:ron_x_preferred":[
        "Manea"
    ],
    "name:rus_x_preferred":[
        "\u041c\u0430\u043d\u044f"
    ],
    "name:swe_x_preferred":[
        "Manea"
    ],
    "wof:name":"Manea",
    "wof:placetype":"locality",
    "wof:population":23
},
  "geometry": {"coordinates":[11.47252,45.69547],"type":"Point"}
}