{
  "type": "Feature",
  "properties": {
    "gn:admin1_code":"5.0",
    "gn:admin2_code":"MO",
    "gn:admin3_code":"36006.0",
    "gn:asciiname":"Recovato",
    "gn:country_code":"IT",
    "gn:dem":30,
    "gn:feature_class":"P",
    "gn:feature_code":"PPL",
    "gn:name":"Recovato",
    "gn:population":348,
    "gn:timezone":"Europe/Rome",
    "iso:country":"IT",
    "wof:name":"Recovato",
    "wof:placetype":"locality",
    "wof:population":348
},
  "geometry": {"coordinates":[11.06339,44.63844],"type":"Point"}
}