{
  "type": "Feature",
  "properties": {
    "gn:admin1_code":"4",
    "gn:admin2_code":"BN",
    "gn:admin3_code":"62026.0",
    "gn:asciiname":"Grottole",
    "gn:country_code":"IT",
    "gn:dem":388,
    "gn:feature_class":"P",
    "gn:feature_code":"PPL",
    "gn:name":"Grottole",
    "gn:population":57,
    "gn:timezone":"Europe/Rome",
    "iso:country":"IT",
    "wof:name":"Grottole",
    "wof:placetype":"locality",
    "wof:population":57
},
  "geometry": {"coordinates":[14.51999,41.31751],"type":"Point"}
}