{
  "type": "Feature",
  "properties": {
    "gn:admin1_code":"4",
    "gn:admin2_code":"BN",
    "gn:admin3_code":"62026.0",
    "gn:asciiname":"Grottole",
    "gn:country_code":"IT",
    "gn:dem":388,
    "gn:feature_class":"P",
    "gn:feature_code":"PPL",
    "gn:name":"Grottole",
    "gn:population":57,
    "gn:timezone":"Europe/Rome",
    "iso:country":"IT",
    "name:ara_x_preferred":[
        "\u063a\u0631\u0648\u062a\u0648\u0644\u064a"
    ],
    "name:azb_x_preferred":[
        "\u0642\u0631\u0648\u062a\u0648\u0644\u0647"
    ],
    "name:bul_x_preferred":[
        "\u0413\u0440\u043e\u0442\u043e\u043b\u0435"
    ],
    "name:ceb_x_preferred":[
        "Grottole"
    ],
    "name:deu_x_preferred":[
        "Grottole"
    ],
    "name:epo_x_preferred":[
        "Grottole"
    ],
    "name:eus_x_preferred":[
        "Grottole"
    ],
    "name:fas_x_preferred":[
        "\u06af\u0631\u0648\u062a\u0648\u0644\u0647"
    ],
    "name:fra_x_preferred":[
        "Grottole"
    ],
    "name:hun_x_preferred":[
        "Grottole"
    ],
    "name:hye_x_preferred":[
        "\u0533\u0580\u0578\u057f\u0578\u056c\u0565"
    ],
    "name:ina_x_preferred":[
        "Grottole"
    ],
    "name:ita_x_preferred":[
        "Grottole"
    ],
    "name:jpn_x_preferred":[
        "\u30b0\u30ed\u30c3\u30c8\u30ec"
    ],
    "name:kaz_x_preferred":[
        "\u0413\u0440\u043e\u0442\u0442\u043e\u043b\u0435"
    ],
    "name:lat_x_preferred":[
        "Cryptulae"
    ],
    "name:lmo_x_preferred":[
        "Grottole"
    ],
    "name:msa_x_preferred":[
        "Grottole"
    ],
    "name:mwl_x_preferred":[
        "Grottole"
    ],
    "name:nap_x_preferred":[
        "Grottole"
    ],
    "name:nld_x_preferred":[
        "Grottole"
    ],
    "name:pms_x_preferred":[
        "Grottole"
    ],
    "name:pol_x_preferred":[
        "Grottole"
    ],
    "name:por_x_preferred":[
        "Grottole"
    ],
    "name:ron_x_preferred":[
        "Grottole"
    ],
    "name:rus_x_preferred":[
        "\u0413\u0440\u043e\u0442\u0442\u043e\u043b\u0435"
    ],
    "name:scn_x_preferred":[
        "Grottoli"
    ],
    "name:spa_x_preferred":[
        "Grottole"
    ],
    "name:srp_x_preferred":[
        "\u0413\u0440\u043e\u0442\u043e\u043b\u0435"
    ],
    "name:tur_x_preferred":[
        "Grottole"
    ],
    "name:ukr_x_preferred":[
        "\u0413\u0440\u043e\u0442\u0442\u043e\u043b\u0435"
    ],
    "name:uzb_x_preferred":[
        "Grottole"
    ],
    "name:vol_x_preferred":[
        "Grottole"
    ],
    "name:war_x_preferred":[
        "Grottole"
    ],
    "name:zho_x_preferred":[
        "\u683c\u7f57\u6258\u83b1"
    ],
    "wof:name":"Grottole",
    "wof:placetype":"locality",
    "wof:population":57
},
  "geometry": {"coordinates":[14.51999,41.31751],"type":"Point"}
}