{
  "type": "Feature",
  "properties": {
    "gn:admin1_code":"16",
    "gn:admin2_code":"AR",
    "gn:admin3_code":"51002.0",
    "gn:asciiname":"Talzano",
    "gn:country_code":"IT",
    "gn:dem":328,
    "gn:feature_class":"P",
    "gn:feature_code":"PPL",
    "gn:name":"Talzano",
    "gn:population":26,
    "gn:timezone":"Europe/Rome",
    "iso:country":"IT",
    "wof:name":"Talzano",
    "wof:placetype":"locality",
    "wof:population":26
},
  "geometry": {"coordinates":[11.78613,43.47433],"type":"Point"}
}