{
  "type": "Feature",
  "properties": {
    "gn:admin1_code":"20",
    "gn:admin2_code":"TV",
    "gn:admin3_code":"26026.0",
    "gn:asciiname":"Fagher",
    "gn:country_code":"IT",
    "gn:dem":140,
    "gn:feature_class":"P",
    "gn:feature_code":"PPL",
    "gn:name":"Fagher",
    "gn:population":23,
    "gn:timezone":"Europe/Rome",
    "iso:country":"IT",
    "wof:name":"Fagher",
    "wof:placetype":"locality",
    "wof:population":23
},
  "geometry": {"coordinates":[12.15281,45.89577],"type":"Point"}
}