{
  "type": "Feature",
  "properties": {
    "gn:admin1_code":"9",
    "gn:admin2_code":"PV",
    "gn:admin3_code":"18005.0",
    "gn:asciiname":"Salerno",
    "gn:country_code":"IT",
    "gn:dem":95,
    "gn:feature_class":"P",
    "gn:feature_code":"PPL",
    "gn:name":"Salerno",
    "gn:population":52,
    "gn:timezone":"Europe/Rome",
    "iso:country":"IT",
    "wof:name":"Salerno",
    "wof:placetype":"locality",
    "wof:population":52
},
  "geometry": {"coordinates":[9.35298,45.06905],"type":"Point"}
}