{
  "type": "Feature",
  "properties": {
    "gn:admin1_code":"12",
    "gn:admin2_code":"CN",
    "gn:admin3_code":"4245.0",
    "gn:asciiname":"Dossi",
    "gn:country_code":"IT",
    "gn:dem":593,
    "gn:feature_class":"P",
    "gn:feature_code":"PPL",
    "gn:name":"Dossi",
    "gn:population":14,
    "gn:timezone":"Europe/Rome",
    "iso:country":"IT",
    "name:rus_x_preferred":[
        "\u0414\u043e\u0441\u0441\u0438"
    ],
    "wof:name":"Dossi",
    "wof:placetype":"locality",
    "wof:population":14
},
  "geometry": {"coordinates":[7.74046,44.34118],"type":"Point"}
}