{
  "type": "Feature",
  "properties": {
    "gn:admin1_code":"15.0",
    "gn:admin2_code":"PA",
    "gn:admin3_code":"82070.0",
    "gn:asciiname":"Buonfornello",
    "gn:country_code":"IT",
    "gn:dem":20,
    "gn:feature_class":"P",
    "gn:feature_code":"PPL",
    "gn:name":"Buonfornello",
    "gn:population":0,
    "gn:timezone":"Europe/Rome",
    "iso:country":"IT",
    "wof:name":"Buonfornello",
    "wof:placetype":"locality"
},
  "geometry": {"coordinates":[13.82222,37.97262],"type":"Point"}
}