{
  "type": "Feature",
  "properties": {
    "gn:admin1_code":"12",
    "gn:admin2_code":"TO",
    "gn:admin3_code":"1217.0",
    "gn:asciiname":"Vittorio Veneto",
    "gn:country_code":"IT",
    "gn:dem":276,
    "gn:feature_class":"P",
    "gn:feature_code":"PPL",
    "gn:name":"Vittorio Veneto",
    "gn:population":18,
    "gn:timezone":"Europe/Rome",
    "iso:country":"IT",
    "name:azb_x_preferred":[
        "\u0648\u06cc\u062a\u0648\u0631\u06cc\u0648 \u0648\u0646\u0647\u200c\u062a\u0648"
    ],
    "name:bul_x_preferred":[
        "\u0412\u0438\u0442\u043e\u0440\u0438\u043e \u0412\u0435\u043d\u0435\u0442\u043e"
    ],
    "name:cat_x_preferred":[
        "Vittorio Veneto"
    ],
    "name:ceb_x_preferred":[
        "Vittorio Veneto"
    ],
    "name:ces_x_preferred":[
        "Vittorio Veneto"
    ],
    "name:dan_x_preferred":[
        "Vittorio Veneto"
    ],
    "name:deu_x_preferred":[
        "Vittorio Veneto"
    ],
    "name:epo_x_preferred":[
        "Vittorio Veneto"
    ],
    "name:eus_x_preferred":[
        "Vittorio Veneto"
    ],
    "name:fas_x_preferred":[
        "\u0648\u06cc\u062a\u0648\u0631\u06cc\u0648 \u0648\u0646\u0647\u200c\u062a\u0648"
    ],
    "name:fin_x_preferred":[
        "Vittorio Veneto"
    ],
    "name:fra_x_preferred":[
        "Vittorio Veneto"
    ],
    "name:hun_x_preferred":[
        "Vittorio Veneto"
    ],
    "name:hye_x_preferred":[
        "\u054e\u056b\u057f\u0578\u0580\u056b\u0578 \u054e\u0565\u0576\u0565\u057f\u0578"
    ],
    "name:ita_x_preferred":[
        "Vittorio Veneto"
    ],
    "name:jpn_x_preferred":[
        "\u30f4\u30a3\u30c3\u30c8\u30ea\u30aa\u30fb\u30f4\u30a7\u30cd\u30c8"
    ],
    "name:kaz_x_preferred":[
        "\u0412\u0438\u0442\u0442\u043e\u0440\u0438\u043e-\u0412\u0435\u043d\u0435\u0442\u043e"
    ],
    "name:lat_x_preferred":[
        "Victorius Venetorum"
    ],
    "name:lmo_x_preferred":[
        "Vittorio Veneto"
    ],
    "name:msa_x_preferred":[
        "Vittorio Veneto"
    ],
    "name:nap_x_preferred":[
        "Vittorio Veneto"
    ],
    "name:nld_x_preferred":[
        "Vittorio Veneto"
    ],
    "name:nor_x_preferred":[
        "Vittorio Veneto"
    ],
    "name:pms_x_preferred":[
        "Vittorio Veneto"
    ],
    "name:pol_x_preferred":[
        "Vittorio Veneto"
    ],
    "name:por_x_preferred":[
        "Vittorio Veneto"
    ],
    "name:ron_x_preferred":[
        "Vittorio Veneto"
    ],
    "name:rus_x_preferred":[
        "\u0412\u0438\u0442\u0442\u043e\u0440\u0438\u043e-\u0412\u0435\u043d\u0435\u0442\u043e"
    ],
    "name:scn_x_preferred":[
        "Vittorio Veneto"
    ],
    "name:slv_x_preferred":[
        "Vittorio Veneto"
    ],
    "name:spa_x_preferred":[
        "Vittorio Veneto"
    ],
    "name:srp_x_preferred":[
        "\u0412\u0438\u0442\u043e\u0440\u0438\u043e \u0412\u0435\u043d\u0435\u0442\u043e"
    ],
    "name:swe_x_preferred":[
        "Vittorio Veneto"
    ],
    "name:tgl_x_preferred":[
        "Vittorio Veneto"
    ],
    "name:tur_x_preferred":[
        "Vittorio Veneto"
    ],
    "name:ukr_x_preferred":[
        "\u0412\u0456\u0442\u0442\u043e\u0440\u0456\u043e-\u0412\u0435\u043d\u0435\u0442\u043e"
    ],
    "name:uzb_x_preferred":[
        "Vittorio Veneto"
    ],
    "name:vec_x_preferred":[
        "Vit\u00f2rio"
    ],
    "name:vie_x_preferred":[
        "Vittorio Veneto"
    ],
    "name:vol_x_preferred":[
        "Vittorio Veneto"
    ],
    "name:war_x_preferred":[
        "Vittorio Veneto"
    ],
    "name:zho_x_preferred":[
        "\u7ef4\u6258\u5ed6\u97e6\u5185\u6258"
    ],
    "wof:name":"Vittorio Veneto",
    "wof:placetype":"locality",
    "wof:population":18
},
  "geometry": {"coordinates":[7.71997,45.29955],"type":"Point"}
}