{
  "type": "Feature",
  "properties": {
    "gn:admin1_code":"12",
    "gn:admin2_code":"TO",
    "gn:admin3_code":"1217.0",
    "gn:asciiname":"Vittorio Veneto",
    "gn:country_code":"IT",
    "gn:dem":276,
    "gn:feature_class":"P",
    "gn:feature_code":"PPL",
    "gn:name":"Vittorio Veneto",
    "gn:population":18,
    "gn:timezone":"Europe/Rome",
    "iso:country":"IT",
    "wof:name":"Vittorio Veneto",
    "wof:placetype":"locality",
    "wof:population":18
},
  "geometry": {"coordinates":[7.71997,45.29955],"type":"Point"}
}