{
  "type": "Feature",
  "properties": {
    "gn:admin1_code":"5",
    "gn:admin2_code":"RE",
    "gn:admin3_code":"35020.0",
    "gn:asciiname":"Casino Salati",
    "gn:country_code":"IT",
    "gn:dem":29,
    "gn:feature_class":"P",
    "gn:feature_code":"PPL",
    "gn:name":"Casino Salati",
    "gn:population":14,
    "gn:timezone":"Europe/Rome",
    "iso:country":"IT",
    "wof:name":"Casino Salati",
    "wof:placetype":"locality",
    "wof:population":14
},
  "geometry": {"coordinates":[10.76306,44.78677],"type":"Point"}
}