{
  "type": "Feature",
  "properties": {
    "gn:admin1_code":"5.0",
    "gn:admin2_code":"RE",
    "gn:admin3_code":"35045.0",
    "gn:asciiname":"Parco dei Principi",
    "gn:country_code":"IT",
    "gn:dem":1023,
    "gn:feature_class":"P",
    "gn:feature_code":"PPLL",
    "gn:name":"Parco dei Principi",
    "gn:population":3,
    "gn:timezone":"Europe/Rome",
    "iso:country":"IT",
    "wof:name":"Parco dei Principi",
    "wof:placetype":"locality",
    "wof:population":3
},
  "geometry": {"coordinates":[10.47709,44.24954],"type":"Point"}
}