{
  "type": "Feature",
  "properties": {
    "gn:admin1_code":"5",
    "gn:admin2_code":"BO",
    "gn:admin3_code":"37041.0",
    "gn:asciiname":"Villa di Cassano",
    "gn:country_code":"IT",
    "gn:dem":418,
    "gn:feature_class":"P",
    "gn:feature_code":"PPL",
    "gn:name":"Villa di Cassano",
    "gn:population":73,
    "gn:timezone":"Europe/Rome",
    "iso:country":"IT",
    "wof:name":"Villa di Cassano",
    "wof:placetype":"locality",
    "wof:population":73
},
  "geometry": {"coordinates":[11.4161,44.29635],"type":"Point"}
}