{
  "type": "Feature",
  "properties": {
    "iso:country":"IT",
    "qs_pg:aaroncc":"IT",
    "qs_pg:name":"Roccacaramanico",
    "qs_pg:name_adm0":"Italia",
    "qs_pg:name_adm1":"Abruzzo",
    "qs_pg:photos":73,
    "qs_pg:photos_1k":15,
    "qs_pg:photos_9k":1,
    "qs_pg:photos_9r":2,
    "qs_pg:photos_all":73,
    "qs_pg:photos_sr":2,
    "qs_pg:pop_sr":0,
    "qs_pg:qs_pg_placetype":"locality",
    "qs_pg:qs_pg_placetype_gp":"Town",
    "qs_pg:woe_adm0":23424853,
    "woe:adm0_id":23424853,
    "woe:name_adm0":"Italia",
    "woe:name_adm1":"Abruzzo",
    "woe:placetype":"Town",
    "wof:name":"Roccacaramanico",
    "wof:placetype":"locality"
},
  "geometry": {"coordinates":[14.01354,42.103469],"type":"Point"}
}