{
  "type": "Feature",
  "properties": {
    "gn:admin1_code":"9",
    "gn:admin2_code":"CO",
    "gn:admin3_code":"13058.0",
    "gn:asciiname":"Ravella",
    "gn:country_code":"IT",
    "gn:dem":353,
    "gn:feature_class":"P",
    "gn:feature_code":"PPL",
    "gn:name":"Ravella",
    "gn:population":277,
    "gn:timezone":"Europe/Rome",
    "iso:country":"IT",
    "wof:name":"Ravella",
    "wof:placetype":"locality",
    "wof:population":277
},
  "geometry": {"coordinates":[9.25211,45.84245],"type":"Point"}
}