{
  "type": "Feature",
  "properties": {
    "gn:admin1_code":"12",
    "gn:admin2_code":"AL",
    "gn:admin3_code":"6029.0",
    "gn:asciiname":"Pratalborato",
    "gn:country_code":"IT",
    "gn:dem":159,
    "gn:feature_class":"P",
    "gn:feature_code":"PPL",
    "gn:name":"Pratalborato",
    "gn:population":177,
    "gn:timezone":"Europe/Rome",
    "iso:country":"IT",
    "wof:name":"Pratalborato",
    "wof:placetype":"locality",
    "wof:population":177
},
  "geometry": {"coordinates":[8.68475,44.70757],"type":"Point"}
}