{
  "type": "Feature",
  "properties": {
    "gn:admin1_code":"9",
    "gn:admin2_code":"VA",
    "gn:admin3_code":"12004.0",
    "gn:asciiname":"Mirabello",
    "gn:country_code":"IT",
    "gn:dem":410,
    "gn:feature_class":"P",
    "gn:feature_code":"PPL",
    "gn:name":"Mirabello",
    "gn:population":17,
    "gn:timezone":"Europe/Rome",
    "iso:country":"IT",
    "wof:name":"Mirabello",
    "wof:placetype":"locality",
    "wof:population":17
},
  "geometry": {"coordinates":[8.86743,45.84591],"type":"Point"}
}