{
  "type": "Feature",
  "properties": {
    "gn:admin1_code":"9.0",
    "gn:admin2_code":"BS",
    "gn:admin3_code":"17071.0",
    "gn:asciiname":"Cadimarco",
    "gn:cc2":"IT",
    "gn:country_code":"IT",
    "gn:dem":41,
    "gn:elevation":"44.0",
    "gn:feature_class":"P",
    "gn:feature_code":"PPL",
    "gn:name":"Cadimarco",
    "gn:population":350,
    "gn:timezone":"Europe/Rome",
    "iso:country":"IT",
    "name:und_x_variant":[
        "Ca'di Marco di Fiessa",
        "Cadimarco"
    ],
    "wof:name":"Cadimarco",
    "wof:placetype":"locality",
    "wof:population":350
},
  "geometry": {"coordinates":[10.35582,45.22669000000001],"type":"Point"}
}