{
  "type": "Feature",
  "properties": {
    "gn:admin1_code":"10.0",
    "gn:admin2_code":"AN",
    "gn:admin3_code":"42047.0",
    "gn:asciiname":"Rotorscio",
    "gn:country_code":"IT",
    "gn:dem":385,
    "gn:feature_class":"P",
    "gn:feature_code":"PPL",
    "gn:name":"Rotorscio",
    "gn:population":0,
    "gn:timezone":"Europe/Rome",
    "iso:country":"IT",
    "wof:name":"Rotorscio",
    "wof:placetype":"locality"
},
  "geometry": {"coordinates":[13.05,43.41667],"type":"Point"}
}