{
  "type": "Feature",
  "properties": {
    "gn:admin1_code":"9.0",
    "gn:admin2_code":"CO",
    "gn:admin3_code":"13251.0",
    "gn:asciiname":"Gironico al Monte",
    "gn:country_code":"IT",
    "gn:dem":419,
    "gn:feature_class":"P",
    "gn:feature_code":"PPL",
    "gn:name":"Gironico al Monte",
    "gn:population":71,
    "gn:timezone":"Europe/Rome",
    "iso:country":"IT",
    "wof:name":"Gironico al Monte",
    "wof:placetype":"locality",
    "wof:population":71
},
  "geometry": {"coordinates":[8.99875,45.79055],"type":"Point"}
}