{
  "type": "Feature",
  "properties": {
    "gn:admin1_code":"5",
    "gn:admin2_code":"RA",
    "gn:admin3_code":"39010.0",
    "gn:asciiname":"San Mamante-Case Lenzuola",
    "gn:country_code":"IT",
    "gn:dem":53,
    "gn:feature_class":"P",
    "gn:feature_code":"PPL",
    "gn:name":"San Mamante-Case Lenzuola",
    "gn:population":30,
    "gn:timezone":"Europe/Rome",
    "iso:country":"IT",
    "wof:name":"San Mamante-Case Lenzuola",
    "wof:placetype":"locality",
    "wof:population":30
},
  "geometry": {"coordinates":[11.91962,44.24302],"type":"Point"}
}