{
  "type": "Feature",
  "properties": {
    "gn:admin1_code":"5",
    "gn:admin2_code":"BO",
    "gn:admin3_code":"37005.0",
    "gn:asciiname":"Fabbreria",
    "gn:country_code":"IT",
    "gn:dem":11,
    "gn:feature_class":"P",
    "gn:feature_code":"PPL",
    "gn:name":"Fabbreria",
    "gn:population":113,
    "gn:timezone":"Europe/Rome",
    "iso:country":"IT",
    "wof:name":"Fabbreria",
    "wof:placetype":"locality",
    "wof:population":113
},
  "geometry": {"coordinates":[11.4432,44.63687],"type":"Point"}
}