{
  "type": "Feature",
  "properties": {
    "gn:admin1_code":"13",
    "gn:admin2_code":"BA",
    "gn:admin3_code":"72023.0",
    "gn:asciiname":"Graviglione-Carrara Cupa",
    "gn:country_code":"IT",
    "gn:dem":369,
    "gn:feature_class":"P",
    "gn:feature_code":"PPL",
    "gn:name":"Graviglione-Carrara Cupa",
    "gn:population":56,
    "gn:timezone":"Europe/Rome",
    "iso:country":"IT",
    "wof:name":"Graviglione-Carrara Cupa",
    "wof:placetype":"locality",
    "wof:population":56
},
  "geometry": {"coordinates":[16.40824,40.83824],"type":"Point"}
}