{
  "type": "Feature",
  "properties": {
    "gn:admin1_code":"1",
    "gn:admin2_code":"CH",
    "gn:admin3_code":"69058.0",
    "gn:asciiname":"Foro",
    "gn:country_code":"IT",
    "gn:dem":1,
    "gn:feature_class":"P",
    "gn:feature_code":"PPL",
    "gn:name":"Foro",
    "gn:population":328,
    "gn:timezone":"Europe/Rome",
    "iso:country":"IT",
    "name:ast_x_preferred":[
        "Foru"
    ],
    "name:jpn_x_preferred":[
        "\u30d5\u30a9\u30ed"
    ],
    "name:por_x_preferred":[
        "Foro"
    ],
    "name:rus_x_preferred":[
        "\u0424\u043e\u0440\u043e"
    ],
    "name:spa_x_preferred":[
        "Foro"
    ],
    "wof:name":"Foro",
    "wof:placetype":"locality",
    "wof:population":328
},
  "geometry": {"coordinates":[14.33384,42.39685],"type":"Point"}
}