{
  "type": "Feature",
  "properties": {
    "gn:admin1_code":"12",
    "gn:admin2_code":"VC",
    "gn:admin3_code":"2113.0",
    "gn:asciiname":"Pianello",
    "gn:country_code":"IT",
    "gn:dem":1077,
    "gn:feature_class":"P",
    "gn:feature_code":"PPLL",
    "gn:name":"Pianello",
    "gn:population":5,
    "gn:timezone":"Europe/Rome",
    "iso:country":"IT",
    "name:cat_x_preferred":[
        "Pianello"
    ],
    "name:ceb_x_preferred":[
        "Pianello"
    ],
    "name:cos_x_preferred":[
        "U Pianellu"
    ],
    "name:deu_x_preferred":[
        "Pianello"
    ],
    "name:eus_x_preferred":[
        "Pianello"
    ],
    "name:fra_x_preferred":[
        "Pianello"
    ],
    "name:hun_x_preferred":[
        "Pianello"
    ],
    "name:ita_x_preferred":[
        "Pianello"
    ],
    "name:kaz_x_preferred":[
        "\u041f\u044c\u044f\u043d\u0435\u043b\u043b\u043e"
    ],
    "name:lat_x_preferred":[
        "Pianello"
    ],
    "name:lmo_x_preferred":[
        "Pianello"
    ],
    "name:mlg_x_preferred":[
        "Pianello"
    ],
    "name:msa_x_preferred":[
        "Pianello"
    ],
    "name:nld_x_preferred":[
        "Pianello"
    ],
    "name:oci_x_preferred":[
        "Pianello"
    ],
    "name:pol_x_preferred":[
        "Pianello"
    ],
    "name:por_x_preferred":[
        "Pianello"
    ],
    "name:rus_x_preferred":[
        "\u041f\u044c\u044f\u043d\u0435\u043b\u043b\u043e"
    ],
    "name:slk_x_preferred":[
        "Pianello"
    ],
    "name:slv_x_preferred":[
        "Pianello"
    ],
    "name:spa_x_preferred":[
        "Pianello"
    ],
    "name:swe_x_preferred":[
        "Pianello"
    ],
    "name:ukr_x_preferred":[
        "\u041f'\u044f\u043d\u0435\u043b\u043b\u043e"
    ],
    "name:vie_x_preferred":[
        "Pianello"
    ],
    "name:vol_x_preferred":[
        "Pianello"
    ],
    "name:war_x_preferred":[
        "Pianello"
    ],
    "wof:name":"Pianello",
    "wof:placetype":"locality",
    "wof:population":5
},
  "geometry": {"coordinates":[8.1775,45.91682],"type":"Point"}
}