{
  "type": "Feature",
  "properties": {
    "gn:admin1_code":"12.0",
    "gn:admin2_code":"TO",
    "gn:admin3_code":"1234.0",
    "gn:asciiname":"Inverso",
    "gn:country_code":"IT",
    "gn:dem":1249,
    "gn:feature_class":"P",
    "gn:feature_code":"PPLL",
    "gn:name":"Inverso",
    "gn:population":3,
    "gn:timezone":"Europe/Rome",
    "iso:country":"IT",
    "wof:name":"Inverso",
    "wof:placetype":"locality",
    "wof:population":3
},
  "geometry": {"coordinates":[7.05054,44.9392],"type":"Point"}
}