{
  "type": "Feature",
  "properties": {
    "gn:admin1_code":"9",
    "gn:admin2_code":"MN",
    "gn:admin3_code":"20045.0",
    "gn:asciiname":"Loghini",
    "gn:country_code":"IT",
    "gn:dem":22,
    "gn:feature_class":"P",
    "gn:feature_code":"PPL",
    "gn:name":"Loghini",
    "gn:population":49,
    "gn:timezone":"Europe/Rome",
    "iso:country":"IT",
    "wof:name":"Loghini",
    "wof:placetype":"locality",
    "wof:population":49
},
  "geometry": {"coordinates":[10.7261,45.18994],"type":"Point"}
}