{
  "type": "Feature",
  "properties": {
    "gn:admin1_code":"10.0",
    "gn:admin2_code":"PU",
    "gn:admin3_code":"41038.0",
    "gn:asciiname":"Molino di San Costanzo",
    "gn:country_code":"IT",
    "gn:dem":48,
    "gn:feature_class":"P",
    "gn:feature_code":"PPL",
    "gn:name":"Molino di San Costanzo",
    "gn:population":0,
    "gn:timezone":"Europe/Rome",
    "iso:country":"IT",
    "wof:name":"Molino di San Costanzo",
    "wof:placetype":"locality"
},
  "geometry": {"coordinates":[13.08333,43.71667],"type":"Point"}
}