{
  "type": "Feature",
  "properties": {
    "gn:admin1_code":"16",
    "gn:admin2_code":"AR",
    "gn:admin3_code":"51005.0",
    "gn:asciiname":"Gavignano",
    "gn:country_code":"IT",
    "gn:dem":307,
    "gn:feature_class":"P",
    "gn:feature_code":"PPL",
    "gn:name":"Gavignano",
    "gn:population":19,
    "gn:timezone":"Europe/Rome",
    "iso:country":"IT",
    "name:azb_x_preferred":[
        "\u0642\u0627\u0648\u06cc\u0646\u06cc\u0627\u0646\u0648"
    ],
    "name:bcl_x_preferred":[
        "Gavignano"
    ],
    "name:bul_x_preferred":[
        "\u0413\u0430\u0432\u0438\u043d\u044f\u043d\u043e"
    ],
    "name:cat_x_preferred":[
        "Gavignano"
    ],
    "name:ceb_x_preferred":[
        "Gavignano"
    ],
    "name:deu_x_preferred":[
        "Gavignano"
    ],
    "name:epo_x_preferred":[
        "Gavignano"
    ],
    "name:eus_x_preferred":[
        "Gavignano"
    ],
    "name:fas_x_preferred":[
        "\u06af\u0627\u0648\u06cc\u0646\u06cc\u0627\u0646\u0648"
    ],
    "name:fra_x_preferred":[
        "Gavignano"
    ],
    "name:hun_x_preferred":[
        "Gavignano"
    ],
    "name:hye_x_preferred":[
        "\u0533\u0561\u057e\u056b\u0576\u0575\u0561\u0576\u0578"
    ],
    "name:ina_x_preferred":[
        "Gavignano"
    ],
    "name:ita_x_preferred":[
        "Gavignano"
    ],
    "name:jpn_x_preferred":[
        "\u30ac\u30f4\u30a3\u30cb\u30e3\u30fc\u30ce"
    ],
    "name:kaz_x_preferred":[
        "\u0413\u0430\u0432\u0438\u043d\u044c\u044f\u043d\u043e"
    ],
    "name:kor_x_preferred":[
        "\uac00\ube44\ub0d0\ub178"
    ],
    "name:lat_x_preferred":[
        "Gabinianum"
    ],
    "name:lmo_x_preferred":[
        "Gavignano"
    ],
    "name:msa_x_preferred":[
        "Gavignano"
    ],
    "name:nld_x_preferred":[
        "Gavignano"
    ],
    "name:pms_x_preferred":[
        "Gavignano"
    ],
    "name:pol_x_preferred":[
        "Gavignano"
    ],
    "name:por_x_preferred":[
        "Gavignano"
    ],
    "name:ron_x_preferred":[
        "Gavignano"
    ],
    "name:rus_x_preferred":[
        "\u0413\u0430\u0432\u0438\u043d\u044c\u044f\u043d\u043e"
    ],
    "name:scn_x_preferred":[
        "Gavignanu"
    ],
    "name:sco_x_preferred":[
        "Gavignano"
    ],
    "name:srp_x_preferred":[
        "\u0413\u0430\u0432\u0438\u045a\u0430\u043d\u043e"
    ],
    "name:ukr_x_preferred":[
        "\u0413\u0430\u0432\u0456\u043d\u044c\u044f\u043d\u043e"
    ],
    "name:uzb_x_preferred":[
        "Gavignano"
    ],
    "name:vie_x_preferred":[
        "Gavignano"
    ],
    "name:vol_x_preferred":[
        "Gavignano"
    ],
    "name:war_x_preferred":[
        "Gavignano"
    ],
    "name:zho_x_preferred":[
        "\u52a0\u7ef4\u7eb3\u8bfa"
    ],
    "wof:name":"Gavignano",
    "wof:placetype":"locality",
    "wof:population":19
},
  "geometry": {"coordinates":[11.61963,43.42302],"type":"Point"}
}