{
  "type": "Feature",
  "properties": {
    "gn:admin1_code":"16",
    "gn:admin2_code":"AR",
    "gn:admin3_code":"51005.0",
    "gn:asciiname":"Gavignano",
    "gn:country_code":"IT",
    "gn:dem":307,
    "gn:feature_class":"P",
    "gn:feature_code":"PPL",
    "gn:name":"Gavignano",
    "gn:population":19,
    "gn:timezone":"Europe/Rome",
    "iso:country":"IT",
    "wof:name":"Gavignano",
    "wof:placetype":"locality",
    "wof:population":19
},
  "geometry": {"coordinates":[11.61963,43.42302],"type":"Point"}
}