{
  "type": "Feature",
  "properties": {
    "gn:admin1_code":"7",
    "gn:admin2_code":"FR",
    "gn:admin3_code":"60074.0",
    "gn:asciiname":"Case Ontola",
    "gn:country_code":"IT",
    "gn:dem":347,
    "gn:feature_class":"P",
    "gn:feature_code":"PPL",
    "gn:name":"Case Ontola",
    "gn:population":51,
    "gn:timezone":"Europe/Rome",
    "iso:country":"IT",
    "wof:name":"Case Ontola",
    "wof:placetype":"locality",
    "wof:population":51
},
  "geometry": {"coordinates":[13.62332,41.74733],"type":"Point"}
}