{
  "type": "Feature",
  "properties": {
    "gn:admin1_code":"20",
    "gn:admin2_code":"VR",
    "gn:admin3_code":"23049.0",
    "gn:asciiname":"Maranello",
    "gn:country_code":"IT",
    "gn:dem":233,
    "gn:feature_class":"P",
    "gn:feature_code":"PPL",
    "gn:name":"Maranello",
    "gn:population":31,
    "gn:timezone":"Europe/Rome",
    "iso:country":"IT",
    "wof:name":"Maranello",
    "wof:placetype":"locality",
    "wof:population":31
},
  "geometry": {"coordinates":[11.25461,45.50689000000001],"type":"Point"}
}