{
  "type": "Feature",
  "properties": {
    "gn:admin1_code":"20",
    "gn:admin2_code":"TV",
    "gn:admin3_code":"26091.0",
    "gn:asciiname":"Case Gasparotto",
    "gn:country_code":"IT",
    "gn:dem":19,
    "gn:feature_class":"P",
    "gn:feature_code":"PPL",
    "gn:name":"Case Gasparotto",
    "gn:population":28,
    "gn:timezone":"Europe/Rome",
    "iso:country":"IT",
    "wof:name":"Case Gasparotto",
    "wof:placetype":"locality",
    "wof:population":28
},
  "geometry": {"coordinates":[12.275,45.70225],"type":"Point"}
}