{
  "type": "Feature",
  "properties": {
    "iso:country":"IT",
    "wof:name":"Porta Tenaglia",
    "wof:placetype":"neighbourhood"
},
  "geometry": {"coordinates":[9.18106317659876,45.47842853212354],"type":"Point"}
}