{
  "type": "Feature",
  "properties": {
    "iso:country":"IT",
    "name:bul_x_preferred":[
        "\u041f\u043e\u0440\u0442\u0430 \u0422\u0435\u043d\u0430\u043b\u0438\u044f"
    ],
    "name:ita_x_preferred":[
        "Porta Tenaglia"
    ],
    "name:rus_x_preferred":[
        "\u041f\u043e\u0440\u0442\u0430-\u0422\u0435\u043d\u0430\u043b\u044c\u044f"
    ],
    "wof:name":"Porta Tenaglia",
    "wof:placetype":"neighbourhood"
},
  "geometry": {"coordinates":[9.18106317659876,45.47842853212354],"type":"Point"}
}