{
  "type": "Feature",
  "properties": {
    "gn:admin1_code":"20",
    "gn:admin2_code":"TV",
    "gn:admin3_code":"26002.0",
    "gn:asciiname":"Bainsizza",
    "gn:country_code":"IT",
    "gn:dem":59,
    "gn:feature_class":"P",
    "gn:feature_code":"PPL",
    "gn:name":"Bainsizza",
    "gn:population":23,
    "gn:timezone":"Europe/Rome",
    "iso:country":"IT",
    "wof:name":"Bainsizza",
    "wof:placetype":"locality",
    "wof:population":23
},
  "geometry": {"coordinates":[12.23994,45.79103],"type":"Point"}
}