{
  "type": "Feature",
  "properties": {
    "gn:admin1_code":"1",
    "gn:admin2_code":"TE",
    "gn:admin3_code":"67040.0",
    "gn:asciiname":"Bufali",
    "gn:country_code":"IT",
    "gn:dem":170,
    "gn:feature_class":"P",
    "gn:feature_code":"PPL",
    "gn:name":"Bufali",
    "gn:population":33,
    "gn:timezone":"Europe/Rome",
    "iso:country":"IT",
    "name:arg_x_preferred":[
        "Bufal\u00ed"
    ],
    "name:ast_x_preferred":[
        "Bufali"
    ],
    "name:azb_x_preferred":[
        "\u0628\u0648\u0641\u0627\u0644\u06cc"
    ],
    "name:cat_x_preferred":[
        "Bufali"
    ],
    "name:ceb_x_preferred":[
        "Bufali"
    ],
    "name:eus_x_preferred":[
        "Bufali"
    ],
    "name:fas_x_preferred":[
        "\u0628\u0648\u0641\u0627\u0644\u06cc"
    ],
    "name:fra_x_preferred":[
        "Bufali"
    ],
    "name:hun_x_preferred":[
        "Bufali"
    ],
    "name:ita_x_preferred":[
        "Bufali"
    ],
    "name:msa_x_preferred":[
        "Bufal\u00ed"
    ],
    "name:nld_x_preferred":[
        "Bufali"
    ],
    "name:oci_x_preferred":[
        "Bufali"
    ],
    "name:pol_x_preferred":[
        "Bufali"
    ],
    "name:por_x_preferred":[
        "Bufali"
    ],
    "name:rus_x_preferred":[
        "\u0411\u0443\u0444\u0430\u043b\u0438"
    ],
    "name:spa_x_preferred":[
        "Bufali"
    ],
    "name:sqi_x_preferred":[
        "Bufali"
    ],
    "name:swe_x_preferred":[
        "Bufali"
    ],
    "name:ukr_x_preferred":[
        "\u0411\u0443\u0444\u0430\u043b\u0456"
    ],
    "name:vie_x_preferred":[
        "Bufal\u00ed"
    ],
    "name:war_x_preferred":[
        "Bufali"
    ],
    "name:zho_x_preferred":[
        "\u5e03\u6cd5\u5229"
    ],
    "wof:name":"Bufali",
    "wof:placetype":"locality",
    "wof:population":33
},
  "geometry": {"coordinates":[14.09786,42.55786],"type":"Point"}
}