{
  "type": "Feature",
  "properties": {
    "gn:admin1_code":"1",
    "gn:admin2_code":"TE",
    "gn:admin3_code":"67040.0",
    "gn:asciiname":"Bufali",
    "gn:country_code":"IT",
    "gn:dem":170,
    "gn:feature_class":"P",
    "gn:feature_code":"PPL",
    "gn:name":"Bufali",
    "gn:population":33,
    "gn:timezone":"Europe/Rome",
    "iso:country":"IT",
    "wof:name":"Bufali",
    "wof:placetype":"locality",
    "wof:population":33
},
  "geometry": {"coordinates":[14.09786,42.55786],"type":"Point"}
}