{
  "type": "Feature",
  "properties": {
    "gn:admin1_code":"16",
    "gn:admin2_code":"LU",
    "gn:admin3_code":"46033.0",
    "gn:asciiname":"Sasso Bianco",
    "gn:country_code":"IT",
    "gn:dem":0,
    "gn:feature_class":"P",
    "gn:feature_code":"PPL",
    "gn:name":"Sasso Bianco",
    "gn:population":19,
    "gn:timezone":"Europe/Rome",
    "iso:country":"IT",
    "wof:name":"Sasso Bianco",
    "wof:placetype":"locality",
    "wof:population":19
},
  "geometry": {"coordinates":[10.28716,43.83956],"type":"Point"}
}