{
  "type": "Feature",
  "properties": {
    "gn:admin1_code":"5.0",
    "gn:admin2_code":"PR",
    "gn:admin3_code":"34006.0",
    "gn:asciiname":"Branzone",
    "gn:country_code":"IT",
    "gn:dem":491,
    "gn:feature_class":"P",
    "gn:feature_code":"PPL",
    "gn:name":"Branzone",
    "gn:population":0,
    "gn:timezone":"Europe/Rome",
    "iso:country":"IT",
    "wof:name":"Branzone",
    "wof:placetype":"locality"
},
  "geometry": {"coordinates":[9.85,44.53333],"type":"Point"}
}