{
  "type": "Feature",
  "properties": {
    "gn:admin1_code":"8.0",
    "gn:admin2_code":"GE",
    "gn:admin3_code":"10047.0",
    "gn:asciiname":"Ageno",
    "gn:country_code":"IT",
    "gn:dem":283,
    "gn:feature_class":"P",
    "gn:feature_code":"PPL",
    "gn:name":"Ageno",
    "gn:population":0,
    "gn:timezone":"Europe/Rome",
    "iso:country":"IT",
    "wof:name":"Ageno",
    "wof:placetype":"locality"
},
  "geometry": {"coordinates":[9.13083,44.37333],"type":"Point"}
}