{
  "type": "Feature",
  "properties": {
    "gn:admin1_code":"10.0",
    "gn:admin2_code":"FM",
    "gn:admin3_code":"109006.0",
    "gn:asciiname":"Ponte Ete-Caldarette",
    "gn:country_code":"IT",
    "gn:dem":50,
    "gn:feature_class":"P",
    "gn:feature_code":"PPL",
    "gn:name":"Ponte Ete-Caldarette",
    "gn:population":560,
    "gn:timezone":"Europe/Rome",
    "iso:country":"IT",
    "wof:name":"Ponte Ete-Caldarette",
    "wof:placetype":"locality",
    "wof:population":560
},
  "geometry": {"coordinates":[13.71733,43.13896],"type":"Point"}
}