{
  "type": "Feature",
  "properties": {
    "gn:admin1_code":"20.0",
    "gn:admin2_code":"RO",
    "gn:admin3_code":"29030.0",
    "gn:asciiname":"Retinella",
    "gn:country_code":"IT",
    "gn:dem":0,
    "gn:elevation":"1.0",
    "gn:feature_class":"P",
    "gn:feature_code":"PPL",
    "gn:name":"Retinella",
    "gn:population":36,
    "gn:timezone":"Europe/Rome",
    "iso:country":"IT",
    "wof:name":"Retinella",
    "wof:placetype":"locality",
    "wof:population":36
},
  "geometry": {"coordinates":[12.17699,45.04831],"type":"Point"}
}