{
  "type": "Feature",
  "properties": {
    "gn:admin1_code":"8",
    "gn:admin2_code":"GE",
    "gn:admin3_code":"10060.0",
    "gn:asciiname":"Fulle",
    "gn:country_code":"IT",
    "gn:dem":178,
    "gn:feature_class":"P",
    "gn:feature_code":"PPL",
    "gn:name":"Fulle",
    "gn:population":19,
    "gn:timezone":"Europe/Rome",
    "iso:country":"IT",
    "wof:name":"Fulle",
    "wof:placetype":"locality",
    "wof:population":19
},
  "geometry": {"coordinates":[9.12196,44.39754],"type":"Point"}
}