{
  "type": "Feature",
  "properties": {
    "gn:admin1_code":"16",
    "gn:admin2_code":"AR",
    "gn:admin3_code":"51001.0",
    "gn:asciiname":"Palazzo",
    "gn:country_code":"IT",
    "gn:dem":333,
    "gn:feature_class":"P",
    "gn:feature_code":"PPL",
    "gn:name":"Palazzo",
    "gn:population":33,
    "gn:timezone":"Europe/Rome",
    "iso:country":"IT",
    "wof:name":"Palazzo",
    "wof:placetype":"locality",
    "wof:population":33
},
  "geometry": {"coordinates":[12.06381,43.50649],"type":"Point"}
}