{
  "type": "Feature",
  "properties": {
    "gn:admin1_code":"9.0",
    "gn:admin2_code":"LO",
    "gn:admin3_code":"98053.0",
    "gn:asciiname":"Malpaga",
    "gn:country_code":"IT",
    "gn:dem":50,
    "gn:feature_class":"P",
    "gn:feature_code":"PPL",
    "gn:name":"Malpaga",
    "gn:population":40,
    "gn:timezone":"Europe/Rome",
    "iso:country":"IT",
    "wof:name":"Malpaga",
    "wof:placetype":"locality",
    "wof:population":40
},
  "geometry": {"coordinates":[9.58537,45.1374],"type":"Point"}
}