{
  "type": "Feature",
  "properties": {
    "gn:admin1_code":"17",
    "gn:admin2_code":"BZ",
    "gn:admin3_code":"21069.0",
    "gn:asciiname":"Mezzaluna",
    "gn:country_code":"IT",
    "gn:dem":1469,
    "gn:feature_class":"P",
    "gn:feature_code":"PPL",
    "gn:name":"Mezzaluna",
    "gn:population":22,
    "gn:timezone":"Europe/Rome",
    "iso:country":"IT",
    "name:deu_x_preferred":[
        "Wiegemesser"
    ],
    "name:eus_x_preferred":[
        "Taiel"
    ],
    "name:ita_x_preferred":[
        "Mezzaluna"
    ],
    "name:nld_x_preferred":[
        "Wiegemes"
    ],
    "name:por_x_preferred":[
        "Mezzaluna"
    ],
    "name:rus_x_preferred":[
        "\u041c\u0435\u0446\u0446\u0430\u043b\u0443\u043d\u0430"
    ],
    "name:spa_x_preferred":[
        "Tajadera"
    ],
    "name:srp_x_preferred":[
        "\u041c\u0435\u0446\u0430\u043b\u0443\u043d\u0430"
    ],
    "wof:name":"Mezzaluna",
    "wof:placetype":"locality",
    "wof:population":22
},
  "geometry": {"coordinates":[11.03142,46.48792],"type":"Point"}
}