{
  "type": "Feature",
  "properties": {
    "gn:admin1_code":"3",
    "gn:admin2_code":"RC",
    "gn:admin3_code":"80093.0",
    "gn:asciiname":"Casolaro",
    "gn:country_code":"IT",
    "gn:dem":156,
    "gn:feature_class":"P",
    "gn:feature_code":"PPL",
    "gn:name":"Casolaro",
    "gn:population":97,
    "gn:timezone":"Europe/Rome",
    "iso:country":"IT",
    "wof:name":"Casolaro",
    "wof:placetype":"locality",
    "wof:population":97
},
  "geometry": {"coordinates":[16.00422,38.38263],"type":"Point"}
}