{
  "type": "Feature",
  "properties": {
    "gn:admin1_code":"18",
    "gn:admin2_code":"PG",
    "gn:admin3_code":"54013.0",
    "gn:asciiname":"Tassinara",
    "gn:country_code":"IT",
    "gn:dem":281,
    "gn:feature_class":"P",
    "gn:feature_code":"PPL",
    "gn:name":"Tassinara",
    "gn:population":132,
    "gn:timezone":"Europe/Rome",
    "iso:country":"IT",
    "wof:name":"Tassinara",
    "wof:placetype":"locality",
    "wof:population":132
},
  "geometry": {"coordinates":[12.21847,43.36746],"type":"Point"}
}