{
  "type": "Feature",
  "properties": {
    "gn:admin1_code":"10",
    "gn:admin2_code":"AN",
    "gn:admin3_code":"42027.0",
    "gn:asciiname":"Santa Veneranda",
    "gn:country_code":"IT",
    "gn:dem":105,
    "gn:feature_class":"P",
    "gn:feature_code":"PPL",
    "gn:name":"Santa Veneranda",
    "gn:population":17,
    "gn:timezone":"Europe/Rome",
    "iso:country":"IT",
    "wof:name":"Santa Veneranda",
    "wof:placetype":"locality",
    "wof:population":17
},
  "geometry": {"coordinates":[13.28627,43.64238],"type":"Point"}
}