{
  "type": "Feature",
  "properties": {
    "gn:admin1_code":"18",
    "gn:admin2_code":"PG",
    "gn:admin3_code":"54022.0",
    "gn:asciiname":"Torri",
    "gn:country_code":"IT",
    "gn:dem":454,
    "gn:feature_class":"P",
    "gn:feature_code":"PPL",
    "gn:name":"Torri",
    "gn:population":115,
    "gn:timezone":"Europe/Rome",
    "iso:country":"IT",
    "name:ceb_x_preferred":[
        "Torri"
    ],
    "name:deu_x_preferred":[
        "Torri"
    ],
    "name:fra_x_preferred":[
        "Torri"
    ],
    "name:ita_x_preferred":[
        "Torri"
    ],
    "name:por_x_preferred":[
        "Torri"
    ],
    "name:swe_x_preferred":[
        "Torri"
    ],
    "wof:name":"Torri",
    "wof:placetype":"locality",
    "wof:population":115
},
  "geometry": {"coordinates":[12.51412,42.85256],"type":"Point"}
}