{
  "type": "Feature",
  "properties": {
    "gn:admin1_code":"10",
    "gn:admin2_code":"MC",
    "gn:admin3_code":"43012.0",
    "gn:asciiname":"Saltregna",
    "gn:country_code":"IT",
    "gn:dem":261,
    "gn:feature_class":"P",
    "gn:feature_code":"PPL",
    "gn:name":"Saltregna",
    "gn:population":47,
    "gn:timezone":"Europe/Rome",
    "iso:country":"IT",
    "wof:name":"Saltregna",
    "wof:placetype":"locality",
    "wof:population":47
},
  "geometry": {"coordinates":[13.25849,43.41776],"type":"Point"}
}