{
  "type": "Feature",
  "properties": {
    "gn:admin1_code":"5.0",
    "gn:admin2_code":"RA",
    "gn:admin3_code":"39004.0",
    "gn:asciiname":"Vespignano",
    "gn:country_code":"IT",
    "gn:dem":266,
    "gn:feature_class":"P",
    "gn:feature_code":"PPL",
    "gn:name":"Vespignano",
    "gn:population":0,
    "gn:timezone":"Europe/Rome",
    "iso:country":"IT",
    "wof:name":"Vespignano",
    "wof:placetype":"locality"
},
  "geometry": {"coordinates":[11.73333,44.23333],"type":"Point"}
}