{
  "type": "Feature",
  "properties": {
    "gn:admin1_code":"4",
    "gn:admin2_code":"CE",
    "gn:admin3_code":"61100.0",
    "gn:asciiname":"Molinella",
    "gn:country_code":"IT",
    "gn:dem":24,
    "gn:feature_class":"P",
    "gn:feature_code":"PPL",
    "gn:name":"Molinella",
    "gn:population":91,
    "gn:timezone":"Europe/Rome",
    "iso:country":"IT",
    "name:ara_x_preferred":[
        "\u0645\u0648\u0644\u064a\u0646\u064a\u0644\u0627"
    ],
    "name:azb_x_preferred":[
        "\u0645\u0648\u0646\u0644\u06cc\u0646\u0644\u0627"
    ],
    "name:bul_x_preferred":[
        "\u041c\u043e\u043b\u0438\u043d\u0435\u043b\u0430"
    ],
    "name:cat_x_preferred":[
        "Molinella"
    ],
    "name:ceb_x_preferred":[
        "Molinella"
    ],
    "name:deu_x_preferred":[
        "Molinella"
    ],
    "name:eml_x_preferred":[
        "Mulin\u00e8la"
    ],
    "name:epo_x_preferred":[
        "Molinella"
    ],
    "name:eus_x_preferred":[
        "Molinella"
    ],
    "name:fas_x_preferred":[
        "\u0645\u0648\u0646\u0644\u06cc\u0646\u0644\u0627"
    ],
    "name:fra_x_preferred":[
        "Molinella"
    ],
    "name:hun_x_preferred":[
        "Molinella"
    ],
    "name:hye_x_preferred":[
        "\u0544\u0578\u056c\u056b\u0576\u0565\u056c\u0561"
    ],
    "name:ina_x_preferred":[
        "Molinella"
    ],
    "name:ita_x_preferred":[
        "Molinella"
    ],
    "name:jpn_x_preferred":[
        "\u30e2\u30ea\u30cd\u30c3\u30e9"
    ],
    "name:kaz_x_preferred":[
        "\u041c\u043e\u043b\u0438\u043d\u0435\u043b\u043b\u0430"
    ],
    "name:lat_x_preferred":[
        "Molinella"
    ],
    "name:lmo_x_preferred":[
        "Molinella"
    ],
    "name:msa_x_preferred":[
        "Molinella"
    ],
    "name:nap_x_preferred":[
        "Molinella"
    ],
    "name:nld_x_preferred":[
        "Molinella"
    ],
    "name:pms_x_preferred":[
        "Molinella"
    ],
    "name:pol_x_preferred":[
        "Molinella"
    ],
    "name:por_x_preferred":[
        "Molinella"
    ],
    "name:ron_x_preferred":[
        "Molinella"
    ],
    "name:rus_x_preferred":[
        "\u041c\u043e\u043b\u0438\u043d\u0435\u043b\u043b\u0430"
    ],
    "name:scn_x_preferred":[
        "Molinella"
    ],
    "name:spa_x_preferred":[
        "Molinella"
    ],
    "name:srp_x_preferred":[
        "\u041c\u043e\u043b\u0438\u043d\u0435\u043b\u0430"
    ],
    "name:tur_x_preferred":[
        "Molinella"
    ],
    "name:ukr_x_preferred":[
        "\u041c\u043e\u043b\u0456\u043d\u0435\u043b\u043b\u0430"
    ],
    "name:uzb_x_preferred":[
        "Molinella"
    ],
    "name:vec_x_preferred":[
        "Mo\u0142ine\u0142a"
    ],
    "name:vie_x_preferred":[
        "Molinella"
    ],
    "name:vol_x_preferred":[
        "Molinella"
    ],
    "name:war_x_preferred":[
        "Molinella"
    ],
    "name:zho_x_preferred":[
        "\u83ab\u5229\u5185\u62c9"
    ],
    "wof:name":"Molinella",
    "wof:placetype":"locality",
    "wof:population":91
},
  "geometry": {"coordinates":[14.20257,41.11994],"type":"Point"}
}