{
  "type": "Feature",
  "properties": {
    "gn:admin1_code":"4",
    "gn:admin2_code":"CE",
    "gn:admin3_code":"61100.0",
    "gn:asciiname":"Molinella",
    "gn:country_code":"IT",
    "gn:dem":24,
    "gn:feature_class":"P",
    "gn:feature_code":"PPL",
    "gn:name":"Molinella",
    "gn:population":91,
    "gn:timezone":"Europe/Rome",
    "iso:country":"IT",
    "wof:name":"Molinella",
    "wof:placetype":"locality",
    "wof:population":91
},
  "geometry": {"coordinates":[14.20257,41.11994],"type":"Point"}
}