{
  "type": "Feature",
  "properties": {
    "gn:gn_country":"IT",
    "gn:gn_fcode":"PPLA3",
    "gn:gn_pop":805,
    "gn:population":362,
    "iso:country":"IT",
    "name:ara_x_preferred":[
        "\u0643\u0627\u0631\u062a\u0648\u0632\u064a\u0648"
    ],
    "name:azb_x_preferred":[
        "\u06a9\u0627\u0631\u062a\u0648\u0632\u06cc\u0648"
    ],
    "name:bel_x_preferred":[
        "\u041a\u0430\u0440\u0442\u043e\u0437\u0456\u0430"
    ],
    "name:bul_x_preferred":[
        "\u041a\u0430\u0440\u0442\u043e\u0437\u0438\u043e"
    ],
    "name:cat_x_preferred":[
        "Cartosio"
    ],
    "name:ceb_x_preferred":[
        "Cartosio"
    ],
    "name:deu_x_preferred":[
        "Cartosio"
    ],
    "name:eng_x_preferred":[
        "Cartosio"
    ],
    "name:epo_x_preferred":[
        "Cartosio"
    ],
    "name:eus_x_preferred":[
        "Cartosio"
    ],
    "name:fas_x_preferred":[
        "\u06a9\u0627\u0631\u062a\u0648\u0632\u06cc\u0648"
    ],
    "name:fra_x_preferred":[
        "Cartosio"
    ],
    "name:hun_x_preferred":[
        "Cartosio"
    ],
    "name:hye_x_preferred":[
        "\u053f\u0561\u0580\u057f\u0578\u0566\u056b\u0578"
    ],
    "name:ind_x_preferred":[
        "Cartosio"
    ],
    "name:ita_x_preferred":[
        "Cartosio"
    ],
    "name:jpn_x_preferred":[
        "\u30ab\u30eb\u30c8\u30fc\u30b8\u30aa"
    ],
    "name:kaz_x_preferred":[
        "\u041a\u0430\u0440\u0442\u043e\u0437\u0438\u043e"
    ],
    "name:lat_x_preferred":[
        "Cartosium"
    ],
    "name:lmo_x_preferred":[
        "Cartosio"
    ],
    "name:msa_x_preferred":[
        "Cartosio"
    ],
    "name:nan_x_preferred":[
        "Cartosio"
    ],
    "name:nap_x_preferred":[
        "Cartosio"
    ],
    "name:nld_x_preferred":[
        "Cartosio"
    ],
    "name:oci_x_preferred":[
        "Cartosio"
    ],
    "name:pms_x_preferred":[
        "Cart\u00f2s"
    ],
    "name:pol_x_preferred":[
        "Cartosio"
    ],
    "name:por_x_preferred":[
        "Cartosio"
    ],
    "name:ron_x_preferred":[
        "Cartosio"
    ],
    "name:rus_x_preferred":[
        "\u041a\u0430\u0440\u0442\u043e\u0437\u0438\u043e"
    ],
    "name:scn_x_preferred":[
        "Cartosio"
    ],
    "name:spa_x_preferred":[
        "Cartosio"
    ],
    "name:srp_x_preferred":[
        "Cartosio"
    ],
    "name:tgl_x_preferred":[
        "Cartosio"
    ],
    "name:ukr_x_preferred":[
        "\u041a\u0430\u0440\u0442\u043e\u0437\u0456\u043e"
    ],
    "name:uzb_x_preferred":[
        "Cartosio"
    ],
    "name:vie_x_preferred":[
        "Cartosio"
    ],
    "name:vol_x_preferred":[
        "Cartosio"
    ],
    "name:war_x_preferred":[
        "Cartosio"
    ],
    "name:zho_x_preferred":[
        "\u5361\u5c14\u6258\u8096"
    ],
    "qs_pg:aaroncc":"IT",
    "qs_pg:gn_country":"IT",
    "qs_pg:gn_fcode":"PPLA3",
    "qs_pg:gn_pop":805,
    "qs_pg:name":"Cartosio",
    "qs_pg:name_adm0":"Italia",
    "qs_pg:name_adm1":"Piemonte",
    "qs_pg:photos_9r":0,
    "qs_pg:photos_sr":0,
    "qs_pg:pop_sr":2,
    "qs_pg:qs_pg_placetype":"locality",
    "qs_pg:qs_pg_placetype_gp":"Town",
    "qs_pg:woe_adm0":23424853,
    "woe:adm0_id":23424853,
    "woe:name_adm0":"Italia",
    "woe:name_adm1":"Piemonte",
    "woe:placetype":"Town",
    "wof:name":"Cartosio",
    "wof:placetype":"locality",
    "wof:population":362
},
  "geometry": {"coordinates":[8.42065,44.59024],"type":"Point"}
}