{
  "type": "Feature",
  "properties": {
    "gn:admin1_code":"3.0",
    "gn:admin2_code":"KR",
    "gn:admin3_code":"101007.0",
    "gn:asciiname":"Casa Picanello",
    "gn:cc2":"IT",
    "gn:country_code":"IT",
    "gn:dem":80,
    "gn:feature_class":"P",
    "gn:feature_code":"PPL",
    "gn:name":"Casa Picanello",
    "gn:population":0,
    "gn:timezone":"Europe/Rome",
    "iso:country":"IT",
    "name:und_x_variant":[
        "Picanello",
        "Casa Picanello"
    ],
    "wof:name":"Casa Picanello",
    "wof:placetype":"locality"
},
  "geometry": {"coordinates":[17.08333,39.38333],"type":"Point"}
}