{
  "type": "Feature",
  "properties": {
    "gn:admin1_code":"10.0",
    "gn:admin2_code":"MC",
    "gn:admin3_code":"43046.0",
    "gn:asciiname":"Pieca",
    "gn:country_code":"IT",
    "gn:dem":459,
    "gn:feature_class":"P",
    "gn:feature_code":"PPL",
    "gn:name":"Pieca",
    "gn:population":33,
    "gn:timezone":"Europe/Rome",
    "iso:country":"IT",
    "wof:name":"Pieca",
    "wof:placetype":"locality",
    "wof:population":33
},
  "geometry": {"coordinates":[13.28553,43.08095],"type":"Point"}
}