{
  "type": "Feature",
  "properties": {
    "gn:admin1_code":"3",
    "gn:admin2_code":"CS",
    "gn:admin3_code":"78123.0",
    "gn:asciiname":"Valle Morelli",
    "gn:country_code":"IT",
    "gn:dem":163,
    "gn:feature_class":"P",
    "gn:feature_code":"PPL",
    "gn:name":"Valle Morelli",
    "gn:population":66,
    "gn:timezone":"Europe/Rome",
    "iso:country":"IT",
    "wof:name":"Valle Morelli",
    "wof:placetype":"locality",
    "wof:population":66
},
  "geometry": {"coordinates":[16.21629,39.5845],"type":"Point"}
}