{
  "type": "Feature",
  "properties": {
    "gn:admin1_code":"16.0",
    "gn:admin2_code":"SI",
    "gn:admin3_code":"52021.0",
    "gn:asciiname":"Zona Pip-Localita Trieste",
    "gn:country_code":"IT",
    "gn:dem":416,
    "gn:feature_class":"P",
    "gn:feature_code":"PPL",
    "gn:name":"Zona Pip-Localit\u00e0 Trieste",
    "gn:population":16,
    "gn:timezone":"Europe/Rome",
    "iso:country":"IT",
    "name:und_x_variant":[
        "Zona Pip-Localit\u00e0 Trieste"
    ],
    "wof:name":"Zona Pip-Localita Trieste",
    "wof:placetype":"locality",
    "wof:population":16
},
  "geometry": {"coordinates":[11.68704,43.09441],"type":"Point"}
}