{
  "type": "Feature",
  "properties": {
    "gn:admin1_code":"20.0",
    "gn:admin2_code":"VR",
    "gn:admin3_code":"23082.0",
    "gn:asciiname":"Caselle",
    "gn:country_code":"IT",
    "gn:dem":77,
    "gn:feature_class":"P",
    "gn:feature_code":"PPL",
    "gn:name":"Caselle",
    "gn:population":4791,
    "gn:timezone":"Europe/Rome",
    "iso:country":"IT",
    "name:ceb_x_preferred":[
        "Caselle"
    ],
    "name:deu_x_preferred":[
        "Caselle"
    ],
    "name:ita_x_preferred":[
        "Caselle"
    ],
    "name:pol_x_preferred":[
        "Caselle"
    ],
    "name:por_x_preferred":[
        "Caselle"
    ],
    "name:srp_x_preferred":[
        "Kazele"
    ],
    "name:swe_x_preferred":[
        "Caselle"
    ],
    "wof:name":"Caselle",
    "wof:placetype":"locality",
    "wof:population":4791
},
  "geometry": {"coordinates":[10.8957,45.4134],"type":"Point"}
}