{
  "type": "Feature",
  "properties": {
    "gn:admin1_code":"5.0",
    "gn:admin2_code":"FC",
    "gn:admin3_code":"40020.0",
    "gn:asciiname":"Bora Bassa",
    "gn:country_code":"IT",
    "gn:dem":96,
    "gn:feature_class":"P",
    "gn:feature_code":"PPL",
    "gn:name":"Bora Bassa",
    "gn:population":1115,
    "gn:timezone":"Europe/Rome",
    "iso:country":"IT",
    "wof:name":"Bora Bassa",
    "wof:placetype":"locality",
    "wof:population":1115
},
  "geometry": {"coordinates":[12.18066,44.04636],"type":"Point"}
}