{
  "type": "Feature",
  "properties": {
    "gn:gn_country":"IT",
    "gn:gn_fcode":"PPL",
    "gn:gn_pop":0,
    "gn:population":86,
    "iso:country":"IT",
    "qs_pg:aaroncc":"IT",
    "qs_pg:gn_country":"IT",
    "qs_pg:gn_fcode":"PPL",
    "qs_pg:gn_pop":0,
    "qs_pg:name":"Lidarno",
    "qs_pg:name_adm0":"Italia",
    "qs_pg:name_adm1":"Umbria",
    "qs_pg:photos":9,
    "qs_pg:photos_1k":2,
    "qs_pg:photos_9k":1,
    "qs_pg:photos_9r":1,
    "qs_pg:photos_all":9,
    "qs_pg:photos_sr":1,
    "qs_pg:pop_sr":0,
    "qs_pg:qs_pg_placetype":"locality",
    "qs_pg:qs_pg_placetype_gp":"Town",
    "qs_pg:woe_adm0":23424853,
    "woe:adm0_id":23424853,
    "woe:name_adm0":"Italia",
    "woe:name_adm1":"Umbria",
    "woe:placetype":"Town",
    "wof:name":"Lidarno",
    "wof:placetype":"locality",
    "wof:population":86
},
  "geometry": {"coordinates":[12.48333,43.11667],"type":"Point"}
}