{
  "type": "Feature",
  "properties": {
    "gn:admin1_code":"16",
    "gn:admin2_code":"LU",
    "gn:admin3_code":"46036.0",
    "gn:asciiname":"Gragliana",
    "gn:country_code":"IT",
    "gn:dem":463,
    "gn:feature_class":"P",
    "gn:feature_code":"PPL",
    "gn:name":"Gragliana",
    "gn:population":49,
    "gn:timezone":"Europe/Rome",
    "iso:country":"IT",
    "wof:name":"Gragliana",
    "wof:placetype":"locality",
    "wof:population":49
},
  "geometry": {"coordinates":[10.40237,44.00187],"type":"Point"}
}