{
  "type": "Feature",
  "properties": {
    "gn:admin1_code":"1.0",
    "gn:admin2_code":"TE",
    "gn:admin3_code":"67012.0",
    "gn:asciiname":"Villa Colli",
    "gn:country_code":"IT",
    "gn:dem":566,
    "gn:feature_class":"P",
    "gn:feature_code":"PPL",
    "gn:name":"Villa Colli",
    "gn:population":22,
    "gn:timezone":"Europe/Rome",
    "iso:country":"IT",
    "wof:name":"Villa Colli",
    "wof:placetype":"locality",
    "wof:population":22
},
  "geometry": {"coordinates":[13.72409,42.50588],"type":"Point"}
}