{
  "type": "Feature",
  "properties": {
    "gn:admin1_code":"16.0",
    "gn:admin2_code":"LU",
    "gn:admin3_code":"46018.0",
    "gn:asciiname":"Pieve a Elici",
    "gn:country_code":"IT",
    "gn:dem":161,
    "gn:elevation":"176.0",
    "gn:feature_class":"P",
    "gn:feature_code":"PPLL",
    "gn:name":"Pieve a Elici",
    "gn:population":249,
    "gn:timezone":"Europe/Rome",
    "iso:country":"IT",
    "wof:name":"Pieve a Elici",
    "wof:placetype":"locality",
    "wof:population":249
},
  "geometry": {"coordinates":[10.33593,43.8851],"type":"Point"}
}