{
  "type": "Feature",
  "properties": {
    "gn:admin1_code":"19",
    "gn:admin2_code":"AO",
    "gn:admin3_code":"7069.0",
    "gn:asciiname":"Lavod",
    "gn:country_code":"IT",
    "gn:dem":1059,
    "gn:feature_class":"P",
    "gn:feature_code":"PPL",
    "gn:name":"Lavod",
    "gn:population":22,
    "gn:timezone":"Europe/Rome",
    "iso:country":"IT",
    "wof:name":"Lavod",
    "wof:placetype":"locality",
    "wof:population":22
},
  "geometry": {"coordinates":[7.34547,45.82903],"type":"Point"}
}