{
  "type": "Feature",
  "properties": {
    "gn:admin1_code":"9",
    "gn:admin2_code":"MN",
    "gn:admin3_code":"20017.0",
    "gn:asciiname":"Fienil Beschi",
    "gn:country_code":"IT",
    "gn:dem":80,
    "gn:feature_class":"P",
    "gn:feature_code":"PPL",
    "gn:name":"Fienil Beschi",
    "gn:population":46,
    "gn:timezone":"Europe/Rome",
    "iso:country":"IT",
    "wof:name":"Fienil Beschi",
    "wof:placetype":"locality",
    "wof:population":46
},
  "geometry": {"coordinates":[10.49162,45.3759],"type":"Point"}
}