{
  "type": "Feature",
  "properties": {
    "gn:admin1_code":"5",
    "gn:admin2_code":"MO",
    "gn:admin3_code":"36012.0",
    "gn:asciiname":"Marchetta",
    "gn:country_code":"IT",
    "gn:dem":12,
    "gn:feature_class":"P",
    "gn:feature_code":"PPL",
    "gn:name":"Marchetta",
    "gn:population":69,
    "gn:timezone":"Europe/Rome",
    "iso:country":"IT",
    "wof:name":"Marchetta",
    "wof:placetype":"locality",
    "wof:population":69
},
  "geometry": {"coordinates":[11.20025,44.8342],"type":"Point"}
}