{
  "type": "Feature",
  "properties": {
    "gn:admin1_code":"17",
    "gn:admin2_code":"TN",
    "gn:admin3_code":"22095.0",
    "gn:asciiname":"Martincelli",
    "gn:country_code":"IT",
    "gn:dem":228,
    "gn:feature_class":"P",
    "gn:feature_code":"PPL",
    "gn:name":"Martincelli",
    "gn:population":98,
    "gn:timezone":"Europe/Rome",
    "iso:country":"IT",
    "wof:name":"Martincelli",
    "wof:placetype":"locality",
    "wof:population":98
},
  "geometry": {"coordinates":[11.68031,45.97855],"type":"Point"}
}