{
  "type": "Feature",
  "properties": {
    "gn:admin1_code":"18.0",
    "gn:admin2_code":"TR",
    "gn:admin3_code":"55020.0",
    "gn:asciiname":"Faiolo",
    "gn:country_code":"IT",
    "gn:dem":472,
    "gn:elevation":"469.0",
    "gn:feature_class":"P",
    "gn:feature_code":"PPL",
    "gn:name":"Faiolo",
    "gn:population":186,
    "gn:timezone":"Europe/Rome",
    "iso:country":"IT",
    "wof:name":"Faiolo",
    "wof:placetype":"locality",
    "wof:population":186
},
  "geometry": {"coordinates":[12.07815,42.89651],"type":"Point"}
}