{
  "type": "Feature",
  "properties": {
    "gn:admin1_code":"7",
    "gn:admin2_code":"FR",
    "gn:admin3_code":"60010.0",
    "gn:asciiname":"Vuotti",
    "gn:country_code":"IT",
    "gn:dem":279,
    "gn:feature_class":"P",
    "gn:feature_code":"PPL",
    "gn:name":"Vuotti",
    "gn:population":40,
    "gn:timezone":"Europe/Rome",
    "iso:country":"IT",
    "wof:name":"Vuotti",
    "wof:placetype":"locality",
    "wof:population":40
},
  "geometry": {"coordinates":[13.60001,41.67989],"type":"Point"}
}