{
  "type": "Feature",
  "properties": {
    "gn:admin1_code":"5",
    "gn:admin2_code":"PR",
    "gn:admin3_code":"34016.0",
    "gn:asciiname":"Case Massi",
    "gn:country_code":"IT",
    "gn:dem":59,
    "gn:feature_class":"P",
    "gn:feature_code":"PPL",
    "gn:name":"Case Massi",
    "gn:population":45,
    "gn:timezone":"Europe/Rome",
    "iso:country":"IT",
    "wof:name":"Case Massi",
    "wof:placetype":"locality",
    "wof:population":45
},
  "geometry": {"coordinates":[10.18712,44.83248],"type":"Point"}
}