{
  "type": "Feature",
  "properties": {
    "gn:gn_country":"IT",
    "gn:gn_fcode":"PPLA3",
    "gn:gn_pop":456,
    "gn:population":138,
    "iso:country":"IT",
    "name:ara_x_preferred":[
        "\u062a\u0634\u064a\u0633\u0648\u0644\u064a"
    ],
    "name:arm_x_preferred":[
        "\u0549\u0565\u057d\u0578\u056c\u0565"
    ],
    "name:baq_x_preferred":[
        "Cessole"
    ],
    "name:bel_x_preferred":[
        "\u0427\u044d\u0441\u043e\u043b\u0435"
    ],
    "name:bul_x_preferred":[
        "\u0427\u0435\u0441\u043e\u043b\u0435"
    ],
    "name:cat_x_preferred":[
        "Cessole"
    ],
    "name:chi_x_preferred":[
        "\u5207\u7d22\u83b1"
    ],
    "name:deu_x_preferred":[
        "Cessole"
    ],
    "name:dut_x_preferred":[
        "Cessole"
    ],
    "name:eng_x_preferred":[
        "Cessole"
    ],
    "name:epo_x_preferred":[
        "Cessole"
    ],
    "name:fra_x_preferred":[
        "Cessole"
    ],
    "name:fre_x_preferred":[
        "Cessole"
    ],
    "name:ger_x_preferred":[
        "Cessole"
    ],
    "name:hun_x_preferred":[
        "Cessole"
    ],
    "name:ind_x_preferred":[
        "Cessole"
    ],
    "name:ita_x_preferred":[
        "Cessole"
    ],
    "name:jpn_x_preferred":[
        "\u30c1\u30a7\u30c3\u30bd\u30ec"
    ],
    "name:kaz_x_preferred":[
        "\u0427\u0435\u0441\u0441\u043e\u043b\u0435"
    ],
    "name:lat_x_preferred":[
        "Cessolae"
    ],
    "name:lmo_x_preferred":[
        "Cessole"
    ],
    "name:may_x_preferred":[
        "Cessole"
    ],
    "name:nan_x_preferred":[
        "Cessole"
    ],
    "name:nap_x_preferred":[
        "Cessole"
    ],
    "name:nld_x_preferred":[
        "Cessole"
    ],
    "name:oci_x_preferred":[
        "Cessole"
    ],
    "name:per_x_preferred":[
        "\u0686\u0633\u0648\u0644\u0647"
    ],
    "name:pms_x_preferred":[
        "S\u00e9ssole"
    ],
    "name:pol_x_preferred":[
        "Cessole"
    ],
    "name:por_x_preferred":[
        "Cessole"
    ],
    "name:rum_x_preferred":[
        "Cessole"
    ],
    "name:rus_x_preferred":[
        "\u0427\u0435\u0441\u0441\u043e\u043b\u0435"
    ],
    "name:scn_x_preferred":[
        "Cessole"
    ],
    "name:spa_x_preferred":[
        "Cessole"
    ],
    "name:srp_x_preferred":[
        "Cessole"
    ],
    "name:tgl_x_preferred":[
        "Cessole"
    ],
    "name:ukr_x_preferred":[
        "\u0427\u0435\u0441\u0441\u043e\u043b\u0435"
    ],
    "name:uzb_x_preferred":[
        "Cessole"
    ],
    "name:vie_x_preferred":[
        "Cessole"
    ],
    "name:vol_x_preferred":[
        "Cessole"
    ],
    "name:war_x_preferred":[
        "Cessole"
    ],
    "qs_pg:aaroncc":"IT",
    "qs_pg:gn_country":"IT",
    "qs_pg:gn_fcode":"PPLA3",
    "qs_pg:gn_pop":456,
    "qs_pg:name":"Cessole",
    "qs_pg:name_adm0":"Italia",
    "qs_pg:name_adm1":"Piemonte",
    "qs_pg:photos_9k":1,
    "qs_pg:photos_9r":1,
    "qs_pg:photos_all":1,
    "qs_pg:photos_sr":0,
    "qs_pg:pop_sr":2,
    "qs_pg:qs_pg_placetype":"locality",
    "qs_pg:qs_pg_placetype_gp":"Town",
    "qs_pg:woe_adm0":23424853,
    "woe:adm0_id":23424853,
    "woe:name_adm0":"Italia",
    "woe:name_adm1":"Piemonte",
    "woe:placetype":"Town",
    "wof:name":"Cessole",
    "wof:placetype":"locality",
    "wof:population":138
},
  "geometry": {"coordinates":[8.24364,44.64894],"type":"Point"}
}