{
  "type": "Feature",
  "properties": {
    "gn:admin1_code":"4.0",
    "gn:admin2_code":"SA",
    "gn:admin3_code":"65081.0",
    "gn:asciiname":"Terzerie-Ficocelle",
    "gn:country_code":"IT",
    "gn:dem":42,
    "gn:feature_class":"P",
    "gn:feature_code":"PPLL",
    "gn:name":"Terzerie-Ficocelle",
    "gn:population":0,
    "gn:timezone":"Europe/Rome",
    "iso:country":"IT",
    "wof:name":"Terzerie-Ficocelle",
    "wof:placetype":"locality"
},
  "geometry": {"coordinates":[15.04723,40.3787],"type":"Point"}
}