{
  "type": "Feature",
  "properties": {
    "gn:admin1_code":"3.0",
    "gn:admin2_code":"CZ",
    "gn:admin3_code":"79160.0",
    "gn:asciiname":"L.P. Prato",
    "gn:country_code":"IT",
    "gn:dem":12,
    "gn:feature_class":"P",
    "gn:feature_code":"PPLL",
    "gn:name":"L.P. Prato",
    "gn:population":0,
    "gn:timezone":"Europe/Rome",
    "iso:country":"IT",
    "wof:name":"L.P. Prato",
    "wof:placetype":"locality"
},
  "geometry": {"coordinates":[16.26986,38.86067],"type":"Point"}
}