{
  "type": "Feature",
  "properties": {
    "gn:admin1_code":"5",
    "gn:admin2_code":"MO",
    "gn:admin3_code":"36033.0",
    "gn:asciiname":"La Fredda",
    "gn:country_code":"IT",
    "gn:dem":221,
    "gn:feature_class":"P",
    "gn:feature_code":"PPL",
    "gn:name":"La Fredda",
    "gn:population":61,
    "gn:timezone":"Europe/Rome",
    "iso:country":"IT",
    "wof:name":"La Fredda",
    "wof:placetype":"locality",
    "wof:population":61
},
  "geometry": {"coordinates":[10.71072,44.48812],"type":"Point"}
}