{
  "type": "Feature",
  "properties": {
    "gn:admin1_code":"16",
    "gn:admin2_code":"LU",
    "gn:admin3_code":"46022.0",
    "gn:asciiname":"Fondagno",
    "gn:country_code":"IT",
    "gn:dem":302,
    "gn:feature_class":"P",
    "gn:feature_code":"PPL",
    "gn:name":"Fondagno",
    "gn:population":44,
    "gn:timezone":"Europe/Rome",
    "iso:country":"IT",
    "wof:name":"Fondagno",
    "wof:placetype":"locality",
    "wof:population":44
},
  "geometry": {"coordinates":[10.45136,43.94993],"type":"Point"}
}