{
  "type": "Feature",
  "properties": {
    "gn:admin1_code":"4.0",
    "gn:admin2_code":"AV",
    "gn:admin3_code":"64063.0",
    "gn:asciiname":"Santa Lucia (Angiluni)",
    "gn:country_code":"IT",
    "gn:dem":604,
    "gn:feature_class":"P",
    "gn:feature_code":"PPL",
    "gn:name":"Santa Lucia (Angiluni)",
    "gn:population":15,
    "gn:timezone":"Europe/Rome",
    "iso:country":"IT",
    "wof:name":"Santa Lucia (Angiluni)",
    "wof:placetype":"locality",
    "wof:population":15
},
  "geometry": {"coordinates":[15.23963,40.91483],"type":"Point"}
}