{
  "type": "Feature",
  "properties": {
    "gn:admin1_code":"9.0",
    "gn:admin2_code":"MB",
    "gn:admin3_code":"108011.0",
    "gn:asciiname":"Fornaci",
    "gn:country_code":"IT",
    "gn:dem":235,
    "gn:feature_class":"P",
    "gn:feature_code":"PPL",
    "gn:name":"Fornaci",
    "gn:population":565,
    "gn:timezone":"Europe/Rome",
    "iso:country":"IT",
    "wof:name":"Fornaci",
    "wof:placetype":"locality",
    "wof:population":565
},
  "geometry": {"coordinates":[9.24086,45.7264],"type":"Point"}
}