{
  "type": "Feature",
  "properties": {
    "gn:admin1_code":"7",
    "gn:admin2_code":"FR",
    "gn:admin3_code":"60070.0",
    "gn:asciiname":"Taverne Vecchie",
    "gn:country_code":"IT",
    "gn:dem":60,
    "gn:feature_class":"P",
    "gn:feature_code":"PPL",
    "gn:name":"Taverne Vecchie",
    "gn:population":32,
    "gn:timezone":"Europe/Rome",
    "iso:country":"IT",
    "wof:name":"Taverne Vecchie",
    "wof:placetype":"locality",
    "wof:population":32
},
  "geometry": {"coordinates":[13.91515,41.44082],"type":"Point"}
}