{
  "type": "Feature",
  "properties": {
    "gn:admin1_code":"9",
    "gn:admin2_code":"MN",
    "gn:admin3_code":"20002.0",
    "gn:asciiname":"Colombarone",
    "gn:country_code":"IT",
    "gn:dem":32,
    "gn:feature_class":"P",
    "gn:feature_code":"PPL",
    "gn:name":"Colombarone",
    "gn:population":11,
    "gn:timezone":"Europe/Rome",
    "iso:country":"IT",
    "wof:name":"Colombarone",
    "wof:placetype":"locality",
    "wof:population":11
},
  "geometry": {"coordinates":[10.4275,45.18901],"type":"Point"}
}