{
  "type": "Feature",
  "properties": {
    "gn:admin1_code":"20",
    "gn:admin2_code":"PD",
    "gn:admin3_code":"28055.0",
    "gn:asciiname":"Divisione Acqui Canaletta",
    "gn:country_code":"IT",
    "gn:dem":9,
    "gn:feature_class":"P",
    "gn:feature_code":"PPL",
    "gn:name":"Divisione Acqui Canaletta",
    "gn:population":38,
    "gn:timezone":"Europe/Rome",
    "iso:country":"IT",
    "wof:name":"Divisione Acqui Canaletta",
    "wof:placetype":"locality",
    "wof:population":38
},
  "geometry": {"coordinates":[11.75803,45.25929],"type":"Point"}
}