{
  "type": "Feature",
  "properties": {
    "gn:admin1_code":"20",
    "gn:admin2_code":"TV",
    "gn:admin3_code":"26077.0",
    "gn:asciiname":"Pozzorotto",
    "gn:country_code":"IT",
    "gn:dem":127,
    "gn:feature_class":"P",
    "gn:feature_code":"PPL",
    "gn:name":"Pozzorotto",
    "gn:population":27,
    "gn:timezone":"Europe/Rome",
    "iso:country":"IT",
    "wof:name":"Pozzorotto",
    "wof:placetype":"locality",
    "wof:population":27
},
  "geometry": {"coordinates":[11.83343,45.78469000000001],"type":"Point"}
}