{
  "type": "Feature",
  "properties": {
    "gn:admin1_code":"16.0",
    "gn:admin2_code":"GR",
    "gn:admin3_code":"53015.0",
    "gn:asciiname":"Casa Vado all'Arancio",
    "gn:country_code":"IT",
    "gn:dem":29,
    "gn:feature_class":"P",
    "gn:feature_code":"PPL",
    "gn:name":"Casa Vado all'Arancio",
    "gn:population":0,
    "gn:timezone":"Europe/Rome",
    "iso:country":"IT",
    "name:und_x_variant":[
        "Casale Vada all'Arancia",
        "Casa Vado all'Arancio"
    ],
    "wof:name":"Casa Vado all'Arancio",
    "wof:placetype":"locality"
},
  "geometry": {"coordinates":[10.81667,42.96667],"type":"Point"}
}