{
  "type": "Feature",
  "properties": {
    "gn:admin1_code":"20",
    "gn:admin2_code":"VI",
    "gn:admin3_code":"24057.0",
    "gn:asciiname":"Canova",
    "gn:country_code":"IT",
    "gn:dem":254,
    "gn:feature_class":"P",
    "gn:feature_code":"PPL",
    "gn:name":"Canova",
    "gn:population":36,
    "gn:timezone":"Europe/Rome",
    "iso:country":"IT",
    "wof:name":"Canova",
    "wof:placetype":"locality",
    "wof:population":36
},
  "geometry": {"coordinates":[11.62893,45.76814],"type":"Point"}
}