{
  "type": "Feature",
  "properties": {
    "gn:admin1_code":"9",
    "gn:admin2_code":"BS",
    "gn:admin3_code":"17113.0",
    "gn:asciiname":"Campagnoli Sera",
    "gn:country_code":"IT",
    "gn:dem":118,
    "gn:feature_class":"P",
    "gn:feature_code":"PPL",
    "gn:name":"Campagnoli Sera",
    "gn:population":65,
    "gn:timezone":"Europe/Rome",
    "iso:country":"IT",
    "wof:name":"Campagnoli Sera",
    "wof:placetype":"locality",
    "wof:population":65
},
  "geometry": {"coordinates":[10.39563,45.43816],"type":"Point"}
}