{
  "type": "Feature",
  "properties": {
    "gn:country":"IT",
    "gn:fcode":"PPL",
    "gn:population":0,
    "iso:country":"IT",
    "name:amh_x_preferred":[
        "\u12a0\u122a\u1295\u130e"
    ],
    "name:ita_x_preferred":[
        "Aringo"
    ],
    "name:nld_x_preferred":[
        "Aringo"
    ],
    "name:spa_x_preferred":[
        "Aringo"
    ],
    "name:srp_x_preferred":[
        "\u0410\u0440\u0438\u043d\u0433\u043e"
    ],
    "qs_pg:aaroncc":"IT",
    "qs_pg:gn_country":"IT",
    "qs_pg:gn_fcode":"PPL",
    "qs_pg:gn_pop":0,
    "qs_pg:name":"Aringo",
    "qs_pg:name_adm0":"Italia",
    "qs_pg:name_adm1":"Lazio",
    "qs_pg:photos_9r":0,
    "qs_pg:photos_sr":0,
    "qs_pg:pop_sr":0,
    "qs_pg:qs_pg_placetype":"locality",
    "qs_pg:qs_pg_placetype_gp":"Town",
    "qs_pg:woe_adm0":23424853,
    "woe:adm0_id":23424853,
    "woe:name_adm0":"Italia",
    "woe:name_adm1":"Lazio",
    "woe:placetype":"Town",
    "wof:name":"Aringo",
    "wof:placetype":"locality",
    "wof:population":68
},
  "geometry": {"coordinates":[13.26667,42.55],"type":"Point"}
}