{
  "type": "Feature",
  "properties": {
    "gn:admin1_code":"9",
    "gn:admin2_code":"LC",
    "gn:admin3_code":"97019.0",
    "gn:asciiname":"Prestabbio",
    "gn:country_code":"IT",
    "gn:dem":318,
    "gn:feature_class":"P",
    "gn:feature_code":"PPL",
    "gn:name":"Prestabbio",
    "gn:population":47,
    "gn:timezone":"Europe/Rome",
    "iso:country":"IT",
    "wof:name":"Prestabbio",
    "wof:placetype":"locality",
    "wof:population":47
},
  "geometry": {"coordinates":[9.36221,45.74583],"type":"Point"}
}