{
  "type": "Feature",
  "properties": {
    "gn:admin1_code":"5.0",
    "gn:admin2_code":"FE",
    "gn:admin3_code":"38004.0",
    "gn:asciiname":"Buonacompra",
    "gn:country_code":"IT",
    "gn:dem":10,
    "gn:feature_class":"P",
    "gn:feature_code":"PPL",
    "gn:name":"Buonacompra",
    "gn:population":392,
    "gn:timezone":"Europe/Rome",
    "iso:country":"IT",
    "wof:name":"Buonacompra",
    "wof:placetype":"locality",
    "wof:population":392
},
  "geometry": {"coordinates":[11.33919,44.80527],"type":"Point"}
}