{
  "type": "Feature",
  "properties": {
    "gn:admin1_code":"3",
    "gn:admin2_code":"RC",
    "gn:admin3_code":"80040.0",
    "gn:asciiname":"Marmora",
    "gn:country_code":"IT",
    "gn:dem":202,
    "gn:feature_class":"P",
    "gn:feature_code":"PPL",
    "gn:name":"Marmora",
    "gn:population":80,
    "gn:timezone":"Europe/Rome",
    "iso:country":"IT",
    "name:ceb_x_preferred":[
        "Marmora"
    ],
    "name:pol_x_preferred":[
        "Marmora"
    ],
    "name:rus_x_preferred":[
        "\u041c\u0430\u0440\u043c\u043e\u0440\u0430"
    ],
    "name:swe_x_preferred":[
        "Marmora"
    ],
    "name:vol_x_preferred":[
        "Marmora"
    ],
    "wof:name":"Marmora",
    "wof:placetype":"locality",
    "wof:population":80
},
  "geometry": {"coordinates":[16.27567,38.34954000000001],"type":"Point"}
}