{
  "type": "Feature",
  "properties": {
    "gn:admin1_code":"1",
    "gn:admin2_code":"PE",
    "gn:admin3_code":"68025.0",
    "gn:asciiname":"San Flaviano",
    "gn:country_code":"IT",
    "gn:dem":227,
    "gn:feature_class":"P",
    "gn:feature_code":"PPL",
    "gn:name":"San Flaviano",
    "gn:population":59,
    "gn:timezone":"Europe/Rome",
    "iso:country":"IT",
    "wof:name":"San Flaviano",
    "wof:placetype":"locality",
    "wof:population":59
},
  "geometry": {"coordinates":[14.06013,42.43019],"type":"Point"}
}