{
  "type": "Feature",
  "properties": {
    "gn:admin1_code":"17.0",
    "gn:admin2_code":"TN",
    "gn:admin3_code":"22062.0",
    "gn:asciiname":"Spinazzeda",
    "gn:country_code":"IT",
    "gn:dem":675,
    "gn:feature_class":"P",
    "gn:feature_code":"PPLL",
    "gn:name":"Spinazzeda",
    "gn:population":0,
    "gn:timezone":"Europe/Rome",
    "iso:country":"IT",
    "wof:name":"Spinazzeda",
    "wof:placetype":"locality"
},
  "geometry": {"coordinates":[11.03079,46.36452],"type":"Point"}
}