{
  "type": "Feature",
  "properties": {
    "gn:admin1_code":"20",
    "gn:admin2_code":"VI",
    "gn:admin3_code":"24110.0",
    "gn:asciiname":"De Cao",
    "gn:country_code":"IT",
    "gn:dem":379,
    "gn:feature_class":"P",
    "gn:feature_code":"PPL",
    "gn:name":"De Cao",
    "gn:population":46,
    "gn:timezone":"Europe/Rome",
    "iso:country":"IT",
    "wof:name":"De Cao",
    "wof:placetype":"locality",
    "wof:population":46
},
  "geometry": {"coordinates":[11.32884,45.56736],"type":"Point"}
}