{
  "type": "Feature",
  "properties": {
    "gn:admin1_code":"15.0",
    "gn:admin2_code":"TP",
    "gn:admin3_code":"81005.0",
    "gn:asciiname":"Case Castello di Baida",
    "gn:country_code":"IT",
    "gn:dem":289,
    "gn:feature_class":"P",
    "gn:feature_code":"PPLL",
    "gn:name":"Case Castello di Baida",
    "gn:population":3,
    "gn:timezone":"Europe/Rome",
    "iso:country":"IT",
    "wof:name":"Case Castello di Baida",
    "wof:placetype":"locality",
    "wof:population":3
},
  "geometry": {"coordinates":[12.79575,38.03703],"type":"Point"}
}