{
  "type": "Feature",
  "properties": {
    "gn:admin1_code":"1",
    "gn:admin2_code":"CH",
    "gn:admin3_code":"69081.0",
    "gn:asciiname":"Muffo",
    "gn:country_code":"IT",
    "gn:dem":15,
    "gn:feature_class":"P",
    "gn:feature_code":"PPL",
    "gn:name":"Muffo",
    "gn:population":204,
    "gn:timezone":"Europe/Rome",
    "iso:country":"IT",
    "wof:name":"Muffo",
    "wof:placetype":"locality",
    "wof:population":204
},
  "geometry": {"coordinates":[14.17134,42.42522],"type":"Point"}
}