{
  "type": "Feature",
  "properties": {
    "gn:elevation":420,
    "gn:population":760,
    "iso:country":"IT",
    "name:bel_x_preferred":[
        "\u0421\u0430\u043b\u0435\u043d\u0442\u0430"
    ],
    "name:bul_x_preferred":[
        "\u0421\u0430\u043b\u0435\u043d\u0442\u043e"
    ],
    "name:deu_x_preferred":[
        "Salento"
    ],
    "name:eng_x_preferred":[
        "Salento"
    ],
    "name:epo_x_preferred":[
        "Salento"
    ],
    "name:eus_x_preferred":[
        "Salento"
    ],
    "name:fas_x_preferred":[
        "\u0633\u0627\u0644\u0646\u062a\u0648"
    ],
    "name:fra_x_preferred":[
        "Salento"
    ],
    "name:hun_x_preferred":[
        "Salento"
    ],
    "name:hye_x_preferred":[
        "\u054d\u0561\u056c\u0565\u0576\u057f\u0578"
    ],
    "name:ina_x_preferred":[
        "Salento"
    ],
    "name:ita_x_preferred":[
        "Salento"
    ],
    "name:jpn_x_preferred":[
        "\u30b5\u30ec\u30f3\u30c8"
    ],
    "name:kor_x_preferred":[
        "\uc0b4\ub80c\ud1a0"
    ],
    "name:lat_x_preferred":[
        "Salentum"
    ],
    "name:lmo_x_preferred":[
        "Salento"
    ],
    "name:msa_x_preferred":[
        "Salento"
    ],
    "name:nan_x_preferred":[
        "Salento"
    ],
    "name:nap_x_preferred":[
        "Salento"
    ],
    "name:nld_x_preferred":[
        "Salento"
    ],
    "name:pms_x_preferred":[
        "Salento"
    ],
    "name:pol_x_preferred":[
        "Salento"
    ],
    "name:por_x_preferred":[
        "Salento"
    ],
    "name:ron_x_preferred":[
        "Salento"
    ],
    "name:rus_x_preferred":[
        "\u0421\u0430\u043b\u0435\u043d\u0442\u043e"
    ],
    "name:scn_x_preferred":[
        "Salentu"
    ],
    "name:spa_x_preferred":[
        "Salento"
    ],
    "name:srp_x_preferred":[
        "Salento"
    ],
    "name:ukr_x_preferred":[
        "\u0421\u0430\u043b\u0435\u043d\u0442\u043e"
    ],
    "name:uzb_x_preferred":[
        "Salento"
    ],
    "name:vie_x_preferred":[
        "Salento"
    ],
    "name:vol_x_preferred":[
        "Salento"
    ],
    "name:war_x_preferred":[
        "Salento"
    ],
    "name:zho_x_preferred":[
        "\u8428\u4f26\u6258"
    ],
    "qs:a0":"Italia",
    "qs:a1":"*Salerno",
    "qs:a1r":"0Campania",
    "qs:adm0":"Italia",
    "qs:la_lc":"*",
    "qs:level":"locality",
    "qs:loc":"Salento",
    "qs:loc_alt":"Salento",
    "qs:pop":0,
    "qs:type":"buffered point",
    "wof:lang":[
        "ita"
    ],
    "wof:name":"Salento",
    "wof:placetype":"locality",
    "wof:population":760
},
  "geometry": {"coordinates":[15.19083,40.249439],"type":"Point"}
}