{
  "type": "Feature",
  "properties": {
    "gn:admin1_code":"12",
    "gn:admin2_code":"AL",
    "gn:admin3_code":"6036.0",
    "gn:asciiname":"Viazzi",
    "gn:country_code":"IT",
    "gn:dem":214,
    "gn:feature_class":"P",
    "gn:feature_code":"PPL",
    "gn:name":"Viazzi",
    "gn:population":32,
    "gn:timezone":"Europe/Rome",
    "iso:country":"IT",
    "wof:name":"Viazzi",
    "wof:placetype":"locality",
    "wof:population":32
},
  "geometry": {"coordinates":[8.41326,44.59384],"type":"Point"}
}