{
  "type": "Feature",
  "properties": {
    "gn:admin1_code":"17.0",
    "gn:admin2_code":"BZ",
    "gn:admin3_code":"21042.0",
    "gn:asciiname":"Traga",
    "gn:country_code":"IT",
    "gn:dem":1297,
    "gn:feature_class":"P",
    "gn:feature_code":"PPL",
    "gn:name":"Traga",
    "gn:population":0,
    "gn:timezone":"Europe/Rome",
    "iso:country":"IT",
    "name:spa_x_preferred":[
        "Traga"
    ],
    "wof:name":"Traga",
    "wof:placetype":"locality"
},
  "geometry": {"coordinates":[10.68333,46.63333],"type":"Point"}
}