{
  "type": "Feature",
  "properties": {
    "gn:admin1_code":"9",
    "gn:admin2_code":"MN",
    "gn:admin3_code":"20057.0",
    "gn:asciiname":"Villanova Maiardina",
    "gn:country_code":"IT",
    "gn:dem":28,
    "gn:feature_class":"P",
    "gn:feature_code":"PPL",
    "gn:name":"Villanova Maiardina",
    "gn:population":154,
    "gn:timezone":"Europe/Rome",
    "iso:country":"IT",
    "wof:name":"Villanova Maiardina",
    "wof:placetype":"locality",
    "wof:population":154
},
  "geometry": {"coordinates":[10.83746,45.20304],"type":"Point"}
}