{
  "type": "Feature",
  "properties": {
    "gn:admin1_code":"6",
    "gn:admin2_code":"UD",
    "gn:admin3_code":"30027.0",
    "gn:asciiname":"Tessitori",
    "gn:country_code":"IT",
    "gn:dem":40,
    "gn:feature_class":"P",
    "gn:feature_code":"PPL",
    "gn:name":"Tessitori",
    "gn:population":17,
    "gn:timezone":"Europe/Rome",
    "iso:country":"IT",
    "wof:name":"Tessitori",
    "wof:placetype":"locality",
    "wof:population":17
},
  "geometry": {"coordinates":[12.99539,45.96642],"type":"Point"}
}