{
  "type": "Feature",
  "properties": {
    "gn:admin1_code":"13.0",
    "gn:admin2_code":"BR",
    "gn:admin3_code":"74001.0",
    "gn:asciiname":"Santa Maria del Casale",
    "gn:country_code":"IT",
    "gn:dem":12,
    "gn:feature_class":"P",
    "gn:feature_code":"PPL",
    "gn:name":"Santa Maria del Casale",
    "gn:population":0,
    "gn:timezone":"Europe/Rome",
    "iso:country":"IT",
    "wof:name":"Santa Maria del Casale",
    "wof:placetype":"locality"
},
  "geometry": {"coordinates":[17.935,40.6525],"type":"Point"}
}