{
  "type": "Feature",
  "properties": {
    "gn:gn_country":"IT",
    "gn:gn_fcode":"PPLA3",
    "gn:gn_pop":285,
    "gn:population":64,
    "iso:country":"IT",
    "name:ara_x_preferred":[
        "\u0633\u064a\u0633\u0627\u0645\u064a"
    ],
    "name:azb_x_preferred":[
        "\u0633\u0633\u0627\u0645\u0647"
    ],
    "name:bel_x_preferred":[
        "\u0421\u0435\u0441\u0430\u043c\u044d"
    ],
    "name:bul_x_preferred":[
        "\u0421\u0435\u0441\u0430\u043c\u0435"
    ],
    "name:cat_x_preferred":[
        "Sessame"
    ],
    "name:ceb_x_preferred":[
        "Sessame"
    ],
    "name:deu_x_preferred":[
        "Sessame"
    ],
    "name:eng_x_preferred":[
        "Sessame"
    ],
    "name:epo_x_preferred":[
        "Sessame"
    ],
    "name:eus_x_preferred":[
        "Sessame"
    ],
    "name:fas_x_preferred":[
        "\u0633\u0633\u0627\u0645\u0647"
    ],
    "name:fra_x_preferred":[
        "Sessame"
    ],
    "name:hun_x_preferred":[
        "Sessame"
    ],
    "name:hye_x_preferred":[
        "\u054d\u0565\u057d\u0561\u0574\u0565"
    ],
    "name:ind_x_preferred":[
        "Sessame"
    ],
    "name:ita_x_preferred":[
        "Sessame"
    ],
    "name:jpn_x_preferred":[
        "\u30bb\u30c3\u30b5\u30fc\u30e1"
    ],
    "name:kaz_x_preferred":[
        "\u0421\u0435\u0441\u0441\u0430\u043c\u0435"
    ],
    "name:lat_x_preferred":[
        "Sexamum"
    ],
    "name:lmo_x_preferred":[
        "Sessame"
    ],
    "name:msa_x_preferred":[
        "Sessame"
    ],
    "name:nan_x_preferred":[
        "Sessame"
    ],
    "name:nap_x_preferred":[
        "Sessame"
    ],
    "name:nld_x_preferred":[
        "Sessame"
    ],
    "name:oci_x_preferred":[
        "Sessame"
    ],
    "name:pms_x_preferred":[
        "Siam"
    ],
    "name:pol_x_preferred":[
        "Sessame"
    ],
    "name:por_x_preferred":[
        "Sessame"
    ],
    "name:ron_x_preferred":[
        "Sessame"
    ],
    "name:rus_x_preferred":[
        "\u0421\u0435\u0441\u0441\u0430\u043c\u0435"
    ],
    "name:scn_x_preferred":[
        "Sessame"
    ],
    "name:spa_x_preferred":[
        "Sessame"
    ],
    "name:srp_x_preferred":[
        "Sessame"
    ],
    "name:tgl_x_preferred":[
        "Sessame"
    ],
    "name:ukr_x_preferred":[
        "\u0421\u0435\u0441\u0441\u0430\u043c\u0435"
    ],
    "name:uzb_x_preferred":[
        "Sessame"
    ],
    "name:vie_x_preferred":[
        "Sessame"
    ],
    "name:vol_x_preferred":[
        "Sessame"
    ],
    "name:war_x_preferred":[
        "Sessame"
    ],
    "name:zho_x_preferred":[
        "\u585e\u8428\u6885"
    ],
    "qs_pg:aaroncc":"IT",
    "qs_pg:gn_country":"IT",
    "qs_pg:gn_fcode":"PPLA3",
    "qs_pg:gn_pop":285,
    "qs_pg:name":"Sessame",
    "qs_pg:name_adm0":"Italia",
    "qs_pg:name_adm1":"Piemonte",
    "qs_pg:photos_9r":0,
    "qs_pg:photos_sr":0,
    "qs_pg:pop_sr":2,
    "qs_pg:qs_pg_placetype":"locality",
    "qs_pg:qs_pg_placetype_gp":"Town",
    "qs_pg:woe_adm0":23424853,
    "woe:adm0_id":23424853,
    "woe:name_adm0":"Italia",
    "woe:name_adm1":"Piemonte",
    "woe:placetype":"Town",
    "wof:name":"Sessame",
    "wof:placetype":"locality",
    "wof:population":64
},
  "geometry": {"coordinates":[8.33684,44.67064],"type":"Point"}
}