{
  "type": "Feature",
  "properties": {
    "gn:admin1_code":"20.0",
    "gn:admin2_code":"PD",
    "gn:admin3_code":"28093.0",
    "gn:asciiname":"Case Gumirato",
    "gn:country_code":"IT",
    "gn:dem":19,
    "gn:feature_class":"P",
    "gn:feature_code":"PPL",
    "gn:name":"Case Gumirato",
    "gn:population":17,
    "gn:timezone":"Europe/Rome",
    "iso:country":"IT",
    "wof:name":"Case Gumirato",
    "wof:placetype":"locality",
    "wof:population":17
},
  "geometry": {"coordinates":[12.07916,45.61262],"type":"Point"}
}