{
  "type": "Feature",
  "properties": {
    "gn:admin1_code":"3.0",
    "gn:admin2_code":"CS",
    "gn:admin3_code":"78003.0",
    "gn:asciiname":"Satacuosco",
    "gn:country_code":"IT",
    "gn:dem":738,
    "gn:feature_class":"P",
    "gn:feature_code":"PPL",
    "gn:name":"Satacuosco",
    "gn:population":0,
    "gn:timezone":"Europe/Rome",
    "iso:country":"IT",
    "wof:name":"Satacuosco",
    "wof:placetype":"locality"
},
  "geometry": {"coordinates":[16.46667,39.53333],"type":"Point"}
}