{
  "type": "Feature",
  "properties": {
    "gn:admin1_code":"9",
    "gn:admin2_code":"BG",
    "gn:admin3_code":"16246.0",
    "gn:asciiname":"Pernice",
    "gn:country_code":"IT",
    "gn:dem":710,
    "gn:feature_class":"P",
    "gn:feature_code":"PPL",
    "gn:name":"Pernice",
    "gn:population":17,
    "gn:timezone":"Europe/Rome",
    "iso:country":"IT",
    "name:ceb_x_preferred":[
        "Pernice"
    ],
    "name:deu_x_preferred":[
        "Pernice"
    ],
    "name:fra_x_preferred":[
        "Pernice"
    ],
    "name:rus_x_preferred":[
        "\u041f\u0435\u0440\u043d\u0438\u0441"
    ],
    "name:swe_x_preferred":[
        "Pernice"
    ],
    "wof:name":"Pernice",
    "wof:placetype":"locality",
    "wof:population":17
},
  "geometry": {"coordinates":[9.66083,45.80706],"type":"Point"}
}