{
  "type": "Feature",
  "properties": {
    "gn:admin1_code":"20",
    "gn:admin2_code":"PD",
    "gn:admin3_code":"28043.0",
    "gn:asciiname":"Gorzon",
    "gn:country_code":"IT",
    "gn:dem":2,
    "gn:feature_class":"P",
    "gn:feature_code":"PPL",
    "gn:name":"Gorzon",
    "gn:population":66,
    "gn:timezone":"Europe/Rome",
    "iso:country":"IT",
    "wof:name":"Gorzon",
    "wof:placetype":"locality",
    "wof:population":66
},
  "geometry": {"coordinates":[11.71302,45.14266],"type":"Point"}
}