{
  "type": "Feature",
  "properties": {
    "gn:admin1_code":"5",
    "gn:admin2_code":"PC",
    "gn:admin3_code":"33002.0",
    "gn:asciiname":"San Rocchino",
    "gn:country_code":"IT",
    "gn:dem":113,
    "gn:feature_class":"P",
    "gn:feature_code":"PPL",
    "gn:name":"San Rocchino",
    "gn:population":39,
    "gn:timezone":"Europe/Rome",
    "iso:country":"IT",
    "wof:name":"San Rocchino",
    "wof:placetype":"locality",
    "wof:population":39
},
  "geometry": {"coordinates":[9.93508,44.88236],"type":"Point"}
}