{
  "type": "Feature",
  "properties": {
    "gn:admin1_code":"20.0",
    "gn:admin2_code":"PD",
    "gn:admin3_code":"28072.0",
    "gn:asciiname":"Villaguattera",
    "gn:country_code":"IT",
    "gn:dem":14,
    "gn:feature_class":"P",
    "gn:feature_code":"PPL",
    "gn:name":"Villaguattera",
    "gn:population":1550,
    "gn:timezone":"Europe/Rome",
    "iso:country":"IT",
    "wof:name":"Villaguattera",
    "wof:placetype":"locality",
    "wof:population":1550
},
  "geometry": {"coordinates":[11.81767,45.44409],"type":"Point"}
}