{
  "type": "Feature",
  "properties": {
    "gn:admin1_code":"15.0",
    "gn:admin2_code":"ME",
    "gn:admin3_code":"83039.0",
    "gn:asciiname":"Colla Maffone",
    "gn:country_code":"IT",
    "gn:dem":244,
    "gn:feature_class":"P",
    "gn:feature_code":"PPL",
    "gn:name":"Colla Maffone",
    "gn:population":635,
    "gn:timezone":"Europe/Rome",
    "iso:country":"IT",
    "wof:name":"Colla Maffone",
    "wof:placetype":"locality",
    "wof:population":635
},
  "geometry": {"coordinates":[14.97433,38.09366],"type":"Point"}
}