{
  "type": "Feature",
  "properties": {
    "gn:admin1_code":"4",
    "gn:admin2_code":"AV",
    "gn:admin3_code":"64050.0",
    "gn:asciiname":"Esche",
    "gn:country_code":"IT",
    "gn:dem":451,
    "gn:feature_class":"P",
    "gn:feature_code":"PPL",
    "gn:name":"Esche",
    "gn:population":83,
    "gn:timezone":"Europe/Rome",
    "iso:country":"IT",
    "wof:name":"Esche",
    "wof:placetype":"locality",
    "wof:population":83
},
  "geometry": {"coordinates":[15.01069,41.03572],"type":"Point"}
}