{
  "type": "Feature",
  "properties": {
    "gn:admin1_code":"16",
    "gn:admin2_code":"AR",
    "gn:admin3_code":"51015.0",
    "gn:asciiname":"Rimbocchi",
    "gn:country_code":"IT",
    "gn:dem":542,
    "gn:feature_class":"P",
    "gn:feature_code":"PPL",
    "gn:name":"Rimbocchi",
    "gn:population":57,
    "gn:timezone":"Europe/Rome",
    "iso:country":"IT",
    "wof:name":"Rimbocchi",
    "wof:placetype":"locality",
    "wof:population":57
},
  "geometry": {"coordinates":[11.92455,43.74683],"type":"Point"}
}