{
  "type": "Feature",
  "properties": {
    "gn:country":"IT",
    "gn:fcode":"PPLA3",
    "gn:population":194,
    "iso:country":"IT",
    "name:azb_x_preferred":[
        "\u067e\u0631\u062a\u0633\u0648"
    ],
    "name:bel_x_preferred":[
        "\u041f\u0440\u044d\u0446\u0446\u0430"
    ],
    "name:cat_x_preferred":[
        "Prezzo"
    ],
    "name:ceb_x_preferred":[
        "Prezzo"
    ],
    "name:deu_x_preferred":[
        "Prezzo"
    ],
    "name:eng_x_preferred":[
        "Prezzo"
    ],
    "name:epo_x_preferred":[
        "Prezzo"
    ],
    "name:eus_x_preferred":[
        "Prezzo"
    ],
    "name:fas_x_preferred":[
        "\u067e\u0631\u062a\u0633\u0648"
    ],
    "name:fra_x_preferred":[
        "Prezzo"
    ],
    "name:hun_x_preferred":[
        "Prezzo"
    ],
    "name:hye_x_preferred":[
        "\u054a\u0580\u0565\u0581\u0578"
    ],
    "name:ind_x_preferred":[
        "Prezzo"
    ],
    "name:ita_x_preferred":[
        "Prezzo"
    ],
    "name:jpn_x_preferred":[
        "\u30d7\u30ec\u30c3\u30c4\u30a9"
    ],
    "name:kaz_x_preferred":[
        "\u041f\u0440\u0435\u0446\u0446\u043e"
    ],
    "name:lat_x_preferred":[
        "Pretium"
    ],
    "name:lmo_x_preferred":[
        "Precc"
    ],
    "name:msa_x_preferred":[
        "Prezzo"
    ],
    "name:nap_x_preferred":[
        "Prezzo"
    ],
    "name:nld_x_preferred":[
        "Prezzo"
    ],
    "name:pms_x_preferred":[
        "Prezzo"
    ],
    "name:pol_x_preferred":[
        "Prezzo"
    ],
    "name:por_x_preferred":[
        "Prezzo"
    ],
    "name:ron_x_preferred":[
        "Prezzo"
    ],
    "name:rus_x_preferred":[
        "\u041f\u0440\u0435\u0446\u0446\u043e"
    ],
    "name:scn_x_preferred":[
        "Prezzo"
    ],
    "name:spa_x_preferred":[
        "Prezzo"
    ],
    "name:srp_x_preferred":[
        "Prezzo"
    ],
    "name:tgl_x_preferred":[
        "Prezzo"
    ],
    "name:ukr_x_preferred":[
        "\u041f\u0440\u0435\u0446\u0446\u043e"
    ],
    "name:uzb_x_preferred":[
        "Prezzo"
    ],
    "name:vie_x_preferred":[
        "Prezzo"
    ],
    "name:vol_x_preferred":[
        "Prezzo"
    ],
    "name:war_x_preferred":[
        "Prezzo"
    ],
    "qs_pg:aaroncc":"IT",
    "qs_pg:gn_country":"IT",
    "qs_pg:gn_fcode":"PPLA3",
    "qs_pg:gn_pop":194,
    "qs_pg:name":"Prezzo",
    "qs_pg:name_adm0":"Italia",
    "qs_pg:name_adm1":"Trentino-Alto Adige",
    "qs_pg:photos_9k":1,
    "qs_pg:photos_9r":4,
    "qs_pg:photos_all":184,
    "qs_pg:photos_sr":0,
    "qs_pg:pop_sr":1,
    "qs_pg:qs_pg_placetype":"locality",
    "qs_pg:qs_pg_placetype_gp":"Town",
    "qs_pg:woe_adm0":23424853,
    "woe:adm0_id":23424853,
    "woe:name_adm0":"Italia",
    "woe:name_adm1":"Trentino-Alto Adige",
    "woe:placetype":"Town",
    "wof:name":"Prezzo",
    "wof:placetype":"locality",
    "wof:population":208
},
  "geometry": {"coordinates":[10.63297,45.9347],"type":"Point"}
}