{
  "type": "Feature",
  "properties": {
    "gn:admin1_code":"1.0",
    "gn:admin2_code":"TE",
    "gn:admin3_code":"67046.0",
    "gn:asciiname":"Basto",
    "gn:country_code":"IT",
    "gn:dem":728,
    "gn:elevation":"750.0",
    "gn:feature_class":"P",
    "gn:feature_code":"PPL",
    "gn:name":"Basto",
    "gn:population":18,
    "gn:timezone":"Europe/Rome",
    "iso:country":"IT",
    "wof:name":"Basto",
    "wof:placetype":"locality",
    "wof:population":18
},
  "geometry": {"coordinates":[13.51702,42.74537],"type":"Point"}
}