{
  "type": "Feature",
  "properties": {
    "gn:admin1_code":"16",
    "gn:admin2_code":"FI",
    "gn:admin3_code":"48006.0",
    "gn:asciiname":"Case Papucci",
    "gn:country_code":"IT",
    "gn:dem":36,
    "gn:feature_class":"P",
    "gn:feature_code":"PPL",
    "gn:name":"Case Papucci",
    "gn:population":47,
    "gn:timezone":"Europe/Rome",
    "iso:country":"IT",
    "wof:name":"Case Papucci",
    "wof:placetype":"locality",
    "wof:population":47
},
  "geometry": {"coordinates":[11.1488,43.78893],"type":"Point"}
}