{
  "type": "Feature",
  "properties": {
    "gn:admin1_code":"18",
    "gn:admin2_code":"PG",
    "gn:admin3_code":"54024.0",
    "gn:asciiname":"Pian Grande",
    "gn:country_code":"IT",
    "gn:dem":439,
    "gn:feature_class":"P",
    "gn:feature_code":"PPL",
    "gn:name":"Pian Grande",
    "gn:population":65,
    "gn:timezone":"Europe/Rome",
    "iso:country":"IT",
    "wof:name":"Pian Grande",
    "wof:placetype":"locality",
    "wof:population":65
},
  "geometry": {"coordinates":[12.56382,43.33178],"type":"Point"}
}