{
  "type": "Feature",
  "properties": {
    "gn:admin1_code":"7",
    "gn:admin2_code":"RM",
    "gn:admin3_code":"58005.0",
    "gn:asciiname":"La Riccia",
    "gn:country_code":"IT",
    "gn:dem":186,
    "gn:feature_class":"P",
    "gn:feature_code":"PPL",
    "gn:name":"La Riccia",
    "gn:population":33,
    "gn:timezone":"Europe/Rome",
    "iso:country":"IT",
    "wof:name":"La Riccia",
    "wof:placetype":"locality",
    "wof:population":33
},
  "geometry": {"coordinates":[12.24544,42.03181],"type":"Point"}
}