{
  "type": "Feature",
  "properties": {
    "gn:admin1_code":"1",
    "gn:admin2_code":"CH",
    "gn:admin3_code":"69085.0",
    "gn:asciiname":"Piana delle Mele",
    "gn:country_code":"IT",
    "gn:dem":150,
    "gn:feature_class":"P",
    "gn:feature_code":"PPL",
    "gn:name":"Piana delle Mele",
    "gn:population":115,
    "gn:timezone":"Europe/Rome",
    "iso:country":"IT",
    "wof:name":"Piana delle Mele",
    "wof:placetype":"locality",
    "wof:population":115
},
  "geometry": {"coordinates":[14.35037,42.15557],"type":"Point"}
}