{
  "type": "Feature",
  "properties": {
    "gn:admin1_code":"16.0",
    "gn:admin2_code":"AR",
    "gn:admin3_code":"51017.0",
    "gn:asciiname":"Adatti",
    "gn:country_code":"IT",
    "gn:dem":662,
    "gn:feature_class":"P",
    "gn:feature_code":"PPLL",
    "gn:name":"Adatti",
    "gn:population":5,
    "gn:timezone":"Europe/Rome",
    "iso:country":"IT",
    "wof:name":"Adatti",
    "wof:placetype":"locality",
    "wof:population":5
},
  "geometry": {"coordinates":[12.08252,43.33767],"type":"Point"}
}