{
  "type": "Feature",
  "properties": {
    "gn:admin1_code":"4",
    "gn:admin2_code":"SA",
    "gn:admin3_code":"65078.0",
    "gn:asciiname":"Rosto",
    "gn:country_code":"IT",
    "gn:dem":22,
    "gn:feature_class":"P",
    "gn:feature_code":"PPL",
    "gn:name":"Rosto",
    "gn:population":24,
    "gn:timezone":"Europe/Rome",
    "iso:country":"IT",
    "wof:name":"Rosto",
    "wof:placetype":"locality",
    "wof:population":24
},
  "geometry": {"coordinates":[14.61435,40.7725],"type":"Point"}
}