{
  "type": "Feature",
  "properties": {
    "gn:admin1_code":"16.0",
    "gn:admin2_code":"SI",
    "gn:admin3_code":"52012.0",
    "gn:asciiname":"Lano",
    "gn:country_code":"IT",
    "gn:dem":273,
    "gn:elevation":"277.0",
    "gn:feature_class":"P",
    "gn:feature_code":"PPL",
    "gn:name":"Lano",
    "gn:population":53,
    "gn:timezone":"Europe/Rome",
    "iso:country":"IT",
    "name:ceb_x_preferred":[
        "Lano"
    ],
    "name:ces_x_preferred":[
        "Lano"
    ],
    "name:deu_x_preferred":[
        "Lano"
    ],
    "name:fra_x_preferred":[
        "Lano"
    ],
    "name:nld_x_preferred":[
        "Lano"
    ],
    "name:slk_x_preferred":[
        "Lano"
    ],
    "name:spa_x_preferred":[
        "Lano"
    ],
    "name:srp_x_preferred":[
        "\u041b\u0430\u043d\u043e"
    ],
    "wof:name":"Lano",
    "wof:placetype":"locality",
    "wof:population":53
},
  "geometry": {"coordinates":[11.09708,43.37434],"type":"Point"}
}