{
  "type": "Feature",
  "properties": {
    "gn:admin1_code":"2.0",
    "gn:admin2_code":"MT",
    "gn:admin3_code":"77014.0",
    "gn:asciiname":"Cementeria",
    "gn:country_code":"IT",
    "gn:dem":388,
    "gn:feature_class":"P",
    "gn:feature_code":"PPLL",
    "gn:name":"Cementeria",
    "gn:population":1,
    "gn:timezone":"Europe/Rome",
    "iso:country":"IT",
    "wof:name":"Cementeria",
    "wof:placetype":"locality",
    "wof:population":1
},
  "geometry": {"coordinates":[16.65736,40.67579],"type":"Point"}
}