{
  "type": "Feature",
  "properties": {
    "gn:admin1_code":"4.0",
    "gn:admin2_code":"SA",
    "gn:admin3_code":"65108.0",
    "gn:asciiname":"Casali-San Potito",
    "gn:country_code":"IT",
    "gn:dem":76,
    "gn:feature_class":"P",
    "gn:feature_code":"PPL",
    "gn:name":"Casali-San Potito",
    "gn:population":2761,
    "gn:timezone":"Europe/Rome",
    "iso:country":"IT",
    "wof:name":"Casali-San Potito",
    "wof:placetype":"locality",
    "wof:population":2761
},
  "geometry": {"coordinates":[14.67501,40.7639],"type":"Point"}
}