{
  "type": "Feature",
  "properties": {
    "gn:admin1_code":"5",
    "gn:admin2_code":"MO",
    "gn:admin3_code":"36046.0",
    "gn:asciiname":"Ca' de' Barozzi",
    "gn:country_code":"IT",
    "gn:dem":104,
    "gn:feature_class":"P",
    "gn:feature_code":"PPL",
    "gn:name":"Ca' de' Barozzi",
    "gn:population":305,
    "gn:timezone":"Europe/Rome",
    "iso:country":"IT",
    "wof:name":"Ca' de' Barozzi",
    "wof:placetype":"locality",
    "wof:population":305
},
  "geometry": {"coordinates":[11.00982,44.49556],"type":"Point"}
}