{
  "type": "Feature",
  "properties": {
    "gn:admin1_code":"9",
    "gn:admin2_code":"MI",
    "gn:admin3_code":"15150.0",
    "gn:asciiname":"Cascina Nuova di Campagna",
    "gn:country_code":"IT",
    "gn:dem":106,
    "gn:feature_class":"P",
    "gn:feature_code":"PPLL",
    "gn:name":"Cascina Nuova di Campagna",
    "gn:population":10,
    "gn:timezone":"Europe/Rome",
    "iso:country":"IT",
    "wof:name":"Cascina Nuova di Campagna",
    "wof:placetype":"locality",
    "wof:population":10
},
  "geometry": {"coordinates":[8.99091,45.33257],"type":"Point"}
}