{
  "type": "Feature",
  "properties": {
    "gn:admin1_code":"20",
    "gn:admin2_code":"VR",
    "gn:admin3_code":"23093.0",
    "gn:asciiname":"Maccadanzi",
    "gn:country_code":"IT",
    "gn:dem":491,
    "gn:feature_class":"P",
    "gn:feature_code":"PPLL",
    "gn:name":"Maccadanzi",
    "gn:population":10,
    "gn:timezone":"Europe/Rome",
    "iso:country":"IT",
    "wof:name":"Maccadanzi",
    "wof:placetype":"locality",
    "wof:population":10
},
  "geometry": {"coordinates":[11.20711,45.56491],"type":"Point"}
}