{
  "type": "Feature",
  "properties": {
    "gn:admin1_code":"20",
    "gn:admin2_code":"VE",
    "gn:admin3_code":"27035.0",
    "gn:asciiname":"Zinaldo",
    "gn:country_code":"IT",
    "gn:dem":8,
    "gn:feature_class":"P",
    "gn:feature_code":"PPL",
    "gn:name":"Zinaldo",
    "gn:population":138,
    "gn:timezone":"Europe/Rome",
    "iso:country":"IT",
    "wof:name":"Zinaldo",
    "wof:placetype":"locality",
    "wof:population":138
},
  "geometry": {"coordinates":[12.0259,45.49299],"type":"Point"}
}