{
  "type": "Feature",
  "properties": {
    "gn:gn_country":"IT",
    "gn:gn_fcode":"ADM3",
    "gn:gn_pop":7507,
    "gn:population":7642,
    "iso:country":"IT",
    "name:bel_x_preferred":[
        "\u0420\u044d\u043d\u043e\u043d"
    ],
    "name:bre_x_preferred":[
        "Ritten"
    ],
    "name:bul_x_preferred":[
        "\u0420\u0435\u043d\u043e\u043d"
    ],
    "name:cat_x_preferred":[
        "Ritten"
    ],
    "name:ces_x_preferred":[
        "Ritten"
    ],
    "name:deu_x_preferred":[
        "Ritten"
    ],
    "name:ell_x_preferred":[
        "\u03a1\u03af\u03c4\u03b5\u03bd"
    ],
    "name:eng_x_preferred":[
        "Renon"
    ],
    "name:eng_x_variant":[
        "Ritten"
    ],
    "name:epo_x_preferred":[
        "Ritten"
    ],
    "name:hye_x_preferred":[
        "\u054c\u0565\u0576\u0578\u0576"
    ],
    "name:ita_x_preferred":[
        "Comune di Renon - Ritten"
    ],
    "name:ita_x_variant":[
        "Renon"
    ],
    "name:jpn_x_preferred":[
        "\u30ec\u30ce\u30f3"
    ],
    "name:kaz_x_preferred":[
        "\u0420\u0435\u043d\u043e\u043d"
    ],
    "name:lat_x_preferred":[
        "Ritanum"
    ],
    "name:lmo_x_preferred":[
        "Ritan"
    ],
    "name:msa_x_preferred":[
        "Ritten"
    ],
    "name:nld_x_preferred":[
        "Ritten"
    ],
    "name:nor_x_preferred":[
        "Ritten"
    ],
    "name:pms_x_preferred":[
        "Ritten"
    ],
    "name:pol_x_preferred":[
        "Ritten"
    ],
    "name:rus_x_preferred":[
        "\u0420\u0435\u043d\u043e\u043d"
    ],
    "name:tgl_x_preferred":[
        "Ritten"
    ],
    "name:ukr_x_preferred":[
        "\u0420\u0435\u043d\u043e\u043d"
    ],
    "name:war_x_preferred":[
        "Ritten"
    ],
    "name:zho_x_preferred":[
        "\u96f7\u519c"
    ],
    "qs_pg:aaroncc":"IT",
    "qs_pg:gn_country":"IT",
    "qs_pg:gn_fcode":"ADM3",
    "qs_pg:gn_pop":7507,
    "qs_pg:name":"Renon",
    "qs_pg:name_adm0":"Italia",
    "qs_pg:name_adm1":"Trentino-Alto Adige",
    "qs_pg:photos":1627,
    "qs_pg:photos_1k":330,
    "qs_pg:photos_9k":7,
    "qs_pg:photos_9r":8,
    "qs_pg:photos_all":1627,
    "qs_pg:photos_sr":13,
    "qs_pg:pop_sr":5,
    "qs_pg:qs_pg_placetype":"locality",
    "qs_pg:qs_pg_placetype_gp":"Town",
    "qs_pg:woe_adm0":23424853,
    "woe:adm0_id":23424853,
    "woe:name_adm0":"Italia",
    "woe:name_adm1":"Trentino-Alto Adige",
    "woe:placetype":"Town",
    "wof:name":"Renon",
    "wof:placetype":"locality",
    "wof:population":7642
},
  "geometry": {"coordinates":[11.45728,46.54152],"type":"Point"}
}