{
  "type": "Feature",
  "properties": {
    "gn:admin1_code":"9",
    "gn:admin2_code":"LC",
    "gn:admin3_code":"97080.0",
    "gn:asciiname":"Sogno",
    "gn:country_code":"IT",
    "gn:dem":790,
    "gn:feature_class":"P",
    "gn:feature_code":"PPL",
    "gn:name":"Sogno",
    "gn:population":43,
    "gn:timezone":"Europe/Rome",
    "iso:country":"IT",
    "name:deu_x_preferred":[
        "Sogno"
    ],
    "name:ind_x_preferred":[
        "Sogno"
    ],
    "name:ita_x_preferred":[
        "Sogno"
    ],
    "name:nld_x_preferred":[
        "Sogno"
    ],
    "name:por_x_preferred":[
        "Sogno"
    ],
    "wof:name":"Sogno",
    "wof:placetype":"locality",
    "wof:population":43
},
  "geometry": {"coordinates":[9.48485,45.78965],"type":"Point"}
}