{
  "type": "Feature",
  "properties": {
    "gn:admin1_code":"3",
    "gn:admin2_code":"CZ",
    "gn:admin3_code":"79146.0",
    "gn:asciiname":"Cutura",
    "gn:country_code":"IT",
    "gn:dem":1271,
    "gn:feature_class":"P",
    "gn:feature_code":"PPL",
    "gn:name":"Cutura",
    "gn:population":17,
    "gn:timezone":"Europe/Rome",
    "iso:country":"IT",
    "wof:name":"Cutura",
    "wof:placetype":"locality",
    "wof:population":17
},
  "geometry": {"coordinates":[16.55234,39.08071],"type":"Point"}
}