{
  "type": "Feature",
  "properties": {
    "gn:admin1_code":"12.0",
    "gn:admin2_code":"CN",
    "gn:admin3_code":"4195.0",
    "gn:asciiname":"Loppiano",
    "gn:country_code":"IT",
    "gn:dem":461,
    "gn:feature_class":"P",
    "gn:feature_code":"PPL",
    "gn:name":"Loppiano",
    "gn:population":0,
    "gn:timezone":"Europe/Rome",
    "iso:country":"IT",
    "wof:name":"Loppiano",
    "wof:placetype":"locality"
},
  "geometry": {"coordinates":[8.01667,44.56667],"type":"Point"}
}