{
  "type": "Feature",
  "properties": {
    "gn:admin1_code":"4",
    "gn:admin2_code":"AV",
    "gn:admin3_code":"64034.0",
    "gn:asciiname":"Rapone",
    "gn:country_code":"IT",
    "gn:dem":399,
    "gn:feature_class":"P",
    "gn:feature_code":"PPL",
    "gn:name":"Rapone",
    "gn:population":118,
    "gn:timezone":"Europe/Rome",
    "iso:country":"IT",
    "wof:name":"Rapone",
    "wof:placetype":"locality",
    "wof:population":118
},
  "geometry": {"coordinates":[14.75564,40.86107],"type":"Point"}
}