{
  "type": "Feature",
  "properties": {
    "gn:admin1_code":"4",
    "gn:admin2_code":"AV",
    "gn:admin3_code":"64034.0",
    "gn:asciiname":"Rapone",
    "gn:country_code":"IT",
    "gn:dem":399,
    "gn:feature_class":"P",
    "gn:feature_code":"PPL",
    "gn:name":"Rapone",
    "gn:population":118,
    "gn:timezone":"Europe/Rome",
    "iso:country":"IT",
    "name:ara_x_preferred":[
        "\u0631\u0627\u0628\u0648\u0646\u064a"
    ],
    "name:azb_x_preferred":[
        "\u0631\u0627\u067e\u0648\u0646\u0647"
    ],
    "name:bar_x_preferred":[
        "Rapone"
    ],
    "name:bul_x_preferred":[
        "\u0420\u0430\u043f\u043e\u043d\u0435"
    ],
    "name:ceb_x_preferred":[
        "Rapone"
    ],
    "name:deu_x_preferred":[
        "Rapone"
    ],
    "name:epo_x_preferred":[
        "Rapone"
    ],
    "name:eus_x_preferred":[
        "Rapone"
    ],
    "name:fas_x_preferred":[
        "\u0631\u0627\u067e\u0648\u0646\u0647"
    ],
    "name:fra_x_preferred":[
        "Rapone"
    ],
    "name:hun_x_preferred":[
        "Rapone"
    ],
    "name:hye_x_preferred":[
        "\u054c\u0561\u057a\u0578\u0576\u0565"
    ],
    "name:ina_x_preferred":[
        "Rapone"
    ],
    "name:ita_x_preferred":[
        "Rapone"
    ],
    "name:jpn_x_preferred":[
        "\u30e9\u30dd\u30fc\u30cd"
    ],
    "name:kaz_x_preferred":[
        "\u0420\u0430\u043f\u043e\u043d\u0435"
    ],
    "name:lat_x_preferred":[
        "Rapo"
    ],
    "name:lmo_x_preferred":[
        "Rapone"
    ],
    "name:msa_x_preferred":[
        "Rapone"
    ],
    "name:nap_x_preferred":[
        "Rapone"
    ],
    "name:nld_x_preferred":[
        "Rapone"
    ],
    "name:pms_x_preferred":[
        "Rapone"
    ],
    "name:pol_x_preferred":[
        "Rapone"
    ],
    "name:por_x_preferred":[
        "Rapone"
    ],
    "name:ron_x_preferred":[
        "Rapone"
    ],
    "name:rus_x_preferred":[
        "\u0420\u0430\u043f\u043e\u043d\u0435"
    ],
    "name:scn_x_preferred":[
        "Rapuni"
    ],
    "name:spa_x_preferred":[
        "Rapone"
    ],
    "name:srp_x_preferred":[
        "\u0420\u0430\u043f\u043e\u043d\u0435"
    ],
    "name:ukr_x_preferred":[
        "\u0420\u0430\u043f\u043e\u043d\u0435"
    ],
    "name:uzb_x_preferred":[
        "Rapone"
    ],
    "name:vol_x_preferred":[
        "Rapone"
    ],
    "name:war_x_preferred":[
        "Rapone"
    ],
    "name:zho_x_preferred":[
        "\u62c9\u6ce2\u5185"
    ],
    "wof:name":"Rapone",
    "wof:placetype":"locality",
    "wof:population":118
},
  "geometry": {"coordinates":[14.75564,40.86107],"type":"Point"}
}