{
  "type": "Feature",
  "properties": {
    "gn:admin1_code":"20",
    "gn:admin2_code":"VI",
    "gn:admin3_code":"24048.0",
    "gn:asciiname":"Balzarin",
    "gn:country_code":"IT",
    "gn:dem":319,
    "gn:feature_class":"P",
    "gn:feature_code":"PPL",
    "gn:name":"Balzarin",
    "gn:population":22,
    "gn:timezone":"Europe/Rome",
    "iso:country":"IT",
    "wof:name":"Balzarin",
    "wof:placetype":"locality",
    "wof:population":22
},
  "geometry": {"coordinates":[11.41886,45.61462],"type":"Point"}
}