{
  "type": "Feature",
  "properties": {
    "gn:admin1_code":"7",
    "gn:admin2_code":"RM",
    "gn:admin3_code":"58117.0",
    "gn:asciiname":"Muratella",
    "gn:country_code":"IT",
    "gn:dem":42,
    "gn:feature_class":"P",
    "gn:feature_code":"PPL",
    "gn:name":"Muratella",
    "gn:population":38,
    "gn:timezone":"Europe/Rome",
    "iso:country":"IT",
    "wof:name":"Muratella",
    "wof:placetype":"locality",
    "wof:population":38
},
  "geometry": {"coordinates":[12.55529,41.65152],"type":"Point"}
}