{
  "type": "Feature",
  "properties": {
    "gn:admin1_code":"9",
    "gn:admin2_code":"CO",
    "gn:admin3_code":"13063.0",
    "gn:asciiname":"Veglio",
    "gn:country_code":"IT",
    "gn:dem":675,
    "gn:feature_class":"P",
    "gn:feature_code":"PPL",
    "gn:name":"Veglio",
    "gn:population":119,
    "gn:timezone":"Europe/Rome",
    "iso:country":"IT",
    "name:azb_x_preferred":[
        "\u0648\u0642\u0644\u06cc\u0648"
    ],
    "name:bel_x_preferred":[
        "\u0412\u0435\u043b\u044c\u0451"
    ],
    "name:bul_x_preferred":[
        "\u0412\u0435\u043b\u044c\u043e"
    ],
    "name:ceb_x_preferred":[
        "Veglio"
    ],
    "name:deu_x_preferred":[
        "Veglio"
    ],
    "name:epo_x_preferred":[
        "Veglio"
    ],
    "name:eus_x_preferred":[
        "Veglio"
    ],
    "name:fas_x_preferred":[
        "\u0648\u06af\u0644\u06cc\u0648"
    ],
    "name:fra_x_preferred":[
        "Veglio"
    ],
    "name:hun_x_preferred":[
        "Veglio"
    ],
    "name:hye_x_preferred":[
        "\u054e\u0565\u056c\u056b\u0578"
    ],
    "name:ind_x_preferred":[
        "Veglio"
    ],
    "name:ita_x_preferred":[
        "Veglio"
    ],
    "name:jpn_x_preferred":[
        "\u30f4\u30a7\u30fc\u30ea\u30aa"
    ],
    "name:kaz_x_preferred":[
        "\u0412\u0435\u043b\u044c\u043e"
    ],
    "name:lat_x_preferred":[
        "Velium"
    ],
    "name:lmo_x_preferred":[
        "Veglio"
    ],
    "name:msa_x_preferred":[
        "Veglio"
    ],
    "name:nap_x_preferred":[
        "Veglio"
    ],
    "name:nld_x_preferred":[
        "Veglio"
    ],
    "name:pms_x_preferred":[
        "Vej"
    ],
    "name:pol_x_preferred":[
        "Veglio"
    ],
    "name:por_x_preferred":[
        "Veglio"
    ],
    "name:ron_x_preferred":[
        "Veglio"
    ],
    "name:rus_x_preferred":[
        "\u0412\u0435\u043b\u044c\u043e"
    ],
    "name:scn_x_preferred":[
        "Veglio"
    ],
    "name:spa_x_preferred":[
        "Veglio"
    ],
    "name:srp_x_preferred":[
        "\u0412\u0435\u0459\u043e"
    ],
    "name:tgl_x_preferred":[
        "Veglio"
    ],
    "name:ukr_x_preferred":[
        "\u0412\u0435\u043b\u044c\u0439\u043e"
    ],
    "name:uzb_x_preferred":[
        "Veglio"
    ],
    "name:vie_x_preferred":[
        "Veglio"
    ],
    "name:vol_x_preferred":[
        "Veglio"
    ],
    "name:war_x_preferred":[
        "Veglio"
    ],
    "wof:name":"Veglio",
    "wof:placetype":"locality",
    "wof:population":119
},
  "geometry": {"coordinates":[9.08335,45.94884],"type":"Point"}
}