{
  "type": "Feature",
  "properties": {
    "gn:admin1_code":"9",
    "gn:admin2_code":"CO",
    "gn:admin3_code":"13063.0",
    "gn:asciiname":"Veglio",
    "gn:country_code":"IT",
    "gn:dem":675,
    "gn:feature_class":"P",
    "gn:feature_code":"PPL",
    "gn:name":"Veglio",
    "gn:population":119,
    "gn:timezone":"Europe/Rome",
    "iso:country":"IT",
    "wof:name":"Veglio",
    "wof:placetype":"locality",
    "wof:population":119
},
  "geometry": {"coordinates":[9.08335,45.94884],"type":"Point"}
}