{
  "type": "Feature",
  "properties": {
    "gn:admin1_code":"9.0",
    "gn:admin2_code":"PV",
    "gn:admin3_code":"18132.0",
    "gn:asciiname":"Canavera",
    "gn:country_code":"IT",
    "gn:dem":348,
    "gn:elevation":"350.0",
    "gn:feature_class":"P",
    "gn:feature_code":"PPL",
    "gn:name":"Canavera",
    "gn:population":51,
    "gn:timezone":"Europe/Rome",
    "iso:country":"IT",
    "wof:name":"Canavera",
    "wof:placetype":"locality",
    "wof:population":51
},
  "geometry": {"coordinates":[9.23547,44.93023],"type":"Point"}
}