{
  "type": "Feature",
  "properties": {
    "gn:admin1_code":"20",
    "gn:admin2_code":"VR",
    "gn:admin3_code":"23023.0",
    "gn:asciiname":"Cantinegirelli",
    "gn:country_code":"IT",
    "gn:dem":152,
    "gn:feature_class":"P",
    "gn:feature_code":"PPL",
    "gn:name":"Cantinegirelli",
    "gn:population":12,
    "gn:timezone":"Europe/Rome",
    "iso:country":"IT",
    "wof:name":"Cantinegirelli",
    "wof:placetype":"locality",
    "wof:population":12
},
  "geometry": {"coordinates":[10.75442,45.53047],"type":"Point"}
}