{
  "type": "Feature",
  "properties": {
    "gn:admin1_code":"9.0",
    "gn:admin2_code":"MN",
    "gn:admin3_code":"20002.0",
    "gn:asciiname":"Barchi",
    "gn:country_code":"IT",
    "gn:dem":35,
    "gn:feature_class":"P",
    "gn:feature_code":"PPL",
    "gn:name":"Barchi",
    "gn:population":201,
    "gn:timezone":"Europe/Rome",
    "iso:country":"IT",
    "name:bel_x_preferred":[
        "\u0411\u0430\u0440\u043a\u0456"
    ],
    "name:ceb_x_preferred":[
        "Barchi"
    ],
    "name:rus_x_preferred":[
        "\u0411\u0430\u0440\u043a\u0438"
    ],
    "name:srp_x_preferred":[
        "Barki"
    ],
    "name:swe_x_preferred":[
        "Barchi"
    ],
    "name:ukr_x_preferred":[
        "\u0411\u0430\u0440\u043a\u0456"
    ],
    "wof:name":"Barchi",
    "wof:placetype":"locality",
    "wof:population":201
},
  "geometry": {"coordinates":[10.42618,45.19456],"type":"Point"}
}