{
  "type": "Feature",
  "properties": {
    "gn:admin1_code":"16",
    "gn:admin2_code":"GR",
    "gn:admin3_code":"53028.0",
    "gn:asciiname":"Verziliani",
    "gn:country_code":"IT",
    "gn:dem":534,
    "gn:feature_class":"P",
    "gn:feature_code":"PPL",
    "gn:name":"Verziliani",
    "gn:population":14,
    "gn:timezone":"Europe/Rome",
    "iso:country":"IT",
    "wof:name":"Verziliani",
    "wof:placetype":"locality",
    "wof:population":14
},
  "geometry": {"coordinates":[11.56424,42.7041],"type":"Point"}
}