{
  "type": "Feature",
  "properties": {
    "gn:admin1_code":"7",
    "gn:admin2_code":"VT",
    "gn:admin3_code":"56059.0",
    "gn:asciiname":"Campolungo",
    "gn:country_code":"IT",
    "gn:dem":397,
    "gn:feature_class":"P",
    "gn:feature_code":"PPL",
    "gn:name":"Campolungo",
    "gn:population":83,
    "gn:timezone":"Europe/Rome",
    "iso:country":"IT",
    "wof:name":"Campolungo",
    "wof:placetype":"locality",
    "wof:population":83
},
  "geometry": {"coordinates":[12.10194,42.3741],"type":"Point"}
}