{
  "type": "Feature",
  "properties": {
    "gn:admin1_code":"10.0",
    "gn:admin2_code":"MC",
    "gn:admin3_code":"43049.0",
    "gn:asciiname":"Cardagnano Basso",
    "gn:country_code":"IT",
    "gn:dem":443,
    "gn:feature_class":"P",
    "gn:feature_code":"PPL",
    "gn:name":"Cardagnano Basso",
    "gn:population":21,
    "gn:timezone":"Europe/Rome",
    "iso:country":"IT",
    "wof:name":"Cardagnano Basso",
    "wof:placetype":"locality",
    "wof:population":21
},
  "geometry": {"coordinates":[13.3246,43.02225],"type":"Point"}
}