{
  "type": "Feature",
  "properties": {
    "gn:admin1_code":"3",
    "gn:admin2_code":"CS",
    "gn:admin3_code":"78016.0",
    "gn:asciiname":"Serra di Piro Paragolo",
    "gn:country_code":"IT",
    "gn:dem":857,
    "gn:feature_class":"P",
    "gn:feature_code":"PPL",
    "gn:name":"Serra di Piro Paragolo",
    "gn:population":211,
    "gn:timezone":"Europe/Rome",
    "iso:country":"IT",
    "wof:name":"Serra di Piro Paragolo",
    "wof:placetype":"locality",
    "wof:population":211
},
  "geometry": {"coordinates":[16.42741,39.11213],"type":"Point"}
}