{
  "type": "Feature",
  "properties": {
    "gn:admin1_code":"18",
    "gn:admin2_code":"PG",
    "gn:admin3_code":"54023.0",
    "gn:asciiname":"Busche",
    "gn:country_code":"IT",
    "gn:dem":510,
    "gn:feature_class":"P",
    "gn:feature_code":"PPL",
    "gn:name":"Busche",
    "gn:population":97,
    "gn:timezone":"Europe/Rome",
    "iso:country":"IT",
    "wof:name":"Busche",
    "wof:placetype":"locality",
    "wof:population":97
},
  "geometry": {"coordinates":[12.76816,43.19117],"type":"Point"}
}