{
  "type": "Feature",
  "properties": {
    "iso:country":"IT",
    "name:deu_x_preferred":[
        "Pagano"
    ],
    "name:fra_x_preferred":[
        "Pagano"
    ],
    "name:ita_x_preferred":[
        "Pagano"
    ],
    "name:rus_x_preferred":[
        "\u041f\u0430\u0433\u0430\u043d\u043e"
    ],
    "wof:name":"Pagano",
    "wof:placetype":"neighbourhood"
},
  "geometry": {"coordinates":[9.1639399456321,45.47221935168512],"type":"Point"}
}