{
  "type": "Feature",
  "properties": {
    "gn:admin1_code":"9.0",
    "gn:admin2_code":"BG",
    "gn:admin3_code":"16222.0",
    "gn:asciiname":"Via Roma-Basella",
    "gn:country_code":"IT",
    "gn:dem":190,
    "gn:feature_class":"P",
    "gn:feature_code":"PPL",
    "gn:name":"Via Roma-Basella",
    "gn:population":17,
    "gn:timezone":"Europe/Rome",
    "iso:country":"IT",
    "wof:name":"Via Roma-Basella",
    "wof:placetype":"locality",
    "wof:population":17
},
  "geometry": {"coordinates":[9.72987,45.62123],"type":"Point"}
}