{
  "type": "Feature",
  "properties": {
    "gn:admin1_code":"12",
    "gn:admin2_code":"CN",
    "gn:admin3_code":"4148.0",
    "gn:asciiname":"Tetti",
    "gn:country_code":"IT",
    "gn:dem":243,
    "gn:feature_class":"P",
    "gn:feature_code":"PPL",
    "gn:name":"Tetti",
    "gn:population":33,
    "gn:timezone":"Europe/Rome",
    "iso:country":"IT",
    "wof:name":"Tetti",
    "wof:placetype":"locality",
    "wof:population":33
},
  "geometry": {"coordinates":[8.09282,44.71938],"type":"Point"}
}