{
  "type": "Feature",
  "properties": {
    "gn:admin1_code":"18.0",
    "gn:admin2_code":"PG",
    "gn:admin3_code":"54013.0",
    "gn:asciiname":"Cinquemiglia",
    "gn:country_code":"IT",
    "gn:dem":290,
    "gn:elevation":"278.0",
    "gn:feature_class":"P",
    "gn:feature_code":"PPL",
    "gn:name":"Cinquemiglia",
    "gn:population":472,
    "gn:timezone":"Europe/Rome",
    "iso:country":"IT",
    "name:ceb_x_preferred":[
        "Cinquemiglia"
    ],
    "name:srp_x_preferred":[
        "\u0427\u0438\u043d\u043a\u0432\u0435\u043c\u0438\u0459\u0438\u0458\u0430"
    ],
    "wof:name":"Cinquemiglia",
    "wof:placetype":"locality",
    "wof:population":472
},
  "geometry": {"coordinates":[12.25903,43.37898],"type":"Point"}
}