{
  "type": "Feature",
  "properties": {
    "gn:admin1_code":"12",
    "gn:admin2_code":"BI",
    "gn:admin3_code":"96054.0",
    "gn:asciiname":"Peverano",
    "gn:country_code":"IT",
    "gn:dem":400,
    "gn:feature_class":"P",
    "gn:feature_code":"PPL",
    "gn:name":"Peverano",
    "gn:population":27,
    "gn:timezone":"Europe/Rome",
    "iso:country":"IT",
    "wof:name":"Peverano",
    "wof:placetype":"locality",
    "wof:population":27
},
  "geometry": {"coordinates":[8.07345,45.43212],"type":"Point"}
}