{
  "type": "Feature",
  "properties": {
    "gn:admin1_code":"5",
    "gn:admin2_code":"FE",
    "gn:admin3_code":"38009.0",
    "gn:asciiname":"Palazzo Maianti",
    "gn:country_code":"IT",
    "gn:dem":0,
    "gn:feature_class":"P",
    "gn:feature_code":"PPL",
    "gn:name":"Palazzo Maianti",
    "gn:population":33,
    "gn:timezone":"Europe/Rome",
    "iso:country":"IT",
    "wof:name":"Palazzo Maianti",
    "wof:placetype":"locality",
    "wof:population":33
},
  "geometry": {"coordinates":[11.85273,44.83511],"type":"Point"}
}