{
  "type": "Feature",
  "properties": {
    "gn:admin1_code":"12",
    "gn:admin2_code":"VB",
    "gn:admin3_code":"103020.0",
    "gn:asciiname":"Lunecco",
    "gn:country_code":"IT",
    "gn:dem":412,
    "gn:feature_class":"P",
    "gn:feature_code":"PPL",
    "gn:name":"Lunecco",
    "gn:population":26,
    "gn:timezone":"Europe/Rome",
    "iso:country":"IT",
    "wof:name":"Lunecco",
    "wof:placetype":"locality",
    "wof:population":26
},
  "geometry": {"coordinates":[8.60705,46.07176],"type":"Point"}
}