{
  "type": "Feature",
  "properties": {
    "gn:admin1_code":"20.0",
    "gn:admin2_code":"VI",
    "gn:admin3_code":"24079.0",
    "gn:asciiname":"Cagnano",
    "gn:country_code":"IT",
    "gn:dem":16,
    "gn:elevation":"19.0",
    "gn:feature_class":"P",
    "gn:feature_code":"PPL",
    "gn:name":"Cagnano",
    "gn:population":878,
    "gn:timezone":"Europe/Rome",
    "iso:country":"IT",
    "wof:name":"Cagnano",
    "wof:placetype":"locality",
    "wof:population":878
},
  "geometry": {"coordinates":[11.50372,45.31474],"type":"Point"}
}