{
  "type": "Feature",
  "properties": {
    "gn:admin1_code":"20.0",
    "gn:admin2_code":"VI",
    "gn:admin3_code":"24079.0",
    "gn:asciiname":"Cagnano",
    "gn:country_code":"IT",
    "gn:dem":16,
    "gn:elevation":"19.0",
    "gn:feature_class":"P",
    "gn:feature_code":"PPL",
    "gn:name":"Cagnano",
    "gn:population":878,
    "gn:timezone":"Europe/Rome",
    "iso:country":"IT",
    "name:cat_x_preferred":[
        "Cagnano"
    ],
    "name:ceb_x_preferred":[
        "Cagnano"
    ],
    "name:cos_x_preferred":[
        "Cagnanu"
    ],
    "name:deu_x_preferred":[
        "Cagnano"
    ],
    "name:eus_x_preferred":[
        "Cagnano"
    ],
    "name:fra_x_preferred":[
        "Cagnano"
    ],
    "name:hun_x_preferred":[
        "Cagnano"
    ],
    "name:ita_x_preferred":[
        "Cagnano"
    ],
    "name:kaz_x_preferred":[
        "\u041a\u0430\u043d\u044c\u044f\u043d\u043e"
    ],
    "name:lat_x_preferred":[
        "Cagnano"
    ],
    "name:lmo_x_preferred":[
        "Cagnano"
    ],
    "name:mlg_x_preferred":[
        "Cagnano"
    ],
    "name:msa_x_preferred":[
        "Cagnano"
    ],
    "name:nld_x_preferred":[
        "Cagnano"
    ],
    "name:oci_x_preferred":[
        "Cagnano"
    ],
    "name:pol_x_preferred":[
        "Cagnano"
    ],
    "name:por_x_preferred":[
        "Cagnano"
    ],
    "name:rus_x_preferred":[
        "\u041a\u0430\u043d\u044c\u044f\u043d\u043e"
    ],
    "name:slk_x_preferred":[
        "Cagnano"
    ],
    "name:slv_x_preferred":[
        "Cagnano"
    ],
    "name:spa_x_preferred":[
        "Cagnano"
    ],
    "name:srp_x_preferred":[
        "\u041a\u0430\u045a\u0430\u043d\u043e"
    ],
    "name:swe_x_preferred":[
        "Cagnano"
    ],
    "name:ukr_x_preferred":[
        "\u041a\u0430\u043d\u044c\u044f\u043d\u043e"
    ],
    "name:vie_x_preferred":[
        "Cagnano"
    ],
    "name:vol_x_preferred":[
        "Cagnano"
    ],
    "name:war_x_preferred":[
        "Cagnano"
    ],
    "wof:name":"Cagnano",
    "wof:placetype":"locality",
    "wof:population":878
},
  "geometry": {"coordinates":[11.50372,45.31474],"type":"Point"}
}