{
  "type": "Feature",
  "properties": {
    "gn:admin1_code":"1.0",
    "gn:admin2_code":"TE",
    "gn:admin3_code":"67030.0",
    "gn:asciiname":"Ripoli",
    "gn:country_code":"IT",
    "gn:dem":109,
    "gn:feature_class":"P",
    "gn:feature_code":"PPL",
    "gn:name":"Ripoli",
    "gn:population":500,
    "gn:timezone":"Europe/Rome",
    "iso:country":"IT",
    "wof:name":"Ripoli",
    "wof:placetype":"locality",
    "wof:population":500
},
  "geometry": {"coordinates":[13.89965,42.72831],"type":"Point"}
}