{
  "type": "Feature",
  "properties": {
    "gn:admin1_code":"6",
    "gn:admin2_code":"UD",
    "gn:admin3_code":"30057.0",
    "gn:asciiname":"Localita Molin Nuovo",
    "gn:country_code":"IT",
    "gn:dem":128,
    "gn:feature_class":"P",
    "gn:feature_code":"PPL",
    "gn:name":"Localit\u00e0 Molin Nuovo",
    "gn:population":18,
    "gn:timezone":"Europe/Rome",
    "iso:country":"IT",
    "name:und_x_variant":[
        "Localit\u00e0 Molin Nuovo"
    ],
    "wof:name":"Localita Molin Nuovo",
    "wof:placetype":"locality",
    "wof:population":18
},
  "geometry": {"coordinates":[13.11873,46.08694000000001],"type":"Point"}
}