{
  "type": "Feature",
  "properties": {
    "gn:admin1_code":"18",
    "gn:admin2_code":"PG",
    "gn:admin3_code":"54028.0",
    "gn:asciiname":"Pozzi",
    "gn:country_code":"IT",
    "gn:dem":312,
    "gn:feature_class":"P",
    "gn:feature_code":"PPL",
    "gn:name":"Pozzi",
    "gn:population":27,
    "gn:timezone":"Europe/Rome",
    "iso:country":"IT",
    "wof:name":"Pozzi",
    "wof:placetype":"locality",
    "wof:population":27
},
  "geometry": {"coordinates":[12.55213,42.73189],"type":"Point"}
}