{
  "type": "Feature",
  "properties": {
    "gn:admin1_code":"20.0",
    "gn:admin2_code":"VI",
    "gn:admin3_code":"24031.0",
    "gn:asciiname":"Osteria del Forcelletto",
    "gn:country_code":"IT",
    "gn:dem":1333,
    "gn:feature_class":"P",
    "gn:feature_code":"PPL",
    "gn:name":"Osteria del Forcelletto",
    "gn:population":0,
    "gn:timezone":"Europe/Rome",
    "iso:country":"IT",
    "wof:name":"Osteria del Forcelletto",
    "wof:placetype":"locality"
},
  "geometry": {"coordinates":[11.75,45.88333],"type":"Point"}
}