{
  "type": "Feature",
  "properties": {
    "gn:admin1_code":"3",
    "gn:admin2_code":"VV",
    "gn:admin3_code":"102011.0",
    "gn:asciiname":"Palermi",
    "gn:country_code":"IT",
    "gn:dem":511,
    "gn:feature_class":"P",
    "gn:feature_code":"PPL",
    "gn:name":"Palermi",
    "gn:population":57,
    "gn:timezone":"Europe/Rome",
    "iso:country":"IT",
    "wof:name":"Palermi",
    "wof:placetype":"locality",
    "wof:population":57
},
  "geometry": {"coordinates":[16.32203,38.789],"type":"Point"}
}