{
  "type": "Feature",
  "properties": {
    "gn:admin1_code":"20",
    "gn:admin2_code":"VI",
    "gn:admin3_code":"24024.0",
    "gn:asciiname":"Tavani",
    "gn:country_code":"IT",
    "gn:dem":301,
    "gn:feature_class":"P",
    "gn:feature_code":"PPL",
    "gn:name":"Tavani",
    "gn:population":15,
    "gn:timezone":"Europe/Rome",
    "iso:country":"IT",
    "name:ceb_x_preferred":[
        "Tavani"
    ],
    "name:deu_x_preferred":[
        "Tavani"
    ],
    "name:srp_x_preferred":[
        "Tavani"
    ],
    "name:swe_x_preferred":[
        "Tavani"
    ],
    "wof:name":"Tavani",
    "wof:placetype":"locality",
    "wof:population":15
},
  "geometry": {"coordinates":[11.47746,45.74812],"type":"Point"}
}