{
  "type": "Feature",
  "properties": {
    "gn:admin1_code":"12",
    "gn:admin2_code":"TO",
    "gn:admin3_code":"1059.0",
    "gn:asciiname":"Madama",
    "gn:country_code":"IT",
    "gn:dem":237,
    "gn:feature_class":"P",
    "gn:feature_code":"PPL",
    "gn:name":"Madama",
    "gn:population":27,
    "gn:timezone":"Europe/Rome",
    "iso:country":"IT",
    "name:deu_x_preferred":[
        "Madama"
    ],
    "name:fin_x_preferred":[
        "Madama"
    ],
    "name:fra_x_preferred":[
        "Madama"
    ],
    "wof:name":"Madama",
    "wof:placetype":"locality",
    "wof:population":27
},
  "geometry": {"coordinates":[7.7041,44.87637],"type":"Point"}
}