{
  "type": "Feature",
  "properties": {
    "gn:admin1_code":"15",
    "gn:admin2_code":"ME",
    "gn:admin3_code":"83033.0",
    "gn:asciiname":"Santa Lucia",
    "gn:country_code":"IT",
    "gn:dem":235,
    "gn:feature_class":"P",
    "gn:feature_code":"PPL",
    "gn:name":"Santa Lucia",
    "gn:population":86,
    "gn:timezone":"Europe/Rome",
    "iso:country":"IT",
    "wof:name":"Santa Lucia",
    "wof:placetype":"locality",
    "wof:population":86
},
  "geometry": {"coordinates":[14.90816,38.15632],"type":"Point"}
}