{
  "type": "Feature",
  "properties": {
    "gn:admin1_code":"13.0",
    "gn:admin2_code":"LE",
    "gn:admin3_code":"75043.0",
    "gn:asciiname":"Torre Saracena",
    "gn:country_code":"IT",
    "gn:dem":15,
    "gn:elevation":"17.0",
    "gn:feature_class":"P",
    "gn:feature_code":"PPL",
    "gn:name":"Torre Saracena",
    "gn:population":9,
    "gn:timezone":"Europe/Rome",
    "iso:country":"IT",
    "wof:name":"Torre Saracena",
    "wof:placetype":"locality",
    "wof:population":9
},
  "geometry": {"coordinates":[18.4312,40.25719],"type":"Point"}
}