{
  "type": "Feature",
  "properties": {
    "gn:admin1_code":"7",
    "gn:admin2_code":"VT",
    "gn:admin3_code":"56045.0",
    "gn:asciiname":"Convento Carmelitane Scalze",
    "gn:country_code":"IT",
    "gn:dem":305,
    "gn:feature_class":"P",
    "gn:feature_code":"PPL",
    "gn:name":"Convento Carmelitane Scalze",
    "gn:population":18,
    "gn:timezone":"Europe/Rome",
    "iso:country":"IT",
    "wof:name":"Convento Carmelitane Scalze",
    "wof:placetype":"locality",
    "wof:population":18
},
  "geometry": {"coordinates":[12.252,42.2675],"type":"Point"}
}