{
  "type": "Feature",
  "properties": {
    "gn:admin1_code":"20.0",
    "gn:admin2_code":"BL",
    "gn:admin3_code":"25073.0",
    "gn:asciiname":"Foppa",
    "gn:country_code":"IT",
    "gn:dem":1085,
    "gn:feature_class":"P",
    "gn:feature_code":"PPL",
    "gn:name":"Foppa",
    "gn:population":0,
    "gn:timezone":"Europe/Rome",
    "iso:country":"IT",
    "wof:name":"Foppa",
    "wof:placetype":"locality"
},
  "geometry": {"coordinates":[12.15,46.35],"type":"Point"}
}