{
  "type": "Feature",
  "properties": {
    "gn:admin1_code":"1",
    "gn:admin2_code":"CH",
    "gn:admin3_code":"69064.0",
    "gn:asciiname":"Pisavini",
    "gn:country_code":"IT",
    "gn:dem":506,
    "gn:feature_class":"P",
    "gn:feature_code":"PPL",
    "gn:name":"Pisavini",
    "gn:population":14,
    "gn:timezone":"Europe/Rome",
    "iso:country":"IT",
    "wof:name":"Pisavini",
    "wof:placetype":"locality",
    "wof:population":14
},
  "geometry": {"coordinates":[14.20817,42.15938],"type":"Point"}
}