{
  "type": "Feature",
  "properties": {
    "gn:admin1_code":"4.0",
    "gn:admin2_code":"CE",
    "gn:admin3_code":"61003.0",
    "gn:asciiname":"Alvignano",
    "gn:country_code":"IT",
    "gn:dem":133,
    "gn:elevation":"132.0",
    "gn:feature_class":"P",
    "gn:feature_code":"PPLA3",
    "gn:name":"Alvignano",
    "gn:population":3067,
    "gn:timezone":"Europe/Rome",
    "iso:country":"IT",
    "name:azb_x_preferred":[
        "\u0627\u0644\u0648\u06cc\u0642\u0646\u0627\u0646\u0648"
    ],
    "name:bul_x_preferred":[
        "\u0410\u043b\u0432\u0438\u043d\u044f\u043d\u043e"
    ],
    "name:ceb_x_preferred":[
        "Alvignano"
    ],
    "name:deu_x_preferred":[
        "Alvignano"
    ],
    "name:eng_x_preferred":[
        "Alvignano"
    ],
    "name:epo_x_preferred":[
        "Alvignano"
    ],
    "name:eus_x_preferred":[
        "Alvignano"
    ],
    "name:fas_x_preferred":[
        "\u0627\u0644\u0648\u06cc\u06af\u0646\u0627\u0646\u0648"
    ],
    "name:fra_x_preferred":[
        "Alvignano"
    ],
    "name:hun_x_preferred":[
        "Alvignano"
    ],
    "name:hye_x_preferred":[
        "\u0531\u056c\u057e\u056b\u0576\u0575\u0561\u0576\u0578"
    ],
    "name:ina_x_preferred":[
        "Alvignano"
    ],
    "name:ind_x_preferred":[
        "Alvignano"
    ],
    "name:ita_x_preferred":[
        "Alvignano"
    ],
    "name:jpn_x_preferred":[
        "\u30a2\u30eb\u30f4\u30a3\u30cb\u30e3\u30fc\u30ce"
    ],
    "name:kaz_x_preferred":[
        "\u0410\u043b\u044c\u0432\u0438\u043d\u044c\u0430\u043d\u043e"
    ],
    "name:kor_x_preferred":[
        "\uc54c\ube44\ub0d0\ub178"
    ],
    "name:lat_x_preferred":[
        "Albinianum"
    ],
    "name:lmo_x_preferred":[
        "Alvignano"
    ],
    "name:mkd_x_preferred":[
        "\u0410\u043b\u0432\u0438\u045a\u0430\u043d\u043e"
    ],
    "name:msa_x_preferred":[
        "Alvignano"
    ],
    "name:nap_x_preferred":[
        "Alvignano"
    ],
    "name:nld_x_preferred":[
        "Alvignano"
    ],
    "name:pms_x_preferred":[
        "Alvignano"
    ],
    "name:pol_x_preferred":[
        "Alvignano"
    ],
    "name:por_x_preferred":[
        "Alvignano"
    ],
    "name:ron_x_preferred":[
        "Alvignano"
    ],
    "name:rus_x_preferred":[
        "\u0410\u043b\u044c\u0432\u0438\u043d\u044c\u044f\u043d\u043e"
    ],
    "name:scn_x_preferred":[
        "Alvignanu"
    ],
    "name:spa_x_preferred":[
        "Alvignano"
    ],
    "name:srp_x_preferred":[
        "\u0410\u043b\u0432\u0438\u045a\u0430\u043d\u043e"
    ],
    "name:tgl_x_preferred":[
        "Alvignano"
    ],
    "name:ukr_x_preferred":[
        "\u0410\u043b\u044c\u0432\u0456\u043d\u044c\u044f\u043d\u043e"
    ],
    "name:uzb_x_preferred":[
        "Alvignano"
    ],
    "name:vec_x_preferred":[
        "Alvignano"
    ],
    "name:vie_x_preferred":[
        "Alvignano"
    ],
    "name:vol_x_preferred":[
        "Alvignano"
    ],
    "name:war_x_preferred":[
        "Alvignano"
    ],
    "name:zho_x_preferred":[
        "\u963f\u5c14\u7ef4\u5c3c\u4e9a\u8bfa"
    ],
    "wof:name":"Alvignano",
    "wof:placetype":"locality",
    "wof:population":3067
},
  "geometry": {"coordinates":[14.33671,41.24427],"type":"Point"}
}