{
  "type": "Feature",
  "properties": {
    "gn:admin1_code":"4.0",
    "gn:admin2_code":"CE",
    "gn:admin3_code":"61003.0",
    "gn:asciiname":"Alvignano",
    "gn:country_code":"IT",
    "gn:dem":133,
    "gn:elevation":"132.0",
    "gn:feature_class":"P",
    "gn:feature_code":"PPLA3",
    "gn:name":"Alvignano",
    "gn:population":3067,
    "gn:timezone":"Europe/Rome",
    "iso:country":"IT",
    "name:eng_x_preferred":[
        "Alvignano"
    ],
    "name:epo_x_preferred":[
        "Alvignano"
    ],
    "name:fra_x_preferred":[
        "Alvignano"
    ],
    "name:ita_x_preferred":[
        "Alvignano"
    ],
    "name:nap_x_preferred":[
        "Alvignano"
    ],
    "name:nld_x_preferred":[
        "Alvignano"
    ],
    "name:pol_x_preferred":[
        "Alvignano"
    ],
    "name:por_x_preferred":[
        "Alvignano"
    ],
    "wof:name":"Alvignano",
    "wof:placetype":"locality",
    "wof:population":3067
},
  "geometry": {"coordinates":[14.33671,41.24427],"type":"Point"}
}