{
  "type": "Feature",
  "properties": {
    "gn:admin1_code":"7",
    "gn:admin2_code":"FR",
    "gn:admin3_code":"60024.0",
    "gn:asciiname":"Casamarciano",
    "gn:country_code":"IT",
    "gn:dem":134,
    "gn:feature_class":"P",
    "gn:feature_code":"PPL",
    "gn:name":"Casamarciano",
    "gn:population":310,
    "gn:timezone":"Europe/Rome",
    "iso:country":"IT",
    "wof:name":"Casamarciano",
    "wof:placetype":"locality",
    "wof:population":310
},
  "geometry": {"coordinates":[13.35732,41.55518],"type":"Point"}
}