{
  "type": "Feature",
  "properties": {
    "gn:admin1_code":"7",
    "gn:admin2_code":"FR",
    "gn:admin3_code":"60024.0",
    "gn:asciiname":"Casamarciano",
    "gn:country_code":"IT",
    "gn:dem":134,
    "gn:feature_class":"P",
    "gn:feature_code":"PPL",
    "gn:name":"Casamarciano",
    "gn:population":310,
    "gn:timezone":"Europe/Rome",
    "iso:country":"IT",
    "name:arg_x_preferred":[
        "Casamarciano"
    ],
    "name:azb_x_preferred":[
        "\u06a9\u0627\u0633\u0627\u0645\u0627\u0631\u0633\u06cc\u0627\u0646\u0648"
    ],
    "name:bar_x_preferred":[
        "Casamarciano"
    ],
    "name:bul_x_preferred":[
        "\u041a\u0430\u0437\u0430\u043c\u0430\u0440\u0447\u0430\u043d\u043e"
    ],
    "name:ceb_x_preferred":[
        "Casamarciano"
    ],
    "name:deu_x_preferred":[
        "Casamarciano"
    ],
    "name:epo_x_preferred":[
        "Casamarciano"
    ],
    "name:eus_x_preferred":[
        "Casamarciano"
    ],
    "name:fas_x_preferred":[
        "\u06a9\u0627\u0633\u0627\u0645\u0627\u0631\u0633\u06cc\u0627\u0646\u0648"
    ],
    "name:fra_x_preferred":[
        "Casamarciano"
    ],
    "name:hun_x_preferred":[
        "Casamarciano"
    ],
    "name:hye_x_preferred":[
        "\u053f\u0561\u0566\u0561\u0574\u0561\u0580\u0579\u0561\u0576\u0578"
    ],
    "name:ina_x_preferred":[
        "Casamarciano"
    ],
    "name:ind_x_preferred":[
        "Casamarciano"
    ],
    "name:ita_x_preferred":[
        "Casamarciano"
    ],
    "name:jpn_x_preferred":[
        "\u30ab\u30b6\u30de\u30eb\u30c1\u30e3\u30fc\u30ce"
    ],
    "name:kaz_x_preferred":[
        "\u041a\u0430\u0437\u0430\u043c\u0430\u0440\u0447\u0430\u043d\u043e"
    ],
    "name:kor_x_preferred":[
        "\uce74\uc0ac\ub9c8\ub974\ucc28\ub178"
    ],
    "name:lat_x_preferred":[
        "Casamarcianum"
    ],
    "name:lmo_x_preferred":[
        "Casamarciano"
    ],
    "name:msa_x_preferred":[
        "Casamarciano"
    ],
    "name:nap_x_preferred":[
        "Casamarciano"
    ],
    "name:nld_x_preferred":[
        "Casamarciano"
    ],
    "name:pms_x_preferred":[
        "Casamarciano"
    ],
    "name:pol_x_preferred":[
        "Casamarciano"
    ],
    "name:por_x_preferred":[
        "Casamarciano"
    ],
    "name:ron_x_preferred":[
        "Casamarciano"
    ],
    "name:rus_x_preferred":[
        "\u041a\u0430\u0437\u0430\u043c\u0430\u0440\u0447\u0430\u043d\u043e"
    ],
    "name:scn_x_preferred":[
        "Casamarcianu"
    ],
    "name:spa_x_preferred":[
        "Casamarciano"
    ],
    "name:srp_x_preferred":[
        "\u041a\u0430\u0437\u0430\u043c\u0430\u0440\u0447\u0430\u043d\u043e"
    ],
    "name:tgl_x_preferred":[
        "Casamarciano"
    ],
    "name:ukr_x_preferred":[
        "\u041a\u0430\u0437\u0430\u043c\u0430\u0440\u0447\u0456\u0430\u043d\u043e"
    ],
    "name:uzb_x_preferred":[
        "Casamarciano"
    ],
    "name:vie_x_preferred":[
        "Casamarciano"
    ],
    "name:vol_x_preferred":[
        "Casamarciano"
    ],
    "name:war_x_preferred":[
        "Casamarciano"
    ],
    "name:zho_x_preferred":[
        "\u5361\u8428\u9a6c\u5c14\u6070\u8bfa"
    ],
    "wof:name":"Casamarciano",
    "wof:placetype":"locality",
    "wof:population":310
},
  "geometry": {"coordinates":[13.35732,41.55518],"type":"Point"}
}