{
  "type": "Feature",
  "properties": {
    "gn:admin1_code":"6.0",
    "gn:admin2_code":"UD",
    "gn:admin3_code":"30025.0",
    "gn:asciiname":"Piani di La",
    "gn:country_code":"IT",
    "gn:dem":687,
    "gn:feature_class":"P",
    "gn:feature_code":"PPL",
    "gn:name":"Piani di L\u00e0",
    "gn:population":34,
    "gn:timezone":"Europe/Rome",
    "iso:country":"IT",
    "wof:name":"Piani di La",
    "wof:placetype":"locality",
    "wof:population":34
},
  "geometry": {"coordinates":[13.42075,46.40249],"type":"Point"}
}