{
  "type": "Feature",
  "properties": {
    "gn:admin1_code":"3",
    "gn:admin2_code":"CS",
    "gn:admin3_code":"78034.0",
    "gn:asciiname":"Lagaro Lupinacci",
    "gn:country_code":"IT",
    "gn:dem":1160,
    "gn:feature_class":"P",
    "gn:feature_code":"PPL",
    "gn:name":"Lagar\u00f2 Lupinacci",
    "gn:population":95,
    "gn:timezone":"Europe/Rome",
    "iso:country":"IT",
    "name:und_x_variant":[
        "Lagar\u00f2 Lupinacci"
    ],
    "wof:name":"Lagaro Lupinacci",
    "wof:placetype":"locality",
    "wof:population":95
},
  "geometry": {"coordinates":[16.47018,39.41263],"type":"Point"}
}