{
  "type": "Feature",
  "properties": {
    "gn:admin1_code":"5",
    "gn:admin2_code":"PR",
    "gn:admin3_code":"34040.0",
    "gn:asciiname":"Boresasco",
    "gn:country_code":"IT",
    "gn:dem":668,
    "gn:feature_class":"P",
    "gn:feature_code":"PPL",
    "gn:name":"Boresasco",
    "gn:population":11,
    "gn:timezone":"Europe/Rome",
    "iso:country":"IT",
    "wof:name":"Boresasco",
    "wof:placetype":"locality",
    "wof:population":11
},
  "geometry": {"coordinates":[9.64538,44.458],"type":"Point"}
}