{
  "type": "Feature",
  "properties": {
    "gn:admin1_code":"1.0",
    "gn:admin2_code":"AQ",
    "gn:admin3_code":"66049.0",
    "gn:asciiname":"Filetto",
    "gn:country_code":"IT",
    "gn:dem":1066,
    "gn:elevation":"1090.0",
    "gn:feature_class":"P",
    "gn:feature_code":"PPL",
    "gn:name":"Filetto",
    "gn:population":223,
    "gn:timezone":"Europe/Rome",
    "iso:country":"IT",
    "wof:name":"Filetto",
    "wof:placetype":"locality",
    "wof:population":223
},
  "geometry": {"coordinates":[13.51988,42.37838],"type":"Point"}
}