{
  "type": "Feature",
  "properties": {
    "gn:admin1_code":"1.0",
    "gn:admin2_code":"AQ",
    "gn:admin3_code":"66049.0",
    "gn:asciiname":"Filetto",
    "gn:country_code":"IT",
    "gn:dem":1066,
    "gn:elevation":"1090.0",
    "gn:feature_class":"P",
    "gn:feature_code":"PPL",
    "gn:name":"Filetto",
    "gn:population":223,
    "gn:timezone":"Europe/Rome",
    "iso:country":"IT",
    "name:ara_x_preferred":[
        "\u0641\u064a\u0644\u064a\u062a\u0648"
    ],
    "name:azb_x_preferred":[
        "\u0641\u06cc\u0644\u062a\u0648"
    ],
    "name:bcl_x_preferred":[
        "Filetto"
    ],
    "name:bul_x_preferred":[
        "\u0424\u0438\u043b\u0435\u0442\u043e"
    ],
    "name:ceb_x_preferred":[
        "Filetto"
    ],
    "name:deu_x_preferred":[
        "Filetto"
    ],
    "name:epo_x_preferred":[
        "Filetto"
    ],
    "name:eus_x_preferred":[
        "Filetto"
    ],
    "name:fas_x_preferred":[
        "\u0641\u06cc\u0644\u062a\u0648"
    ],
    "name:fin_x_preferred":[
        "Filetto"
    ],
    "name:fra_x_preferred":[
        "Filetto"
    ],
    "name:hun_x_preferred":[
        "Filetto"
    ],
    "name:hye_x_preferred":[
        "\u0556\u056b\u056c\u0565\u057f\u0578"
    ],
    "name:ina_x_preferred":[
        "Filetto"
    ],
    "name:ita_x_preferred":[
        "Filetto"
    ],
    "name:jav_x_preferred":[
        "Filetto"
    ],
    "name:jpn_x_preferred":[
        "\u30d5\u30a3\u30ec\u30c3\u30c8"
    ],
    "name:kaz_x_preferred":[
        "\u0424\u0438\u043b\u0435\u0442\u0442\u043e"
    ],
    "name:kor_x_preferred":[
        "\ud544\ub808\ud1a0"
    ],
    "name:lat_x_preferred":[
        "Filectus"
    ],
    "name:lmo_x_preferred":[
        "Filetto"
    ],
    "name:msa_x_preferred":[
        "Filetto"
    ],
    "name:nap_x_preferred":[
        "Filetto"
    ],
    "name:nld_x_preferred":[
        "Filetto"
    ],
    "name:pms_x_preferred":[
        "Filetto"
    ],
    "name:pol_x_preferred":[
        "Filetto"
    ],
    "name:por_x_preferred":[
        "Filetto"
    ],
    "name:ron_x_preferred":[
        "Filetto"
    ],
    "name:rus_x_preferred":[
        "\u0424\u0438\u043b\u0435\u0442\u0442\u043e"
    ],
    "name:spa_x_preferred":[
        "Filetto"
    ],
    "name:srp_x_preferred":[
        "\u0424\u0438\u043b\u0435\u0442\u043e"
    ],
    "name:ukr_x_preferred":[
        "\u0424\u0456\u043b\u0435\u0442\u0442\u043e"
    ],
    "name:uzb_x_preferred":[
        "Filetto"
    ],
    "name:vol_x_preferred":[
        "Filetto"
    ],
    "name:war_x_preferred":[
        "Filetto"
    ],
    "name:zho_x_preferred":[
        "\u83f2\u83b1\u6258"
    ],
    "wof:name":"Filetto",
    "wof:placetype":"locality",
    "wof:population":223
},
  "geometry": {"coordinates":[13.51988,42.37838],"type":"Point"}
}