{
  "type": "Feature",
  "properties": {
    "gn:admin1_code":"12.0",
    "gn:admin2_code":"AL",
    "gn:admin3_code":"6018.0",
    "gn:asciiname":"Poggio Maggiore",
    "gn:country_code":"IT",
    "gn:dem":583,
    "gn:elevation":"583.0",
    "gn:feature_class":"P",
    "gn:feature_code":"PPL",
    "gn:name":"Poggio Maggiore",
    "gn:population":9,
    "gn:timezone":"Europe/Rome",
    "iso:country":"IT",
    "wof:name":"Poggio Maggiore",
    "wof:placetype":"locality",
    "wof:population":9
},
  "geometry": {"coordinates":[8.97677,44.76429],"type":"Point"}
}