{
  "type": "Feature",
  "properties": {
    "gn:admin1_code":"16",
    "gn:admin2_code":"PI",
    "gn:admin3_code":"50026.0",
    "gn:asciiname":"Case Guidotti",
    "gn:country_code":"IT",
    "gn:dem":1,
    "gn:feature_class":"P",
    "gn:feature_code":"PPL",
    "gn:name":"Case Guidotti",
    "gn:population":13,
    "gn:timezone":"Europe/Rome",
    "iso:country":"IT",
    "wof:name":"Case Guidotti",
    "wof:placetype":"locality",
    "wof:population":13
},
  "geometry": {"coordinates":[10.42076,43.67119],"type":"Point"}
}