{
  "type": "Feature",
  "properties": {
    "gn:admin1_code":"11.0",
    "gn:admin2_code":"CB",
    "gn:admin3_code":"70010.0",
    "gn:asciiname":"Nucleo Industriale Termoli",
    "gn:country_code":"IT",
    "gn:dem":7,
    "gn:feature_class":"P",
    "gn:feature_code":"PPLL",
    "gn:name":"Nucleo Industriale Termoli",
    "gn:population":0,
    "gn:timezone":"Europe/Rome",
    "iso:country":"IT",
    "wof:name":"Nucleo Industriale Termoli",
    "wof:placetype":"locality"
},
  "geometry": {"coordinates":[15.00299,41.94344],"type":"Point"}
}