{
  "type": "Feature",
  "properties": {
    "gn:admin1_code":"12",
    "gn:admin2_code":"VC",
    "gn:admin3_code":"2049.0",
    "gn:asciiname":"Porzioni",
    "gn:country_code":"IT",
    "gn:dem":149,
    "gn:feature_class":"P",
    "gn:feature_code":"PPL",
    "gn:name":"Porzioni",
    "gn:population":31,
    "gn:timezone":"Europe/Rome",
    "iso:country":"IT",
    "wof:name":"Porzioni",
    "wof:placetype":"locality",
    "wof:population":31
},
  "geometry": {"coordinates":[8.1284,45.18005],"type":"Point"}
}