{
  "type": "Feature",
  "properties": {
    "gn:admin1_code":"7",
    "gn:admin2_code":"RI",
    "gn:admin3_code":"57026.0",
    "gn:asciiname":"Acquaviva",
    "gn:country_code":"IT",
    "gn:dem":442,
    "gn:feature_class":"P",
    "gn:feature_code":"PPL",
    "gn:name":"Acquaviva",
    "gn:population":14,
    "gn:timezone":"Europe/Rome",
    "iso:country":"IT",
    "wof:name":"Acquaviva",
    "wof:placetype":"locality",
    "wof:population":14
},
  "geometry": {"coordinates":[12.67416,42.41871],"type":"Point"}
}