{
  "type": "Feature",
  "properties": {
    "gn:admin1_code":"16",
    "gn:admin2_code":"AR",
    "gn:admin3_code":"51015.0",
    "gn:asciiname":"Sarna",
    "gn:country_code":"IT",
    "gn:dem":607,
    "gn:feature_class":"P",
    "gn:feature_code":"PPL",
    "gn:name":"Sarna",
    "gn:population":15,
    "gn:timezone":"Europe/Rome",
    "iso:country":"IT",
    "name:deu_x_preferred":[
        "Sarna"
    ],
    "name:fra_x_preferred":[
        "Sarna"
    ],
    "name:ita_x_preferred":[
        "Sarna"
    ],
    "name:pol_x_preferred":[
        "Sarna"
    ],
    "name:spa_x_preferred":[
        "Sarna"
    ],
    "name:srp_x_preferred":[
        "Sarna"
    ],
    "wof:name":"Sarna",
    "wof:placetype":"locality",
    "wof:population":15
},
  "geometry": {"coordinates":[11.87251,43.68341],"type":"Point"}
}