{
  "type": "Feature",
  "properties": {
    "gn:admin1_code":"14",
    "gn:admin2_code":"SS",
    "gn:admin3_code":"90086.0",
    "gn:asciiname":"Caldeddu",
    "gn:country_code":"IT",
    "gn:dem":283,
    "gn:feature_class":"P",
    "gn:feature_code":"PPL",
    "gn:name":"Caldeddu",
    "gn:population":40,
    "gn:timezone":"Europe/Rome",
    "iso:country":"IT",
    "wof:name":"Caldeddu",
    "wof:placetype":"locality",
    "wof:population":40
},
  "geometry": {"coordinates":[8.72532,40.87179],"type":"Point"}
}