{
  "type": "Feature",
  "properties": {
    "gn:admin1_code":"6.0",
    "gn:admin2_code":"UD",
    "gn:admin3_code":"30116.0",
    "gn:asciiname":"Molinis",
    "gn:country_code":"IT",
    "gn:dem":201,
    "gn:feature_class":"P",
    "gn:feature_code":"PPL",
    "gn:name":"Molinis",
    "gn:population":0,
    "gn:timezone":"Europe/Rome",
    "iso:country":"IT",
    "name:cat_x_preferred":[
        "Molinis"
    ],
    "name:ceb_x_preferred":[
        "Molinis"
    ],
    "name:deu_x_preferred":[
        "Molinis"
    ],
    "name:epo_x_preferred":[
        "Molinis"
    ],
    "name:fra_x_preferred":[
        "Molinis"
    ],
    "name:ita_x_preferred":[
        "Molinis"
    ],
    "name:kaz_x_preferred":[
        "\u041c\u043e\u043b\u0438\u043d\u0438\u0441"
    ],
    "name:lat_x_preferred":[
        "Mulina"
    ],
    "name:lit_x_preferred":[
        "Molinisas"
    ],
    "name:lmo_x_preferred":[
        "Molinis"
    ],
    "name:msa_x_preferred":[
        "Molinis"
    ],
    "name:nld_x_preferred":[
        "Molinis"
    ],
    "name:nno_x_preferred":[
        "Molinis"
    ],
    "name:pms_x_preferred":[
        "Molinis"
    ],
    "name:por_x_preferred":[
        "Molinis"
    ],
    "name:roh_x_preferred":[
        "Molinis"
    ],
    "name:rus_x_preferred":[
        "\u041c\u043e\u043b\u0438\u043d\u0438\u0441"
    ],
    "name:spa_x_preferred":[
        "Molinis"
    ],
    "name:sqi_x_preferred":[
        "Molinis"
    ],
    "name:swe_x_preferred":[
        "Molinis"
    ],
    "name:uzb_x_preferred":[
        "Molinis"
    ],
    "name:vol_x_preferred":[
        "Molinis"
    ],
    "name:war_x_preferred":[
        "Molinis"
    ],
    "name:zho_x_preferred":[
        "\u83ab\u5229\u5c3c\u65af"
    ],
    "wof:name":"Molinis",
    "wof:placetype":"locality"
},
  "geometry": {"coordinates":[13.22944,46.20028],"type":"Point"}
}