{
  "type": "Feature",
  "properties": {
    "gn:admin1_code":"6.0",
    "gn:admin2_code":"UD",
    "gn:admin3_code":"30116.0",
    "gn:asciiname":"Molinis",
    "gn:country_code":"IT",
    "gn:dem":201,
    "gn:feature_class":"P",
    "gn:feature_code":"PPL",
    "gn:name":"Molinis",
    "gn:population":0,
    "gn:timezone":"Europe/Rome",
    "iso:country":"IT",
    "wof:name":"Molinis",
    "wof:placetype":"locality"
},
  "geometry": {"coordinates":[13.22944,46.20028],"type":"Point"}
}