{
  "type": "Feature",
  "properties": {
    "gn:admin1_code":"12.0",
    "gn:admin2_code":"TO",
    "gn:admin3_code":"1219.0",
    "gn:asciiname":"Allamano",
    "gn:country_code":"IT",
    "gn:dem":312,
    "gn:feature_class":"P",
    "gn:feature_code":"PPLL",
    "gn:name":"Allamano",
    "gn:population":4,
    "gn:timezone":"Europe/Rome",
    "iso:country":"IT",
    "wof:name":"Allamano",
    "wof:placetype":"locality",
    "wof:population":4
},
  "geometry": {"coordinates":[7.5465,45.06108],"type":"Point"}
}