{
  "type": "Feature",
  "properties": {
    "iso:country":"IT",
    "wof:name":"Valco San Paolo",
    "wof:placetype":"neighbourhood"
},
  "geometry": {"coordinates":[12.47078385267971,41.85524790515169],"type":"Point"}
}