{
  "type": "Feature",
  "properties": {
    "gn:admin1_code":"9",
    "gn:admin2_code":"LC",
    "gn:admin3_code":"97028.0",
    "gn:asciiname":"Monte Gregorio",
    "gn:country_code":"IT",
    "gn:dem":356,
    "gn:feature_class":"P",
    "gn:feature_code":"PPL",
    "gn:name":"Monte Gregorio",
    "gn:population":11,
    "gn:timezone":"Europe/Rome",
    "iso:country":"IT",
    "wof:name":"Monte Gregorio",
    "wof:placetype":"locality",
    "wof:population":11
},
  "geometry": {"coordinates":[9.30514,45.74966],"type":"Point"}
}