{
  "type": "Feature",
  "properties": {
    "gn:admin1_code":"20",
    "gn:admin2_code":"VE",
    "gn:admin3_code":"27042.0",
    "gn:asciiname":"Fontana",
    "gn:country_code":"IT",
    "gn:dem":2,
    "gn:feature_class":"P",
    "gn:feature_code":"PPL",
    "gn:name":"Fontana",
    "gn:population":142,
    "gn:timezone":"Europe/Rome",
    "iso:country":"IT",
    "wof:name":"Fontana",
    "wof:placetype":"locality",
    "wof:population":142
},
  "geometry": {"coordinates":[12.27304,45.51638],"type":"Point"}
}