{
  "type": "Feature",
  "properties": {
    "gn:admin1_code":"8",
    "gn:admin2_code":"GE",
    "gn:admin3_code":"10031.0",
    "gn:asciiname":"Scagnelli",
    "gn:country_code":"IT",
    "gn:dem":292,
    "gn:feature_class":"P",
    "gn:feature_code":"PPLL",
    "gn:name":"Scagnelli",
    "gn:population":9,
    "gn:timezone":"Europe/Rome",
    "iso:country":"IT",
    "wof:name":"Scagnelli",
    "wof:placetype":"locality",
    "wof:population":9
},
  "geometry": {"coordinates":[9.15193,44.44133],"type":"Point"}
}