{
  "type": "Feature",
  "properties": {
    "gn:admin1_code":"2",
    "gn:admin2_code":"PZ",
    "gn:admin3_code":"76063.0",
    "gn:asciiname":"Case Telesca Rinaldi",
    "gn:country_code":"IT",
    "gn:dem":747,
    "gn:feature_class":"P",
    "gn:feature_code":"PPL",
    "gn:name":"Case Telesca Rinaldi",
    "gn:population":27,
    "gn:timezone":"Europe/Rome",
    "iso:country":"IT",
    "wof:name":"Case Telesca Rinaldi",
    "wof:placetype":"locality",
    "wof:population":27
},
  "geometry": {"coordinates":[15.81153,40.67824],"type":"Point"}
}