{
  "type": "Feature",
  "properties": {
    "gn:admin1_code":"10",
    "gn:admin2_code":"PU",
    "gn:admin3_code":"41043.0",
    "gn:asciiname":"Luchino",
    "gn:country_code":"IT",
    "gn:dem":420,
    "gn:feature_class":"P",
    "gn:feature_code":"PPLL",
    "gn:name":"Luchino",
    "gn:population":8,
    "gn:timezone":"Europe/Rome",
    "iso:country":"IT",
    "wof:name":"Luchino",
    "wof:placetype":"locality",
    "wof:population":8
},
  "geometry": {"coordinates":[12.82191,43.52741],"type":"Point"}
}