{
  "type": "Feature",
  "properties": {
    "gn:admin1_code":"17",
    "gn:admin2_code":"TN",
    "gn:admin3_code":"22091.0",
    "gn:asciiname":"Gatter",
    "gn:country_code":"IT",
    "gn:dem":902,
    "gn:feature_class":"P",
    "gn:feature_code":"PPL",
    "gn:name":"Gatter",
    "gn:population":25,
    "gn:timezone":"Europe/Rome",
    "iso:country":"IT",
    "wof:name":"Gatter",
    "wof:placetype":"locality",
    "wof:population":25
},
  "geometry": {"coordinates":[11.08076,45.99128],"type":"Point"}
}