{
  "type": "Feature",
  "properties": {
    "gn:admin1_code":"1",
    "gn:admin2_code":"CH",
    "gn:admin3_code":"69058.0",
    "gn:asciiname":"Ciampino",
    "gn:country_code":"IT",
    "gn:dem":79,
    "gn:feature_class":"P",
    "gn:feature_code":"PPL",
    "gn:name":"Ciampino",
    "gn:population":79,
    "gn:timezone":"Europe/Rome",
    "iso:country":"IT",
    "name:ara_x_preferred":[
        "\u062a\u0634\u0627\u0645\u0628\u064a\u0646\u0648"
    ],
    "name:azb_x_preferred":[
        "\u0686\u0627\u0645\u067e\u06cc\u0646\u0648"
    ],
    "name:bcl_x_preferred":[
        "Ciampino"
    ],
    "name:bul_x_preferred":[
        "\u0427\u0430\u043c\u043f\u0438\u043d\u043e"
    ],
    "name:cat_x_preferred":[
        "Ciampino"
    ],
    "name:ceb_x_preferred":[
        "Ciampino"
    ],
    "name:deu_x_preferred":[
        "Ciampino"
    ],
    "name:epo_x_preferred":[
        "Ciampino"
    ],
    "name:eus_x_preferred":[
        "Ciampino"
    ],
    "name:fas_x_preferred":[
        "\u0686\u0627\u0645\u067e\u06cc\u0646\u0648"
    ],
    "name:fin_x_preferred":[
        "Ciampino"
    ],
    "name:fra_x_preferred":[
        "Ciampino"
    ],
    "name:hun_x_preferred":[
        "Ciampino"
    ],
    "name:hye_x_preferred":[
        "\u0549\u0561\u0574\u057a\u056b\u0576\u0578"
    ],
    "name:ina_x_preferred":[
        "Ciampino"
    ],
    "name:ita_x_preferred":[
        "Ciampino"
    ],
    "name:jpn_x_preferred":[
        "\u30c1\u30e3\u30f3\u30d4\u30fc\u30ce"
    ],
    "name:kaz_x_preferred":[
        "\u0427\u0430\u043c\u043f\u0438\u043d\u043e"
    ],
    "name:kir_x_preferred":[
        "\u0427\u0430\u043c\u043f\u0438\u043d\u043e"
    ],
    "name:kor_x_preferred":[
        "\ucc38\ud53c\ub178"
    ],
    "name:lat_x_preferred":[
        "Ciampinum"
    ],
    "name:lit_x_preferred":[
        "\u010campinas"
    ],
    "name:lmo_x_preferred":[
        "Ciampino"
    ],
    "name:msa_x_preferred":[
        "Ciampino"
    ],
    "name:nap_x_preferred":[
        "Ciampino"
    ],
    "name:nld_x_preferred":[
        "Ciampino"
    ],
    "name:nno_x_preferred":[
        "Ciampino"
    ],
    "name:pms_x_preferred":[
        "Ciampino"
    ],
    "name:pol_x_preferred":[
        "Ciampino"
    ],
    "name:por_x_preferred":[
        "Ciampino"
    ],
    "name:ron_x_preferred":[
        "Ciampino"
    ],
    "name:rus_x_preferred":[
        "\u0427\u0430\u043c\u043f\u0438\u043d\u043e"
    ],
    "name:scn_x_preferred":[
        "Ciampinu"
    ],
    "name:sco_x_preferred":[
        "Ciampino"
    ],
    "name:spa_x_preferred":[
        "Ciampino"
    ],
    "name:srp_x_preferred":[
        "\u0427\u0430\u043c\u043f\u0438\u043d\u043e"
    ],
    "name:swe_x_preferred":[
        "Ciampino"
    ],
    "name:ukr_x_preferred":[
        "\u0427\u0456\u0430\u043c\u043f\u0456\u043d\u043e"
    ],
    "name:urd_x_preferred":[
        "\u0686\u06cc\u0627\u0645\u067e\u06cc\u0646\u0648"
    ],
    "name:uzb_x_preferred":[
        "Ciampino"
    ],
    "name:vls_x_preferred":[
        "Ciampino"
    ],
    "name:vol_x_preferred":[
        "Ciampino"
    ],
    "name:war_x_preferred":[
        "Ciampino"
    ],
    "name:zho_x_preferred":[
        "\u94b1\u76ae\u8bfa"
    ],
    "wof:name":"Ciampino",
    "wof:placetype":"locality",
    "wof:population":79
},
  "geometry": {"coordinates":[14.40557,42.34002],"type":"Point"}
}