{
  "type": "Feature",
  "properties": {
    "gn:admin1_code":"1",
    "gn:admin2_code":"CH",
    "gn:admin3_code":"69058.0",
    "gn:asciiname":"Ciampino",
    "gn:country_code":"IT",
    "gn:dem":79,
    "gn:feature_class":"P",
    "gn:feature_code":"PPL",
    "gn:name":"Ciampino",
    "gn:population":79,
    "gn:timezone":"Europe/Rome",
    "iso:country":"IT",
    "wof:name":"Ciampino",
    "wof:placetype":"locality",
    "wof:population":79
},
  "geometry": {"coordinates":[14.40557,42.34002],"type":"Point"}
}