{
  "type": "Feature",
  "properties": {
    "gn:admin1_code":"16",
    "gn:admin2_code":"LI",
    "gn:admin3_code":"49014.0",
    "gn:asciiname":"Val di Denari",
    "gn:country_code":"IT",
    "gn:dem":52,
    "gn:feature_class":"P",
    "gn:feature_code":"PPL",
    "gn:name":"Val di Denari",
    "gn:population":30,
    "gn:timezone":"Europe/Rome",
    "iso:country":"IT",
    "wof:name":"Val di Denari",
    "wof:placetype":"locality",
    "wof:population":30
},
  "geometry": {"coordinates":[10.29982,42.80834],"type":"Point"}
}