{
  "type": "Feature",
  "properties": {
    "gn:admin1_code":"10",
    "gn:admin2_code":"AN",
    "gn:admin3_code":"42044.0",
    "gn:asciiname":"Aia Cupa",
    "gn:country_code":"IT",
    "gn:dem":368,
    "gn:feature_class":"P",
    "gn:feature_code":"PPL",
    "gn:name":"Aia Cupa",
    "gn:population":44,
    "gn:timezone":"Europe/Rome",
    "iso:country":"IT",
    "wof:name":"Aia Cupa",
    "wof:placetype":"locality",
    "wof:population":44
},
  "geometry": {"coordinates":[12.8588,43.41287],"type":"Point"}
}