{
  "type": "Feature",
  "properties": {
    "gn:admin1_code":"3.0",
    "gn:admin2_code":"CZ",
    "gn:admin3_code":"79133.0",
    "gn:asciiname":"Simeri Mare",
    "gn:country_code":"IT",
    "gn:dem":5,
    "gn:feature_class":"P",
    "gn:feature_code":"PPL",
    "gn:name":"Simeri Mare",
    "gn:population":767,
    "gn:timezone":"Europe/Rome",
    "iso:country":"IT",
    "wof:name":"Simeri Mare",
    "wof:placetype":"locality",
    "wof:population":767
},
  "geometry": {"coordinates":[16.69753,38.86502],"type":"Point"}
}