{
  "type": "Feature",
  "properties": {
    "gn:admin1_code":"5.0",
    "gn:admin2_code":"FE",
    "gn:admin3_code":"38027.0",
    "gn:asciiname":"La Chiarina",
    "gn:country_code":"IT",
    "gn:dem":-4,
    "gn:feature_class":"P",
    "gn:feature_code":"PPL",
    "gn:name":"La Chiarina",
    "gn:population":0,
    "gn:timezone":"Europe/Rome",
    "iso:country":"IT",
    "wof:name":"La Chiarina",
    "wof:placetype":"locality"
},
  "geometry": {"coordinates":[12.02028,44.77389],"type":"Point"}
}