{
  "type": "Feature",
  "properties": {
    "gn:admin1_code":"16.0",
    "gn:admin2_code":"MS",
    "gn:admin3_code":"45005.0",
    "gn:asciiname":"Castello di Camporaghena",
    "gn:country_code":"IT",
    "gn:dem":876,
    "gn:feature_class":"P",
    "gn:feature_code":"PPL",
    "gn:name":"Castello di Camporaghena",
    "gn:population":8,
    "gn:timezone":"Europe/Rome",
    "iso:country":"IT",
    "wof:name":"Castello di Camporaghena",
    "wof:placetype":"locality",
    "wof:population":8
},
  "geometry": {"coordinates":[10.16705,44.30497],"type":"Point"}
}