{
  "type": "Feature",
  "properties": {
    "gn:admin1_code":"8",
    "gn:admin2_code":"SV",
    "gn:admin3_code":"9001.0",
    "gn:asciiname":"Vigo-Peirano",
    "gn:country_code":"IT",
    "gn:dem":94,
    "gn:feature_class":"P",
    "gn:feature_code":"PPL",
    "gn:name":"Vigo-Peirano",
    "gn:population":68,
    "gn:timezone":"Europe/Rome",
    "iso:country":"IT",
    "wof:name":"Vigo-Peirano",
    "wof:placetype":"locality",
    "wof:population":68
},
  "geometry": {"coordinates":[8.20159,44.03463],"type":"Point"}
}