{
  "type": "Feature",
  "properties": {
    "gn:admin1_code":"6",
    "gn:admin2_code":"UD",
    "gn:admin3_code":"30109.0",
    "gn:asciiname":"Redenzicco",
    "gn:country_code":"IT",
    "gn:dem":84,
    "gn:feature_class":"P",
    "gn:feature_code":"PPL",
    "gn:name":"Redenzicco",
    "gn:population":60,
    "gn:timezone":"Europe/Rome",
    "iso:country":"IT",
    "wof:name":"Redenzicco",
    "wof:placetype":"locality",
    "wof:population":60
},
  "geometry": {"coordinates":[12.93185,46.0398],"type":"Point"}
}