{
  "type": "Feature",
  "properties": {
    "gn:admin1_code":"20",
    "gn:admin2_code":"PD",
    "gn:admin3_code":"28044.0",
    "gn:asciiname":"Nanetti",
    "gn:country_code":"IT",
    "gn:dem":5,
    "gn:feature_class":"P",
    "gn:feature_code":"PPL",
    "gn:name":"Nanetti",
    "gn:population":78,
    "gn:timezone":"Europe/Rome",
    "iso:country":"IT",
    "wof:name":"Nanetti",
    "wof:placetype":"locality",
    "wof:population":78
},
  "geometry": {"coordinates":[11.98434,45.32681],"type":"Point"}
}