{
  "type": "Feature",
  "properties": {
    "gn:admin1_code":"3",
    "gn:admin2_code":"KR",
    "gn:admin3_code":"101010.0",
    "gn:asciiname":"Gabella Grande",
    "gn:country_code":"IT",
    "gn:dem":6,
    "gn:feature_class":"P",
    "gn:feature_code":"PPL",
    "gn:name":"Gabella Grande",
    "gn:population":115,
    "gn:timezone":"Europe/Rome",
    "iso:country":"IT",
    "wof:name":"Gabella Grande",
    "wof:placetype":"locality",
    "wof:population":115
},
  "geometry": {"coordinates":[17.10136,39.15218],"type":"Point"}
}