{
  "type": "Feature",
  "properties": {
    "gn:admin1_code":"3.0",
    "gn:admin2_code":"RC",
    "gn:admin3_code":"80004.0",
    "gn:asciiname":"San Nicola",
    "gn:country_code":"IT",
    "gn:dem":464,
    "gn:feature_class":"P",
    "gn:feature_code":"PPL",
    "gn:name":"San Nicola",
    "gn:population":91,
    "gn:timezone":"Europe/Rome",
    "iso:country":"IT",
    "wof:name":"San Nicola",
    "wof:placetype":"locality",
    "wof:population":91
},
  "geometry": {"coordinates":[16.16016,38.29128],"type":"Point"}
}