{
  "type": "Feature",
  "properties": {
    "iso:country":"IT",
    "wof:name":"Albergheria",
    "wof:placetype":"neighbourhood"
},
  "geometry": {"coordinates":[13.35910106641365,38.1119064111022],"type":"Point"}
}