{
  "type": "Feature",
  "properties": {
    "iso:country":"IT",
    "wof:name":"Cesano Stazione",
    "wof:placetype":"neighbourhood"
},
  "geometry": {"coordinates":[12.32761819226653,42.06310620629475],"type":"Point"}
}