{
  "type": "Feature",
  "properties": {
    "gn:admin1_code":"5",
    "gn:admin2_code":"MO",
    "gn:admin3_code":"36008.0",
    "gn:asciiname":"Belvedere",
    "gn:country_code":"IT",
    "gn:dem":78,
    "gn:feature_class":"P",
    "gn:feature_code":"PPLL",
    "gn:name":"Belvedere",
    "gn:population":10,
    "gn:timezone":"Europe/Rome",
    "iso:country":"IT",
    "wof:name":"Belvedere",
    "wof:placetype":"locality",
    "wof:population":10
},
  "geometry": {"coordinates":[10.96705,44.53729000000001],"type":"Point"}
}