{
  "type": "Feature",
  "properties": {
    "gn:admin1_code":"5",
    "gn:admin2_code":"MO",
    "gn:admin3_code":"36008.0",
    "gn:asciiname":"Belvedere",
    "gn:country_code":"IT",
    "gn:dem":78,
    "gn:feature_class":"P",
    "gn:feature_code":"PPLL",
    "gn:name":"Belvedere",
    "gn:population":10,
    "gn:timezone":"Europe/Rome",
    "iso:country":"IT",
    "name:bar_x_preferred":[
        "Belvedere"
    ],
    "name:bul_x_preferred":[
        "\u0411\u0435\u043b\u0432\u0435\u0434\u0435\u0440\u0435"
    ],
    "name:cat_x_preferred":[
        "Belvedere"
    ],
    "name:ceb_x_preferred":[
        "Belvedere"
    ],
    "name:deu_x_preferred":[
        "Belvedere"
    ],
    "name:fra_x_preferred":[
        "Belvedere"
    ],
    "name:heb_x_preferred":[
        "\u05d1\u05dc\u05d5\u05d5\u05d3\u05d9\u05e8"
    ],
    "name:hun_x_preferred":[
        "Belvedere"
    ],
    "name:ind_x_preferred":[
        "Belvedere"
    ],
    "name:ita_x_preferred":[
        "Belvedere"
    ],
    "name:kor_x_preferred":[
        "\ubca8\ubca0\ub370\ub808"
    ],
    "name:lat_x_preferred":[
        "Belvederium"
    ],
    "name:lit_x_preferred":[
        "Belvederis"
    ],
    "name:nld_x_preferred":[
        "Belved\u00e8re"
    ],
    "name:pol_x_preferred":[
        "Belvedere"
    ],
    "name:por_x_preferred":[
        "Belvedere"
    ],
    "name:ron_x_preferred":[
        "Belvedere"
    ],
    "name:rus_x_preferred":[
        "\u0411\u0435\u043b\u044c\u0432\u0435\u0434\u0435\u0440"
    ],
    "name:slk_x_preferred":[
        "Belvedere"
    ],
    "name:spa_x_preferred":[
        "Belvedere"
    ],
    "name:srp_x_preferred":[
        "\u0411\u0435\u043b\u0432\u0435\u0434\u0438\u0440"
    ],
    "name:swe_x_preferred":[
        "Belvedere"
    ],
    "name:tgl_x_preferred":[
        "Belvedere"
    ],
    "name:ukr_x_preferred":[
        "\u0411\u0435\u043b\u044c\u0432\u0435\u0434\u0435\u0440"
    ],
    "name:vol_x_preferred":[
        "Belvedere"
    ],
    "wof:name":"Belvedere",
    "wof:placetype":"locality",
    "wof:population":10
},
  "geometry": {"coordinates":[10.96705,44.53729000000001],"type":"Point"}
}