{
  "type": "Feature",
  "properties": {
    "gn:admin1_code":"13.0",
    "gn:admin2_code":"TA",
    "gn:admin3_code":"73027.0",
    "gn:asciiname":"Ruberto",
    "gn:country_code":"IT",
    "gn:dem":29,
    "gn:feature_class":"P",
    "gn:feature_code":"PPL",
    "gn:name":"Ruberto",
    "gn:population":0,
    "gn:timezone":"Europe/Rome",
    "iso:country":"IT",
    "wof:name":"Ruberto",
    "wof:placetype":"locality"
},
  "geometry": {"coordinates":[17.25972,40.4625],"type":"Point"}
}