{
  "type": "Feature",
  "properties": {
    "gn:admin1_code":"12",
    "gn:admin2_code":"NO",
    "gn:admin3_code":"3106.0",
    "gn:asciiname":"Pagliate",
    "gn:country_code":"IT",
    "gn:dem":136,
    "gn:feature_class":"P",
    "gn:feature_code":"PPL",
    "gn:name":"Pagliate",
    "gn:population":43,
    "gn:timezone":"Europe/Rome",
    "iso:country":"IT",
    "wof:name":"Pagliate",
    "wof:placetype":"locality",
    "wof:population":43
},
  "geometry": {"coordinates":[8.58416,45.3953],"type":"Point"}
}