{
  "type": "Feature",
  "properties": {
    "gn:admin1_code":"7.0",
    "gn:admin2_code":"FR",
    "gn:admin3_code":"60038.0",
    "gn:asciiname":"La Selvotta-Area Industriale",
    "gn:country_code":"IT",
    "gn:dem":156,
    "gn:feature_class":"P",
    "gn:feature_code":"PPL",
    "gn:name":"La Selvotta-Area Industriale",
    "gn:population":0,
    "gn:timezone":"Europe/Rome",
    "iso:country":"IT",
    "wof:name":"La Selvotta-Area Industriale",
    "wof:placetype":"locality"
},
  "geometry": {"coordinates":[13.3016,41.6201],"type":"Point"}
}