{
  "type": "Feature",
  "properties": {
    "gn:admin1_code":"10",
    "gn:admin2_code":"AN",
    "gn:admin3_code":"42017.0",
    "gn:asciiname":"Viacce",
    "gn:country_code":"IT",
    "gn:dem":491,
    "gn:feature_class":"P",
    "gn:feature_code":"PPL",
    "gn:name":"Viacce",
    "gn:population":36,
    "gn:timezone":"Europe/Rome",
    "iso:country":"IT",
    "wof:name":"Viacce",
    "wof:placetype":"locality",
    "wof:population":36
},
  "geometry": {"coordinates":[12.7973,43.36539000000001],"type":"Point"}
}