{
  "type": "Feature",
  "properties": {
    "gn:admin1_code":"5",
    "gn:admin2_code":"BO",
    "gn:admin3_code":"37041.0",
    "gn:asciiname":"San Chierico",
    "gn:country_code":"IT",
    "gn:dem":153,
    "gn:feature_class":"P",
    "gn:feature_code":"PPL",
    "gn:name":"San Chierico",
    "gn:population":23,
    "gn:timezone":"Europe/Rome",
    "iso:country":"IT",
    "wof:name":"San Chierico",
    "wof:placetype":"locality",
    "wof:population":23
},
  "geometry": {"coordinates":[11.41758,44.36127000000001],"type":"Point"}
}