{
  "type": "Feature",
  "properties": {
    "gn:admin1_code":"4",
    "gn:admin2_code":"AV",
    "gn:admin3_code":"64008.0",
    "gn:asciiname":"Archi 2",
    "gn:country_code":"IT",
    "gn:dem":401,
    "gn:feature_class":"P",
    "gn:feature_code":"PPL",
    "gn:name":"Archi 2",
    "gn:population":54,
    "gn:timezone":"Europe/Rome",
    "iso:country":"IT",
    "wof:name":"Archi 2",
    "wof:placetype":"locality",
    "wof:population":54
},
  "geometry": {"coordinates":[14.81255,40.92755],"type":"Point"}
}