{
  "type": "Feature",
  "properties": {
    "gn:admin1_code":"6.0",
    "gn:admin2_code":"PN",
    "gn:admin3_code":"93036.0",
    "gn:asciiname":"Lovera-Ceolini",
    "gn:country_code":"IT",
    "gn:dem":76,
    "gn:feature_class":"P",
    "gn:feature_code":"PPL",
    "gn:name":"Lovera-Ceolini",
    "gn:population":67,
    "gn:timezone":"Europe/Rome",
    "iso:country":"IT",
    "wof:name":"Lovera-Ceolini",
    "wof:placetype":"locality",
    "wof:population":67
},
  "geometry": {"coordinates":[12.60334,45.99586],"type":"Point"}
}