{
  "type": "Feature",
  "properties": {
    "gn:admin1_code":"9",
    "gn:admin2_code":"BG",
    "gn:admin3_code":"16074.0",
    "gn:asciiname":"Tronchera di Mezzo",
    "gn:country_code":"IT",
    "gn:dem":327,
    "gn:feature_class":"P",
    "gn:feature_code":"PPL",
    "gn:name":"Tronchera di Mezzo",
    "gn:population":18,
    "gn:timezone":"Europe/Rome",
    "iso:country":"IT",
    "wof:name":"Tronchera di Mezzo",
    "wof:placetype":"locality",
    "wof:population":18
},
  "geometry": {"coordinates":[9.47285,45.74851],"type":"Point"}
}