{
  "type": "Feature",
  "properties": {
    "gn:country":"IT",
    "gn:fcode":"PPLX",
    "gn:population":0,
    "iso:country":"IT",
    "name:azb_x_preferred":[
        "\u0645\u06cc\u0644\u0627\u0646\u0648 \u062f\u0648\u0626\u0647"
    ],
    "name:ceb_x_preferred":[
        "Milano Due"
    ],
    "name:eng_x_preferred":[
        "Milano Due"
    ],
    "name:fas_x_preferred":[
        "\u0645\u06cc\u0644\u0627\u0646\u0648 \u062f\u0648\u0626\u0647"
    ],
    "name:fra_x_preferred":[
        "Milano Due"
    ],
    "name:hun_x_preferred":[
        "Milano Due"
    ],
    "name:ita_x_preferred":[
        "Milano Due"
    ],
    "name:jpn_x_preferred":[
        "\u30df\u30e9\u30ce\u30fb\u30c9\u30a5\u30fc\u30a8"
    ],
    "name:nld_x_preferred":[
        "Milano Due"
    ],
    "name:spa_x_preferred":[
        "Milano Due"
    ],
    "name:zho_x_preferred":[
        "\u7c73\u51702"
    ],
    "qs_pg:aaroncc":"IT",
    "qs_pg:gn_country":"IT",
    "qs_pg:gn_fcode":"PPLX",
    "qs_pg:gn_pop":0,
    "qs_pg:name":"Milano Due",
    "qs_pg:name_adm0":"Italia",
    "qs_pg:name_adm1":"Lombardia",
    "qs_pg:photos":95,
    "qs_pg:photos_1k":19,
    "qs_pg:photos_9k":1,
    "qs_pg:photos_9r":3,
    "qs_pg:photos_all":95,
    "qs_pg:photos_sr":3,
    "qs_pg:pop_sr":0,
    "qs_pg:qs_pg_placetype":"locality_gp_neighbourhood_gn",
    "qs_pg:qs_pg_placetype_gp":"Town",
    "qs_pg:woe_adm0":23424853,
    "woe:adm0_id":23424853,
    "woe:name_adm0":"Italia",
    "woe:name_adm1":"Lombardia",
    "woe:placetype":"Town",
    "wof:name":"Milano Due",
    "wof:placetype":"locality"
},
  "geometry": {"coordinates":[9.26577,45.49979],"type":"Point"}
}