{
  "type": "Feature",
  "properties": {
    "gn:admin1_code":"1.0",
    "gn:admin2_code":"CH",
    "gn:admin3_code":"69092.0",
    "gn:asciiname":"San Giovanni",
    "gn:country_code":"IT",
    "gn:dem":686,
    "gn:feature_class":"P",
    "gn:feature_code":"PPL",
    "gn:name":"San Giovanni",
    "gn:population":448,
    "gn:timezone":"Europe/Rome",
    "iso:country":"IT",
    "name:ceb_x_preferred":[
        "San Giovanni"
    ],
    "name:ces_x_preferred":[
        "San Giovanni"
    ],
    "name:deu_x_preferred":[
        "San Giovanni"
    ],
    "name:epo_x_preferred":[
        "San Giovanni"
    ],
    "name:fas_x_preferred":[
        "\u0633\u0646 \u062c\u06cc\u0648\u0648\u0627\u0646\u06cc"
    ],
    "name:ita_x_preferred":[
        "San Giovanni"
    ],
    "name:nld_x_preferred":[
        "San Giovanni"
    ],
    "name:pol_x_preferred":[
        "San Giovanni"
    ],
    "name:por_x_preferred":[
        "San Giovanni"
    ],
    "name:rus_x_preferred":[
        "\u0421\u0430\u043d-\u0414\u0436\u043e\u0432\u0430\u043d\u043d\u0438"
    ],
    "name:sco_x_preferred":[
        "San Giovanni"
    ],
    "name:srp_x_preferred":[
        "San \u0110ovani"
    ],
    "name:swe_x_preferred":[
        "San Giovanni"
    ],
    "wof:name":"San Giovanni",
    "wof:placetype":"locality",
    "wof:population":448
},
  "geometry": {"coordinates":[14.42015,42.01915],"type":"Point"}
}