{
  "type": "Feature",
  "properties": {
    "gn:admin1_code":"1.0",
    "gn:admin2_code":"CH",
    "gn:admin3_code":"69092.0",
    "gn:asciiname":"San Giovanni",
    "gn:country_code":"IT",
    "gn:dem":686,
    "gn:feature_class":"P",
    "gn:feature_code":"PPL",
    "gn:name":"San Giovanni",
    "gn:population":448,
    "gn:timezone":"Europe/Rome",
    "iso:country":"IT",
    "wof:name":"San Giovanni",
    "wof:placetype":"locality",
    "wof:population":448
},
  "geometry": {"coordinates":[14.42015,42.01915],"type":"Point"}
}