{
  "type": "Feature",
  "properties": {
    "gn:admin1_code":"9",
    "gn:admin2_code":"BG",
    "gn:admin3_code":"16253.0",
    "gn:asciiname":"Tesotti",
    "gn:country_code":"IT",
    "gn:dem":543,
    "gn:feature_class":"P",
    "gn:feature_code":"PPL",
    "gn:name":"Tesotti",
    "gn:population":36,
    "gn:timezone":"Europe/Rome",
    "iso:country":"IT",
    "wof:name":"Tesotti",
    "wof:placetype":"locality",
    "wof:population":36
},
  "geometry": {"coordinates":[9.5915,45.83298],"type":"Point"}
}