{
  "type": "Feature",
  "properties": {
    "gn:admin1_code":"5",
    "gn:admin2_code":"MO",
    "gn:admin3_code":"36038.0",
    "gn:asciiname":"Tre Case",
    "gn:country_code":"IT",
    "gn:dem":16,
    "gn:feature_class":"P",
    "gn:feature_code":"PPL",
    "gn:name":"Tre Case",
    "gn:population":25,
    "gn:timezone":"Europe/Rome",
    "iso:country":"IT",
    "wof:name":"Tre Case",
    "wof:placetype":"locality",
    "wof:population":25
},
  "geometry": {"coordinates":[11.01468,44.90245],"type":"Point"}
}