{
  "type": "Feature",
  "properties": {
    "gn:admin1_code":"10.0",
    "gn:admin2_code":"PU",
    "gn:admin3_code":"41067.0",
    "gn:asciiname":"Armellina",
    "gn:country_code":"IT",
    "gn:dem":130,
    "gn:feature_class":"P",
    "gn:feature_code":"PPL",
    "gn:name":"Armellina",
    "gn:population":17,
    "gn:timezone":"Europe/Rome",
    "iso:country":"IT",
    "wof:name":"Armellina",
    "wof:placetype":"locality",
    "wof:population":17
},
  "geometry": {"coordinates":[12.68729,43.78057],"type":"Point"}
}