{
  "type": "Feature",
  "properties": {
    "gn:admin1_code":"16",
    "gn:admin2_code":"SI",
    "gn:admin3_code":"52016.0",
    "gn:asciiname":"Case Operaie",
    "gn:country_code":"IT",
    "gn:dem":241,
    "gn:feature_class":"P",
    "gn:feature_code":"PPL",
    "gn:name":"Case Operaie",
    "gn:population":26,
    "gn:timezone":"Europe/Rome",
    "iso:country":"IT",
    "wof:name":"Case Operaie",
    "wof:placetype":"locality",
    "wof:population":26
},
  "geometry": {"coordinates":[11.27603,43.38804],"type":"Point"}
}