{
  "type": "Feature",
  "properties": {
    "gn:admin1_code":"3.0",
    "gn:admin2_code":"CZ",
    "gn:admin3_code":"79011.0",
    "gn:asciiname":"Sabatino",
    "gn:cc2":"IT",
    "gn:country_code":"IT",
    "gn:dem":358,
    "gn:feature_class":"P",
    "gn:feature_code":"PPL",
    "gn:name":"Sabatino",
    "gn:population":0,
    "gn:timezone":"Europe/Rome",
    "iso:country":"IT",
    "name:und_x_variant":[
        "Casino Sabatino",
        "Casa Sabatino",
        "Sabatino"
    ],
    "wof:name":"Sabatino",
    "wof:placetype":"locality"
},
  "geometry": {"coordinates":[16.51667,38.81667],"type":"Point"}
}