{
  "type": "Feature",
  "properties": {
    "gn:admin1_code":"5",
    "gn:admin2_code":"RE",
    "gn:admin3_code":"35016.0",
    "gn:asciiname":"Frascaro",
    "gn:country_code":"IT",
    "gn:dem":650,
    "gn:feature_class":"P",
    "gn:feature_code":"PPL",
    "gn:name":"Frascaro",
    "gn:population":66,
    "gn:timezone":"Europe/Rome",
    "iso:country":"IT",
    "name:ara_x_preferred":[
        "\u0641\u0631\u0627\u0633\u0643\u0627\u0631\u0648"
    ],
    "name:azb_x_preferred":[
        "\u0641\u0631\u0627\u0633\u0627\u0631\u0648"
    ],
    "name:bel_x_preferred":[
        "\u0424\u0440\u0430\u0441\u043a\u0430\u0440\u0430"
    ],
    "name:bul_x_preferred":[
        "\u0424\u0440\u0430\u0441\u043a\u0430\u0440\u043e"
    ],
    "name:cat_x_preferred":[
        "Frascaro"
    ],
    "name:ceb_x_preferred":[
        "Frascaro"
    ],
    "name:deu_x_preferred":[
        "Frascaro"
    ],
    "name:epo_x_preferred":[
        "Frascaro"
    ],
    "name:eus_x_preferred":[
        "Frascaro"
    ],
    "name:fas_x_preferred":[
        "\u0641\u0631\u0627\u0633\u0627\u0631\u0648"
    ],
    "name:fra_x_preferred":[
        "Frascaro"
    ],
    "name:hun_x_preferred":[
        "Frascaro"
    ],
    "name:hye_x_preferred":[
        "\u0556\u0580\u0561\u057d\u056f\u0561\u0580\u0578"
    ],
    "name:ind_x_preferred":[
        "Frascaro"
    ],
    "name:ita_x_preferred":[
        "Frascaro"
    ],
    "name:jpn_x_preferred":[
        "\u30d5\u30e9\u30b9\u30ab\u30fc\u30ed"
    ],
    "name:kaz_x_preferred":[
        "\u0424\u0440\u0430\u0441\u043a\u0430\u0440\u043e"
    ],
    "name:lat_x_preferred":[
        "Frascarium"
    ],
    "name:lmo_x_preferred":[
        "Frascaro"
    ],
    "name:msa_x_preferred":[
        "Frascaro"
    ],
    "name:nap_x_preferred":[
        "Frascaro"
    ],
    "name:nld_x_preferred":[
        "Frascaro"
    ],
    "name:pms_x_preferred":[
        "Frasch\u00e9"
    ],
    "name:pol_x_preferred":[
        "Frascaro"
    ],
    "name:por_x_preferred":[
        "Frascaro"
    ],
    "name:ron_x_preferred":[
        "Frascaro"
    ],
    "name:rus_x_preferred":[
        "\u0424\u0440\u0430\u0441\u043a\u0430\u0440\u043e"
    ],
    "name:scn_x_preferred":[
        "Frascaro"
    ],
    "name:spa_x_preferred":[
        "Frascaro"
    ],
    "name:srp_x_preferred":[
        "\u0424\u0440\u0430\u0441\u043a\u0430\u0440\u043e"
    ],
    "name:tgl_x_preferred":[
        "Frascaro"
    ],
    "name:ukr_x_preferred":[
        "\u0424\u0440\u0430\u0441\u043a\u0430\u0440\u043e"
    ],
    "name:uzb_x_preferred":[
        "Frascaro"
    ],
    "name:vie_x_preferred":[
        "Frascaro"
    ],
    "name:vol_x_preferred":[
        "Frascaro"
    ],
    "name:war_x_preferred":[
        "Frascaro"
    ],
    "name:zho_x_preferred":[
        "\u5f17\u62c9\u65af\u5361\u7f57"
    ],
    "wof:name":"Frascaro",
    "wof:placetype":"locality",
    "wof:population":66
},
  "geometry": {"coordinates":[10.37658,44.44082],"type":"Point"}
}