{
  "type": "Feature",
  "properties": {
    "gn:admin1_code":"5",
    "gn:admin2_code":"RE",
    "gn:admin3_code":"35016.0",
    "gn:asciiname":"Frascaro",
    "gn:country_code":"IT",
    "gn:dem":650,
    "gn:feature_class":"P",
    "gn:feature_code":"PPL",
    "gn:name":"Frascaro",
    "gn:population":66,
    "gn:timezone":"Europe/Rome",
    "iso:country":"IT",
    "wof:name":"Frascaro",
    "wof:placetype":"locality",
    "wof:population":66
},
  "geometry": {"coordinates":[10.37658,44.44082],"type":"Point"}
}