{
  "type": "Feature",
  "properties": {
    "gn:admin1_code":"7",
    "gn:admin2_code":"VT",
    "gn:admin3_code":"56038.0",
    "gn:asciiname":"Via Monte Pogliano",
    "gn:country_code":"IT",
    "gn:dem":254,
    "gn:feature_class":"P",
    "gn:feature_code":"PPL",
    "gn:name":"Via Monte Pogliano",
    "gn:population":44,
    "gn:timezone":"Europe/Rome",
    "iso:country":"IT",
    "wof:name":"Via Monte Pogliano",
    "wof:placetype":"locality",
    "wof:population":44
},
  "geometry": {"coordinates":[12.31258,42.18918],"type":"Point"}
}