{
  "type": "Feature",
  "properties": {
    "gn:admin1_code":"20",
    "gn:admin2_code":"VR",
    "gn:admin3_code":"23098.0",
    "gn:asciiname":"Massarina",
    "gn:country_code":"IT",
    "gn:dem":25,
    "gn:feature_class":"P",
    "gn:feature_code":"PPL",
    "gn:name":"Massarina",
    "gn:population":22,
    "gn:timezone":"Europe/Rome",
    "iso:country":"IT",
    "name:ceb_x_preferred":[
        "Massarina"
    ],
    "name:pol_x_preferred":[
        "Massarina"
    ],
    "name:swe_x_preferred":[
        "Massarina"
    ],
    "name:war_x_preferred":[
        "Massarina"
    ],
    "wof:name":"Massarina",
    "wof:placetype":"locality",
    "wof:population":22
},
  "geometry": {"coordinates":[11.32796,45.37058],"type":"Point"}
}