{
  "type": "Feature",
  "properties": {
    "gn:admin1_code":"3",
    "gn:admin2_code":"VV",
    "gn:admin3_code":"102002.0",
    "gn:asciiname":"Castellina",
    "gn:country_code":"IT",
    "gn:dem":742,
    "gn:feature_class":"P",
    "gn:feature_code":"PPL",
    "gn:name":"Castellina",
    "gn:population":122,
    "gn:timezone":"Europe/Rome",
    "iso:country":"IT",
    "name:ceb_x_preferred":[
        "Castellina"
    ],
    "name:deu_x_preferred":[
        "Castellina"
    ],
    "name:fra_x_preferred":[
        "Castellina"
    ],
    "name:ita_x_preferred":[
        "Castellina"
    ],
    "name:lat_x_preferred":[
        "Castellina"
    ],
    "name:srp_x_preferred":[
        "Kastelina"
    ],
    "name:swe_x_preferred":[
        "Castellina"
    ],
    "wof:name":"Castellina",
    "wof:placetype":"locality",
    "wof:population":122
},
  "geometry": {"coordinates":[16.22866,38.53865],"type":"Point"}
}