{
  "type": "Feature",
  "properties": {
    "gn:admin1_code":"16",
    "gn:admin2_code":"AR",
    "gn:admin3_code":"51039.0",
    "gn:asciiname":"Il Piano",
    "gn:country_code":"IT",
    "gn:dem":247,
    "gn:feature_class":"P",
    "gn:feature_code":"PPL",
    "gn:name":"Il Piano",
    "gn:population":31,
    "gn:timezone":"Europe/Rome",
    "iso:country":"IT",
    "wof:name":"Il Piano",
    "wof:placetype":"locality",
    "wof:population":31
},
  "geometry": {"coordinates":[11.64846,43.51628],"type":"Point"}
}