{
  "type": "Feature",
  "properties": {
    "gn:admin1_code":"16.0",
    "gn:admin2_code":"LU",
    "gn:admin3_code":"46024.0",
    "gn:asciiname":"Metati Rossi Alti",
    "gn:country_code":"IT",
    "gn:dem":236,
    "gn:feature_class":"P",
    "gn:feature_code":"PPL",
    "gn:name":"Metati Rossi Alti",
    "gn:population":13,
    "gn:timezone":"Europe/Rome",
    "iso:country":"IT",
    "wof:name":"Metati Rossi Alti",
    "wof:placetype":"locality",
    "wof:population":13
},
  "geometry": {"coordinates":[10.18369,44.00488],"type":"Point"}
}