{
  "type": "Feature",
  "properties": {
    "gn:admin1_code":"7",
    "gn:admin2_code":"VT",
    "gn:admin3_code":"56045.0",
    "gn:asciiname":"Localita Campo Maggiore",
    "gn:country_code":"IT",
    "gn:dem":254,
    "gn:feature_class":"P",
    "gn:feature_code":"PPL",
    "gn:name":"Localit\u00e0 Campo Maggiore",
    "gn:population":35,
    "gn:timezone":"Europe/Rome",
    "iso:country":"IT",
    "name:und_x_variant":[
        "Localit\u00e0 Campo Maggiore"
    ],
    "wof:name":"Localita Campo Maggiore",
    "wof:placetype":"locality",
    "wof:population":35
},
  "geometry": {"coordinates":[12.29189,42.25901],"type":"Point"}
}