{
  "type": "Feature",
  "properties": {
    "gn:admin1_code":"20",
    "gn:admin2_code":"TV",
    "gn:admin3_code":"26014.0",
    "gn:asciiname":"Costalunga",
    "gn:country_code":"IT",
    "gn:dem":253,
    "gn:feature_class":"P",
    "gn:feature_code":"PPL",
    "gn:name":"Costalunga",
    "gn:population":41,
    "gn:timezone":"Europe/Rome",
    "iso:country":"IT",
    "wof:name":"Costalunga",
    "wof:placetype":"locality",
    "wof:population":41
},
  "geometry": {"coordinates":[11.90447,45.84817],"type":"Point"}
}