{
  "type": "Feature",
  "properties": {
    "gn:admin1_code":"5.0",
    "gn:admin2_code":"MO",
    "gn:admin3_code":"36039.0",
    "gn:asciiname":"Staggia",
    "gn:country_code":"IT",
    "gn:dem":22,
    "gn:feature_class":"P",
    "gn:feature_code":"PPL",
    "gn:name":"Staggia",
    "gn:population":393,
    "gn:timezone":"Europe/Rome",
    "iso:country":"IT",
    "wof:name":"Staggia",
    "wof:placetype":"locality",
    "wof:population":393
},
  "geometry": {"coordinates":[11.05318,44.80303],"type":"Point"}
}