{
  "type": "Feature",
  "properties": {
    "gn:admin1_code":"12",
    "gn:admin2_code":"CN",
    "gn:admin3_code":"4071.0",
    "gn:asciiname":"I Tetti",
    "gn:country_code":"IT",
    "gn:dem":277,
    "gn:feature_class":"P",
    "gn:feature_code":"PPL",
    "gn:name":"I Tetti",
    "gn:population":64,
    "gn:timezone":"Europe/Rome",
    "iso:country":"IT",
    "wof:name":"I Tetti",
    "wof:placetype":"locality",
    "wof:population":64
},
  "geometry": {"coordinates":[7.90482,44.48979],"type":"Point"}
}