{
  "type": "Feature",
  "properties": {
    "gn:elevation":510,
    "gn:population":864,
    "iso:country":"IT",
    "name:azb_x_preferred":[
        "\u0627\u0648\u0646\u0627\u0646\u0648"
    ],
    "name:bcl_x_preferred":[
        "Onano"
    ],
    "name:bel_x_preferred":[
        "\u0410\u043d\u0430\u043d\u0430"
    ],
    "name:bul_x_preferred":[
        "\u041e\u043d\u0430\u043d\u043e"
    ],
    "name:ceb_x_preferred":[
        "Onano"
    ],
    "name:deu_x_preferred":[
        "Onano"
    ],
    "name:eng_x_preferred":[
        "Onano"
    ],
    "name:epo_x_preferred":[
        "Onano"
    ],
    "name:eus_x_preferred":[
        "Onano"
    ],
    "name:fas_x_preferred":[
        "\u0627\u0648\u0646\u0627\u0646\u0648"
    ],
    "name:fra_x_preferred":[
        "Onano"
    ],
    "name:hbs_x_preferred":[
        "Onano"
    ],
    "name:hun_x_preferred":[
        "Onano"
    ],
    "name:hye_x_preferred":[
        "\u0555\u0576\u0561\u0576\u0578"
    ],
    "name:ina_x_preferred":[
        "Onano"
    ],
    "name:ita_x_preferred":[
        "Onano"
    ],
    "name:jpn_x_preferred":[
        "\u30aa\u30ca\u30fc\u30ce"
    ],
    "name:kaz_x_preferred":[
        "\u041e\u043d\u0430\u043d\u043e"
    ],
    "name:kor_x_preferred":[
        "\uc624\ub098\ub178"
    ],
    "name:lat_x_preferred":[
        "Onanum"
    ],
    "name:lat_x_variant":[
        "Haunanus"
    ],
    "name:lmo_x_preferred":[
        "Onano"
    ],
    "name:msa_x_preferred":[
        "Onano"
    ],
    "name:nan_x_preferred":[
        "Onano"
    ],
    "name:nap_x_preferred":[
        "Onano"
    ],
    "name:nld_x_preferred":[
        "Onano"
    ],
    "name:nno_x_preferred":[
        "Onano"
    ],
    "name:nob_x_preferred":[
        "Onano"
    ],
    "name:pms_x_preferred":[
        "Onano"
    ],
    "name:pol_x_preferred":[
        "Onano"
    ],
    "name:por_x_preferred":[
        "Onano"
    ],
    "name:ron_x_preferred":[
        "Onano"
    ],
    "name:rus_x_preferred":[
        "\u041e\u043d\u0430\u043d\u043e"
    ],
    "name:scn_x_preferred":[
        "Onanu"
    ],
    "name:slv_x_preferred":[
        "Onano"
    ],
    "name:spa_x_preferred":[
        "Onano"
    ],
    "name:srp_x_preferred":[
        "\u041e\u043d\u0430\u043d\u043e"
    ],
    "name:srp_x_variant":[
        "Onano"
    ],
    "name:ukr_x_preferred":[
        "\u041e\u043d\u0430\u043d\u043e"
    ],
    "name:uzb_x_preferred":[
        "Onano"
    ],
    "name:vie_x_preferred":[
        "Onano"
    ],
    "name:vol_x_preferred":[
        "Onano"
    ],
    "name:war_x_preferred":[
        "Onano"
    ],
    "name:zho_min_nan_x_preferred":[
        "Onano"
    ],
    "name:zho_x_preferred":[
        "\u5965\u7eb3\u8bfa"
    ],
    "qs:a0":"Italia",
    "qs:a1":"*Viterbo",
    "qs:a1r":"0Lazio",
    "qs:adm0":"Italia",
    "qs:la_lc":"*",
    "qs:level":"locality",
    "qs:loc":"Onano",
    "qs:loc_alt":"Onano",
    "qs:pop":0,
    "qs:type":"buffered point",
    "wd:wordcount":77,
    "wof:lang":[
        "ita"
    ],
    "wof:name":"Onano",
    "wof:placetype":"locality",
    "wof:population":864
},
  "geometry": {"coordinates":[11.816941,42.692219],"type":"Point"}
}