{
  "type": "Feature",
  "properties": {
    "gn:admin1_code":"6.0",
    "gn:admin2_code":"PN",
    "gn:admin3_code":"93035.0",
    "gn:asciiname":"Barco",
    "gn:country_code":"IT",
    "gn:dem":8,
    "gn:elevation":"8.0",
    "gn:feature_class":"P",
    "gn:feature_code":"PPL",
    "gn:name":"Barco",
    "gn:population":760,
    "gn:timezone":"Europe/Rome",
    "iso:country":"IT",
    "wof:name":"Barco",
    "wof:placetype":"locality",
    "wof:population":760
},
  "geometry": {"coordinates":[12.67171,45.81887],"type":"Point"}
}