{
  "type": "Feature",
  "properties": {
    "gn:admin1_code":"6.0",
    "gn:admin2_code":"PN",
    "gn:admin3_code":"93035.0",
    "gn:asciiname":"Barco",
    "gn:country_code":"IT",
    "gn:dem":8,
    "gn:elevation":"8.0",
    "gn:feature_class":"P",
    "gn:feature_code":"PPL",
    "gn:name":"Barco",
    "gn:population":760,
    "gn:timezone":"Europe/Rome",
    "iso:country":"IT",
    "name:cat_x_preferred":[
        "Barco"
    ],
    "name:ceb_x_preferred":[
        "Barco"
    ],
    "name:deu_x_preferred":[
        "Barco"
    ],
    "name:fra_x_preferred":[
        "Barco"
    ],
    "name:ita_x_preferred":[
        "Barco"
    ],
    "name:nld_x_preferred":[
        "Barco"
    ],
    "name:por_x_preferred":[
        "Barco"
    ],
    "name:rus_x_preferred":[
        "\u0411\u0430\u0440\u043a\u0443"
    ],
    "name:slv_x_preferred":[
        "Barco"
    ],
    "name:spa_x_preferred":[
        "Barco"
    ],
    "name:srp_x_preferred":[
        "\u0411\u0430\u0440\u043a\u043e"
    ],
    "name:swe_x_preferred":[
        "Barco"
    ],
    "name:ukr_x_preferred":[
        "\u0411\u0430\u0440\u043a\u0443"
    ],
    "wof:name":"Barco",
    "wof:placetype":"locality",
    "wof:population":760
},
  "geometry": {"coordinates":[12.67171,45.81887],"type":"Point"}
}