{
  "type": "Feature",
  "properties": {
    "gn:admin1_code":"5",
    "gn:admin2_code":"BO",
    "gn:admin3_code":"37022.0",
    "gn:asciiname":"Ca Motori",
    "gn:country_code":"IT",
    "gn:dem":534,
    "gn:feature_class":"P",
    "gn:feature_code":"PPL",
    "gn:name":"C\u00e0 Motori",
    "gn:population":31,
    "gn:timezone":"Europe/Rome",
    "iso:country":"IT",
    "name:und_x_variant":[
        "C\u00e0 Motori"
    ],
    "wof:name":"Ca Motori",
    "wof:placetype":"locality",
    "wof:population":31
},
  "geometry": {"coordinates":[11.17048,44.18444],"type":"Point"}
}