{
  "type": "Feature",
  "properties": {
    "gn:admin1_code":"17",
    "gn:admin2_code":"BZ",
    "gn:admin3_code":"21033.0",
    "gn:asciiname":"Colle",
    "gn:country_code":"IT",
    "gn:dem":1407,
    "gn:feature_class":"P",
    "gn:feature_code":"PPL",
    "gn:name":"Colle",
    "gn:population":15,
    "gn:timezone":"Europe/Rome",
    "iso:country":"IT",
    "wof:name":"Colle",
    "wof:placetype":"locality",
    "wof:population":15
},
  "geometry": {"coordinates":[11.69957,46.64862],"type":"Point"}
}