{
  "type": "Feature",
  "properties": {
    "gn:admin1_code":"8.0",
    "gn:admin2_code":"SV",
    "gn:admin3_code":"9056.0",
    "gn:asciiname":"Maschio Stazione",
    "gn:country_code":"IT",
    "gn:dem":201,
    "gn:feature_class":"P",
    "gn:feature_code":"PPL",
    "gn:name":"Maschio Stazione",
    "gn:population":25,
    "gn:timezone":"Europe/Rome",
    "iso:country":"IT",
    "wof:name":"Maschio Stazione",
    "wof:placetype":"locality",
    "wof:population":25
},
  "geometry": {"coordinates":[8.43603,44.32667],"type":"Point"}
}