{
  "type": "Feature",
  "properties": {
    "gn:admin1_code":"20",
    "gn:admin2_code":"RO",
    "gn:admin3_code":"29041.0",
    "gn:asciiname":"Le Giarelle",
    "gn:country_code":"IT",
    "gn:dem":5,
    "gn:feature_class":"P",
    "gn:feature_code":"PPL",
    "gn:name":"Le Giarelle",
    "gn:population":23,
    "gn:timezone":"Europe/Rome",
    "iso:country":"IT",
    "wof:name":"Le Giarelle",
    "wof:placetype":"locality",
    "wof:population":23
},
  "geometry": {"coordinates":[11.71127,45.08479000000001],"type":"Point"}
}