{
  "type": "Feature",
  "properties": {
    "gn:admin1_code":"2",
    "gn:admin2_code":"PZ",
    "gn:admin3_code":"76070.0",
    "gn:asciiname":"Cozzo Fratta",
    "gn:country_code":"IT",
    "gn:dem":733,
    "gn:feature_class":"P",
    "gn:feature_code":"PPL",
    "gn:name":"Cozzo Fratta",
    "gn:population":20,
    "gn:timezone":"Europe/Rome",
    "iso:country":"IT",
    "wof:name":"Cozzo Fratta",
    "wof:placetype":"locality",
    "wof:population":20
},
  "geometry": {"coordinates":[16.02764,39.92882],"type":"Point"}
}