{
  "type": "Feature",
  "properties": {
    "gn:admin1_code":"4",
    "gn:admin2_code":"SA",
    "gn:admin3_code":"65025.0",
    "gn:asciiname":"C.Procuzzi",
    "gn:country_code":"IT",
    "gn:dem":18,
    "gn:feature_class":"P",
    "gn:feature_code":"PPL",
    "gn:name":"C.Procuzzi",
    "gn:population":92,
    "gn:timezone":"Europe/Rome",
    "iso:country":"IT",
    "wof:name":"C.Procuzzi",
    "wof:placetype":"locality",
    "wof:population":92
},
  "geometry": {"coordinates":[14.99918,40.4605],"type":"Point"}
}