{
  "type": "Feature",
  "properties": {
    "gn:admin1_code":"20",
    "gn:admin2_code":"TV",
    "gn:admin3_code":"26084.0",
    "gn:asciiname":"Resera",
    "gn:country_code":"IT",
    "gn:dem":354,
    "gn:feature_class":"P",
    "gn:feature_code":"PPL",
    "gn:name":"Resera",
    "gn:population":123,
    "gn:timezone":"Europe/Rome",
    "iso:country":"IT",
    "wof:name":"Resera",
    "wof:placetype":"locality",
    "wof:population":123
},
  "geometry": {"coordinates":[12.2037,45.96879000000001],"type":"Point"}
}