{
  "type": "Feature",
  "properties": {
    "gn:admin1_code":"4",
    "gn:admin3_code":"63041.0",
    "gn:asciiname":"Cupa dei Cani",
    "gn:country_code":"IT",
    "gn:dem":188,
    "gn:feature_class":"P",
    "gn:feature_code":"PPL",
    "gn:name":"Cupa dei Cani",
    "gn:population":232,
    "gn:timezone":"Europe/Rome",
    "iso:country":"IT",
    "wof:name":"Cupa dei Cani",
    "wof:placetype":"locality",
    "wof:population":232
},
  "geometry": {"coordinates":[14.20185,40.89184],"type":"Point"}
}