{
  "type": "Feature",
  "properties": {
    "gn:admin1_code":"9",
    "gn:admin2_code":"SO",
    "gn:admin3_code":"14065.0",
    "gn:asciiname":"Panaggia",
    "gn:country_code":"IT",
    "gn:dem":835,
    "gn:feature_class":"P",
    "gn:feature_code":"PPL",
    "gn:name":"Panaggia",
    "gn:population":17,
    "gn:timezone":"Europe/Rome",
    "iso:country":"IT",
    "wof:name":"Panaggia",
    "wof:placetype":"locality",
    "wof:population":17
},
  "geometry": {"coordinates":[10.03333,46.17438],"type":"Point"}
}