{
  "type": "Feature",
  "properties": {
    "gn:admin1_code":"13",
    "gn:admin2_code":"BA",
    "gn:admin3_code":"72017.0",
    "gn:asciiname":"Torre di Mastro",
    "gn:country_code":"IT",
    "gn:dem":329,
    "gn:feature_class":"P",
    "gn:feature_code":"PPL",
    "gn:name":"Torre di Mastro",
    "gn:population":27,
    "gn:timezone":"Europe/Rome",
    "iso:country":"IT",
    "wof:name":"Torre di Mastro",
    "wof:placetype":"locality",
    "wof:population":27
},
  "geometry": {"coordinates":[17.13555,40.88241],"type":"Point"}
}