{
  "type": "Feature",
  "properties": {
    "gn:gn_country":"IT",
    "gn:gn_fcode":"PPLA3",
    "gn:gn_pop":454,
    "gn:population":405,
    "iso:country":"IT",
    "name:bel_x_preferred":[
        "\u0413\u043e\u0440\u0430\u0434 \u0414\u0440\u044d\u043d\u0430"
    ],
    "name:cat_x_preferred":[
        "Drena"
    ],
    "name:deu_x_preferred":[
        "Drena"
    ],
    "name:eng_x_preferred":[
        "Drena"
    ],
    "name:epo_x_preferred":[
        "Drena"
    ],
    "name:eus_x_preferred":[
        "Drena"
    ],
    "name:fas_x_preferred":[
        "\u062f\u0631\u0646\u0627"
    ],
    "name:fra_x_preferred":[
        "Drena"
    ],
    "name:hun_x_preferred":[
        "Drena"
    ],
    "name:hye_x_preferred":[
        "\u0534\u0580\u0565\u0576\u0561"
    ],
    "name:ind_x_preferred":[
        "Drena"
    ],
    "name:ita_x_preferred":[
        "Drena"
    ],
    "name:jpn_x_preferred":[
        "\u30c9\u30ec\u30fc\u30ca"
    ],
    "name:lat_x_preferred":[
        "Drena"
    ],
    "name:lmo_x_preferred":[
        "Drena"
    ],
    "name:msa_x_preferred":[
        "Drena"
    ],
    "name:nap_x_preferred":[
        "Drena"
    ],
    "name:nld_x_preferred":[
        "Drena"
    ],
    "name:pms_x_preferred":[
        "Drena"
    ],
    "name:pol_x_preferred":[
        "Drena"
    ],
    "name:por_x_preferred":[
        "Drena"
    ],
    "name:ron_x_preferred":[
        "Drena"
    ],
    "name:rus_x_preferred":[
        "\u0414\u0440\u0435\u043d\u0430"
    ],
    "name:scn_x_preferred":[
        "Drena"
    ],
    "name:spa_x_preferred":[
        "Drena"
    ],
    "name:srp_x_preferred":[
        "Drena"
    ],
    "name:tgl_x_preferred":[
        "Drena"
    ],
    "name:ukr_x_preferred":[
        "\u0414\u0440\u0435\u043d\u0430"
    ],
    "name:uzb_x_preferred":[
        "Drena"
    ],
    "name:vec_x_preferred":[
        "Drena"
    ],
    "name:vie_x_preferred":[
        "Drena"
    ],
    "name:vol_x_preferred":[
        "Drena"
    ],
    "name:war_x_preferred":[
        "Drena"
    ],
    "name:zho_x_preferred":[
        "\u5fb7\u96f7\u7eb3"
    ],
    "qs_pg:aaroncc":"IT",
    "qs_pg:gn_country":"IT",
    "qs_pg:gn_fcode":"PPLA3",
    "qs_pg:gn_pop":454,
    "qs_pg:name":"Drena",
    "qs_pg:name_adm0":"Italia",
    "qs_pg:name_adm1":"Trentino-Alto Adige",
    "qs_pg:photos":165,
    "qs_pg:photos_1k":33,
    "qs_pg:photos_9k":1,
    "qs_pg:photos_9r":4,
    "qs_pg:photos_all":165,
    "qs_pg:photos_sr":4,
    "qs_pg:pop_sr":2,
    "qs_pg:qs_pg_placetype":"locality",
    "qs_pg:qs_pg_placetype_gp":"Town",
    "qs_pg:woe_adm0":23424853,
    "woe:adm0_id":23424853,
    "woe:name_adm0":"Italia",
    "woe:name_adm1":"Trentino-Alto Adige",
    "woe:placetype":"Town",
    "wof:name":"Drena",
    "wof:placetype":"locality",
    "wof:population":405
},
  "geometry": {"coordinates":[10.94448,45.9693],"type":"Point"}
}