{
  "type": "Feature",
  "properties": {
    "gn:admin1_code":"16",
    "gn:admin2_code":"SI",
    "gn:admin3_code":"52015.0",
    "gn:asciiname":"Casella",
    "gn:country_code":"IT",
    "gn:dem":258,
    "gn:feature_class":"P",
    "gn:feature_code":"PPL",
    "gn:name":"Casella",
    "gn:population":30,
    "gn:timezone":"Europe/Rome",
    "iso:country":"IT",
    "name:ceb_x_preferred":[
        "Casella"
    ],
    "name:deu_x_preferred":[
        "Casella"
    ],
    "name:fra_x_preferred":[
        "Casella"
    ],
    "name:ita_x_preferred":[
        "Casella"
    ],
    "name:jpn_x_preferred":[
        "\u30ab\u30bc\u30c3\u30e9"
    ],
    "name:ltz_x_preferred":[
        "Casella"
    ],
    "name:nld_x_preferred":[
        "Casella"
    ],
    "name:rus_x_preferred":[
        "\u041a\u0430\u0437\u0435\u043b\u043b\u0430"
    ],
    "name:srp_x_preferred":[
        "Casella"
    ],
    "name:swe_x_preferred":[
        "Casella"
    ],
    "wof:name":"Casella",
    "wof:placetype":"locality",
    "wof:population":30
},
  "geometry": {"coordinates":[11.85624,43.14222],"type":"Point"}
}