{
  "type": "Feature",
  "properties": {
    "gn:admin1_code":"20.0",
    "gn:admin2_code":"PD",
    "gn:admin3_code":"28106.0",
    "gn:asciiname":"Cornegliana",
    "gn:country_code":"IT",
    "gn:dem":7,
    "gn:elevation":"8.0",
    "gn:feature_class":"P",
    "gn:feature_code":"PPL",
    "gn:name":"Cornegliana",
    "gn:population":799,
    "gn:timezone":"Europe/Rome",
    "iso:country":"IT",
    "wof:name":"Cornegliana",
    "wof:placetype":"locality",
    "wof:population":799
},
  "geometry": {"coordinates":[11.85313,45.30254],"type":"Point"}
}