{
  "type": "Feature",
  "properties": {
    "gn:admin1_code":"16.0",
    "gn:admin2_code":"FI",
    "gn:admin3_code":"48021.0",
    "gn:asciiname":"Greti",
    "gn:country_code":"IT",
    "gn:dem":216,
    "gn:feature_class":"P",
    "gn:feature_code":"PPL",
    "gn:name":"Greti",
    "gn:population":355,
    "gn:timezone":"Europe/Rome",
    "iso:country":"IT",
    "wof:name":"Greti",
    "wof:placetype":"locality",
    "wof:population":355
},
  "geometry": {"coordinates":[11.30534,43.6064],"type":"Point"}
}