{
  "type": "Feature",
  "properties": {
    "gn:admin1_code":"3.0",
    "gn:admin2_code":"CS",
    "gn:admin3_code":"78058.0",
    "gn:asciiname":"San Pietro",
    "gn:country_code":"IT",
    "gn:dem":243,
    "gn:elevation":"254.0",
    "gn:feature_class":"P",
    "gn:feature_code":"PPL",
    "gn:name":"San Pietro",
    "gn:population":180,
    "gn:timezone":"Europe/Rome",
    "iso:country":"IT",
    "name:ceb_x_preferred":[
        "San Pietro"
    ],
    "name:deu_x_preferred":[
        "San Pietro"
    ],
    "name:epo_x_preferred":[
        "San Pietro"
    ],
    "name:fra_x_preferred":[
        "San Pietro"
    ],
    "name:ita_x_preferred":[
        "San Pietro"
    ],
    "name:pol_x_preferred":[
        "San Pietro"
    ],
    "name:por_x_preferred":[
        "San Pietro"
    ],
    "name:sco_x_preferred":[
        "San Pietro"
    ],
    "name:srp_x_preferred":[
        "San Pjetro"
    ],
    "name:swe_x_preferred":[
        "San Pietro"
    ],
    "wof:name":"San Pietro",
    "wof:placetype":"locality",
    "wof:population":180
},
  "geometry": {"coordinates":[16.03127000000001,39.4055],"type":"Point"}
}