{
  "type": "Feature",
  "properties": {
    "gn:admin1_code":"2",
    "gn:admin2_code":"PZ",
    "gn:admin3_code":"76098.0",
    "gn:asciiname":"Case Rosse",
    "gn:country_code":"IT",
    "gn:dem":649,
    "gn:feature_class":"P",
    "gn:feature_code":"PPL",
    "gn:name":"Case Rosse",
    "gn:population":37,
    "gn:timezone":"Europe/Rome",
    "iso:country":"IT",
    "wof:name":"Case Rosse",
    "wof:placetype":"locality",
    "wof:population":37
},
  "geometry": {"coordinates":[15.8549,40.35633],"type":"Point"}
}