{
  "type": "Feature",
  "properties": {
    "gn:admin1_code":"20.0",
    "gn:admin2_code":"VE",
    "gn:admin3_code":"27023.0",
    "gn:asciiname":"Dogaletto",
    "gn:country_code":"IT",
    "gn:dem":0,
    "gn:elevation":"3.0",
    "gn:feature_class":"P",
    "gn:feature_code":"PPL",
    "gn:name":"Dogaletto",
    "gn:population":519,
    "gn:timezone":"Europe/Rome",
    "iso:country":"IT",
    "wof:name":"Dogaletto",
    "wof:placetype":"locality",
    "wof:population":519
},
  "geometry": {"coordinates":[12.19109,45.41457],"type":"Point"}
}