{
  "type": "Feature",
  "properties": {
    "gn:admin1_code":"12",
    "gn:admin2_code":"BI",
    "gn:admin3_code":"96070.0",
    "gn:asciiname":"Mazzucco",
    "gn:country_code":"IT",
    "gn:dem":613,
    "gn:feature_class":"P",
    "gn:feature_code":"PPL",
    "gn:name":"Mazzucco",
    "gn:population":62,
    "gn:timezone":"Europe/Rome",
    "iso:country":"IT",
    "wof:name":"Mazzucco",
    "wof:placetype":"locality",
    "wof:population":62
},
  "geometry": {"coordinates":[8.16414,45.65854],"type":"Point"}
}