{
  "type": "Feature",
  "properties": {
    "gn:admin1_code":"7",
    "gn:admin2_code":"FR",
    "gn:admin3_code":"60055.0",
    "gn:asciiname":"Forestella",
    "gn:country_code":"IT",
    "gn:dem":152,
    "gn:feature_class":"P",
    "gn:feature_code":"PPL",
    "gn:name":"Forestella",
    "gn:population":35,
    "gn:timezone":"Europe/Rome",
    "iso:country":"IT",
    "wof:name":"Forestella",
    "wof:placetype":"locality",
    "wof:population":35
},
  "geometry": {"coordinates":[13.40186,41.55366],"type":"Point"}
}