{
  "type": "Feature",
  "properties": {
    "gn:admin1_code":"9.0",
    "gn:admin2_code":"LO",
    "gn:admin3_code":"98056.0",
    "gn:asciiname":"Pezzolo",
    "gn:country_code":"IT",
    "gn:dem":84,
    "gn:elevation":"87.0",
    "gn:feature_class":"P",
    "gn:feature_code":"PPL",
    "gn:name":"Pezzolo",
    "gn:population":51,
    "gn:timezone":"Europe/Rome",
    "iso:country":"IT",
    "wof:name":"Pezzolo",
    "wof:placetype":"locality",
    "wof:population":51
},
  "geometry": {"coordinates":[9.39074,45.3262],"type":"Point"}
}