{
  "type": "Feature",
  "properties": {
    "gn:admin1_code":"9",
    "gn:admin2_code":"VA",
    "gn:admin3_code":"12103.0",
    "gn:asciiname":"Cucco",
    "gn:country_code":"IT",
    "gn:dem":214,
    "gn:feature_class":"P",
    "gn:feature_code":"PPL",
    "gn:name":"Cucco",
    "gn:population":123,
    "gn:timezone":"Europe/Rome",
    "iso:country":"IT",
    "wof:name":"Cucco",
    "wof:placetype":"locality",
    "wof:population":123
},
  "geometry": {"coordinates":[8.75531,45.96869],"type":"Point"}
}