{
  "type": "Feature",
  "properties": {
    "gn:admin1_code":"20",
    "gn:admin2_code":"PD",
    "gn:admin3_code":"28057.0",
    "gn:asciiname":"P. Gobetti",
    "gn:country_code":"IT",
    "gn:dem":33,
    "gn:feature_class":"P",
    "gn:feature_code":"PPL",
    "gn:name":"P. Gobetti",
    "gn:population":31,
    "gn:timezone":"Europe/Rome",
    "iso:country":"IT",
    "wof:name":"P. Gobetti",
    "wof:placetype":"locality",
    "wof:population":31
},
  "geometry": {"coordinates":[11.75742,45.31608],"type":"Point"}
}