{
  "type": "Feature",
  "properties": {
    "iso:country":"IT",
    "name:bar_x_preferred":[
        "Pescegallo"
    ],
    "name:bre_x_preferred":[
        "Pescegallo"
    ],
    "name:cat_x_preferred":[
        "Pescegallo"
    ],
    "name:ceb_x_preferred":[
        "Pescegallo"
    ],
    "name:cos_x_preferred":[
        "Pescegallo"
    ],
    "name:dan_x_preferred":[
        "Pescegallo"
    ],
    "name:deu_x_preferred":[
        "Pescegallo"
    ],
    "name:eng_x_preferred":[
        "Pescegallo"
    ],
    "name:fra_x_preferred":[
        "Pescegallo"
    ],
    "name:ind_x_preferred":[
        "Pescegallo"
    ],
    "name:ita_x_preferred":[
        "Pescegallo"
    ],
    "name:nds_x_preferred":[
        "Pescegallo"
    ],
    "name:nld_x_preferred":[
        "Pescegallo"
    ],
    "name:pol_x_preferred":[
        "Pescegallo"
    ],
    "name:por_x_preferred":[
        "Pescegallo"
    ],
    "name:ron_x_preferred":[
        "Pescegallo"
    ],
    "name:spa_x_preferred":[
        "Pescegallo"
    ],
    "name:srp_x_preferred":[
        "Pescegallo"
    ],
    "name:swe_x_preferred":[
        "Pescegallo"
    ],
    "name:tah_x_preferred":[
        "Pescegallo"
    ],
    "qs_pg:aaroncc":"IT",
    "qs_pg:name":"Pescegallo",
    "qs_pg:name_adm0":"Italia",
    "qs_pg:name_adm1":"Lombardia",
    "qs_pg:photos":227,
    "qs_pg:photos_1k":46,
    "qs_pg:photos_9k":1,
    "qs_pg:photos_9r":4,
    "qs_pg:photos_all":227,
    "qs_pg:photos_sr":4,
    "qs_pg:pop_sr":0,
    "qs_pg:qs_pg_placetype":"locality",
    "qs_pg:qs_pg_placetype_gp":"Town",
    "qs_pg:woe_adm0":23424853,
    "woe:adm0_id":23424853,
    "woe:name_adm0":"Italia",
    "woe:name_adm1":"Lombardia",
    "woe:placetype":"Town",
    "wof:name":"Pescegallo",
    "wof:placetype":"locality"
},
  "geometry": {"coordinates":[9.572059,46.033381],"type":"Point"}
}