{
  "type": "Feature",
  "properties": {
    "gn:admin1_code":"4.0",
    "gn:admin2_code":"AV",
    "gn:admin3_code":"64057.0",
    "gn:asciiname":"Garzano",
    "gn:country_code":"IT",
    "gn:dem":664,
    "gn:feature_class":"P",
    "gn:feature_code":"PPL",
    "gn:name":"Garzano",
    "gn:population":0,
    "gn:timezone":"Europe/Rome",
    "iso:country":"IT",
    "wof:name":"Garzano",
    "wof:placetype":"locality"
},
  "geometry": {"coordinates":[15.01667,40.85],"type":"Point"}
}