{
  "type": "Feature",
  "properties": {
    "gn:gn_country":"IT",
    "gn:gn_fcode":"PPL",
    "gn:gn_pop":0,
    "gn:population":543,
    "iso:country":"IT",
    "name:dut_x_preferred":[
        "Castagna"
    ],
    "name:eng_x_preferred":[
        "Castagna"
    ],
    "name:fre_x_preferred":[
        "Castagna"
    ],
    "name:hun_x_preferred":[
        "Castagna"
    ],
    "name:ita_x_preferred":[
        "Castagna"
    ],
    "name:srp_x_preferred":[
        "Castagna"
    ],
    "qs_pg:aaroncc":"IT",
    "qs_pg:gn_country":"IT",
    "qs_pg:gn_fcode":"PPL",
    "qs_pg:gn_pop":0,
    "qs_pg:name":"Castagna",
    "qs_pg:name_adm0":"Italia",
    "qs_pg:name_adm1":"Calabria",
    "qs_pg:photos":4,
    "qs_pg:photos_1k":1,
    "qs_pg:photos_9k":1,
    "qs_pg:photos_9r":1,
    "qs_pg:photos_all":4,
    "qs_pg:photos_sr":1,
    "qs_pg:pop_sr":0,
    "qs_pg:qs_pg_placetype":"locality",
    "qs_pg:qs_pg_placetype_gp":"Town",
    "qs_pg:woe_adm0":23424853,
    "woe:adm0_id":23424853,
    "woe:name_adm0":"Italia",
    "woe:name_adm1":"Calabria",
    "woe:placetype":"Town",
    "wof:name":"Castagna",
    "wof:placetype":"locality",
    "wof:population":543
},
  "geometry": {"coordinates":[16.43333,39.05],"type":"Point"}
}