{
  "type": "Feature",
  "properties": {
    "gn:admin1_code":"12.0",
    "gn:admin2_code":"CN",
    "gn:admin3_code":"4086.0",
    "gn:asciiname":"Quartiere Sottano Mellea",
    "gn:country_code":"IT",
    "gn:dem":329,
    "gn:feature_class":"P",
    "gn:feature_code":"PPL",
    "gn:name":"Quartiere Sottano Mellea",
    "gn:population":48,
    "gn:timezone":"Europe/Rome",
    "iso:country":"IT",
    "wof:name":"Quartiere Sottano Mellea",
    "wof:placetype":"locality",
    "wof:population":48
},
  "geometry": {"coordinates":[7.89327,44.50028],"type":"Point"}
}