{
  "type": "Feature",
  "properties": {
    "gn:admin1_code":"9",
    "gn:admin2_code":"BS",
    "gn:admin3_code":"17133.0",
    "gn:asciiname":"Gardale",
    "gn:country_code":"IT",
    "gn:dem":168,
    "gn:feature_class":"P",
    "gn:feature_code":"PPL",
    "gn:name":"Gardale",
    "gn:population":17,
    "gn:timezone":"Europe/Rome",
    "iso:country":"IT",
    "wof:name":"Gardale",
    "wof:placetype":"locality",
    "wof:population":17
},
  "geometry": {"coordinates":[9.87906,45.5793],"type":"Point"}
}