{
  "type": "Feature",
  "properties": {
    "gn:admin1_code":"12",
    "gn:admin2_code":"TO",
    "gn:admin3_code":"1204.0",
    "gn:asciiname":"Lussie",
    "gn:country_code":"IT",
    "gn:dem":704,
    "gn:feature_class":"P",
    "gn:feature_code":"PPLL",
    "gn:name":"Lussie",
    "gn:population":5,
    "gn:timezone":"Europe/Rome",
    "iso:country":"IT",
    "wof:name":"Lussie",
    "wof:placetype":"locality",
    "wof:population":5
},
  "geometry": {"coordinates":[7.21179,44.90476],"type":"Point"}
}