{
  "type": "Feature",
  "properties": {
    "gn:admin1_code":"15.0",
    "gn:admin2_code":"TP",
    "gn:admin3_code":"81001.0",
    "gn:asciiname":"Casa Valdibella",
    "gn:country_code":"IT",
    "gn:dem":292,
    "gn:feature_class":"P",
    "gn:feature_code":"PPL",
    "gn:name":"Casa Valdibella",
    "gn:population":0,
    "gn:timezone":"Europe/Rome",
    "iso:country":"IT",
    "wof:name":"Casa Valdibella",
    "wof:placetype":"locality"
},
  "geometry": {"coordinates":[12.96667,37.93333],"type":"Point"}
}