{
  "type": "Feature",
  "properties": {
    "gn:admin1_code":"16",
    "gn:admin2_code":"LI",
    "gn:admin3_code":"49014.0",
    "gn:asciiname":"Schiopparello I",
    "gn:country_code":"IT",
    "gn:dem":23,
    "gn:feature_class":"P",
    "gn:feature_code":"PPL",
    "gn:name":"Schiopparello I",
    "gn:population":258,
    "gn:timezone":"Europe/Rome",
    "iso:country":"IT",
    "wof:name":"Schiopparello I",
    "wof:placetype":"locality",
    "wof:population":258
},
  "geometry": {"coordinates":[10.33997,42.79354],"type":"Point"}
}