{
  "type": "Feature",
  "properties": {
    "gn:admin1_code":"11",
    "gn:admin2_code":"CB",
    "gn:admin3_code":"70017.0",
    "gn:asciiname":"Riglioni",
    "gn:country_code":"IT",
    "gn:dem":749,
    "gn:feature_class":"P",
    "gn:feature_code":"PPL",
    "gn:name":"Riglioni",
    "gn:population":37,
    "gn:timezone":"Europe/Rome",
    "iso:country":"IT",
    "wof:name":"Riglioni",
    "wof:placetype":"locality",
    "wof:population":37
},
  "geometry": {"coordinates":[14.74958,41.47155],"type":"Point"}
}