{
  "type": "Feature",
  "properties": {
    "gn:admin1_code":"20",
    "gn:admin2_code":"PD",
    "gn:admin3_code":"28055.0",
    "gn:asciiname":"Pozzetto",
    "gn:country_code":"IT",
    "gn:dem":4,
    "gn:feature_class":"P",
    "gn:feature_code":"PPL",
    "gn:name":"Pozzetto",
    "gn:population":66,
    "gn:timezone":"Europe/Rome",
    "iso:country":"IT",
    "wof:name":"Pozzetto",
    "wof:placetype":"locality",
    "wof:population":66
},
  "geometry": {"coordinates":[11.81064,45.21488],"type":"Point"}
}