{
  "type": "Feature",
  "properties": {
    "gn:admin1_code":"1",
    "gn:admin2_code":"CH",
    "gn:admin3_code":"69040.0",
    "gn:asciiname":"Rossi",
    "gn:country_code":"IT",
    "gn:dem":605,
    "gn:feature_class":"P",
    "gn:feature_code":"PPL",
    "gn:name":"Rossi",
    "gn:population":36,
    "gn:timezone":"Europe/Rome",
    "iso:country":"IT",
    "wof:name":"Rossi",
    "wof:placetype":"locality",
    "wof:population":36
},
  "geometry": {"coordinates":[14.27657,42.04349000000001],"type":"Point"}
}