{
  "type": "Feature",
  "properties": {
    "gn:admin1_code":"1",
    "gn:admin2_code":"CH",
    "gn:admin3_code":"69040.0",
    "gn:asciiname":"Rossi",
    "gn:country_code":"IT",
    "gn:dem":605,
    "gn:feature_class":"P",
    "gn:feature_code":"PPL",
    "gn:name":"Rossi",
    "gn:population":36,
    "gn:timezone":"Europe/Rome",
    "iso:country":"IT",
    "name:bel_x_preferred":[
        "\u0420\u043e\u0441\u0456"
    ],
    "name:cat_x_preferred":[
        "Rossi"
    ],
    "name:ceb_x_preferred":[
        "Rossi"
    ],
    "name:ces_x_preferred":[
        "Rossi"
    ],
    "name:fin_x_preferred":[
        "Rossi"
    ],
    "name:fra_x_preferred":[
        "Rossi"
    ],
    "name:heb_x_preferred":[
        "\u05e8\u05d5\u05e1\u05d9"
    ],
    "name:ita_x_preferred":[
        "Rossi"
    ],
    "name:jpn_x_preferred":[
        "\u30ed\u30c3\u30b7"
    ],
    "name:nld_x_preferred":[
        "Rossi"
    ],
    "name:pol_x_preferred":[
        "Rossi"
    ],
    "name:por_x_preferred":[
        "Rossi"
    ],
    "name:rus_x_preferred":[
        "\u0420\u043e\u0441\u0441\u0438"
    ],
    "name:slv_x_preferred":[
        "Rossi"
    ],
    "name:spa_x_preferred":[
        "Rossi"
    ],
    "name:srp_x_preferred":[
        "Rossi"
    ],
    "name:swe_x_preferred":[
        "Rossi"
    ],
    "wof:name":"Rossi",
    "wof:placetype":"locality",
    "wof:population":36
},
  "geometry": {"coordinates":[14.27657,42.04349000000001],"type":"Point"}
}