{
  "type": "Feature",
  "properties": {
    "gn:admin1_code":"16",
    "gn:admin2_code":"FI",
    "gn:admin3_code":"48003.0",
    "gn:asciiname":"Zona Industriale",
    "gn:country_code":"IT",
    "gn:dem":103,
    "gn:feature_class":"P",
    "gn:feature_code":"PPL",
    "gn:name":"Zona Industriale",
    "gn:population":284,
    "gn:timezone":"Europe/Rome",
    "iso:country":"IT",
    "name:deu_x_preferred":[
        "Zona Industriale"
    ],
    "name:fra_x_preferred":[
        "Zona Industriale"
    ],
    "name:ita_x_preferred":[
        "Zona Industriale"
    ],
    "name:nap_x_preferred":[
        "Zona Nnustriale"
    ],
    "wof:name":"Zona Industriale",
    "wof:placetype":"locality",
    "wof:population":284
},
  "geometry": {"coordinates":[11.13061,43.48477000000001],"type":"Point"}
}