{
  "type": "Feature",
  "properties": {
    "gn:admin1_code":"12.0",
    "gn:admin2_code":"CN",
    "gn:admin3_code":"4205.0",
    "gn:asciiname":"Serre Superiore",
    "gn:country_code":"IT",
    "gn:dem":1424,
    "gn:feature_class":"P",
    "gn:feature_code":"PPL",
    "gn:name":"Serre Superiore",
    "gn:population":4,
    "gn:timezone":"Europe/Rome",
    "iso:country":"IT",
    "wof:name":"Serre Superiore",
    "wof:placetype":"locality",
    "wof:population":4
},
  "geometry": {"coordinates":[7.21167,44.59528],"type":"Point"}
}