{
  "type": "Feature",
  "properties": {
    "gn:admin1_code":"9.0",
    "gn:admin2_code":"VA",
    "gn:admin3_code":"12097.0",
    "gn:asciiname":"Aisel",
    "gn:country_code":"IT",
    "gn:dem":807,
    "gn:feature_class":"P",
    "gn:feature_code":"PPLL",
    "gn:name":"Aisel",
    "gn:population":0,
    "gn:timezone":"Europe/Rome",
    "iso:country":"IT",
    "wof:name":"Aisel",
    "wof:placetype":"locality"
},
  "geometry": {"coordinates":[8.84495,45.9281],"type":"Point"}
}