{
  "type": "Feature",
  "properties": {
    "gn:admin1_code":"7",
    "gn:admin2_code":"FR",
    "gn:admin3_code":"60024.0",
    "gn:asciiname":"Guarcini",
    "gn:country_code":"IT",
    "gn:dem":251,
    "gn:feature_class":"P",
    "gn:feature_code":"PPL",
    "gn:name":"Guarcini",
    "gn:population":53,
    "gn:timezone":"Europe/Rome",
    "iso:country":"IT",
    "wof:name":"Guarcini",
    "wof:placetype":"locality",
    "wof:population":53
},
  "geometry": {"coordinates":[13.3225,41.53975],"type":"Point"}
}