{
  "type": "Feature",
  "properties": {
    "gn:admin1_code":"5",
    "gn:admin2_code":"FE",
    "gn:admin3_code":"38003.0",
    "gn:asciiname":"Romea",
    "gn:country_code":"IT",
    "gn:dem":8,
    "gn:feature_class":"P",
    "gn:feature_code":"PPL",
    "gn:name":"Romea",
    "gn:population":47,
    "gn:timezone":"Europe/Rome",
    "iso:country":"IT",
    "name:ita_x_preferred":[
        "Romea"
    ],
    "wof:name":"Romea",
    "wof:placetype":"locality",
    "wof:population":47
},
  "geometry": {"coordinates":[11.30205,44.94619],"type":"Point"}
}