{
  "type": "Feature",
  "properties": {
    "gn:admin1_code":"16",
    "gn:admin2_code":"PI",
    "gn:admin3_code":"50026.0",
    "gn:asciiname":"Cascine Nuove",
    "gn:country_code":"IT",
    "gn:dem":6,
    "gn:feature_class":"P",
    "gn:feature_code":"PPL",
    "gn:name":"Cascine Nuove",
    "gn:population":48,
    "gn:timezone":"Europe/Rome",
    "iso:country":"IT",
    "wof:name":"Cascine Nuove",
    "wof:placetype":"locality",
    "wof:population":48
},
  "geometry": {"coordinates":[10.34281,43.6919],"type":"Point"}
}