{
  "type": "Feature",
  "properties": {
    "gn:admin1_code":"9",
    "gn:admin2_code":"LO",
    "gn:admin3_code":"98011.0",
    "gn:asciiname":"Isola",
    "gn:country_code":"IT",
    "gn:dem":43,
    "gn:feature_class":"P",
    "gn:feature_code":"PPL",
    "gn:name":"Isola",
    "gn:population":50,
    "gn:timezone":"Europe/Rome",
    "iso:country":"IT",
    "wof:name":"Isola",
    "wof:placetype":"locality",
    "wof:population":50
},
  "geometry": {"coordinates":[9.77819,45.10909],"type":"Point"}
}