{
  "type": "Feature",
  "properties": {
    "gn:admin1_code":"9",
    "gn:admin2_code":"LO",
    "gn:admin3_code":"98011.0",
    "gn:asciiname":"Isola",
    "gn:country_code":"IT",
    "gn:dem":43,
    "gn:feature_class":"P",
    "gn:feature_code":"PPL",
    "gn:name":"Isola",
    "gn:population":50,
    "gn:timezone":"Europe/Rome",
    "iso:country":"IT",
    "name:ceb_x_preferred":[
        "Isola"
    ],
    "name:deu_x_preferred":[
        "Isola"
    ],
    "name:fin_x_preferred":[
        "Isola"
    ],
    "name:fra_x_preferred":[
        "Isola"
    ],
    "name:ita_x_preferred":[
        "Isola"
    ],
    "name:jpn_x_preferred":[
        "\u30a4\u30bd\u30e9"
    ],
    "name:nld_x_preferred":[
        "Isola"
    ],
    "name:nor_x_preferred":[
        "Isola"
    ],
    "name:por_x_preferred":[
        "Isola"
    ],
    "name:scn_x_preferred":[
        "\u00ccsula"
    ],
    "name:srp_x_preferred":[
        "\u0418\u0437\u043e\u043b\u0430"
    ],
    "name:swe_x_preferred":[
        "Isola"
    ],
    "name:vol_x_preferred":[
        "Isola"
    ],
    "wof:name":"Isola",
    "wof:placetype":"locality",
    "wof:population":50
},
  "geometry": {"coordinates":[9.77819,45.10909],"type":"Point"}
}