{
  "type": "Feature",
  "properties": {
    "gn:admin1_code":"3.0",
    "gn:admin2_code":"VV",
    "gn:admin3_code":"102050.0",
    "gn:asciiname":"Casa Nucara",
    "gn:country_code":"IT",
    "gn:dem":511,
    "gn:feature_class":"P",
    "gn:feature_code":"PPL",
    "gn:name":"Casa Nucara",
    "gn:population":0,
    "gn:timezone":"Europe/Rome",
    "iso:country":"IT",
    "wof:name":"Casa Nucara",
    "wof:placetype":"locality"
},
  "geometry": {"coordinates":[15.98333,38.65],"type":"Point"}
}