{
  "type": "Feature",
  "properties": {
    "gn:admin1_code":"14",
    "gn:admin2_code":"OR",
    "gn:admin3_code":"95006.0",
    "gn:asciiname":"Pompongias",
    "gn:country_code":"IT",
    "gn:dem":11,
    "gn:feature_class":"P",
    "gn:feature_code":"PPL",
    "gn:name":"Pompongias",
    "gn:population":45,
    "gn:timezone":"Europe/Rome",
    "iso:country":"IT",
    "wof:name":"Pompongias",
    "wof:placetype":"locality",
    "wof:population":45
},
  "geometry": {"coordinates":[8.56124,39.74952],"type":"Point"}
}