{
  "type": "Feature",
  "properties": {
    "gn:admin1_code":"9.0",
    "gn:admin2_code":"SO",
    "gn:admin3_code":"14012.0",
    "gn:asciiname":"Bondeno",
    "gn:country_code":"IT",
    "gn:dem":1632,
    "gn:feature_class":"P",
    "gn:feature_code":"PPLL",
    "gn:name":"Bondeno",
    "gn:population":0,
    "gn:timezone":"Europe/Rome",
    "iso:country":"IT",
    "name:ara_x_preferred":[
        "\u0628\u0648\u0646\u062f\u064a\u0646\u0648"
    ],
    "name:azb_x_preferred":[
        "\u0628\u0648\u0646\u062f\u0646\u0648"
    ],
    "name:aze_x_preferred":[
        "Bondeno"
    ],
    "name:bul_x_preferred":[
        "\u0411\u043e\u043d\u0434\u0435\u043d\u043e"
    ],
    "name:cat_x_preferred":[
        "Bondeno"
    ],
    "name:ceb_x_preferred":[
        "Bondeno"
    ],
    "name:deu_x_preferred":[
        "Bondeno"
    ],
    "name:eml_x_preferred":[
        "Bund\u00e9n"
    ],
    "name:epo_x_preferred":[
        "Bondeno"
    ],
    "name:eus_x_preferred":[
        "Bondeno"
    ],
    "name:fas_x_preferred":[
        "\u0628\u0648\u0646\u062f\u0646\u0648"
    ],
    "name:fra_x_preferred":[
        "Bondeno"
    ],
    "name:hun_x_preferred":[
        "Bondeno"
    ],
    "name:hye_x_preferred":[
        "\u0532\u0578\u0576\u0564\u0565\u0576\u0578"
    ],
    "name:ina_x_preferred":[
        "Bondeno"
    ],
    "name:ind_x_preferred":[
        "Bondeno"
    ],
    "name:ita_x_preferred":[
        "Bondeno"
    ],
    "name:jpn_x_preferred":[
        "\u30dc\u30f3\u30c7\u30fc\u30ce"
    ],
    "name:kaz_x_preferred":[
        "\u0411\u043e\u043d\u0434\u0435\u043d\u043e"
    ],
    "name:lat_x_preferred":[
        "Bondenum"
    ],
    "name:lmo_x_preferred":[
        "Bondeno"
    ],
    "name:msa_x_preferred":[
        "Bondeno"
    ],
    "name:nap_x_preferred":[
        "Bondeno"
    ],
    "name:nld_x_preferred":[
        "Bondeno"
    ],
    "name:pms_x_preferred":[
        "Bondeno"
    ],
    "name:pol_x_preferred":[
        "Bondeno"
    ],
    "name:por_x_preferred":[
        "Bondeno"
    ],
    "name:ron_x_preferred":[
        "Bondeno"
    ],
    "name:rus_x_preferred":[
        "\u0411\u043e\u043d\u0434\u0435\u043d\u043e"
    ],
    "name:scn_x_preferred":[
        "Bondeno"
    ],
    "name:spa_x_preferred":[
        "Bondeno"
    ],
    "name:srp_x_preferred":[
        "\u0411\u043e\u043d\u0434\u0435\u043d\u043e"
    ],
    "name:tur_x_preferred":[
        "Bondeno"
    ],
    "name:ukr_x_preferred":[
        "\u0411\u043e\u043d\u0434\u0435\u043d\u043e"
    ],
    "name:uzb_x_preferred":[
        "Bondeno"
    ],
    "name:vec_x_preferred":[
        "Bondeno"
    ],
    "name:vie_x_preferred":[
        "Bondeno"
    ],
    "name:vol_x_preferred":[
        "Bondeno"
    ],
    "name:war_x_preferred":[
        "Bondeno"
    ],
    "name:zho_x_preferred":[
        "\u90a6\u5fb7\u8bfa"
    ],
    "wof:name":"Bondeno",
    "wof:placetype":"locality"
},
  "geometry": {"coordinates":[9.36632,46.38108],"type":"Point"}
}