{
  "type": "Feature",
  "properties": {
    "gn:admin1_code":"9.0",
    "gn:admin2_code":"SO",
    "gn:admin3_code":"14012.0",
    "gn:asciiname":"Bondeno",
    "gn:country_code":"IT",
    "gn:dem":1632,
    "gn:feature_class":"P",
    "gn:feature_code":"PPLL",
    "gn:name":"Bondeno",
    "gn:population":0,
    "gn:timezone":"Europe/Rome",
    "iso:country":"IT",
    "wof:name":"Bondeno",
    "wof:placetype":"locality"
},
  "geometry": {"coordinates":[9.36632,46.38108],"type":"Point"}
}