{
  "type": "Feature",
  "properties": {
    "gn:admin1_code":"3.0",
    "gn:admin2_code":"CS",
    "gn:admin3_code":"78146.0",
    "gn:asciiname":"Casa Feraudi",
    "gn:cc2":"IT",
    "gn:country_code":"IT",
    "gn:dem":115,
    "gn:feature_class":"P",
    "gn:feature_code":"PPL",
    "gn:name":"Casa Feraudi",
    "gn:population":0,
    "gn:timezone":"Europe/Rome",
    "iso:country":"IT",
    "name:und_x_variant":[
        "Deangelis",
        "Casa Feraudi"
    ],
    "wof:name":"Casa Feraudi",
    "wof:placetype":"locality"
},
  "geometry": {"coordinates":[16.35,39.68333],"type":"Point"}
}