{
  "type": "Feature",
  "properties": {
    "gn:admin1_code":"9",
    "gn:admin2_code":"BG",
    "gn:admin3_code":"16122.0",
    "gn:asciiname":"Zona Ind. Via Largo Fornace",
    "gn:country_code":"IT",
    "gn:dem":103,
    "gn:feature_class":"P",
    "gn:feature_code":"PPL",
    "gn:name":"Zona Ind. Via Largo Fornace",
    "gn:population":27,
    "gn:timezone":"Europe/Rome",
    "iso:country":"IT",
    "wof:name":"Zona Ind. Via Largo Fornace",
    "wof:placetype":"locality",
    "wof:population":27
},
  "geometry": {"coordinates":[9.75129,45.47825],"type":"Point"}
}