{
  "type": "Feature",
  "properties": {
    "gn:admin1_code":"17",
    "gn:admin2_code":"BZ",
    "gn:admin3_code":"21049.0",
    "gn:asciiname":"Burgone",
    "gn:country_code":"IT",
    "gn:dem":1094,
    "gn:feature_class":"P",
    "gn:feature_code":"PPL",
    "gn:name":"Burgone",
    "gn:population":30,
    "gn:timezone":"Europe/Rome",
    "iso:country":"IT",
    "wof:name":"Burgone",
    "wof:placetype":"locality",
    "wof:population":30
},
  "geometry": {"coordinates":[10.81181,46.57669],"type":"Point"}
}