{
  "type": "Feature",
  "properties": {
    "gn:admin1_code":"12",
    "gn:admin2_code":"TO",
    "gn:admin3_code":"1152.0",
    "gn:asciiname":"Conce",
    "gn:country_code":"IT",
    "gn:dem":700,
    "gn:feature_class":"P",
    "gn:feature_code":"PPLL",
    "gn:name":"Conce",
    "gn:population":7,
    "gn:timezone":"Europe/Rome",
    "iso:country":"IT",
    "wof:name":"Conce",
    "wof:placetype":"locality",
    "wof:population":7
},
  "geometry": {"coordinates":[7.39643,45.28671],"type":"Point"}
}