{
  "type": "Feature",
  "properties": {
    "gn:admin1_code":"10.0",
    "gn:admin2_code":"FM",
    "gn:admin3_code":"109015.0",
    "gn:asciiname":"Poggio",
    "gn:country_code":"IT",
    "gn:dem":736,
    "gn:feature_class":"P",
    "gn:feature_code":"PPL",
    "gn:name":"Poggio",
    "gn:population":0,
    "gn:timezone":"Europe/Rome",
    "iso:country":"IT",
    "wof:name":"Poggio",
    "wof:placetype":"locality"
},
  "geometry": {"coordinates":[13.36667,42.91667],"type":"Point"}
}