{
  "type": "Feature",
  "properties": {
    "iso:country":"IT",
    "qs:a0":"Italia",
    "qs:a1":"*Massa-Carrara",
    "qs:a1r":"0Toscana",
    "qs:adm0":"Italia",
    "qs:la_lc":"*",
    "qs:level":"locality",
    "qs:loc":"Montale",
    "qs:loc_alt":"Montale",
    "qs:pop":0,
    "qs:type":"buffered point",
    "wd:wordcount":100,
    "wof:name":"Montale",
    "wof:placetype":"locality"
},
  "geometry": {"coordinates":[9.94278,44.20694],"type":"Point"}
}