{
  "type": "Feature",
  "properties": {
    "gn:elevation":799,
    "gn:population":871,
    "iso:country":"IT",
    "name:arg_x_preferred":[
        "Seulu"
    ],
    "name:bel_x_preferred":[
        "\u0421\u0435\u045e\u043b\u0430"
    ],
    "name:bul_x_preferred":[
        "\u0421\u0435\u0443\u043b\u043e"
    ],
    "name:cat_x_preferred":[
        "Seulo"
    ],
    "name:deu_x_preferred":[
        "Seulo"
    ],
    "name:eng_x_preferred":[
        "Seulo"
    ],
    "name:epo_x_preferred":[
        "Seulo"
    ],
    "name:eus_x_preferred":[
        "Seulo"
    ],
    "name:fas_x_preferred":[
        "\u0633\u0626\u0648\u0644\u0648"
    ],
    "name:fra_x_preferred":[
        "Seulo"
    ],
    "name:hbs_x_preferred":[
        "Seulo"
    ],
    "name:hun_x_preferred":[
        "Seulo"
    ],
    "name:hye_x_preferred":[
        "\u054d\u0565\u0578\u0582\u056c\u0578"
    ],
    "name:ita_x_preferred":[
        "Seulo"
    ],
    "name:jpn_x_preferred":[
        "\u30bb\u30a6\u30fc\u30ed"
    ],
    "name:kaz_x_preferred":[
        "\u0421\u0435\u0443\u043b\u043e"
    ],
    "name:lat_x_preferred":[
        "Seulum"
    ],
    "name:lmo_x_preferred":[
        "Seulo"
    ],
    "name:msa_x_preferred":[
        "Seulo"
    ],
    "name:nan_x_preferred":[
        "Seulo"
    ],
    "name:nap_x_preferred":[
        "Seulo"
    ],
    "name:nld_x_preferred":[
        "Seulo"
    ],
    "name:pms_x_preferred":[
        "Seulo"
    ],
    "name:pol_x_preferred":[
        "Seulo"
    ],
    "name:por_x_preferred":[
        "Seulo"
    ],
    "name:ron_x_preferred":[
        "Seulo"
    ],
    "name:rus_x_preferred":[
        "\u0421\u0435\u0443\u043b\u043e"
    ],
    "name:scn_x_preferred":[
        "Seulo"
    ],
    "name:spa_x_preferred":[
        "Seulo"
    ],
    "name:srd_x_preferred":[
        "Seulu"
    ],
    "name:srp_x_preferred":[
        "\u0421\u0435\u0443\u043b\u043e"
    ],
    "name:tgl_x_preferred":[
        "Seulo"
    ],
    "name:ukr_x_preferred":[
        "\u0421\u0435\u0443\u043b\u043e"
    ],
    "name:uzb_x_preferred":[
        "Seulo"
    ],
    "name:vie_x_preferred":[
        "Seulo"
    ],
    "name:vol_x_preferred":[
        "Seulo"
    ],
    "name:war_x_preferred":[
        "Seulo"
    ],
    "name:zho_min_nan_x_preferred":[
        "Seulo"
    ],
    "name:zho_x_preferred":[
        "\u585e\u4e4c\u6d1b"
    ],
    "qs:a0":"Italia",
    "qs:a1":"*Cagliari",
    "qs:a1r":"0Sardegna",
    "qs:adm0":"Italia",
    "qs:la_lc":"*",
    "qs:level":"locality",
    "qs:loc":"Seulo",
    "qs:loc_alt":"Seulo",
    "qs:pop":0,
    "qs:type":"buffered point",
    "wd:wordcount":72,
    "wof:lang":[
        "ita"
    ],
    "wof:name":"Seulo",
    "wof:placetype":"locality",
    "wof:population":871
},
  "geometry": {"coordinates":[9.23667,39.870831],"type":"Point"}
}