{
  "type": "Feature",
  "properties": {
    "gn:admin1_code":"9",
    "gn:admin2_code":"MN",
    "gn:admin3_code":"20018.0",
    "gn:asciiname":"Pagliette",
    "gn:country_code":"IT",
    "gn:dem":141,
    "gn:feature_class":"P",
    "gn:feature_code":"PPL",
    "gn:name":"Pagliette",
    "gn:population":11,
    "gn:timezone":"Europe/Rome",
    "iso:country":"IT",
    "wof:name":"Pagliette",
    "wof:placetype":"locality",
    "wof:population":11
},
  "geometry": {"coordinates":[10.58646,45.35606],"type":"Point"}
}