{
  "type": "Feature",
  "properties": {
    "gn:admin1_code":"16",
    "gn:admin2_code":"FI",
    "gn:admin3_code":"48050.0",
    "gn:asciiname":"Dianella",
    "gn:country_code":"IT",
    "gn:dem":33,
    "gn:feature_class":"P",
    "gn:feature_code":"PPL",
    "gn:name":"Dianella",
    "gn:population":18,
    "gn:timezone":"Europe/Rome",
    "iso:country":"IT",
    "name:nld_x_preferred":[
        "Dianella"
    ],
    "wof:name":"Dianella",
    "wof:placetype":"locality",
    "wof:population":18
},
  "geometry": {"coordinates":[10.93508,43.74175],"type":"Point"}
}