{
  "type": "Feature",
  "properties": {
    "gn:admin1_code":"6.0",
    "gn:admin2_code":"UD",
    "gn:admin3_code":"30035.0",
    "gn:asciiname":"Fresis",
    "gn:country_code":"IT",
    "gn:dem":568,
    "gn:elevation":"574.0",
    "gn:feature_class":"P",
    "gn:feature_code":"PPL",
    "gn:name":"Fresis",
    "gn:population":82,
    "gn:timezone":"Europe/Rome",
    "iso:country":"IT",
    "wof:name":"Fresis",
    "wof:placetype":"locality",
    "wof:population":82
},
  "geometry": {"coordinates":[12.86109,46.4176],"type":"Point"}
}