{
  "type": "Feature",
  "properties": {
    "gn:admin1_code":"1",
    "gn:admin2_code":"CH",
    "gn:admin3_code":"69027.0",
    "gn:asciiname":"Villa Consalvi",
    "gn:country_code":"IT",
    "gn:dem":248,
    "gn:feature_class":"P",
    "gn:feature_code":"PPL",
    "gn:name":"Villa Consalvi",
    "gn:population":215,
    "gn:timezone":"Europe/Rome",
    "iso:country":"IT",
    "wof:name":"Villa Consalvi",
    "wof:placetype":"locality",
    "wof:population":215
},
  "geometry": {"coordinates":[14.3306,42.27992],"type":"Point"}
}