{
  "type": "Feature",
  "properties": {
    "gn:admin1_code":"12",
    "gn:admin2_code":"CN",
    "gn:admin3_code":"4139.0",
    "gn:asciiname":"Tetti Rossi",
    "gn:country_code":"IT",
    "gn:dem":1141,
    "gn:feature_class":"P",
    "gn:feature_code":"PPL",
    "gn:name":"Tetti Rossi",
    "gn:population":14,
    "gn:timezone":"Europe/Rome",
    "iso:country":"IT",
    "wof:name":"Tetti Rossi",
    "wof:placetype":"locality",
    "wof:population":14
},
  "geometry": {"coordinates":[7.31506,44.3762],"type":"Point"}
}