{
  "type": "Feature",
  "properties": {
    "gn:admin1_code":"5.0",
    "gn:admin2_code":"MO",
    "gn:admin3_code":"36018.0",
    "gn:asciiname":"Casine",
    "gn:country_code":"IT",
    "gn:dem":828,
    "gn:feature_class":"P",
    "gn:feature_code":"PPL",
    "gn:name":"Casine",
    "gn:population":9,
    "gn:timezone":"Europe/Rome",
    "iso:country":"IT",
    "wof:name":"Casine",
    "wof:placetype":"locality",
    "wof:population":9
},
  "geometry": {"coordinates":[10.76507,44.31817],"type":"Point"}
}