{
  "type": "Feature",
  "properties": {
    "gn:admin1_code":"9.0",
    "gn:admin2_code":"CO",
    "gn:admin3_code":"13239.0",
    "gn:asciiname":"Piazzo",
    "gn:country_code":"IT",
    "gn:dem":497,
    "gn:feature_class":"P",
    "gn:feature_code":"PPL",
    "gn:name":"Piazzo",
    "gn:population":18,
    "gn:timezone":"Europe/Rome",
    "iso:country":"IT",
    "wof:name":"Piazzo",
    "wof:placetype":"locality",
    "wof:population":18
},
  "geometry": {"coordinates":[9.32633,46.16393],"type":"Point"}
}