{
  "type": "Feature",
  "properties": {
    "gn:admin1_code":"5.0",
    "gn:admin2_code":"PC",
    "gn:admin3_code":"33039.0",
    "gn:asciiname":"Sant'Imento",
    "gn:country_code":"IT",
    "gn:dem":59,
    "gn:elevation":"59.0",
    "gn:feature_class":"P",
    "gn:feature_code":"PPL",
    "gn:name":"Sant'Imento",
    "gn:population":221,
    "gn:timezone":"Europe/Rome",
    "iso:country":"IT",
    "wof:name":"Sant'Imento",
    "wof:placetype":"locality",
    "wof:population":221
},
  "geometry": {"coordinates":[9.5679,45.0785],"type":"Point"}
}