{
  "type": "Feature",
  "properties": {
    "gn:admin1_code":"20",
    "gn:admin2_code":"VR",
    "gn:admin3_code":"23049.0",
    "gn:asciiname":"Carbognini",
    "gn:country_code":"IT",
    "gn:dem":74,
    "gn:feature_class":"P",
    "gn:feature_code":"PPL",
    "gn:name":"Carbognini",
    "gn:population":50,
    "gn:timezone":"Europe/Rome",
    "iso:country":"IT",
    "wof:name":"Carbognini",
    "wof:placetype":"locality",
    "wof:population":50
},
  "geometry": {"coordinates":[11.26745,45.48048],"type":"Point"}
}