{
  "type": "Feature",
  "properties": {
    "gn:admin1_code":"4.0",
    "gn:admin3_code":"63086.0",
    "gn:asciiname":"Ticciano",
    "gn:country_code":"IT",
    "gn:dem":496,
    "gn:feature_class":"P",
    "gn:feature_code":"PPL",
    "gn:name":"Ticciano",
    "gn:population":617,
    "gn:timezone":"Europe/Rome",
    "iso:country":"IT",
    "wof:name":"Ticciano",
    "wof:placetype":"locality",
    "wof:population":617
},
  "geometry": {"coordinates":[14.45378,40.64536],"type":"Point"}
}