{
  "type": "Feature",
  "properties": {
    "gn:admin1_code":"4",
    "gn:admin2_code":"SA",
    "gn:admin3_code":"65009.0",
    "gn:asciiname":"Scifro",
    "gn:country_code":"IT",
    "gn:dem":18,
    "gn:feature_class":"P",
    "gn:feature_code":"PPL",
    "gn:name":"Scifro",
    "gn:population":28,
    "gn:timezone":"Europe/Rome",
    "iso:country":"IT",
    "wof:name":"Scifro",
    "wof:placetype":"locality",
    "wof:population":28
},
  "geometry": {"coordinates":[15.16175,40.17205],"type":"Point"}
}