{
  "type": "Feature",
  "properties": {
    "gn:admin1_code":"20.0",
    "gn:admin2_code":"VI",
    "gn:admin3_code":"24041.0",
    "gn:asciiname":"Tessar Sotto",
    "gn:country_code":"IT",
    "gn:dem":820,
    "gn:feature_class":"P",
    "gn:feature_code":"PPL",
    "gn:name":"Tessar Sotto",
    "gn:population":13,
    "gn:timezone":"Europe/Rome",
    "iso:country":"IT",
    "wof:name":"Tessar Sotto",
    "wof:placetype":"locality",
    "wof:population":13
},
  "geometry": {"coordinates":[11.62301,45.88656],"type":"Point"}
}