{
  "type": "Feature",
  "properties": {
    "gn:admin1_code":"9",
    "gn:admin2_code":"VA",
    "gn:admin3_code":"12103.0",
    "gn:asciiname":"Cadorna",
    "gn:country_code":"IT",
    "gn:dem":607,
    "gn:feature_class":"P",
    "gn:feature_code":"PPL",
    "gn:name":"Cadorna",
    "gn:population":36,
    "gn:timezone":"Europe/Rome",
    "iso:country":"IT",
    "wof:name":"Cadorna",
    "wof:placetype":"locality",
    "wof:population":36
},
  "geometry": {"coordinates":[8.77321,45.97682],"type":"Point"}
}