{
  "type": "Feature",
  "properties": {
    "gn:admin1_code":"20",
    "gn:admin2_code":"VR",
    "gn:admin3_code":"23070.0",
    "gn:asciiname":"Coltrini",
    "gn:country_code":"IT",
    "gn:dem":191,
    "gn:feature_class":"P",
    "gn:feature_code":"PPL",
    "gn:name":"Coltrini",
    "gn:population":73,
    "gn:timezone":"Europe/Rome",
    "iso:country":"IT",
    "wof:name":"Coltrini",
    "wof:placetype":"locality",
    "wof:population":73
},
  "geometry": {"coordinates":[11.24378,45.51271],"type":"Point"}
}