{
  "type": "Feature",
  "properties": {
    "gn:admin1_code":"1",
    "gn:admin2_code":"PE",
    "gn:admin3_code":"68014.0",
    "gn:asciiname":"Fazio",
    "gn:country_code":"IT",
    "gn:dem":422,
    "gn:feature_class":"P",
    "gn:feature_code":"PPL",
    "gn:name":"Fazio",
    "gn:population":36,
    "gn:timezone":"Europe/Rome",
    "iso:country":"IT",
    "name:deu_x_preferred":[
        "Fazio"
    ],
    "name:fra_x_preferred":[
        "Fazio"
    ],
    "name:ita_x_preferred":[
        "Fazio"
    ],
    "name:por_x_preferred":[
        "Fazio"
    ],
    "name:rus_x_preferred":[
        "\u0424\u0430\u0446\u0438\u043e"
    ],
    "name:srp_x_preferred":[
        "Fazio"
    ],
    "wof:name":"Fazio",
    "wof:placetype":"locality",
    "wof:population":36
},
  "geometry": {"coordinates":[13.9094,42.39982],"type":"Point"}
}