{
  "type": "Feature",
  "properties": {
    "gn:admin1_code":"20.0",
    "gn:admin2_code":"VI",
    "gn:admin3_code":"24002.0",
    "gn:asciiname":"Ponti Nuovi",
    "gn:country_code":"IT",
    "gn:dem":13,
    "gn:feature_class":"P",
    "gn:feature_code":"PPLL",
    "gn:name":"Ponti Nuovi",
    "gn:population":0,
    "gn:timezone":"Europe/Rome",
    "iso:country":"IT",
    "wof:name":"Ponti Nuovi",
    "wof:placetype":"locality"
},
  "geometry": {"coordinates":[11.5996,45.35051],"type":"Point"}
}