{
  "type": "Feature",
  "properties": {
    "gn:admin1_code":"3",
    "gn:admin2_code":"RC",
    "gn:admin3_code":"80028.0",
    "gn:asciiname":"San Pietro",
    "gn:country_code":"IT",
    "gn:dem":143,
    "gn:feature_class":"P",
    "gn:feature_code":"PPL",
    "gn:name":"San Pietro",
    "gn:population":220,
    "gn:timezone":"Europe/Rome",
    "iso:country":"IT",
    "wof:name":"San Pietro",
    "wof:placetype":"locality",
    "wof:population":220
},
  "geometry": {"coordinates":[16.02059,38.40958],"type":"Point"}
}