{
  "type": "Feature",
  "properties": {
    "gn:admin1_code":"6.0",
    "gn:admin2_code":"PN",
    "gn:admin3_code":"93040.0",
    "gn:asciiname":"Roiata",
    "gn:country_code":"IT",
    "gn:dem":105,
    "gn:feature_class":"P",
    "gn:feature_code":"PPL",
    "gn:name":"Roiata",
    "gn:population":22,
    "gn:timezone":"Europe/Rome",
    "iso:country":"IT",
    "wof:name":"Roiata",
    "wof:placetype":"locality",
    "wof:population":22
},
  "geometry": {"coordinates":[12.65431,46.02128],"type":"Point"}
}