{
  "type": "Feature",
  "properties": {
    "gn:admin1_code":"12",
    "gn:admin2_code":"TO",
    "gn:admin3_code":"1304.0",
    "gn:asciiname":"Gerbido",
    "gn:country_code":"IT",
    "gn:dem":245,
    "gn:feature_class":"P",
    "gn:feature_code":"PPL",
    "gn:name":"Gerbido",
    "gn:population":64,
    "gn:timezone":"Europe/Rome",
    "iso:country":"IT",
    "wof:name":"Gerbido",
    "wof:placetype":"locality",
    "wof:population":64
},
  "geometry": {"coordinates":[7.97767,45.28717],"type":"Point"}
}