{
  "type": "Feature",
  "properties": {
    "gn:admin1_code":"16.0",
    "gn:admin2_code":"GR",
    "gn:admin3_code":"53026.0",
    "gn:asciiname":"San Giovanni delle Contee",
    "gn:cc2":"IT",
    "gn:country_code":"IT",
    "gn:dem":472,
    "gn:elevation":"470.0",
    "gn:feature_class":"P",
    "gn:feature_code":"PPL",
    "gn:name":"San Giovanni delle Contee",
    "gn:population":224,
    "gn:timezone":"Europe/Rome",
    "iso:country":"IT",
    "name:ceb_x_preferred":[
        "San Giovanni delle Contee"
    ],
    "name:ita_x_preferred":[
        "San Giovanni delle Contee"
    ],
    "name:nld_x_preferred":[
        "San Giovanni delle Contee"
    ],
    "name:srp_x_preferred":[
        "\u0421\u0430\u043d \u0402\u043e\u0432\u0430\u043d\u0438 \u0434\u0435\u043b\u0435 \u041a\u043e\u043d\u0442\u0435"
    ],
    "name:und_x_variant":[
        "San Giovanni"
    ],
    "wof:name":"San Giovanni delle Contee",
    "wof:placetype":"locality",
    "wof:population":224
},
  "geometry": {"coordinates":[11.76432,42.75308],"type":"Point"}
}