{
  "type": "Feature",
  "properties": {
    "gn:admin1_code":"9",
    "gn:admin2_code":"BS",
    "gn:admin3_code":"17116.0",
    "gn:asciiname":"Singia",
    "gn:country_code":"IT",
    "gn:dem":335,
    "gn:feature_class":"P",
    "gn:feature_code":"PPL",
    "gn:name":"Singia",
    "gn:population":11,
    "gn:timezone":"Europe/Rome",
    "iso:country":"IT",
    "wof:name":"Singia",
    "wof:placetype":"locality",
    "wof:population":11
},
  "geometry": {"coordinates":[10.47545,45.56369],"type":"Point"}
}