{
  "type": "Feature",
  "properties": {
    "gn:admin1_code":"6",
    "gn:admin2_code":"PN",
    "gn:admin3_code":"93006.0",
    "gn:asciiname":"Roppe",
    "gn:country_code":"IT",
    "gn:dem":556,
    "gn:feature_class":"P",
    "gn:feature_code":"PPL",
    "gn:name":"Roppe",
    "gn:population":19,
    "gn:timezone":"Europe/Rome",
    "iso:country":"IT",
    "wof:name":"Roppe",
    "wof:placetype":"locality",
    "wof:population":19
},
  "geometry": {"coordinates":[12.57321,46.19687],"type":"Point"}
}