{
  "type": "Feature",
  "properties": {
    "gn:admin1_code":"6",
    "gn:admin2_code":"PN",
    "gn:admin3_code":"93006.0",
    "gn:asciiname":"Roppe",
    "gn:country_code":"IT",
    "gn:dem":556,
    "gn:feature_class":"P",
    "gn:feature_code":"PPL",
    "gn:name":"Roppe",
    "gn:population":19,
    "gn:timezone":"Europe/Rome",
    "iso:country":"IT",
    "name:als_x_preferred":[
        "Roppe"
    ],
    "name:cat_x_preferred":[
        "Roppe"
    ],
    "name:ceb_x_preferred":[
        "Roppe"
    ],
    "name:deu_x_preferred":[
        "Roppe"
    ],
    "name:eus_x_preferred":[
        "Roppe"
    ],
    "name:fra_x_preferred":[
        "Roppe"
    ],
    "name:hun_x_preferred":[
        "Roppe"
    ],
    "name:ita_x_preferred":[
        "Roppe"
    ],
    "name:lat_x_preferred":[
        "Roppe"
    ],
    "name:mkd_x_preferred":[
        "\u0420\u043e\u043f"
    ],
    "name:msa_x_preferred":[
        "Roppe"
    ],
    "name:nld_x_preferred":[
        "Roppe"
    ],
    "name:oci_x_preferred":[
        "Roppe"
    ],
    "name:pms_x_preferred":[
        "Roppe"
    ],
    "name:pol_x_preferred":[
        "Roppe"
    ],
    "name:por_x_preferred":[
        "Roppe"
    ],
    "name:slk_x_preferred":[
        "Roppe"
    ],
    "name:spa_x_preferred":[
        "Roppe"
    ],
    "name:swe_x_preferred":[
        "Roppe"
    ],
    "name:ukr_x_preferred":[
        "\u0420\u043e\u043f\u043f"
    ],
    "name:uzb_x_preferred":[
        "Roppe"
    ],
    "name:vie_x_preferred":[
        "Roppe"
    ],
    "name:vol_x_preferred":[
        "Roppe"
    ],
    "name:war_x_preferred":[
        "Roppe"
    ],
    "name:zho_x_preferred":[
        "\u7f57\u666e"
    ],
    "wof:name":"Roppe",
    "wof:placetype":"locality",
    "wof:population":19
},
  "geometry": {"coordinates":[12.57321,46.19687],"type":"Point"}
}