{
  "type": "Feature",
  "properties": {
    "gn:admin1_code":"20",
    "gn:admin2_code":"TV",
    "gn:admin3_code":"26051.0",
    "gn:asciiname":"Borgo San Rocco",
    "gn:country_code":"IT",
    "gn:dem":8,
    "gn:feature_class":"P",
    "gn:feature_code":"PPL",
    "gn:name":"Borgo San Rocco",
    "gn:population":67,
    "gn:timezone":"Europe/Rome",
    "iso:country":"IT",
    "wof:name":"Borgo San Rocco",
    "wof:placetype":"locality",
    "wof:population":67
},
  "geometry": {"coordinates":[12.47278,45.75588],"type":"Point"}
}