{
  "type": "Feature",
  "properties": {
    "gn:admin1_code":"5",
    "gn:admin2_code":"PR",
    "gn:admin3_code":"34003.0",
    "gn:asciiname":"Casamurata",
    "gn:country_code":"IT",
    "gn:dem":954,
    "gn:feature_class":"P",
    "gn:feature_code":"PPL",
    "gn:name":"Casamurata",
    "gn:population":34,
    "gn:timezone":"Europe/Rome",
    "iso:country":"IT",
    "wof:name":"Casamurata",
    "wof:placetype":"locality",
    "wof:population":34
},
  "geometry": {"coordinates":[9.56761,44.56548],"type":"Point"}
}