{
  "type": "Feature",
  "properties": {
    "gn:admin1_code":"4",
    "gn:admin2_code":"SA",
    "gn:admin3_code":"65014.0",
    "gn:asciiname":"San Luigi",
    "gn:country_code":"IT",
    "gn:dem":0,
    "gn:feature_class":"P",
    "gn:feature_code":"PPL",
    "gn:name":"San Luigi",
    "gn:population":41,
    "gn:timezone":"Europe/Rome",
    "iso:country":"IT",
    "wof:name":"San Luigi",
    "wof:placetype":"locality",
    "wof:population":41
},
  "geometry": {"coordinates":[14.91884,40.55563],"type":"Point"}
}