{
  "type": "Feature",
  "properties": {
    "gn:admin1_code":"20",
    "gn:admin2_code":"VI",
    "gn:admin3_code":"24036.0",
    "gn:asciiname":"Rivella",
    "gn:country_code":"IT",
    "gn:dem":183,
    "gn:feature_class":"P",
    "gn:feature_code":"PPL",
    "gn:name":"Rivella",
    "gn:population":62,
    "gn:timezone":"Europe/Rome",
    "iso:country":"IT",
    "name:als_x_preferred":[
        "Rivella"
    ],
    "name:ces_x_preferred":[
        "Rivella"
    ],
    "name:dan_x_preferred":[
        "Rivella"
    ],
    "name:deu_x_preferred":[
        "Rivella"
    ],
    "name:epo_x_preferred":[
        "Rivella"
    ],
    "name:est_x_preferred":[
        "Rivella"
    ],
    "name:fin_x_preferred":[
        "Rivella"
    ],
    "name:fra_x_preferred":[
        "Rivella"
    ],
    "name:fry_x_preferred":[
        "Rivella"
    ],
    "name:ita_x_preferred":[
        "Rivella"
    ],
    "name:nld_x_preferred":[
        "Rivella"
    ],
    "name:por_x_preferred":[
        "Rivella"
    ],
    "name:rus_x_preferred":[
        "Rivella"
    ],
    "name:spa_x_preferred":[
        "Rivella"
    ],
    "name:ukr_x_preferred":[
        "Rivella"
    ],
    "name:zho_x_preferred":[
        "Rivella"
    ],
    "wof:name":"Rivella",
    "wof:placetype":"locality",
    "wof:population":62
},
  "geometry": {"coordinates":[11.46394,45.54468],"type":"Point"}
}