{
  "type": "Feature",
  "properties": {
    "gn:admin1_code":"20",
    "gn:admin2_code":"VI",
    "gn:admin3_code":"24036.0",
    "gn:asciiname":"Rivella",
    "gn:country_code":"IT",
    "gn:dem":183,
    "gn:feature_class":"P",
    "gn:feature_code":"PPL",
    "gn:name":"Rivella",
    "gn:population":62,
    "gn:timezone":"Europe/Rome",
    "iso:country":"IT",
    "wof:name":"Rivella",
    "wof:placetype":"locality",
    "wof:population":62
},
  "geometry": {"coordinates":[11.46394,45.54468],"type":"Point"}
}