{
  "type": "Feature",
  "properties": {
    "gn:admin1_code":"17.0",
    "gn:admin2_code":"BZ",
    "gn:admin3_code":"21017.0",
    "gn:asciiname":"Caminata di Tures",
    "gn:country_code":"IT",
    "gn:dem":854,
    "gn:feature_class":"P",
    "gn:feature_code":"PPL",
    "gn:name":"Caminata di Tures",
    "gn:population":342,
    "gn:timezone":"Europe/Rome",
    "iso:country":"IT",
    "wof:name":"Caminata di Tures",
    "wof:placetype":"locality",
    "wof:population":342
},
  "geometry": {"coordinates":[11.95724,46.90119],"type":"Point"}
}