{
  "type": "Feature",
  "properties": {
    "gn:admin1_code":"1",
    "gn:admin2_code":"PE",
    "gn:admin3_code":"68042.0",
    "gn:asciiname":"Marano",
    "gn:country_code":"IT",
    "gn:dem":300,
    "gn:feature_class":"P",
    "gn:feature_code":"PPL",
    "gn:name":"Marano",
    "gn:population":44,
    "gn:timezone":"Europe/Rome",
    "iso:country":"IT",
    "wof:name":"Marano",
    "wof:placetype":"locality",
    "wof:population":44
},
  "geometry": {"coordinates":[13.93368,42.21052],"type":"Point"}
}