{
  "type": "Feature",
  "properties": {
    "gn:admin1_code":"8.0",
    "gn:admin2_code":"SV",
    "gn:admin3_code":"9027.0",
    "gn:asciiname":"Santa Giulia Chiesa",
    "gn:country_code":"IT",
    "gn:dem":677,
    "gn:feature_class":"P",
    "gn:feature_code":"PPLL",
    "gn:name":"Santa Giulia Chiesa",
    "gn:population":5,
    "gn:timezone":"Europe/Rome",
    "iso:country":"IT",
    "wof:name":"Santa Giulia Chiesa",
    "wof:placetype":"locality",
    "wof:population":5
},
  "geometry": {"coordinates":[8.22973,44.47112],"type":"Point"}
}