{
  "type": "Feature",
  "properties": {
    "gn:admin1_code":"12",
    "gn:admin2_code":"CN",
    "gn:admin3_code":"4214.0",
    "gn:asciiname":"San Lorenzo",
    "gn:country_code":"IT",
    "gn:dem":298,
    "gn:feature_class":"P",
    "gn:feature_code":"PPL",
    "gn:name":"San Lorenzo",
    "gn:population":148,
    "gn:timezone":"Europe/Rome",
    "iso:country":"IT",
    "wof:name":"San Lorenzo",
    "wof:placetype":"locality",
    "wof:population":148
},
  "geometry": {"coordinates":[7.89578,44.81998],"type":"Point"}
}