{
  "type": "Feature",
  "properties": {
    "gn:admin1_code":"7.0",
    "gn:admin2_code":"FR",
    "gn:admin3_code":"60014.0",
    "gn:asciiname":"Farnete",
    "gn:country_code":"IT",
    "gn:dem":225,
    "gn:feature_class":"P",
    "gn:feature_code":"PPL",
    "gn:name":"Farnete",
    "gn:population":55,
    "gn:timezone":"Europe/Rome",
    "iso:country":"IT",
    "wof:name":"Farnete",
    "wof:placetype":"locality",
    "wof:population":55
},
  "geometry": {"coordinates":[13.44474,41.62357],"type":"Point"}
}