{
  "type": "Feature",
  "properties": {
    "gn:admin1_code":"7.0",
    "gn:admin2_code":"FR",
    "gn:admin3_code":"60014.0",
    "gn:asciiname":"Antica Colle Piscioso",
    "gn:country_code":"IT",
    "gn:dem":349,
    "gn:feature_class":"P",
    "gn:feature_code":"PPL",
    "gn:name":"Antica Colle Piscioso",
    "gn:population":743,
    "gn:timezone":"Europe/Rome",
    "iso:country":"IT",
    "wof:name":"Antica Colle Piscioso",
    "wof:placetype":"locality",
    "wof:population":743
},
  "geometry": {"coordinates":[13.48151,41.66183],"type":"Point"}
}