{
  "type": "Feature",
  "properties": {
    "gn:admin1_code":"6.0",
    "gn:admin2_code":"PN",
    "gn:admin3_code":"93007.0",
    "gn:asciiname":"Cral Tamai",
    "gn:country_code":"IT",
    "gn:dem":19,
    "gn:feature_class":"P",
    "gn:feature_code":"PPL",
    "gn:name":"Cral Tamai",
    "gn:population":301,
    "gn:timezone":"Europe/Rome",
    "iso:country":"IT",
    "wof:name":"Cral Tamai",
    "wof:placetype":"locality",
    "wof:population":301
},
  "geometry": {"coordinates":[12.55198,45.92479],"type":"Point"}
}