{
  "type": "Feature",
  "properties": {
    "gn:admin1_code":"4",
    "gn:admin2_code":"AV",
    "gn:admin3_code":"64086.0",
    "gn:asciiname":"Contrada Ramiera",
    "gn:country_code":"IT",
    "gn:dem":350,
    "gn:feature_class":"P",
    "gn:feature_code":"PPL",
    "gn:name":"Contrada Ramiera",
    "gn:population":104,
    "gn:timezone":"Europe/Rome",
    "iso:country":"IT",
    "wof:name":"Contrada Ramiera",
    "wof:placetype":"locality",
    "wof:population":104
},
  "geometry": {"coordinates":[14.84738,40.92298],"type":"Point"}
}