{
  "type": "Feature",
  "properties": {
    "gn:admin1_code":"1",
    "gn:admin2_code":"CH",
    "gn:admin3_code":"69068.0",
    "gn:asciiname":"Piano Croce-Piano Valle",
    "gn:country_code":"IT",
    "gn:dem":138,
    "gn:feature_class":"P",
    "gn:feature_code":"PPL",
    "gn:name":"Piano Croce-Piano Valle",
    "gn:population":257,
    "gn:timezone":"Europe/Rome",
    "iso:country":"IT",
    "wof:name":"Piano Croce-Piano Valle",
    "wof:placetype":"locality",
    "wof:population":257
},
  "geometry": {"coordinates":[14.61823,42.13908],"type":"Point"}
}