{
  "type": "Feature",
  "properties": {
    "gn:admin1_code":"16",
    "gn:admin2_code":"SI",
    "gn:admin3_code":"52004.0",
    "gn:asciiname":"Capannino della Suvera",
    "gn:country_code":"IT",
    "gn:dem":235,
    "gn:feature_class":"P",
    "gn:feature_code":"PPL",
    "gn:name":"Capannino della Suvera",
    "gn:population":26,
    "gn:timezone":"Europe/Rome",
    "iso:country":"IT",
    "wof:name":"Capannino della Suvera",
    "wof:placetype":"locality",
    "wof:population":26
},
  "geometry": {"coordinates":[11.1116,43.30704],"type":"Point"}
}