{
  "type": "Feature",
  "properties": {
    "gn:admin1_code":"10.0",
    "gn:admin2_code":"AP",
    "gn:admin3_code":"44007.0",
    "gn:asciiname":"Funti",
    "gn:country_code":"IT",
    "gn:dem":521,
    "gn:elevation":"512.0",
    "gn:feature_class":"P",
    "gn:feature_code":"PPL",
    "gn:name":"Funti",
    "gn:population":33,
    "gn:timezone":"Europe/Rome",
    "iso:country":"IT",
    "wof:name":"Funti",
    "wof:placetype":"locality",
    "wof:population":33
},
  "geometry": {"coordinates":[13.51091,42.80227],"type":"Point"}
}