{
  "type": "Feature",
  "properties": {
    "gn:admin1_code":"16",
    "gn:admin2_code":"PI",
    "gn:admin3_code":"50012.0",
    "gn:asciiname":"Sassi Bianchi",
    "gn:country_code":"IT",
    "gn:dem":426,
    "gn:feature_class":"P",
    "gn:feature_code":"PPL",
    "gn:name":"Sassi Bianchi",
    "gn:population":24,
    "gn:timezone":"Europe/Rome",
    "iso:country":"IT",
    "wof:name":"Sassi Bianchi",
    "wof:placetype":"locality",
    "wof:population":24
},
  "geometry": {"coordinates":[10.63586,43.47711],"type":"Point"}
}