{
  "type": "Feature",
  "properties": {
    "gn:admin1_code":"20",
    "gn:admin2_code":"VI",
    "gn:admin3_code":"24057.0",
    "gn:asciiname":"Pianezzola",
    "gn:country_code":"IT",
    "gn:dem":264,
    "gn:feature_class":"P",
    "gn:feature_code":"PPL",
    "gn:name":"Pianezzola",
    "gn:population":33,
    "gn:timezone":"Europe/Rome",
    "iso:country":"IT",
    "wof:name":"Pianezzola",
    "wof:placetype":"locality",
    "wof:population":33
},
  "geometry": {"coordinates":[11.66871,45.7721],"type":"Point"}
}