{
  "type": "Feature",
  "properties": {
    "gn:admin1_code":"12",
    "gn:admin2_code":"AL",
    "gn:admin3_code":"6067.0",
    "gn:asciiname":"Salogni",
    "gn:country_code":"IT",
    "gn:dem":952,
    "gn:feature_class":"P",
    "gn:feature_code":"PPL",
    "gn:name":"Salogni",
    "gn:population":26,
    "gn:timezone":"Europe/Rome",
    "iso:country":"IT",
    "wof:name":"Salogni",
    "wof:placetype":"locality",
    "wof:population":26
},
  "geometry": {"coordinates":[9.17346,44.71809],"type":"Point"}
}