{
  "type": "Feature",
  "properties": {
    "gn:admin1_code":"5",
    "gn:admin2_code":"PC",
    "gn:admin3_code":"33004.0",
    "gn:asciiname":"Grilli",
    "gn:country_code":"IT",
    "gn:dem":570,
    "gn:feature_class":"P",
    "gn:feature_code":"PPL",
    "gn:name":"Grilli",
    "gn:population":12,
    "gn:timezone":"Europe/Rome",
    "iso:country":"IT",
    "wof:name":"Grilli",
    "wof:placetype":"locality",
    "wof:population":12
},
  "geometry": {"coordinates":[9.56673,44.82455],"type":"Point"}
}