{
  "type": "Feature",
  "properties": {
    "gn:admin1_code":"5",
    "gn:admin2_code":"MO",
    "gn:admin3_code":"36029.0",
    "gn:asciiname":"Pianacci",
    "gn:country_code":"IT",
    "gn:dem":799,
    "gn:feature_class":"P",
    "gn:feature_code":"PPL",
    "gn:name":"Pianacci",
    "gn:population":13,
    "gn:timezone":"Europe/Rome",
    "iso:country":"IT",
    "name:ita_x_preferred":[
        "Pianacci"
    ],
    "name:ltz_x_preferred":[
        "Pianacci"
    ],
    "name:ukr_x_preferred":[
        "\u041f'\u044f\u043d\u0430\u0447\u0447\u0456"
    ],
    "wof:name":"Pianacci",
    "wof:placetype":"locality",
    "wof:population":13
},
  "geometry": {"coordinates":[10.64217,44.31375],"type":"Point"}
}