{
  "type": "Feature",
  "properties": {
    "gn:admin1_code":"9",
    "gn:admin2_code":"BG",
    "gn:admin3_code":"16147.0",
    "gn:asciiname":"Valzurio",
    "gn:country_code":"IT",
    "gn:dem":820,
    "gn:feature_class":"P",
    "gn:feature_code":"PPL",
    "gn:name":"Valzurio",
    "gn:population":30,
    "gn:timezone":"Europe/Rome",
    "iso:country":"IT",
    "wof:name":"Valzurio",
    "wof:placetype":"locality",
    "wof:population":30
},
  "geometry": {"coordinates":[9.97143,45.92394],"type":"Point"}
}