{
  "type": "Feature",
  "properties": {
    "gn:admin1_code":"5.0",
    "gn:admin2_code":"FE",
    "gn:admin3_code":"38005.0",
    "gn:asciiname":"Cartiera",
    "gn:country_code":"IT",
    "gn:dem":-5,
    "gn:feature_class":"P",
    "gn:feature_code":"PPL",
    "gn:name":"Cartiera",
    "gn:population":0,
    "gn:timezone":"Europe/Rome",
    "iso:country":"IT",
    "wof:name":"Cartiera",
    "wof:placetype":"locality"
},
  "geometry": {"coordinates":[12.06667,44.85],"type":"Point"}
}