{
  "type": "Feature",
  "properties": {
    "gn:admin1_code":"4.0",
    "gn:admin3_code":"63049.0",
    "gn:asciiname":"Villanova",
    "gn:country_code":"IT",
    "gn:dem":78,
    "gn:feature_class":"P",
    "gn:feature_code":"PPL",
    "gn:name":"Villanova",
    "gn:population":0,
    "gn:timezone":"Europe/Rome",
    "iso:country":"IT",
    "wof:name":"Villanova",
    "wof:placetype":"locality"
},
  "geometry": {"coordinates":[14.21667,40.83333],"type":"Point"}
}