{
  "type": "Feature",
  "properties": {
    "gn:admin1_code":"15",
    "gn:admin2_code":"ME",
    "gn:admin3_code":"83019.0",
    "gn:asciiname":"Belvedere",
    "gn:country_code":"IT",
    "gn:dem":95,
    "gn:feature_class":"P",
    "gn:feature_code":"PPL",
    "gn:name":"Belvedere",
    "gn:population":276,
    "gn:timezone":"Europe/Rome",
    "iso:country":"IT",
    "wof:name":"Belvedere",
    "wof:placetype":"locality",
    "wof:population":276
},
  "geometry": {"coordinates":[15.08141,38.10574],"type":"Point"}
}