{
  "type": "Feature",
  "properties": {
    "gn:admin1_code":"1.0",
    "gn:admin2_code":"AQ",
    "gn:admin3_code":"66101.0",
    "gn:asciiname":"Viaro",
    "gn:country_code":"IT",
    "gn:dem":767,
    "gn:elevation":"805.0",
    "gn:feature_class":"P",
    "gn:feature_code":"PPL",
    "gn:name":"Viaro",
    "gn:population":20,
    "gn:timezone":"Europe/Rome",
    "iso:country":"IT",
    "wof:name":"Viaro",
    "wof:placetype":"locality",
    "wof:population":20
},
  "geometry": {"coordinates":[13.2866,42.30847],"type":"Point"}
}