{
  "type": "Feature",
  "properties": {
    "gn:admin1_code":"5.0",
    "gn:admin2_code":"FC",
    "gn:admin3_code":"40037.0",
    "gn:asciiname":"Roncofreddo-Santa Paola",
    "gn:country_code":"IT",
    "gn:dem":300,
    "gn:feature_class":"P",
    "gn:feature_code":"PPLA3",
    "gn:name":"Roncofreddo-Santa Paola",
    "gn:population":1237,
    "gn:timezone":"Europe/Rome",
    "iso:country":"IT",
    "wof:name":"Roncofreddo-Santa Paola",
    "wof:placetype":"locality",
    "wof:population":1237
},
  "geometry": {"coordinates":[12.31523,44.04251],"type":"Point"}
}