{
  "type": "Feature",
  "properties": {
    "gn:admin1_code":"4",
    "gn:admin2_code":"AV",
    "gn:admin3_code":"64104.0",
    "gn:asciiname":"Serrapreta",
    "gn:country_code":"IT",
    "gn:dem":425,
    "gn:feature_class":"P",
    "gn:feature_code":"PPL",
    "gn:name":"Serrapreta",
    "gn:population":66,
    "gn:timezone":"Europe/Rome",
    "iso:country":"IT",
    "wof:name":"Serrapreta",
    "wof:placetype":"locality",
    "wof:population":66
},
  "geometry": {"coordinates":[15.14888,41.02813],"type":"Point"}
}