{
  "type": "Feature",
  "properties": {
    "gn:admin1_code":"16.0",
    "gn:admin2_code":"PT",
    "gn:admin3_code":"47007.0",
    "gn:asciiname":"Casore del Monte",
    "gn:country_code":"IT",
    "gn:dem":551,
    "gn:feature_class":"P",
    "gn:feature_code":"PPL",
    "gn:name":"Casore del Monte",
    "gn:population":54,
    "gn:timezone":"Europe/Rome",
    "iso:country":"IT",
    "wof:name":"Casore del Monte",
    "wof:placetype":"locality",
    "wof:population":54
},
  "geometry": {"coordinates":[10.80995,43.93425],"type":"Point"}
}