{
  "type": "Feature",
  "properties": {
    "gn:admin1_code":"7",
    "gn:admin2_code":"FR",
    "gn:admin3_code":"60048.0",
    "gn:asciiname":"Celleta",
    "gn:country_code":"IT",
    "gn:dem":152,
    "gn:feature_class":"P",
    "gn:feature_code":"PPL",
    "gn:name":"Celleta",
    "gn:population":213,
    "gn:timezone":"Europe/Rome",
    "iso:country":"IT",
    "wof:name":"Celleta",
    "wof:placetype":"locality",
    "wof:population":213
},
  "geometry": {"coordinates":[13.27573,41.57887],"type":"Point"}
}