{
  "type": "Feature",
  "properties": {
    "gn:admin1_code":"5.0",
    "gn:admin2_code":"FC",
    "gn:admin3_code":"40008.0",
    "gn:asciiname":"Stradone Sala",
    "gn:country_code":"IT",
    "gn:dem":4,
    "gn:feature_class":"P",
    "gn:feature_code":"PPL",
    "gn:name":"Stradone Sala",
    "gn:population":64,
    "gn:timezone":"Europe/Rome",
    "iso:country":"IT",
    "wof:name":"Stradone Sala",
    "wof:placetype":"locality",
    "wof:population":64
},
  "geometry": {"coordinates":[12.39464,44.16774],"type":"Point"}
}