{
  "type": "Feature",
  "properties": {
    "iso:country":"IT",
    "wof:name":"Tetti Basse di Dora",
    "wof:placetype":"neighbourhood"
},
  "geometry": {"coordinates":[7.62195807661331,45.08641020432994],"type":"Point"}
}