{
  "type": "Feature",
  "properties": {
    "gn:admin1_code":"12",
    "gn:admin2_code":"BI",
    "gn:admin3_code":"96015.0",
    "gn:asciiname":"Terzoglio",
    "gn:country_code":"IT",
    "gn:dem":226,
    "gn:feature_class":"P",
    "gn:feature_code":"PPL",
    "gn:name":"Terzoglio",
    "gn:population":138,
    "gn:timezone":"Europe/Rome",
    "iso:country":"IT",
    "wof:name":"Terzoglio",
    "wof:placetype":"locality",
    "wof:population":138
},
  "geometry": {"coordinates":[8.22017,45.53215],"type":"Point"}
}