{
  "type": "Feature",
  "properties": {
    "gn:admin1_code":"16",
    "gn:admin2_code":"LU",
    "gn:admin3_code":"46010.0",
    "gn:asciiname":"Mozzanella",
    "gn:country_code":"IT",
    "gn:dem":434,
    "gn:feature_class":"P",
    "gn:feature_code":"PPLL",
    "gn:name":"Mozzanella",
    "gn:population":10,
    "gn:timezone":"Europe/Rome",
    "iso:country":"IT",
    "wof:name":"Mozzanella",
    "wof:placetype":"locality",
    "wof:population":10
},
  "geometry": {"coordinates":[10.38815,44.14913],"type":"Point"}
}