{
  "type": "Feature",
  "properties": {
    "gn:admin1_code":"1.0",
    "gn:admin2_code":"CH",
    "gn:admin3_code":"69046.0",
    "gn:asciiname":"Torre Marino II",
    "gn:country_code":"IT",
    "gn:dem":350,
    "gn:feature_class":"P",
    "gn:feature_code":"PPL",
    "gn:name":"Torre Marino II",
    "gn:population":50,
    "gn:timezone":"Europe/Rome",
    "iso:country":"IT",
    "wof:name":"Torre Marino II",
    "wof:placetype":"locality",
    "wof:population":50
},
  "geometry": {"coordinates":[14.37298,42.20043],"type":"Point"}
}