{
  "type": "Feature",
  "properties": {
    "gn:admin1_code":"7",
    "gn:admin2_code":"FR",
    "gn:admin3_code":"60058.0",
    "gn:asciiname":"Scarafone I",
    "gn:country_code":"IT",
    "gn:dem":183,
    "gn:feature_class":"P",
    "gn:feature_code":"PPL",
    "gn:name":"Scarafone I",
    "gn:population":35,
    "gn:timezone":"Europe/Rome",
    "iso:country":"IT",
    "wof:name":"Scarafone I",
    "wof:placetype":"locality",
    "wof:population":35
},
  "geometry": {"coordinates":[13.46434,41.61049000000001],"type":"Point"}
}