{
  "type": "Feature",
  "properties": {
    "gn:admin1_code":"4",
    "gn:admin3_code":"63050.0",
    "gn:asciiname":"Pagliarone",
    "gn:country_code":"IT",
    "gn:dem":75,
    "gn:feature_class":"P",
    "gn:feature_code":"PPL",
    "gn:name":"Pagliarone",
    "gn:population":107,
    "gn:timezone":"Europe/Rome",
    "iso:country":"IT",
    "wof:name":"Pagliarone",
    "wof:placetype":"locality",
    "wof:population":107
},
  "geometry": {"coordinates":[14.51062,40.85888],"type":"Point"}
}