{
  "type": "Feature",
  "properties": {
    "gn:admin1_code":"8",
    "gn:admin2_code":"GE",
    "gn:admin3_code":"10065.0",
    "gn:asciiname":"Chiappa",
    "gn:country_code":"IT",
    "gn:dem":881,
    "gn:feature_class":"P",
    "gn:feature_code":"PPLL",
    "gn:name":"Chiappa",
    "gn:population":8,
    "gn:timezone":"Europe/Rome",
    "iso:country":"IT",
    "wof:name":"Chiappa",
    "wof:placetype":"locality",
    "wof:population":8
},
  "geometry": {"coordinates":[9.11799,44.56099],"type":"Point"}
}