{
  "type": "Feature",
  "properties": {
    "iso:country":"IT",
    "name:arg_x_preferred":[
        "Santa Lucia"
    ],
    "name:bre_x_preferred":[
        "Santa Lucia"
    ],
    "name:ces_x_preferred":[
        "Santa Lucia"
    ],
    "name:dan_x_preferred":[
        "Santa Lucia"
    ],
    "name:deu_x_preferred":[
        "Santa Lucia"
    ],
    "name:eml_x_preferred":[
        "Santa Lucia"
    ],
    "name:fin_x_preferred":[
        "Santa Lucia"
    ],
    "name:fra_x_preferred":[
        "Santa Lucia"
    ],
    "name:heb_x_preferred":[
        "\u05e1\u05e0\u05d8\u05d4 \u05dc\u05d5\u05e6'\u05d9\u05d4"
    ],
    "name:jpn_x_preferred":[
        "\u30b5\u30f3\u30bf\u30fb\u30eb\u30c1\u30a2"
    ],
    "name:nap_x_preferred":[
        "Santa Lucia"
    ],
    "name:nld_x_preferred":[
        "Santa Lucia"
    ],
    "name:nno_x_preferred":[
        "Luciasongen"
    ],
    "name:nor_x_preferred":[
        "Luciasangen"
    ],
    "name:pol_x_preferred":[
        "Santa Lucia"
    ],
    "name:por_x_preferred":[
        "Santa Lucia"
    ],
    "name:rus_x_preferred":[
        "\u0421\u0430\u043d\u0442\u0430 \u041b\u044e\u0447\u0438\u044f"
    ],
    "name:swe_x_preferred":[
        "Lucias\u00e5ngen"
    ],
    "name:tha_x_preferred":[
        "\u0e0b\u0e32\u0e19\u0e15\u0e32\u0e25\u0e39\u0e0a\u0e35\u0e2d\u0e32"
    ],
    "name:ukr_x_preferred":[
        "Santa Lucia"
    ],
    "name:zho_x_preferred":[
        "\u6851\u5854\u9732\u742a\u5a05"
    ],
    "qs_pg:aaroncc":"IT",
    "qs_pg:name":"Santa Lucia",
    "qs_pg:name_adm0":"Italia",
    "qs_pg:name_adm1":"Toscana",
    "qs_pg:photos":43,
    "qs_pg:photos_1k":9,
    "qs_pg:photos_9k":1,
    "qs_pg:photos_9r":2,
    "qs_pg:photos_all":43,
    "qs_pg:photos_sr":2,
    "qs_pg:pop_sr":0,
    "qs_pg:qs_pg_placetype":"locality",
    "qs_pg:qs_pg_placetype_gp":"Town",
    "qs_pg:woe_adm0":23424853,
    "woe:adm0_id":23424853,
    "woe:name_adm0":"Italia",
    "woe:name_adm1":"Toscana",
    "woe:placetype":"Town",
    "wof:name":"Santa Lucia",
    "wof:placetype":"locality"
},
  "geometry": {"coordinates":[11.114044,43.906055],"type":"Point"}
}