{
  "type": "Feature",
  "properties": {
    "gn:admin1_code":"8",
    "gn:admin2_code":"IM",
    "gn:admin3_code":"8049.0",
    "gn:asciiname":"Lavina",
    "gn:country_code":"IT",
    "gn:dem":337,
    "gn:feature_class":"P",
    "gn:feature_code":"PPL",
    "gn:name":"Lavina",
    "gn:population":103,
    "gn:timezone":"Europe/Rome",
    "iso:country":"IT",
    "wof:name":"Lavina",
    "wof:placetype":"locality",
    "wof:population":103
},
  "geometry": {"coordinates":[7.90345,44.02717],"type":"Point"}
}