{
  "type": "Feature",
  "properties": {
    "gn:admin1_code":"16.0",
    "gn:admin2_code":"MS",
    "gn:admin3_code":"45005.0",
    "gn:asciiname":"Casa Pelati",
    "gn:country_code":"IT",
    "gn:dem":481,
    "gn:feature_class":"P",
    "gn:feature_code":"PPLL",
    "gn:name":"Casa Pelati",
    "gn:population":1,
    "gn:timezone":"Europe/Rome",
    "iso:country":"IT",
    "wof:name":"Casa Pelati",
    "wof:placetype":"locality",
    "wof:population":1
},
  "geometry": {"coordinates":[10.12491,44.28997],"type":"Point"}
}