{
  "type": "Feature",
  "properties": {
    "gn:admin1_code":"9",
    "gn:admin2_code":"MN",
    "gn:admin3_code":"20015.0",
    "gn:asciiname":"Perosso Sopra",
    "gn:country_code":"IT",
    "gn:dem":55,
    "gn:feature_class":"P",
    "gn:feature_code":"PPL",
    "gn:name":"Perosso Sopra",
    "gn:population":58,
    "gn:timezone":"Europe/Rome",
    "iso:country":"IT",
    "wof:name":"Perosso Sopra",
    "wof:placetype":"locality",
    "wof:population":58
},
  "geometry": {"coordinates":[10.47789,45.31973],"type":"Point"}
}