{
  "type": "Feature",
  "properties": {
    "gn:admin1_code":"15",
    "gn:admin2_code":"SR",
    "gn:admin3_code":"89001.0",
    "gn:asciiname":"Torre I",
    "gn:country_code":"IT",
    "gn:dem":162,
    "gn:feature_class":"P",
    "gn:feature_code":"PPLL",
    "gn:name":"Torre I",
    "gn:population":9,
    "gn:timezone":"Europe/Rome",
    "iso:country":"IT",
    "wof:name":"Torre I",
    "wof:placetype":"locality",
    "wof:population":9
},
  "geometry": {"coordinates":[15.08074,37.27861],"type":"Point"}
}