{
  "type": "Feature",
  "properties": {
    "gn:admin1_code":"14.0",
    "gn:admin2_code":"CA",
    "gn:admin3_code":"92050.0",
    "gn:asciiname":"Foxi'e Sali",
    "gn:country_code":"IT",
    "gn:dem":8,
    "gn:feature_class":"P",
    "gn:feature_code":"PPL",
    "gn:name":"Foxi'e Sali",
    "gn:population":0,
    "gn:timezone":"Europe/Rome",
    "iso:country":"IT",
    "wof:name":"Foxi'e Sali",
    "wof:placetype":"locality"
},
  "geometry": {"coordinates":[8.98472,38.97111],"type":"Point"}
}