{
  "type": "Feature",
  "properties": {
    "gn:admin1_code":"16",
    "gn:admin2_code":"FI",
    "gn:admin3_code":"48052.0",
    "gn:asciiname":"San Michele",
    "gn:country_code":"IT",
    "gn:dem":297,
    "gn:feature_class":"P",
    "gn:feature_code":"PPL",
    "gn:name":"San Michele",
    "gn:population":19,
    "gn:timezone":"Europe/Rome",
    "iso:country":"IT",
    "wof:name":"San Michele",
    "wof:placetype":"locality",
    "wof:population":19
},
  "geometry": {"coordinates":[11.40253,43.6822],"type":"Point"}
}