{
  "type": "Feature",
  "properties": {
    "gn:admin1_code":"11",
    "gn:admin2_code":"IS",
    "gn:admin3_code":"94010.0",
    "gn:asciiname":"Fiaschi",
    "gn:country_code":"IT",
    "gn:dem":826,
    "gn:feature_class":"P",
    "gn:feature_code":"PPL",
    "gn:name":"Fiaschi",
    "gn:population":39,
    "gn:timezone":"Europe/Rome",
    "iso:country":"IT",
    "wof:name":"Fiaschi",
    "wof:placetype":"locality",
    "wof:population":39
},
  "geometry": {"coordinates":[14.34268,41.5599],"type":"Point"}
}