{
  "type": "Feature",
  "properties": {
    "gn:admin1_code":"16.0",
    "gn:admin2_code":"LU",
    "gn:admin3_code":"46002.0",
    "gn:asciiname":"Palleggio-Cocciglia",
    "gn:country_code":"IT",
    "gn:dem":231,
    "gn:feature_class":"P",
    "gn:feature_code":"PPL",
    "gn:name":"Palleggio-Cocciglia",
    "gn:population":211,
    "gn:timezone":"Europe/Rome",
    "iso:country":"IT",
    "wof:name":"Palleggio-Cocciglia",
    "wof:placetype":"locality",
    "wof:population":211
},
  "geometry": {"coordinates":[10.65699,44.03703],"type":"Point"}
}