{
  "type": "Feature",
  "properties": {
    "gn:admin1_code":"3",
    "gn:admin2_code":"CS",
    "gn:admin3_code":"78033.0",
    "gn:asciiname":"Svincolo Autostrada",
    "gn:country_code":"IT",
    "gn:dem":471,
    "gn:feature_class":"P",
    "gn:feature_code":"PPL",
    "gn:name":"Svincolo Autostrada",
    "gn:population":59,
    "gn:timezone":"Europe/Rome",
    "iso:country":"IT",
    "wof:name":"Svincolo Autostrada",
    "wof:placetype":"locality",
    "wof:population":59
},
  "geometry": {"coordinates":[16.25399,39.83178],"type":"Point"}
}