{
  "type": "Feature",
  "properties": {
    "gn:admin1_code":"10",
    "gn:admin2_code":"AN",
    "gn:admin3_code":"42003.0",
    "gn:asciiname":"Borgo Giovanni XXIII",
    "gn:country_code":"IT",
    "gn:dem":308,
    "gn:feature_class":"P",
    "gn:feature_code":"PPL",
    "gn:name":"Borgo Giovanni XXIII",
    "gn:population":112,
    "gn:timezone":"Europe/Rome",
    "iso:country":"IT",
    "wof:name":"Borgo Giovanni XXIII",
    "wof:placetype":"locality",
    "wof:population":112
},
  "geometry": {"coordinates":[12.96856,43.53427],"type":"Point"}
}