{
  "type": "Feature",
  "properties": {
    "iso:country":"IT",
    "wof:name":"Borghesiana",
    "wof:placetype":"neighbourhood"
},
  "geometry": {"coordinates":[12.6809761619604,41.86896465126514],"type":"Point"}
}