{
  "type": "Feature",
  "properties": {
    "gn:admin1_code":"8",
    "gn:admin2_code":"SP",
    "gn:admin3_code":"11017.0",
    "gn:asciiname":"Groppo",
    "gn:country_code":"IT",
    "gn:dem":217,
    "gn:feature_class":"P",
    "gn:feature_code":"PPL",
    "gn:name":"Groppo",
    "gn:population":14,
    "gn:timezone":"Europe/Rome",
    "iso:country":"IT",
    "wof:name":"Groppo",
    "wof:placetype":"locality",
    "wof:population":14
},
  "geometry": {"coordinates":[9.61882,44.19116],"type":"Point"}
}