{
  "type": "Feature",
  "properties": {
    "gn:admin1_code":"4",
    "gn:admin2_code":"AV",
    "gn:admin3_code":"64121.0",
    "gn:asciiname":"Volpari",
    "gn:country_code":"IT",
    "gn:dem":186,
    "gn:feature_class":"P",
    "gn:feature_code":"PPL",
    "gn:name":"Volpari",
    "gn:population":82,
    "gn:timezone":"Europe/Rome",
    "iso:country":"IT",
    "wof:name":"Volpari",
    "wof:placetype":"locality",
    "wof:population":82
},
  "geometry": {"coordinates":[14.77264,40.82482],"type":"Point"}
}