{
  "type": "Feature",
  "properties": {
    "iso:country":"IT",
    "name:ita_x_preferred":[
        "Aeroporto"
    ],
    "qs:gn_adm0_cc":"IT",
    "qs:gn_local":3169522,
    "qs:gn_nam_loc":"Reggio nell'Emilia, Reggio nell'Emilia, Reggio nell'Emilia, Emilia-Romagna, IT",
    "qs:gn_namadm1":"05",
    "qs:local_max":3576,
    "qs:local_sum":9003,
    "qs:localhoods":17,
    "qs:name":"Aeroporto",
    "qs:name_adm0":"Italia",
    "qs:name_adm1":"Emilia Romagna",
    "qs:name_adm2":"Reggio nell'Emilia",
    "qs:name_lau":"Reggio nell'Emilia",
    "qs:name_local":"Reggio nell'Emilia",
    "qs:photo_max":418,
    "qs:photo_sum":595,
    "qs:placetype":"Suburb",
    "qs:quad_count":13,
    "qs:woe_adm0":23424853,
    "qs:woe_adm1":7153334,
    "qs:woe_adm2":12591835,
    "qs:woe_lau":12677235,
    "qs:woe_local":721568,
    "qs:woe_ver":"7.10.0",
    "wof:name":"Aeroporto",
    "wof:placetype":"neighbourhood"
},
  "geometry": {"coordinates":[10.665703,44.698064],"type":"Point"}
}