{
  "type": "Feature",
  "properties": {
    "gn:admin1_code":"3",
    "gn:admin2_code":"CS",
    "gn:admin3_code":"78134.0",
    "gn:asciiname":"Foresta",
    "gn:country_code":"IT",
    "gn:dem":988,
    "gn:feature_class":"P",
    "gn:feature_code":"PPL",
    "gn:name":"Foresta",
    "gn:population":15,
    "gn:timezone":"Europe/Rome",
    "iso:country":"IT",
    "wof:name":"Foresta",
    "wof:placetype":"locality",
    "wof:population":15
},
  "geometry": {"coordinates":[16.36121,39.19522],"type":"Point"}
}