{
  "type": "Feature",
  "properties": {
    "gn:admin1_code":"17.0",
    "gn:admin2_code":"BZ",
    "gn:admin3_code":"21033.0",
    "gn:asciiname":"San Giovanni",
    "gn:cc2":"IT",
    "gn:country_code":"IT",
    "gn:dem":1452,
    "gn:feature_class":"P",
    "gn:feature_code":"PPL",
    "gn:name":"San Giovanni",
    "gn:population":0,
    "gn:timezone":"Europe/Rome",
    "iso:country":"IT",
    "name:ceb_x_preferred":[
        "San Giovanni"
    ],
    "name:ces_x_preferred":[
        "San Giovanni"
    ],
    "name:deu_x_preferred":[
        "San Giovanni"
    ],
    "name:epo_x_preferred":[
        "San Giovanni"
    ],
    "name:fas_x_preferred":[
        "\u0633\u0646 \u062c\u06cc\u0648\u0648\u0627\u0646\u06cc"
    ],
    "name:ita_x_preferred":[
        "San Giovanni"
    ],
    "name:nld_x_preferred":[
        "San Giovanni"
    ],
    "name:pol_x_preferred":[
        "San Giovanni"
    ],
    "name:por_x_preferred":[
        "San Giovanni"
    ],
    "name:rus_x_preferred":[
        "\u0421\u0430\u043d-\u0414\u0436\u043e\u0432\u0430\u043d\u043d\u0438"
    ],
    "name:sco_x_preferred":[
        "San Giovanni"
    ],
    "name:srp_x_preferred":[
        "San \u0110ovani"
    ],
    "name:swe_x_preferred":[
        "San Giovanni"
    ],
    "name:und_x_variant":[
        "San Giovanni di Fumes",
        "San Giovanni"
    ],
    "wof:name":"San Giovanni",
    "wof:placetype":"locality"
},
  "geometry": {"coordinates":[11.73333,46.63333],"type":"Point"}
}