{
  "type": "Feature",
  "properties": {
    "gn:admin1_code":"17.0",
    "gn:admin2_code":"BZ",
    "gn:admin3_code":"21033.0",
    "gn:asciiname":"San Giovanni",
    "gn:cc2":"IT",
    "gn:country_code":"IT",
    "gn:dem":1452,
    "gn:feature_class":"P",
    "gn:feature_code":"PPL",
    "gn:name":"San Giovanni",
    "gn:population":0,
    "gn:timezone":"Europe/Rome",
    "iso:country":"IT",
    "name:und_x_variant":[
        "San Giovanni di Fumes",
        "San Giovanni"
    ],
    "wof:name":"San Giovanni",
    "wof:placetype":"locality"
},
  "geometry": {"coordinates":[11.73333,46.63333],"type":"Point"}
}