{
  "type": "Feature",
  "properties": {
    "gn:admin1_code":"7",
    "gn:admin2_code":"VT",
    "gn:admin3_code":"56027.0",
    "gn:asciiname":"Valli",
    "gn:country_code":"IT",
    "gn:dem":79,
    "gn:feature_class":"P",
    "gn:feature_code":"PPL",
    "gn:name":"Valli",
    "gn:population":246,
    "gn:timezone":"Europe/Rome",
    "iso:country":"IT",
    "wof:name":"Valli",
    "wof:placetype":"locality",
    "wof:population":246
},
  "geometry": {"coordinates":[12.42518,42.37376],"type":"Point"}
}