{
  "type": "Feature",
  "properties": {
    "gn:admin1_code":"3",
    "gn:admin2_code":"CS",
    "gn:admin3_code":"78013.0",
    "gn:asciiname":"Oliveto",
    "gn:country_code":"IT",
    "gn:dem":84,
    "gn:feature_class":"P",
    "gn:feature_code":"PPL",
    "gn:name":"Oliveto",
    "gn:population":16,
    "gn:timezone":"Europe/Rome",
    "iso:country":"IT",
    "name:ceb_x_preferred":[
        "Oliveto"
    ],
    "name:deu_x_preferred":[
        "Oliveto"
    ],
    "name:ita_x_preferred":[
        "Oliveto"
    ],
    "name:por_x_preferred":[
        "Oliveto"
    ],
    "name:rus_x_preferred":[
        "\u041e\u043b\u0438\u0432\u0435\u0442\u043e"
    ],
    "name:spa_x_preferred":[
        "Oliveto"
    ],
    "name:srp_x_preferred":[
        "Oliveto"
    ],
    "name:swe_x_preferred":[
        "Oliveto"
    ],
    "wof:name":"Oliveto",
    "wof:placetype":"locality",
    "wof:population":16
},
  "geometry": {"coordinates":[16.07953,39.15782],"type":"Point"}
}