{
  "type": "Feature",
  "properties": {
    "gn:admin1_code":"3",
    "gn:admin2_code":"CS",
    "gn:admin3_code":"78013.0",
    "gn:asciiname":"Oliveto",
    "gn:country_code":"IT",
    "gn:dem":84,
    "gn:feature_class":"P",
    "gn:feature_code":"PPL",
    "gn:name":"Oliveto",
    "gn:population":16,
    "gn:timezone":"Europe/Rome",
    "iso:country":"IT",
    "wof:name":"Oliveto",
    "wof:placetype":"locality",
    "wof:population":16
},
  "geometry": {"coordinates":[16.07953,39.15782],"type":"Point"}
}