{
  "type": "Feature",
  "properties": {
    "gn:admin1_code":"14.0",
    "gn:admin2_code":"SS",
    "gn:admin3_code":"90064.0",
    "gn:asciiname":"Fattoria la Crucca",
    "gn:cc2":"IT",
    "gn:country_code":"IT",
    "gn:dem":63,
    "gn:feature_class":"P",
    "gn:feature_code":"PPL",
    "gn:name":"Fattoria la Crucca",
    "gn:population":0,
    "gn:timezone":"Europe/Rome",
    "iso:country":"IT",
    "name:und_x_variant":[
        "La Crucca",
        "Torre sa Crucca"
    ],
    "wof:name":"Fattoria la Crucca",
    "wof:placetype":"locality"
},
  "geometry": {"coordinates":[8.42083,40.76278],"type":"Point"}
}