{
  "type": "Feature",
  "properties": {
    "gn:admin1_code":"16",
    "gn:admin2_code":"PT",
    "gn:admin3_code":"47002.0",
    "gn:asciiname":"Castelletto",
    "gn:country_code":"IT",
    "gn:dem":44,
    "gn:feature_class":"P",
    "gn:feature_code":"PPL",
    "gn:name":"Castelletto",
    "gn:population":236,
    "gn:timezone":"Europe/Rome",
    "iso:country":"IT",
    "name:ceb_x_preferred":[
        "Castelletto"
    ],
    "name:deu_x_preferred":[
        "Castelletto"
    ],
    "name:ita_x_preferred":[
        "Castelletto"
    ],
    "name:lat_x_preferred":[
        "Castellettum"
    ],
    "name:pms_x_preferred":[
        "Castl\u00e8t"
    ],
    "name:por_x_preferred":[
        "Castelletto"
    ],
    "name:rus_x_preferred":[
        "\u041a\u0430\u0441\u0442\u0435\u043b\u043b\u0435\u0442\u0442\u043e"
    ],
    "name:sco_x_preferred":[
        "Castelletto"
    ],
    "name:srp_x_preferred":[
        "Kasteleto"
    ],
    "name:swe_x_preferred":[
        "Castelletto"
    ],
    "wof:name":"Castelletto",
    "wof:placetype":"locality",
    "wof:population":236
},
  "geometry": {"coordinates":[10.98988,43.91007000000001],"type":"Point"}
}