{
  "type": "Feature",
  "properties": {
    "gn:admin1_code":"16",
    "gn:admin2_code":"PT",
    "gn:admin3_code":"47002.0",
    "gn:asciiname":"Castelletto",
    "gn:country_code":"IT",
    "gn:dem":44,
    "gn:feature_class":"P",
    "gn:feature_code":"PPL",
    "gn:name":"Castelletto",
    "gn:population":236,
    "gn:timezone":"Europe/Rome",
    "iso:country":"IT",
    "wof:name":"Castelletto",
    "wof:placetype":"locality",
    "wof:population":236
},
  "geometry": {"coordinates":[10.98988,43.91007000000001],"type":"Point"}
}