{
  "type": "Feature",
  "properties": {
    "gn:admin1_code":"17",
    "gn:admin2_code":"TN",
    "gn:admin3_code":"22193.0",
    "gn:asciiname":"Pergheri",
    "gn:country_code":"IT",
    "gn:dem":912,
    "gn:feature_class":"P",
    "gn:feature_code":"PPL",
    "gn:name":"Pergheri",
    "gn:population":50,
    "gn:timezone":"Europe/Rome",
    "iso:country":"IT",
    "wof:name":"Pergheri",
    "wof:placetype":"locality",
    "wof:population":50
},
  "geometry": {"coordinates":[11.15534,45.88188],"type":"Point"}
}