{
  "type": "Feature",
  "properties": {
    "gn:admin1_code":"8",
    "gn:admin2_code":"GE",
    "gn:admin3_code":"10037.0",
    "gn:asciiname":"Crova",
    "gn:country_code":"IT",
    "gn:dem":249,
    "gn:feature_class":"P",
    "gn:feature_code":"PPL",
    "gn:name":"Crova",
    "gn:population":51,
    "gn:timezone":"Europe/Rome",
    "iso:country":"IT",
    "name:ara_x_preferred":[
        "\u0643\u0631\u0648\u0641\u0627"
    ],
    "name:azb_x_preferred":[
        "\u06a9\u0631\u0648\u0648\u0627"
    ],
    "name:bel_x_preferred":[
        "\u041a\u0440\u043e\u0432\u0430"
    ],
    "name:bul_x_preferred":[
        "\u041a\u0440\u043e\u0432\u0430"
    ],
    "name:ceb_x_preferred":[
        "Crova"
    ],
    "name:ces_x_preferred":[
        "Crova"
    ],
    "name:deu_x_preferred":[
        "Crova"
    ],
    "name:ell_x_preferred":[
        "\u039a\u03c1\u03cc\u03b2\u03b1"
    ],
    "name:epo_x_preferred":[
        "Crova"
    ],
    "name:eus_x_preferred":[
        "Crova"
    ],
    "name:fas_x_preferred":[
        "\u06a9\u0631\u0648\u0648\u0627"
    ],
    "name:fra_x_preferred":[
        "Crova"
    ],
    "name:hun_x_preferred":[
        "Crova"
    ],
    "name:hye_x_preferred":[
        "\u053f\u0580\u0578\u057e\u0561"
    ],
    "name:ind_x_preferred":[
        "Crova"
    ],
    "name:ita_x_preferred":[
        "Crova"
    ],
    "name:jpn_x_preferred":[
        "\u30af\u30ed\u30fc\u30f4\u30a1"
    ],
    "name:kaz_x_preferred":[
        "\u041a\u0440\u043e\u0432\u0430"
    ],
    "name:lat_x_preferred":[
        "Crova"
    ],
    "name:lmo_x_preferred":[
        "Cr\u00f6va"
    ],
    "name:msa_x_preferred":[
        "Crova"
    ],
    "name:nap_x_preferred":[
        "Crova"
    ],
    "name:nld_x_preferred":[
        "Crova"
    ],
    "name:pms_x_preferred":[
        "Cr\u00f2va"
    ],
    "name:pol_x_preferred":[
        "Crova"
    ],
    "name:por_x_preferred":[
        "Crova"
    ],
    "name:ron_x_preferred":[
        "Crova"
    ],
    "name:rus_x_preferred":[
        "\u041a\u0440\u043e\u0432\u0430"
    ],
    "name:scn_x_preferred":[
        "Crova"
    ],
    "name:spa_x_preferred":[
        "Crova"
    ],
    "name:srp_x_preferred":[
        "\u041a\u0440\u043e\u0432\u0430"
    ],
    "name:swe_x_preferred":[
        "Crova"
    ],
    "name:tgl_x_preferred":[
        "Crova"
    ],
    "name:ukr_x_preferred":[
        "\u041a\u0440\u043e\u0432\u0430"
    ],
    "name:vie_x_preferred":[
        "Crova"
    ],
    "name:vol_x_preferred":[
        "Crova"
    ],
    "name:war_x_preferred":[
        "Crova"
    ],
    "wof:name":"Crova",
    "wof:placetype":"locality",
    "wof:population":51
},
  "geometry": {"coordinates":[9.48151,44.25222],"type":"Point"}
}