{
  "type": "Feature",
  "properties": {
    "gn:admin1_code":"8",
    "gn:admin2_code":"GE",
    "gn:admin3_code":"10037.0",
    "gn:asciiname":"Crova",
    "gn:country_code":"IT",
    "gn:dem":249,
    "gn:feature_class":"P",
    "gn:feature_code":"PPL",
    "gn:name":"Crova",
    "gn:population":51,
    "gn:timezone":"Europe/Rome",
    "iso:country":"IT",
    "wof:name":"Crova",
    "wof:placetype":"locality",
    "wof:population":51
},
  "geometry": {"coordinates":[9.48151,44.25222],"type":"Point"}
}