{
  "type": "Feature",
  "properties": {
    "gn:admin1_code":"16",
    "gn:admin2_code":"MS",
    "gn:admin3_code":"45016.0",
    "gn:asciiname":"La Piastra",
    "gn:country_code":"IT",
    "gn:dem":90,
    "gn:feature_class":"P",
    "gn:feature_code":"PPL",
    "gn:name":"La Piastra",
    "gn:population":12,
    "gn:timezone":"Europe/Rome",
    "iso:country":"IT",
    "wof:name":"La Piastra",
    "wof:placetype":"locality",
    "wof:population":12
},
  "geometry": {"coordinates":[9.96062,44.24567],"type":"Point"}
}