{
  "type": "Feature",
  "properties": {
    "gn:admin1_code":"13",
    "gn:admin2_code":"FG",
    "gn:admin3_code":"71013.0",
    "gn:asciiname":"Vallevona",
    "gn:country_code":"IT",
    "gn:dem":184,
    "gn:feature_class":"P",
    "gn:feature_code":"PPL",
    "gn:name":"Vallevona",
    "gn:population":11,
    "gn:timezone":"Europe/Rome",
    "iso:country":"IT",
    "wof:name":"Vallevona",
    "wof:placetype":"locality",
    "wof:population":11
},
  "geometry": {"coordinates":[15.05847,41.65131],"type":"Point"}
}