{
  "type": "Feature",
  "properties": {
    "gn:admin1_code":"9.0",
    "gn:admin2_code":"BG",
    "gn:admin3_code":"16177.0",
    "gn:asciiname":"Cascina Colombarotto",
    "gn:country_code":"IT",
    "gn:dem":105,
    "gn:feature_class":"P",
    "gn:feature_code":"PPL",
    "gn:name":"Cascina Colombarotto",
    "gn:population":24,
    "gn:timezone":"Europe/Rome",
    "iso:country":"IT",
    "wof:name":"Cascina Colombarotto",
    "wof:placetype":"locality",
    "wof:population":24
},
  "geometry": {"coordinates":[9.86954,45.47212],"type":"Point"}
}