{
  "type": "Feature",
  "properties": {
    "gn:admin1_code":"11",
    "gn:admin2_code":"CB",
    "gn:admin3_code":"70006.0",
    "gn:asciiname":"Colle Longo",
    "gn:country_code":"IT",
    "gn:dem":641,
    "gn:feature_class":"P",
    "gn:feature_code":"PPL",
    "gn:name":"Colle Longo",
    "gn:population":59,
    "gn:timezone":"Europe/Rome",
    "iso:country":"IT",
    "wof:name":"Colle Longo",
    "wof:placetype":"locality",
    "wof:population":59
},
  "geometry": {"coordinates":[14.6249,41.56659000000001],"type":"Point"}
}