{
  "type": "Feature",
  "properties": {
    "gn:admin1_code":"5.0",
    "gn:admin2_code":"BO",
    "gn:admin3_code":"37003.0",
    "gn:asciiname":"Boschi",
    "gn:country_code":"IT",
    "gn:dem":9,
    "gn:feature_class":"P",
    "gn:feature_code":"PPL",
    "gn:name":"Boschi",
    "gn:population":507,
    "gn:timezone":"Europe/Rome",
    "iso:country":"IT",
    "wof:name":"Boschi",
    "wof:placetype":"locality",
    "wof:population":507
},
  "geometry": {"coordinates":[11.55721,44.69162],"type":"Point"}
}