{
  "type": "Feature",
  "properties": {
    "gn:admin1_code":"10.0",
    "gn:admin2_code":"AP",
    "gn:admin3_code":"44001.0",
    "gn:asciiname":"Arli",
    "gn:country_code":"IT",
    "gn:dem":324,
    "gn:elevation":"295.0",
    "gn:feature_class":"P",
    "gn:feature_code":"PPL",
    "gn:name":"Arli",
    "gn:population":90,
    "gn:timezone":"Europe/Rome",
    "iso:country":"IT",
    "wof:name":"Arli",
    "wof:placetype":"locality",
    "wof:population":90
},
  "geometry": {"coordinates":[13.45175,42.79971],"type":"Point"}
}