{
  "type": "Feature",
  "properties": {
    "gn:admin1_code":"12",
    "gn:admin2_code":"TO",
    "gn:admin3_code":"1224.0",
    "gn:asciiname":"Bosco - Villaggio Bettussa",
    "gn:country_code":"IT",
    "gn:dem":888,
    "gn:feature_class":"P",
    "gn:feature_code":"PPL",
    "gn:name":"Bosco - Villaggio Bettussa",
    "gn:population":25,
    "gn:timezone":"Europe/Rome",
    "iso:country":"IT",
    "wof:name":"Bosco - Villaggio Bettussa",
    "wof:placetype":"locality",
    "wof:population":25
},
  "geometry": {"coordinates":[7.53952,45.49123],"type":"Point"}
}