{
  "type": "Feature",
  "properties": {
    "gn:admin1_code":"16.0",
    "gn:admin2_code":"PI",
    "gn:admin3_code":"50020.0",
    "gn:asciiname":"Fiorino",
    "gn:country_code":"IT",
    "gn:dem":9,
    "gn:elevation":"14.0",
    "gn:feature_class":"P",
    "gn:feature_code":"PPL",
    "gn:name":"Fiorino",
    "gn:population":503,
    "gn:timezone":"Europe/Rome",
    "iso:country":"IT",
    "wof:name":"Fiorino",
    "wof:placetype":"locality",
    "wof:population":503
},
  "geometry": {"coordinates":[10.53777,43.32247],"type":"Point"}
}