{
  "type": "Feature",
  "properties": {
    "gn:admin1_code":"20.0",
    "gn:admin2_code":"VI",
    "gn:admin3_code":"24012.0",
    "gn:asciiname":"San Michele",
    "gn:country_code":"IT",
    "gn:dem":143,
    "gn:feature_class":"P",
    "gn:feature_code":"PPL",
    "gn:name":"San Michele",
    "gn:population":531,
    "gn:timezone":"Europe/Rome",
    "iso:country":"IT",
    "name:ceb_x_preferred":[
        "San Michele"
    ],
    "name:deu_x_preferred":[
        "San Michele"
    ],
    "name:fra_x_preferred":[
        "San Michele"
    ],
    "name:ita_x_preferred":[
        "San Michele"
    ],
    "name:nap_x_preferred":[
        "San Michele"
    ],
    "name:nld_x_preferred":[
        "San Michele"
    ],
    "name:por_x_preferred":[
        "San Michele"
    ],
    "name:srp_x_preferred":[
        "\u0421\u0430\u043d \u041c\u0438\u043a\u0435\u043b\u0435"
    ],
    "name:swe_x_preferred":[
        "San Michele"
    ],
    "wof:name":"San Michele",
    "wof:placetype":"locality",
    "wof:population":531
},
  "geometry": {"coordinates":[11.69096,45.77722],"type":"Point"}
}