{
  "type": "Feature",
  "properties": {
    "gn:admin1_code":"20",
    "gn:admin2_code":"PD",
    "gn:admin3_code":"28063.0",
    "gn:asciiname":"Pieretto Pitture",
    "gn:country_code":"IT",
    "gn:dem":22,
    "gn:feature_class":"P",
    "gn:feature_code":"PPL",
    "gn:name":"Pieretto Pitture",
    "gn:population":24,
    "gn:timezone":"Europe/Rome",
    "iso:country":"IT",
    "wof:name":"Pieretto Pitture",
    "wof:placetype":"locality",
    "wof:population":24
},
  "geometry": {"coordinates":[11.78983,45.50784],"type":"Point"}
}