{
  "type": "Feature",
  "properties": {
    "gn:admin1_code":"12",
    "gn:admin2_code":"TO",
    "gn:admin3_code":"1156.0",
    "gn:asciiname":"Bauducchi",
    "gn:country_code":"IT",
    "gn:dem":225,
    "gn:feature_class":"P",
    "gn:feature_code":"PPL",
    "gn:name":"Bauducchi",
    "gn:population":303,
    "gn:timezone":"Europe/Rome",
    "iso:country":"IT",
    "wof:name":"Bauducchi",
    "wof:placetype":"locality",
    "wof:population":303
},
  "geometry": {"coordinates":[7.71332,44.96287],"type":"Point"}
}