{
  "type": "Feature",
  "properties": {
    "gn:admin1_code":"12.0",
    "gn:admin2_code":"TO",
    "gn:admin3_code":"1204.0",
    "gn:asciiname":"Tornini",
    "gn:country_code":"IT",
    "gn:dem":855,
    "gn:feature_class":"P",
    "gn:feature_code":"PPLL",
    "gn:name":"Tornini",
    "gn:population":4,
    "gn:timezone":"Europe/Rome",
    "iso:country":"IT",
    "wof:name":"Tornini",
    "wof:placetype":"locality",
    "wof:population":4
},
  "geometry": {"coordinates":[7.20051,44.90473],"type":"Point"}
}