{
  "type": "Feature",
  "properties": {
    "gn:admin1_code":"15",
    "gn:admin2_code":"CT",
    "gn:admin3_code":"87002.0",
    "gn:asciiname":"Gallinaro",
    "gn:country_code":"IT",
    "gn:dem":142,
    "gn:feature_class":"P",
    "gn:feature_code":"PPL",
    "gn:name":"Gallinaro",
    "gn:population":38,
    "gn:timezone":"Europe/Rome",
    "iso:country":"IT",
    "wof:name":"Gallinaro",
    "wof:placetype":"locality",
    "wof:population":38
},
  "geometry": {"coordinates":[15.12626,37.5544],"type":"Point"}
}