{
  "type": "Feature",
  "properties": {
    "gn:admin1_code":"15",
    "gn:admin2_code":"CT",
    "gn:admin3_code":"87002.0",
    "gn:asciiname":"Gallinaro",
    "gn:country_code":"IT",
    "gn:dem":142,
    "gn:feature_class":"P",
    "gn:feature_code":"PPL",
    "gn:name":"Gallinaro",
    "gn:population":38,
    "gn:timezone":"Europe/Rome",
    "iso:country":"IT",
    "name:azb_x_preferred":[
        "\u0642\u0627\u0644\u06cc\u0646\u0627\u0631\u0648"
    ],
    "name:bcl_x_preferred":[
        "Gallinaro"
    ],
    "name:bel_x_preferred":[
        "\u0413\u0430\u043b\u0456\u043d\u0430\u0440\u0430"
    ],
    "name:bul_x_preferred":[
        "\u0413\u0430\u043b\u0438\u043d\u0430\u0440\u043e"
    ],
    "name:ceb_x_preferred":[
        "Gallinaro"
    ],
    "name:cos_x_preferred":[
        "Gallinaro"
    ],
    "name:deu_x_preferred":[
        "Gallinaro"
    ],
    "name:epo_x_preferred":[
        "Gallinaro"
    ],
    "name:eus_x_preferred":[
        "Gallinaro"
    ],
    "name:fas_x_preferred":[
        "\u06af\u0627\u0644\u06cc\u0646\u0627\u0631\u0648"
    ],
    "name:fra_x_preferred":[
        "Gallinaro"
    ],
    "name:hun_x_preferred":[
        "Gallinaro"
    ],
    "name:hye_x_preferred":[
        "\u0533\u0561\u056c\u056b\u0576\u0561\u0580\u0578"
    ],
    "name:ina_x_preferred":[
        "Gallinaro"
    ],
    "name:ita_x_preferred":[
        "Gallinaro"
    ],
    "name:jpn_x_preferred":[
        "\u30ac\u30c3\u30ea\u30ca\u30fc\u30ed"
    ],
    "name:kaz_x_preferred":[
        "\u0413\u0430\u043b\u043b\u0438\u043d\u0430\u0440\u043e"
    ],
    "name:kor_x_preferred":[
        "\uac08\ub9ac\ub098\ub85c"
    ],
    "name:lat_x_preferred":[
        "Gallinarium"
    ],
    "name:lmo_x_preferred":[
        "Gallinaro"
    ],
    "name:msa_x_preferred":[
        "Gallinaro"
    ],
    "name:nap_x_preferred":[
        "Gallinaro"
    ],
    "name:nld_x_preferred":[
        "Gallinaro"
    ],
    "name:pms_x_preferred":[
        "Gallinaro"
    ],
    "name:pol_x_preferred":[
        "Gallinaro"
    ],
    "name:por_x_preferred":[
        "Gallinaro"
    ],
    "name:ron_x_preferred":[
        "Gallinaro"
    ],
    "name:rus_x_preferred":[
        "\u0413\u0430\u043b\u043b\u0438\u043d\u0430\u0440\u043e"
    ],
    "name:scn_x_preferred":[
        "Gaddinaru"
    ],
    "name:spa_x_preferred":[
        "Gallinaro"
    ],
    "name:srp_x_preferred":[
        "\u0413\u0430\u043b\u0438\u043d\u0430\u0440\u043e"
    ],
    "name:tur_x_preferred":[
        "Gallinaro"
    ],
    "name:ukr_x_preferred":[
        "\u0413\u0430\u043b\u043b\u0456\u043d\u0430\u0440\u043e"
    ],
    "name:uzb_x_preferred":[
        "Gallinaro"
    ],
    "name:vie_x_preferred":[
        "Gallinaro"
    ],
    "name:vol_x_preferred":[
        "Gallinaro"
    ],
    "name:war_x_preferred":[
        "Gallinaro"
    ],
    "name:zho_x_preferred":[
        "\u52a0\u5229\u7eb3\u7f57"
    ],
    "wof:name":"Gallinaro",
    "wof:placetype":"locality",
    "wof:population":38
},
  "geometry": {"coordinates":[15.12626,37.5544],"type":"Point"}
}