{
  "type": "Feature",
  "properties": {
    "gn:admin1_code":"12",
    "gn:admin2_code":"TO",
    "gn:admin3_code":"1111.0",
    "gn:asciiname":"Casenuove",
    "gn:country_code":"IT",
    "gn:dem":314,
    "gn:feature_class":"P",
    "gn:feature_code":"PPL",
    "gn:name":"Casenuove",
    "gn:population":42,
    "gn:timezone":"Europe/Rome",
    "iso:country":"IT",
    "wof:name":"Casenuove",
    "wof:placetype":"locality",
    "wof:population":42
},
  "geometry": {"coordinates":[7.37013,44.82461],"type":"Point"}
}