{
  "type": "Feature",
  "properties": {
    "gn:admin1_code":"20.0",
    "gn:admin2_code":"VR",
    "gn:admin3_code":"23061.0",
    "gn:asciiname":"Caselle",
    "gn:country_code":"IT",
    "gn:dem":17,
    "gn:feature_class":"P",
    "gn:feature_code":"PPL",
    "gn:name":"Caselle",
    "gn:population":624,
    "gn:timezone":"Europe/Rome",
    "iso:country":"IT",
    "wof:name":"Caselle",
    "wof:placetype":"locality",
    "wof:population":624
},
  "geometry": {"coordinates":[11.36268,45.27486],"type":"Point"}
}