{
  "type": "Feature",
  "properties": {
    "gn:admin1_code":"16",
    "gn:admin2_code":"AR",
    "gn:admin3_code":"51041.0",
    "gn:asciiname":"Tartiglia",
    "gn:country_code":"IT",
    "gn:dem":594,
    "gn:feature_class":"P",
    "gn:feature_code":"PPL",
    "gn:name":"Tartiglia",
    "gn:population":26,
    "gn:timezone":"Europe/Rome",
    "iso:country":"IT",
    "wof:name":"Tartiglia",
    "wof:placetype":"locality",
    "wof:population":26
},
  "geometry": {"coordinates":[11.68753,43.76972],"type":"Point"}
}