{
  "type": "Feature",
  "properties": {
    "gn:admin1_code":"20",
    "gn:admin2_code":"VR",
    "gn:admin3_code":"23012.0",
    "gn:asciiname":"Malpasso",
    "gn:country_code":"IT",
    "gn:dem":24,
    "gn:feature_class":"P",
    "gn:feature_code":"PPL",
    "gn:name":"Malpasso",
    "gn:population":38,
    "gn:timezone":"Europe/Rome",
    "iso:country":"IT",
    "wof:name":"Malpasso",
    "wof:placetype":"locality",
    "wof:population":38
},
  "geometry": {"coordinates":[11.09117,45.25671],"type":"Point"}
}