{
  "type": "Feature",
  "properties": {
    "gn:admin1_code":"9.0",
    "gn:admin2_code":"CR",
    "gn:admin3_code":"19090.0",
    "gn:asciiname":"San Zavedro",
    "gn:country_code":"IT",
    "gn:dem":25,
    "gn:feature_class":"P",
    "gn:feature_code":"PPL",
    "gn:name":"San Zavedro",
    "gn:population":0,
    "gn:timezone":"Europe/Rome",
    "iso:country":"IT",
    "wof:name":"San Zavedro",
    "wof:placetype":"locality"
},
  "geometry": {"coordinates":[10.36667,45.06667],"type":"Point"}
}