{
  "type": "Feature",
  "properties": {
    "gn:admin1_code":"13",
    "gn:admin2_code":"BA",
    "gn:admin3_code":"72017.0",
    "gn:asciiname":"Iuscafez",
    "gn:country_code":"IT",
    "gn:dem":290,
    "gn:feature_class":"P",
    "gn:feature_code":"PPL",
    "gn:name":"Iuscafez",
    "gn:population":59,
    "gn:timezone":"Europe/Rome",
    "iso:country":"IT",
    "wof:name":"Iuscafez",
    "wof:placetype":"locality",
    "wof:population":59
},
  "geometry": {"coordinates":[17.1576,40.89001],"type":"Point"}
}