{
  "type": "Feature",
  "properties": {
    "gn:admin1_code":"10.0",
    "gn:admin2_code":"PU",
    "gn:admin3_code":"41028.0",
    "gn:asciiname":"Passo Sant'Andrea",
    "gn:country_code":"IT",
    "gn:dem":122,
    "gn:feature_class":"P",
    "gn:feature_code":"PPL",
    "gn:name":"Passo Sant'Andrea",
    "gn:population":59,
    "gn:timezone":"Europe/Rome",
    "iso:country":"IT",
    "wof:name":"Passo Sant'Andrea",
    "wof:placetype":"locality",
    "wof:population":59
},
  "geometry": {"coordinates":[12.97539,43.64914],"type":"Point"}
}