{
  "type": "Feature",
  "properties": {
    "gn:admin1_code":"9.0",
    "gn:admin2_code":"BS",
    "gn:admin3_code":"17185.0",
    "gn:asciiname":"Olzano",
    "gn:country_code":"IT",
    "gn:dem":481,
    "gn:feature_class":"P",
    "gn:feature_code":"PPL",
    "gn:name":"Olzano",
    "gn:population":0,
    "gn:timezone":"Europe/Rome",
    "iso:country":"IT",
    "wof:name":"Olzano",
    "wof:placetype":"locality"
},
  "geometry": {"coordinates":[10.72077,45.7359],"type":"Point"}
}