{
  "type": "Feature",
  "properties": {
    "gn:admin1_code":"1",
    "gn:admin2_code":"CH",
    "gn:admin3_code":"69017.0",
    "gn:asciiname":"Caravotti",
    "gn:country_code":"IT",
    "gn:dem":227,
    "gn:feature_class":"P",
    "gn:feature_code":"PPL",
    "gn:name":"Caravotti",
    "gn:population":41,
    "gn:timezone":"Europe/Rome",
    "iso:country":"IT",
    "wof:name":"Caravotti",
    "wof:placetype":"locality",
    "wof:population":41
},
  "geometry": {"coordinates":[14.26911,42.13176],"type":"Point"}
}