{
  "type": "Feature",
  "properties": {
    "gn:gn_country":"IT",
    "gn:gn_fcode":"PPLA3",
    "gn:gn_pop":1488,
    "gn:population":1433,
    "iso:country":"IT",
    "name:arm_x_preferred":[
        "\u054a\u0578\u0576\u0578"
    ],
    "name:baq_x_preferred":[
        "Pogno"
    ],
    "name:bel_x_preferred":[
        "\u041f\u043e\u043d\u044c\u044f"
    ],
    "name:bul_x_preferred":[
        "\u041f\u043e\u043d\u044c\u043e"
    ],
    "name:cat_x_preferred":[
        "Pogno"
    ],
    "name:chi_x_preferred":[
        "\u6ce2\u5c3c\u5965"
    ],
    "name:deu_x_preferred":[
        "Pogno"
    ],
    "name:dut_x_preferred":[
        "Pogno"
    ],
    "name:eng_x_preferred":[
        "Pogno"
    ],
    "name:epo_x_preferred":[
        "Pogno"
    ],
    "name:fin_x_preferred":[
        "Pogno"
    ],
    "name:fra_x_preferred":[
        "Pogno"
    ],
    "name:fre_x_preferred":[
        "Pogno"
    ],
    "name:ger_x_preferred":[
        "Pogno"
    ],
    "name:hun_x_preferred":[
        "Pogno"
    ],
    "name:ind_x_preferred":[
        "Pogno"
    ],
    "name:ita_x_preferred":[
        "Pogno"
    ],
    "name:jpn_x_preferred":[
        "\u30dd\u30fc\u30cb\u30e7"
    ],
    "name:kaz_x_preferred":[
        "\u041f\u043e\u043d\u044c\u043e"
    ],
    "name:kor_x_preferred":[
        "\ud3ec\ub1e8"
    ],
    "name:lat_x_preferred":[
        "Podonium"
    ],
    "name:lmo_x_preferred":[
        "Pogn"
    ],
    "name:may_x_preferred":[
        "Pogno"
    ],
    "name:nan_x_preferred":[
        "Pogno"
    ],
    "name:nap_x_preferred":[
        "Pogno"
    ],
    "name:nld_x_preferred":[
        "Pogno"
    ],
    "name:oci_x_preferred":[
        "Pogno"
    ],
    "name:per_x_preferred":[
        "\u067e\u0648\u0646\u06cc\u0648"
    ],
    "name:pms_x_preferred":[
        "Pogn"
    ],
    "name:pol_x_preferred":[
        "Pogno"
    ],
    "name:por_x_preferred":[
        "Pogno"
    ],
    "name:rum_x_preferred":[
        "Pogno"
    ],
    "name:rus_x_preferred":[
        "\u041f\u043e\u043d\u044c\u043e"
    ],
    "name:scn_x_preferred":[
        "Pogno"
    ],
    "name:spa_x_preferred":[
        "Pogno"
    ],
    "name:srp_x_preferred":[
        "Pogno"
    ],
    "name:tgl_x_preferred":[
        "Pogno"
    ],
    "name:ukr_x_preferred":[
        "\u041f\u043e\u043d\u044c\u043e"
    ],
    "name:uzb_x_preferred":[
        "Pogno"
    ],
    "name:vie_x_preferred":[
        "Pogno"
    ],
    "name:vol_x_preferred":[
        "Pogno"
    ],
    "name:war_x_preferred":[
        "Pogno"
    ],
    "qs_pg:aaroncc":"IT",
    "qs_pg:gn_country":"IT",
    "qs_pg:gn_fcode":"PPLA3",
    "qs_pg:gn_pop":1488,
    "qs_pg:name":"Pisogno",
    "qs_pg:name_adm0":"Italia",
    "qs_pg:name_adm1":"Piemonte",
    "qs_pg:photos_9k":1,
    "qs_pg:photos_9r":1,
    "qs_pg:photos_all":3,
    "qs_pg:photos_sr":0,
    "qs_pg:pop_sr":3,
    "qs_pg:qs_pg_placetype":"locality",
    "qs_pg:qs_pg_placetype_gp":"Town",
    "qs_pg:woe_adm0":23424853,
    "woe:adm0_id":23424853,
    "woe:name_adm0":"Italia",
    "woe:name_adm1":"Piemonte",
    "woe:placetype":"Town",
    "wof:name":"Pisogno",
    "wof:placetype":"locality",
    "wof:population":1433
},
  "geometry": {"coordinates":[8.38462,45.75557],"type":"Point"}
}