{
  "type": "Feature",
  "properties": {
    "gn:admin1_code":"18",
    "gn:admin2_code":"TR",
    "gn:admin3_code":"55030.0",
    "gn:asciiname":"Poggio Spaccato",
    "gn:country_code":"IT",
    "gn:dem":707,
    "gn:feature_class":"P",
    "gn:feature_code":"PPL",
    "gn:name":"Poggio Spaccato",
    "gn:population":34,
    "gn:timezone":"Europe/Rome",
    "iso:country":"IT",
    "wof:name":"Poggio Spaccato",
    "wof:placetype":"locality",
    "wof:population":34
},
  "geometry": {"coordinates":[12.22395,42.8432],"type":"Point"}
}