{
  "type": "Feature",
  "properties": {
    "gn:admin1_code":"12",
    "gn:admin2_code":"BI",
    "gn:admin3_code":"96071.0",
    "gn:asciiname":"Pratacco",
    "gn:country_code":"IT",
    "gn:dem":266,
    "gn:feature_class":"P",
    "gn:feature_code":"PPL",
    "gn:name":"Pratacco",
    "gn:population":13,
    "gn:timezone":"Europe/Rome",
    "iso:country":"IT",
    "wof:name":"Pratacco",
    "wof:placetype":"locality",
    "wof:population":13
},
  "geometry": {"coordinates":[8.14324,45.55463],"type":"Point"}
}