{
  "type": "Feature",
  "properties": {
    "gn:admin1_code":"18",
    "gn:admin2_code":"PG",
    "gn:admin3_code":"54016.0",
    "gn:asciiname":"Coldagello",
    "gn:country_code":"IT",
    "gn:dem":602,
    "gn:feature_class":"P",
    "gn:feature_code":"PPL",
    "gn:name":"Coldagello",
    "gn:population":22,
    "gn:timezone":"Europe/Rome",
    "iso:country":"IT",
    "wof:name":"Coldagello",
    "wof:placetype":"locality",
    "wof:population":22
},
  "geometry": {"coordinates":[12.68719,43.38636],"type":"Point"}
}