{
  "type": "Feature",
  "properties": {
    "gn:admin1_code":"4",
    "gn:admin2_code":"CE",
    "gn:admin3_code":"61028.0",
    "gn:asciiname":"Rione Mobilia",
    "gn:country_code":"IT",
    "gn:dem":82,
    "gn:feature_class":"P",
    "gn:feature_code":"PPL",
    "gn:name":"Rione Mobilia",
    "gn:population":112,
    "gn:timezone":"Europe/Rome",
    "iso:country":"IT",
    "wof:name":"Rione Mobilia",
    "wof:placetype":"locality",
    "wof:population":112
},
  "geometry": {"coordinates":[14.44594,41.03118],"type":"Point"}
}