{
  "type": "Feature",
  "properties": {
    "gn:admin1_code":"8.0",
    "gn:admin2_code":"IM",
    "gn:admin3_code":"8019.0",
    "gn:asciiname":"Gazzelli",
    "gn:country_code":"IT",
    "gn:dem":263,
    "gn:elevation":"268.0",
    "gn:feature_class":"P",
    "gn:feature_code":"PPL",
    "gn:name":"Gazzelli",
    "gn:population":138,
    "gn:timezone":"Europe/Rome",
    "iso:country":"IT",
    "wof:name":"Gazzelli",
    "wof:placetype":"locality",
    "wof:population":138
},
  "geometry": {"coordinates":[7.99773,43.96137],"type":"Point"}
}