{
  "type": "Feature",
  "properties": {
    "gn:admin1_code":"4",
    "gn:admin2_code":"CE",
    "gn:admin3_code":"61048.0",
    "gn:asciiname":"Perrone",
    "gn:country_code":"IT",
    "gn:dem":36,
    "gn:feature_class":"P",
    "gn:feature_code":"PPL",
    "gn:name":"Perrone",
    "gn:population":190,
    "gn:timezone":"Europe/Rome",
    "iso:country":"IT",
    "wof:name":"Perrone",
    "wof:placetype":"locality",
    "wof:population":190
},
  "geometry": {"coordinates":[14.40214,41.00996],"type":"Point"}
}