{
  "type": "Feature",
  "properties": {
    "gn:admin1_code":"5.0",
    "gn:admin2_code":"PR",
    "gn:admin3_code":"34001.0",
    "gn:asciiname":"Pieve di Campi",
    "gn:country_code":"IT",
    "gn:dem":456,
    "gn:feature_class":"P",
    "gn:feature_code":"PPL",
    "gn:name":"Pieve di Campi",
    "gn:population":29,
    "gn:timezone":"Europe/Rome",
    "iso:country":"IT",
    "wof:name":"Pieve di Campi",
    "wof:placetype":"locality",
    "wof:population":29
},
  "geometry": {"coordinates":[9.69234,44.48039],"type":"Point"}
}