{
  "type": "Feature",
  "properties": {
    "iso:country":"IT",
    "wof:name":"Olivuzza",
    "wof:placetype":"neighbourhood"
},
  "geometry": {"coordinates":[13.34395745643246,38.12034640180462],"type":"Point"}
}