{
  "type": "Feature",
  "properties": {
    "gn:admin1_code":"7",
    "gn:admin2_code":"LT",
    "gn:admin3_code":"59032.0",
    "gn:asciiname":"Machiarella",
    "gn:country_code":"IT",
    "gn:dem":3,
    "gn:feature_class":"P",
    "gn:feature_code":"PPL",
    "gn:name":"Machiarella",
    "gn:population":104,
    "gn:timezone":"Europe/Rome",
    "iso:country":"IT",
    "wof:name":"Machiarella",
    "wof:placetype":"locality",
    "wof:population":104
},
  "geometry": {"coordinates":[13.15427,41.31314],"type":"Point"}
}