{
  "type": "Feature",
  "properties": {
    "gn:admin1_code":"17.0",
    "gn:admin2_code":"TN",
    "gn:admin3_code":"22228.0",
    "gn:asciiname":"Bono",
    "gn:country_code":"IT",
    "gn:dem":532,
    "gn:feature_class":"P",
    "gn:feature_code":"PPL",
    "gn:name":"Bono",
    "gn:population":0,
    "gn:timezone":"Europe/Rome",
    "iso:country":"IT",
    "wof:name":"Bono",
    "wof:placetype":"locality"
},
  "geometry": {"coordinates":[10.849,46.02224],"type":"Point"}
}