{
  "type": "Feature",
  "properties": {
    "gn:admin1_code":"9",
    "gn:admin2_code":"BG",
    "gn:admin3_code":"16120.0",
    "gn:asciiname":"Codera",
    "gn:country_code":"IT",
    "gn:dem":428,
    "gn:feature_class":"P",
    "gn:feature_code":"PPL",
    "gn:name":"Codera",
    "gn:population":44,
    "gn:timezone":"Europe/Rome",
    "iso:country":"IT",
    "wof:name":"Codera",
    "wof:placetype":"locality",
    "wof:population":44
},
  "geometry": {"coordinates":[9.88206,45.6538],"type":"Point"}
}