{
  "type": "Feature",
  "properties": {
    "gn:gn_country":"IT",
    "gn:gn_fcode":"PPL",
    "gn:gn_pop":0,
    "gn:population":150,
    "iso:country":"IT",
    "name:dut_x_preferred":[
        "Poggio Fidoni"
    ],
    "name:eng_x_preferred":[
        "Poggio Fidoni"
    ],
    "name:fre_x_preferred":[
        "Poggio Fidoni"
    ],
    "name:hun_x_preferred":[
        "Poggio Fidoni"
    ],
    "name:ita_x_preferred":[
        "Poggio Fidoni"
    ],
    "name:srp_x_preferred":[
        "Poggio Fidoni"
    ],
    "qs_pg:aaroncc":"IT",
    "qs_pg:gn_country":"IT",
    "qs_pg:gn_fcode":"PPL",
    "qs_pg:gn_pop":0,
    "qs_pg:name":"Poggio Fiorito",
    "qs_pg:name_adm0":"Italia",
    "qs_pg:name_adm1":"Lazio",
    "qs_pg:photos":277,
    "qs_pg:photos_1k":56,
    "qs_pg:photos_9k":1,
    "qs_pg:photos_9r":4,
    "qs_pg:photos_all":277,
    "qs_pg:photos_sr":5,
    "qs_pg:pop_sr":0,
    "qs_pg:qs_pg_placetype":"locality",
    "qs_pg:qs_pg_placetype_gp":"Town",
    "qs_pg:woe_adm0":23424853,
    "woe:adm0_id":23424853,
    "woe:name_adm0":"Italia",
    "woe:name_adm1":"Lazio",
    "woe:placetype":"Town",
    "wof:name":"Poggio Fiorito",
    "wof:placetype":"locality",
    "wof:population":150
},
  "geometry": {"coordinates":[12.78333,42.38333],"type":"Point"}
}