{
  "type": "Feature",
  "properties": {
    "gn:admin1_code":"20",
    "gn:admin2_code":"VE",
    "gn:admin3_code":"27019.0",
    "gn:asciiname":"Ca' Crema",
    "gn:country_code":"IT",
    "gn:dem":0,
    "gn:feature_class":"P",
    "gn:feature_code":"PPL",
    "gn:name":"Ca' Crema",
    "gn:population":57,
    "gn:timezone":"Europe/Rome",
    "iso:country":"IT",
    "wof:name":"Ca' Crema",
    "wof:placetype":"locality",
    "wof:population":57
},
  "geometry": {"coordinates":[12.59457,45.49181],"type":"Point"}
}