{
  "type": "Feature",
  "properties": {
    "gn:admin1_code":"20",
    "gn:admin2_code":"VI",
    "gn:admin3_code":"24054.0",
    "gn:asciiname":"Piazza Campana",
    "gn:country_code":"IT",
    "gn:dem":776,
    "gn:feature_class":"P",
    "gn:feature_code":"PPL",
    "gn:name":"Piazza Campana",
    "gn:population":283,
    "gn:timezone":"Europe/Rome",
    "iso:country":"IT",
    "wof:name":"Piazza Campana",
    "wof:placetype":"locality",
    "wof:population":283
},
  "geometry": {"coordinates":[11.56505,45.78781],"type":"Point"}
}