{
  "type": "Feature",
  "properties": {
    "gn:admin1_code":"13",
    "gn:admin2_code":"BR",
    "gn:admin3_code":"74012.0",
    "gn:asciiname":"Cavallerizza",
    "gn:country_code":"IT",
    "gn:dem":274,
    "gn:feature_class":"P",
    "gn:feature_code":"PPL",
    "gn:name":"Cavallerizza",
    "gn:population":38,
    "gn:timezone":"Europe/Rome",
    "iso:country":"IT",
    "wof:name":"Cavallerizza",
    "wof:placetype":"locality",
    "wof:population":38
},
  "geometry": {"coordinates":[17.47571,40.70769],"type":"Point"}
}