{
  "type": "Feature",
  "properties": {
    "gn:admin1_code":"2",
    "gn:admin2_code":"PZ",
    "gn:admin3_code":"76050.0",
    "gn:asciiname":"Cantarelle",
    "gn:country_code":"IT",
    "gn:dem":743,
    "gn:feature_class":"P",
    "gn:feature_code":"PPL",
    "gn:name":"Cantarelle",
    "gn:population":26,
    "gn:timezone":"Europe/Rome",
    "iso:country":"IT",
    "wof:name":"Cantarelle",
    "wof:placetype":"locality",
    "wof:population":26
},
  "geometry": {"coordinates":[15.87566,40.20103],"type":"Point"}
}