{
  "type": "Feature",
  "properties": {
    "gn:admin1_code":"8.0",
    "gn:admin2_code":"IM",
    "gn:admin3_code":"8056.0",
    "gn:asciiname":"Cavi",
    "gn:country_code":"IT",
    "gn:dem":46,
    "gn:feature_class":"P",
    "gn:feature_code":"PPLL",
    "gn:name":"Cavi",
    "gn:population":3,
    "gn:timezone":"Europe/Rome",
    "iso:country":"IT",
    "wof:name":"Cavi",
    "wof:placetype":"locality",
    "wof:population":3
},
  "geometry": {"coordinates":[7.90746,43.83917],"type":"Point"}
}