{
  "type": "Feature",
  "properties": {
    "gn:admin1_code":"15",
    "gn:admin2_code":"RG",
    "gn:admin3_code":"88006.0",
    "gn:asciiname":"Cappuccini I",
    "gn:country_code":"IT",
    "gn:dem":408,
    "gn:feature_class":"P",
    "gn:feature_code":"PPL",
    "gn:name":"Cappuccini I",
    "gn:population":108,
    "gn:timezone":"Europe/Rome",
    "iso:country":"IT",
    "wof:name":"Cappuccini I",
    "wof:placetype":"locality",
    "wof:population":108
},
  "geometry": {"coordinates":[14.82199,36.84125],"type":"Point"}
}