{
  "type": "Feature",
  "properties": {
    "gn:admin1_code":"17",
    "gn:admin2_code":"BZ",
    "gn:admin3_code":"21047.0",
    "gn:asciiname":"Les Ciases",
    "gn:country_code":"IT",
    "gn:dem":1532,
    "gn:feature_class":"P",
    "gn:feature_code":"PPL",
    "gn:name":"Les Ciases",
    "gn:population":11,
    "gn:timezone":"Europe/Rome",
    "iso:country":"IT",
    "wof:name":"Les Ciases",
    "wof:placetype":"locality",
    "wof:population":11
},
  "geometry": {"coordinates":[11.94409,46.72149],"type":"Point"}
}