{
  "type": "Feature",
  "properties": {
    "gn:admin1_code":"1.0",
    "gn:admin2_code":"AQ",
    "gn:admin3_code":"66013.0",
    "gn:asciiname":"San Giovanni",
    "gn:country_code":"IT",
    "gn:dem":760,
    "gn:elevation":"760.0",
    "gn:feature_class":"P",
    "gn:feature_code":"PPL",
    "gn:name":"San Giovanni",
    "gn:population":401,
    "gn:timezone":"Europe/Rome",
    "iso:country":"IT",
    "wof:name":"San Giovanni",
    "wof:placetype":"locality",
    "wof:population":401
},
  "geometry": {"coordinates":[13.25844,42.46423],"type":"Point"}
}