{
  "type": "Feature",
  "properties": {
    "gn:admin1_code":"7",
    "gn:admin2_code":"LT",
    "gn:admin3_code":"59012.0",
    "gn:asciiname":"Pantano",
    "gn:country_code":"IT",
    "gn:dem":347,
    "gn:feature_class":"P",
    "gn:feature_code":"PPL",
    "gn:name":"Pantano",
    "gn:population":26,
    "gn:timezone":"Europe/Rome",
    "iso:country":"IT",
    "wof:name":"Pantano",
    "wof:placetype":"locality",
    "wof:population":26
},
  "geometry": {"coordinates":[13.47191,41.40762],"type":"Point"}
}