{
  "type": "Feature",
  "properties": {
    "gn:admin1_code":"1",
    "gn:admin2_code":"CH",
    "gn:admin3_code":"69090.0",
    "gn:asciiname":"Colle Cavalieri",
    "gn:country_code":"IT",
    "gn:dem":106,
    "gn:feature_class":"P",
    "gn:feature_code":"PPL",
    "gn:name":"Colle Cavalieri",
    "gn:population":227,
    "gn:timezone":"Europe/Rome",
    "iso:country":"IT",
    "wof:name":"Colle Cavalieri",
    "wof:placetype":"locality",
    "wof:population":227
},
  "geometry": {"coordinates":[14.33485,42.36404],"type":"Point"}
}