{
  "type": "Feature",
  "properties": {
    "gn:admin1_code":"9",
    "gn:admin2_code":"BG",
    "gn:admin3_code":"16087.0",
    "gn:asciiname":"Cascina Cavallina",
    "gn:country_code":"IT",
    "gn:dem":121,
    "gn:feature_class":"P",
    "gn:feature_code":"PPL",
    "gn:name":"Cascina Cavallina",
    "gn:population":37,
    "gn:timezone":"Europe/Rome",
    "iso:country":"IT",
    "wof:name":"Cascina Cavallina",
    "wof:placetype":"locality",
    "wof:population":37
},
  "geometry": {"coordinates":[9.79816,45.51058],"type":"Point"}
}