{
  "type": "Feature",
  "properties": {
    "gn:admin1_code":"4",
    "gn:admin2_code":"AV",
    "gn:admin3_code":"64005.0",
    "gn:asciiname":"Santa Maria A Tuoro",
    "gn:country_code":"IT",
    "gn:dem":613,
    "gn:feature_class":"P",
    "gn:feature_code":"PPL",
    "gn:name":"Santa Maria A Tuoro",
    "gn:population":17,
    "gn:timezone":"Europe/Rome",
    "iso:country":"IT",
    "wof:name":"Santa Maria A Tuoro",
    "wof:placetype":"locality",
    "wof:population":17
},
  "geometry": {"coordinates":[15.06928,41.15556],"type":"Point"}
}