{
  "type": "Feature",
  "properties": {
    "gn:admin1_code":"20.0",
    "gn:admin2_code":"VI",
    "gn:admin3_code":"24048.0",
    "gn:asciiname":"Ceresara",
    "gn:country_code":"IT",
    "gn:dem":82,
    "gn:feature_class":"P",
    "gn:feature_code":"PPL",
    "gn:name":"Ceresara",
    "gn:population":16,
    "gn:timezone":"Europe/Rome",
    "iso:country":"IT",
    "wof:name":"Ceresara",
    "wof:placetype":"locality",
    "wof:population":16
},
  "geometry": {"coordinates":[11.46407,45.64574],"type":"Point"}
}