{
  "type": "Feature",
  "properties": {
    "gn:admin1_code":"20.0",
    "gn:admin2_code":"VI",
    "gn:admin3_code":"24048.0",
    "gn:asciiname":"Ceresara",
    "gn:country_code":"IT",
    "gn:dem":82,
    "gn:feature_class":"P",
    "gn:feature_code":"PPL",
    "gn:name":"Ceresara",
    "gn:population":16,
    "gn:timezone":"Europe/Rome",
    "iso:country":"IT",
    "name:azb_x_preferred":[
        "\u0686\u0631\u0647\u200c\u0633\u0627\u0631\u0627"
    ],
    "name:bul_x_preferred":[
        "\u0427\u0435\u0440\u0435\u0437\u0430\u0440\u0430"
    ],
    "name:cat_x_preferred":[
        "Ceresara"
    ],
    "name:ceb_x_preferred":[
        "Ceresara"
    ],
    "name:deu_x_preferred":[
        "Ceresara"
    ],
    "name:eml_x_preferred":[
        "Sarez\u00e9re"
    ],
    "name:epo_x_preferred":[
        "Ceresara"
    ],
    "name:eus_x_preferred":[
        "Ceresara"
    ],
    "name:fas_x_preferred":[
        "\u0686\u0631\u0647\u200c\u0633\u0627\u0631\u0627"
    ],
    "name:fra_x_preferred":[
        "Ceresara"
    ],
    "name:hun_x_preferred":[
        "Ceresara"
    ],
    "name:hye_x_preferred":[
        "\u0549\u0565\u0580\u0565\u0566\u0561\u0580\u0561"
    ],
    "name:ind_x_preferred":[
        "Ceresara"
    ],
    "name:ita_x_preferred":[
        "Ceresara"
    ],
    "name:jpn_x_preferred":[
        "\u30c1\u30a7\u30ec\u30b6\u30fc\u30e9"
    ],
    "name:kaz_x_preferred":[
        "\u0427\u0435\u0440\u0435\u0437\u0430\u0440\u0430"
    ],
    "name:lat_x_preferred":[
        "Cerasaria"
    ],
    "name:lmo_x_preferred":[
        "Sarez\u00e9re"
    ],
    "name:msa_x_preferred":[
        "Ceresara"
    ],
    "name:nap_x_preferred":[
        "Ceresara"
    ],
    "name:nld_x_preferred":[
        "Ceresara"
    ],
    "name:pms_x_preferred":[
        "Ceresara"
    ],
    "name:pol_x_preferred":[
        "Ceresara"
    ],
    "name:por_x_preferred":[
        "Ceresara"
    ],
    "name:ron_x_preferred":[
        "Ceresara"
    ],
    "name:rus_x_preferred":[
        "\u0427\u0435\u0440\u0435\u0437\u0430\u0440\u0430"
    ],
    "name:scn_x_preferred":[
        "Ceresara"
    ],
    "name:spa_x_preferred":[
        "Ceresara"
    ],
    "name:srp_x_preferred":[
        "\u0427\u0435\u0440\u0435\u0437\u0430\u0440\u0430"
    ],
    "name:tgl_x_preferred":[
        "Ceresara"
    ],
    "name:ukr_x_preferred":[
        "\u0427\u0435\u0440\u0435\u0437\u0430\u0440\u0430"
    ],
    "name:uzb_x_preferred":[
        "Ceresara"
    ],
    "name:vec_x_preferred":[
        "Seresara"
    ],
    "name:vie_x_preferred":[
        "Ceresara"
    ],
    "name:vol_x_preferred":[
        "Ceresara"
    ],
    "name:war_x_preferred":[
        "Ceresara"
    ],
    "name:zho_x_preferred":[
        "\u5207\u96f7\u8428\u62c9"
    ],
    "wof:name":"Ceresara",
    "wof:placetype":"locality",
    "wof:population":16
},
  "geometry": {"coordinates":[11.46407,45.64574],"type":"Point"}
}