{
  "type": "Feature",
  "properties": {
    "gn:admin1_code":"12",
    "gn:admin2_code":"CN",
    "gn:admin3_code":"4199.0",
    "gn:asciiname":"Torelli",
    "gn:country_code":"IT",
    "gn:dem":707,
    "gn:feature_class":"P",
    "gn:feature_code":"PPL",
    "gn:name":"Torelli",
    "gn:population":15,
    "gn:timezone":"Europe/Rome",
    "iso:country":"IT",
    "wof:name":"Torelli",
    "wof:placetype":"locality",
    "wof:population":15
},
  "geometry": {"coordinates":[8.11709,44.40096],"type":"Point"}
}