{
  "type": "Feature",
  "properties": {
    "gn:admin1_code":"20.0",
    "gn:admin2_code":"VI",
    "gn:admin3_code":"24009.0",
    "gn:asciiname":"Malga Fossetta",
    "gn:country_code":"IT",
    "gn:dem":1632,
    "gn:feature_class":"P",
    "gn:feature_code":"PPL",
    "gn:name":"Malga Fossetta",
    "gn:population":0,
    "gn:timezone":"Europe/Rome",
    "iso:country":"IT",
    "wof:name":"Malga Fossetta",
    "wof:placetype":"locality"
},
  "geometry": {"coordinates":[11.55,45.98333],"type":"Point"}
}