{
  "type": "Feature",
  "properties": {
    "gn:admin1_code":"12.0",
    "gn:admin2_code":"NO",
    "gn:admin3_code":"3077.0",
    "gn:asciiname":"Case sparse di Monticello",
    "gn:country_code":"IT",
    "gn:dem":126,
    "gn:feature_class":"P",
    "gn:feature_code":"PPL",
    "gn:name":"Case sparse di Monticello",
    "gn:population":35,
    "gn:timezone":"Europe/Rome",
    "iso:country":"IT",
    "wof:name":"Case sparse di Monticello",
    "wof:placetype":"locality",
    "wof:population":35
},
  "geometry": {"coordinates":[8.59393,45.37133],"type":"Point"}
}