{
  "type": "Feature",
  "properties": {
    "gn:admin1_code":"11",
    "gn:admin2_code":"IS",
    "gn:admin3_code":"94022.0",
    "gn:asciiname":"Sagrestano",
    "gn:country_code":"IT",
    "gn:dem":775,
    "gn:feature_class":"P",
    "gn:feature_code":"PPL",
    "gn:name":"Sagrestano",
    "gn:population":26,
    "gn:timezone":"Europe/Rome",
    "iso:country":"IT",
    "wof:name":"Sagrestano",
    "wof:placetype":"locality",
    "wof:population":26
},
  "geometry": {"coordinates":[14.45816,41.60677],"type":"Point"}
}