{
  "type": "Feature",
  "properties": {
    "gn:admin1_code":"5",
    "gn:admin2_code":"RN",
    "gn:admin3_code":"99009.0",
    "gn:asciiname":"Ca' Baldo",
    "gn:country_code":"IT",
    "gn:dem":104,
    "gn:feature_class":"P",
    "gn:feature_code":"PPL",
    "gn:name":"Ca' Baldo",
    "gn:population":19,
    "gn:timezone":"Europe/Rome",
    "iso:country":"IT",
    "wof:name":"Ca' Baldo",
    "wof:placetype":"locality",
    "wof:population":19
},
  "geometry": {"coordinates":[12.72363,43.87491],"type":"Point"}
}