{
  "type": "Feature",
  "properties": {
    "gn:admin1_code":"7",
    "gn:admin2_code":"RM",
    "gn:admin3_code":"58029.0",
    "gn:asciiname":"Fontanile del Cecio",
    "gn:country_code":"IT",
    "gn:dem":85,
    "gn:feature_class":"P",
    "gn:feature_code":"PPL",
    "gn:name":"Fontanile del Cecio",
    "gn:population":54,
    "gn:timezone":"Europe/Rome",
    "iso:country":"IT",
    "wof:name":"Fontanile del Cecio",
    "wof:placetype":"locality",
    "wof:population":54
},
  "geometry": {"coordinates":[12.17397,41.96123],"type":"Point"}
}