{
  "type": "Feature",
  "properties": {
    "gn:admin1_code":"16.0",
    "gn:admin2_code":"AR",
    "gn:admin3_code":"51039.0",
    "gn:asciiname":"Cicogna",
    "gn:country_code":"IT",
    "gn:dem":253,
    "gn:elevation":"254.0",
    "gn:feature_class":"P",
    "gn:feature_code":"PPL",
    "gn:name":"Cicogna",
    "gn:population":327,
    "gn:timezone":"Europe/Rome",
    "iso:country":"IT",
    "wof:name":"Cicogna",
    "wof:placetype":"locality",
    "wof:population":327
},
  "geometry": {"coordinates":[11.63896,43.54688],"type":"Point"}
}