{
  "type": "Feature",
  "properties": {
    "gn:admin1_code":"1.0",
    "gn:admin2_code":"CH",
    "gn:admin3_code":"69027.0",
    "gn:asciiname":"Villa Mascitti IV",
    "gn:country_code":"IT",
    "gn:dem":220,
    "gn:feature_class":"P",
    "gn:feature_code":"PPL",
    "gn:name":"Villa Mascitti IV",
    "gn:population":49,
    "gn:timezone":"Europe/Rome",
    "iso:country":"IT",
    "wof:name":"Villa Mascitti IV",
    "wof:placetype":"locality",
    "wof:population":49
},
  "geometry": {"coordinates":[14.34153,42.29118],"type":"Point"}
}