{
  "type": "Feature",
  "properties": {
    "gn:admin1_code":"3",
    "gn:admin2_code":"RC",
    "gn:admin3_code":"80029.0",
    "gn:asciiname":"Mangani",
    "gn:country_code":"IT",
    "gn:dem":284,
    "gn:feature_class":"P",
    "gn:feature_code":"PPL",
    "gn:name":"Mangani",
    "gn:population":55,
    "gn:timezone":"Europe/Rome",
    "iso:country":"IT",
    "name:fra_x_preferred":[
        "Langue grand-singe"
    ],
    "wof:name":"Mangani",
    "wof:placetype":"locality",
    "wof:population":55
},
  "geometry": {"coordinates":[15.87349,37.99967],"type":"Point"}
}