{
  "type": "Feature",
  "properties": {
    "gn:admin1_code":"14.0",
    "gn:admin2_code":"SU",
    "gn:admin3_code":"111066.0",
    "gn:asciiname":"Tuerra II",
    "gn:country_code":"IT",
    "gn:dem":16,
    "gn:feature_class":"P",
    "gn:feature_code":"PPL",
    "gn:name":"Tuerra II",
    "gn:population":15,
    "gn:timezone":"Europe/Rome",
    "iso:country":"IT",
    "wof:name":"Tuerra II",
    "wof:placetype":"locality",
    "wof:population":15
},
  "geometry": {"coordinates":[9.52942,39.33695],"type":"Point"}
}