{
  "type": "Feature",
  "properties": {
    "gn:admin1_code":"16",
    "gn:admin2_code":"AR",
    "gn:admin3_code":"51006.0",
    "gn:asciiname":"Il Pino",
    "gn:country_code":"IT",
    "gn:dem":287,
    "gn:feature_class":"P",
    "gn:feature_code":"PPL",
    "gn:name":"Il Pino",
    "gn:population":294,
    "gn:timezone":"Europe/Rome",
    "iso:country":"IT",
    "wof:name":"Il Pino",
    "wof:placetype":"locality",
    "wof:population":294
},
  "geometry": {"coordinates":[11.84732,43.56224],"type":"Point"}
}