{
  "type": "Feature",
  "properties": {
    "gn:admin1_code":"12",
    "gn:admin2_code":"TO",
    "gn:admin3_code":"1216.0",
    "gn:asciiname":"Borgata Bel Boschetto",
    "gn:country_code":"IT",
    "gn:dem":456,
    "gn:feature_class":"P",
    "gn:feature_code":"PPL",
    "gn:name":"Borgata Bel Boschetto",
    "gn:population":18,
    "gn:timezone":"Europe/Rome",
    "iso:country":"IT",
    "wof:name":"Borgata Bel Boschetto",
    "wof:placetype":"locality",
    "wof:population":18
},
  "geometry": {"coordinates":[7.61092,45.34212],"type":"Point"}
}