{
  "type": "Feature",
  "properties": {
    "gn:admin1_code":"9",
    "gn:admin2_code":"PV",
    "gn:admin3_code":"18005.0",
    "gn:asciiname":"Porticone",
    "gn:country_code":"IT",
    "gn:dem":57,
    "gn:feature_class":"P",
    "gn:feature_code":"PPL",
    "gn:name":"Porticone",
    "gn:population":15,
    "gn:timezone":"Europe/Rome",
    "iso:country":"IT",
    "wof:name":"Porticone",
    "wof:placetype":"locality",
    "wof:population":15
},
  "geometry": {"coordinates":[9.33735,45.09817],"type":"Point"}
}