{
  "type": "Feature",
  "properties": {
    "gn:admin1_code":"18",
    "gn:admin2_code":"TR",
    "gn:admin3_code":"55031.0",
    "gn:asciiname":"San Gregorio",
    "gn:country_code":"IT",
    "gn:dem":310,
    "gn:feature_class":"P",
    "gn:feature_code":"PPL",
    "gn:name":"San Gregorio",
    "gn:population":25,
    "gn:timezone":"Europe/Rome",
    "iso:country":"IT",
    "wof:name":"San Gregorio",
    "wof:placetype":"locality",
    "wof:population":25
},
  "geometry": {"coordinates":[12.64731,42.49486],"type":"Point"}
}