{
  "type": "Feature",
  "properties": {
    "gn:admin1_code":"9",
    "gn:admin2_code":"BS",
    "gn:admin3_code":"17043.0",
    "gn:asciiname":"Sant'Eufemino",
    "gn:country_code":"IT",
    "gn:dem":135,
    "gn:feature_class":"P",
    "gn:feature_code":"PPL",
    "gn:name":"Sant'Eufemino",
    "gn:population":23,
    "gn:timezone":"Europe/Rome",
    "iso:country":"IT",
    "wof:name":"Sant'Eufemino",
    "wof:placetype":"locality",
    "wof:population":23
},
  "geometry": {"coordinates":[10.32691,45.47852],"type":"Point"}
}