{
  "type": "Feature",
  "properties": {
    "gn:admin1_code":"12",
    "gn:admin2_code":"CN",
    "gn:admin3_code":"4189.0",
    "gn:asciiname":"Lime",
    "gn:country_code":"IT",
    "gn:dem":398,
    "gn:feature_class":"P",
    "gn:feature_code":"PPL",
    "gn:name":"Lime",
    "gn:population":61,
    "gn:timezone":"Europe/Rome",
    "iso:country":"IT",
    "wof:name":"Lime",
    "wof:placetype":"locality",
    "wof:population":61
},
  "geometry": {"coordinates":[7.76467,44.45081],"type":"Point"}
}