{
  "type": "Feature",
  "properties": {
    "gn:admin1_code":"12",
    "gn:admin2_code":"CN",
    "gn:admin3_code":"4189.0",
    "gn:asciiname":"Lime",
    "gn:country_code":"IT",
    "gn:dem":398,
    "gn:feature_class":"P",
    "gn:feature_code":"PPL",
    "gn:name":"Lime",
    "gn:population":61,
    "gn:timezone":"Europe/Rome",
    "iso:country":"IT",
    "name:asm_x_preferred":[
        "\u0995\u09be\u099c\u09bf\u09a8\u09c7\u09ae\u09c1"
    ],
    "name:ceb_x_preferred":[
        "Lime"
    ],
    "name:deu_x_preferred":[
        "Lime"
    ],
    "name:fra_x_preferred":[
        "Lime"
    ],
    "name:heb_x_preferred":[
        "\u05dc\u05d9\u05d9\u05dd"
    ],
    "name:hun_x_preferred":[
        "M\u00e9szk\u0151"
    ],
    "name:ita_x_preferred":[
        "Lime"
    ],
    "name:jpn_x_preferred":[
        "\u30e9\u30a4\u30e0"
    ],
    "name:kor_x_preferred":[
        "\ub77c\uc784"
    ],
    "name:nld_x_preferred":[
        "Lime"
    ],
    "name:pnb_x_preferred":[
        "\u0644\u0627\u0626\u0645"
    ],
    "name:som_x_preferred":[
        "Liin qarboosh"
    ],
    "name:spa_x_preferred":[
        "Lime"
    ],
    "name:swe_x_preferred":[
        "Lime"
    ],
    "name:tgl_x_preferred":[
        "Lime"
    ],
    "wof:name":"Lime",
    "wof:placetype":"locality",
    "wof:population":61
},
  "geometry": {"coordinates":[7.76467,44.45081],"type":"Point"}
}