{
  "type": "Feature",
  "properties": {
    "gn:admin1_code":"15",
    "gn:admin2_code":"TP",
    "gn:admin3_code":"81002.0",
    "gn:asciiname":"Case Pollina",
    "gn:country_code":"IT",
    "gn:dem":220,
    "gn:feature_class":"P",
    "gn:feature_code":"PPL",
    "gn:name":"Case Pollina",
    "gn:population":22,
    "gn:timezone":"Europe/Rome",
    "iso:country":"IT",
    "wof:name":"Case Pollina",
    "wof:placetype":"locality",
    "wof:population":22
},
  "geometry": {"coordinates":[12.7284,38.00811],"type":"Point"}
}