{
  "type": "Feature",
  "properties": {
    "gn:admin1_code":"20",
    "gn:admin2_code":"TV",
    "gn:admin3_code":"26086.0",
    "gn:asciiname":"Crociera",
    "gn:country_code":"IT",
    "gn:dem":13,
    "gn:feature_class":"P",
    "gn:feature_code":"PPL",
    "gn:name":"Crociera",
    "gn:population":205,
    "gn:timezone":"Europe/Rome",
    "iso:country":"IT",
    "wof:name":"Crociera",
    "wof:placetype":"locality",
    "wof:population":205
},
  "geometry": {"coordinates":[12.1894,45.62343],"type":"Point"}
}