{
  "type": "Feature",
  "properties": {
    "gn:admin1_code":"6",
    "gn:admin2_code":"UD",
    "gn:admin3_code":"30108.0",
    "gn:asciiname":"Iellina",
    "gn:country_code":"IT",
    "gn:dem":615,
    "gn:feature_class":"P",
    "gn:feature_code":"PPL",
    "gn:name":"Iellina",
    "gn:population":15,
    "gn:timezone":"Europe/Rome",
    "iso:country":"IT",
    "wof:name":"Iellina",
    "wof:placetype":"locality",
    "wof:population":15
},
  "geometry": {"coordinates":[13.55052,46.17926],"type":"Point"}
}