{
  "type": "Feature",
  "properties": {
    "gn:admin1_code":"20",
    "gn:admin2_code":"TV",
    "gn:admin3_code":"26095.0",
    "gn:asciiname":"Molino",
    "gn:country_code":"IT",
    "gn:dem":20,
    "gn:feature_class":"P",
    "gn:feature_code":"PPL",
    "gn:name":"Molino",
    "gn:population":19,
    "gn:timezone":"Europe/Rome",
    "iso:country":"IT",
    "wof:name":"Molino",
    "wof:placetype":"locality",
    "wof:population":19
},
  "geometry": {"coordinates":[12.11528,45.62561],"type":"Point"}
}