{
  "type": "Feature",
  "properties": {
    "gn:admin1_code":"6.0",
    "gn:admin2_code":"UD",
    "gn:admin3_code":"30100.0",
    "gn:asciiname":"Nogaro",
    "gn:cc2":"IT",
    "gn:country_code":"IT",
    "gn:dem":2,
    "gn:feature_class":"P",
    "gn:feature_code":"PPL",
    "gn:name":"Nogaro",
    "gn:population":0,
    "gn:timezone":"Europe/Rome",
    "iso:country":"IT",
    "name:arg_x_preferred":[
        "Nogar\u00f2"
    ],
    "name:bug_x_preferred":[
        "Nogaro"
    ],
    "name:cat_x_preferred":[
        "Nogar\u00f2u"
    ],
    "name:ceb_x_preferred":[
        "Nogaro"
    ],
    "name:deu_x_preferred":[
        "Nogaro"
    ],
    "name:eus_x_preferred":[
        "Nogaro"
    ],
    "name:fra_x_preferred":[
        "Nogaro"
    ],
    "name:hun_x_preferred":[
        "Nogaro"
    ],
    "name:ita_x_preferred":[
        "Nogaro"
    ],
    "name:jpn_x_preferred":[
        "\u30ce\u30ac\u30ed"
    ],
    "name:lat_x_preferred":[
        "Nogaro"
    ],
    "name:mlg_x_preferred":[
        "Nogaro"
    ],
    "name:msa_x_preferred":[
        "Nogaro"
    ],
    "name:nld_x_preferred":[
        "Nogaro"
    ],
    "name:oci_x_preferred":[
        "Nogar\u00f2u"
    ],
    "name:pms_x_preferred":[
        "Nogaro"
    ],
    "name:pol_x_preferred":[
        "Nogaro"
    ],
    "name:por_x_preferred":[
        "Nogaro"
    ],
    "name:ron_x_preferred":[
        "Nogaro"
    ],
    "name:rus_x_preferred":[
        "\u041d\u043e\u0433\u0430\u0440\u043e"
    ],
    "name:slk_x_preferred":[
        "Nogaro"
    ],
    "name:slv_x_preferred":[
        "Nogaro"
    ],
    "name:spa_x_preferred":[
        "Nogaro"
    ],
    "name:swe_x_preferred":[
        "Nogaro"
    ],
    "name:ukr_x_preferred":[
        "\u041d\u043e\u0433\u0430\u0440\u043e"
    ],
    "name:und_x_variant":[
        "Porto Nogaro",
        "Nogaro"
    ],
    "name:vie_x_preferred":[
        "Nogaro"
    ],
    "name:vol_x_preferred":[
        "Nogaro"
    ],
    "name:war_x_preferred":[
        "Nogaro"
    ],
    "name:zho_x_preferred":[
        "\u8bfa\u52a0\u7f57"
    ],
    "wof:name":"Nogaro",
    "wof:placetype":"locality"
},
  "geometry": {"coordinates":[13.21722,45.82],"type":"Point"}
}