{
  "type": "Feature",
  "properties": {
    "gn:admin1_code":"6.0",
    "gn:admin2_code":"UD",
    "gn:admin3_code":"30100.0",
    "gn:asciiname":"Nogaro",
    "gn:cc2":"IT",
    "gn:country_code":"IT",
    "gn:dem":2,
    "gn:feature_class":"P",
    "gn:feature_code":"PPL",
    "gn:name":"Nogaro",
    "gn:population":0,
    "gn:timezone":"Europe/Rome",
    "iso:country":"IT",
    "name:und_x_variant":[
        "Porto Nogaro",
        "Nogaro"
    ],
    "wof:name":"Nogaro",
    "wof:placetype":"locality"
},
  "geometry": {"coordinates":[13.21722,45.82],"type":"Point"}
}