{
  "type": "Feature",
  "properties": {
    "gn:admin1_code":"8.0",
    "gn:admin2_code":"SP",
    "gn:admin3_code":"11018.0",
    "gn:asciiname":"Torza",
    "gn:country_code":"IT",
    "gn:dem":384,
    "gn:elevation":"382.0",
    "gn:feature_class":"P",
    "gn:feature_code":"PPL",
    "gn:name":"Torza",
    "gn:population":93,
    "gn:timezone":"Europe/Rome",
    "iso:country":"IT",
    "wof:name":"Torza",
    "wof:placetype":"locality",
    "wof:population":93
},
  "geometry": {"coordinates":[9.56589,44.30096],"type":"Point"}
}