{
  "type": "Feature",
  "properties": {
    "gn:admin1_code":"10.0",
    "gn:admin2_code":"AN",
    "gn:admin3_code":"42004.0",
    "gn:asciiname":"Barbara",
    "gn:country_code":"IT",
    "gn:dem":197,
    "gn:elevation":"219.0",
    "gn:feature_class":"P",
    "gn:feature_code":"PPLA3",
    "gn:name":"Barbara",
    "gn:population":953,
    "gn:timezone":"Europe/Rome",
    "iso:country":"IT",
    "wof:name":"Barbara",
    "wof:placetype":"locality",
    "wof:population":953
},
  "geometry": {"coordinates":[13.02736,43.58036],"type":"Point"}
}