{
  "type": "Feature",
  "properties": {
    "gn:admin1_code":"10.0",
    "gn:admin2_code":"AN",
    "gn:admin3_code":"42004.0",
    "gn:asciiname":"Barbara",
    "gn:country_code":"IT",
    "gn:dem":197,
    "gn:elevation":"219.0",
    "gn:feature_class":"P",
    "gn:feature_code":"PPLA3",
    "gn:name":"Barbara",
    "gn:population":953,
    "gn:timezone":"Europe/Rome",
    "iso:country":"IT",
    "name:ara_x_preferred":[
        "\u0628\u0627\u0631\u0628\u0631\u0627"
    ],
    "name:bel_x_preferred":[
        "\u0411\u0430\u0440\u0431\u0430\u0440\u0430"
    ],
    "name:cat_x_preferred":[
        "B\u00e0rbara"
    ],
    "name:ceb_x_preferred":[
        "Barbara"
    ],
    "name:dan_x_preferred":[
        "Barbara"
    ],
    "name:deu_x_preferred":[
        "Barbara"
    ],
    "name:ell_x_preferred":[
        "\u0392\u03b1\u03c1\u03b2\u03ac\u03c1\u03b1"
    ],
    "name:epo_x_preferred":[
        "Barbara"
    ],
    "name:est_x_preferred":[
        "Barbara"
    ],
    "name:fao_x_preferred":[
        "Barbara"
    ],
    "name:fas_x_preferred":[
        "\u0628\u0627\u0631\u0628\u0627\u0631\u0627"
    ],
    "name:fra_x_preferred":[
        "Barbara"
    ],
    "name:heb_x_preferred":[
        "\u05d1\u05e8\u05d1\u05e8\u05d4"
    ],
    "name:hun_x_preferred":[
        "Barbara"
    ],
    "name:hye_x_preferred":[
        "\u0532\u0561\u0580\u0562\u0561\u0580\u0561"
    ],
    "name:ita_x_preferred":[
        "Barbara"
    ],
    "name:jpn_x_preferred":[
        "\u30d0\u30fc\u30d0\u30e9"
    ],
    "name:kor_x_preferred":[
        "\ubc14\ubc84\ub77c"
    ],
    "name:lat_x_preferred":[
        "Barbara"
    ],
    "name:lav_x_preferred":[
        "Barbara"
    ],
    "name:nld_x_preferred":[
        "Barbara"
    ],
    "name:pol_x_preferred":[
        "Barbara"
    ],
    "name:por_x_preferred":[
        "Barbara"
    ],
    "name:ron_x_preferred":[
        "Barbara"
    ],
    "name:rus_x_preferred":[
        "\u0411\u0430\u0440\u0431\u0430\u0440\u0430"
    ],
    "name:slk_x_preferred":[
        "Barbara"
    ],
    "name:slv_x_preferred":[
        "Barbara"
    ],
    "name:swe_x_preferred":[
        "Barbara"
    ],
    "name:vie_x_preferred":[
        "Barbara"
    ],
    "wof:name":"Barbara",
    "wof:placetype":"locality",
    "wof:population":953
},
  "geometry": {"coordinates":[13.02736,43.58036],"type":"Point"}
}