{
  "type": "Feature",
  "properties": {
    "gn:admin1_code":"15.0",
    "gn:admin2_code":"PA",
    "gn:admin3_code":"82025.0",
    "gn:asciiname":"Marcato Bianco",
    "gn:country_code":"IT",
    "gn:dem":656,
    "gn:feature_class":"P",
    "gn:feature_code":"PPL",
    "gn:name":"Marcato Bianco",
    "gn:population":113,
    "gn:timezone":"Europe/Rome",
    "iso:country":"IT",
    "wof:name":"Marcato Bianco",
    "wof:placetype":"locality",
    "wof:population":113
},
  "geometry": {"coordinates":[13.70476,37.74268],"type":"Point"}
}