{
  "type": "Feature",
  "properties": {
    "gn:admin1_code":"9.0",
    "gn:admin2_code":"SO",
    "gn:admin3_code":"14057.0",
    "gn:asciiname":"Era",
    "gn:country_code":"IT",
    "gn:dem":218,
    "gn:feature_class":"P",
    "gn:feature_code":"PPLA3",
    "gn:name":"Era",
    "gn:population":889,
    "gn:timezone":"Europe/Rome",
    "iso:country":"IT",
    "wof:name":"Era",
    "wof:placetype":"locality",
    "wof:population":889
},
  "geometry": {"coordinates":[9.39515,46.24422],"type":"Point"}
}