{
  "type": "Feature",
  "properties": {
    "gn:gn_country":"IT",
    "gn:gn_fcode":"PPL",
    "gn:gn_pop":0,
    "gn:population":3,
    "iso:country":"IT",
    "name:dut_x_preferred":[
        "Porto Badisco"
    ],
    "name:eng_x_preferred":[
        "Porto Badisco"
    ],
    "name:fre_x_preferred":[
        "Porto Badisco"
    ],
    "name:ger_x_preferred":[
        "Porto Badisco"
    ],
    "name:hun_x_preferred":[
        "Porto Badisco"
    ],
    "name:ita_x_preferred":[
        "Porto Badisco"
    ],
    "name:srp_x_preferred":[
        "Porto Badisco"
    ],
    "qs_pg:aaroncc":"IT",
    "qs_pg:gn_country":"IT",
    "qs_pg:gn_fcode":"PPL",
    "qs_pg:gn_pop":0,
    "qs_pg:name":"Porto Badisco",
    "qs_pg:name_adm0":"Italia",
    "qs_pg:name_adm1":"Puglia",
    "qs_pg:photos":652,
    "qs_pg:photos_1k":132,
    "qs_pg:photos_9k":3,
    "qs_pg:photos_9r":5,
    "qs_pg:photos_all":652,
    "qs_pg:photos_sr":8,
    "qs_pg:pop_sr":0,
    "qs_pg:qs_pg_placetype":"locality",
    "qs_pg:qs_pg_placetype_gp":"Town",
    "qs_pg:woe_adm0":23424853,
    "woe:adm0_id":23424853,
    "woe:name_adm0":"Italia",
    "woe:name_adm1":"Puglia",
    "woe:placetype":"Town",
    "wof:name":"Porto Badisco",
    "wof:placetype":"locality",
    "wof:population":3
},
  "geometry": {"coordinates":[18.48338,40.07991],"type":"Point"}
}