{
  "type": "Feature",
  "properties": {
    "gn:admin1_code":"12",
    "gn:admin2_code":"VC",
    "gn:admin3_code":"2128.0",
    "gn:asciiname":"Casale Benne",
    "gn:country_code":"IT",
    "gn:dem":165,
    "gn:feature_class":"P",
    "gn:feature_code":"PPL",
    "gn:name":"Casale Benne",
    "gn:population":24,
    "gn:timezone":"Europe/Rome",
    "iso:country":"IT",
    "wof:name":"Casale Benne",
    "wof:placetype":"locality",
    "wof:population":24
},
  "geometry": {"coordinates":[8.03762,45.20494],"type":"Point"}
}