{
  "type": "Feature",
  "properties": {
    "gn:admin1_code":"15",
    "gn:admin2_code":"PA",
    "gn:admin3_code":"82049.0",
    "gn:asciiname":"Barone",
    "gn:country_code":"IT",
    "gn:dem":463,
    "gn:feature_class":"P",
    "gn:feature_code":"PPL",
    "gn:name":"Barone",
    "gn:population":296,
    "gn:timezone":"Europe/Rome",
    "iso:country":"IT",
    "name:ceb_x_preferred":[
        "Barone"
    ],
    "name:deu_x_preferred":[
        "Barone"
    ],
    "name:fra_x_preferred":[
        "Barone"
    ],
    "name:ita_x_preferred":[
        "Barone"
    ],
    "name:rus_x_preferred":[
        "\u0411\u0430\u0440\u043e\u043d\u0435"
    ],
    "name:slv_x_preferred":[
        "Barone"
    ],
    "name:spa_x_preferred":[
        "Barone"
    ],
    "name:srp_x_preferred":[
        "Barone"
    ],
    "name:swe_x_preferred":[
        "Barone"
    ],
    "wof:name":"Barone",
    "wof:placetype":"locality",
    "wof:population":296
},
  "geometry": {"coordinates":[13.25191,38.04223],"type":"Point"}
}