{
  "type": "Feature",
  "properties": {
    "gn:admin1_code":"3",
    "gn:admin2_code":"VV",
    "gn:admin3_code":"102044.0",
    "gn:asciiname":"Vulcano",
    "gn:country_code":"IT",
    "gn:dem":98,
    "gn:feature_class":"P",
    "gn:feature_code":"PPL",
    "gn:name":"Vulcano",
    "gn:population":203,
    "gn:timezone":"Europe/Rome",
    "iso:country":"IT",
    "wof:name":"Vulcano",
    "wof:placetype":"locality",
    "wof:population":203
},
  "geometry": {"coordinates":[15.88294,38.66525],"type":"Point"}
}