{
  "type": "Feature",
  "properties": {
    "gn:admin1_code":"5",
    "gn:admin2_code":"BO",
    "gn:admin3_code":"37037.0",
    "gn:asciiname":"Casa Cacciatori",
    "gn:country_code":"IT",
    "gn:dem":7,
    "gn:feature_class":"P",
    "gn:feature_code":"PPL",
    "gn:name":"Casa Cacciatori",
    "gn:population":27,
    "gn:timezone":"Europe/Rome",
    "iso:country":"IT",
    "wof:name":"Casa Cacciatori",
    "wof:placetype":"locality",
    "wof:population":27
},
  "geometry": {"coordinates":[11.7077,44.51076],"type":"Point"}
}