{
  "type": "Feature",
  "properties": {
    "gn:admin1_code":"12",
    "gn:admin2_code":"BI",
    "gn:admin3_code":"96075.0",
    "gn:asciiname":"Cavaglioni",
    "gn:country_code":"IT",
    "gn:dem":569,
    "gn:feature_class":"P",
    "gn:feature_code":"PPL",
    "gn:name":"Cavaglioni",
    "gn:population":115,
    "gn:timezone":"Europe/Rome",
    "iso:country":"IT",
    "wof:name":"Cavaglioni",
    "wof:placetype":"locality",
    "wof:population":115
},
  "geometry": {"coordinates":[8.12052,45.63447],"type":"Point"}
}