{
  "type": "Feature",
  "properties": {
    "gn:admin1_code":"5",
    "gn:admin2_code":"FC",
    "gn:admin3_code":"40007.0",
    "gn:asciiname":"Aie",
    "gn:country_code":"IT",
    "gn:dem":53,
    "gn:feature_class":"P",
    "gn:feature_code":"PPL",
    "gn:name":"Aie",
    "gn:population":111,
    "gn:timezone":"Europe/Rome",
    "iso:country":"IT",
    "wof:name":"Aie",
    "wof:placetype":"locality",
    "wof:population":111
},
  "geometry": {"coordinates":[12.19623,44.11954],"type":"Point"}
}