{
  "type": "Feature",
  "properties": {
    "gn:admin1_code":"3",
    "gn:admin2_code":"CS",
    "gn:admin3_code":"78044.0",
    "gn:asciiname":"Muzzari",
    "gn:country_code":"IT",
    "gn:dem":58,
    "gn:feature_class":"P",
    "gn:feature_code":"PPL",
    "gn:name":"Muzzari",
    "gn:population":31,
    "gn:timezone":"Europe/Rome",
    "iso:country":"IT",
    "wof:name":"Muzzari",
    "wof:placetype":"locality",
    "wof:population":31
},
  "geometry": {"coordinates":[16.49085,39.63455],"type":"Point"}
}