{
  "type": "Feature",
  "properties": {
    "gn:admin1_code":"4",
    "gn:admin2_code":"BN",
    "gn:admin3_code":"62064.0",
    "gn:asciiname":"Peschiti",
    "gn:country_code":"IT",
    "gn:dem":670,
    "gn:feature_class":"P",
    "gn:feature_code":"PPL",
    "gn:name":"Peschiti",
    "gn:population":31,
    "gn:timezone":"Europe/Rome",
    "iso:country":"IT",
    "wof:name":"Peschiti",
    "wof:placetype":"locality",
    "wof:population":31
},
  "geometry": {"coordinates":[14.87256,41.30945],"type":"Point"}
}