{
  "type": "Feature",
  "properties": {
    "gn:admin1_code":"4",
    "gn:admin2_code":"BN",
    "gn:admin3_code":"62061.0",
    "gn:asciiname":"Izzo",
    "gn:country_code":"IT",
    "gn:dem":205,
    "gn:feature_class":"P",
    "gn:feature_code":"PPL",
    "gn:name":"Izzo",
    "gn:population":63,
    "gn:timezone":"Europe/Rome",
    "iso:country":"IT",
    "name:deu_x_preferred":[
        "Izzo"
    ],
    "name:fra_x_preferred":[
        "Izzo"
    ],
    "name:ita_x_preferred":[
        "Izzo"
    ],
    "name:rus_x_preferred":[
        "\u0418\u0446\u0446\u043e"
    ],
    "wof:name":"Izzo",
    "wof:placetype":"locality",
    "wof:population":63
},
  "geometry": {"coordinates":[14.53442,41.2678],"type":"Point"}
}