{
  "type": "Feature",
  "properties": {
    "gn:admin1_code":"6.0",
    "gn:admin2_code":"UD",
    "gn:admin3_code":"30116.0",
    "gn:asciiname":"Pradandons II",
    "gn:country_code":"IT",
    "gn:dem":201,
    "gn:feature_class":"P",
    "gn:feature_code":"PPL",
    "gn:name":"Pradandons II",
    "gn:population":15,
    "gn:timezone":"Europe/Rome",
    "iso:country":"IT",
    "wof:name":"Pradandons II",
    "wof:placetype":"locality",
    "wof:population":15
},
  "geometry": {"coordinates":[13.23758,46.19619],"type":"Point"}
}