{
  "type": "Feature",
  "properties": {
    "gn:admin1_code":"9",
    "gn:admin2_code":"MN",
    "gn:admin3_code":"20055.0",
    "gn:asciiname":"Zovo",
    "gn:country_code":"IT",
    "gn:dem":16,
    "gn:feature_class":"P",
    "gn:feature_code":"PPL",
    "gn:name":"Zovo",
    "gn:population":64,
    "gn:timezone":"Europe/Rome",
    "iso:country":"IT",
    "wof:name":"Zovo",
    "wof:placetype":"locality",
    "wof:population":64
},
  "geometry": {"coordinates":[10.91111,45.00258],"type":"Point"}
}