{
  "type": "Feature",
  "properties": {
    "gn:admin1_code":"5",
    "gn:admin2_code":"RE",
    "gn:admin3_code":"35016.0",
    "gn:asciiname":"Ronchi",
    "gn:country_code":"IT",
    "gn:dem":597,
    "gn:feature_class":"P",
    "gn:feature_code":"PPLL",
    "gn:name":"Ronchi",
    "gn:population":8,
    "gn:timezone":"Europe/Rome",
    "iso:country":"IT",
    "name:ceb_x_preferred":[
        "Ronchi"
    ],
    "name:deu_x_preferred":[
        "Ronchi"
    ],
    "name:epo_x_preferred":[
        "Ronchi"
    ],
    "name:ita_x_preferred":[
        "Ronchi"
    ],
    "name:lat_x_preferred":[
        "Ronches"
    ],
    "name:por_x_preferred":[
        "Ronchi"
    ],
    "name:scn_x_preferred":[
        "Ronchi"
    ],
    "name:srp_x_preferred":[
        "Ronki"
    ],
    "name:swe_x_preferred":[
        "Ronchi"
    ],
    "wof:name":"Ronchi",
    "wof:placetype":"locality",
    "wof:population":8
},
  "geometry": {"coordinates":[10.44371,44.46936],"type":"Point"}
}