{
  "type": "Feature",
  "properties": {
    "gn:admin1_code":"12",
    "gn:admin2_code":"CN",
    "gn:admin3_code":"4089.0",
    "gn:asciiname":"San Sebastiano",
    "gn:country_code":"IT",
    "gn:dem":383,
    "gn:feature_class":"P",
    "gn:feature_code":"PPL",
    "gn:name":"San Sebastiano",
    "gn:population":286,
    "gn:timezone":"Europe/Rome",
    "iso:country":"IT",
    "name:bre_x_preferred":[
        "San Sebastiano"
    ],
    "name:ceb_x_preferred":[
        "San Sebastiano"
    ],
    "name:deu_x_preferred":[
        "San Sebastiano"
    ],
    "name:fra_x_preferred":[
        "San Sebastiano"
    ],
    "name:ita_x_preferred":[
        "San Sebastiano"
    ],
    "name:pms_x_preferred":[
        "San Bastian"
    ],
    "name:por_x_preferred":[
        "San Sebastiano"
    ],
    "name:srp_x_preferred":[
        "San Sebastijano"
    ],
    "name:swe_x_preferred":[
        "San Sebastiano"
    ],
    "wof:name":"San Sebastiano",
    "wof:placetype":"locality",
    "wof:population":286
},
  "geometry": {"coordinates":[7.68768,44.51107],"type":"Point"}
}