{
  "type": "Feature",
  "properties": {
    "gn:admin1_code":"7",
    "gn:admin2_code":"FR",
    "gn:admin3_code":"60027.0",
    "gn:asciiname":"Guglielmi",
    "gn:country_code":"IT",
    "gn:dem":164,
    "gn:feature_class":"P",
    "gn:feature_code":"PPL",
    "gn:name":"Guglielmi",
    "gn:population":55,
    "gn:timezone":"Europe/Rome",
    "iso:country":"IT",
    "name:deu_x_preferred":[
        "Guglielmi"
    ],
    "name:fra_x_preferred":[
        "Guglielmi"
    ],
    "name:ita_x_preferred":[
        "Guglielmi"
    ],
    "name:rus_x_preferred":[
        "\u0413\u0443\u043b\u044c\u0435\u043b\u044c\u043c\u0438"
    ],
    "wof:name":"Guglielmi",
    "wof:placetype":"locality",
    "wof:population":55
},
  "geometry": {"coordinates":[13.60439,41.56249],"type":"Point"}
}