{
  "type": "Feature",
  "properties": {
    "gn:admin1_code":"9.0",
    "gn:admin2_code":"SO",
    "gn:admin3_code":"14060.0",
    "gn:asciiname":"Villaggio Sanatoriale E. Morelli",
    "gn:country_code":"IT",
    "gn:dem":1072,
    "gn:feature_class":"P",
    "gn:feature_code":"PPLL",
    "gn:name":"Villaggio Sanatoriale E. Morelli",
    "gn:population":1,
    "gn:timezone":"Europe/Rome",
    "iso:country":"IT",
    "wof:name":"Villaggio Sanatoriale E. Morelli",
    "wof:placetype":"locality",
    "wof:population":1
},
  "geometry": {"coordinates":[10.32685,46.33557],"type":"Point"}
}