{
  "type": "Feature",
  "properties": {
    "gn:admin1_code":"17",
    "gn:admin2_code":"BZ",
    "gn:admin3_code":"21072.0",
    "gn:asciiname":"Costalovara",
    "gn:country_code":"IT",
    "gn:dem":1210,
    "gn:feature_class":"P",
    "gn:feature_code":"PPL",
    "gn:name":"Costalovara",
    "gn:population":36,
    "gn:timezone":"Europe/Rome",
    "iso:country":"IT",
    "wof:name":"Costalovara",
    "wof:placetype":"locality",
    "wof:population":36
},
  "geometry": {"coordinates":[11.42553,46.52513],"type":"Point"}
}