{
  "type": "Feature",
  "properties": {
    "gn:admin1_code":"9",
    "gn:admin2_code":"BS",
    "gn:admin3_code":"17196.0",
    "gn:asciiname":"Cascina Malgherosse",
    "gn:country_code":"IT",
    "gn:dem":59,
    "gn:feature_class":"P",
    "gn:feature_code":"PPL",
    "gn:name":"Cascina Malgherosse",
    "gn:population":39,
    "gn:timezone":"Europe/Rome",
    "iso:country":"IT",
    "wof:name":"Cascina Malgherosse",
    "wof:placetype":"locality",
    "wof:population":39
},
  "geometry": {"coordinates":[10.03972,45.30051],"type":"Point"}
}