{
  "type": "Feature",
  "properties": {
    "gn:admin1_code":"19.0",
    "gn:admin2_code":"AO",
    "gn:admin3_code":"7059.0",
    "gn:asciiname":"Del",
    "gn:country_code":"IT",
    "gn:dem":1266,
    "gn:feature_class":"P",
    "gn:feature_code":"PPL",
    "gn:name":"Del",
    "gn:population":12,
    "gn:timezone":"Europe/Rome",
    "iso:country":"IT",
    "wof:name":"Del",
    "wof:placetype":"locality",
    "wof:population":12
},
  "geometry": {"coordinates":[7.55687,45.76927],"type":"Point"}
}