{
  "type": "Feature",
  "properties": {
    "gn:admin1_code":"19.0",
    "gn:admin2_code":"AO",
    "gn:admin3_code":"7059.0",
    "gn:asciiname":"Del",
    "gn:country_code":"IT",
    "gn:dem":1266,
    "gn:feature_class":"P",
    "gn:feature_code":"PPL",
    "gn:name":"Del",
    "gn:population":12,
    "gn:timezone":"Europe/Rome",
    "iso:country":"IT",
    "name:ara_x_preferred":[
        "\u0645\u0624\u062b\u0631 \u062f\u0644"
    ],
    "name:cat_x_preferred":[
        "Operador nabla"
    ],
    "name:ces_x_preferred":[
        "Nabla"
    ],
    "name:dan_x_preferred":[
        "Nabla-operatoren"
    ],
    "name:deu_x_preferred":[
        "Nabla-Operator"
    ],
    "name:ell_x_preferred":[
        "\u0391\u03bd\u03ac\u03b4\u03b5\u03bb\u03c4\u03b1"
    ],
    "name:epo_x_preferred":[
        "Nabla operatoro"
    ],
    "name:est_x_preferred":[
        "Nabla-operaator"
    ],
    "name:fas_x_preferred":[
        "\u0639\u0645\u0644\u06af\u0631 \u062f\u0644"
    ],
    "name:fin_x_preferred":[
        "Nabla"
    ],
    "name:fra_x_preferred":[
        "Nabla"
    ],
    "name:hrv_x_preferred":[
        "Hamiltonov operator"
    ],
    "name:hun_x_preferred":[
        "Nabla oper\u00e1tor"
    ],
    "name:hye_x_preferred":[
        "\u0546\u0561\u0562\u056c\u0561 \u0585\u057a\u0565\u0580\u0561\u057f\u0578\u0580"
    ],
    "name:ita_x_preferred":[
        "Operatore nabla"
    ],
    "name:jpn_x_preferred":[
        "\u30ca\u30d6\u30e9"
    ],
    "name:kaz_x_preferred":[
        "\u041d\u0430\u0431\u043b\u0430-\u043e\u043f\u0435\u0440\u0430\u0442\u043e\u0440"
    ],
    "name:kor_x_preferred":[
        "\ub378"
    ],
    "name:lav_x_preferred":[
        "Nabla"
    ],
    "name:nld_x_preferred":[
        "Nabla"
    ],
    "name:nor_x_preferred":[
        "Nabla-operator"
    ],
    "name:pol_x_preferred":[
        "Operator nabla"
    ],
    "name:por_x_preferred":[
        "Del"
    ],
    "name:ron_x_preferred":[
        "Nabla"
    ],
    "name:rus_x_preferred":[
        "\u041e\u043f\u0435\u0440\u0430\u0442\u043e\u0440 \u043d\u0430\u0431\u043b\u0430"
    ],
    "name:slk_x_preferred":[
        "Oper\u00e1tor nabla"
    ],
    "name:spa_x_preferred":[
        "Nabla"
    ],
    "name:swe_x_preferred":[
        "Nablaoperatorn"
    ],
    "name:tam_x_preferred":[
        "\u0b9f\u0bc6\u0bb2\u0bcd \u0b87\u0baf\u0b95\u0bcd\u0b95\u0bbf"
    ],
    "name:tat_x_preferred":[
        "\u041d\u0430\u0431\u043b\u0430 \u043e\u043f\u0435\u0440\u0430\u0442\u043e\u0440\u044b"
    ],
    "name:tur_x_preferred":[
        "Del i\u015flemcisi"
    ],
    "name:ukr_x_preferred":[
        "\u041e\u043f\u0435\u0440\u0430\u0442\u043e\u0440 \u0413\u0430\u043c\u0456\u043b\u044c\u0442\u043e\u043d\u0430"
    ],
    "name:zho_x_preferred":[
        "Nabla\u7b97\u5b50"
    ],
    "wof:name":"Del",
    "wof:placetype":"locality",
    "wof:population":12
},
  "geometry": {"coordinates":[7.55687,45.76927],"type":"Point"}
}