{
  "type": "Feature",
  "properties": {
    "gn:admin1_code":"5",
    "gn:admin2_code":"BO",
    "gn:admin3_code":"37027.0",
    "gn:asciiname":"Vivalle",
    "gn:country_code":"IT",
    "gn:dem":379,
    "gn:feature_class":"P",
    "gn:feature_code":"PPL",
    "gn:name":"Vivalle",
    "gn:population":48,
    "gn:timezone":"Europe/Rome",
    "iso:country":"IT",
    "wof:name":"Vivalle",
    "wof:placetype":"locality",
    "wof:population":48
},
  "geometry": {"coordinates":[10.96124,44.18955],"type":"Point"}
}