{
  "type": "Feature",
  "properties": {
    "gn:admin1_code":"20.0",
    "gn:admin2_code":"VI",
    "gn:admin3_code":"24100.0",
    "gn:asciiname":"Costenieri",
    "gn:cc2":"IT",
    "gn:country_code":"IT",
    "gn:dem":833,
    "gn:feature_class":"P",
    "gn:feature_code":"PPL",
    "gn:name":"Costenieri",
    "gn:population":12,
    "gn:timezone":"Europe/Rome",
    "iso:country":"IT",
    "name:und_x_variant":[
        "Costemeri",
        "I Costenieri"
    ],
    "wof:name":"Costenieri",
    "wof:placetype":"locality",
    "wof:population":12
},
  "geometry": {"coordinates":[11.31182,45.74734],"type":"Point"}
}