{
  "type": "Feature",
  "properties": {
    "gn:admin1_code":"9",
    "gn:admin2_code":"BG",
    "gn:admin3_code":"16082.0",
    "gn:asciiname":"Canito",
    "gn:country_code":"IT",
    "gn:dem":704,
    "gn:feature_class":"P",
    "gn:feature_code":"PPL",
    "gn:name":"Canito",
    "gn:population":100,
    "gn:timezone":"Europe/Rome",
    "iso:country":"IT",
    "name:spa_x_preferred":[
        "Canito"
    ],
    "wof:name":"Canito",
    "wof:placetype":"locality",
    "wof:population":100
},
  "geometry": {"coordinates":[9.55356,45.82904],"type":"Point"}
}