{
  "type": "Feature",
  "properties": {
    "iso:country":"IT",
    "wof:name":"Cenisia",
    "wof:placetype":"neighbourhood"
},
  "geometry": {"coordinates":[7.65237076586571,45.06721701519624],"type":"Point"}
}