{
  "type": "Feature",
  "properties": {
    "gn:admin1_code":"12",
    "gn:admin2_code":"AT",
    "gn:admin3_code":"5084.0",
    "gn:asciiname":"Vallia",
    "gn:country_code":"IT",
    "gn:dem":245,
    "gn:feature_class":"P",
    "gn:feature_code":"PPL",
    "gn:name":"Vallia",
    "gn:population":30,
    "gn:timezone":"Europe/Rome",
    "iso:country":"IT",
    "wof:name":"Vallia",
    "wof:placetype":"locality",
    "wof:population":30
},
  "geometry": {"coordinates":[8.05973,45.0251],"type":"Point"}
}