{
  "type": "Feature",
  "properties": {
    "gn:admin1_code":"20",
    "gn:admin2_code":"VI",
    "gn:admin3_code":"24100.0",
    "gn:asciiname":"Pozzo",
    "gn:country_code":"IT",
    "gn:dem":161,
    "gn:feature_class":"P",
    "gn:feature_code":"PPL",
    "gn:name":"Pozzo",
    "gn:population":25,
    "gn:timezone":"Europe/Rome",
    "iso:country":"IT",
    "wof:name":"Pozzo",
    "wof:placetype":"locality",
    "wof:population":25
},
  "geometry": {"coordinates":[11.40117,45.70756],"type":"Point"}
}