{
  "type": "Feature",
  "properties": {
    "gn:admin1_code":"9",
    "gn:admin2_code":"PV",
    "gn:admin3_code":"18128.0",
    "gn:asciiname":"Canevizza",
    "gn:country_code":"IT",
    "gn:dem":689,
    "gn:feature_class":"P",
    "gn:feature_code":"PPL",
    "gn:name":"Canevizza",
    "gn:population":15,
    "gn:timezone":"Europe/Rome",
    "iso:country":"IT",
    "wof:name":"Canevizza",
    "wof:placetype":"locality",
    "wof:population":15
},
  "geometry": {"coordinates":[9.32577,44.83282],"type":"Point"}
}