{
  "type": "Feature",
  "properties": {
    "gn:admin1_code":"4",
    "gn:admin2_code":"AV",
    "gn:admin3_code":"64052.0",
    "gn:asciiname":"Cesine",
    "gn:country_code":"IT",
    "gn:dem":558,
    "gn:feature_class":"P",
    "gn:feature_code":"PPL",
    "gn:name":"Cesine",
    "gn:population":225,
    "gn:timezone":"Europe/Rome",
    "iso:country":"IT",
    "name:por_x_preferred":[
        "Cesine"
    ],
    "wof:name":"Cesine",
    "wof:placetype":"locality",
    "wof:population":225
},
  "geometry": {"coordinates":[15.05027,41.1947],"type":"Point"}
}