{
  "type": "Feature",
  "properties": {
    "gn:admin1_code":"7",
    "gn:admin2_code":"RI",
    "gn:admin3_code":"57055.0",
    "gn:asciiname":"Macaiola",
    "gn:country_code":"IT",
    "gn:dem":446,
    "gn:feature_class":"P",
    "gn:feature_code":"PPL",
    "gn:name":"Macaiola",
    "gn:population":43,
    "gn:timezone":"Europe/Rome",
    "iso:country":"IT",
    "wof:name":"Macaiola",
    "wof:placetype":"locality",
    "wof:population":43
},
  "geometry": {"coordinates":[12.79514,42.2253],"type":"Point"}
}