{
  "type": "Feature",
  "properties": {
    "gn:admin1_code":"11",
    "gn:admin2_code":"CB",
    "gn:admin3_code":"70005.0",
    "gn:asciiname":"Calcarella",
    "gn:country_code":"IT",
    "gn:dem":726,
    "gn:feature_class":"P",
    "gn:feature_code":"PPL",
    "gn:name":"Calcarella",
    "gn:population":53,
    "gn:timezone":"Europe/Rome",
    "iso:country":"IT",
    "wof:name":"Calcarella",
    "wof:placetype":"locality",
    "wof:population":53
},
  "geometry": {"coordinates":[14.57485,41.54718],"type":"Point"}
}