{
  "type": "Feature",
  "properties": {
    "gn:admin1_code":"15.0",
    "gn:admin2_code":"TP",
    "gn:admin3_code":"81005.0",
    "gn:asciiname":"Case Tropea",
    "gn:country_code":"IT",
    "gn:dem":56,
    "gn:feature_class":"P",
    "gn:feature_code":"PPLL",
    "gn:name":"Case Tropea",
    "gn:population":2,
    "gn:timezone":"Europe/Rome",
    "iso:country":"IT",
    "wof:name":"Case Tropea",
    "wof:placetype":"locality",
    "wof:population":2
},
  "geometry": {"coordinates":[12.8336,38.05023],"type":"Point"}
}