{
  "type": "Feature",
  "properties": {
    "gn:admin1_code":"10.0",
    "gn:admin2_code":"MC",
    "gn:admin3_code":"43041.0",
    "gn:asciiname":"Potenza",
    "gn:country_code":"IT",
    "gn:dem":133,
    "gn:feature_class":"P",
    "gn:feature_code":"PPL",
    "gn:name":"Potenza",
    "gn:population":17,
    "gn:timezone":"Europe/Rome",
    "iso:country":"IT",
    "wof:name":"Potenza",
    "wof:placetype":"locality",
    "wof:population":17
},
  "geometry": {"coordinates":[13.35054,43.28614],"type":"Point"}
}