{
  "type": "Feature",
  "properties": {
    "gn:admin1_code":"8",
    "gn:admin2_code":"SV",
    "gn:admin3_code":"9025.0",
    "gn:asciiname":"Moraire",
    "gn:country_code":"IT",
    "gn:dem":62,
    "gn:feature_class":"P",
    "gn:feature_code":"PPL",
    "gn:name":"Moraire",
    "gn:population":48,
    "gn:timezone":"Europe/Rome",
    "iso:country":"IT",
    "wof:name":"Moraire",
    "wof:placetype":"locality",
    "wof:population":48
},
  "geometry": {"coordinates":[8.16143,44.07928],"type":"Point"}
}