{
  "type": "Feature",
  "properties": {
    "gn:admin1_code":"6.0",
    "gn:admin2_code":"UD",
    "gn:admin3_code":"30059.0",
    "gn:asciiname":"Pradis di Sotto",
    "gn:country_code":"IT",
    "gn:dem":369,
    "gn:feature_class":"P",
    "gn:feature_code":"PPL",
    "gn:name":"Pradis di Sotto",
    "gn:population":23,
    "gn:timezone":"Europe/Rome",
    "iso:country":"IT",
    "wof:name":"Pradis di Sotto",
    "wof:placetype":"locality",
    "wof:population":23
},
  "geometry": {"coordinates":[13.20245,46.42456],"type":"Point"}
}