{
  "type": "Feature",
  "properties": {
    "gn:admin1_code":"9",
    "gn:admin2_code":"CR",
    "gn:admin3_code":"19008.0",
    "gn:asciiname":"Galizia",
    "gn:country_code":"IT",
    "gn:dem":30,
    "gn:feature_class":"P",
    "gn:feature_code":"PPL",
    "gn:name":"Galizia",
    "gn:population":31,
    "gn:timezone":"Europe/Rome",
    "iso:country":"IT",
    "wof:name":"Galizia",
    "wof:placetype":"locality",
    "wof:population":31
},
  "geometry": {"coordinates":[10.28363,45.10234000000001],"type":"Point"}
}