{
  "type": "Feature",
  "properties": {
    "gn:admin1_code":"15",
    "gn:admin2_code":"ME",
    "gn:admin3_code":"83080.0",
    "gn:asciiname":"Zifronte",
    "gn:country_code":"IT",
    "gn:dem":127,
    "gn:feature_class":"P",
    "gn:feature_code":"PPL",
    "gn:name":"Zifronte",
    "gn:population":61,
    "gn:timezone":"Europe/Rome",
    "iso:country":"IT",
    "wof:name":"Zifronte",
    "wof:placetype":"locality",
    "wof:population":61
},
  "geometry": {"coordinates":[15.3355,38.18178],"type":"Point"}
}