{
  "type": "Feature",
  "properties": {
    "gn:admin1_code":"20",
    "gn:admin2_code":"VI",
    "gn:admin3_code":"24048.0",
    "gn:asciiname":"Fossanigo",
    "gn:country_code":"IT",
    "gn:dem":64,
    "gn:feature_class":"P",
    "gn:feature_code":"PPL",
    "gn:name":"Fossanigo",
    "gn:population":32,
    "gn:timezone":"Europe/Rome",
    "iso:country":"IT",
    "wof:name":"Fossanigo",
    "wof:placetype":"locality",
    "wof:population":32
},
  "geometry": {"coordinates":[11.4812,45.62636],"type":"Point"}
}