{
  "type": "Feature",
  "properties": {
    "gn:admin1_code":"8",
    "gn:admin2_code":"SV",
    "gn:admin3_code":"9013.0",
    "gn:asciiname":"Verezzi",
    "gn:country_code":"IT",
    "gn:dem":178,
    "gn:feature_class":"P",
    "gn:feature_code":"PPL",
    "gn:name":"Verezzi",
    "gn:population":130,
    "gn:timezone":"Europe/Rome",
    "iso:country":"IT",
    "wof:name":"Verezzi",
    "wof:placetype":"locality",
    "wof:population":130
},
  "geometry": {"coordinates":[8.31252,44.16684],"type":"Point"}
}