{
  "type": "Feature",
  "properties": {
    "gn:admin1_code":"16",
    "gn:admin2_code":"MS",
    "gn:admin3_code":"45015.0",
    "gn:asciiname":"Careggia",
    "gn:country_code":"IT",
    "gn:dem":322,
    "gn:feature_class":"P",
    "gn:feature_code":"PPL",
    "gn:name":"Careggia",
    "gn:population":20,
    "gn:timezone":"Europe/Rome",
    "iso:country":"IT",
    "wof:name":"Careggia",
    "wof:placetype":"locality",
    "wof:population":20
},
  "geometry": {"coordinates":[9.91053,44.24769000000001],"type":"Point"}
}