{
  "type": "Feature",
  "properties": {
    "gn:admin1_code":"12",
    "gn:admin2_code":"TO",
    "gn:admin3_code":"1189.0",
    "gn:asciiname":"Casa di Cura",
    "gn:country_code":"IT",
    "gn:dem":322,
    "gn:feature_class":"P",
    "gn:feature_code":"PPL",
    "gn:name":"Casa di Cura",
    "gn:population":15,
    "gn:timezone":"Europe/Rome",
    "iso:country":"IT",
    "wof:name":"Casa di Cura",
    "wof:placetype":"locality",
    "wof:population":15
},
  "geometry": {"coordinates":[7.53983,45.12469],"type":"Point"}
}