{
  "type": "Feature",
  "properties": {
    "gn:admin1_code":"9",
    "gn:admin2_code":"SO",
    "gn:admin3_code":"14014.0",
    "gn:asciiname":"Curtini",
    "gn:country_code":"IT",
    "gn:dem":449,
    "gn:feature_class":"P",
    "gn:feature_code":"PPL",
    "gn:name":"Curtini",
    "gn:population":16,
    "gn:timezone":"Europe/Rome",
    "iso:country":"IT",
    "wof:name":"Curtini",
    "wof:placetype":"locality",
    "wof:population":16
},
  "geometry": {"coordinates":[10.00227,46.15526],"type":"Point"}
}