{
  "type": "Feature",
  "properties": {
    "gn:admin1_code":"20",
    "gn:admin2_code":"VI",
    "gn:admin3_code":"24053.0",
    "gn:asciiname":"Santa Maria",
    "gn:country_code":"IT",
    "gn:dem":252,
    "gn:feature_class":"P",
    "gn:feature_code":"PPL",
    "gn:name":"Santa Maria",
    "gn:population":52,
    "gn:timezone":"Europe/Rome",
    "iso:country":"IT",
    "wof:name":"Santa Maria",
    "wof:placetype":"locality",
    "wof:population":52
},
  "geometry": {"coordinates":[11.50333,45.75354],"type":"Point"}
}