{
  "type": "Feature",
  "properties": {
    "gn:admin1_code":"20",
    "gn:admin2_code":"PD",
    "gn:admin3_code":"28022.0",
    "gn:asciiname":"Paluan",
    "gn:country_code":"IT",
    "gn:dem":4,
    "gn:feature_class":"P",
    "gn:feature_code":"PPL",
    "gn:name":"Paluan",
    "gn:population":120,
    "gn:timezone":"Europe/Rome",
    "iso:country":"IT",
    "wof:name":"Paluan",
    "wof:placetype":"locality",
    "wof:population":120
},
  "geometry": {"coordinates":[11.62172,45.18659],"type":"Point"}
}