{
  "type": "Feature",
  "properties": {
    "gn:admin1_code":"5",
    "gn:admin2_code":"RE",
    "gn:admin3_code":"35011.0",
    "gn:asciiname":"Savognatica",
    "gn:country_code":"IT",
    "gn:dem":620,
    "gn:feature_class":"P",
    "gn:feature_code":"PPL",
    "gn:name":"Savognatica",
    "gn:population":28,
    "gn:timezone":"Europe/Rome",
    "iso:country":"IT",
    "wof:name":"Savognatica",
    "wof:placetype":"locality",
    "wof:population":28
},
  "geometry": {"coordinates":[10.52539,44.44174],"type":"Point"}
}