{
  "type": "Feature",
  "properties": {
    "gn:admin1_code":"5.0",
    "gn:admin2_code":"PC",
    "gn:admin3_code":"33028.0",
    "gn:asciiname":"Sperongia",
    "gn:country_code":"IT",
    "gn:dem":460,
    "gn:feature_class":"P",
    "gn:feature_code":"PPL",
    "gn:name":"Sperongia",
    "gn:population":0,
    "gn:timezone":"Europe/Rome",
    "iso:country":"IT",
    "wof:name":"Sperongia",
    "wof:placetype":"locality"
},
  "geometry": {"coordinates":[9.75,44.73333],"type":"Point"}
}