{
  "type": "Feature",
  "properties": {
    "gn:admin1_code":"7.0",
    "gn:admin2_code":"RI",
    "gn:admin3_code":"57007.0",
    "gn:asciiname":"Nesce",
    "gn:country_code":"IT",
    "gn:dem":815,
    "gn:feature_class":"P",
    "gn:feature_code":"PPL",
    "gn:name":"Nesce",
    "gn:population":0,
    "gn:timezone":"Europe/Rome",
    "iso:country":"IT",
    "wof:name":"Nesce",
    "wof:placetype":"locality"
},
  "geometry": {"coordinates":[13.27423,42.17829],"type":"Point"}
}