{
  "type": "Feature",
  "properties": {
    "gn:admin1_code":"20",
    "gn:admin2_code":"VI",
    "gn:admin3_code":"24059.0",
    "gn:asciiname":"Scalabrin",
    "gn:country_code":"IT",
    "gn:dem":167,
    "gn:feature_class":"P",
    "gn:feature_code":"PPL",
    "gn:name":"Scalabrin",
    "gn:population":75,
    "gn:timezone":"Europe/Rome",
    "iso:country":"IT",
    "wof:name":"Scalabrin",
    "wof:placetype":"locality",
    "wof:population":75
},
  "geometry": {"coordinates":[11.58998,45.74379],"type":"Point"}
}