{
  "type": "Feature",
  "properties": {
    "gn:admin1_code":"5.0",
    "gn:admin2_code":"FE",
    "gn:admin3_code":"38001.0",
    "gn:asciiname":"San Nicolo",
    "gn:cc2":"IT",
    "gn:country_code":"IT",
    "gn:dem":4,
    "gn:feature_class":"P",
    "gn:feature_code":"PPL",
    "gn:name":"San Nicol\u00f2",
    "gn:population":731,
    "gn:timezone":"Europe/Rome",
    "iso:country":"IT",
    "name:und_x_variant":[
        "San Nicol\u00f2 Ferrarese"
    ],
    "wof:name":"San Nicolo",
    "wof:placetype":"locality",
    "wof:population":731
},
  "geometry": {"coordinates":[11.70968,44.70795],"type":"Point"}
}