{
  "type": "Feature",
  "properties": {
    "gn:admin1_code":"16",
    "gn:admin2_code":"SI",
    "gn:admin3_code":"52016.0",
    "gn:asciiname":"La Colonna",
    "gn:country_code":"IT",
    "gn:dem":206,
    "gn:feature_class":"P",
    "gn:feature_code":"PPL",
    "gn:name":"La Colonna",
    "gn:population":42,
    "gn:timezone":"Europe/Rome",
    "iso:country":"IT",
    "wof:name":"La Colonna",
    "wof:placetype":"locality",
    "wof:population":42
},
  "geometry": {"coordinates":[11.21855,43.39272],"type":"Point"}
}