{
  "type": "Feature",
  "properties": {
    "gn:admin1_code":"18.0",
    "gn:admin2_code":"TR",
    "gn:admin3_code":"55032.0",
    "gn:asciiname":"Appecano",
    "gn:country_code":"IT",
    "gn:dem":553,
    "gn:elevation":"572.0",
    "gn:feature_class":"P",
    "gn:feature_code":"PPL",
    "gn:name":"Appecano",
    "gn:population":31,
    "gn:timezone":"Europe/Rome",
    "iso:country":"IT",
    "wof:name":"Appecano",
    "wof:placetype":"locality",
    "wof:population":31
},
  "geometry": {"coordinates":[12.65224,42.6255],"type":"Point"}
}