{
  "type": "Feature",
  "properties": {
    "gn:admin1_code":"2",
    "gn:admin2_code":"PZ",
    "gn:admin3_code":"76012.0",
    "gn:asciiname":"Sant'Antonio Casalini",
    "gn:country_code":"IT",
    "gn:dem":692,
    "gn:feature_class":"P",
    "gn:feature_code":"PPL",
    "gn:name":"Sant'Antonio Casalini",
    "gn:population":28,
    "gn:timezone":"Europe/Rome",
    "iso:country":"IT",
    "wof:name":"Sant'Antonio Casalini",
    "wof:placetype":"locality",
    "wof:population":28
},
  "geometry": {"coordinates":[15.59269,40.73214],"type":"Point"}
}