{
  "type": "Feature",
  "properties": {
    "iso:country":"IT",
    "name:eng_x_preferred":[
        "Guadagna"
    ],
    "name:ita_x_preferred":[
        "Guadagna"
    ],
    "name:ita_x_variant":[
        "Oreto-Guadagna"
    ],
    "qs:gn_adm0_cc":"IT",
    "qs:gn_local":2523920,
    "qs:gn_nam_loc":"Palermo, Palermo, Palermo, Sicilia, IT",
    "qs:gn_namadm1":"15",
    "qs:local_max":6072,
    "qs:local_sum":26183,
    "qs:localhoods":18,
    "qs:name":"Guadagna",
    "qs:name_adm0":"Italia",
    "qs:name_adm1":"Sicilia",
    "qs:name_adm2":"Palermo",
    "qs:name_lau":"Palermo",
    "qs:name_local":"Palermo",
    "qs:photo_max":672,
    "qs:photo_sum":5208,
    "qs:placetype":"Suburb",
    "qs:quad_count":78,
    "qs:woe_adm0":23424853,
    "qs:woe_adm1":7153344,
    "qs:woe_adm2":12591846,
    "qs:woe_lau":12675770,
    "qs:woe_local":719846,
    "qs:woe_ver":"7.10.0",
    "wd:wordcount":31,
    "wof:lang":[
        "ita"
    ],
    "wof:name":"Guadagna",
    "wof:placetype":"neighbourhood"
},
  "geometry": {"coordinates":[13.369378,38.098659],"type":"Point"}
}