{
  "type": "Feature",
  "properties": {
    "gn:admin1_code":"1.0",
    "gn:admin2_code":"TE",
    "gn:admin3_code":"67008.0",
    "gn:asciiname":"Roiano",
    "gn:country_code":"IT",
    "gn:dem":687,
    "gn:elevation":"212.0",
    "gn:feature_class":"P",
    "gn:feature_code":"PPL",
    "gn:name":"Roiano",
    "gn:population":47,
    "gn:timezone":"Europe/Rome",
    "iso:country":"IT",
    "wof:name":"Roiano",
    "wof:placetype":"locality",
    "wof:population":47
},
  "geometry": {"coordinates":[13.63753,42.70334],"type":"Point"}
}