{
  "type": "Feature",
  "properties": {
    "gn:admin1_code":"20.0",
    "gn:admin2_code":"RO",
    "gn:admin3_code":"29024.0",
    "gn:asciiname":"Sabbioni",
    "gn:country_code":"IT",
    "gn:dem":5,
    "gn:feature_class":"P",
    "gn:feature_code":"PPL",
    "gn:name":"Sabbioni",
    "gn:population":13,
    "gn:timezone":"Europe/Rome",
    "iso:country":"IT",
    "wof:name":"Sabbioni",
    "wof:placetype":"locality",
    "wof:population":13
},
  "geometry": {"coordinates":[11.65877,45.04934],"type":"Point"}
}