{
  "type": "Feature",
  "properties": {
    "gn:admin1_code":"16",
    "gn:admin2_code":"FI",
    "gn:admin3_code":"48039.0",
    "gn:asciiname":"San Bavello",
    "gn:country_code":"IT",
    "gn:dem":254,
    "gn:feature_class":"P",
    "gn:feature_code":"PPL",
    "gn:name":"San Bavello",
    "gn:population":83,
    "gn:timezone":"Europe/Rome",
    "iso:country":"IT",
    "wof:name":"San Bavello",
    "wof:placetype":"locality",
    "wof:population":83
},
  "geometry": {"coordinates":[11.57385,43.92199],"type":"Point"}
}