{
  "type": "Feature",
  "properties": {
    "gn:admin1_code":"20",
    "gn:admin2_code":"VR",
    "gn:admin3_code":"23093.0",
    "gn:asciiname":"Cerati",
    "gn:country_code":"IT",
    "gn:dem":514,
    "gn:feature_class":"P",
    "gn:feature_code":"PPL",
    "gn:name":"Cerati",
    "gn:population":23,
    "gn:timezone":"Europe/Rome",
    "iso:country":"IT",
    "wof:name":"Cerati",
    "wof:placetype":"locality",
    "wof:population":23
},
  "geometry": {"coordinates":[11.22143,45.57753],"type":"Point"}
}