{
  "type": "Feature",
  "properties": {
    "gn:admin1_code":"3.0",
    "gn:admin2_code":"RC",
    "gn:admin3_code":"80056.0",
    "gn:asciiname":"Spropolo",
    "gn:country_code":"IT",
    "gn:dem":11,
    "gn:elevation":"12.0",
    "gn:feature_class":"P",
    "gn:feature_code":"PPL",
    "gn:name":"Spropolo",
    "gn:population":291,
    "gn:timezone":"Europe/Rome",
    "iso:country":"IT",
    "wof:name":"Spropolo",
    "wof:placetype":"locality",
    "wof:population":291
},
  "geometry": {"coordinates":[16.0395,37.92428],"type":"Point"}
}