{
  "type": "Feature",
  "properties": {
    "gn:admin1_code":"20",
    "gn:admin2_code":"PD",
    "gn:admin3_code":"28073.0",
    "gn:asciiname":"Vallona",
    "gn:country_code":"IT",
    "gn:dem":14,
    "gn:feature_class":"P",
    "gn:feature_code":"PPL",
    "gn:name":"Vallona",
    "gn:population":19,
    "gn:timezone":"Europe/Rome",
    "iso:country":"IT",
    "wof:name":"Vallona",
    "wof:placetype":"locality",
    "wof:population":19
},
  "geometry": {"coordinates":[11.75742,45.40974],"type":"Point"}
}