{
  "type": "Feature",
  "properties": {
    "gn:admin1_code":"11",
    "gn:admin2_code":"CB",
    "gn:admin3_code":"70084.0",
    "gn:asciiname":"Aia Vecchia",
    "gn:country_code":"IT",
    "gn:dem":627,
    "gn:feature_class":"P",
    "gn:feature_code":"PPL",
    "gn:name":"Aia Vecchia",
    "gn:population":29,
    "gn:timezone":"Europe/Rome",
    "iso:country":"IT",
    "wof:name":"Aia Vecchia",
    "wof:placetype":"locality",
    "wof:population":29
},
  "geometry": {"coordinates":[14.59099,41.48212],"type":"Point"}
}