{
  "type": "Feature",
  "properties": {
    "gn:admin1_code":"5",
    "gn:admin2_code":"MO",
    "gn:admin3_code":"36030.0",
    "gn:asciiname":"Casa Bellei",
    "gn:country_code":"IT",
    "gn:dem":706,
    "gn:feature_class":"P",
    "gn:feature_code":"PPL",
    "gn:name":"Casa Bellei",
    "gn:population":31,
    "gn:timezone":"Europe/Rome",
    "iso:country":"IT",
    "wof:name":"Casa Bellei",
    "wof:placetype":"locality",
    "wof:population":31
},
  "geometry": {"coordinates":[10.82169,44.33892],"type":"Point"}
}