{
  "type": "Feature",
  "properties": {
    "gn:admin1_code":"16",
    "gn:admin2_code":"LU",
    "gn:admin3_code":"46033.0",
    "gn:asciiname":"Fosso Guidario",
    "gn:country_code":"IT",
    "gn:dem":-1,
    "gn:feature_class":"P",
    "gn:feature_code":"PPL",
    "gn:name":"Fosso Guidario",
    "gn:population":16,
    "gn:timezone":"Europe/Rome",
    "iso:country":"IT",
    "wof:name":"Fosso Guidario",
    "wof:placetype":"locality",
    "wof:population":16
},
  "geometry": {"coordinates":[10.29095,43.84065],"type":"Point"}
}