{
  "type": "Feature",
  "properties": {
    "iso:country":"IT",
    "wof:name":"F\u00e1bbriche",
    "wof:placetype":"neighbourhood"
},
  "geometry": {"coordinates":[8.71851571387882,44.44785114957261],"type":"Point"}
}