{
  "type": "Feature",
  "properties": {
    "gn:admin1_code":"9.0",
    "gn:admin2_code":"MN",
    "gn:admin3_code":"20015.0",
    "gn:asciiname":"Perosso",
    "gn:country_code":"IT",
    "gn:dem":54,
    "gn:feature_class":"P",
    "gn:feature_code":"PPL",
    "gn:name":"Perosso",
    "gn:population":21,
    "gn:timezone":"Europe/Rome",
    "iso:country":"IT",
    "wof:name":"Perosso",
    "wof:placetype":"locality",
    "wof:population":21
},
  "geometry": {"coordinates":[10.48137,45.31587],"type":"Point"}
}