{
  "type": "Feature",
  "properties": {
    "gn:admin1_code":"20",
    "gn:admin2_code":"TV",
    "gn:admin3_code":"26064.0",
    "gn:asciiname":"Zagaria",
    "gn:country_code":"IT",
    "gn:dem":13,
    "gn:feature_class":"P",
    "gn:feature_code":"PPL",
    "gn:name":"Zagaria",
    "gn:population":41,
    "gn:timezone":"Europe/Rome",
    "iso:country":"IT",
    "wof:name":"Zagaria",
    "wof:placetype":"locality",
    "wof:population":41
},
  "geometry": {"coordinates":[12.17504,45.62006],"type":"Point"}
}