{
  "type": "Feature",
  "properties": {
    "gn:admin1_code":"12",
    "gn:admin2_code":"TO",
    "gn:admin3_code":"1221.0",
    "gn:asciiname":"Montiglio",
    "gn:country_code":"IT",
    "gn:dem":381,
    "gn:feature_class":"P",
    "gn:feature_code":"PPL",
    "gn:name":"Montiglio",
    "gn:population":68,
    "gn:timezone":"Europe/Rome",
    "iso:country":"IT",
    "wof:name":"Montiglio",
    "wof:placetype":"locality",
    "wof:population":68
},
  "geometry": {"coordinates":[7.5945,45.30919],"type":"Point"}
}