{
  "type": "Feature",
  "properties": {
    "gn:admin1_code":"8",
    "gn:admin2_code":"SP",
    "gn:admin3_code":"11003.0",
    "gn:asciiname":"Santa Martina",
    "gn:country_code":"IT",
    "gn:dem":74,
    "gn:feature_class":"P",
    "gn:feature_code":"PPL",
    "gn:name":"Santa Martina",
    "gn:population":21,
    "gn:timezone":"Europe/Rome",
    "iso:country":"IT",
    "wof:name":"Santa Martina",
    "wof:placetype":"locality",
    "wof:population":21
},
  "geometry": {"coordinates":[9.7878,44.19308],"type":"Point"}
}