{
  "type": "Feature",
  "properties": {
    "gn:admin1_code":"11.0",
    "gn:admin2_code":"CB",
    "gn:admin3_code":"70008.0",
    "gn:asciiname":"San Giovanni Cerreto",
    "gn:country_code":"IT",
    "gn:dem":549,
    "gn:feature_class":"P",
    "gn:feature_code":"PPL",
    "gn:name":"San Giovanni Cerreto",
    "gn:population":18,
    "gn:timezone":"Europe/Rome",
    "iso:country":"IT",
    "wof:name":"San Giovanni Cerreto",
    "wof:placetype":"locality",
    "wof:population":18
},
  "geometry": {"coordinates":[14.72134,41.5626],"type":"Point"}
}