{
  "type": "Feature",
  "properties": {
    "gn:admin1_code":"4",
    "gn:admin2_code":"BN",
    "gn:admin3_code":"62045.0",
    "gn:asciiname":"Contrada Montesanto",
    "gn:country_code":"IT",
    "gn:dem":331,
    "gn:feature_class":"P",
    "gn:feature_code":"PPL",
    "gn:name":"Contrada Montesanto",
    "gn:population":28,
    "gn:timezone":"Europe/Rome",
    "iso:country":"IT",
    "wof:name":"Contrada Montesanto",
    "wof:placetype":"locality",
    "wof:population":28
},
  "geometry": {"coordinates":[14.87133,41.15657],"type":"Point"}
}