{
  "type": "Feature",
  "properties": {
    "gn:admin1_code":"12",
    "gn:admin2_code":"AL",
    "gn:admin3_code":"6009.0",
    "gn:asciiname":"Ca Bianca",
    "gn:country_code":"IT",
    "gn:dem":286,
    "gn:feature_class":"P",
    "gn:feature_code":"PPL",
    "gn:name":"C\u00e0 Bianca",
    "gn:population":19,
    "gn:timezone":"Europe/Rome",
    "iso:country":"IT",
    "name:und_x_variant":[
        "C\u00e0 Bianca"
    ],
    "wof:name":"Ca Bianca",
    "wof:placetype":"locality",
    "wof:population":19
},
  "geometry": {"coordinates":[8.8938,44.66993],"type":"Point"}
}