{
  "type": "Feature",
  "properties": {
    "gn:admin1_code":"10",
    "gn:admin2_code":"PU",
    "gn:admin3_code":"41029.0",
    "gn:asciiname":"Molino Vecchio",
    "gn:country_code":"IT",
    "gn:dem":19,
    "gn:feature_class":"P",
    "gn:feature_code":"PPL",
    "gn:name":"Molino Vecchio",
    "gn:population":67,
    "gn:timezone":"Europe/Rome",
    "iso:country":"IT",
    "wof:name":"Molino Vecchio",
    "wof:placetype":"locality",
    "wof:population":67
},
  "geometry": {"coordinates":[13.13589,43.74183],"type":"Point"}
}