{
  "type": "Feature",
  "properties": {
    "gn:admin1_code":"18",
    "gn:admin2_code":"PG",
    "gn:admin3_code":"54037.0",
    "gn:asciiname":"Mongiovino Vecchio",
    "gn:country_code":"IT",
    "gn:dem":471,
    "gn:feature_class":"P",
    "gn:feature_code":"PPLL",
    "gn:name":"Mongiovino Vecchio",
    "gn:population":6,
    "gn:timezone":"Europe/Rome",
    "iso:country":"IT",
    "wof:name":"Mongiovino Vecchio",
    "wof:placetype":"locality",
    "wof:population":6
},
  "geometry": {"coordinates":[12.14367,43.02119],"type":"Point"}
}