{
  "type": "Feature",
  "properties": {
    "gn:admin1_code":"12",
    "gn:admin2_code":"TO",
    "gn:admin3_code":"1082.0",
    "gn:asciiname":"Violina-Repetto",
    "gn:country_code":"IT",
    "gn:dem":213,
    "gn:feature_class":"P",
    "gn:feature_code":"PPL",
    "gn:name":"Violina-Repetto",
    "gn:population":20,
    "gn:timezone":"Europe/Rome",
    "iso:country":"IT",
    "wof:name":"Violina-Repetto",
    "wof:placetype":"locality",
    "wof:population":20
},
  "geometry": {"coordinates":[7.9191,45.24117],"type":"Point"}
}