{
  "type": "Feature",
  "properties": {
    "gn:admin1_code":"7.0",
    "gn:admin2_code":"LT",
    "gn:admin3_code":"59005.0",
    "gn:asciiname":"Castelverde",
    "gn:country_code":"IT",
    "gn:dem":33,
    "gn:feature_class":"P",
    "gn:feature_code":"PPL",
    "gn:name":"Castelverde",
    "gn:population":348,
    "gn:timezone":"Europe/Rome",
    "iso:country":"IT",
    "name:bul_x_preferred":[
        "\u041a\u0430\u0441\u0442\u0435\u043b\u0432\u0435\u0440\u0434\u0435"
    ],
    "name:ceb_x_preferred":[
        "Castelverde"
    ],
    "name:deu_x_preferred":[
        "Castelverde"
    ],
    "name:epo_x_preferred":[
        "Castelverde"
    ],
    "name:eus_x_preferred":[
        "Castelverde"
    ],
    "name:fra_x_preferred":[
        "Castelverde"
    ],
    "name:hun_x_preferred":[
        "Castelverde"
    ],
    "name:hye_x_preferred":[
        "\u053f\u0561\u057d\u057f\u0565\u056c\u057e\u0565\u0580\u0564\u0565"
    ],
    "name:ita_x_preferred":[
        "Castelverde"
    ],
    "name:jpn_x_preferred":[
        "\u30ab\u30b9\u30c6\u30eb\u30f4\u30a7\u30eb\u30c7"
    ],
    "name:kaz_x_preferred":[
        "\u041a\u0430\u0441\u0442\u0435\u043b\u044c\u0432\u0435\u0440\u0434\u0435"
    ],
    "name:lat_x_preferred":[
        "Castegninum Sichum"
    ],
    "name:lmo_x_preferred":[
        "Castegnin"
    ],
    "name:msa_x_preferred":[
        "Castelverde"
    ],
    "name:nap_x_preferred":[
        "Castelverde"
    ],
    "name:nld_x_preferred":[
        "Castelverde"
    ],
    "name:pms_x_preferred":[
        "Castelverde"
    ],
    "name:pol_x_preferred":[
        "Castelverde"
    ],
    "name:por_x_preferred":[
        "Castelverde"
    ],
    "name:ron_x_preferred":[
        "Castelverde"
    ],
    "name:rus_x_preferred":[
        "\u041a\u0430\u0441\u0442\u0435\u043b\u044c\u0432\u0435\u0440\u0434\u0435"
    ],
    "name:scn_x_preferred":[
        "Castelverde"
    ],
    "name:spa_x_preferred":[
        "Castelverde"
    ],
    "name:srp_x_preferred":[
        "\u041a\u0430\u0441\u0442\u0435\u043b\u0432\u0435\u0440\u0434\u0435"
    ],
    "name:ukr_x_preferred":[
        "\u041a\u0430\u0441\u0442\u0435\u043b\u044c\u0432\u0435\u0440\u0434\u0435"
    ],
    "name:uzb_x_preferred":[
        "Castelverde"
    ],
    "name:vie_x_preferred":[
        "Castelverde"
    ],
    "name:vol_x_preferred":[
        "Castelverde"
    ],
    "name:war_x_preferred":[
        "Castelverde"
    ],
    "name:zho_x_preferred":[
        "\u5361\u65af\u6cf0\u5c14\u97e6\u5c14\u5fb7"
    ],
    "wof:name":"Castelverde",
    "wof:placetype":"locality",
    "wof:population":348
},
  "geometry": {"coordinates":[12.79928,41.49462],"type":"Point"}
}