{
  "type": "Feature",
  "properties": {
    "iso:country":"IT",
    "wof:name":"Fonte Meravigliosa",
    "wof:placetype":"neighbourhood"
},
  "geometry": {"coordinates":[12.50714032009976,41.82390942130093],"type":"Point"}
}