{
  "type": "Feature",
  "properties": {
    "gn:admin1_code":"13.0",
    "gn:admin2_code":"LE",
    "gn:admin3_code":"75093.0",
    "gn:asciiname":"Vanze",
    "gn:country_code":"IT",
    "gn:dem":32,
    "gn:elevation":"29.0",
    "gn:feature_class":"P",
    "gn:feature_code":"PPL",
    "gn:name":"Vanze",
    "gn:population":245,
    "gn:timezone":"Europe/Rome",
    "iso:country":"IT",
    "wof:name":"Vanze",
    "wof:placetype":"locality",
    "wof:population":245
},
  "geometry": {"coordinates":[18.31734,40.32222],"type":"Point"}
}