{
  "type": "Feature",
  "properties": {
    "gn:gn_country":"IT",
    "gn:gn_fcode":"PPL",
    "gn:gn_pop":0,
    "iso:country":"IT",
    "name:eng_x_preferred":[
        "San Momm\u00e8"
    ],
    "name:fra_x_preferred":[
        "San Momm\u00e8"
    ],
    "name:hun_x_preferred":[
        "San Momm\u00e8"
    ],
    "name:ita_x_preferred":[
        "San Momm\u00e8"
    ],
    "name:nld_x_preferred":[
        "San Momm\u00e8"
    ],
    "qs_pg:aaroncc":"IT",
    "qs_pg:gn_country":"IT",
    "qs_pg:gn_fcode":"PPL",
    "qs_pg:gn_pop":0,
    "qs_pg:name":"San Momme",
    "qs_pg:name_adm0":"Italia",
    "qs_pg:name_adm1":"Toscana",
    "qs_pg:photos":16,
    "qs_pg:photos_1k":3,
    "qs_pg:photos_9k":1,
    "qs_pg:photos_9r":1,
    "qs_pg:photos_all":16,
    "qs_pg:photos_sr":1,
    "qs_pg:pop_sr":0,
    "qs_pg:qs_pg_placetype":"locality",
    "qs_pg:qs_pg_placetype_gp":"Town",
    "qs_pg:woe_adm0":23424853,
    "woe:adm0_id":23424853,
    "woe:name_adm0":"Italia",
    "woe:name_adm1":"Toscana",
    "woe:placetype":"Town",
    "wof:name":"San Momme",
    "wof:placetype":"locality"
},
  "geometry": {"coordinates":[10.91667,44.03333],"type":"Point"}
}