{
  "type": "Feature",
  "properties": {
    "gn:admin1_code":"16",
    "gn:admin2_code":"AR",
    "gn:admin3_code":"51030.0",
    "gn:asciiname":"Ville di Roti",
    "gn:country_code":"IT",
    "gn:dem":665,
    "gn:feature_class":"P",
    "gn:feature_code":"PPL",
    "gn:name":"Ville di Roti",
    "gn:population":19,
    "gn:timezone":"Europe/Rome",
    "iso:country":"IT",
    "wof:name":"Ville di Roti",
    "wof:placetype":"locality",
    "wof:population":19
},
  "geometry": {"coordinates":[12.05894,43.7204],"type":"Point"}
}