{
  "type": "Feature",
  "properties": {
    "gn:admin1_code":"18",
    "gn:admin2_code":"PG",
    "gn:admin3_code":"54052.0",
    "gn:asciiname":"Pontecuti Nuovo",
    "gn:country_code":"IT",
    "gn:dem":171,
    "gn:feature_class":"P",
    "gn:feature_code":"PPL",
    "gn:name":"Pontecuti Nuovo",
    "gn:population":210,
    "gn:timezone":"Europe/Rome",
    "iso:country":"IT",
    "wof:name":"Pontecuti Nuovo",
    "wof:placetype":"locality",
    "wof:population":210
},
  "geometry": {"coordinates":[12.36899,42.77612],"type":"Point"}
}