{
  "type": "Feature",
  "properties": {
    "gn:admin1_code":"12.0",
    "gn:admin2_code":"TO",
    "gn:admin3_code":"1212.0",
    "gn:asciiname":"Costa",
    "gn:country_code":"IT",
    "gn:dem":1136,
    "gn:feature_class":"P",
    "gn:feature_code":"PPLL",
    "gn:name":"Costa",
    "gn:population":1,
    "gn:timezone":"Europe/Rome",
    "iso:country":"IT",
    "wof:name":"Costa",
    "wof:placetype":"locality",
    "wof:population":1
},
  "geometry": {"coordinates":[7.49652,45.43676],"type":"Point"}
}