{
  "type": "Feature",
  "properties": {
    "gn:admin1_code":"4",
    "gn:admin3_code":"63060.0",
    "gn:asciiname":"Montagna Spaccata",
    "gn:country_code":"IT",
    "gn:dem":52,
    "gn:feature_class":"P",
    "gn:feature_code":"PPL",
    "gn:name":"Montagna Spaccata",
    "gn:population":108,
    "gn:timezone":"Europe/Rome",
    "iso:country":"IT",
    "wof:name":"Montagna Spaccata",
    "wof:placetype":"locality",
    "wof:population":108
},
  "geometry": {"coordinates":[14.1226,40.87046],"type":"Point"}
}