{
  "type": "Feature",
  "properties": {
    "gn:admin1_code":"18.0",
    "gn:admin2_code":"TR",
    "gn:admin3_code":"55005.0",
    "gn:asciiname":"Casteldilago",
    "gn:country_code":"IT",
    "gn:dem":252,
    "gn:elevation":"292.0",
    "gn:feature_class":"P",
    "gn:feature_code":"PPL",
    "gn:name":"Casteldilago",
    "gn:population":475,
    "gn:timezone":"Europe/Rome",
    "iso:country":"IT",
    "wof:name":"Casteldilago",
    "wof:placetype":"locality",
    "wof:population":475
},
  "geometry": {"coordinates":[12.75487,42.58153],"type":"Point"}
}