{
  "type": "Feature",
  "properties": {
    "gn:admin1_code":"7",
    "gn:admin2_code":"RM",
    "gn:admin3_code":"58086.0",
    "gn:asciiname":"Valle Pantano",
    "gn:country_code":"IT",
    "gn:dem":753,
    "gn:feature_class":"P",
    "gn:feature_code":"PPL",
    "gn:name":"Valle Pantano",
    "gn:population":64,
    "gn:timezone":"Europe/Rome",
    "iso:country":"IT",
    "wof:name":"Valle Pantano",
    "wof:placetype":"locality",
    "wof:population":64
},
  "geometry": {"coordinates":[12.72233,41.7526],"type":"Point"}
}