{
  "type": "Feature",
  "properties": {
    "gn:admin1_code":"7",
    "gn:admin2_code":"RM",
    "gn:admin3_code":"58041.0",
    "gn:asciiname":"Fornarelli",
    "gn:country_code":"IT",
    "gn:dem":266,
    "gn:feature_class":"P",
    "gn:feature_code":"PPL",
    "gn:name":"Fornarelli",
    "gn:population":45,
    "gn:timezone":"Europe/Rome",
    "iso:country":"IT",
    "wof:name":"Fornarelli",
    "wof:placetype":"locality",
    "wof:population":45
},
  "geometry": {"coordinates":[13.0678,41.69852],"type":"Point"}
}