{
  "type": "Feature",
  "properties": {
    "gn:admin1_code":"6.0",
    "gn:admin2_code":"UD",
    "gn:admin3_code":"30101.0",
    "gn:asciiname":"Medeuzza",
    "gn:country_code":"IT",
    "gn:dem":42,
    "gn:elevation":"43.0",
    "gn:feature_class":"P",
    "gn:feature_code":"PPL",
    "gn:name":"Medeuzza",
    "gn:population":567,
    "gn:timezone":"Europe/Rome",
    "iso:country":"IT",
    "wof:name":"Medeuzza",
    "wof:placetype":"locality",
    "wof:population":567
},
  "geometry": {"coordinates":[13.39628,45.94118],"type":"Point"}
}