{
  "type": "Feature",
  "properties": {
    "gn:admin1_code":"5.0",
    "gn:admin2_code":"RE",
    "gn:admin3_code":"35040.0",
    "gn:asciiname":"Bosco",
    "gn:country_code":"IT",
    "gn:dem":88,
    "gn:feature_class":"P",
    "gn:feature_code":"PPL",
    "gn:name":"Bosco",
    "gn:population":706,
    "gn:timezone":"Europe/Rome",
    "iso:country":"IT",
    "wof:name":"Bosco",
    "wof:placetype":"locality",
    "wof:population":706
},
  "geometry": {"coordinates":[10.6715,44.62259],"type":"Point"}
}