{
  "type": "Feature",
  "properties": {
    "gn:admin1_code":"2.0",
    "gn:admin2_code":"PZ",
    "gn:admin3_code":"76007.0",
    "gn:asciiname":"Masi",
    "gn:cc2":"IT",
    "gn:country_code":"IT",
    "gn:dem":734,
    "gn:feature_class":"P",
    "gn:feature_code":"PPL",
    "gn:name":"Masi",
    "gn:population":41,
    "gn:timezone":"Europe/Rome",
    "iso:country":"IT",
    "name:ceb_x_preferred":[
        "Masi"
    ],
    "name:deu_x_preferred":[
        "Masi"
    ],
    "name:fra_x_preferred":[
        "Masi"
    ],
    "name:ita_x_preferred":[
        "Masi"
    ],
    "name:nld_x_preferred":[
        "Masi"
    ],
    "name:pol_x_preferred":[
        "Masi"
    ],
    "name:spa_x_preferred":[
        "Masi"
    ],
    "name:srp_x_preferred":[
        "Mazi"
    ],
    "name:swe_x_preferred":[
        "Masi"
    ],
    "name:und_x_variant":[
        "I Masi"
    ],
    "wof:name":"Masi",
    "wof:placetype":"locality",
    "wof:population":41
},
  "geometry": {"coordinates":[15.72444,40.80316],"type":"Point"}
}