{
  "type": "Feature",
  "properties": {
    "gn:admin1_code":"2.0",
    "gn:admin2_code":"PZ",
    "gn:admin3_code":"76007.0",
    "gn:asciiname":"Masi",
    "gn:cc2":"IT",
    "gn:country_code":"IT",
    "gn:dem":734,
    "gn:feature_class":"P",
    "gn:feature_code":"PPL",
    "gn:name":"Masi",
    "gn:population":41,
    "gn:timezone":"Europe/Rome",
    "iso:country":"IT",
    "name:ara_x_preferred":[
        "\u0645\u0627\u0633\u064a"
    ],
    "name:ben_x_preferred":[
        "\u09ae\u09be\u09b8\u09bf"
    ],
    "name:ceb_x_preferred":[
        "Masi"
    ],
    "name:deu_x_preferred":[
        "Masi"
    ],
    "name:ell_x_preferred":[
        "\u039c\u03ac\u03c3\u03b9"
    ],
    "name:fas_x_preferred":[
        "\u0645\u0627\u0633\u06cc"
    ],
    "name:fra_x_preferred":[
        "Masi"
    ],
    "name:heb_x_preferred":[
        "\u05de\u05d0\u05e1\u05d9\u05e3 \u05d3\u05d4 \u05d1\u05d5\u05e0\u05d2\u05d5\u05e1"
    ],
    "name:hin_x_preferred":[
        "\u092e\u093e\u0938\u0940"
    ],
    "name:hun_x_preferred":[
        "Masi"
    ],
    "name:ind_x_preferred":[
        "Masi"
    ],
    "name:ita_x_preferred":[
        "Masi"
    ],
    "name:jpn_x_preferred":[
        "\u30de\u30b7\u5ddd"
    ],
    "name:kor_x_preferred":[
        "\ub9c8\uc2dc"
    ],
    "name:nld_x_preferred":[
        "Masi"
    ],
    "name:pol_x_preferred":[
        "Masi"
    ],
    "name:por_x_preferred":[
        "Masi"
    ],
    "name:rus_x_preferred":[
        "\u0440\u0435\u043a\u0430 \u041c\u0443\u0441\u0438"
    ],
    "name:spa_x_preferred":[
        "Masi"
    ],
    "name:srp_x_preferred":[
        "Mazi"
    ],
    "name:swe_x_preferred":[
        "Masi"
    ],
    "name:tur_x_preferred":[
        "Masi"
    ],
    "name:ukr_x_preferred":[
        "\u041c\u0430\u0441\u0456"
    ],
    "name:und_x_variant":[
        "I Masi"
    ],
    "name:urd_x_preferred":[
        "\u0645\u0627\u0633\u06cc"
    ],
    "name:vie_x_preferred":[
        "S\u00f4ng Masi"
    ],
    "name:zho_cn_x_preferred":[
        "\u9a6c\u897f\u6cb3"
    ],
    "name:zho_tw_x_preferred":[
        "\u99ac\u897f\u6cb3"
    ],
    "wof:name":"Masi",
    "wof:placetype":"locality",
    "wof:population":41
},
  "geometry": {"coordinates":[15.72444,40.80316],"type":"Point"}
}