{
  "type": "Feature",
  "properties": {
    "gn:admin1_code":"17",
    "gn:admin2_code":"BZ",
    "gn:admin3_code":"21033.0",
    "gn:asciiname":"Masi della Volpe",
    "gn:country_code":"IT",
    "gn:dem":1017,
    "gn:feature_class":"P",
    "gn:feature_code":"PPL",
    "gn:name":"Masi della Volpe",
    "gn:population":25,
    "gn:timezone":"Europe/Rome",
    "iso:country":"IT",
    "wof:name":"Masi della Volpe",
    "wof:placetype":"locality",
    "wof:population":25
},
  "geometry": {"coordinates":[11.66623,46.63585],"type":"Point"}
}