{
  "type": "Feature",
  "properties": {
    "gn:admin1_code":"17",
    "gn:admin2_code":"TN",
    "gn:admin3_code":"22139.0",
    "gn:asciiname":"Zava",
    "gn:country_code":"IT",
    "gn:dem":677,
    "gn:feature_class":"P",
    "gn:feature_code":"PPL",
    "gn:name":"Zava",
    "gn:population":55,
    "gn:timezone":"Europe/Rome",
    "iso:country":"IT",
    "wof:name":"Zava",
    "wof:placetype":"locality",
    "wof:population":55
},
  "geometry": {"coordinates":[11.25132,46.0424],"type":"Point"}
}