{
  "type": "Feature",
  "properties": {
    "gn:admin1_code":"17.0",
    "gn:admin2_code":"BZ",
    "gn:admin3_code":"21088.0",
    "gn:asciiname":"Cesa",
    "gn:country_code":"IT",
    "gn:dem":1718,
    "gn:feature_class":"P",
    "gn:feature_code":"PPLL",
    "gn:name":"Cesa",
    "gn:population":5,
    "gn:timezone":"Europe/Rome",
    "iso:country":"IT",
    "wof:name":"Cesa",
    "wof:placetype":"locality",
    "wof:population":5
},
  "geometry": {"coordinates":[11.78511,46.922],"type":"Point"}
}