{
  "type": "Feature",
  "properties": {
    "gn:admin1_code":"17.0",
    "gn:admin2_code":"BZ",
    "gn:admin3_code":"21088.0",
    "gn:asciiname":"Cesa",
    "gn:country_code":"IT",
    "gn:dem":1718,
    "gn:feature_class":"P",
    "gn:feature_code":"PPLL",
    "gn:name":"Cesa",
    "gn:population":5,
    "gn:timezone":"Europe/Rome",
    "iso:country":"IT",
    "name:azb_x_preferred":[
        "\u0686\u0633\u0627"
    ],
    "name:bul_x_preferred":[
        "\u0427\u0435\u0437\u0430"
    ],
    "name:ceb_x_preferred":[
        "Cesa"
    ],
    "name:deu_x_preferred":[
        "Cesa"
    ],
    "name:epo_x_preferred":[
        "Cesa"
    ],
    "name:eus_x_preferred":[
        "Cesa"
    ],
    "name:fas_x_preferred":[
        "\u0686\u0633\u0627"
    ],
    "name:fra_x_preferred":[
        "Cesa"
    ],
    "name:glg_x_preferred":[
        "Cesa"
    ],
    "name:hun_x_preferred":[
        "Cesa"
    ],
    "name:hye_x_preferred":[
        "\u0549\u0565\u0566\u0561"
    ],
    "name:ina_x_preferred":[
        "Cesa"
    ],
    "name:ind_x_preferred":[
        "Cesa"
    ],
    "name:ita_x_preferred":[
        "Cesa"
    ],
    "name:jpn_x_preferred":[
        "\u30c1\u30a7\u30fc\u30b6"
    ],
    "name:kaz_x_preferred":[
        "\u0427\u0435\u0437\u0430"
    ],
    "name:lat_x_preferred":[
        "Caesa"
    ],
    "name:lmo_x_preferred":[
        "Cesa"
    ],
    "name:mkd_x_preferred":[
        "\u0427\u0435\u0437\u0430"
    ],
    "name:msa_x_preferred":[
        "Cesa"
    ],
    "name:nap_x_preferred":[
        "Cesa"
    ],
    "name:nld_x_preferred":[
        "Cesa"
    ],
    "name:pms_x_preferred":[
        "Cesa"
    ],
    "name:pol_x_preferred":[
        "Cesa"
    ],
    "name:por_x_preferred":[
        "Cesa"
    ],
    "name:ron_x_preferred":[
        "Cesa"
    ],
    "name:rus_x_preferred":[
        "\u0427\u0435\u0437\u0430"
    ],
    "name:scn_x_preferred":[
        "Cesa"
    ],
    "name:spa_x_preferred":[
        "Cesa"
    ],
    "name:srp_x_preferred":[
        "\u0427\u0435\u0437\u0430"
    ],
    "name:tgl_x_preferred":[
        "Cesa"
    ],
    "name:tur_x_preferred":[
        "Cesa"
    ],
    "name:ukr_x_preferred":[
        "\u0427\u0435\u0437\u0430"
    ],
    "name:uzb_x_preferred":[
        "Cesa"
    ],
    "name:vec_x_preferred":[
        "C\u00e9xa"
    ],
    "name:vie_x_preferred":[
        "Cesa"
    ],
    "name:vol_x_preferred":[
        "Cesa"
    ],
    "name:war_x_preferred":[
        "Cesa"
    ],
    "wof:name":"Cesa",
    "wof:placetype":"locality",
    "wof:population":5
},
  "geometry": {"coordinates":[11.78511,46.922],"type":"Point"}
}