{
  "type": "Feature",
  "properties": {
    "gn:admin1_code":"12",
    "gn:admin2_code":"AT",
    "gn:admin3_code":"5100.0",
    "gn:asciiname":"Italiana",
    "gn:country_code":"IT",
    "gn:dem":188,
    "gn:feature_class":"P",
    "gn:feature_code":"PPL",
    "gn:name":"Italiana",
    "gn:population":17,
    "gn:timezone":"Europe/Rome",
    "iso:country":"IT",
    "wof:name":"Italiana",
    "wof:placetype":"locality",
    "wof:population":17
},
  "geometry": {"coordinates":[8.29495,44.76543],"type":"Point"}
}