{
  "type": "Feature",
  "properties": {
    "gn:admin1_code":"17",
    "gn:admin2_code":"BZ",
    "gn:admin3_code":"21027.0",
    "gn:asciiname":"Monteplair",
    "gn:country_code":"IT",
    "gn:dem":1497,
    "gn:feature_class":"P",
    "gn:feature_code":"PPL",
    "gn:name":"Monteplair",
    "gn:population":94,
    "gn:timezone":"Europe/Rome",
    "iso:country":"IT",
    "wof:name":"Monteplair",
    "wof:placetype":"locality",
    "wof:population":94
},
  "geometry": {"coordinates":[10.5441,46.75742],"type":"Point"}
}