{
  "type": "Feature",
  "properties": {
    "gn:admin1_code":"7",
    "gn:admin2_code":"RM",
    "gn:admin3_code":"58084.0",
    "gn:asciiname":"Rocca di Mezzo",
    "gn:country_code":"IT",
    "gn:dem":823,
    "gn:feature_class":"P",
    "gn:feature_code":"PPL",
    "gn:name":"Rocca di Mezzo",
    "gn:population":70,
    "gn:timezone":"Europe/Rome",
    "iso:country":"IT",
    "wof:name":"Rocca di Mezzo",
    "wof:placetype":"locality",
    "wof:population":70
},
  "geometry": {"coordinates":[13.00978,41.96519],"type":"Point"}
}