{
  "type": "Feature",
  "properties": {
    "gn:admin1_code":"7",
    "gn:admin2_code":"RM",
    "gn:admin3_code":"58084.0",
    "gn:asciiname":"Rocca di Mezzo",
    "gn:country_code":"IT",
    "gn:dem":823,
    "gn:feature_class":"P",
    "gn:feature_code":"PPL",
    "gn:name":"Rocca di Mezzo",
    "gn:population":70,
    "gn:timezone":"Europe/Rome",
    "iso:country":"IT",
    "name:ara_x_preferred":[
        "\u0631\u0648\u0643\u0627 \u062f\u064a \u0645\u064a\u062a\u0633\u0648"
    ],
    "name:azb_x_preferred":[
        "\u0631\u0648\u06a9\u0627 \u062f\u06cc \u0645\u062a\u0633\u0648"
    ],
    "name:bul_x_preferred":[
        "\u0420\u043e\u043a\u0430 \u0434\u0438 \u041c\u0435\u0434\u0437\u043e"
    ],
    "name:fas_x_preferred":[
        "\u0631\u0648\u06a9\u0627 \u062f\u06cc \u0645\u062a\u0633\u0648"
    ],
    "name:hye_x_preferred":[
        "\u054c\u0578\u056f\u0561 \u0564\u056b \u0544\u0565\u0571\u0578"
    ],
    "name:jpn_x_preferred":[
        "\u30ed\u30c3\u30ab\u30fb\u30c7\u30a3\u30fb\u30e1\u30c3\u30c4\u30a9"
    ],
    "name:kaz_x_preferred":[
        "\u0420\u043e\u043a\u043a\u0430-\u0434\u0438-\u041c\u0435\u0446\u0446\u043e"
    ],
    "name:kor_x_preferred":[
        "\ub85c\uce74\ub514\uba54\ucd08"
    ],
    "name:lat_x_preferred":[
        "Rocca Medii"
    ],
    "name:rus_x_preferred":[
        "\u0420\u043e\u043a\u043a\u0430-\u0434\u0438-\u041c\u0435\u0434\u0437\u043e"
    ],
    "name:srp_x_preferred":[
        "\u0420\u043e\u043a\u0430 \u0434\u0438 \u041c\u0435\u0446\u043e"
    ],
    "name:ukr_x_preferred":[
        "\u0420\u043e\u043a\u043a\u0430-\u0434\u0456-\u041c\u0435\u0446\u0446\u043e"
    ],
    "name:zho_x_preferred":[
        "\u7f57\u5361\u8fea\u6885\u4f50"
    ],
    "wof:name":"Rocca di Mezzo",
    "wof:placetype":"locality",
    "wof:population":70
},
  "geometry": {"coordinates":[13.00978,41.96519],"type":"Point"}
}