{
  "type": "Feature",
  "properties": {
    "gn:admin1_code":"7",
    "gn:admin2_code":"RM",
    "gn:admin3_code":"58040.0",
    "gn:asciiname":"Colle Selva II",
    "gn:country_code":"IT",
    "gn:dem":216,
    "gn:feature_class":"P",
    "gn:feature_code":"PPL",
    "gn:name":"Colle Selva II",
    "gn:population":80,
    "gn:timezone":"Europe/Rome",
    "iso:country":"IT",
    "wof:name":"Colle Selva II",
    "wof:placetype":"locality",
    "wof:population":80
},
  "geometry": {"coordinates":[12.8037,41.87181],"type":"Point"}
}