{
  "type": "Feature",
  "properties": {
    "iso:country":"IT",
    "name:deu_x_preferred":[
        "Pontedecimo"
    ],
    "name:eng_x_preferred":[
        "Pontedecimo"
    ],
    "name:fra_x_preferred":[
        "Pontedecimo"
    ],
    "name:ita_x_preferred":[
        "Pontedecimo"
    ],
    "name:lij_x_preferred":[
        "Ponted\u00eaximo"
    ],
    "name:nld_x_preferred":[
        "Pontedecimo"
    ],
    "name:por_x_preferred":[
        "Pontedecimo"
    ],
    "wof:name":"Pontedecimo",
    "wof:placetype":"neighbourhood"
},
  "geometry": {"coordinates":[8.90339510987974,44.49797690759848],"type":"Point"}
}