{
  "type": "Feature",
  "properties": {
    "gn:admin1_code":"5",
    "gn:admin2_code":"MO",
    "gn:admin3_code":"36015.0",
    "gn:asciiname":"Rodello",
    "gn:country_code":"IT",
    "gn:dem":85,
    "gn:feature_class":"P",
    "gn:feature_code":"PPL",
    "gn:name":"Rodello",
    "gn:population":21,
    "gn:timezone":"Europe/Rome",
    "iso:country":"IT",
    "name:azb_x_preferred":[
        "\u0631\u0648\u062f\u0644\u0648"
    ],
    "name:bel_x_preferred":[
        "\u0420\u043e\u0434\u044d\u043b\u0430"
    ],
    "name:bul_x_preferred":[
        "\u0420\u043e\u0434\u0435\u043b\u043e"
    ],
    "name:ceb_x_preferred":[
        "Rodello"
    ],
    "name:deu_x_preferred":[
        "Rodello"
    ],
    "name:epo_x_preferred":[
        "Rodello"
    ],
    "name:est_x_preferred":[
        "Rodello"
    ],
    "name:eus_x_preferred":[
        "Rodello"
    ],
    "name:fas_x_preferred":[
        "\u0631\u0648\u062f\u0644\u0648"
    ],
    "name:fra_x_preferred":[
        "Rodello"
    ],
    "name:hun_x_preferred":[
        "Rodello"
    ],
    "name:hye_x_preferred":[
        "\u054c\u0578\u0564\u0565\u056c\u056c\u0578"
    ],
    "name:ind_x_preferred":[
        "Rodello"
    ],
    "name:ita_x_preferred":[
        "Rodello"
    ],
    "name:jpn_x_preferred":[
        "\u30ed\u30c7\u30c3\u30ed"
    ],
    "name:kaz_x_preferred":[
        "\u0420\u043e\u0434\u0435\u043b\u043b\u043e"
    ],
    "name:lat_x_preferred":[
        "Rodellum"
    ],
    "name:lmo_x_preferred":[
        "Rodello"
    ],
    "name:msa_x_preferred":[
        "Rodello"
    ],
    "name:nap_x_preferred":[
        "Rodello"
    ],
    "name:nld_x_preferred":[
        "Rodello"
    ],
    "name:pms_x_preferred":[
        "Rodel"
    ],
    "name:pol_x_preferred":[
        "Rodello"
    ],
    "name:por_x_preferred":[
        "Rodello"
    ],
    "name:ron_x_preferred":[
        "Rodello"
    ],
    "name:rus_x_preferred":[
        "\u0420\u043e\u0434\u0435\u043b\u043b\u043e"
    ],
    "name:scn_x_preferred":[
        "Rodello"
    ],
    "name:spa_x_preferred":[
        "Rodello"
    ],
    "name:srp_x_preferred":[
        "\u0420\u043e\u0434\u0435\u043b\u043e"
    ],
    "name:tgl_x_preferred":[
        "Rodello"
    ],
    "name:ukr_x_preferred":[
        "\u0420\u043e\u0434\u0435\u043b\u043b\u043e"
    ],
    "name:uzb_x_preferred":[
        "Rodello"
    ],
    "name:vie_x_preferred":[
        "Rodello"
    ],
    "name:vol_x_preferred":[
        "Rodello"
    ],
    "name:war_x_preferred":[
        "Rodello"
    ],
    "name:zho_x_preferred":[
        "\u7f57\u5fb7\u6d1b"
    ],
    "wof:name":"Rodello",
    "wof:placetype":"locality",
    "wof:population":21
},
  "geometry": {"coordinates":[10.81263,44.58189],"type":"Point"}
}