{
  "type": "Feature",
  "properties": {
    "gn:admin1_code":"9.0",
    "gn:admin2_code":"SO",
    "gn:admin3_code":"14069.0",
    "gn:asciiname":"Moncucco Alto",
    "gn:country_code":"IT",
    "gn:dem":441,
    "gn:feature_class":"P",
    "gn:feature_code":"PPL",
    "gn:name":"Moncucco Alto",
    "gn:population":0,
    "gn:timezone":"Europe/Rome",
    "iso:country":"IT",
    "wof:name":"Moncucco Alto",
    "wof:placetype":"locality"
},
  "geometry": {"coordinates":[9.51951,46.15482],"type":"Point"}
}