{
  "type": "Feature",
  "properties": {
    "gn:admin1_code":"7",
    "gn:admin2_code":"RM",
    "gn:admin3_code":"58120.0",
    "gn:asciiname":"Centro delle Cavalle",
    "gn:country_code":"IT",
    "gn:dem":28,
    "gn:feature_class":"P",
    "gn:feature_code":"PPL",
    "gn:name":"Centro delle Cavalle",
    "gn:population":18,
    "gn:timezone":"Europe/Rome",
    "iso:country":"IT",
    "wof:name":"Centro delle Cavalle",
    "wof:placetype":"locality",
    "wof:population":18
},
  "geometry": {"coordinates":[12.23053,41.89763],"type":"Point"}
}