{
  "type": "Feature",
  "properties": {
    "gn:admin1_code":"5",
    "gn:admin2_code":"PC",
    "gn:admin3_code":"33035.0",
    "gn:asciiname":"San Rocco di Sopra",
    "gn:country_code":"IT",
    "gn:dem":107,
    "gn:feature_class":"P",
    "gn:feature_code":"PPL",
    "gn:name":"San Rocco di Sopra",
    "gn:population":21,
    "gn:timezone":"Europe/Rome",
    "iso:country":"IT",
    "wof:name":"San Rocco di Sopra",
    "wof:placetype":"locality",
    "wof:population":21
},
  "geometry": {"coordinates":[9.7158,44.95393],"type":"Point"}
}