{
  "type": "Feature",
  "properties": {
    "gn:admin1_code":"20.0",
    "gn:admin2_code":"RO",
    "gn:admin3_code":"29002.0",
    "gn:asciiname":"Le Tombe",
    "gn:country_code":"IT",
    "gn:dem":-4,
    "gn:feature_class":"P",
    "gn:feature_code":"PPL",
    "gn:name":"Le Tombe",
    "gn:population":0,
    "gn:timezone":"Europe/Rome",
    "iso:country":"IT",
    "wof:name":"Le Tombe",
    "wof:placetype":"locality"
},
  "geometry": {"coordinates":[12.16083,44.975],"type":"Point"}
}