{
  "type": "Feature",
  "properties": {
    "gn:admin1_code":"6",
    "gn:admin2_code":"PN",
    "gn:admin3_code":"93030.0",
    "gn:asciiname":"Campeis",
    "gn:country_code":"IT",
    "gn:dem":172,
    "gn:feature_class":"P",
    "gn:feature_code":"PPL",
    "gn:name":"Campeis",
    "gn:population":62,
    "gn:timezone":"Europe/Rome",
    "iso:country":"IT",
    "wof:name":"Campeis",
    "wof:placetype":"locality",
    "wof:population":62
},
  "geometry": {"coordinates":[12.95048,46.19254],"type":"Point"}
}