{
  "type": "Feature",
  "properties": {
    "gn:admin1_code":"12",
    "gn:admin2_code":"AL",
    "gn:admin3_code":"6159.0",
    "gn:asciiname":"San Iorio",
    "gn:country_code":"IT",
    "gn:dem":168,
    "gn:feature_class":"P",
    "gn:feature_code":"PPL",
    "gn:name":"San Iorio",
    "gn:population":43,
    "gn:timezone":"Europe/Rome",
    "iso:country":"IT",
    "wof:name":"San Iorio",
    "wof:placetype":"locality",
    "wof:population":43
},
  "geometry": {"coordinates":[8.30159,45.10212],"type":"Point"}
}