{
  "type": "Feature",
  "properties": {
    "gn:admin1_code":"20",
    "gn:admin2_code":"VI",
    "gn:admin3_code":"24048.0",
    "gn:asciiname":"Parigi",
    "gn:country_code":"IT",
    "gn:dem":115,
    "gn:feature_class":"P",
    "gn:feature_code":"PPL",
    "gn:name":"Parigi",
    "gn:population":31,
    "gn:timezone":"Europe/Rome",
    "iso:country":"IT",
    "wof:name":"Parigi",
    "wof:placetype":"locality",
    "wof:population":31
},
  "geometry": {"coordinates":[11.41584,45.62504000000001],"type":"Point"}
}