{
  "type": "Feature",
  "properties": {
    "gn:admin1_code":"20",
    "gn:admin2_code":"VR",
    "gn:admin3_code":"23073.0",
    "gn:asciiname":"Ca' del Ferro",
    "gn:country_code":"IT",
    "gn:dem":30,
    "gn:feature_class":"P",
    "gn:feature_code":"PPL",
    "gn:name":"Ca' del Ferro",
    "gn:population":19,
    "gn:timezone":"Europe/Rome",
    "iso:country":"IT",
    "wof:name":"Ca' del Ferro",
    "wof:placetype":"locality",
    "wof:population":19
},
  "geometry": {"coordinates":[11.11908,45.39131],"type":"Point"}
}