{
  "type": "Feature",
  "properties": {
    "gn:admin1_code":"4",
    "gn:admin2_code":"SA",
    "gn:admin3_code":"65012.0",
    "gn:asciiname":"Tempe di Lizzi",
    "gn:country_code":"IT",
    "gn:dem":421,
    "gn:feature_class":"P",
    "gn:feature_code":"PPL",
    "gn:name":"Tempe di Lizzi",
    "gn:population":73,
    "gn:timezone":"Europe/Rome",
    "iso:country":"IT",
    "wof:name":"Tempe di Lizzi",
    "wof:placetype":"locality",
    "wof:population":73
},
  "geometry": {"coordinates":[15.41194,40.59624],"type":"Point"}
}