{
  "type": "Feature",
  "properties": {
    "gn:admin1_code":"18",
    "gn:admin2_code":"PG",
    "gn:admin3_code":"54013.0",
    "gn:asciiname":"Volterrano",
    "gn:country_code":"IT",
    "gn:dem":316,
    "gn:feature_class":"P",
    "gn:feature_code":"PPL",
    "gn:name":"Volterrano",
    "gn:population":76,
    "gn:timezone":"Europe/Rome",
    "iso:country":"IT",
    "wof:name":"Volterrano",
    "wof:placetype":"locality",
    "wof:population":76
},
  "geometry": {"coordinates":[12.0915,43.36956],"type":"Point"}
}