{
  "type": "Feature",
  "properties": {
    "gn:admin1_code":"5.0",
    "gn:admin2_code":"RN",
    "gn:admin3_code":"99028.0",
    "gn:asciiname":"Montebello",
    "gn:country_code":"IT",
    "gn:dem":407,
    "gn:feature_class":"P",
    "gn:feature_code":"PPL",
    "gn:name":"Montebello",
    "gn:population":36,
    "gn:timezone":"Europe/Rome",
    "iso:country":"IT",
    "name:bul_x_preferred":[
        "\u041c\u043e\u043d\u0442\u0435\u0431\u0435\u043b\u043e"
    ],
    "name:cat_x_preferred":[
        "Montebello"
    ],
    "name:ceb_x_preferred":[
        "Montebello"
    ],
    "name:deu_x_preferred":[
        "Montebello"
    ],
    "name:fas_x_preferred":[
        "\u0645\u0648\u0646\u062a\u0647\u200c\u0628\u0644\u0648"
    ],
    "name:fra_x_preferred":[
        "Montebello"
    ],
    "name:ita_x_preferred":[
        "Montebello"
    ],
    "name:jpn_x_preferred":[
        "\u30e2\u30f3\u30c6\u30d9\u30ed"
    ],
    "name:kor_x_preferred":[
        "\ubaac\ud14c\ubca8\ub85c"
    ],
    "name:nld_x_preferred":[
        "Montebello"
    ],
    "name:nor_x_preferred":[
        "Montebello"
    ],
    "name:pol_x_preferred":[
        "Montebello"
    ],
    "name:por_x_preferred":[
        "Montebello"
    ],
    "name:rus_x_preferred":[
        "\u041c\u043e\u043d\u0442\u0435\u0431\u0435\u043b\u043b\u043e"
    ],
    "name:spa_x_preferred":[
        "Montebello"
    ],
    "name:srp_x_preferred":[
        "\u041c\u043e\u043d\u0442\u0435\u0431\u0435\u043b\u043e"
    ],
    "name:swe_x_preferred":[
        "Montebello"
    ],
    "name:ukr_x_preferred":[
        "\u041c\u043e\u043d\u0442\u0435\u0431\u0435\u043b\u043b\u043e"
    ],
    "name:vie_x_preferred":[
        "Montebello"
    ],
    "name:vol_x_preferred":[
        "Montebello"
    ],
    "name:war_x_preferred":[
        "Montebello"
    ],
    "wof:name":"Montebello",
    "wof:placetype":"locality",
    "wof:population":36
},
  "geometry": {"coordinates":[12.36756,43.97054],"type":"Point"}
}