{
  "type": "Feature",
  "properties": {
    "gn:admin1_code":"4",
    "gn:admin2_code":"BN",
    "gn:admin3_code":"62008.0",
    "gn:asciiname":"Sant'Angelo di Sotto",
    "gn:country_code":"IT",
    "gn:dem":134,
    "gn:feature_class":"P",
    "gn:feature_code":"PPL",
    "gn:name":"Sant'Angelo di Sotto",
    "gn:population":33,
    "gn:timezone":"Europe/Rome",
    "iso:country":"IT",
    "wof:name":"Sant'Angelo di Sotto",
    "wof:placetype":"locality",
    "wof:population":33
},
  "geometry": {"coordinates":[14.74912,41.14136],"type":"Point"}
}