{
  "type": "Feature",
  "properties": {
    "gn:admin1_code":"9.0",
    "gn:admin2_code":"SO",
    "gn:admin3_code":"14050.0",
    "gn:asciiname":"Gualdo",
    "gn:country_code":"IT",
    "gn:dem":1927,
    "gn:feature_class":"P",
    "gn:feature_code":"PPL",
    "gn:name":"Gualdo",
    "gn:population":0,
    "gn:timezone":"Europe/Rome",
    "iso:country":"IT",
    "name:ceb_x_preferred":[
        "Gualdo"
    ],
    "name:deu_x_preferred":[
        "Gualdo"
    ],
    "name:ita_x_preferred":[
        "Gualdo"
    ],
    "name:lat_x_preferred":[
        "Gualdum"
    ],
    "name:srp_x_preferred":[
        "Gvaldo"
    ],
    "name:swe_x_preferred":[
        "Gualdo"
    ],
    "wof:name":"Gualdo",
    "wof:placetype":"locality"
},
  "geometry": {"coordinates":[9.45,46.48333],"type":"Point"}
}