{
  "type": "Feature",
  "properties": {
    "gn:admin1_code":"7",
    "gn:admin2_code":"RM",
    "gn:admin3_code":"58003.0",
    "gn:asciiname":"Sardilli",
    "gn:country_code":"IT",
    "gn:dem":209,
    "gn:feature_class":"P",
    "gn:feature_code":"PPL",
    "gn:name":"Sardilli",
    "gn:population":49,
    "gn:timezone":"Europe/Rome",
    "iso:country":"IT",
    "wof:name":"Sardilli",
    "wof:placetype":"locality",
    "wof:population":49
},
  "geometry": {"coordinates":[12.63638,41.70038],"type":"Point"}
}