{
  "type": "Feature",
  "properties": {
    "gn:admin1_code":"7.0",
    "gn:admin2_code":"FR",
    "gn:admin3_code":"60024.0",
    "gn:asciiname":"Farneta",
    "gn:country_code":"IT",
    "gn:dem":167,
    "gn:feature_class":"P",
    "gn:feature_code":"PPL",
    "gn:name":"Farneta",
    "gn:population":843,
    "gn:timezone":"Europe/Rome",
    "iso:country":"IT",
    "name:ceb_x_preferred":[
        "Farneta"
    ],
    "name:fas_x_preferred":[
        "\u0641\u0627\u0631\u0646\u062a\u0627"
    ],
    "name:ita_x_preferred":[
        "Farneta"
    ],
    "name:srp_x_preferred":[
        "\u0424\u0430\u0440\u043d\u0435\u0442\u0430"
    ],
    "wof:name":"Farneta",
    "wof:placetype":"locality",
    "wof:population":843
},
  "geometry": {"coordinates":[13.35755,41.56184],"type":"Point"}
}