{
  "type": "Feature",
  "properties": {
    "gn:gn_country":"IT",
    "gn:gn_fcode":"PPLA3",
    "gn:gn_pop":356,
    "gn:population":373,
    "iso:country":"IT",
    "name:bel_x_preferred":[
        "\u041c\u0430\u043b\u043e\u0441\u043a\u0430"
    ],
    "name:cat_x_preferred":[
        "Malosco"
    ],
    "name:deu_x_preferred":[
        "Malosco"
    ],
    "name:eng_x_preferred":[
        "Malosco"
    ],
    "name:epo_x_preferred":[
        "Malosco"
    ],
    "name:eus_x_preferred":[
        "Malosco"
    ],
    "name:fas_x_preferred":[
        "\u0645\u0627\u0644\u0648\u0633\u06a9\u0648"
    ],
    "name:fra_x_preferred":[
        "Malosco"
    ],
    "name:hun_x_preferred":[
        "Malosco"
    ],
    "name:hye_x_preferred":[
        "\u0544\u0561\u056c\u0578\u057d\u056f\u0578"
    ],
    "name:ind_x_preferred":[
        "Malosco"
    ],
    "name:ita_x_preferred":[
        "Malosco"
    ],
    "name:jpn_x_preferred":[
        "\u30de\u30ed\u30b9\u30b3"
    ],
    "name:kaz_x_preferred":[
        "\u041c\u0430\u043b\u043e\u0441\u043a\u043e"
    ],
    "name:lat_x_preferred":[
        "Maluscum"
    ],
    "name:lmo_x_preferred":[
        "Malosco"
    ],
    "name:msa_x_preferred":[
        "Malosco"
    ],
    "name:nap_x_preferred":[
        "Malosco"
    ],
    "name:nld_x_preferred":[
        "Malosco"
    ],
    "name:pms_x_preferred":[
        "Malosco"
    ],
    "name:pol_x_preferred":[
        "Malosco"
    ],
    "name:por_x_preferred":[
        "Malosco"
    ],
    "name:ron_x_preferred":[
        "Malosco"
    ],
    "name:rus_x_preferred":[
        "\u041c\u0430\u043b\u043e\u0441\u043a\u043e"
    ],
    "name:scn_x_preferred":[
        "Malosco"
    ],
    "name:spa_x_preferred":[
        "Malosco"
    ],
    "name:srp_x_preferred":[
        "Malosco"
    ],
    "name:tgl_x_preferred":[
        "Malosco"
    ],
    "name:ukr_x_preferred":[
        "\u041c\u0430\u043b\u043e\u0441\u043a\u043e"
    ],
    "name:uzb_x_preferred":[
        "Malosco"
    ],
    "name:vol_x_preferred":[
        "Malosco"
    ],
    "name:war_x_preferred":[
        "Malosco"
    ],
    "name:zho_x_preferred":[
        "\u9a6c\u6d1b\u65af\u79d1"
    ],
    "qs_pg:aaroncc":"IT",
    "qs_pg:gn_country":"IT",
    "qs_pg:gn_fcode":"PPLA3",
    "qs_pg:gn_pop":356,
    "qs_pg:name":"Malosco",
    "qs_pg:name_adm0":"Italia",
    "qs_pg:name_adm1":"Trentino-Alto Adige",
    "qs_pg:photos":50,
    "qs_pg:photos_1k":10,
    "qs_pg:photos_9k":1,
    "qs_pg:photos_9r":2,
    "qs_pg:photos_all":50,
    "qs_pg:photos_sr":2,
    "qs_pg:pop_sr":2,
    "qs_pg:qs_pg_placetype":"locality",
    "qs_pg:qs_pg_placetype_gp":"Town",
    "qs_pg:woe_adm0":23424853,
    "woe:adm0_id":23424853,
    "woe:name_adm0":"Italia",
    "woe:name_adm1":"Trentino-Alto Adige",
    "woe:placetype":"Town",
    "wof:name":"Malosco",
    "wof:placetype":"locality",
    "wof:population":373
},
  "geometry": {"coordinates":[11.14627,46.43611],"type":"Point"}
}