{
  "type": "Feature",
  "properties": {
    "gn:admin1_code":"4",
    "gn:admin2_code":"CE",
    "gn:admin3_code":"61050.0",
    "gn:asciiname":"Tuorofunaro",
    "gn:country_code":"IT",
    "gn:dem":344,
    "gn:feature_class":"P",
    "gn:feature_code":"PPL",
    "gn:name":"Tuorofunaro",
    "gn:population":115,
    "gn:timezone":"Europe/Rome",
    "iso:country":"IT",
    "wof:name":"Tuorofunaro",
    "wof:placetype":"locality",
    "wof:population":115
},
  "geometry": {"coordinates":[14.03538,41.30945],"type":"Point"}
}