{
  "type": "Feature",
  "properties": {
    "gn:admin1_code":"12.0",
    "gn:admin2_code":"AL",
    "gn:admin3_code":"6014.0",
    "gn:asciiname":"Santo Criste",
    "gn:country_code":"IT",
    "gn:dem":242,
    "gn:feature_class":"P",
    "gn:feature_code":"PPLL",
    "gn:name":"Santo Criste",
    "gn:population":0,
    "gn:timezone":"Europe/Rome",
    "iso:country":"IT",
    "wof:name":"Santo Criste",
    "wof:placetype":"locality"
},
  "geometry": {"coordinates":[8.66441,44.5865],"type":"Point"}
}