{
  "type": "Feature",
  "properties": {
    "gn:admin1_code":"12",
    "gn:admin2_code":"AT",
    "gn:admin3_code":"5005.0",
    "gn:asciiname":"Ca dei Coppi",
    "gn:country_code":"IT",
    "gn:dem":128,
    "gn:feature_class":"P",
    "gn:feature_code":"PPL",
    "gn:name":"C\u00e0 dei Coppi",
    "gn:population":44,
    "gn:timezone":"Europe/Rome",
    "iso:country":"IT",
    "name:und_x_variant":[
        "C\u00e0 dei Coppi"
    ],
    "wof:name":"Ca dei Coppi",
    "wof:placetype":"locality",
    "wof:population":44
},
  "geometry": {"coordinates":[8.22297,44.94288],"type":"Point"}
}