{
  "type": "Feature",
  "properties": {
    "gn:admin1_code":"20",
    "gn:admin2_code":"VI",
    "gn:admin3_code":"24034.0",
    "gn:asciiname":"Cracchi",
    "gn:country_code":"IT",
    "gn:dem":187,
    "gn:feature_class":"P",
    "gn:feature_code":"PPL",
    "gn:name":"Cracchi",
    "gn:population":26,
    "gn:timezone":"Europe/Rome",
    "iso:country":"IT",
    "wof:name":"Cracchi",
    "wof:placetype":"locality",
    "wof:population":26
},
  "geometry": {"coordinates":[11.38843,45.61033],"type":"Point"}
}