{
  "type": "Feature",
  "properties": {
    "gn:admin1_code":"20",
    "gn:admin2_code":"VI",
    "gn:admin3_code":"24035.0",
    "gn:asciiname":"Pignare",
    "gn:country_code":"IT",
    "gn:dem":137,
    "gn:feature_class":"P",
    "gn:feature_code":"PPL",
    "gn:name":"Pignare",
    "gn:population":153,
    "gn:timezone":"Europe/Rome",
    "iso:country":"IT",
    "wof:name":"Pignare",
    "wof:placetype":"locality",
    "wof:population":153
},
  "geometry": {"coordinates":[11.4748,45.58278],"type":"Point"}
}