{
  "type": "Feature",
  "properties": {
    "gn:admin1_code":"8",
    "gn:admin2_code":"SP",
    "gn:admin3_code":"11022.0",
    "gn:asciiname":"Terrizzo",
    "gn:country_code":"IT",
    "gn:dem":51,
    "gn:feature_class":"P",
    "gn:feature_code":"PPL",
    "gn:name":"Terrizzo",
    "gn:population":55,
    "gn:timezone":"Europe/Rome",
    "iso:country":"IT",
    "wof:name":"Terrizzo",
    "wof:placetype":"locality",
    "wof:population":55
},
  "geometry": {"coordinates":[9.84871,44.04847],"type":"Point"}
}