{
  "type": "Feature",
  "properties": {
    "gn:country":"IT",
    "gn:fcode":"PPL",
    "gn:population":0,
    "iso:country":"IT",
    "name:und_x_variant":[
        "Towregaia"
    ],
    "qs_pg:aaroncc":"IT",
    "qs_pg:gn_country":"IT",
    "qs_pg:gn_fcode":"PPL",
    "qs_pg:gn_pop":0,
    "qs_pg:name":"Torre Gaia",
    "qs_pg:name_adm0":"Italia",
    "qs_pg:name_adm1":"Lazio",
    "qs_pg:photos":477,
    "qs_pg:photos_1k":97,
    "qs_pg:photos_9k":2,
    "qs_pg:photos_9r":5,
    "qs_pg:photos_all":477,
    "qs_pg:photos_sr":7,
    "qs_pg:pop_sr":0,
    "qs_pg:qs_pg_placetype":"locality",
    "qs_pg:qs_pg_placetype_gp":"Town",
    "qs_pg:woe_adm0":23424853,
    "woe:adm0_id":23424853,
    "woe:name_adm0":"Italia",
    "woe:name_adm1":"Lazio",
    "woe:placetype":"Town",
    "wof:name":"Torre Gaia",
    "wof:placetype":"locality"
},
  "geometry": {"coordinates":[12.64093,41.8563],"type":"Point"}
}