{
  "type": "Feature",
  "properties": {
    "gn:admin1_code":"2.0",
    "gn:admin2_code":"MT",
    "gn:admin3_code":"77007.0",
    "gn:asciiname":"Craco Peschiera",
    "gn:country_code":"IT",
    "gn:dem":83,
    "gn:feature_class":"P",
    "gn:feature_code":"PPL",
    "gn:name":"Craco Peschiera",
    "gn:population":642,
    "gn:timezone":"Europe/Rome",
    "iso:country":"IT",
    "wof:name":"Craco Peschiera",
    "wof:placetype":"locality",
    "wof:population":642
},
  "geometry": {"coordinates":[16.49635,40.35905],"type":"Point"}
}