{
  "type": "Feature",
  "properties": {
    "gn:admin1_code":"19",
    "gn:admin2_code":"AO",
    "gn:admin3_code":"7010.0",
    "gn:asciiname":"Moulin",
    "gn:country_code":"IT",
    "gn:dem":1585,
    "gn:feature_class":"P",
    "gn:feature_code":"PPL",
    "gn:name":"Moulin",
    "gn:population":17,
    "gn:timezone":"Europe/Rome",
    "iso:country":"IT",
    "wof:name":"Moulin",
    "wof:placetype":"locality",
    "wof:population":17
},
  "geometry": {"coordinates":[7.40739,45.86877],"type":"Point"}
}