{
  "type": "Feature",
  "properties": {
    "gn:admin1_code":"20",
    "gn:admin2_code":"BL",
    "gn:admin3_code":"25021.0",
    "gn:asciiname":"Zermen",
    "gn:country_code":"IT",
    "gn:dem":358,
    "gn:feature_class":"P",
    "gn:feature_code":"PPL",
    "gn:name":"Zermen",
    "gn:population":279,
    "gn:timezone":"Europe/Rome",
    "iso:country":"IT",
    "wof:name":"Zermen",
    "wof:placetype":"locality",
    "wof:population":279
},
  "geometry": {"coordinates":[11.94413,46.02403],"type":"Point"}
}