{
  "type": "Feature",
  "properties": {
    "gn:admin1_code":"20",
    "gn:admin2_code":"VI",
    "gn:admin3_code":"24111.0",
    "gn:asciiname":"Pozza",
    "gn:country_code":"IT",
    "gn:dem":656,
    "gn:feature_class":"P",
    "gn:feature_code":"PPL",
    "gn:name":"Pozza",
    "gn:population":24,
    "gn:timezone":"Europe/Rome",
    "iso:country":"IT",
    "wof:name":"Pozza",
    "wof:placetype":"locality",
    "wof:population":24
},
  "geometry": {"coordinates":[11.25197,45.64936],"type":"Point"}
}