{
  "type": "Feature",
  "properties": {
    "gn:admin1_code":"1",
    "gn:admin2_code":"CH",
    "gn:admin3_code":"69100.0",
    "gn:asciiname":"Di Tullio",
    "gn:country_code":"IT",
    "gn:dem":130,
    "gn:feature_class":"P",
    "gn:feature_code":"PPL",
    "gn:name":"Di Tullio",
    "gn:population":37,
    "gn:timezone":"Europe/Rome",
    "iso:country":"IT",
    "wof:name":"Di Tullio",
    "wof:placetype":"locality",
    "wof:population":37
},
  "geometry": {"coordinates":[14.58264,42.1773],"type":"Point"}
}