{
  "type": "Feature",
  "properties": {
    "gn:admin1_code":"9",
    "gn:admin2_code":"BS",
    "gn:admin3_code":"17077.0",
    "gn:asciiname":"Soseto",
    "gn:country_code":"IT",
    "gn:dem":251,
    "gn:feature_class":"P",
    "gn:feature_code":"PPL",
    "gn:name":"Soseto",
    "gn:population":327,
    "gn:timezone":"Europe/Rome",
    "iso:country":"IT",
    "wof:name":"Soseto",
    "wof:placetype":"locality",
    "wof:population":327
},
  "geometry": {"coordinates":[10.42191,45.60307],"type":"Point"}
}