{
  "type": "Feature",
  "properties": {
    "gn:admin1_code":"3",
    "gn:admin2_code":"CS",
    "gn:admin3_code":"78148.0",
    "gn:asciiname":"Sant'Andrea",
    "gn:country_code":"IT",
    "gn:dem":78,
    "gn:feature_class":"P",
    "gn:feature_code":"PPL",
    "gn:name":"Sant'Andrea",
    "gn:population":36,
    "gn:timezone":"Europe/Rome",
    "iso:country":"IT",
    "wof:name":"Sant'Andrea",
    "wof:placetype":"locality",
    "wof:population":36
},
  "geometry": {"coordinates":[16.21792,39.53086],"type":"Point"}
}