{
  "type": "Feature",
  "properties": {
    "gn:admin1_code":"20.0",
    "gn:admin2_code":"PD",
    "gn:admin3_code":"28099.0",
    "gn:asciiname":"Busiago",
    "gn:country_code":"IT",
    "gn:dem":14,
    "gn:feature_class":"P",
    "gn:feature_code":"PPL",
    "gn:name":"Busiago",
    "gn:population":126,
    "gn:timezone":"Europe/Rome",
    "iso:country":"IT",
    "wof:name":"Busiago",
    "wof:placetype":"locality",
    "wof:population":126
},
  "geometry": {"coordinates":[11.87135,45.48277],"type":"Point"}
}