{
  "type": "Feature",
  "properties": {
    "gn:admin1_code":"20.0",
    "gn:admin2_code":"BL",
    "gn:admin3_code":"25006.0",
    "gn:asciiname":"Tisoi",
    "gn:country_code":"IT",
    "gn:dem":567,
    "gn:elevation":"559.0",
    "gn:feature_class":"P",
    "gn:feature_code":"PPL",
    "gn:name":"Tisoi",
    "gn:population":363,
    "gn:timezone":"Europe/Rome",
    "iso:country":"IT",
    "wof:name":"Tisoi",
    "wof:placetype":"locality",
    "wof:population":363
},
  "geometry": {"coordinates":[12.16908,46.16366],"type":"Point"}
}