{
  "type": "Feature",
  "properties": {
    "gn:admin1_code":"17",
    "gn:admin2_code":"TN",
    "gn:admin3_code":"22139.0",
    "gn:asciiname":"Roncogno",
    "gn:country_code":"IT",
    "gn:dem":473,
    "gn:feature_class":"P",
    "gn:feature_code":"PPL",
    "gn:name":"Roncogno",
    "gn:population":293,
    "gn:timezone":"Europe/Rome",
    "iso:country":"IT",
    "wof:name":"Roncogno",
    "wof:placetype":"locality",
    "wof:population":293
},
  "geometry": {"coordinates":[11.20642,46.06915],"type":"Point"}
}