{
  "type": "Feature",
  "properties": {
    "gn:admin1_code":"6",
    "gn:admin2_code":"UD",
    "gn:admin3_code":"30032.0",
    "gn:asciiname":"Borgata Mezzoli",
    "gn:country_code":"IT",
    "gn:dem":113,
    "gn:feature_class":"P",
    "gn:feature_code":"PPL",
    "gn:name":"Borgata Mezzoli",
    "gn:population":28,
    "gn:timezone":"Europe/Rome",
    "iso:country":"IT",
    "wof:name":"Borgata Mezzoli",
    "wof:placetype":"locality",
    "wof:population":28
},
  "geometry": {"coordinates":[12.94124,46.09116],"type":"Point"}
}