{
  "type": "Feature",
  "properties": {
    "gn:admin1_code":"4.0",
    "gn:admin2_code":"AV",
    "gn:admin3_code":"64008.0",
    "gn:asciiname":"Selve",
    "gn:country_code":"IT",
    "gn:dem":431,
    "gn:feature_class":"P",
    "gn:feature_code":"PPL",
    "gn:name":"Selve",
    "gn:population":46,
    "gn:timezone":"Europe/Rome",
    "iso:country":"IT",
    "name:deu_x_preferred":[
        "Selve"
    ],
    "name:fin_x_preferred":[
        "Selve"
    ],
    "name:fra_x_preferred":[
        "Selve Automobilwerke"
    ],
    "name:ita_x_preferred":[
        "Selve Automobilwerke"
    ],
    "name:swe_x_preferred":[
        "Selve Automobilwerke"
    ],
    "name:ukr_x_preferred":[
        "Selve"
    ],
    "wof:name":"Selve",
    "wof:placetype":"locality",
    "wof:population":46
},
  "geometry": {"coordinates":[14.78149,40.89996],"type":"Point"}
}