{
  "type": "Feature",
  "properties": {
    "gn:admin1_code":"20.0",
    "gn:admin2_code":"VR",
    "gn:admin3_code":"23064.0",
    "gn:asciiname":"Tombazosana",
    "gn:country_code":"IT",
    "gn:dem":19,
    "gn:feature_class":"P",
    "gn:feature_code":"PPL",
    "gn:name":"Tombazosana",
    "gn:population":586,
    "gn:timezone":"Europe/Rome",
    "iso:country":"IT",
    "wof:name":"Tombazosana",
    "wof:placetype":"locality",
    "wof:population":586
},
  "geometry": {"coordinates":[11.25667,45.31477],"type":"Point"}
}