{
  "type": "Feature",
  "properties": {
    "gn:admin1_code":"17.0",
    "gn:admin2_code":"TN",
    "gn:admin3_code":"22248.0",
    "gn:asciiname":"Covelo",
    "gn:country_code":"IT",
    "gn:dem":538,
    "gn:elevation":"548.0",
    "gn:feature_class":"P",
    "gn:feature_code":"PPL",
    "gn:name":"Covelo",
    "gn:population":361,
    "gn:timezone":"Europe/Rome",
    "iso:country":"IT",
    "name:ceb_x_preferred":[
        "Covelo"
    ],
    "name:deu_x_preferred":[
        "Covelo"
    ],
    "name:fra_x_preferred":[
        "Covelo"
    ],
    "name:glg_x_preferred":[
        "Covelo"
    ],
    "name:ita_x_preferred":[
        "Covelo"
    ],
    "name:nld_x_preferred":[
        "Covelo"
    ],
    "name:por_x_preferred":[
        "Covelo"
    ],
    "name:srp_x_preferred":[
        "Covelo"
    ],
    "name:swe_x_preferred":[
        "Covelo"
    ],
    "name:tur_x_preferred":[
        "Covelo"
    ],
    "name:ukr_x_preferred":[
        "\u041a\u043e\u0432\u0435\u043b\u0443"
    ],
    "wof:name":"Covelo",
    "wof:placetype":"locality",
    "wof:population":361
},
  "geometry": {"coordinates":[11.02152,46.09871],"type":"Point"}
}