{
  "type": "Feature",
  "properties": {
    "gn:admin1_code":"5",
    "gn:admin2_code":"BO",
    "gn:admin3_code":"37062.0",
    "gn:asciiname":"La Piazza",
    "gn:country_code":"IT",
    "gn:dem":572,
    "gn:feature_class":"P",
    "gn:feature_code":"PPL",
    "gn:name":"La Piazza",
    "gn:population":50,
    "gn:timezone":"Europe/Rome",
    "iso:country":"IT",
    "wof:name":"La Piazza",
    "wof:placetype":"locality",
    "wof:population":50
},
  "geometry": {"coordinates":[10.94596,44.1521],"type":"Point"}
}