{
  "type": "Feature",
  "properties": {
    "gn:admin1_code":"20",
    "gn:admin2_code":"PD",
    "gn:admin3_code":"28035.0",
    "gn:asciiname":"Mira Bassa",
    "gn:country_code":"IT",
    "gn:dem":0,
    "gn:feature_class":"P",
    "gn:feature_code":"PPL",
    "gn:name":"Mira Bassa",
    "gn:population":21,
    "gn:timezone":"Europe/Rome",
    "iso:country":"IT",
    "wof:name":"Mira Bassa",
    "wof:placetype":"locality",
    "wof:population":21
},
  "geometry": {"coordinates":[12.1517,45.19896],"type":"Point"}
}