{
  "type": "Feature",
  "properties": {
    "gn:admin1_code":"12.0",
    "gn:admin2_code":"AT",
    "gn:admin3_code":"5022.0",
    "gn:asciiname":"Area Produttiva Valle Tanaro",
    "gn:country_code":"IT",
    "gn:dem":138,
    "gn:feature_class":"P",
    "gn:feature_code":"PPL",
    "gn:name":"Area Produttiva Valle Tanaro",
    "gn:population":0,
    "gn:timezone":"Europe/Rome",
    "iso:country":"IT",
    "wof:name":"Area Produttiva Valle Tanaro",
    "wof:placetype":"locality"
},
  "geometry": {"coordinates":[8.12969,44.77798],"type":"Point"}
}