{
  "type": "Feature",
  "properties": {
    "gn:admin1_code":"5",
    "gn:admin2_code":"RA",
    "gn:admin3_code":"39007.0",
    "gn:asciiname":"Tantlon",
    "gn:country_code":"IT",
    "gn:dem":0,
    "gn:feature_class":"P",
    "gn:feature_code":"PPL",
    "gn:name":"Tantlon",
    "gn:population":220,
    "gn:timezone":"Europe/Rome",
    "iso:country":"IT",
    "wof:name":"Tantlon",
    "wof:placetype":"locality",
    "wof:population":220
},
  "geometry": {"coordinates":[12.29567,44.25562],"type":"Point"}
}