{
  "type": "Feature",
  "properties": {
    "gn:admin1_code":"8",
    "gn:admin2_code":"SP",
    "gn:admin3_code":"11018.0",
    "gn:asciiname":"Ossegna",
    "gn:country_code":"IT",
    "gn:dem":568,
    "gn:feature_class":"P",
    "gn:feature_code":"PPL",
    "gn:name":"Ossegna",
    "gn:population":50,
    "gn:timezone":"Europe/Rome",
    "iso:country":"IT",
    "wof:name":"Ossegna",
    "wof:placetype":"locality",
    "wof:population":50
},
  "geometry": {"coordinates":[9.55669,44.35715],"type":"Point"}
}