{
  "type": "Feature",
  "properties": {
    "gn:admin1_code":"5.0",
    "gn:admin2_code":"RA",
    "gn:admin3_code":"39014.0",
    "gn:asciiname":"Romea Vecchia",
    "gn:country_code":"IT",
    "gn:dem":0,
    "gn:feature_class":"P",
    "gn:feature_code":"PPL",
    "gn:name":"Romea Vecchia",
    "gn:population":875,
    "gn:timezone":"Europe/Rome",
    "iso:country":"IT",
    "wof:name":"Romea Vecchia",
    "wof:placetype":"locality",
    "wof:population":875
},
  "geometry": {"coordinates":[12.23253,44.38911],"type":"Point"}
}