{
  "type": "Feature",
  "properties": {
    "gn:admin1_code":"4.0",
    "gn:admin2_code":"SA",
    "gn:admin3_code":"65119.0",
    "gn:asciiname":"Strazzari",
    "gn:country_code":"IT",
    "gn:dem":30,
    "gn:feature_class":"P",
    "gn:feature_code":"PPLL",
    "gn:name":"Strazzari",
    "gn:population":2,
    "gn:timezone":"Europe/Rome",
    "iso:country":"IT",
    "wof:name":"Strazzari",
    "wof:placetype":"locality",
    "wof:population":2
},
  "geometry": {"coordinates":[15.48179,40.09166],"type":"Point"}
}