{
  "type": "Feature",
  "properties": {
    "gn:admin1_code":"9.0",
    "gn:admin2_code":"BS",
    "gn:admin3_code":"17163.0",
    "gn:asciiname":"Bettolino",
    "gn:country_code":"IT",
    "gn:dem":161,
    "gn:feature_class":"P",
    "gn:feature_code":"PPL",
    "gn:name":"Bettolino",
    "gn:population":397,
    "gn:timezone":"Europe/Rome",
    "iso:country":"IT",
    "wof:name":"Bettolino",
    "wof:placetype":"locality",
    "wof:population":397
},
  "geometry": {"coordinates":[10.11054,45.58176],"type":"Point"}
}