{
  "type": "Feature",
  "properties": {
    "gn:admin1_code":"16.0",
    "gn:admin2_code":"LI",
    "gn:admin3_code":"49010.0",
    "gn:asciiname":"Zanca-Sant'Andrea",
    "gn:cc2":"IT",
    "gn:country_code":"IT",
    "gn:dem":20,
    "gn:feature_class":"P",
    "gn:feature_code":"PPL",
    "gn:name":"Zanca-Sant'Andrea",
    "gn:population":166,
    "gn:timezone":"Europe/Rome",
    "iso:country":"IT",
    "name:und_x_variant":[
        "San Andrea"
    ],
    "wof:name":"Zanca-Sant'Andrea",
    "wof:placetype":"locality",
    "wof:population":166
},
  "geometry": {"coordinates":[10.14077,42.80592],"type":"Point"}
}