{
  "type": "Feature",
  "properties": {
    "gn:admin1_code":"20",
    "gn:admin2_code":"VR",
    "gn:admin3_code":"23044.0",
    "gn:asciiname":"Cannavecchia",
    "gn:country_code":"IT",
    "gn:dem":11,
    "gn:feature_class":"P",
    "gn:feature_code":"PPL",
    "gn:name":"Cannavecchia",
    "gn:population":16,
    "gn:timezone":"Europe/Rome",
    "iso:country":"IT",
    "wof:name":"Cannavecchia",
    "wof:placetype":"locality",
    "wof:population":16
},
  "geometry": {"coordinates":[11.29202,45.15004],"type":"Point"}
}