{
  "type": "Feature",
  "properties": {
    "gn:admin1_code":"20",
    "gn:admin2_code":"PD",
    "gn:admin3_code":"28100.0",
    "gn:asciiname":"Giora",
    "gn:country_code":"IT",
    "gn:dem":10,
    "gn:feature_class":"P",
    "gn:feature_code":"PPL",
    "gn:name":"Giora",
    "gn:population":71,
    "gn:timezone":"Europe/Rome",
    "iso:country":"IT",
    "wof:name":"Giora",
    "wof:placetype":"locality",
    "wof:population":71
},
  "geometry": {"coordinates":[11.95521,45.42336],"type":"Point"}
}