{
  "type": "Feature",
  "properties": {
    "gn:admin1_code":"6.0",
    "gn:admin2_code":"UD",
    "gn:admin3_code":"30126.0",
    "gn:asciiname":"Carvacco",
    "gn:country_code":"IT",
    "gn:dem":177,
    "gn:feature_class":"P",
    "gn:feature_code":"PPL",
    "gn:name":"Carvacco",
    "gn:population":0,
    "gn:timezone":"Europe/Rome",
    "iso:country":"IT",
    "wof:name":"Carvacco",
    "wof:placetype":"locality"
},
  "geometry": {"coordinates":[13.14278,46.18444],"type":"Point"}
}