{
  "type": "Feature",
  "properties": {
    "gn:admin1_code":"17.0",
    "gn:admin2_code":"TN",
    "gn:admin3_code":"22161.0",
    "gn:asciiname":"Moietto",
    "gn:country_code":"IT",
    "gn:dem":915,
    "gn:feature_class":"P",
    "gn:feature_code":"PPLL",
    "gn:name":"Moietto",
    "gn:population":3,
    "gn:timezone":"Europe/Rome",
    "iso:country":"IT",
    "wof:name":"Moietto",
    "wof:placetype":"locality",
    "wof:population":3
},
  "geometry": {"coordinates":[11.08614,45.89562],"type":"Point"}
}