{
  "type": "Feature",
  "properties": {
    "gn:admin1_code":"17",
    "gn:admin2_code":"BZ",
    "gn:admin3_code":"21056.0",
    "gn:asciiname":"Zona Industriale Artigianale",
    "gn:country_code":"IT",
    "gn:dem":516,
    "gn:feature_class":"P",
    "gn:feature_code":"PPL",
    "gn:name":"Zona Industriale Artigianale",
    "gn:population":24,
    "gn:timezone":"Europe/Rome",
    "iso:country":"IT",
    "wof:name":"Zona Industriale Artigianale",
    "wof:placetype":"locality",
    "wof:population":24
},
  "geometry": {"coordinates":[11.03199,46.65686],"type":"Point"}
}