{
  "type": "Feature",
  "properties": {
    "gn:admin1_code":"5.0",
    "gn:admin2_code":"RA",
    "gn:admin3_code":"39005.0",
    "gn:asciiname":"Valsenio",
    "gn:country_code":"IT",
    "gn:dem":171,
    "gn:feature_class":"P",
    "gn:feature_code":"PPL",
    "gn:name":"Valsenio",
    "gn:population":54,
    "gn:timezone":"Europe/Rome",
    "iso:country":"IT",
    "wof:name":"Valsenio",
    "wof:placetype":"locality",
    "wof:population":54
},
  "geometry": {"coordinates":[11.64606,44.24145],"type":"Point"}
}