{
  "type": "Feature",
  "properties": {
    "gn:admin1_code":"20",
    "gn:admin2_code":"RO",
    "gn:admin3_code":"29047.0",
    "gn:asciiname":"Case Brancaleoni",
    "gn:country_code":"IT",
    "gn:dem":8,
    "gn:feature_class":"P",
    "gn:feature_code":"PPL",
    "gn:name":"Case Brancaleoni",
    "gn:population":30,
    "gn:timezone":"Europe/Rome",
    "iso:country":"IT",
    "wof:name":"Case Brancaleoni",
    "wof:placetype":"locality",
    "wof:population":30
},
  "geometry": {"coordinates":[11.43044,45.02104],"type":"Point"}
}