{
  "type": "Feature",
  "properties": {
    "gn:admin1_code":"15",
    "gn:admin2_code":"ME",
    "gn:admin3_code":"83023.0",
    "gn:asciiname":"Masseria",
    "gn:country_code":"IT",
    "gn:dem":588,
    "gn:feature_class":"P",
    "gn:feature_code":"PPL",
    "gn:name":"Masseria",
    "gn:population":13,
    "gn:timezone":"Europe/Rome",
    "iso:country":"IT",
    "wof:name":"Masseria",
    "wof:placetype":"locality",
    "wof:population":13
},
  "geometry": {"coordinates":[15.17301,38.00798],"type":"Point"}
}