{
  "type": "Feature",
  "properties": {
    "gn:admin1_code":"5",
    "gn:admin2_code":"PC",
    "gn:admin3_code":"33027.0",
    "gn:asciiname":"Casazza",
    "gn:country_code":"IT",
    "gn:dem":40,
    "gn:feature_class":"P",
    "gn:feature_code":"PPLL",
    "gn:name":"Casazza",
    "gn:population":9,
    "gn:timezone":"Europe/Rome",
    "iso:country":"IT",
    "name:azb_x_preferred":[
        "\u06a9\u0627\u0633\u0627\u062a\u0633\u0627"
    ],
    "name:ceb_x_preferred":[
        "Casazza"
    ],
    "name:deu_x_preferred":[
        "Casazza"
    ],
    "name:epo_x_preferred":[
        "Casazza"
    ],
    "name:eus_x_preferred":[
        "Casazza"
    ],
    "name:fas_x_preferred":[
        "\u06a9\u0627\u0633\u0627\u062a\u0633\u0627"
    ],
    "name:fra_x_preferred":[
        "Casazza"
    ],
    "name:hun_x_preferred":[
        "Casazza"
    ],
    "name:hye_x_preferred":[
        "\u053f\u0561\u0566\u0561\u0581\u0561"
    ],
    "name:ina_x_preferred":[
        "Casazza"
    ],
    "name:ita_x_preferred":[
        "Casazza"
    ],
    "name:jpn_x_preferred":[
        "\u30ab\u30b6\u30c3\u30c4\u30a1"
    ],
    "name:kaz_x_preferred":[
        "\u041a\u0430\u0437\u0430\u0446\u0446\u0430"
    ],
    "name:lat_x_preferred":[
        "Casaccia"
    ],
    "name:lmo_x_preferred":[
        "Casassa"
    ],
    "name:msa_x_preferred":[
        "Casazza"
    ],
    "name:nap_x_preferred":[
        "Casazza"
    ],
    "name:nld_x_preferred":[
        "Casazza"
    ],
    "name:pms_x_preferred":[
        "Casazza"
    ],
    "name:pol_x_preferred":[
        "Casazza"
    ],
    "name:por_x_preferred":[
        "Casazza"
    ],
    "name:ron_x_preferred":[
        "Casazza"
    ],
    "name:rus_x_preferred":[
        "\u041a\u0430\u0437\u0430\u0446\u0446\u0430"
    ],
    "name:scn_x_preferred":[
        "Casazza"
    ],
    "name:spa_x_preferred":[
        "Casazza"
    ],
    "name:srp_x_preferred":[
        "\u041a\u0430\u0437\u0430\u0446\u0430"
    ],
    "name:tgl_x_preferred":[
        "Casazza"
    ],
    "name:ukr_x_preferred":[
        "\u041a\u0430\u0437\u0430\u0446\u0446\u0430"
    ],
    "name:uzb_x_preferred":[
        "Casazza"
    ],
    "name:vie_x_preferred":[
        "Casazza"
    ],
    "name:vol_x_preferred":[
        "Casazza"
    ],
    "name:war_x_preferred":[
        "Casazza"
    ],
    "name:zho_x_preferred":[
        "\u5361\u8428\u624e"
    ],
    "wof:name":"Casazza",
    "wof:placetype":"locality",
    "wof:population":9
},
  "geometry": {"coordinates":[9.92124,45.09277],"type":"Point"}
}