{
  "type": "Feature",
  "properties": {
    "gn:admin1_code":"5",
    "gn:admin2_code":"PC",
    "gn:admin3_code":"33027.0",
    "gn:asciiname":"Casazza",
    "gn:country_code":"IT",
    "gn:dem":40,
    "gn:feature_class":"P",
    "gn:feature_code":"PPLL",
    "gn:name":"Casazza",
    "gn:population":9,
    "gn:timezone":"Europe/Rome",
    "iso:country":"IT",
    "wof:name":"Casazza",
    "wof:placetype":"locality",
    "wof:population":9
},
  "geometry": {"coordinates":[9.92124,45.09277],"type":"Point"}
}