{
  "type": "Feature",
  "properties": {
    "gn:admin1_code":"6",
    "gn:admin2_code":"UD",
    "gn:admin3_code":"30038.0",
    "gn:asciiname":"Laghetto",
    "gn:country_code":"IT",
    "gn:dem":5,
    "gn:feature_class":"P",
    "gn:feature_code":"PPL",
    "gn:name":"Laghetto",
    "gn:population":17,
    "gn:timezone":"Europe/Rome",
    "iso:country":"IT",
    "name:ita_x_preferred":[
        "Colico#Laghetto"
    ],
    "name:lat_x_preferred":[
        "Parvus lacus"
    ],
    "wof:name":"Laghetto",
    "wof:placetype":"locality",
    "wof:population":17
},
  "geometry": {"coordinates":[13.40344,45.80491],"type":"Point"}
}