{
  "type": "Feature",
  "properties": {
    "gn:admin1_code":"12",
    "gn:admin2_code":"CN",
    "gn:admin3_code":"4190.0",
    "gn:asciiname":"Sacconi",
    "gn:country_code":"IT",
    "gn:dem":604,
    "gn:feature_class":"P",
    "gn:feature_code":"PPL",
    "gn:name":"Sacconi",
    "gn:population":70,
    "gn:timezone":"Europe/Rome",
    "iso:country":"IT",
    "wof:name":"Sacconi",
    "wof:placetype":"locality",
    "wof:population":70
},
  "geometry": {"coordinates":[7.72385,44.31197],"type":"Point"}
}