{
  "type": "Feature",
  "properties": {
    "gn:admin1_code":"18.0",
    "gn:admin2_code":"TR",
    "gn:admin3_code":"55032.0",
    "gn:asciiname":"Poggio Lavarino",
    "gn:country_code":"IT",
    "gn:dem":361,
    "gn:elevation":"362.0",
    "gn:feature_class":"P",
    "gn:feature_code":"PPL",
    "gn:name":"Poggio Lavarino",
    "gn:population":67,
    "gn:timezone":"Europe/Rome",
    "iso:country":"IT",
    "wof:name":"Poggio Lavarino",
    "wof:placetype":"locality",
    "wof:population":67
},
  "geometry": {"coordinates":[12.65216,42.63726],"type":"Point"}
}