{
  "type": "Feature",
  "properties": {
    "gn:gn_country":"IT",
    "gn:gn_fcode":"PPLA3",
    "gn:gn_pop":1743,
    "gn:population":1743,
    "iso:country":"IT",
    "name:arm_x_preferred":[
        "\u054a\u0561\u057a\u0578\u0581\u0565"
    ],
    "name:baq_x_preferred":[
        "Papozze"
    ],
    "name:bul_x_preferred":[
        "\u041f\u0430\u043f\u043e\u0446\u0435"
    ],
    "name:cat_x_preferred":[
        "Papozze"
    ],
    "name:chi_x_preferred":[
        "\u5e15\u6ce2\u6cfd"
    ],
    "name:dut_x_preferred":[
        "Papozze"
    ],
    "name:eng_x_preferred":[
        "Papozze"
    ],
    "name:epo_x_preferred":[
        "Papozze"
    ],
    "name:fre_x_preferred":[
        "Papozze"
    ],
    "name:ger_x_preferred":[
        "Papozze"
    ],
    "name:hun_x_preferred":[
        "Papozze"
    ],
    "name:hye_x_preferred":[
        "\u054a\u0561\u057a\u0578\u0581\u0565"
    ],
    "name:ita_x_preferred":[
        "Papozze"
    ],
    "name:jpn_x_preferred":[
        "\u30d1\u30dd\u30c3\u30c4\u30a7"
    ],
    "name:kaz_x_preferred":[
        "\u041f\u0430\u043f\u043e\u0446\u0446\u0435"
    ],
    "name:lat_x_preferred":[
        "Papoxia"
    ],
    "name:lmo_x_preferred":[
        "Papozze"
    ],
    "name:may_x_preferred":[
        "Papozze"
    ],
    "name:nan_x_preferred":[
        "Papozze"
    ],
    "name:nap_x_preferred":[
        "Papozze"
    ],
    "name:oci_x_preferred":[
        "Papozze"
    ],
    "name:per_x_preferred":[
        "\u067e\u0627\u067e\u0648\u062a\u0632\u0647"
    ],
    "name:pms_x_preferred":[
        "Papozze"
    ],
    "name:pol_x_preferred":[
        "Papozze"
    ],
    "name:por_x_preferred":[
        "Papozze"
    ],
    "name:rum_x_preferred":[
        "Papozze"
    ],
    "name:rus_x_preferred":[
        "\u041f\u0430\u043f\u043e\u0446\u0446\u0435"
    ],
    "name:scn_x_preferred":[
        "Papozze"
    ],
    "name:spa_x_preferred":[
        "Papozze"
    ],
    "name:srp_x_preferred":[
        "Papozze"
    ],
    "name:tgl_x_preferred":[
        "Papozze"
    ],
    "name:ukr_x_preferred":[
        "\u041f\u0430\u043f\u043e\u0446\u0446\u0435"
    ],
    "name:uzb_x_preferred":[
        "Papozze"
    ],
    "name:vec_x_preferred":[
        "Papoze"
    ],
    "name:vie_x_preferred":[
        "Papozze"
    ],
    "name:vol_x_preferred":[
        "Papozze"
    ],
    "name:war_x_preferred":[
        "Papozze"
    ],
    "name:zho_x_preferred":[
        "\u5e15\u6ce2\u6cfd"
    ],
    "qs_pg:aaroncc":"IT",
    "qs_pg:gn_country":"IT",
    "qs_pg:gn_fcode":"PPLA3",
    "qs_pg:gn_pop":1743,
    "qs_pg:name":"Papozze",
    "qs_pg:name_adm0":"Italia",
    "qs_pg:name_adm1":"Veneto",
    "qs_pg:photos":701,
    "qs_pg:photos_1k":142,
    "qs_pg:photos_9k":3,
    "qs_pg:photos_9r":5,
    "qs_pg:photos_all":701,
    "qs_pg:photos_sr":8,
    "qs_pg:pop_sr":3,
    "qs_pg:qs_pg_placetype":"locality",
    "qs_pg:qs_pg_placetype_gp":"Town",
    "qs_pg:woe_adm0":23424853,
    "woe:adm0_id":23424853,
    "woe:name_adm0":"Italia",
    "woe:name_adm1":"Veneto",
    "woe:placetype":"Town",
    "wof:name":"Papozze",
    "wof:placetype":"locality",
    "wof:population":1743
},
  "geometry": {"coordinates":[12.03092,44.98578],"type":"Point"}
}