{
  "type": "Feature",
  "properties": {
    "gn:admin1_code":"9",
    "gn:admin2_code":"MN",
    "gn:admin3_code":"20013.0",
    "gn:asciiname":"Maldritto",
    "gn:country_code":"IT",
    "gn:dem":27,
    "gn:feature_class":"P",
    "gn:feature_code":"PPL",
    "gn:name":"Maldritto",
    "gn:population":53,
    "gn:timezone":"Europe/Rome",
    "iso:country":"IT",
    "wof:name":"Maldritto",
    "wof:placetype":"locality",
    "wof:population":53
},
  "geometry": {"coordinates":[10.90248,45.23252],"type":"Point"}
}