{
  "type": "Feature",
  "properties": {
    "gn:country":"IT",
    "gn:fcode":"PPL",
    "gn:population":70288,
    "iso:country":"IT",
    "name:ceb_x_preferred":[
        "Nicastro-Sambiase"
    ],
    "name:eng_x_preferred":[
        "Nicastro"
    ],
    "name:fra_x_preferred":[
        "Nicastro"
    ],
    "name:hun_x_preferred":[
        "Nicastro"
    ],
    "name:ita_x_preferred":[
        "Nicastro"
    ],
    "name:jpn_x_preferred":[
        "\u30cb\u30ab\u30b9\u30c8\u30ed"
    ],
    "name:nld_x_preferred":[
        "Nicastro"
    ],
    "name:rus_x_preferred":[
        "\u041d\u0438\u043a\u0430\u0441\u0442\u0440\u043e"
    ],
    "name:scn_x_preferred":[
        "Nicastru"
    ],
    "name:srp_x_preferred":[
        "Nicastro-Sambiase"
    ],
    "qs_pg:aaroncc":"IT",
    "qs_pg:gn_country":"IT",
    "qs_pg:gn_fcode":"PPL",
    "qs_pg:gn_pop":70288,
    "qs_pg:name":"Nicastro",
    "qs_pg:name_adm0":"Italia",
    "qs_pg:name_adm1":"Calabria",
    "qs_pg:photos":284,
    "qs_pg:photos_1k":58,
    "qs_pg:photos_9k":1,
    "qs_pg:photos_9r":4,
    "qs_pg:photos_all":284,
    "qs_pg:photos_sr":5,
    "qs_pg:pop_sr":8,
    "qs_pg:qs_pg_placetype":"locality",
    "qs_pg:qs_pg_placetype_gp":"Town",
    "qs_pg:woe_adm0":23424853,
    "woe:adm0_id":23424853,
    "woe:name_adm0":"Italia",
    "woe:name_adm1":"Calabria",
    "woe:placetype":"Town",
    "wof:name":"Nicastro",
    "wof:placetype":"locality",
    "wof:population":55687
},
  "geometry": {"coordinates":[16.31667,38.98333],"type":"Point"}
}