{
  "type": "Feature",
  "properties": {
    "gn:admin1_code":"7",
    "gn:admin2_code":"RM",
    "gn:admin3_code":"58093.0",
    "gn:asciiname":"Strada Romana Dritta",
    "gn:country_code":"IT",
    "gn:dem":160,
    "gn:feature_class":"P",
    "gn:feature_code":"PPL",
    "gn:name":"Strada Romana Dritta",
    "gn:population":275,
    "gn:timezone":"Europe/Rome",
    "iso:country":"IT",
    "wof:name":"Strada Romana Dritta",
    "wof:placetype":"locality",
    "wof:population":275
},
  "geometry": {"coordinates":[12.46571,42.07658],"type":"Point"}
}