{
  "type": "Feature",
  "properties": {
    "gn:admin1_code":"12",
    "gn:admin2_code":"BI",
    "gn:admin3_code":"96008.0",
    "gn:asciiname":"Virla-Trabbia-Lucca-Socco",
    "gn:country_code":"IT",
    "gn:dem":849,
    "gn:feature_class":"P",
    "gn:feature_code":"PPLL",
    "gn:name":"Virla-Trabbia-Lucca-Socco",
    "gn:population":7,
    "gn:timezone":"Europe/Rome",
    "iso:country":"IT",
    "wof:name":"Virla-Trabbia-Lucca-Socco",
    "wof:placetype":"locality",
    "wof:population":7
},
  "geometry": {"coordinates":[8.07995,45.63539],"type":"Point"}
}