{
  "type": "Feature",
  "properties": {
    "gn:admin1_code":"9.0",
    "gn:admin2_code":"LO",
    "gn:admin3_code":"98034.0",
    "gn:asciiname":"Cascina Griona",
    "gn:country_code":"IT",
    "gn:dem":68,
    "gn:feature_class":"P",
    "gn:feature_code":"PPL",
    "gn:name":"Cascina Griona",
    "gn:population":15,
    "gn:timezone":"Europe/Rome",
    "iso:country":"IT",
    "wof:name":"Cascina Griona",
    "wof:placetype":"locality",
    "wof:population":15
},
  "geometry": {"coordinates":[9.57556,45.24126],"type":"Point"}
}