{
  "type": "Feature",
  "properties": {
    "gn:admin1_code":"9",
    "gn:admin2_code":"LC",
    "gn:admin3_code":"97014.0",
    "gn:asciiname":"Boccio",
    "gn:country_code":"IT",
    "gn:dem":821,
    "gn:feature_class":"P",
    "gn:feature_code":"PPL",
    "gn:name":"Boccio",
    "gn:population":73,
    "gn:timezone":"Europe/Rome",
    "iso:country":"IT",
    "wof:name":"Boccio",
    "wof:placetype":"locality",
    "wof:population":73
},
  "geometry": {"coordinates":[9.47418,45.80336],"type":"Point"}
}