{
  "type": "Feature",
  "properties": {
    "gn:admin1_code":"12",
    "gn:admin2_code":"CN",
    "gn:admin3_code":"4043.0",
    "gn:asciiname":"Cardoni",
    "gn:country_code":"IT",
    "gn:dem":404,
    "gn:feature_class":"P",
    "gn:feature_code":"PPL",
    "gn:name":"Cardoni",
    "gn:population":64,
    "gn:timezone":"Europe/Rome",
    "iso:country":"IT",
    "wof:name":"Cardoni",
    "wof:placetype":"locality",
    "wof:population":64
},
  "geometry": {"coordinates":[7.8349,44.4805],"type":"Point"}
}