{
  "type": "Feature",
  "properties": {
    "gn:admin1_code":"12",
    "gn:admin2_code":"CN",
    "gn:admin3_code":"4033.0",
    "gn:asciiname":"Colletto",
    "gn:country_code":"IT",
    "gn:dem":686,
    "gn:feature_class":"P",
    "gn:feature_code":"PPLL",
    "gn:name":"Colletto",
    "gn:population":8,
    "gn:timezone":"Europe/Rome",
    "iso:country":"IT",
    "wof:name":"Colletto",
    "wof:placetype":"locality",
    "wof:population":8
},
  "geometry": {"coordinates":[7.3429,44.57727],"type":"Point"}
}