{
  "type": "Feature",
  "properties": {
    "gn:admin1_code":"2",
    "gn:admin2_code":"PZ",
    "gn:admin3_code":"76045.0",
    "gn:asciiname":"Santa Maria",
    "gn:country_code":"IT",
    "gn:dem":684,
    "gn:feature_class":"P",
    "gn:feature_code":"PPL",
    "gn:name":"Santa Maria",
    "gn:population":78,
    "gn:timezone":"Europe/Rome",
    "iso:country":"IT",
    "wof:name":"Santa Maria",
    "wof:placetype":"locality",
    "wof:population":78
},
  "geometry": {"coordinates":[15.73844,40.41153],"type":"Point"}
}