{
  "type": "Feature",
  "properties": {
    "gn:admin1_code":"12",
    "gn:admin2_code":"AL",
    "gn:admin3_code":"6018.0",
    "gn:asciiname":"Cervari",
    "gn:country_code":"IT",
    "gn:dem":586,
    "gn:feature_class":"P",
    "gn:feature_code":"PPL",
    "gn:name":"Cervari",
    "gn:population":15,
    "gn:timezone":"Europe/Rome",
    "iso:country":"IT",
    "wof:name":"Cervari",
    "wof:placetype":"locality",
    "wof:population":15
},
  "geometry": {"coordinates":[8.97284,44.76398],"type":"Point"}
}