{
  "type": "Feature",
  "properties": {
    "gn:admin1_code":"7.0",
    "gn:admin2_code":"RI",
    "gn:admin3_code":"57006.0",
    "gn:asciiname":"Borbona",
    "gn:country_code":"IT",
    "gn:dem":780,
    "gn:elevation":"760.0",
    "gn:feature_class":"P",
    "gn:feature_code":"PPLA3",
    "gn:name":"Borbona",
    "gn:population":533,
    "gn:timezone":"Europe/Rome",
    "iso:country":"IT",
    "name:eng_x_preferred":[
        "Borbona"
    ],
    "name:epo_x_preferred":[
        "Borbona"
    ],
    "name:fra_x_preferred":[
        "Borbona"
    ],
    "name:ita_x_preferred":[
        "Borbona"
    ],
    "name:nap_x_preferred":[
        "Borbona"
    ],
    "name:nld_x_preferred":[
        "Borbona"
    ],
    "name:pol_x_preferred":[
        "Borbona"
    ],
    "name:por_x_preferred":[
        "Borbona"
    ],
    "name:und_x_variant":[
        "Barbona"
    ],
    "wof:name":"Borbona",
    "wof:placetype":"locality",
    "wof:population":533
},
  "geometry": {"coordinates":[13.13206,42.50939],"type":"Point"}
}