{
  "type": "Feature",
  "properties": {
    "gn:admin1_code":"15.0",
    "gn:admin2_code":"PA",
    "gn:admin3_code":"82049.0",
    "gn:asciiname":"Dammusi I",
    "gn:country_code":"IT",
    "gn:dem":457,
    "gn:feature_class":"P",
    "gn:feature_code":"PPLL",
    "gn:name":"Dammusi I",
    "gn:population":4,
    "gn:timezone":"Europe/Rome",
    "iso:country":"IT",
    "wof:name":"Dammusi I",
    "wof:placetype":"locality",
    "wof:population":4
},
  "geometry": {"coordinates":[13.18665,37.99832],"type":"Point"}
}