{
  "type": "Feature",
  "properties": {
    "gn:admin1_code":"5",
    "gn:admin2_code":"PR",
    "gn:admin3_code":"34009.0",
    "gn:asciiname":"Maraffa",
    "gn:country_code":"IT",
    "gn:dem":95,
    "gn:feature_class":"P",
    "gn:feature_code":"PPL",
    "gn:name":"Maraffa",
    "gn:population":25,
    "gn:timezone":"Europe/Rome",
    "iso:country":"IT",
    "wof:name":"Maraffa",
    "wof:placetype":"locality",
    "wof:population":25
},
  "geometry": {"coordinates":[10.18213,44.75367],"type":"Point"}
}