{
  "type": "Feature",
  "properties": {
    "gn:admin1_code":"12",
    "gn:admin2_code":"AT",
    "gn:admin3_code":"5050.0",
    "gn:asciiname":"San Carlo",
    "gn:country_code":"IT",
    "gn:dem":292,
    "gn:feature_class":"P",
    "gn:feature_code":"PPL",
    "gn:name":"San Carlo",
    "gn:population":36,
    "gn:timezone":"Europe/Rome",
    "iso:country":"IT",
    "wof:name":"San Carlo",
    "wof:placetype":"locality",
    "wof:population":36
},
  "geometry": {"coordinates":[8.18773,44.79978],"type":"Point"}
}