{
  "type": "Feature",
  "properties": {
    "gn:admin1_code":"12",
    "gn:admin2_code":"AT",
    "gn:admin3_code":"5050.0",
    "gn:asciiname":"San Carlo",
    "gn:country_code":"IT",
    "gn:dem":292,
    "gn:feature_class":"P",
    "gn:feature_code":"PPL",
    "gn:name":"San Carlo",
    "gn:population":36,
    "gn:timezone":"Europe/Rome",
    "iso:country":"IT",
    "name:als_x_preferred":[
        "San Carlo"
    ],
    "name:bre_x_preferred":[
        "San Carlo"
    ],
    "name:ceb_x_preferred":[
        "San Carlo"
    ],
    "name:deu_x_preferred":[
        "San Carlo"
    ],
    "name:epo_x_preferred":[
        "San Carlo"
    ],
    "name:ita_x_preferred":[
        "San Carlo"
    ],
    "name:nld_x_preferred":[
        "San Carlo"
    ],
    "name:pms_x_preferred":[
        "San Carl"
    ],
    "name:pol_x_preferred":[
        "San Carlo"
    ],
    "name:spa_x_preferred":[
        "San Carlo"
    ],
    "name:srp_x_preferred":[
        "San Karlo"
    ],
    "name:swe_x_preferred":[
        "San Carlo"
    ],
    "wof:name":"San Carlo",
    "wof:placetype":"locality",
    "wof:population":36
},
  "geometry": {"coordinates":[8.18773,44.79978],"type":"Point"}
}