{
  "type": "Feature",
  "properties": {
    "gn:admin1_code":"9",
    "gn:admin2_code":"MN",
    "gn:admin3_code":"20048.0",
    "gn:asciiname":"Pagadelli",
    "gn:country_code":"IT",
    "gn:dem":29,
    "gn:feature_class":"P",
    "gn:feature_code":"PPL",
    "gn:name":"Pagadelli",
    "gn:population":45,
    "gn:timezone":"Europe/Rome",
    "iso:country":"IT",
    "wof:name":"Pagadelli",
    "wof:placetype":"locality",
    "wof:population":45
},
  "geometry": {"coordinates":[10.51277,45.15036],"type":"Point"}
}