{
  "type": "Feature",
  "properties": {
    "gn:admin1_code":"20",
    "gn:admin2_code":"RO",
    "gn:admin3_code":"29049.0",
    "gn:asciiname":"Gambero I",
    "gn:country_code":"IT",
    "gn:dem":4,
    "gn:feature_class":"P",
    "gn:feature_code":"PPL",
    "gn:name":"Gambero I",
    "gn:population":20,
    "gn:timezone":"Europe/Rome",
    "iso:country":"IT",
    "wof:name":"Gambero I",
    "wof:placetype":"locality",
    "wof:population":20
},
  "geometry": {"coordinates":[11.69073,44.99988],"type":"Point"}
}