{
  "type": "Feature",
  "properties": {
    "gn:admin1_code":"20",
    "gn:admin2_code":"VR",
    "gn:admin3_code":"23089.0",
    "gn:asciiname":"Barozzino",
    "gn:country_code":"IT",
    "gn:dem":121,
    "gn:feature_class":"P",
    "gn:feature_code":"PPL",
    "gn:name":"Barozzino",
    "gn:population":49,
    "gn:timezone":"Europe/Rome",
    "iso:country":"IT",
    "wof:name":"Barozzino",
    "wof:placetype":"locality",
    "wof:population":49
},
  "geometry": {"coordinates":[10.72626,45.36836],"type":"Point"}
}