{
  "type": "Feature",
  "properties": {
    "gn:admin1_code":"16.0",
    "gn:admin2_code":"LU",
    "gn:admin3_code":"46027.0",
    "gn:asciiname":"Rifugio Orecchielle",
    "gn:country_code":"IT",
    "gn:dem":1284,
    "gn:feature_class":"P",
    "gn:feature_code":"PPLL",
    "gn:name":"Rifugio Orecchielle",
    "gn:population":0,
    "gn:timezone":"Europe/Rome",
    "iso:country":"IT",
    "wof:name":"Rifugio Orecchielle",
    "wof:placetype":"locality"
},
  "geometry": {"coordinates":[10.34007,44.21115],"type":"Point"}
}