{
  "type": "Feature",
  "properties": {
    "gn:admin1_code":"16.0",
    "gn:admin2_code":"GR",
    "gn:admin3_code":"53010.0",
    "gn:asciiname":"Il Bagno",
    "gn:country_code":"IT",
    "gn:dem":46,
    "gn:feature_class":"P",
    "gn:feature_code":"PPL",
    "gn:name":"Il Bagno",
    "gn:population":0,
    "gn:timezone":"Europe/Rome",
    "iso:country":"IT",
    "wof:name":"Il Bagno",
    "wof:placetype":"locality"
},
  "geometry": {"coordinates":[10.88333,42.93333],"type":"Point"}
}