{
  "type": "Feature",
  "properties": {
    "gn:admin1_code":"16",
    "gn:admin2_code":"AR",
    "gn:admin3_code":"51017.0",
    "gn:asciiname":"Sant'Andrea di Sorbello",
    "gn:country_code":"IT",
    "gn:dem":289,
    "gn:feature_class":"P",
    "gn:feature_code":"PPL",
    "gn:name":"Sant'Andrea di Sorbello",
    "gn:population":12,
    "gn:timezone":"Europe/Rome",
    "iso:country":"IT",
    "wof:name":"Sant'Andrea di Sorbello",
    "wof:placetype":"locality",
    "wof:population":12
},
  "geometry": {"coordinates":[12.21141,43.28719],"type":"Point"}
}