{
  "type": "Feature",
  "properties": {
    "gn:admin1_code":"9",
    "gn:admin2_code":"MN",
    "gn:admin3_code":"20061.0",
    "gn:asciiname":"Boschetta",
    "gn:country_code":"IT",
    "gn:dem":11,
    "gn:feature_class":"P",
    "gn:feature_code":"PPLL",
    "gn:name":"Boschetta",
    "gn:population":8,
    "gn:timezone":"Europe/Rome",
    "iso:country":"IT",
    "wof:name":"Boschetta",
    "wof:placetype":"locality",
    "wof:population":8
},
  "geometry": {"coordinates":[11.27668,44.94595],"type":"Point"}
}