{
  "type": "Feature",
  "properties": {
    "gn:admin1_code":"18",
    "gn:admin2_code":"PG",
    "gn:admin3_code":"54044.0",
    "gn:asciiname":"Petricce",
    "gn:country_code":"IT",
    "gn:dem":326,
    "gn:feature_class":"P",
    "gn:feature_code":"PPL",
    "gn:name":"Petricce",
    "gn:population":11,
    "gn:timezone":"Europe/Rome",
    "iso:country":"IT",
    "wof:name":"Petricce",
    "wof:placetype":"locality",
    "wof:population":11
},
  "geometry": {"coordinates":[12.18542,43.54255],"type":"Point"}
}