{
  "type": "Feature",
  "properties": {
    "gn:admin1_code":"20",
    "gn:admin2_code":"TV",
    "gn:admin3_code":"26012.0",
    "gn:asciiname":"Casette di Bella Venezia",
    "gn:country_code":"IT",
    "gn:dem":46,
    "gn:feature_class":"P",
    "gn:feature_code":"PPL",
    "gn:name":"Casette di Bella Venezia",
    "gn:population":319,
    "gn:timezone":"Europe/Rome",
    "iso:country":"IT",
    "wof:name":"Casette di Bella Venezia",
    "wof:placetype":"locality",
    "wof:population":319
},
  "geometry": {"coordinates":[11.91732,45.69454],"type":"Point"}
}