{
  "type": "Feature",
  "properties": {
    "gn:admin1_code":"9.0",
    "gn:admin2_code":"BS",
    "gn:admin3_code":"17091.0",
    "gn:asciiname":"Area Produttiva Industriale",
    "gn:country_code":"IT",
    "gn:dem":107,
    "gn:feature_class":"P",
    "gn:feature_code":"PPLL",
    "gn:name":"Area Produttiva Industriale",
    "gn:population":0,
    "gn:timezone":"Europe/Rome",
    "iso:country":"IT",
    "wof:name":"Area Produttiva Industriale",
    "wof:placetype":"locality"
},
  "geometry": {"coordinates":[10.06792,45.49139],"type":"Point"}
}