{
  "type": "Feature",
  "properties": {
    "gn:admin1_code":"20",
    "gn:admin2_code":"TV",
    "gn:admin3_code":"26072.0",
    "gn:asciiname":"Alle Fruttazze",
    "gn:country_code":"IT",
    "gn:dem":38,
    "gn:feature_class":"P",
    "gn:feature_code":"PPL",
    "gn:name":"Alle Fruttazze",
    "gn:population":25,
    "gn:timezone":"Europe/Rome",
    "iso:country":"IT",
    "wof:name":"Alle Fruttazze",
    "wof:placetype":"locality",
    "wof:population":25
},
  "geometry": {"coordinates":[12.37926,45.89765],"type":"Point"}
}