{
  "type": "Feature",
  "properties": {
    "gn:admin1_code":"12",
    "gn:admin2_code":"CN",
    "gn:admin3_code":"4078.0",
    "gn:asciiname":"Tetto San Giacomo",
    "gn:country_code":"IT",
    "gn:dem":511,
    "gn:feature_class":"P",
    "gn:feature_code":"PPL",
    "gn:name":"Tetto San Giacomo",
    "gn:population":14,
    "gn:timezone":"Europe/Rome",
    "iso:country":"IT",
    "wof:name":"Tetto San Giacomo",
    "wof:placetype":"locality",
    "wof:population":14
},
  "geometry": {"coordinates":[7.531,44.42684000000001],"type":"Point"}
}