{
  "type": "Feature",
  "properties": {
    "gn:admin1_code":"4.0",
    "gn:admin2_code":"CE",
    "gn:admin3_code":"61048.0",
    "gn:asciiname":"Masseriola I",
    "gn:country_code":"IT",
    "gn:dem":60,
    "gn:feature_class":"P",
    "gn:feature_code":"PPL",
    "gn:name":"Masseriola I",
    "gn:population":30,
    "gn:timezone":"Europe/Rome",
    "iso:country":"IT",
    "wof:name":"Masseriola I",
    "wof:placetype":"locality",
    "wof:population":30
},
  "geometry": {"coordinates":[14.43576,41.02172],"type":"Point"}
}