{
  "type": "Feature",
  "properties": {
    "gn:admin1_code":"13",
    "gn:admin2_code":"FG",
    "gn:admin3_code":"71003.0",
    "gn:asciiname":"Portolecchia",
    "gn:country_code":"IT",
    "gn:dem":737,
    "gn:feature_class":"P",
    "gn:feature_code":"PPL",
    "gn:name":"Portolecchia",
    "gn:population":83,
    "gn:timezone":"Europe/Rome",
    "iso:country":"IT",
    "wof:name":"Portolecchia",
    "wof:placetype":"locality",
    "wof:population":83
},
  "geometry": {"coordinates":[15.29492,41.09267],"type":"Point"}
}