{
  "type": "Feature",
  "properties": {
    "gn:admin1_code":"5",
    "gn:admin2_code":"PR",
    "gn:admin3_code":"34023.0",
    "gn:asciiname":"Monte",
    "gn:country_code":"IT",
    "gn:dem":118,
    "gn:feature_class":"P",
    "gn:feature_code":"PPL",
    "gn:name":"Monte",
    "gn:population":49,
    "gn:timezone":"Europe/Rome",
    "iso:country":"IT",
    "wof:name":"Monte",
    "wof:placetype":"locality",
    "wof:population":49
},
  "geometry": {"coordinates":[10.37432,44.70173],"type":"Point"}
}