{
  "type": "Feature",
  "properties": {
    "gn:admin1_code":"4",
    "gn:admin2_code":"SA",
    "gn:admin3_code":"65025.0",
    "gn:asciiname":"Allevatori di Castori",
    "gn:country_code":"IT",
    "gn:dem":1,
    "gn:feature_class":"P",
    "gn:feature_code":"PPL",
    "gn:name":"Allevatori di Castori",
    "gn:population":30,
    "gn:timezone":"Europe/Rome",
    "iso:country":"IT",
    "wof:name":"Allevatori di Castori",
    "wof:placetype":"locality",
    "wof:population":30
},
  "geometry": {"coordinates":[14.95545,40.47158],"type":"Point"}
}