{
  "type": "Feature",
  "properties": {
    "gn:admin1_code":"5",
    "gn:admin2_code":"FE",
    "gn:admin3_code":"38005.0",
    "gn:asciiname":"Corte Bella",
    "gn:country_code":"IT",
    "gn:dem":-5,
    "gn:feature_class":"P",
    "gn:feature_code":"PPL",
    "gn:name":"Corte Bella",
    "gn:population":19,
    "gn:timezone":"Europe/Rome",
    "iso:country":"IT",
    "wof:name":"Corte Bella",
    "wof:placetype":"locality",
    "wof:population":19
},
  "geometry": {"coordinates":[12.07375,44.91345],"type":"Point"}
}