{
  "type": "Feature",
  "properties": {
    "gn:admin1_code":"6.0",
    "gn:admin2_code":"UD",
    "gn:admin3_code":"30013.0",
    "gn:asciiname":"Avilla",
    "gn:country_code":"IT",
    "gn:dem":163,
    "gn:feature_class":"P",
    "gn:feature_code":"PPL",
    "gn:name":"Avilla",
    "gn:population":0,
    "gn:timezone":"Europe/Rome",
    "iso:country":"IT",
    "name:ceb_x_preferred":[
        "Avilla"
    ],
    "name:deu_x_preferred":[
        "Avilla"
    ],
    "name:ita_x_preferred":[
        "Avilla"
    ],
    "name:nld_x_preferred":[
        "Avilla"
    ],
    "name:pol_x_preferred":[
        "Avilla"
    ],
    "name:por_x_preferred":[
        "Avilla"
    ],
    "name:und_x_variant":[
        "Aebura",
        "Avilla"
    ],
    "name:vol_x_preferred":[
        "Avilla"
    ],
    "wof:name":"Avilla",
    "wof:placetype":"locality"
},
  "geometry": {"coordinates":[13.10583,46.205],"type":"Point"}
}