{
  "type": "Feature",
  "properties": {
    "gn:admin1_code":"18",
    "gn:admin2_code":"PG",
    "gn:admin3_code":"54027.0",
    "gn:asciiname":"Stazione",
    "gn:country_code":"IT",
    "gn:dem":173,
    "gn:feature_class":"P",
    "gn:feature_code":"PPL",
    "gn:name":"Stazione",
    "gn:population":174,
    "gn:timezone":"Europe/Rome",
    "iso:country":"IT",
    "wof:name":"Stazione",
    "wof:placetype":"locality",
    "wof:population":174
},
  "geometry": {"coordinates":[12.37237,42.9628],"type":"Point"}
}