{
  "type": "Feature",
  "properties": {
    "gn:admin1_code":"10",
    "gn:admin2_code":"MC",
    "gn:admin3_code":"43019.0",
    "gn:asciiname":"San Cassiano",
    "gn:country_code":"IT",
    "gn:dem":469,
    "gn:feature_class":"P",
    "gn:feature_code":"PPL",
    "gn:name":"San Cassiano",
    "gn:population":31,
    "gn:timezone":"Europe/Rome",
    "iso:country":"IT",
    "wof:name":"San Cassiano",
    "wof:placetype":"locality",
    "wof:population":31
},
  "geometry": {"coordinates":[12.94835,43.17461],"type":"Point"}
}