{
  "type": "Feature",
  "properties": {
    "gn:admin1_code":"10",
    "gn:admin2_code":"MC",
    "gn:admin3_code":"43019.0",
    "gn:asciiname":"San Cassiano",
    "gn:country_code":"IT",
    "gn:dem":469,
    "gn:feature_class":"P",
    "gn:feature_code":"PPL",
    "gn:name":"San Cassiano",
    "gn:population":31,
    "gn:timezone":"Europe/Rome",
    "iso:country":"IT",
    "name:ara_x_preferred":[
        "\u0633\u0627\u0646 \u0643\u0627\u0633\u064a\u0627\u0646\u0648"
    ],
    "name:azb_x_preferred":[
        "\u0633\u0646 \u06a9\u0627\u0633\u06cc\u0627\u0646\u0648"
    ],
    "name:bel_x_preferred":[
        "\u0421\u0430\u043d-\u041a\u0430\u0441\u0456\u044f\u043d\u0430"
    ],
    "name:bul_x_preferred":[
        "\u0421\u0430\u043d \u041a\u0430\u0441\u0438\u0430\u043d\u043e"
    ],
    "name:ceb_x_preferred":[
        "San Cassiano"
    ],
    "name:deu_x_preferred":[
        "San Cassiano"
    ],
    "name:epo_x_preferred":[
        "San Cassiano"
    ],
    "name:eus_x_preferred":[
        "San Cassiano"
    ],
    "name:fas_x_preferred":[
        "\u0633\u0646 \u06a9\u0627\u0633\u06cc\u0627\u0646\u0648"
    ],
    "name:fra_x_preferred":[
        "San Cassiano"
    ],
    "name:hun_x_preferred":[
        "San Cassiano"
    ],
    "name:hye_x_preferred":[
        "\u054d\u0561\u0576 \u053f\u0561\u057d\u056b\u0561\u0576\u0578"
    ],
    "name:ina_x_preferred":[
        "San Cassiano"
    ],
    "name:ita_x_preferred":[
        "San Cassiano"
    ],
    "name:jpn_x_preferred":[
        "\u30b5\u30f3\u30fb\u30ab\u30c3\u30b7\u30a2\u30fc\u30ce"
    ],
    "name:kaz_x_preferred":[
        "\u0421\u0430\u043d-\u041a\u0430\u0441\u0441\u0438\u0430\u043d\u043e"
    ],
    "name:lat_x_preferred":[
        "Fanum Sancti Cassiani"
    ],
    "name:lmo_x_preferred":[
        "San Cassiano"
    ],
    "name:msa_x_preferred":[
        "San Cassiano"
    ],
    "name:nap_x_preferred":[
        "San Cassiano"
    ],
    "name:nld_x_preferred":[
        "San Cassiano"
    ],
    "name:pms_x_preferred":[
        "San Cassiano"
    ],
    "name:pol_x_preferred":[
        "San Cassiano"
    ],
    "name:por_x_preferred":[
        "San Cassiano"
    ],
    "name:ron_x_preferred":[
        "San Cassiano"
    ],
    "name:rus_x_preferred":[
        "\u0421\u0430\u043d-\u041a\u0430\u0441\u0441\u0438\u0430\u043d\u043e"
    ],
    "name:scn_x_preferred":[
        "San Cassianu"
    ],
    "name:spa_x_preferred":[
        "San Cassiano"
    ],
    "name:srp_x_preferred":[
        "\u0421\u0430\u043d \u041a\u0430\u0441\u0438\u0458\u0430\u043d\u043e"
    ],
    "name:ukr_x_preferred":[
        "\u0421\u0430\u043d-\u041a\u0430\u0441\u0441\u0456\u0430\u043d\u043e"
    ],
    "name:uzb_x_preferred":[
        "San Cassiano"
    ],
    "name:vec_x_preferred":[
        "San Casian"
    ],
    "name:vie_x_preferred":[
        "San Cassiano"
    ],
    "name:vol_x_preferred":[
        "San Cassiano"
    ],
    "name:war_x_preferred":[
        "San Cassiano"
    ],
    "name:zho_x_preferred":[
        "\u5723\u5361\u590f\u8bfa"
    ],
    "wof:name":"San Cassiano",
    "wof:placetype":"locality",
    "wof:population":31
},
  "geometry": {"coordinates":[12.94835,43.17461],"type":"Point"}
}