{
  "type": "Feature",
  "properties": {
    "gn:admin1_code":"12.0",
    "gn:admin2_code":"TO",
    "gn:admin3_code":"1220.0",
    "gn:asciiname":"Zona Industriale",
    "gn:country_code":"IT",
    "gn:dem":318,
    "gn:feature_class":"P",
    "gn:feature_code":"PPL",
    "gn:name":"Zona Industriale",
    "gn:population":16,
    "gn:timezone":"Europe/Rome",
    "iso:country":"IT",
    "wof:name":"Zona Industriale",
    "wof:placetype":"locality",
    "wof:population":16
},
  "geometry": {"coordinates":[7.59465,45.17768],"type":"Point"}
}