{
  "type": "Feature",
  "properties": {
    "gn:admin1_code":"6.0",
    "gn:admin2_code":"UD",
    "gn:admin3_code":"30109.0",
    "gn:asciiname":"Grions",
    "gn:country_code":"IT",
    "gn:dem":81,
    "gn:elevation":"86.0",
    "gn:feature_class":"P",
    "gn:feature_code":"PPL",
    "gn:name":"Grions",
    "gn:population":338,
    "gn:timezone":"Europe/Rome",
    "iso:country":"IT",
    "wof:name":"Grions",
    "wof:placetype":"locality",
    "wof:population":338
},
  "geometry": {"coordinates":[12.96798,46.03675],"type":"Point"}
}