{
  "type": "Feature",
  "properties": {
    "gn:admin1_code":"14.0",
    "gn:admin2_code":"CA",
    "gn:admin3_code":"92066.0",
    "gn:asciiname":"San Giorgio",
    "gn:country_code":"IT",
    "gn:dem":80,
    "gn:feature_class":"P",
    "gn:feature_code":"PPL",
    "gn:name":"San Giorgio",
    "gn:population":0,
    "gn:timezone":"Europe/Rome",
    "iso:country":"IT",
    "wof:name":"San Giorgio",
    "wof:placetype":"locality"
},
  "geometry": {"coordinates":[8.995,39.06444000000001],"type":"Point"}
}