{
  "type": "Feature",
  "properties": {
    "gn:admin1_code":"16",
    "gn:admin2_code":"SI",
    "gn:admin3_code":"52035.0",
    "gn:asciiname":"Doccia",
    "gn:country_code":"IT",
    "gn:dem":250,
    "gn:feature_class":"P",
    "gn:feature_code":"PPL",
    "gn:name":"Doccia",
    "gn:population":43,
    "gn:timezone":"Europe/Rome",
    "iso:country":"IT",
    "wof:name":"Doccia",
    "wof:placetype":"locality",
    "wof:population":43
},
  "geometry": {"coordinates":[11.81286,43.17816],"type":"Point"}
}