{
  "type": "Feature",
  "properties": {
    "gn:admin1_code":"4",
    "gn:admin2_code":"SA",
    "gn:admin3_code":"65139.0",
    "gn:asciiname":"San Teodoro",
    "gn:country_code":"IT",
    "gn:dem":222,
    "gn:feature_class":"P",
    "gn:feature_code":"PPL",
    "gn:name":"San Teodoro",
    "gn:population":70,
    "gn:timezone":"Europe/Rome",
    "iso:country":"IT",
    "wof:name":"San Teodoro",
    "wof:placetype":"locality",
    "wof:population":70
},
  "geometry": {"coordinates":[15.01803,40.23325],"type":"Point"}
}