{
  "type": "Feature",
  "properties": {
    "gn:admin1_code":"4",
    "gn:admin2_code":"SA",
    "gn:admin3_code":"65139.0",
    "gn:asciiname":"San Teodoro",
    "gn:country_code":"IT",
    "gn:dem":222,
    "gn:feature_class":"P",
    "gn:feature_code":"PPL",
    "gn:name":"San Teodoro",
    "gn:population":70,
    "gn:timezone":"Europe/Rome",
    "iso:country":"IT",
    "name:bul_x_preferred":[
        "\u0421\u0430\u043d \u0422\u0435\u043e\u0434\u043e\u0440\u043e"
    ],
    "name:ceb_x_preferred":[
        "San Teodoro"
    ],
    "name:deu_x_preferred":[
        "San Teodoro"
    ],
    "name:epo_x_preferred":[
        "San Teodoro"
    ],
    "name:eus_x_preferred":[
        "San Teodoro"
    ],
    "name:fra_x_preferred":[
        "San Teodoro"
    ],
    "name:hun_x_preferred":[
        "San Teodoro"
    ],
    "name:hye_x_preferred":[
        "\u054d\u0561\u0576 \u054f\u0565\u0578\u0564\u0578\u0580\u0578"
    ],
    "name:ita_x_preferred":[
        "San Teodoro"
    ],
    "name:jpn_x_preferred":[
        "\u30b5\u30f3\u30fb\u30c6\u30aa\u30c9\u30fc\u30ed"
    ],
    "name:nds_x_preferred":[
        "San Teodoro"
    ],
    "name:nld_x_preferred":[
        "San Teodoro"
    ],
    "name:pms_x_preferred":[
        "San Teodoro"
    ],
    "name:pol_x_preferred":[
        "San Teodoro"
    ],
    "name:por_x_preferred":[
        "San Teodoro"
    ],
    "name:rus_x_preferred":[
        "\u0421\u0430\u043d-\u0422\u0435\u043e\u0434\u043e\u0440\u043e"
    ],
    "name:srp_x_preferred":[
        "San Teodoro"
    ],
    "name:swe_x_preferred":[
        "San Teodoro"
    ],
    "name:ukr_x_preferred":[
        "\u0421\u0430\u043d-\u0422\u0435\u043e\u0434\u043e\u0440\u043e"
    ],
    "name:war_x_preferred":[
        "San Teodoro"
    ],
    "wof:name":"San Teodoro",
    "wof:placetype":"locality",
    "wof:population":70
},
  "geometry": {"coordinates":[15.01803,40.23325],"type":"Point"}
}