{
  "type": "Feature",
  "properties": {
    "gn:admin1_code":"16",
    "gn:admin2_code":"MS",
    "gn:admin3_code":"45007.0",
    "gn:asciiname":"Cotto",
    "gn:country_code":"IT",
    "gn:dem":503,
    "gn:feature_class":"P",
    "gn:feature_code":"PPL",
    "gn:name":"Cotto",
    "gn:population":32,
    "gn:timezone":"Europe/Rome",
    "iso:country":"IT",
    "wof:name":"Cotto",
    "wof:placetype":"locality",
    "wof:population":32
},
  "geometry": {"coordinates":[10.1177,44.26665],"type":"Point"}
}