{
  "type": "Feature",
  "properties": {
    "gn:elevation":360,
    "gn:population":278,
    "iso:country":"IT",
    "name:bel_x_preferred":[
        "\u041a\u0430\u0440\u0430\u0432\u043e\u043d\u0456\u043a\u0430"
    ],
    "name:bul_x_preferred":[
        "\u041a\u0430\u0440\u0430\u0432\u043e\u043d\u0438\u043a\u0430"
    ],
    "name:cat_x_preferred":[
        "Caravonica"
    ],
    "name:deu_x_preferred":[
        "Caravonica"
    ],
    "name:eng_x_preferred":[
        "Caravonica"
    ],
    "name:epo_x_preferred":[
        "Caravonica"
    ],
    "name:eus_x_preferred":[
        "Caravonica"
    ],
    "name:fas_x_preferred":[
        "\u06a9\u0627\u0631\u0627\u0648\u0648\u0646\u06cc\u06a9\u0627"
    ],
    "name:fra_x_preferred":[
        "Caravonica"
    ],
    "name:hbs_x_preferred":[
        "Caravonica"
    ],
    "name:hun_x_preferred":[
        "Caravonica"
    ],
    "name:hye_x_preferred":[
        "\u053f\u0561\u0580\u0561\u057e\u0578\u0576\u056b\u056f\u0561"
    ],
    "name:ina_x_preferred":[
        "Caravonica"
    ],
    "name:ita_x_preferred":[
        "Caravonica"
    ],
    "name:jpn_x_preferred":[
        "\u30ab\u30e9\u30f4\u30a9\u30fc\u30cb\u30ab"
    ],
    "name:kaz_x_preferred":[
        "\u041a\u0430\u0440\u0430\u0432\u043e\u043d\u0438\u043a\u0430"
    ],
    "name:lat_x_preferred":[
        "Caravonica"
    ],
    "name:lij_x_preferred":[
        "Cair\u00f2nega"
    ],
    "name:lmo_x_preferred":[
        "Caravonica"
    ],
    "name:msa_x_preferred":[
        "Caravonica"
    ],
    "name:nan_x_preferred":[
        "Caravonica"
    ],
    "name:nap_x_preferred":[
        "Caravonica"
    ],
    "name:nld_x_preferred":[
        "Caravonica"
    ],
    "name:pms_x_preferred":[
        "Caravonica"
    ],
    "name:pol_x_preferred":[
        "Caravonica"
    ],
    "name:por_x_preferred":[
        "Caravonica"
    ],
    "name:ron_x_preferred":[
        "Caravonica"
    ],
    "name:rus_x_preferred":[
        "\u041a\u0430\u0440\u0430\u0432\u043e\u043d\u0438\u043a\u0430"
    ],
    "name:scn_x_preferred":[
        "Caravonica"
    ],
    "name:spa_x_preferred":[
        "Caravonica"
    ],
    "name:srp_x_preferred":[
        "\u041a\u0430\u0440\u0430\u0432\u043e\u043d\u0438\u043a\u0430"
    ],
    "name:ukr_x_preferred":[
        "\u041a\u0430\u0440\u0430\u0432\u043e\u043d\u0456\u043a\u0430"
    ],
    "name:uzb_x_preferred":[
        "Caravonica"
    ],
    "name:vie_x_preferred":[
        "Caravonica"
    ],
    "name:vol_x_preferred":[
        "Caravonica"
    ],
    "name:war_x_preferred":[
        "Caravonica"
    ],
    "name:zho_min_nan_x_preferred":[
        "Caravonica"
    ],
    "name:zho_x_preferred":[
        "\u5361\u62c9\u6c83\u5c3c\u5361"
    ],
    "qs:a0":"Italia",
    "qs:a1":"*Imperia",
    "qs:a1r":"0Liguria",
    "qs:adm0":"Italia",
    "qs:la_lc":"*",
    "qs:level":"locality",
    "qs:loc":"Caravonica",
    "qs:loc_alt":"Caravonica",
    "qs:pop":0,
    "qs:type":"buffered point",
    "wd:wordcount":85,
    "wof:lang":[
        "ita"
    ],
    "wof:name":"Caravonica",
    "wof:placetype":"locality",
    "wof:population":278
},
  "geometry": {"coordinates":[7.95889,43.993889],"type":"Point"}
}