{
  "type": "Feature",
  "properties": {
    "gn:admin1_code":"9",
    "gn:admin2_code":"PV",
    "gn:admin3_code":"18081.0",
    "gn:asciiname":"Paltinera",
    "gn:country_code":"IT",
    "gn:dem":74,
    "gn:feature_class":"P",
    "gn:feature_code":"PPL",
    "gn:name":"Paltinera",
    "gn:population":13,
    "gn:timezone":"Europe/Rome",
    "iso:country":"IT",
    "wof:name":"Paltinera",
    "wof:placetype":"locality",
    "wof:population":13
},
  "geometry": {"coordinates":[9.27988,45.15647],"type":"Point"}
}