{
  "type": "Feature",
  "properties": {
    "gn:admin1_code":"20",
    "gn:admin2_code":"VR",
    "gn:admin3_code":"23096.0",
    "gn:asciiname":"Chiodo",
    "gn:country_code":"IT",
    "gn:dem":46,
    "gn:feature_class":"P",
    "gn:feature_code":"PPL",
    "gn:name":"Chiodo",
    "gn:population":67,
    "gn:timezone":"Europe/Rome",
    "iso:country":"IT",
    "wof:name":"Chiodo",
    "wof:placetype":"locality",
    "wof:population":67
},
  "geometry": {"coordinates":[10.92965,45.36711],"type":"Point"}
}