{
  "type": "Feature",
  "properties": {
    "gn:admin1_code":"16.0",
    "gn:admin2_code":"LI",
    "gn:admin3_code":"49019.0",
    "gn:asciiname":"Brancorsi",
    "gn:country_code":"IT",
    "gn:dem":335,
    "gn:feature_class":"P",
    "gn:feature_code":"PPL",
    "gn:name":"Brancorsi",
    "gn:population":0,
    "gn:timezone":"Europe/Rome",
    "iso:country":"IT",
    "wof:name":"Brancorsi",
    "wof:placetype":"locality"
},
  "geometry": {"coordinates":[10.65,43.15],"type":"Point"}
}