{
  "type": "Feature",
  "properties": {
    "gn:admin1_code":"5",
    "gn:admin2_code":"FE",
    "gn:admin3_code":"38023.0",
    "gn:asciiname":"Borgo Carandina",
    "gn:country_code":"IT",
    "gn:dem":3,
    "gn:feature_class":"P",
    "gn:feature_code":"PPL",
    "gn:name":"Borgo Carandina",
    "gn:population":39,
    "gn:timezone":"Europe/Rome",
    "iso:country":"IT",
    "wof:name":"Borgo Carandina",
    "wof:placetype":"locality",
    "wof:population":39
},
  "geometry": {"coordinates":[11.76507,44.7463],"type":"Point"}
}