{
  "type": "Feature",
  "properties": {
    "gn:admin1_code":"12",
    "gn:admin2_code":"VB",
    "gn:admin3_code":"103050.0",
    "gn:asciiname":"Gattugno",
    "gn:country_code":"IT",
    "gn:dem":506,
    "gn:feature_class":"P",
    "gn:feature_code":"PPL",
    "gn:name":"Gattugno",
    "gn:population":64,
    "gn:timezone":"Europe/Rome",
    "iso:country":"IT",
    "wof:name":"Gattugno",
    "wof:placetype":"locality",
    "wof:population":64
},
  "geometry": {"coordinates":[8.40201,45.89742],"type":"Point"}
}