{
  "type": "Feature",
  "properties": {
    "gn:admin1_code":"16",
    "gn:admin2_code":"FI",
    "gn:admin3_code":"48038.0",
    "gn:asciiname":"Croce di Via",
    "gn:country_code":"IT",
    "gn:dem":245,
    "gn:feature_class":"P",
    "gn:feature_code":"PPL",
    "gn:name":"Croce di Via",
    "gn:population":22,
    "gn:timezone":"Europe/Rome",
    "iso:country":"IT",
    "wof:name":"Croce di Via",
    "wof:placetype":"locality",
    "wof:population":22
},
  "geometry": {"coordinates":[11.15469,43.67329],"type":"Point"}
}