{
  "type": "Feature",
  "properties": {
    "gn:gn_country":"IT",
    "gn:gn_fcode":"PPLX",
    "gn:gn_pop":0,
    "iso:country":"IT",
    "name:fra_x_preferred":[
        "Port-Maurice"
    ],
    "name:lat_x_preferred":[
        "Portus Mauricii"
    ],
    "qs_pg:aaroncc":"IT",
    "qs_pg:gn_country":"IT",
    "qs_pg:gn_fcode":"PPLX",
    "qs_pg:gn_pop":0,
    "qs_pg:name":"Porto Maurizio",
    "qs_pg:name_adm0":"Italia",
    "qs_pg:name_adm1":"Liguria",
    "qs_pg:photos":522,
    "qs_pg:photos_1k":106,
    "qs_pg:photos_9k":17,
    "qs_pg:photos_9r":12,
    "qs_pg:photos_all":3772,
    "qs_pg:photos_sr":7,
    "qs_pg:pop_sr":0,
    "qs_pg:qs_pg_placetype":"locality_gp_neighbourhood_gn",
    "qs_pg:qs_pg_placetype_gp":"Town",
    "qs_pg:woe_adm0":23424853,
    "woe:adm0_id":23424853,
    "woe:name_adm0":"Italia",
    "woe:name_adm1":"Liguria",
    "woe:placetype":"Town",
    "wof:name":"Porto Maurizio",
    "wof:placetype":"locality"
},
  "geometry": {"coordinates":[8.01401,43.87439],"type":"Point"}
}