{
  "type": "Feature",
  "properties": {
    "gn:admin1_code":"9.0",
    "gn:admin2_code":"BS",
    "gn:admin3_code":"17092.0",
    "gn:asciiname":"Castel Venzago",
    "gn:country_code":"IT",
    "gn:dem":141,
    "gn:elevation":"142.0",
    "gn:feature_class":"P",
    "gn:feature_code":"PPL",
    "gn:name":"Castel Venzago",
    "gn:population":152,
    "gn:timezone":"Europe/Rome",
    "iso:country":"IT",
    "wof:name":"Castel Venzago",
    "wof:placetype":"locality",
    "wof:population":152
},
  "geometry": {"coordinates":[10.53456,45.42086],"type":"Point"}
}