{
  "type": "Feature",
  "properties": {
    "gn:admin1_code":"8",
    "gn:admin2_code":"GE",
    "gn:admin3_code":"10056.0",
    "gn:asciiname":"Montegrosso",
    "gn:country_code":"IT",
    "gn:dem":806,
    "gn:feature_class":"P",
    "gn:feature_code":"PPL",
    "gn:name":"Montegrosso",
    "gn:population":13,
    "gn:timezone":"Europe/Rome",
    "iso:country":"IT",
    "wof:name":"Montegrosso",
    "wof:placetype":"locality",
    "wof:population":13
},
  "geometry": {"coordinates":[9.45116,44.51843],"type":"Point"}
}