{
  "type": "Feature",
  "properties": {
    "gn:admin1_code":"8",
    "gn:admin2_code":"GE",
    "gn:admin3_code":"10056.0",
    "gn:asciiname":"Montegrosso",
    "gn:country_code":"IT",
    "gn:dem":806,
    "gn:feature_class":"P",
    "gn:feature_code":"PPL",
    "gn:name":"Montegrosso",
    "gn:population":13,
    "gn:timezone":"Europe/Rome",
    "iso:country":"IT",
    "name:cat_x_preferred":[
        "Montegrosso"
    ],
    "name:ceb_x_preferred":[
        "Montegrosso"
    ],
    "name:cos_x_preferred":[
        "Montegrossu"
    ],
    "name:deu_x_preferred":[
        "Montegrosso"
    ],
    "name:eus_x_preferred":[
        "Montegrosso"
    ],
    "name:fra_x_preferred":[
        "Montegrosso"
    ],
    "name:hun_x_preferred":[
        "Montegrosso"
    ],
    "name:ind_x_preferred":[
        "Montegrosso"
    ],
    "name:ita_x_preferred":[
        "Montegrosso"
    ],
    "name:kaz_x_preferred":[
        "\u041c\u043e\u043d\u0442\u0435\u0433\u0440\u043e\u0441\u0441\u043e"
    ],
    "name:lat_x_preferred":[
        "Montegrosso"
    ],
    "name:lmo_x_preferred":[
        "Montegrosso"
    ],
    "name:mlg_x_preferred":[
        "Montegrosso"
    ],
    "name:msa_x_preferred":[
        "Montegrosso"
    ],
    "name:nld_x_preferred":[
        "Montegrosso"
    ],
    "name:oci_x_preferred":[
        "Montegrosso"
    ],
    "name:pol_x_preferred":[
        "Montegrosso"
    ],
    "name:por_x_preferred":[
        "Montegrosso"
    ],
    "name:rus_x_preferred":[
        "\u041c\u043e\u043d\u0442\u0435\u0433\u0440\u043e\u0441\u0441\u043e"
    ],
    "name:slk_x_preferred":[
        "Montegrosso"
    ],
    "name:slv_x_preferred":[
        "Montegrosso"
    ],
    "name:spa_x_preferred":[
        "Montegrosso"
    ],
    "name:swe_x_preferred":[
        "Montegrosso"
    ],
    "name:ukr_x_preferred":[
        "\u041c\u043e\u043d\u0442\u0435\u0433\u0440\u043e\u0441\u0441\u043e"
    ],
    "name:vie_x_preferred":[
        "Montegrosso"
    ],
    "name:vol_x_preferred":[
        "Montegrosso"
    ],
    "name:war_x_preferred":[
        "Montegrosso"
    ],
    "wof:name":"Montegrosso",
    "wof:placetype":"locality",
    "wof:population":13
},
  "geometry": {"coordinates":[9.45116,44.51843],"type":"Point"}
}