{
  "type": "Feature",
  "properties": {
    "gn:admin1_code":"17.0",
    "gn:admin2_code":"BZ",
    "gn:admin3_code":"21042.0",
    "gn:asciiname":"Cengles",
    "gn:country_code":"IT",
    "gn:dem":952,
    "gn:elevation":"950.0",
    "gn:feature_class":"P",
    "gn:feature_code":"PPL",
    "gn:name":"Cengles",
    "gn:population":413,
    "gn:timezone":"Europe/Rome",
    "iso:country":"IT",
    "wof:name":"Cengles",
    "wof:placetype":"locality",
    "wof:population":413
},
  "geometry": {"coordinates":[10.63667,46.61261],"type":"Point"}
}