{
  "type": "Feature",
  "properties": {
    "gn:admin1_code":"12.0",
    "gn:admin2_code":"AL",
    "gn:admin3_code":"6102.0",
    "gn:asciiname":"Poggio",
    "gn:country_code":"IT",
    "gn:dem":580,
    "gn:elevation":"585.0",
    "gn:feature_class":"P",
    "gn:feature_code":"PPL",
    "gn:name":"Poggio",
    "gn:population":8,
    "gn:timezone":"Europe/Rome",
    "iso:country":"IT",
    "name:ceb_x_preferred":[
        "Poggio"
    ],
    "name:ces_x_preferred":[
        "Poggio"
    ],
    "name:deu_x_preferred":[
        "Poggio"
    ],
    "name:fas_x_preferred":[
        "\u067e\u0648\u062c\u06cc\u0648"
    ],
    "name:fra_x_preferred":[
        "Poggio"
    ],
    "name:ita_x_preferred":[
        "Poggio"
    ],
    "name:pol_x_preferred":[
        "Poggio"
    ],
    "name:por_x_preferred":[
        "Poggio"
    ],
    "name:rus_x_preferred":[
        "\u041f\u043e\u0434\u0436\u0438\u043e"
    ],
    "name:spa_x_preferred":[
        "Poggio"
    ],
    "name:srp_x_preferred":[
        "\u041f\u043e\u0452\u043e"
    ],
    "name:swe_x_preferred":[
        "Poggio"
    ],
    "name:ukr_x_preferred":[
        "\u041f\u043e\u0434\u0436\u0456\u043e"
    ],
    "wof:name":"Poggio",
    "wof:placetype":"locality",
    "wof:population":8
},
  "geometry": {"coordinates":[9.08681,44.76051],"type":"Point"}
}