{
  "type": "Feature",
  "properties": {
    "gn:admin1_code":"8",
    "gn:admin2_code":"SP",
    "gn:admin3_code":"11023.0",
    "gn:asciiname":"Falabiana",
    "gn:country_code":"IT",
    "gn:dem":376,
    "gn:feature_class":"P",
    "gn:feature_code":"PPL",
    "gn:name":"Falabiana",
    "gn:population":11,
    "gn:timezone":"Europe/Rome",
    "iso:country":"IT",
    "wof:name":"Falabiana",
    "wof:placetype":"locality",
    "wof:population":11
},
  "geometry": {"coordinates":[9.74701,44.15126],"type":"Point"}
}