{
  "type": "Feature",
  "properties": {
    "gn:admin1_code":"20",
    "gn:admin2_code":"PD",
    "gn:admin3_code":"28006.0",
    "gn:asciiname":"Case Neri",
    "gn:country_code":"IT",
    "gn:dem":2,
    "gn:feature_class":"P",
    "gn:feature_code":"PPL",
    "gn:name":"Case Neri",
    "gn:population":28,
    "gn:timezone":"Europe/Rome",
    "iso:country":"IT",
    "wof:name":"Case Neri",
    "wof:placetype":"locality",
    "wof:population":28
},
  "geometry": {"coordinates":[11.94803,45.19901],"type":"Point"}
}