{
  "type": "Feature",
  "properties": {
    "gn:gn_country":"IT",
    "gn:gn_fcode":"PPLA3",
    "gn:gn_pop":461,
    "gn:population":377,
    "iso:country":"IT",
    "name:arm_x_preferred":[
        "\u0533\u0561\u0562\u056b"
    ],
    "name:baq_x_preferred":[
        "Gaby"
    ],
    "name:bel_x_preferred":[
        "\u0413\u0430\u0431\u0456"
    ],
    "name:bul_x_preferred":[
        "\u0413\u0430\u0431\u0438"
    ],
    "name:cat_x_preferred":[
        "Gaby"
    ],
    "name:chi_x_preferred":[
        "\u52a0\u6bd4"
    ],
    "name:deu_x_preferred":[
        "Gaby"
    ],
    "name:dut_x_preferred":[
        "Gaby"
    ],
    "name:eng_x_preferred":[
        "Gaby"
    ],
    "name:epo_x_preferred":[
        "Gaby"
    ],
    "name:fra_x_preferred":[
        "Gaby"
    ],
    "name:fre_x_preferred":[
        "Gaby"
    ],
    "name:frp_x_preferred":[
        "Gabi"
    ],
    "name:ger_x_preferred":[
        "Gaby"
    ],
    "name:gre_x_preferred":[
        "\u0393\u03ba\u03b1\u03bc\u03c0\u03af"
    ],
    "name:gsw_x_preferred":[
        "Goaby"
    ],
    "name:hun_x_preferred":[
        "Gaby"
    ],
    "name:ina_x_preferred":[
        "Gaby"
    ],
    "name:ita_x_preferred":[
        "Gaby"
    ],
    "name:jpn_x_preferred":[
        "\u30ac\u30d6\u30a4"
    ],
    "name:kaz_x_preferred":[
        "\u0413\u0430\u0431\u0438"
    ],
    "name:lat_x_preferred":[
        "Gabbium"
    ],
    "name:lmo_x_preferred":[
        "Gaby"
    ],
    "name:may_x_preferred":[
        "Gaby"
    ],
    "name:nap_x_preferred":[
        "Gaby"
    ],
    "name:nld_x_preferred":[
        "Gaby"
    ],
    "name:oci_x_preferred":[
        "Gaby"
    ],
    "name:per_x_preferred":[
        "\u062c\u0627\u0628\u06cc"
    ],
    "name:pms_x_preferred":[
        "Gaby"
    ],
    "name:pol_x_preferred":[
        "Gaby"
    ],
    "name:por_x_preferred":[
        "Gaby"
    ],
    "name:rum_x_preferred":[
        "Gaby"
    ],
    "name:rus_x_preferred":[
        "\u0413\u0430\u0431\u0438"
    ],
    "name:scn_x_preferred":[
        "Gaby"
    ],
    "name:sco_x_preferred":[
        "Gaby"
    ],
    "name:spa_x_preferred":[
        "Gaby"
    ],
    "name:srp_x_preferred":[
        "Gaby"
    ],
    "name:tgl_x_preferred":[
        "Gaby"
    ],
    "name:ukr_x_preferred":[
        "\u0413\u0430\u0431\u0456"
    ],
    "name:uzb_x_preferred":[
        "Gaby"
    ],
    "name:vie_x_preferred":[
        "Gaby"
    ],
    "name:vol_x_preferred":[
        "Gaby"
    ],
    "name:war_x_preferred":[
        "Gaby"
    ],
    "qs_pg:aaroncc":"IT",
    "qs_pg:gn_country":"IT",
    "qs_pg:gn_fcode":"PPLA3",
    "qs_pg:gn_pop":461,
    "qs_pg:name":"Gaby",
    "qs_pg:name_adm0":"Italia",
    "qs_pg:name_adm1":"Valle d'Aosta",
    "qs_pg:photos":63,
    "qs_pg:photos_1k":13,
    "qs_pg:photos_9k":1,
    "qs_pg:photos_9r":2,
    "qs_pg:photos_all":63,
    "qs_pg:photos_sr":2,
    "qs_pg:pop_sr":2,
    "qs_pg:qs_pg_placetype":"locality",
    "qs_pg:qs_pg_placetype_gp":"Town",
    "qs_pg:woe_adm0":23424853,
    "woe:adm0_id":23424853,
    "woe:name_adm0":"Italia",
    "woe:name_adm1":"Valle d'Aosta",
    "woe:placetype":"Town",
    "wof:name":"Gaby",
    "wof:placetype":"locality",
    "wof:population":377
},
  "geometry": {"coordinates":[7.88281,45.71216],"type":"Point"}
}