{
  "type": "Feature",
  "properties": {
    "gn:admin1_code":"20",
    "gn:admin2_code":"PD",
    "gn:admin3_code":"28051.0",
    "gn:asciiname":"Frassenara",
    "gn:country_code":"IT",
    "gn:dem":9,
    "gn:feature_class":"P",
    "gn:feature_code":"PPL",
    "gn:name":"Frassenara",
    "gn:population":21,
    "gn:timezone":"Europe/Rome",
    "iso:country":"IT",
    "wof:name":"Frassenara",
    "wof:placetype":"locality",
    "wof:population":21
},
  "geometry": {"coordinates":[11.50478,45.22885],"type":"Point"}
}