{
  "type": "Feature",
  "properties": {
    "gn:elevation":545,
    "gn:population":852,
    "iso:country":"IT",
    "name:ita_x_preferred":[
        "Terreti"
    ],
    "qs:a0":"Italia",
    "qs:a1":"*Reggio di Calabria",
    "qs:a1r":"0Calabria",
    "qs:adm0":"Italia",
    "qs:la_lc":"*",
    "qs:level":"locality",
    "qs:loc":"Terreti",
    "qs:loc_alt":"Terreti",
    "qs:pop":0,
    "qs:type":"buffered point",
    "wof:lang":[
        "ita"
    ],
    "wof:name":"Terreti",
    "wof:placetype":"locality",
    "wof:population":852
},
  "geometry": {"coordinates":[15.71292,38.119049],"type":"Point"}
}