{
  "type": "Feature",
  "properties": {
    "gn:elevation":545,
    "gn:population":852,
    "iso:country":"IT",
    "name:bul_x_preferred":[
        "\u0422\u0435\u0440\u0435\u0442\u0438"
    ],
    "name:cat_x_preferred":[
        "Terreti"
    ],
    "name:ceb_x_preferred":[
        "Terreti"
    ],
    "name:ces_x_preferred":[
        "Terreti"
    ],
    "name:dan_x_preferred":[
        "Terreti"
    ],
    "name:eng_x_preferred":[
        "Terreti"
    ],
    "name:eus_x_preferred":[
        "Terreti"
    ],
    "name:fin_x_preferred":[
        "Terreti"
    ],
    "name:fra_x_preferred":[
        "Terreti"
    ],
    "name:ind_x_preferred":[
        "Terreti"
    ],
    "name:ita_x_preferred":[
        "Terreti"
    ],
    "name:nld_x_preferred":[
        "Terreti"
    ],
    "name:nno_x_preferred":[
        "Terreti"
    ],
    "name:nob_x_preferred":[
        "Terreti"
    ],
    "name:oci_x_preferred":[
        "Terreti"
    ],
    "name:pol_x_preferred":[
        "Terreti"
    ],
    "name:por_x_preferred":[
        "Terreti"
    ],
    "name:ron_x_preferred":[
        "Terreti"
    ],
    "name:slk_x_preferred":[
        "Terreti"
    ],
    "name:slv_x_preferred":[
        "Terreti"
    ],
    "name:spa_x_preferred":[
        "Terreti"
    ],
    "name:srp_x_preferred":[
        "Terreti"
    ],
    "name:swe_x_preferred":[
        "Terreti"
    ],
    "name:tgl_x_preferred":[
        "Terreti"
    ],
    "name:tur_x_preferred":[
        "Terreti"
    ],
    "name:war_x_preferred":[
        "Terreti"
    ],
    "qs:a0":"Italia",
    "qs:a1":"*Reggio di Calabria",
    "qs:a1r":"0Calabria",
    "qs:adm0":"Italia",
    "qs:la_lc":"*",
    "qs:level":"locality",
    "qs:loc":"Terreti",
    "qs:loc_alt":"Terreti",
    "qs:pop":0,
    "qs:type":"buffered point",
    "wof:name":"Terreti",
    "wof:placetype":"locality",
    "wof:population":852
},
  "geometry": {"coordinates":[15.71292,38.119049],"type":"Point"}
}