{
  "type": "Feature",
  "properties": {
    "iso:country":"IT",
    "name:eng_x_preferred":[
        "Quadrilatero"
    ],
    "name:ita_x_preferred":[
        "Quadrilatero"
    ],
    "wof:name":"Quadrilatero",
    "wof:placetype":"neighbourhood"
},
  "geometry": {"coordinates":[11.34419267906467,44.49251071632458],"type":"Point"}
}