{
  "type": "Feature",
  "properties": {
    "gn:admin1_code":"4",
    "gn:admin2_code":"CE",
    "gn:admin3_code":"61048.0",
    "gn:asciiname":"Galazia",
    "gn:country_code":"IT",
    "gn:dem":53,
    "gn:feature_class":"P",
    "gn:feature_code":"PPL",
    "gn:name":"Galazia",
    "gn:population":29,
    "gn:timezone":"Europe/Rome",
    "iso:country":"IT",
    "wof:name":"Galazia",
    "wof:placetype":"locality",
    "wof:population":29
},
  "geometry": {"coordinates":[14.36134,41.04274],"type":"Point"}
}