{
  "type": "Feature",
  "properties": {
    "gn:admin1_code":"9",
    "gn:admin2_code":"BG",
    "gn:admin3_code":"16252.0",
    "gn:asciiname":"Ronco",
    "gn:country_code":"IT",
    "gn:dem":462,
    "gn:feature_class":"P",
    "gn:feature_code":"PPL",
    "gn:name":"Ronco",
    "gn:population":27,
    "gn:timezone":"Europe/Rome",
    "iso:country":"IT",
    "wof:name":"Ronco",
    "wof:placetype":"locality",
    "wof:population":27
},
  "geometry": {"coordinates":[9.53708,45.79917],"type":"Point"}
}