{
  "type": "Feature",
  "properties": {
    "gn:admin1_code":"4.0",
    "gn:admin3_code":"63079.0",
    "gn:asciiname":"Lupa",
    "gn:country_code":"IT",
    "gn:dem":108,
    "gn:feature_class":"P",
    "gn:feature_code":"PPL",
    "gn:name":"Lupa",
    "gn:population":478,
    "gn:timezone":"Europe/Rome",
    "iso:country":"IT",
    "wof:name":"Lupa",
    "wof:placetype":"locality",
    "wof:population":478
},
  "geometry": {"coordinates":[14.41888,40.88148],"type":"Point"}
}