{
  "type": "Feature",
  "properties": {
    "gn:admin1_code":"9",
    "gn:admin2_code":"BG",
    "gn:admin3_code":"16110.0",
    "gn:asciiname":"Trate",
    "gn:country_code":"IT",
    "gn:dem":496,
    "gn:feature_class":"P",
    "gn:feature_code":"PPL",
    "gn:name":"Trate",
    "gn:population":209,
    "gn:timezone":"Europe/Rome",
    "iso:country":"IT",
    "wof:name":"Trate",
    "wof:placetype":"locality",
    "wof:population":209
},
  "geometry": {"coordinates":[9.89682,45.76053],"type":"Point"}
}