{
  "type": "Feature",
  "properties": {
    "gn:admin1_code":"10",
    "gn:admin2_code":"MC",
    "gn:admin3_code":"43052.0",
    "gn:asciiname":"Costa",
    "gn:country_code":"IT",
    "gn:dem":900,
    "gn:feature_class":"P",
    "gn:feature_code":"PPL",
    "gn:name":"Costa",
    "gn:population":40,
    "gn:timezone":"Europe/Rome",
    "iso:country":"IT",
    "wof:name":"Costa",
    "wof:placetype":"locality",
    "wof:population":40
},
  "geometry": {"coordinates":[12.92322,42.99349],"type":"Point"}
}