{
  "type": "Feature",
  "properties": {
    "gn:admin1_code":"6",
    "gn:admin2_code":"PN",
    "gn:admin3_code":"93037.0",
    "gn:asciiname":"Case Padernelli",
    "gn:country_code":"IT",
    "gn:dem":17,
    "gn:feature_class":"P",
    "gn:feature_code":"PPL",
    "gn:name":"Case Padernelli",
    "gn:population":59,
    "gn:timezone":"Europe/Rome",
    "iso:country":"IT",
    "wof:name":"Case Padernelli",
    "wof:placetype":"locality",
    "wof:population":59
},
  "geometry": {"coordinates":[12.51724,45.93353],"type":"Point"}
}