{
  "type": "Feature",
  "properties": {
    "gn:admin1_code":"12",
    "gn:admin2_code":"AT",
    "gn:admin3_code":"5058.0",
    "gn:asciiname":"Briccomonte-Stazione",
    "gn:country_code":"IT",
    "gn:dem":139,
    "gn:feature_class":"P",
    "gn:feature_code":"PPL",
    "gn:name":"Briccomonte-Stazione",
    "gn:population":37,
    "gn:timezone":"Europe/Rome",
    "iso:country":"IT",
    "wof:name":"Briccomonte-Stazione",
    "wof:placetype":"locality",
    "wof:population":37
},
  "geometry": {"coordinates":[8.38689,44.80087],"type":"Point"}
}