{
  "type": "Feature",
  "properties": {
    "gn:admin1_code":"6.0",
    "gn:admin2_code":"PN",
    "gn:admin3_code":"93022.0",
    "gn:asciiname":"Schiavol",
    "gn:country_code":"IT",
    "gn:dem":24,
    "gn:feature_class":"P",
    "gn:feature_code":"PPL",
    "gn:name":"Schiavol",
    "gn:population":0,
    "gn:timezone":"Europe/Rome",
    "iso:country":"IT",
    "wof:name":"Schiavol",
    "wof:placetype":"locality"
},
  "geometry": {"coordinates":[12.55417,45.94472],"type":"Point"}
}