{
  "type": "Feature",
  "properties": {
    "gn:admin1_code":"20",
    "gn:admin2_code":"TV",
    "gn:admin3_code":"26058.0",
    "gn:asciiname":"Concie",
    "gn:country_code":"IT",
    "gn:dem":13,
    "gn:feature_class":"P",
    "gn:feature_code":"PPL",
    "gn:name":"Concie",
    "gn:population":39,
    "gn:timezone":"Europe/Rome",
    "iso:country":"IT",
    "wof:name":"Concie",
    "wof:placetype":"locality",
    "wof:population":39
},
  "geometry": {"coordinates":[12.41742,45.74218],"type":"Point"}
}