{
  "type": "Feature",
  "properties": {
    "gn:admin1_code":"20.0",
    "gn:admin2_code":"VE",
    "gn:admin3_code":"27025.0",
    "gn:asciiname":"Intestadura",
    "gn:country_code":"IT",
    "gn:dem":2,
    "gn:feature_class":"P",
    "gn:feature_code":"PPL",
    "gn:name":"Intestadura",
    "gn:population":0,
    "gn:timezone":"Europe/Rome",
    "iso:country":"IT",
    "wof:name":"Intestadura",
    "wof:placetype":"locality"
},
  "geometry": {"coordinates":[12.57132,45.61572],"type":"Point"}
}