{
  "type": "Feature",
  "properties": {
    "iso:country":"IT",
    "name:ceb_x_preferred":[
        "Diamantina"
    ],
    "name:nld_x_preferred":[
        "Diamantina"
    ],
    "name:pol_x_preferred":[
        "Diamantina"
    ],
    "name:slk_x_preferred":[
        "Diamantina"
    ],
    "name:swe_x_preferred":[
        "Diamantina"
    ],
    "qs_pg:aaroncc":"IT",
    "qs_pg:name":"Diamantina",
    "qs_pg:name_adm0":"Italia",
    "qs_pg:name_adm1":"Emilia Romagna",
    "qs_pg:photos":49,
    "qs_pg:photos_1k":10,
    "qs_pg:photos_9k":1,
    "qs_pg:photos_9r":2,
    "qs_pg:photos_all":49,
    "qs_pg:photos_sr":2,
    "qs_pg:pop_sr":0,
    "qs_pg:qs_pg_placetype":"locality",
    "qs_pg:qs_pg_placetype_gp":"Town",
    "qs_pg:woe_adm0":23424853,
    "woe:adm0_id":23424853,
    "woe:name_adm0":"Italia",
    "woe:name_adm1":"Emilia Romagna",
    "woe:placetype":"Town",
    "wof:name":"Diamantina",
    "wof:placetype":"locality"
},
  "geometry": {"coordinates":[11.509294,44.885613],"type":"Point"}
}