{
  "type": "Feature",
  "properties": {
    "gn:elevation":766,
    "gn:population":472,
    "iso:country":"IT",
    "name:arm_x_preferred":[
        "\u0533\u0578\u0580\u0563\u0561"
    ],
    "name:baq_x_preferred":[
        "Gorga"
    ],
    "name:bcl_x_preferred":[
        "Gorga"
    ],
    "name:bul_x_preferred":[
        "\u0413\u043e\u0440\u0433\u0430"
    ],
    "name:chi_x_preferred":[
        "\u6208\u5c14\u52a0"
    ],
    "name:deu_x_preferred":[
        "Gorga"
    ],
    "name:dut_x_preferred":[
        "Gorga"
    ],
    "name:eng_x_preferred":[
        "Gorga"
    ],
    "name:epo_x_preferred":[
        "Gorga"
    ],
    "name:eus_x_preferred":[
        "Gorga"
    ],
    "name:fra_x_preferred":[
        "Gorga"
    ],
    "name:fre_x_preferred":[
        "Gorga"
    ],
    "name:ger_x_preferred":[
        "Gorga"
    ],
    "name:glg_x_preferred":[
        "Gorga"
    ],
    "name:hbs_x_preferred":[
        "Gorga"
    ],
    "name:hun_x_preferred":[
        "Gorga"
    ],
    "name:hye_x_preferred":[
        "\u0533\u0578\u0580\u0563\u0561"
    ],
    "name:ina_x_preferred":[
        "Gorga"
    ],
    "name:ita_x_preferred":[
        "Gorga"
    ],
    "name:jpn_x_preferred":[
        "\u30b4\u30eb\u30ac"
    ],
    "name:kor_x_preferred":[
        "\uace0\ub974\uac00"
    ],
    "name:lat_x_preferred":[
        "Gorga"
    ],
    "name:lmo_x_preferred":[
        "Gorga"
    ],
    "name:may_x_preferred":[
        "Gorga"
    ],
    "name:msa_x_preferred":[
        "Gorga"
    ],
    "name:nan_x_preferred":[
        "Gorga"
    ],
    "name:nap_x_preferred":[
        "Gorga"
    ],
    "name:nld_x_preferred":[
        "Gorga"
    ],
    "name:nno_x_preferred":[
        "Gorga"
    ],
    "name:nob_x_preferred":[
        "Gorga"
    ],
    "name:pms_x_preferred":[
        "Gorga"
    ],
    "name:pol_x_preferred":[
        "Gorga"
    ],
    "name:por_x_preferred":[
        "Gorga"
    ],
    "name:ron_x_preferred":[
        "Gorga"
    ],
    "name:rum_x_preferred":[
        "Gorga"
    ],
    "name:rus_x_preferred":[
        "\u0413\u043e\u0440\u0433\u0430"
    ],
    "name:scn_x_preferred":[
        "Gorga"
    ],
    "name:sco_x_preferred":[
        "Gorga"
    ],
    "name:slv_x_preferred":[
        "Gorga"
    ],
    "name:spa_x_preferred":[
        "Gorga"
    ],
    "name:srp_x_preferred":[
        "\u0413\u043e\u0440\u0433\u0430"
    ],
    "name:ukr_x_preferred":[
        "\u0413\u043e\u0440\u0433\u0430"
    ],
    "name:vie_x_preferred":[
        "Gorga"
    ],
    "name:vol_x_preferred":[
        "Gorga"
    ],
    "name:war_x_preferred":[
        "Gorga"
    ],
    "name:zho_min_nan_x_preferred":[
        "Gorga"
    ],
    "name:zho_x_preferred":[
        "\u6208\u5c14\u52a0"
    ],
    "qs:a0":"Italia",
    "qs:a1":"*Roma",
    "qs:a1r":"0Lazio",
    "qs:adm0":"Italia",
    "qs:la_lc":"*",
    "qs:level":"locality",
    "qs:loc":"Gorga",
    "qs:loc_alt":"Gorga",
    "qs:pop":0,
    "qs:type":"buffered point",
    "wd:wordcount":108,
    "wof:lang":[
        "ita"
    ],
    "wof:name":"Gorga",
    "wof:placetype":"locality",
    "wof:population":472
},
  "geometry": {"coordinates":[13.11,41.655831],"type":"Point"}
}