{
  "type": "Feature",
  "properties": {
    "gn:admin1_code":"4",
    "gn:admin2_code":"AV",
    "gn:admin3_code":"64078.0",
    "gn:asciiname":"Vernilli",
    "gn:country_code":"IT",
    "gn:dem":396,
    "gn:feature_class":"P",
    "gn:feature_code":"PPL",
    "gn:name":"Vernilli",
    "gn:population":73,
    "gn:timezone":"Europe/Rome",
    "iso:country":"IT",
    "wof:name":"Vernilli",
    "wof:placetype":"locality",
    "wof:population":73
},
  "geometry": {"coordinates":[14.71351,41.04059],"type":"Point"}
}