{
  "type": "Feature",
  "properties": {
    "gn:admin1_code":"1.0",
    "gn:admin2_code":"AQ",
    "gn:admin3_code":"66054.0",
    "gn:asciiname":"Albe",
    "gn:country_code":"IT",
    "gn:dem":968,
    "gn:feature_class":"P",
    "gn:feature_code":"PPL",
    "gn:name":"Albe",
    "gn:population":83,
    "gn:timezone":"Europe/Rome",
    "iso:country":"IT",
    "wof:name":"Albe",
    "wof:placetype":"locality",
    "wof:population":83
},
  "geometry": {"coordinates":[13.4092,42.08104],"type":"Point"}
}