{
  "type": "Feature",
  "properties": {
    "gn:admin1_code":"3.0",
    "gn:admin2_code":"CZ",
    "gn:admin3_code":"79034.0",
    "gn:asciiname":"Casa Pellegrino",
    "gn:cc2":"IT",
    "gn:country_code":"IT",
    "gn:dem":151,
    "gn:feature_class":"P",
    "gn:feature_code":"PPL",
    "gn:name":"Casa Pellegrino",
    "gn:population":0,
    "gn:timezone":"Europe/Rome",
    "iso:country":"IT",
    "name:und_x_variant":[
        "Scuteri",
        "Casa Pellegrino"
    ],
    "wof:name":"Casa Pellegrino",
    "wof:placetype":"locality"
},
  "geometry": {"coordinates":[16.41667,38.86667],"type":"Point"}
}