{
  "type": "Feature",
  "properties": {
    "gn:admin1_code":"12",
    "gn:admin2_code":"AT",
    "gn:admin3_code":"5058.0",
    "gn:asciiname":"Borgo Villa - Il Poggio",
    "gn:country_code":"IT",
    "gn:dem":187,
    "gn:feature_class":"P",
    "gn:feature_code":"PPL",
    "gn:name":"Borgo Villa - Il Poggio",
    "gn:population":137,
    "gn:timezone":"Europe/Rome",
    "iso:country":"IT",
    "wof:name":"Borgo Villa - Il Poggio",
    "wof:placetype":"locality",
    "wof:population":137
},
  "geometry": {"coordinates":[8.38665,44.80716],"type":"Point"}
}