{
  "type": "Feature",
  "properties": {
    "gn:admin1_code":"7",
    "gn:admin2_code":"LT",
    "gn:admin3_code":"59015.0",
    "gn:asciiname":"Valle Marina",
    "gn:country_code":"IT",
    "gn:dem":5,
    "gn:feature_class":"P",
    "gn:feature_code":"PPL",
    "gn:name":"Valle Marina",
    "gn:population":40,
    "gn:timezone":"Europe/Rome",
    "iso:country":"IT",
    "wof:name":"Valle Marina",
    "wof:placetype":"locality",
    "wof:population":40
},
  "geometry": {"coordinates":[13.31515,41.33391],"type":"Point"}
}