{
  "type": "Feature",
  "properties": {
    "gn:admin1_code":"12.0",
    "gn:admin2_code":"TO",
    "gn:admin3_code":"1242.0",
    "gn:asciiname":"Chiotasso",
    "gn:country_code":"IT",
    "gn:dem":803,
    "gn:feature_class":"P",
    "gn:feature_code":"PPLL",
    "gn:name":"Chiotasso",
    "gn:population":3,
    "gn:timezone":"Europe/Rome",
    "iso:country":"IT",
    "wof:name":"Chiotasso",
    "wof:placetype":"locality",
    "wof:population":3
},
  "geometry": {"coordinates":[7.23346,44.87477],"type":"Point"}
}