{
  "type": "Feature",
  "properties": {
    "gn:admin1_code":"8",
    "gn:admin2_code":"SV",
    "gn:admin3_code":"9004.0",
    "gn:asciiname":"Porzi",
    "gn:country_code":"IT",
    "gn:dem":170,
    "gn:feature_class":"P",
    "gn:feature_code":"PPL",
    "gn:name":"Porzi",
    "gn:population":14,
    "gn:timezone":"Europe/Rome",
    "iso:country":"IT",
    "name:fas_x_preferred":[
        "\u067e\u0631\u0632\u06cc"
    ],
    "name:msa_x_preferred":[
        "Porzi"
    ],
    "wof:name":"Porzi",
    "wof:placetype":"locality",
    "wof:population":14
},
  "geometry": {"coordinates":[8.51081,44.35793],"type":"Point"}
}