{
  "type": "Feature",
  "properties": {
    "gn:admin1_code":"7",
    "gn:admin2_code":"FR",
    "gn:admin3_code":"60063.0",
    "gn:asciiname":"Giuliani",
    "gn:country_code":"IT",
    "gn:dem":47,
    "gn:feature_class":"P",
    "gn:feature_code":"PPL",
    "gn:name":"Giuliani",
    "gn:population":28,
    "gn:timezone":"Europe/Rome",
    "iso:country":"IT",
    "name:deu_x_preferred":[
        "Giuliani"
    ],
    "name:nds_x_preferred":[
        "Giuliani"
    ],
    "wof:name":"Giuliani",
    "wof:placetype":"locality",
    "wof:population":28
},
  "geometry": {"coordinates":[13.74247,41.40492],"type":"Point"}
}