{
  "type": "Feature",
  "properties": {
    "gn:admin1_code":"18.0",
    "gn:admin2_code":"PG",
    "gn:admin3_code":"54024.0",
    "gn:asciiname":"Casanova di Torre",
    "gn:country_code":"IT",
    "gn:dem":413,
    "gn:feature_class":"P",
    "gn:feature_code":"PPL",
    "gn:name":"Casanova di Torre",
    "gn:population":811,
    "gn:timezone":"Europe/Rome",
    "iso:country":"IT",
    "wof:name":"Casanova di Torre",
    "wof:placetype":"locality",
    "wof:population":811
},
  "geometry": {"coordinates":[12.66031,43.2926],"type":"Point"}
}