{
  "type": "Feature",
  "properties": {
    "gn:admin1_code":"5.0",
    "gn:admin2_code":"RE",
    "gn:admin3_code":"35010.0",
    "gn:asciiname":"Case Cocconi",
    "gn:country_code":"IT",
    "gn:dem":35,
    "gn:feature_class":"P",
    "gn:feature_code":"PPL",
    "gn:name":"Case Cocconi",
    "gn:population":513,
    "gn:timezone":"Europe/Rome",
    "iso:country":"IT",
    "wof:name":"Case Cocconi",
    "wof:placetype":"locality",
    "wof:population":513
},
  "geometry": {"coordinates":[10.52383,44.78952],"type":"Point"}
}