{
  "type": "Feature",
  "properties": {
    "gn:admin1_code":"3",
    "gn:admin2_code":"RC",
    "gn:admin3_code":"80020.0",
    "gn:asciiname":"Giannarena",
    "gn:country_code":"IT",
    "gn:dem":617,
    "gn:feature_class":"P",
    "gn:feature_code":"PPL",
    "gn:name":"Giannarena",
    "gn:population":14,
    "gn:timezone":"Europe/Rome",
    "iso:country":"IT",
    "wof:name":"Giannarena",
    "wof:placetype":"locality",
    "wof:population":14
},
  "geometry": {"coordinates":[16.19009,38.29584000000001],"type":"Point"}
}