{
  "type": "Feature",
  "properties": {
    "gn:admin1_code":"4.0",
    "gn:admin2_code":"CE",
    "gn:admin3_code":"61036.0",
    "gn:asciiname":"Montanaro",
    "gn:country_code":"IT",
    "gn:dem":88,
    "gn:feature_class":"P",
    "gn:feature_code":"PPL",
    "gn:name":"Montanaro",
    "gn:population":154,
    "gn:timezone":"Europe/Rome",
    "iso:country":"IT",
    "wof:name":"Montanaro",
    "wof:placetype":"locality",
    "wof:population":154
},
  "geometry": {"coordinates":[14.07604,41.20389],"type":"Point"}
}