{
  "type": "Feature",
  "properties": {
    "gn:admin1_code":"4.0",
    "gn:admin2_code":"CE",
    "gn:admin3_code":"61036.0",
    "gn:asciiname":"Montanaro",
    "gn:country_code":"IT",
    "gn:dem":88,
    "gn:feature_class":"P",
    "gn:feature_code":"PPL",
    "gn:name":"Montanaro",
    "gn:population":154,
    "gn:timezone":"Europe/Rome",
    "iso:country":"IT",
    "name:azb_x_preferred":[
        "\u0645\u0648\u0646\u062a\u0627\u0646\u0627\u0631\u0648"
    ],
    "name:bel_x_preferred":[
        "\u041c\u0430\u043d\u0442\u0430\u043d\u0430\u0440\u0430"
    ],
    "name:bul_x_preferred":[
        "\u041c\u043e\u043d\u0442\u0430\u043d\u0430\u0440\u043e"
    ],
    "name:ceb_x_preferred":[
        "Montanaro"
    ],
    "name:deu_x_preferred":[
        "Montanaro"
    ],
    "name:epo_x_preferred":[
        "Montanaro"
    ],
    "name:eus_x_preferred":[
        "Montanaro"
    ],
    "name:fas_x_preferred":[
        "\u0645\u0648\u0646\u062a\u0627\u0646\u0627\u0631\u0648"
    ],
    "name:fra_x_preferred":[
        "Montanaro"
    ],
    "name:hun_x_preferred":[
        "Montanaro"
    ],
    "name:hye_x_preferred":[
        "\u0544\u0578\u0576\u057f\u0561\u0576\u0561\u0580\u0578"
    ],
    "name:ind_x_preferred":[
        "Montanaro"
    ],
    "name:ita_x_preferred":[
        "Montanaro"
    ],
    "name:jpn_x_preferred":[
        "\u30e2\u30f3\u30bf\u30ca\u30fc\u30ed"
    ],
    "name:kaz_x_preferred":[
        "\u041c\u043e\u043d\u0442\u0430\u043d\u0430\u0440\u043e"
    ],
    "name:lat_x_preferred":[
        "Montanarius"
    ],
    "name:lmo_x_preferred":[
        "Montanaro"
    ],
    "name:msa_x_preferred":[
        "Montanaro"
    ],
    "name:nap_x_preferred":[
        "Montanaro"
    ],
    "name:nld_x_preferred":[
        "Montanaro"
    ],
    "name:pms_x_preferred":[
        "Montanar"
    ],
    "name:pol_x_preferred":[
        "Montanaro"
    ],
    "name:por_x_preferred":[
        "Montanaro"
    ],
    "name:ron_x_preferred":[
        "Montanaro"
    ],
    "name:rus_x_preferred":[
        "\u041c\u043e\u043d\u0442\u0430\u043d\u0430\u0440\u043e"
    ],
    "name:scn_x_preferred":[
        "Montanaro"
    ],
    "name:spa_x_preferred":[
        "Montanaro"
    ],
    "name:srp_x_preferred":[
        "\u041c\u043e\u043d\u0442\u0430\u043d\u0430\u0440\u043e"
    ],
    "name:swe_x_preferred":[
        "Montanaro"
    ],
    "name:tgl_x_preferred":[
        "Montanaro"
    ],
    "name:ukr_x_preferred":[
        "\u041c\u043e\u043d\u0442\u0430\u043d\u0430\u0440\u043e"
    ],
    "name:uzb_x_preferred":[
        "Montanaro"
    ],
    "name:vie_x_preferred":[
        "Montanaro"
    ],
    "name:vol_x_preferred":[
        "Montanaro"
    ],
    "name:war_x_preferred":[
        "Montanaro"
    ],
    "name:zho_x_preferred":[
        "\u8499\u5854\u7eb3\u7f57"
    ],
    "wof:name":"Montanaro",
    "wof:placetype":"locality",
    "wof:population":154
},
  "geometry": {"coordinates":[14.07604,41.20389],"type":"Point"}
}