{
  "type": "Feature",
  "properties": {
    "gn:admin1_code":"6",
    "gn:admin2_code":"UD",
    "gn:admin3_code":"30076.0",
    "gn:asciiname":"Graben",
    "gn:country_code":"IT",
    "gn:dem":621,
    "gn:feature_class":"P",
    "gn:feature_code":"PPL",
    "gn:name":"Graben",
    "gn:population":12,
    "gn:timezone":"Europe/Rome",
    "iso:country":"IT",
    "wof:name":"Graben",
    "wof:placetype":"locality",
    "wof:population":12
},
  "geometry": {"coordinates":[13.28844,46.5187],"type":"Point"}
}