{
  "type": "Feature",
  "properties": {
    "gn:admin1_code":"15.0",
    "gn:admin2_code":"RG",
    "gn:admin3_code":"88008.0",
    "gn:asciiname":"Pozzallo",
    "gn:country_code":"IT",
    "gn:dem":11,
    "gn:elevation":"20.0",
    "gn:feature_class":"P",
    "gn:feature_code":"PPLA3",
    "gn:name":"Pozzallo",
    "gn:population":18166,
    "gn:timezone":"Europe/Rome",
    "iso:country":"IT",
    "name:deu_x_preferred":[
        "Pozzallo"
    ],
    "name:eng_x_preferred":[
        "Pozzallo"
    ],
    "name:epo_x_preferred":[
        "Pozzallo"
    ],
    "name:fra_x_preferred":[
        "Pozzallo"
    ],
    "name:ita_x_preferred":[
        "Pozzallo"
    ],
    "name:jpn_x_preferred":[
        "\u30dd\u30c3\u30c4\u30a1\u30c3\u30ed"
    ],
    "name:nap_x_preferred":[
        "Pozzallo"
    ],
    "name:nld_x_preferred":[
        "Pozzallo"
    ],
    "name:pol_x_preferred":[
        "Pozzallo"
    ],
    "name:por_x_preferred":[
        "Pozzallo"
    ],
    "name:scn_x_preferred":[
        "Puzzaddu"
    ],
    "wof:name":"Pozzallo",
    "wof:placetype":"locality",
    "wof:population":18166
},
  "geometry": {"coordinates":[14.84672,36.73028],"type":"Point"}
}