{
  "type": "Feature",
  "properties": {
    "gn:admin1_code":"20.0",
    "gn:admin2_code":"VE",
    "gn:admin3_code":"27036.0",
    "gn:asciiname":"Biverone",
    "gn:country_code":"IT",
    "gn:dem":0,
    "gn:feature_class":"P",
    "gn:feature_code":"PPL",
    "gn:name":"Biverone",
    "gn:population":441,
    "gn:timezone":"Europe/Rome",
    "iso:country":"IT",
    "wof:name":"Biverone",
    "wof:placetype":"locality",
    "wof:population":441
},
  "geometry": {"coordinates":[12.71431,45.6946],"type":"Point"}
}