{
  "type": "Feature",
  "properties": {
    "gn:admin1_code":"9.0",
    "gn:admin2_code":"MI",
    "gn:admin3_code":"15202.0",
    "gn:asciiname":"Villa Bissone",
    "gn:country_code":"IT",
    "gn:dem":86,
    "gn:feature_class":"P",
    "gn:feature_code":"PPL",
    "gn:name":"Villa Bissone",
    "gn:population":467,
    "gn:timezone":"Europe/Rome",
    "iso:country":"IT",
    "wof:name":"Villa Bissone",
    "wof:placetype":"locality",
    "wof:population":467
},
  "geometry": {"coordinates":[9.3633,45.33796],"type":"Point"}
}