{
  "type": "Feature",
  "properties": {
    "gn:admin1_code":"17.0",
    "gn:admin2_code":"TN",
    "gn:admin3_code":"22009.0",
    "gn:asciiname":"Prada",
    "gn:country_code":"IT",
    "gn:dem":915,
    "gn:elevation":"928.0",
    "gn:feature_class":"P",
    "gn:feature_code":"PPLL",
    "gn:name":"Prada",
    "gn:population":0,
    "gn:timezone":"Europe/Rome",
    "iso:country":"IT",
    "name:ara_x_preferred":[
        "\u0628\u0631\u0627\u062f\u0627"
    ],
    "name:arz_x_preferred":[
        "\u0628\u0631\u0627\u062f\u0627"
    ],
    "name:azb_x_preferred":[
        "\u067e\u0631\u0627\u062f\u0627"
    ],
    "name:aze_x_preferred":[
        "Prada"
    ],
    "name:cat_x_preferred":[
        "Prada"
    ],
    "name:ces_x_preferred":[
        "Prada"
    ],
    "name:dan_x_preferred":[
        "Prada"
    ],
    "name:deu_x_preferred":[
        "Prada"
    ],
    "name:fas_x_preferred":[
        "\u067e\u0631\u0627\u062f\u0627"
    ],
    "name:fin_x_preferred":[
        "Prada"
    ],
    "name:fra_x_preferred":[
        "Prada"
    ],
    "name:gan_x_preferred":[
        "Prada"
    ],
    "name:glg_x_preferred":[
        "Prada"
    ],
    "name:heb_x_preferred":[
        "\u05e4\u05e8\u05d0\u05d3\u05d4"
    ],
    "name:hin_x_preferred":[
        "\u092a\u094d\u0930\u093e\u0926\u093e"
    ],
    "name:hun_x_preferred":[
        "Prada"
    ],
    "name:hye_x_preferred":[
        "\u054a\u0580\u0561\u0564\u0561"
    ],
    "name:ind_x_preferred":[
        "Prada"
    ],
    "name:ita_x_preferred":[
        "Prada"
    ],
    "name:jav_x_preferred":[
        "Prada"
    ],
    "name:jpn_x_preferred":[
        "\u30d7\u30e9\u30c0"
    ],
    "name:kat_x_preferred":[
        "Prada"
    ],
    "name:kor_x_preferred":[
        "\ud504\ub77c\ub2e4"
    ],
    "name:lav_x_preferred":[
        "Prada"
    ],
    "name:lit_x_preferred":[
        "Prada"
    ],
    "name:mkd_x_preferred":[
        "\u041f\u0440\u0430\u0434\u0430"
    ],
    "name:msa_x_preferred":[
        "Prada"
    ],
    "name:nld_x_preferred":[
        "Prada"
    ],
    "name:nor_x_preferred":[
        "Prada"
    ],
    "name:pan_x_preferred":[
        "\u0a2a\u0a30\u0a3e\u0a21\u0a3e"
    ],
    "name:pol_x_preferred":[
        "Prada"
    ],
    "name:por_x_preferred":[
        "Prada"
    ],
    "name:ron_x_preferred":[
        "Prada"
    ],
    "name:rus_x_preferred":[
        "Prada"
    ],
    "name:sco_x_preferred":[
        "Prada"
    ],
    "name:slk_x_preferred":[
        "Prada"
    ],
    "name:srp_x_preferred":[
        "\u041f\u0440\u0430\u0434\u0430"
    ],
    "name:swe_x_preferred":[
        "Prada"
    ],
    "name:tam_x_preferred":[
        "\u0baa\u0bbf\u0bb0\u0bbe\u0b9f\u0bbe"
    ],
    "name:tur_x_preferred":[
        "Prada"
    ],
    "name:ukr_x_preferred":[
        "Prada"
    ],
    "name:vie_x_preferred":[
        "Prada"
    ],
    "name:zho_x_preferred":[
        "\u666e\u62c9\u9054"
    ],
    "wof:name":"Prada",
    "wof:placetype":"locality"
},
  "geometry": {"coordinates":[11.24897,46.11409],"type":"Point"}
}