{
  "type": "Feature",
  "properties": {
    "gn:admin1_code":"17.0",
    "gn:admin2_code":"TN",
    "gn:admin3_code":"22009.0",
    "gn:asciiname":"Prada",
    "gn:country_code":"IT",
    "gn:dem":915,
    "gn:elevation":"928.0",
    "gn:feature_class":"P",
    "gn:feature_code":"PPLL",
    "gn:name":"Prada",
    "gn:population":0,
    "gn:timezone":"Europe/Rome",
    "iso:country":"IT",
    "wof:name":"Prada",
    "wof:placetype":"locality"
},
  "geometry": {"coordinates":[11.24897,46.11409],"type":"Point"}
}