{
  "type": "Feature",
  "properties": {
    "gn:admin1_code":"1.0",
    "gn:admin2_code":"TE",
    "gn:admin3_code":"67041.0",
    "gn:asciiname":"Ponzano",
    "gn:country_code":"IT",
    "gn:dem":283,
    "gn:feature_class":"P",
    "gn:feature_code":"PPL",
    "gn:name":"Ponzano",
    "gn:population":36,
    "gn:timezone":"Europe/Rome",
    "iso:country":"IT",
    "name:ceb_x_preferred":[
        "Ponzano"
    ],
    "name:deu_x_preferred":[
        "Ponzano"
    ],
    "name:fra_x_preferred":[
        "Ponzano"
    ],
    "name:ita_x_preferred":[
        "Ponzano"
    ],
    "name:lat_x_preferred":[
        "Pontianum"
    ],
    "name:por_x_preferred":[
        "Ponzano"
    ],
    "name:rus_x_preferred":[
        "\u041f\u043e\u043d\u0446\u0430\u043d\u043e"
    ],
    "name:srp_x_preferred":[
        "Poncano"
    ],
    "name:swe_x_preferred":[
        "Ponzano"
    ],
    "wof:name":"Ponzano",
    "wof:placetype":"locality",
    "wof:population":36
},
  "geometry": {"coordinates":[13.72535,42.69897],"type":"Point"}
}