{
  "type": "Feature",
  "properties": {
    "gn:admin1_code":"20",
    "gn:admin2_code":"PD",
    "gn:admin3_code":"28023.0",
    "gn:asciiname":"Borghi",
    "gn:country_code":"IT",
    "gn:dem":51,
    "gn:feature_class":"P",
    "gn:feature_code":"PPL",
    "gn:name":"Borghi",
    "gn:population":47,
    "gn:timezone":"Europe/Rome",
    "iso:country":"IT",
    "wof:name":"Borghi",
    "wof:placetype":"locality",
    "wof:population":47
},
  "geometry": {"coordinates":[11.68379,45.64576],"type":"Point"}
}