{
  "type": "Feature",
  "properties": {
    "gn:admin1_code":"20",
    "gn:admin2_code":"PD",
    "gn:admin3_code":"28023.0",
    "gn:asciiname":"Borghi",
    "gn:country_code":"IT",
    "gn:dem":51,
    "gn:feature_class":"P",
    "gn:feature_code":"PPL",
    "gn:name":"Borghi",
    "gn:population":47,
    "gn:timezone":"Europe/Rome",
    "iso:country":"IT",
    "name:ara_x_preferred":[
        "\u0628\u0648\u0631\u063a\u064a"
    ],
    "name:azb_x_preferred":[
        "\u0628\u0648\u0631\u0642\u06cc"
    ],
    "name:bel_x_preferred":[
        "\u0411\u043e\u0440\u0433\u0456"
    ],
    "name:bul_x_preferred":[
        "\u0411\u043e\u0440\u0433\u0438"
    ],
    "name:ceb_x_preferred":[
        "Borghi"
    ],
    "name:deu_x_preferred":[
        "Borghi"
    ],
    "name:eml_x_preferred":[
        "I Burch"
    ],
    "name:epo_x_preferred":[
        "Borghi"
    ],
    "name:eus_x_preferred":[
        "Borghi"
    ],
    "name:fas_x_preferred":[
        "\u0628\u0648\u0631\u06af\u06cc"
    ],
    "name:fra_x_preferred":[
        "Borghi"
    ],
    "name:hun_x_preferred":[
        "Borghi"
    ],
    "name:hye_x_preferred":[
        "\u0532\u0578\u0580\u0563\u056b"
    ],
    "name:ina_x_preferred":[
        "Borghi"
    ],
    "name:ita_x_preferred":[
        "Borghi"
    ],
    "name:jpn_x_preferred":[
        "\u30dc\u30eb\u30ae"
    ],
    "name:kaz_x_preferred":[
        "\u0411\u043e\u0440\u0433\u0438"
    ],
    "name:lmo_x_preferred":[
        "Borghi"
    ],
    "name:msa_x_preferred":[
        "Borghi"
    ],
    "name:nap_x_preferred":[
        "Borghi"
    ],
    "name:nld_x_preferred":[
        "Borghi"
    ],
    "name:pms_x_preferred":[
        "Borghi"
    ],
    "name:pol_x_preferred":[
        "Borghi"
    ],
    "name:por_x_preferred":[
        "Borghi"
    ],
    "name:ron_x_preferred":[
        "Borghi"
    ],
    "name:rus_x_preferred":[
        "\u0411\u043e\u0440\u0433\u0438"
    ],
    "name:sco_x_preferred":[
        "Borghi"
    ],
    "name:spa_x_preferred":[
        "Borghi"
    ],
    "name:srp_x_preferred":[
        "\u0411\u043e\u0440\u0433\u0438"
    ],
    "name:ukr_x_preferred":[
        "\u0411\u043e\u0440\u0433\u0456"
    ],
    "name:uzb_x_preferred":[
        "Borghi"
    ],
    "name:vec_x_preferred":[
        "Borghi"
    ],
    "name:vie_x_preferred":[
        "Borghi"
    ],
    "name:vol_x_preferred":[
        "Borghi"
    ],
    "name:war_x_preferred":[
        "Borghi"
    ],
    "name:zho_x_preferred":[
        "\u535a\u5c14\u5409"
    ],
    "wof:name":"Borghi",
    "wof:placetype":"locality",
    "wof:population":47
},
  "geometry": {"coordinates":[11.68379,45.64576],"type":"Point"}
}