{
  "type": "Feature",
  "properties": {
    "gn:admin1_code":"9",
    "gn:admin2_code":"MN",
    "gn:admin3_code":"20061.0",
    "gn:asciiname":"Ca' Bianche",
    "gn:country_code":"IT",
    "gn:dem":11,
    "gn:feature_class":"P",
    "gn:feature_code":"PPL",
    "gn:name":"Ca' Bianche",
    "gn:population":19,
    "gn:timezone":"Europe/Rome",
    "iso:country":"IT",
    "wof:name":"Ca' Bianche",
    "wof:placetype":"locality",
    "wof:population":19
},
  "geometry": {"coordinates":[11.2585,44.98939],"type":"Point"}
}