{
  "type": "Feature",
  "properties": {
    "gn:admin1_code":"18",
    "gn:admin2_code":"PG",
    "gn:admin3_code":"54001.0",
    "gn:asciiname":"Tombetta",
    "gn:country_code":"IT",
    "gn:dem":207,
    "gn:feature_class":"P",
    "gn:feature_code":"PPL",
    "gn:name":"Tombetta",
    "gn:population":50,
    "gn:timezone":"Europe/Rome",
    "iso:country":"IT",
    "wof:name":"Tombetta",
    "wof:placetype":"locality",
    "wof:population":50
},
  "geometry": {"coordinates":[12.59378,43.04131],"type":"Point"}
}