{
  "type": "Feature",
  "properties": {
    "gn:admin1_code":"9.0",
    "gn:admin2_code":"MN",
    "gn:admin3_code":"20042.0",
    "gn:asciiname":"I Colombaroni",
    "gn:country_code":"IT",
    "gn:dem":10,
    "gn:feature_class":"P",
    "gn:feature_code":"PPL",
    "gn:name":"I Colombaroni",
    "gn:population":0,
    "gn:timezone":"Europe/Rome",
    "iso:country":"IT",
    "wof:name":"I Colombaroni",
    "wof:placetype":"locality"
},
  "geometry": {"coordinates":[11.16667,44.95],"type":"Point"}
}