{
  "type": "Feature",
  "properties": {
    "gn:admin1_code":"3",
    "gn:admin2_code":"CS",
    "gn:admin3_code":"78091.0",
    "gn:asciiname":"Tenimento-Manca di Gatto",
    "gn:country_code":"IT",
    "gn:dem":97,
    "gn:feature_class":"P",
    "gn:feature_code":"PPL",
    "gn:name":"Tenimento-Manca di Gatto",
    "gn:population":267,
    "gn:timezone":"Europe/Rome",
    "iso:country":"IT",
    "wof:name":"Tenimento-Manca di Gatto",
    "wof:placetype":"locality",
    "wof:population":267
},
  "geometry": {"coordinates":[16.04696,39.33926],"type":"Point"}
}