{
  "type": "Feature",
  "properties": {
    "gn:admin1_code":"9",
    "gn:admin2_code":"MN",
    "gn:admin3_code":"20031.0",
    "gn:asciiname":"Senga",
    "gn:country_code":"IT",
    "gn:dem":21,
    "gn:feature_class":"P",
    "gn:feature_code":"PPL",
    "gn:name":"Senga",
    "gn:population":27,
    "gn:timezone":"Europe/Rome",
    "iso:country":"IT",
    "name:ceb_x_preferred":[
        "Senga"
    ],
    "name:ita_x_preferred":[
        "Senga"
    ],
    "name:swa_x_preferred":[
        "Senga"
    ],
    "name:swe_x_preferred":[
        "Senga"
    ],
    "wof:name":"Senga",
    "wof:placetype":"locality",
    "wof:population":27
},
  "geometry": {"coordinates":[10.63764,45.08419],"type":"Point"}
}