{
  "type": "Feature",
  "properties": {
    "gn:admin1_code":"20",
    "gn:admin2_code":"PD",
    "gn:admin3_code":"28032.0",
    "gn:asciiname":"Ca' Comin",
    "gn:country_code":"IT",
    "gn:dem":48,
    "gn:feature_class":"P",
    "gn:feature_code":"PPL",
    "gn:name":"Ca' Comin",
    "gn:population":69,
    "gn:timezone":"Europe/Rome",
    "iso:country":"IT",
    "wof:name":"Ca' Comin",
    "wof:placetype":"locality",
    "wof:population":69
},
  "geometry": {"coordinates":[11.80601,45.65735],"type":"Point"}
}