{
  "type": "Feature",
  "properties": {
    "gn:admin1_code":"12",
    "gn:admin2_code":"TO",
    "gn:admin3_code":"1156.0",
    "gn:asciiname":"Pomaretto",
    "gn:country_code":"IT",
    "gn:dem":227,
    "gn:feature_class":"P",
    "gn:feature_code":"PPL",
    "gn:name":"Pomaretto",
    "gn:population":13,
    "gn:timezone":"Europe/Rome",
    "iso:country":"IT",
    "name:azb_x_preferred":[
        "\u067e\u0648\u0645\u0627\u0631\u062a\u0648"
    ],
    "name:bel_x_preferred":[
        "\u041f\u0430\u043c\u0430\u0440\u044d\u0442\u0430"
    ],
    "name:bul_x_preferred":[
        "\u041f\u043e\u043c\u0430\u0440\u0435\u0442\u043e"
    ],
    "name:cat_x_preferred":[
        "Pomaret"
    ],
    "name:ceb_x_preferred":[
        "Pomaretto"
    ],
    "name:deu_x_preferred":[
        "Pomaretto"
    ],
    "name:epo_x_preferred":[
        "Pomaretto"
    ],
    "name:est_x_preferred":[
        "Pomaretto"
    ],
    "name:eus_x_preferred":[
        "Pomaretto"
    ],
    "name:fas_x_preferred":[
        "\u067e\u0648\u0645\u0627\u0631\u062a\u0648"
    ],
    "name:fra_x_preferred":[
        "Pomaretto"
    ],
    "name:hun_x_preferred":[
        "Pomaretto"
    ],
    "name:hye_x_preferred":[
        "\u054a\u0578\u0574\u0561\u0580\u0565\u057f\u0578"
    ],
    "name:ind_x_preferred":[
        "Pomaretto"
    ],
    "name:ita_x_preferred":[
        "Pomaretto"
    ],
    "name:jpn_x_preferred":[
        "\u30dd\u30de\u30ec\u30c3\u30c8"
    ],
    "name:kaz_x_preferred":[
        "\u041f\u043e\u043c\u0430\u0440\u0435\u0442\u0442\u043e"
    ],
    "name:lat_x_preferred":[
        "Pomaretum"
    ],
    "name:lmo_x_preferred":[
        "Pomaretto"
    ],
    "name:msa_x_preferred":[
        "Pomaretto"
    ],
    "name:nap_x_preferred":[
        "Pomaretto"
    ],
    "name:nld_x_preferred":[
        "Pomaretto"
    ],
    "name:oci_x_preferred":[
        "Pomaret"
    ],
    "name:pms_x_preferred":[
        "Pomaret"
    ],
    "name:pol_x_preferred":[
        "Pomaretto"
    ],
    "name:por_x_preferred":[
        "Pomaretto"
    ],
    "name:ron_x_preferred":[
        "Pomaretto"
    ],
    "name:rus_x_preferred":[
        "\u041f\u043e\u043c\u0430\u0440\u0435\u0442\u0442\u043e"
    ],
    "name:scn_x_preferred":[
        "Pomaretto"
    ],
    "name:spa_x_preferred":[
        "Pomaretto"
    ],
    "name:srp_x_preferred":[
        "\u041f\u043e\u043c\u0430\u0440\u0435\u0442\u043e"
    ],
    "name:swe_x_preferred":[
        "Pomaretto"
    ],
    "name:tgl_x_preferred":[
        "Pomaretto"
    ],
    "name:ukr_x_preferred":[
        "\u041f\u043e\u043c\u0430\u0440\u0435\u0442\u0442\u043e"
    ],
    "name:uzb_x_preferred":[
        "Pomaretto"
    ],
    "name:vie_x_preferred":[
        "Pomaretto"
    ],
    "name:vol_x_preferred":[
        "Pomaretto"
    ],
    "name:war_x_preferred":[
        "Pomaretto"
    ],
    "name:zho_x_preferred":[
        "\u6ce2\u9a6c\u96f7\u6258"
    ],
    "wof:name":"Pomaretto",
    "wof:placetype":"locality",
    "wof:population":13
},
  "geometry": {"coordinates":[7.70387,44.93765],"type":"Point"}
}