{
  "type": "Feature",
  "properties": {
    "gn:admin1_code":"12",
    "gn:admin2_code":"TO",
    "gn:admin3_code":"1156.0",
    "gn:asciiname":"Pomaretto",
    "gn:country_code":"IT",
    "gn:dem":227,
    "gn:feature_class":"P",
    "gn:feature_code":"PPL",
    "gn:name":"Pomaretto",
    "gn:population":13,
    "gn:timezone":"Europe/Rome",
    "iso:country":"IT",
    "wof:name":"Pomaretto",
    "wof:placetype":"locality",
    "wof:population":13
},
  "geometry": {"coordinates":[7.70387,44.93765],"type":"Point"}
}