{
  "type": "Feature",
  "properties": {
    "gn:admin1_code":"6",
    "gn:admin2_code":"UD",
    "gn:admin3_code":"30073.0",
    "gn:asciiname":"Cogliat",
    "gn:country_code":"IT",
    "gn:dem":754,
    "gn:feature_class":"P",
    "gn:feature_code":"PPL",
    "gn:name":"Cogliat",
    "gn:population":48,
    "gn:timezone":"Europe/Rome",
    "iso:country":"IT",
    "wof:name":"Cogliat",
    "wof:placetype":"locality",
    "wof:population":48
},
  "geometry": {"coordinates":[13.12214,46.54043],"type":"Point"}
}