{
  "type": "Feature",
  "properties": {
    "gn:admin1_code":"3.0",
    "gn:admin2_code":"VV",
    "gn:admin3_code":"102035.0",
    "gn:asciiname":"Borgo Piccione",
    "gn:country_code":"IT",
    "gn:dem":331,
    "gn:feature_class":"P",
    "gn:feature_code":"PPLL",
    "gn:name":"Borgo Piccione",
    "gn:population":0,
    "gn:timezone":"Europe/Rome",
    "iso:country":"IT",
    "wof:name":"Borgo Piccione",
    "wof:placetype":"locality"
},
  "geometry": {"coordinates":[16.27548,38.6598],"type":"Point"}
}