{
  "type": "Feature",
  "properties": {
    "gn:elevation":549,
    "gn:population":148,
    "iso:country":"IT",
    "name:bcl_x_preferred":[
        "Configni"
    ],
    "name:bel_x_preferred":[
        "\u041a\u0430\u043d\u0444\u0456\u043d'\u0456"
    ],
    "name:bul_x_preferred":[
        "\u041a\u043e\u043d\u0444\u0438\u043d\u0438"
    ],
    "name:deu_x_preferred":[
        "Configni"
    ],
    "name:eng_x_preferred":[
        "Configni"
    ],
    "name:epo_x_preferred":[
        "Configni"
    ],
    "name:est_x_preferred":[
        "Configni"
    ],
    "name:eus_x_preferred":[
        "Configni"
    ],
    "name:fas_x_preferred":[
        "\u06a9\u0646\u0641\u06cc\u0646\u06cc\u06cc"
    ],
    "name:fra_x_preferred":[
        "Configni"
    ],
    "name:hbs_x_preferred":[
        "Configni"
    ],
    "name:hun_x_preferred":[
        "Configni"
    ],
    "name:hye_x_preferred":[
        "\u053f\u0578\u0576\u0586\u056b\u0576\u0575\u056b"
    ],
    "name:ina_x_preferred":[
        "Configni"
    ],
    "name:ita_x_preferred":[
        "Configni"
    ],
    "name:jpn_x_preferred":[
        "\u30b3\u30f3\u30d5\u30a3\u30fc\u30cb"
    ],
    "name:kaz_x_preferred":[
        "\u041a\u043e\u043d\u0444\u0438\u043d\u044c\u0438"
    ],
    "name:kor_x_preferred":[
        "\ucf58\ud53c\ub2c8"
    ],
    "name:lat_x_preferred":[
        "Confinium"
    ],
    "name:lmo_x_preferred":[
        "Configni"
    ],
    "name:msa_x_preferred":[
        "Configni"
    ],
    "name:nan_x_preferred":[
        "Configni"
    ],
    "name:nap_x_preferred":[
        "Configni"
    ],
    "name:nld_x_preferred":[
        "Configni"
    ],
    "name:pms_x_preferred":[
        "Configni"
    ],
    "name:pol_x_preferred":[
        "Configni"
    ],
    "name:por_x_preferred":[
        "Configni"
    ],
    "name:ron_x_preferred":[
        "Configni"
    ],
    "name:rus_x_preferred":[
        "\u041a\u043e\u043d\u0444\u0438\u043d\u044c\u0438"
    ],
    "name:scn_x_preferred":[
        "Configni"
    ],
    "name:spa_x_preferred":[
        "Configni"
    ],
    "name:srp_x_preferred":[
        "\u041a\u043e\u043d\u0444\u0438\u045a\u0438"
    ],
    "name:ukr_x_preferred":[
        "\u041a\u043e\u043d\u0444\u0456\u043d\u044c\u0457"
    ],
    "name:uzb_x_preferred":[
        "Configni"
    ],
    "name:vie_x_preferred":[
        "Configni"
    ],
    "name:vol_x_preferred":[
        "Configni"
    ],
    "name:war_x_preferred":[
        "Configni"
    ],
    "name:zho_min_nan_x_preferred":[
        "Configni"
    ],
    "name:zho_x_preferred":[
        "\u5b54\u83f2\u5c3c"
    ],
    "qs:a0":"Italia",
    "qs:a1":"*Rieti",
    "qs:a1r":"0Lazio",
    "qs:adm0":"Italia",
    "qs:la_lc":"*",
    "qs:level":"locality",
    "qs:loc":"Configni",
    "qs:loc_alt":"Configni",
    "qs:pop":0,
    "qs:type":"buffered point",
    "wd:wordcount":42,
    "wof:lang":[
        "ita"
    ],
    "wof:name":"Configni",
    "wof:placetype":"locality",
    "wof:population":148
},
  "geometry": {"coordinates":[12.6411,42.422298],"type":"Point"}
}