{
  "type": "Feature",
  "properties": {
    "gn:admin1_code":"2",
    "gn:admin2_code":"MT",
    "gn:admin3_code":"77029.0",
    "gn:asciiname":"Caprarico Vallo",
    "gn:country_code":"IT",
    "gn:dem":132,
    "gn:feature_class":"P",
    "gn:feature_code":"PPL",
    "gn:name":"Caprarico Vallo",
    "gn:population":62,
    "gn:timezone":"Europe/Rome",
    "iso:country":"IT",
    "wof:name":"Caprarico Vallo",
    "wof:placetype":"locality",
    "wof:population":62
},
  "geometry": {"coordinates":[16.39698,40.30725],"type":"Point"}
}