{
  "type": "Feature",
  "properties": {
    "gn:admin1_code":"9",
    "gn:admin2_code":"SO",
    "gn:admin3_code":"14037.0",
    "gn:asciiname":"Chiesa Veglia",
    "gn:country_code":"IT",
    "gn:dem":2151,
    "gn:feature_class":"P",
    "gn:feature_code":"PPL",
    "gn:name":"Chiesa Veglia",
    "gn:population":16,
    "gn:timezone":"Europe/Rome",
    "iso:country":"IT",
    "wof:name":"Chiesa Veglia",
    "wof:placetype":"locality",
    "wof:population":16
},
  "geometry": {"coordinates":[10.17233,46.53977],"type":"Point"}
}