{
  "type": "Feature",
  "properties": {
    "gn:admin1_code":"16.0",
    "gn:admin2_code":"AR",
    "gn:admin3_code":"51005.0",
    "gn:asciiname":"Pogi",
    "gn:country_code":"IT",
    "gn:dem":222,
    "gn:elevation":"226.0",
    "gn:feature_class":"P",
    "gn:feature_code":"PPL",
    "gn:name":"Pogi",
    "gn:population":248,
    "gn:timezone":"Europe/Rome",
    "iso:country":"IT",
    "wof:name":"Pogi",
    "wof:placetype":"locality",
    "wof:population":248
},
  "geometry": {"coordinates":[11.61504,43.46619000000001],"type":"Point"}
}