{
  "type": "Feature",
  "properties": {
    "gn:admin1_code":"5",
    "gn:admin2_code":"MO",
    "gn:admin3_code":"36044.0",
    "gn:asciiname":"Secchia",
    "gn:country_code":"IT",
    "gn:dem":30,
    "gn:feature_class":"P",
    "gn:feature_code":"PPL",
    "gn:name":"Secchia",
    "gn:population":38,
    "gn:timezone":"Europe/Rome",
    "iso:country":"IT",
    "name:bar_x_preferred":[
        "Secchia"
    ],
    "name:cat_x_preferred":[
        "Secchia"
    ],
    "name:ceb_x_preferred":[
        "Fiume Secchia"
    ],
    "name:deu_x_preferred":[
        "Secchia"
    ],
    "name:eml_x_preferred":[
        "S\u00e8cia"
    ],
    "name:fra_x_preferred":[
        "Secchia"
    ],
    "name:ita_x_preferred":[
        "Secchia"
    ],
    "name:nld_x_preferred":[
        "Secchia"
    ],
    "name:nno_x_preferred":[
        "Secchia"
    ],
    "name:nor_x_preferred":[
        "Secchia"
    ],
    "name:por_x_preferred":[
        "Rio Secchia"
    ],
    "name:spa_x_preferred":[
        "R\u00edo Secchia"
    ],
    "name:zho_x_preferred":[
        "\u585e\u57fa\u4e9e\u6cb3"
    ],
    "wof:name":"Secchia",
    "wof:placetype":"locality",
    "wof:population":38
},
  "geometry": {"coordinates":[10.95483,44.71739],"type":"Point"}
}