{
  "type": "Feature",
  "properties": {
    "gn:admin1_code":"5",
    "gn:admin2_code":"MO",
    "gn:admin3_code":"36044.0",
    "gn:asciiname":"Secchia",
    "gn:country_code":"IT",
    "gn:dem":30,
    "gn:feature_class":"P",
    "gn:feature_code":"PPL",
    "gn:name":"Secchia",
    "gn:population":38,
    "gn:timezone":"Europe/Rome",
    "iso:country":"IT",
    "wof:name":"Secchia",
    "wof:placetype":"locality",
    "wof:population":38
},
  "geometry": {"coordinates":[10.95483,44.71739],"type":"Point"}
}