{
  "type": "Feature",
  "properties": {
    "gn:admin1_code":"5",
    "gn:admin2_code":"PC",
    "gn:admin3_code":"33020.0",
    "gn:asciiname":"Torrio Sopra",
    "gn:country_code":"IT",
    "gn:dem":1070,
    "gn:feature_class":"P",
    "gn:feature_code":"PPLL",
    "gn:name":"Torrio Sopra",
    "gn:population":10,
    "gn:timezone":"Europe/Rome",
    "iso:country":"IT",
    "wof:name":"Torrio Sopra",
    "wof:placetype":"locality",
    "wof:population":10
},
  "geometry": {"coordinates":[9.44411,44.57424],"type":"Point"}
}