{
  "type": "Feature",
  "properties": {
    "gn:admin1_code":"5",
    "gn:admin2_code":"PC",
    "gn:admin3_code":"33024.0",
    "gn:asciiname":"Piscine",
    "gn:country_code":"IT",
    "gn:dem":84,
    "gn:feature_class":"P",
    "gn:feature_code":"PPL",
    "gn:name":"Piscine",
    "gn:population":25,
    "gn:timezone":"Europe/Rome",
    "iso:country":"IT",
    "name:fra_x_preferred":[
        "Piscine"
    ],
    "name:srp_x_preferred":[
        "Piscine"
    ],
    "wof:name":"Piscine",
    "wof:placetype":"locality",
    "wof:population":25
},
  "geometry": {"coordinates":[9.55329,45.00587],"type":"Point"}
}