{
  "type": "Feature",
  "properties": {
    "gn:admin1_code":"5.0",
    "gn:admin2_code":"RA",
    "gn:admin3_code":"39012.0",
    "gn:asciiname":"Belricetto",
    "gn:country_code":"IT",
    "gn:dem":5,
    "gn:feature_class":"P",
    "gn:feature_code":"PPL",
    "gn:name":"Belricetto",
    "gn:population":361,
    "gn:timezone":"Europe/Rome",
    "iso:country":"IT",
    "wof:name":"Belricetto",
    "wof:placetype":"locality",
    "wof:population":361
},
  "geometry": {"coordinates":[11.90593,44.49676],"type":"Point"}
}