{
  "type": "Feature",
  "properties": {
    "gn:admin1_code":"16",
    "gn:admin2_code":"MS",
    "gn:admin3_code":"45009.0",
    "gn:asciiname":"Cisigliana",
    "gn:country_code":"IT",
    "gn:dem":599,
    "gn:feature_class":"P",
    "gn:feature_code":"PPL",
    "gn:name":"Cisigliana",
    "gn:population":17,
    "gn:timezone":"Europe/Rome",
    "iso:country":"IT",
    "wof:name":"Cisigliana",
    "wof:placetype":"locality",
    "wof:population":17
},
  "geometry": {"coordinates":[10.07458,44.26512],"type":"Point"}
}