{
  "type": "Feature",
  "properties": {
    "gn:admin1_code":"7",
    "gn:admin2_code":"FR",
    "gn:admin3_code":"60075.0",
    "gn:asciiname":"Verdara",
    "gn:country_code":"IT",
    "gn:dem":209,
    "gn:feature_class":"P",
    "gn:feature_code":"PPL",
    "gn:name":"Verdara",
    "gn:population":261,
    "gn:timezone":"Europe/Rome",
    "iso:country":"IT",
    "wof:name":"Verdara",
    "wof:placetype":"locality",
    "wof:population":261
},
  "geometry": {"coordinates":[13.50123,41.59597],"type":"Point"}
}