{
  "type": "Feature",
  "properties": {
    "gn:admin1_code":"5",
    "gn:admin2_code":"PR",
    "gn:admin3_code":"34025.0",
    "gn:asciiname":"Case Furia",
    "gn:country_code":"IT",
    "gn:dem":118,
    "gn:feature_class":"P",
    "gn:feature_code":"PPL",
    "gn:name":"Case Furia",
    "gn:population":20,
    "gn:timezone":"Europe/Rome",
    "iso:country":"IT",
    "wof:name":"Case Furia",
    "wof:placetype":"locality",
    "wof:population":20
},
  "geometry": {"coordinates":[10.10083,44.81297],"type":"Point"}
}