{
  "type": "Feature",
  "properties": {
    "gn:admin1_code":"18.0",
    "gn:admin2_code":"PG",
    "gn:admin3_code":"54023.0",
    "gn:asciiname":"Pastina",
    "gn:country_code":"IT",
    "gn:dem":574,
    "gn:elevation":"592.0",
    "gn:feature_class":"P",
    "gn:feature_code":"PPL",
    "gn:name":"Pastina",
    "gn:population":11,
    "gn:timezone":"Europe/Rome",
    "iso:country":"IT",
    "name:ara_x_preferred":[
        "\u0628\u0627\u0633\u062a\u064a\u0646\u0627"
    ],
    "name:cat_x_preferred":[
        "\u015eehriye"
    ],
    "name:diq_x_preferred":[
        "\u015eahriyevan"
    ],
    "name:jpn_x_preferred":[
        "\u30d1\u30b9\u30c6\u30a3\u30fc\u30ca"
    ],
    "name:kor_x_preferred":[
        "\ud30c\uc2a4\ud2f0\ub098"
    ],
    "name:tur_x_preferred":[
        "\u015eehriye"
    ],
    "wof:name":"Pastina",
    "wof:placetype":"locality",
    "wof:population":11
},
  "geometry": {"coordinates":[12.7404,43.22167],"type":"Point"}
}