{
  "type": "Feature",
  "properties": {
    "gn:admin1_code":"18.0",
    "gn:admin2_code":"PG",
    "gn:admin3_code":"54023.0",
    "gn:asciiname":"Pastina",
    "gn:country_code":"IT",
    "gn:dem":574,
    "gn:elevation":"592.0",
    "gn:feature_class":"P",
    "gn:feature_code":"PPL",
    "gn:name":"Pastina",
    "gn:population":11,
    "gn:timezone":"Europe/Rome",
    "iso:country":"IT",
    "wof:name":"Pastina",
    "wof:placetype":"locality",
    "wof:population":11
},
  "geometry": {"coordinates":[12.7404,43.22167],"type":"Point"}
}