{
  "type": "Feature",
  "properties": {
    "gn:admin1_code":"8",
    "gn:admin2_code":"SV",
    "gn:admin3_code":"9019.0",
    "gn:asciiname":"Roveira",
    "gn:country_code":"IT",
    "gn:dem":311,
    "gn:feature_class":"P",
    "gn:feature_code":"PPLL",
    "gn:name":"Roveira",
    "gn:population":6,
    "gn:timezone":"Europe/Rome",
    "iso:country":"IT",
    "wof:name":"Roveira",
    "wof:placetype":"locality",
    "wof:population":6
},
  "geometry": {"coordinates":[8.06918,44.04449],"type":"Point"}
}