{
  "type": "Feature",
  "properties": {
    "gn:admin1_code":"15",
    "gn:admin2_code":"SR",
    "gn:admin3_code":"89001.0",
    "gn:asciiname":"Piano Ippolito",
    "gn:country_code":"IT",
    "gn:dem":54,
    "gn:feature_class":"P",
    "gn:feature_code":"PPL",
    "gn:name":"Piano Ippolito",
    "gn:population":82,
    "gn:timezone":"Europe/Rome",
    "iso:country":"IT",
    "wof:name":"Piano Ippolito",
    "wof:placetype":"locality",
    "wof:population":82
},
  "geometry": {"coordinates":[15.19233,37.26859],"type":"Point"}
}