{
  "type": "Feature",
  "properties": {
    "gn:admin1_code":"20",
    "gn:admin2_code":"VI",
    "gn:admin3_code":"24111.0",
    "gn:asciiname":"Biceghi",
    "gn:country_code":"IT",
    "gn:dem":649,
    "gn:feature_class":"P",
    "gn:feature_code":"PPL",
    "gn:name":"Biceghi",
    "gn:population":58,
    "gn:timezone":"Europe/Rome",
    "iso:country":"IT",
    "wof:name":"Biceghi",
    "wof:placetype":"locality",
    "wof:population":58
},
  "geometry": {"coordinates":[11.2546,45.63927],"type":"Point"}
}