{
  "type": "Feature",
  "properties": {
    "gn:admin1_code":"12",
    "gn:admin2_code":"CN",
    "gn:admin3_code":"4035.0",
    "gn:asciiname":"Gabutti",
    "gn:country_code":"IT",
    "gn:dem":385,
    "gn:feature_class":"P",
    "gn:feature_code":"PPL",
    "gn:name":"Gabutti",
    "gn:population":135,
    "gn:timezone":"Europe/Rome",
    "iso:country":"IT",
    "wof:name":"Gabutti",
    "wof:placetype":"locality",
    "wof:population":135
},
  "geometry": {"coordinates":[8.15449,44.43795],"type":"Point"}
}