{
  "type": "Feature",
  "properties": {
    "gn:admin1_code":"1.0",
    "gn:admin2_code":"TE",
    "gn:admin3_code":"67046.0",
    "gn:asciiname":"Mattere",
    "gn:country_code":"IT",
    "gn:dem":753,
    "gn:elevation":"744.0",
    "gn:feature_class":"P",
    "gn:feature_code":"PPL",
    "gn:name":"Mattere",
    "gn:population":39,
    "gn:timezone":"Europe/Rome",
    "iso:country":"IT",
    "wof:name":"Mattere",
    "wof:placetype":"locality",
    "wof:population":39
},
  "geometry": {"coordinates":[13.50759,42.72486],"type":"Point"}
}