{
  "type": "Feature",
  "properties": {
    "gn:admin1_code":"18",
    "gn:admin2_code":"PG",
    "gn:admin3_code":"54030.0",
    "gn:asciiname":"Turrita",
    "gn:country_code":"IT",
    "gn:dem":305,
    "gn:feature_class":"P",
    "gn:feature_code":"PPL",
    "gn:name":"Turrita",
    "gn:population":231,
    "gn:timezone":"Europe/Rome",
    "iso:country":"IT",
    "wof:name":"Turrita",
    "wof:placetype":"locality",
    "wof:population":231
},
  "geometry": {"coordinates":[12.65793,42.86854],"type":"Point"}
}