{
  "type": "Feature",
  "properties": {
    "gn:admin1_code":"5.0",
    "gn:admin2_code":"PR",
    "gn:admin3_code":"34012.0",
    "gn:asciiname":"Signatico",
    "gn:country_code":"IT",
    "gn:dem":838,
    "gn:elevation":"816.0",
    "gn:feature_class":"P",
    "gn:feature_code":"PPL",
    "gn:name":"Signatico",
    "gn:population":53,
    "gn:timezone":"Europe/Rome",
    "iso:country":"IT",
    "wof:name":"Signatico",
    "wof:placetype":"locality",
    "wof:population":53
},
  "geometry": {"coordinates":[10.13038,44.54499000000001],"type":"Point"}
}