{
  "type": "Feature",
  "properties": {
    "gn:admin1_code":"17",
    "gn:admin2_code":"BZ",
    "gn:admin3_code":"21033.0",
    "gn:asciiname":"San Valentino",
    "gn:country_code":"IT",
    "gn:dem":1137,
    "gn:feature_class":"P",
    "gn:feature_code":"PPL",
    "gn:name":"San Valentino",
    "gn:population":67,
    "gn:timezone":"Europe/Rome",
    "iso:country":"IT",
    "name:ceb_x_preferred":[
        "San Valentino"
    ],
    "name:ita_x_preferred":[
        "San Valentino"
    ],
    "name:pms_x_preferred":[
        "San Valentino"
    ],
    "name:pol_x_preferred":[
        "\u015awi\u0119ty Walenty"
    ],
    "name:srp_x_preferred":[
        "San Valentino"
    ],
    "name:swe_x_preferred":[
        "San Valentino"
    ],
    "wof:name":"San Valentino",
    "wof:placetype":"locality",
    "wof:population":67
},
  "geometry": {"coordinates":[11.66653,46.63945],"type":"Point"}
}