{
  "type": "Feature",
  "properties": {
    "gn:admin1_code":"5",
    "gn:admin2_code":"PR",
    "gn:admin3_code":"34002.0",
    "gn:asciiname":"Geminiano",
    "gn:country_code":"IT",
    "gn:dem":638,
    "gn:feature_class":"P",
    "gn:feature_code":"PPLL",
    "gn:name":"Geminiano",
    "gn:population":7,
    "gn:timezone":"Europe/Rome",
    "iso:country":"IT",
    "name:bpy_x_preferred":[
        "\u0997\u09c7\u09ae\u09bf\u09a8\u09bf\u09af\u09bc\u09be\u09a8\u09cb"
    ],
    "name:ceb_x_preferred":[
        "Geminiano"
    ],
    "name:eus_x_preferred":[
        "Geminiano"
    ],
    "name:fra_x_preferred":[
        "Geminiano"
    ],
    "name:ita_x_preferred":[
        "Geminiano"
    ],
    "name:kat_x_preferred":[
        "\u10df\u10d4\u10db\u10d8\u10dc\u10d8\u10d0\u10dc\u10e3"
    ],
    "name:kaz_x_preferred":[
        "\u0416\u0435\u043c\u0438\u043d\u0438\u0430\u043d\u0443"
    ],
    "name:nld_x_preferred":[
        "Geminiano"
    ],
    "name:nor_x_preferred":[
        "Geminiano"
    ],
    "name:por_x_preferred":[
        "Geminiano"
    ],
    "name:ron_x_preferred":[
        "Geminiano"
    ],
    "name:rus_x_preferred":[
        "\u0416\u0435\u043c\u0438\u043d\u0438\u0430\u043d\u0443"
    ],
    "name:swe_x_preferred":[
        "Geminiano"
    ],
    "name:vie_x_preferred":[
        "Geminiano"
    ],
    "name:vol_x_preferred":[
        "Geminiano"
    ],
    "name:war_x_preferred":[
        "Geminiano"
    ],
    "name:zho_x_preferred":[
        "\u70ed\u7c73\u5c3c\u4e9a\u52aa"
    ],
    "wof:name":"Geminiano",
    "wof:placetype":"locality",
    "wof:population":7
},
  "geometry": {"coordinates":[9.6599,44.63277],"type":"Point"}
}