{
  "type": "Feature",
  "properties": {
    "gn:admin1_code":"12",
    "gn:admin2_code":"AT",
    "gn:admin3_code":"5069.0",
    "gn:asciiname":"Santa Maria",
    "gn:country_code":"IT",
    "gn:dem":247,
    "gn:feature_class":"P",
    "gn:feature_code":"PPL",
    "gn:name":"Santa Maria",
    "gn:population":19,
    "gn:timezone":"Europe/Rome",
    "iso:country":"IT",
    "wof:name":"Santa Maria",
    "wof:placetype":"locality",
    "wof:population":19
},
  "geometry": {"coordinates":[8.29208,45.02908],"type":"Point"}
}