{
  "type": "Feature",
  "properties": {
    "gn:admin1_code":"1.0",
    "gn:admin2_code":"AQ",
    "gn:admin3_code":"66072.0",
    "gn:asciiname":"Cermone",
    "gn:country_code":"IT",
    "gn:dem":678,
    "gn:feature_class":"P",
    "gn:feature_code":"PPL",
    "gn:name":"Cermone",
    "gn:population":12,
    "gn:timezone":"Europe/Rome",
    "iso:country":"IT",
    "wof:name":"Cermone",
    "wof:placetype":"locality",
    "wof:population":12
},
  "geometry": {"coordinates":[13.30599,42.40704],"type":"Point"}
}