{
  "type": "Feature",
  "properties": {
    "gn:admin1_code":"16.0",
    "gn:admin2_code":"LU",
    "gn:admin3_code":"46002.0",
    "gn:asciiname":"Grotte",
    "gn:country_code":"IT",
    "gn:dem":651,
    "gn:feature_class":"P",
    "gn:feature_code":"PPL",
    "gn:name":"Grotte",
    "gn:population":0,
    "gn:timezone":"Europe/Rome",
    "iso:country":"IT",
    "wof:name":"Grotte",
    "wof:placetype":"locality"
},
  "geometry": {"coordinates":[10.71667,44.05],"type":"Point"}
}