{
  "type": "Feature",
  "properties": {
    "gn:admin1_code":"4",
    "gn:admin2_code":"CE",
    "gn:admin3_code":"61102.0",
    "gn:asciiname":"Farnete",
    "gn:country_code":"IT",
    "gn:dem":9,
    "gn:feature_class":"P",
    "gn:feature_code":"PPL",
    "gn:name":"Farnete",
    "gn:population":21,
    "gn:timezone":"Europe/Rome",
    "iso:country":"IT",
    "wof:name":"Farnete",
    "wof:placetype":"locality",
    "wof:population":21
},
  "geometry": {"coordinates":[13.83678,41.21476],"type":"Point"}
}