{
  "type": "Feature",
  "properties": {
    "gn:admin1_code":"20",
    "gn:admin2_code":"PD",
    "gn:admin3_code":"28076.0",
    "gn:asciiname":"Valli",
    "gn:country_code":"IT",
    "gn:dem":31,
    "gn:feature_class":"P",
    "gn:feature_code":"PPL",
    "gn:name":"Valli",
    "gn:population":65,
    "gn:timezone":"Europe/Rome",
    "iso:country":"IT",
    "wof:name":"Valli",
    "wof:placetype":"locality",
    "wof:population":65
},
  "geometry": {"coordinates":[11.79317,45.58888],"type":"Point"}
}