{
  "type": "Feature",
  "properties": {
    "gn:admin1_code":"20",
    "gn:admin2_code":"PD",
    "gn:admin3_code":"28076.0",
    "gn:asciiname":"Valli",
    "gn:country_code":"IT",
    "gn:dem":31,
    "gn:feature_class":"P",
    "gn:feature_code":"PPL",
    "gn:name":"Valli",
    "gn:population":65,
    "gn:timezone":"Europe/Rome",
    "iso:country":"IT",
    "name:tam_x_preferred":[
        "\u0bb5\u0bb3\u0bcd\u0bb3\u0bbf"
    ],
    "name:tel_x_preferred":[
        "\u0c35\u0c32\u0c4d\u0c32\u0c40 \u0c26\u0c47\u0c35\u0c3f"
    ],
    "name:tha_x_preferred":[
        "\u0e1e\u0e23\u0e30\u0e41\u0e21\u0e48\u0e27\u0e31\u0e25\u0e25\u0e35"
    ],
    "wof:name":"Valli",
    "wof:placetype":"locality",
    "wof:population":65
},
  "geometry": {"coordinates":[11.79317,45.58888],"type":"Point"}
}