{
  "type": "Feature",
  "properties": {
    "gn:admin1_code":"11",
    "gn:admin2_code":"CB",
    "gn:admin3_code":"70058.0",
    "gn:asciiname":"Cerro",
    "gn:country_code":"IT",
    "gn:dem":698,
    "gn:feature_class":"P",
    "gn:feature_code":"PPL",
    "gn:name":"Cerro",
    "gn:population":12,
    "gn:timezone":"Europe/Rome",
    "iso:country":"IT",
    "name:ceb_x_preferred":[
        "Cerro"
    ],
    "name:deu_x_preferred":[
        "Cerro"
    ],
    "name:fra_x_preferred":[
        "Cerro"
    ],
    "name:ita_x_preferred":[
        "Cerro"
    ],
    "name:pms_x_preferred":[
        "Cerro"
    ],
    "name:por_x_preferred":[
        "Cerro"
    ],
    "name:rus_x_preferred":[
        "\u0421\u0435\u0440\u0440\u043e"
    ],
    "name:spa_x_preferred":[
        "Cerro"
    ],
    "name:srp_x_preferred":[
        "\u010cero"
    ],
    "name:swe_x_preferred":[
        "Cerro"
    ],
    "wof:name":"Cerro",
    "wof:placetype":"locality",
    "wof:population":12
},
  "geometry": {"coordinates":[14.84381,41.6703],"type":"Point"}
}