{
  "type": "Feature",
  "properties": {
    "gn:admin1_code":"20.0",
    "gn:admin2_code":"VR",
    "gn:admin3_code":"23094.0",
    "gn:asciiname":"Isolalta",
    "gn:country_code":"IT",
    "gn:dem":42,
    "gn:feature_class":"P",
    "gn:feature_code":"PPL",
    "gn:name":"Isolalta",
    "gn:population":758,
    "gn:timezone":"Europe/Rome",
    "iso:country":"IT",
    "wof:name":"Isolalta",
    "wof:placetype":"locality",
    "wof:population":758
},
  "geometry": {"coordinates":[10.92266,45.33711],"type":"Point"}
}