{
  "type": "Feature",
  "properties": {
    "gn:admin1_code":"12",
    "gn:admin2_code":"AL",
    "gn:admin3_code":"6169.0",
    "gn:asciiname":"Varo",
    "gn:country_code":"IT",
    "gn:dem":236,
    "gn:feature_class":"P",
    "gn:feature_code":"PPL",
    "gn:name":"Varo",
    "gn:population":21,
    "gn:timezone":"Europe/Rome",
    "iso:country":"IT",
    "name:ceb_x_preferred":[
        "Varo"
    ],
    "name:epo_x_preferred":[
        "Varo"
    ],
    "name:fra_x_preferred":[
        "Varo"
    ],
    "name:ita_x_preferred":[
        "Varo"
    ],
    "wof:name":"Varo",
    "wof:placetype":"locality",
    "wof:population":21
},
  "geometry": {"coordinates":[8.67692,44.64519],"type":"Point"}
}