{
  "type": "Feature",
  "properties": {
    "gn:admin1_code":"9.0",
    "gn:admin2_code":"SO",
    "gn:admin3_code":"14054.0",
    "gn:asciiname":"Porrettina Bassa",
    "gn:country_code":"IT",
    "gn:dem":207,
    "gn:feature_class":"P",
    "gn:feature_code":"PPL",
    "gn:name":"Porrettina Bassa",
    "gn:population":53,
    "gn:timezone":"Europe/Rome",
    "iso:country":"IT",
    "wof:name":"Porrettina Bassa",
    "wof:placetype":"locality",
    "wof:population":53
},
  "geometry": {"coordinates":[9.40954,46.26235],"type":"Point"}
}