{
  "type": "Feature",
  "properties": {
    "iso:country":"IT",
    "name:eng_x_preferred":[
        "Corticella"
    ],
    "name:ita_x_preferred":[
        "Corticella"
    ],
    "wof:name":"Corticella",
    "wof:placetype":"neighbourhood"
},
  "geometry": {"coordinates":[11.3576824090576,44.54283517295737],"type":"Point"}
}