{
  "type": "Feature",
  "properties": {
    "gn:gn_country":"IT",
    "gn:gn_fcode":"PPL",
    "gn:gn_pop":0,
    "gn:population":39,
    "iso:country":"IT",
    "name:cat_x_preferred":[
        "Sambra"
    ],
    "name:deu_x_preferred":[
        "Zambra"
    ],
    "name:epo_x_preferred":[
        "Zambra"
    ],
    "name:fra_x_preferred":[
        "Zambra"
    ],
    "name:ita_x_preferred":[
        "Zambra"
    ],
    "name:msa_x_preferred":[
        "Zambra"
    ],
    "name:por_x_preferred":[
        "Zambra"
    ],
    "name:spa_x_preferred":[
        "Zambra mora"
    ],
    "name:tam_x_preferred":[
        "\u0b9a\u0bbe\u0bae\u0bcd\u0baa\u0bcd\u0bb0\u0bbe"
    ],
    "qs_pg:aaroncc":"IT",
    "qs_pg:gn_country":"IT",
    "qs_pg:gn_fcode":"PPL",
    "qs_pg:gn_pop":0,
    "qs_pg:name":"Zambra",
    "qs_pg:name_adm0":"Italia",
    "qs_pg:name_adm1":"Toscana",
    "qs_pg:photos_9r":0,
    "qs_pg:photos_sr":0,
    "qs_pg:pop_sr":0,
    "qs_pg:qs_pg_placetype":"locality",
    "qs_pg:qs_pg_placetype_gp":"Town",
    "qs_pg:woe_adm0":23424853,
    "woe:adm0_id":23424853,
    "woe:name_adm0":"Italia",
    "woe:name_adm1":"Toscana",
    "woe:placetype":"Town",
    "wof:name":"Zambra",
    "wof:placetype":"locality",
    "wof:population":39
},
  "geometry": {"coordinates":[11.11027,43.50387],"type":"Point"}
}