{
  "type": "Feature",
  "properties": {
    "gn:admin1_code":"16",
    "gn:admin2_code":"MS",
    "gn:admin3_code":"45010.0",
    "gn:asciiname":"Caglieglia",
    "gn:country_code":"IT",
    "gn:dem":259,
    "gn:feature_class":"P",
    "gn:feature_code":"PPL",
    "gn:name":"Caglieglia",
    "gn:population":106,
    "gn:timezone":"Europe/Rome",
    "iso:country":"IT",
    "wof:name":"Caglieglia",
    "wof:placetype":"locality",
    "wof:population":106
},
  "geometry": {"coordinates":[10.16901,44.06972],"type":"Point"}
}