{
  "type": "Feature",
  "properties": {
    "gn:admin1_code":"20",
    "gn:admin2_code":"VI",
    "gn:admin3_code":"24104.0",
    "gn:asciiname":"Brega",
    "gn:country_code":"IT",
    "gn:dem":74,
    "gn:feature_class":"P",
    "gn:feature_code":"PPL",
    "gn:name":"Brega",
    "gn:population":83,
    "gn:timezone":"Europe/Rome",
    "iso:country":"IT",
    "wof:name":"Brega",
    "wof:placetype":"locality",
    "wof:population":83
},
  "geometry": {"coordinates":[11.74392,45.69263],"type":"Point"}
}