{
  "type": "Feature",
  "properties": {
    "gn:admin1_code":"20",
    "gn:admin2_code":"VI",
    "gn:admin3_code":"24104.0",
    "gn:asciiname":"Brega",
    "gn:country_code":"IT",
    "gn:dem":74,
    "gn:feature_class":"P",
    "gn:feature_code":"PPL",
    "gn:name":"Brega",
    "gn:population":83,
    "gn:timezone":"Europe/Rome",
    "iso:country":"IT",
    "name:afr_x_preferred":[
        "Brega"
    ],
    "name:ara_x_preferred":[
        "\u0645\u0631\u0633\u0649 \u0627\u0644\u0628\u0631\u064a\u0642\u0629"
    ],
    "name:azb_x_preferred":[
        "\u0628\u0631\u06cc\u0642\u0647"
    ],
    "name:bul_x_preferred":[
        "\u041c\u0430\u0440\u0441\u0430 \u0411\u0440\u0435\u0433\u0430"
    ],
    "name:ces_x_preferred":[
        "Briga"
    ],
    "name:dan_x_preferred":[
        "Marsa al-Burayqah"
    ],
    "name:deu_x_preferred":[
        "Brega"
    ],
    "name:epo_x_preferred":[
        "Brega"
    ],
    "name:fas_x_preferred":[
        "\u0628\u0631\u06cc\u0642\u0647"
    ],
    "name:heb_x_preferred":[
        "\u05d1\u05d5\u05e8\u05d9\u05d9\u05e7\u05d4"
    ],
    "name:hun_x_preferred":[
        "Brega"
    ],
    "name:ind_x_preferred":[
        "Brega"
    ],
    "name:ita_x_preferred":[
        "Brega"
    ],
    "name:jpn_x_preferred":[
        "\u30d6\u30ec\u30ac"
    ],
    "name:kab_x_preferred":[
        "Lmer\u1e63a Briga"
    ],
    "name:kat_x_preferred":[
        "\u10db\u10d0\u10e0\u10e1\u10d0-\u10d4\u10da-\u10d1\u10e3\u10e0\u10d4\u10d8\u10d9\u10d0"
    ],
    "name:kor_x_preferred":[
        "\ube0c\ub808\uac00"
    ],
    "name:nld_x_preferred":[
        "Brega"
    ],
    "name:nno_x_preferred":[
        "Marsa al-Burayqah"
    ],
    "name:nor_x_preferred":[
        "Marsa al-Burayqah"
    ],
    "name:pol_x_preferred":[
        "Marsa al-Burajka"
    ],
    "name:por_x_preferred":[
        "Brega"
    ],
    "name:rus_x_preferred":[
        "\u042d\u043b\u044c-\u0411\u0443\u0440\u0430\u0439\u043a\u0430"
    ],
    "name:scn_x_preferred":[
        "Brega"
    ],
    "name:slk_x_preferred":[
        "Mars\u00e1 al-Burajka"
    ],
    "name:srp_x_preferred":[
        "\u0411\u0440\u0435\u0433\u0430"
    ],
    "name:swe_x_preferred":[
        "Marsa al-Burayqah"
    ],
    "name:ukr_x_preferred":[
        "\u0411\u0440\u0435\u0433\u0430"
    ],
    "name:vie_x_preferred":[
        "Brega"
    ],
    "name:zho_x_preferred":[
        "\u5e03\u96f7\u52a0"
    ],
    "wof:name":"Brega",
    "wof:placetype":"locality",
    "wof:population":83
},
  "geometry": {"coordinates":[11.74392,45.69263],"type":"Point"}
}