{
  "type": "Feature",
  "properties": {
    "gn:admin1_code":"18",
    "gn:admin2_code":"PG",
    "gn:admin3_code":"54044.0",
    "gn:asciiname":"Corposano",
    "gn:country_code":"IT",
    "gn:dem":523,
    "gn:feature_class":"P",
    "gn:feature_code":"PPL",
    "gn:name":"Corposano",
    "gn:population":39,
    "gn:timezone":"Europe/Rome",
    "iso:country":"IT",
    "wof:name":"Corposano",
    "wof:placetype":"locality",
    "wof:population":39
},
  "geometry": {"coordinates":[12.19437,43.56996],"type":"Point"}
}