{
  "type": "Feature",
  "properties": {
    "gn:gn_country":"IT",
    "gn:gn_fcode":"PPL",
    "gn:gn_pop":0,
    "gn:population":4087,
    "iso:country":"IT",
    "qs_pg:aaroncc":"IT",
    "qs_pg:gn_country":"IT",
    "qs_pg:gn_fcode":"PPL",
    "qs_pg:gn_pop":0,
    "qs_pg:name":"Pontecagnano Faiano",
    "qs_pg:name_adm0":"Italia",
    "qs_pg:name_adm1":"Campania",
    "qs_pg:photos":366,
    "qs_pg:photos_1k":74,
    "qs_pg:photos_9k":2,
    "qs_pg:photos_9r":5,
    "qs_pg:photos_all":366,
    "qs_pg:photos_sr":6,
    "qs_pg:pop_sr":0,
    "qs_pg:qs_pg_placetype":"locality",
    "qs_pg:qs_pg_placetype_gp":"Town",
    "qs_pg:woe_adm0":23424853,
    "woe:adm0_id":23424853,
    "woe:name_adm0":"Italia",
    "woe:name_adm1":"Campania",
    "woe:placetype":"Town",
    "wof:name":"Pontecagnano Faiano",
    "wof:placetype":"locality",
    "wof:population":4087
},
  "geometry": {"coordinates":[14.90244,40.66254],"type":"Point"}
}