{
  "type": "Feature",
  "properties": {
    "gn:admin1_code":"12.0",
    "gn:admin2_code":"VB",
    "gn:admin3_code":"103072.0",
    "gn:asciiname":"Suna",
    "gn:country_code":"IT",
    "gn:dem":208,
    "gn:feature_class":"P",
    "gn:feature_code":"PPL",
    "gn:name":"Suna",
    "gn:population":0,
    "gn:timezone":"Europe/Rome",
    "iso:country":"IT",
    "name:bel_x_preferred":[
        "\u0421\u0443\u043d\u0430"
    ],
    "name:cat_x_preferred":[
        "Suna"
    ],
    "name:ceb_x_preferred":[
        "Suna"
    ],
    "name:deu_x_preferred":[
        "Suna"
    ],
    "name:ita_x_preferred":[
        "Suna"
    ],
    "name:lit_x_preferred":[
        "Suna"
    ],
    "name:rus_x_preferred":[
        "\u0421\u0443\u043d\u0430"
    ],
    "name:swe_x_preferred":[
        "Suna"
    ],
    "name:tur_x_preferred":[
        "Suna"
    ],
    "wof:name":"Suna",
    "wof:placetype":"locality"
},
  "geometry": {"coordinates":[8.54178,45.93081],"type":"Point"}
}