{
  "type": "Feature",
  "properties": {
    "gn:admin1_code":"12.0",
    "gn:admin2_code":"VB",
    "gn:admin3_code":"103072.0",
    "gn:asciiname":"Suna",
    "gn:country_code":"IT",
    "gn:dem":208,
    "gn:feature_class":"P",
    "gn:feature_code":"PPL",
    "gn:name":"Suna",
    "gn:population":0,
    "gn:timezone":"Europe/Rome",
    "iso:country":"IT",
    "wof:name":"Suna",
    "wof:placetype":"locality"
},
  "geometry": {"coordinates":[8.54178,45.93081],"type":"Point"}
}