{
  "type": "Feature",
  "properties": {
    "gn:admin1_code":"12",
    "gn:admin2_code":"CN",
    "gn:admin3_code":"4082.0",
    "gn:asciiname":"Lerda",
    "gn:country_code":"IT",
    "gn:dem":568,
    "gn:feature_class":"P",
    "gn:feature_code":"PPL",
    "gn:name":"Lerda",
    "gn:population":63,
    "gn:timezone":"Europe/Rome",
    "iso:country":"IT",
    "wof:name":"Lerda",
    "wof:placetype":"locality",
    "wof:population":63
},
  "geometry": {"coordinates":[7.42295,44.46405],"type":"Point"}
}