{
  "type": "Feature",
  "properties": {
    "gn:admin1_code":"6",
    "gn:admin2_code":"GO",
    "gn:admin3_code":"31011.0",
    "gn:asciiname":"Atleti Azzurri d'Italia",
    "gn:country_code":"IT",
    "gn:dem":39,
    "gn:feature_class":"P",
    "gn:feature_code":"PPL",
    "gn:name":"Atleti Azzurri d'Italia",
    "gn:population":16,
    "gn:timezone":"Europe/Rome",
    "iso:country":"IT",
    "wof:name":"Atleti Azzurri d'Italia",
    "wof:placetype":"locality",
    "wof:population":16
},
  "geometry": {"coordinates":[13.44187,45.92782],"type":"Point"}
}