{
  "type": "Feature",
  "properties": {
    "gn:admin1_code":"4.0",
    "gn:admin2_code":"AV",
    "gn:admin3_code":"64103.0",
    "gn:asciiname":"Localita Santa",
    "gn:country_code":"IT",
    "gn:dem":165,
    "gn:feature_class":"P",
    "gn:feature_code":"PPLL",
    "gn:name":"Localit\u00e0 Santa",
    "gn:population":0,
    "gn:timezone":"Europe/Rome",
    "iso:country":"IT",
    "name:und_x_variant":[
        "Localit\u00e0 Santa"
    ],
    "wof:name":"Localita Santa",
    "wof:placetype":"locality"
},
  "geometry": {"coordinates":[14.59874,40.94579],"type":"Point"}
}