{
  "type": "Feature",
  "properties": {
    "gn:admin1_code":"4.0",
    "gn:admin2_code":"SA",
    "gn:admin3_code":"65067.0",
    "gn:asciiname":"Monticelli di Sopra",
    "gn:country_code":"IT",
    "gn:dem":157,
    "gn:feature_class":"P",
    "gn:feature_code":"PPL",
    "gn:name":"Monticelli di Sopra",
    "gn:population":52,
    "gn:timezone":"Europe/Rome",
    "iso:country":"IT",
    "wof:name":"Monticelli di Sopra",
    "wof:placetype":"locality",
    "wof:population":52
},
  "geometry": {"coordinates":[14.75718,40.77139],"type":"Point"}
}