{
  "type": "Feature",
  "properties": {
    "gn:admin1_code":"12",
    "gn:admin2_code":"TO",
    "gn:admin3_code":"1240.0",
    "gn:asciiname":"Massa",
    "gn:country_code":"IT",
    "gn:dem":311,
    "gn:feature_class":"P",
    "gn:feature_code":"PPL",
    "gn:name":"Massa",
    "gn:population":66,
    "gn:timezone":"Europe/Rome",
    "iso:country":"IT",
    "wof:name":"Massa",
    "wof:placetype":"locality",
    "wof:population":66
},
  "geometry": {"coordinates":[7.67886,45.23464],"type":"Point"}
}