{
  "type": "Feature",
  "properties": {
    "gn:admin1_code":"4",
    "gn:admin2_code":"BN",
    "gn:admin3_code":"62025.0",
    "gn:asciiname":"Paolucci",
    "gn:country_code":"IT",
    "gn:dem":747,
    "gn:feature_class":"P",
    "gn:feature_code":"PPL",
    "gn:name":"Paolucci",
    "gn:population":30,
    "gn:timezone":"Europe/Rome",
    "iso:country":"IT",
    "wof:name":"Paolucci",
    "wof:placetype":"locality",
    "wof:population":30
},
  "geometry": {"coordinates":[14.88447,41.39763],"type":"Point"}
}