{
  "type": "Feature",
  "properties": {
    "gn:admin1_code":"4",
    "gn:admin2_code":"AV",
    "gn:admin3_code":"64014.0",
    "gn:asciiname":"San Mauro",
    "gn:country_code":"IT",
    "gn:dem":354,
    "gn:feature_class":"P",
    "gn:feature_code":"PPL",
    "gn:name":"San Mauro",
    "gn:population":39,
    "gn:timezone":"Europe/Rome",
    "iso:country":"IT",
    "wof:name":"San Mauro",
    "wof:placetype":"locality",
    "wof:population":39
},
  "geometry": {"coordinates":[15.23159,40.77505],"type":"Point"}
}