{
  "type": "Feature",
  "properties": {
    "gn:admin1_code":"4",
    "gn:admin2_code":"AV",
    "gn:admin3_code":"64014.0",
    "gn:asciiname":"San Mauro",
    "gn:country_code":"IT",
    "gn:dem":354,
    "gn:feature_class":"P",
    "gn:feature_code":"PPL",
    "gn:name":"San Mauro",
    "gn:population":39,
    "gn:timezone":"Europe/Rome",
    "iso:country":"IT",
    "name:ceb_x_preferred":[
        "San Mauro"
    ],
    "name:deu_x_preferred":[
        "San Mauro"
    ],
    "name:glg_x_preferred":[
        "San Mauro"
    ],
    "name:ita_x_preferred":[
        "San Mauro"
    ],
    "name:nld_x_preferred":[
        "San Mauro"
    ],
    "name:por_x_preferred":[
        "San Mauro"
    ],
    "name:rus_x_preferred":[
        "\u0421\u0432\u044f\u0442\u043e\u0439 \u041c\u0430\u0432\u0440"
    ],
    "name:scn_x_preferred":[
        "Santu M\u00e0uru"
    ],
    "name:sco_x_preferred":[
        "San Mauro"
    ],
    "name:srp_x_preferred":[
        "San Mauro"
    ],
    "name:swe_x_preferred":[
        "San Mauro"
    ],
    "wof:name":"San Mauro",
    "wof:placetype":"locality",
    "wof:population":39
},
  "geometry": {"coordinates":[15.23159,40.77505],"type":"Point"}
}