{
  "type": "Feature",
  "properties": {
    "gn:admin1_code":"7",
    "gn:admin2_code":"RM",
    "gn:admin3_code":"58041.0",
    "gn:asciiname":"Sant'Antonio",
    "gn:country_code":"IT",
    "gn:dem":233,
    "gn:feature_class":"P",
    "gn:feature_code":"PPL",
    "gn:name":"Sant'Antonio",
    "gn:population":20,
    "gn:timezone":"Europe/Rome",
    "iso:country":"IT",
    "name:als_x_preferred":[
        "Sant\u2019Antonio"
    ],
    "name:ceb_x_preferred":[
        "Sant'Antonio"
    ],
    "name:deu_x_preferred":[
        "Sant\u2019Antonio"
    ],
    "name:epo_x_preferred":[
        "Sant'Antonio"
    ],
    "name:eus_x_preferred":[
        "Sant'Antonio"
    ],
    "name:ita_x_preferred":[
        "Sant'Antonio"
    ],
    "name:nld_x_preferred":[
        "Sant'Antonio"
    ],
    "name:pol_x_preferred":[
        "Sant\u2019Antonio"
    ],
    "name:por_x_preferred":[
        "Sant'Antonio"
    ],
    "name:srp_x_preferred":[
        "Sant'Antonio"
    ],
    "name:swe_x_preferred":[
        "Sant'Antonio"
    ],
    "name:vec_x_preferred":[
        "Sant'Antonio"
    ],
    "wof:name":"Sant'Antonio",
    "wof:placetype":"locality",
    "wof:population":20
},
  "geometry": {"coordinates":[13.07941,41.69874],"type":"Point"}
}