{
  "type": "Feature",
  "properties": {
    "gn:admin1_code":"16.0",
    "gn:admin2_code":"PT",
    "gn:admin3_code":"47008.0",
    "gn:asciiname":"Cozzile",
    "gn:country_code":"IT",
    "gn:dem":396,
    "gn:elevation":"411.0",
    "gn:feature_class":"P",
    "gn:feature_code":"PPL",
    "gn:name":"Cozzile",
    "gn:population":55,
    "gn:timezone":"Europe/Rome",
    "iso:country":"IT",
    "wof:name":"Cozzile",
    "wof:placetype":"locality",
    "wof:population":55
},
  "geometry": {"coordinates":[10.74132,43.91649],"type":"Point"}
}