{
  "type": "Feature",
  "properties": {
    "gn:admin1_code":"4",
    "gn:admin2_code":"BN",
    "gn:admin3_code":"62013.0",
    "gn:asciiname":"Masserie Mancini",
    "gn:country_code":"IT",
    "gn:dem":448,
    "gn:feature_class":"P",
    "gn:feature_code":"PPL",
    "gn:name":"Masserie Mancini",
    "gn:population":30,
    "gn:timezone":"Europe/Rome",
    "iso:country":"IT",
    "wof:name":"Masserie Mancini",
    "wof:placetype":"locality",
    "wof:population":30
},
  "geometry": {"coordinates":[14.74787,41.29321],"type":"Point"}
}