{
  "type": "Feature",
  "properties": {
    "gn:admin1_code":"16",
    "gn:admin2_code":"MS",
    "gn:admin3_code":"45015.0",
    "gn:asciiname":"Lorenzana",
    "gn:country_code":"IT",
    "gn:dem":394,
    "gn:feature_class":"P",
    "gn:feature_code":"PPLL",
    "gn:name":"Lorenzana",
    "gn:population":10,
    "gn:timezone":"Europe/Rome",
    "iso:country":"IT",
    "wof:name":"Lorenzana",
    "wof:placetype":"locality",
    "wof:population":10
},
  "geometry": {"coordinates":[9.92255,44.26547],"type":"Point"}
}