{
  "type": "Feature",
  "properties": {
    "gn:admin1_code":"9",
    "gn:admin2_code":"CR",
    "gn:admin3_code":"19074.0",
    "gn:asciiname":"Bardelle",
    "gn:country_code":"IT",
    "gn:dem":36,
    "gn:feature_class":"P",
    "gn:feature_code":"PPL",
    "gn:name":"Bardelle",
    "gn:population":62,
    "gn:timezone":"Europe/Rome",
    "iso:country":"IT",
    "wof:name":"Bardelle",
    "wof:placetype":"locality",
    "wof:population":62
},
  "geometry": {"coordinates":[10.12717,45.09671],"type":"Point"}
}