{
  "type": "Feature",
  "properties": {
    "gn:admin1_code":"4",
    "gn:admin2_code":"BN",
    "gn:admin3_code":"62029.0",
    "gn:asciiname":"Porti",
    "gn:country_code":"IT",
    "gn:dem":233,
    "gn:feature_class":"P",
    "gn:feature_code":"PPL",
    "gn:name":"Porti",
    "gn:population":14,
    "gn:timezone":"Europe/Rome",
    "iso:country":"IT",
    "wof:name":"Porti",
    "wof:placetype":"locality",
    "wof:population":14
},
  "geometry": {"coordinates":[14.45984,41.28518],"type":"Point"}
}