{
  "type": "Feature",
  "properties": {
    "gn:admin1_code":"20",
    "gn:admin2_code":"RO",
    "gn:admin3_code":"29021.0",
    "gn:asciiname":"Coronella",
    "gn:country_code":"IT",
    "gn:dem":8,
    "gn:feature_class":"P",
    "gn:feature_code":"PPL",
    "gn:name":"Coronella",
    "gn:population":20,
    "gn:timezone":"Europe/Rome",
    "iso:country":"IT",
    "name:aze_x_preferred":[
        "Qonur ilan"
    ],
    "name:bul_x_preferred":[
        "\u041c\u0435\u0434\u044f\u043d\u043a\u0438"
    ],
    "name:cat_x_preferred":[
        "Coronella"
    ],
    "name:ceb_x_preferred":[
        "Coronella"
    ],
    "name:deu_x_preferred":[
        "Glattnattern"
    ],
    "name:est_x_preferred":[
        "Silenastik"
    ],
    "name:eus_x_preferred":[
        "Coronella"
    ],
    "name:fra_x_preferred":[
        "Coronella"
    ],
    "name:hye_x_preferred":[
        "\u054a\u0572\u0576\u0571\u0585\u0571\u0565\u0580"
    ],
    "name:ita_x_preferred":[
        "Coronella"
    ],
    "name:kat_x_preferred":[
        "\u10e1\u10de\u10d8\u10da\u10d4\u10dc\u10eb\u10d0"
    ],
    "name:kir_x_preferred":[
        "\u0416\u044b\u043b\u043c\u0430 \u0441\u0443\u0443\u0436\u044b\u043b\u0430\u043d\u0434\u0430\u0440"
    ],
    "name:lav_x_preferred":[
        "Gluden\u0101s \u010d\u016bskas"
    ],
    "name:lit_x_preferred":[
        "Lygia\u017evyniai \u017eal\u010diai"
    ],
    "name:nld_x_preferred":[
        "Coronella"
    ],
    "name:pol_x_preferred":[
        "Coronella"
    ],
    "name:ron_x_preferred":[
        "Coronella"
    ],
    "name:rus_x_preferred":[
        "\u041c\u0435\u0434\u044f\u043d\u043a\u0438"
    ],
    "name:slk_x_preferred":[
        "Coronella"
    ],
    "name:spa_x_preferred":[
        "Coronella"
    ],
    "name:swe_x_preferred":[
        "Coronella"
    ],
    "name:ukr_x_preferred":[
        "\u041c\u0456\u0434\u044f\u043d\u043a\u0430"
    ],
    "name:war_x_preferred":[
        "Coronella"
    ],
    "wof:name":"Coronella",
    "wof:placetype":"locality",
    "wof:population":20
},
  "geometry": {"coordinates":[11.43304,44.96257],"type":"Point"}
}