{
  "type": "Feature",
  "properties": {
    "gn:admin1_code":"5.0",
    "gn:admin2_code":"BO",
    "gn:admin3_code":"37010.0",
    "gn:asciiname":"Carpineta",
    "gn:country_code":"IT",
    "gn:dem":474,
    "gn:elevation":"495.0",
    "gn:feature_class":"P",
    "gn:feature_code":"PPL",
    "gn:name":"Carpineta",
    "gn:population":103,
    "gn:timezone":"Europe/Rome",
    "iso:country":"IT",
    "wof:name":"Carpineta",
    "wof:placetype":"locality",
    "wof:population":103
},
  "geometry": {"coordinates":[11.07125,44.17369],"type":"Point"}
}