{
  "type": "Feature",
  "properties": {
    "gn:admin1_code":"8.0",
    "gn:admin2_code":"GE",
    "gn:admin3_code":"10034.0",
    "gn:asciiname":"Pontegiacomo Inferiore",
    "gn:country_code":"IT",
    "gn:dem":374,
    "gn:feature_class":"P",
    "gn:feature_code":"PPL",
    "gn:name":"Pontegiacomo Inferiore",
    "gn:population":0,
    "gn:timezone":"Europe/Rome",
    "iso:country":"IT",
    "wof:name":"Pontegiacomo Inferiore",
    "wof:placetype":"locality"
},
  "geometry": {"coordinates":[9.41614,44.4022],"type":"Point"}
}