{
  "type": "Feature",
  "properties": {
    "gn:admin1_code":"7.0",
    "gn:admin2_code":"RM",
    "gn:admin3_code":"58029.0",
    "gn:asciiname":"Valle del Canneto",
    "gn:country_code":"IT",
    "gn:dem":122,
    "gn:feature_class":"P",
    "gn:feature_code":"PPL",
    "gn:name":"Valle del Canneto",
    "gn:population":15,
    "gn:timezone":"Europe/Rome",
    "iso:country":"IT",
    "wof:name":"Valle del Canneto",
    "wof:placetype":"locality",
    "wof:population":15
},
  "geometry": {"coordinates":[12.16073,41.97304000000001],"type":"Point"}
}