{
  "type": "Feature",
  "properties": {
    "iso:country":"IT",
    "qs_pg:aaroncc":"IT",
    "qs_pg:name":"Katharinaberg",
    "qs_pg:name_adm0":"Italia",
    "qs_pg:name_adm1":"Trentino-Alto Adige",
    "qs_pg:photos":48,
    "qs_pg:photos_1k":10,
    "qs_pg:photos_9k":1,
    "qs_pg:photos_9r":2,
    "qs_pg:photos_all":48,
    "qs_pg:photos_sr":2,
    "qs_pg:pop_sr":0,
    "qs_pg:qs_pg_placetype":"locality",
    "qs_pg:qs_pg_placetype_gp":"Town",
    "qs_pg:woe_adm0":23424853,
    "woe:adm0_id":23424853,
    "woe:name_adm0":"Italia",
    "woe:name_adm1":"Trentino-Alto Adige",
    "woe:placetype":"Town",
    "wof:name":"Katharinaberg",
    "wof:placetype":"locality"
},
  "geometry": {"coordinates":[10.934368,46.689239],"type":"Point"}
}