{
  "type": "Feature",
  "properties": {
    "gn:admin1_code":"1",
    "gn:admin2_code":"AQ",
    "gn:admin3_code":"66089.0",
    "gn:asciiname":"Stazione Ferroviaria",
    "gn:country_code":"IT",
    "gn:dem":789,
    "gn:feature_class":"P",
    "gn:feature_code":"PPL",
    "gn:name":"Stazione Ferroviaria",
    "gn:population":20,
    "gn:timezone":"Europe/Rome",
    "iso:country":"IT",
    "wof:name":"Stazione Ferroviaria",
    "wof:placetype":"locality",
    "wof:population":20
},
  "geometry": {"coordinates":[13.21722,42.09729],"type":"Point"}
}