{
  "type": "Feature",
  "properties": {
    "gn:admin1_code":"5",
    "gn:admin2_code":"RA",
    "gn:admin3_code":"39005.0",
    "gn:asciiname":"San Ruffillo",
    "gn:country_code":"IT",
    "gn:dem":410,
    "gn:feature_class":"P",
    "gn:feature_code":"PPLL",
    "gn:name":"San Ruffillo",
    "gn:population":6,
    "gn:timezone":"Europe/Rome",
    "iso:country":"IT",
    "wof:name":"San Ruffillo",
    "wof:placetype":"locality",
    "wof:population":6
},
  "geometry": {"coordinates":[11.59912,44.21442],"type":"Point"}
}