{
  "type": "Feature",
  "properties": {
    "gn:admin1_code":"20",
    "gn:admin2_code":"PD",
    "gn:admin3_code":"28032.0",
    "gn:asciiname":"Delle Forche",
    "gn:country_code":"IT",
    "gn:dem":44,
    "gn:feature_class":"P",
    "gn:feature_code":"PPL",
    "gn:name":"Delle Forche",
    "gn:population":18,
    "gn:timezone":"Europe/Rome",
    "iso:country":"IT",
    "wof:name":"Delle Forche",
    "wof:placetype":"locality",
    "wof:population":18
},
  "geometry": {"coordinates":[11.81299,45.65245],"type":"Point"}
}