{
  "type": "Feature",
  "properties": {
    "gn:admin1_code":"20.0",
    "gn:admin2_code":"TV",
    "gn:admin3_code":"26018.0",
    "gn:asciiname":"Gai",
    "gn:country_code":"IT",
    "gn:dem":254,
    "gn:elevation":"259.0",
    "gn:feature_class":"P",
    "gn:feature_code":"PPL",
    "gn:name":"Gai",
    "gn:population":224,
    "gn:timezone":"Europe/Rome",
    "iso:country":"IT",
    "name:cat_x_preferred":[
        "Gai"
    ],
    "name:ceb_x_preferred":[
        "Gai"
    ],
    "name:fra_x_preferred":[
        "Gai"
    ],
    "name:rus_x_preferred":[
        "\u0413\u0430\u0438"
    ],
    "name:spa_x_preferred":[
        "Gai"
    ],
    "name:swe_x_preferred":[
        "Gai"
    ],
    "name:ukr_x_preferred":[
        "\u0413\u0430\u0457"
    ],
    "name:zho_x_preferred":[
        "Gai"
    ],
    "wof:name":"Gai",
    "wof:placetype":"locality",
    "wof:population":224
},
  "geometry": {"coordinates":[12.17396,45.9679],"type":"Point"}
}