{
  "type": "Feature",
  "properties": {
    "gn:admin1_code":"1.0",
    "gn:admin2_code":"AQ",
    "gn:admin3_code":"66101.0",
    "gn:asciiname":"Colle San Vito",
    "gn:cc2":"IT",
    "gn:country_code":"IT",
    "gn:dem":845,
    "gn:elevation":"847.0",
    "gn:feature_class":"P",
    "gn:feature_code":"PPL",
    "gn:name":"Colle San Vito",
    "gn:population":157,
    "gn:timezone":"Europe/Rome",
    "iso:country":"IT",
    "name:und_x_variant":[
        "San Vito",
        "Colle San Vito"
    ],
    "wof:name":"Colle San Vito",
    "wof:placetype":"locality",
    "wof:population":157
},
  "geometry": {"coordinates":[13.29195,42.29388],"type":"Point"}
}