{
  "type": "Feature",
  "properties": {
    "gn:admin1_code":"7",
    "gn:admin2_code":"FR",
    "gn:admin3_code":"60026.0",
    "gn:asciiname":"Prata-Conte",
    "gn:country_code":"IT",
    "gn:dem":90,
    "gn:feature_class":"P",
    "gn:feature_code":"PPL",
    "gn:name":"Prata-Conte",
    "gn:population":99,
    "gn:timezone":"Europe/Rome",
    "iso:country":"IT",
    "wof:name":"Prata-Conte",
    "wof:placetype":"locality",
    "wof:population":99
},
  "geometry": {"coordinates":[13.89281,41.46354],"type":"Point"}
}