{
  "type": "Feature",
  "properties": {
    "gn:admin1_code":"12.0",
    "gn:admin2_code":"TO",
    "gn:admin3_code":"1269.0",
    "gn:asciiname":"Cerone",
    "gn:country_code":"IT",
    "gn:dem":226,
    "gn:feature_class":"P",
    "gn:feature_code":"PPL",
    "gn:name":"Cerone",
    "gn:population":885,
    "gn:timezone":"Europe/Rome",
    "iso:country":"IT",
    "wof:name":"Cerone",
    "wof:placetype":"locality",
    "wof:population":885
},
  "geometry": {"coordinates":[7.89157,45.39852],"type":"Point"}
}