{
  "type": "Feature",
  "properties": {
    "gn:admin1_code":"20.0",
    "gn:admin2_code":"RO",
    "gn:admin3_code":"29047.0",
    "gn:asciiname":"Vallalta sul Canale",
    "gn:country_code":"IT",
    "gn:dem":8,
    "gn:feature_class":"P",
    "gn:feature_code":"PPL",
    "gn:name":"Vallalta sul Canale",
    "gn:population":10,
    "gn:timezone":"Europe/Rome",
    "iso:country":"IT",
    "wof:name":"Vallalta sul Canale",
    "wof:placetype":"locality",
    "wof:population":10
},
  "geometry": {"coordinates":[11.48105,45.0359],"type":"Point"}
}