{
  "type": "Feature",
  "properties": {
    "gn:admin1_code":"9",
    "gn:admin2_code":"LO",
    "gn:admin3_code":"98008.0",
    "gn:asciiname":"Gugnano",
    "gn:country_code":"IT",
    "gn:dem":86,
    "gn:feature_class":"P",
    "gn:feature_code":"PPL",
    "gn:name":"Gugnano",
    "gn:population":321,
    "gn:timezone":"Europe/Rome",
    "iso:country":"IT",
    "wof:name":"Gugnano",
    "wof:placetype":"locality",
    "wof:population":321
},
  "geometry": {"coordinates":[9.33213,45.29263],"type":"Point"}
}