{
  "type": "Feature",
  "properties": {
    "gn:admin1_code":"5",
    "gn:admin2_code":"RE",
    "gn:admin3_code":"35041.0",
    "gn:asciiname":"Salvarana",
    "gn:country_code":"IT",
    "gn:dem":384,
    "gn:feature_class":"P",
    "gn:feature_code":"PPL",
    "gn:name":"Salvarana",
    "gn:population":13,
    "gn:timezone":"Europe/Rome",
    "iso:country":"IT",
    "wof:name":"Salvarana",
    "wof:placetype":"locality",
    "wof:population":13
},
  "geometry": {"coordinates":[10.50056,44.40408],"type":"Point"}
}