{
  "type": "Feature",
  "properties": {
    "gn:admin1_code":"12",
    "gn:admin2_code":"AL",
    "gn:admin3_code":"6184.0",
    "gn:asciiname":"Case dei Rei",
    "gn:country_code":"IT",
    "gn:dem":292,
    "gn:feature_class":"P",
    "gn:feature_code":"PPL",
    "gn:name":"Case dei Rei",
    "gn:population":12,
    "gn:timezone":"Europe/Rome",
    "iso:country":"IT",
    "wof:name":"Case dei Rei",
    "wof:placetype":"locality",
    "wof:population":12
},
  "geometry": {"coordinates":[8.1726,45.13702],"type":"Point"}
}