{
  "type": "Feature",
  "properties": {
    "iso:country":"IT",
    "wof:name":"Valle Aurelia",
    "wof:placetype":"neighbourhood"
},
  "geometry": {"coordinates":[12.43133032635884,41.90411402280834],"type":"Point"}
}