{
  "type": "Feature",
  "properties": {
    "gn:admin1_code":"18",
    "gn:admin2_code":"TR",
    "gn:admin3_code":"55019.0",
    "gn:asciiname":"Varcone",
    "gn:country_code":"IT",
    "gn:dem":477,
    "gn:feature_class":"P",
    "gn:feature_code":"PPL",
    "gn:name":"Varcone",
    "gn:population":23,
    "gn:timezone":"Europe/Rome",
    "iso:country":"IT",
    "wof:name":"Varcone",
    "wof:placetype":"locality",
    "wof:population":23
},
  "geometry": {"coordinates":[12.73925,42.59767],"type":"Point"}
}