{
  "type": "Feature",
  "properties": {
    "gn:admin1_code":"4",
    "gn:admin2_code":"AV",
    "gn:admin3_code":"64048.0",
    "gn:asciiname":"Orticello",
    "gn:country_code":"IT",
    "gn:dem":356,
    "gn:feature_class":"P",
    "gn:feature_code":"PPL",
    "gn:name":"Orticello",
    "gn:population":145,
    "gn:timezone":"Europe/Rome",
    "iso:country":"IT",
    "wof:name":"Orticello",
    "wof:placetype":"locality",
    "wof:population":145
},
  "geometry": {"coordinates":[15.03052,41.11267],"type":"Point"}
}