{
  "type": "Feature",
  "properties": {
    "gn:admin1_code":"5.0",
    "gn:admin2_code":"BO",
    "gn:admin3_code":"37034.0",
    "gn:asciiname":"Scanello",
    "gn:country_code":"IT",
    "gn:dem":629,
    "gn:feature_class":"P",
    "gn:feature_code":"PPL",
    "gn:name":"Scanello",
    "gn:population":0,
    "gn:timezone":"Europe/Rome",
    "iso:country":"IT",
    "wof:name":"Scanello",
    "wof:placetype":"locality"
},
  "geometry": {"coordinates":[11.35,44.26667],"type":"Point"}
}