{
  "type": "Feature",
  "properties": {
    "gn:admin1_code":"10",
    "gn:admin2_code":"MC",
    "gn:admin3_code":"43055.0",
    "gn:asciiname":"Illuminati",
    "gn:country_code":"IT",
    "gn:dem":371,
    "gn:feature_class":"P",
    "gn:feature_code":"PPL",
    "gn:name":"Illuminati",
    "gn:population":40,
    "gn:timezone":"Europe/Rome",
    "iso:country":"IT",
    "wof:name":"Illuminati",
    "wof:placetype":"locality",
    "wof:population":40
},
  "geometry": {"coordinates":[13.36618,43.18236],"type":"Point"}
}