{
  "type": "Feature",
  "properties": {
    "gn:admin1_code":"12",
    "gn:admin2_code":"TO",
    "gn:admin3_code":"1300.0",
    "gn:asciiname":"Palot",
    "gn:country_code":"IT",
    "gn:dem":271,
    "gn:feature_class":"P",
    "gn:feature_code":"PPL",
    "gn:name":"Palot",
    "gn:population":36,
    "gn:timezone":"Europe/Rome",
    "iso:country":"IT",
    "wof:name":"Palot",
    "wof:placetype":"locality",
    "wof:population":36
},
  "geometry": {"coordinates":[7.44256,44.80294],"type":"Point"}
}