{
  "type": "Feature",
  "properties": {
    "gn:admin1_code":"20",
    "gn:admin2_code":"VI",
    "gn:admin3_code":"24077.0",
    "gn:asciiname":"Malossi",
    "gn:country_code":"IT",
    "gn:dem":232,
    "gn:feature_class":"P",
    "gn:feature_code":"PPL",
    "gn:name":"Malossi",
    "gn:population":22,
    "gn:timezone":"Europe/Rome",
    "iso:country":"IT",
    "wof:name":"Malossi",
    "wof:placetype":"locality",
    "wof:population":22
},
  "geometry": {"coordinates":[11.62665,45.74549],"type":"Point"}
}