{
  "type": "Feature",
  "properties": {
    "iso:country":"IT",
    "name:bul_x_preferred":[
        "\u041f\u043e\u043d\u0442\u0435\u0441\u0442\u0430\u0437\u0435\u043c\u0435\u0441\u0435"
    ],
    "name:dut_x_preferred":[
        "Pontestazzemese"
    ],
    "name:eng_x_preferred":[
        "Pontestazzemese"
    ],
    "name:fre_x_preferred":[
        "Pontestazzemese"
    ],
    "name:hun_x_preferred":[
        "Pontestazzemese"
    ],
    "name:ita_x_preferred":[
        "Pontestazzemese"
    ],
    "name:srp_x_preferred":[
        "Pontestazzemese"
    ],
    "qs:a0":"Italia",
    "qs:a1":"*Lucca",
    "qs:a1r":"0Toscana",
    "qs:adm0":"Italia",
    "qs:la_lc":"*",
    "qs:level":"locality",
    "qs:loc":"Pontestazzemese",
    "qs:loc_alt":"Pontestazzemese",
    "qs:pop":0,
    "qs:type":"buffered point",
    "wof:name":"Pontestazzemese",
    "wof:placetype":"locality"
},
  "geometry": {"coordinates":[10.29584,43.998348],"type":"Point"}
}