{
  "type": "Feature",
  "properties": {
    "gn:admin1_code":"10",
    "gn:admin2_code":"AP",
    "gn:admin3_code":"44036.0",
    "gn:asciiname":"Cimula",
    "gn:country_code":"IT",
    "gn:dem":59,
    "gn:feature_class":"P",
    "gn:feature_code":"PPL",
    "gn:name":"Cimula",
    "gn:population":46,
    "gn:timezone":"Europe/Rome",
    "iso:country":"IT",
    "wof:name":"Cimula",
    "wof:placetype":"locality",
    "wof:population":46
},
  "geometry": {"coordinates":[13.7789,43.07446],"type":"Point"}
}