{
  "type": "Feature",
  "properties": {
    "gn:admin1_code":"18",
    "gn:admin2_code":"PG",
    "gn:admin3_code":"54033.0",
    "gn:asciiname":"Santa Maria Disette",
    "gn:country_code":"IT",
    "gn:dem":260,
    "gn:feature_class":"P",
    "gn:feature_code":"PPL",
    "gn:name":"Santa Maria Disette",
    "gn:population":229,
    "gn:timezone":"Europe/Rome",
    "iso:country":"IT",
    "wof:name":"Santa Maria Disette",
    "wof:placetype":"locality",
    "wof:population":229
},
  "geometry": {"coordinates":[12.32061,43.33037],"type":"Point"}
}