{
  "type": "Feature",
  "properties": {
    "gn:admin1_code":"4.0",
    "gn:admin2_code":"SA",
    "gn:admin3_code":"65103.0",
    "gn:asciiname":"San Giuliano",
    "gn:country_code":"IT",
    "gn:dem":413,
    "gn:feature_class":"P",
    "gn:feature_code":"PPL",
    "gn:name":"San Giuliano",
    "gn:population":0,
    "gn:timezone":"Europe/Rome",
    "iso:country":"IT",
    "wof:name":"San Giuliano",
    "wof:placetype":"locality"
},
  "geometry": {"coordinates":[15.06667,40.33333],"type":"Point"}
}