{
  "type": "Feature",
  "properties": {
    "iso:country":"IT",
    "name:deu_x_preferred":[
        "Sant'Ambrogio Olona"
    ],
    "name:eng_x_preferred":[
        "Sant'Ambrogio Olona"
    ],
    "name:fra_x_preferred":[
        "Sant'Ambrogio Olona"
    ],
    "name:ita_x_preferred":[
        "Sant'Ambrogio Olona"
    ],
    "name:nld_x_preferred":[
        "Sant'Ambrogio Olona"
    ],
    "qs_pg:aaroncc":"IT",
    "qs_pg:name":"Sant'Ambrogio Olona",
    "qs_pg:name_adm0":"Italia",
    "qs_pg:name_adm1":"Lombardia",
    "qs_pg:photos":28,
    "qs_pg:photos_1k":6,
    "qs_pg:photos_9k":1,
    "qs_pg:photos_9r":2,
    "qs_pg:photos_all":28,
    "qs_pg:photos_sr":2,
    "qs_pg:pop_sr":0,
    "qs_pg:qs_pg_placetype":"locality",
    "qs_pg:qs_pg_placetype_gp":"Town",
    "qs_pg:woe_adm0":23424853,
    "woe:adm0_id":23424853,
    "woe:name_adm0":"Italia",
    "woe:name_adm1":"Lombardia",
    "woe:placetype":"Town",
    "wof:name":"Sant'Ambrogio Olona",
    "wof:placetype":"locality"
},
  "geometry": {"coordinates":[8.812322,45.8404935],"type":"Point"}
}