{
  "type": "Feature",
  "properties": {
    "gn:admin1_code":"3.0",
    "gn:admin2_code":"CS",
    "gn:admin3_code":"78021.0",
    "gn:asciiname":"San Giacomo-Marinella",
    "gn:country_code":"IT",
    "gn:dem":7,
    "gn:feature_class":"P",
    "gn:feature_code":"PPL",
    "gn:name":"San Giacomo-Marinella",
    "gn:population":604,
    "gn:timezone":"Europe/Rome",
    "iso:country":"IT",
    "wof:name":"San Giacomo-Marinella",
    "wof:placetype":"locality",
    "wof:population":604
},
  "geometry": {"coordinates":[16.82186,39.57362],"type":"Point"}
}