{
  "type": "Feature",
  "properties": {
    "gn:admin1_code":"4",
    "gn:admin2_code":"AV",
    "gn:admin3_code":"64054.0",
    "gn:asciiname":"Gaudi",
    "gn:country_code":"IT",
    "gn:dem":446,
    "gn:feature_class":"P",
    "gn:feature_code":"PPL",
    "gn:name":"Gaudi",
    "gn:population":82,
    "gn:timezone":"Europe/Rome",
    "iso:country":"IT",
    "wof:name":"Gaudi",
    "wof:placetype":"locality",
    "wof:population":82
},
  "geometry": {"coordinates":[14.67327,40.91406],"type":"Point"}
}