{
  "type": "Feature",
  "properties": {
    "gn:admin1_code":"12",
    "gn:admin2_code":"CN",
    "gn:admin3_code":"4079.0",
    "gn:asciiname":"Medich-Torre",
    "gn:country_code":"IT",
    "gn:dem":763,
    "gn:feature_class":"P",
    "gn:feature_code":"PPL",
    "gn:name":"Medich-Torre",
    "gn:population":42,
    "gn:timezone":"Europe/Rome",
    "iso:country":"IT",
    "wof:name":"Medich-Torre",
    "wof:placetype":"locality",
    "wof:population":42
},
  "geometry": {"coordinates":[7.33491,44.31625],"type":"Point"}
}