{
  "type": "Feature",
  "properties": {
    "gn:admin1_code":"4.0",
    "gn:admin2_code":"BN",
    "gn:admin3_code":"62051.0",
    "gn:asciiname":"Mastramici di Sopra",
    "gn:country_code":"IT",
    "gn:dem":961,
    "gn:feature_class":"P",
    "gn:feature_code":"PPL",
    "gn:name":"Mastramici di Sopra",
    "gn:population":18,
    "gn:timezone":"Europe/Rome",
    "iso:country":"IT",
    "wof:name":"Mastramici di Sopra",
    "wof:placetype":"locality",
    "wof:population":18
},
  "geometry": {"coordinates":[14.57326,41.32797],"type":"Point"}
}