{
  "type": "Feature",
  "properties": {
    "gn:admin1_code":"15",
    "gn:admin2_code":"ME",
    "gn:admin3_code":"83088.0",
    "gn:asciiname":"Cancello",
    "gn:country_code":"IT",
    "gn:dem":681,
    "gn:feature_class":"P",
    "gn:feature_code":"PPL",
    "gn:name":"Cancello",
    "gn:population":76,
    "gn:timezone":"Europe/Rome",
    "iso:country":"IT",
    "name:ceb_x_preferred":[
        "Cancello"
    ],
    "name:ita_x_preferred":[
        "Cancello"
    ],
    "name:nld_x_preferred":[
        "Cancello"
    ],
    "name:srp_x_preferred":[
        "Kan\u010delo"
    ],
    "name:swe_x_preferred":[
        "Cancello"
    ],
    "wof:name":"Cancello",
    "wof:placetype":"locality",
    "wof:population":76
},
  "geometry": {"coordinates":[14.89422,38.07994],"type":"Point"}
}