{
  "type": "Feature",
  "properties": {
    "gn:admin1_code":"20",
    "gn:admin2_code":"PD",
    "gn:admin3_code":"28084.0",
    "gn:asciiname":"Ponte Nuovo",
    "gn:country_code":"IT",
    "gn:dem":5,
    "gn:feature_class":"P",
    "gn:feature_code":"PPL",
    "gn:name":"Ponte Nuovo",
    "gn:population":33,
    "gn:timezone":"Europe/Rome",
    "iso:country":"IT",
    "wof:name":"Ponte Nuovo",
    "wof:placetype":"locality",
    "wof:population":33
},
  "geometry": {"coordinates":[11.64869,45.1344],"type":"Point"}
}