{
  "type": "Feature",
  "properties": {
    "gn:admin1_code":"7.0",
    "gn:admin2_code":"RM",
    "gn:admin3_code":"58050.0",
    "gn:asciiname":"Stragonello",
    "gn:country_code":"IT",
    "gn:dem":172,
    "gn:feature_class":"P",
    "gn:feature_code":"PPL",
    "gn:name":"Stragonello",
    "gn:population":342,
    "gn:timezone":"Europe/Rome",
    "iso:country":"IT",
    "wof:name":"Stragonello",
    "wof:placetype":"locality",
    "wof:population":342
},
  "geometry": {"coordinates":[12.70452,41.65706],"type":"Point"}
}