{
  "type": "Feature",
  "properties": {
    "gn:admin1_code":"8.0",
    "gn:admin2_code":"GE",
    "gn:admin3_code":"10046.0",
    "gn:asciiname":"San Martino di Noceto",
    "gn:country_code":"IT",
    "gn:dem":223,
    "gn:elevation":"232.0",
    "gn:feature_class":"P",
    "gn:feature_code":"PPL",
    "gn:name":"San Martino di Noceto",
    "gn:population":317,
    "gn:timezone":"Europe/Rome",
    "iso:country":"IT",
    "wof:name":"San Martino di Noceto",
    "wof:placetype":"locality",
    "wof:population":317
},
  "geometry": {"coordinates":[9.17496,44.35988],"type":"Point"}
}