{
  "type": "Feature",
  "properties": {
    "gn:admin1_code":"12",
    "gn:admin2_code":"TO",
    "gn:admin3_code":"1063.0",
    "gn:asciiname":"Monache",
    "gn:country_code":"IT",
    "gn:dem":278,
    "gn:feature_class":"P",
    "gn:feature_code":"PPL",
    "gn:name":"Monache",
    "gn:population":24,
    "gn:timezone":"Europe/Rome",
    "iso:country":"IT",
    "wof:name":"Monache",
    "wof:placetype":"locality",
    "wof:population":24
},
  "geometry": {"coordinates":[7.66639,45.18943],"type":"Point"}
}