{
  "type": "Feature",
  "properties": {
    "iso:country":"IT",
    "name:ita_x_preferred":[
        "Porta Monforte"
    ],
    "wof:name":"Porta Monforte",
    "wof:placetype":"neighbourhood"
},
  "geometry": {"coordinates":[9.20473815341565,45.46792569168674],"type":"Point"}
}