{
  "type": "Feature",
  "properties": {
    "gn:admin1_code":"17",
    "gn:admin2_code":"BZ",
    "gn:admin3_code":"21047.0",
    "gn:asciiname":"Costa",
    "gn:country_code":"IT",
    "gn:dem":1346,
    "gn:feature_class":"P",
    "gn:feature_code":"PPL",
    "gn:name":"Costa",
    "gn:population":33,
    "gn:timezone":"Europe/Rome",
    "iso:country":"IT",
    "wof:name":"Costa",
    "wof:placetype":"locality",
    "wof:population":33
},
  "geometry": {"coordinates":[11.93077,46.71051],"type":"Point"}
}