{
  "type": "Feature",
  "properties": {
    "gn:admin1_code":"18.0",
    "gn:admin2_code":"PG",
    "gn:admin3_code":"54005.0",
    "gn:asciiname":"Eremo Francescano",
    "gn:country_code":"IT",
    "gn:dem":506,
    "gn:feature_class":"P",
    "gn:feature_code":"PPLL",
    "gn:name":"Eremo Francescano",
    "gn:population":3,
    "gn:timezone":"Europe/Rome",
    "iso:country":"IT",
    "wof:name":"Eremo Francescano",
    "wof:placetype":"locality",
    "wof:population":3
},
  "geometry": {"coordinates":[12.7658,42.84431],"type":"Point"}
}