{
  "type": "Feature",
  "properties": {
    "gn:admin1_code":"20",
    "gn:admin2_code":"PD",
    "gn:admin3_code":"28045.0",
    "gn:asciiname":"Scarso",
    "gn:country_code":"IT",
    "gn:dem":18,
    "gn:feature_class":"P",
    "gn:feature_code":"PPL",
    "gn:name":"Scarso",
    "gn:population":115,
    "gn:timezone":"Europe/Rome",
    "iso:country":"IT",
    "wof:name":"Scarso",
    "wof:placetype":"locality",
    "wof:population":115
},
  "geometry": {"coordinates":[11.82267,45.46194000000001],"type":"Point"}
}