{
  "type": "Feature",
  "properties": {
    "gn:admin1_code":"5.0",
    "gn:admin2_code":"FC",
    "gn:admin3_code":"40016.0",
    "gn:asciiname":"Verzaglia",
    "gn:country_code":"IT",
    "gn:dem":7,
    "gn:feature_class":"P",
    "gn:feature_code":"PPL",
    "gn:name":"Verzaglia",
    "gn:population":0,
    "gn:timezone":"Europe/Rome",
    "iso:country":"IT",
    "wof:name":"Verzaglia",
    "wof:placetype":"locality"
},
  "geometry": {"coordinates":[12.38917,44.14111],"type":"Point"}
}