{
  "type": "Feature",
  "properties": {
    "gn:admin1_code":"16",
    "gn:admin2_code":"PT",
    "gn:admin3_code":"47007.0",
    "gn:asciiname":"La Sassa",
    "gn:country_code":"IT",
    "gn:dem":311,
    "gn:feature_class":"P",
    "gn:feature_code":"PPL",
    "gn:name":"La Sassa",
    "gn:population":22,
    "gn:timezone":"Europe/Rome",
    "iso:country":"IT",
    "name:ceb_x_preferred":[
        "Sassa"
    ],
    "name:ita_x_preferred":[
        "La Sassa"
    ],
    "name:lat_x_preferred":[
        "Castrum Saxae"
    ],
    "name:nld_x_preferred":[
        "La Sassa"
    ],
    "name:srp_x_preferred":[
        "\u041b\u0430 \u0421\u0430\u0441\u0430"
    ],
    "wof:name":"La Sassa",
    "wof:placetype":"locality",
    "wof:population":22
},
  "geometry": {"coordinates":[10.77619,43.93045],"type":"Point"}
}