{
  "type": "Feature",
  "properties": {
    "gn:admin1_code":"9",
    "gn:admin2_code":"BG",
    "gn:admin3_code":"16194.0",
    "gn:asciiname":"Costa del Gavarno",
    "gn:country_code":"IT",
    "gn:dem":473,
    "gn:feature_class":"P",
    "gn:feature_code":"PPL",
    "gn:name":"Costa del Gavarno",
    "gn:population":29,
    "gn:timezone":"Europe/Rome",
    "iso:country":"IT",
    "wof:name":"Costa del Gavarno",
    "wof:placetype":"locality",
    "wof:population":29
},
  "geometry": {"coordinates":[9.7794,45.72462],"type":"Point"}
}