{
  "type": "Feature",
  "properties": {
    "gn:admin1_code":"20",
    "gn:admin2_code":"VE",
    "gn:admin3_code":"27029.0",
    "gn:asciiname":"Fossalato",
    "gn:country_code":"IT",
    "gn:dem":4,
    "gn:feature_class":"P",
    "gn:feature_code":"PPL",
    "gn:name":"Fossalato",
    "gn:population":90,
    "gn:timezone":"Europe/Rome",
    "iso:country":"IT",
    "wof:name":"Fossalato",
    "wof:placetype":"locality",
    "wof:population":90
},
  "geometry": {"coordinates":[12.8545,45.79348],"type":"Point"}
}