{
  "type": "Feature",
  "properties": {
    "gn:admin1_code":"9.0",
    "gn:admin2_code":"PV",
    "gn:admin3_code":"18090.0",
    "gn:asciiname":"Oxon Italia S.P.A.",
    "gn:country_code":"IT",
    "gn:dem":72,
    "gn:feature_class":"P",
    "gn:feature_code":"PPLL",
    "gn:name":"Oxon Italia S.P.A.",
    "gn:population":0,
    "gn:timezone":"Europe/Rome",
    "iso:country":"IT",
    "wof:name":"Oxon Italia S.P.A.",
    "wof:placetype":"locality"
},
  "geometry": {"coordinates":[8.87082,45.05879],"type":"Point"}
}