{
  "type": "Feature",
  "properties": {
    "gn:admin1_code":"13",
    "gn:admin2_code":"LE",
    "gn:admin3_code":"75079.0",
    "gn:asciiname":"Zona Canuta",
    "gn:country_code":"IT",
    "gn:dem":2,
    "gn:feature_class":"P",
    "gn:feature_code":"PPLL",
    "gn:name":"Zona Canuta",
    "gn:population":9,
    "gn:timezone":"Europe/Rome",
    "iso:country":"IT",
    "wof:name":"Zona Canuta",
    "wof:placetype":"locality",
    "wof:population":9
},
  "geometry": {"coordinates":[18.09615,40.51154],"type":"Point"}
}