{
  "type": "Feature",
  "properties": {
    "gn:admin1_code":"18",
    "gn:admin2_code":"PG",
    "gn:admin3_code":"54037.0",
    "gn:asciiname":"Missiano",
    "gn:country_code":"IT",
    "gn:dem":328,
    "gn:feature_class":"P",
    "gn:feature_code":"PPL",
    "gn:name":"Missiano",
    "gn:population":115,
    "gn:timezone":"Europe/Rome",
    "iso:country":"IT",
    "wof:name":"Missiano",
    "wof:placetype":"locality",
    "wof:population":115
},
  "geometry": {"coordinates":[12.10085,43.00513],"type":"Point"}
}