{
  "type": "Feature",
  "properties": {
    "gn:admin1_code":"5",
    "gn:admin2_code":"FC",
    "gn:admin3_code":"40016.0",
    "gn:asciiname":"Case Roncadello",
    "gn:country_code":"IT",
    "gn:dem":22,
    "gn:feature_class":"P",
    "gn:feature_code":"PPL",
    "gn:name":"Case Roncadello",
    "gn:population":51,
    "gn:timezone":"Europe/Rome",
    "iso:country":"IT",
    "wof:name":"Case Roncadello",
    "wof:placetype":"locality",
    "wof:population":51
},
  "geometry": {"coordinates":[12.37903,44.10617],"type":"Point"}
}