{
  "type": "Feature",
  "properties": {
    "gn:admin1_code":"13.0",
    "gn:admin2_code":"LE",
    "gn:admin3_code":"75070.0",
    "gn:asciiname":"Rossina",
    "gn:country_code":"IT",
    "gn:dem":0,
    "gn:feature_class":"P",
    "gn:feature_code":"PPLL",
    "gn:name":"Rossina",
    "gn:population":1,
    "gn:timezone":"Europe/Rome",
    "iso:country":"IT",
    "wof:name":"Rossina",
    "wof:placetype":"locality",
    "wof:population":1
},
  "geometry": {"coordinates":[18.01634,40.0978],"type":"Point"}
}