{
  "type": "Feature",
  "properties": {
    "gn:admin1_code":"5",
    "gn:admin2_code":"RN",
    "gn:admin3_code":"99014.0",
    "gn:asciiname":"La Fasolina",
    "gn:country_code":"IT",
    "gn:dem":25,
    "gn:feature_class":"P",
    "gn:feature_code":"PPL",
    "gn:name":"La Fasolina",
    "gn:population":21,
    "gn:timezone":"Europe/Rome",
    "iso:country":"IT",
    "wof:name":"La Fasolina",
    "wof:placetype":"locality",
    "wof:population":21
},
  "geometry": {"coordinates":[12.54957,44.02418],"type":"Point"}
}