{
  "type": "Feature",
  "properties": {
    "gn:admin1_code":"11",
    "gn:admin2_code":"CB",
    "gn:admin3_code":"70075.0",
    "gn:asciiname":"Altilia I",
    "gn:country_code":"IT",
    "gn:dem":554,
    "gn:feature_class":"P",
    "gn:feature_code":"PPL",
    "gn:name":"Altilia I",
    "gn:population":49,
    "gn:timezone":"Europe/Rome",
    "iso:country":"IT",
    "wof:name":"Altilia I",
    "wof:placetype":"locality",
    "wof:population":49
},
  "geometry": {"coordinates":[14.61732,41.43249],"type":"Point"}
}