{
  "type": "Feature",
  "properties": {
    "gn:admin1_code":"14.0",
    "gn:admin2_code":"SS",
    "gn:admin3_code":"90058.0",
    "gn:asciiname":"La Reale",
    "gn:country_code":"IT",
    "gn:dem":3,
    "gn:feature_class":"P",
    "gn:feature_code":"PPL",
    "gn:name":"La Reale",
    "gn:population":0,
    "gn:timezone":"Europe/Rome",
    "iso:country":"IT",
    "wof:name":"La Reale",
    "wof:placetype":"locality"
},
  "geometry": {"coordinates":[8.28455,41.06609],"type":"Point"}
}