{
  "type": "Feature",
  "properties": {
    "gn:admin1_code":"12",
    "gn:admin2_code":"AT",
    "gn:admin3_code":"5069.0",
    "gn:asciiname":"Stazione",
    "gn:country_code":"IT",
    "gn:dem":192,
    "gn:feature_class":"P",
    "gn:feature_code":"PPL",
    "gn:name":"Stazione",
    "gn:population":254,
    "gn:timezone":"Europe/Rome",
    "iso:country":"IT",
    "wof:name":"Stazione",
    "wof:placetype":"locality",
    "wof:population":254
},
  "geometry": {"coordinates":[8.26086,45.05891],"type":"Point"}
}