{
  "type": "Feature",
  "properties": {
    "gn:admin1_code":"19",
    "gn:admin2_code":"AO",
    "gn:admin3_code":"7036.0",
    "gn:asciiname":"Seingles",
    "gn:country_code":"IT",
    "gn:dem":955,
    "gn:feature_class":"P",
    "gn:feature_code":"PPLL",
    "gn:name":"Seingles",
    "gn:population":10,
    "gn:timezone":"Europe/Rome",
    "iso:country":"IT",
    "wof:name":"Seingles",
    "wof:placetype":"locality",
    "wof:population":10
},
  "geometry": {"coordinates":[7.85928,45.678],"type":"Point"}
}