{
  "type": "Feature",
  "properties": {
    "gn:admin1_code":"8.0",
    "gn:admin2_code":"SV",
    "gn:admin3_code":"9034.0",
    "gn:asciiname":"Verzi",
    "gn:country_code":"IT",
    "gn:dem":142,
    "gn:feature_class":"P",
    "gn:feature_code":"PPL",
    "gn:name":"Verzi",
    "gn:population":495,
    "gn:timezone":"Europe/Rome",
    "iso:country":"IT",
    "wof:name":"Verzi",
    "wof:placetype":"locality",
    "wof:population":495
},
  "geometry": {"coordinates":[8.23673,44.15415],"type":"Point"}
}