{
  "type": "Feature",
  "properties": {
    "gn:admin1_code":"5.0",
    "gn:admin2_code":"FC",
    "gn:admin3_code":"40044.0",
    "gn:asciiname":"Quarto",
    "gn:country_code":"IT",
    "gn:dem":343,
    "gn:elevation":"340.0",
    "gn:feature_class":"P",
    "gn:feature_code":"PPL",
    "gn:name":"Quarto",
    "gn:population":107,
    "gn:timezone":"Europe/Rome",
    "iso:country":"IT",
    "wof:name":"Quarto",
    "wof:placetype":"locality",
    "wof:population":107
},
  "geometry": {"coordinates":[12.08669,43.8917],"type":"Point"}
}