{
  "type": "Feature",
  "properties": {
    "gn:admin1_code":"5.0",
    "gn:admin2_code":"FC",
    "gn:admin3_code":"40044.0",
    "gn:asciiname":"Quarto",
    "gn:country_code":"IT",
    "gn:dem":343,
    "gn:elevation":"340.0",
    "gn:feature_class":"P",
    "gn:feature_code":"PPL",
    "gn:name":"Quarto",
    "gn:population":107,
    "gn:timezone":"Europe/Rome",
    "iso:country":"IT",
    "name:cat_x_preferred":[
        "Quart"
    ],
    "name:deu_x_preferred":[
        "Quarto"
    ],
    "name:fas_x_preferred":[
        "\u0631\u062d\u0644\u06cc"
    ],
    "name:fra_x_preferred":[
        "In-quarto"
    ],
    "name:ita_x_preferred":[
        "In quarto"
    ],
    "name:nld_x_preferred":[
        "Quarto"
    ],
    "name:nor_x_preferred":[
        "Kvartformat"
    ],
    "name:por_x_preferred":[
        "Quarto"
    ],
    "name:rus_x_preferred":[
        "\u0418\u043d-\u043a\u0432\u0430\u0440\u0442\u043e"
    ],
    "name:spa_x_preferred":[
        "Cuartilla"
    ],
    "name:swe_x_preferred":[
        "Kvarto"
    ],
    "name:tur_x_preferred":[
        "Quarto"
    ],
    "wof:name":"Quarto",
    "wof:placetype":"locality",
    "wof:population":107
},
  "geometry": {"coordinates":[12.08669,43.8917],"type":"Point"}
}