{
  "type": "Feature",
  "properties": {
    "gn:admin1_code":"20",
    "gn:admin2_code":"BL",
    "gn:admin3_code":"25070.0",
    "gn:asciiname":"Caorera",
    "gn:country_code":"IT",
    "gn:dem":232,
    "gn:feature_class":"P",
    "gn:feature_code":"PPL",
    "gn:name":"Caorera",
    "gn:population":96,
    "gn:timezone":"Europe/Rome",
    "iso:country":"IT",
    "wof:name":"Caorera",
    "wof:placetype":"locality",
    "wof:population":96
},
  "geometry": {"coordinates":[11.96406,45.97851],"type":"Point"}
}