{
  "type": "Feature",
  "properties": {
    "gn:admin1_code":"16",
    "gn:admin2_code":"LU",
    "gn:admin3_code":"46034.0",
    "gn:asciiname":"Buoso",
    "gn:country_code":"IT",
    "gn:dem":262,
    "gn:feature_class":"P",
    "gn:feature_code":"PPL",
    "gn:name":"Buoso",
    "gn:population":27,
    "gn:timezone":"Europe/Rome",
    "iso:country":"IT",
    "wof:name":"Buoso",
    "wof:placetype":"locality",
    "wof:population":27
},
  "geometry": {"coordinates":[10.64886,43.93746],"type":"Point"}
}