{
  "type": "Feature",
  "properties": {
    "gn:admin1_code":"2.0",
    "gn:admin2_code":"PZ",
    "gn:admin3_code":"76030.0",
    "gn:asciiname":"Manca di Basso",
    "gn:country_code":"IT",
    "gn:dem":533,
    "gn:feature_class":"P",
    "gn:feature_code":"PPL",
    "gn:name":"Manca di Basso",
    "gn:population":195,
    "gn:timezone":"Europe/Rome",
    "iso:country":"IT",
    "wof:name":"Manca di Basso",
    "wof:placetype":"locality",
    "wof:population":195
},
  "geometry": {"coordinates":[16.13022,40.0745],"type":"Point"}
}