{
  "type": "Feature",
  "properties": {
    "gn:admin1_code":"7.0",
    "gn:admin2_code":"RI",
    "gn:admin3_code":"57049.0",
    "gn:asciiname":"Porcareccia",
    "gn:country_code":"IT",
    "gn:dem":1243,
    "gn:feature_class":"P",
    "gn:feature_code":"PPL",
    "gn:name":"Porcareccia",
    "gn:population":0,
    "gn:timezone":"Europe/Rome",
    "iso:country":"IT",
    "wof:name":"Porcareccia",
    "wof:placetype":"locality"
},
  "geometry": {"coordinates":[13.23333,42.26667],"type":"Point"}
}