{
  "type": "Feature",
  "properties": {
    "gn:admin1_code":"9",
    "gn:admin2_code":"SO",
    "gn:admin3_code":"14037.0",
    "gn:asciiname":"Palipert",
    "gn:country_code":"IT",
    "gn:dem":1868,
    "gn:feature_class":"P",
    "gn:feature_code":"PPL",
    "gn:name":"Palipert",
    "gn:population":52,
    "gn:timezone":"Europe/Rome",
    "iso:country":"IT",
    "wof:name":"Palipert",
    "wof:placetype":"locality",
    "wof:population":52
},
  "geometry": {"coordinates":[10.11955,46.50615],"type":"Point"}
}