{
  "type": "Feature",
  "properties": {
    "gn:admin1_code":"13",
    "gn:admin2_code":"BA",
    "gn:admin3_code":"72017.0",
    "gn:asciiname":"Oronzo Persio",
    "gn:country_code":"IT",
    "gn:dem":291,
    "gn:feature_class":"P",
    "gn:feature_code":"PPL",
    "gn:name":"Oronzo Persio",
    "gn:population":94,
    "gn:timezone":"Europe/Rome",
    "iso:country":"IT",
    "wof:name":"Oronzo Persio",
    "wof:placetype":"locality",
    "wof:population":94
},
  "geometry": {"coordinates":[17.18763,40.89323],"type":"Point"}
}