{
  "type": "Feature",
  "properties": {
    "iso:country":"IT",
    "name:eng_x_preferred":[
        "Z.A.I. Borgo Roma"
    ],
    "name:ita_x_preferred":[
        "Z.A.I. Borgo Roma"
    ],
    "name:ita_x_variant":[
        "ZAI"
    ],
    "wof:name":"Z.A.I. Borgo Roma",
    "wof:placetype":"neighbourhood"
},
  "geometry": {"coordinates":[10.97702442549275,45.40328401138468],"type":"Point"}
}