{
  "type": "Feature",
  "properties": {
    "gn:admin1_code":"15.0",
    "gn:admin2_code":"AG",
    "gn:admin3_code":"84010.0",
    "gn:asciiname":"Favarotta",
    "gn:country_code":"IT",
    "gn:dem":245,
    "gn:feature_class":"P",
    "gn:feature_code":"PPL",
    "gn:name":"Favarotta",
    "gn:population":0,
    "gn:timezone":"Europe/Rome",
    "iso:country":"IT",
    "wof:name":"Favarotta",
    "wof:placetype":"locality"
},
  "geometry": {"coordinates":[13.91667,37.21667],"type":"Point"}
}