{
  "type": "Feature",
  "properties": {
    "gn:admin1_code":"20",
    "gn:admin2_code":"PD",
    "gn:admin3_code":"28035.0",
    "gn:asciiname":"San Gerardo",
    "gn:country_code":"IT",
    "gn:dem":3,
    "gn:feature_class":"P",
    "gn:feature_code":"PPL",
    "gn:name":"San Gerardo",
    "gn:population":30,
    "gn:timezone":"Europe/Rome",
    "iso:country":"IT",
    "name:ceb_x_preferred":[
        "San Gerardo"
    ],
    "name:ita_x_preferred":[
        "San Gerardo"
    ],
    "name:por_x_preferred":[
        "San Gerardo"
    ],
    "name:spa_x_preferred":[
        "San Gerardo"
    ],
    "name:zho_x_preferred":[
        "\u8056\u8d6b\u62c9\u723e\u591a"
    ],
    "wof:name":"San Gerardo",
    "wof:placetype":"locality",
    "wof:population":30
},
  "geometry": {"coordinates":[12.02375,45.19945],"type":"Point"}
}