{
  "type": "Feature",
  "properties": {
    "gn:admin1_code":"3.0",
    "gn:admin2_code":"RC",
    "gn:admin3_code":"80043.0",
    "gn:asciiname":"Mandorleto",
    "gn:country_code":"IT",
    "gn:dem":6,
    "gn:feature_class":"P",
    "gn:feature_code":"PPL",
    "gn:name":"Mandorleto",
    "gn:population":516,
    "gn:timezone":"Europe/Rome",
    "iso:country":"IT",
    "wof:name":"Mandorleto",
    "wof:placetype":"locality",
    "wof:population":516
},
  "geometry": {"coordinates":[16.24401,38.21378],"type":"Point"}
}