{
  "type": "Feature",
  "properties": {
    "gn:admin1_code":"5",
    "gn:admin2_code":"MO",
    "gn:admin3_code":"36025.0",
    "gn:asciiname":"Macognano",
    "gn:country_code":"IT",
    "gn:dem":508,
    "gn:feature_class":"P",
    "gn:feature_code":"PPL",
    "gn:name":"Macognano",
    "gn:population":26,
    "gn:timezone":"Europe/Rome",
    "iso:country":"IT",
    "wof:name":"Macognano",
    "wof:placetype":"locality",
    "wof:population":26
},
  "geometry": {"coordinates":[10.54442,44.3547],"type":"Point"}
}