{
  "type": "Feature",
  "properties": {
    "gn:admin1_code":"5",
    "gn:admin2_code":"MO",
    "gn:admin3_code":"36043.0",
    "gn:asciiname":"Vesale",
    "gn:country_code":"IT",
    "gn:dem":632,
    "gn:feature_class":"P",
    "gn:feature_code":"PPL",
    "gn:name":"Vesale",
    "gn:population":58,
    "gn:timezone":"Europe/Rome",
    "iso:country":"IT",
    "wof:name":"Vesale",
    "wof:placetype":"locality",
    "wof:population":58
},
  "geometry": {"coordinates":[10.79135,44.25637],"type":"Point"}
}