{
  "type": "Feature",
  "properties": {
    "gn:admin1_code":"15",
    "gn:admin2_code":"PA",
    "gn:admin3_code":"82072.0",
    "gn:asciiname":"Orioles",
    "gn:country_code":"IT",
    "gn:dem":120,
    "gn:feature_class":"P",
    "gn:feature_code":"PPL",
    "gn:name":"Orioles",
    "gn:population":284,
    "gn:timezone":"Europe/Rome",
    "iso:country":"IT",
    "wof:name":"Orioles",
    "wof:placetype":"locality",
    "wof:population":284
},
  "geometry": {"coordinates":[13.22572,38.1448],"type":"Point"}
}