{
  "type": "Feature",
  "properties": {
    "gn:admin1_code":"7",
    "gn:admin2_code":"FR",
    "gn:admin3_code":"60061.0",
    "gn:asciiname":"Fontana Cicchetta",
    "gn:country_code":"IT",
    "gn:dem":939,
    "gn:feature_class":"P",
    "gn:feature_code":"PPL",
    "gn:name":"Fontana Cicchetta",
    "gn:population":88,
    "gn:timezone":"Europe/Rome",
    "iso:country":"IT",
    "wof:name":"Fontana Cicchetta",
    "wof:placetype":"locality",
    "wof:population":88
},
  "geometry": {"coordinates":[13.96128,41.60967],"type":"Point"}
}