{
  "type": "Feature",
  "properties": {
    "gn:admin1_code":"5",
    "gn:admin2_code":"BO",
    "gn:admin3_code":"37030.0",
    "gn:asciiname":"Frullo",
    "gn:country_code":"IT",
    "gn:dem":37,
    "gn:feature_class":"P",
    "gn:feature_code":"PPL",
    "gn:name":"Frullo",
    "gn:population":14,
    "gn:timezone":"Europe/Rome",
    "iso:country":"IT",
    "wof:name":"Frullo",
    "wof:placetype":"locality",
    "wof:population":14
},
  "geometry": {"coordinates":[11.42934,44.5232],"type":"Point"}
}