{
  "type": "Feature",
  "properties": {
    "gn:admin1_code":"1.0",
    "gn:admin2_code":"TE",
    "gn:admin3_code":"67036.0",
    "gn:asciiname":"Acquaratola",
    "gn:country_code":"IT",
    "gn:dem":1049,
    "gn:elevation":"1036.0",
    "gn:feature_class":"P",
    "gn:feature_code":"PPL",
    "gn:name":"Acquaratola",
    "gn:population":33,
    "gn:timezone":"Europe/Rome",
    "iso:country":"IT",
    "wof:name":"Acquaratola",
    "wof:placetype":"locality",
    "wof:population":33
},
  "geometry": {"coordinates":[13.55962,42.70133],"type":"Point"}
}