{
  "type": "Feature",
  "properties": {
    "gn:admin1_code":"16.0",
    "gn:admin2_code":"FI",
    "gn:admin3_code":"48013.0",
    "gn:asciiname":"I filipponi",
    "gn:country_code":"IT",
    "gn:dem":206,
    "gn:feature_class":"P",
    "gn:feature_code":"PPL",
    "gn:name":"I filipponi",
    "gn:population":853,
    "gn:timezone":"Europe/Rome",
    "iso:country":"IT",
    "wof:name":"I filipponi",
    "wof:placetype":"locality",
    "wof:population":853
},
  "geometry": {"coordinates":[11.5588,43.8655],"type":"Point"}
}