{
  "type": "Feature",
  "properties": {
    "gn:admin1_code":"5",
    "gn:admin2_code":"MO",
    "gn:admin3_code":"36025.0",
    "gn:asciiname":"Caselle",
    "gn:country_code":"IT",
    "gn:dem":1097,
    "gn:feature_class":"P",
    "gn:feature_code":"PPL",
    "gn:name":"Caselle",
    "gn:population":17,
    "gn:timezone":"Europe/Rome",
    "iso:country":"IT",
    "name:ceb_x_preferred":[
        "Caselle"
    ],
    "name:deu_x_preferred":[
        "Caselle"
    ],
    "name:ita_x_preferred":[
        "Caselle"
    ],
    "name:pol_x_preferred":[
        "Caselle"
    ],
    "name:por_x_preferred":[
        "Caselle"
    ],
    "name:srp_x_preferred":[
        "Kazele"
    ],
    "name:swe_x_preferred":[
        "Caselle"
    ],
    "wof:name":"Caselle",
    "wof:placetype":"locality",
    "wof:population":17
},
  "geometry": {"coordinates":[10.58294,44.32712],"type":"Point"}
}