{
  "type": "Feature",
  "properties": {
    "gn:admin1_code":"5.0",
    "gn:admin2_code":"BO",
    "gn:admin3_code":"37032.0",
    "gn:asciiname":"Piratello",
    "gn:country_code":"IT",
    "gn:dem":78,
    "gn:elevation":"75.0",
    "gn:feature_class":"P",
    "gn:feature_code":"PPL",
    "gn:name":"Piratello",
    "gn:population":100,
    "gn:timezone":"Europe/Rome",
    "iso:country":"IT",
    "wof:name":"Piratello",
    "wof:placetype":"locality",
    "wof:population":100
},
  "geometry": {"coordinates":[11.67046,44.36998],"type":"Point"}
}