{
  "type": "Feature",
  "properties": {
    "gn:admin1_code":"1",
    "gn:admin2_code":"TE",
    "gn:admin3_code":"67018.0",
    "gn:asciiname":"Vico",
    "gn:country_code":"IT",
    "gn:dem":568,
    "gn:feature_class":"P",
    "gn:feature_code":"PPL",
    "gn:name":"Vico",
    "gn:population":43,
    "gn:timezone":"Europe/Rome",
    "iso:country":"IT",
    "wof:name":"Vico",
    "wof:placetype":"locality",
    "wof:population":43
},
  "geometry": {"coordinates":[13.64752,42.52493],"type":"Point"}
}