{
  "type": "Feature",
  "properties": {
    "gn:admin1_code":"16.0",
    "gn:admin2_code":"SI",
    "gn:admin3_code":"52004.0",
    "gn:asciiname":"Lucciana",
    "gn:country_code":"IT",
    "gn:dem":326,
    "gn:elevation":"323.0",
    "gn:feature_class":"P",
    "gn:feature_code":"PPL",
    "gn:name":"Lucciana",
    "gn:population":16,
    "gn:timezone":"Europe/Rome",
    "iso:country":"IT",
    "wof:name":"Lucciana",
    "wof:placetype":"locality",
    "wof:population":16
},
  "geometry": {"coordinates":[11.05366,43.37372],"type":"Point"}
}