{
  "type": "Feature",
  "properties": {
    "gn:admin1_code":"16.0",
    "gn:admin2_code":"SI",
    "gn:admin3_code":"52004.0",
    "gn:asciiname":"Lucciana",
    "gn:country_code":"IT",
    "gn:dem":326,
    "gn:elevation":"323.0",
    "gn:feature_class":"P",
    "gn:feature_code":"PPL",
    "gn:name":"Lucciana",
    "gn:population":16,
    "gn:timezone":"Europe/Rome",
    "iso:country":"IT",
    "name:cat_x_preferred":[
        "Lucciana"
    ],
    "name:ceb_x_preferred":[
        "Lucciana"
    ],
    "name:cos_x_preferred":[
        "Lucciana"
    ],
    "name:deu_x_preferred":[
        "Lucciana"
    ],
    "name:eus_x_preferred":[
        "Lucciana"
    ],
    "name:fra_x_preferred":[
        "Lucciana"
    ],
    "name:hun_x_preferred":[
        "Lucciana"
    ],
    "name:ita_x_preferred":[
        "Lucciana"
    ],
    "name:jpn_x_preferred":[
        "\u30ea\u30e5\u30af\u30b7\u30a2\u30ca"
    ],
    "name:kaz_x_preferred":[
        "\u041b\u0443\u0447\u0447\u0430\u043d\u0430"
    ],
    "name:lat_x_preferred":[
        "Lucciana"
    ],
    "name:lmo_x_preferred":[
        "Lucciana"
    ],
    "name:mlg_x_preferred":[
        "Lucciana"
    ],
    "name:msa_x_preferred":[
        "Lucciana"
    ],
    "name:nld_x_preferred":[
        "Lucciana"
    ],
    "name:oci_x_preferred":[
        "Lucciana"
    ],
    "name:pol_x_preferred":[
        "Lucciana"
    ],
    "name:por_x_preferred":[
        "Lucciana"
    ],
    "name:rus_x_preferred":[
        "\u041b\u0443\u0447\u0447\u0430\u043d\u0430"
    ],
    "name:slk_x_preferred":[
        "Lucciana"
    ],
    "name:slv_x_preferred":[
        "Lucciana"
    ],
    "name:spa_x_preferred":[
        "Lucciana"
    ],
    "name:swe_x_preferred":[
        "Lucciana"
    ],
    "name:ukr_x_preferred":[
        "\u041b\u0443\u0447\u0447\u0430\u043d\u0430"
    ],
    "name:vie_x_preferred":[
        "Lucciana"
    ],
    "name:vol_x_preferred":[
        "Lucciana"
    ],
    "name:war_x_preferred":[
        "Lucciana"
    ],
    "wof:name":"Lucciana",
    "wof:placetype":"locality",
    "wof:population":16
},
  "geometry": {"coordinates":[11.05366,43.37372],"type":"Point"}
}