{
  "type": "Feature",
  "properties": {
    "gn:admin1_code":"4",
    "gn:admin2_code":"SA",
    "gn:admin3_code":"65029.0",
    "gn:asciiname":"Tempe",
    "gn:country_code":"IT",
    "gn:dem":485,
    "gn:feature_class":"P",
    "gn:feature_code":"PPL",
    "gn:name":"Tempe",
    "gn:population":200,
    "gn:timezone":"Europe/Rome",
    "iso:country":"IT",
    "name:cat_x_preferred":[
        "Tempe"
    ],
    "name:ceb_x_preferred":[
        "Tempe"
    ],
    "name:dan_x_preferred":[
        "Tempe"
    ],
    "name:deu_x_preferred":[
        "Tempe"
    ],
    "name:epo_x_preferred":[
        "Tempe"
    ],
    "name:fin_x_preferred":[
        "Tempe"
    ],
    "name:fra_x_preferred":[
        "Tempe"
    ],
    "name:heb_x_preferred":[
        "\u05d8\u05de\u05e4\u05d4"
    ],
    "name:ind_x_preferred":[
        "Tempe"
    ],
    "name:ita_x_preferred":[
        "Tempe"
    ],
    "name:jav_x_preferred":[
        "Tempe"
    ],
    "name:lat_x_preferred":[
        "Tempe"
    ],
    "name:nld_x_preferred":[
        "Tempe"
    ],
    "name:nor_x_preferred":[
        "Tempe"
    ],
    "name:pol_x_preferred":[
        "Tempe"
    ],
    "name:por_x_preferred":[
        "Tempe"
    ],
    "name:ron_x_preferred":[
        "Tempe"
    ],
    "name:rus_x_preferred":[
        "\u0422\u0435\u043c\u043f\u0435"
    ],
    "name:spa_x_preferred":[
        "Tempe"
    ],
    "name:swe_x_preferred":[
        "Tempe"
    ],
    "name:ukr_x_preferred":[
        "\u0422\u0435\u043c\u043f\u0456"
    ],
    "wof:name":"Tempe",
    "wof:placetype":"locality",
    "wof:population":200
},
  "geometry": {"coordinates":[15.53982,40.18082],"type":"Point"}
}