{
  "type": "Feature",
  "properties": {
    "gn:admin1_code":"4.0",
    "gn:admin2_code":"SA",
    "gn:admin3_code":"65050.0",
    "gn:asciiname":"Eboli Mare",
    "gn:country_code":"IT",
    "gn:dem":-1,
    "gn:feature_class":"P",
    "gn:feature_code":"PPL",
    "gn:name":"Eboli Mare",
    "gn:population":0,
    "gn:timezone":"Europe/Rome",
    "iso:country":"IT",
    "wof:name":"Eboli Mare",
    "wof:placetype":"locality"
},
  "geometry": {"coordinates":[14.94827,40.48665],"type":"Point"}
}