{
  "type": "Feature",
  "properties": {
    "gn:admin1_code":"15.0",
    "gn:admin2_code":"ME",
    "gn:admin3_code":"83041.0",
    "gn:asciiname":"Vulcano Porto",
    "gn:country_code":"IT",
    "gn:dem":9,
    "gn:elevation":"11.0",
    "gn:feature_class":"P",
    "gn:feature_code":"PPL",
    "gn:name":"Vulcano Porto",
    "gn:population":425,
    "gn:timezone":"Europe/Rome",
    "iso:country":"IT",
    "wof:name":"Vulcano Porto",
    "wof:placetype":"locality",
    "wof:population":425
},
  "geometry": {"coordinates":[14.95707,38.41362],"type":"Point"}
}