{
  "type": "Feature",
  "properties": {
    "gn:admin1_code":"20",
    "gn:admin2_code":"VE",
    "gn:admin3_code":"27034.0",
    "gn:asciiname":"Boscatto",
    "gn:country_code":"IT",
    "gn:dem":8,
    "gn:feature_class":"P",
    "gn:feature_code":"PPL",
    "gn:name":"Boscatto",
    "gn:population":37,
    "gn:timezone":"Europe/Rome",
    "iso:country":"IT",
    "wof:name":"Boscatto",
    "wof:placetype":"locality",
    "wof:population":37
},
  "geometry": {"coordinates":[12.96905,45.81096],"type":"Point"}
}