{
  "type": "Feature",
  "properties": {
    "gn:admin1_code":"5.0",
    "gn:admin2_code":"BO",
    "gn:admin3_code":"37012.0",
    "gn:asciiname":"Carseggio",
    "gn:country_code":"IT",
    "gn:dem":196,
    "gn:feature_class":"P",
    "gn:feature_code":"PPL",
    "gn:name":"Carseggio",
    "gn:population":0,
    "gn:timezone":"Europe/Rome",
    "iso:country":"IT",
    "wof:name":"Carseggio",
    "wof:placetype":"locality"
},
  "geometry": {"coordinates":[11.51667,44.23333],"type":"Point"}
}