{
  "type": "Feature",
  "properties": {
    "gn:admin1_code":"12",
    "gn:admin2_code":"TO",
    "gn:admin3_code":"1292.0",
    "gn:asciiname":"Madonnina I",
    "gn:country_code":"IT",
    "gn:dem":280,
    "gn:feature_class":"P",
    "gn:feature_code":"PPL",
    "gn:name":"Madonnina I",
    "gn:population":20,
    "gn:timezone":"Europe/Rome",
    "iso:country":"IT",
    "wof:name":"Madonnina I",
    "wof:placetype":"locality",
    "wof:population":20
},
  "geometry": {"coordinates":[7.62119,45.15558],"type":"Point"}
}