{
  "type": "Feature",
  "properties": {
    "gn:admin1_code":"20.0",
    "gn:admin2_code":"VI",
    "gn:admin3_code":"24113.0",
    "gn:asciiname":"Pra'",
    "gn:country_code":"IT",
    "gn:dem":316,
    "gn:feature_class":"P",
    "gn:feature_code":"PPL",
    "gn:name":"Pra'",
    "gn:population":76,
    "gn:timezone":"Europe/Rome",
    "iso:country":"IT",
    "wof:name":"Pra'",
    "wof:placetype":"locality",
    "wof:population":76
},
  "geometry": {"coordinates":[11.27276,45.73177],"type":"Point"}
}