{
  "type": "Feature",
  "properties": {
    "gn:admin1_code":"1",
    "gn:admin2_code":"CH",
    "gn:admin3_code":"69099.0",
    "gn:asciiname":"Torre Sinello",
    "gn:country_code":"IT",
    "gn:dem":51,
    "gn:feature_class":"P",
    "gn:feature_code":"PPL",
    "gn:name":"Torre Sinello",
    "gn:population":219,
    "gn:timezone":"Europe/Rome",
    "iso:country":"IT",
    "wof:name":"Torre Sinello",
    "wof:placetype":"locality",
    "wof:population":219
},
  "geometry": {"coordinates":[14.66216,42.17759],"type":"Point"}
}