{
  "type": "Feature",
  "properties": {
    "gn:admin1_code":"20.0",
    "gn:admin2_code":"VI",
    "gn:admin3_code":"24084.0",
    "gn:asciiname":"Tunche",
    "gn:country_code":"IT",
    "gn:dem":1054,
    "gn:feature_class":"P",
    "gn:feature_code":"PPLL",
    "gn:name":"Tunche",
    "gn:population":4,
    "gn:timezone":"Europe/Rome",
    "iso:country":"IT",
    "wof:name":"Tunche",
    "wof:placetype":"locality",
    "wof:population":4
},
  "geometry": {"coordinates":[11.22327,45.68158],"type":"Point"}
}