{
  "type": "Feature",
  "properties": {
    "gn:admin1_code":"14.0",
    "gn:admin2_code":"SS",
    "gn:admin3_code":"90055.0",
    "gn:asciiname":"Zona Artigianale",
    "gn:country_code":"IT",
    "gn:dem":662,
    "gn:feature_class":"P",
    "gn:feature_code":"PPLL",
    "gn:name":"Zona Artigianale",
    "gn:population":0,
    "gn:timezone":"Europe/Rome",
    "iso:country":"IT",
    "wof:name":"Zona Artigianale",
    "wof:placetype":"locality"
},
  "geometry": {"coordinates":[9.08849,40.56227],"type":"Point"}
}