{
  "type": "Feature",
  "properties": {
    "gn:admin1_code":"12",
    "gn:admin2_code":"BI",
    "gn:admin3_code":"96033.0",
    "gn:asciiname":"Fangazio",
    "gn:country_code":"IT",
    "gn:dem":414,
    "gn:feature_class":"P",
    "gn:feature_code":"PPL",
    "gn:name":"Fangazio",
    "gn:population":43,
    "gn:timezone":"Europe/Rome",
    "iso:country":"IT",
    "wof:name":"Fangazio",
    "wof:placetype":"locality",
    "wof:population":43
},
  "geometry": {"coordinates":[8.1945,45.62736],"type":"Point"}
}