{
  "type": "Feature",
  "properties": {
    "gn:admin1_code":"3",
    "gn:admin2_code":"CS",
    "gn:admin3_code":"78014.0",
    "gn:asciiname":"Chiusi",
    "gn:country_code":"IT",
    "gn:dem":609,
    "gn:feature_class":"P",
    "gn:feature_code":"PPL",
    "gn:name":"Chiusi",
    "gn:population":68,
    "gn:timezone":"Europe/Rome",
    "iso:country":"IT",
    "wof:name":"Chiusi",
    "wof:placetype":"locality",
    "wof:population":68
},
  "geometry": {"coordinates":[16.28889,39.1714],"type":"Point"}
}