{
  "type": "Feature",
  "properties": {
    "gn:admin1_code":"3",
    "gn:admin2_code":"CS",
    "gn:admin3_code":"78014.0",
    "gn:asciiname":"Chiusi",
    "gn:country_code":"IT",
    "gn:dem":609,
    "gn:feature_class":"P",
    "gn:feature_code":"PPL",
    "gn:name":"Chiusi",
    "gn:population":68,
    "gn:timezone":"Europe/Rome",
    "iso:country":"IT",
    "name:azb_x_preferred":[
        "\u06a9\u06cc\u0648\u0632\u06cc"
    ],
    "name:bcl_x_preferred":[
        "Chiusi"
    ],
    "name:bel_x_preferred":[
        "\u041a\u2019\u044e\u0437\u0456"
    ],
    "name:bul_x_preferred":[
        "\u041a\u0438\u0443\u0437\u0438"
    ],
    "name:cat_x_preferred":[
        "Chiusi"
    ],
    "name:ceb_x_preferred":[
        "Chiusi"
    ],
    "name:cos_x_preferred":[
        "Chiusi"
    ],
    "name:deu_x_preferred":[
        "Chiusi"
    ],
    "name:ell_x_preferred":[
        "\u039a\u03b9\u03bf\u03cd\u03b6\u03b9"
    ],
    "name:epo_x_preferred":[
        "Chiusi"
    ],
    "name:eus_x_preferred":[
        "Chiusi"
    ],
    "name:fas_x_preferred":[
        "\u06a9\u06cc\u0648\u0632\u06cc"
    ],
    "name:fra_x_preferred":[
        "Chiusi"
    ],
    "name:hun_x_preferred":[
        "Chiusi"
    ],
    "name:hye_x_preferred":[
        "\u053f\u056b\u0578\u0582\u0566\u056b"
    ],
    "name:ita_x_preferred":[
        "Chiusi"
    ],
    "name:jpn_x_preferred":[
        "\u30ad\u30a6\u30fc\u30b8"
    ],
    "name:kaz_x_preferred":[
        "\u041a\u044c\u044e\u0437\u0438"
    ],
    "name:kor_x_preferred":[
        "\ud0a4\uc6b0\uc2dc"
    ],
    "name:lat_x_preferred":[
        "Clusium"
    ],
    "name:lmo_x_preferred":[
        "Chiusi"
    ],
    "name:msa_x_preferred":[
        "Chiusi"
    ],
    "name:nap_x_preferred":[
        "Chiusi"
    ],
    "name:nld_x_preferred":[
        "Chiusi"
    ],
    "name:pms_x_preferred":[
        "Chiusi"
    ],
    "name:pol_x_preferred":[
        "Chiusi"
    ],
    "name:por_x_preferred":[
        "Chiusi"
    ],
    "name:ron_x_preferred":[
        "Chiusi"
    ],
    "name:rus_x_preferred":[
        "\u041a\u044c\u044e\u0441\u0438"
    ],
    "name:scn_x_preferred":[
        "Chiusi"
    ],
    "name:slv_x_preferred":[
        "Chiusi"
    ],
    "name:spa_x_preferred":[
        "Chiusi"
    ],
    "name:srp_x_preferred":[
        "\u041a\u0458\u0443\u0437\u0438"
    ],
    "name:swe_x_preferred":[
        "Chiusi"
    ],
    "name:ukr_x_preferred":[
        "\u041a'\u044e\u0437\u0456"
    ],
    "name:uzb_x_preferred":[
        "Chiusi"
    ],
    "name:vol_x_preferred":[
        "Chiusi"
    ],
    "name:war_x_preferred":[
        "Chiusi"
    ],
    "wof:name":"Chiusi",
    "wof:placetype":"locality",
    "wof:population":68
},
  "geometry": {"coordinates":[16.28889,39.1714],"type":"Point"}
}