{
  "type": "Feature",
  "properties": {
    "gn:admin1_code":"5",
    "gn:admin2_code":"FE",
    "gn:admin3_code":"38023.0",
    "gn:asciiname":"Containa",
    "gn:country_code":"IT",
    "gn:dem":2,
    "gn:feature_class":"P",
    "gn:feature_code":"PPL",
    "gn:name":"Containa",
    "gn:population":40,
    "gn:timezone":"Europe/Rome",
    "iso:country":"IT",
    "wof:name":"Containa",
    "wof:placetype":"locality",
    "wof:population":40
},
  "geometry": {"coordinates":[11.71408,44.73772],"type":"Point"}
}