{
  "type": "Feature",
  "properties": {
    "gn:admin1_code":"5",
    "gn:admin2_code":"PR",
    "gn:admin3_code":"34020.0",
    "gn:asciiname":"Case Faggi",
    "gn:country_code":"IT",
    "gn:dem":398,
    "gn:feature_class":"P",
    "gn:feature_code":"PPL",
    "gn:name":"Case Faggi",
    "gn:population":12,
    "gn:timezone":"Europe/Rome",
    "iso:country":"IT",
    "wof:name":"Case Faggi",
    "wof:placetype":"locality",
    "wof:population":12
},
  "geometry": {"coordinates":[9.99421,44.74915],"type":"Point"}
}