{
  "type": "Feature",
  "properties": {
    "gn:admin1_code":"10",
    "gn:admin2_code":"MC",
    "gn:admin3_code":"43007.0",
    "gn:asciiname":"Strada",
    "gn:country_code":"IT",
    "gn:dem":488,
    "gn:feature_class":"P",
    "gn:feature_code":"PPL",
    "gn:name":"Strada",
    "gn:population":42,
    "gn:timezone":"Europe/Rome",
    "iso:country":"IT",
    "wof:name":"Strada",
    "wof:placetype":"locality",
    "wof:population":42
},
  "geometry": {"coordinates":[13.05162,43.11608],"type":"Point"}
}