{
  "type": "Feature",
  "properties": {
    "gn:country":"IT",
    "gn:fcode":"PPLX",
    "gn:population":3367,
    "iso:country":"IT",
    "name:rus_x_preferred":[
        "\u041f\u0438\u043d\u043e\u043a\u043a\u0438\u043e-\u0434\u0438-\u0410\u043d\u043a\u043e\u043d\u0430"
    ],
    "name:und_x_variant":[
        "Pinocchio"
    ],
    "qs_pg:aaroncc":"IT",
    "qs_pg:gn_country":"IT",
    "qs_pg:gn_fcode":"PPLX",
    "qs_pg:gn_pop":3367,
    "qs_pg:name":"Pinocchio di Ancona",
    "qs_pg:name_adm0":"Italia",
    "qs_pg:name_adm1":"Marche",
    "qs_pg:photos_9r":0,
    "qs_pg:photos_sr":0,
    "qs_pg:pop_sr":9,
    "qs_pg:qs_pg_placetype":"locality_gp_neighbourhood_gn",
    "qs_pg:qs_pg_placetype_gp":"Town",
    "qs_pg:woe_adm0":23424853,
    "woe:adm0_id":23424853,
    "woe:name_adm0":"Italia",
    "woe:name_adm1":"Marche",
    "woe:placetype":"Town",
    "wof:name":"Pinocchio di Ancona",
    "wof:placetype":"locality",
    "wof:population":3367
},
  "geometry": {"coordinates":[13.49413,43.58986],"type":"Point"}
}