{
  "type": "Feature",
  "properties": {
    "gn:admin1_code":"15",
    "gn:admin2_code":"SR",
    "gn:admin3_code":"89015.0",
    "gn:asciiname":"Porticaletto",
    "gn:country_code":"IT",
    "gn:dem":624,
    "gn:feature_class":"P",
    "gn:feature_code":"PPL",
    "gn:name":"Porticaletto",
    "gn:population":85,
    "gn:timezone":"Europe/Rome",
    "iso:country":"IT",
    "wof:name":"Porticaletto",
    "wof:placetype":"locality",
    "wof:population":85
},
  "geometry": {"coordinates":[14.9208,37.05113],"type":"Point"}
}