{
  "type": "Feature",
  "properties": {
    "gn:admin1_code":"10.0",
    "gn:admin2_code":"MC",
    "gn:admin3_code":"43054.0",
    "gn:asciiname":"Chiesanuova",
    "gn:country_code":"IT",
    "gn:dem":197,
    "gn:feature_class":"P",
    "gn:feature_code":"PPL",
    "gn:name":"Chiesanuova",
    "gn:population":811,
    "gn:timezone":"Europe/Rome",
    "iso:country":"IT",
    "wof:name":"Chiesanuova",
    "wof:placetype":"locality",
    "wof:population":811
},
  "geometry": {"coordinates":[13.32662,43.33827],"type":"Point"}
}