{
  "type": "Feature",
  "properties": {
    "gn:admin1_code":"5",
    "gn:admin2_code":"BO",
    "gn:admin3_code":"37055.0",
    "gn:asciiname":"La Contea",
    "gn:country_code":"IT",
    "gn:dem":14,
    "gn:feature_class":"P",
    "gn:feature_code":"PPL",
    "gn:name":"La Contea",
    "gn:population":19,
    "gn:timezone":"Europe/Rome",
    "iso:country":"IT",
    "wof:name":"La Contea",
    "wof:placetype":"locality",
    "wof:population":19
},
  "geometry": {"coordinates":[11.41315,44.67998],"type":"Point"}
}