{
  "type": "Feature",
  "properties": {
    "gn:admin1_code":"4.0",
    "gn:admin2_code":"CE",
    "gn:admin3_code":"61049.0",
    "gn:asciiname":"Zona Industriale Marcianise Sud",
    "gn:country_code":"IT",
    "gn:dem":23,
    "gn:feature_class":"P",
    "gn:feature_code":"PPL",
    "gn:name":"Zona Industriale Marcianise Sud",
    "gn:population":25,
    "gn:timezone":"Europe/Rome",
    "iso:country":"IT",
    "wof:name":"Zona Industriale Marcianise Sud",
    "wof:placetype":"locality",
    "wof:population":25
},
  "geometry": {"coordinates":[14.30572,41.00966],"type":"Point"}
}