{
  "type": "Feature",
  "properties": {
    "gn:admin1_code":"4.0",
    "gn:admin2_code":"CE",
    "gn:admin3_code":"61009.0",
    "gn:asciiname":"San Giovanni e Paolo",
    "gn:country_code":"IT",
    "gn:dem":263,
    "gn:elevation":"255.0",
    "gn:feature_class":"P",
    "gn:feature_code":"PPL",
    "gn:name":"San Giovanni e Paolo",
    "gn:population":510,
    "gn:timezone":"Europe/Rome",
    "iso:country":"IT",
    "wof:name":"San Giovanni e Paolo",
    "wof:placetype":"locality",
    "wof:population":510
},
  "geometry": {"coordinates":[14.38784,41.17584],"type":"Point"}
}