{
  "type": "Feature",
  "properties": {
    "gn:admin1_code":"20.0",
    "gn:admin2_code":"VI",
    "gn:admin3_code":"24029.0",
    "gn:asciiname":"Vandini",
    "gn:country_code":"IT",
    "gn:dem":410,
    "gn:feature_class":"P",
    "gn:feature_code":"PPL",
    "gn:name":"Vandini",
    "gn:population":18,
    "gn:timezone":"Europe/Rome",
    "iso:country":"IT",
    "wof:name":"Vandini",
    "wof:placetype":"locality",
    "wof:population":18
},
  "geometry": {"coordinates":[11.27494,45.52934000000001],"type":"Point"}
}