{
  "type": "Feature",
  "properties": {
    "gn:admin1_code":"12",
    "gn:admin2_code":"CN",
    "gn:admin3_code":"4126.0",
    "gn:asciiname":"Bertolini Soprani",
    "gn:country_code":"IT",
    "gn:dem":682,
    "gn:feature_class":"P",
    "gn:feature_code":"PPL",
    "gn:name":"Bertolini Soprani",
    "gn:population":23,
    "gn:timezone":"Europe/Rome",
    "iso:country":"IT",
    "wof:name":"Bertolini Soprani",
    "wof:placetype":"locality",
    "wof:population":23
},
  "geometry": {"coordinates":[7.81557,44.3224],"type":"Point"}
}