{
  "type": "Feature",
  "properties": {
    "gn:admin1_code":"7.0",
    "gn:admin2_code":"RM",
    "gn:admin3_code":"58047.0",
    "gn:asciiname":"Laghetto",
    "gn:country_code":"IT",
    "gn:dem":94,
    "gn:feature_class":"P",
    "gn:feature_code":"PPL",
    "gn:name":"Laghetto",
    "gn:population":4038,
    "gn:timezone":"Europe/Rome",
    "iso:country":"IT",
    "wof:name":"Laghetto",
    "wof:placetype":"locality",
    "wof:population":4038
},
  "geometry": {"coordinates":[12.65609,41.96734],"type":"Point"}
}