{
  "type": "Feature",
  "properties": {
    "gn:admin1_code":"2",
    "gn:admin2_code":"PZ",
    "gn:admin3_code":"76045.0",
    "gn:asciiname":"Fontana Capano",
    "gn:country_code":"IT",
    "gn:dem":609,
    "gn:feature_class":"P",
    "gn:feature_code":"PPL",
    "gn:name":"Fontana Capano",
    "gn:population":99,
    "gn:timezone":"Europe/Rome",
    "iso:country":"IT",
    "wof:name":"Fontana Capano",
    "wof:placetype":"locality",
    "wof:population":99
},
  "geometry": {"coordinates":[15.77199,40.37959],"type":"Point"}
}