{
  "type": "Feature",
  "properties": {
    "gn:admin1_code":"13.0",
    "gn:admin2_code":"LE",
    "gn:admin3_code":"75057.0",
    "gn:asciiname":"Conca Specchiulla",
    "gn:country_code":"IT",
    "gn:dem":19,
    "gn:feature_class":"P",
    "gn:feature_code":"PPL",
    "gn:name":"Conca Specchiulla",
    "gn:population":11,
    "gn:timezone":"Europe/Rome",
    "iso:country":"IT",
    "wof:name":"Conca Specchiulla",
    "wof:placetype":"locality",
    "wof:population":11
},
  "geometry": {"coordinates":[18.4451,40.24475],"type":"Point"}
}