{
  "type": "Feature",
  "properties": {
    "gn:gn_country":"IT",
    "gn:gn_fcode":"PPL",
    "gn:gn_pop":0,
    "iso:country":"IT",
    "name:cat_x_preferred":[
        "Costa Rei"
    ],
    "name:dut_x_preferred":[
        "Costa Rei"
    ],
    "name:eng_x_preferred":[
        "Costa Rei"
    ],
    "name:fre_x_preferred":[
        "Costa Rei"
    ],
    "name:ger_x_preferred":[
        "Costa Rei"
    ],
    "name:glg_x_preferred":[
        "Costa Rei"
    ],
    "name:heb_x_preferred":[
        "\u05e7\u05d5\u05e1\u05d8\u05d4 \u05e8\u05d9\u05d9"
    ],
    "name:hun_x_preferred":[
        "Costa Rei"
    ],
    "name:ita_x_preferred":[
        "Costa Rei"
    ],
    "name:spa_x_preferred":[
        "Costa Rei"
    ],
    "qs_pg:aaroncc":"IT",
    "qs_pg:gn_country":"IT",
    "qs_pg:gn_fcode":"PPL",
    "qs_pg:gn_pop":0,
    "qs_pg:name":"Costa Rei",
    "qs_pg:name_adm0":"Italia",
    "qs_pg:name_adm1":"Sardegna",
    "qs_pg:photos":2117,
    "qs_pg:photos_1k":429,
    "qs_pg:photos_9k":9,
    "qs_pg:photos_9r":9,
    "qs_pg:photos_all":2117,
    "qs_pg:photos_sr":16,
    "qs_pg:pop_sr":0,
    "qs_pg:qs_pg_placetype":"locality",
    "qs_pg:qs_pg_placetype_gp":"Town",
    "qs_pg:woe_adm0":23424853,
    "woe:adm0_id":23424853,
    "woe:name_adm0":"Italia",
    "woe:name_adm1":"Sardegna",
    "woe:placetype":"Town",
    "wof:name":"Costa Rei",
    "wof:placetype":"locality"
},
  "geometry": {"coordinates":[9.59674,39.35618],"type":"Point"}
}