{
  "type": "Feature",
  "properties": {
    "gn:admin1_code":"20",
    "gn:admin2_code":"BL",
    "gn:admin3_code":"25034.0",
    "gn:asciiname":"Signa",
    "gn:country_code":"IT",
    "gn:dem":636,
    "gn:feature_class":"P",
    "gn:feature_code":"PPL",
    "gn:name":"Signa",
    "gn:population":13,
    "gn:timezone":"Europe/Rome",
    "iso:country":"IT",
    "name:azb_x_preferred":[
        "\u0633\u06cc\u0646\u06cc\u0627"
    ],
    "name:bcl_x_preferred":[
        "Signa"
    ],
    "name:bel_x_preferred":[
        "\u0421\u0456\u043d\u2019\u044f"
    ],
    "name:bul_x_preferred":[
        "\u0421\u0438\u043d\u044f"
    ],
    "name:cat_x_preferred":[
        "Signa"
    ],
    "name:ceb_x_preferred":[
        "Signa"
    ],
    "name:cos_x_preferred":[
        "Signa"
    ],
    "name:deu_x_preferred":[
        "Signa"
    ],
    "name:epo_x_preferred":[
        "Signa"
    ],
    "name:eus_x_preferred":[
        "Signa"
    ],
    "name:fas_x_preferred":[
        "\u0633\u06cc\u0646\u06cc\u0627"
    ],
    "name:fra_x_preferred":[
        "Signa"
    ],
    "name:hun_x_preferred":[
        "Signa"
    ],
    "name:hye_x_preferred":[
        "\u054d\u056b\u0576\u0575\u0561"
    ],
    "name:ita_x_preferred":[
        "Signa"
    ],
    "name:jpn_x_preferred":[
        "\u30b7\u30fc\u30cb\u30e3"
    ],
    "name:kaz_x_preferred":[
        "\u0421\u0438\u043d\u044c\u044f"
    ],
    "name:kor_x_preferred":[
        "\uc2dc\ub0d0"
    ],
    "name:lat_x_preferred":[
        "Exinea"
    ],
    "name:lmo_x_preferred":[
        "Signa"
    ],
    "name:msa_x_preferred":[
        "Signa"
    ],
    "name:nap_x_preferred":[
        "Signa"
    ],
    "name:nld_x_preferred":[
        "Signa"
    ],
    "name:pms_x_preferred":[
        "Signa"
    ],
    "name:pol_x_preferred":[
        "Signa"
    ],
    "name:por_x_preferred":[
        "Signa"
    ],
    "name:ron_x_preferred":[
        "Signa"
    ],
    "name:rus_x_preferred":[
        "\u0421\u0438\u043d\u044c\u044f"
    ],
    "name:spa_x_preferred":[
        "Signa"
    ],
    "name:srp_x_preferred":[
        "\u0421\u0438\u045a\u0430"
    ],
    "name:ukr_x_preferred":[
        "\u0421\u0456\u043d\u044c\u044f"
    ],
    "name:uzb_x_preferred":[
        "Signa"
    ],
    "name:vec_x_preferred":[
        "Signa"
    ],
    "name:vie_x_preferred":[
        "Signa"
    ],
    "name:vol_x_preferred":[
        "Signa"
    ],
    "name:war_x_preferred":[
        "Signa"
    ],
    "name:zho_x_preferred":[
        "\u897f\u5c3c\u4e9a"
    ],
    "wof:name":"Signa",
    "wof:placetype":"locality",
    "wof:population":13
},
  "geometry": {"coordinates":[12.15648,46.02372],"type":"Point"}
}