{
  "type": "Feature",
  "properties": {
    "gn:admin1_code":"20",
    "gn:admin2_code":"BL",
    "gn:admin3_code":"25034.0",
    "gn:asciiname":"Signa",
    "gn:country_code":"IT",
    "gn:dem":636,
    "gn:feature_class":"P",
    "gn:feature_code":"PPL",
    "gn:name":"Signa",
    "gn:population":13,
    "gn:timezone":"Europe/Rome",
    "iso:country":"IT",
    "wof:name":"Signa",
    "wof:placetype":"locality",
    "wof:population":13
},
  "geometry": {"coordinates":[12.15648,46.02372],"type":"Point"}
}