{
  "type": "Feature",
  "properties": {
    "gn:admin1_code":"12.0",
    "gn:admin2_code":"TO",
    "gn:admin3_code":"1222.0",
    "gn:asciiname":"Rostagno-Costagrande",
    "gn:country_code":"IT",
    "gn:dem":429,
    "gn:feature_class":"P",
    "gn:feature_code":"PPL",
    "gn:name":"Rostagno-Costagrande",
    "gn:population":123,
    "gn:timezone":"Europe/Rome",
    "iso:country":"IT",
    "wof:name":"Rostagno-Costagrande",
    "wof:placetype":"locality",
    "wof:population":123
},
  "geometry": {"coordinates":[7.32413,44.92014],"type":"Point"}
}