{
  "type": "Feature",
  "properties": {
    "gn:admin1_code":"5.0",
    "gn:admin2_code":"FE",
    "gn:admin3_code":"38012.0",
    "gn:asciiname":"Masi San Giacomo",
    "gn:country_code":"IT",
    "gn:dem":2,
    "gn:elevation":"3.0",
    "gn:feature_class":"P",
    "gn:feature_code":"PPL",
    "gn:name":"Masi San Giacomo",
    "gn:population":459,
    "gn:timezone":"Europe/Rome",
    "iso:country":"IT",
    "wof:name":"Masi San Giacomo",
    "wof:placetype":"locality",
    "wof:population":459
},
  "geometry": {"coordinates":[11.79384,44.77483],"type":"Point"}
}