{
  "type": "Feature",
  "properties": {
    "gn:admin1_code":"18",
    "gn:admin2_code":"TR",
    "gn:admin3_code":"55008.0",
    "gn:asciiname":"San Giacomo",
    "gn:country_code":"IT",
    "gn:dem":275,
    "gn:feature_class":"P",
    "gn:feature_code":"PPL",
    "gn:name":"San Giacomo",
    "gn:population":41,
    "gn:timezone":"Europe/Rome",
    "iso:country":"IT",
    "wof:name":"San Giacomo",
    "wof:placetype":"locality",
    "wof:population":41
},
  "geometry": {"coordinates":[12.56174,42.38794],"type":"Point"}
}