{
  "type": "Feature",
  "properties": {
    "gn:admin1_code":"8",
    "gn:admin2_code":"SV",
    "gn:admin3_code":"9015.0",
    "gn:asciiname":"Sant'Anna",
    "gn:country_code":"IT",
    "gn:dem":427,
    "gn:feature_class":"P",
    "gn:feature_code":"PPLL",
    "gn:name":"Sant'Anna",
    "gn:population":7,
    "gn:timezone":"Europe/Rome",
    "iso:country":"IT",
    "name:bre_x_preferred":[
        "Sant'Anna"
    ],
    "name:ceb_x_preferred":[
        "Sant'Anna"
    ],
    "name:deu_x_preferred":[
        "Sant\u2019Anna"
    ],
    "name:epo_x_preferred":[
        "Sant'Anna"
    ],
    "name:ita_x_preferred":[
        "Sant'Anna"
    ],
    "name:nld_x_preferred":[
        "Sant'Anna"
    ],
    "name:por_x_preferred":[
        "Sant'Anna"
    ],
    "name:srp_x_preferred":[
        "Sant'Ana"
    ],
    "name:swe_x_preferred":[
        "Sant'Anna"
    ],
    "wof:name":"Sant'Anna",
    "wof:placetype":"locality",
    "wof:population":7
},
  "geometry": {"coordinates":[8.26729,44.39315],"type":"Point"}
}