{
  "type": "Feature",
  "properties": {
    "gn:admin1_code":"4",
    "gn:admin2_code":"SA",
    "gn:admin3_code":"65025.0",
    "gn:asciiname":"Spinazzo",
    "gn:country_code":"IT",
    "gn:dem":17,
    "gn:feature_class":"P",
    "gn:feature_code":"PPL",
    "gn:name":"Spinazzo",
    "gn:population":74,
    "gn:timezone":"Europe/Rome",
    "iso:country":"IT",
    "wof:name":"Spinazzo",
    "wof:placetype":"locality",
    "wof:population":74
},
  "geometry": {"coordinates":[15.0258,40.40901],"type":"Point"}
}