{
  "type": "Feature",
  "properties": {
    "gn:admin1_code":"16.0",
    "gn:admin2_code":"PO",
    "gn:admin3_code":"100001.0",
    "gn:asciiname":"Gricigliana",
    "gn:cc2":"IT",
    "gn:country_code":"IT",
    "gn:dem":385,
    "gn:feature_class":"P",
    "gn:feature_code":"PPL",
    "gn:name":"Gricigliana",
    "gn:population":0,
    "gn:timezone":"Europe/Rome",
    "iso:country":"IT",
    "name:und_x_variant":[
        "Grieigliano",
        "Gricigliana"
    ],
    "wof:name":"Gricigliana",
    "wof:placetype":"locality"
},
  "geometry": {"coordinates":[11.13333,44.01667],"type":"Point"}
}