{
  "type": "Feature",
  "properties": {
    "gn:admin1_code":"12",
    "gn:admin2_code":"TO",
    "gn:admin3_code":"1311.0",
    "gn:asciiname":"Cascina Moncucco",
    "gn:country_code":"IT",
    "gn:dem":230,
    "gn:feature_class":"P",
    "gn:feature_code":"PPL",
    "gn:name":"Cascina Moncucco",
    "gn:population":29,
    "gn:timezone":"Europe/Rome",
    "iso:country":"IT",
    "wof:name":"Cascina Moncucco",
    "wof:placetype":"locality",
    "wof:population":29
},
  "geometry": {"coordinates":[7.9246,45.34608],"type":"Point"}
}