{
  "type": "Feature",
  "properties": {
    "gn:admin1_code":"7.0",
    "gn:admin2_code":"LT",
    "gn:admin3_code":"59028.0",
    "gn:asciiname":"Villafranca",
    "gn:cc2":"IT",
    "gn:country_code":"IT",
    "gn:dem":9,
    "gn:feature_class":"P",
    "gn:feature_code":"PPL",
    "gn:name":"Villafranca",
    "gn:population":0,
    "gn:timezone":"Europe/Rome",
    "iso:country":"IT",
    "name:arg_x_preferred":[
        "Villafranca"
    ],
    "name:bre_x_preferred":[
        "Alesbes"
    ],
    "name:cat_x_preferred":[
        "Villafranca"
    ],
    "name:ceb_x_preferred":[
        "Villafranca"
    ],
    "name:eus_x_preferred":[
        "Alesbes"
    ],
    "name:fra_x_preferred":[
        "Villafranca"
    ],
    "name:glg_x_preferred":[
        "Villafranca"
    ],
    "name:hun_x_preferred":[
        "Villafranca"
    ],
    "name:ita_x_preferred":[
        "Villafranca"
    ],
    "name:msa_x_preferred":[
        "Villafranca"
    ],
    "name:nld_x_preferred":[
        "Villafranca"
    ],
    "name:oci_x_preferred":[
        "Villafranca"
    ],
    "name:pol_x_preferred":[
        "Villafranca"
    ],
    "name:por_x_preferred":[
        "Villafranca"
    ],
    "name:rus_x_preferred":[
        "\u0412\u0438\u043b\u044c\u044f\u0444\u0440\u0430\u043d\u043a\u0430"
    ],
    "name:spa_x_preferred":[
        "Villafranca"
    ],
    "name:sqi_x_preferred":[
        "Villafranca"
    ],
    "name:swe_x_preferred":[
        "Villafranca"
    ],
    "name:ukr_x_preferred":[
        "\u0412\u0456\u043b\u044c\u044f\u0444\u0440\u0430\u043d\u043a\u0430"
    ],
    "name:und_x_variant":[
        "Casa Villafranca",
        "Villafranca"
    ],
    "name:vie_x_preferred":[
        "Villafranca"
    ],
    "name:war_x_preferred":[
        "Villafranca"
    ],
    "wof:name":"Villafranca",
    "wof:placetype":"locality"
},
  "geometry": {"coordinates":[12.98333,41.48333],"type":"Point"}
}