{
  "type": "Feature",
  "properties": {
    "gn:admin1_code":"5",
    "gn:admin2_code":"MO",
    "gn:admin3_code":"36030.0",
    "gn:asciiname":"Monta",
    "gn:country_code":"IT",
    "gn:dem":767,
    "gn:feature_class":"P",
    "gn:feature_code":"PPL",
    "gn:name":"Monta",
    "gn:population":18,
    "gn:timezone":"Europe/Rome",
    "iso:country":"IT",
    "name:ceb_x_preferred":[
        "Monta"
    ],
    "name:deu_x_preferred":[
        "Monta"
    ],
    "name:fra_x_preferred":[
        "Monta"
    ],
    "name:nld_x_preferred":[
        "Monta"
    ],
    "name:por_x_preferred":[
        "Monta"
    ],
    "name:spa_x_preferred":[
        "Monta"
    ],
    "name:srp_x_preferred":[
        "Monta"
    ],
    "name:swe_x_preferred":[
        "Monta"
    ],
    "wof:name":"Monta",
    "wof:placetype":"locality",
    "wof:population":18
},
  "geometry": {"coordinates":[10.80842,44.39034],"type":"Point"}
}