{
  "type": "Feature",
  "properties": {
    "gn:admin1_code":"3.0",
    "gn:admin2_code":"CZ",
    "gn:admin3_code":"79116.0",
    "gn:asciiname":"Santa Domenica",
    "gn:cc2":"IT",
    "gn:country_code":"IT",
    "gn:dem":219,
    "gn:feature_class":"P",
    "gn:feature_code":"PPL",
    "gn:name":"Santa Domenica",
    "gn:population":0,
    "gn:timezone":"Europe/Rome",
    "iso:country":"IT",
    "name:und_x_variant":[
        "San Domenico"
    ],
    "wof:name":"Santa Domenica",
    "wof:placetype":"locality"
},
  "geometry": {"coordinates":[16.51667,38.63333],"type":"Point"}
}