{
  "type": "Feature",
  "properties": {
    "gn:admin1_code":"5",
    "gn:admin2_code":"BO",
    "gn:admin3_code":"37044.0",
    "gn:asciiname":"San Rocco",
    "gn:country_code":"IT",
    "gn:dem":539,
    "gn:feature_class":"P",
    "gn:feature_code":"PPL",
    "gn:name":"San Rocco",
    "gn:population":38,
    "gn:timezone":"Europe/Rome",
    "iso:country":"IT",
    "wof:name":"San Rocco",
    "wof:placetype":"locality",
    "wof:population":38
},
  "geometry": {"coordinates":[11.22335,44.27497],"type":"Point"}
}