{
  "type": "Feature",
  "properties": {
    "gn:admin1_code":"12.0",
    "gn:admin2_code":"TO",
    "gn:admin3_code":"1073.0",
    "gn:asciiname":"Alpe Pilocca",
    "gn:country_code":"IT",
    "gn:dem":2377,
    "gn:feature_class":"P",
    "gn:feature_code":"PPL",
    "gn:name":"Alpe Pilocca",
    "gn:population":0,
    "gn:timezone":"Europe/Rome",
    "iso:country":"IT",
    "name:und_x_variant":[
        "Alpe Pitocca",
        "Alpe Pilocca"
    ],
    "wof:name":"Alpe Pilocca",
    "wof:placetype":"locality"
},
  "geometry": {"coordinates":[7.15,45.46667],"type":"Point"}
}