{
  "type": "Feature",
  "properties": {
    "gn:admin1_code":"1",
    "gn:admin2_code":"CH",
    "gn:admin3_code":"69098.0",
    "gn:asciiname":"Selve",
    "gn:country_code":"IT",
    "gn:dem":230,
    "gn:feature_class":"P",
    "gn:feature_code":"PPL",
    "gn:name":"Selve",
    "gn:population":37,
    "gn:timezone":"Europe/Rome",
    "iso:country":"IT",
    "name:deu_x_preferred":[
        "Selve"
    ],
    "name:fin_x_preferred":[
        "Selve"
    ],
    "name:fra_x_preferred":[
        "Selve Automobilwerke"
    ],
    "name:ita_x_preferred":[
        "Selve Automobilwerke"
    ],
    "name:swe_x_preferred":[
        "Selve Automobilwerke"
    ],
    "name:ukr_x_preferred":[
        "Selve"
    ],
    "wof:name":"Selve",
    "wof:placetype":"locality",
    "wof:population":37
},
  "geometry": {"coordinates":[14.23031,42.26516],"type":"Point"}
}