{
  "type": "Feature",
  "properties": {
    "gn:admin1_code":"12.0",
    "gn:admin2_code":"CN",
    "gn:admin3_code":"4044.0",
    "gn:asciiname":"Copetto",
    "gn:country_code":"IT",
    "gn:dem":726,
    "gn:feature_class":"P",
    "gn:feature_code":"PPL",
    "gn:name":"Copetto",
    "gn:population":4,
    "gn:timezone":"Europe/Rome",
    "iso:country":"IT",
    "wof:name":"Copetto",
    "wof:placetype":"locality",
    "wof:population":4
},
  "geometry": {"coordinates":[7.29281,44.4711],"type":"Point"}
}