{
  "type": "Feature",
  "properties": {
    "gn:admin1_code":"9",
    "gn:admin2_code":"PV",
    "gn:admin3_code":"18171.0",
    "gn:asciiname":"Celletta",
    "gn:country_code":"IT",
    "gn:dem":552,
    "gn:feature_class":"P",
    "gn:feature_code":"PPL",
    "gn:name":"Celletta",
    "gn:population":21,
    "gn:timezone":"Europe/Rome",
    "iso:country":"IT",
    "wof:name":"Celletta",
    "wof:placetype":"locality",
    "wof:population":21
},
  "geometry": {"coordinates":[9.17704,44.84253],"type":"Point"}
}