{
  "type": "Feature",
  "properties": {
    "gn:admin1_code":"15",
    "gn:admin2_code":"PA",
    "gn:admin3_code":"82047.0",
    "gn:asciiname":"Filippo Turati",
    "gn:country_code":"IT",
    "gn:dem":577,
    "gn:feature_class":"P",
    "gn:feature_code":"PPL",
    "gn:name":"Filippo Turati",
    "gn:population":38,
    "gn:timezone":"Europe/Rome",
    "iso:country":"IT",
    "name:ast_x_preferred":[
        "Filippo Turati"
    ],
    "name:deu_x_preferred":[
        "Filippo Turati"
    ],
    "name:fin_x_preferred":[
        "Filippo Turati"
    ],
    "name:fra_x_preferred":[
        "Filippo Turati"
    ],
    "name:hye_x_preferred":[
        "\u0556\u056b\u056c\u056b\u057a\u057a\u0578 \u054f\u0578\u0582\u0580\u0561\u057f\u056b"
    ],
    "name:ita_x_preferred":[
        "Filippo Turati"
    ],
    "name:jpn_x_preferred":[
        "\u30d5\u30a3\u30ea\u30c3\u30dd\u30fb\u30c8\u30a5\u30e9\u30fc\u30c6\u30a3"
    ],
    "name:lat_x_preferred":[
        "Philippus Turati"
    ],
    "name:lmo_x_preferred":[
        "Filippo Turati"
    ],
    "name:nep_x_preferred":[
        "\u092b\u093f\u0932\u093f\u092a\u094d\u092a\u094b \u0924\u0941\u0930\u0924\u0940"
    ],
    "name:nno_x_preferred":[
        "Filippo Turati"
    ],
    "name:rus_x_preferred":[
        "\u0422\u0443\u0440\u0430\u0442\u0438"
    ],
    "name:spa_x_preferred":[
        "Filippo Turati"
    ],
    "name:swe_x_preferred":[
        "Filippo Turati"
    ],
    "name:ukr_x_preferred":[
        "\u0424\u0456\u043b\u0456\u043f\u043f\u043e \u0422\u0443\u0440\u0430\u0442\u0456"
    ],
    "name:vec_x_preferred":[
        "Filippo Turati"
    ],
    "name:zho_x_preferred":[
        "\u83f2\u5229\u6ce2\u00b7\u5c60\u62c9\u8482"
    ],
    "wof:name":"Filippo Turati",
    "wof:placetype":"locality",
    "wof:population":38
},
  "geometry": {"coordinates":[13.47184,37.86306],"type":"Point"}
}