{
  "type": "Feature",
  "properties": {
    "gn:admin1_code":"15",
    "gn:admin2_code":"PA",
    "gn:admin3_code":"82047.0",
    "gn:asciiname":"Filippo Turati",
    "gn:country_code":"IT",
    "gn:dem":577,
    "gn:feature_class":"P",
    "gn:feature_code":"PPL",
    "gn:name":"Filippo Turati",
    "gn:population":38,
    "gn:timezone":"Europe/Rome",
    "iso:country":"IT",
    "wof:name":"Filippo Turati",
    "wof:placetype":"locality",
    "wof:population":38
},
  "geometry": {"coordinates":[13.47184,37.86306],"type":"Point"}
}