{
  "type": "Feature",
  "properties": {
    "gn:admin1_code":"5",
    "gn:admin2_code":"PR",
    "gn:admin3_code":"34017.0",
    "gn:asciiname":"Villanova",
    "gn:country_code":"IT",
    "gn:dem":289,
    "gn:feature_class":"P",
    "gn:feature_code":"PPL",
    "gn:name":"Villanova",
    "gn:population":31,
    "gn:timezone":"Europe/Rome",
    "iso:country":"IT",
    "wof:name":"Villanova",
    "wof:placetype":"locality",
    "wof:population":31
},
  "geometry": {"coordinates":[10.10741,44.63547],"type":"Point"}
}