{
  "type": "Feature",
  "properties": {
    "gn:admin1_code":"12",
    "gn:admin2_code":"CN",
    "gn:admin3_code":"4155.0",
    "gn:asciiname":"Prale",
    "gn:country_code":"IT",
    "gn:dem":996,
    "gn:feature_class":"P",
    "gn:feature_code":"PPLL",
    "gn:name":"Prale",
    "gn:population":8,
    "gn:timezone":"Europe/Rome",
    "iso:country":"IT",
    "wof:name":"Prale",
    "wof:placetype":"locality",
    "wof:population":8
},
  "geometry": {"coordinates":[7.90491,44.11783],"type":"Point"}
}