{
  "type": "Feature",
  "properties": {
    "gn:admin1_code":"12.0",
    "gn:admin2_code":"AL",
    "gn:admin3_code":"6172.0",
    "gn:asciiname":"Terzo",
    "gn:country_code":"IT",
    "gn:dem":212,
    "gn:elevation":"222.0",
    "gn:feature_class":"P",
    "gn:feature_code":"PPLA3",
    "gn:name":"Terzo",
    "gn:population":428,
    "gn:timezone":"Europe/Rome",
    "iso:country":"IT",
    "name:bel_x_preferred":[
        "\u0422\u044d\u0440\u0446\u0430"
    ],
    "name:ceb_x_preferred":[
        "Terzo"
    ],
    "name:ita_x_preferred":[
        "Terzo"
    ],
    "name:por_x_preferred":[
        "Terzo"
    ],
    "name:scn_x_preferred":[
        "Terzo"
    ],
    "name:srp_x_preferred":[
        "Terco"
    ],
    "name:swe_x_preferred":[
        "Terzo"
    ],
    "wof:name":"Terzo",
    "wof:placetype":"locality",
    "wof:population":428
},
  "geometry": {"coordinates":[8.42164,44.67045],"type":"Point"}
}