{
  "type": "Feature",
  "properties": {
    "gn:admin1_code":"20",
    "gn:admin2_code":"TV",
    "gn:admin3_code":"26081.0",
    "gn:asciiname":"Case Scomparin",
    "gn:country_code":"IT",
    "gn:dem":5,
    "gn:feature_class":"P",
    "gn:feature_code":"PPL",
    "gn:name":"Case Scomparin",
    "gn:population":69,
    "gn:timezone":"Europe/Rome",
    "iso:country":"IT",
    "wof:name":"Case Scomparin",
    "wof:placetype":"locality",
    "wof:population":69
},
  "geometry": {"coordinates":[12.34958,45.61791],"type":"Point"}
}