{
  "type": "Feature",
  "properties": {
    "gn:admin1_code":"1",
    "gn:admin2_code":"CH",
    "gn:admin3_code":"69059.0",
    "gn:asciiname":"Pinciare",
    "gn:country_code":"IT",
    "gn:dem":75,
    "gn:feature_class":"P",
    "gn:feature_code":"PPL",
    "gn:name":"Pinciare",
    "gn:population":35,
    "gn:timezone":"Europe/Rome",
    "iso:country":"IT",
    "wof:name":"Pinciare",
    "wof:placetype":"locality",
    "wof:population":35
},
  "geometry": {"coordinates":[14.47541,42.14754],"type":"Point"}
}