{
  "type": "Feature",
  "properties": {
    "gn:admin1_code":"7.0",
    "gn:admin2_code":"FR",
    "gn:admin3_code":"60014.0",
    "gn:asciiname":"Brecciaro",
    "gn:country_code":"IT",
    "gn:dem":236,
    "gn:feature_class":"P",
    "gn:feature_code":"PPL",
    "gn:name":"Brecciaro",
    "gn:population":796,
    "gn:timezone":"Europe/Rome",
    "iso:country":"IT",
    "wof:name":"Brecciaro",
    "wof:placetype":"locality",
    "wof:population":796
},
  "geometry": {"coordinates":[13.47381,41.6313],"type":"Point"}
}