{
  "type": "Feature",
  "properties": {
    "gn:admin1_code":"20",
    "gn:admin2_code":"PD",
    "gn:admin3_code":"28097.0",
    "gn:asciiname":"Mondonovo",
    "gn:country_code":"IT",
    "gn:dem":2,
    "gn:feature_class":"P",
    "gn:feature_code":"PPL",
    "gn:name":"Mondonovo",
    "gn:population":211,
    "gn:timezone":"Europe/Rome",
    "iso:country":"IT",
    "wof:name":"Mondonovo",
    "wof:placetype":"locality",
    "wof:population":211
},
  "geometry": {"coordinates":[11.75726,45.12639],"type":"Point"}
}