{
  "type": "Feature",
  "properties": {
    "gn:admin1_code":"16",
    "gn:admin2_code":"MS",
    "gn:admin3_code":"45007.0",
    "gn:asciiname":"La Funicolare",
    "gn:country_code":"IT",
    "gn:dem":531,
    "gn:feature_class":"P",
    "gn:feature_code":"PPL",
    "gn:name":"La Funicolare",
    "gn:population":16,
    "gn:timezone":"Europe/Rome",
    "iso:country":"IT",
    "wof:name":"La Funicolare",
    "wof:placetype":"locality",
    "wof:population":16
},
  "geometry": {"coordinates":[10.17113,44.24791],"type":"Point"}
}