{
  "type": "Feature",
  "properties": {
    "gn:admin1_code":"1.0",
    "gn:admin2_code":"CH",
    "gn:admin3_code":"69006.0",
    "gn:asciiname":"Valle Cupa",
    "gn:country_code":"IT",
    "gn:dem":376,
    "gn:feature_class":"P",
    "gn:feature_code":"PPL",
    "gn:name":"Valle Cupa",
    "gn:population":56,
    "gn:timezone":"Europe/Rome",
    "iso:country":"IT",
    "wof:name":"Valle Cupa",
    "wof:placetype":"locality",
    "wof:population":56
},
  "geometry": {"coordinates":[14.35551,42.05357],"type":"Point"}
}