{
  "type": "Feature",
  "properties": {
    "gn:country":"IT",
    "gn:fcode":"PPL",
    "gn:population":0,
    "iso:country":"IT",
    "name:ceb_x_preferred":[
        "Vico d'Elsa"
    ],
    "name:deu_x_preferred":[
        "Vico d\u2019Elsa"
    ],
    "name:eng_x_preferred":[
        "Vico d'Elsa"
    ],
    "name:fra_x_preferred":[
        "Vico d'Elsa"
    ],
    "name:hun_x_preferred":[
        "Vico d'Elsa"
    ],
    "name:ita_x_preferred":[
        "Vico d'Elsa"
    ],
    "name:srp_x_preferred":[
        "Vico d'Elsa"
    ],
    "name:und_x_variant":[
        "Vico Val d'Elsa"
    ],
    "qs_pg:aaroncc":"IT",
    "qs_pg:gn_country":"IT",
    "qs_pg:gn_fcode":"PPL",
    "qs_pg:gn_pop":0,
    "qs_pg:name":"Vico D'elsa",
    "qs_pg:name_adm0":"Italia",
    "qs_pg:name_adm1":"Toscana",
    "qs_pg:photos":131,
    "qs_pg:photos_1k":27,
    "qs_pg:photos_9k":1,
    "qs_pg:photos_9r":3,
    "qs_pg:photos_all":131,
    "qs_pg:photos_sr":3,
    "qs_pg:pop_sr":0,
    "qs_pg:qs_pg_placetype":"locality",
    "qs_pg:qs_pg_placetype_gp":"Town",
    "qs_pg:woe_adm0":23424853,
    "woe:adm0_id":23424853,
    "woe:name_adm0":"Italia",
    "woe:name_adm1":"Toscana",
    "woe:placetype":"Town",
    "wof:name":"Vico D'elsa",
    "wof:placetype":"locality",
    "wof:population":468
},
  "geometry": {"coordinates":[11.09877,43.51308],"type":"Point"}
}