{
  "type": "Feature",
  "properties": {
    "iso:country":"IT",
    "name:deu_x_preferred":[
        "Prati"
    ],
    "name:eus_x_preferred":[
        "Prati"
    ],
    "name:fin_x_preferred":[
        "Prati"
    ],
    "name:fra_x_preferred":[
        "Prati"
    ],
    "name:heb_x_preferred":[
        "\u05e4\u05e8\u05d0\u05d8\u05d9"
    ],
    "name:nor_x_preferred":[
        "Prati"
    ],
    "name:pol_x_preferred":[
        "Prati"
    ],
    "name:rus_x_preferred":[
        "\u041f\u0440\u0430\u0442\u0438"
    ],
    "name:spa_x_preferred":[
        "Prati"
    ],
    "name:swe_x_preferred":[
        "Prati"
    ],
    "name:ukr_x_preferred":[
        "\u041f\u0440\u0430\u0442\u0456"
    ],
    "name:zho_x_preferred":[
        "\u666e\u62c9\u8482"
    ],
    "wof:name":"Prati",
    "wof:placetype":"neighbourhood"
},
  "geometry": {"coordinates":[12.4641176658539,41.90903264636038],"type":"Point"}
}