{
  "type": "Feature",
  "properties": {
    "iso:country":"IT",
    "wof:name":"Prati",
    "wof:placetype":"neighbourhood"
},
  "geometry": {"coordinates":[12.4641176658539,41.90903264636038],"type":"Point"}
}