{
  "type": "Feature",
  "properties": {
    "gn:admin1_code":"3.0",
    "gn:admin2_code":"CS",
    "gn:admin3_code":"78003.0",
    "gn:asciiname":"Pagania",
    "gn:country_code":"IT",
    "gn:dem":856,
    "gn:feature_class":"P",
    "gn:feature_code":"PPL",
    "gn:name":"Pagania",
    "gn:population":0,
    "gn:timezone":"Europe/Rome",
    "iso:country":"IT",
    "wof:name":"Pagania",
    "wof:placetype":"locality"
},
  "geometry": {"coordinates":[16.43333,39.55],"type":"Point"}
}