{
  "type": "Feature",
  "properties": {
    "gn:admin1_code":"17.0",
    "gn:admin2_code":"BZ",
    "gn:admin3_code":"21107.0",
    "gn:asciiname":"Kematen",
    "gn:cc2":"IT",
    "gn:country_code":"IT",
    "gn:dem":1450,
    "gn:elevation":"1444.0",
    "gn:feature_class":"P",
    "gn:feature_code":"PPL",
    "gn:name":"Kematen",
    "gn:population":0,
    "gn:timezone":"Europe/Rome",
    "iso:country":"IT",
    "name:ces_x_preferred":[
        "Kematen"
    ],
    "name:deu_x_preferred":[
        "Kematen"
    ],
    "name:ita_x_preferred":[
        "Kematen"
    ],
    "name:nld_x_preferred":[
        "Kematen"
    ],
    "name:pol_x_preferred":[
        "Kematen"
    ],
    "wof:name":"Kematen",
    "wof:placetype":"locality"
},
  "geometry": {"coordinates":[11.54363,46.95893],"type":"Point"}
}