{
  "type": "Feature",
  "properties": {
    "gn:admin1_code":"3",
    "gn:admin2_code":"RC",
    "gn:admin3_code":"80040.0",
    "gn:asciiname":"Nebla",
    "gn:country_code":"IT",
    "gn:dem":217,
    "gn:feature_class":"P",
    "gn:feature_code":"PPL",
    "gn:name":"Nebl\u00e0",
    "gn:population":20,
    "gn:timezone":"Europe/Rome",
    "iso:country":"IT",
    "name:und_x_variant":[
        "Nebl\u00e0"
    ],
    "wof:name":"Nebla",
    "wof:placetype":"locality",
    "wof:population":20
},
  "geometry": {"coordinates":[16.25452,38.36392],"type":"Point"}
}