{
  "type": "Feature",
  "properties": {
    "gn:admin1_code":"16.0",
    "gn:admin2_code":"AR",
    "gn:admin3_code":"51034.0",
    "gn:asciiname":"Gricignano",
    "gn:country_code":"IT",
    "gn:dem":308,
    "gn:elevation":"306.0",
    "gn:feature_class":"P",
    "gn:feature_code":"PPL",
    "gn:name":"Gricignano",
    "gn:population":368,
    "gn:timezone":"Europe/Rome",
    "iso:country":"IT",
    "wof:name":"Gricignano",
    "wof:placetype":"locality",
    "wof:population":368
},
  "geometry": {"coordinates":[12.11186,43.54312],"type":"Point"}
}