{
  "type": "Feature",
  "properties": {
    "gn:admin1_code":"9",
    "gn:admin2_code":"BG",
    "gn:admin3_code":"16188.0",
    "gn:asciiname":"Cornalita",
    "gn:country_code":"IT",
    "gn:dem":547,
    "gn:feature_class":"P",
    "gn:feature_code":"PPL",
    "gn:name":"Cornalita",
    "gn:population":319,
    "gn:timezone":"Europe/Rome",
    "iso:country":"IT",
    "wof:name":"Cornalita",
    "wof:placetype":"locality",
    "wof:population":319
},
  "geometry": {"coordinates":[9.64377,45.87141],"type":"Point"}
}