{
  "type": "Feature",
  "properties": {
    "gn:admin1_code":"12",
    "gn:admin2_code":"TO",
    "gn:admin3_code":"1224.0",
    "gn:asciiname":"Lilla",
    "gn:country_code":"IT",
    "gn:dem":818,
    "gn:feature_class":"P",
    "gn:feature_code":"PPL",
    "gn:name":"Lilla",
    "gn:population":11,
    "gn:timezone":"Europe/Rome",
    "iso:country":"IT",
    "wof:name":"Lilla",
    "wof:placetype":"locality",
    "wof:population":11
},
  "geometry": {"coordinates":[7.55013,45.48273],"type":"Point"}
}