{
  "type": "Feature",
  "properties": {
    "gn:admin1_code":"3.0",
    "gn:admin2_code":"RC",
    "gn:admin3_code":"80063.0",
    "gn:asciiname":"Trunca",
    "gn:country_code":"IT",
    "gn:dem":576,
    "gn:elevation":"622.0",
    "gn:feature_class":"P",
    "gn:feature_code":"PPL",
    "gn:name":"Trunca",
    "gn:population":530,
    "gn:timezone":"Europe/Rome",
    "iso:country":"IT",
    "wof:name":"Trunca",
    "wof:placetype":"locality",
    "wof:population":530
},
  "geometry": {"coordinates":[15.7505,38.04642],"type":"Point"}
}