{
  "type": "Feature",
  "properties": {
    "gn:admin1_code":"10",
    "gn:admin2_code":"AN",
    "gn:admin3_code":"42017.0",
    "gn:asciiname":"Dante-Campo dell'Olmo",
    "gn:country_code":"IT",
    "gn:dem":270,
    "gn:feature_class":"P",
    "gn:feature_code":"PPL",
    "gn:name":"Dante-Campo dell'Olmo",
    "gn:population":22,
    "gn:timezone":"Europe/Rome",
    "iso:country":"IT",
    "wof:name":"Dante-Campo dell'Olmo",
    "wof:placetype":"locality",
    "wof:population":22
},
  "geometry": {"coordinates":[12.94325,43.34759],"type":"Point"}
}