{
  "type": "Feature",
  "properties": {
    "gn:admin1_code":"12.0",
    "gn:admin2_code":"VB",
    "gn:admin3_code":"103001.0",
    "gn:asciiname":"Alpe Russi",
    "gn:country_code":"IT",
    "gn:dem":1092,
    "gn:feature_class":"P",
    "gn:feature_code":"PPLL",
    "gn:name":"Alpe Russi",
    "gn:population":0,
    "gn:timezone":"Europe/Rome",
    "iso:country":"IT",
    "wof:name":"Alpe Russi",
    "wof:placetype":"locality"
},
  "geometry": {"coordinates":[8.09592,46.0544],"type":"Point"}
}