{
  "type": "Feature",
  "properties": {
    "gn:admin1_code":"2",
    "gn:admin2_code":"PZ",
    "gn:admin3_code":"76040.0",
    "gn:asciiname":"Preti",
    "gn:country_code":"IT",
    "gn:dem":793,
    "gn:feature_class":"P",
    "gn:feature_code":"PPL",
    "gn:name":"Preti",
    "gn:population":140,
    "gn:timezone":"Europe/Rome",
    "iso:country":"IT",
    "wof:name":"Preti",
    "wof:placetype":"locality",
    "wof:population":140
},
  "geometry": {"coordinates":[16.02827000000001,40.04732],"type":"Point"}
}