{
  "type": "Feature",
  "properties": {
    "gn:admin1_code":"5.0",
    "gn:admin2_code":"MO",
    "gn:admin3_code":"36008.0",
    "gn:asciiname":"Ca' di Sola",
    "gn:country_code":"IT",
    "gn:dem":92,
    "gn:feature_class":"P",
    "gn:feature_code":"PPL",
    "gn:name":"Ca' di Sola",
    "gn:population":1061,
    "gn:timezone":"Europe/Rome",
    "iso:country":"IT",
    "wof:name":"Ca' di Sola",
    "wof:placetype":"locality",
    "wof:population":1061
},
  "geometry": {"coordinates":[10.95448,44.52986],"type":"Point"}
}