{
  "type": "Feature",
  "properties": {
    "gn:admin1_code":"16",
    "gn:admin2_code":"AR",
    "gn:admin3_code":"51013.0",
    "gn:asciiname":"Bellosguardo",
    "gn:country_code":"IT",
    "gn:dem":275,
    "gn:feature_class":"P",
    "gn:feature_code":"PPL",
    "gn:name":"Bellosguardo",
    "gn:population":16,
    "gn:timezone":"Europe/Rome",
    "iso:country":"IT",
    "name:azb_x_preferred":[
        "\u0628\u0644\u0648\u0633\u0642\u0648\u0626\u0627\u0631\u062f\u0648"
    ],
    "name:bel_x_preferred":[
        "\u0411\u0435\u043b\u0430\u0437\u0433\u0443\u0430\u0440\u0434\u0430"
    ],
    "name:bul_x_preferred":[
        "\u0411\u0435\u043b\u043e\u0437\u0433\u0443\u0430\u0440\u0434\u043e"
    ],
    "name:ceb_x_preferred":[
        "Bellosguardo"
    ],
    "name:deu_x_preferred":[
        "Bellosguardo"
    ],
    "name:epo_x_preferred":[
        "Bellosguardo"
    ],
    "name:eus_x_preferred":[
        "Bellosguardo"
    ],
    "name:fas_x_preferred":[
        "\u0628\u0644\u0648\u0633\u06af\u0648\u0626\u0627\u0631\u062f\u0648"
    ],
    "name:fra_x_preferred":[
        "Bellosguardo"
    ],
    "name:hun_x_preferred":[
        "Bellosguardo"
    ],
    "name:hye_x_preferred":[
        "\u0532\u0565\u056c\u0578\u0566\u0563\u0578\u0582\u0561\u0580\u0564\u0578"
    ],
    "name:ina_x_preferred":[
        "Bellosguardo"
    ],
    "name:ind_x_preferred":[
        "Bellosguardo"
    ],
    "name:ita_x_preferred":[
        "Bellosguardo"
    ],
    "name:jpn_x_preferred":[
        "\u30d9\u30c3\u30ed\u30ba\u30b0\u30a2\u30eb\u30c9"
    ],
    "name:kaz_x_preferred":[
        "\u0411\u0435\u043b\u043b\u043e\u0437\u0433\u0443\u0430\u0440\u0434\u043e"
    ],
    "name:kor_x_preferred":[
        "\ubca8\ub85c\uc2a4\uad6c\uc544\ub974\ub3c4"
    ],
    "name:lat_x_preferred":[
        "Belrisguardum"
    ],
    "name:lmo_x_preferred":[
        "Bellosguardo"
    ],
    "name:msa_x_preferred":[
        "Bellosguardo"
    ],
    "name:nap_x_preferred":[
        "Bellosguardo"
    ],
    "name:nld_x_preferred":[
        "Bellosguardo"
    ],
    "name:pms_x_preferred":[
        "Bellosguardo"
    ],
    "name:pol_x_preferred":[
        "Bellosguardo"
    ],
    "name:por_x_preferred":[
        "Bellosguardo"
    ],
    "name:ron_x_preferred":[
        "Bellosguardo"
    ],
    "name:rus_x_preferred":[
        "\u0411\u0435\u043b\u043b\u043e\u0437\u0433\u0443\u0430\u0440\u0434\u043e"
    ],
    "name:scn_x_preferred":[
        "Bellosguardo"
    ],
    "name:spa_x_preferred":[
        "Bellosguardo"
    ],
    "name:srp_x_preferred":[
        "\u0411\u0435\u043b\u043e\u0437\u0433\u0432\u0430\u0440\u0434\u043e"
    ],
    "name:tgl_x_preferred":[
        "Bellosguardo"
    ],
    "name:ukr_x_preferred":[
        "\u0411\u0435\u043b\u043b\u043e\u0437\u0433\u0443\u0430\u0440\u0434\u043e"
    ],
    "name:uzb_x_preferred":[
        "Bellosguardo"
    ],
    "name:vec_x_preferred":[
        "Bellosguardo"
    ],
    "name:vie_x_preferred":[
        "Bellosguardo"
    ],
    "name:vol_x_preferred":[
        "Bellosguardo"
    ],
    "name:war_x_preferred":[
        "Bellosguardo"
    ],
    "name:zho_x_preferred":[
        "\u8d1d\u6d1b\u65af\u74dc\u5c14\u591a"
    ],
    "wof:name":"Bellosguardo",
    "wof:placetype":"locality",
    "wof:population":16
},
  "geometry": {"coordinates":[11.48969,43.53247],"type":"Point"}
}