{
  "type": "Feature",
  "properties": {
    "gn:admin1_code":"16",
    "gn:admin2_code":"AR",
    "gn:admin3_code":"51013.0",
    "gn:asciiname":"Bellosguardo",
    "gn:country_code":"IT",
    "gn:dem":275,
    "gn:feature_class":"P",
    "gn:feature_code":"PPL",
    "gn:name":"Bellosguardo",
    "gn:population":16,
    "gn:timezone":"Europe/Rome",
    "iso:country":"IT",
    "wof:name":"Bellosguardo",
    "wof:placetype":"locality",
    "wof:population":16
},
  "geometry": {"coordinates":[11.48969,43.53247],"type":"Point"}
}