{
  "type": "Feature",
  "properties": {
    "gn:admin1_code":"20",
    "gn:admin2_code":"VI",
    "gn:admin3_code":"24040.0",
    "gn:asciiname":"Ca' Viero-Carollo",
    "gn:country_code":"IT",
    "gn:dem":248,
    "gn:feature_class":"P",
    "gn:feature_code":"PPL",
    "gn:name":"Ca' Viero-Carollo",
    "gn:population":23,
    "gn:timezone":"Europe/Rome",
    "iso:country":"IT",
    "wof:name":"Ca' Viero-Carollo",
    "wof:placetype":"locality",
    "wof:population":23
},
  "geometry": {"coordinates":[11.56115,45.7289],"type":"Point"}
}