{
  "type": "Feature",
  "properties": {
    "gn:admin1_code":"9",
    "gn:admin2_code":"CO",
    "gn:admin3_code":"13010.0",
    "gn:asciiname":"San Bartolomeo",
    "gn:country_code":"IT",
    "gn:dem":366,
    "gn:feature_class":"P",
    "gn:feature_code":"PPL",
    "gn:name":"San Bartolomeo",
    "gn:population":31,
    "gn:timezone":"Europe/Rome",
    "iso:country":"IT",
    "name:ceb_x_preferred":[
        "San Bartolomeo"
    ],
    "name:deu_x_preferred":[
        "San Bartolomeo"
    ],
    "name:epo_x_preferred":[
        "San Bartolomeo"
    ],
    "name:hun_x_preferred":[
        "San Bartolomeo"
    ],
    "name:ita_x_preferred":[
        "San Bartolomeo"
    ],
    "name:por_x_preferred":[
        "San Bartolomeo"
    ],
    "name:srp_x_preferred":[
        "San Bartolomeo"
    ],
    "name:swe_x_preferred":[
        "San Bartolomeo"
    ],
    "name:war_x_preferred":[
        "San Bartolomeo"
    ],
    "wof:name":"San Bartolomeo",
    "wof:placetype":"locality",
    "wof:population":31
},
  "geometry": {"coordinates":[8.94569,45.73845],"type":"Point"}
}