{
  "type": "Feature",
  "properties": {
    "gn:admin1_code":"12",
    "gn:admin2_code":"NO",
    "gn:admin3_code":"3120.0",
    "gn:asciiname":"Prerro",
    "gn:country_code":"IT",
    "gn:dem":554,
    "gn:feature_class":"P",
    "gn:feature_code":"PPL",
    "gn:name":"Prerro",
    "gn:population":112,
    "gn:timezone":"Europe/Rome",
    "iso:country":"IT",
    "wof:name":"Prerro",
    "wof:placetype":"locality",
    "wof:population":112
},
  "geometry": {"coordinates":[8.37275,45.76488],"type":"Point"}
}