{
  "type": "Feature",
  "properties": {
    "gn:admin1_code":"9",
    "gn:admin2_code":"MN",
    "gn:admin3_code":"20002.0",
    "gn:asciiname":"Caminate",
    "gn:country_code":"IT",
    "gn:dem":35,
    "gn:feature_class":"P",
    "gn:feature_code":"PPL",
    "gn:name":"Caminate",
    "gn:population":24,
    "gn:timezone":"Europe/Rome",
    "iso:country":"IT",
    "wof:name":"Caminate",
    "wof:placetype":"locality",
    "wof:population":24
},
  "geometry": {"coordinates":[10.38736,45.22479000000001],"type":"Point"}
}