{
  "type": "Feature",
  "properties": {
    "gn:admin1_code":"6.0",
    "gn:admin2_code":"PN",
    "gn:admin3_code":"93006.0",
    "gn:asciiname":"Arcola",
    "gn:country_code":"IT",
    "gn:dem":459,
    "gn:feature_class":"P",
    "gn:feature_code":"PPL",
    "gn:name":"\u00c0rcola",
    "gn:population":0,
    "gn:timezone":"Europe/Rome",
    "iso:country":"IT",
    "wof:name":"Arcola",
    "wof:placetype":"locality"
},
  "geometry": {"coordinates":[12.52444,46.20056],"type":"Point"}
}