{
  "type": "Feature",
  "properties": {
    "gn:admin1_code":"5",
    "gn:admin2_code":"FE",
    "gn:admin3_code":"38019.0",
    "gn:asciiname":"Santa Teresa",
    "gn:country_code":"IT",
    "gn:dem":4,
    "gn:feature_class":"P",
    "gn:feature_code":"PPL",
    "gn:name":"Santa Teresa",
    "gn:population":17,
    "gn:timezone":"Europe/Rome",
    "iso:country":"IT",
    "wof:name":"Santa Teresa",
    "wof:placetype":"locality",
    "wof:population":17
},
  "geometry": {"coordinates":[11.75747,44.72219000000001],"type":"Point"}
}