{
  "type": "Feature",
  "properties": {
    "gn:admin1_code":"9",
    "gn:admin2_code":"PV",
    "gn:admin3_code":"18100.0",
    "gn:asciiname":"Bosco Negredo",
    "gn:country_code":"IT",
    "gn:dem":210,
    "gn:feature_class":"P",
    "gn:feature_code":"PPL",
    "gn:name":"Bosco Negredo",
    "gn:population":55,
    "gn:timezone":"Europe/Rome",
    "iso:country":"IT",
    "wof:name":"Bosco Negredo",
    "wof:placetype":"locality",
    "wof:population":55
},
  "geometry": {"coordinates":[9.33057,45.03637],"type":"Point"}
}