{
  "type": "Feature",
  "properties": {
    "gn:admin1_code":"20.0",
    "gn:admin2_code":"PD",
    "gn:admin3_code":"28060.0",
    "gn:asciiname":"Pozzoveggiani",
    "gn:country_code":"IT",
    "gn:dem":8,
    "gn:feature_class":"P",
    "gn:feature_code":"PPL",
    "gn:name":"Pozzoveggiani",
    "gn:population":365,
    "gn:timezone":"Europe/Rome",
    "iso:country":"IT",
    "wof:name":"Pozzoveggiani",
    "wof:placetype":"locality",
    "wof:population":365
},
  "geometry": {"coordinates":[11.90297,45.35302],"type":"Point"}
}