{
  "type": "Feature",
  "properties": {
    "gn:admin1_code":"20",
    "gn:admin2_code":"TV",
    "gn:admin3_code":"26058.0",
    "gn:asciiname":"Case Biancolin",
    "gn:country_code":"IT",
    "gn:dem":8,
    "gn:feature_class":"P",
    "gn:feature_code":"PPL",
    "gn:name":"Case Biancolin",
    "gn:population":43,
    "gn:timezone":"Europe/Rome",
    "iso:country":"IT",
    "wof:name":"Case Biancolin",
    "wof:placetype":"locality",
    "wof:population":43
},
  "geometry": {"coordinates":[12.49627,45.74296],"type":"Point"}
}