{
  "type": "Feature",
  "properties": {
    "gn:admin1_code":"16",
    "gn:admin2_code":"GR",
    "gn:admin3_code":"53006.0",
    "gn:asciiname":"Le Palazzine",
    "gn:country_code":"IT",
    "gn:dem":33,
    "gn:feature_class":"P",
    "gn:feature_code":"PPL",
    "gn:name":"Le Palazzine",
    "gn:population":20,
    "gn:timezone":"Europe/Rome",
    "iso:country":"IT",
    "wof:name":"Le Palazzine",
    "wof:placetype":"locality",
    "wof:population":20
},
  "geometry": {"coordinates":[10.99486,42.80753],"type":"Point"}
}