{
  "type": "Feature",
  "properties": {
    "gn:admin1_code":"15",
    "gn:admin2_code":"PA",
    "gn:admin3_code":"82006.0",
    "gn:asciiname":"Porcara",
    "gn:country_code":"IT",
    "gn:dem":240,
    "gn:feature_class":"P",
    "gn:feature_code":"PPL",
    "gn:name":"Porcara",
    "gn:population":36,
    "gn:timezone":"Europe/Rome",
    "iso:country":"IT",
    "wof:name":"Porcara",
    "wof:placetype":"locality",
    "wof:population":36
},
  "geometry": {"coordinates":[13.48182,38.04973],"type":"Point"}
}