{
  "type": "Feature",
  "properties": {
    "gn:admin1_code":"10.0",
    "gn:admin2_code":"MC",
    "gn:admin3_code":"43048.0",
    "gn:asciiname":"San Martino",
    "gn:country_code":"IT",
    "gn:dem":335,
    "gn:elevation":"330.0",
    "gn:feature_class":"P",
    "gn:feature_code":"PPL",
    "gn:name":"San Martino",
    "gn:population":58,
    "gn:timezone":"Europe/Rome",
    "iso:country":"IT",
    "wof:name":"San Martino",
    "wof:placetype":"locality",
    "wof:population":58
},
  "geometry": {"coordinates":[13.4207,43.12036],"type":"Point"}
}