{
  "type": "Feature",
  "properties": {
    "gn:admin1_code":"8",
    "gn:admin2_code":"GE",
    "gn:admin3_code":"10001.0",
    "gn:asciiname":"Terrarossa",
    "gn:country_code":"IT",
    "gn:dem":134,
    "gn:feature_class":"P",
    "gn:feature_code":"PPL",
    "gn:name":"Terrarossa",
    "gn:population":27,
    "gn:timezone":"Europe/Rome",
    "iso:country":"IT",
    "name:ceb_x_preferred":[
        "Terrarossa"
    ],
    "name:ita_x_preferred":[
        "Terrarossa"
    ],
    "name:nld_x_preferred":[
        "Terrarossa"
    ],
    "name:srp_x_preferred":[
        "\u0422\u0435\u0440\u0430\u0440\u043e\u0441\u0430"
    ],
    "wof:name":"Terrarossa",
    "wof:placetype":"locality",
    "wof:population":27
},
  "geometry": {"coordinates":[8.69651,44.41292],"type":"Point"}
}