{
  "type": "Feature",
  "properties": {
    "gn:admin1_code":"15.0",
    "gn:admin2_code":"PA",
    "gn:admin3_code":"82005.0",
    "gn:asciiname":"Cava Valle Rena",
    "gn:country_code":"IT",
    "gn:dem":745,
    "gn:feature_class":"P",
    "gn:feature_code":"PPLL",
    "gn:name":"Cava Valle Rena",
    "gn:population":3,
    "gn:timezone":"Europe/Rome",
    "iso:country":"IT",
    "wof:name":"Cava Valle Rena",
    "wof:placetype":"locality",
    "wof:population":3
},
  "geometry": {"coordinates":[13.34305,38.02522],"type":"Point"}
}