{
  "type": "Feature",
  "properties": {
    "gn:elevation":405,
    "gn:population":557,
    "iso:country":"IT",
    "name:ceb_x_preferred":[
        "Giglio Castello"
    ],
    "name:che_x_preferred":[
        "\u0414\u0436\u0438\u043b\u044c\u0438\u043e \u041a\u0430\u0437\u0442\u0435\u043b\u043e"
    ],
    "name:deu_x_preferred":[
        "Giglio Castello"
    ],
    "name:eng_x_preferred":[
        "Giglio Isola"
    ],
    "name:eng_x_variant":[
        "Giglio",
        "Giglio Castello"
    ],
    "name:fra_x_preferred":[
        "Giglio Castello"
    ],
    "name:hbs_x_preferred":[
        "Giglio Castello"
    ],
    "name:hun_x_preferred":[
        "Giglio Castello"
    ],
    "name:ita_x_preferred":[
        "Giglio Castello"
    ],
    "name:nld_x_preferred":[
        "Giglio Castello"
    ],
    "name:spa_x_preferred":[
        "Giglio Castello"
    ],
    "name:srp_x_preferred":[
        "Giglio Castello"
    ],
    "name:tat_x_preferred":[
        "\u0496\u0438\u043b\u044c\u0438\u043e \u041a\u0430\u0437\u0442\u0435\u043b\u043e"
    ],
    "qs:a0":"Italia",
    "qs:a1":"*Grosseto",
    "qs:a1r":"0Toscana",
    "qs:adm0":"Italia",
    "qs:la_lc":"*",
    "qs:level":"locality",
    "qs:loc":"Giglio Castello",
    "qs:loc_alt":"Giglio Castello",
    "qs:pop":0,
    "qs:type":"buffered point",
    "wd:wordcount":246,
    "wof:lang":[
        "ita"
    ],
    "wof:name":"Giglio Castello",
    "wof:placetype":"locality",
    "wof:population":557
},
  "geometry": {"coordinates":[10.90194,42.365829],"type":"Point"}
}