{
  "type": "Feature",
  "properties": {
    "gn:admin1_code":"16.0",
    "gn:admin2_code":"LU",
    "gn:admin3_code":"46018.0",
    "gn:asciiname":"Corsanico-Bargecchia",
    "gn:country_code":"IT",
    "gn:dem":205,
    "gn:feature_class":"P",
    "gn:feature_code":"PPL",
    "gn:name":"Corsanico-Bargecchia",
    "gn:population":1595,
    "gn:timezone":"Europe/Rome",
    "iso:country":"IT",
    "wof:name":"Corsanico-Bargecchia",
    "wof:placetype":"locality",
    "wof:population":1595
},
  "geometry": {"coordinates":[10.30621,43.90828],"type":"Point"}
}