{
  "type": "Feature",
  "properties": {
    "gn:elevation":714,
    "gn:population":766,
    "iso:country":"IT",
    "name:eng_x_preferred":[
        "Sto Stefano"
    ],
    "name:eng_x_variant":[
        "Santo Stefano",
        "Sto. Stefano",
        "Santo Stefano in Aspromonte"
    ],
    "name:epo_x_preferred":[
        "Santo Stefano in Aspromonte"
    ],
    "name:fra_x_preferred":[
        "Santo Stefano in Aspromonte"
    ],
    "name:ita_x_preferred":[
        "Santo Stefano in Aspromonte"
    ],
    "name:ita_x_variant":[
        "Santo Stefano d'Aspromonte",
        "Sto Stefano d'Aspromonte",
        "Sto Stefano in Aspromonte",
        "Sto. Stefano d'Aspromonte",
        "Sto. Stefano in Aspromonte"
    ],
    "name:nap_x_preferred":[
        "Santo Stefano in Aspromonte"
    ],
    "name:nld_x_preferred":[
        "Santo Stefano in Aspromonte"
    ],
    "name:pol_x_preferred":[
        "Santo Stefano in Aspromonte"
    ],
    "name:por_x_preferred":[
        "Santo Stefano in Aspromonte"
    ],
    "name:unk_x_variant":[
        "Santo Stefano d'Aspromonte"
    ],
    "qs:a0":"Italia",
    "qs:a1":"*Reggio di Calabria",
    "qs:a1r":"0Calabria",
    "qs:adm0":"Italia",
    "qs:la_lc":"*",
    "qs:level":"locality",
    "qs:loc":"Santo Stefano in Aspromonte",
    "qs:loc_alt":"Santo Stefano in Aspromonte",
    "qs:pop":0,
    "qs:type":"buffered point",
    "wd:wordcount":123,
    "wof:lang":[
        "ita"
    ],
    "wof:name":"Santo Stefano in Aspromonte",
    "wof:placetype":"locality",
    "wof:population":766
},
  "geometry": {"coordinates":[15.79,38.169998],"type":"Point"}
}