{
  "type": "Feature",
  "properties": {
    "gn:admin1_code":"20",
    "gn:admin2_code":"RO",
    "gn:admin3_code":"29014.0",
    "gn:asciiname":"Vaccara",
    "gn:country_code":"IT",
    "gn:dem":8,
    "gn:feature_class":"P",
    "gn:feature_code":"PPL",
    "gn:name":"Vaccara",
    "gn:population":20,
    "gn:timezone":"Europe/Rome",
    "iso:country":"IT",
    "wof:name":"Vaccara",
    "wof:placetype":"locality",
    "wof:population":20
},
  "geometry": {"coordinates":[11.39168,45.03806],"type":"Point"}
}