{
  "type": "Feature",
  "properties": {
    "gn:admin1_code":"17",
    "gn:admin2_code":"TN",
    "gn:admin3_code":"22161.0",
    "gn:asciiname":"Senter",
    "gn:country_code":"IT",
    "gn:dem":654,
    "gn:feature_class":"P",
    "gn:feature_code":"PPL",
    "gn:name":"Senter",
    "gn:population":28,
    "gn:timezone":"Europe/Rome",
    "iso:country":"IT",
    "wof:name":"Senter",
    "wof:placetype":"locality",
    "wof:population":28
},
  "geometry": {"coordinates":[11.0899,45.87673],"type":"Point"}
}