{
  "type": "Feature",
  "properties": {
    "gn:admin1_code":"11",
    "gn:admin2_code":"CB",
    "gn:admin3_code":"70064.0",
    "gn:asciiname":"Montagna III",
    "gn:country_code":"IT",
    "gn:dem":464,
    "gn:feature_class":"P",
    "gn:feature_code":"PPL",
    "gn:name":"Montagna III",
    "gn:population":18,
    "gn:timezone":"Europe/Rome",
    "iso:country":"IT",
    "wof:name":"Montagna III",
    "wof:placetype":"locality",
    "wof:population":18
},
  "geometry": {"coordinates":[14.68985,41.87817],"type":"Point"}
}