{
  "type": "Feature",
  "properties": {
    "gn:elevation":450,
    "gn:population":249,
    "iso:country":"IT",
    "name:bel_x_preferred":[
        "\u041a\u0430\u0440\u0430"
    ],
    "name:bul_x_preferred":[
        "\u041a\u0430\u0440\u043e"
    ],
    "name:deu_x_preferred":[
        "Carro"
    ],
    "name:eng_x_preferred":[
        "Carro"
    ],
    "name:epo_x_preferred":[
        "Carro"
    ],
    "name:eus_x_preferred":[
        "Carro"
    ],
    "name:fas_x_preferred":[
        "\u06a9\u0627\u0631\u0648"
    ],
    "name:fra_x_preferred":[
        "Carro"
    ],
    "name:hbs_x_preferred":[
        "Carro"
    ],
    "name:hun_x_preferred":[
        "Carro"
    ],
    "name:hye_x_preferred":[
        "\u053f\u0561\u0580\u0578"
    ],
    "name:ina_x_preferred":[
        "Carro"
    ],
    "name:ita_x_preferred":[
        "Carro"
    ],
    "name:jpn_x_preferred":[
        "\u30ab\u30c3\u30ed"
    ],
    "name:kaz_x_preferred":[
        "\u041a\u0430\u0440\u0440\u043e"
    ],
    "name:lat_x_preferred":[
        "Carrum"
    ],
    "name:lij_x_preferred":[
        "O C\u00e4ro"
    ],
    "name:lmo_x_preferred":[
        "Carro"
    ],
    "name:msa_x_preferred":[
        "Carro"
    ],
    "name:nan_x_preferred":[
        "Carro"
    ],
    "name:nap_x_preferred":[
        "Carro"
    ],
    "name:nld_x_preferred":[
        "Carro"
    ],
    "name:pms_x_preferred":[
        "Carro"
    ],
    "name:pol_x_preferred":[
        "Carro"
    ],
    "name:por_x_preferred":[
        "Carro"
    ],
    "name:ron_x_preferred":[
        "Carro"
    ],
    "name:rus_x_preferred":[
        "\u041a\u0430\u0440\u0440\u043e"
    ],
    "name:scn_x_preferred":[
        "Carro"
    ],
    "name:spa_x_preferred":[
        "Carro"
    ],
    "name:srp_x_preferred":[
        "\u041a\u0430\u0440\u043e"
    ],
    "name:swe_x_preferred":[
        "Carro"
    ],
    "name:ukr_x_preferred":[
        "\u041a\u0430\u0440\u0440\u043e"
    ],
    "name:uzb_x_preferred":[
        "Carro"
    ],
    "name:vie_x_preferred":[
        "Carro"
    ],
    "name:vol_x_preferred":[
        "Carro"
    ],
    "name:war_x_preferred":[
        "Carro"
    ],
    "name:zho_min_nan_x_preferred":[
        "Carro"
    ],
    "name:zho_x_preferred":[
        "\u5361\u7f57"
    ],
    "qs:a0":"Italia",
    "qs:a1":"*La Spezia",
    "qs:a1r":"0Liguria",
    "qs:adm0":"Italia",
    "qs:la_lc":"*",
    "qs:level":"locality",
    "qs:loc":"Carro",
    "qs:loc_alt":"Carro",
    "qs:pop":0,
    "qs:type":"buffered point",
    "wd:wordcount":91,
    "wof:lang":[
        "ita"
    ],
    "wof:name":"Carro",
    "wof:placetype":"locality",
    "wof:population":249
},
  "geometry": {"coordinates":[9.609819,44.272801],"type":"Point"}
}