{
  "type": "Feature",
  "properties": {
    "gn:admin1_code":"20",
    "gn:admin2_code":"VR",
    "gn:admin3_code":"23093.0",
    "gn:asciiname":"Giordani",
    "gn:country_code":"IT",
    "gn:dem":678,
    "gn:feature_class":"P",
    "gn:feature_code":"PPL",
    "gn:name":"Giordani",
    "gn:population":21,
    "gn:timezone":"Europe/Rome",
    "iso:country":"IT",
    "wof:name":"Giordani",
    "wof:placetype":"locality",
    "wof:population":21
},
  "geometry": {"coordinates":[11.21728,45.58846],"type":"Point"}
}