{
  "type": "Feature",
  "properties": {
    "gn:admin1_code":"1",
    "gn:admin2_code":"AQ",
    "gn:admin3_code":"66098.0",
    "gn:asciiname":"Vallecorvo",
    "gn:country_code":"IT",
    "gn:dem":416,
    "gn:feature_class":"P",
    "gn:feature_code":"PPL",
    "gn:name":"Vallecorvo",
    "gn:population":50,
    "gn:timezone":"Europe/Rome",
    "iso:country":"IT",
    "wof:name":"Vallecorvo",
    "wof:placetype":"locality",
    "wof:population":50
},
  "geometry": {"coordinates":[13.88441,42.04298],"type":"Point"}
}