{
  "type": "Feature",
  "properties": {
    "gn:country":"IT",
    "gn:fcode":"PPL",
    "gn:population":0,
    "iso:country":"IT",
    "name:und_x_variant":[
        "Perriasc"
    ],
    "qs_pg:aaroncc":"IT",
    "qs_pg:gn_country":"IT",
    "qs_pg:gn_fcode":"PPL",
    "qs_pg:gn_pop":0,
    "qs_pg:name":"Periase",
    "qs_pg:name_adm0":"Italia",
    "qs_pg:name_adm1":"Valle d'Aosta",
    "qs_pg:photos":140,
    "qs_pg:photos_1k":28,
    "qs_pg:photos_9k":1,
    "qs_pg:photos_9r":3,
    "qs_pg:photos_all":140,
    "qs_pg:photos_sr":3,
    "qs_pg:pop_sr":0,
    "qs_pg:qs_pg_placetype":"locality",
    "qs_pg:qs_pg_placetype_gp":"Town",
    "qs_pg:woe_adm0":23424853,
    "woe:adm0_id":23424853,
    "woe:name_adm0":"Italia",
    "woe:name_adm1":"Valle d'Aosta",
    "woe:placetype":"Town",
    "wof:name":"Periase",
    "wof:placetype":"locality",
    "wof:population":133
},
  "geometry": {"coordinates":[7.68333,45.81667],"type":"Point"}
}