{
  "type": "Feature",
  "properties": {
    "gn:admin1_code":"16",
    "gn:admin2_code":"FI",
    "gn:admin3_code":"48044.0",
    "gn:asciiname":"La Beccheria",
    "gn:country_code":"IT",
    "gn:dem":58,
    "gn:feature_class":"P",
    "gn:feature_code":"PPL",
    "gn:name":"La Beccheria",
    "gn:population":39,
    "gn:timezone":"Europe/Rome",
    "iso:country":"IT",
    "wof:name":"La Beccheria",
    "wof:placetype":"locality",
    "wof:population":39
},
  "geometry": {"coordinates":[11.08551,43.79037],"type":"Point"}
}