{
  "type": "Feature",
  "properties": {
    "gn:admin1_code":"3.0",
    "gn:admin2_code":"CS",
    "gn:admin3_code":"78073.0",
    "gn:asciiname":"Il Seduttore",
    "gn:country_code":"IT",
    "gn:dem":426,
    "gn:feature_class":"P",
    "gn:feature_code":"PPL",
    "gn:name":"Il Seduttore",
    "gn:population":0,
    "gn:timezone":"Europe/Rome",
    "iso:country":"IT",
    "wof:name":"Il Seduttore",
    "wof:placetype":"locality"
},
  "geometry": {"coordinates":[16.03333,39.61667],"type":"Point"}
}