{
  "type": "Feature",
  "properties": {
    "gn:elevation":772,
    "gn:population":119,
    "iso:country":"IT",
    "name:bel_x_preferred":[
        "\u041c\u0430\u0441\u0456\u0451\u043b\u0430"
    ],
    "name:bul_x_preferred":[
        "\u041c\u0430\u0441\u0438\u043e\u043b\u0430"
    ],
    "name:cat_x_preferred":[
        "Massiola"
    ],
    "name:ces_x_preferred":[
        "Massiola"
    ],
    "name:deu_x_preferred":[
        "Massiola"
    ],
    "name:eng_x_preferred":[
        "Massiola"
    ],
    "name:epo_x_preferred":[
        "Massiola"
    ],
    "name:eus_x_preferred":[
        "Massiola"
    ],
    "name:fas_x_preferred":[
        "\u0645\u0627\u0633\u06cc\u0648\u0644\u0627"
    ],
    "name:fin_x_preferred":[
        "Massiola"
    ],
    "name:fra_x_preferred":[
        "Massiola"
    ],
    "name:hbs_x_preferred":[
        "Massiola"
    ],
    "name:hun_x_preferred":[
        "Massiola"
    ],
    "name:hye_x_preferred":[
        "\u0544\u0561\u057d\u056b\u0578\u056c\u0561"
    ],
    "name:ita_x_preferred":[
        "Massiola"
    ],
    "name:jpn_x_preferred":[
        "\u30de\u30c3\u30b7\u30aa\u30fc\u30e9"
    ],
    "name:kaz_x_preferred":[
        "\u041c\u0430\u0441\u0441\u0438\u043e\u043b\u0430"
    ],
    "name:lat_x_preferred":[
        "Massiola"
    ],
    "name:lmo_x_preferred":[
        "Maciola"
    ],
    "name:msa_x_preferred":[
        "Massiola"
    ],
    "name:nan_x_preferred":[
        "Massiola"
    ],
    "name:nap_x_preferred":[
        "Massiola"
    ],
    "name:nld_x_preferred":[
        "Massiola"
    ],
    "name:oci_x_preferred":[
        "Massiola"
    ],
    "name:pms_x_preferred":[
        "Maci\u00f2la"
    ],
    "name:pol_x_preferred":[
        "Massiola"
    ],
    "name:por_x_preferred":[
        "Massiola"
    ],
    "name:ron_x_preferred":[
        "Massiola"
    ],
    "name:rus_x_preferred":[
        "\u041c\u0430\u0441\u0441\u0438\u043e\u043b\u0430"
    ],
    "name:scn_x_preferred":[
        "Massiola"
    ],
    "name:spa_x_preferred":[
        "Massiola"
    ],
    "name:srp_x_preferred":[
        "\u041c\u0430\u0441\u0438\u043e\u043b\u0430"
    ],
    "name:tgl_x_preferred":[
        "Massiola"
    ],
    "name:ukr_x_preferred":[
        "\u041c\u0430\u0441\u0441\u0456\u043e\u043b\u0430"
    ],
    "name:uzb_x_preferred":[
        "Massiola"
    ],
    "name:vie_x_preferred":[
        "Massiola"
    ],
    "name:vol_x_preferred":[
        "Massiola"
    ],
    "name:war_x_preferred":[
        "Massiola"
    ],
    "name:zho_min_nan_x_preferred":[
        "Massiola"
    ],
    "name:zho_x_preferred":[
        "\u9a6c\u8096\u62c9"
    ],
    "qs:a0":"Italia",
    "qs:a1":"*Verbano-Cusio-Ossola",
    "qs:a1r":"0Piemonte",
    "qs:adm0":"Italia",
    "qs:la_lc":"*",
    "qs:level":"locality",
    "qs:loc":"Massiola",
    "qs:loc_alt":"Massiola",
    "qs:pop":0,
    "qs:type":"buffered point",
    "wd:wordcount":75,
    "wof:lang":[
        "ita"
    ],
    "wof:name":"Massiola",
    "wof:placetype":"locality",
    "wof:population":119
},
  "geometry": {"coordinates":[8.320991,45.912312],"type":"Point"}
}