{
  "type": "Feature",
  "properties": {
    "gn:admin1_code":"9",
    "gn:admin2_code":"PV",
    "gn:admin3_code":"18183.0",
    "gn:asciiname":"Casa Persoli",
    "gn:country_code":"IT",
    "gn:dem":402,
    "gn:feature_class":"P",
    "gn:feature_code":"PPLL",
    "gn:name":"Casa Persoli",
    "gn:population":10,
    "gn:timezone":"Europe/Rome",
    "iso:country":"IT",
    "wof:name":"Casa Persoli",
    "wof:placetype":"locality",
    "wof:population":10
},
  "geometry": {"coordinates":[9.29306,44.94857],"type":"Point"}
}