{
  "type": "Feature",
  "properties": {
    "gn:admin1_code":"20",
    "gn:admin2_code":"PD",
    "gn:admin3_code":"28032.0",
    "gn:asciiname":"Santa Lucia",
    "gn:country_code":"IT",
    "gn:dem":62,
    "gn:feature_class":"P",
    "gn:feature_code":"PPL",
    "gn:name":"Santa Lucia",
    "gn:population":61,
    "gn:timezone":"Europe/Rome",
    "iso:country":"IT",
    "wof:name":"Santa Lucia",
    "wof:placetype":"locality",
    "wof:population":61
},
  "geometry": {"coordinates":[11.71229,45.67422],"type":"Point"}
}