{
  "type": "Feature",
  "properties": {
    "gn:admin1_code":"20",
    "gn:admin2_code":"TV",
    "gn:admin3_code":"26058.0",
    "gn:asciiname":"Campagne",
    "gn:country_code":"IT",
    "gn:dem":11,
    "gn:feature_class":"P",
    "gn:feature_code":"PPL",
    "gn:name":"Campagne",
    "gn:population":77,
    "gn:timezone":"Europe/Rome",
    "iso:country":"IT",
    "name:ceb_x_preferred":[
        "Campagne"
    ],
    "name:deu_x_preferred":[
        "Campagne"
    ],
    "name:fra_x_preferred":[
        "Campagne"
    ],
    "name:ita_x_preferred":[
        "Campagne"
    ],
    "name:jpn_x_preferred":[
        "\u30ab\u30f3\u30d1\u30fc\u30cb\u30e5"
    ],
    "name:nds_x_preferred":[
        "Campagne"
    ],
    "name:nld_x_preferred":[
        "Campagne"
    ],
    "name:oci_x_preferred":[
        "Campagne"
    ],
    "name:pms_x_preferred":[
        "Campagne"
    ],
    "name:pol_x_preferred":[
        "Campagne"
    ],
    "name:por_x_preferred":[
        "Campagne"
    ],
    "name:rus_x_preferred":[
        "\u041a\u0430\u043c\u043f\u0430\u043d\u044c"
    ],
    "name:slk_x_preferred":[
        "Campagne"
    ],
    "name:spa_x_preferred":[
        "Campagne"
    ],
    "name:swe_x_preferred":[
        "Campagne"
    ],
    "name:ukr_x_preferred":[
        "\u041a\u0430\u043c\u043f\u0430\u043d\u044c"
    ],
    "name:uzb_x_preferred":[
        "Kampaniya"
    ],
    "wof:name":"Campagne",
    "wof:placetype":"locality",
    "wof:population":77
},
  "geometry": {"coordinates":[12.47135,45.72462],"type":"Point"}
}