{
  "type": "Feature",
  "properties": {
    "gn:admin1_code":"20",
    "gn:admin2_code":"TV",
    "gn:admin3_code":"26058.0",
    "gn:asciiname":"Campagne",
    "gn:country_code":"IT",
    "gn:dem":11,
    "gn:feature_class":"P",
    "gn:feature_code":"PPL",
    "gn:name":"Campagne",
    "gn:population":77,
    "gn:timezone":"Europe/Rome",
    "iso:country":"IT",
    "wof:name":"Campagne",
    "wof:placetype":"locality",
    "wof:population":77
},
  "geometry": {"coordinates":[12.47135,45.72462],"type":"Point"}
}