{
  "type": "Feature",
  "properties": {
    "gn:admin1_code":"20.0",
    "gn:admin2_code":"VI",
    "gn:admin3_code":"24072.0",
    "gn:asciiname":"Lovati",
    "gn:country_code":"IT",
    "gn:dem":511,
    "gn:feature_class":"P",
    "gn:feature_code":"PPL",
    "gn:name":"Lovati",
    "gn:population":11,
    "gn:timezone":"Europe/Rome",
    "iso:country":"IT",
    "wof:name":"Lovati",
    "wof:placetype":"locality",
    "wof:population":11
},
  "geometry": {"coordinates":[11.30457,45.56956],"type":"Point"}
}