{
  "type": "Feature",
  "properties": {
    "gn:admin1_code":"20.0",
    "gn:admin2_code":"VE",
    "gn:admin3_code":"27025.0",
    "gn:asciiname":"Lazzaretto",
    "gn:country_code":"IT",
    "gn:dem":0,
    "gn:elevation":"1.0",
    "gn:feature_class":"P",
    "gn:feature_code":"PPL",
    "gn:name":"Lazzaretto",
    "gn:population":96,
    "gn:timezone":"Europe/Rome",
    "iso:country":"IT",
    "wof:name":"Lazzaretto",
    "wof:placetype":"locality",
    "wof:population":96
},
  "geometry": {"coordinates":[12.53745,45.60506],"type":"Point"}
}