{
  "type": "Feature",
  "properties": {
    "iso:country":"IT",
    "wof:name":"Mantingnano",
    "wof:placetype":"neighbourhood"
},
  "geometry": {"coordinates":[11.17818575918387,43.78165943877737],"type":"Point"}
}