{
  "type": "Feature",
  "properties": {
    "gn:admin1_code":"16.0",
    "gn:admin2_code":"MS",
    "gn:admin3_code":"45017.0",
    "gn:asciiname":"La Dolce",
    "gn:country_code":"IT",
    "gn:dem":754,
    "gn:feature_class":"P",
    "gn:feature_code":"PPLL",
    "gn:name":"La Dolce",
    "gn:population":4,
    "gn:timezone":"Europe/Rome",
    "iso:country":"IT",
    "wof:name":"La Dolce",
    "wof:placetype":"locality",
    "wof:population":4
},
  "geometry": {"coordinates":[9.77365,44.33855],"type":"Point"}
}