{
  "type": "Feature",
  "properties": {
    "gn:admin1_code":"5",
    "gn:admin2_code":"PR",
    "gn:admin3_code":"34002.0",
    "gn:asciiname":"Bre",
    "gn:country_code":"IT",
    "gn:dem":664,
    "gn:feature_class":"P",
    "gn:feature_code":"PPL",
    "gn:name":"Bre",
    "gn:population":21,
    "gn:timezone":"Europe/Rome",
    "iso:country":"IT",
    "wof:name":"Bre",
    "wof:placetype":"locality",
    "wof:population":21
},
  "geometry": {"coordinates":[9.77557,44.59251],"type":"Point"}
}