{
  "type": "Feature",
  "properties": {
    "gn:admin1_code":"5.0",
    "gn:admin2_code":"PC",
    "gn:admin3_code":"33016.0",
    "gn:asciiname":"Scabiazza",
    "gn:cc2":"IT",
    "gn:country_code":"IT",
    "gn:dem":465,
    "gn:feature_class":"P",
    "gn:feature_code":"PPL",
    "gn:name":"Scabiazza",
    "gn:population":6,
    "gn:timezone":"Europe/Rome",
    "iso:country":"IT",
    "name:und_x_variant":[
        "Scabbiazza",
        "Scabiazza"
    ],
    "wof:name":"Scabiazza",
    "wof:placetype":"locality",
    "wof:population":6
},
  "geometry": {"coordinates":[9.43404,44.79491],"type":"Point"}
}