{
  "type": "Feature",
  "properties": {
    "gn:admin1_code":"20",
    "gn:admin2_code":"VE",
    "gn:admin3_code":"27042.0",
    "gn:asciiname":"Boaria Baroffio",
    "gn:country_code":"IT",
    "gn:dem":0,
    "gn:feature_class":"P",
    "gn:feature_code":"PPL",
    "gn:name":"Boaria Baroffio",
    "gn:population":238,
    "gn:timezone":"Europe/Rome",
    "iso:country":"IT",
    "wof:name":"Boaria Baroffio",
    "wof:placetype":"locality",
    "wof:population":238
},
  "geometry": {"coordinates":[12.3088,45.5053],"type":"Point"}
}