{
  "type": "Feature",
  "properties": {
    "gn:admin1_code":"9.0",
    "gn:admin2_code":"PV",
    "gn:admin3_code":"18166.0",
    "gn:asciiname":"Montacuto",
    "gn:country_code":"IT",
    "gn:dem":529,
    "gn:feature_class":"P",
    "gn:feature_code":"PPL",
    "gn:name":"Montacuto",
    "gn:population":16,
    "gn:timezone":"Europe/Rome",
    "iso:country":"IT",
    "name:ara_x_preferred":[
        "\u0645\u0648\u0646\u062a\u0627\u0643\u0648\u062a\u0648"
    ],
    "name:azb_x_preferred":[
        "\u0645\u0648\u0646\u062a\u0627\u06a9\u0648\u062a\u0648"
    ],
    "name:bel_x_preferred":[
        "\u041c\u0430\u043d\u0442\u0430\u043a\u0443\u0442\u0430"
    ],
    "name:bul_x_preferred":[
        "\u041c\u043e\u043d\u0442\u0430\u043a\u0443\u0442\u043e"
    ],
    "name:cat_x_preferred":[
        "Montacuto"
    ],
    "name:ceb_x_preferred":[
        "Montacuto"
    ],
    "name:deu_x_preferred":[
        "Montacuto"
    ],
    "name:epo_x_preferred":[
        "Montacuto"
    ],
    "name:est_x_preferred":[
        "Montacuto"
    ],
    "name:eus_x_preferred":[
        "Montacuto"
    ],
    "name:fas_x_preferred":[
        "\u0645\u0648\u0646\u062a\u0627\u06a9\u0648\u062a\u0648"
    ],
    "name:fra_x_preferred":[
        "Montacuto"
    ],
    "name:hun_x_preferred":[
        "Montacuto"
    ],
    "name:hye_x_preferred":[
        "\u0544\u0578\u0576\u057f\u0561\u056f\u0578\u0582\u057f\u0578"
    ],
    "name:ind_x_preferred":[
        "Montacuto"
    ],
    "name:ita_x_preferred":[
        "Montacuto"
    ],
    "name:jpn_x_preferred":[
        "\u30e2\u30f3\u30bf\u30af\u30fc\u30c8"
    ],
    "name:kaz_x_preferred":[
        "\u041c\u043e\u043d\u0442\u0430\u043a\u0443\u0442\u043e"
    ],
    "name:lat_x_preferred":[
        "Mons Acutus"
    ],
    "name:lmo_x_preferred":[
        "Munteigu"
    ],
    "name:msa_x_preferred":[
        "Montacuto"
    ],
    "name:nap_x_preferred":[
        "Montacuto"
    ],
    "name:nld_x_preferred":[
        "Montacuto"
    ],
    "name:pms_x_preferred":[
        "Mont\u00e8igo"
    ],
    "name:pol_x_preferred":[
        "Montacuto"
    ],
    "name:por_x_preferred":[
        "Montacuto"
    ],
    "name:ron_x_preferred":[
        "Montacuto"
    ],
    "name:rus_x_preferred":[
        "\u041c\u043e\u043d\u0442\u0430\u043a\u0443\u0442\u043e"
    ],
    "name:scn_x_preferred":[
        "Montacuto"
    ],
    "name:spa_x_preferred":[
        "Montacuto"
    ],
    "name:srp_x_preferred":[
        "\u041c\u043e\u043d\u0442\u0430\u043a\u0443\u0442\u043e"
    ],
    "name:tgl_x_preferred":[
        "Montacuto"
    ],
    "name:ukr_x_preferred":[
        "\u041c\u043e\u043d\u0442\u0430\u043a\u0443\u0442\u043e"
    ],
    "name:uzb_x_preferred":[
        "Montacuto"
    ],
    "name:vie_x_preferred":[
        "Montacuto"
    ],
    "name:vol_x_preferred":[
        "Montacuto"
    ],
    "name:war_x_preferred":[
        "Montacuto"
    ],
    "name:zho_x_preferred":[
        "\u8499\u5854\u5e93\u6258"
    ],
    "wof:name":"Montacuto",
    "wof:placetype":"locality",
    "wof:population":16
},
  "geometry": {"coordinates":[9.20423,44.8951],"type":"Point"}
}