{
  "type": "Feature",
  "properties": {
    "gn:admin1_code":"9.0",
    "gn:admin2_code":"PV",
    "gn:admin3_code":"18166.0",
    "gn:asciiname":"Montacuto",
    "gn:country_code":"IT",
    "gn:dem":529,
    "gn:feature_class":"P",
    "gn:feature_code":"PPL",
    "gn:name":"Montacuto",
    "gn:population":16,
    "gn:timezone":"Europe/Rome",
    "iso:country":"IT",
    "wof:name":"Montacuto",
    "wof:placetype":"locality",
    "wof:population":16
},
  "geometry": {"coordinates":[9.20423,44.8951],"type":"Point"}
}