{
  "type": "Feature",
  "properties": {
    "gn:admin1_code":"5.0",
    "gn:admin2_code":"PR",
    "gn:admin3_code":"34038.0",
    "gn:asciiname":"Lesignano Palmia",
    "gn:country_code":"IT",
    "gn:dem":464,
    "gn:feature_class":"P",
    "gn:feature_code":"PPL",
    "gn:name":"Lesignano Palmia",
    "gn:population":91,
    "gn:timezone":"Europe/Rome",
    "iso:country":"IT",
    "wof:name":"Lesignano Palmia",
    "wof:placetype":"locality",
    "wof:population":91
},
  "geometry": {"coordinates":[10.12137,44.62153],"type":"Point"}
}