{
  "type": "Feature",
  "properties": {
    "gn:admin1_code":"14.0",
    "gn:admin2_code":"SS",
    "gn:admin3_code":"90083.0",
    "gn:asciiname":"Marinella",
    "gn:country_code":"IT",
    "gn:dem":8,
    "gn:feature_class":"P",
    "gn:feature_code":"PPL",
    "gn:name":"Marinella",
    "gn:population":0,
    "gn:timezone":"Europe/Rome",
    "iso:country":"IT",
    "name:bul_x_preferred":[
        "\u041c\u0430\u0440\u0438\u043d\u0435\u043b\u0430"
    ],
    "name:deu_x_preferred":[
        "Marinella"
    ],
    "name:ell_x_preferred":[
        "\u039c\u03b1\u03c1\u03b9\u03bd\u03ad\u03bb\u03bb\u03b1"
    ],
    "name:est_x_preferred":[
        "Marin\u00e9lla"
    ],
    "name:fra_x_preferred":[
        "Marinella"
    ],
    "name:kor_x_preferred":[
        "\ub9c8\ub9ac\ub12c\ub77c"
    ],
    "name:lit_x_preferred":[
        "Marinella"
    ],
    "name:nld_x_preferred":[
        "Marinella"
    ],
    "name:pol_x_preferred":[
        "Marinella"
    ],
    "name:por_x_preferred":[
        "Marinella"
    ],
    "name:rus_x_preferred":[
        "\u041c\u0430\u0440\u0438\u043d\u0435\u043b\u043b\u0430"
    ],
    "name:spa_x_preferred":[
        "Marinella"
    ],
    "name:swe_x_preferred":[
        "Marinella"
    ],
    "name:tur_x_preferred":[
        "Marinella"
    ],
    "name:ukr_x_preferred":[
        "\u041c\u0430\u0440\u0456\u043d\u0435\u043b\u043b\u0430"
    ],
    "wof:name":"Marinella",
    "wof:placetype":"locality"
},
  "geometry": {"coordinates":[9.56229,41.00125],"type":"Point"}
}