{
  "type": "Feature",
  "properties": {
    "gn:admin1_code":"1",
    "gn:admin2_code":"PE",
    "gn:admin3_code":"68014.0",
    "gn:asciiname":"Santanello",
    "gn:country_code":"IT",
    "gn:dem":764,
    "gn:feature_class":"P",
    "gn:feature_code":"PPL",
    "gn:name":"Santanello",
    "gn:population":16,
    "gn:timezone":"Europe/Rome",
    "iso:country":"IT",
    "wof:name":"Santanello",
    "wof:placetype":"locality",
    "wof:population":16
},
  "geometry": {"coordinates":[13.87219,42.39362],"type":"Point"}
}