{
  "type": "Feature",
  "properties": {
    "gn:admin1_code":"16.0",
    "gn:admin2_code":"FI",
    "gn:admin3_code":"48004.0",
    "gn:asciiname":"Asilo Poggiolo",
    "gn:country_code":"IT",
    "gn:dem":261,
    "gn:feature_class":"P",
    "gn:feature_code":"PPLL",
    "gn:name":"Asilo Poggiolo",
    "gn:population":5,
    "gn:timezone":"Europe/Rome",
    "iso:country":"IT",
    "wof:name":"Asilo Poggiolo",
    "wof:placetype":"locality",
    "wof:population":5
},
  "geometry": {"coordinates":[11.3739,43.90829],"type":"Point"}
}