{
  "type": "Feature",
  "properties": {
    "gn:admin1_code":"4",
    "gn:admin2_code":"AV",
    "gn:admin3_code":"64052.0",
    "gn:asciiname":"Frascino",
    "gn:country_code":"IT",
    "gn:dem":536,
    "gn:feature_class":"P",
    "gn:feature_code":"PPL",
    "gn:name":"Frascino",
    "gn:population":30,
    "gn:timezone":"Europe/Rome",
    "iso:country":"IT",
    "wof:name":"Frascino",
    "wof:placetype":"locality",
    "wof:population":30
},
  "geometry": {"coordinates":[15.05103,41.20291],"type":"Point"}
}