{
  "type": "Feature",
  "properties": {
    "gn:admin1_code":"12.0",
    "gn:admin2_code":"CN",
    "gn:admin3_code":"4155.0",
    "gn:asciiname":"Toria",
    "gn:country_code":"IT",
    "gn:dem":1324,
    "gn:feature_class":"P",
    "gn:feature_code":"PPLL",
    "gn:name":"Toria",
    "gn:population":3,
    "gn:timezone":"Europe/Rome",
    "iso:country":"IT",
    "wof:name":"Toria",
    "wof:placetype":"locality",
    "wof:population":3
},
  "geometry": {"coordinates":[7.78971,44.14061],"type":"Point"}
}