{
  "type": "Feature",
  "properties": {
    "gn:admin1_code":"9",
    "gn:admin2_code":"BS",
    "gn:admin3_code":"17043.0",
    "gn:asciiname":"Osteria Finiletti",
    "gn:country_code":"IT",
    "gn:dem":114,
    "gn:feature_class":"P",
    "gn:feature_code":"PPL",
    "gn:name":"Osteria Finiletti",
    "gn:population":32,
    "gn:timezone":"Europe/Rome",
    "iso:country":"IT",
    "wof:name":"Osteria Finiletti",
    "wof:placetype":"locality",
    "wof:population":32
},
  "geometry": {"coordinates":[10.29334,45.45533],"type":"Point"}
}