{
  "type": "Feature",
  "properties": {
    "gn:admin1_code":"16",
    "gn:admin2_code":"LU",
    "gn:admin3_code":"46028.0",
    "gn:asciiname":"Giustagnana",
    "gn:country_code":"IT",
    "gn:dem":337,
    "gn:feature_class":"P",
    "gn:feature_code":"PPL",
    "gn:name":"Giustagnana",
    "gn:population":103,
    "gn:timezone":"Europe/Rome",
    "iso:country":"IT",
    "wof:name":"Giustagnana",
    "wof:placetype":"locality",
    "wof:population":103
},
  "geometry": {"coordinates":[10.23107,44.00305],"type":"Point"}
}