{
  "type": "Feature",
  "properties": {
    "iso:country":"IT",
    "name:ceb_x_preferred":[
        "Galleno"
    ],
    "name:eng_x_preferred":[
        "Galleno"
    ],
    "name:fra_x_preferred":[
        "Galleno"
    ],
    "name:hun_x_preferred":[
        "Galleno"
    ],
    "name:ita_x_preferred":[
        "Galleno"
    ],
    "name:lmo_x_preferred":[
        "G\u00e0len"
    ],
    "name:nld_x_preferred":[
        "Galleno"
    ],
    "name:srp_x_preferred":[
        "Galleno"
    ],
    "qs_pg:aaroncc":"IT",
    "qs_pg:name":"Galleno",
    "qs_pg:name_adm0":"Italia",
    "qs_pg:name_adm1":"Lombardia",
    "qs_pg:photos":17,
    "qs_pg:photos_1k":3,
    "qs_pg:photos_9k":1,
    "qs_pg:photos_9r":1,
    "qs_pg:photos_all":17,
    "qs_pg:photos_sr":1,
    "qs_pg:pop_sr":0,
    "qs_pg:qs_pg_placetype":"locality",
    "qs_pg:qs_pg_placetype_gp":"Town",
    "qs_pg:woe_adm0":23424853,
    "woe:adm0_id":23424853,
    "woe:name_adm0":"Italia",
    "woe:name_adm1":"Lombardia",
    "woe:placetype":"Town",
    "wof:name":"Galleno",
    "wof:placetype":"locality"
},
  "geometry": {"coordinates":[10.232305,46.166932],"type":"Point"}
}