{
  "type": "Feature",
  "properties": {
    "gn:admin1_code":"5",
    "gn:admin2_code":"PR",
    "gn:admin3_code":"34027.0",
    "gn:asciiname":"Valera",
    "gn:country_code":"IT",
    "gn:dem":63,
    "gn:feature_class":"P",
    "gn:feature_code":"PPL",
    "gn:name":"Valera",
    "gn:population":23,
    "gn:timezone":"Europe/Rome",
    "iso:country":"IT",
    "name:ara_x_preferred":[
        "\u0641\u0627\u0644\u064a\u0631\u0627"
    ],
    "name:deu_x_preferred":[
        "Valera"
    ],
    "name:epo_x_preferred":[
        "Valera"
    ],
    "name:fra_x_preferred":[
        "Valera"
    ],
    "name:ita_x_preferred":[
        "Valera"
    ],
    "name:kat_x_preferred":[
        "\u10d5\u10d0\u10da\u10d4\u10e0\u10d0"
    ],
    "name:kor_x_preferred":[
        "\ubc1c\ub808\ub77c"
    ],
    "name:lit_x_preferred":[
        "Valera"
    ],
    "name:nld_x_preferred":[
        "Valera"
    ],
    "name:pol_x_preferred":[
        "Valera"
    ],
    "name:por_x_preferred":[
        "Valera"
    ],
    "name:rus_x_preferred":[
        "\u0412\u0430\u043b\u0435\u0440\u0430"
    ],
    "name:spa_x_preferred":[
        "Valera"
    ],
    "name:swe_x_preferred":[
        "Valera"
    ],
    "name:szl_x_preferred":[
        "Valera"
    ],
    "name:tat_x_preferred":[
        "\u0412\u0430\u043b\u0435\u0440\u0430"
    ],
    "name:urd_x_preferred":[
        "\u0648\u0627\u0644\u06cc\u0631\u0627"
    ],
    "name:war_x_preferred":[
        "Valera"
    ],
    "name:zho_x_preferred":[
        "\u5df4\u83b1\u62c9"
    ],
    "wof:name":"Valera",
    "wof:placetype":"locality",
    "wof:population":23
},
  "geometry": {"coordinates":[10.28422,44.79933],"type":"Point"}
}