{
  "type": "Feature",
  "properties": {
    "gn:admin1_code":"16.0",
    "gn:admin2_code":"FI",
    "gn:admin3_code":"48036.0",
    "gn:asciiname":"Troghi",
    "gn:country_code":"IT",
    "gn:dem":263,
    "gn:elevation":"263.0",
    "gn:feature_class":"P",
    "gn:feature_code":"PPL",
    "gn:name":"Troghi",
    "gn:population":871,
    "gn:timezone":"Europe/Rome",
    "iso:country":"IT",
    "wof:name":"Troghi",
    "wof:placetype":"locality",
    "wof:population":871
},
  "geometry": {"coordinates":[11.39557,43.71479],"type":"Point"}
}