{
  "type": "Feature",
  "properties": {
    "gn:admin1_code":"7",
    "gn:admin2_code":"RI",
    "gn:admin3_code":"57007.0",
    "gn:asciiname":"San Francesco Vecchio",
    "gn:country_code":"IT",
    "gn:dem":845,
    "gn:feature_class":"P",
    "gn:feature_code":"PPL",
    "gn:name":"San Francesco Vecchio",
    "gn:population":65,
    "gn:timezone":"Europe/Rome",
    "iso:country":"IT",
    "wof:name":"San Francesco Vecchio",
    "wof:placetype":"locality",
    "wof:population":65
},
  "geometry": {"coordinates":[13.28173,42.19168],"type":"Point"}
}