{
  "type": "Feature",
  "properties": {
    "gn:admin1_code":"3",
    "gn:admin2_code":"KR",
    "gn:admin3_code":"101025.0",
    "gn:asciiname":"Marina di Strongoli",
    "gn:country_code":"IT",
    "gn:dem":12,
    "gn:feature_class":"P",
    "gn:feature_code":"PPL",
    "gn:name":"Marina di Strongoli",
    "gn:population":42,
    "gn:timezone":"Europe/Rome",
    "iso:country":"IT",
    "wof:name":"Marina di Strongoli",
    "wof:placetype":"locality",
    "wof:population":42
},
  "geometry": {"coordinates":[17.10349,39.22826],"type":"Point"}
}