{
  "type": "Feature",
  "properties": {
    "gn:admin1_code":"9",
    "gn:admin2_code":"CO",
    "gn:admin3_code":"13215.0",
    "gn:asciiname":"Cascina Piella",
    "gn:country_code":"IT",
    "gn:dem":438,
    "gn:feature_class":"P",
    "gn:feature_code":"PPL",
    "gn:name":"Cascina Piella",
    "gn:population":11,
    "gn:timezone":"Europe/Rome",
    "iso:country":"IT",
    "wof:name":"Cascina Piella",
    "wof:placetype":"locality",
    "wof:population":11
},
  "geometry": {"coordinates":[8.92564,45.79017],"type":"Point"}
}