{
  "type": "Feature",
  "properties": {
    "gn:admin1_code":"20.0",
    "gn:admin2_code":"TV",
    "gn:admin3_code":"26013.0",
    "gn:asciiname":"Grande",
    "gn:country_code":"IT",
    "gn:dem":52,
    "gn:feature_class":"P",
    "gn:feature_code":"PPL",
    "gn:name":"Grande",
    "gn:population":475,
    "gn:timezone":"Europe/Rome",
    "iso:country":"IT",
    "name:ceb_x_preferred":[
        "Grande"
    ],
    "name:deu_x_preferred":[
        "Grande"
    ],
    "name:fra_x_preferred":[
        "Grande"
    ],
    "name:fry_x_preferred":[
        "Grande"
    ],
    "name:glg_x_preferred":[
        "Grande"
    ],
    "name:ita_x_preferred":[
        "Grande"
    ],
    "name:jpn_x_preferred":[
        "\u30b0\u30e9\u30f3\u30c7"
    ],
    "name:nld_x_preferred":[
        "Grande"
    ],
    "name:pol_x_preferred":[
        "Grande"
    ],
    "name:por_x_preferred":[
        "Grande"
    ],
    "name:ron_x_preferred":[
        "Grande"
    ],
    "name:rus_x_preferred":[
        "\u0413\u0440\u0430\u043d\u0434\u0435\u043d"
    ],
    "name:slk_x_preferred":[
        "Grande"
    ],
    "name:spa_x_preferred":[
        "Grande"
    ],
    "name:srp_x_preferred":[
        "Grande"
    ],
    "name:swe_x_preferred":[
        "Grande"
    ],
    "wof:name":"Grande",
    "wof:placetype":"locality",
    "wof:population":475
},
  "geometry": {"coordinates":[11.86033,45.68626],"type":"Point"}
}