{
  "type": "Feature",
  "properties": {
    "gn:admin1_code":"20.0",
    "gn:admin2_code":"TV",
    "gn:admin3_code":"26013.0",
    "gn:asciiname":"Grande",
    "gn:country_code":"IT",
    "gn:dem":52,
    "gn:feature_class":"P",
    "gn:feature_code":"PPL",
    "gn:name":"Grande",
    "gn:population":475,
    "gn:timezone":"Europe/Rome",
    "iso:country":"IT",
    "wof:name":"Grande",
    "wof:placetype":"locality",
    "wof:population":475
},
  "geometry": {"coordinates":[11.86033,45.68626],"type":"Point"}
}