{
  "type": "Feature",
  "properties": {
    "gn:admin1_code":"9",
    "gn:admin2_code":"BS",
    "gn:admin3_code":"17151.0",
    "gn:asciiname":"Le Benedette",
    "gn:country_code":"IT",
    "gn:dem":116,
    "gn:feature_class":"P",
    "gn:feature_code":"PPL",
    "gn:name":"Le Benedette",
    "gn:population":15,
    "gn:timezone":"Europe/Rome",
    "iso:country":"IT",
    "wof:name":"Le Benedette",
    "wof:placetype":"locality",
    "wof:population":15
},
  "geometry": {"coordinates":[10.60976,45.39593],"type":"Point"}
}