{
  "type": "Feature",
  "properties": {
    "gn:admin1_code":"7",
    "gn:admin2_code":"FR",
    "gn:admin3_code":"60015.0",
    "gn:asciiname":"Brocco",
    "gn:country_code":"IT",
    "gn:dem":518,
    "gn:feature_class":"P",
    "gn:feature_code":"PPL",
    "gn:name":"Brocco",
    "gn:population":37,
    "gn:timezone":"Europe/Rome",
    "iso:country":"IT",
    "wof:name":"Brocco",
    "wof:placetype":"locality",
    "wof:population":37
},
  "geometry": {"coordinates":[13.6457,41.70996],"type":"Point"}
}