{
  "type": "Feature",
  "properties": {
    "gn:admin1_code":"11",
    "gn:admin2_code":"IS",
    "gn:admin3_code":"94050.0",
    "gn:asciiname":"Corso Piemonte Seconda Traversa",
    "gn:country_code":"IT",
    "gn:dem":149,
    "gn:feature_class":"P",
    "gn:feature_code":"PPL",
    "gn:name":"Corso Piemonte Seconda Traversa",
    "gn:population":20,
    "gn:timezone":"Europe/Rome",
    "iso:country":"IT",
    "wof:name":"Corso Piemonte Seconda Traversa",
    "wof:placetype":"locality",
    "wof:population":20
},
  "geometry": {"coordinates":[14.09103,41.42388],"type":"Point"}
}