{
  "type": "Feature",
  "properties": {
    "gn:admin1_code":"20.0",
    "gn:admin2_code":"VR",
    "gn:admin3_code":"23040.0",
    "gn:asciiname":"Brognoligo-Buttapietra",
    "gn:country_code":"IT",
    "gn:dem":34,
    "gn:feature_class":"P",
    "gn:feature_code":"PPL",
    "gn:name":"Brognoligo-Buttapietra",
    "gn:population":57,
    "gn:timezone":"Europe/Rome",
    "iso:country":"IT",
    "wof:name":"Brognoligo-Buttapietra",
    "wof:placetype":"locality",
    "wof:population":57
},
  "geometry": {"coordinates":[11.00818,45.33254],"type":"Point"}
}