{
  "type": "Feature",
  "properties": {
    "gn:admin1_code":"12",
    "gn:admin2_code":"TO",
    "gn:admin3_code":"1175.0",
    "gn:asciiname":"Casermette",
    "gn:country_code":"IT",
    "gn:dem":1073,
    "gn:feature_class":"P",
    "gn:feature_code":"PPL",
    "gn:name":"Casermette",
    "gn:population":13,
    "gn:timezone":"Europe/Rome",
    "iso:country":"IT",
    "wof:name":"Casermette",
    "wof:placetype":"locality",
    "wof:population":13
},
  "geometry": {"coordinates":[6.83389,45.04578],"type":"Point"}
}