{
  "type": "Feature",
  "properties": {
    "gn:admin1_code":"15.0",
    "gn:admin2_code":"ME",
    "gn:admin3_code":"83065.0",
    "gn:asciiname":"Rocchenere",
    "gn:country_code":"IT",
    "gn:dem":85,
    "gn:feature_class":"P",
    "gn:feature_code":"PPL",
    "gn:name":"Rocchenere",
    "gn:population":701,
    "gn:timezone":"Europe/Rome",
    "iso:country":"IT",
    "wof:name":"Rocchenere",
    "wof:placetype":"locality",
    "wof:population":701
},
  "geometry": {"coordinates":[15.37618,37.97428],"type":"Point"}
}