{
  "type": "Feature",
  "properties": {
    "gn:admin1_code":"12",
    "gn:admin2_code":"AL",
    "gn:admin3_code":"6131.0",
    "gn:asciiname":"Strada Madonna della Neve",
    "gn:country_code":"IT",
    "gn:dem":90,
    "gn:feature_class":"P",
    "gn:feature_code":"PPL",
    "gn:name":"Strada Madonna della Neve",
    "gn:population":15,
    "gn:timezone":"Europe/Rome",
    "iso:country":"IT",
    "wof:name":"Strada Madonna della Neve",
    "wof:placetype":"locality",
    "wof:population":15
},
  "geometry": {"coordinates":[8.60054,45.06882],"type":"Point"}
}