{
  "type": "Feature",
  "properties": {
    "gn:admin1_code":"9.0",
    "gn:admin2_code":"MI",
    "gn:admin3_code":"15050.0",
    "gn:asciiname":"Cascina Calnago",
    "gn:country_code":"IT",
    "gn:dem":88,
    "gn:feature_class":"P",
    "gn:feature_code":"PPL",
    "gn:name":"Cascina Calnago",
    "gn:population":16,
    "gn:timezone":"Europe/Rome",
    "iso:country":"IT",
    "wof:name":"Cascina Calnago",
    "wof:placetype":"locality",
    "wof:population":16
},
  "geometry": {"coordinates":[9.29293,45.33107],"type":"Point"}
}