{
  "type": "Feature",
  "properties": {
    "gn:admin1_code":"9",
    "gn:admin2_code":"MN",
    "gn:admin3_code":"20026.0",
    "gn:asciiname":"Maglio",
    "gn:country_code":"IT",
    "gn:dem":27,
    "gn:feature_class":"P",
    "gn:feature_code":"PPL",
    "gn:name":"Maglio",
    "gn:population":63,
    "gn:timezone":"Europe/Rome",
    "iso:country":"IT",
    "wof:name":"Maglio",
    "wof:placetype":"locality",
    "wof:population":63
},
  "geometry": {"coordinates":[10.69789,45.21641],"type":"Point"}
}