{
  "type": "Feature",
  "properties": {
    "gn:admin1_code":"1",
    "gn:admin2_code":"PE",
    "gn:admin3_code":"68018.0",
    "gn:asciiname":"Quattrostrade",
    "gn:country_code":"IT",
    "gn:dem":87,
    "gn:feature_class":"P",
    "gn:feature_code":"PPL",
    "gn:name":"Quattrostrade",
    "gn:population":122,
    "gn:timezone":"Europe/Rome",
    "iso:country":"IT",
    "wof:name":"Quattrostrade",
    "wof:placetype":"locality",
    "wof:population":122
},
  "geometry": {"coordinates":[13.99204,42.49396],"type":"Point"}
}