{
  "type": "Feature",
  "properties": {
    "gn:admin1_code":"8.0",
    "gn:admin2_code":"IM",
    "gn:admin3_code":"8008.0",
    "gn:asciiname":"Borghetto San Nicolo",
    "gn:country_code":"IT",
    "gn:dem":121,
    "gn:elevation":"90.0",
    "gn:feature_class":"P",
    "gn:feature_code":"PPL",
    "gn:name":"Borghetto San Nicol\u00f2",
    "gn:population":341,
    "gn:timezone":"Europe/Rome",
    "iso:country":"IT",
    "wof:name":"Borghetto San Nicolo",
    "wof:placetype":"locality",
    "wof:population":341
},
  "geometry": {"coordinates":[7.66125,43.80406],"type":"Point"}
}