{
  "type": "Feature",
  "properties": {
    "gn:admin1_code":"16.0",
    "gn:admin2_code":"PI",
    "gn:admin3_code":"50031.0",
    "gn:asciiname":"Cafaggiareggi",
    "gn:country_code":"IT",
    "gn:dem":2,
    "gn:feature_class":"P",
    "gn:feature_code":"PPL",
    "gn:name":"Cafaggiareggi",
    "gn:population":428,
    "gn:timezone":"Europe/Rome",
    "iso:country":"IT",
    "wof:name":"Cafaggiareggi",
    "wof:placetype":"locality",
    "wof:population":428
},
  "geometry": {"coordinates":[10.36021,43.7728],"type":"Point"}
}