{
  "type": "Feature",
  "properties": {
    "gn:admin1_code":"20",
    "gn:admin2_code":"VR",
    "gn:admin3_code":"23056.0",
    "gn:asciiname":"Casotti",
    "gn:country_code":"IT",
    "gn:dem":22,
    "gn:feature_class":"P",
    "gn:feature_code":"PPL",
    "gn:name":"Casotti",
    "gn:population":58,
    "gn:timezone":"Europe/Rome",
    "iso:country":"IT",
    "wof:name":"Casotti",
    "wof:placetype":"locality",
    "wof:population":58
},
  "geometry": {"coordinates":[11.17399,45.32178],"type":"Point"}
}