{
  "type": "Feature",
  "properties": {
    "gn:admin1_code":"16.0",
    "gn:admin2_code":"FI",
    "gn:admin3_code":"48005.0",
    "gn:asciiname":"Legri",
    "gn:country_code":"IT",
    "gn:dem":198,
    "gn:elevation":"196.0",
    "gn:feature_class":"P",
    "gn:feature_code":"PPL",
    "gn:name":"Legri",
    "gn:population":294,
    "gn:timezone":"Europe/Rome",
    "iso:country":"IT",
    "wof:name":"Legri",
    "wof:placetype":"locality",
    "wof:population":294
},
  "geometry": {"coordinates":[11.22474,43.91448],"type":"Point"}
}