{
  "type": "Feature",
  "properties": {
    "gn:admin1_code":"11.0",
    "gn:admin2_code":"CB",
    "gn:admin3_code":"70002.0",
    "gn:asciiname":"Cappella",
    "gn:country_code":"IT",
    "gn:dem":657,
    "gn:feature_class":"P",
    "gn:feature_code":"PPL",
    "gn:name":"Cappella",
    "gn:population":29,
    "gn:timezone":"Europe/Rome",
    "iso:country":"IT",
    "name:ceb_x_preferred":[
        "Cappella"
    ],
    "name:deu_x_preferred":[
        "Cappella"
    ],
    "name:fra_x_preferred":[
        "Cappella"
    ],
    "name:ita_x_preferred":[
        "Cappella"
    ],
    "name:nld_x_preferred":[
        "Cappella"
    ],
    "name:por_x_preferred":[
        "Cappella"
    ],
    "name:srp_x_preferred":[
        "Cappella"
    ],
    "name:swe_x_preferred":[
        "Cappella"
    ],
    "wof:name":"Cappella",
    "wof:placetype":"locality",
    "wof:population":29
},
  "geometry": {"coordinates":[14.54284,41.5194],"type":"Point"}
}