{
  "type": "Feature",
  "properties": {
    "gn:admin1_code":"15",
    "gn:admin2_code":"CT",
    "gn:admin3_code":"87013.0",
    "gn:asciiname":"Franchetto",
    "gn:country_code":"IT",
    "gn:dem":217,
    "gn:feature_class":"P",
    "gn:feature_code":"PPL",
    "gn:name":"Franchetto",
    "gn:population":56,
    "gn:timezone":"Europe/Rome",
    "iso:country":"IT",
    "wof:name":"Franchetto",
    "wof:placetype":"locality",
    "wof:population":56
},
  "geometry": {"coordinates":[14.71071,37.48889000000001],"type":"Point"}
}