{
  "type": "Feature",
  "properties": {
    "gn:admin1_code":"6.0",
    "gn:admin2_code":"PN",
    "gn:admin3_code":"93044.0",
    "gn:asciiname":"Baseglia",
    "gn:country_code":"IT",
    "gn:dem":146,
    "gn:feature_class":"P",
    "gn:feature_code":"PPL",
    "gn:name":"Baseglia",
    "gn:population":0,
    "gn:timezone":"Europe/Rome",
    "iso:country":"IT",
    "wof:name":"Baseglia",
    "wof:placetype":"locality"
},
  "geometry": {"coordinates":[12.9025,46.12889000000001],"type":"Point"}
}