{
  "type": "Feature",
  "properties": {
    "gn:admin1_code":"12.0",
    "gn:admin2_code":"CN",
    "gn:admin3_code":"4165.0",
    "gn:asciiname":"Stazione Margarita",
    "gn:country_code":"IT",
    "gn:dem":468,
    "gn:feature_class":"P",
    "gn:feature_code":"PPL",
    "gn:name":"Stazione Margarita",
    "gn:population":30,
    "gn:timezone":"Europe/Rome",
    "iso:country":"IT",
    "wof:name":"Stazione Margarita",
    "wof:placetype":"locality",
    "wof:population":30
},
  "geometry": {"coordinates":[7.68798,44.38025],"type":"Point"}
}