{
  "type": "Feature",
  "properties": {
    "gn:admin1_code":"5",
    "gn:admin2_code":"PR",
    "gn:admin3_code":"34022.0",
    "gn:asciiname":"Trincera",
    "gn:country_code":"IT",
    "gn:dem":849,
    "gn:feature_class":"P",
    "gn:feature_code":"PPL",
    "gn:name":"Trincera",
    "gn:population":34,
    "gn:timezone":"Europe/Rome",
    "iso:country":"IT",
    "wof:name":"Trincera",
    "wof:placetype":"locality",
    "wof:population":34
},
  "geometry": {"coordinates":[10.12189,44.40417],"type":"Point"}
}