{
  "type": "Feature",
  "properties": {
    "gn:admin1_code":"12",
    "gn:admin2_code":"TO",
    "gn:admin3_code":"1207.0",
    "gn:asciiname":"Valtorta",
    "gn:country_code":"IT",
    "gn:dem":433,
    "gn:feature_class":"P",
    "gn:feature_code":"PPL",
    "gn:name":"Valtorta",
    "gn:population":18,
    "gn:timezone":"Europe/Rome",
    "iso:country":"IT",
    "name:ceb_x_preferred":[
        "Valtorta"
    ],
    "name:deu_x_preferred":[
        "Valtorta"
    ],
    "name:fra_x_preferred":[
        "Valtorta"
    ],
    "name:ita_x_preferred":[
        "Valtorta"
    ],
    "name:pol_x_preferred":[
        "Valtorta"
    ],
    "name:srp_x_preferred":[
        "Valtorta"
    ],
    "name:swe_x_preferred":[
        "Valtorta"
    ],
    "wof:name":"Valtorta",
    "wof:placetype":"locality",
    "wof:population":18
},
  "geometry": {"coordinates":[7.61349,45.34572],"type":"Point"}
}