{
  "type": "Feature",
  "properties": {
    "gn:admin1_code":"15",
    "gn:admin2_code":"PA",
    "gn:admin3_code":"82035.0",
    "gn:asciiname":"Contrada de Simone",
    "gn:country_code":"IT",
    "gn:dem":41,
    "gn:feature_class":"P",
    "gn:feature_code":"PPL",
    "gn:name":"Contrada de Simone",
    "gn:population":34,
    "gn:timezone":"Europe/Rome",
    "iso:country":"IT",
    "wof:name":"Contrada de Simone",
    "wof:placetype":"locality",
    "wof:population":34
},
  "geometry": {"coordinates":[13.45592,38.08164],"type":"Point"}
}