{
  "type": "Feature",
  "properties": {
    "gn:admin1_code":"6",
    "gn:admin2_code":"UD",
    "gn:admin3_code":"30086.0",
    "gn:asciiname":"Loch-Specognis",
    "gn:country_code":"IT",
    "gn:dem":188,
    "gn:feature_class":"P",
    "gn:feature_code":"PPL",
    "gn:name":"Loch-Specognis",
    "gn:population":92,
    "gn:timezone":"Europe/Rome",
    "iso:country":"IT",
    "wof:name":"Loch-Specognis",
    "wof:placetype":"locality",
    "wof:population":92
},
  "geometry": {"coordinates":[13.47706,46.18041],"type":"Point"}
}