{
  "type": "Feature",
  "properties": {
    "gn:admin1_code":"13",
    "gn:admin2_code":"BA",
    "gn:admin3_code":"72017.0",
    "gn:asciiname":"Convento Immacolata",
    "gn:country_code":"IT",
    "gn:dem":361,
    "gn:feature_class":"P",
    "gn:feature_code":"PPLL",
    "gn:name":"Convento Immacolata",
    "gn:population":8,
    "gn:timezone":"Europe/Rome",
    "iso:country":"IT",
    "wof:name":"Convento Immacolata",
    "wof:placetype":"locality",
    "wof:population":8
},
  "geometry": {"coordinates":[17.18051,40.85959],"type":"Point"}
}