{
  "type": "Feature",
  "properties": {
    "gn:admin1_code":"12",
    "gn:admin2_code":"AL",
    "gn:admin3_code":"6026.0",
    "gn:asciiname":"Bonina",
    "gn:country_code":"IT",
    "gn:dem":172,
    "gn:feature_class":"P",
    "gn:feature_code":"PPL",
    "gn:name":"Bonina",
    "gn:population":34,
    "gn:timezone":"Europe/Rome",
    "iso:country":"IT",
    "wof:name":"Bonina",
    "wof:placetype":"locality",
    "wof:population":34
},
  "geometry": {"coordinates":[8.43683,45.03354],"type":"Point"}
}