{
  "type": "Feature",
  "properties": {
    "gn:admin1_code":"18.0",
    "gn:admin2_code":"PG",
    "gn:admin3_code":"54039.0",
    "gn:asciiname":"Rancolfo",
    "gn:country_code":"IT",
    "gn:dem":326,
    "gn:feature_class":"P",
    "gn:feature_code":"PPL",
    "gn:name":"Rancolfo",
    "gn:population":169,
    "gn:timezone":"Europe/Rome",
    "iso:country":"IT",
    "wof:name":"Rancolfo",
    "wof:placetype":"locality",
    "wof:population":169
},
  "geometry": {"coordinates":[12.42707,43.23971],"type":"Point"}
}