{
  "type": "Feature",
  "properties": {
    "gn:admin1_code":"3",
    "gn:admin2_code":"RC",
    "gn:admin3_code":"80036.0",
    "gn:asciiname":"Zipari",
    "gn:country_code":"IT",
    "gn:dem":463,
    "gn:feature_class":"P",
    "gn:feature_code":"PPL",
    "gn:name":"Zipari",
    "gn:population":124,
    "gn:timezone":"Europe/Rome",
    "iso:country":"IT",
    "wof:name":"Zipari",
    "wof:placetype":"locality",
    "wof:population":124
},
  "geometry": {"coordinates":[16.16597,38.29845],"type":"Point"}
}