{
  "type": "Feature",
  "properties": {
    "gn:admin1_code":"20",
    "gn:admin2_code":"PD",
    "gn:admin3_code":"28082.0",
    "gn:asciiname":"Da Fai",
    "gn:country_code":"IT",
    "gn:dem":7,
    "gn:feature_class":"P",
    "gn:feature_code":"PPL",
    "gn:name":"Da Fai",
    "gn:population":40,
    "gn:timezone":"Europe/Rome",
    "iso:country":"IT",
    "wof:name":"Da Fai",
    "wof:placetype":"locality",
    "wof:population":40
},
  "geometry": {"coordinates":[11.99811,45.35329],"type":"Point"}
}