{
  "type": "Feature",
  "properties": {
    "gn:admin1_code":"12",
    "gn:admin2_code":"AL",
    "gn:admin3_code":"6050.0",
    "gn:asciiname":"Sogliano",
    "gn:country_code":"IT",
    "gn:dem":268,
    "gn:feature_class":"P",
    "gn:feature_code":"PPL",
    "gn:name":"Sogliano",
    "gn:population":16,
    "gn:timezone":"Europe/Rome",
    "iso:country":"IT",
    "name:deu_x_preferred":[
        "Sogliano"
    ],
    "name:ita_x_preferred":[
        "Sogliano"
    ],
    "name:lat_x_preferred":[
        "Sullianum"
    ],
    "wof:name":"Sogliano",
    "wof:placetype":"locality",
    "wof:population":16
},
  "geometry": {"coordinates":[8.25421,45.07468],"type":"Point"}
}