{
  "type": "Feature",
  "properties": {
    "gn:admin1_code":"11.0",
    "gn:admin2_code":"IS",
    "gn:admin3_code":"94023.0",
    "gn:asciiname":"Castelromano",
    "gn:country_code":"IT",
    "gn:dem":642,
    "gn:elevation":"646.0",
    "gn:feature_class":"P",
    "gn:feature_code":"PPL",
    "gn:name":"Castelromano",
    "gn:population":515,
    "gn:timezone":"Europe/Rome",
    "iso:country":"IT",
    "wof:name":"Castelromano",
    "wof:placetype":"locality",
    "wof:population":515
},
  "geometry": {"coordinates":[14.19707,41.61874],"type":"Point"}
}