{
  "type": "Feature",
  "properties": {
    "gn:admin1_code":"9",
    "gn:admin2_code":"PV",
    "gn:admin3_code":"18124.0",
    "gn:asciiname":"Robecchina",
    "gn:country_code":"IT",
    "gn:dem":64,
    "gn:feature_class":"P",
    "gn:feature_code":"PPL",
    "gn:name":"Robecchina",
    "gn:population":37,
    "gn:timezone":"Europe/Rome",
    "iso:country":"IT",
    "wof:name":"Robecchina",
    "wof:placetype":"locality",
    "wof:population":37
},
  "geometry": {"coordinates":[9.14611,45.07321],"type":"Point"}
}