{
  "type": "Feature",
  "properties": {
    "gn:admin1_code":"9",
    "gn:admin2_code":"MN",
    "gn:admin3_code":"20022.0",
    "gn:asciiname":"Pomella",
    "gn:country_code":"IT",
    "gn:dem":20,
    "gn:feature_class":"P",
    "gn:feature_code":"PPL",
    "gn:name":"Pomella",
    "gn:population":35,
    "gn:timezone":"Europe/Rome",
    "iso:country":"IT",
    "wof:name":"Pomella",
    "wof:placetype":"locality",
    "wof:population":35
},
  "geometry": {"coordinates":[10.63816,44.97455],"type":"Point"}
}