{
  "type": "Feature",
  "properties": {
    "gn:admin1_code":"7",
    "gn:admin2_code":"RI",
    "gn:admin3_code":"57026.0",
    "gn:asciiname":"Colle della Fonte",
    "gn:country_code":"IT",
    "gn:dem":520,
    "gn:feature_class":"P",
    "gn:feature_code":"PPL",
    "gn:name":"Colle della Fonte",
    "gn:population":58,
    "gn:timezone":"Europe/Rome",
    "iso:country":"IT",
    "wof:name":"Colle della Fonte",
    "wof:placetype":"locality",
    "wof:population":58
},
  "geometry": {"coordinates":[12.69284,42.40113],"type":"Point"}
}