{
  "type": "Feature",
  "properties": {
    "gn:admin1_code":"20",
    "gn:admin2_code":"VI",
    "gn:admin3_code":"24107.0",
    "gn:asciiname":"Cavion",
    "gn:country_code":"IT",
    "gn:dem":441,
    "gn:feature_class":"P",
    "gn:feature_code":"PPL",
    "gn:name":"Cavion",
    "gn:population":48,
    "gn:timezone":"Europe/Rome",
    "iso:country":"IT",
    "wof:name":"Cavion",
    "wof:placetype":"locality",
    "wof:population":48
},
  "geometry": {"coordinates":[11.27507,45.72645],"type":"Point"}
}