{
  "type": "Feature",
  "properties": {
    "gn:admin1_code":"12",
    "gn:admin2_code":"BI",
    "gn:admin3_code":"96009.0",
    "gn:asciiname":"Canova-Governati-Viglieno",
    "gn:country_code":"IT",
    "gn:dem":721,
    "gn:feature_class":"P",
    "gn:feature_code":"PPL",
    "gn:name":"Canova-Governati-Viglieno",
    "gn:population":96,
    "gn:timezone":"Europe/Rome",
    "iso:country":"IT",
    "wof:name":"Canova-Governati-Viglieno",
    "wof:placetype":"locality",
    "wof:population":96
},
  "geometry": {"coordinates":[8.10263,45.63711],"type":"Point"}
}