{
  "type": "Feature",
  "properties": {
    "gn:elevation":250,
    "gn:population":1085,
    "iso:country":"IT",
    "name:bul_x_preferred":[
        "\u0422\u0440\u043e\u0432\u0438\u0433\u0438\u0430\u043d\u043e"
    ],
    "name:cat_x_preferred":[
        "Troviggiano"
    ],
    "name:ceb_x_preferred":[
        "Troviggiano"
    ],
    "name:ces_x_preferred":[
        "Troviggiano"
    ],
    "name:dan_x_preferred":[
        "Troviggiano"
    ],
    "name:eng_x_preferred":[
        "Troviggiano"
    ],
    "name:eus_x_preferred":[
        "Troviggiano"
    ],
    "name:fin_x_preferred":[
        "Troviggiano"
    ],
    "name:fra_x_preferred":[
        "Troviggiano"
    ],
    "name:ind_x_preferred":[
        "Troviggiano"
    ],
    "name:ita_x_preferred":[
        "Troviggiano"
    ],
    "name:nld_x_preferred":[
        "Troviggiano"
    ],
    "name:nno_x_preferred":[
        "Troviggiano"
    ],
    "name:nob_x_preferred":[
        "Troviggiano"
    ],
    "name:oci_x_preferred":[
        "Troviggiano"
    ],
    "name:pol_x_preferred":[
        "Troviggiano"
    ],
    "name:por_x_preferred":[
        "Troviggiano"
    ],
    "name:ron_x_preferred":[
        "Troviggiano"
    ],
    "name:slk_x_preferred":[
        "Troviggiano"
    ],
    "name:slv_x_preferred":[
        "Troviggiano"
    ],
    "name:spa_x_preferred":[
        "Troviggiano"
    ],
    "name:srp_x_preferred":[
        "Troviggiano"
    ],
    "name:swe_x_preferred":[
        "Troviggiano"
    ],
    "name:tgl_x_preferred":[
        "Troviggiano"
    ],
    "name:tur_x_preferred":[
        "Troviggiano"
    ],
    "name:war_x_preferred":[
        "Troviggiano"
    ],
    "qs:a0":"Italia",
    "qs:a1":"*Macerata",
    "qs:a1r":"0Marche",
    "qs:adm0":"Italia",
    "qs:la_lc":"*",
    "qs:level":"locality",
    "qs:loc":"Troviggiano",
    "qs:loc_alt":"Troviggiano",
    "qs:pop":0,
    "qs:type":"buffered point",
    "wof:lang":[
        "ita"
    ],
    "wof:name":"Troviggiano",
    "wof:placetype":"locality",
    "wof:population":1085
},
  "geometry": {"coordinates":[13.25152,43.377941],"type":"Point"}
}