{
  "type": "Feature",
  "properties": {
    "gn:elevation":250,
    "gn:population":1085,
    "iso:country":"IT",
    "name:ita_x_preferred":[
        "Troviggiano"
    ],
    "qs:a0":"Italia",
    "qs:a1":"*Macerata",
    "qs:a1r":"0Marche",
    "qs:adm0":"Italia",
    "qs:la_lc":"*",
    "qs:level":"locality",
    "qs:loc":"Troviggiano",
    "qs:loc_alt":"Troviggiano",
    "qs:pop":0,
    "qs:type":"buffered point",
    "wof:lang":[
        "ita"
    ],
    "wof:name":"Troviggiano",
    "wof:placetype":"locality",
    "wof:population":1085
},
  "geometry": {"coordinates":[13.25152,43.377941],"type":"Point"}
}