{
  "type": "Feature",
  "properties": {
    "gn:admin1_code":"16.0",
    "gn:admin2_code":"PI",
    "gn:admin3_code":"50036.0",
    "gn:asciiname":"Soiana",
    "gn:country_code":"IT",
    "gn:dem":142,
    "gn:feature_class":"P",
    "gn:feature_code":"PPL",
    "gn:name":"Soiana",
    "gn:population":317,
    "gn:timezone":"Europe/Rome",
    "iso:country":"IT",
    "name:ceb_x_preferred":[
        "Soiana"
    ],
    "name:fas_x_preferred":[
        "\u0633\u06cc\u0648\u0627\u0646\u0627"
    ],
    "name:ita_x_preferred":[
        "Soiana"
    ],
    "name:srp_x_preferred":[
        "\u0421\u043e\u0438\u0458\u0430\u043d\u0430"
    ],
    "wof:name":"Soiana",
    "wof:placetype":"locality",
    "wof:population":317
},
  "geometry": {"coordinates":[10.6486,43.55267],"type":"Point"}
}