{
  "type": "Feature",
  "properties": {
    "gn:admin1_code":"20",
    "gn:admin2_code":"TV",
    "gn:admin3_code":"26011.0",
    "gn:asciiname":"San Francesco",
    "gn:country_code":"IT",
    "gn:dem":217,
    "gn:feature_class":"P",
    "gn:feature_code":"PPL",
    "gn:name":"San Francesco",
    "gn:population":117,
    "gn:timezone":"Europe/Rome",
    "iso:country":"IT",
    "wof:name":"San Francesco",
    "wof:placetype":"locality",
    "wof:population":117
},
  "geometry": {"coordinates":[11.87257,45.83493],"type":"Point"}
}