{
  "type": "Feature",
  "properties": {
    "gn:admin1_code":"9.0",
    "gn:admin2_code":"SO",
    "gn:admin3_code":"14058.0",
    "gn:asciiname":"San Bernardo",
    "gn:country_code":"IT",
    "gn:dem":1108,
    "gn:elevation":"1099.0",
    "gn:feature_class":"P",
    "gn:feature_code":"PPL",
    "gn:name":"San Bernardo",
    "gn:population":10,
    "gn:timezone":"Europe/Rome",
    "iso:country":"IT",
    "wof:name":"San Bernardo",
    "wof:placetype":"locality",
    "wof:population":10
},
  "geometry": {"coordinates":[9.35694,46.34713],"type":"Point"}
}