{
  "type": "Feature",
  "properties": {
    "gn:admin1_code":"18.0",
    "gn:admin2_code":"PG",
    "gn:admin3_code":"54009.0",
    "gn:asciiname":"Casamaggiore",
    "gn:country_code":"IT",
    "gn:dem":344,
    "gn:elevation":"356.0",
    "gn:feature_class":"P",
    "gn:feature_code":"PPL",
    "gn:name":"Casamaggiore",
    "gn:population":75,
    "gn:timezone":"Europe/Rome",
    "iso:country":"IT",
    "name:azb_x_preferred":[
        "\u06a9\u0627\u0632\u0627\u0645\u0627\u062c\u0648\u0631\u0647"
    ],
    "name:fas_x_preferred":[
        "\u06a9\u0627\u0632\u0627\u0645\u0627\u062c\u0648\u0631\u0647"
    ],
    "name:ita_x_preferred":[
        "Casamaggiore"
    ],
    "name:nld_x_preferred":[
        "Casamaggiore"
    ],
    "name:srp_x_preferred":[
        "\u041a\u0430\u0437\u0430\u043c\u0430\u0452\u043e\u0440\u0435"
    ],
    "wof:name":"Casamaggiore",
    "wof:placetype":"locality",
    "wof:population":75
},
  "geometry": {"coordinates":[11.97075,43.10234000000001],"type":"Point"}
}