{
  "type": "Feature",
  "properties": {
    "gn:admin1_code":"18.0",
    "gn:admin2_code":"PG",
    "gn:admin3_code":"54009.0",
    "gn:asciiname":"Casamaggiore",
    "gn:country_code":"IT",
    "gn:dem":344,
    "gn:elevation":"356.0",
    "gn:feature_class":"P",
    "gn:feature_code":"PPL",
    "gn:name":"Casamaggiore",
    "gn:population":75,
    "gn:timezone":"Europe/Rome",
    "iso:country":"IT",
    "wof:name":"Casamaggiore",
    "wof:placetype":"locality",
    "wof:population":75
},
  "geometry": {"coordinates":[11.97075,43.10234000000001],"type":"Point"}
}