{
  "type": "Feature",
  "properties": {
    "gn:admin1_code":"3",
    "gn:admin2_code":"VV",
    "gn:admin3_code":"102001.0",
    "gn:asciiname":"Budellara",
    "gn:country_code":"IT",
    "gn:dem":795,
    "gn:feature_class":"P",
    "gn:feature_code":"PPL",
    "gn:name":"Budellara",
    "gn:population":107,
    "gn:timezone":"Europe/Rome",
    "iso:country":"IT",
    "wof:name":"Budellara",
    "wof:placetype":"locality",
    "wof:population":107
},
  "geometry": {"coordinates":[16.21209,38.52347],"type":"Point"}
}