{
  "type": "Feature",
  "properties": {
    "gn:admin1_code":"5",
    "gn:admin2_code":"RE",
    "gn:admin3_code":"35037.0",
    "gn:asciiname":"Stiolo",
    "gn:country_code":"IT",
    "gn:dem":37,
    "gn:feature_class":"P",
    "gn:feature_code":"PPL",
    "gn:name":"Stiolo",
    "gn:population":39,
    "gn:timezone":"Europe/Rome",
    "iso:country":"IT",
    "wof:name":"Stiolo",
    "wof:placetype":"locality",
    "wof:population":39
},
  "geometry": {"coordinates":[10.78422,44.71546],"type":"Point"}
}