{
  "type": "Feature",
  "properties": {
    "gn:admin1_code":"9",
    "gn:admin2_code":"MN",
    "gn:admin3_code":"20066.0",
    "gn:asciiname":"La Zuccona",
    "gn:country_code":"IT",
    "gn:dem":19,
    "gn:feature_class":"P",
    "gn:feature_code":"PPL",
    "gn:name":"La Zuccona",
    "gn:population":21,
    "gn:timezone":"Europe/Rome",
    "iso:country":"IT",
    "wof:name":"La Zuccona",
    "wof:placetype":"locality",
    "wof:population":21
},
  "geometry": {"coordinates":[10.56832,44.95673],"type":"Point"}
}