{
  "type": "Feature",
  "properties": {
    "gn:admin1_code":"5.0",
    "gn:admin2_code":"BO",
    "gn:admin3_code":"37032.0",
    "gn:asciiname":"Casa Poggio di Sopra",
    "gn:country_code":"IT",
    "gn:dem":188,
    "gn:feature_class":"P",
    "gn:feature_code":"PPL",
    "gn:name":"Casa Poggio di Sopra",
    "gn:population":0,
    "gn:timezone":"Europe/Rome",
    "iso:country":"IT",
    "wof:name":"Casa Poggio di Sopra",
    "wof:placetype":"locality"
},
  "geometry": {"coordinates":[11.65,44.33333],"type":"Point"}
}