{
  "type": "Feature",
  "properties": {
    "gn:admin1_code":"5",
    "gn:admin2_code":"MO",
    "gn:admin3_code":"36025.0",
    "gn:asciiname":"Casa Maestri",
    "gn:country_code":"IT",
    "gn:dem":771,
    "gn:feature_class":"P",
    "gn:feature_code":"PPLL",
    "gn:name":"Casa Maestri",
    "gn:population":8,
    "gn:timezone":"Europe/Rome",
    "iso:country":"IT",
    "wof:name":"Casa Maestri",
    "wof:placetype":"locality",
    "wof:population":8
},
  "geometry": {"coordinates":[10.61785,44.33678],"type":"Point"}
}