{
  "type": "Feature",
  "properties": {
    "gn:admin1_code":"17.0",
    "gn:admin2_code":"TN",
    "gn:admin3_code":"22228.0",
    "gn:asciiname":"Campo Lomaso",
    "gn:country_code":"IT",
    "gn:dem":493,
    "gn:elevation":"492.0",
    "gn:feature_class":"P",
    "gn:feature_code":"PPL",
    "gn:name":"Campo Lomaso",
    "gn:population":232,
    "gn:timezone":"Europe/Rome",
    "iso:country":"IT",
    "name:azb_x_preferred":[
        "\u0644\u0648\u0645\u0627\u0633\u0648"
    ],
    "name:bel_x_preferred":[
        "\u041b\u0430\u043c\u0430\u0437\u0430"
    ],
    "name:cat_x_preferred":[
        "Lomaso"
    ],
    "name:fas_x_preferred":[
        "\u0644\u0648\u0645\u0627\u0633\u0648"
    ],
    "name:fra_x_preferred":[
        "Lomaso"
    ],
    "name:hye_x_preferred":[
        "\u053c\u0578\u0574\u0561\u0566\u0578"
    ],
    "name:ind_x_preferred":[
        "Lomaso"
    ],
    "name:ita_x_preferred":[
        "Lomaso"
    ],
    "name:jpn_x_preferred":[
        "\u30ed\u30de\u30fc\u30be"
    ],
    "name:kaz_x_preferred":[
        "\u041b\u043e\u043c\u0430\u0437\u043e"
    ],
    "name:lmo_x_preferred":[
        "Lomaso"
    ],
    "name:nap_x_preferred":[
        "Lomaso"
    ],
    "name:nld_x_preferred":[
        "Lomaso"
    ],
    "name:pms_x_preferred":[
        "Lomaso"
    ],
    "name:pol_x_preferred":[
        "Lomaso"
    ],
    "name:por_x_preferred":[
        "Lomaso"
    ],
    "name:rus_x_preferred":[
        "\u041b\u043e\u043c\u0430\u0437\u043e"
    ],
    "name:spa_x_preferred":[
        "Lomaso"
    ],
    "name:srp_x_preferred":[
        "\u041b\u043e\u043c\u0430\u0437\u043e"
    ],
    "name:ukr_x_preferred":[
        "\u041b\u043e\u043c\u0430\u0437\u043e"
    ],
    "name:uzb_x_preferred":[
        "Lomaso"
    ],
    "name:vec_x_preferred":[
        "\u0141omaxo"
    ],
    "name:vie_x_preferred":[
        "Lomaso"
    ],
    "name:vol_x_preferred":[
        "Lomaso"
    ],
    "name:war_x_preferred":[
        "Lomaso"
    ],
    "name:zho_x_preferred":[
        "\u6d1b\u9a6c\u7d22"
    ],
    "wof:name":"Campo Lomaso",
    "wof:placetype":"locality",
    "wof:population":232
},
  "geometry": {"coordinates":[10.86606,46.02349],"type":"Point"}
}