{
  "type": "Feature",
  "properties": {
    "gn:admin1_code":"17.0",
    "gn:admin2_code":"TN",
    "gn:admin3_code":"22228.0",
    "gn:asciiname":"Campo Lomaso",
    "gn:country_code":"IT",
    "gn:dem":493,
    "gn:elevation":"492.0",
    "gn:feature_class":"P",
    "gn:feature_code":"PPL",
    "gn:name":"Campo Lomaso",
    "gn:population":232,
    "gn:timezone":"Europe/Rome",
    "iso:country":"IT",
    "name:und_x_variant":[
        "Lomaso"
    ],
    "wof:name":"Campo Lomaso",
    "wof:placetype":"locality",
    "wof:population":232
},
  "geometry": {"coordinates":[10.86606,46.02349],"type":"Point"}
}