{
  "type": "Feature",
  "properties": {
    "gn:admin1_code":"1.0",
    "gn:admin2_code":"AQ",
    "gn:admin3_code":"66049.0",
    "gn:asciiname":"Colle di Sassa",
    "gn:country_code":"IT",
    "gn:dem":783,
    "gn:elevation":"750.0",
    "gn:feature_class":"P",
    "gn:feature_code":"PPL",
    "gn:name":"Colle di Sassa",
    "gn:population":224,
    "gn:timezone":"Europe/Rome",
    "iso:country":"IT",
    "wof:name":"Colle di Sassa",
    "wof:placetype":"locality",
    "wof:population":224
},
  "geometry": {"coordinates":[13.29146,42.34664],"type":"Point"}
}