{
  "type": "Feature",
  "properties": {
    "gn:admin1_code":"5.0",
    "gn:admin2_code":"RA",
    "gn:admin3_code":"39010.0",
    "gn:asciiname":"Felisio",
    "gn:cc2":"IT",
    "gn:country_code":"IT",
    "gn:dem":29,
    "gn:feature_class":"P",
    "gn:feature_code":"PPL",
    "gn:name":"Felisio",
    "gn:population":0,
    "gn:timezone":"Europe/Rome",
    "iso:country":"IT",
    "name:und_x_variant":[
        "Feliso",
        "Folisio"
    ],
    "wof:name":"Felisio",
    "wof:placetype":"locality"
},
  "geometry": {"coordinates":[11.86755,44.34893],"type":"Point"}
}