{
  "type": "Feature",
  "properties": {
    "gn:admin1_code":"17",
    "gn:admin2_code":"BZ",
    "gn:admin3_code":"21082.0",
    "gn:asciiname":"Ties",
    "gn:country_code":"IT",
    "gn:dem":1303,
    "gn:feature_class":"P",
    "gn:feature_code":"PPL",
    "gn:name":"Ties",
    "gn:population":42,
    "gn:timezone":"Europe/Rome",
    "iso:country":"IT",
    "wof:name":"Ties",
    "wof:placetype":"locality",
    "wof:population":42
},
  "geometry": {"coordinates":[11.87556,46.65069],"type":"Point"}
}