{
  "type": "Feature",
  "properties": {
    "gn:admin1_code":"7.0",
    "gn:admin2_code":"RI",
    "gn:admin3_code":"57049.0",
    "gn:asciiname":"Monte Moro",
    "gn:country_code":"IT",
    "gn:dem":810,
    "gn:feature_class":"P",
    "gn:feature_code":"PPLL",
    "gn:name":"Monte Moro",
    "gn:population":0,
    "gn:timezone":"Europe/Rome",
    "iso:country":"IT",
    "wof:name":"Monte Moro",
    "wof:placetype":"locality"
},
  "geometry": {"coordinates":[13.19307,42.22636],"type":"Point"}
}