{
  "type": "Feature",
  "properties": {
    "gn:admin1_code":"5",
    "gn:admin2_code":"RE",
    "gn:admin3_code":"35026.0",
    "gn:asciiname":"Buca Bertona",
    "gn:country_code":"IT",
    "gn:dem":20,
    "gn:feature_class":"P",
    "gn:feature_code":"PPL",
    "gn:name":"Buca Bertona",
    "gn:population":119,
    "gn:timezone":"Europe/Rome",
    "iso:country":"IT",
    "wof:name":"Buca Bertona",
    "wof:placetype":"locality",
    "wof:population":119
},
  "geometry": {"coordinates":[10.68277,44.9338],"type":"Point"}
}