{
  "type": "Feature",
  "properties": {
    "gn:admin1_code":"8.0",
    "gn:admin2_code":"GE",
    "gn:admin3_code":"10024.0",
    "gn:asciiname":"Vallescura",
    "gn:country_code":"IT",
    "gn:dem":973,
    "gn:elevation":"963.0",
    "gn:feature_class":"P",
    "gn:feature_code":"PPL",
    "gn:name":"Vallescura",
    "gn:population":22,
    "gn:timezone":"Europe/Rome",
    "iso:country":"IT",
    "wof:name":"Vallescura",
    "wof:placetype":"locality",
    "wof:population":22
},
  "geometry": {"coordinates":[9.29943,44.52173],"type":"Point"}
}