{
  "type": "Feature",
  "properties": {
    "gn:admin1_code":"5",
    "gn:admin2_code":"PC",
    "gn:admin3_code":"33017.0",
    "gn:asciiname":"Rovaiola",
    "gn:country_code":"IT",
    "gn:dem":420,
    "gn:feature_class":"P",
    "gn:feature_code":"PPL",
    "gn:name":"Rovaiola",
    "gn:population":18,
    "gn:timezone":"Europe/Rome",
    "iso:country":"IT",
    "wof:name":"Rovaiola",
    "wof:placetype":"locality",
    "wof:population":18
},
  "geometry": {"coordinates":[9.33738,44.69113],"type":"Point"}
}