{
  "type": "Feature",
  "properties": {
    "gn:admin1_code":"20.0",
    "gn:admin2_code":"VR",
    "gn:admin3_code":"23091.0",
    "gn:asciiname":"Nesente",
    "gn:country_code":"IT",
    "gn:dem":84,
    "gn:feature_class":"P",
    "gn:feature_code":"PPL",
    "gn:name":"Nesente",
    "gn:population":388,
    "gn:timezone":"Europe/Rome",
    "iso:country":"IT",
    "wof:name":"Nesente",
    "wof:placetype":"locality",
    "wof:population":388
},
  "geometry": {"coordinates":[11.03388,45.47923],"type":"Point"}
}