{
  "type": "Feature",
  "properties": {
    "gn:admin1_code":"9",
    "gn:admin2_code":"BS",
    "gn:admin3_code":"17024.0",
    "gn:asciiname":"Graticelle",
    "gn:country_code":"IT",
    "gn:dem":706,
    "gn:feature_class":"P",
    "gn:feature_code":"PPL",
    "gn:name":"Graticelle",
    "gn:population":110,
    "gn:timezone":"Europe/Rome",
    "iso:country":"IT",
    "wof:name":"Graticelle",
    "wof:placetype":"locality",
    "wof:population":110
},
  "geometry": {"coordinates":[10.27185,45.80317],"type":"Point"}
}