{
  "type": "Feature",
  "properties": {
    "gn:admin1_code":"10.0",
    "gn:admin2_code":"AP",
    "gn:admin3_code":"44015.0",
    "gn:asciiname":"Piantabete",
    "gn:country_code":"IT",
    "gn:dem":787,
    "gn:feature_class":"P",
    "gn:feature_code":"PPL",
    "gn:name":"Piantabete",
    "gn:population":0,
    "gn:timezone":"Europe/Rome",
    "iso:country":"IT",
    "wof:name":"Piantabete",
    "wof:placetype":"locality"
},
  "geometry": {"coordinates":[13.36667,42.88333],"type":"Point"}
}