{
  "type": "Feature",
  "properties": {
    "gn:admin1_code":"6.0",
    "gn:admin2_code":"PN",
    "gn:admin3_code":"93046.0",
    "gn:asciiname":"Faidona",
    "gn:country_code":"IT",
    "gn:dem":351,
    "gn:elevation":"343.0",
    "gn:feature_class":"P",
    "gn:feature_code":"PPL",
    "gn:name":"Faidona",
    "gn:population":36,
    "gn:timezone":"Europe/Rome",
    "iso:country":"IT",
    "wof:name":"Faidona",
    "wof:placetype":"locality",
    "wof:population":36
},
  "geometry": {"coordinates":[12.74448,46.25041],"type":"Point"}
}