{
  "type": "Feature",
  "properties": {
    "gn:gn_country":"IT",
    "gn:gn_fcode":"PPL",
    "gn:gn_pop":0,
    "gn:population":204,
    "iso:country":"IT",
    "name:baq_x_preferred":[
        "Carvanno"
    ],
    "name:cat_x_preferred":[
        "Carvanno"
    ],
    "name:cze_x_preferred":[
        "Carvanno"
    ],
    "name:dan_x_preferred":[
        "Carvanno"
    ],
    "name:dut_x_preferred":[
        "Carvanno"
    ],
    "name:eng_x_preferred":[
        "Carvanno"
    ],
    "name:fin_x_preferred":[
        "Carvanno"
    ],
    "name:fre_x_preferred":[
        "Carvanno"
    ],
    "name:ind_x_preferred":[
        "Carvanno"
    ],
    "name:ita_x_preferred":[
        "Carvanno"
    ],
    "name:nno_x_preferred":[
        "Carvanno"
    ],
    "name:nob_x_preferred":[
        "Carvanno"
    ],
    "name:oci_x_preferred":[
        "Carvanno"
    ],
    "name:pol_x_preferred":[
        "Carvanno"
    ],
    "name:por_x_preferred":[
        "Carvanno"
    ],
    "name:rum_x_preferred":[
        "Carvanno"
    ],
    "name:slo_x_preferred":[
        "Carvanno"
    ],
    "name:slv_x_preferred":[
        "Carvanno"
    ],
    "name:spa_x_preferred":[
        "Carvanno"
    ],
    "name:srp_x_preferred":[
        "Carvanno"
    ],
    "name:swe_x_preferred":[
        "Carvanno"
    ],
    "name:tgl_x_preferred":[
        "Carvanno"
    ],
    "name:tur_x_preferred":[
        "Carvanno"
    ],
    "name:war_x_preferred":[
        "Carvanno"
    ],
    "qs_pg:aaroncc":"IT",
    "qs_pg:gn_country":"IT",
    "qs_pg:gn_fcode":"PPL",
    "qs_pg:gn_pop":0,
    "qs_pg:name":"Carvanno",
    "qs_pg:name_adm0":"Italia",
    "qs_pg:name_adm1":"Lombardia",
    "qs_pg:photos_9r":0,
    "qs_pg:photos_sr":0,
    "qs_pg:pop_sr":0,
    "qs_pg:qs_pg_placetype":"locality",
    "qs_pg:qs_pg_placetype_gp":"Town",
    "qs_pg:woe_adm0":23424853,
    "woe:adm0_id":23424853,
    "woe:name_adm0":"Italia",
    "woe:name_adm1":"Lombardia",
    "woe:placetype":"Town",
    "wof:name":"Carvanno",
    "wof:placetype":"locality",
    "wof:population":204
},
  "geometry": {"coordinates":[10.09506,45.71673],"type":"Point"}
}