{
  "type": "Feature",
  "properties": {
    "gn:admin1_code":"12",
    "gn:admin2_code":"TO",
    "gn:admin3_code":"1253.0",
    "gn:asciiname":"Bellavalle",
    "gn:country_code":"IT",
    "gn:dem":226,
    "gn:feature_class":"P",
    "gn:feature_code":"PPL",
    "gn:name":"Bellavalle",
    "gn:population":40,
    "gn:timezone":"Europe/Rome",
    "iso:country":"IT",
    "wof:name":"Bellavalle",
    "wof:placetype":"locality",
    "wof:population":40
},
  "geometry": {"coordinates":[7.91865,45.15941],"type":"Point"}
}