{
  "type": "Feature",
  "properties": {
    "gn:admin1_code":"12",
    "gn:admin2_code":"CN",
    "gn:admin3_code":"4017.0",
    "gn:asciiname":"Fontanile",
    "gn:country_code":"IT",
    "gn:dem":1485,
    "gn:feature_class":"P",
    "gn:feature_code":"PPLL",
    "gn:name":"Fontanile",
    "gn:population":8,
    "gn:timezone":"Europe/Rome",
    "iso:country":"IT",
    "name:ara_x_preferred":[
        "\u0641\u0648\u0646\u062a\u0627\u0646\u064a\u0644\u064a"
    ],
    "name:azb_x_preferred":[
        "\u0641\u0648\u0646\u062a\u0627\u0646\u06cc\u0644\u06cc"
    ],
    "name:bel_x_preferred":[
        "\u0424\u0430\u043d\u0442\u0430\u043d\u0456\u043b\u0435"
    ],
    "name:bul_x_preferred":[
        "\u0424\u043e\u043d\u0442\u0430\u043d\u0438\u043b\u0435"
    ],
    "name:cat_x_preferred":[
        "Fontanile"
    ],
    "name:ceb_x_preferred":[
        "Fontanile"
    ],
    "name:deu_x_preferred":[
        "Fontanile"
    ],
    "name:epo_x_preferred":[
        "Fontanile"
    ],
    "name:eus_x_preferred":[
        "Fontanile"
    ],
    "name:fas_x_preferred":[
        "\u0641\u0648\u0646\u062a\u0627\u0646\u06cc\u0644\u06cc"
    ],
    "name:fra_x_preferred":[
        "Fontanile"
    ],
    "name:hun_x_preferred":[
        "Fontanile"
    ],
    "name:hye_x_preferred":[
        "\u0556\u0578\u0576\u057f\u0561\u0576\u056b\u056c\u0565"
    ],
    "name:ind_x_preferred":[
        "Fontanile"
    ],
    "name:ita_x_preferred":[
        "Fontanile"
    ],
    "name:jpn_x_preferred":[
        "\u30d5\u30a9\u30f3\u30bf\u30cb\u30fc\u30ec"
    ],
    "name:kaz_x_preferred":[
        "\u0424\u043e\u043d\u0442\u0430\u043d\u0438\u043b\u0435"
    ],
    "name:lat_x_preferred":[
        "Fontanile"
    ],
    "name:lmo_x_preferred":[
        "Fontanile"
    ],
    "name:msa_x_preferred":[
        "Fontanile"
    ],
    "name:nap_x_preferred":[
        "Fontanile"
    ],
    "name:nld_x_preferred":[
        "Fontanile"
    ],
    "name:pms_x_preferred":[
        "Fontanij"
    ],
    "name:pol_x_preferred":[
        "Fontanile"
    ],
    "name:por_x_preferred":[
        "Fontanile"
    ],
    "name:ron_x_preferred":[
        "Fontanile"
    ],
    "name:rus_x_preferred":[
        "\u0424\u043e\u043d\u0442\u0430\u043d\u0438\u043b\u0435"
    ],
    "name:scn_x_preferred":[
        "Fontanile"
    ],
    "name:spa_x_preferred":[
        "Fontanile"
    ],
    "name:srp_x_preferred":[
        "\u0424\u043e\u043d\u0442\u0430\u043d\u0438\u043b\u0435"
    ],
    "name:tgl_x_preferred":[
        "Fontanile"
    ],
    "name:ukr_x_preferred":[
        "\u0424\u043e\u043d\u0442\u0430\u043d\u0456\u043b\u0435"
    ],
    "name:uzb_x_preferred":[
        "Fontanile"
    ],
    "name:vie_x_preferred":[
        "Fontanile"
    ],
    "name:vol_x_preferred":[
        "Fontanile"
    ],
    "name:war_x_preferred":[
        "Fontanile"
    ],
    "name:zho_x_preferred":[
        "\u4e30\u5854\u5c3c\u83b1"
    ],
    "wof:name":"Fontanile",
    "wof:placetype":"locality",
    "wof:population":8
},
  "geometry": {"coordinates":[7.029,44.58219],"type":"Point"}
}