{
  "type": "Feature",
  "properties": {
    "gn:admin1_code":"12",
    "gn:admin2_code":"CN",
    "gn:admin3_code":"4017.0",
    "gn:asciiname":"Fontanile",
    "gn:country_code":"IT",
    "gn:dem":1485,
    "gn:feature_class":"P",
    "gn:feature_code":"PPLL",
    "gn:name":"Fontanile",
    "gn:population":8,
    "gn:timezone":"Europe/Rome",
    "iso:country":"IT",
    "wof:name":"Fontanile",
    "wof:placetype":"locality",
    "wof:population":8
},
  "geometry": {"coordinates":[7.029,44.58219],"type":"Point"}
}