{
  "type": "Feature",
  "properties": {
    "gn:admin1_code":"12.0",
    "gn:admin2_code":"TO",
    "gn:admin3_code":"1059.0",
    "gn:asciiname":"Tuninetti",
    "gn:country_code":"IT",
    "gn:dem":254,
    "gn:feature_class":"P",
    "gn:feature_code":"PPL",
    "gn:name":"Tuninetti",
    "gn:population":587,
    "gn:timezone":"Europe/Rome",
    "iso:country":"IT",
    "wof:name":"Tuninetti",
    "wof:placetype":"locality",
    "wof:population":587
},
  "geometry": {"coordinates":[7.77384,44.85556],"type":"Point"}
}