{
  "type": "Feature",
  "properties": {
    "gn:admin1_code":"18.0",
    "gn:admin2_code":"PG",
    "gn:admin3_code":"54039.0",
    "gn:asciiname":"Morleschio",
    "gn:country_code":"IT",
    "gn:dem":334,
    "gn:feature_class":"P",
    "gn:feature_code":"PPL",
    "gn:name":"Morleschio",
    "gn:population":0,
    "gn:timezone":"Europe/Rome",
    "iso:country":"IT",
    "wof:name":"Morleschio",
    "wof:placetype":"locality"
},
  "geometry": {"coordinates":[12.46667,43.21667],"type":"Point"}
}