{
  "type": "Feature",
  "properties": {
    "gn:admin1_code":"9.0",
    "gn:admin2_code":"CR",
    "gn:admin3_code":"19035.0",
    "gn:asciiname":"Santo Stefano in Vairano",
    "gn:country_code":"IT",
    "gn:dem":79,
    "gn:feature_class":"P",
    "gn:feature_code":"PPL",
    "gn:name":"Santo Stefano in Vairano",
    "gn:population":682,
    "gn:timezone":"Europe/Rome",
    "iso:country":"IT",
    "name:ceb_x_preferred":[
        "Santo Stefano in Vairano"
    ],
    "name:ita_x_preferred":[
        "Santo Stefano in Vairano"
    ],
    "name:nld_x_preferred":[
        "Santo Stefano in Vairano"
    ],
    "name:srp_x_preferred":[
        "\u0421\u0430\u043d\u0442\u043e \u0421\u0442\u0435\u0444\u0430\u043d\u043e \u0438\u043d \u0412\u0430\u0438\u0440\u0430\u043d\u043e"
    ],
    "wof:name":"Santo Stefano in Vairano",
    "wof:placetype":"locality",
    "wof:population":682
},
  "geometry": {"coordinates":[9.67613,45.37849],"type":"Point"}
}