{
  "type": "Feature",
  "properties": {
    "gn:admin1_code":"1.0",
    "gn:admin2_code":"AQ",
    "gn:admin3_code":"66059.0",
    "gn:asciiname":"Valle-Cavalletto d'Ocre",
    "gn:country_code":"IT",
    "gn:dem":651,
    "gn:feature_class":"P",
    "gn:feature_code":"PPL",
    "gn:name":"Valle-Cavalletto d'Ocre",
    "gn:population":434,
    "gn:timezone":"Europe/Rome",
    "iso:country":"IT",
    "wof:name":"Valle-Cavalletto d'Ocre",
    "wof:placetype":"locality",
    "wof:population":434
},
  "geometry": {"coordinates":[13.45757,42.30575],"type":"Point"}
}