{
  "type": "Feature",
  "properties": {
    "gn:admin1_code":"5",
    "gn:admin2_code":"MO",
    "gn:admin3_code":"36017.0",
    "gn:asciiname":"Ca' Fegatelli",
    "gn:country_code":"IT",
    "gn:dem":626,
    "gn:feature_class":"P",
    "gn:feature_code":"PPL",
    "gn:name":"Ca' Fegatelli",
    "gn:population":19,
    "gn:timezone":"Europe/Rome",
    "iso:country":"IT",
    "wof:name":"Ca' Fegatelli",
    "wof:placetype":"locality",
    "wof:population":19
},
  "geometry": {"coordinates":[10.95104,44.36311],"type":"Point"}
}