{
  "type": "Feature",
  "properties": {
    "gn:admin1_code":"9",
    "gn:admin2_code":"PV",
    "gn:admin3_code":"18171.0",
    "gn:asciiname":"Torretta Casa di Fiori",
    "gn:country_code":"IT",
    "gn:dem":729,
    "gn:feature_class":"P",
    "gn:feature_code":"PPL",
    "gn:name":"Torretta Casa di Fiori",
    "gn:population":19,
    "gn:timezone":"Europe/Rome",
    "iso:country":"IT",
    "wof:name":"Torretta Casa di Fiori",
    "wof:placetype":"locality",
    "wof:population":19
},
  "geometry": {"coordinates":[9.25844,44.84355],"type":"Point"}
}