{
  "type": "Feature",
  "properties": {
    "gn:admin1_code":"9",
    "gn:admin2_code":"PV",
    "gn:admin3_code":"18189.0",
    "gn:asciiname":"Mulino di Limido",
    "gn:country_code":"IT",
    "gn:dem":63,
    "gn:feature_class":"P",
    "gn:feature_code":"PPL",
    "gn:name":"Mulino di Limido",
    "gn:population":11,
    "gn:timezone":"Europe/Rome",
    "iso:country":"IT",
    "wof:name":"Mulino di Limido",
    "wof:placetype":"locality",
    "wof:population":11
},
  "geometry": {"coordinates":[9.05914,45.18743],"type":"Point"}
}