{
  "type": "Feature",
  "properties": {
    "gn:admin1_code":"1.0",
    "gn:admin2_code":"CH",
    "gn:admin3_code":"69043.0",
    "gn:asciiname":"San Vincenzo-Cerchiara",
    "gn:country_code":"IT",
    "gn:dem":391,
    "gn:feature_class":"P",
    "gn:feature_code":"PPL",
    "gn:name":"San Vincenzo-Cerchiara",
    "gn:population":483,
    "gn:timezone":"Europe/Rome",
    "iso:country":"IT",
    "wof:name":"San Vincenzo-Cerchiara",
    "wof:placetype":"locality",
    "wof:population":483
},
  "geometry": {"coordinates":[14.27889,42.18525],"type":"Point"}
}