{
  "type": "Feature",
  "properties": {
    "gn:admin1_code":"5.0",
    "gn:admin2_code":"RE",
    "gn:admin3_code":"35038.0",
    "gn:asciiname":"Barcaccia",
    "gn:country_code":"IT",
    "gn:dem":127,
    "gn:feature_class":"P",
    "gn:feature_code":"PPL",
    "gn:name":"Barcaccia",
    "gn:population":657,
    "gn:timezone":"Europe/Rome",
    "iso:country":"IT",
    "wof:name":"Barcaccia",
    "wof:placetype":"locality",
    "wof:population":657
},
  "geometry": {"coordinates":[10.429,44.66332],"type":"Point"}
}