{
  "type": "Feature",
  "properties": {
    "gn:admin1_code":"9",
    "gn:admin2_code":"CO",
    "gn:admin3_code":"13099.0",
    "gn:asciiname":"Filatoio",
    "gn:country_code":"IT",
    "gn:dem":289,
    "gn:feature_class":"P",
    "gn:feature_code":"PPL",
    "gn:name":"Filatoio",
    "gn:population":32,
    "gn:timezone":"Europe/Rome",
    "iso:country":"IT",
    "wof:name":"Filatoio",
    "wof:placetype":"locality",
    "wof:population":32
},
  "geometry": {"coordinates":[8.97997,45.81478],"type":"Point"}
}