{
  "type": "Feature",
  "properties": {
    "gn:admin1_code":"20",
    "gn:admin2_code":"VR",
    "gn:admin3_code":"23002.0",
    "gn:asciiname":"San Tomio",
    "gn:country_code":"IT",
    "gn:dem":21,
    "gn:feature_class":"P",
    "gn:feature_code":"PPL",
    "gn:name":"San Tomio",
    "gn:population":22,
    "gn:timezone":"Europe/Rome",
    "iso:country":"IT",
    "wof:name":"San Tomio",
    "wof:placetype":"locality",
    "wof:population":22
},
  "geometry": {"coordinates":[11.27273,45.2884],"type":"Point"}
}