{
  "type": "Feature",
  "properties": {
    "gn:admin1_code":"5",
    "gn:admin2_code":"FE",
    "gn:admin3_code":"38008.0",
    "gn:asciiname":"Viconovo",
    "gn:country_code":"IT",
    "gn:dem":5,
    "gn:feature_class":"P",
    "gn:feature_code":"PPL",
    "gn:name":"Viconovo",
    "gn:population":215,
    "gn:timezone":"Europe/Rome",
    "iso:country":"IT",
    "wof:name":"Viconovo",
    "wof:placetype":"locality",
    "wof:population":215
},
  "geometry": {"coordinates":[11.76919,44.84487],"type":"Point"}
}