{
  "type": "Feature",
  "properties": {
    "gn:admin1_code":"2",
    "gn:admin2_code":"PZ",
    "gn:admin3_code":"76070.0",
    "gn:asciiname":"Montagna di Basso",
    "gn:country_code":"IT",
    "gn:dem":553,
    "gn:feature_class":"P",
    "gn:feature_code":"PPL",
    "gn:name":"Montagna di Basso",
    "gn:population":21,
    "gn:timezone":"Europe/Rome",
    "iso:country":"IT",
    "wof:name":"Montagna di Basso",
    "wof:placetype":"locality",
    "wof:population":21
},
  "geometry": {"coordinates":[16.02004,39.94735],"type":"Point"}
}