{
  "type": "Feature",
  "properties": {
    "gn:admin1_code":"7",
    "gn:admin2_code":"RM",
    "gn:admin3_code":"58018.0",
    "gn:asciiname":"Selvotta",
    "gn:country_code":"IT",
    "gn:dem":75,
    "gn:feature_class":"P",
    "gn:feature_code":"PPL",
    "gn:name":"Selvotta",
    "gn:population":201,
    "gn:timezone":"Europe/Rome",
    "iso:country":"IT",
    "wof:name":"Selvotta",
    "wof:placetype":"locality",
    "wof:population":201
},
  "geometry": {"coordinates":[12.56119,42.11997],"type":"Point"}
}