{
  "type": "Feature",
  "properties": {
    "gn:admin1_code":"9.0",
    "gn:admin2_code":"SO",
    "gn:admin3_code":"14046.0",
    "gn:asciiname":"Campo",
    "gn:country_code":"IT",
    "gn:dem":211,
    "gn:feature_class":"P",
    "gn:feature_code":"PPL",
    "gn:name":"Campo",
    "gn:population":413,
    "gn:timezone":"Europe/Rome",
    "iso:country":"IT",
    "wof:name":"Campo",
    "wof:placetype":"locality",
    "wof:population":413
},
  "geometry": {"coordinates":[9.4585,46.21046],"type":"Point"}
}