{
  "type": "Feature",
  "properties": {
    "gn:admin1_code":"7",
    "gn:admin2_code":"RM",
    "gn:admin3_code":"58009.0",
    "gn:asciiname":"Moletta",
    "gn:country_code":"IT",
    "gn:dem":298,
    "gn:feature_class":"P",
    "gn:feature_code":"PPL",
    "gn:name":"Moletta",
    "gn:population":44,
    "gn:timezone":"Europe/Rome",
    "iso:country":"IT",
    "wof:name":"Moletta",
    "wof:placetype":"locality",
    "wof:population":44
},
  "geometry": {"coordinates":[12.67407,41.70879],"type":"Point"}
}