{
  "type": "Feature",
  "properties": {
    "gn:admin1_code":"7",
    "gn:admin2_code":"RM",
    "gn:admin3_code":"58013.0",
    "gn:asciiname":"Molare",
    "gn:country_code":"IT",
    "gn:dem":258,
    "gn:feature_class":"P",
    "gn:feature_code":"PPL",
    "gn:name":"Molare",
    "gn:population":48,
    "gn:timezone":"Europe/Rome",
    "iso:country":"IT",
    "name:ara_x_preferred":[
        "\u0645\u0648\u0644\u0627\u0631\u064a"
    ],
    "name:bul_x_preferred":[
        "\u041c\u043e\u043b\u0430\u0440\u0435"
    ],
    "name:cat_x_preferred":[
        "Molare"
    ],
    "name:ceb_x_preferred":[
        "Molare"
    ],
    "name:deu_x_preferred":[
        "Molare"
    ],
    "name:epo_x_preferred":[
        "Molare"
    ],
    "name:eus_x_preferred":[
        "Molare"
    ],
    "name:fas_x_preferred":[
        "\u0645\u0648\u0644\u0627\u0631\u0647"
    ],
    "name:fra_x_preferred":[
        "Molare"
    ],
    "name:hun_x_preferred":[
        "Molare"
    ],
    "name:hye_x_preferred":[
        "\u0544\u0578\u056c\u0561\u0580\u0565"
    ],
    "name:ind_x_preferred":[
        "Molare"
    ],
    "name:ita_x_preferred":[
        "Molare"
    ],
    "name:jpn_x_preferred":[
        "\u30e2\u30e9\u30fc\u30ec"
    ],
    "name:kaz_x_preferred":[
        "\u041c\u043e\u043b\u0430\u0440\u0435"
    ],
    "name:lat_x_preferred":[
        "Mollariae"
    ],
    "name:lmo_x_preferred":[
        "Molare"
    ],
    "name:msa_x_preferred":[
        "Molare"
    ],
    "name:nap_x_preferred":[
        "Molare"
    ],
    "name:nld_x_preferred":[
        "Molare"
    ],
    "name:pms_x_preferred":[
        "Morele"
    ],
    "name:pol_x_preferred":[
        "Molare"
    ],
    "name:por_x_preferred":[
        "Molare"
    ],
    "name:ron_x_preferred":[
        "Molare"
    ],
    "name:rus_x_preferred":[
        "\u041c\u043e\u043b\u0430\u0440\u0435"
    ],
    "name:scn_x_preferred":[
        "Molare"
    ],
    "name:spa_x_preferred":[
        "Molare"
    ],
    "name:srp_x_preferred":[
        "\u041c\u043e\u043b\u0430\u0440\u0435"
    ],
    "name:ukr_x_preferred":[
        "\u041c\u043e\u043b\u0430\u0440\u0435"
    ],
    "name:uzb_x_preferred":[
        "Molare"
    ],
    "name:vie_x_preferred":[
        "Molare"
    ],
    "name:vol_x_preferred":[
        "Molare"
    ],
    "name:war_x_preferred":[
        "Molare"
    ],
    "name:zho_x_preferred":[
        "\u83ab\u62c9\u96f7"
    ],
    "wof:name":"Molare",
    "wof:placetype":"locality",
    "wof:population":48
},
  "geometry": {"coordinates":[12.18051,42.08576],"type":"Point"}
}