{
  "type": "Feature",
  "properties": {
    "iso:country":"IT",
    "name:deu_x_preferred":[
        "Constantino"
    ],
    "name:glg_x_preferred":[
        "Constantino"
    ],
    "name:ita_x_preferred":[
        "Constantino"
    ],
    "name:por_x_preferred":[
        "Constantino"
    ],
    "name:spa_x_preferred":[
        "Constantino"
    ],
    "qs:gn_adm0_cc":"IT",
    "qs:gn_local":3165198,
    "qs:gn_nam_loc":"Trezzano sul Naviglio, Trezzano sul Naviglio, Milano, Lombardia, IT",
    "qs:gn_namadm1":"09",
    "qs:local_max":389,
    "qs:local_sum":391,
    "qs:localhoods":2,
    "qs:name":"Constantino",
    "qs:name_adm0":"Italia",
    "qs:name_adm1":"Lombardia",
    "qs:name_adm2":"Milano",
    "qs:name_lau":"Cesano Boscone",
    "qs:name_local":"Trezzano sul Naviglio",
    "qs:photo_max":2,
    "qs:photo_sum":2,
    "qs:placetype":"Suburb",
    "qs:quad_count":1,
    "qs:woe_adm0":23424853,
    "qs:woe_adm1":7153338,
    "qs:woe_adm2":12591813,
    "qs:woe_lau":12678559,
    "qs:woe_local":725289,
    "qs:woe_ver":"7.10.0",
    "wof:name":"Constantino",
    "wof:placetype":"neighbourhood"
},
  "geometry": {"coordinates":[9.122772,45.455315],"type":"Point"}
}