{
  "type": "Feature",
  "properties": {
    "gn:admin1_code":"4",
    "gn:admin2_code":"AV",
    "gn:admin3_code":"64083.0",
    "gn:asciiname":"Iardino",
    "gn:country_code":"IT",
    "gn:dem":237,
    "gn:feature_class":"P",
    "gn:feature_code":"PPL",
    "gn:name":"Iardino",
    "gn:population":254,
    "gn:timezone":"Europe/Rome",
    "iso:country":"IT",
    "wof:name":"Iardino",
    "wof:placetype":"locality",
    "wof:population":254
},
  "geometry": {"coordinates":[14.69107,41.02969],"type":"Point"}
}