{
  "type": "Feature",
  "properties": {
    "gn:admin1_code":"12.0",
    "gn:admin2_code":"BI",
    "gn:admin3_code":"96076.0",
    "gn:asciiname":"Regione le Torrette",
    "gn:country_code":"IT",
    "gn:dem":267,
    "gn:feature_class":"P",
    "gn:feature_code":"PPLL",
    "gn:name":"Regione le Torrette",
    "gn:population":0,
    "gn:timezone":"Europe/Rome",
    "iso:country":"IT",
    "wof:name":"Regione le Torrette",
    "wof:placetype":"locality"
},
  "geometry": {"coordinates":[8.11815,45.48547],"type":"Point"}
}