{
  "type": "Feature",
  "properties": {
    "iso:country":"IT",
    "name:eng_x_preferred":[
        "San Nicolo di Villola"
    ],
    "name:ita_x_preferred":[
        "San Nicol\u00f2 di Villola"
    ],
    "wof:name":"San Nicolo di Villola",
    "wof:placetype":"neighbourhood"
},
  "geometry": {"coordinates":[11.38055629904567,44.52117560806188],"type":"Point"}
}