{
  "type": "Feature",
  "properties": {
    "gn:admin1_code":"8",
    "gn:admin2_code":"GE",
    "gn:admin3_code":"10021.0",
    "gn:asciiname":"Sella",
    "gn:country_code":"IT",
    "gn:dem":587,
    "gn:feature_class":"P",
    "gn:feature_code":"PPL",
    "gn:name":"Sella",
    "gn:population":83,
    "gn:timezone":"Europe/Rome",
    "iso:country":"IT",
    "name:arg_x_preferred":[
        "Sella"
    ],
    "name:cat_x_preferred":[
        "Sella"
    ],
    "name:ceb_x_preferred":[
        "Sella"
    ],
    "name:deu_x_preferred":[
        "Sella"
    ],
    "name:ell_x_preferred":[
        "\u03a3\u03b5\u03bb\u03bb\u03ac"
    ],
    "name:eus_x_preferred":[
        "Sella"
    ],
    "name:fra_x_preferred":[
        "Sella"
    ],
    "name:glg_x_preferred":[
        "Sella"
    ],
    "name:ita_x_preferred":[
        "Sella"
    ],
    "name:nld_x_preferred":[
        "Sella"
    ],
    "name:por_x_preferred":[
        "Sella"
    ],
    "name:rus_x_preferred":[
        "\u0421\u0435\u043b\u043b\u0430"
    ],
    "name:spa_x_preferred":[
        "Sella"
    ],
    "name:srp_x_preferred":[
        "Sella"
    ],
    "name:swe_x_preferred":[
        "Sella"
    ],
    "wof:name":"Sella",
    "wof:placetype":"locality",
    "wof:population":83
},
  "geometry": {"coordinates":[9.0967,44.4765],"type":"Point"}
}