{
  "type": "Feature",
  "properties": {
    "gn:admin1_code":"12",
    "gn:admin2_code":"AT",
    "gn:admin3_code":"5074.0",
    "gn:asciiname":"Orto",
    "gn:country_code":"IT",
    "gn:dem":160,
    "gn:feature_class":"P",
    "gn:feature_code":"PPL",
    "gn:name":"Orto",
    "gn:population":58,
    "gn:timezone":"Europe/Rome",
    "iso:country":"IT",
    "name:cat_x_preferred":[
        "Orto"
    ],
    "name:ceb_x_preferred":[
        "Orto"
    ],
    "name:cos_x_preferred":[
        "Ortu"
    ],
    "name:deu_x_preferred":[
        "Orto"
    ],
    "name:eus_x_preferred":[
        "Orto"
    ],
    "name:fra_x_preferred":[
        "Orto"
    ],
    "name:hun_x_preferred":[
        "Orto"
    ],
    "name:hye_x_preferred":[
        "\u0555\u0580\u057f\u0578"
    ],
    "name:ind_x_preferred":[
        "Orto"
    ],
    "name:ita_x_preferred":[
        "Orto"
    ],
    "name:kaz_x_preferred":[
        "\u041e\u0440\u0442\u043e"
    ],
    "name:lat_x_preferred":[
        "Orto"
    ],
    "name:lmo_x_preferred":[
        "Orto"
    ],
    "name:msa_x_preferred":[
        "Orto"
    ],
    "name:nld_x_preferred":[
        "Orto"
    ],
    "name:nor_x_preferred":[
        "Orto"
    ],
    "name:oci_x_preferred":[
        "Orto"
    ],
    "name:pol_x_preferred":[
        "Orto"
    ],
    "name:por_x_preferred":[
        "Orto"
    ],
    "name:rus_x_preferred":[
        "\u041e\u0440\u0442\u043e"
    ],
    "name:slk_x_preferred":[
        "Orto"
    ],
    "name:slv_x_preferred":[
        "Orto"
    ],
    "name:spa_x_preferred":[
        "Orto"
    ],
    "name:swe_x_preferred":[
        "Orto"
    ],
    "name:ukr_x_preferred":[
        "\u041e\u0440\u0442\u043e"
    ],
    "name:vie_x_preferred":[
        "Orto"
    ],
    "name:vol_x_preferred":[
        "Orto"
    ],
    "name:war_x_preferred":[
        "Orto"
    ],
    "wof:name":"Orto",
    "wof:placetype":"locality",
    "wof:population":58
},
  "geometry": {"coordinates":[8.24761,44.81802],"type":"Point"}
}