{
  "type": "Feature",
  "properties": {
    "gn:admin1_code":"12",
    "gn:admin2_code":"AT",
    "gn:admin3_code":"5074.0",
    "gn:asciiname":"Orto",
    "gn:country_code":"IT",
    "gn:dem":160,
    "gn:feature_class":"P",
    "gn:feature_code":"PPL",
    "gn:name":"Orto",
    "gn:population":58,
    "gn:timezone":"Europe/Rome",
    "iso:country":"IT",
    "wof:name":"Orto",
    "wof:placetype":"locality",
    "wof:population":58
},
  "geometry": {"coordinates":[8.24761,44.81802],"type":"Point"}
}