{
  "type": "Feature",
  "properties": {
    "gn:admin1_code":"12",
    "gn:admin2_code":"TO",
    "gn:admin3_code":"1123.0",
    "gn:asciiname":"Nucleo Case Sparse",
    "gn:country_code":"IT",
    "gn:dem":268,
    "gn:feature_class":"P",
    "gn:feature_code":"PPL",
    "gn:name":"Nucleo Case Sparse",
    "gn:population":11,
    "gn:timezone":"Europe/Rome",
    "iso:country":"IT",
    "wof:name":"Nucleo Case Sparse",
    "wof:placetype":"locality",
    "wof:population":11
},
  "geometry": {"coordinates":[7.92116,44.90006],"type":"Point"}
}