{
  "type": "Feature",
  "properties": {
    "gn:admin1_code":"20",
    "gn:admin2_code":"TV",
    "gn:admin3_code":"26025.0",
    "gn:asciiname":"Rivette",
    "gn:country_code":"IT",
    "gn:dem":130,
    "gn:feature_class":"P",
    "gn:feature_code":"PPL",
    "gn:name":"Rivette",
    "gn:population":60,
    "gn:timezone":"Europe/Rome",
    "iso:country":"IT",
    "wof:name":"Rivette",
    "wof:placetype":"locality",
    "wof:population":60
},
  "geometry": {"coordinates":[12.04985,45.82912],"type":"Point"}
}