{
  "type": "Feature",
  "properties": {
    "gn:admin1_code":"4",
    "gn:admin3_code":"63062.0",
    "gn:asciiname":"Oleandro",
    "gn:country_code":"IT",
    "gn:dem":68,
    "gn:feature_class":"P",
    "gn:feature_code":"PPL",
    "gn:name":"Oleandro",
    "gn:population":43,
    "gn:timezone":"Europe/Rome",
    "iso:country":"IT",
    "wof:name":"Oleandro",
    "wof:placetype":"locality",
    "wof:population":43
},
  "geometry": {"coordinates":[14.11657,40.9297],"type":"Point"}
}