{
  "type": "Feature",
  "properties": {
    "gn:admin1_code":"7",
    "gn:admin2_code":"FR",
    "gn:admin3_code":"60004.0",
    "gn:asciiname":"Santa Poppa",
    "gn:country_code":"IT",
    "gn:dem":443,
    "gn:feature_class":"P",
    "gn:feature_code":"PPL",
    "gn:name":"Santa Poppa",
    "gn:population":34,
    "gn:timezone":"Europe/Rome",
    "iso:country":"IT",
    "wof:name":"Santa Poppa",
    "wof:placetype":"locality",
    "wof:population":34
},
  "geometry": {"coordinates":[13.75698,41.69149],"type":"Point"}
}