{
  "type": "Feature",
  "properties": {
    "gn:admin1_code":"12",
    "gn:admin2_code":"TO",
    "gn:admin3_code":"1055.0",
    "gn:asciiname":"Peroldrado",
    "gn:country_code":"IT",
    "gn:dem":624,
    "gn:feature_class":"P",
    "gn:feature_code":"PPL",
    "gn:name":"Peroldrado",
    "gn:population":12,
    "gn:timezone":"Europe/Rome",
    "iso:country":"IT",
    "wof:name":"Peroldrado",
    "wof:placetype":"locality",
    "wof:population":12
},
  "geometry": {"coordinates":[7.32422,45.12677],"type":"Point"}
}