{
  "type": "Feature",
  "properties": {
    "gn:admin1_code":"20",
    "gn:admin2_code":"BL",
    "gn:admin3_code":"25070.0",
    "gn:asciiname":"Area Artigianale del Fagher",
    "gn:country_code":"IT",
    "gn:dem":234,
    "gn:feature_class":"P",
    "gn:feature_code":"PPL",
    "gn:name":"Area Artigianale del Fagher",
    "gn:population":80,
    "gn:timezone":"Europe/Rome",
    "iso:country":"IT",
    "wof:name":"Area Artigianale del Fagher",
    "wof:placetype":"locality",
    "wof:population":80
},
  "geometry": {"coordinates":[11.93605,45.92746],"type":"Point"}
}