{
  "type": "Feature",
  "properties": {
    "gn:admin1_code":"12",
    "gn:admin2_code":"BI",
    "gn:admin3_code":"96009.0",
    "gn:asciiname":"Molino-Vacchiero",
    "gn:country_code":"IT",
    "gn:dem":680,
    "gn:feature_class":"P",
    "gn:feature_code":"PPL",
    "gn:name":"Molino-Vacchiero",
    "gn:population":25,
    "gn:timezone":"Europe/Rome",
    "iso:country":"IT",
    "wof:name":"Molino-Vacchiero",
    "wof:placetype":"locality",
    "wof:population":25
},
  "geometry": {"coordinates":[8.09225,45.63822],"type":"Point"}
}