{
  "type": "Feature",
  "properties": {
    "gn:admin1_code":"20",
    "gn:admin2_code":"VR",
    "gn:admin3_code":"23080.0",
    "gn:asciiname":"San Bortolo",
    "gn:country_code":"IT",
    "gn:dem":905,
    "gn:feature_class":"P",
    "gn:feature_code":"PPL",
    "gn:name":"San Bortolo",
    "gn:population":99,
    "gn:timezone":"Europe/Rome",
    "iso:country":"IT",
    "wof:name":"San Bortolo",
    "wof:placetype":"locality",
    "wof:population":99
},
  "geometry": {"coordinates":[11.17967,45.60747],"type":"Point"}
}