{
  "type": "Feature",
  "properties": {
    "gn:admin1_code":"8",
    "gn:admin2_code":"SV",
    "gn:admin3_code":"9002.0",
    "gn:asciiname":"Rollo",
    "gn:country_code":"IT",
    "gn:dem":1,
    "gn:feature_class":"P",
    "gn:feature_code":"PPL",
    "gn:name":"Rollo",
    "gn:population":35,
    "gn:timezone":"Europe/Rome",
    "iso:country":"IT",
    "name:ang_x_preferred":[
        "Hrolf Gangere"
    ],
    "name:azb_x_preferred":[
        "\u0631\u0648\u0644\u0648"
    ],
    "name:bre_x_preferred":[
        "Rollon"
    ],
    "name:bul_x_preferred":[
        "\u0420\u043e\u043b\u043e"
    ],
    "name:cat_x_preferred":[
        "Rol\u00b7l\u00f3"
    ],
    "name:ces_x_preferred":[
        "Rollo"
    ],
    "name:dan_x_preferred":[
        "Rollo"
    ],
    "name:deu_x_preferred":[
        "Rollo"
    ],
    "name:ell_x_preferred":[
        "\u03a1\u03cc\u03bb\u03bb\u03bf"
    ],
    "name:epo_x_preferred":[
        "Rollo"
    ],
    "name:eus_x_preferred":[
        "Rollon"
    ],
    "name:fas_x_preferred":[
        "\u0631\u0648\u0644\u0648"
    ],
    "name:fin_x_preferred":[
        "Rollo"
    ],
    "name:fra_x_preferred":[
        "Rollon"
    ],
    "name:glg_x_preferred":[
        "Hrolf Ganger"
    ],
    "name:heb_x_preferred":[
        "\u05e8\u05d5\u05dc\u05d5 \u05de\u05e0\u05d5\u05e8\u05de\u05e0\u05d3\u05d9"
    ],
    "name:hrv_x_preferred":[
        "Rolon"
    ],
    "name:hye_x_preferred":[
        "\u054c\u0578\u056c\u056c\u0578\u0576"
    ],
    "name:ind_x_preferred":[
        "Rollo"
    ],
    "name:isl_x_preferred":[
        "G\u00f6ngu-Hr\u00f3lfur"
    ],
    "name:ita_x_preferred":[
        "Rollone"
    ],
    "name:nld_x_preferred":[
        "Rollo"
    ],
    "name:nrm_x_preferred":[
        "Rou"
    ],
    "name:pol_x_preferred":[
        "Rolf"
    ],
    "name:por_x_preferred":[
        "Rol\u00e3o"
    ],
    "name:ron_x_preferred":[
        "Rollo"
    ],
    "name:rus_x_preferred":[
        "\u0420\u043e\u043b\u043b\u043e\u043d"
    ],
    "name:sco_x_preferred":[
        "Rollo"
    ],
    "name:spa_x_preferred":[
        "Hrolf Ganger"
    ],
    "name:sqi_x_preferred":[
        "Rollo"
    ],
    "name:srp_x_preferred":[
        "\u0420\u043e\u043b\u043e"
    ],
    "name:swe_x_preferred":[
        "Rollo"
    ],
    "name:tgl_x_preferred":[
        "Rolyon"
    ],
    "name:tha_x_preferred":[
        "\u0e23\u0e2d\u0e25\u0e42\u0e25\u0e41\u0e2b\u0e48\u0e07\u0e19\u0e2d\u0e23\u0e4c\u0e21\u0e47\u0e2d\u0e07\u0e14\u0e35"
    ],
    "name:tur_x_preferred":[
        "Rollo"
    ],
    "name:ukr_x_preferred":[
        "\u0420\u043e\u043b\u043b\u043e"
    ],
    "name:vls_x_preferred":[
        "Rollo"
    ],
    "name:zho_x_preferred":[
        "\u7f85\u6d1b"
    ],
    "wof:name":"Rollo",
    "wof:placetype":"locality",
    "wof:population":35
},
  "geometry": {"coordinates":[8.2167,44.06932000000001],"type":"Point"}
}