{
  "type": "Feature",
  "properties": {
    "gn:admin1_code":"8",
    "gn:admin2_code":"SV",
    "gn:admin3_code":"9002.0",
    "gn:asciiname":"Rollo",
    "gn:country_code":"IT",
    "gn:dem":1,
    "gn:feature_class":"P",
    "gn:feature_code":"PPL",
    "gn:name":"Rollo",
    "gn:population":35,
    "gn:timezone":"Europe/Rome",
    "iso:country":"IT",
    "wof:name":"Rollo",
    "wof:placetype":"locality",
    "wof:population":35
},
  "geometry": {"coordinates":[8.2167,44.06932000000001],"type":"Point"}
}