{
  "type": "Feature",
  "properties": {
    "gn:admin1_code":"9",
    "gn:admin2_code":"BG",
    "gn:admin3_code":"16196.0",
    "gn:asciiname":"Cassettone",
    "gn:country_code":"IT",
    "gn:dem":334,
    "gn:feature_class":"P",
    "gn:feature_code":"PPL",
    "gn:name":"Cassettone",
    "gn:population":179,
    "gn:timezone":"Europe/Rome",
    "iso:country":"IT",
    "wof:name":"Cassettone",
    "wof:placetype":"locality",
    "wof:population":179
},
  "geometry": {"coordinates":[9.63699,45.7857],"type":"Point"}
}