{
  "type": "Feature",
  "properties": {
    "gn:country":"IT",
    "gn:fcode":"PPL",
    "gn:population":0,
    "iso:country":"IT",
    "name:ceb_x_preferred":[
        "Cesuna"
    ],
    "name:eng_x_preferred":[
        "Cesuna"
    ],
    "name:fra_x_preferred":[
        "Cesuna"
    ],
    "name:ita_x_preferred":[
        "Cesuna"
    ],
    "name:nld_x_preferred":[
        "Cesuna"
    ],
    "name:srp_x_preferred":[
        "Cesuna"
    ],
    "qs_pg:aaroncc":"IT",
    "qs_pg:gn_country":"IT",
    "qs_pg:gn_fcode":"PPL",
    "qs_pg:gn_pop":0,
    "qs_pg:name":"Cesuna",
    "qs_pg:name_adm0":"Italia",
    "qs_pg:name_adm1":"Veneto",
    "qs_pg:photos":293,
    "qs_pg:photos_1k":59,
    "qs_pg:photos_9k":1,
    "qs_pg:photos_9r":4,
    "qs_pg:photos_all":293,
    "qs_pg:photos_sr":5,
    "qs_pg:pop_sr":0,
    "qs_pg:qs_pg_placetype":"locality",
    "qs_pg:qs_pg_placetype_gp":"Town",
    "qs_pg:woe_adm0":23424853,
    "woe:adm0_id":23424853,
    "woe:name_adm0":"Italia",
    "woe:name_adm1":"Veneto",
    "woe:placetype":"Town",
    "wof:name":"Cesuna",
    "wof:placetype":"locality",
    "wof:population":606
},
  "geometry": {"coordinates":[11.45,45.83333],"type":"Point"}
}