{
  "type": "Feature",
  "properties": {
    "gn:admin1_code":"8",
    "gn:admin2_code":"SV",
    "gn:admin3_code":"9060.0",
    "gn:asciiname":"Dani",
    "gn:country_code":"IT",
    "gn:dem":361,
    "gn:feature_class":"P",
    "gn:feature_code":"PPL",
    "gn:name":"Dani",
    "gn:population":13,
    "gn:timezone":"Europe/Rome",
    "iso:country":"IT",
    "name:bos_x_preferred":[
        "Dani"
    ],
    "name:bul_x_preferred":[
        "\u0414\u0430\u043d\u0438"
    ],
    "name:ceb_x_preferred":[
        "Dani"
    ],
    "name:deu_x_preferred":[
        "Dani"
    ],
    "name:fra_x_preferred":[
        "Dani"
    ],
    "name:hrv_x_preferred":[
        "Dani"
    ],
    "name:hun_x_preferred":[
        "Dani"
    ],
    "name:ind_x_preferred":[
        "Dani"
    ],
    "name:ita_x_preferred":[
        "Dani"
    ],
    "name:jpn_x_preferred":[
        "\u30c0\u30cb"
    ],
    "name:nld_x_preferred":[
        "Dani"
    ],
    "name:rus_x_preferred":[
        "\u0414\u0430\u043d\u0438"
    ],
    "name:slk_x_preferred":[
        "Dani"
    ],
    "name:slv_x_preferred":[
        "Dani"
    ],
    "name:srp_x_preferred":[
        "Dani"
    ],
    "name:swe_x_preferred":[
        "Dani"
    ],
    "name:zho_x_preferred":[
        "Dani"
    ],
    "wof:name":"Dani",
    "wof:placetype":"locality",
    "wof:population":13
},
  "geometry": {"coordinates":[8.03362,44.00351],"type":"Point"}
}