{
  "type": "Feature",
  "properties": {
    "gn:admin1_code":"8",
    "gn:admin2_code":"SV",
    "gn:admin3_code":"9060.0",
    "gn:asciiname":"Dani",
    "gn:country_code":"IT",
    "gn:dem":361,
    "gn:feature_class":"P",
    "gn:feature_code":"PPL",
    "gn:name":"Dani",
    "gn:population":13,
    "gn:timezone":"Europe/Rome",
    "iso:country":"IT",
    "wof:name":"Dani",
    "wof:placetype":"locality",
    "wof:population":13
},
  "geometry": {"coordinates":[8.03362,44.00351],"type":"Point"}
}