{
  "type": "Feature",
  "properties": {
    "gn:admin1_code":"20",
    "gn:admin2_code":"PD",
    "gn:admin3_code":"28013.0",
    "gn:asciiname":"Ronchi",
    "gn:country_code":"IT",
    "gn:dem":13,
    "gn:feature_class":"P",
    "gn:feature_code":"PPL",
    "gn:name":"Ronchi",
    "gn:population":276,
    "gn:timezone":"Europe/Rome",
    "iso:country":"IT",
    "wof:name":"Ronchi",
    "wof:placetype":"locality",
    "wof:population":276
},
  "geometry": {"coordinates":[11.98109,45.5222],"type":"Point"}
}