{
  "type": "Feature",
  "properties": {
    "gn:admin1_code":"6.0",
    "gn:admin2_code":"UD",
    "gn:admin3_code":"30033.0",
    "gn:asciiname":"Dogna",
    "gn:country_code":"IT",
    "gn:dem":440,
    "gn:elevation":"419.0",
    "gn:feature_class":"P",
    "gn:feature_code":"PPLA3",
    "gn:name":"Dogna",
    "gn:population":100,
    "gn:timezone":"Europe/Rome",
    "iso:country":"IT",
    "name:eng_x_preferred":[
        "Dogna"
    ],
    "name:epo_x_preferred":[
        "Dogna"
    ],
    "name:fra_x_preferred":[
        "Dogna"
    ],
    "name:fur_x_preferred":[
        "Dogne"
    ],
    "name:ita_x_preferred":[
        "Dogna"
    ],
    "name:nap_x_preferred":[
        "Dogna"
    ],
    "name:nld_x_preferred":[
        "Dogna"
    ],
    "name:pol_x_preferred":[
        "Dogna"
    ],
    "name:por_x_preferred":[
        "Dogna"
    ],
    "wof:name":"Dogna",
    "wof:placetype":"locality",
    "wof:population":100
},
  "geometry": {"coordinates":[13.31502,46.44793],"type":"Point"}
}