{
  "type": "Feature",
  "properties": {
    "gn:admin1_code":"6.0",
    "gn:admin2_code":"UD",
    "gn:admin3_code":"30033.0",
    "gn:asciiname":"Dogna",
    "gn:country_code":"IT",
    "gn:dem":440,
    "gn:elevation":"419.0",
    "gn:feature_class":"P",
    "gn:feature_code":"PPLA3",
    "gn:name":"Dogna",
    "gn:population":100,
    "gn:timezone":"Europe/Rome",
    "iso:country":"IT",
    "name:azb_x_preferred":[
        "\u062f\u0648\u0642\u0646\u0627"
    ],
    "name:bel_x_preferred":[
        "\u0414\u043e\u043d\u2019\u044f"
    ],
    "name:bul_x_preferred":[
        "\u0414\u043e\u043d\u044f"
    ],
    "name:cat_x_preferred":[
        "Dogna"
    ],
    "name:ceb_x_preferred":[
        "Dogna"
    ],
    "name:deu_x_preferred":[
        "Dogna"
    ],
    "name:eng_x_preferred":[
        "Dogna"
    ],
    "name:epo_x_preferred":[
        "Dogna"
    ],
    "name:eus_x_preferred":[
        "Dogna"
    ],
    "name:fas_x_preferred":[
        "\u062f\u0648\u06af\u0646\u0627"
    ],
    "name:fra_x_preferred":[
        "Dogna"
    ],
    "name:fur_x_preferred":[
        "Dogne"
    ],
    "name:hun_x_preferred":[
        "Dogna"
    ],
    "name:hye_x_preferred":[
        "\u0534\u0578\u0576\u0575\u0561"
    ],
    "name:ina_x_preferred":[
        "Dogna"
    ],
    "name:ind_x_preferred":[
        "Dogna"
    ],
    "name:ita_x_preferred":[
        "Dogna"
    ],
    "name:jpn_x_preferred":[
        "\u30c9\u30fc\u30cb\u30e3"
    ],
    "name:kaz_x_preferred":[
        "\u0414\u043e\u043d\u044c\u044f"
    ],
    "name:lat_x_preferred":[
        "Dogna"
    ],
    "name:lmo_x_preferred":[
        "Dogna"
    ],
    "name:msa_x_preferred":[
        "Dogna"
    ],
    "name:nap_x_preferred":[
        "Dogna"
    ],
    "name:nld_x_preferred":[
        "Dogna"
    ],
    "name:pms_x_preferred":[
        "Dogna"
    ],
    "name:pol_x_preferred":[
        "Dogna"
    ],
    "name:por_x_preferred":[
        "Dogna"
    ],
    "name:ron_x_preferred":[
        "Dogna"
    ],
    "name:rus_x_preferred":[
        "\u0414\u043e\u043d\u044c\u044f"
    ],
    "name:scn_x_preferred":[
        "Dogna"
    ],
    "name:spa_x_preferred":[
        "Dogna"
    ],
    "name:srp_x_preferred":[
        "\u0414\u043e\u045a\u0430"
    ],
    "name:ukr_x_preferred":[
        "\u0414\u043e\u043d\u044c\u044f"
    ],
    "name:uzb_x_preferred":[
        "Dogna"
    ],
    "name:vie_x_preferred":[
        "Dogna"
    ],
    "name:vol_x_preferred":[
        "Dogna"
    ],
    "name:war_x_preferred":[
        "Dogna"
    ],
    "name:zho_x_preferred":[
        "\u591a\u5c3c\u4e9a"
    ],
    "wof:name":"Dogna",
    "wof:placetype":"locality",
    "wof:population":100
},
  "geometry": {"coordinates":[13.31502,46.44793],"type":"Point"}
}