{
  "type": "Feature",
  "properties": {
    "gn:admin1_code":"13.0",
    "gn:admin2_code":"BA",
    "gn:admin3_code":"72028.0",
    "gn:asciiname":"San Maderno",
    "gn:country_code":"IT",
    "gn:dem":114,
    "gn:feature_class":"P",
    "gn:feature_code":"PPL",
    "gn:name":"San Maderno",
    "gn:population":0,
    "gn:timezone":"Europe/Rome",
    "iso:country":"IT",
    "wof:name":"San Maderno",
    "wof:placetype":"locality"
},
  "geometry": {"coordinates":[17.04666,41.03547],"type":"Point"}
}