{
  "type": "Feature",
  "properties": {
    "gn:admin1_code":"12",
    "gn:admin2_code":"CN",
    "gn:admin3_code":"4134.0",
    "gn:asciiname":"Villero",
    "gn:country_code":"IT",
    "gn:dem":692,
    "gn:feature_class":"P",
    "gn:feature_code":"PPL",
    "gn:name":"Villero",
    "gn:population":83,
    "gn:timezone":"Europe/Rome",
    "iso:country":"IT",
    "wof:name":"Villero",
    "wof:placetype":"locality",
    "wof:population":83
},
  "geometry": {"coordinates":[7.84551,44.29985],"type":"Point"}
}