{
  "type": "Feature",
  "properties": {
    "gn:admin1_code":"5.0",
    "gn:admin2_code":"PR",
    "gn:admin3_code":"34011.0",
    "gn:asciiname":"Ponte",
    "gn:country_code":"IT",
    "gn:dem":467,
    "gn:feature_class":"P",
    "gn:feature_code":"PPL",
    "gn:name":"Ponte",
    "gn:population":28,
    "gn:timezone":"Europe/Rome",
    "iso:country":"IT",
    "wof:name":"Ponte",
    "wof:placetype":"locality",
    "wof:population":28
},
  "geometry": {"coordinates":[9.65909,44.49513],"type":"Point"}
}