{
  "type": "Feature",
  "properties": {
    "gn:admin1_code":"1.0",
    "gn:admin2_code":"AQ",
    "gn:admin3_code":"66095.0",
    "gn:asciiname":"Cave",
    "gn:country_code":"IT",
    "gn:dem":870,
    "gn:elevation":"898.0",
    "gn:feature_class":"P",
    "gn:feature_code":"PPL",
    "gn:name":"Cave",
    "gn:population":100,
    "gn:timezone":"Europe/Rome",
    "iso:country":"IT",
    "wof:name":"Cave",
    "wof:placetype":"locality",
    "wof:population":100
},
  "geometry": {"coordinates":[13.24634,42.36546],"type":"Point"}
}