{
  "type": "Feature",
  "properties": {
    "gn:admin1_code":"7",
    "gn:admin2_code":"LT",
    "gn:admin3_code":"59005.0",
    "gn:asciiname":"Tenuta",
    "gn:country_code":"IT",
    "gn:dem":67,
    "gn:feature_class":"P",
    "gn:feature_code":"PPL",
    "gn:name":"Tenuta",
    "gn:population":18,
    "gn:timezone":"Europe/Rome",
    "iso:country":"IT",
    "name:deu_x_preferred":[
        "Tenuta"
    ],
    "name:ita_x_preferred":[
        "Tenuta"
    ],
    "wof:name":"Tenuta",
    "wof:placetype":"locality",
    "wof:population":18
},
  "geometry": {"coordinates":[12.79927,41.57363],"type":"Point"}
}