{
  "type": "Feature",
  "properties": {
    "gn:admin1_code":"4",
    "gn:admin2_code":"AV",
    "gn:admin3_code":"64072.0",
    "gn:asciiname":"Dentecane",
    "gn:country_code":"IT",
    "gn:dem":390,
    "gn:feature_class":"P",
    "gn:feature_code":"PPL",
    "gn:name":"Dentecane",
    "gn:population":201,
    "gn:timezone":"Europe/Rome",
    "iso:country":"IT",
    "wof:name":"Dentecane",
    "wof:placetype":"locality",
    "wof:population":201
},
  "geometry": {"coordinates":[14.89419,41.03588],"type":"Point"}
}