{
  "type": "Feature",
  "properties": {
    "gn:admin1_code":"20",
    "gn:admin2_code":"VI",
    "gn:admin3_code":"24100.0",
    "gn:asciiname":"Reghellini",
    "gn:country_code":"IT",
    "gn:dem":510,
    "gn:feature_class":"P",
    "gn:feature_code":"PPLL",
    "gn:name":"Reghellini",
    "gn:population":9,
    "gn:timezone":"Europe/Rome",
    "iso:country":"IT",
    "wof:name":"Reghellini",
    "wof:placetype":"locality",
    "wof:population":9
},
  "geometry": {"coordinates":[11.34176,45.73891],"type":"Point"}
}