{
  "type": "Feature",
  "properties": {
    "gn:admin1_code":"7",
    "gn:admin2_code":"RM",
    "gn:admin3_code":"58041.0",
    "gn:asciiname":"Le Cese",
    "gn:country_code":"IT",
    "gn:dem":247,
    "gn:feature_class":"P",
    "gn:feature_code":"PPL",
    "gn:name":"Le Cese",
    "gn:population":12,
    "gn:timezone":"Europe/Rome",
    "iso:country":"IT",
    "wof:name":"Le Cese",
    "wof:placetype":"locality",
    "wof:population":12
},
  "geometry": {"coordinates":[13.05779,41.71697],"type":"Point"}
}