{
  "type": "Feature",
  "properties": {
    "iso:country":"IT",
    "name:fra_x_preferred":[
        "Settecamini"
    ],
    "name:ita_x_preferred":[
        "Settecamini"
    ],
    "wof:name":"Settecamini",
    "wof:placetype":"neighbourhood"
},
  "geometry": {"coordinates":[12.62289736686871,41.93672210643694],"type":"Point"}
}