{
  "type": "Feature",
  "properties": {
    "gn:admin1_code":"20",
    "gn:admin2_code":"PD",
    "gn:admin3_code":"28103.0",
    "gn:asciiname":"Cascina Norbiato",
    "gn:country_code":"IT",
    "gn:dem":17,
    "gn:feature_class":"P",
    "gn:feature_code":"PPL",
    "gn:name":"Cascina Norbiato",
    "gn:population":117,
    "gn:timezone":"Europe/Rome",
    "iso:country":"IT",
    "wof:name":"Cascina Norbiato",
    "wof:placetype":"locality",
    "wof:population":117
},
  "geometry": {"coordinates":[11.81534,45.45026],"type":"Point"}
}