{
  "type": "Feature",
  "properties": {
    "gn:admin1_code":"3",
    "gn:admin2_code":"CS",
    "gn:admin3_code":"78040.0",
    "gn:asciiname":"Rammatico",
    "gn:country_code":"IT",
    "gn:dem":277,
    "gn:feature_class":"P",
    "gn:feature_code":"PPL",
    "gn:name":"Rammatico",
    "gn:population":51,
    "gn:timezone":"Europe/Rome",
    "iso:country":"IT",
    "wof:name":"Rammatico",
    "wof:placetype":"locality",
    "wof:population":51
},
  "geometry": {"coordinates":[15.97836,39.53265],"type":"Point"}
}