{
  "type": "Feature",
  "properties": {
    "gn:admin1_code":"12",
    "gn:admin2_code":"AT",
    "gn:admin3_code":"5108.0",
    "gn:asciiname":"Mulino",
    "gn:country_code":"IT",
    "gn:dem":137,
    "gn:feature_class":"P",
    "gn:feature_code":"PPL",
    "gn:name":"Mulino",
    "gn:population":19,
    "gn:timezone":"Europe/Rome",
    "iso:country":"IT",
    "wof:name":"Mulino",
    "wof:placetype":"locality",
    "wof:population":19
},
  "geometry": {"coordinates":[8.10958,44.88604],"type":"Point"}
}