{
  "type": "Feature",
  "properties": {
    "gn:admin1_code":"20",
    "gn:admin2_code":"VR",
    "gn:admin3_code":"23083.0",
    "gn:asciiname":"Fratelli Rosselli",
    "gn:country_code":"IT",
    "gn:dem":141,
    "gn:feature_class":"P",
    "gn:feature_code":"PPL",
    "gn:name":"Fratelli Rosselli",
    "gn:population":19,
    "gn:timezone":"Europe/Rome",
    "iso:country":"IT",
    "wof:name":"Fratelli Rosselli",
    "wof:placetype":"locality",
    "wof:population":19
},
  "geometry": {"coordinates":[10.82617,45.44361],"type":"Point"}
}