{
  "type": "Feature",
  "properties": {
    "gn:admin1_code":"9",
    "gn:admin2_code":"PV",
    "gn:admin3_code":"18024.0",
    "gn:asciiname":"Casottelli",
    "gn:country_code":"IT",
    "gn:dem":57,
    "gn:feature_class":"P",
    "gn:feature_code":"PPL",
    "gn:name":"Casottelli",
    "gn:population":24,
    "gn:timezone":"Europe/Rome",
    "iso:country":"IT",
    "wof:name":"Casottelli",
    "wof:placetype":"locality",
    "wof:population":24
},
  "geometry": {"coordinates":[9.24943,45.10882],"type":"Point"}
}