{
  "type": "Feature",
  "properties": {
    "gn:admin1_code":"5",
    "gn:admin2_code":"FC",
    "gn:admin3_code":"40037.0",
    "gn:asciiname":"Villa Venti",
    "gn:country_code":"IT",
    "gn:dem":195,
    "gn:feature_class":"P",
    "gn:feature_code":"PPL",
    "gn:name":"Villa Venti",
    "gn:population":16,
    "gn:timezone":"Europe/Rome",
    "iso:country":"IT",
    "wof:name":"Villa Venti",
    "wof:placetype":"locality",
    "wof:population":16
},
  "geometry": {"coordinates":[12.31786,44.0582],"type":"Point"}
}