{
  "type": "Feature",
  "properties": {
    "gn:admin1_code":"20",
    "gn:admin2_code":"PD",
    "gn:admin3_code":"28009.0",
    "gn:asciiname":"Banze",
    "gn:country_code":"IT",
    "gn:dem":16,
    "gn:feature_class":"P",
    "gn:feature_code":"PPL",
    "gn:name":"Banze",
    "gn:population":34,
    "gn:timezone":"Europe/Rome",
    "iso:country":"IT",
    "wof:name":"Banze",
    "wof:placetype":"locality",
    "wof:population":34
},
  "geometry": {"coordinates":[11.64527,45.25625],"type":"Point"}
}