{
  "type": "Feature",
  "properties": {
    "gn:admin1_code":"20.0",
    "gn:admin2_code":"BL",
    "gn:admin3_code":"25021.0",
    "gn:asciiname":"Pren",
    "gn:country_code":"IT",
    "gn:dem":530,
    "gn:feature_class":"P",
    "gn:feature_code":"PPL",
    "gn:name":"Pren",
    "gn:population":168,
    "gn:timezone":"Europe/Rome",
    "iso:country":"IT",
    "wof:name":"Pren",
    "wof:placetype":"locality",
    "wof:population":168
},
  "geometry": {"coordinates":[11.89463,46.05722],"type":"Point"}
}