{
  "type": "Feature",
  "properties": {
    "gn:admin1_code":"9.0",
    "gn:admin2_code":"SO",
    "gn:admin3_code":"14073.0",
    "gn:asciiname":"Malga dei Forni",
    "gn:cc2":"IT",
    "gn:country_code":"IT",
    "gn:dem":2199,
    "gn:feature_class":"P",
    "gn:feature_code":"PPL",
    "gn:name":"Malga dei Forni",
    "gn:population":0,
    "gn:timezone":"Europe/Rome",
    "iso:country":"IT",
    "name:und_x_variant":[
        "Malga del Forno",
        "Malga dei Forni"
    ],
    "wof:name":"Malga dei Forni",
    "wof:placetype":"locality"
},
  "geometry": {"coordinates":[10.55,46.41667],"type":"Point"}
}