{
  "type": "Feature",
  "properties": {
    "gn:admin1_code":"12",
    "gn:admin2_code":"VB",
    "gn:admin3_code":"103069.0",
    "gn:asciiname":"Fornero",
    "gn:country_code":"IT",
    "gn:dem":587,
    "gn:feature_class":"P",
    "gn:feature_code":"PPL",
    "gn:name":"Fornero",
    "gn:population":191,
    "gn:timezone":"Europe/Rome",
    "iso:country":"IT",
    "wof:name":"Fornero",
    "wof:placetype":"locality",
    "wof:population":191
},
  "geometry": {"coordinates":[8.33165,45.90579],"type":"Point"}
}