{
  "type": "Feature",
  "properties": {
    "gn:admin1_code":"6.0",
    "gn:admin2_code":"UD",
    "gn:admin3_code":"30071.0",
    "gn:asciiname":"Casali Sega II",
    "gn:country_code":"IT",
    "gn:dem":818,
    "gn:feature_class":"P",
    "gn:feature_code":"PPL",
    "gn:name":"Casali Sega II",
    "gn:population":23,
    "gn:timezone":"Europe/Rome",
    "iso:country":"IT",
    "wof:name":"Casali Sega II",
    "wof:placetype":"locality",
    "wof:population":23
},
  "geometry": {"coordinates":[13.00705,46.57662],"type":"Point"}
}