{
  "type": "Feature",
  "properties": {
    "gn:admin1_code":"4",
    "gn:admin3_code":"63034.0",
    "gn:asciiname":"Pini Nord E",
    "gn:country_code":"IT",
    "gn:dem":1,
    "gn:feature_class":"P",
    "gn:feature_code":"PPL",
    "gn:name":"Pini Nord E",
    "gn:population":92,
    "gn:timezone":"Europe/Rome",
    "iso:country":"IT",
    "wof:name":"Pini Nord E",
    "wof:placetype":"locality",
    "wof:population":92
},
  "geometry": {"coordinates":[14.04219,40.91397],"type":"Point"}
}