{
  "type": "Feature",
  "properties": {
    "gn:admin1_code":"7.0",
    "gn:admin2_code":"RM",
    "gn:admin3_code":"58104.0",
    "gn:asciiname":"Martellona I",
    "gn:country_code":"IT",
    "gn:dem":34,
    "gn:feature_class":"P",
    "gn:feature_code":"PPL",
    "gn:name":"Martellona I",
    "gn:population":438,
    "gn:timezone":"Europe/Rome",
    "iso:country":"IT",
    "wof:name":"Martellona I",
    "wof:placetype":"locality",
    "wof:population":438
},
  "geometry": {"coordinates":[12.69598,41.9397],"type":"Point"}
}