{
  "type": "Feature",
  "properties": {
    "gn:admin1_code":"18.0",
    "gn:admin2_code":"PG",
    "gn:admin3_code":"54035.0",
    "gn:asciiname":"Popoli",
    "gn:country_code":"IT",
    "gn:dem":710,
    "gn:elevation":"709.0",
    "gn:feature_class":"P",
    "gn:feature_code":"PPL",
    "gn:name":"Popoli",
    "gn:population":36,
    "gn:timezone":"Europe/Rome",
    "iso:country":"IT",
    "wof:name":"Popoli",
    "wof:placetype":"locality",
    "wof:population":36
},
  "geometry": {"coordinates":[13.10453,42.75172],"type":"Point"}
}