{
  "type": "Feature",
  "properties": {
    "gn:admin1_code":"18.0",
    "gn:admin2_code":"PG",
    "gn:admin3_code":"54035.0",
    "gn:asciiname":"Popoli",
    "gn:country_code":"IT",
    "gn:dem":710,
    "gn:elevation":"709.0",
    "gn:feature_class":"P",
    "gn:feature_code":"PPL",
    "gn:name":"Popoli",
    "gn:population":36,
    "gn:timezone":"Europe/Rome",
    "iso:country":"IT",
    "name:ara_x_preferred":[
        "\u0628\u0648\u0628\u0648\u0644\u064a"
    ],
    "name:azb_x_preferred":[
        "\u067e\u0648\u067e\u0648\u0644\u06cc"
    ],
    "name:bcl_x_preferred":[
        "Popoli"
    ],
    "name:bul_x_preferred":[
        "\u041f\u043e\u043f\u043e\u043b\u0438"
    ],
    "name:ceb_x_preferred":[
        "Popoli"
    ],
    "name:deu_x_preferred":[
        "Popoli"
    ],
    "name:epo_x_preferred":[
        "Popoli"
    ],
    "name:eus_x_preferred":[
        "Popoli"
    ],
    "name:fas_x_preferred":[
        "\u067e\u0648\u067e\u0648\u0644\u06cc"
    ],
    "name:fin_x_preferred":[
        "Popoli"
    ],
    "name:fra_x_preferred":[
        "Popoli"
    ],
    "name:hun_x_preferred":[
        "Popoli"
    ],
    "name:hye_x_preferred":[
        "\u054a\u0578\u057a\u0578\u056c\u056b"
    ],
    "name:ina_x_preferred":[
        "Popoli"
    ],
    "name:ita_x_preferred":[
        "Popoli"
    ],
    "name:jpn_x_preferred":[
        "\u30dd\u30fc\u30dd\u30ea"
    ],
    "name:kaz_x_preferred":[
        "\u041f\u043e\u043f\u043e\u043b\u0438"
    ],
    "name:kor_x_preferred":[
        "\ud3ec\ud3f4\ub9ac"
    ],
    "name:lat_x_preferred":[
        "Populum"
    ],
    "name:lmo_x_preferred":[
        "Popoli"
    ],
    "name:msa_x_preferred":[
        "Popoli"
    ],
    "name:nap_x_preferred":[
        "Popoli"
    ],
    "name:nld_x_preferred":[
        "Popoli"
    ],
    "name:pms_x_preferred":[
        "Popoli"
    ],
    "name:pol_x_preferred":[
        "Popoli"
    ],
    "name:por_x_preferred":[
        "Popoli"
    ],
    "name:ron_x_preferred":[
        "Popoli"
    ],
    "name:rus_x_preferred":[
        "\u041f\u043e\u043f\u043e\u043b\u0438"
    ],
    "name:spa_x_preferred":[
        "Popoli"
    ],
    "name:srp_x_preferred":[
        "\u041f\u043e\u043f\u043e\u043b\u0438"
    ],
    "name:tgl_x_preferred":[
        "Popoli"
    ],
    "name:ukr_x_preferred":[
        "\u041f\u043e\u043f\u043e\u043b\u0456"
    ],
    "name:uzb_x_preferred":[
        "Popoli"
    ],
    "name:vie_x_preferred":[
        "Popoli"
    ],
    "name:vol_x_preferred":[
        "Popoli"
    ],
    "name:war_x_preferred":[
        "Popoli"
    ],
    "name:zho_x_preferred":[
        "\u6ce2\u6ce2\u5229"
    ],
    "wof:name":"Popoli",
    "wof:placetype":"locality",
    "wof:population":36
},
  "geometry": {"coordinates":[13.10453,42.75172],"type":"Point"}
}