{
  "type": "Feature",
  "properties": {
    "gn:admin1_code":"18",
    "gn:admin2_code":"PG",
    "gn:admin3_code":"54046.0",
    "gn:asciiname":"Campitello",
    "gn:country_code":"IT",
    "gn:dem":659,
    "gn:feature_class":"P",
    "gn:feature_code":"PPL",
    "gn:name":"Campitello",
    "gn:population":64,
    "gn:timezone":"Europe/Rome",
    "iso:country":"IT",
    "name:cat_x_preferred":[
        "Campitello"
    ],
    "name:ceb_x_preferred":[
        "Campitello"
    ],
    "name:cos_x_preferred":[
        "Campitellu"
    ],
    "name:deu_x_preferred":[
        "Campitello"
    ],
    "name:eus_x_preferred":[
        "Campitello"
    ],
    "name:fra_x_preferred":[
        "Campitello"
    ],
    "name:hun_x_preferred":[
        "Campitello"
    ],
    "name:ita_x_preferred":[
        "Campitello"
    ],
    "name:kaz_x_preferred":[
        "\u041a\u0430\u043c\u043f\u0438\u0442\u0435\u043b\u043b\u043e"
    ],
    "name:lat_x_preferred":[
        "Campitello"
    ],
    "name:lmo_x_preferred":[
        "Campitello"
    ],
    "name:msa_x_preferred":[
        "Campitello"
    ],
    "name:nld_x_preferred":[
        "Campitello"
    ],
    "name:oci_x_preferred":[
        "Campitello"
    ],
    "name:pol_x_preferred":[
        "Campitello"
    ],
    "name:por_x_preferred":[
        "Campitello"
    ],
    "name:rus_x_preferred":[
        "\u041a\u0430\u043c\u043f\u0438\u0442\u0435\u043b\u043b\u043e"
    ],
    "name:sco_x_preferred":[
        "Campitello"
    ],
    "name:slk_x_preferred":[
        "Campitello"
    ],
    "name:slv_x_preferred":[
        "Campitello"
    ],
    "name:spa_x_preferred":[
        "Campitello"
    ],
    "name:srp_x_preferred":[
        "\u041a\u0430\u043c\u043f\u0438\u0442\u0435\u043b\u043e"
    ],
    "name:swe_x_preferred":[
        "Campitello"
    ],
    "name:ukr_x_preferred":[
        "\u041a\u0430\u043c\u043f\u0456\u0442\u0435\u043b\u043b\u043e"
    ],
    "name:vie_x_preferred":[
        "Campitello"
    ],
    "name:vol_x_preferred":[
        "Campitello"
    ],
    "name:war_x_preferred":[
        "Campitello"
    ],
    "wof:name":"Campitello",
    "wof:placetype":"locality",
    "wof:population":64
},
  "geometry": {"coordinates":[12.69252,43.40256],"type":"Point"}
}