{
  "type": "Feature",
  "properties": {
    "gn:admin1_code":"4",
    "gn:admin2_code":"BN",
    "gn:admin3_code":"62014.0",
    "gn:asciiname":"Marzano",
    "gn:country_code":"IT",
    "gn:dem":398,
    "gn:feature_class":"P",
    "gn:feature_code":"PPL",
    "gn:name":"Marzano",
    "gn:population":66,
    "gn:timezone":"Europe/Rome",
    "iso:country":"IT",
    "wof:name":"Marzano",
    "wof:placetype":"locality",
    "wof:population":66
},
  "geometry": {"coordinates":[14.65581,41.11949],"type":"Point"}
}