{
  "type": "Feature",
  "properties": {
    "gn:admin1_code":"16",
    "gn:admin2_code":"LU",
    "gn:admin3_code":"46008.0",
    "gn:asciiname":"Porreta",
    "gn:country_code":"IT",
    "gn:dem":951,
    "gn:feature_class":"P",
    "gn:feature_code":"PPL",
    "gn:name":"Porreta",
    "gn:population":53,
    "gn:timezone":"Europe/Rome",
    "iso:country":"IT",
    "wof:name":"Porreta",
    "wof:placetype":"locality",
    "wof:population":53
},
  "geometry": {"coordinates":[10.32223,44.08697],"type":"Point"}
}