{
  "type": "Feature",
  "properties": {
    "gn:admin1_code":"13.0",
    "gn:admin2_code":"LE",
    "gn:admin3_code":"75031.0",
    "gn:asciiname":"Baia di Gallipoli",
    "gn:country_code":"IT",
    "gn:dem":13,
    "gn:feature_class":"P",
    "gn:feature_code":"PPL",
    "gn:name":"Baia di Gallipoli",
    "gn:population":12,
    "gn:timezone":"Europe/Rome",
    "iso:country":"IT",
    "wof:name":"Baia di Gallipoli",
    "wof:placetype":"locality",
    "wof:population":12
},
  "geometry": {"coordinates":[18.03042,40.0011],"type":"Point"}
}