{
  "type": "Feature",
  "properties": {
    "gn:admin1_code":"4",
    "gn:admin2_code":"AV",
    "gn:admin3_code":"64053.0",
    "gn:asciiname":"Toriello-Petruzzielli",
    "gn:country_code":"IT",
    "gn:dem":463,
    "gn:feature_class":"P",
    "gn:feature_code":"PPL",
    "gn:name":"Toriello-Petruzzielli",
    "gn:population":40,
    "gn:timezone":"Europe/Rome",
    "iso:country":"IT",
    "wof:name":"Toriello-Petruzzielli",
    "wof:placetype":"locality",
    "wof:population":40
},
  "geometry": {"coordinates":[14.88094,40.98547],"type":"Point"}
}