{
  "type": "Feature",
  "properties": {
    "gn:admin1_code":"16",
    "gn:admin2_code":"FI",
    "gn:admin3_code":"48004.0",
    "gn:asciiname":"Castellina di Sotto",
    "gn:country_code":"IT",
    "gn:dem":195,
    "gn:feature_class":"P",
    "gn:feature_code":"PPL",
    "gn:name":"Castellina di Sotto",
    "gn:population":23,
    "gn:timezone":"Europe/Rome",
    "iso:country":"IT",
    "wof:name":"Castellina di Sotto",
    "wof:placetype":"locality",
    "wof:population":23
},
  "geometry": {"coordinates":[11.35253,43.95672],"type":"Point"}
}