{
  "type": "Feature",
  "properties": {
    "gn:admin1_code":"17.0",
    "gn:admin2_code":"TN",
    "gn:admin3_code":"22001.0",
    "gn:asciiname":"Santa Margherita",
    "gn:country_code":"IT",
    "gn:dem":168,
    "gn:elevation":"166.0",
    "gn:feature_class":"P",
    "gn:feature_code":"PPL",
    "gn:name":"Santa Margherita",
    "gn:population":744,
    "gn:timezone":"Europe/Rome",
    "iso:country":"IT",
    "wof:name":"Santa Margherita",
    "wof:placetype":"locality",
    "wof:population":744
},
  "geometry": {"coordinates":[11.02582,45.79781],"type":"Point"}
}