{
  "type": "Feature",
  "properties": {
    "gn:admin1_code":"5.0",
    "gn:admin2_code":"BO",
    "gn:admin3_code":"37041.0",
    "gn:asciiname":"Farneto",
    "gn:country_code":"IT",
    "gn:dem":409,
    "gn:feature_class":"P",
    "gn:feature_code":"PPL",
    "gn:name":"Farneto",
    "gn:population":0,
    "gn:timezone":"Europe/Rome",
    "iso:country":"IT",
    "wof:name":"Farneto",
    "wof:placetype":"locality"
},
  "geometry": {"coordinates":[11.46667,44.35],"type":"Point"}
}