{
  "type": "Feature",
  "properties": {
    "gn:admin1_code":"14",
    "gn:admin2_code":"SS",
    "gn:admin3_code":"90089.0",
    "gn:asciiname":"Tonnara Saline",
    "gn:country_code":"IT",
    "gn:dem":3,
    "gn:feature_class":"P",
    "gn:feature_code":"PPLL",
    "gn:name":"Tonnara Saline",
    "gn:population":7,
    "gn:timezone":"Europe/Rome",
    "iso:country":"IT",
    "wof:name":"Tonnara Saline",
    "wof:placetype":"locality",
    "wof:population":7
},
  "geometry": {"coordinates":[8.23403,40.91523],"type":"Point"}
}