{
  "type": "Feature",
  "properties": {
    "gn:admin1_code":"12",
    "gn:admin2_code":"AL",
    "gn:admin3_code":"6036.0",
    "gn:asciiname":"Ferrari",
    "gn:country_code":"IT",
    "gn:dem":313,
    "gn:feature_class":"P",
    "gn:feature_code":"PPLL",
    "gn:name":"Ferrari",
    "gn:population":9,
    "gn:timezone":"Europe/Rome",
    "iso:country":"IT",
    "wof:name":"Ferrari",
    "wof:placetype":"locality",
    "wof:population":9
},
  "geometry": {"coordinates":[8.43012,44.60725],"type":"Point"}
}