{
  "type": "Feature",
  "properties": {
    "gn:admin1_code":"4",
    "gn:admin2_code":"CE",
    "gn:admin3_code":"61061.0",
    "gn:asciiname":"Pellegrino",
    "gn:country_code":"IT",
    "gn:dem":126,
    "gn:feature_class":"P",
    "gn:feature_code":"PPL",
    "gn:name":"Pellegrino",
    "gn:population":22,
    "gn:timezone":"Europe/Rome",
    "iso:country":"IT",
    "wof:name":"Pellegrino",
    "wof:placetype":"locality",
    "wof:population":22
},
  "geometry": {"coordinates":[14.24995,41.19079],"type":"Point"}
}