{
  "type": "Feature",
  "properties": {
    "gn:admin1_code":"4",
    "gn:admin2_code":"CE",
    "gn:admin3_code":"61061.0",
    "gn:asciiname":"Pellegrino",
    "gn:country_code":"IT",
    "gn:dem":126,
    "gn:feature_class":"P",
    "gn:feature_code":"PPL",
    "gn:name":"Pellegrino",
    "gn:population":22,
    "gn:timezone":"Europe/Rome",
    "iso:country":"IT",
    "name:ceb_x_preferred":[
        "Pellegrino"
    ],
    "name:deu_x_preferred":[
        "Pellegrino"
    ],
    "name:fra_x_preferred":[
        "Pellegrino"
    ],
    "name:ita_x_preferred":[
        "Pellegrino"
    ],
    "name:nld_x_preferred":[
        "Pellegrino"
    ],
    "name:por_x_preferred":[
        "Pellegrino"
    ],
    "name:rus_x_preferred":[
        "\u041f\u0435\u043b\u044c\u0435\u0433\u0440\u0438\u043d\u043e"
    ],
    "name:srp_x_preferred":[
        "\u041f\u0435\u043b\u0435\u0433\u0440\u0438\u043d\u043e"
    ],
    "name:swe_x_preferred":[
        "Pellegrino"
    ],
    "name:ukr_x_preferred":[
        "\u041f\u0435\u043b\u043b\u0435\u0433\u0440\u0456\u043d\u043e"
    ],
    "wof:name":"Pellegrino",
    "wof:placetype":"locality",
    "wof:population":22
},
  "geometry": {"coordinates":[14.24995,41.19079],"type":"Point"}
}