{
  "type": "Feature",
  "properties": {
    "gn:admin1_code":"12",
    "gn:admin2_code":"AT",
    "gn:admin3_code":"5025.0",
    "gn:asciiname":"Moncestino",
    "gn:country_code":"IT",
    "gn:dem":173,
    "gn:feature_class":"P",
    "gn:feature_code":"PPL",
    "gn:name":"Moncestino",
    "gn:population":32,
    "gn:timezone":"Europe/Rome",
    "iso:country":"IT",
    "name:ara_x_preferred":[
        "\u0645\u0648\u0646\u062a\u0634\u0633\u062a\u064a\u0646\u0648"
    ],
    "name:azb_x_preferred":[
        "\u0645\u0648\u0646\u0686\u0633\u062a\u06cc\u0646\u0648"
    ],
    "name:bel_x_preferred":[
        "\u041c\u0430\u043d\u0447\u044d\u0441\u0446\u0456\u043d\u0430"
    ],
    "name:bul_x_preferred":[
        "\u041c\u043e\u043d\u0447\u0435\u0441\u0442\u0438\u043d\u043e"
    ],
    "name:cat_x_preferred":[
        "Moncestino"
    ],
    "name:ceb_x_preferred":[
        "Moncestino"
    ],
    "name:deu_x_preferred":[
        "Moncestino"
    ],
    "name:epo_x_preferred":[
        "Moncestino"
    ],
    "name:eus_x_preferred":[
        "Moncestino"
    ],
    "name:fas_x_preferred":[
        "\u0645\u0648\u0646\u0686\u0633\u062a\u06cc\u0646\u0648"
    ],
    "name:fra_x_preferred":[
        "Moncestino"
    ],
    "name:hun_x_preferred":[
        "Moncestino"
    ],
    "name:hye_x_preferred":[
        "\u0544\u0578\u0576\u0579\u0565\u057d\u057f\u056b\u0576\u0578"
    ],
    "name:ind_x_preferred":[
        "Moncestino"
    ],
    "name:ita_x_preferred":[
        "Moncestino"
    ],
    "name:jpn_x_preferred":[
        "\u30e2\u30f3\u30c1\u30a7\u30b9\u30c6\u30a3\u30fc\u30ce"
    ],
    "name:kaz_x_preferred":[
        "\u041c\u043e\u043d\u0447\u0435\u0441\u0442\u0438\u043d\u043e"
    ],
    "name:lat_x_preferred":[
        "Moncestinus"
    ],
    "name:lmo_x_preferred":[
        "Moncestino"
    ],
    "name:msa_x_preferred":[
        "Moncestino"
    ],
    "name:nap_x_preferred":[
        "Moncestino"
    ],
    "name:nld_x_preferred":[
        "Moncestino"
    ],
    "name:pms_x_preferred":[
        "Moncistin"
    ],
    "name:pol_x_preferred":[
        "Moncestino"
    ],
    "name:por_x_preferred":[
        "Moncestino"
    ],
    "name:ron_x_preferred":[
        "Moncestino"
    ],
    "name:rus_x_preferred":[
        "\u041c\u043e\u043d\u0447\u0435\u0441\u0442\u0438\u043d\u043e"
    ],
    "name:scn_x_preferred":[
        "Moncestino"
    ],
    "name:spa_x_preferred":[
        "Moncestino"
    ],
    "name:srp_x_preferred":[
        "\u041c\u043e\u043d\u0447\u0435\u0437\u0442\u0438\u043d\u043e"
    ],
    "name:tgl_x_preferred":[
        "Moncestino"
    ],
    "name:ukr_x_preferred":[
        "\u041c\u043e\u043d\u0447\u0435\u0441\u0442\u0456\u043d\u043e"
    ],
    "name:uzb_x_preferred":[
        "Moncestino"
    ],
    "name:vie_x_preferred":[
        "Moncestino"
    ],
    "name:vol_x_preferred":[
        "Moncestino"
    ],
    "name:war_x_preferred":[
        "Moncestino"
    ],
    "name:zho_x_preferred":[
        "\u8499\u5207\u65af\u8482\u8bfa"
    ],
    "wof:name":"Moncestino",
    "wof:placetype":"locality",
    "wof:population":32
},
  "geometry": {"coordinates":[8.1913,44.97191],"type":"Point"}
}