{
  "type": "Feature",
  "properties": {
    "gn:admin1_code":"12",
    "gn:admin2_code":"AT",
    "gn:admin3_code":"5025.0",
    "gn:asciiname":"Moncestino",
    "gn:country_code":"IT",
    "gn:dem":173,
    "gn:feature_class":"P",
    "gn:feature_code":"PPL",
    "gn:name":"Moncestino",
    "gn:population":32,
    "gn:timezone":"Europe/Rome",
    "iso:country":"IT",
    "wof:name":"Moncestino",
    "wof:placetype":"locality",
    "wof:population":32
},
  "geometry": {"coordinates":[8.1913,44.97191],"type":"Point"}
}