{
  "type": "Feature",
  "properties": {
    "gn:admin1_code":"7",
    "gn:admin2_code":"RI",
    "gn:admin3_code":"57069.0",
    "gn:asciiname":"Colli-Vallicelli",
    "gn:country_code":"IT",
    "gn:dem":612,
    "gn:feature_class":"P",
    "gn:feature_code":"PPL",
    "gn:name":"Colli-Vallicelli",
    "gn:population":62,
    "gn:timezone":"Europe/Rome",
    "iso:country":"IT",
    "wof:name":"Colli-Vallicelli",
    "wof:placetype":"locality",
    "wof:population":62
},
  "geometry": {"coordinates":[12.87244,42.257],"type":"Point"}
}