{
  "type": "Feature",
  "properties": {
    "gn:admin1_code":"17",
    "gn:admin2_code":"BZ",
    "gn:admin3_code":"21001.0",
    "gn:asciiname":"Grube",
    "gn:country_code":"IT",
    "gn:dem":1402,
    "gn:feature_class":"P",
    "gn:feature_code":"PPL",
    "gn:name":"Grube",
    "gn:population":24,
    "gn:timezone":"Europe/Rome",
    "iso:country":"IT",
    "name:ceb_x_preferred":[
        "Grube"
    ],
    "name:dan_x_preferred":[
        "Grube"
    ],
    "name:deu_x_preferred":[
        "Grube"
    ],
    "name:epo_x_preferred":[
        "Grube"
    ],
    "name:eus_x_preferred":[
        "Grube"
    ],
    "name:fas_x_preferred":[
        "\u06af\u0631\u0648\u0628\u0647"
    ],
    "name:fra_x_preferred":[
        "Grube"
    ],
    "name:hun_x_preferred":[
        "Grube"
    ],
    "name:ita_x_preferred":[
        "Grube"
    ],
    "name:mkd_x_preferred":[
        "\u0413\u0440\u0443\u0431\u0435"
    ],
    "name:msa_x_preferred":[
        "Grube"
    ],
    "name:nld_x_preferred":[
        "Grube"
    ],
    "name:nor_x_preferred":[
        "Grube"
    ],
    "name:pol_x_preferred":[
        "Grube"
    ],
    "name:por_x_preferred":[
        "Grube"
    ],
    "name:ron_x_preferred":[
        "Grube"
    ],
    "name:rus_x_preferred":[
        "\u0413\u0440\u0443\u0431\u0435"
    ],
    "name:spa_x_preferred":[
        "Grube"
    ],
    "name:srp_x_preferred":[
        "\u0413\u0440\u0443\u0431\u0435"
    ],
    "name:tur_x_preferred":[
        "Grube"
    ],
    "name:ukr_x_preferred":[
        "\u0413\u0440\u0443\u0431\u0435"
    ],
    "name:uzb_x_preferred":[
        "Grube"
    ],
    "name:vie_x_preferred":[
        "Grube"
    ],
    "name:vol_x_preferred":[
        "Grube"
    ],
    "name:war_x_preferred":[
        "Grube"
    ],
    "name:zho_x_preferred":[
        "\u683c\u9c81\u4f2f"
    ],
    "wof:name":"Grube",
    "wof:placetype":"locality",
    "wof:population":24
},
  "geometry": {"coordinates":[11.40114,46.34253],"type":"Point"}
}