{
  "type": "Feature",
  "properties": {
    "gn:admin1_code":"18.0",
    "gn:admin2_code":"TR",
    "gn:admin3_code":"55031.0",
    "gn:asciiname":"Zona Industriale Vascigliano",
    "gn:country_code":"IT",
    "gn:dem":180,
    "gn:feature_class":"P",
    "gn:feature_code":"PPL",
    "gn:name":"Zona Industriale Vascigliano",
    "gn:population":5,
    "gn:timezone":"Europe/Rome",
    "iso:country":"IT",
    "wof:name":"Zona Industriale Vascigliano",
    "wof:placetype":"locality",
    "wof:population":5
},
  "geometry": {"coordinates":[12.62584,42.49513],"type":"Point"}
}