{
  "type": "Feature",
  "properties": {
    "gn:admin1_code":"3",
    "gn:admin2_code":"CZ",
    "gn:admin3_code":"79043.0",
    "gn:asciiname":"Liardi",
    "gn:country_code":"IT",
    "gn:dem":757,
    "gn:feature_class":"P",
    "gn:feature_code":"PPL",
    "gn:name":"Liardi",
    "gn:population":47,
    "gn:timezone":"Europe/Rome",
    "iso:country":"IT",
    "wof:name":"Liardi",
    "wof:placetype":"locality",
    "wof:population":47
},
  "geometry": {"coordinates":[16.362,39.08097],"type":"Point"}
}