{
  "type": "Feature",
  "properties": {
    "gn:admin1_code":"16",
    "gn:admin2_code":"LI",
    "gn:admin3_code":"49009.0",
    "gn:asciiname":"Lazzaretto",
    "gn:country_code":"IT",
    "gn:dem":67,
    "gn:feature_class":"P",
    "gn:feature_code":"PPL",
    "gn:name":"Lazzaretto",
    "gn:population":27,
    "gn:timezone":"Europe/Rome",
    "iso:country":"IT",
    "wof:name":"Lazzaretto",
    "wof:placetype":"locality",
    "wof:population":27
},
  "geometry": {"coordinates":[10.35613,43.52395],"type":"Point"}
}