{
  "type": "Feature",
  "properties": {
    "gn:admin1_code":"2",
    "gn:admin2_code":"PZ",
    "gn:admin3_code":"76046.0",
    "gn:asciiname":"Arbusto",
    "gn:country_code":"IT",
    "gn:dem":629,
    "gn:feature_class":"P",
    "gn:feature_code":"PPL",
    "gn:name":"Arbusto",
    "gn:population":32,
    "gn:timezone":"Europe/Rome",
    "iso:country":"IT",
    "wof:name":"Arbusto",
    "wof:placetype":"locality",
    "wof:population":32
},
  "geometry": {"coordinates":[15.79967,40.36748],"type":"Point"}
}