{
  "type": "Feature",
  "properties": {
    "gn:admin1_code":"12",
    "gn:admin2_code":"TO",
    "gn:admin3_code":"1238.0",
    "gn:asciiname":"Sale",
    "gn:country_code":"IT",
    "gn:dem":564,
    "gn:feature_class":"P",
    "gn:feature_code":"PPL",
    "gn:name":"Sale",
    "gn:population":39,
    "gn:timezone":"Europe/Rome",
    "iso:country":"IT",
    "name:ben_x_preferred":[
        "\u09b8\u09c7\u09b2"
    ],
    "name:bul_x_preferred":[
        "\u0421\u0430\u043b\u0435"
    ],
    "name:cat_x_preferred":[
        "Sale"
    ],
    "name:ceb_x_preferred":[
        "Sale"
    ],
    "name:ces_x_preferred":[
        "Sale"
    ],
    "name:cym_x_preferred":[
        "Sale"
    ],
    "name:deu_x_preferred":[
        "Sale"
    ],
    "name:ell_x_preferred":[
        "\u03a3\u03ad\u03b9\u03bb"
    ],
    "name:fin_x_preferred":[
        "Sale"
    ],
    "name:fra_x_preferred":[
        "Sale"
    ],
    "name:heb_x_preferred":[
        "\u05e1\u05d9\u05d9\u05dc"
    ],
    "name:hin_x_preferred":[
        "\u0938\u0947\u0932"
    ],
    "name:hun_x_preferred":[
        "Sale"
    ],
    "name:hye_x_preferred":[
        "\u054d\u0561\u056c\u0565"
    ],
    "name:ind_x_preferred":[
        "Sale"
    ],
    "name:ita_x_preferred":[
        "Sale"
    ],
    "name:jpn_x_preferred":[
        "\u30bb\u30fc\u30eb"
    ],
    "name:lmo_x_preferred":[
        "S\u00e0le"
    ],
    "name:nld_x_preferred":[
        "Sale"
    ],
    "name:pol_x_preferred":[
        "Sale"
    ],
    "name:por_x_preferred":[
        "Sale"
    ],
    "name:rus_x_preferred":[
        "\u0421\u0430\u043b\u0435"
    ],
    "name:spa_x_preferred":[
        "Sale"
    ],
    "name:srp_x_preferred":[
        "Sale"
    ],
    "name:swe_x_preferred":[
        "Sale"
    ],
    "name:tur_x_preferred":[
        "Sale"
    ],
    "name:ukr_x_preferred":[
        "\u0421\u0430\u043b\u0435"
    ],
    "name:uzb_x_preferred":[
        "Sale"
    ],
    "wof:name":"Sale",
    "wof:placetype":"locality",
    "wof:population":39
},
  "geometry": {"coordinates":[7.61153,45.37719],"type":"Point"}
}