{
  "type": "Feature",
  "properties": {
    "gn:admin1_code":"12",
    "gn:admin2_code":"TO",
    "gn:admin3_code":"1238.0",
    "gn:asciiname":"Sale",
    "gn:country_code":"IT",
    "gn:dem":564,
    "gn:feature_class":"P",
    "gn:feature_code":"PPL",
    "gn:name":"Sale",
    "gn:population":39,
    "gn:timezone":"Europe/Rome",
    "iso:country":"IT",
    "wof:name":"Sale",
    "wof:placetype":"locality",
    "wof:population":39
},
  "geometry": {"coordinates":[7.61153,45.37719],"type":"Point"}
}