{
  "type": "Feature",
  "properties": {
    "gn:admin1_code":"5",
    "gn:admin2_code":"BO",
    "gn:admin3_code":"37059.0",
    "gn:asciiname":"Palazzina",
    "gn:country_code":"IT",
    "gn:dem":155,
    "gn:feature_class":"P",
    "gn:feature_code":"PPL",
    "gn:name":"Palazzina",
    "gn:population":72,
    "gn:timezone":"Europe/Rome",
    "iso:country":"IT",
    "wof:name":"Palazzina",
    "wof:placetype":"locality",
    "wof:population":72
},
  "geometry": {"coordinates":[11.15869,44.31207],"type":"Point"}
}