{
  "type": "Feature",
  "properties": {
    "gn:admin1_code":"12",
    "gn:admin2_code":"CN",
    "gn:admin3_code":"4141.0",
    "gn:asciiname":"Maglino",
    "gn:country_code":"IT",
    "gn:dem":706,
    "gn:feature_class":"P",
    "gn:feature_code":"PPL",
    "gn:name":"Maglino",
    "gn:population":24,
    "gn:timezone":"Europe/Rome",
    "iso:country":"IT",
    "wof:name":"Maglino",
    "wof:placetype":"locality",
    "wof:population":24
},
  "geometry": {"coordinates":[8.12593,44.37074000000001],"type":"Point"}
}