{
  "type": "Feature",
  "properties": {
    "gn:admin1_code":"12",
    "gn:admin2_code":"AL",
    "gn:admin3_code":"6160.0",
    "gn:asciiname":"Feriolo",
    "gn:country_code":"IT",
    "gn:dem":209,
    "gn:feature_class":"P",
    "gn:feature_code":"PPL",
    "gn:name":"Feriolo",
    "gn:population":98,
    "gn:timezone":"Europe/Rome",
    "iso:country":"IT",
    "wof:name":"Feriolo",
    "wof:placetype":"locality",
    "wof:population":98
},
  "geometry": {"coordinates":[8.86869,44.71102],"type":"Point"}
}