{
  "type": "Feature",
  "properties": {
    "gn:gn_country":"IT",
    "gn:gn_fcode":"PPLL",
    "gn:gn_pop":30,
    "gn:population":30,
    "iso:country":"IT",
    "name:baq_x_preferred":[
        "Tesselberg"
    ],
    "name:cat_x_preferred":[
        "Tesselberg"
    ],
    "name:cze_x_preferred":[
        "Tesselberg"
    ],
    "name:dan_x_preferred":[
        "Tesselberg"
    ],
    "name:dut_x_preferred":[
        "Tesselberg"
    ],
    "name:eng_x_preferred":[
        "Tesselberg"
    ],
    "name:fin_x_preferred":[
        "Tesselberg"
    ],
    "name:fre_x_preferred":[
        "Tesselberg"
    ],
    "name:ind_x_preferred":[
        "Tesselberg"
    ],
    "name:ita_x_preferred":[
        "Tesselberg"
    ],
    "name:nno_x_preferred":[
        "Tesselberg"
    ],
    "name:nob_x_preferred":[
        "Tesselberg"
    ],
    "name:oci_x_preferred":[
        "Tesselberg"
    ],
    "name:pol_x_preferred":[
        "Tesselberg"
    ],
    "name:por_x_preferred":[
        "Tesselberg"
    ],
    "name:rum_x_preferred":[
        "Tesselberg"
    ],
    "name:slo_x_preferred":[
        "Tesselberg"
    ],
    "name:slv_x_preferred":[
        "Tesselberg"
    ],
    "name:spa_x_preferred":[
        "Tesselberg"
    ],
    "name:srp_x_preferred":[
        "Tesselberg"
    ],
    "name:swe_x_preferred":[
        "Tesselberg"
    ],
    "name:tgl_x_preferred":[
        "Tesselberg"
    ],
    "name:tur_x_preferred":[
        "Tesselberg"
    ],
    "name:war_x_preferred":[
        "Tesselberg"
    ],
    "qs_pg:aaroncc":"IT",
    "qs_pg:gn_country":"IT",
    "qs_pg:gn_fcode":"PPLL",
    "qs_pg:gn_pop":30,
    "qs_pg:name":"Tesselberg",
    "qs_pg:photos_9r":0,
    "qs_pg:photos_sr":0,
    "qs_pg:pop_sr":1,
    "qs_pg:qs_pg_placetype":"locality",
    "wof:name":"Tesselberg",
    "wof:placetype":"locality",
    "wof:population":30
},
  "geometry": {"coordinates":[11.98436,46.82779],"type":"Point"}
}