{
  "type": "Feature",
  "properties": {
    "gn:admin1_code":"9",
    "gn:admin2_code":"BG",
    "gn:admin3_code":"16074.0",
    "gn:asciiname":"Tre Fontane",
    "gn:country_code":"IT",
    "gn:dem":199,
    "gn:feature_class":"P",
    "gn:feature_code":"PPLL",
    "gn:name":"Tre Fontane",
    "gn:population":7,
    "gn:timezone":"Europe/Rome",
    "iso:country":"IT",
    "wof:name":"Tre Fontane",
    "wof:placetype":"locality",
    "wof:population":7
},
  "geometry": {"coordinates":[9.45862,45.75113],"type":"Point"}
}