{
  "type": "Feature",
  "properties": {
    "gn:admin1_code":"20",
    "gn:admin2_code":"PD",
    "gn:admin3_code":"28080.0",
    "gn:asciiname":"Tergolina",
    "gn:country_code":"IT",
    "gn:dem":27,
    "gn:feature_class":"P",
    "gn:feature_code":"PPL",
    "gn:name":"Tergolina",
    "gn:population":26,
    "gn:timezone":"Europe/Rome",
    "iso:country":"IT",
    "wof:name":"Tergolina",
    "wof:placetype":"locality",
    "wof:population":26
},
  "geometry": {"coordinates":[11.88485,45.59614000000001],"type":"Point"}
}