{
  "type": "Feature",
  "properties": {
    "gn:admin1_code":"20",
    "gn:admin2_code":"BL",
    "gn:admin3_code":"25056.0",
    "gn:asciiname":"Piai",
    "gn:country_code":"IT",
    "gn:dem":444,
    "gn:feature_class":"P",
    "gn:feature_code":"PPLL",
    "gn:name":"Piai",
    "gn:population":10,
    "gn:timezone":"Europe/Rome",
    "iso:country":"IT",
    "wof:name":"Piai",
    "wof:placetype":"locality",
    "wof:population":10
},
  "geometry": {"coordinates":[12.1091,46.15125],"type":"Point"}
}