{
  "type": "Feature",
  "properties": {
    "gn:admin1_code":"5",
    "gn:admin2_code":"PR",
    "gn:admin3_code":"34015.0",
    "gn:asciiname":"Pizzale",
    "gn:country_code":"IT",
    "gn:dem":60,
    "gn:feature_class":"P",
    "gn:feature_code":"PPL",
    "gn:name":"Pizzale",
    "gn:population":14,
    "gn:timezone":"Europe/Rome",
    "iso:country":"IT",
    "name:ara_x_preferred":[
        "\u0628\u064a\u0632\u0627\u0644"
    ],
    "name:azb_x_preferred":[
        "\u067e\u06cc\u062a\u0632\u0627\u0644\u0647"
    ],
    "name:bel_x_preferred":[
        "\u041f\u0456\u0446\u0446\u0430\u043b\u0435"
    ],
    "name:ceb_x_preferred":[
        "Pizzale"
    ],
    "name:deu_x_preferred":[
        "Pizzale"
    ],
    "name:epo_x_preferred":[
        "Pizzale"
    ],
    "name:eus_x_preferred":[
        "Pizzale"
    ],
    "name:fas_x_preferred":[
        "\u067e\u06cc\u062a\u0632\u0627\u0644\u0647"
    ],
    "name:fra_x_preferred":[
        "Pizzale"
    ],
    "name:hun_x_preferred":[
        "Pizzale"
    ],
    "name:hye_x_preferred":[
        "\u054a\u056b\u0581\u0561\u056c\u0565"
    ],
    "name:ind_x_preferred":[
        "Pizzale"
    ],
    "name:ita_x_preferred":[
        "Pizzale"
    ],
    "name:jpn_x_preferred":[
        "\u30d4\u30c3\u30c4\u30a1\u30fc\u30ec"
    ],
    "name:kaz_x_preferred":[
        "\u041f\u0438\u0446\u0446\u0430\u043b\u0435"
    ],
    "name:lat_x_preferred":[
        "Pitiale"
    ],
    "name:lmo_x_preferred":[
        "Al Piss\u00e0"
    ],
    "name:msa_x_preferred":[
        "Pizzale"
    ],
    "name:nap_x_preferred":[
        "Pizzale"
    ],
    "name:nld_x_preferred":[
        "Pizzale"
    ],
    "name:pms_x_preferred":[
        "Pizzale"
    ],
    "name:pol_x_preferred":[
        "Pizzale"
    ],
    "name:por_x_preferred":[
        "Pizzale"
    ],
    "name:ron_x_preferred":[
        "Pizzale"
    ],
    "name:rus_x_preferred":[
        "\u041f\u0438\u0446\u0446\u0430\u043b\u0435"
    ],
    "name:scn_x_preferred":[
        "Pizzale"
    ],
    "name:spa_x_preferred":[
        "Pizzale"
    ],
    "name:srp_x_preferred":[
        "\u041f\u0438\u0446\u0430\u043b\u0435"
    ],
    "name:tgl_x_preferred":[
        "Pizzale"
    ],
    "name:ukr_x_preferred":[
        "\u041f\u0456\u0446\u0446\u0430\u043b\u0435"
    ],
    "name:uzb_x_preferred":[
        "Pizzale"
    ],
    "name:vie_x_preferred":[
        "Pizzale"
    ],
    "name:vol_x_preferred":[
        "Pizzale"
    ],
    "name:war_x_preferred":[
        "Pizzale"
    ],
    "name:zho_x_preferred":[
        "\u76ae\u624e\u83b1"
    ],
    "wof:name":"Pizzale",
    "wof:placetype":"locality",
    "wof:population":14
},
  "geometry": {"coordinates":[10.1364,44.85867],"type":"Point"}
}