{
  "type": "Feature",
  "properties": {
    "gn:admin1_code":"5",
    "gn:admin2_code":"PR",
    "gn:admin3_code":"34015.0",
    "gn:asciiname":"Pizzale",
    "gn:country_code":"IT",
    "gn:dem":60,
    "gn:feature_class":"P",
    "gn:feature_code":"PPL",
    "gn:name":"Pizzale",
    "gn:population":14,
    "gn:timezone":"Europe/Rome",
    "iso:country":"IT",
    "wof:name":"Pizzale",
    "wof:placetype":"locality",
    "wof:population":14
},
  "geometry": {"coordinates":[10.1364,44.85867],"type":"Point"}
}