{
  "type": "Feature",
  "properties": {
    "gn:admin1_code":"15",
    "gn:admin2_code":"ME",
    "gn:admin3_code":"83062.0",
    "gn:asciiname":"Vallancazza",
    "gn:country_code":"IT",
    "gn:dem":496,
    "gn:feature_class":"P",
    "gn:feature_code":"PPL",
    "gn:name":"Vallancazza",
    "gn:population":64,
    "gn:timezone":"Europe/Rome",
    "iso:country":"IT",
    "wof:name":"Vallancazza",
    "wof:placetype":"locality",
    "wof:population":64
},
  "geometry": {"coordinates":[15.10638,38.00624000000001],"type":"Point"}
}