{
  "type": "Feature",
  "properties": {
    "gn:admin1_code":"20.0",
    "gn:admin2_code":"RO",
    "gn:admin3_code":"29039.0",
    "gn:asciiname":"Polesine Camerini",
    "gn:country_code":"IT",
    "gn:dem":-3,
    "gn:elevation":"1.0",
    "gn:feature_class":"P",
    "gn:feature_code":"PPL",
    "gn:name":"Polesine Camerini",
    "gn:population":265,
    "gn:timezone":"Europe/Rome",
    "iso:country":"IT",
    "wof:name":"Polesine Camerini",
    "wof:placetype":"locality",
    "wof:population":265
},
  "geometry": {"coordinates":[12.44035,44.93743],"type":"Point"}
}