{
  "type": "Feature",
  "properties": {
    "gn:admin1_code":"9",
    "gn:admin2_code":"LO",
    "gn:admin3_code":"98047.0",
    "gn:asciiname":"Lazzaretto",
    "gn:country_code":"IT",
    "gn:dem":55,
    "gn:feature_class":"P",
    "gn:feature_code":"PPL",
    "gn:name":"Lazzaretto",
    "gn:population":67,
    "gn:timezone":"Europe/Rome",
    "iso:country":"IT",
    "wof:name":"Lazzaretto",
    "wof:placetype":"locality",
    "wof:population":67
},
  "geometry": {"coordinates":[9.71461,45.14912],"type":"Point"}
}