{
  "type": "Feature",
  "properties": {
    "gn:admin1_code":"4",
    "gn:admin2_code":"BN",
    "gn:admin3_code":"62060.0",
    "gn:asciiname":"Masserie",
    "gn:country_code":"IT",
    "gn:dem":327,
    "gn:feature_class":"P",
    "gn:feature_code":"PPL",
    "gn:name":"Masserie",
    "gn:population":21,
    "gn:timezone":"Europe/Rome",
    "iso:country":"IT",
    "wof:name":"Masserie",
    "wof:placetype":"locality",
    "wof:population":21
},
  "geometry": {"coordinates":[14.76501,41.07882],"type":"Point"}
}