{
  "type": "Feature",
  "properties": {
    "gn:admin1_code":"20",
    "gn:admin2_code":"PD",
    "gn:admin3_code":"28017.0",
    "gn:asciiname":"Case Barison",
    "gn:country_code":"IT",
    "gn:dem":14,
    "gn:feature_class":"P",
    "gn:feature_code":"PPL",
    "gn:name":"Case Barison",
    "gn:population":37,
    "gn:timezone":"Europe/Rome",
    "iso:country":"IT",
    "wof:name":"Case Barison",
    "wof:placetype":"locality",
    "wof:population":37
},
  "geometry": {"coordinates":[11.94852,45.5174],"type":"Point"}
}