{
  "type": "Feature",
  "properties": {
    "gn:admin1_code":"17",
    "gn:admin2_code":"BZ",
    "gn:admin3_code":"21029.0",
    "gn:asciiname":"Stazione",
    "gn:country_code":"IT",
    "gn:dem":212,
    "gn:feature_class":"P",
    "gn:feature_code":"PPL",
    "gn:name":"Stazione",
    "gn:population":122,
    "gn:timezone":"Europe/Rome",
    "iso:country":"IT",
    "wof:name":"Stazione",
    "wof:placetype":"locality",
    "wof:population":122
},
  "geometry": {"coordinates":[11.26188,46.32027],"type":"Point"}
}