{
  "type": "Feature",
  "properties": {
    "gn:admin1_code":"12",
    "gn:admin2_code":"CN",
    "gn:admin3_code":"4126.0",
    "gn:asciiname":"Comini di Vasco",
    "gn:country_code":"IT",
    "gn:dem":530,
    "gn:feature_class":"P",
    "gn:feature_code":"PPL",
    "gn:name":"Comini di Vasco",
    "gn:population":31,
    "gn:timezone":"Europe/Rome",
    "iso:country":"IT",
    "wof:name":"Comini di Vasco",
    "wof:placetype":"locality",
    "wof:population":31
},
  "geometry": {"coordinates":[7.82181,44.35011],"type":"Point"}
}