{
  "type": "Feature",
  "properties": {
    "gn:admin1_code":"12",
    "gn:admin2_code":"CN",
    "gn:admin3_code":"4154.0",
    "gn:asciiname":"Ruata",
    "gn:country_code":"IT",
    "gn:dem":1145,
    "gn:feature_class":"P",
    "gn:feature_code":"PPLL",
    "gn:name":"Ruata",
    "gn:population":5,
    "gn:timezone":"Europe/Rome",
    "iso:country":"IT",
    "wof:name":"Ruata",
    "wof:placetype":"locality",
    "wof:population":5
},
  "geometry": {"coordinates":[7.19071,44.6713],"type":"Point"}
}