{
  "type": "Feature",
  "properties": {
    "gn:admin1_code":"17.0",
    "gn:admin2_code":"TN",
    "gn:admin3_code":"22001.0",
    "gn:asciiname":"Ronchi",
    "gn:country_code":"IT",
    "gn:dem":688,
    "gn:elevation":"700.0",
    "gn:feature_class":"P",
    "gn:feature_code":"PPL",
    "gn:name":"Ronchi",
    "gn:population":49,
    "gn:timezone":"Europe/Rome",
    "iso:country":"IT",
    "wof:name":"Ronchi",
    "wof:placetype":"locality",
    "wof:population":49
},
  "geometry": {"coordinates":[11.06466,45.73927],"type":"Point"}
}