{
  "type": "Feature",
  "properties": {
    "gn:admin1_code":"8",
    "gn:admin2_code":"IM",
    "gn:admin3_code":"8033.0",
    "gn:asciiname":"Case Molini",
    "gn:country_code":"IT",
    "gn:dem":181,
    "gn:feature_class":"P",
    "gn:feature_code":"PPLL",
    "gn:name":"Case Molini",
    "gn:population":6,
    "gn:timezone":"Europe/Rome",
    "iso:country":"IT",
    "wof:name":"Case Molini",
    "wof:placetype":"locality",
    "wof:population":6
},
  "geometry": {"coordinates":[7.9695,43.9754],"type":"Point"}
}