{
  "type": "Feature",
  "properties": {
    "gn:admin1_code":"16",
    "gn:admin2_code":"PI",
    "gn:admin3_code":"50040.0",
    "gn:asciiname":"Ceppato",
    "gn:country_code":"IT",
    "gn:dem":247,
    "gn:feature_class":"P",
    "gn:feature_code":"PPL",
    "gn:name":"Ceppato",
    "gn:population":104,
    "gn:timezone":"Europe/Rome",
    "iso:country":"IT",
    "name:ceb_x_preferred":[
        "Ceppato"
    ],
    "name:fas_x_preferred":[
        "\u0633\u067e\u0627\u062a\u0648"
    ],
    "name:ita_x_preferred":[
        "Ceppato"
    ],
    "name:srp_x_preferred":[
        "\u0427\u0435\u043f\u0430\u0442\u043e"
    ],
    "wof:name":"Ceppato",
    "wof:placetype":"locality",
    "wof:population":104
},
  "geometry": {"coordinates":[10.5926,43.53091],"type":"Point"}
}