{
  "type": "Feature",
  "properties": {
    "gn:admin1_code":"20",
    "gn:admin2_code":"VE",
    "gn:admin3_code":"27037.0",
    "gn:asciiname":"Giusto",
    "gn:country_code":"IT",
    "gn:dem":8,
    "gn:feature_class":"P",
    "gn:feature_code":"PPL",
    "gn:name":"Giusto",
    "gn:population":39,
    "gn:timezone":"Europe/Rome",
    "iso:country":"IT",
    "wof:name":"Giusto",
    "wof:placetype":"locality",
    "wof:population":39
},
  "geometry": {"coordinates":[12.20471,45.57019],"type":"Point"}
}