{
  "type": "Feature",
  "properties": {
    "gn:admin1_code":"5",
    "gn:admin2_code":"PR",
    "gn:admin3_code":"34042.0",
    "gn:asciiname":"Orio",
    "gn:country_code":"IT",
    "gn:dem":226,
    "gn:feature_class":"P",
    "gn:feature_code":"PPL",
    "gn:name":"Orio",
    "gn:population":37,
    "gn:timezone":"Europe/Rome",
    "iso:country":"IT",
    "name:ara_x_preferred":[
        "\u0623\u0648\u0631\u064a\u0648"
    ],
    "name:arg_x_preferred":[
        "Orio"
    ],
    "name:ast_x_preferred":[
        "Orio"
    ],
    "name:bre_x_preferred":[
        "Orio"
    ],
    "name:cat_x_preferred":[
        "Orio"
    ],
    "name:ceb_x_preferred":[
        "Orio"
    ],
    "name:deu_x_preferred":[
        "Orio"
    ],
    "name:eus_x_preferred":[
        "Orio"
    ],
    "name:fra_x_preferred":[
        "Orio"
    ],
    "name:glg_x_preferred":[
        "Orio"
    ],
    "name:hun_x_preferred":[
        "Orio"
    ],
    "name:ita_x_preferred":[
        "Orio"
    ],
    "name:jpn_x_preferred":[
        "\u30aa\u30ea\u30aa"
    ],
    "name:msa_x_preferred":[
        "Orio"
    ],
    "name:nld_x_preferred":[
        "Orio"
    ],
    "name:oci_x_preferred":[
        "Orio"
    ],
    "name:pol_x_preferred":[
        "Orio"
    ],
    "name:por_x_preferred":[
        "Orio"
    ],
    "name:rus_x_preferred":[
        "\u041e\u0440\u0438\u043e"
    ],
    "name:spa_x_preferred":[
        "Orio"
    ],
    "name:swe_x_preferred":[
        "Orio"
    ],
    "name:ukr_x_preferred":[
        "\u041e\u0440\u0456\u043e"
    ],
    "name:uzb_x_preferred":[
        "Orio"
    ],
    "name:vie_x_preferred":[
        "Orio"
    ],
    "name:war_x_preferred":[
        "Orio"
    ],
    "name:zho_x_preferred":[
        "\u5965\u91cc\u5965"
    ],
    "wof:name":"Orio",
    "wof:placetype":"locality",
    "wof:population":37
},
  "geometry": {"coordinates":[10.35788,44.59492],"type":"Point"}
}