{
  "type": "Feature",
  "properties": {
    "gn:admin1_code":"9.0",
    "gn:admin2_code":"BS",
    "gn:admin3_code":"17065.0",
    "gn:asciiname":"Bessimo Superiore I",
    "gn:country_code":"IT",
    "gn:dem":209,
    "gn:feature_class":"P",
    "gn:feature_code":"PPL",
    "gn:name":"Bessimo Superiore I",
    "gn:population":43,
    "gn:timezone":"Europe/Rome",
    "iso:country":"IT",
    "wof:name":"Bessimo Superiore I",
    "wof:placetype":"locality",
    "wof:population":43
},
  "geometry": {"coordinates":[10.15664,45.87291],"type":"Point"}
}