{
  "type": "Feature",
  "properties": {
    "gn:admin1_code":"11",
    "gn:admin2_code":"CB",
    "gn:admin3_code":"70017.0",
    "gn:asciiname":"Cacerno",
    "gn:country_code":"IT",
    "gn:dem":854,
    "gn:feature_class":"P",
    "gn:feature_code":"PPL",
    "gn:name":"Cacerno",
    "gn:population":61,
    "gn:timezone":"Europe/Rome",
    "iso:country":"IT",
    "wof:name":"Cacerno",
    "wof:placetype":"locality",
    "wof:population":61
},
  "geometry": {"coordinates":[14.74645,41.46356],"type":"Point"}
}