{
  "type": "Feature",
  "properties": {
    "gn:admin1_code":"20",
    "gn:admin2_code":"TV",
    "gn:admin3_code":"26074.0",
    "gn:asciiname":"Case Risera",
    "gn:country_code":"IT",
    "gn:dem":21,
    "gn:feature_class":"P",
    "gn:feature_code":"PPL",
    "gn:name":"Case Risera",
    "gn:population":28,
    "gn:timezone":"Europe/Rome",
    "iso:country":"IT",
    "wof:name":"Case Risera",
    "wof:placetype":"locality",
    "wof:population":28
},
  "geometry": {"coordinates":[12.41117,45.79231],"type":"Point"}
}