{
  "type": "Feature",
  "properties": {
    "gn:admin1_code":"20.0",
    "gn:admin2_code":"PD",
    "gn:admin3_code":"28076.0",
    "gn:asciiname":"Paviola",
    "gn:country_code":"IT",
    "gn:dem":28,
    "gn:feature_class":"P",
    "gn:feature_code":"PPL",
    "gn:name":"Paviola",
    "gn:population":470,
    "gn:timezone":"Europe/Rome",
    "iso:country":"IT",
    "wof:name":"Paviola",
    "wof:placetype":"locality",
    "wof:population":470
},
  "geometry": {"coordinates":[11.8136,45.5734],"type":"Point"}
}