{
  "type": "Feature",
  "properties": {
    "gn:admin1_code":"4",
    "gn:admin2_code":"AV",
    "gn:admin3_code":"64112.0",
    "gn:asciiname":"Vecito",
    "gn:country_code":"IT",
    "gn:dem":847,
    "gn:feature_class":"P",
    "gn:feature_code":"PPL",
    "gn:name":"Vecito",
    "gn:population":24,
    "gn:timezone":"Europe/Rome",
    "iso:country":"IT",
    "wof:name":"Vecito",
    "wof:placetype":"locality",
    "wof:population":24
},
  "geometry": {"coordinates":[15.25091,41.04945],"type":"Point"}
}