{
  "type": "Feature",
  "properties": {
    "gn:admin1_code":"5.0",
    "gn:admin2_code":"BO",
    "gn:admin3_code":"37050.0",
    "gn:asciiname":"Bonconvento",
    "gn:country_code":"IT",
    "gn:dem":24,
    "gn:elevation":"29.0",
    "gn:feature_class":"P",
    "gn:feature_code":"PPL",
    "gn:name":"Bonconvento",
    "gn:population":63,
    "gn:timezone":"Europe/Rome",
    "iso:country":"IT",
    "wof:name":"Bonconvento",
    "wof:placetype":"locality",
    "wof:population":63
},
  "geometry": {"coordinates":[11.31093,44.60417],"type":"Point"}
}