{
  "type": "Feature",
  "properties": {
    "gn:admin1_code":"4.0",
    "gn:admin2_code":"AV",
    "gn:admin3_code":"64017.0",
    "gn:asciiname":"Materdomini",
    "gn:country_code":"IT",
    "gn:dem":539,
    "gn:feature_class":"P",
    "gn:feature_code":"PPL",
    "gn:name":"Materdomini",
    "gn:population":636,
    "gn:timezone":"Europe/Rome",
    "iso:country":"IT",
    "name:ceb_x_preferred":[
        "Materdomini"
    ],
    "name:ita_x_preferred":[
        "Materdomini"
    ],
    "name:nld_x_preferred":[
        "Materdomini"
    ],
    "name:srp_x_preferred":[
        "\u041c\u0430\u0442\u0435\u0440\u0434\u043e\u043c\u0438\u043d\u0438"
    ],
    "wof:name":"Materdomini",
    "wof:placetype":"locality",
    "wof:population":636
},
  "geometry": {"coordinates":[15.23587,40.81801],"type":"Point"}
}