{
  "type": "Feature",
  "properties": {
    "gn:admin1_code":"9",
    "gn:admin2_code":"BS",
    "gn:admin3_code":"17092.0",
    "gn:asciiname":"Malocco Sotto",
    "gn:country_code":"IT",
    "gn:dem":115,
    "gn:feature_class":"P",
    "gn:feature_code":"PPL",
    "gn:name":"Malocco Sotto",
    "gn:population":102,
    "gn:timezone":"Europe/Rome",
    "iso:country":"IT",
    "wof:name":"Malocco Sotto",
    "wof:placetype":"locality",
    "wof:population":102
},
  "geometry": {"coordinates":[10.47692,45.42496],"type":"Point"}
}