{
  "type": "Feature",
  "properties": {
    "gn:admin1_code":"20",
    "gn:admin2_code":"BL",
    "gn:admin3_code":"25026.0",
    "gn:asciiname":"Furianoi",
    "gn:country_code":"IT",
    "gn:dem":811,
    "gn:feature_class":"P",
    "gn:feature_code":"PPL",
    "gn:name":"Furianoi",
    "gn:population":26,
    "gn:timezone":"Europe/Rome",
    "iso:country":"IT",
    "wof:name":"Furianoi",
    "wof:placetype":"locality",
    "wof:population":26
},
  "geometry": {"coordinates":[11.75189,46.06213],"type":"Point"}
}