{
  "type": "Feature",
  "properties": {
    "gn:admin1_code":"7.0",
    "gn:admin2_code":"LT",
    "gn:admin3_code":"59011.0",
    "gn:asciiname":"Scopeto Madonna Gulia",
    "gn:country_code":"IT",
    "gn:dem":21,
    "gn:feature_class":"P",
    "gn:feature_code":"PPL",
    "gn:name":"Scopeto Madonna Gulia",
    "gn:population":524,
    "gn:timezone":"Europe/Rome",
    "iso:country":"IT",
    "wof:name":"Scopeto Madonna Gulia",
    "wof:placetype":"locality",
    "wof:population":524
},
  "geometry": {"coordinates":[12.96265,41.42359],"type":"Point"}
}