{
  "type": "Feature",
  "properties": {
    "gn:admin1_code":"6.0",
    "gn:admin2_code":"PN",
    "gn:admin3_code":"93030.0",
    "gn:asciiname":"Castelnuovo del Fruili",
    "gn:country_code":"IT",
    "gn:dem":193,
    "gn:feature_class":"P",
    "gn:feature_code":"PPL",
    "gn:name":"Castelnuovo del Fruili",
    "gn:population":0,
    "gn:timezone":"Europe/Rome",
    "iso:country":"IT",
    "wof:name":"Castelnuovo del Fruili",
    "wof:placetype":"locality"
},
  "geometry": {"coordinates":[12.94806,46.195],"type":"Point"}
}