{
  "type": "Feature",
  "properties": {
    "gn:admin1_code":"10.0",
    "gn:admin2_code":"AN",
    "gn:admin3_code":"42003.0",
    "gn:asciiname":"Castiglioni",
    "gn:country_code":"IT",
    "gn:dem":239,
    "gn:elevation":"228.0",
    "gn:feature_class":"P",
    "gn:feature_code":"PPL",
    "gn:name":"Castiglioni",
    "gn:population":212,
    "gn:timezone":"Europe/Rome",
    "iso:country":"IT",
    "wof:name":"Castiglioni",
    "wof:placetype":"locality",
    "wof:population":212
},
  "geometry": {"coordinates":[13.00817,43.50611],"type":"Point"}
}