{
  "type": "Feature",
  "properties": {
    "gn:admin1_code":"12.0",
    "gn:admin2_code":"AT",
    "gn:admin3_code":"5086.0",
    "gn:asciiname":"Freis",
    "gn:country_code":"IT",
    "gn:dem":280,
    "gn:feature_class":"P",
    "gn:feature_code":"PPL",
    "gn:name":"Freis",
    "gn:population":19,
    "gn:timezone":"Europe/Rome",
    "iso:country":"IT",
    "name:deu_x_preferred":[
        "Freis"
    ],
    "wof:name":"Freis",
    "wof:placetype":"locality",
    "wof:population":19
},
  "geometry": {"coordinates":[8.06292,45.05461],"type":"Point"}
}