{
  "type": "Feature",
  "properties": {
    "gn:admin1_code":"10",
    "gn:admin2_code":"MC",
    "gn:admin3_code":"43030.0",
    "gn:asciiname":"Becerica",
    "gn:country_code":"IT",
    "gn:dem":32,
    "gn:feature_class":"P",
    "gn:feature_code":"PPL",
    "gn:name":"Becerica",
    "gn:population":94,
    "gn:timezone":"Europe/Rome",
    "iso:country":"IT",
    "wof:name":"Becerica",
    "wof:placetype":"locality",
    "wof:population":94
},
  "geometry": {"coordinates":[13.57893,43.37116],"type":"Point"}
}