{
  "type": "Feature",
  "properties": {
    "gn:admin1_code":"5",
    "gn:admin2_code":"RA",
    "gn:admin3_code":"39002.0",
    "gn:asciiname":"Localita Pozzarda",
    "gn:country_code":"IT",
    "gn:dem":2,
    "gn:feature_class":"P",
    "gn:feature_code":"PPL",
    "gn:name":"Localit\u00e0 Pozzarda",
    "gn:population":13,
    "gn:timezone":"Europe/Rome",
    "iso:country":"IT",
    "name:und_x_variant":[
        "Localit\u00e0 Pozzarda"
    ],
    "wof:name":"Localita Pozzarda",
    "wof:placetype":"locality",
    "wof:population":13
},
  "geometry": {"coordinates":[11.99922,44.44407],"type":"Point"}
}