{
  "type": "Feature",
  "properties": {
    "gn:admin1_code":"20",
    "gn:admin2_code":"TV",
    "gn:admin3_code":"26012.0",
    "gn:asciiname":"Panigaia",
    "gn:country_code":"IT",
    "gn:dem":32,
    "gn:feature_class":"P",
    "gn:feature_code":"PPL",
    "gn:name":"Panigaia",
    "gn:population":68,
    "gn:timezone":"Europe/Rome",
    "iso:country":"IT",
    "wof:name":"Panigaia",
    "wof:placetype":"locality",
    "wof:population":68
},
  "geometry": {"coordinates":[11.91889,45.63041],"type":"Point"}
}