{
  "type": "Feature",
  "properties": {
    "gn:admin1_code":"14",
    "gn:admin2_code":"SU",
    "gn:admin3_code":"111089.0",
    "gn:asciiname":"Is Carillus",
    "gn:country_code":"IT",
    "gn:dem":154,
    "gn:feature_class":"P",
    "gn:feature_code":"PPL",
    "gn:name":"Is Carillus",
    "gn:population":18,
    "gn:timezone":"Europe/Rome",
    "iso:country":"IT",
    "wof:name":"Is Carillus",
    "wof:placetype":"locality",
    "wof:population":18
},
  "geometry": {"coordinates":[8.70916,39.02296],"type":"Point"}
}