{
  "type": "Feature",
  "properties": {
    "gn:admin1_code":"9",
    "gn:admin2_code":"CR",
    "gn:admin3_code":"19097.0",
    "gn:asciiname":"Villacampagna",
    "gn:country_code":"IT",
    "gn:dem":76,
    "gn:feature_class":"P",
    "gn:feature_code":"PPL",
    "gn:name":"Villacampagna",
    "gn:population":246,
    "gn:timezone":"Europe/Rome",
    "iso:country":"IT",
    "wof:name":"Villacampagna",
    "wof:placetype":"locality",
    "wof:population":246
},
  "geometry": {"coordinates":[9.85802,45.37225],"type":"Point"}
}