{
  "type": "Feature",
  "properties": {
    "gn:admin1_code":"9.0",
    "gn:admin2_code":"BS",
    "gn:admin3_code":"17185.0",
    "gn:asciiname":"Montecastello",
    "gn:country_code":"IT",
    "gn:dem":678,
    "gn:feature_class":"P",
    "gn:feature_code":"PPLL",
    "gn:name":"Montecastello",
    "gn:population":3,
    "gn:timezone":"Europe/Rome",
    "iso:country":"IT",
    "name:ara_x_preferred":[
        "\u0645\u0648\u0646\u062a\u064a\u0643\u0627\u0633\u062a\u0644\u0648"
    ],
    "name:bel_x_preferred":[
        "\u041c\u0430\u043d\u0442\u044d\u043a\u0430\u0441\u0442\u044d\u043b\u0430"
    ],
    "name:bul_x_preferred":[
        "\u041c\u043e\u043d\u0442\u0435\u043a\u0430\u0441\u0442\u0435\u043b\u043e"
    ],
    "name:cat_x_preferred":[
        "Montecastello"
    ],
    "name:ceb_x_preferred":[
        "Montecastello"
    ],
    "name:deu_x_preferred":[
        "Montecastello"
    ],
    "name:epo_x_preferred":[
        "Montecastello"
    ],
    "name:eus_x_preferred":[
        "Montecastello"
    ],
    "name:fas_x_preferred":[
        "\u0645\u0648\u0646\u062a\u0647 \u06a9\u0627\u0633\u062a\u0644\u0648"
    ],
    "name:fra_x_preferred":[
        "Montecastello"
    ],
    "name:hun_x_preferred":[
        "Montecastello"
    ],
    "name:hye_x_preferred":[
        "\u0544\u0578\u0576\u057f\u0565\u056f\u0561\u057d\u057f\u0565\u056c\u0578"
    ],
    "name:ind_x_preferred":[
        "Montecastello"
    ],
    "name:ita_x_preferred":[
        "Montecastello"
    ],
    "name:jpn_x_preferred":[
        "\u30e2\u30f3\u30c6\u30ab\u30b9\u30c6\u30c3\u30ed"
    ],
    "name:kaz_x_preferred":[
        "\u041c\u043e\u043d\u0442\u0435\u043a\u0430\u0441\u0442\u0435\u043b\u043b\u043e"
    ],
    "name:lat_x_preferred":[
        "Mons Castellus"
    ],
    "name:lmo_x_preferred":[
        "Montecastello"
    ],
    "name:msa_x_preferred":[
        "Montecastello"
    ],
    "name:nap_x_preferred":[
        "Montecastello"
    ],
    "name:nld_x_preferred":[
        "Montecastello"
    ],
    "name:pms_x_preferred":[
        "Moncast\u00e9"
    ],
    "name:pol_x_preferred":[
        "Montecastello"
    ],
    "name:por_x_preferred":[
        "Montecastello"
    ],
    "name:ron_x_preferred":[
        "Montecastello"
    ],
    "name:rus_x_preferred":[
        "\u041c\u043e\u043d\u0442\u0435\u043a\u0430\u0441\u0442\u0435\u043b\u043b\u043e"
    ],
    "name:scn_x_preferred":[
        "Montecastello"
    ],
    "name:spa_x_preferred":[
        "Montecastello"
    ],
    "name:srp_x_preferred":[
        "\u041c\u043e\u043d\u0442\u0435\u043a\u0430\u0441\u0442\u0435\u043b\u043e"
    ],
    "name:tgl_x_preferred":[
        "Montecastello"
    ],
    "name:ukr_x_preferred":[
        "\u041c\u043e\u043d\u0442\u0435\u043a\u0430\u0441\u0442\u0435\u043b\u043b\u043e"
    ],
    "name:uzb_x_preferred":[
        "Montecastello"
    ],
    "name:vie_x_preferred":[
        "Montecastello"
    ],
    "name:vol_x_preferred":[
        "Montecastello"
    ],
    "name:war_x_preferred":[
        "Montecastello"
    ],
    "name:zho_x_preferred":[
        "\u8499\u6cf0\u5361\u65af\u6cf0\u6d1b"
    ],
    "wof:name":"Montecastello",
    "wof:placetype":"locality",
    "wof:population":3
},
  "geometry": {"coordinates":[10.73325,45.74239],"type":"Point"}
}