{
  "type": "Feature",
  "properties": {
    "gn:admin1_code":"9.0",
    "gn:admin2_code":"BS",
    "gn:admin3_code":"17185.0",
    "gn:asciiname":"Montecastello",
    "gn:country_code":"IT",
    "gn:dem":678,
    "gn:feature_class":"P",
    "gn:feature_code":"PPLL",
    "gn:name":"Montecastello",
    "gn:population":3,
    "gn:timezone":"Europe/Rome",
    "iso:country":"IT",
    "wof:name":"Montecastello",
    "wof:placetype":"locality",
    "wof:population":3
},
  "geometry": {"coordinates":[10.73325,45.74239],"type":"Point"}
}