{
  "type": "Feature",
  "properties": {
    "gn:admin1_code":"3.0",
    "gn:admin2_code":"KR",
    "gn:admin3_code":"101007.0",
    "gn:asciiname":"Casa Favare",
    "gn:country_code":"IT",
    "gn:dem":239,
    "gn:feature_class":"P",
    "gn:feature_code":"PPL",
    "gn:name":"Casa Favare",
    "gn:population":0,
    "gn:timezone":"Europe/Rome",
    "iso:country":"IT",
    "wof:name":"Casa Favare",
    "wof:placetype":"locality"
},
  "geometry": {"coordinates":[17.03333,39.36667],"type":"Point"}
}