{
  "type": "Feature",
  "properties": {
    "gn:admin1_code":"12.0",
    "gn:admin2_code":"NO",
    "gn:admin3_code":"3095.0",
    "gn:asciiname":"Ghevio",
    "gn:country_code":"IT",
    "gn:dem":384,
    "gn:feature_class":"P",
    "gn:feature_code":"PPL",
    "gn:name":"Ghevio",
    "gn:population":506,
    "gn:timezone":"Europe/Rome",
    "iso:country":"IT",
    "wof:name":"Ghevio",
    "wof:placetype":"locality",
    "wof:population":506
},
  "geometry": {"coordinates":[8.50257,45.78172],"type":"Point"}
}