{
  "type": "Feature",
  "properties": {
    "gn:admin1_code":"1",
    "gn:admin2_code":"PE",
    "gn:admin3_code":"68017.0",
    "gn:asciiname":"Santa Maria del Ponte",
    "gn:country_code":"IT",
    "gn:dem":233,
    "gn:feature_class":"P",
    "gn:feature_code":"PPL",
    "gn:name":"Santa Maria del Ponte",
    "gn:population":39,
    "gn:timezone":"Europe/Rome",
    "iso:country":"IT",
    "name:ita_x_preferred":[
        "Santa Maria del Ponte"
    ],
    "name:srp_x_preferred":[
        "\u0421\u0430\u043d\u0442\u0430 \u041c\u0430\u0440\u0438\u0458\u0430 \u0434\u0435\u043b \u041f\u043e\u043d\u0442\u0435"
    ],
    "wof:name":"Santa Maria del Ponte",
    "wof:placetype":"locality",
    "wof:population":39
},
  "geometry": {"coordinates":[13.9457,42.31483],"type":"Point"}
}