{
  "type": "Feature",
  "properties": {
    "gn:admin1_code":"7",
    "gn:admin2_code":"RM",
    "gn:admin3_code":"58038.0",
    "gn:asciiname":"Prato Roseto-Case Bianche",
    "gn:country_code":"IT",
    "gn:dem":106,
    "gn:feature_class":"P",
    "gn:feature_code":"PPL",
    "gn:name":"Prato Roseto-Case Bianche",
    "gn:population":142,
    "gn:timezone":"Europe/Rome",
    "iso:country":"IT",
    "wof:name":"Prato Roseto-Case Bianche",
    "wof:placetype":"locality",
    "wof:population":142
},
  "geometry": {"coordinates":[12.40758,42.04532],"type":"Point"}
}