{
  "type": "Feature",
  "properties": {
    "gn:admin1_code":"10",
    "gn:admin2_code":"AN",
    "gn:admin3_code":"42020.0",
    "gn:asciiname":"Spineto",
    "gn:country_code":"IT",
    "gn:dem":308,
    "gn:feature_class":"P",
    "gn:feature_code":"PPL",
    "gn:name":"Spineto",
    "gn:population":18,
    "gn:timezone":"Europe/Rome",
    "iso:country":"IT",
    "wof:name":"Spineto",
    "wof:placetype":"locality",
    "wof:population":18
},
  "geometry": {"coordinates":[12.93569,43.39726],"type":"Point"}
}