{
  "type": "Feature",
  "properties": {
    "gn:admin1_code":"5",
    "gn:admin2_code":"FE",
    "gn:admin3_code":"38011.0",
    "gn:asciiname":"Corte Michelina",
    "gn:country_code":"IT",
    "gn:dem":0,
    "gn:feature_class":"P",
    "gn:feature_code":"PPL",
    "gn:name":"Corte Michelina",
    "gn:population":13,
    "gn:timezone":"Europe/Rome",
    "iso:country":"IT",
    "wof:name":"Corte Michelina",
    "wof:placetype":"locality",
    "wof:population":13
},
  "geometry": {"coordinates":[12.16384,44.77971],"type":"Point"}
}