{
  "type": "Feature",
  "properties": {
    "gn:admin1_code":"20.0",
    "gn:admin2_code":"TV",
    "gn:admin3_code":"26028.0",
    "gn:asciiname":"Nucleo Zanet",
    "gn:country_code":"IT",
    "gn:dem":13,
    "gn:feature_class":"P",
    "gn:feature_code":"PPL",
    "gn:name":"Nucleo Zanet",
    "gn:population":26,
    "gn:timezone":"Europe/Rome",
    "iso:country":"IT",
    "wof:name":"Nucleo Zanet",
    "wof:placetype":"locality",
    "wof:population":26
},
  "geometry": {"coordinates":[12.45604,45.80504000000001],"type":"Point"}
}