{
  "type": "Feature",
  "properties": {
    "gn:admin1_code":"4",
    "gn:admin3_code":"63044.0",
    "gn:asciiname":"Sant'Anna",
    "gn:country_code":"IT",
    "gn:dem":184,
    "gn:feature_class":"P",
    "gn:feature_code":"PPL",
    "gn:name":"Sant'Anna",
    "gn:population":43,
    "gn:timezone":"Europe/Rome",
    "iso:country":"IT",
    "name:bre_x_preferred":[
        "Sant'Anna"
    ],
    "name:ceb_x_preferred":[
        "Sant'Anna"
    ],
    "name:deu_x_preferred":[
        "Sant\u2019Anna"
    ],
    "name:epo_x_preferred":[
        "Sant'Anna"
    ],
    "name:ita_x_preferred":[
        "Sant'Anna"
    ],
    "name:nld_x_preferred":[
        "Sant'Anna"
    ],
    "name:por_x_preferred":[
        "Sant'Anna"
    ],
    "name:srp_x_preferred":[
        "Sant'Ana"
    ],
    "name:swe_x_preferred":[
        "Sant'Anna"
    ],
    "wof:name":"Sant'Anna",
    "wof:placetype":"locality",
    "wof:population":43
},
  "geometry": {"coordinates":[14.33858,40.60059],"type":"Point"}
}