{
  "type": "Feature",
  "properties": {
    "iso:country":"IT",
    "name:ceb_x_preferred":[
        "Fuorigrotta"
    ],
    "name:deu_x_preferred":[
        "Fuorigrotta"
    ],
    "name:eng_x_preferred":[
        "Fuorigrotta"
    ],
    "name:fra_x_preferred":[
        "Fuorigrotta"
    ],
    "name:ita_x_preferred":[
        "Fuorigrotta"
    ],
    "name:nap_x_preferred":[
        "Forerotta"
    ],
    "name:nld_x_preferred":[
        "Fuorigrotta"
    ],
    "wof:name":"Fuorigrotta",
    "wof:placetype":"neighbourhood"
},
  "geometry": {"coordinates":[14.19606035308171,40.82851390453432],"type":"Point"}
}