{
  "type": "Feature",
  "properties": {
    "iso:country":"IT",
    "name:ceb_x_preferred":[
        "Fuorigrotta"
    ],
    "name:deu_x_preferred":[
        "Fuorigrotta"
    ],
    "name:eng_x_preferred":[
        "Fuorigrotta"
    ],
    "name:fra_x_preferred":[
        "Fuorigrotta"
    ],
    "name:hrv_x_preferred":[
        "Fuorigrotta"
    ],
    "name:ita_x_preferred":[
        "Fuorigrotta"
    ],
    "name:jpn_x_preferred":[
        "\u30d5\u30aa\u30ea\u30b0\u30ed\u30c3\u30bf"
    ],
    "name:nap_x_preferred":[
        "Forerotta"
    ],
    "name:nld_x_preferred":[
        "Fuorigrotta"
    ],
    "name:spa_x_preferred":[
        "Fuorigrotta"
    ],
    "name:tgl_x_preferred":[
        "Fuorigrotta"
    ],
    "wof:name":"Fuorigrotta",
    "wof:placetype":"neighbourhood"
},
  "geometry": {"coordinates":[14.19606,40.828514],"type":"Point"}
}