{
  "type": "Feature",
  "properties": {
    "gn:admin1_code":"4.0",
    "gn:admin2_code":"SA",
    "gn:admin3_code":"65139.0",
    "gn:asciiname":"Capograssi",
    "gn:country_code":"IT",
    "gn:dem":260,
    "gn:elevation":"255.0",
    "gn:feature_class":"P",
    "gn:feature_code":"PPL",
    "gn:name":"Capograssi",
    "gn:population":69,
    "gn:timezone":"Europe/Rome",
    "iso:country":"IT",
    "wof:name":"Capograssi",
    "wof:placetype":"locality",
    "wof:population":69
},
  "geometry": {"coordinates":[15.0167,40.24256],"type":"Point"}
}