{
  "type": "Feature",
  "properties": {
    "gn:gn_country":"IT",
    "gn:gn_fcode":"PPL",
    "gn:gn_pop":0,
    "gn:population":3,
    "iso:country":"IT",
    "name:cat_x_preferred":[
        "Pieve di Sant'Andrea"
    ],
    "name:ces_x_preferred":[
        "Pieve di Sant'Andrea"
    ],
    "name:dan_x_preferred":[
        "Pieve di Sant'Andrea"
    ],
    "name:eng_x_preferred":[
        "Pieve di Sant'Andrea"
    ],
    "name:eus_x_preferred":[
        "Pieve di Sant'Andrea"
    ],
    "name:fin_x_preferred":[
        "Pieve di Sant'Andrea"
    ],
    "name:fra_x_preferred":[
        "Pieve di Sant'Andrea"
    ],
    "name:ind_x_preferred":[
        "Pieve di Sant'Andrea"
    ],
    "name:ita_x_preferred":[
        "Pieve di Sant'Andrea"
    ],
    "name:nld_x_preferred":[
        "Pieve di Sant'Andrea"
    ],
    "name:nno_x_preferred":[
        "Pieve di Sant'Andrea"
    ],
    "name:nob_x_preferred":[
        "Pieve di Sant'Andrea"
    ],
    "name:oci_x_preferred":[
        "Pieve di Sant'Andrea"
    ],
    "name:pol_x_preferred":[
        "Pieve di Sant'Andrea"
    ],
    "name:por_x_preferred":[
        "Pieve di Sant'Andrea"
    ],
    "name:ron_x_preferred":[
        "Pieve di Sant'Andrea"
    ],
    "name:slk_x_preferred":[
        "Pieve di Sant'Andrea"
    ],
    "name:slv_x_preferred":[
        "Pieve di Sant'Andrea"
    ],
    "name:spa_x_preferred":[
        "Pieve di Sant'Andrea"
    ],
    "name:srp_x_preferred":[
        "Pieve di Sant'Andrea"
    ],
    "name:swe_x_preferred":[
        "Pieve di Sant'Andrea"
    ],
    "name:tgl_x_preferred":[
        "Pieve di Sant'Andrea"
    ],
    "name:tur_x_preferred":[
        "Pieve di Sant'Andrea"
    ],
    "name:unk_x_variant":[
        "Pieve Sant'Andrea"
    ],
    "name:war_x_preferred":[
        "Pieve di Sant'Andrea"
    ],
    "qs_pg:aaroncc":"IT",
    "qs_pg:gn_country":"IT",
    "qs_pg:gn_fcode":"PPL",
    "qs_pg:gn_pop":0,
    "qs_pg:name":"Pieve di Sant'Andrea",
    "qs_pg:name_adm0":"Italia",
    "qs_pg:name_adm1":"Emilia Romagna",
    "qs_pg:photos":17,
    "qs_pg:photos_1k":3,
    "qs_pg:photos_9k":1,
    "qs_pg:photos_9r":1,
    "qs_pg:photos_all":17,
    "qs_pg:photos_sr":1,
    "qs_pg:pop_sr":0,
    "qs_pg:qs_pg_placetype":"locality",
    "qs_pg:qs_pg_placetype_gp":"Town",
    "qs_pg:woe_adm0":23424853,
    "woe:adm0_id":23424853,
    "woe:name_adm0":"Italia",
    "woe:name_adm1":"Emilia Romagna",
    "woe:placetype":"Town",
    "wof:name":"Pieve di Sant'Andrea",
    "wof:placetype":"locality",
    "wof:population":3
},
  "geometry": {"coordinates":[11.58333,44.33333],"type":"Point"}
}