{
  "type": "Feature",
  "properties": {
    "gn:admin1_code":"19",
    "gn:admin2_code":"AO",
    "gn:admin3_code":"7040.0",
    "gn:asciiname":"La Clusaz",
    "gn:country_code":"IT",
    "gn:dem":1012,
    "gn:feature_class":"P",
    "gn:feature_code":"PPL",
    "gn:name":"La Clusaz",
    "gn:population":30,
    "gn:timezone":"Europe/Rome",
    "iso:country":"IT",
    "name:bul_x_preferred":[
        "\u041a\u043b\u044e\u0437\u0430\u0437"
    ],
    "name:cat_x_preferred":[
        "La Clusaz"
    ],
    "name:ceb_x_preferred":[
        "La Clusaz"
    ],
    "name:ces_x_preferred":[
        "La Clusaz"
    ],
    "name:deu_x_preferred":[
        "La Clusaz"
    ],
    "name:eus_x_preferred":[
        "La Clusaz"
    ],
    "name:fin_x_preferred":[
        "La Clusaz"
    ],
    "name:fra_x_preferred":[
        "La Clusaz"
    ],
    "name:frp_x_preferred":[
        "La Cllusa"
    ],
    "name:hun_x_preferred":[
        "La Clusaz"
    ],
    "name:ita_x_preferred":[
        "La Clusaz"
    ],
    "name:lat_x_preferred":[
        "Clusa Annicensium"
    ],
    "name:lmo_x_preferred":[
        "La Clusaz"
    ],
    "name:msa_x_preferred":[
        "La Clusaz"
    ],
    "name:nld_x_preferred":[
        "La Clusaz"
    ],
    "name:nor_x_preferred":[
        "La Clusaz"
    ],
    "name:oci_x_preferred":[
        "La Clusaz"
    ],
    "name:pol_x_preferred":[
        "Clusaz"
    ],
    "name:por_x_preferred":[
        "La Clusaz"
    ],
    "name:ron_x_preferred":[
        "La Clusaz"
    ],
    "name:slk_x_preferred":[
        "La Clusaz"
    ],
    "name:spa_x_preferred":[
        "La Clusaz"
    ],
    "name:srp_x_preferred":[
        "\u041a\u043b\u0438\u0437\u0430\u0437"
    ],
    "name:swe_x_preferred":[
        "La Clusaz"
    ],
    "name:ukr_x_preferred":[
        "\u041b\u0430-\u041a\u043b\u044e\u0437\u0430"
    ],
    "name:urd_x_preferred":[
        "\u0644\u0627 \u06a9\u0644\u06cc\u0648\u0633\u0627\u0632"
    ],
    "name:uzb_x_preferred":[
        "La Clusaz"
    ],
    "name:vie_x_preferred":[
        "La Clusaz"
    ],
    "name:vol_x_preferred":[
        "La Clusaz"
    ],
    "name:war_x_preferred":[
        "La Clusaz"
    ],
    "name:zho_x_preferred":[
        "\u62c9\u514b\u5415\u8428"
    ],
    "wof:name":"La Clusaz",
    "wof:placetype":"locality",
    "wof:population":30
},
  "geometry": {"coordinates":[7.06629,45.7521],"type":"Point"}
}