{
  "type": "Feature",
  "properties": {
    "gn:admin1_code":"19",
    "gn:admin2_code":"AO",
    "gn:admin3_code":"7040.0",
    "gn:asciiname":"La Clusaz",
    "gn:country_code":"IT",
    "gn:dem":1012,
    "gn:feature_class":"P",
    "gn:feature_code":"PPL",
    "gn:name":"La Clusaz",
    "gn:population":30,
    "gn:timezone":"Europe/Rome",
    "iso:country":"IT",
    "wof:name":"La Clusaz",
    "wof:placetype":"locality",
    "wof:population":30
},
  "geometry": {"coordinates":[7.06629,45.7521],"type":"Point"}
}