{
  "type": "Feature",
  "properties": {
    "gn:admin1_code":"5",
    "gn:admin2_code":"BO",
    "gn:admin3_code":"37051.0",
    "gn:asciiname":"Malburo",
    "gn:country_code":"IT",
    "gn:dem":826,
    "gn:feature_class":"P",
    "gn:feature_code":"PPL",
    "gn:name":"Malburo",
    "gn:population":15,
    "gn:timezone":"Europe/Rome",
    "iso:country":"IT",
    "wof:name":"Malburo",
    "wof:placetype":"locality",
    "wof:population":15
},
  "geometry": {"coordinates":[11.27138,44.17625],"type":"Point"}
}