{
  "type": "Feature",
  "properties": {
    "gn:admin1_code":"10",
    "gn:admin2_code":"MC",
    "gn:admin3_code":"43025.0",
    "gn:asciiname":"Santa Lucia",
    "gn:country_code":"IT",
    "gn:dem":204,
    "gn:feature_class":"P",
    "gn:feature_code":"PPL",
    "gn:name":"Santa Lucia",
    "gn:population":60,
    "gn:timezone":"Europe/Rome",
    "iso:country":"IT",
    "wof:name":"Santa Lucia",
    "wof:placetype":"locality",
    "wof:population":60
},
  "geometry": {"coordinates":[13.49519,43.20425],"type":"Point"}
}