{
  "type": "Feature",
  "properties": {
    "gn:admin1_code":"8",
    "gn:admin2_code":"GE",
    "gn:admin3_code":"10025.0",
    "gn:asciiname":"Filanda Profondo",
    "gn:country_code":"IT",
    "gn:dem":77,
    "gn:feature_class":"P",
    "gn:feature_code":"PPL",
    "gn:name":"Filanda Profondo",
    "gn:population":29,
    "gn:timezone":"Europe/Rome",
    "iso:country":"IT",
    "wof:name":"Filanda Profondo",
    "wof:placetype":"locality",
    "wof:population":29
},
  "geometry": {"coordinates":[8.8179,44.4447],"type":"Point"}
}