{
  "type": "Feature",
  "properties": {
    "gn:admin1_code":"12",
    "gn:admin2_code":"AL",
    "gn:admin3_code":"6125.0",
    "gn:asciiname":"Valla",
    "gn:country_code":"IT",
    "gn:dem":343,
    "gn:feature_class":"P",
    "gn:feature_code":"PPL",
    "gn:name":"Valla",
    "gn:population":17,
    "gn:timezone":"Europe/Rome",
    "iso:country":"IT",
    "wof:name":"Valla",
    "wof:placetype":"locality",
    "wof:population":17
},
  "geometry": {"coordinates":[8.35732,44.51085],"type":"Point"}
}