{
  "type": "Feature",
  "properties": {
    "gn:admin1_code":"12",
    "gn:admin2_code":"AL",
    "gn:admin3_code":"6125.0",
    "gn:asciiname":"Valla",
    "gn:country_code":"IT",
    "gn:dem":343,
    "gn:feature_class":"P",
    "gn:feature_code":"PPL",
    "gn:name":"Valla",
    "gn:population":17,
    "gn:timezone":"Europe/Rome",
    "iso:country":"IT",
    "name:ceb_x_preferred":[
        "Valla"
    ],
    "name:deu_x_preferred":[
        "Valla"
    ],
    "name:fra_x_preferred":[
        "Valla"
    ],
    "name:heb_x_preferred":[
        "\u05d5\u05d0\u05dc\u05d4"
    ],
    "name:ita_x_preferred":[
        "Valla"
    ],
    "name:lat_x_preferred":[
        "Valla"
    ],
    "name:nld_x_preferred":[
        "Valla"
    ],
    "name:nor_x_preferred":[
        "Valla"
    ],
    "name:pol_x_preferred":[
        "Valla"
    ],
    "name:rus_x_preferred":[
        "\u0412\u0430\u043b\u043b\u0430"
    ],
    "name:swe_x_preferred":[
        "Valla"
    ],
    "name:tam_x_preferred":[
        "\u0bb5\u0bc7\u0bb2\u0bbf"
    ],
    "wof:name":"Valla",
    "wof:placetype":"locality",
    "wof:population":17
},
  "geometry": {"coordinates":[8.35732,44.51085],"type":"Point"}
}