{
  "type": "Feature",
  "properties": {
    "gn:admin1_code":"4",
    "gn:admin2_code":"AV",
    "gn:admin3_code":"64046.0",
    "gn:asciiname":"Festola",
    "gn:country_code":"IT",
    "gn:dem":339,
    "gn:feature_class":"P",
    "gn:feature_code":"PPL",
    "gn:name":"Festola",
    "gn:population":42,
    "gn:timezone":"Europe/Rome",
    "iso:country":"IT",
    "wof:name":"Festola",
    "wof:placetype":"locality",
    "wof:population":42
},
  "geometry": {"coordinates":[14.84363,40.9294],"type":"Point"}
}