{
  "type": "Feature",
  "properties": {
    "gn:admin1_code":"8",
    "gn:admin2_code":"GE",
    "gn:admin3_code":"10013.0",
    "gn:asciiname":"Fiume",
    "gn:country_code":"IT",
    "gn:dem":145,
    "gn:feature_class":"P",
    "gn:feature_code":"PPL",
    "gn:name":"Fiume",
    "gn:population":11,
    "gn:timezone":"Europe/Rome",
    "iso:country":"IT",
    "wof:name":"Fiume",
    "wof:placetype":"locality",
    "wof:population":11
},
  "geometry": {"coordinates":[9.50802,44.27074],"type":"Point"}
}