{
  "type": "Feature",
  "properties": {
    "gn:admin1_code":"1",
    "gn:admin2_code":"PE",
    "gn:admin3_code":"68032.0",
    "gn:asciiname":"Case Boccacci",
    "gn:country_code":"IT",
    "gn:dem":399,
    "gn:feature_class":"P",
    "gn:feature_code":"PPL",
    "gn:name":"Case Boccacci",
    "gn:population":23,
    "gn:timezone":"Europe/Rome",
    "iso:country":"IT",
    "wof:name":"Case Boccacci",
    "wof:placetype":"locality",
    "wof:population":23
},
  "geometry": {"coordinates":[13.92816,42.27755],"type":"Point"}
}