{
  "type": "Feature",
  "properties": {
    "gn:admin1_code":"20",
    "gn:admin2_code":"VR",
    "gn:admin3_code":"23011.0",
    "gn:asciiname":"Croce",
    "gn:country_code":"IT",
    "gn:dem":1157,
    "gn:feature_class":"P",
    "gn:feature_code":"PPL",
    "gn:name":"Croce",
    "gn:population":12,
    "gn:timezone":"Europe/Rome",
    "iso:country":"IT",
    "wof:name":"Croce",
    "wof:placetype":"locality",
    "wof:population":12
},
  "geometry": {"coordinates":[11.03126,45.63817],"type":"Point"}
}