{
  "type": "Feature",
  "properties": {
    "gn:admin1_code":"12.0",
    "gn:admin2_code":"CN",
    "gn:admin3_code":"4207.0",
    "gn:asciiname":"Pagliero Chiesa",
    "gn:country_code":"IT",
    "gn:dem":1018,
    "gn:feature_class":"P",
    "gn:feature_code":"PPLL",
    "gn:name":"Pagliero Chiesa",
    "gn:population":3,
    "gn:timezone":"Europe/Rome",
    "iso:country":"IT",
    "wof:name":"Pagliero Chiesa",
    "wof:placetype":"locality",
    "wof:population":3
},
  "geometry": {"coordinates":[7.24744,44.50447],"type":"Point"}
}