{
  "type": "Feature",
  "properties": {
    "gn:admin1_code":"20",
    "gn:admin2_code":"VI",
    "gn:admin3_code":"24014.0",
    "gn:asciiname":"Pajaron",
    "gn:country_code":"IT",
    "gn:dem":82,
    "gn:feature_class":"P",
    "gn:feature_code":"PPL",
    "gn:name":"Pajaron",
    "gn:population":26,
    "gn:timezone":"Europe/Rome",
    "iso:country":"IT",
    "wof:name":"Pajaron",
    "wof:placetype":"locality",
    "wof:population":26
},
  "geometry": {"coordinates":[11.59735,45.69888],"type":"Point"}
}