{
  "type": "Feature",
  "properties": {
    "gn:admin1_code":"12",
    "gn:admin2_code":"CN",
    "gn:admin3_code":"4082.0",
    "gn:asciiname":"Gangotta Sottana",
    "gn:country_code":"IT",
    "gn:dem":552,
    "gn:feature_class":"P",
    "gn:feature_code":"PPL",
    "gn:name":"Gangotta Sottana",
    "gn:population":33,
    "gn:timezone":"Europe/Rome",
    "iso:country":"IT",
    "wof:name":"Gangotta Sottana",
    "wof:placetype":"locality",
    "wof:population":33
},
  "geometry": {"coordinates":[7.43616,44.47091],"type":"Point"}
}