{
  "type": "Feature",
  "properties": {
    "gn:admin1_code":"4",
    "gn:admin2_code":"AV",
    "gn:admin3_code":"64050.0",
    "gn:asciiname":"Coculo",
    "gn:country_code":"IT",
    "gn:dem":363,
    "gn:feature_class":"P",
    "gn:feature_code":"PPL",
    "gn:name":"Coculo",
    "gn:population":164,
    "gn:timezone":"Europe/Rome",
    "iso:country":"IT",
    "wof:name":"Coculo",
    "wof:placetype":"locality",
    "wof:population":164
},
  "geometry": {"coordinates":[14.97716,41.05796],"type":"Point"}
}