{
  "type": "Feature",
  "properties": {
    "gn:admin1_code":"16.0",
    "gn:admin2_code":"PT",
    "gn:admin3_code":"47006.0",
    "gn:asciiname":"Puntoni",
    "gn:country_code":"IT",
    "gn:dem":30,
    "gn:elevation":"32.0",
    "gn:feature_class":"P",
    "gn:feature_code":"PPL",
    "gn:name":"Puntoni",
    "gn:population":27,
    "gn:timezone":"Europe/Rome",
    "iso:country":"IT",
    "wof:name":"Puntoni",
    "wof:placetype":"locality",
    "wof:population":27
},
  "geometry": {"coordinates":[10.83883,43.81216],"type":"Point"}
}