{
  "type": "Feature",
  "properties": {
    "gn:admin1_code":"7",
    "gn:admin2_code":"RM",
    "gn:admin3_code":"58029.0",
    "gn:asciiname":"Cerqueto",
    "gn:country_code":"IT",
    "gn:dem":114,
    "gn:feature_class":"P",
    "gn:feature_code":"PPL",
    "gn:name":"Cerqueto",
    "gn:population":75,
    "gn:timezone":"Europe/Rome",
    "iso:country":"IT",
    "wof:name":"Cerqueto",
    "wof:placetype":"locality",
    "wof:population":75
},
  "geometry": {"coordinates":[12.03658,42.03525],"type":"Point"}
}