{
  "type": "Feature",
  "properties": {
    "gn:admin1_code":"5",
    "gn:admin2_code":"PR",
    "gn:admin3_code":"34024.0",
    "gn:asciiname":"Canale",
    "gn:country_code":"IT",
    "gn:dem":623,
    "gn:feature_class":"P",
    "gn:feature_code":"PPL",
    "gn:name":"Canale",
    "gn:population":21,
    "gn:timezone":"Europe/Rome",
    "iso:country":"IT",
    "wof:name":"Canale",
    "wof:placetype":"locality",
    "wof:population":21
},
  "geometry": {"coordinates":[10.31308,44.50084],"type":"Point"}
}