{
  "type": "Feature",
  "properties": {
    "gn:admin1_code":"5",
    "gn:admin2_code":"PR",
    "gn:admin3_code":"34024.0",
    "gn:asciiname":"Canale",
    "gn:country_code":"IT",
    "gn:dem":623,
    "gn:feature_class":"P",
    "gn:feature_code":"PPL",
    "gn:name":"Canale",
    "gn:population":21,
    "gn:timezone":"Europe/Rome",
    "iso:country":"IT",
    "name:bel_x_preferred":[
        "\u041a\u0430\u043d\u0430\u043b\u0435"
    ],
    "name:ceb_x_preferred":[
        "Canale"
    ],
    "name:deu_x_preferred":[
        "Canale"
    ],
    "name:eus_x_preferred":[
        "Canale"
    ],
    "name:fra_x_preferred":[
        "Canale"
    ],
    "name:ind_x_preferred":[
        "Canale"
    ],
    "name:ita_x_preferred":[
        "Canale"
    ],
    "name:por_x_preferred":[
        "Canale"
    ],
    "name:rus_x_preferred":[
        "\u041a\u0430\u043d\u0430\u043b\u0435"
    ],
    "name:srp_x_preferred":[
        "\u041a\u0430\u043d\u0430\u043b\u0435"
    ],
    "name:swe_x_preferred":[
        "Canale"
    ],
    "wof:name":"Canale",
    "wof:placetype":"locality",
    "wof:population":21
},
  "geometry": {"coordinates":[10.31308,44.50084],"type":"Point"}
}