{
  "type": "Feature",
  "properties": {
    "gn:admin1_code":"20",
    "gn:admin2_code":"TV",
    "gn:admin3_code":"26077.0",
    "gn:asciiname":"Comunella",
    "gn:country_code":"IT",
    "gn:dem":81,
    "gn:feature_class":"P",
    "gn:feature_code":"PPL",
    "gn:name":"Comunella",
    "gn:population":58,
    "gn:timezone":"Europe/Rome",
    "iso:country":"IT",
    "wof:name":"Comunella",
    "wof:placetype":"locality",
    "wof:population":58
},
  "geometry": {"coordinates":[11.83978,45.74538],"type":"Point"}
}