{
  "type": "Feature",
  "properties": {
    "gn:admin1_code":"16",
    "gn:admin2_code":"AR",
    "gn:admin3_code":"51041.0",
    "gn:asciiname":"Santo Stefano",
    "gn:country_code":"IT",
    "gn:dem":500,
    "gn:feature_class":"P",
    "gn:feature_code":"PPL",
    "gn:name":"Santo Stefano",
    "gn:population":76,
    "gn:timezone":"Europe/Rome",
    "iso:country":"IT",
    "wof:name":"Santo Stefano",
    "wof:placetype":"locality",
    "wof:population":76
},
  "geometry": {"coordinates":[11.71196,43.81234],"type":"Point"}
}