{
  "type": "Feature",
  "properties": {
    "gn:admin1_code":"4.0",
    "gn:admin2_code":"AV",
    "gn:admin3_code":"64072.0",
    "gn:asciiname":"P.I.P. Dentecane",
    "gn:country_code":"IT",
    "gn:dem":348,
    "gn:feature_class":"P",
    "gn:feature_code":"PPL",
    "gn:name":"P.I.P. Dentecane",
    "gn:population":85,
    "gn:timezone":"Europe/Rome",
    "iso:country":"IT",
    "wof:name":"P.I.P. Dentecane",
    "wof:placetype":"locality",
    "wof:population":85
},
  "geometry": {"coordinates":[14.8986,41.03749000000001],"type":"Point"}
}