{
  "type": "Feature",
  "properties": {
    "gn:admin1_code":"3",
    "gn:admin2_code":"CS",
    "gn:admin3_code":"78070.0",
    "gn:asciiname":"Serra Civita",
    "gn:country_code":"IT",
    "gn:dem":499,
    "gn:feature_class":"P",
    "gn:feature_code":"PPL",
    "gn:name":"Serra Civita",
    "gn:population":212,
    "gn:timezone":"Europe/Rome",
    "iso:country":"IT",
    "wof:name":"Serra Civita",
    "wof:placetype":"locality",
    "wof:population":212
},
  "geometry": {"coordinates":[16.29945,39.43783],"type":"Point"}
}