{
  "type": "Feature",
  "properties": {
    "gn:admin1_code":"10",
    "gn:admin2_code":"AP",
    "gn:admin3_code":"44038.0",
    "gn:asciiname":"Collicello-Corbara",
    "gn:country_code":"IT",
    "gn:dem":677,
    "gn:feature_class":"P",
    "gn:feature_code":"PPL",
    "gn:name":"Collicello-Corbara",
    "gn:population":39,
    "gn:timezone":"Europe/Rome",
    "iso:country":"IT",
    "wof:name":"Collicello-Corbara",
    "wof:placetype":"locality",
    "wof:population":39
},
  "geometry": {"coordinates":[13.35027,42.84347],"type":"Point"}
}