{
  "type": "Feature",
  "properties": {
    "gn:admin1_code":"10",
    "gn:admin2_code":"PU",
    "gn:admin3_code":"41065.0",
    "gn:asciiname":"Case Corbucci",
    "gn:country_code":"IT",
    "gn:dem":109,
    "gn:feature_class":"P",
    "gn:feature_code":"PPL",
    "gn:name":"Case Corbucci",
    "gn:population":13,
    "gn:timezone":"Europe/Rome",
    "iso:country":"IT",
    "wof:name":"Case Corbucci",
    "wof:placetype":"locality",
    "wof:population":13
},
  "geometry": {"coordinates":[12.74241,43.89059],"type":"Point"}
}