{
  "type": "Feature",
  "properties": {
    "gn:admin1_code":"8",
    "gn:admin2_code":"IM",
    "gn:admin3_code":"8018.0",
    "gn:asciiname":"Arzeno d'Oneglia",
    "gn:country_code":"IT",
    "gn:dem":512,
    "gn:feature_class":"P",
    "gn:feature_code":"PPL",
    "gn:name":"Arzeno d'Oneglia",
    "gn:population":29,
    "gn:timezone":"Europe/Rome",
    "iso:country":"IT",
    "wof:name":"Arzeno d'Oneglia",
    "wof:placetype":"locality",
    "wof:population":29
},
  "geometry": {"coordinates":[7.96305,44.00943],"type":"Point"}
}