{
  "type": "Feature",
  "properties": {
    "gn:admin1_code":"8",
    "gn:admin2_code":"SP",
    "gn:admin3_code":"11008.0",
    "gn:asciiname":"Bruscarolo",
    "gn:country_code":"IT",
    "gn:dem":501,
    "gn:feature_class":"P",
    "gn:feature_code":"PPL",
    "gn:name":"Bruscarolo",
    "gn:population":51,
    "gn:timezone":"Europe/Rome",
    "iso:country":"IT",
    "wof:name":"Bruscarolo",
    "wof:placetype":"locality",
    "wof:population":51
},
  "geometry": {"coordinates":[9.86237,44.22108],"type":"Point"}
}