{
  "type": "Feature",
  "properties": {
    "gn:admin1_code":"10",
    "gn:admin2_code":"MC",
    "gn:admin3_code":"43043.0",
    "gn:asciiname":"Pamperduto",
    "gn:country_code":"IT",
    "gn:dem":142,
    "gn:feature_class":"P",
    "gn:feature_code":"PPL",
    "gn:name":"Pamperduto",
    "gn:population":216,
    "gn:timezone":"Europe/Rome",
    "iso:country":"IT",
    "wof:name":"Pamperduto",
    "wof:placetype":"locality",
    "wof:population":216
},
  "geometry": {"coordinates":[13.66428,43.37756],"type":"Point"}
}