{
  "type": "Feature",
  "properties": {
    "gn:admin1_code":"16",
    "gn:admin2_code":"LI",
    "gn:admin3_code":"49014.0",
    "gn:asciiname":"Campo Ai Peri",
    "gn:country_code":"IT",
    "gn:dem":54,
    "gn:feature_class":"P",
    "gn:feature_code":"PPL",
    "gn:name":"Campo Ai Peri",
    "gn:population":59,
    "gn:timezone":"Europe/Rome",
    "iso:country":"IT",
    "wof:name":"Campo Ai Peri",
    "wof:placetype":"locality",
    "wof:population":59
},
  "geometry": {"coordinates":[10.34541,42.77734],"type":"Point"}
}