{
  "type": "Feature",
  "properties": {
    "gn:admin1_code":"17.0",
    "gn:admin2_code":"BZ",
    "gn:admin3_code":"21023.0",
    "gn:asciiname":"Zona Artigianale Obergummer",
    "gn:country_code":"IT",
    "gn:dem":807,
    "gn:feature_class":"P",
    "gn:feature_code":"PPL",
    "gn:name":"Zona Artigianale Obergummer",
    "gn:population":4,
    "gn:timezone":"Europe/Rome",
    "iso:country":"IT",
    "wof:name":"Zona Artigianale Obergummer",
    "wof:placetype":"locality",
    "wof:population":4
},
  "geometry": {"coordinates":[11.46665,46.43831],"type":"Point"}
}