{
  "type": "Feature",
  "properties": {
    "gn:admin1_code":"10",
    "gn:admin2_code":"PU",
    "gn:admin3_code":"41061.0",
    "gn:asciiname":"Pedaletti",
    "gn:country_code":"IT",
    "gn:dem":461,
    "gn:feature_class":"P",
    "gn:feature_code":"PPL",
    "gn:name":"Pedaletti",
    "gn:population":19,
    "gn:timezone":"Europe/Rome",
    "iso:country":"IT",
    "wof:name":"Pedaletti",
    "wof:placetype":"locality",
    "wof:population":19
},
  "geometry": {"coordinates":[12.77126,43.51067000000001],"type":"Point"}
}