{
  "type": "Feature",
  "properties": {
    "gn:admin1_code":"12",
    "gn:admin2_code":"TO",
    "gn:admin3_code":"1292.0",
    "gn:asciiname":"Medico Inferiore",
    "gn:country_code":"IT",
    "gn:dem":284,
    "gn:feature_class":"P",
    "gn:feature_code":"PPL",
    "gn:name":"Medico Inferiore",
    "gn:population":28,
    "gn:timezone":"Europe/Rome",
    "iso:country":"IT",
    "wof:name":"Medico Inferiore",
    "wof:placetype":"locality",
    "wof:population":28
},
  "geometry": {"coordinates":[7.61558,45.15534],"type":"Point"}
}