{
  "type": "Feature",
  "properties": {
    "gn:admin1_code":"20",
    "gn:admin2_code":"VE",
    "gn:admin3_code":"27013.0",
    "gn:asciiname":"Brian",
    "gn:country_code":"IT",
    "gn:dem":-2,
    "gn:feature_class":"P",
    "gn:feature_code":"PPL",
    "gn:name":"Brian",
    "gn:population":326,
    "gn:timezone":"Europe/Rome",
    "iso:country":"IT",
    "name:bel_x_preferred":[
        "\u0411\u0440\u0430\u044f\u043d"
    ],
    "name:dan_x_preferred":[
        "Brian"
    ],
    "name:deu_x_preferred":[
        "Brian"
    ],
    "name:fra_x_preferred":[
        "Brian"
    ],
    "name:gla_x_preferred":[
        "Brian"
    ],
    "name:ita_x_preferred":[
        "Brian"
    ],
    "name:nno_x_preferred":[
        "Brian"
    ],
    "name:nor_x_preferred":[
        "Brian"
    ],
    "name:rus_x_preferred":[
        "\u0411\u0440\u0430\u0439\u0435\u043d"
    ],
    "name:spa_x_preferred":[
        "Brian"
    ],
    "name:swe_x_preferred":[
        "Brian"
    ],
    "name:vie_x_preferred":[
        "Brian"
    ],
    "wof:name":"Brian",
    "wof:placetype":"locality",
    "wof:population":326
},
  "geometry": {"coordinates":[12.81327,45.59134],"type":"Point"}
}