{
  "type": "Feature",
  "properties": {
    "gn:admin1_code":"5.0",
    "gn:admin2_code":"MO",
    "gn:admin3_code":"36021.0",
    "gn:asciiname":"Gambro-Dasco",
    "gn:country_code":"IT",
    "gn:dem":26,
    "gn:feature_class":"P",
    "gn:feature_code":"PPLL",
    "gn:name":"Gambro-Dasco",
    "gn:population":3,
    "gn:timezone":"Europe/Rome",
    "iso:country":"IT",
    "wof:name":"Gambro-Dasco",
    "wof:placetype":"locality",
    "wof:population":3
},
  "geometry": {"coordinates":[11.06671,44.86335],"type":"Point"}
}