{
  "type": "Feature",
  "properties": {
    "gn:admin1_code":"12",
    "gn:admin2_code":"CN",
    "gn:admin3_code":"4123.0",
    "gn:asciiname":"Tetto Tederei",
    "gn:country_code":"IT",
    "gn:dem":1102,
    "gn:feature_class":"P",
    "gn:feature_code":"PPLL",
    "gn:name":"Tetto Tederei",
    "gn:population":5,
    "gn:timezone":"Europe/Rome",
    "iso:country":"IT",
    "wof:name":"Tetto Tederei",
    "wof:placetype":"locality",
    "wof:population":5
},
  "geometry": {"coordinates":[7.36479,44.32669],"type":"Point"}
}