{
  "type": "Feature",
  "properties": {
    "gn:admin1_code":"9.0",
    "gn:admin2_code":"SO",
    "gn:admin3_code":"14012.0",
    "gn:asciiname":"Mottala",
    "gn:country_code":"IT",
    "gn:dem":1357,
    "gn:feature_class":"P",
    "gn:feature_code":"PPL",
    "gn:name":"Mottala",
    "gn:population":0,
    "gn:timezone":"Europe/Rome",
    "iso:country":"IT",
    "wof:name":"Mottala",
    "wof:placetype":"locality"
},
  "geometry": {"coordinates":[9.36246,46.39814000000001],"type":"Point"}
}