{
  "type": "Feature",
  "properties": {
    "gn:admin1_code":"9",
    "gn:admin2_code":"CR",
    "gn:admin3_code":"19083.0",
    "gn:asciiname":"Breda Azzolini",
    "gn:country_code":"IT",
    "gn:dem":20,
    "gn:feature_class":"P",
    "gn:feature_code":"PPL",
    "gn:name":"Breda Azzolini",
    "gn:population":83,
    "gn:timezone":"Europe/Rome",
    "iso:country":"IT",
    "wof:name":"Breda Azzolini",
    "wof:placetype":"locality",
    "wof:population":83
},
  "geometry": {"coordinates":[10.48146,45.04434000000001],"type":"Point"}
}