{
  "type": "Feature",
  "properties": {
    "gn:admin1_code":"20",
    "gn:admin2_code":"PD",
    "gn:admin3_code":"28041.0",
    "gn:asciiname":"Follo",
    "gn:country_code":"IT",
    "gn:dem":30,
    "gn:feature_class":"P",
    "gn:feature_code":"PPL",
    "gn:name":"Follo",
    "gn:population":47,
    "gn:timezone":"Europe/Rome",
    "iso:country":"IT",
    "name:azb_x_preferred":[
        "\u0641\u0648\u0644\u0644\u0648"
    ],
    "name:dan_x_preferred":[
        "Follo"
    ],
    "name:ita_x_preferred":[
        "Follo"
    ],
    "name:nno_x_preferred":[
        "Follo"
    ],
    "name:nor_x_preferred":[
        "Follo"
    ],
    "name:sme_x_preferred":[
        "Follo"
    ],
    "name:spa_x_preferred":[
        "Follo"
    ],
    "name:swe_x_preferred":[
        "Follo"
    ],
    "wof:name":"Follo",
    "wof:placetype":"locality",
    "wof:population":47
},
  "geometry": {"coordinates":[11.71856,45.56875],"type":"Point"}
}