{
  "type": "Feature",
  "properties": {
    "gn:admin1_code":"20",
    "gn:admin2_code":"PD",
    "gn:admin3_code":"28041.0",
    "gn:asciiname":"Follo",
    "gn:country_code":"IT",
    "gn:dem":30,
    "gn:feature_class":"P",
    "gn:feature_code":"PPL",
    "gn:name":"Follo",
    "gn:population":47,
    "gn:timezone":"Europe/Rome",
    "iso:country":"IT",
    "wof:name":"Follo",
    "wof:placetype":"locality",
    "wof:population":47
},
  "geometry": {"coordinates":[11.71856,45.56875],"type":"Point"}
}