{
  "type": "Feature",
  "properties": {
    "gn:admin1_code":"4",
    "gn:admin2_code":"BN",
    "gn:admin3_code":"62027.0",
    "gn:asciiname":"Cocola",
    "gn:country_code":"IT",
    "gn:dem":72,
    "gn:feature_class":"P",
    "gn:feature_code":"PPL",
    "gn:name":"Cocola",
    "gn:population":52,
    "gn:timezone":"Europe/Rome",
    "iso:country":"IT",
    "wof:name":"Cocola",
    "wof:placetype":"locality",
    "wof:population":52
},
  "geometry": {"coordinates":[14.47448,41.14803],"type":"Point"}
}