{
  "type": "Feature",
  "properties": {
    "gn:admin1_code":"10",
    "gn:admin2_code":"AP",
    "gn:admin3_code":"44063.0",
    "gn:asciiname":"San Salvatore",
    "gn:country_code":"IT",
    "gn:dem":50,
    "gn:feature_class":"P",
    "gn:feature_code":"PPL",
    "gn:name":"San Salvatore",
    "gn:population":304,
    "gn:timezone":"Europe/Rome",
    "iso:country":"IT",
    "name:cat_x_preferred":[
        "San Salvatore"
    ],
    "name:ceb_x_preferred":[
        "San Salvatore"
    ],
    "name:deu_x_preferred":[
        "San Salvatore"
    ],
    "name:fra_x_preferred":[
        "San Salvatore"
    ],
    "name:ita_x_preferred":[
        "San Salvatore"
    ],
    "name:por_x_preferred":[
        "San Salvatore"
    ],
    "name:rus_x_preferred":[
        "\u0421\u0430\u043d-\u0421\u0430\u043b\u044c\u0432\u0430\u0442\u043e\u0440\u0435"
    ],
    "name:srp_x_preferred":[
        "San Salvatore"
    ],
    "name:swe_x_preferred":[
        "San Salvatore"
    ],
    "wof:name":"San Salvatore",
    "wof:placetype":"locality",
    "wof:population":304
},
  "geometry": {"coordinates":[13.81161,42.98182],"type":"Point"}
}