{
  "type": "Feature",
  "properties": {
    "gn:admin1_code":"14.0",
    "gn:admin2_code":"SU",
    "gn:admin3_code":"111063.0",
    "gn:asciiname":"Is Urigus",
    "gn:country_code":"IT",
    "gn:dem":35,
    "gn:feature_class":"P",
    "gn:feature_code":"PPL",
    "gn:name":"Is Urigus",
    "gn:population":575,
    "gn:timezone":"Europe/Rome",
    "iso:country":"IT",
    "wof:name":"Is Urigus",
    "wof:placetype":"locality",
    "wof:population":575
},
  "geometry": {"coordinates":[8.49455,39.13497],"type":"Point"}
}