{
  "type": "Feature",
  "properties": {
    "gn:admin1_code":"3",
    "gn:admin2_code":"KR",
    "gn:admin3_code":"101010.0",
    "gn:asciiname":"Capocolonna",
    "gn:country_code":"IT",
    "gn:dem":20,
    "gn:feature_class":"P",
    "gn:feature_code":"PPL",
    "gn:name":"Capocolonna",
    "gn:population":58,
    "gn:timezone":"Europe/Rome",
    "iso:country":"IT",
    "wof:name":"Capocolonna",
    "wof:placetype":"locality",
    "wof:population":58
},
  "geometry": {"coordinates":[17.19749,39.02283],"type":"Point"}
}