{
  "type": "Feature",
  "properties": {
    "gn:admin1_code":"6.0",
    "gn:admin2_code":"UD",
    "gn:admin3_code":"30073.0",
    "gn:asciiname":"Trelli",
    "gn:country_code":"IT",
    "gn:dem":770,
    "gn:elevation":"776.0",
    "gn:feature_class":"P",
    "gn:feature_code":"PPL",
    "gn:name":"Trelli",
    "gn:population":214,
    "gn:timezone":"Europe/Rome",
    "iso:country":"IT",
    "wof:name":"Trelli",
    "wof:placetype":"locality",
    "wof:population":214
},
  "geometry": {"coordinates":[13.10094,46.4971],"type":"Point"}
}