{
  "type": "Feature",
  "properties": {
    "gn:admin1_code":"16",
    "gn:admin2_code":"LU",
    "gn:admin3_code":"46023.0",
    "gn:asciiname":"Livignano",
    "gn:country_code":"IT",
    "gn:dem":689,
    "gn:feature_class":"P",
    "gn:feature_code":"PPL",
    "gn:name":"Livignano",
    "gn:population":39,
    "gn:timezone":"Europe/Rome",
    "iso:country":"IT",
    "wof:name":"Livignano",
    "wof:placetype":"locality",
    "wof:population":39
},
  "geometry": {"coordinates":[10.31021,44.20477],"type":"Point"}
}