{
  "type": "Feature",
  "properties": {
    "gn:admin1_code":"12",
    "gn:admin2_code":"AT",
    "gn:admin3_code":"5082.0",
    "gn:asciiname":"Boscorotondo",
    "gn:country_code":"IT",
    "gn:dem":223,
    "gn:feature_class":"P",
    "gn:feature_code":"PPL",
    "gn:name":"Boscorotondo",
    "gn:population":63,
    "gn:timezone":"Europe/Rome",
    "iso:country":"IT",
    "wof:name":"Boscorotondo",
    "wof:placetype":"locality",
    "wof:population":63
},
  "geometry": {"coordinates":[8.01594,45.03836],"type":"Point"}
}