{
  "type": "Feature",
  "properties": {
    "gn:admin1_code":"7",
    "gn:admin2_code":"FR",
    "gn:admin3_code":"60043.0",
    "gn:asciiname":"Ponte Marmone",
    "gn:country_code":"IT",
    "gn:dem":271,
    "gn:feature_class":"P",
    "gn:feature_code":"PPL",
    "gn:name":"Ponte Marmone",
    "gn:population":34,
    "gn:timezone":"Europe/Rome",
    "iso:country":"IT",
    "wof:name":"Ponte Marmone",
    "wof:placetype":"locality",
    "wof:population":34
},
  "geometry": {"coordinates":[13.57372,41.69622],"type":"Point"}
}