{
  "type": "Feature",
  "properties": {
    "gn:admin1_code":"9",
    "gn:admin2_code":"MN",
    "gn:admin3_code":"20063.0",
    "gn:asciiname":"Saresine",
    "gn:country_code":"IT",
    "gn:dem":110,
    "gn:feature_class":"P",
    "gn:feature_code":"PPL",
    "gn:name":"Saresine",
    "gn:population":16,
    "gn:timezone":"Europe/Rome",
    "iso:country":"IT",
    "wof:name":"Saresine",
    "wof:placetype":"locality",
    "wof:population":16
},
  "geometry": {"coordinates":[10.57679,45.38114],"type":"Point"}
}