{
  "type": "Feature",
  "properties": {
    "gn:admin1_code":"9.0",
    "gn:admin2_code":"MI",
    "gn:admin3_code":"15122.0",
    "gn:asciiname":"Localita Produttiva Danzas",
    "gn:country_code":"IT",
    "gn:dem":111,
    "gn:feature_class":"P",
    "gn:feature_code":"PPLL",
    "gn:name":"Localit\u00e0 Produttiva Danzas",
    "gn:population":0,
    "gn:timezone":"Europe/Rome",
    "iso:country":"IT",
    "name:und_x_variant":[
        "Localit\u00e0 Produttiva Danzas"
    ],
    "wof:name":"Localita Produttiva Danzas",
    "wof:placetype":"locality"
},
  "geometry": {"coordinates":[9.42672,45.4761],"type":"Point"}
}