{
  "type": "Feature",
  "properties": {
    "gn:admin1_code":"16.0",
    "gn:admin2_code":"AR",
    "gn:admin3_code":"51002.0",
    "gn:asciiname":"Puglia",
    "gn:country_code":"IT",
    "gn:dem":280,
    "gn:feature_class":"P",
    "gn:feature_code":"PPL",
    "gn:name":"Puglia",
    "gn:population":452,
    "gn:timezone":"Europe/Rome",
    "iso:country":"IT",
    "wof:name":"Puglia",
    "wof:placetype":"locality",
    "wof:population":452
},
  "geometry": {"coordinates":[11.88261,43.5012],"type":"Point"}
}