{
  "type": "Feature",
  "properties": {
    "gn:admin1_code":"5",
    "gn:admin2_code":"PR",
    "gn:admin3_code":"34012.0",
    "gn:asciiname":"Moretta",
    "gn:country_code":"IT",
    "gn:dem":542,
    "gn:feature_class":"P",
    "gn:feature_code":"PPL",
    "gn:name":"Moretta",
    "gn:population":18,
    "gn:timezone":"Europe/Rome",
    "iso:country":"IT",
    "wof:name":"Moretta",
    "wof:placetype":"locality",
    "wof:population":18
},
  "geometry": {"coordinates":[10.12233,44.50708],"type":"Point"}
}