{
  "type": "Feature",
  "properties": {
    "gn:admin1_code":"5",
    "gn:admin2_code":"PR",
    "gn:admin3_code":"34012.0",
    "gn:asciiname":"Moretta",
    "gn:country_code":"IT",
    "gn:dem":542,
    "gn:feature_class":"P",
    "gn:feature_code":"PPL",
    "gn:name":"Moretta",
    "gn:population":18,
    "gn:timezone":"Europe/Rome",
    "iso:country":"IT",
    "name:azb_x_preferred":[
        "\u0645\u0648\u0631\u062a\u0627"
    ],
    "name:bul_x_preferred":[
        "\u041c\u043e\u0440\u0435\u0442\u0430"
    ],
    "name:ceb_x_preferred":[
        "Moretta"
    ],
    "name:deu_x_preferred":[
        "Moretta"
    ],
    "name:epo_x_preferred":[
        "Moretta"
    ],
    "name:eus_x_preferred":[
        "Moretta"
    ],
    "name:fas_x_preferred":[
        "\u0645\u0648\u0631\u062a\u0627"
    ],
    "name:fra_x_preferred":[
        "Moretta"
    ],
    "name:hun_x_preferred":[
        "Moretta"
    ],
    "name:hye_x_preferred":[
        "\u0544\u0578\u0580\u0565\u057f\u0561"
    ],
    "name:ind_x_preferred":[
        "Moretta"
    ],
    "name:ita_x_preferred":[
        "Moretta"
    ],
    "name:jpn_x_preferred":[
        "\u30e2\u30ec\u30c3\u30bf"
    ],
    "name:kaz_x_preferred":[
        "\u041c\u043e\u0440\u0435\u0442\u0442\u0430"
    ],
    "name:lat_x_preferred":[
        "Moreta"
    ],
    "name:lmo_x_preferred":[
        "Moretta"
    ],
    "name:msa_x_preferred":[
        "Moretta"
    ],
    "name:nap_x_preferred":[
        "Moretta"
    ],
    "name:nld_x_preferred":[
        "Moretta"
    ],
    "name:pms_x_preferred":[
        "Mor\u00ebtta"
    ],
    "name:pol_x_preferred":[
        "Moretta"
    ],
    "name:por_x_preferred":[
        "Moretta"
    ],
    "name:ron_x_preferred":[
        "Moretta"
    ],
    "name:rus_x_preferred":[
        "\u041c\u043e\u0440\u0435\u0442\u0442\u0430"
    ],
    "name:scn_x_preferred":[
        "Moretta"
    ],
    "name:spa_x_preferred":[
        "Moretta"
    ],
    "name:srp_x_preferred":[
        "\u041c\u043e\u0440\u0435\u0442\u0430"
    ],
    "name:tgl_x_preferred":[
        "Moretta"
    ],
    "name:tur_x_preferred":[
        "Moretta"
    ],
    "name:ukr_x_preferred":[
        "\u041c\u043e\u0440\u0435\u0442\u0442\u0430"
    ],
    "name:uzb_x_preferred":[
        "Moretta"
    ],
    "name:vie_x_preferred":[
        "Moretta"
    ],
    "name:vol_x_preferred":[
        "Moretta"
    ],
    "name:war_x_preferred":[
        "Moretta"
    ],
    "name:zho_x_preferred":[
        "\u83ab\u96f7\u5854"
    ],
    "wof:name":"Moretta",
    "wof:placetype":"locality",
    "wof:population":18
},
  "geometry": {"coordinates":[10.12233,44.50708],"type":"Point"}
}