{
  "type": "Feature",
  "properties": {
    "gn:admin1_code":"18.0",
    "gn:admin2_code":"PG",
    "gn:admin3_code":"54039.0",
    "gn:asciiname":"Mugnano",
    "gn:country_code":"IT",
    "gn:dem":241,
    "gn:elevation":"234.0",
    "gn:feature_class":"P",
    "gn:feature_code":"PPL",
    "gn:name":"Mugnano",
    "gn:population":871,
    "gn:timezone":"Europe/Rome",
    "iso:country":"IT",
    "wof:name":"Mugnano",
    "wof:placetype":"locality",
    "wof:population":871
},
  "geometry": {"coordinates":[12.21985,43.05546],"type":"Point"}
}