{
  "type": "Feature",
  "properties": {
    "gn:admin1_code":"15",
    "gn:admin2_code":"ME",
    "gn:admin3_code":"83068.0",
    "gn:asciiname":"Acquarancio",
    "gn:country_code":"IT",
    "gn:dem":294,
    "gn:feature_class":"P",
    "gn:feature_code":"PPL",
    "gn:name":"Acquarancio",
    "gn:population":19,
    "gn:timezone":"Europe/Rome",
    "iso:country":"IT",
    "wof:name":"Acquarancio",
    "wof:placetype":"locality",
    "wof:population":19
},
  "geometry": {"coordinates":[14.89951,38.14248],"type":"Point"}
}