{
  "type": "Feature",
  "properties": {
    "gn:admin1_code":"12",
    "gn:admin2_code":"BI",
    "gn:admin3_code":"96065.0",
    "gn:asciiname":"Cesa Bianco",
    "gn:country_code":"IT",
    "gn:dem":442,
    "gn:feature_class":"P",
    "gn:feature_code":"PPL",
    "gn:name":"Cesa Bianco",
    "gn:population":64,
    "gn:timezone":"Europe/Rome",
    "iso:country":"IT",
    "wof:name":"Cesa Bianco",
    "wof:placetype":"locality",
    "wof:population":64
},
  "geometry": {"coordinates":[8.1718,45.61523],"type":"Point"}
}