{
  "type": "Feature",
  "properties": {
    "gn:admin1_code":"12",
    "gn:admin2_code":"CN",
    "gn:admin3_code":"4122.0",
    "gn:asciiname":"Valcurta",
    "gn:country_code":"IT",
    "gn:dem":685,
    "gn:feature_class":"P",
    "gn:feature_code":"PPL",
    "gn:name":"Valcurta",
    "gn:population":14,
    "gn:timezone":"Europe/Rome",
    "iso:country":"IT",
    "wof:name":"Valcurta",
    "wof:placetype":"locality",
    "wof:population":14
},
  "geometry": {"coordinates":[7.33655,44.55737],"type":"Point"}
}