{
  "type": "Feature",
  "properties": {
    "gn:admin1_code":"9",
    "gn:admin2_code":"BS",
    "gn:admin3_code":"17194.0",
    "gn:asciiname":"Persone",
    "gn:country_code":"IT",
    "gn:dem":899,
    "gn:feature_class":"P",
    "gn:feature_code":"PPL",
    "gn:name":"Persone",
    "gn:population":45,
    "gn:timezone":"Europe/Rome",
    "iso:country":"IT",
    "wof:name":"Persone",
    "wof:placetype":"locality",
    "wof:population":45
},
  "geometry": {"coordinates":[10.57536,45.77336],"type":"Point"}
}