{
  "type": "Feature",
  "properties": {
    "gn:admin1_code":"6.0",
    "gn:admin2_code":"TS",
    "gn:admin3_code":"32001.0",
    "gn:asciiname":"Visogliano",
    "gn:country_code":"IT",
    "gn:dem":165,
    "gn:feature_class":"P",
    "gn:feature_code":"PPL",
    "gn:name":"Visogliano",
    "gn:population":0,
    "gn:timezone":"Europe/Rome",
    "iso:country":"IT",
    "wof:name":"Visogliano",
    "wof:placetype":"locality"
},
  "geometry": {"coordinates":[13.65,45.78333],"type":"Point"}
}