{
  "type": "Feature",
  "properties": {
    "gn:admin1_code":"16",
    "gn:admin2_code":"LU",
    "gn:admin3_code":"46030.0",
    "gn:asciiname":"Alla Costa",
    "gn:country_code":"IT",
    "gn:dem":509,
    "gn:feature_class":"P",
    "gn:feature_code":"PPL",
    "gn:name":"Alla Costa",
    "gn:population":61,
    "gn:timezone":"Europe/Rome",
    "iso:country":"IT",
    "wof:name":"Alla Costa",
    "wof:placetype":"locality",
    "wof:population":61
},
  "geometry": {"coordinates":[10.26553,44.01551],"type":"Point"}
}