{
  "type": "Feature",
  "properties": {
    "gn:admin1_code":"12",
    "gn:admin2_code":"CN",
    "gn:admin3_code":"4234.0",
    "gn:asciiname":"Arlotto",
    "gn:country_code":"IT",
    "gn:dem":684,
    "gn:feature_class":"P",
    "gn:feature_code":"PPL",
    "gn:name":"Arlotto",
    "gn:population":13,
    "gn:timezone":"Europe/Rome",
    "iso:country":"IT",
    "wof:name":"Arlotto",
    "wof:placetype":"locality",
    "wof:population":13
},
  "geometry": {"coordinates":[7.35999,44.41463],"type":"Point"}
}