{
  "type": "Feature",
  "properties": {
    "gn:admin1_code":"12",
    "gn:admin2_code":"BI",
    "gn:admin3_code":"96058.0",
    "gn:asciiname":"Campagnola",
    "gn:country_code":"IT",
    "gn:dem":229,
    "gn:feature_class":"P",
    "gn:feature_code":"PPL",
    "gn:name":"Campagnola",
    "gn:population":14,
    "gn:timezone":"Europe/Rome",
    "iso:country":"IT",
    "wof:name":"Campagnola",
    "wof:placetype":"locality",
    "wof:population":14
},
  "geometry": {"coordinates":[8.13158,45.45798],"type":"Point"}
}