{
  "type": "Feature",
  "properties": {
    "gn:admin1_code":"15",
    "gn:admin2_code":"ME",
    "gn:admin3_code":"83033.0",
    "gn:asciiname":"Passolauro",
    "gn:country_code":"IT",
    "gn:dem":447,
    "gn:feature_class":"P",
    "gn:feature_code":"PPL",
    "gn:name":"Passolauro",
    "gn:population":17,
    "gn:timezone":"Europe/Rome",
    "iso:country":"IT",
    "wof:name":"Passolauro",
    "wof:placetype":"locality",
    "wof:population":17
},
  "geometry": {"coordinates":[14.90169,38.134],"type":"Point"}
}