{
  "type": "Feature",
  "properties": {
    "gn:admin1_code":"16",
    "gn:admin2_code":"SI",
    "gn:admin3_code":"52032.0",
    "gn:asciiname":"Montechiaro",
    "gn:country_code":"IT",
    "gn:dem":277,
    "gn:feature_class":"P",
    "gn:feature_code":"PPL",
    "gn:name":"Montechiaro",
    "gn:population":18,
    "gn:timezone":"Europe/Rome",
    "iso:country":"IT",
    "name:ceb_x_preferred":[
        "Montechiaro"
    ],
    "name:ita_x_preferred":[
        "Montechiaro"
    ],
    "name:por_x_preferred":[
        "Montechiaro"
    ],
    "name:srp_x_preferred":[
        "Montekjaro"
    ],
    "name:swe_x_preferred":[
        "Montechiaro"
    ],
    "wof:name":"Montechiaro",
    "wof:placetype":"locality",
    "wof:population":18
},
  "geometry": {"coordinates":[11.40462,43.33215],"type":"Point"}
}