{
  "type": "Feature",
  "properties": {
    "gn:admin1_code":"20",
    "gn:admin2_code":"TV",
    "gn:admin3_code":"26036.0",
    "gn:asciiname":"Case Nervo",
    "gn:country_code":"IT",
    "gn:dem":80,
    "gn:feature_class":"P",
    "gn:feature_code":"PPL",
    "gn:name":"Case Nervo",
    "gn:population":27,
    "gn:timezone":"Europe/Rome",
    "iso:country":"IT",
    "wof:name":"Case Nervo",
    "wof:placetype":"locality",
    "wof:population":27
},
  "geometry": {"coordinates":[11.83508,45.7394],"type":"Point"}
}