{
  "type": "Feature",
  "properties": {
    "gn:admin1_code":"20.0",
    "gn:admin2_code":"BL",
    "gn:admin3_code":"25044.0",
    "gn:asciiname":"Caracoi Agoin",
    "gn:country_code":"IT",
    "gn:dem":1265,
    "gn:feature_class":"P",
    "gn:feature_code":"PPL",
    "gn:name":"Caracoi Agoin",
    "gn:population":6,
    "gn:timezone":"Europe/Rome",
    "iso:country":"IT",
    "wof:name":"Caracoi Agoin",
    "wof:placetype":"locality",
    "wof:population":6
},
  "geometry": {"coordinates":[11.99827,46.42302],"type":"Point"}
}