{
  "type": "Feature",
  "properties": {
    "gn:admin1_code":"20.0",
    "gn:admin2_code":"VE",
    "gn:admin3_code":"27034.0",
    "gn:asciiname":"Marinella",
    "gn:cc2":"IT",
    "gn:country_code":"IT",
    "gn:dem":-2,
    "gn:elevation":"3.0",
    "gn:feature_class":"P",
    "gn:feature_code":"PPL",
    "gn:name":"Marinella",
    "gn:population":320,
    "gn:timezone":"Europe/Rome",
    "iso:country":"IT",
    "name:bul_x_preferred":[
        "\u041c\u0430\u0440\u0438\u043d\u0435\u043b\u0430"
    ],
    "name:deu_x_preferred":[
        "Marinella"
    ],
    "name:ell_x_preferred":[
        "\u039c\u03b1\u03c1\u03b9\u03bd\u03ad\u03bb\u03bb\u03b1"
    ],
    "name:est_x_preferred":[
        "Marin\u00e9lla"
    ],
    "name:fra_x_preferred":[
        "Marinella"
    ],
    "name:kor_x_preferred":[
        "\ub9c8\ub9ac\ub12c\ub77c"
    ],
    "name:lit_x_preferred":[
        "Marinella"
    ],
    "name:nld_x_preferred":[
        "Marinella"
    ],
    "name:pol_x_preferred":[
        "Marinella"
    ],
    "name:por_x_preferred":[
        "Marinella"
    ],
    "name:rus_x_preferred":[
        "\u041c\u0430\u0440\u0438\u043d\u0435\u043b\u043b\u0430"
    ],
    "name:spa_x_preferred":[
        "Marinella"
    ],
    "name:swe_x_preferred":[
        "Marinella"
    ],
    "name:tur_x_preferred":[
        "Marinella"
    ],
    "name:ukr_x_preferred":[
        "\u041c\u0430\u0440\u0456\u043d\u0435\u043b\u043b\u0430"
    ],
    "name:und_x_variant":[
        "Brigolo di Sopra",
        "Brigolo",
        "Marinella"
    ],
    "wof:name":"Marinella",
    "wof:placetype":"locality",
    "wof:population":320
},
  "geometry": {"coordinates":[13.02824,45.69805],"type":"Point"}
}