{
  "type": "Feature",
  "properties": {
    "gn:admin1_code":"10",
    "gn:admin2_code":"PU",
    "gn:admin3_code":"41043.0",
    "gn:asciiname":"Percozzone",
    "gn:country_code":"IT",
    "gn:dem":399,
    "gn:feature_class":"P",
    "gn:feature_code":"PPL",
    "gn:name":"Percozzone",
    "gn:population":21,
    "gn:timezone":"Europe/Rome",
    "iso:country":"IT",
    "wof:name":"Percozzone",
    "wof:placetype":"locality",
    "wof:population":21
},
  "geometry": {"coordinates":[12.8389,43.51806],"type":"Point"}
}