{
  "type": "Feature",
  "properties": {
    "gn:admin1_code":"9.0",
    "gn:admin2_code":"PV",
    "gn:admin3_code":"18060.0",
    "gn:asciiname":"Prado",
    "gn:country_code":"IT",
    "gn:dem":81,
    "gn:feature_class":"P",
    "gn:feature_code":"PPL",
    "gn:name":"Prado",
    "gn:population":0,
    "gn:timezone":"Europe/Rome",
    "iso:country":"IT",
    "wof:name":"Prado",
    "wof:placetype":"locality"
},
  "geometry": {"coordinates":[9.21693,45.20876],"type":"Point"}
}