{
  "type": "Feature",
  "properties": {
    "gn:admin1_code":"5",
    "gn:admin2_code":"RE",
    "gn:admin3_code":"35041.0",
    "gn:asciiname":"L'Oca",
    "gn:country_code":"IT",
    "gn:dem":480,
    "gn:feature_class":"P",
    "gn:feature_code":"PPL",
    "gn:name":"L'Oca",
    "gn:population":63,
    "gn:timezone":"Europe/Rome",
    "iso:country":"IT",
    "wof:name":"L'Oca",
    "wof:placetype":"locality",
    "wof:population":63
},
  "geometry": {"coordinates":[10.54223,44.40624],"type":"Point"}
}