{
  "type": "Feature",
  "properties": {
    "gn:admin1_code":"7",
    "gn:admin2_code":"FR",
    "gn:admin3_code":"60070.0",
    "gn:asciiname":"Ponte Sette Archi",
    "gn:country_code":"IT",
    "gn:dem":75,
    "gn:feature_class":"P",
    "gn:feature_code":"PPL",
    "gn:name":"Ponte Sette Archi",
    "gn:population":38,
    "gn:timezone":"Europe/Rome",
    "iso:country":"IT",
    "wof:name":"Ponte Sette Archi",
    "wof:placetype":"locality",
    "wof:population":38
},
  "geometry": {"coordinates":[13.90646,41.45181],"type":"Point"}
}