{
  "type": "Feature",
  "properties": {
    "gn:admin1_code":"7.0",
    "gn:admin2_code":"RM",
    "gn:admin3_code":"58007.0",
    "gn:asciiname":"Casale Vignarola",
    "gn:country_code":"IT",
    "gn:dem":15,
    "gn:feature_class":"P",
    "gn:feature_code":"PPL",
    "gn:name":"Casale Vignarola",
    "gn:population":0,
    "gn:timezone":"Europe/Rome",
    "iso:country":"IT",
    "wof:name":"Casale Vignarola",
    "wof:placetype":"locality"
},
  "geometry": {"coordinates":[12.59136,41.48878],"type":"Point"}
}