{
  "type": "Feature",
  "properties": {
    "gn:admin1_code":"17.0",
    "gn:admin2_code":"BZ",
    "gn:admin3_code":"21022.0",
    "gn:asciiname":"Ronchi",
    "gn:country_code":"IT",
    "gn:dem":1197,
    "gn:feature_class":"P",
    "gn:feature_code":"PPL",
    "gn:name":"Ronchi",
    "gn:population":0,
    "gn:timezone":"Europe/Rome",
    "iso:country":"IT",
    "name:ceb_x_preferred":[
        "Ronchi"
    ],
    "name:deu_x_preferred":[
        "Ronchi"
    ],
    "name:epo_x_preferred":[
        "Ronchi"
    ],
    "name:ita_x_preferred":[
        "Ronchi"
    ],
    "name:lat_x_preferred":[
        "Ronches"
    ],
    "name:por_x_preferred":[
        "Ronchi"
    ],
    "name:scn_x_preferred":[
        "Ronchi"
    ],
    "name:srp_x_preferred":[
        "Ronki"
    ],
    "name:swe_x_preferred":[
        "Ronchi"
    ],
    "wof:name":"Ronchi",
    "wof:placetype":"locality"
},
  "geometry": {"coordinates":[11.53333,46.68333],"type":"Point"}
}