{
  "type": "Feature",
  "properties": {
    "gn:admin1_code":"16",
    "gn:admin2_code":"PI",
    "gn:admin3_code":"50008.0",
    "gn:asciiname":"Chiesanuova",
    "gn:country_code":"IT",
    "gn:dem":4,
    "gn:feature_class":"P",
    "gn:feature_code":"PPL",
    "gn:name":"Chiesanuova",
    "gn:population":86,
    "gn:timezone":"Europe/Rome",
    "iso:country":"IT",
    "name:ara_x_preferred":[
        "\u062a\u0634\u064a\u0633\u0627\u0646\u0648\u0641\u0627"
    ],
    "name:ast_x_preferred":[
        "Chiesanuova"
    ],
    "name:cat_x_preferred":[
        "Chiesanuova"
    ],
    "name:ces_x_preferred":[
        "Chiesanuova"
    ],
    "name:deu_x_preferred":[
        "Chiesanuova"
    ],
    "name:epo_x_preferred":[
        "Chiesanuova"
    ],
    "name:eus_x_preferred":[
        "Chiesanuova"
    ],
    "name:fas_x_preferred":[
        "\u06a9\u06cc\u0633\u0627\u0646\u0648\u0648\u0648\u0627"
    ],
    "name:fin_x_preferred":[
        "Chiesanuova"
    ],
    "name:fra_x_preferred":[
        "Chiesanuova"
    ],
    "name:glg_x_preferred":[
        "Chiesanuova"
    ],
    "name:heb_x_preferred":[
        "\u05e7\u05d9\u05d9\u05d6\u05d0\u05e0\u05d5\u05d0\u05d5\u05d1\u05d4"
    ],
    "name:hun_x_preferred":[
        "Chiesanuova"
    ],
    "name:hye_x_preferred":[
        "\u053f\u056b\u0565\u0566\u0561\u0576\u0578\u0582\u0578\u057e\u0561"
    ],
    "name:ind_x_preferred":[
        "Chiesanuova"
    ],
    "name:ita_x_preferred":[
        "Chiesanuova"
    ],
    "name:jpn_x_preferred":[
        "\u30ad\u30a8\u30b6\u30cc\u30aa\u30fc\u30f4\u30a1"
    ],
    "name:kor_x_preferred":[
        "\ud0a4\uc5d0\uc0ac\ub204\uc624\ubc14"
    ],
    "name:lat_x_preferred":[
        "Ecclesia Nova"
    ],
    "name:lit_x_preferred":[
        "Kjezanuova"
    ],
    "name:lmo_x_preferred":[
        "Chiesanuova"
    ],
    "name:ltz_x_preferred":[
        "Chiesanuova"
    ],
    "name:nap_x_preferred":[
        "Chiesanuova"
    ],
    "name:nld_x_preferred":[
        "Chiesanuova"
    ],
    "name:nno_x_preferred":[
        "Chiesanuova"
    ],
    "name:nor_x_preferred":[
        "Chiesanuova"
    ],
    "name:pol_x_preferred":[
        "Chiesanuova"
    ],
    "name:por_x_preferred":[
        "Chiesanuova"
    ],
    "name:ron_x_preferred":[
        "Chiesanuova"
    ],
    "name:run_x_preferred":[
        "Chiesanuova"
    ],
    "name:rus_x_preferred":[
        "\u041a\u044c\u0435\u0437\u0430\u043d\u0443\u043e\u0432\u0430"
    ],
    "name:sco_x_preferred":[
        "Chiesanuova"
    ],
    "name:slk_x_preferred":[
        "Chiesanuova"
    ],
    "name:spa_x_preferred":[
        "Chiesanuova"
    ],
    "name:srp_x_preferred":[
        "\u041a\u0458\u0435\u0437\u0430\u043d\u0443\u043e\u0432\u0430"
    ],
    "name:swe_x_preferred":[
        "Chiesanuova"
    ],
    "name:tur_x_preferred":[
        "Chiesanuova"
    ],
    "name:ukr_x_preferred":[
        "\u041a'\u0454\u0437\u0430\u043d\u0443\u043e\u0432\u0430"
    ],
    "name:urd_x_preferred":[
        "\u06a9\u06cc\u0626\u0632\u0627\u0646\u0648\u0648\u0627"
    ],
    "name:vol_x_preferred":[
        "Chiesanuova"
    ],
    "name:war_x_preferred":[
        "Chiesanuova"
    ],
    "name:zho_x_preferred":[
        "\u57fa\u57c3\u8428\u52aa\u6b27\u74e6"
    ],
    "wof:name":"Chiesanuova",
    "wof:placetype":"locality",
    "wof:population":86
},
  "geometry": {"coordinates":[10.50255,43.65312],"type":"Point"}
}