{
  "type": "Feature",
  "properties": {
    "gn:admin1_code":"16",
    "gn:admin2_code":"PI",
    "gn:admin3_code":"50008.0",
    "gn:asciiname":"Chiesanuova",
    "gn:country_code":"IT",
    "gn:dem":4,
    "gn:feature_class":"P",
    "gn:feature_code":"PPL",
    "gn:name":"Chiesanuova",
    "gn:population":86,
    "gn:timezone":"Europe/Rome",
    "iso:country":"IT",
    "wof:name":"Chiesanuova",
    "wof:placetype":"locality",
    "wof:population":86
},
  "geometry": {"coordinates":[10.50255,43.65312],"type":"Point"}
}