{
  "type": "Feature",
  "properties": {
    "gn:admin1_code":"20.0",
    "gn:admin2_code":"VE",
    "gn:admin3_code":"27023.0",
    "gn:asciiname":"Romea",
    "gn:country_code":"IT",
    "gn:dem":2,
    "gn:feature_class":"P",
    "gn:feature_code":"PPLL",
    "gn:name":"Romea",
    "gn:population":0,
    "gn:timezone":"Europe/Rome",
    "iso:country":"IT",
    "name:ita_x_preferred":[
        "Romea"
    ],
    "wof:name":"Romea",
    "wof:placetype":"locality"
},
  "geometry": {"coordinates":[12.17134,45.42255],"type":"Point"}
}