{
  "type": "Feature",
  "properties": {
    "gn:admin1_code":"20.0",
    "gn:admin2_code":"BL",
    "gn:admin3_code":"25073.0",
    "gn:asciiname":"Gavaz",
    "gn:country_code":"IT",
    "gn:dem":1184,
    "gn:elevation":"1177.0",
    "gn:feature_class":"P",
    "gn:feature_code":"PPL",
    "gn:name":"Gavaz",
    "gn:population":116,
    "gn:timezone":"Europe/Rome",
    "iso:country":"IT",
    "wof:name":"Gavaz",
    "wof:placetype":"locality",
    "wof:population":116
},
  "geometry": {"coordinates":[12.12133,46.34664],"type":"Point"}
}