{
  "type": "Feature",
  "properties": {
    "gn:admin1_code":"20",
    "gn:admin2_code":"VE",
    "gn:admin3_code":"27021.0",
    "gn:asciiname":"Ca' Longo",
    "gn:country_code":"IT",
    "gn:dem":10,
    "gn:feature_class":"P",
    "gn:feature_code":"PPL",
    "gn:name":"Ca' Longo",
    "gn:population":49,
    "gn:timezone":"Europe/Rome",
    "iso:country":"IT",
    "wof:name":"Ca' Longo",
    "wof:placetype":"locality",
    "wof:population":49
},
  "geometry": {"coordinates":[12.12877,45.56278],"type":"Point"}
}