{
  "type": "Feature",
  "properties": {
    "gn:admin1_code":"5.0",
    "gn:admin2_code":"RE",
    "gn:admin3_code":"35033.0",
    "gn:asciiname":"Cantone",
    "gn:country_code":"IT",
    "gn:dem":104,
    "gn:feature_class":"P",
    "gn:feature_code":"PPL",
    "gn:name":"Cantone",
    "gn:population":0,
    "gn:timezone":"Europe/Rome",
    "iso:country":"IT",
    "wof:name":"Cantone",
    "wof:placetype":"locality"
},
  "geometry": {"coordinates":[10.58333,44.65],"type":"Point"}
}