{
  "type": "Feature",
  "properties": {
    "gn:admin1_code":"4",
    "gn:admin2_code":"CE",
    "gn:admin3_code":"61088.0",
    "gn:asciiname":"Le Perle",
    "gn:country_code":"IT",
    "gn:dem":5,
    "gn:feature_class":"P",
    "gn:feature_code":"PPL",
    "gn:name":"Le Perle",
    "gn:population":16,
    "gn:timezone":"Europe/Rome",
    "iso:country":"IT",
    "wof:name":"Le Perle",
    "wof:placetype":"locality",
    "wof:population":16
},
  "geometry": {"coordinates":[13.84536,41.15915],"type":"Point"}
}