{
  "type": "Feature",
  "properties": {
    "gn:admin1_code":"20",
    "gn:admin2_code":"VI",
    "gn:admin3_code":"24055.0",
    "gn:asciiname":"Colombaretta",
    "gn:country_code":"IT",
    "gn:dem":112,
    "gn:feature_class":"P",
    "gn:feature_code":"PPL",
    "gn:name":"Colombaretta",
    "gn:population":21,
    "gn:timezone":"Europe/Rome",
    "iso:country":"IT",
    "wof:name":"Colombaretta",
    "wof:placetype":"locality",
    "wof:population":21
},
  "geometry": {"coordinates":[11.42417,45.66445],"type":"Point"}
}