{
  "type": "Feature",
  "properties": {
    "gn:admin1_code":"9",
    "gn:admin2_code":"PV",
    "gn:admin3_code":"18023.0",
    "gn:asciiname":"Padana",
    "gn:country_code":"IT",
    "gn:dem":64,
    "gn:feature_class":"P",
    "gn:feature_code":"PPLL",
    "gn:name":"Padana",
    "gn:population":9,
    "gn:timezone":"Europe/Rome",
    "iso:country":"IT",
    "wof:name":"Padana",
    "wof:placetype":"locality",
    "wof:population":9
},
  "geometry": {"coordinates":[9.1393,45.06788],"type":"Point"}
}