{
  "type": "Feature",
  "properties": {
    "gn:admin1_code":"20",
    "gn:admin2_code":"PD",
    "gn:admin3_code":"28019.0",
    "gn:asciiname":"Patissi",
    "gn:country_code":"IT",
    "gn:dem":20,
    "gn:feature_class":"P",
    "gn:feature_code":"PPL",
    "gn:name":"Patissi",
    "gn:population":54,
    "gn:timezone":"Europe/Rome",
    "iso:country":"IT",
    "wof:name":"Patissi",
    "wof:placetype":"locality",
    "wof:population":54
},
  "geometry": {"coordinates":[11.98323,45.58125],"type":"Point"}
}