{
  "type": "Feature",
  "properties": {
    "gn:admin1_code":"5",
    "gn:admin2_code":"PR",
    "gn:admin3_code":"34020.0",
    "gn:asciiname":"Arduini",
    "gn:country_code":"IT",
    "gn:dem":168,
    "gn:feature_class":"P",
    "gn:feature_code":"PPL",
    "gn:name":"Arduini",
    "gn:population":52,
    "gn:timezone":"Europe/Rome",
    "iso:country":"IT",
    "name:ita_x_preferred":[
        "Arduini"
    ],
    "wof:name":"Arduini",
    "wof:placetype":"locality",
    "wof:population":52
},
  "geometry": {"coordinates":[10.12548,44.75737],"type":"Point"}
}