{
  "type": "Feature",
  "properties": {
    "gn:admin1_code":"5",
    "gn:admin2_code":"RE",
    "gn:admin3_code":"35046.0",
    "gn:asciiname":"Piolo",
    "gn:country_code":"IT",
    "gn:dem":853,
    "gn:feature_class":"P",
    "gn:feature_code":"PPL",
    "gn:name":"Piolo",
    "gn:population":86,
    "gn:timezone":"Europe/Rome",
    "iso:country":"IT",
    "wof:name":"Piolo",
    "wof:placetype":"locality",
    "wof:population":86
},
  "geometry": {"coordinates":[10.35432,44.33061],"type":"Point"}
}