{
  "type": "Feature",
  "properties": {
    "gn:admin1_code":"12",
    "gn:admin2_code":"VC",
    "gn:admin3_code":"2052.0",
    "gn:asciiname":"Viancino",
    "gn:country_code":"IT",
    "gn:dem":164,
    "gn:feature_class":"P",
    "gn:feature_code":"PPL",
    "gn:name":"Viancino",
    "gn:population":35,
    "gn:timezone":"Europe/Rome",
    "iso:country":"IT",
    "wof:name":"Viancino",
    "wof:placetype":"locality",
    "wof:population":35
},
  "geometry": {"coordinates":[8.23166,45.32618],"type":"Point"}
}