{
  "type": "Feature",
  "properties": {
    "gn:admin1_code":"9.0",
    "gn:admin2_code":"BG",
    "gn:admin3_code":"16064.0",
    "gn:asciiname":"Dorga",
    "gn:country_code":"IT",
    "gn:dem":948,
    "gn:feature_class":"P",
    "gn:feature_code":"PPL",
    "gn:name":"Dorga",
    "gn:population":0,
    "gn:timezone":"Europe/Rome",
    "iso:country":"IT",
    "wof:name":"Dorga",
    "wof:placetype":"locality"
},
  "geometry": {"coordinates":[10.05,45.91667],"type":"Point"}
}