{
  "type": "Feature",
  "properties": {
    "gn:admin1_code":"16",
    "gn:admin2_code":"PT",
    "gn:admin3_code":"47014.0",
    "gn:asciiname":"Prombialla",
    "gn:country_code":"IT",
    "gn:dem":355,
    "gn:feature_class":"P",
    "gn:feature_code":"PPL",
    "gn:name":"Prombialla",
    "gn:population":68,
    "gn:timezone":"Europe/Rome",
    "iso:country":"IT",
    "wof:name":"Prombialla",
    "wof:placetype":"locality",
    "wof:population":68
},
  "geometry": {"coordinates":[10.90693,44.01854],"type":"Point"}
}