{
  "type": "Feature",
  "properties": {
    "gn:admin1_code":"3.0",
    "gn:admin2_code":"CS",
    "gn:admin3_code":"78031.0",
    "gn:asciiname":"Ortomatera",
    "gn:country_code":"IT",
    "gn:dem":240,
    "gn:feature_class":"P",
    "gn:feature_code":"PPL",
    "gn:name":"Ortomatera",
    "gn:population":941,
    "gn:timezone":"Europe/Rome",
    "iso:country":"IT",
    "wof:name":"Ortomatera",
    "wof:placetype":"locality",
    "wof:population":941
},
  "geometry": {"coordinates":[16.21433,39.32452],"type":"Point"}
}