{
  "type": "Feature",
  "properties": {
    "gn:admin1_code":"19.0",
    "gn:admin2_code":"AO",
    "gn:admin3_code":"7030.0",
    "gn:asciiname":"Variney Chez Roncoz",
    "gn:country_code":"IT",
    "gn:dem":775,
    "gn:feature_class":"P",
    "gn:feature_code":"PPL",
    "gn:name":"Variney Chez Roncoz",
    "gn:population":541,
    "gn:timezone":"Europe/Rome",
    "iso:country":"IT",
    "wof:name":"Variney Chez Roncoz",
    "wof:placetype":"locality",
    "wof:population":541
},
  "geometry": {"coordinates":[7.31051,45.76882],"type":"Point"}
}