{
  "type": "Feature",
  "properties": {
    "gn:admin1_code":"15.0",
    "gn:admin2_code":"RG",
    "gn:admin3_code":"88005.0",
    "gn:asciiname":"Aziende Agricole Associate Fonte Verde",
    "gn:country_code":"IT",
    "gn:dem":54,
    "gn:feature_class":"P",
    "gn:feature_code":"PPL",
    "gn:name":"Aziende Agricole Associate Fonte Verde",
    "gn:population":1,
    "gn:timezone":"Europe/Rome",
    "iso:country":"IT",
    "wof:name":"Aziende Agricole Associate Fonte Verde",
    "wof:placetype":"locality",
    "wof:population":1
},
  "geometry": {"coordinates":[14.93721,36.75914],"type":"Point"}
}