{
  "type": "Feature",
  "properties": {
    "gn:admin1_code":"6.0",
    "gn:admin2_code":"UD",
    "gn:admin3_code":"30136.0",
    "gn:asciiname":"Formeaso",
    "gn:country_code":"IT",
    "gn:dem":440,
    "gn:feature_class":"P",
    "gn:feature_code":"PPL",
    "gn:name":"Formeaso",
    "gn:population":0,
    "gn:timezone":"Europe/Rome",
    "iso:country":"IT",
    "wof:name":"Formeaso",
    "wof:placetype":"locality"
},
  "geometry": {"coordinates":[13.02222,46.45472],"type":"Point"}
}