{
  "type": "Feature",
  "properties": {
    "gn:admin1_code":"5",
    "gn:admin2_code":"PC",
    "gn:admin3_code":"33004.0",
    "gn:asciiname":"Groppo Ducale",
    "gn:country_code":"IT",
    "gn:dem":769,
    "gn:feature_class":"P",
    "gn:feature_code":"PPL",
    "gn:name":"Groppo Ducale",
    "gn:population":22,
    "gn:timezone":"Europe/Rome",
    "iso:country":"IT",
    "wof:name":"Groppo Ducale",
    "wof:placetype":"locality",
    "wof:population":22
},
  "geometry": {"coordinates":[9.64024,44.73784000000001],"type":"Point"}
}