{
  "type": "Feature",
  "properties": {
    "gn:admin1_code":"5",
    "gn:admin2_code":"PR",
    "gn:admin3_code":"34025.0",
    "gn:asciiname":"Giarine",
    "gn:country_code":"IT",
    "gn:dem":84,
    "gn:feature_class":"P",
    "gn:feature_code":"PPL",
    "gn:name":"Giarine",
    "gn:population":18,
    "gn:timezone":"Europe/Rome",
    "iso:country":"IT",
    "wof:name":"Giarine",
    "wof:placetype":"locality",
    "wof:population":18
},
  "geometry": {"coordinates":[10.09552,44.83294],"type":"Point"}
}