{
  "type": "Feature",
  "properties": {
    "iso:country":"IT",
    "name:ita_x_preferred":[
        "Riviera"
    ],
    "name:unk_x_variant":[
        "Riviera"
    ],
    "qs:gn_adm0_cc":"IT",
    "qs:gn_fcode":"PPL",
    "qs:gn_local":3165185,
    "qs:gn_nam_loc":"Trieste, Trieste, Trieste, Friuli Venezia Giulia, IT",
    "qs:gn_namadm1":"06",
    "qs:gn_name":"Riviera",
    "qs:local_max":9211,
    "qs:local_sum":26825,
    "qs:localhoods":32,
    "qs:name":"Riviera",
    "qs:name_adm0":"Italia",
    "qs:name_adm1":"Friuli-Venezia Giulia",
    "qs:name_adm2":"Trieste",
    "qs:name_lau":"Trieste",
    "qs:name_local":"Trieste",
    "qs:photo_max":184,
    "qs:photo_sum":371,
    "qs:placetype":"Suburb",
    "qs:quad_count":22,
    "qs:woe_adm0":23424853,
    "qs:woe_adm1":7153335,
    "qs:woe_adm2":12591892,
    "qs:woe_lau":12676517,
    "qs:woe_local":725300,
    "qs:woe_ver":"7.10.0",
    "wof:lang":[
        "ita"
    ],
    "wof:name":"Riviera",
    "wof:placetype":"neighbourhood"
},
  "geometry": {"coordinates":[13.751933,45.679947],"type":"Point"}
}