{
  "type": "Feature",
  "properties": {
    "iso:country":"IT",
    "name:ara_x_preferred":[
        "\u0631\u064a\u0641\u064a\u064a\u0631\u0627"
    ],
    "name:ben_x_preferred":[
        "\u09b0\u09bf\u09ad\u09bf\u09df\u09c7\u09b0\u09be"
    ],
    "name:bre_x_preferred":[
        "Riviera"
    ],
    "name:bul_x_preferred":[
        "\u0420\u0438\u0432\u0438\u0435\u0440\u0430"
    ],
    "name:deu_x_preferred":[
        "Riviera"
    ],
    "name:ell_x_preferred":[
        "\u03a1\u03b9\u03b2\u03b9\u03ad\u03c1\u03b1"
    ],
    "name:epo_x_preferred":[
        "Riviero"
    ],
    "name:fin_x_preferred":[
        "Riviera"
    ],
    "name:fra_x_preferred":[
        "Riviera"
    ],
    "name:hin_x_preferred":[
        "\u0930\u093f\u0935\u0947\u0930\u093e"
    ],
    "name:hun_x_preferred":[
        "Rivi\u00e9ra"
    ],
    "name:hye_x_preferred":[
        "\u054c\u056b\u057e\u056b\u0565\u0580\u0561"
    ],
    "name:ita_x_preferred":[
        "Riviera"
    ],
    "name:kir_x_preferred":[
        "\u0420\u0438\u0432\u044c\u0435\u0440\u0430"
    ],
    "name:lav_x_preferred":[
        "Rivj\u0113ra"
    ],
    "name:nld_x_preferred":[
        "Rivi\u00e8ra"
    ],
    "name:nor_x_preferred":[
        "Rivieraen"
    ],
    "name:pol_x_preferred":[
        "Riwiera"
    ],
    "name:ron_x_preferred":[
        "Riviera"
    ],
    "name:rus_x_preferred":[
        "\u0420\u0438\u0432\u044c\u0435\u0440\u0430"
    ],
    "name:spa_x_preferred":[
        "Riviera"
    ],
    "name:swe_x_preferred":[
        "Rivieran"
    ],
    "name:urd_x_preferred":[
        "\u0631\u0627\u0626\u06cc\u0648\u06cc\u0631\u0627"
    ],
    "qs:gn_adm0_cc":"IT",
    "qs:gn_fcode":"PPL",
    "qs:gn_local":3165185,
    "qs:gn_nam_loc":"Trieste, Trieste, Trieste, Friuli Venezia Giulia, IT",
    "qs:gn_namadm1":"06",
    "qs:gn_name":"Riviera",
    "qs:local_max":9211,
    "qs:local_sum":26825,
    "qs:localhoods":32,
    "qs:name":"Riviera",
    "qs:name_adm0":"Italia",
    "qs:name_adm1":"Friuli-Venezia Giulia",
    "qs:name_adm2":"Trieste",
    "qs:name_lau":"Trieste",
    "qs:name_local":"Trieste",
    "qs:photo_max":184,
    "qs:photo_sum":371,
    "qs:placetype":"Suburb",
    "qs:quad_count":22,
    "qs:woe_adm0":23424853,
    "qs:woe_adm1":7153335,
    "qs:woe_adm2":12591892,
    "qs:woe_lau":12676517,
    "qs:woe_local":725300,
    "qs:woe_ver":"7.10.0",
    "wof:lang":[
        "ita"
    ],
    "wof:name":"Riviera",
    "wof:placetype":"neighbourhood"
},
  "geometry": {"coordinates":[13.751933,45.679947],"type":"Point"}
}