{
  "type": "Feature",
  "properties": {
    "gn:admin1_code":"3",
    "gn:admin2_code":"RC",
    "gn:admin3_code":"80045.0",
    "gn:asciiname":"Romano",
    "gn:country_code":"IT",
    "gn:dem":19,
    "gn:feature_class":"P",
    "gn:feature_code":"PPL",
    "gn:name":"Romano",
    "gn:population":106,
    "gn:timezone":"Europe/Rome",
    "iso:country":"IT",
    "name:cat_x_preferred":[
        "Romano"
    ],
    "name:ceb_x_preferred":[
        "Romano"
    ],
    "name:deu_x_preferred":[
        "Romano"
    ],
    "name:fas_x_preferred":[
        "\u0631\u0648\u0645\u0627\u0646\u0648"
    ],
    "name:fra_x_preferred":[
        "Romano"
    ],
    "name:glg_x_preferred":[
        "Romano"
    ],
    "name:heb_x_preferred":[
        "\u05e8\u05d5\u05de\u05e0\u05d5"
    ],
    "name:ita_x_preferred":[
        "Romano"
    ],
    "name:rus_x_preferred":[
        "\u0420\u043e\u043c\u0430\u043d\u043e"
    ],
    "name:scn_x_preferred":[
        "Rumanu"
    ],
    "name:spa_x_preferred":[
        "Romano"
    ],
    "name:srp_x_preferred":[
        "\u0420\u043e\u043c\u0430\u043d\u043e"
    ],
    "name:swe_x_preferred":[
        "Romano"
    ],
    "name:tgl_x_preferred":[
        "Romano"
    ],
    "name:ukr_x_preferred":[
        "\u0420\u043e\u043c\u0430\u043d\u043e"
    ],
    "wof:name":"Romano",
    "wof:placetype":"locality",
    "wof:population":106
},
  "geometry": {"coordinates":[16.34547,38.30917],"type":"Point"}
}