{
  "type": "Feature",
  "properties": {
    "gn:admin1_code":"3",
    "gn:admin2_code":"RC",
    "gn:admin3_code":"80045.0",
    "gn:asciiname":"Romano",
    "gn:country_code":"IT",
    "gn:dem":19,
    "gn:feature_class":"P",
    "gn:feature_code":"PPL",
    "gn:name":"Romano",
    "gn:population":106,
    "gn:timezone":"Europe/Rome",
    "iso:country":"IT",
    "wof:name":"Romano",
    "wof:placetype":"locality",
    "wof:population":106
},
  "geometry": {"coordinates":[16.34547,38.30917],"type":"Point"}
}