{
  "type": "Feature",
  "properties": {
    "gn:admin1_code":"6.0",
    "gn:admin2_code":"GO",
    "gn:admin3_code":"31003.0",
    "gn:asciiname":"Devetachi",
    "gn:country_code":"IT",
    "gn:dem":61,
    "gn:elevation":"66.0",
    "gn:feature_class":"P",
    "gn:feature_code":"PPL",
    "gn:name":"Devetachi",
    "gn:population":18,
    "gn:timezone":"Europe/Rome",
    "iso:country":"IT",
    "name:slv_x_preferred":[
        "Devetaki"
    ],
    "wof:name":"Devetachi",
    "wof:placetype":"locality",
    "wof:population":18
},
  "geometry": {"coordinates":[13.56949,45.86798],"type":"Point"}
}