{
  "type": "Feature",
  "properties": {
    "gn:admin1_code":"20",
    "gn:admin2_code":"BL",
    "gn:admin3_code":"25029.0",
    "gn:asciiname":"Ceresera",
    "gn:country_code":"IT",
    "gn:dem":542,
    "gn:feature_class":"P",
    "gn:feature_code":"PPL",
    "gn:name":"Ceresera",
    "gn:population":28,
    "gn:timezone":"Europe/Rome",
    "iso:country":"IT",
    "wof:name":"Ceresera",
    "wof:placetype":"locality",
    "wof:population":28
},
  "geometry": {"coordinates":[12.22217,46.0927],"type":"Point"}
}