{
  "type": "Feature",
  "properties": {
    "gn:admin1_code":"15",
    "gn:admin2_code":"TP",
    "gn:admin3_code":"81011.0",
    "gn:asciiname":"Di Girolamo",
    "gn:country_code":"IT",
    "gn:dem":120,
    "gn:feature_class":"P",
    "gn:feature_code":"PPL",
    "gn:name":"Di Girolamo",
    "gn:population":18,
    "gn:timezone":"Europe/Rome",
    "iso:country":"IT",
    "wof:name":"Di Girolamo",
    "wof:placetype":"locality",
    "wof:population":18
},
  "geometry": {"coordinates":[12.51795,37.80078],"type":"Point"}
}