{
  "type": "Feature",
  "properties": {
    "gn:admin1_code":"5",
    "gn:admin2_code":"RA",
    "gn:admin3_code":"39010.0",
    "gn:asciiname":"Pieve Cesato",
    "gn:country_code":"IT",
    "gn:dem":16,
    "gn:feature_class":"P",
    "gn:feature_code":"PPL",
    "gn:name":"Pieve Cesato",
    "gn:population":256,
    "gn:timezone":"Europe/Rome",
    "iso:country":"IT",
    "wof:name":"Pieve Cesato",
    "wof:placetype":"locality",
    "wof:population":256
},
  "geometry": {"coordinates":[11.95997,44.33885],"type":"Point"}
}