{
  "type": "Feature",
  "properties": {
    "gn:admin1_code":"3.0",
    "gn:admin2_code":"CS",
    "gn:admin3_code":"78048.0",
    "gn:asciiname":"Cucco-Riviere",
    "gn:country_code":"IT",
    "gn:dem":31,
    "gn:feature_class":"P",
    "gn:feature_code":"PPL",
    "gn:name":"Cucco-Riviere",
    "gn:population":655,
    "gn:timezone":"Europe/Rome",
    "iso:country":"IT",
    "wof:name":"Cucco-Riviere",
    "wof:placetype":"locality",
    "wof:population":655
},
  "geometry": {"coordinates":[15.81562,39.70134],"type":"Point"}
}