{
  "type": "Feature",
  "properties": {
    "gn:admin1_code":"1",
    "gn:admin2_code":"TE",
    "gn:admin3_code":"67045.0",
    "gn:asciiname":"Palozza",
    "gn:country_code":"IT",
    "gn:dem":390,
    "gn:feature_class":"P",
    "gn:feature_code":"PPL",
    "gn:name":"Palozza",
    "gn:population":59,
    "gn:timezone":"Europe/Rome",
    "iso:country":"IT",
    "wof:name":"Palozza",
    "wof:placetype":"locality",
    "wof:population":59
},
  "geometry": {"coordinates":[13.67244,42.55606],"type":"Point"}
}