{
  "type": "Feature",
  "properties": {
    "gn:admin1_code":"15",
    "gn:admin2_code":"ME",
    "gn:admin3_code":"83100.0",
    "gn:asciiname":"San Cono",
    "gn:country_code":"IT",
    "gn:dem":618,
    "gn:feature_class":"P",
    "gn:feature_code":"PPL",
    "gn:name":"San Cono",
    "gn:population":74,
    "gn:timezone":"Europe/Rome",
    "iso:country":"IT",
    "wof:name":"San Cono",
    "wof:placetype":"locality",
    "wof:population":74
},
  "geometry": {"coordinates":[15.08234,38.04949000000001],"type":"Point"}
}