{
  "type": "Feature",
  "properties": {
    "gn:admin1_code":"12",
    "gn:admin2_code":"AL",
    "gn:admin3_code":"6001.0",
    "gn:asciiname":"Regione Abergo",
    "gn:country_code":"IT",
    "gn:dem":252,
    "gn:feature_class":"P",
    "gn:feature_code":"PPL",
    "gn:name":"Regione Abergo",
    "gn:population":15,
    "gn:timezone":"Europe/Rome",
    "iso:country":"IT",
    "wof:name":"Regione Abergo",
    "wof:placetype":"locality",
    "wof:population":15
},
  "geometry": {"coordinates":[8.47045,44.64651],"type":"Point"}
}