{
  "type": "Feature",
  "properties": {
    "iso:country":"IT",
    "wof:name":"Casal Boccone",
    "wof:placetype":"neighbourhood"
},
  "geometry": {"coordinates":[12.55411834056308,41.96140524183625],"type":"Point"}
}