{
  "type": "Feature",
  "properties": {
    "gn:admin1_code":"20.0",
    "gn:admin2_code":"TV",
    "gn:admin3_code":"26055.0",
    "gn:asciiname":"Case Sartori",
    "gn:country_code":"IT",
    "gn:dem":56,
    "gn:feature_class":"P",
    "gn:feature_code":"PPL",
    "gn:name":"Case Sartori",
    "gn:population":32,
    "gn:timezone":"Europe/Rome",
    "iso:country":"IT",
    "wof:name":"Case Sartori",
    "wof:placetype":"locality",
    "wof:population":32
},
  "geometry": {"coordinates":[12.15563,45.72457],"type":"Point"}
}