{
  "type": "Feature",
  "properties": {
    "gn:admin1_code":"17",
    "gn:admin2_code":"TN",
    "gn:admin3_code":"22136.0",
    "gn:asciiname":"Comasine",
    "gn:country_code":"IT",
    "gn:dem":1202,
    "gn:feature_class":"P",
    "gn:feature_code":"PPL",
    "gn:name":"Comasine",
    "gn:population":110,
    "gn:timezone":"Europe/Rome",
    "iso:country":"IT",
    "wof:name":"Comasine",
    "wof:placetype":"locality",
    "wof:population":110
},
  "geometry": {"coordinates":[10.70569,46.3284],"type":"Point"}
}