{
  "type": "Feature",
  "properties": {
    "gn:admin1_code":"5",
    "gn:admin2_code":"PR",
    "gn:admin3_code":"34039.0",
    "gn:asciiname":"Carpaneto",
    "gn:country_code":"IT",
    "gn:dem":590,
    "gn:feature_class":"P",
    "gn:feature_code":"PPL",
    "gn:name":"Carpaneto",
    "gn:population":77,
    "gn:timezone":"Europe/Rome",
    "iso:country":"IT",
    "wof:name":"Carpaneto",
    "wof:placetype":"locality",
    "wof:population":77
},
  "geometry": {"coordinates":[10.21795,44.51567],"type":"Point"}
}