{
  "type": "Feature",
  "properties": {
    "iso:country":"IT",
    "name:ceb_x_preferred":[
        "Colma"
    ],
    "name:fra_x_preferred":[
        "Colma"
    ],
    "name:glg_x_preferred":[
        "Colma"
    ],
    "name:ita_x_preferred":[
        "Colma"
    ],
    "name:pol_x_preferred":[
        "Colma"
    ],
    "name:por_x_preferred":[
        "Colma"
    ],
    "name:srp_x_preferred":[
        "Colma"
    ],
    "name:swe_x_preferred":[
        "Colma"
    ],
    "qs_pg:aaroncc":"IT",
    "qs_pg:name":"Colma",
    "qs_pg:name_adm0":"Italia",
    "qs_pg:name_adm1":"Piemonte",
    "qs_pg:photos":22,
    "qs_pg:photos_1k":4,
    "qs_pg:photos_9k":1,
    "qs_pg:photos_9r":1,
    "qs_pg:photos_all":22,
    "qs_pg:photos_sr":1,
    "qs_pg:pop_sr":0,
    "qs_pg:qs_pg_placetype":"locality",
    "qs_pg:qs_pg_placetype_gp":"Town",
    "qs_pg:woe_adm0":23424853,
    "woe:adm0_id":23424853,
    "woe:name_adm0":"Italia",
    "woe:name_adm1":"Piemonte",
    "woe:placetype":"Town",
    "wof:name":"Colma",
    "wof:placetype":"locality"
},
  "geometry": {"coordinates":[8.423575,45.0923445],"type":"Point"}
}