{
  "type": "Feature",
  "properties": {
    "gn:gn_country":"IT",
    "gn:gn_fcode":"PPLA3",
    "gn:gn_pop":1054,
    "gn:population":693,
    "iso:country":"IT",
    "name:arm_x_preferred":[
        "\u0544\u0561\u0575\u0580\u0561\u0563\u0578"
    ],
    "name:baq_x_preferred":[
        "Mairago"
    ],
    "name:bel_x_preferred":[
        "\u041c\u0430\u0439\u0440\u0430\u0433\u0430"
    ],
    "name:bul_x_preferred":[
        "\u041c\u0430\u0439\u0440\u0430\u0433\u043e"
    ],
    "name:cat_x_preferred":[
        "Mairago"
    ],
    "name:chi_x_preferred":[
        "\u9a6c\u4f0a\u62c9\u6208"
    ],
    "name:dut_x_preferred":[
        "Mairago"
    ],
    "name:eml_x_preferred":[
        "Mair\u00e0gh"
    ],
    "name:eng_x_preferred":[
        "Mairago"
    ],
    "name:epo_x_preferred":[
        "Mairago"
    ],
    "name:fre_x_preferred":[
        "Mairago"
    ],
    "name:ger_x_preferred":[
        "Mairago"
    ],
    "name:hun_x_preferred":[
        "Mairago"
    ],
    "name:ind_x_preferred":[
        "Mairago"
    ],
    "name:ita_x_preferred":[
        "Mairago"
    ],
    "name:jpn_x_preferred":[
        "\u30de\u30a4\u30e9\u30fc\u30b4"
    ],
    "name:kaz_x_preferred":[
        "\u041c\u0430\u0439\u0440\u0430\u0433\u043e"
    ],
    "name:lat_x_preferred":[
        "Mairagum"
    ],
    "name:lmo_x_preferred":[
        "Mair\u00e0gh"
    ],
    "name:may_x_preferred":[
        "Mairago"
    ],
    "name:nan_x_preferred":[
        "Mairago"
    ],
    "name:nap_x_preferred":[
        "Mairago"
    ],
    "name:oci_x_preferred":[
        "Mairago"
    ],
    "name:per_x_preferred":[
        "\u0645\u0627\u06cc\u0631\u0627\u06af\u0648"
    ],
    "name:pms_x_preferred":[
        "Mairago"
    ],
    "name:pol_x_preferred":[
        "Mairago"
    ],
    "name:por_x_preferred":[
        "Mairago"
    ],
    "name:rum_x_preferred":[
        "Mairago"
    ],
    "name:rus_x_preferred":[
        "\u041c\u0430\u0439\u0440\u0430\u0433\u043e"
    ],
    "name:scn_x_preferred":[
        "Mairago"
    ],
    "name:spa_x_preferred":[
        "Mairago"
    ],
    "name:srp_x_preferred":[
        "Mairago"
    ],
    "name:tgl_x_preferred":[
        "Mairago"
    ],
    "name:ukr_x_preferred":[
        "\u041c\u0430\u0457\u0440\u0430\u0433\u043e"
    ],
    "name:uzb_x_preferred":[
        "Mairago"
    ],
    "name:vie_x_preferred":[
        "Mairago"
    ],
    "name:vol_x_preferred":[
        "Mairago"
    ],
    "name:war_x_preferred":[
        "Mairago"
    ],
    "qs_pg:aaroncc":"IT",
    "qs_pg:gn_country":"IT",
    "qs_pg:gn_fcode":"PPLA3",
    "qs_pg:gn_pop":1054,
    "qs_pg:name":"Mairago",
    "qs_pg:name_adm0":"Italia",
    "qs_pg:name_adm1":"Lombardia",
    "qs_pg:photos":21,
    "qs_pg:photos_1k":4,
    "qs_pg:photos_9k":1,
    "qs_pg:photos_9r":1,
    "qs_pg:photos_all":21,
    "qs_pg:photos_sr":1,
    "qs_pg:pop_sr":3,
    "qs_pg:qs_pg_placetype":"locality",
    "qs_pg:qs_pg_placetype_gp":"Town",
    "qs_pg:woe_adm0":23424853,
    "woe:adm0_id":23424853,
    "woe:name_adm0":"Italia",
    "woe:name_adm1":"Lombardia",
    "woe:placetype":"Town",
    "wof:name":"Mairago",
    "wof:placetype":"locality",
    "wof:population":693
},
  "geometry": {"coordinates":[9.57836,45.25177],"type":"Point"}
}