{
  "type": "Feature",
  "properties": {
    "gn:admin1_code":"15",
    "gn:admin2_code":"CT",
    "gn:admin3_code":"87052.0",
    "gn:asciiname":"Nizzetti I",
    "gn:country_code":"IT",
    "gn:dem":253,
    "gn:feature_class":"P",
    "gn:feature_code":"PPL",
    "gn:name":"Nizzetti I",
    "gn:population":230,
    "gn:timezone":"Europe/Rome",
    "iso:country":"IT",
    "wof:name":"Nizzetti I",
    "wof:placetype":"locality",
    "wof:population":230
},
  "geometry": {"coordinates":[15.13238,37.56468],"type":"Point"}
}