{
  "type": "Feature",
  "properties": {
    "gn:gn_country":"IT",
    "gn:gn_fcode":"PPL",
    "gn:gn_pop":1038,
    "gn:population":1038,
    "iso:country":"IT",
    "qs_pg:aaroncc":"IT",
    "qs_pg:gn_country":"IT",
    "qs_pg:gn_fcode":"PPL",
    "qs_pg:gn_pop":1038,
    "qs_pg:name":"Miola di Pin\u00e8",
    "qs_pg:photos_9r":0,
    "qs_pg:photos_sr":0,
    "qs_pg:pop_sr":3,
    "qs_pg:qs_pg_placetype":"locality",
    "wof:name":"Miola di Pin\u00e8",
    "wof:placetype":"locality",
    "wof:population":1038
},
  "geometry": {"coordinates":[11.2485,46.12668],"type":"Point"}
}