{
  "type": "Feature",
  "properties": {
    "gn:gn_country":"IT",
    "gn:gn_fcode":"PPLA3",
    "gn:gn_pop":411,
    "gn:population":411,
    "iso:country":"IT",
    "name:arm_x_preferred":[
        "\u054d\u0574\u0565\u0580\u056b\u056c\u0578"
    ],
    "name:baq_x_preferred":[
        "Smerillo"
    ],
    "name:bel_x_preferred":[
        "\u0417\u043c\u0435\u0440\u044b\u043b\u0430"
    ],
    "name:bul_x_preferred":[
        "\u0421\u043c\u0435\u0440\u0438\u043b\u043e"
    ],
    "name:cat_x_preferred":[
        "Smerillo"
    ],
    "name:chi_x_preferred":[
        "\u65af\u6885\u91cc\u6d1b"
    ],
    "name:dut_x_preferred":[
        "Smerillo"
    ],
    "name:eng_x_preferred":[
        "Smerillo"
    ],
    "name:epo_x_preferred":[
        "Smerillo"
    ],
    "name:fre_x_preferred":[
        "Smerillo"
    ],
    "name:ger_x_preferred":[
        "Smerillo"
    ],
    "name:hun_x_preferred":[
        "Smerillo"
    ],
    "name:ina_x_preferred":[
        "Smerillo"
    ],
    "name:ita_x_preferred":[
        "Smerillo"
    ],
    "name:jpn_x_preferred":[
        "\u30ba\u30e1\u30ea\u30c3\u30ed"
    ],
    "name:kaz_x_preferred":[
        "\u0417\u043c\u0435\u0440\u0438\u043b\u043b\u043e"
    ],
    "name:lat_x_preferred":[
        "Smerillum"
    ],
    "name:lmo_x_preferred":[
        "Smerillo"
    ],
    "name:may_x_preferred":[
        "Smerillo"
    ],
    "name:nan_x_preferred":[
        "Smerillo"
    ],
    "name:nap_x_preferred":[
        "Smerillo"
    ],
    "name:oci_x_preferred":[
        "Smerillo"
    ],
    "name:per_x_preferred":[
        "\u0633\u0645\u0631\u06cc\u0644\u0648"
    ],
    "name:pms_x_preferred":[
        "Smerillo"
    ],
    "name:pol_x_preferred":[
        "Smerillo"
    ],
    "name:por_x_preferred":[
        "Smerillo"
    ],
    "name:rum_x_preferred":[
        "Smerillo"
    ],
    "name:rus_x_preferred":[
        "\u0417\u043c\u0435\u0440\u0438\u043b\u043b\u043e"
    ],
    "name:spa_x_preferred":[
        "Smerillo"
    ],
    "name:srp_x_preferred":[
        "Smerillo"
    ],
    "name:tgl_x_preferred":[
        "Smerillo"
    ],
    "name:ukr_x_preferred":[
        "\u0417\u043c\u0435\u0440\u0438\u043b\u043b\u043e"
    ],
    "name:uzb_x_preferred":[
        "Smerillo"
    ],
    "name:vie_x_preferred":[
        "Smerillo"
    ],
    "name:vol_x_preferred":[
        "Smerillo"
    ],
    "name:war_x_preferred":[
        "Smerillo"
    ],
    "qs_pg:aaroncc":"IT",
    "qs_pg:gn_country":"IT",
    "qs_pg:gn_fcode":"PPLA3",
    "qs_pg:gn_pop":411,
    "qs_pg:name":"Smerillo",
    "qs_pg:name_adm0":"Italia",
    "qs_pg:name_adm1":"Marche",
    "qs_pg:photos":278,
    "qs_pg:photos_1k":56,
    "qs_pg:photos_9k":1,
    "qs_pg:photos_9r":4,
    "qs_pg:photos_all":278,
    "qs_pg:photos_sr":5,
    "qs_pg:pop_sr":2,
    "qs_pg:qs_pg_placetype":"locality",
    "qs_pg:qs_pg_placetype_gp":"Town",
    "qs_pg:woe_adm0":23424853,
    "woe:adm0_id":23424853,
    "woe:name_adm0":"Italia",
    "woe:name_adm1":"Marche",
    "woe:placetype":"Town",
    "wof:name":"Smerillo",
    "wof:placetype":"locality",
    "wof:population":411
},
  "geometry": {"coordinates":[13.44498,43.00515],"type":"Point"}
}