{
  "type": "Feature",
  "properties": {
    "gn:admin1_code":"7.0",
    "gn:admin2_code":"RI",
    "gn:admin3_code":"57049.0",
    "gn:asciiname":"Ospanesco",
    "gn:country_code":"IT",
    "gn:dem":814,
    "gn:elevation":"827.0",
    "gn:feature_class":"P",
    "gn:feature_code":"PPL",
    "gn:name":"Ospanesco",
    "gn:population":13,
    "gn:timezone":"Europe/Rome",
    "iso:country":"IT",
    "wof:name":"Ospanesco",
    "wof:placetype":"locality",
    "wof:population":13
},
  "geometry": {"coordinates":[13.10271,42.22344],"type":"Point"}
}