{
  "type": "Feature",
  "properties": {
    "gn:admin1_code":"9",
    "gn:admin2_code":"BG",
    "gn:admin3_code":"16023.0",
    "gn:asciiname":"Ceresola",
    "gn:country_code":"IT",
    "gn:dem":530,
    "gn:feature_class":"P",
    "gn:feature_code":"PPL",
    "gn:name":"Ceresola",
    "gn:population":36,
    "gn:timezone":"Europe/Rome",
    "iso:country":"IT",
    "wof:name":"Ceresola",
    "wof:placetype":"locality",
    "wof:population":36
},
  "geometry": {"coordinates":[9.57253,45.79763],"type":"Point"}
}