{
  "type": "Feature",
  "properties": {
    "gn:admin1_code":"4",
    "gn:admin2_code":"SA",
    "gn:admin3_code":"65116.0",
    "gn:asciiname":"Case de Rosa",
    "gn:country_code":"IT",
    "gn:dem":126,
    "gn:feature_class":"P",
    "gn:feature_code":"PPL",
    "gn:name":"Case de Rosa",
    "gn:population":224,
    "gn:timezone":"Europe/Rome",
    "iso:country":"IT",
    "wof:name":"Case de Rosa",
    "wof:placetype":"locality",
    "wof:population":224
},
  "geometry": {"coordinates":[14.82335,40.67654],"type":"Point"}
}