{
  "type": "Feature",
  "properties": {
    "gn:admin1_code":"3.0",
    "gn:admin2_code":"CZ",
    "gn:admin3_code":"79138.0",
    "gn:asciiname":"Cupa Sottana",
    "gn:country_code":"IT",
    "gn:dem":722,
    "gn:feature_class":"P",
    "gn:feature_code":"PPL",
    "gn:name":"Cupa Sottana",
    "gn:population":14,
    "gn:timezone":"Europe/Rome",
    "iso:country":"IT",
    "wof:name":"Cupa Sottana",
    "wof:placetype":"locality",
    "wof:population":14
},
  "geometry": {"coordinates":[16.41761,39.04044],"type":"Point"}
}