{
  "type": "Feature",
  "properties": {
    "gn:admin1_code":"6.0",
    "gn:admin2_code":"GO",
    "gn:admin3_code":"31011.0",
    "gn:asciiname":"Ponte sul Versa",
    "gn:country_code":"IT",
    "gn:dem":32,
    "gn:feature_class":"P",
    "gn:feature_code":"PPL",
    "gn:name":"Ponte sul Versa",
    "gn:population":9,
    "gn:timezone":"Europe/Rome",
    "iso:country":"IT",
    "wof:name":"Ponte sul Versa",
    "wof:placetype":"locality",
    "wof:population":9
},
  "geometry": {"coordinates":[13.45442,45.92112],"type":"Point"}
}