{
  "type": "Feature",
  "properties": {
    "gn:admin1_code":"12",
    "gn:admin2_code":"TO",
    "gn:admin3_code":"1184.0",
    "gn:asciiname":"Brandoneugna",
    "gn:country_code":"IT",
    "gn:dem":686,
    "gn:feature_class":"P",
    "gn:feature_code":"PPL",
    "gn:name":"Brandoneugna",
    "gn:population":66,
    "gn:timezone":"Europe/Rome",
    "iso:country":"IT",
    "wof:name":"Brandoneugna",
    "wof:placetype":"locality",
    "wof:population":66
},
  "geometry": {"coordinates":[7.17835,44.972],"type":"Point"}
}