{
  "type": "Feature",
  "properties": {
    "gn:admin1_code":"5",
    "gn:admin2_code":"RE",
    "gn:admin3_code":"35016.0",
    "gn:asciiname":"Roncadelli",
    "gn:country_code":"IT",
    "gn:dem":635,
    "gn:feature_class":"P",
    "gn:feature_code":"PPL",
    "gn:name":"Roncadelli",
    "gn:population":22,
    "gn:timezone":"Europe/Rome",
    "iso:country":"IT",
    "wof:name":"Roncadelli",
    "wof:placetype":"locality",
    "wof:population":22
},
  "geometry": {"coordinates":[10.47378,44.44906],"type":"Point"}
}