{
  "type": "Feature",
  "properties": {
    "gn:admin1_code":"18",
    "gn:admin2_code":"PG",
    "gn:admin3_code":"54039.0",
    "gn:asciiname":"Podere Castellaccio",
    "gn:country_code":"IT",
    "gn:dem":335,
    "gn:feature_class":"P",
    "gn:feature_code":"PPL",
    "gn:name":"Podere Castellaccio",
    "gn:population":24,
    "gn:timezone":"Europe/Rome",
    "iso:country":"IT",
    "wof:name":"Podere Castellaccio",
    "wof:placetype":"locality",
    "wof:population":24
},
  "geometry": {"coordinates":[12.3457,43.15735],"type":"Point"}
}