{
  "type": "Feature",
  "properties": {
    "gn:admin1_code":"4",
    "gn:admin2_code":"BN",
    "gn:admin3_code":"62044.0",
    "gn:asciiname":"Masseria Giordano",
    "gn:country_code":"IT",
    "gn:dem":447,
    "gn:feature_class":"P",
    "gn:feature_code":"PPL",
    "gn:name":"Masseria Giordano",
    "gn:population":34,
    "gn:timezone":"Europe/Rome",
    "iso:country":"IT",
    "wof:name":"Masseria Giordano",
    "wof:placetype":"locality",
    "wof:population":34
},
  "geometry": {"coordinates":[14.74939,41.32476],"type":"Point"}
}