{
  "type": "Feature",
  "properties": {
    "gn:admin1_code":"16",
    "gn:admin2_code":"FI",
    "gn:admin3_code":"48030.0",
    "gn:asciiname":"Monte Albino",
    "gn:country_code":"IT",
    "gn:dem":269,
    "gn:feature_class":"P",
    "gn:feature_code":"PPL",
    "gn:name":"Monte Albino",
    "gn:population":33,
    "gn:timezone":"Europe/Rome",
    "iso:country":"IT",
    "wof:name":"Monte Albino",
    "wof:placetype":"locality",
    "wof:population":33
},
  "geometry": {"coordinates":[11.09084,43.6099],"type":"Point"}
}