{
  "type": "Feature",
  "properties": {
    "gn:admin1_code":"15",
    "gn:admin2_code":"CT",
    "gn:admin3_code":"87039.0",
    "gn:asciiname":"Santa Margherita",
    "gn:country_code":"IT",
    "gn:dem":145,
    "gn:feature_class":"P",
    "gn:feature_code":"PPL",
    "gn:name":"Santa Margherita",
    "gn:population":59,
    "gn:timezone":"Europe/Rome",
    "iso:country":"IT",
    "wof:name":"Santa Margherita",
    "wof:placetype":"locality",
    "wof:population":59
},
  "geometry": {"coordinates":[15.18023,37.69671],"type":"Point"}
}