{
  "type": "Feature",
  "properties": {
    "gn:admin1_code":"12.0",
    "gn:admin2_code":"VC",
    "gn:admin3_code":"2114.0",
    "gn:asciiname":"Casa Verno",
    "gn:country_code":"IT",
    "gn:dem":1389,
    "gn:feature_class":"P",
    "gn:feature_code":"PPLL",
    "gn:name":"Casa Verno",
    "gn:population":4,
    "gn:timezone":"Europe/Rome",
    "iso:country":"IT",
    "wof:name":"Casa Verno",
    "wof:placetype":"locality",
    "wof:population":4
},
  "geometry": {"coordinates":[7.93354,45.81673],"type":"Point"}
}