{
  "type": "Feature",
  "properties": {
    "gn:admin1_code":"3.0",
    "gn:admin2_code":"CS",
    "gn:admin3_code":"78114.0",
    "gn:asciiname":"Sant'Agata",
    "gn:country_code":"IT",
    "gn:dem":43,
    "gn:elevation":"53.0",
    "gn:feature_class":"P",
    "gn:feature_code":"PPL",
    "gn:name":"Sant'Agata",
    "gn:population":56,
    "gn:timezone":"Europe/Rome",
    "iso:country":"IT",
    "name:ceb_x_preferred":[
        "Sant'Agata"
    ],
    "name:deu_x_preferred":[
        "Sant\u2019Agata"
    ],
    "name:fra_x_preferred":[
        "Sant'Agata"
    ],
    "name:ita_x_preferred":[
        "Sant'Agata"
    ],
    "name:jpn_x_preferred":[
        "\u30b5\u30f3\u30bf\u30fc\u30ac\u30bf"
    ],
    "name:por_x_preferred":[
        "Sant'Agata"
    ],
    "name:scn_x_preferred":[
        "Sant'\u00c0gata"
    ],
    "name:srp_x_preferred":[
        "Sant'Agata"
    ],
    "name:swe_x_preferred":[
        "Sant'Agata"
    ],
    "wof:name":"Sant'Agata",
    "wof:placetype":"locality",
    "wof:population":56
},
  "geometry": {"coordinates":[16.38486,39.64159],"type":"Point"}
}