{
  "type": "Feature",
  "properties": {
    "gn:admin1_code":"3.0",
    "gn:admin2_code":"CS",
    "gn:admin3_code":"78114.0",
    "gn:asciiname":"Sant'Agata",
    "gn:country_code":"IT",
    "gn:dem":43,
    "gn:elevation":"53.0",
    "gn:feature_class":"P",
    "gn:feature_code":"PPL",
    "gn:name":"Sant'Agata",
    "gn:population":56,
    "gn:timezone":"Europe/Rome",
    "iso:country":"IT",
    "wof:name":"Sant'Agata",
    "wof:placetype":"locality",
    "wof:population":56
},
  "geometry": {"coordinates":[16.38486,39.64159],"type":"Point"}
}