{
  "type": "Feature",
  "properties": {
    "gn:admin1_code":"9.0",
    "gn:admin2_code":"BS",
    "gn:admin3_code":"17148.0",
    "gn:asciiname":"Case di Viso",
    "gn:country_code":"IT",
    "gn:dem":1760,
    "gn:elevation":"1754.0",
    "gn:feature_class":"P",
    "gn:feature_code":"PPLL",
    "gn:name":"Case di Viso",
    "gn:population":0,
    "gn:timezone":"Europe/Rome",
    "iso:country":"IT",
    "wof:name":"Case di Viso",
    "wof:placetype":"locality"
},
  "geometry": {"coordinates":[10.54992,46.29954],"type":"Point"}
}