{
  "type": "Feature",
  "properties": {
    "gn:admin1_code":"12",
    "gn:admin2_code":"CN",
    "gn:admin3_code":"4064.0",
    "gn:asciiname":"Cascina Chiabotassa",
    "gn:country_code":"IT",
    "gn:dem":518,
    "gn:feature_class":"P",
    "gn:feature_code":"PPL",
    "gn:name":"Cascina Chiabotassa",
    "gn:population":14,
    "gn:timezone":"Europe/Rome",
    "iso:country":"IT",
    "wof:name":"Cascina Chiabotassa",
    "wof:placetype":"locality",
    "wof:population":14
},
  "geometry": {"coordinates":[7.49201,44.4277],"type":"Point"}
}