{
  "type": "Feature",
  "properties": {
    "gn:admin1_code":"9",
    "gn:admin2_code":"MN",
    "gn:admin3_code":"20037.0",
    "gn:asciiname":"Casate",
    "gn:country_code":"IT",
    "gn:dem":20,
    "gn:feature_class":"P",
    "gn:feature_code":"PPL",
    "gn:name":"Casate",
    "gn:population":31,
    "gn:timezone":"Europe/Rome",
    "iso:country":"IT",
    "wof:name":"Casate",
    "wof:placetype":"locality",
    "wof:population":31
},
  "geometry": {"coordinates":[10.71182,45.04008],"type":"Point"}
}