{
  "type": "Feature",
  "properties": {
    "gn:admin1_code":"4",
    "gn:admin2_code":"AV",
    "gn:admin3_code":"64044.0",
    "gn:asciiname":"Santa Maria del Piano",
    "gn:country_code":"IT",
    "gn:dem":545,
    "gn:feature_class":"P",
    "gn:feature_code":"PPL",
    "gn:name":"Santa Maria del Piano",
    "gn:population":90,
    "gn:timezone":"Europe/Rome",
    "iso:country":"IT",
    "wof:name":"Santa Maria del Piano",
    "wof:placetype":"locality",
    "wof:population":90
},
  "geometry": {"coordinates":[15.18848,40.86807],"type":"Point"}
}