{
  "type": "Feature",
  "properties": {
    "gn:admin1_code":"16",
    "gn:admin2_code":"SI",
    "gn:admin3_code":"52012.0",
    "gn:asciiname":"Pian dell'Olmino",
    "gn:country_code":"IT",
    "gn:dem":182,
    "gn:feature_class":"P",
    "gn:feature_code":"PPL",
    "gn:name":"Pian dell'Olmino",
    "gn:population":17,
    "gn:timezone":"Europe/Rome",
    "iso:country":"IT",
    "wof:name":"Pian dell'Olmino",
    "wof:placetype":"locality",
    "wof:population":17
},
  "geometry": {"coordinates":[11.13123,43.38058],"type":"Point"}
}