{
  "type": "Feature",
  "properties": {
    "gn:admin1_code":"20.0",
    "gn:admin2_code":"PD",
    "gn:admin3_code":"28073.0",
    "gn:asciiname":"Casa Carta",
    "gn:country_code":"IT",
    "gn:dem":13,
    "gn:feature_class":"P",
    "gn:feature_code":"PPL",
    "gn:name":"Casa Carta",
    "gn:population":0,
    "gn:timezone":"Europe/Rome",
    "iso:country":"IT",
    "wof:name":"Casa Carta",
    "wof:placetype":"locality"
},
  "geometry": {"coordinates":[11.76667,45.41667],"type":"Point"}
}