{
  "type": "Feature",
  "properties": {
    "gn:admin1_code":"4",
    "gn:admin2_code":"SA",
    "gn:admin3_code":"65089.0",
    "gn:asciiname":"Monte Pruno",
    "gn:country_code":"IT",
    "gn:dem":301,
    "gn:feature_class":"P",
    "gn:feature_code":"PPL",
    "gn:name":"Monte Pruno",
    "gn:population":69,
    "gn:timezone":"Europe/Rome",
    "iso:country":"IT",
    "name:hun_x_preferred":[
        "Pruno"
    ],
    "name:ita_x_preferred":[
        "Monte Pruno"
    ],
    "wof:name":"Monte Pruno",
    "wof:placetype":"locality",
    "wof:population":69
},
  "geometry": {"coordinates":[15.26714,40.67232],"type":"Point"}
}