{
  "type": "Feature",
  "properties": {
    "gn:admin1_code":"9.0",
    "gn:admin2_code":"MN",
    "gn:admin3_code":"20071.0",
    "gn:asciiname":"San Nicolo Po",
    "gn:country_code":"IT",
    "gn:dem":20,
    "gn:feature_class":"P",
    "gn:feature_code":"PPL",
    "gn:name":"San Nicol\u00f2 Po",
    "gn:population":0,
    "gn:timezone":"Europe/Rome",
    "iso:country":"IT",
    "wof:name":"San Nicolo Po",
    "wof:placetype":"locality"
},
  "geometry": {"coordinates":[10.83333,45.05],"type":"Point"}
}