{
  "type": "Feature",
  "properties": {
    "gn:admin1_code":"10",
    "gn:admin2_code":"MC",
    "gn:admin3_code":"43017.0",
    "gn:asciiname":"Campobonomo",
    "gn:country_code":"IT",
    "gn:dem":890,
    "gn:feature_class":"P",
    "gn:feature_code":"PPLL",
    "gn:name":"Campobonomo",
    "gn:population":8,
    "gn:timezone":"Europe/Rome",
    "iso:country":"IT",
    "wof:name":"Campobonomo",
    "wof:placetype":"locality",
    "wof:population":8
},
  "geometry": {"coordinates":[13.12459,43.04083],"type":"Point"}
}