{
  "type": "Feature",
  "properties": {
    "gn:admin1_code":"9",
    "gn:admin2_code":"BG",
    "gn:admin3_code":"16006.0",
    "gn:asciiname":"Longoni Nord",
    "gn:country_code":"IT",
    "gn:dem":317,
    "gn:feature_class":"P",
    "gn:feature_code":"PPL",
    "gn:name":"Longoni Nord",
    "gn:population":19,
    "gn:timezone":"Europe/Rome",
    "iso:country":"IT",
    "wof:name":"Longoni Nord",
    "wof:placetype":"locality",
    "wof:population":19
},
  "geometry": {"coordinates":[9.55945,45.74488],"type":"Point"}
}