{
  "type": "Feature",
  "properties": {
    "gn:admin1_code":"8.0",
    "gn:admin2_code":"IM",
    "gn:admin3_code":"8047.0",
    "gn:asciiname":"Praelo",
    "gn:country_code":"IT",
    "gn:dem":268,
    "gn:elevation":"245.0",
    "gn:feature_class":"P",
    "gn:feature_code":"PPL",
    "gn:name":"Praelo",
    "gn:population":17,
    "gn:timezone":"Europe/Rome",
    "iso:country":"IT",
    "wof:name":"Praelo",
    "wof:placetype":"locality",
    "wof:population":17
},
  "geometry": {"coordinates":[7.9392,43.92761],"type":"Point"}
}