{
  "type": "Feature",
  "properties": {
    "gn:admin1_code":"15",
    "gn:admin2_code":"ME",
    "gn:admin3_code":"83091.0",
    "gn:asciiname":"Contrada Felicita",
    "gn:country_code":"IT",
    "gn:dem":591,
    "gn:feature_class":"P",
    "gn:feature_code":"PPL",
    "gn:name":"Contrada Felicita",
    "gn:population":15,
    "gn:timezone":"Europe/Rome",
    "iso:country":"IT",
    "wof:name":"Contrada Felicita",
    "wof:placetype":"locality",
    "wof:population":15
},
  "geometry": {"coordinates":[14.36601,37.97999],"type":"Point"}
}