{
  "type": "Feature",
  "properties": {
    "gn:admin1_code":"12",
    "gn:admin2_code":"TO",
    "gn:admin3_code":"1130.0",
    "gn:asciiname":"Canova",
    "gn:country_code":"IT",
    "gn:dem":278,
    "gn:feature_class":"P",
    "gn:feature_code":"PPL",
    "gn:name":"Canova",
    "gn:population":36,
    "gn:timezone":"Europe/Rome",
    "iso:country":"IT",
    "wof:name":"Canova",
    "wof:placetype":"locality",
    "wof:population":36
},
  "geometry": {"coordinates":[7.71297,45.21323],"type":"Point"}
}