{
  "type": "Feature",
  "properties": {
    "gn:admin1_code":"5",
    "gn:admin2_code":"BO",
    "gn:admin3_code":"37036.0",
    "gn:asciiname":"Villa Aria",
    "gn:country_code":"IT",
    "gn:dem":175,
    "gn:feature_class":"P",
    "gn:feature_code":"PPL",
    "gn:name":"Villa Aria",
    "gn:population":12,
    "gn:timezone":"Europe/Rome",
    "iso:country":"IT",
    "wof:name":"Villa Aria",
    "wof:placetype":"locality",
    "wof:population":12
},
  "geometry": {"coordinates":[11.20023,44.33847],"type":"Point"}
}