{
  "type": "Feature",
  "properties": {
    "gn:admin1_code":"5",
    "gn:admin2_code":"PR",
    "gn:admin3_code":"34002.0",
    "gn:asciiname":"Berlini",
    "gn:country_code":"IT",
    "gn:dem":675,
    "gn:feature_class":"P",
    "gn:feature_code":"PPL",
    "gn:name":"Berlini",
    "gn:population":14,
    "gn:timezone":"Europe/Rome",
    "iso:country":"IT",
    "wof:name":"Berlini",
    "wof:placetype":"locality",
    "wof:population":14
},
  "geometry": {"coordinates":[9.73596,44.65496],"type":"Point"}
}