{
  "type": "Feature",
  "properties": {
    "gn:admin1_code":"3.0",
    "gn:admin2_code":"RC",
    "gn:admin3_code":"80017.0",
    "gn:asciiname":"Torre Ellera",
    "gn:country_code":"IT",
    "gn:dem":18,
    "gn:feature_class":"P",
    "gn:feature_code":"PPL",
    "gn:name":"Torre Ellera",
    "gn:population":46,
    "gn:timezone":"Europe/Rome",
    "iso:country":"IT",
    "wof:name":"Torre Ellera",
    "wof:placetype":"locality",
    "wof:population":46
},
  "geometry": {"coordinates":[16.55848,38.42005],"type":"Point"}
}