{
  "type": "Feature",
  "properties": {
    "gn:admin1_code":"4",
    "gn:admin2_code":"SA",
    "gn:admin3_code":"65135.0",
    "gn:asciiname":"Masseria de Crescenzi",
    "gn:country_code":"IT",
    "gn:dem":62,
    "gn:feature_class":"P",
    "gn:feature_code":"PPL",
    "gn:name":"Masseria de Crescenzi",
    "gn:population":124,
    "gn:timezone":"Europe/Rome",
    "iso:country":"IT",
    "wof:name":"Masseria de Crescenzi",
    "wof:placetype":"locality",
    "wof:population":124
},
  "geometry": {"coordinates":[14.64481,40.80344],"type":"Point"}
}