{
  "type": "Feature",
  "properties": {
    "gn:admin1_code":"20.0",
    "gn:admin2_code":"VI",
    "gn:admin3_code":"24009.0",
    "gn:asciiname":"Gianesoni-Cotti di Sasso",
    "gn:country_code":"IT",
    "gn:dem":1055,
    "gn:feature_class":"P",
    "gn:feature_code":"PPL",
    "gn:name":"Gianesoni-Cotti di Sasso",
    "gn:population":91,
    "gn:timezone":"Europe/Rome",
    "iso:country":"IT",
    "wof:name":"Gianesoni-Cotti di Sasso",
    "wof:placetype":"locality",
    "wof:population":91
},
  "geometry": {"coordinates":[11.60748,45.86579],"type":"Point"}
}