{
  "type": "Feature",
  "properties": {
    "gn:admin1_code":"12",
    "gn:admin2_code":"CN",
    "gn:admin3_code":"4078.0",
    "gn:asciiname":"Segheria Torrette",
    "gn:country_code":"IT",
    "gn:dem":463,
    "gn:feature_class":"P",
    "gn:feature_code":"PPL",
    "gn:name":"Segheria Torrette",
    "gn:population":22,
    "gn:timezone":"Europe/Rome",
    "iso:country":"IT",
    "wof:name":"Segheria Torrette",
    "wof:placetype":"locality",
    "wof:population":22
},
  "geometry": {"coordinates":[7.53961,44.47254],"type":"Point"}
}