{
  "type": "Feature",
  "properties": {
    "gn:admin1_code":"12",
    "gn:admin2_code":"NO",
    "gn:admin3_code":"3149.0",
    "gn:asciiname":"San Martino",
    "gn:country_code":"IT",
    "gn:dem":132,
    "gn:feature_class":"P",
    "gn:feature_code":"PPL",
    "gn:name":"San Martino",
    "gn:population":169,
    "gn:timezone":"Europe/Rome",
    "iso:country":"IT",
    "wof:name":"San Martino",
    "wof:placetype":"locality",
    "wof:population":169
},
  "geometry": {"coordinates":[8.78712,45.43854],"type":"Point"}
}