{
  "type": "Feature",
  "properties": {
    "gn:admin1_code":"9",
    "gn:admin2_code":"BG",
    "gn:admin3_code":"16077.0",
    "gn:asciiname":"Frere",
    "gn:country_code":"IT",
    "gn:dem":570,
    "gn:feature_class":"P",
    "gn:feature_code":"PPL",
    "gn:name":"Frere",
    "gn:population":65,
    "gn:timezone":"Europe/Rome",
    "iso:country":"IT",
    "wof:name":"Frere",
    "wof:placetype":"locality",
    "wof:population":65
},
  "geometry": {"coordinates":[9.94766,45.87892],"type":"Point"}
}