{
  "type": "Feature",
  "properties": {
    "gn:admin1_code":"8",
    "gn:admin2_code":"GE",
    "gn:admin3_code":"10020.0",
    "gn:asciiname":"Crosi",
    "gn:country_code":"IT",
    "gn:dem":752,
    "gn:feature_class":"P",
    "gn:feature_code":"PPL",
    "gn:name":"Crosi",
    "gn:population":15,
    "gn:timezone":"Europe/Rome",
    "iso:country":"IT",
    "wof:name":"Crosi",
    "wof:placetype":"locality",
    "wof:population":15
},
  "geometry": {"coordinates":[9.03685,44.57627],"type":"Point"}
}