{
  "type": "Feature",
  "properties": {
    "gn:admin1_code":"9",
    "gn:admin2_code":"BG",
    "gn:admin3_code":"16092.0",
    "gn:asciiname":"Ca' Cadene",
    "gn:country_code":"IT",
    "gn:dem":887,
    "gn:feature_class":"P",
    "gn:feature_code":"PPL",
    "gn:name":"Ca' Cadene",
    "gn:population":46,
    "gn:timezone":"Europe/Rome",
    "iso:country":"IT",
    "wof:name":"Ca' Cadene",
    "wof:placetype":"locality",
    "wof:population":46
},
  "geometry": {"coordinates":[9.70016,45.87524000000001],"type":"Point"}
}