{
  "type": "Feature",
  "properties": {
    "gn:admin1_code":"20",
    "gn:admin2_code":"PD",
    "gn:admin3_code":"28017.0",
    "gn:asciiname":"Case Zampieri",
    "gn:country_code":"IT",
    "gn:dem":11,
    "gn:feature_class":"P",
    "gn:feature_code":"PPL",
    "gn:name":"Case Zampieri",
    "gn:population":74,
    "gn:timezone":"Europe/Rome",
    "iso:country":"IT",
    "wof:name":"Case Zampieri",
    "wof:placetype":"locality",
    "wof:population":74
},
  "geometry": {"coordinates":[11.91312,45.49052],"type":"Point"}
}