{
  "type": "Feature",
  "properties": {
    "gn:admin1_code":"4",
    "gn:admin2_code":"AV",
    "gn:admin3_code":"64077.0",
    "gn:asciiname":"Bosagro",
    "gn:country_code":"IT",
    "gn:dem":197,
    "gn:feature_class":"P",
    "gn:feature_code":"PPL",
    "gn:name":"Bosagro",
    "gn:population":311,
    "gn:timezone":"Europe/Rome",
    "iso:country":"IT",
    "wof:name":"Bosagro",
    "wof:placetype":"locality",
    "wof:population":311
},
  "geometry": {"coordinates":[14.63111,40.87114],"type":"Point"}
}