{
  "type": "Feature",
  "properties": {
    "gn:admin1_code":"6",
    "gn:admin2_code":"UD",
    "gn:admin3_code":"30086.0",
    "gn:asciiname":"Coceanzi",
    "gn:country_code":"IT",
    "gn:dem":549,
    "gn:feature_class":"P",
    "gn:feature_code":"PPL",
    "gn:name":"Coceanzi",
    "gn:population":30,
    "gn:timezone":"Europe/Rome",
    "iso:country":"IT",
    "wof:name":"Coceanzi",
    "wof:placetype":"locality",
    "wof:population":30
},
  "geometry": {"coordinates":[13.46219,46.16618],"type":"Point"}
}