{
  "type": "Feature",
  "properties": {
    "gn:admin1_code":"16.0",
    "gn:admin2_code":"FI",
    "gn:admin3_code":"48036.0",
    "gn:asciiname":"Cellai",
    "gn:country_code":"IT",
    "gn:dem":250,
    "gn:elevation":"250.0",
    "gn:feature_class":"P",
    "gn:feature_code":"PPL",
    "gn:name":"Cellai",
    "gn:population":327,
    "gn:timezone":"Europe/Rome",
    "iso:country":"IT",
    "wof:name":"Cellai",
    "wof:placetype":"locality",
    "wof:population":327
},
  "geometry": {"coordinates":[11.40484,43.70536],"type":"Point"}
}