{
  "type": "Feature",
  "properties": {
    "gn:admin1_code":"4",
    "gn:admin2_code":"AV",
    "gn:admin3_code":"64023.0",
    "gn:asciiname":"Vallicelli",
    "gn:country_code":"IT",
    "gn:dem":671,
    "gn:feature_class":"P",
    "gn:feature_code":"PPL",
    "gn:name":"Vallicelli",
    "gn:population":154,
    "gn:timezone":"Europe/Rome",
    "iso:country":"IT",
    "wof:name":"Vallicelli",
    "wof:placetype":"locality",
    "wof:population":154
},
  "geometry": {"coordinates":[15.06207,40.92393],"type":"Point"}
}