{
  "type": "Feature",
  "properties": {
    "gn:admin1_code":"6.0",
    "gn:admin2_code":"UD",
    "gn:admin3_code":"30025.0",
    "gn:asciiname":"Raccolana",
    "gn:country_code":"IT",
    "gn:dem":381,
    "gn:elevation":"382.0",
    "gn:feature_class":"P",
    "gn:feature_code":"PPL",
    "gn:name":"Raccolana",
    "gn:population":132,
    "gn:timezone":"Europe/Rome",
    "iso:country":"IT",
    "wof:name":"Raccolana",
    "wof:placetype":"locality",
    "wof:population":132
},
  "geometry": {"coordinates":[13.315,46.40756],"type":"Point"}
}