{
  "type": "Feature",
  "properties": {
    "gn:admin1_code":"12.0",
    "gn:admin2_code":"TO",
    "gn:admin3_code":"1254.0",
    "gn:asciiname":"Airali Sottani",
    "gn:country_code":"IT",
    "gn:dem":352,
    "gn:feature_class":"P",
    "gn:feature_code":"PPL",
    "gn:name":"Airali Sottani",
    "gn:population":17,
    "gn:timezone":"Europe/Rome",
    "iso:country":"IT",
    "wof:name":"Airali Sottani",
    "wof:placetype":"locality",
    "wof:population":17
},
  "geometry": {"coordinates":[7.32371,44.84877],"type":"Point"}
}