{
  "type": "Feature",
  "properties": {
    "gn:admin1_code":"19.0",
    "gn:admin2_code":"AO",
    "gn:admin3_code":"7066.0",
    "gn:asciiname":"Touraz",
    "gn:cc2":"IT",
    "gn:country_code":"IT",
    "gn:dem":2026,
    "gn:feature_class":"P",
    "gn:feature_code":"PPL",
    "gn:name":"Touraz",
    "gn:population":0,
    "gn:timezone":"Europe/Rome",
    "iso:country":"IT",
    "name:und_x_variant":[
        "Thourraz",
        "Touraz"
    ],
    "wof:name":"Touraz",
    "wof:placetype":"locality"
},
  "geometry": {"coordinates":[7.25,45.75],"type":"Point"}
}