{
  "type": "Feature",
  "properties": {
    "gn:admin1_code":"18",
    "gn:admin2_code":"PG",
    "gn:admin3_code":"54030.0",
    "gn:asciiname":"Belvedere",
    "gn:country_code":"IT",
    "gn:dem":318,
    "gn:feature_class":"P",
    "gn:feature_code":"PPL",
    "gn:name":"Belvedere",
    "gn:population":31,
    "gn:timezone":"Europe/Rome",
    "iso:country":"IT",
    "wof:name":"Belvedere",
    "wof:placetype":"locality",
    "wof:population":31
},
  "geometry": {"coordinates":[12.63751,42.913],"type":"Point"}
}