{
  "type": "Feature",
  "properties": {
    "gn:admin1_code":"12",
    "gn:admin2_code":"AL",
    "gn:admin3_code":"6122.0",
    "gn:asciiname":"Regione Boschi",
    "gn:country_code":"IT",
    "gn:dem":162,
    "gn:feature_class":"P",
    "gn:feature_code":"PPL",
    "gn:name":"Regione Boschi",
    "gn:population":13,
    "gn:timezone":"Europe/Rome",
    "iso:country":"IT",
    "wof:name":"Regione Boschi",
    "wof:placetype":"locality",
    "wof:population":13
},
  "geometry": {"coordinates":[8.43551,44.84386],"type":"Point"}
}