{
  "type": "Feature",
  "properties": {
    "gn:admin1_code":"20",
    "gn:admin2_code":"PD",
    "gn:admin3_code":"28059.0",
    "gn:asciiname":"Tre Ponti",
    "gn:country_code":"IT",
    "gn:dem":10,
    "gn:feature_class":"P",
    "gn:feature_code":"PPL",
    "gn:name":"Tre Ponti",
    "gn:population":27,
    "gn:timezone":"Europe/Rome",
    "iso:country":"IT",
    "wof:name":"Tre Ponti",
    "wof:placetype":"locality",
    "wof:population":27
},
  "geometry": {"coordinates":[11.58951,45.24403],"type":"Point"}
}