{
  "type": "Feature",
  "properties": {
    "gn:admin1_code":"17",
    "gn:admin2_code":"TN",
    "gn:admin3_code":"22091.0",
    "gn:asciiname":"Garniga Vecchia Superiore",
    "gn:country_code":"IT",
    "gn:dem":952,
    "gn:feature_class":"P",
    "gn:feature_code":"PPL",
    "gn:name":"Garniga Vecchia Superiore",
    "gn:population":62,
    "gn:timezone":"Europe/Rome",
    "iso:country":"IT",
    "wof:name":"Garniga Vecchia Superiore",
    "wof:placetype":"locality",
    "wof:population":62
},
  "geometry": {"coordinates":[11.08367,46.01386],"type":"Point"}
}