{
  "type": "Feature",
  "properties": {
    "gn:admin1_code":"12.0",
    "gn:admin2_code":"TO",
    "gn:admin3_code":"1197.0",
    "gn:asciiname":"Marocchi",
    "gn:country_code":"IT",
    "gn:dem":245,
    "gn:feature_class":"P",
    "gn:feature_code":"PPL",
    "gn:name":"Marocchi",
    "gn:population":1175,
    "gn:timezone":"Europe/Rome",
    "iso:country":"IT",
    "wof:name":"Marocchi",
    "wof:placetype":"locality",
    "wof:population":1175
},
  "geometry": {"coordinates":[7.81888,44.94201],"type":"Point"}
}