{
  "type": "Feature",
  "properties": {
    "gn:admin1_code":"4.0",
    "gn:admin2_code":"BN",
    "gn:admin3_code":"62008.0",
    "gn:asciiname":"San Vitale III",
    "gn:country_code":"IT",
    "gn:dem":211,
    "gn:feature_class":"P",
    "gn:feature_code":"PPL",
    "gn:name":"San Vitale III",
    "gn:population":31,
    "gn:timezone":"Europe/Rome",
    "iso:country":"IT",
    "wof:name":"San Vitale III",
    "wof:placetype":"locality",
    "wof:population":31
},
  "geometry": {"coordinates":[14.74394,41.15413],"type":"Point"}
}