{
  "type": "Feature",
  "properties": {
    "gn:admin1_code":"17",
    "gn:admin2_code":"TN",
    "gn:admin3_code":"22080.0",
    "gn:asciiname":"Cadino",
    "gn:country_code":"IT",
    "gn:dem":220,
    "gn:feature_class":"P",
    "gn:feature_code":"PPL",
    "gn:name":"Cadino",
    "gn:population":37,
    "gn:timezone":"Europe/Rome",
    "iso:country":"IT",
    "wof:name":"Cadino",
    "wof:placetype":"locality",
    "wof:population":37
},
  "geometry": {"coordinates":[11.153,46.21804],"type":"Point"}
}