{
  "type": "Feature",
  "properties": {
    "gn:admin1_code":"18",
    "gn:admin2_code":"PG",
    "gn:admin3_code":"54048.0",
    "gn:asciiname":"Civitella",
    "gn:country_code":"IT",
    "gn:dem":812,
    "gn:feature_class":"P",
    "gn:feature_code":"PPL",
    "gn:name":"Civitella",
    "gn:population":17,
    "gn:timezone":"Europe/Rome",
    "iso:country":"IT",
    "name:ceb_x_preferred":[
        "Civitella"
    ],
    "name:deu_x_preferred":[
        "Civitella"
    ],
    "name:fra_x_preferred":[
        "Civitella"
    ],
    "name:ita_x_preferred":[
        "Civitella"
    ],
    "name:lat_x_preferred":[
        "Civitella"
    ],
    "name:pms_x_preferred":[
        "Civitella"
    ],
    "name:sco_x_preferred":[
        "Civitella"
    ],
    "name:spa_x_preferred":[
        "Civitella"
    ],
    "name:srp_x_preferred":[
        "\u010civitela"
    ],
    "name:swe_x_preferred":[
        "Civitella"
    ],
    "wof:name":"Civitella",
    "wof:placetype":"locality",
    "wof:population":17
},
  "geometry": {"coordinates":[12.95804,42.90434000000001],"type":"Point"}
}