{
  "type": "Feature",
  "properties": {
    "gn:admin1_code":"20.0",
    "gn:admin2_code":"VR",
    "gn:admin3_code":"23097.0",
    "gn:asciiname":"Ca' dell'Ora Bassa",
    "gn:country_code":"IT",
    "gn:dem":24,
    "gn:feature_class":"P",
    "gn:feature_code":"PPL",
    "gn:name":"Ca' dell'Ora Bassa",
    "gn:population":54,
    "gn:timezone":"Europe/Rome",
    "iso:country":"IT",
    "wof:name":"Ca' dell'Ora Bassa",
    "wof:placetype":"locality",
    "wof:population":54
},
  "geometry": {"coordinates":[11.15463,45.34937],"type":"Point"}
}