{
  "type": "Feature",
  "properties": {
    "gn:admin1_code":"16",
    "gn:admin2_code":"AR",
    "gn:admin3_code":"51037.0",
    "gn:asciiname":"Giuliano",
    "gn:country_code":"IT",
    "gn:dem":463,
    "gn:feature_class":"P",
    "gn:feature_code":"PPL",
    "gn:name":"Giuliano",
    "gn:population":22,
    "gn:timezone":"Europe/Rome",
    "iso:country":"IT",
    "name:ceb_x_preferred":[
        "Giuliano"
    ],
    "name:deu_x_preferred":[
        "Giuliano"
    ],
    "name:ita_x_preferred":[
        "Giuliano"
    ],
    "name:rus_x_preferred":[
        "\u0414\u0436\u0443\u043b\u0438\u0430\u043d\u043e"
    ],
    "name:srp_x_preferred":[
        "\u0110ulijano"
    ],
    "name:swe_x_preferred":[
        "Giuliano"
    ],
    "wof:name":"Giuliano",
    "wof:placetype":"locality",
    "wof:population":22
},
  "geometry": {"coordinates":[11.88323,43.60211],"type":"Point"}
}