{
  "type": "Feature",
  "properties": {
    "gn:elevation":233,
    "gn:population":355,
    "iso:country":"IT",
    "name:arg_x_preferred":[
        "Asuni"
    ],
    "name:bel_x_preferred":[
        "\u0413\u043e\u0440\u0430\u0434 \u0410\u0437\u0443\u043d\u0456"
    ],
    "name:bul_x_preferred":[
        "\u0410\u0437\u0443\u043d\u0438"
    ],
    "name:cat_x_preferred":[
        "Asuni"
    ],
    "name:deu_x_preferred":[
        "Asuni"
    ],
    "name:eng_x_preferred":[
        "Asuni"
    ],
    "name:epo_x_preferred":[
        "Asuni"
    ],
    "name:eus_x_preferred":[
        "Asuni"
    ],
    "name:fas_x_preferred":[
        "\u0622\u0633\u0648\u0646\u06cc"
    ],
    "name:fra_x_preferred":[
        "Asuni"
    ],
    "name:hbs_x_preferred":[
        "Asuni"
    ],
    "name:hun_x_preferred":[
        "Asuni"
    ],
    "name:hye_x_preferred":[
        "\u0531\u0566\u0578\u0582\u0576\u056b"
    ],
    "name:hye_x_variant":[
        "\u0531\u057d\u0578\u0582\u0576\u056b"
    ],
    "name:ita_x_preferred":[
        "Asuni"
    ],
    "name:jpn_x_preferred":[
        "\u30a2\u30ba\u30fc\u30cb"
    ],
    "name:kaz_x_preferred":[
        "\u0410\u0437\u0443\u043d\u0438"
    ],
    "name:lat_x_preferred":[
        "Asunis"
    ],
    "name:lmo_x_preferred":[
        "Asuni"
    ],
    "name:msa_x_preferred":[
        "Asuni"
    ],
    "name:nan_x_preferred":[
        "Asuni"
    ],
    "name:nap_x_preferred":[
        "Asuni"
    ],
    "name:nld_x_preferred":[
        "Asuni"
    ],
    "name:pms_x_preferred":[
        "Asuni"
    ],
    "name:pol_x_preferred":[
        "Asuni"
    ],
    "name:por_x_preferred":[
        "Asuni"
    ],
    "name:ron_x_preferred":[
        "Asuni"
    ],
    "name:rus_x_preferred":[
        "\u0410\u0437\u0443\u043d\u0438"
    ],
    "name:scn_x_preferred":[
        "Asuni"
    ],
    "name:spa_x_preferred":[
        "Asuni"
    ],
    "name:srd_x_preferred":[
        "Asuni"
    ],
    "name:srp_x_preferred":[
        "\u0410\u0437\u0443\u043d\u0438"
    ],
    "name:tgl_x_preferred":[
        "Asuni"
    ],
    "name:ukr_x_preferred":[
        "\u0410\u0437\u0443\u043d\u0456"
    ],
    "name:uzb_x_preferred":[
        "Asuni"
    ],
    "name:vie_x_preferred":[
        "Asuni"
    ],
    "name:vol_x_preferred":[
        "Asuni"
    ],
    "name:war_x_preferred":[
        "Asuni"
    ],
    "name:zho_min_nan_x_preferred":[
        "Asuni"
    ],
    "name:zho_x_preferred":[
        "\u963f\u82cf\u5c3c"
    ],
    "qs:a0":"Italia",
    "qs:a1":"*Oristano",
    "qs:a1r":"0Sardegna",
    "qs:adm0":"Italia",
    "qs:la_lc":"*",
    "qs:level":"locality",
    "qs:loc":"Asuni",
    "qs:loc_alt":"Asuni",
    "qs:pop":0,
    "qs:type":"buffered point",
    "wd:wordcount":80,
    "wof:lang":[
        "ita"
    ],
    "wof:name":"Asuni",
    "wof:placetype":"locality",
    "wof:population":355
},
  "geometry": {"coordinates":[8.94722,39.873329],"type":"Point"}
}