{
  "type": "Feature",
  "properties": {
    "gn:admin1_code":"9",
    "gn:admin2_code":"VA",
    "gn:admin3_code":"12029.0",
    "gn:asciiname":"Barlam",
    "gn:country_code":"IT",
    "gn:dem":278,
    "gn:feature_class":"P",
    "gn:feature_code":"PPL",
    "gn:name":"Barlam",
    "gn:population":59,
    "gn:timezone":"Europe/Rome",
    "iso:country":"IT",
    "wof:name":"Barlam",
    "wof:placetype":"locality",
    "wof:population":59
},
  "geometry": {"coordinates":[8.88462,45.68737],"type":"Point"}
}