{
  "type": "Feature",
  "properties": {
    "gn:admin1_code":"10",
    "gn:admin2_code":"AP",
    "gn:admin3_code":"44002.0",
    "gn:asciiname":"Conca degli Ulivi",
    "gn:country_code":"IT",
    "gn:dem":172,
    "gn:feature_class":"P",
    "gn:feature_code":"PPL",
    "gn:name":"Conca degli Ulivi",
    "gn:population":28,
    "gn:timezone":"Europe/Rome",
    "iso:country":"IT",
    "wof:name":"Conca degli Ulivi",
    "wof:placetype":"locality",
    "wof:population":28
},
  "geometry": {"coordinates":[13.84312,42.9395],"type":"Point"}
}