{
  "type": "Feature",
  "properties": {
    "gn:admin1_code":"8",
    "gn:admin2_code":"IM",
    "gn:admin3_code":"8066.0",
    "gn:asciiname":"Lenzari",
    "gn:country_code":"IT",
    "gn:dem":505,
    "gn:feature_class":"P",
    "gn:feature_code":"PPL",
    "gn:name":"Lenzari",
    "gn:population":19,
    "gn:timezone":"Europe/Rome",
    "iso:country":"IT",
    "name:azb_x_preferred":[
        "\u0644\u0646\u0632\u0627\u0631\u06cc"
    ],
    "name:fas_x_preferred":[
        "\u0644\u0646\u0632\u0627\u0631\u06cc"
    ],
    "wof:name":"Lenzari",
    "wof:placetype":"locality",
    "wof:population":19
},
  "geometry": {"coordinates":[7.95922,44.0647],"type":"Point"}
}