{
  "type": "Feature",
  "properties": {
    "gn:admin1_code":"20.0",
    "gn:admin2_code":"BL",
    "gn:admin3_code":"25005.0",
    "gn:asciiname":"Stabinrigo",
    "gn:country_code":"IT",
    "gn:dem":1240,
    "gn:feature_class":"P",
    "gn:feature_code":"PPL",
    "gn:name":"Stabinrigo",
    "gn:population":0,
    "gn:timezone":"Europe/Rome",
    "iso:country":"IT",
    "wof:name":"Stabinrigo",
    "wof:placetype":"locality"
},
  "geometry": {"coordinates":[12.27306,46.53722],"type":"Point"}
}