{
  "type": "Feature",
  "properties": {
    "gn:admin1_code":"19",
    "gn:admin2_code":"AO",
    "gn:admin3_code":"7074.0",
    "gn:asciiname":"Champagnole",
    "gn:country_code":"IT",
    "gn:dem":679,
    "gn:feature_class":"P",
    "gn:feature_code":"PPL",
    "gn:name":"Champagnole",
    "gn:population":28,
    "gn:timezone":"Europe/Rome",
    "iso:country":"IT",
    "wof:name":"Champagnole",
    "wof:placetype":"locality",
    "wof:population":28
},
  "geometry": {"coordinates":[7.22943,45.70276],"type":"Point"}
}