{
  "type": "Feature",
  "properties": {
    "gn:admin1_code":"19",
    "gn:admin2_code":"AO",
    "gn:admin3_code":"7074.0",
    "gn:asciiname":"Champagnole",
    "gn:country_code":"IT",
    "gn:dem":679,
    "gn:feature_class":"P",
    "gn:feature_code":"PPL",
    "gn:name":"Champagnole",
    "gn:population":28,
    "gn:timezone":"Europe/Rome",
    "iso:country":"IT",
    "name:cat_x_preferred":[
        "Champagnole"
    ],
    "name:ceb_x_preferred":[
        "Champagnole"
    ],
    "name:ces_x_preferred":[
        "Champagnole"
    ],
    "name:deu_x_preferred":[
        "Champagnole"
    ],
    "name:epo_x_preferred":[
        "Champagnole"
    ],
    "name:eus_x_preferred":[
        "Champagnole"
    ],
    "name:fin_x_preferred":[
        "Champagnole"
    ],
    "name:fra_x_preferred":[
        "Champagnole"
    ],
    "name:frp_x_preferred":[
        "Champagn\u00f4la"
    ],
    "name:hun_x_preferred":[
        "Champagnole"
    ],
    "name:ita_x_preferred":[
        "Champagnole"
    ],
    "name:lat_x_preferred":[
        "Champagnole"
    ],
    "name:ltz_x_preferred":[
        "Champagnole"
    ],
    "name:msa_x_preferred":[
        "Champagnole"
    ],
    "name:nld_x_preferred":[
        "Champagnole"
    ],
    "name:oci_x_preferred":[
        "Champagnole"
    ],
    "name:pms_x_preferred":[
        "Champagnole"
    ],
    "name:pol_x_preferred":[
        "Champagnole"
    ],
    "name:por_x_preferred":[
        "Champagnole"
    ],
    "name:slk_x_preferred":[
        "Champagnole"
    ],
    "name:slv_x_preferred":[
        "Champagnole"
    ],
    "name:spa_x_preferred":[
        "Champagnole"
    ],
    "name:srp_x_preferred":[
        "\u0428\u0430\u043c\u043f\u0430\u045a\u043e\u043b"
    ],
    "name:swe_x_preferred":[
        "Champagnole"
    ],
    "name:ukr_x_preferred":[
        "\u0428\u0430\u043c\u043f\u0430\u043d\u044c\u043e\u043b\u044c"
    ],
    "name:uzb_x_preferred":[
        "Champagnole"
    ],
    "name:vie_x_preferred":[
        "Champagnole"
    ],
    "name:vol_x_preferred":[
        "Champagnole"
    ],
    "name:war_x_preferred":[
        "Champagnole"
    ],
    "name:zho_x_preferred":[
        "\u5c1a\u5e15\u5c3c\u5965\u52d2"
    ],
    "wof:name":"Champagnole",
    "wof:placetype":"locality",
    "wof:population":28
},
  "geometry": {"coordinates":[7.22943,45.70276],"type":"Point"}
}