{
  "type": "Feature",
  "properties": {
    "gn:admin1_code":"9.0",
    "gn:admin2_code":"PV",
    "gn:admin3_code":"18143.0",
    "gn:asciiname":"Valdamonte",
    "gn:country_code":"IT",
    "gn:dem":294,
    "gn:elevation":"299.0",
    "gn:feature_class":"P",
    "gn:feature_code":"PPL",
    "gn:name":"Valdamonte",
    "gn:population":78,
    "gn:timezone":"Europe/Rome",
    "iso:country":"IT",
    "wof:name":"Valdamonte",
    "wof:placetype":"locality",
    "wof:population":78
},
  "geometry": {"coordinates":[9.31787,44.98805],"type":"Point"}
}