{
  "type": "Feature",
  "properties": {
    "gn:admin1_code":"20",
    "gn:admin2_code":"VR",
    "gn:admin3_code":"23044.0",
    "gn:asciiname":"Rampin",
    "gn:country_code":"IT",
    "gn:dem":10,
    "gn:feature_class":"P",
    "gn:feature_code":"PPL",
    "gn:name":"Rampin",
    "gn:population":118,
    "gn:timezone":"Europe/Rome",
    "iso:country":"IT",
    "wof:name":"Rampin",
    "wof:placetype":"locality",
    "wof:population":118
},
  "geometry": {"coordinates":[11.26491,45.16503],"type":"Point"}
}