{
  "type": "Feature",
  "properties": {
    "gn:admin1_code":"5",
    "gn:admin2_code":"PC",
    "gn:admin3_code":"33004.0",
    "gn:asciiname":"Vaio",
    "gn:country_code":"IT",
    "gn:dem":733,
    "gn:feature_class":"P",
    "gn:feature_code":"PPL",
    "gn:name":"Vaio",
    "gn:population":11,
    "gn:timezone":"Europe/Rome",
    "iso:country":"IT",
    "name:ara_x_preferred":[
        "\u0641\u0627\u064a\u0648"
    ],
    "name:azb_x_preferred":[
        "\u0648\u0627\u06cc\u0648"
    ],
    "name:ces_x_preferred":[
        "Vaio"
    ],
    "name:deu_x_preferred":[
        "VAIO Corporation"
    ],
    "name:fas_x_preferred":[
        "\u0648\u0627\u06cc\u0648"
    ],
    "name:ita_x_preferred":[
        "Sony VAIO"
    ],
    "name:kor_x_preferred":[
        "\ubc14\uc774\uc624"
    ],
    "name:slk_x_preferred":[
        "Vaio"
    ],
    "name:swe_x_preferred":[
        "Vaio"
    ],
    "name:tha_x_preferred":[
        "\u0e44\u0e27\u0e42\u0e2d\u0e49"
    ],
    "name:tur_x_preferred":[
        "Sony Vaio"
    ],
    "wof:name":"Vaio",
    "wof:placetype":"locality",
    "wof:population":11
},
  "geometry": {"coordinates":[9.53237,44.77],"type":"Point"}
}