{
  "type": "Feature",
  "properties": {
    "gn:admin1_code":"3.0",
    "gn:admin2_code":"KR",
    "gn:admin3_code":"101010.0",
    "gn:asciiname":"Gabella Iv",
    "gn:country_code":"IT",
    "gn:dem":5,
    "gn:feature_class":"P",
    "gn:feature_code":"PPL",
    "gn:name":"Gabella Iv",
    "gn:population":33,
    "gn:timezone":"Europe/Rome",
    "iso:country":"IT",
    "wof:name":"Gabella Iv",
    "wof:placetype":"locality",
    "wof:population":33
},
  "geometry": {"coordinates":[17.10067,39.15547],"type":"Point"}
}