{
  "type": "Feature",
  "properties": {
    "gn:admin1_code":"9.0",
    "gn:admin2_code":"SO",
    "gn:admin3_code":"14026.0",
    "gn:asciiname":"Canargo di Sotto",
    "gn:country_code":"IT",
    "gn:dem":931,
    "gn:feature_class":"P",
    "gn:feature_code":"PPL",
    "gn:name":"Canargo di Sotto",
    "gn:population":0,
    "gn:timezone":"Europe/Rome",
    "iso:country":"IT",
    "wof:name":"Canargo di Sotto",
    "wof:placetype":"locality"
},
  "geometry": {"coordinates":[9.45867,46.11424],"type":"Point"}
}