{
  "type": "Feature",
  "properties": {
    "gn:admin1_code":"9",
    "gn:admin2_code":"SO",
    "gn:admin3_code":"14045.0",
    "gn:asciiname":"San Bello",
    "gn:country_code":"IT",
    "gn:dem":326,
    "gn:feature_class":"P",
    "gn:feature_code":"PPL",
    "gn:name":"San Bello",
    "gn:population":17,
    "gn:timezone":"Europe/Rome",
    "iso:country":"IT",
    "wof:name":"San Bello",
    "wof:placetype":"locality",
    "wof:population":17
},
  "geometry": {"coordinates":[9.57225,46.1477],"type":"Point"}
}