{
  "type": "Feature",
  "properties": {
    "gn:admin1_code":"10.0",
    "gn:admin2_code":"AP",
    "gn:admin3_code":"44011.0",
    "gn:asciiname":"Colle",
    "gn:country_code":"IT",
    "gn:dem":188,
    "gn:feature_class":"P",
    "gn:feature_code":"PPL",
    "gn:name":"Colle",
    "gn:population":26,
    "gn:timezone":"Europe/Rome",
    "iso:country":"IT",
    "name:ceb_x_preferred":[
        "Colle"
    ],
    "name:deu_x_preferred":[
        "Colle"
    ],
    "name:fra_x_preferred":[
        "Colle"
    ],
    "name:ita_x_preferred":[
        "Colle"
    ],
    "name:nld_x_preferred":[
        "Colle"
    ],
    "name:por_x_preferred":[
        "Colle"
    ],
    "name:swe_x_preferred":[
        "Colle"
    ],
    "wof:name":"Colle",
    "wof:placetype":"locality",
    "wof:population":26
},
  "geometry": {"coordinates":[13.70124,42.8704],"type":"Point"}
}