{
  "type": "Feature",
  "properties": {
    "gn:admin1_code":"3",
    "gn:admin2_code":"CS",
    "gn:admin3_code":"78058.0",
    "gn:asciiname":"Donnasivila-Gemarca",
    "gn:country_code":"IT",
    "gn:dem":82,
    "gn:feature_class":"P",
    "gn:feature_code":"PPL",
    "gn:name":"Donnasivila-Gemarca",
    "gn:population":157,
    "gn:timezone":"Europe/Rome",
    "iso:country":"IT",
    "wof:name":"Donnasivila-Gemarca",
    "wof:placetype":"locality",
    "wof:population":157
},
  "geometry": {"coordinates":[16.0139,39.42358],"type":"Point"}
}