{
  "type": "Feature",
  "properties": {
    "gn:admin1_code":"5",
    "gn:admin2_code":"BO",
    "gn:admin3_code":"37039.0",
    "gn:asciiname":"Guarda",
    "gn:country_code":"IT",
    "gn:dem":13,
    "gn:feature_class":"P",
    "gn:feature_code":"PPL",
    "gn:name":"Guarda",
    "gn:population":150,
    "gn:timezone":"Europe/Rome",
    "iso:country":"IT",
    "wof:name":"Guarda",
    "wof:placetype":"locality",
    "wof:population":150
},
  "geometry": {"coordinates":[11.62255,44.61002],"type":"Point"}
}