{
  "type": "Feature",
  "properties": {
    "gn:admin1_code":"5",
    "gn:admin2_code":"BO",
    "gn:admin3_code":"37039.0",
    "gn:asciiname":"Guarda",
    "gn:country_code":"IT",
    "gn:dem":13,
    "gn:feature_class":"P",
    "gn:feature_code":"PPL",
    "gn:name":"Guarda",
    "gn:population":150,
    "gn:timezone":"Europe/Rome",
    "iso:country":"IT",
    "name:arg_x_preferred":[
        "Guarda"
    ],
    "name:bre_x_preferred":[
        "Guarda"
    ],
    "name:cat_x_preferred":[
        "Guarda"
    ],
    "name:ceb_x_preferred":[
        "Guarda"
    ],
    "name:deu_x_preferred":[
        "Guarda"
    ],
    "name:epo_x_preferred":[
        "Guarda"
    ],
    "name:fra_x_preferred":[
        "Guarda"
    ],
    "name:glg_x_preferred":[
        "Guarda"
    ],
    "name:ind_x_preferred":[
        "Guarda"
    ],
    "name:ita_x_preferred":[
        "Guarda"
    ],
    "name:msa_x_preferred":[
        "Guarda"
    ],
    "name:nld_x_preferred":[
        "Guarda"
    ],
    "name:nno_x_preferred":[
        "Guarda"
    ],
    "name:pnb_x_preferred":[
        "\u06af\u0648\u0622\u0631\u062f\u0627"
    ],
    "name:pol_x_preferred":[
        "Guarda"
    ],
    "name:por_x_preferred":[
        "Guarda"
    ],
    "name:sco_x_preferred":[
        "Guarda"
    ],
    "name:slk_x_preferred":[
        "Guarda"
    ],
    "name:spa_x_preferred":[
        "Guarda"
    ],
    "name:srp_x_preferred":[
        "Gvarda"
    ],
    "name:swe_x_preferred":[
        "Guarda"
    ],
    "name:ukr_x_preferred":[
        "\u0413\u0443\u0430\u0440\u0434\u0430"
    ],
    "name:vie_x_preferred":[
        "Guarda"
    ],
    "name:vol_x_preferred":[
        "Guarda"
    ],
    "name:war_x_preferred":[
        "Guarda"
    ],
    "wof:name":"Guarda",
    "wof:placetype":"locality",
    "wof:population":150
},
  "geometry": {"coordinates":[11.62255,44.61002],"type":"Point"}
}