{
  "type": "Feature",
  "properties": {
    "gn:admin1_code":"20",
    "gn:admin2_code":"PD",
    "gn:admin3_code":"28100.0",
    "gn:asciiname":"Case Via Rigato",
    "gn:country_code":"IT",
    "gn:dem":7,
    "gn:feature_class":"P",
    "gn:feature_code":"PPL",
    "gn:name":"Case Via Rigato",
    "gn:population":70,
    "gn:timezone":"Europe/Rome",
    "iso:country":"IT",
    "wof:name":"Case Via Rigato",
    "wof:placetype":"locality",
    "wof:population":70
},
  "geometry": {"coordinates":[11.93972,45.44404],"type":"Point"}
}