{
  "type": "Feature",
  "properties": {
    "gn:admin1_code":"1.0",
    "gn:admin2_code":"AQ",
    "gn:admin3_code":"66029.0",
    "gn:asciiname":"Pagliara",
    "gn:country_code":"IT",
    "gn:dem":1042,
    "gn:elevation":"1100.0",
    "gn:feature_class":"P",
    "gn:feature_code":"PPL",
    "gn:name":"Pagliara",
    "gn:population":45,
    "gn:timezone":"Europe/Rome",
    "iso:country":"IT",
    "wof:name":"Pagliara",
    "wof:placetype":"locality",
    "wof:population":45
},
  "geometry": {"coordinates":[13.32131,42.00505],"type":"Point"}
}