{
  "type": "Feature",
  "properties": {
    "gn:admin1_code":"6.0",
    "gn:admin2_code":"UD",
    "gn:admin3_code":"30081.0",
    "gn:asciiname":"Avausa",
    "gn:country_code":"IT",
    "gn:dem":644,
    "gn:elevation":"652.0",
    "gn:feature_class":"P",
    "gn:feature_code":"PPL",
    "gn:name":"Avausa",
    "gn:population":122,
    "gn:timezone":"Europe/Rome",
    "iso:country":"IT",
    "wof:name":"Avausa",
    "wof:placetype":"locality",
    "wof:population":122
},
  "geometry": {"coordinates":[12.81873,46.51824000000001],"type":"Point"}
}