{
  "type": "Feature",
  "properties": {
    "iso:country":"IT",
    "name:cat_x_preferred":[
        "Custoza"
    ],
    "name:ceb_x_preferred":[
        "Custoza"
    ],
    "name:ces_x_preferred":[
        "Custoza"
    ],
    "name:dan_x_preferred":[
        "Custoza"
    ],
    "name:deu_x_preferred":[
        "Custoza"
    ],
    "name:eng_x_preferred":[
        "Custoza"
    ],
    "name:eus_x_preferred":[
        "Custoza"
    ],
    "name:fas_x_preferred":[
        "\u06a9\u0648\u0632\u062a\u0648\u0632\u0627"
    ],
    "name:fin_x_preferred":[
        "Custoza"
    ],
    "name:fra_x_preferred":[
        "Custoza"
    ],
    "name:hun_x_preferred":[
        "Custoza"
    ],
    "name:ind_x_preferred":[
        "Custoza"
    ],
    "name:ita_x_preferred":[
        "Custoza"
    ],
    "name:jpn_x_preferred":[
        "\u30af\u30b9\u30c8\u30fc\u30c4\u30a1"
    ],
    "name:lmo_x_preferred":[
        "Custoza"
    ],
    "name:nld_x_preferred":[
        "Custoza"
    ],
    "name:nno_x_preferred":[
        "Custoza"
    ],
    "name:nob_x_preferred":[
        "Custoza"
    ],
    "name:oci_x_preferred":[
        "Custoza"
    ],
    "name:pol_x_preferred":[
        "Custoza"
    ],
    "name:por_x_preferred":[
        "Custoza"
    ],
    "name:ron_x_preferred":[
        "Custoza"
    ],
    "name:rus_x_preferred":[
        "\u041a\u0443\u0441\u0442\u043e\u0446\u0446\u0430"
    ],
    "name:slk_x_preferred":[
        "Custoza"
    ],
    "name:slv_x_preferred":[
        "Custoza"
    ],
    "name:spa_x_preferred":[
        "Custoza"
    ],
    "name:srp_x_preferred":[
        "Custoza"
    ],
    "name:swe_x_preferred":[
        "Custoza"
    ],
    "name:tgl_x_preferred":[
        "Custoza"
    ],
    "name:tur_x_preferred":[
        "Custoza"
    ],
    "name:ukr_x_preferred":[
        "\u041a\u0443\u0441\u0442\u043e\u0437\u0430"
    ],
    "name:vec_x_preferred":[
        "Custoxa"
    ],
    "name:war_x_preferred":[
        "Custoza"
    ],
    "qs_pg:aaroncc":"IT",
    "qs_pg:name":"Custoza",
    "qs_pg:name_adm0":"Italia",
    "qs_pg:name_adm1":"Veneto",
    "qs_pg:photos":47,
    "qs_pg:photos_1k":10,
    "qs_pg:photos_9k":1,
    "qs_pg:photos_9r":2,
    "qs_pg:photos_all":47,
    "qs_pg:photos_sr":2,
    "qs_pg:pop_sr":0,
    "qs_pg:qs_pg_placetype":"locality",
    "qs_pg:qs_pg_placetype_gp":"Town",
    "qs_pg:woe_adm0":23424853,
    "woe:adm0_id":23424853,
    "woe:name_adm0":"Italia",
    "woe:name_adm1":"Veneto",
    "woe:placetype":"Town",
    "wof:name":"Custoza",
    "wof:placetype":"locality"
},
  "geometry": {"coordinates":[10.79502,45.372909],"type":"Point"}
}