{
  "type": "Feature",
  "properties": {
    "gn:admin1_code":"13",
    "gn:admin2_code":"BR",
    "gn:admin3_code":"74005.0",
    "gn:asciiname":"Figazzano",
    "gn:country_code":"IT",
    "gn:dem":349,
    "gn:feature_class":"P",
    "gn:feature_code":"PPL",
    "gn:name":"Figazzano",
    "gn:population":74,
    "gn:timezone":"Europe/Rome",
    "iso:country":"IT",
    "wof:name":"Figazzano",
    "wof:placetype":"locality",
    "wof:population":74
},
  "geometry": {"coordinates":[17.37425,40.74826],"type":"Point"}
}