{
  "type": "Feature",
  "properties": {
    "gn:admin1_code":"12",
    "gn:admin2_code":"CN",
    "gn:admin3_code":"4101.0",
    "gn:asciiname":"Osteria",
    "gn:country_code":"IT",
    "gn:dem":176,
    "gn:feature_class":"P",
    "gn:feature_code":"PPL",
    "gn:name":"Osteria",
    "gn:population":78,
    "gn:timezone":"Europe/Rome",
    "iso:country":"IT",
    "wof:name":"Osteria",
    "wof:placetype":"locality",
    "wof:population":78
},
  "geometry": {"coordinates":[8.02104,44.72594],"type":"Point"}
}