{
  "type": "Feature",
  "properties": {
    "gn:admin1_code":"12",
    "gn:admin2_code":"CN",
    "gn:admin3_code":"4101.0",
    "gn:asciiname":"Osteria",
    "gn:country_code":"IT",
    "gn:dem":176,
    "gn:feature_class":"P",
    "gn:feature_code":"PPL",
    "gn:name":"Osteria",
    "gn:population":78,
    "gn:timezone":"Europe/Rome",
    "iso:country":"IT",
    "name:deu_x_preferred":[
        "Osteria"
    ],
    "name:fra_x_preferred":[
        "Osteria"
    ],
    "name:ita_x_preferred":[
        "Osteria"
    ],
    "name:jpn_x_preferred":[
        "\u30aa\u30b9\u30c6\u30ea\u30a2"
    ],
    "name:rus_x_preferred":[
        "\u041e\u0441\u0442\u0435\u0440\u0438\u044f"
    ],
    "name:scn_x_preferred":[
        "Ostar\u00eca"
    ],
    "name:ukr_x_preferred":[
        "\u041e\u0441\u0442\u0435\u0440\u0456\u044f"
    ],
    "wof:name":"Osteria",
    "wof:placetype":"locality",
    "wof:population":78
},
  "geometry": {"coordinates":[8.02104,44.72594],"type":"Point"}
}