{
  "type": "Feature",
  "properties": {
    "gn:admin1_code":"20",
    "gn:admin2_code":"RO",
    "gn:admin3_code":"29027.0",
    "gn:asciiname":"Tadiole",
    "gn:country_code":"IT",
    "gn:dem":8,
    "gn:feature_class":"P",
    "gn:feature_code":"PPL",
    "gn:name":"Tadiole",
    "gn:population":50,
    "gn:timezone":"Europe/Rome",
    "iso:country":"IT",
    "wof:name":"Tadiole",
    "wof:placetype":"locality",
    "wof:population":50
},
  "geometry": {"coordinates":[11.45973,45.07052],"type":"Point"}
}