{
  "type": "Feature",
  "properties": {
    "gn:gn_country":"IT",
    "gn:gn_fcode":"PPLA3",
    "gn:gn_pop":3108,
    "gn:population":3108,
    "iso:country":"IT",
    "name:bel_x_preferred":[
        "\u0412\u0430\u043d\u0434\u043e\u0435\u0441"
    ],
    "name:bul_x_preferred":[
        "\u0412\u0430\u043d\u0434\u043e\u0439\u0435\u0441"
    ],
    "name:cat_x_preferred":[
        "Vintl"
    ],
    "name:deu_x_preferred":[
        "Vintl"
    ],
    "name:eng_x_preferred":[
        "Vintl"
    ],
    "name:epo_x_preferred":[
        "Vintl"
    ],
    "name:est_x_preferred":[
        "Vintli vald"
    ],
    "name:eus_x_preferred":[
        "Vintl"
    ],
    "name:fra_x_preferred":[
        "Vandoies"
    ],
    "name:hun_x_preferred":[
        "Vandoies"
    ],
    "name:hye_x_preferred":[
        "\u054e\u0561\u0576\u0564\u0578\u0575\u0565\u057d"
    ],
    "name:ina_x_preferred":[
        "Vandoies"
    ],
    "name:ita_x_preferred":[
        "Vandoies"
    ],
    "name:jpn_x_preferred":[
        "\u30f4\u30a1\u30f3\u30c9\u30fc\u30a4\u30a8\u30b9"
    ],
    "name:kaz_x_preferred":[
        "\u0412\u0430\u043d\u0434\u043e\u0439\u0435\u0441"
    ],
    "name:lat_x_preferred":[
        "Vallis Uintulla"
    ],
    "name:lmo_x_preferred":[
        "Vandoies"
    ],
    "name:msa_x_preferred":[
        "Vintl"
    ],
    "name:nap_x_preferred":[
        "Vandoies"
    ],
    "name:nld_x_preferred":[
        "Vintl"
    ],
    "name:pms_x_preferred":[
        "Vintl"
    ],
    "name:pol_x_preferred":[
        "Vintl"
    ],
    "name:por_x_preferred":[
        "Vandoies"
    ],
    "name:ron_x_preferred":[
        "Vandoies"
    ],
    "name:rus_x_preferred":[
        "\u0412\u0430\u043d\u0434\u043e\u0439\u0435\u0441"
    ],
    "name:scn_x_preferred":[
        "Vandoies"
    ],
    "name:spa_x_preferred":[
        "Vandoies"
    ],
    "name:srp_x_preferred":[
        "Vandoies - Vintl"
    ],
    "name:tgl_x_preferred":[
        "Vintl"
    ],
    "name:ukr_x_preferred":[
        "\u0412\u0430\u043d\u0434\u043e\u0457\u0454\u0441"
    ],
    "name:vie_x_preferred":[
        "Vandoies"
    ],
    "name:vol_x_preferred":[
        "Vandoies"
    ],
    "name:war_x_preferred":[
        "Vintl"
    ],
    "name:zho_x_preferred":[
        "\u4e07\u591a\u8036\u65af"
    ],
    "qs_pg:aaroncc":"IT",
    "qs_pg:gn_country":"IT",
    "qs_pg:gn_fcode":"PPLA3",
    "qs_pg:gn_pop":3108,
    "qs_pg:name":"Vandoies - Vintl",
    "qs_pg:photos_9r":0,
    "qs_pg:photos_sr":0,
    "qs_pg:pop_sr":4,
    "qs_pg:qs_pg_placetype":"locality",
    "wof:name":"Vandoies - Vintl",
    "wof:placetype":"locality",
    "wof:population":3108
},
  "geometry": {"coordinates":[11.72068,46.81513],"type":"Point"}
}