{
  "type": "Feature",
  "properties": {
    "gn:admin1_code":"5",
    "gn:admin2_code":"FE",
    "gn:admin3_code":"38003.0",
    "gn:asciiname":"Casal Federico",
    "gn:country_code":"IT",
    "gn:dem":7,
    "gn:feature_class":"P",
    "gn:feature_code":"PPL",
    "gn:name":"Casal Federico",
    "gn:population":25,
    "gn:timezone":"Europe/Rome",
    "iso:country":"IT",
    "wof:name":"Casal Federico",
    "wof:placetype":"locality",
    "wof:population":25
},
  "geometry": {"coordinates":[11.3878,44.91258],"type":"Point"}
}