{
  "type": "Feature",
  "properties": {
    "gn:admin1_code":"8",
    "gn:admin2_code":"SV",
    "gn:admin3_code":"9045.0",
    "gn:asciiname":"Campi",
    "gn:country_code":"IT",
    "gn:dem":183,
    "gn:feature_class":"P",
    "gn:feature_code":"PPL",
    "gn:name":"Campi",
    "gn:population":25,
    "gn:timezone":"Europe/Rome",
    "iso:country":"IT",
    "name:bre_x_preferred":[
        "Campi"
    ],
    "name:ceb_x_preferred":[
        "Campi"
    ],
    "name:deu_x_preferred":[
        "Campi"
    ],
    "name:ita_x_preferred":[
        "Campi"
    ],
    "name:nds_x_preferred":[
        "Campi"
    ],
    "name:rus_x_preferred":[
        "\u041a\u0430\u043c\u043f\u0438"
    ],
    "name:spa_x_preferred":[
        "Campi"
    ],
    "name:srp_x_preferred":[
        "Kampi"
    ],
    "name:swe_x_preferred":[
        "Campi"
    ],
    "name:ukr_x_preferred":[
        "\u041a\u0430\u043c\u043f\u0456"
    ],
    "wof:name":"Campi",
    "wof:placetype":"locality",
    "wof:population":25
},
  "geometry": {"coordinates":[8.08999,44.06615],"type":"Point"}
}