{
  "type": "Feature",
  "properties": {
    "gn:admin1_code":"4",
    "gn:admin2_code":"AV",
    "gn:admin3_code":"64053.0",
    "gn:asciiname":"Cataldi",
    "gn:country_code":"IT",
    "gn:dem":599,
    "gn:feature_class":"P",
    "gn:feature_code":"PPL",
    "gn:name":"Cataldi",
    "gn:population":40,
    "gn:timezone":"Europe/Rome",
    "iso:country":"IT",
    "wof:name":"Cataldi",
    "wof:placetype":"locality",
    "wof:population":40
},
  "geometry": {"coordinates":[14.89601,40.96084000000001],"type":"Point"}
}