{
  "type": "Feature",
  "properties": {
    "gn:admin1_code":"12",
    "gn:admin2_code":"TO",
    "gn:admin3_code":"1282.0",
    "gn:asciiname":"Crot",
    "gn:country_code":"IT",
    "gn:dem":1296,
    "gn:feature_class":"P",
    "gn:feature_code":"PPL",
    "gn:name":"Crot",
    "gn:population":26,
    "gn:timezone":"Europe/Rome",
    "iso:country":"IT",
    "wof:name":"Crot",
    "wof:placetype":"locality",
    "wof:population":26
},
  "geometry": {"coordinates":[7.20319,45.23088],"type":"Point"}
}