{
  "type": "Feature",
  "properties": {
    "gn:admin1_code":"20.0",
    "gn:admin2_code":"VE",
    "gn:admin3_code":"27036.0",
    "gn:asciiname":"Corbolone",
    "gn:country_code":"IT",
    "gn:dem":2,
    "gn:elevation":"5.0",
    "gn:feature_class":"P",
    "gn:feature_code":"PPL",
    "gn:name":"Corbolone",
    "gn:population":1014,
    "gn:timezone":"Europe/Rome",
    "iso:country":"IT",
    "wof:name":"Corbolone",
    "wof:placetype":"locality",
    "wof:population":1014
},
  "geometry": {"coordinates":[12.66969,45.74962],"type":"Point"}
}