{
  "type": "Feature",
  "properties": {
    "gn:admin1_code":"5",
    "gn:admin2_code":"RN",
    "gn:admin3_code":"99020.0",
    "gn:asciiname":"Brocchi I",
    "gn:country_code":"IT",
    "gn:dem":211,
    "gn:feature_class":"P",
    "gn:feature_code":"PPL",
    "gn:name":"Brocchi I",
    "gn:population":38,
    "gn:timezone":"Europe/Rome",
    "iso:country":"IT",
    "wof:name":"Brocchi I",
    "wof:placetype":"locality",
    "wof:population":38
},
  "geometry": {"coordinates":[12.42466,43.98704],"type":"Point"}
}