{
  "type": "Feature",
  "properties": {
    "gn:admin1_code":"5",
    "gn:admin2_code":"MO",
    "gn:admin3_code":"36024.0",
    "gn:asciiname":"Rovinella",
    "gn:country_code":"IT",
    "gn:dem":562,
    "gn:feature_class":"P",
    "gn:feature_code":"PPL",
    "gn:name":"Rovinella",
    "gn:population":14,
    "gn:timezone":"Europe/Rome",
    "iso:country":"IT",
    "wof:name":"Rovinella",
    "wof:placetype":"locality",
    "wof:population":14
},
  "geometry": {"coordinates":[10.74956,44.28733],"type":"Point"}
}