{
  "type": "Feature",
  "properties": {
    "gn:admin1_code":"4",
    "gn:admin2_code":"SA",
    "gn:admin3_code":"65088.0",
    "gn:asciiname":"Mannara",
    "gn:country_code":"IT",
    "gn:dem":25,
    "gn:feature_class":"P",
    "gn:feature_code":"PPL",
    "gn:name":"Mannara",
    "gn:population":20,
    "gn:timezone":"Europe/Rome",
    "iso:country":"IT",
    "wof:name":"Mannara",
    "wof:placetype":"locality",
    "wof:population":20
},
  "geometry": {"coordinates":[14.61728,40.76556],"type":"Point"}
}