{
  "type": "Feature",
  "properties": {
    "gn:admin1_code":"3",
    "gn:admin2_code":"CZ",
    "gn:admin3_code":"79138.0",
    "gn:asciiname":"Fiumarella",
    "gn:country_code":"IT",
    "gn:dem":729,
    "gn:feature_class":"P",
    "gn:feature_code":"PPL",
    "gn:name":"Fiumarella",
    "gn:population":44,
    "gn:timezone":"Europe/Rome",
    "iso:country":"IT",
    "wof:name":"Fiumarella",
    "wof:placetype":"locality",
    "wof:population":44
},
  "geometry": {"coordinates":[16.39494,39.05095],"type":"Point"}
}