{
  "type": "Feature",
  "properties": {
    "gn:admin1_code":"16.0",
    "gn:admin2_code":"FI",
    "gn:asciiname":"Casa Sabbatino",
    "gn:cc2":"IT",
    "gn:country_code":"IT",
    "gn:dem":808,
    "gn:feature_class":"P",
    "gn:feature_code":"PPL",
    "gn:name":"Casa Sabbatino",
    "gn:population":0,
    "gn:timezone":"Europe/Rome",
    "iso:country":"IT",
    "name:und_x_variant":[
        "Casale Sabbatino",
        "Casa Sabbatino"
    ],
    "wof:name":"Casa Sabbatino",
    "wof:placetype":"locality"
},
  "geometry": {"coordinates":[11.28333,44.16667],"type":"Point"}
}