{
  "type": "Feature",
  "properties": {
    "gn:admin1_code":"12",
    "gn:admin2_code":"CN",
    "gn:admin3_code":"4152.0",
    "gn:asciiname":"Fasana",
    "gn:country_code":"IT",
    "gn:dem":231,
    "gn:feature_class":"P",
    "gn:feature_code":"PPL",
    "gn:name":"Fasana",
    "gn:population":12,
    "gn:timezone":"Europe/Rome",
    "iso:country":"IT",
    "wof:name":"Fasana",
    "wof:placetype":"locality",
    "wof:population":12
},
  "geometry": {"coordinates":[7.90363,44.58487],"type":"Point"}
}