{
  "type": "Feature",
  "properties": {
    "gn:admin1_code":"17",
    "gn:admin2_code":"BZ",
    "gn:admin3_code":"21040.0",
    "gn:asciiname":"La Costa",
    "gn:country_code":"IT",
    "gn:dem":838,
    "gn:feature_class":"P",
    "gn:feature_code":"PPL",
    "gn:name":"La Costa",
    "gn:population":17,
    "gn:timezone":"Europe/Rome",
    "iso:country":"IT",
    "name:ara_x_preferred":[
        "\u0644\u0627 \u0643\u0648\u0633\u062a\u0627"
    ],
    "wof:name":"La Costa",
    "wof:placetype":"locality",
    "wof:population":17
},
  "geometry": {"coordinates":[11.35069,46.45746],"type":"Point"}
}