{
  "type": "Feature",
  "properties": {
    "gn:admin1_code":"5",
    "gn:admin2_code":"BO",
    "gn:admin3_code":"37055.0",
    "gn:asciiname":"Tombe",
    "gn:country_code":"IT",
    "gn:dem":10,
    "gn:feature_class":"P",
    "gn:feature_code":"PPL",
    "gn:name":"Tombe",
    "gn:population":80,
    "gn:timezone":"Europe/Rome",
    "iso:country":"IT",
    "wof:name":"Tombe",
    "wof:placetype":"locality",
    "wof:population":80
},
  "geometry": {"coordinates":[11.45018,44.71588],"type":"Point"}
}