{
  "type": "Feature",
  "properties": {
    "gn:admin1_code":"12.0",
    "gn:admin2_code":"AL",
    "gn:admin3_code":"6030.0",
    "gn:asciiname":"Zerbi",
    "gn:country_code":"IT",
    "gn:dem":139,
    "gn:feature_class":"P",
    "gn:feature_code":"PPL",
    "gn:name":"Zerbi",
    "gn:population":415,
    "gn:timezone":"Europe/Rome",
    "iso:country":"IT",
    "wof:name":"Zerbi",
    "wof:placetype":"locality",
    "wof:population":415
},
  "geometry": {"coordinates":[8.85562,44.85523],"type":"Point"}
}