{
  "type": "Feature",
  "properties": {
    "gn:admin1_code":"14.0",
    "gn:admin2_code":"OR",
    "gn:admin3_code":"95018.0",
    "gn:asciiname":"San Salvatore",
    "gn:country_code":"IT",
    "gn:dem":8,
    "gn:elevation":"6.0",
    "gn:feature_class":"P",
    "gn:feature_code":"PPL",
    "gn:name":"San Salvatore",
    "gn:population":2,
    "gn:timezone":"Europe/Rome",
    "iso:country":"IT",
    "wof:name":"San Salvatore",
    "wof:placetype":"locality",
    "wof:population":2
},
  "geometry": {"coordinates":[8.45197,39.92083],"type":"Point"}
}