{
  "type": "Feature",
  "properties": {
    "gn:admin1_code":"20",
    "gn:admin2_code":"PD",
    "gn:admin3_code":"28035.0",
    "gn:asciiname":"Castelletto",
    "gn:country_code":"IT",
    "gn:dem":2,
    "gn:feature_class":"P",
    "gn:feature_code":"PPL",
    "gn:name":"Castelletto",
    "gn:population":53,
    "gn:timezone":"Europe/Rome",
    "iso:country":"IT",
    "wof:name":"Castelletto",
    "wof:placetype":"locality",
    "wof:population":53
},
  "geometry": {"coordinates":[12.04579,45.21533],"type":"Point"}
}