{
  "type": "Feature",
  "properties": {
    "gn:admin1_code":"12",
    "gn:admin2_code":"NO",
    "gn:admin3_code":"3021.0",
    "gn:asciiname":"Montecchio",
    "gn:country_code":"IT",
    "gn:dem":287,
    "gn:feature_class":"P",
    "gn:feature_code":"PPL",
    "gn:name":"Montecchio",
    "gn:population":46,
    "gn:timezone":"Europe/Rome",
    "iso:country":"IT",
    "wof:name":"Montecchio",
    "wof:placetype":"locality",
    "wof:population":46
},
  "geometry": {"coordinates":[8.54771,45.65127],"type":"Point"}
}