{
  "type": "Feature",
  "properties": {
    "gn:admin1_code":"7",
    "gn:admin2_code":"LT",
    "gn:admin3_code":"59001.0",
    "gn:asciiname":"Campo del Fico-Sele",
    "gn:country_code":"IT",
    "gn:dem":41,
    "gn:feature_class":"P",
    "gn:feature_code":"PPL",
    "gn:name":"Campo del Fico-Sele",
    "gn:population":213,
    "gn:timezone":"Europe/Rome",
    "iso:country":"IT",
    "wof:name":"Campo del Fico-Sele",
    "wof:placetype":"locality",
    "wof:population":213
},
  "geometry": {"coordinates":[12.5626,41.60447],"type":"Point"}
}