{
  "type": "Feature",
  "properties": {
    "gn:admin1_code":"5",
    "gn:admin2_code":"PC",
    "gn:admin3_code":"33023.0",
    "gn:asciiname":"Molinazzo di Sotto",
    "gn:country_code":"IT",
    "gn:dem":105,
    "gn:feature_class":"P",
    "gn:feature_code":"PPL",
    "gn:name":"Molinazzo di Sotto",
    "gn:population":14,
    "gn:timezone":"Europe/Rome",
    "iso:country":"IT",
    "wof:name":"Molinazzo di Sotto",
    "wof:placetype":"locality",
    "wof:population":14
},
  "geometry": {"coordinates":[9.60427,44.97019],"type":"Point"}
}