{
  "type": "Feature",
  "properties": {
    "gn:admin1_code":"7",
    "gn:admin2_code":"FR",
    "gn:admin3_code":"60014.0",
    "gn:asciiname":"Bivio Papetti",
    "gn:country_code":"IT",
    "gn:dem":387,
    "gn:feature_class":"P",
    "gn:feature_code":"PPL",
    "gn:name":"Bivio Papetti",
    "gn:population":168,
    "gn:timezone":"Europe/Rome",
    "iso:country":"IT",
    "wof:name":"Bivio Papetti",
    "wof:placetype":"locality",
    "wof:population":168
},
  "geometry": {"coordinates":[13.46081,41.66925],"type":"Point"}
}