{
  "type": "Feature",
  "properties": {
    "gn:admin1_code":"5.0",
    "gn:admin2_code":"MO",
    "gn:admin3_code":"36037.0",
    "gn:asciiname":"Rivara",
    "gn:country_code":"IT",
    "gn:dem":19,
    "gn:feature_class":"P",
    "gn:feature_code":"PPL",
    "gn:name":"Rivara",
    "gn:population":759,
    "gn:timezone":"Europe/Rome",
    "iso:country":"IT",
    "name:azb_x_preferred":[
        "\u0631\u06cc\u0648\u0627\u0631\u0627"
    ],
    "name:bel_x_preferred":[
        "\u0420\u044b\u0432\u0430\u0440\u0430"
    ],
    "name:bul_x_preferred":[
        "\u0420\u0438\u0432\u0430\u0440\u0430"
    ],
    "name:ceb_x_preferred":[
        "Rivara"
    ],
    "name:deu_x_preferred":[
        "Rivara"
    ],
    "name:epo_x_preferred":[
        "Rivara"
    ],
    "name:eus_x_preferred":[
        "Rivara"
    ],
    "name:fas_x_preferred":[
        "\u0631\u06cc\u0648\u0627\u0631\u0627"
    ],
    "name:fra_x_preferred":[
        "Rivara"
    ],
    "name:hun_x_preferred":[
        "Rivara"
    ],
    "name:hye_x_preferred":[
        "\u054c\u056b\u057e\u0561\u0580\u0561"
    ],
    "name:ind_x_preferred":[
        "Rivara"
    ],
    "name:ita_x_preferred":[
        "Rivara"
    ],
    "name:jpn_x_preferred":[
        "\u30ea\u30f4\u30a1\u30fc\u30e9"
    ],
    "name:kaz_x_preferred":[
        "\u0420\u0438\u0432\u0430\u0440\u0430"
    ],
    "name:lat_x_preferred":[
        "Riparia"
    ],
    "name:lmo_x_preferred":[
        "Rivara"
    ],
    "name:msa_x_preferred":[
        "Rivara"
    ],
    "name:nap_x_preferred":[
        "Rivara"
    ],
    "name:nld_x_preferred":[
        "Rivara"
    ],
    "name:pms_x_preferred":[
        "Ruvera"
    ],
    "name:pol_x_preferred":[
        "Rivara"
    ],
    "name:por_x_preferred":[
        "Rivara"
    ],
    "name:ron_x_preferred":[
        "Rivara"
    ],
    "name:rus_x_preferred":[
        "\u0420\u0438\u0432\u0430\u0440\u0430"
    ],
    "name:scn_x_preferred":[
        "Rivara"
    ],
    "name:spa_x_preferred":[
        "Rivara"
    ],
    "name:srp_x_preferred":[
        "\u0420\u0438\u0432\u0430\u0440\u0430"
    ],
    "name:swe_x_preferred":[
        "Rivara"
    ],
    "name:tgl_x_preferred":[
        "Rivara"
    ],
    "name:ukr_x_preferred":[
        "\u0420\u0438\u0432\u0430\u0440\u0430"
    ],
    "name:uzb_x_preferred":[
        "Rivara"
    ],
    "name:vie_x_preferred":[
        "Rivara"
    ],
    "name:vol_x_preferred":[
        "Rivara"
    ],
    "name:war_x_preferred":[
        "Rivara"
    ],
    "name:zho_x_preferred":[
        "\u91cc\u74e6\u62c9"
    ],
    "wof:name":"Rivara",
    "wof:placetype":"locality",
    "wof:population":759
},
  "geometry": {"coordinates":[11.16947,44.84058],"type":"Point"}
}