{
  "type": "Feature",
  "properties": {
    "gn:admin1_code":"5.0",
    "gn:admin2_code":"MO",
    "gn:admin3_code":"36037.0",
    "gn:asciiname":"Rivara",
    "gn:country_code":"IT",
    "gn:dem":19,
    "gn:feature_class":"P",
    "gn:feature_code":"PPL",
    "gn:name":"Rivara",
    "gn:population":759,
    "gn:timezone":"Europe/Rome",
    "iso:country":"IT",
    "wof:name":"Rivara",
    "wof:placetype":"locality",
    "wof:population":759
},
  "geometry": {"coordinates":[11.16947,44.84058],"type":"Point"}
}