{
  "type": "Feature",
  "properties": {
    "gn:admin1_code":"5.0",
    "gn:admin2_code":"FE",
    "gn:admin3_code":"38008.0",
    "gn:asciiname":"Torre della Fossa",
    "gn:country_code":"IT",
    "gn:dem":8,
    "gn:feature_class":"P",
    "gn:feature_code":"PPL",
    "gn:name":"Torre della Fossa",
    "gn:population":430,
    "gn:timezone":"Europe/Rome",
    "iso:country":"IT",
    "wof:name":"Torre della Fossa",
    "wof:placetype":"locality",
    "wof:population":430
},
  "geometry": {"coordinates":[11.61858,44.79761],"type":"Point"}
}