{
  "type": "Feature",
  "properties": {
    "gn:admin1_code":"9",
    "gn:admin2_code":"VA",
    "gn:admin3_code":"12092.0",
    "gn:asciiname":"Brughiere",
    "gn:country_code":"IT",
    "gn:dem":327,
    "gn:feature_class":"P",
    "gn:feature_code":"PPL",
    "gn:name":"Brughiere",
    "gn:population":18,
    "gn:timezone":"Europe/Rome",
    "iso:country":"IT",
    "wof:name":"Brughiere",
    "wof:placetype":"locality",
    "wof:population":18
},
  "geometry": {"coordinates":[8.76924,45.99705],"type":"Point"}
}