{
  "type": "Feature",
  "properties": {
    "gn:admin1_code":"14.0",
    "gn:admin2_code":"NU",
    "gn:admin3_code":"91070.0",
    "gn:asciiname":"Area Piano Insediamenti Produttivi",
    "gn:country_code":"IT",
    "gn:dem":166,
    "gn:feature_class":"P",
    "gn:feature_code":"PPLL",
    "gn:name":"Area Piano Insediamenti Produttivi",
    "gn:population":0,
    "gn:timezone":"Europe/Rome",
    "iso:country":"IT",
    "wof:name":"Area Piano Insediamenti Produttivi",
    "wof:placetype":"locality"
},
  "geometry": {"coordinates":[9.01885,40.24167],"type":"Point"}
}