{
  "type": "Feature",
  "properties": {
    "gn:admin1_code":"16",
    "gn:admin2_code":"AR",
    "gn:admin3_code":"51005.0",
    "gn:asciiname":"Casa Caroni",
    "gn:country_code":"IT",
    "gn:dem":255,
    "gn:feature_class":"P",
    "gn:feature_code":"PPL",
    "gn:name":"Casa Caroni",
    "gn:population":24,
    "gn:timezone":"Europe/Rome",
    "iso:country":"IT",
    "wof:name":"Casa Caroni",
    "wof:placetype":"locality",
    "wof:population":24
},
  "geometry": {"coordinates":[11.60202,43.40536],"type":"Point"}
}