{
  "type": "Feature",
  "properties": {
    "gn:admin1_code":"12.0",
    "gn:admin2_code":"CN",
    "gn:admin3_code":"4218.0",
    "gn:asciiname":"Sorano",
    "gn:country_code":"IT",
    "gn:dem":302,
    "gn:elevation":"310.0",
    "gn:feature_class":"P",
    "gn:feature_code":"PPL",
    "gn:name":"Sorano",
    "gn:population":18,
    "gn:timezone":"Europe/Rome",
    "iso:country":"IT",
    "wof:name":"Sorano",
    "wof:placetype":"locality",
    "wof:population":18
},
  "geometry": {"coordinates":[7.99296,44.63289],"type":"Point"}
}