{
  "type": "Feature",
  "properties": {
    "gn:admin1_code":"12.0",
    "gn:admin2_code":"CN",
    "gn:admin3_code":"4218.0",
    "gn:asciiname":"Sorano",
    "gn:country_code":"IT",
    "gn:dem":302,
    "gn:elevation":"310.0",
    "gn:feature_class":"P",
    "gn:feature_code":"PPL",
    "gn:name":"Sorano",
    "gn:population":18,
    "gn:timezone":"Europe/Rome",
    "iso:country":"IT",
    "name:azb_x_preferred":[
        "\u0633\u0631\u0627\u0646\u0648"
    ],
    "name:bcl_x_preferred":[
        "Sorano"
    ],
    "name:bel_x_preferred":[
        "\u0421\u0430\u0440\u0430\u043d\u0430"
    ],
    "name:bul_x_preferred":[
        "\u0421\u043e\u0440\u0430\u043d\u043e"
    ],
    "name:cat_x_preferred":[
        "Sorano"
    ],
    "name:ceb_x_preferred":[
        "Sorano"
    ],
    "name:cos_x_preferred":[
        "Sorano"
    ],
    "name:deu_x_preferred":[
        "Sorano"
    ],
    "name:epo_x_preferred":[
        "Sorano"
    ],
    "name:est_x_preferred":[
        "Sorano"
    ],
    "name:eus_x_preferred":[
        "Sorano"
    ],
    "name:fas_x_preferred":[
        "\u0633\u0631\u0627\u0646\u0648"
    ],
    "name:fra_x_preferred":[
        "Sorano"
    ],
    "name:hun_x_preferred":[
        "Sorano"
    ],
    "name:hye_x_preferred":[
        "\u054d\u0578\u0580\u0561\u0576\u0578"
    ],
    "name:ita_x_preferred":[
        "Sorano"
    ],
    "name:jpn_x_preferred":[
        "\u30bd\u30e9\u30fc\u30ce"
    ],
    "name:kaz_x_preferred":[
        "\u0421\u043e\u0440\u0430\u043d\u043e"
    ],
    "name:kor_x_preferred":[
        "\uc18c\ub77c\ub178"
    ],
    "name:lat_x_preferred":[
        "Soranum"
    ],
    "name:lmo_x_preferred":[
        "Sorano"
    ],
    "name:msa_x_preferred":[
        "Sorano"
    ],
    "name:nap_x_preferred":[
        "Sorano"
    ],
    "name:nld_x_preferred":[
        "Sorano"
    ],
    "name:pms_x_preferred":[
        "Sorano"
    ],
    "name:pol_x_preferred":[
        "Sorano"
    ],
    "name:por_x_preferred":[
        "Sorano"
    ],
    "name:ron_x_preferred":[
        "Sorano"
    ],
    "name:rus_x_preferred":[
        "\u0421\u043e\u0440\u0430\u043d\u043e"
    ],
    "name:scn_x_preferred":[
        "Soranu"
    ],
    "name:spa_x_preferred":[
        "Sorano"
    ],
    "name:srp_x_preferred":[
        "\u0421\u043e\u0440\u0430\u043d\u043e"
    ],
    "name:tgl_x_preferred":[
        "Sorano"
    ],
    "name:ukr_x_preferred":[
        "\u0421\u043e\u0440\u0430\u043d\u043e"
    ],
    "name:uzb_x_preferred":[
        "Sorano"
    ],
    "name:vie_x_preferred":[
        "Sorano"
    ],
    "name:vol_x_preferred":[
        "Sorano"
    ],
    "name:war_x_preferred":[
        "Sorano"
    ],
    "name:zho_x_preferred":[
        "\u7d22\u62c9\u8bfa"
    ],
    "wof:name":"Sorano",
    "wof:placetype":"locality",
    "wof:population":18
},
  "geometry": {"coordinates":[7.99296,44.63289],"type":"Point"}
}