{
  "type": "Feature",
  "properties": {
    "gn:admin1_code":"20.0",
    "gn:admin2_code":"TV",
    "gn:admin3_code":"26071.0",
    "gn:asciiname":"Rovare",
    "gn:country_code":"IT",
    "gn:dem":8,
    "gn:elevation":"9.0",
    "gn:feature_class":"P",
    "gn:feature_code":"PPL",
    "gn:name":"Rovar\u00e8",
    "gn:population":526,
    "gn:timezone":"Europe/Rome",
    "iso:country":"IT",
    "wof:name":"Rovare",
    "wof:placetype":"locality",
    "wof:population":526
},
  "geometry": {"coordinates":[12.40414,45.67871],"type":"Point"}
}