{
  "type": "Feature",
  "properties": {
    "gn:admin1_code":"5.0",
    "gn:admin2_code":"MO",
    "gn:admin3_code":"36047.0",
    "gn:asciiname":"Dragodena",
    "gn:country_code":"IT",
    "gn:dem":689,
    "gn:feature_class":"P",
    "gn:feature_code":"PPL",
    "gn:name":"Dragodena",
    "gn:population":0,
    "gn:timezone":"Europe/Rome",
    "iso:country":"IT",
    "wof:name":"Dragodena",
    "wof:placetype":"locality"
},
  "geometry": {"coordinates":[11.03333,44.33333],"type":"Point"}
}