{
  "type": "Feature",
  "properties": {
    "gn:admin1_code":"12",
    "gn:admin2_code":"CN",
    "gn:admin3_code":"4092.0",
    "gn:asciiname":"Borgata Centrale",
    "gn:country_code":"IT",
    "gn:dem":804,
    "gn:feature_class":"P",
    "gn:feature_code":"PPLL",
    "gn:name":"Borgata Centrale",
    "gn:population":7,
    "gn:timezone":"Europe/Rome",
    "iso:country":"IT",
    "wof:name":"Borgata Centrale",
    "wof:placetype":"locality",
    "wof:population":7
},
  "geometry": {"coordinates":[7.25318,44.57056],"type":"Point"}
}