{
  "type": "Feature",
  "properties": {
    "gn:admin1_code":"18.0",
    "gn:admin2_code":"PG",
    "gn:admin3_code":"54001.0",
    "gn:asciiname":"Sterpeto",
    "gn:country_code":"IT",
    "gn:dem":342,
    "gn:elevation":"344.0",
    "gn:feature_class":"P",
    "gn:feature_code":"PPL",
    "gn:name":"Sterpeto",
    "gn:population":45,
    "gn:timezone":"Europe/Rome",
    "iso:country":"IT",
    "name:ceb_x_preferred":[
        "Sterpeto"
    ],
    "name:srp_x_preferred":[
        "\u0421\u0442\u0435\u0440\u043f\u0435\u0442\u043e"
    ],
    "wof:name":"Sterpeto",
    "wof:placetype":"locality",
    "wof:population":45
},
  "geometry": {"coordinates":[12.55423,43.11336],"type":"Point"}
}