{
  "type": "Feature",
  "properties": {
    "gn:admin1_code":"3.0",
    "gn:admin2_code":"CS",
    "gn:admin3_code":"78074.0",
    "gn:asciiname":"Stazione di Mandatoriccio",
    "gn:country_code":"IT",
    "gn:dem":18,
    "gn:feature_class":"P",
    "gn:feature_code":"PPL",
    "gn:name":"Stazione di Mandatoriccio",
    "gn:population":311,
    "gn:timezone":"Europe/Rome",
    "iso:country":"IT",
    "wof:name":"Stazione di Mandatoriccio",
    "wof:placetype":"locality",
    "wof:population":311
},
  "geometry": {"coordinates":[16.88621,39.52718],"type":"Point"}
}