{
  "type": "Feature",
  "properties": {
    "gn:admin1_code":"4",
    "gn:admin2_code":"AV",
    "gn:admin3_code":"64073.0",
    "gn:asciiname":"Paradisi",
    "gn:country_code":"IT",
    "gn:dem":344,
    "gn:feature_class":"P",
    "gn:feature_code":"PPL",
    "gn:name":"Paradisi",
    "gn:population":16,
    "gn:timezone":"Europe/Rome",
    "iso:country":"IT",
    "name:deu_x_preferred":[
        "Paradisi"
    ],
    "name:fra_x_preferred":[
        "Paradisi"
    ],
    "name:ita_x_preferred":[
        "Paradisi"
    ],
    "wof:name":"Paradisi",
    "wof:placetype":"locality",
    "wof:population":16
},
  "geometry": {"coordinates":[14.74286,41.01131],"type":"Point"}
}