{
  "type": "Feature",
  "properties": {
    "gn:admin1_code":"16",
    "gn:admin2_code":"AR",
    "gn:admin3_code":"51012.0",
    "gn:asciiname":"Santa Margherita",
    "gn:country_code":"IT",
    "gn:dem":297,
    "gn:feature_class":"P",
    "gn:feature_code":"PPL",
    "gn:name":"Santa Margherita",
    "gn:population":39,
    "gn:timezone":"Europe/Rome",
    "iso:country":"IT",
    "wof:name":"Santa Margherita",
    "wof:placetype":"locality",
    "wof:population":39
},
  "geometry": {"coordinates":[11.96203,43.35485],"type":"Point"}
}