{
  "type": "Feature",
  "properties": {
    "gn:admin1_code":"9.0",
    "gn:admin2_code":"CR",
    "gn:admin3_code":"19046.0",
    "gn:asciiname":"Pieve Delmona",
    "gn:country_code":"IT",
    "gn:dem":45,
    "gn:feature_class":"P",
    "gn:feature_code":"PPL",
    "gn:name":"Pieve Delmona",
    "gn:population":394,
    "gn:timezone":"Europe/Rome",
    "iso:country":"IT",
    "wof:name":"Pieve Delmona",
    "wof:placetype":"locality",
    "wof:population":394
},
  "geometry": {"coordinates":[10.12737,45.16654000000001],"type":"Point"}
}