{
  "type": "Feature",
  "properties": {
    "gn:admin1_code":"5",
    "gn:admin2_code":"RE",
    "gn:admin3_code":"35029.0",
    "gn:asciiname":"Case Molinara",
    "gn:country_code":"IT",
    "gn:dem":23,
    "gn:feature_class":"P",
    "gn:feature_code":"PPL",
    "gn:name":"Case Molinara",
    "gn:population":49,
    "gn:timezone":"Europe/Rome",
    "iso:country":"IT",
    "wof:name":"Case Molinara",
    "wof:placetype":"locality",
    "wof:population":49
},
  "geometry": {"coordinates":[10.55223,44.86258],"type":"Point"}
}