{
  "type": "Feature",
  "properties": {
    "gn:admin1_code":"9",
    "gn:admin2_code":"BG",
    "gn:admin3_code":"16202.0",
    "gn:asciiname":"Lacsolo",
    "gn:country_code":"IT",
    "gn:dem":328,
    "gn:feature_class":"P",
    "gn:feature_code":"PPL",
    "gn:name":"Lacsolo",
    "gn:population":37,
    "gn:timezone":"Europe/Rome",
    "iso:country":"IT",
    "wof:name":"Lacsolo",
    "wof:placetype":"locality",
    "wof:population":37
},
  "geometry": {"coordinates":[9.64179,45.7408],"type":"Point"}
}