{
  "type": "Feature",
  "properties": {
    "gn:admin1_code":"9",
    "gn:admin2_code":"CR",
    "gn:admin3_code":"19103.0",
    "gn:asciiname":"Straconcolo",
    "gn:country_code":"IT",
    "gn:dem":34,
    "gn:feature_class":"P",
    "gn:feature_code":"PPL",
    "gn:name":"Straconcolo",
    "gn:population":14,
    "gn:timezone":"Europe/Rome",
    "iso:country":"IT",
    "wof:name":"Straconcolo",
    "wof:placetype":"locality",
    "wof:population":14
},
  "geometry": {"coordinates":[10.10567,45.07073],"type":"Point"}
}