{
  "type": "Feature",
  "properties": {
    "gn:admin1_code":"20",
    "gn:admin2_code":"VE",
    "gn:admin3_code":"27021.0",
    "gn:asciiname":"Zigaraga I",
    "gn:country_code":"IT",
    "gn:dem":5,
    "gn:feature_class":"P",
    "gn:feature_code":"PPL",
    "gn:name":"Zigaraga I",
    "gn:population":57,
    "gn:timezone":"Europe/Rome",
    "iso:country":"IT",
    "wof:name":"Zigaraga I",
    "wof:placetype":"locality",
    "wof:population":57
},
  "geometry": {"coordinates":[12.13806,45.51608],"type":"Point"}
}