{
  "type": "Feature",
  "properties": {
    "gn:admin1_code":"3.0",
    "gn:admin2_code":"RC",
    "gn:admin3_code":"80065.0",
    "gn:asciiname":"Pomari",
    "gn:country_code":"IT",
    "gn:dem":75,
    "gn:feature_class":"P",
    "gn:feature_code":"PPL",
    "gn:name":"Pomari",
    "gn:population":0,
    "gn:timezone":"Europe/Rome",
    "iso:country":"IT",
    "wof:name":"Pomari",
    "wof:placetype":"locality"
},
  "geometry": {"coordinates":[15.96667,38.43333],"type":"Point"}
}