{
  "type": "Feature",
  "properties": {
    "gn:admin1_code":"20.0",
    "gn:admin2_code":"BL",
    "gn:admin3_code":"25006.0",
    "gn:asciiname":"Caleipa",
    "gn:country_code":"IT",
    "gn:dem":437,
    "gn:feature_class":"P",
    "gn:feature_code":"PPL",
    "gn:name":"Cal\u00e8ipa",
    "gn:population":0,
    "gn:timezone":"Europe/Rome",
    "iso:country":"IT",
    "name:eng_x_preferred":[
        "Caleipo"
    ],
    "name:eng_x_variant":[
        "Caleipa"
    ],
    "wof:name":"Caleipo",
    "wof:placetype":"locality"
},
  "geometry": {"coordinates":[12.2475,46.12611],"type":"Point"}
}