{
  "type": "Feature",
  "properties": {
    "gn:admin1_code":"15",
    "gn:admin2_code":"PA",
    "gn:admin3_code":"82055.0",
    "gn:asciiname":"Miranti",
    "gn:country_code":"IT",
    "gn:dem":912,
    "gn:feature_class":"P",
    "gn:feature_code":"PPL",
    "gn:name":"Miranti",
    "gn:population":20,
    "gn:timezone":"Europe/Rome",
    "iso:country":"IT",
    "wof:name":"Miranti",
    "wof:placetype":"locality",
    "wof:population":20
},
  "geometry": {"coordinates":[14.14655,37.81371],"type":"Point"}
}