{
  "type": "Feature",
  "properties": {
    "gn:admin1_code":"20",
    "gn:admin2_code":"TV",
    "gn:admin3_code":"26028.0",
    "gn:asciiname":"Nucleo Casette",
    "gn:country_code":"IT",
    "gn:dem":14,
    "gn:feature_class":"P",
    "gn:feature_code":"PPL",
    "gn:name":"Nucleo Casette",
    "gn:population":47,
    "gn:timezone":"Europe/Rome",
    "iso:country":"IT",
    "wof:name":"Nucleo Casette",
    "wof:placetype":"locality",
    "wof:population":47
},
  "geometry": {"coordinates":[12.47967,45.8199],"type":"Point"}
}