{
  "type": "Feature",
  "properties": {
    "gn:admin1_code":"12",
    "gn:admin2_code":"CN",
    "gn:admin3_code":"4140.0",
    "gn:asciiname":"Occhetti",
    "gn:country_code":"IT",
    "gn:dem":264,
    "gn:feature_class":"P",
    "gn:feature_code":"PPL",
    "gn:name":"Occhetti",
    "gn:population":83,
    "gn:timezone":"Europe/Rome",
    "iso:country":"IT",
    "wof:name":"Occhetti",
    "wof:placetype":"locality",
    "wof:population":83
},
  "geometry": {"coordinates":[7.95888,44.76626],"type":"Point"}
}