{
  "type": "Feature",
  "properties": {
    "gn:admin1_code":"9",
    "gn:admin2_code":"MN",
    "gn:admin3_code":"20016.0",
    "gn:asciiname":"Gaffuro",
    "gn:country_code":"IT",
    "gn:dem":31,
    "gn:feature_class":"P",
    "gn:feature_code":"PPL",
    "gn:name":"Gaffuro",
    "gn:population":61,
    "gn:timezone":"Europe/Rome",
    "iso:country":"IT",
    "wof:name":"Gaffuro",
    "wof:placetype":"locality",
    "wof:population":61
},
  "geometry": {"coordinates":[10.60526,45.16902],"type":"Point"}
}