{
  "type": "Feature",
  "properties": {
    "gn:admin1_code":"12",
    "gn:admin2_code":"CN",
    "gn:admin3_code":"4215.0",
    "gn:asciiname":"Rigrasso",
    "gn:country_code":"IT",
    "gn:dem":314,
    "gn:feature_class":"P",
    "gn:feature_code":"PPL",
    "gn:name":"Rigrasso",
    "gn:population":54,
    "gn:timezone":"Europe/Rome",
    "iso:country":"IT",
    "wof:name":"Rigrasso",
    "wof:placetype":"locality",
    "wof:population":54
},
  "geometry": {"coordinates":[7.60355,44.65705],"type":"Point"}
}