{
  "type": "Feature",
  "properties": {
    "gn:admin1_code":"9",
    "gn:admin2_code":"MI",
    "gn:admin3_code":"15062.0",
    "gn:asciiname":"Arese",
    "gn:country_code":"IT",
    "gn:dem":173,
    "gn:feature_class":"P",
    "gn:feature_code":"PPL",
    "gn:name":"Arese",
    "gn:population":25,
    "gn:timezone":"Europe/Rome",
    "iso:country":"IT",
    "wof:name":"Arese",
    "wof:placetype":"locality",
    "wof:population":25
},
  "geometry": {"coordinates":[8.76251,45.53786],"type":"Point"}
}