{
  "type": "Feature",
  "properties": {
    "gn:admin1_code":"9",
    "gn:admin2_code":"MI",
    "gn:admin3_code":"15062.0",
    "gn:asciiname":"Arese",
    "gn:country_code":"IT",
    "gn:dem":173,
    "gn:feature_class":"P",
    "gn:feature_code":"PPL",
    "gn:name":"Arese",
    "gn:population":25,
    "gn:timezone":"Europe/Rome",
    "iso:country":"IT",
    "name:ara_x_preferred":[
        "\u0623\u0631\u064a\u0633\u064a"
    ],
    "name:azb_x_preferred":[
        "\u0622\u0631\u0632\u0647"
    ],
    "name:bul_x_preferred":[
        "\u0410\u0440\u0435\u0437\u0435"
    ],
    "name:ceb_x_preferred":[
        "Arese"
    ],
    "name:deu_x_preferred":[
        "Arese"
    ],
    "name:epo_x_preferred":[
        "Arese"
    ],
    "name:eus_x_preferred":[
        "Arese"
    ],
    "name:fas_x_preferred":[
        "\u0622\u0631\u0632\u0647"
    ],
    "name:fra_x_preferred":[
        "Arese"
    ],
    "name:hun_x_preferred":[
        "Arese"
    ],
    "name:hye_x_preferred":[
        "\u0531\u0580\u0565\u0566\u0565"
    ],
    "name:ita_x_preferred":[
        "Arese"
    ],
    "name:jpn_x_preferred":[
        "\u30a2\u30ec\u30fc\u30bc"
    ],
    "name:kor_x_preferred":[
        "\uc544\ub808\uc138"
    ],
    "name:lat_x_preferred":[
        "Aresium"
    ],
    "name:lmo_x_preferred":[
        "Ares"
    ],
    "name:msa_x_preferred":[
        "Arese"
    ],
    "name:nap_x_preferred":[
        "Arese"
    ],
    "name:nld_x_preferred":[
        "Arese"
    ],
    "name:pms_x_preferred":[
        "Arese"
    ],
    "name:pol_x_preferred":[
        "Arese"
    ],
    "name:por_x_preferred":[
        "Arese"
    ],
    "name:ron_x_preferred":[
        "Arese"
    ],
    "name:rus_x_preferred":[
        "\u0410\u0440\u0435\u0437\u0435"
    ],
    "name:scn_x_preferred":[
        "Arese"
    ],
    "name:slk_x_preferred":[
        "Arese"
    ],
    "name:spa_x_preferred":[
        "Arese"
    ],
    "name:srp_x_preferred":[
        "\u0410\u0440\u0435\u0437\u0435"
    ],
    "name:swe_x_preferred":[
        "Arese"
    ],
    "name:tgl_x_preferred":[
        "Arese"
    ],
    "name:tur_x_preferred":[
        "Arese"
    ],
    "name:ukr_x_preferred":[
        "\u0410\u0440\u0435\u0437\u0435"
    ],
    "name:vie_x_preferred":[
        "Arese"
    ],
    "name:vol_x_preferred":[
        "Arese"
    ],
    "name:war_x_preferred":[
        "Arese"
    ],
    "name:zho_x_preferred":[
        "\u963f\u96f7\u585e"
    ],
    "wof:name":"Arese",
    "wof:placetype":"locality",
    "wof:population":25
},
  "geometry": {"coordinates":[8.76251,45.53786],"type":"Point"}
}