{
  "type": "Feature",
  "properties": {
    "gn:admin1_code":"20",
    "gn:admin2_code":"VI",
    "gn:admin3_code":"24100.0",
    "gn:asciiname":"Corobolli",
    "gn:country_code":"IT",
    "gn:dem":426,
    "gn:feature_class":"P",
    "gn:feature_code":"PPL",
    "gn:name":"Corobolli",
    "gn:population":40,
    "gn:timezone":"Europe/Rome",
    "iso:country":"IT",
    "wof:name":"Corobolli",
    "wof:placetype":"locality",
    "wof:population":40
},
  "geometry": {"coordinates":[11.31812,45.73094],"type":"Point"}
}