{
  "type": "Feature",
  "properties": {
    "gn:elevation":225,
    "gn:population":587,
    "iso:country":"IT",
    "name:cat_x_preferred":[
        "Pozzillo"
    ],
    "name:ceb_x_preferred":[
        "Pozzillo"
    ],
    "name:ces_x_preferred":[
        "Pozzillo"
    ],
    "name:dan_x_preferred":[
        "Pozzillo"
    ],
    "name:eng_x_preferred":[
        "Pozzillo"
    ],
    "name:eus_x_preferred":[
        "Pozzillo"
    ],
    "name:fin_x_preferred":[
        "Pozzillo"
    ],
    "name:fra_x_preferred":[
        "Pozzillo"
    ],
    "name:ind_x_preferred":[
        "Pozzillo"
    ],
    "name:ita_x_preferred":[
        "Pozzillo"
    ],
    "name:nld_x_preferred":[
        "Pozzillo"
    ],
    "name:nno_x_preferred":[
        "Pozzillo"
    ],
    "name:nob_x_preferred":[
        "Pozzillo"
    ],
    "name:oci_x_preferred":[
        "Pozzillo"
    ],
    "name:pol_x_preferred":[
        "Pozzillo"
    ],
    "name:por_x_preferred":[
        "Pozzillo"
    ],
    "name:ron_x_preferred":[
        "Pozzillo"
    ],
    "name:slk_x_preferred":[
        "Pozzillo"
    ],
    "name:slv_x_preferred":[
        "Pozzillo"
    ],
    "name:spa_x_preferred":[
        "Pozzillo"
    ],
    "name:srp_x_preferred":[
        "Pozzillo"
    ],
    "name:swe_x_preferred":[
        "Pozzillo"
    ],
    "name:tgl_x_preferred":[
        "Pozzillo"
    ],
    "name:tur_x_preferred":[
        "Pozzillo"
    ],
    "name:unk_x_variant":[
        "Casa Pozzillo"
    ],
    "name:war_x_preferred":[
        "Pozzillo"
    ],
    "qs:a0":"Italia",
    "qs:a1":"*Caserta",
    "qs:a1r":"0Campania",
    "qs:adm0":"Italia",
    "qs:la_lc":"*",
    "qs:level":"locality",
    "qs:loc":"Pozzillo",
    "qs:loc_alt":"Pozzillo",
    "qs:pop":0,
    "qs:type":"buffered point",
    "wof:lang":[
        "ita"
    ],
    "wof:name":"Pozzillo",
    "wof:placetype":"locality",
    "wof:population":587
},
  "geometry": {"coordinates":[14.194529,41.202358],"type":"Point"}
}