{
  "type": "Feature",
  "properties": {
    "gn:admin1_code":"16",
    "gn:admin2_code":"PI",
    "gn:admin3_code":"50008.0",
    "gn:asciiname":"La Gronchia",
    "gn:country_code":"IT",
    "gn:dem":5,
    "gn:feature_class":"P",
    "gn:feature_code":"PPL",
    "gn:name":"La Gronchia",
    "gn:population":20,
    "gn:timezone":"Europe/Rome",
    "iso:country":"IT",
    "wof:name":"La Gronchia",
    "wof:placetype":"locality",
    "wof:population":20
},
  "geometry": {"coordinates":[10.53342,43.65607],"type":"Point"}
}