{
  "type": "Feature",
  "properties": {
    "gn:admin1_code":"5",
    "gn:admin2_code":"PC",
    "gn:admin3_code":"33019.0",
    "gn:asciiname":"Casetta",
    "gn:country_code":"IT",
    "gn:dem":765,
    "gn:feature_class":"P",
    "gn:feature_code":"PPLL",
    "gn:name":"Casetta",
    "gn:population":7,
    "gn:timezone":"Europe/Rome",
    "iso:country":"IT",
    "wof:name":"Casetta",
    "wof:placetype":"locality",
    "wof:population":7
},
  "geometry": {"coordinates":[9.61754,44.66796],"type":"Point"}
}