{
  "type": "Feature",
  "properties": {
    "gn:admin1_code":"20.0",
    "gn:admin2_code":"VR",
    "gn:admin3_code":"23085.0",
    "gn:asciiname":"Nichesola",
    "gn:country_code":"IT",
    "gn:dem":11,
    "gn:elevation":"13.0",
    "gn:feature_class":"P",
    "gn:feature_code":"PPL",
    "gn:name":"Nichesola",
    "gn:population":139,
    "gn:timezone":"Europe/Rome",
    "iso:country":"IT",
    "wof:name":"Nichesola",
    "wof:placetype":"locality",
    "wof:population":139
},
  "geometry": {"coordinates":[11.36696,45.16733],"type":"Point"}
}