{
  "type": "Feature",
  "properties": {
    "gn:admin1_code":"20",
    "gn:admin2_code":"VI",
    "gn:admin3_code":"24115.0",
    "gn:asciiname":"Maso",
    "gn:country_code":"IT",
    "gn:dem":470,
    "gn:feature_class":"P",
    "gn:feature_code":"PPL",
    "gn:name":"Maso",
    "gn:population":51,
    "gn:timezone":"Europe/Rome",
    "iso:country":"IT",
    "name:bul_x_preferred":[
        "\u041c\u0430\u0437\u043e\u043d"
    ],
    "name:ceb_x_preferred":[
        "Maso"
    ],
    "name:deu_x_preferred":[
        "Maso"
    ],
    "name:fra_x_preferred":[
        "Maso"
    ],
    "name:ita_x_preferred":[
        "Maso"
    ],
    "name:rus_x_preferred":[
        "\u041c\u0430\u0441\u043e"
    ],
    "name:spa_x_preferred":[
        "Maso"
    ],
    "name:srp_x_preferred":[
        "Maso"
    ],
    "name:swe_x_preferred":[
        "Maso"
    ],
    "wof:name":"Maso",
    "wof:placetype":"locality",
    "wof:population":51
},
  "geometry": {"coordinates":[11.34326,45.79293],"type":"Point"}
}