{
  "type": "Feature",
  "properties": {
    "gn:admin1_code":"7",
    "gn:admin2_code":"VT",
    "gn:admin3_code":"56022.0",
    "gn:asciiname":"Campo del Pero",
    "gn:country_code":"IT",
    "gn:dem":103,
    "gn:feature_class":"P",
    "gn:feature_code":"PPL",
    "gn:name":"Campo del Pero",
    "gn:population":29,
    "gn:timezone":"Europe/Rome",
    "iso:country":"IT",
    "wof:name":"Campo del Pero",
    "wof:placetype":"locality",
    "wof:population":29
},
  "geometry": {"coordinates":[12.22793,42.61539000000001],"type":"Point"}
}