{
  "type": "Feature",
  "properties": {
    "gn:admin1_code":"5.0",
    "gn:admin2_code":"FE",
    "gn:admin3_code":"38006.0",
    "gn:asciiname":"Casone Caldirolo",
    "gn:country_code":"IT",
    "gn:dem":-3,
    "gn:feature_class":"P",
    "gn:feature_code":"PPL",
    "gn:name":"Casone Caldirolo",
    "gn:population":0,
    "gn:timezone":"Europe/Rome",
    "iso:country":"IT",
    "wof:name":"Casone Caldirolo",
    "wof:placetype":"locality"
},
  "geometry": {"coordinates":[12.13889,44.64611],"type":"Point"}
}