{
  "type": "Feature",
  "properties": {
    "gn:admin1_code":"16",
    "gn:admin2_code":"LU",
    "gn:admin3_code":"46010.0",
    "gn:asciiname":"Isola",
    "gn:country_code":"IT",
    "gn:dem":623,
    "gn:feature_class":"P",
    "gn:feature_code":"PPL",
    "gn:name":"Isola",
    "gn:population":22,
    "gn:timezone":"Europe/Rome",
    "iso:country":"IT",
    "wof:name":"Isola",
    "wof:placetype":"locality",
    "wof:population":22
},
  "geometry": {"coordinates":[10.42773,44.17231],"type":"Point"}
}