{
  "type": "Feature",
  "properties": {
    "gn:admin1_code":"20",
    "gn:admin2_code":"TV",
    "gn:admin3_code":"26006.0",
    "gn:asciiname":"Don Minzoni",
    "gn:country_code":"IT",
    "gn:dem":96,
    "gn:feature_class":"P",
    "gn:feature_code":"PPL",
    "gn:name":"Don Minzoni",
    "gn:population":20,
    "gn:timezone":"Europe/Rome",
    "iso:country":"IT",
    "wof:name":"Don Minzoni",
    "wof:placetype":"locality",
    "wof:population":20
},
  "geometry": {"coordinates":[11.9976,45.76355],"type":"Point"}
}