{
  "type": "Feature",
  "properties": {
    "gn:admin1_code":"20",
    "gn:admin2_code":"VE",
    "gn:admin3_code":"27009.0",
    "gn:asciiname":"San Gaetano",
    "gn:country_code":"IT",
    "gn:dem":8,
    "gn:feature_class":"P",
    "gn:feature_code":"PPL",
    "gn:name":"San Gaetano",
    "gn:population":45,
    "gn:timezone":"Europe/Rome",
    "iso:country":"IT",
    "wof:name":"San Gaetano",
    "wof:placetype":"locality",
    "wof:population":45
},
  "geometry": {"coordinates":[12.78438,45.81028],"type":"Point"}
}