{
  "type": "Feature",
  "properties": {
    "gn:admin1_code":"2.0",
    "gn:admin2_code":"PZ",
    "gn:admin3_code":"76042.0",
    "gn:asciiname":"Tempone Seluci",
    "gn:country_code":"IT",
    "gn:dem":905,
    "gn:feature_class":"P",
    "gn:feature_code":"PPL",
    "gn:name":"Tempone Seluci",
    "gn:population":145,
    "gn:timezone":"Europe/Rome",
    "iso:country":"IT",
    "wof:name":"Tempone Seluci",
    "wof:placetype":"locality",
    "wof:population":145
},
  "geometry": {"coordinates":[15.96824,40.0595],"type":"Point"}
}