{
  "type": "Feature",
  "properties": {
    "gn:admin1_code":"16",
    "gn:admin2_code":"MS",
    "gn:admin3_code":"45002.0",
    "gn:asciiname":"Collesino",
    "gn:country_code":"IT",
    "gn:dem":716,
    "gn:feature_class":"P",
    "gn:feature_code":"PPL",
    "gn:name":"Collesino",
    "gn:population":22,
    "gn:timezone":"Europe/Rome",
    "iso:country":"IT",
    "wof:name":"Collesino",
    "wof:placetype":"locality",
    "wof:population":22
},
  "geometry": {"coordinates":[10.04225,44.31726],"type":"Point"}
}