{
  "type": "Feature",
  "properties": {
    "gn:admin1_code":"4.0",
    "gn:admin2_code":"BN",
    "gn:admin3_code":"62005.0",
    "gn:asciiname":"Via Appia Ovest",
    "gn:country_code":"IT",
    "gn:dem":218,
    "gn:feature_class":"P",
    "gn:feature_code":"PPL",
    "gn:name":"Via Appia Ovest",
    "gn:population":48,
    "gn:timezone":"Europe/Rome",
    "iso:country":"IT",
    "wof:name":"Via Appia Ovest",
    "wof:placetype":"locality",
    "wof:population":48
},
  "geometry": {"coordinates":[14.53268,41.03609],"type":"Point"}
}