{
  "type": "Feature",
  "properties": {
    "gn:admin1_code":"9",
    "gn:admin2_code":"LO",
    "gn:admin3_code":"98039.0",
    "gn:asciiname":"Marzano",
    "gn:country_code":"IT",
    "gn:dem":95,
    "gn:feature_class":"P",
    "gn:feature_code":"PPL",
    "gn:name":"Marzano",
    "gn:population":339,
    "gn:timezone":"Europe/Rome",
    "iso:country":"IT",
    "wof:name":"Marzano",
    "wof:placetype":"locality",
    "wof:population":339
},
  "geometry": {"coordinates":[9.44288,45.42553],"type":"Point"}
}