{
  "type": "Feature",
  "properties": {
    "gn:admin1_code":"9",
    "gn:admin2_code":"LO",
    "gn:admin3_code":"98039.0",
    "gn:asciiname":"Marzano",
    "gn:country_code":"IT",
    "gn:dem":95,
    "gn:feature_class":"P",
    "gn:feature_code":"PPL",
    "gn:name":"Marzano",
    "gn:population":339,
    "gn:timezone":"Europe/Rome",
    "iso:country":"IT",
    "name:ara_x_preferred":[
        "\u0645\u0627\u0631\u0632\u0627\u0646\u0648"
    ],
    "name:azb_x_preferred":[
        "\u0645\u0627\u0631\u0632\u0627\u0646\u0648"
    ],
    "name:bel_x_preferred":[
        "\u041c\u0430\u0440\u0446\u0430\u043d\u0430"
    ],
    "name:bul_x_preferred":[
        "\u041c\u0430\u0440\u0446\u0430\u043d\u043e"
    ],
    "name:ceb_x_preferred":[
        "Marzano"
    ],
    "name:ces_x_preferred":[
        "Marzano"
    ],
    "name:deu_x_preferred":[
        "Marzano"
    ],
    "name:epo_x_preferred":[
        "Marzano"
    ],
    "name:eus_x_preferred":[
        "Marzano"
    ],
    "name:fas_x_preferred":[
        "\u0645\u0627\u0631\u0632\u0627\u0646\u0648"
    ],
    "name:fra_x_preferred":[
        "Marzano"
    ],
    "name:hun_x_preferred":[
        "Marzano"
    ],
    "name:hye_x_preferred":[
        "\u0544\u0561\u0580\u0581\u0561\u0576\u0578"
    ],
    "name:ita_x_preferred":[
        "Marzano"
    ],
    "name:jpn_x_preferred":[
        "\u30de\u30eb\u30c4\u30a1\u30fc\u30ce"
    ],
    "name:kaz_x_preferred":[
        "\u041c\u0430\u0440\u0446\u0430\u043d\u043e"
    ],
    "name:lat_x_preferred":[
        "Marcianum"
    ],
    "name:lmo_x_preferred":[
        "Mars\u00e4n"
    ],
    "name:msa_x_preferred":[
        "Marzano"
    ],
    "name:nap_x_preferred":[
        "Marzano"
    ],
    "name:nld_x_preferred":[
        "Marzano"
    ],
    "name:pms_x_preferred":[
        "Marzano"
    ],
    "name:pol_x_preferred":[
        "Marzano"
    ],
    "name:por_x_preferred":[
        "Marzano"
    ],
    "name:ron_x_preferred":[
        "Marzano"
    ],
    "name:rus_x_preferred":[
        "\u041c\u0430\u0440\u0446\u0430\u043d\u043e"
    ],
    "name:scn_x_preferred":[
        "Marzano"
    ],
    "name:spa_x_preferred":[
        "Marzano"
    ],
    "name:srp_x_preferred":[
        "\u041c\u0430\u0440\u0446\u0430\u043d\u043e"
    ],
    "name:tgl_x_preferred":[
        "Marzano"
    ],
    "name:ukr_x_preferred":[
        "\u041c\u0430\u0440\u0446\u0430\u043d\u043e"
    ],
    "name:uzb_x_preferred":[
        "Marzano"
    ],
    "name:vie_x_preferred":[
        "Marzano"
    ],
    "name:vol_x_preferred":[
        "Marzano"
    ],
    "name:war_x_preferred":[
        "Marzano"
    ],
    "name:zho_x_preferred":[
        "\u9a6c\u5c14\u624e\u8bfa"
    ],
    "wof:name":"Marzano",
    "wof:placetype":"locality",
    "wof:population":339
},
  "geometry": {"coordinates":[9.44288,45.42553],"type":"Point"}
}