{
  "type": "Feature",
  "properties": {
    "gn:admin1_code":"12.0",
    "gn:admin2_code":"CN",
    "gn:admin3_code":"4018.0",
    "gn:asciiname":"Regione Rossi",
    "gn:country_code":"IT",
    "gn:dem":629,
    "gn:feature_class":"P",
    "gn:feature_code":"PPLL",
    "gn:name":"Regione Rossi",
    "gn:population":4,
    "gn:timezone":"Europe/Rome",
    "iso:country":"IT",
    "wof:name":"Regione Rossi",
    "wof:placetype":"locality",
    "wof:population":4
},
  "geometry": {"coordinates":[7.97919,44.49152],"type":"Point"}
}