{
  "type": "Feature",
  "properties": {
    "gn:admin1_code":"6.0",
    "gn:admin2_code":"TS",
    "gn:admin3_code":"32006.0",
    "gn:asciiname":"Farneto",
    "gn:country_code":"IT",
    "gn:dem":113,
    "gn:feature_class":"P",
    "gn:feature_code":"PPLL",
    "gn:name":"Farneto",
    "gn:population":0,
    "gn:timezone":"Europe/Rome",
    "iso:country":"IT",
    "wof:name":"Farneto",
    "wof:placetype":"locality"
},
  "geometry": {"coordinates":[13.80814,45.6517],"type":"Point"}
}