{
  "type": "Feature",
  "properties": {
    "gn:admin1_code":"3",
    "gn:admin2_code":"RC",
    "gn:admin3_code":"80097.0",
    "gn:asciiname":"Pineta",
    "gn:country_code":"IT",
    "gn:dem":7,
    "gn:feature_class":"P",
    "gn:feature_code":"PPLL",
    "gn:name":"Pineta",
    "gn:population":8,
    "gn:timezone":"Europe/Rome",
    "iso:country":"IT",
    "wof:name":"Pineta",
    "wof:placetype":"locality",
    "wof:population":8
},
  "geometry": {"coordinates":[15.91925,38.50186],"type":"Point"}
}