{
  "type": "Feature",
  "properties": {
    "gn:admin1_code":"12",
    "gn:admin2_code":"BI",
    "gn:admin3_code":"96079.0",
    "gn:asciiname":"Cascina Grangia",
    "gn:country_code":"IT",
    "gn:dem":204,
    "gn:feature_class":"P",
    "gn:feature_code":"PPL",
    "gn:name":"Cascina Grangia",
    "gn:population":14,
    "gn:timezone":"Europe/Rome",
    "iso:country":"IT",
    "wof:name":"Cascina Grangia",
    "wof:placetype":"locality",
    "wof:population":14
},
  "geometry": {"coordinates":[8.19368,45.46203],"type":"Point"}
}