{
  "type": "Feature",
  "properties": {
    "gn:admin1_code":"1",
    "gn:admin2_code":"CH",
    "gn:admin3_code":"69102.0",
    "gn:asciiname":"Santa Maria in Basilico",
    "gn:country_code":"IT",
    "gn:dem":272,
    "gn:feature_class":"P",
    "gn:feature_code":"PPL",
    "gn:name":"Santa Maria in Basilico",
    "gn:population":51,
    "gn:timezone":"Europe/Rome",
    "iso:country":"IT",
    "wof:name":"Santa Maria in Basilico",
    "wof:placetype":"locality",
    "wof:population":51
},
  "geometry": {"coordinates":[14.35618,41.95226],"type":"Point"}
}