{
  "type": "Feature",
  "properties": {
    "gn:admin1_code":"9",
    "gn:admin2_code":"BG",
    "gn:admin3_code":"16071.0",
    "gn:asciiname":"Cedrini",
    "gn:country_code":"IT",
    "gn:dem":536,
    "gn:feature_class":"P",
    "gn:feature_code":"PPL",
    "gn:name":"Cedrini",
    "gn:population":12,
    "gn:timezone":"Europe/Rome",
    "iso:country":"IT",
    "wof:name":"Cedrini",
    "wof:placetype":"locality",
    "wof:population":12
},
  "geometry": {"coordinates":[10.00225,45.85476],"type":"Point"}
}