{
  "type": "Feature",
  "properties": {
    "gn:admin1_code":"20",
    "gn:admin2_code":"PD",
    "gn:admin3_code":"28019.0",
    "gn:asciiname":"Negrin",
    "gn:country_code":"IT",
    "gn:dem":20,
    "gn:feature_class":"P",
    "gn:feature_code":"PPL",
    "gn:name":"Negrin",
    "gn:population":72,
    "gn:timezone":"Europe/Rome",
    "iso:country":"IT",
    "wof:name":"Negrin",
    "wof:placetype":"locality",
    "wof:population":72
},
  "geometry": {"coordinates":[11.9839,45.57617],"type":"Point"}
}