{
  "type": "Feature",
  "properties": {
    "gn:admin1_code":"4",
    "gn:admin2_code":"SA",
    "gn:admin3_code":"65083.0",
    "gn:asciiname":"Serroni",
    "gn:country_code":"IT",
    "gn:dem":434,
    "gn:feature_class":"P",
    "gn:feature_code":"PPL",
    "gn:name":"Serroni",
    "gn:population":85,
    "gn:timezone":"Europe/Rome",
    "iso:country":"IT",
    "wof:name":"Serroni",
    "wof:placetype":"locality",
    "wof:population":85
},
  "geometry": {"coordinates":[15.19552,40.68219000000001],"type":"Point"}
}