{
  "type": "Feature",
  "properties": {
    "gn:admin1_code":"5",
    "gn:admin2_code":"BO",
    "gn:admin3_code":"37027.0",
    "gn:asciiname":"Torretta",
    "gn:country_code":"IT",
    "gn:dem":366,
    "gn:feature_class":"P",
    "gn:feature_code":"PPL",
    "gn:name":"Torretta",
    "gn:population":23,
    "gn:timezone":"Europe/Rome",
    "iso:country":"IT",
    "wof:name":"Torretta",
    "wof:placetype":"locality",
    "wof:population":23
},
  "geometry": {"coordinates":[10.95547,44.18692],"type":"Point"}
}