{
  "type": "Feature",
  "properties": {
    "gn:admin1_code":"5",
    "gn:admin2_code":"FC",
    "gn:admin3_code":"40046.0",
    "gn:asciiname":"Ca' Domenichino",
    "gn:country_code":"IT",
    "gn:dem":452,
    "gn:feature_class":"P",
    "gn:feature_code":"PPL",
    "gn:name":"Ca' Domenichino",
    "gn:population":26,
    "gn:timezone":"Europe/Rome",
    "iso:country":"IT",
    "wof:name":"Ca' Domenichino",
    "wof:placetype":"locality",
    "wof:population":26
},
  "geometry": {"coordinates":[12.24733,43.95656],"type":"Point"}
}