{
  "type": "Feature",
  "properties": {
    "gn:admin1_code":"4.0",
    "gn:admin2_code":"BN",
    "gn:admin3_code":"62074.0",
    "gn:asciiname":"Via Fausto Coppi",
    "gn:country_code":"IT",
    "gn:dem":50,
    "gn:feature_class":"P",
    "gn:feature_code":"PPL",
    "gn:name":"Via Fausto Coppi",
    "gn:population":634,
    "gn:timezone":"Europe/Rome",
    "iso:country":"IT",
    "wof:name":"Via Fausto Coppi",
    "wof:placetype":"locality",
    "wof:population":634
},
  "geometry": {"coordinates":[14.52772,41.21016],"type":"Point"}
}