{
  "type": "Feature",
  "properties": {
    "gn:admin1_code":"2.0",
    "gn:admin2_code":"PZ",
    "gn:admin3_code":"76033.0",
    "gn:asciiname":"Accio",
    "gn:country_code":"IT",
    "gn:dem":844,
    "gn:feature_class":"P",
    "gn:feature_code":"PPL",
    "gn:name":"Accio",
    "gn:population":0,
    "gn:timezone":"Europe/Rome",
    "iso:country":"IT",
    "wof:name":"Accio",
    "wof:placetype":"locality"
},
  "geometry": {"coordinates":[15.81667,40.88333],"type":"Point"}
}