{
  "type": "Feature",
  "properties": {
    "gn:admin1_code":"5",
    "gn:admin2_code":"PR",
    "gn:admin3_code":"34007.0",
    "gn:asciiname":"Madonna Prati",
    "gn:country_code":"IT",
    "gn:dem":36,
    "gn:feature_class":"P",
    "gn:feature_code":"PPL",
    "gn:name":"Madonna Prati",
    "gn:population":66,
    "gn:timezone":"Europe/Rome",
    "iso:country":"IT",
    "wof:name":"Madonna Prati",
    "wof:placetype":"locality",
    "wof:population":66
},
  "geometry": {"coordinates":[10.08572,44.96768],"type":"Point"}
}