{
  "type": "Feature",
  "properties": {
    "gn:admin1_code":"20.0",
    "gn:admin2_code":"PD",
    "gn:admin3_code":"28001.0",
    "gn:asciiname":"San Daniele",
    "gn:country_code":"IT",
    "gn:dem":73,
    "gn:elevation":"80.0",
    "gn:feature_class":"P",
    "gn:feature_code":"PPL",
    "gn:name":"San Daniele",
    "gn:population":24,
    "gn:timezone":"Europe/Rome",
    "iso:country":"IT",
    "wof:name":"San Daniele",
    "wof:placetype":"locality",
    "wof:population":24
},
  "geometry": {"coordinates":[11.76508,45.34517],"type":"Point"}
}