{
  "type": "Feature",
  "properties": {
    "gn:admin1_code":"4.0",
    "gn:admin2_code":"CE",
    "gn:admin3_code":"61088.0",
    "gn:asciiname":"Fasani",
    "gn:country_code":"IT",
    "gn:dem":53,
    "gn:elevation":"49.0",
    "gn:feature_class":"P",
    "gn:feature_code":"PPL",
    "gn:name":"Fasani",
    "gn:population":426,
    "gn:timezone":"Europe/Rome",
    "iso:country":"IT",
    "wof:name":"Fasani",
    "wof:placetype":"locality",
    "wof:population":426
},
  "geometry": {"coordinates":[13.87751,41.2367],"type":"Point"}
}