{
  "type": "Feature",
  "properties": {
    "gn:admin1_code":"20",
    "gn:admin2_code":"RO",
    "gn:admin3_code":"29025.0",
    "gn:asciiname":"Surchio",
    "gn:country_code":"IT",
    "gn:dem":8,
    "gn:feature_class":"P",
    "gn:feature_code":"PPL",
    "gn:name":"Surchio",
    "gn:population":39,
    "gn:timezone":"Europe/Rome",
    "iso:country":"IT",
    "wof:name":"Surchio",
    "wof:placetype":"locality",
    "wof:population":39
},
  "geometry": {"coordinates":[11.50113,44.9469],"type":"Point"}
}