{
  "type": "Feature",
  "properties": {
    "gn:admin1_code":"3.0",
    "gn:admin2_code":"CZ",
    "gn:admin3_code":"79142.0",
    "gn:asciiname":"Ceraso",
    "gn:country_code":"IT",
    "gn:dem":29,
    "gn:feature_class":"P",
    "gn:feature_code":"PPL",
    "gn:name":"Ceraso",
    "gn:population":0,
    "gn:timezone":"Europe/Rome",
    "iso:country":"IT",
    "name:azb_x_preferred":[
        "\u0686\u0631\u0627\u0632\u0648"
    ],
    "name:bar_x_preferred":[
        "Ceraso"
    ],
    "name:bul_x_preferred":[
        "\u0427\u0435\u0440\u0430\u0437\u043e"
    ],
    "name:ceb_x_preferred":[
        "Ceraso"
    ],
    "name:deu_x_preferred":[
        "Ceraso"
    ],
    "name:epo_x_preferred":[
        "Ceraso"
    ],
    "name:eus_x_preferred":[
        "Ceraso"
    ],
    "name:fas_x_preferred":[
        "\u0686\u0631\u0627\u0632\u0648"
    ],
    "name:fra_x_preferred":[
        "Ceraso"
    ],
    "name:hun_x_preferred":[
        "Ceraso"
    ],
    "name:hye_x_preferred":[
        "\u0549\u0565\u0580\u0561\u0566\u0578"
    ],
    "name:ina_x_preferred":[
        "Ceraso"
    ],
    "name:ind_x_preferred":[
        "Ceraso"
    ],
    "name:ita_x_preferred":[
        "Ceraso"
    ],
    "name:jpn_x_preferred":[
        "\u30c1\u30a7\u30e9\u30fc\u30be"
    ],
    "name:kaz_x_preferred":[
        "\u0427\u0435\u0440\u0430\u0437\u043e"
    ],
    "name:kor_x_preferred":[
        "\uccb4\ub77c\uc18c"
    ],
    "name:lat_x_preferred":[
        "Cerasus"
    ],
    "name:lmo_x_preferred":[
        "Ceraso"
    ],
    "name:msa_x_preferred":[
        "Ceraso"
    ],
    "name:nap_x_preferred":[
        "Ceraso"
    ],
    "name:nld_x_preferred":[
        "Ceraso"
    ],
    "name:pms_x_preferred":[
        "Ceraso"
    ],
    "name:pol_x_preferred":[
        "Ceraso"
    ],
    "name:por_x_preferred":[
        "Ceraso"
    ],
    "name:ron_x_preferred":[
        "Ceraso"
    ],
    "name:rus_x_preferred":[
        "\u0427\u0435\u0440\u0430\u0437\u043e"
    ],
    "name:scn_x_preferred":[
        "Cirasu"
    ],
    "name:spa_x_preferred":[
        "Ceraso"
    ],
    "name:srp_x_preferred":[
        "\u0427\u0435\u0440\u0430\u0437\u043e"
    ],
    "name:tgl_x_preferred":[
        "Ceraso"
    ],
    "name:ukr_x_preferred":[
        "\u0427\u0435\u0440\u0430\u0437\u043e"
    ],
    "name:uzb_x_preferred":[
        "Ceraso"
    ],
    "name:vec_x_preferred":[
        "Ceraso"
    ],
    "name:vie_x_preferred":[
        "Ceraso"
    ],
    "name:vol_x_preferred":[
        "Ceraso"
    ],
    "name:war_x_preferred":[
        "Ceraso"
    ],
    "name:zho_x_preferred":[
        "\u5207\u62c9\u7d22"
    ],
    "wof:name":"Ceraso",
    "wof:placetype":"locality"
},
  "geometry": {"coordinates":[16.55,38.78333],"type":"Point"}
}