{
  "type": "Feature",
  "properties": {
    "gn:admin1_code":"5",
    "gn:admin2_code":"RE",
    "gn:admin3_code":"35041.0",
    "gn:asciiname":"Roncolo",
    "gn:country_code":"IT",
    "gn:dem":499,
    "gn:feature_class":"P",
    "gn:feature_code":"PPL",
    "gn:name":"Roncolo",
    "gn:population":42,
    "gn:timezone":"Europe/Rome",
    "iso:country":"IT",
    "wof:name":"Roncolo",
    "wof:placetype":"locality",
    "wof:population":42
},
  "geometry": {"coordinates":[10.5802,44.3954],"type":"Point"}
}