{
  "type": "Feature",
  "properties": {
    "gn:admin1_code":"1.0",
    "gn:admin2_code":"CH",
    "gn:admin3_code":"69022.0",
    "gn:asciiname":"Bivio Brecciarola",
    "gn:country_code":"IT",
    "gn:dem":40,
    "gn:feature_class":"P",
    "gn:feature_code":"PPL",
    "gn:name":"Bivio Brecciarola",
    "gn:population":463,
    "gn:timezone":"Europe/Rome",
    "iso:country":"IT",
    "wof:name":"Bivio Brecciarola",
    "wof:placetype":"locality",
    "wof:population":463
},
  "geometry": {"coordinates":[14.11602,42.33014],"type":"Point"}
}