{
  "type": "Feature",
  "properties": {
    "gn:admin1_code":"12",
    "gn:admin2_code":"TO",
    "gn:admin3_code":"1092.0",
    "gn:asciiname":"Campana",
    "gn:country_code":"IT",
    "gn:dem":243,
    "gn:feature_class":"P",
    "gn:feature_code":"PPL",
    "gn:name":"Campana",
    "gn:population":35,
    "gn:timezone":"Europe/Rome",
    "iso:country":"IT",
    "wof:name":"Campana",
    "wof:placetype":"locality",
    "wof:population":35
},
  "geometry": {"coordinates":[7.81238,45.43899],"type":"Point"}
}