{
  "type": "Feature",
  "properties": {
    "gn:admin1_code":"9",
    "gn:admin2_code":"BS",
    "gn:admin3_code":"17059.0",
    "gn:asciiname":"Mirandola",
    "gn:country_code":"IT",
    "gn:dem":178,
    "gn:feature_class":"P",
    "gn:feature_code":"PPL",
    "gn:name":"Mirandola",
    "gn:population":18,
    "gn:timezone":"Europe/Rome",
    "iso:country":"IT",
    "name:afr_x_preferred":[
        "Mirandola"
    ],
    "name:ara_x_preferred":[
        "\u0645\u064a\u0631\u0627\u0646\u062f\u0648\u0644\u0627"
    ],
    "name:arg_x_preferred":[
        "Mirandola"
    ],
    "name:azb_x_preferred":[
        "\u0645\u06cc\u0631\u0627\u0646\u062f\u0648\u0644\u0627"
    ],
    "name:bul_x_preferred":[
        "\u041c\u0438\u0440\u0430\u043d\u0434\u043e\u043b\u0430"
    ],
    "name:cat_x_preferred":[
        "Mirandola"
    ],
    "name:ceb_x_preferred":[
        "Mirandola"
    ],
    "name:deu_x_preferred":[
        "Mirandola"
    ],
    "name:eml_x_preferred":[
        "La Mir\u00e0ndla"
    ],
    "name:epo_x_preferred":[
        "Mirandola"
    ],
    "name:eus_x_preferred":[
        "Mirandola"
    ],
    "name:fas_x_preferred":[
        "\u0645\u06cc\u0631\u0627\u0646\u062f\u0648\u0644\u0627"
    ],
    "name:fin_x_preferred":[
        "Mirandola"
    ],
    "name:fra_x_preferred":[
        "Mirandola"
    ],
    "name:hun_x_preferred":[
        "Mirandola"
    ],
    "name:hye_x_preferred":[
        "\u0544\u056b\u0580\u0561\u0576\u0564\u0578\u056c\u0561"
    ],
    "name:ina_x_preferred":[
        "Mirandola"
    ],
    "name:ind_x_preferred":[
        "Mirandola"
    ],
    "name:ita_x_preferred":[
        "Mirandola"
    ],
    "name:jpn_x_preferred":[
        "\u30df\u30e9\u30f3\u30c9\u30e9"
    ],
    "name:kaz_x_preferred":[
        "\u041c\u0438\u0440\u0430\u043d\u0434\u043e\u043b\u0430"
    ],
    "name:lat_x_preferred":[
        "Mirandula"
    ],
    "name:lmo_x_preferred":[
        "Mirandola"
    ],
    "name:msa_x_preferred":[
        "Mirandola"
    ],
    "name:nap_x_preferred":[
        "Mirandola"
    ],
    "name:nld_x_preferred":[
        "Mirandola"
    ],
    "name:nno_x_preferred":[
        "Mirandola"
    ],
    "name:nor_x_preferred":[
        "Mirandola"
    ],
    "name:pms_x_preferred":[
        "Mirandola"
    ],
    "name:pol_x_preferred":[
        "Mirandola"
    ],
    "name:por_x_preferred":[
        "Mirandola"
    ],
    "name:ron_x_preferred":[
        "Mirandola"
    ],
    "name:rus_x_preferred":[
        "\u041c\u0438\u0440\u0430\u043d\u0434\u043e\u043b\u0430"
    ],
    "name:sco_x_preferred":[
        "Mirandola"
    ],
    "name:spa_x_preferred":[
        "Mirandola"
    ],
    "name:srp_x_preferred":[
        "\u041c\u0438\u0440\u0430\u043d\u0434\u043e\u043b\u0430"
    ],
    "name:swe_x_preferred":[
        "Mirandola"
    ],
    "name:tur_x_preferred":[
        "Mirandola"
    ],
    "name:ukr_x_preferred":[
        "\u041c\u0456\u0440\u0430\u043d\u0434\u043e\u043b\u0430"
    ],
    "name:uzb_x_preferred":[
        "Mirandola"
    ],
    "name:vec_x_preferred":[
        "Mirandola"
    ],
    "name:vie_x_preferred":[
        "Mirandola"
    ],
    "name:vol_x_preferred":[
        "Mirandola"
    ],
    "name:war_x_preferred":[
        "Mirandola"
    ],
    "wof:name":"Mirandola",
    "wof:placetype":"locality",
    "wof:population":18
},
  "geometry": {"coordinates":[9.91386,45.58114000000001],"type":"Point"}
}