{
  "type": "Feature",
  "properties": {
    "gn:admin1_code":"9",
    "gn:admin2_code":"MI",
    "gn:admin3_code":"15078.0",
    "gn:asciiname":"San Giacomo",
    "gn:country_code":"IT",
    "gn:dem":130,
    "gn:feature_class":"P",
    "gn:feature_code":"PPL",
    "gn:name":"San Giacomo",
    "gn:population":33,
    "gn:timezone":"Europe/Rome",
    "iso:country":"IT",
    "name:ceb_x_preferred":[
        "San Giacomo"
    ],
    "name:deu_x_preferred":[
        "San Giacomo"
    ],
    "name:ita_x_preferred":[
        "San Giacomo"
    ],
    "name:por_x_preferred":[
        "San Giacomo"
    ],
    "name:srp_x_preferred":[
        "San \u0110akomo"
    ],
    "name:swe_x_preferred":[
        "San Giacomo"
    ],
    "wof:name":"San Giacomo",
    "wof:placetype":"locality",
    "wof:population":33
},
  "geometry": {"coordinates":[8.97414,45.45144000000001],"type":"Point"}
}