{
  "type": "Feature",
  "properties": {
    "gn:admin1_code":"7",
    "gn:admin2_code":"FR",
    "gn:admin3_code":"60085.0",
    "gn:asciiname":"Casamari",
    "gn:country_code":"IT",
    "gn:dem":303,
    "gn:feature_class":"P",
    "gn:feature_code":"PPL",
    "gn:name":"Casamari",
    "gn:population":27,
    "gn:timezone":"Europe/Rome",
    "iso:country":"IT",
    "wof:name":"Casamari",
    "wof:placetype":"locality",
    "wof:population":27
},
  "geometry": {"coordinates":[13.48776,41.67147],"type":"Point"}
}