{
  "type": "Feature",
  "properties": {
    "iso:country":"IT",
    "wof:name":"Pagliarelli",
    "wof:placetype":"neighbourhood"
},
  "geometry": {"coordinates":[13.33026194057506,38.08945976156669],"type":"Point"}
}