{
  "type": "Feature",
  "properties": {
    "gn:admin1_code":"20",
    "gn:admin2_code":"VE",
    "gn:admin3_code":"27009.0",
    "gn:asciiname":"Anese",
    "gn:country_code":"IT",
    "gn:dem":13,
    "gn:feature_class":"P",
    "gn:feature_code":"PPL",
    "gn:name":"Anese",
    "gn:population":24,
    "gn:timezone":"Europe/Rome",
    "iso:country":"IT",
    "wof:name":"Anese",
    "wof:placetype":"locality",
    "wof:population":24
},
  "geometry": {"coordinates":[12.77741,45.84316],"type":"Point"}
}