{
  "type": "Feature",
  "properties": {
    "gn:admin1_code":"15.0",
    "gn:admin2_code":"ME",
    "gn:admin3_code":"83099.0",
    "gn:asciiname":"Sant'Antonino Sciortino",
    "gn:country_code":"IT",
    "gn:dem":780,
    "gn:feature_class":"P",
    "gn:feature_code":"PPL",
    "gn:name":"Sant'Antonino Sciortino",
    "gn:population":366,
    "gn:timezone":"Europe/Rome",
    "iso:country":"IT",
    "wof:name":"Sant'Antonino Sciortino",
    "wof:placetype":"locality",
    "wof:population":366
},
  "geometry": {"coordinates":[14.8175,38.01917],"type":"Point"}
}