{
  "type": "Feature",
  "properties": {
    "gn:gn_country":"IT",
    "gn:gn_fcode":"PPLL",
    "gn:gn_pop":0,
    "gn:population":264,
    "iso:country":"IT",
    "name:bul_x_preferred":[
        "\u041f\u043e\u043c\u0430\u0438\u0430"
    ],
    "name:deu_x_preferred":[
        "Pomaia"
    ],
    "name:eng_x_preferred":[
        "Pomaia"
    ],
    "name:fra_x_preferred":[
        "Pomaia"
    ],
    "name:hun_x_preferred":[
        "Pomaia"
    ],
    "name:ita_x_preferred":[
        "Pomaia"
    ],
    "name:nld_x_preferred":[
        "Pomaia"
    ],
    "name:srp_x_preferred":[
        "Pomaia"
    ],
    "qs_pg:aaroncc":"IT",
    "qs_pg:gn_country":"IT",
    "qs_pg:gn_fcode":"PPLL",
    "qs_pg:gn_pop":0,
    "qs_pg:name":"Pomaia",
    "qs_pg:name_adm0":"Italia",
    "qs_pg:name_adm1":"Toscana",
    "qs_pg:photos":309,
    "qs_pg:photos_1k":63,
    "qs_pg:photos_9k":1,
    "qs_pg:photos_9r":5,
    "qs_pg:photos_all":309,
    "qs_pg:photos_sr":5,
    "qs_pg:pop_sr":0,
    "qs_pg:qs_pg_placetype":"locality",
    "qs_pg:qs_pg_placetype_gp":"Town",
    "qs_pg:woe_adm0":23424853,
    "woe:adm0_id":23424853,
    "woe:name_adm0":"Italia",
    "woe:name_adm1":"Toscana",
    "woe:placetype":"Town",
    "wof:name":"Pomaia",
    "wof:placetype":"locality",
    "wof:population":264
},
  "geometry": {"coordinates":[10.56631,43.43374],"type":"Point"}
}