{
  "type": "Feature",
  "properties": {
    "gn:admin1_code":"5.0",
    "gn:admin2_code":"FC",
    "gn:admin3_code":"40043.0",
    "gn:asciiname":"Raggio",
    "gn:country_code":"IT",
    "gn:dem":421,
    "gn:feature_class":"P",
    "gn:feature_code":"PPL",
    "gn:name":"Raggio",
    "gn:population":0,
    "gn:timezone":"Europe/Rome",
    "iso:country":"IT",
    "wof:name":"Raggio",
    "wof:placetype":"locality"
},
  "geometry": {"coordinates":[11.93333,43.93333],"type":"Point"}
}