{
  "type": "Feature",
  "properties": {
    "gn:admin1_code":"17.0",
    "gn:admin2_code":"BZ",
    "gn:admin3_code":"21088.0",
    "gn:asciiname":"Lappago",
    "gn:cc2":"IT",
    "gn:country_code":"IT",
    "gn:dem":1448,
    "gn:elevation":"1436.0",
    "gn:feature_class":"P",
    "gn:feature_code":"PPL",
    "gn:name":"Lappago",
    "gn:population":165,
    "gn:timezone":"Europe/Rome",
    "iso:country":"IT",
    "name:und_x_variant":[
        "Lappach",
        "Lappago"
    ],
    "wof:name":"Lappago",
    "wof:placetype":"locality",
    "wof:population":165
},
  "geometry": {"coordinates":[11.80331,46.9192],"type":"Point"}
}