{
  "type": "Feature",
  "properties": {
    "gn:admin1_code":"20",
    "gn:admin2_code":"VE",
    "gn:admin3_code":"27035.0",
    "gn:asciiname":"Marinoni",
    "gn:country_code":"IT",
    "gn:dem":8,
    "gn:feature_class":"P",
    "gn:feature_code":"PPL",
    "gn:name":"Marinoni",
    "gn:population":190,
    "gn:timezone":"Europe/Rome",
    "iso:country":"IT",
    "wof:name":"Marinoni",
    "wof:placetype":"locality",
    "wof:population":190
},
  "geometry": {"coordinates":[12.02107,45.47427],"type":"Point"}
}