{
  "type": "Feature",
  "properties": {
    "gn:admin1_code":"16",
    "gn:admin2_code":"AR",
    "gn:admin3_code":"51020.0",
    "gn:asciiname":"La Casa",
    "gn:country_code":"IT",
    "gn:dem":715,
    "gn:feature_class":"P",
    "gn:feature_code":"PPLL",
    "gn:name":"La Casa",
    "gn:population":9,
    "gn:timezone":"Europe/Rome",
    "iso:country":"IT",
    "name:ceb_x_preferred":[
        "La Casa"
    ],
    "name:ita_x_preferred":[
        "La casa"
    ],
    "name:spa_x_preferred":[
        "La casa"
    ],
    "name:srp_x_preferred":[
        "La Casa"
    ],
    "name:swe_x_preferred":[
        "La Casa"
    ],
    "wof:name":"La Casa",
    "wof:placetype":"locality",
    "wof:population":9
},
  "geometry": {"coordinates":[11.64694,43.61783],"type":"Point"}
}