{
  "type": "Feature",
  "properties": {
    "gn:admin1_code":"12",
    "gn:admin2_code":"TO",
    "gn:admin3_code":"1289.0",
    "gn:asciiname":"Moncolombone",
    "gn:country_code":"IT",
    "gn:dem":572,
    "gn:feature_class":"P",
    "gn:feature_code":"PPLL",
    "gn:name":"Moncolombone",
    "gn:population":7,
    "gn:timezone":"Europe/Rome",
    "iso:country":"IT",
    "wof:name":"Moncolombone",
    "wof:placetype":"locality",
    "wof:population":7
},
  "geometry": {"coordinates":[7.47402,45.20022],"type":"Point"}
}