{
  "type": "Feature",
  "properties": {
    "gn:admin1_code":"20",
    "gn:admin2_code":"TV",
    "gn:admin3_code":"26058.0",
    "gn:asciiname":"Peschiere",
    "gn:country_code":"IT",
    "gn:dem":10,
    "gn:feature_class":"P",
    "gn:feature_code":"PPL",
    "gn:name":"Peschiere",
    "gn:population":25,
    "gn:timezone":"Europe/Rome",
    "iso:country":"IT",
    "wof:name":"Peschiere",
    "wof:placetype":"locality",
    "wof:population":25
},
  "geometry": {"coordinates":[12.44256,45.74172],"type":"Point"}
}