{
  "type": "Feature",
  "properties": {
    "gn:admin1_code":"7.0",
    "gn:admin2_code":"FR",
    "gn:admin3_code":"60048.0",
    "gn:asciiname":"Zona Industriale A.S.P.",
    "gn:country_code":"IT",
    "gn:dem":142,
    "gn:feature_class":"P",
    "gn:feature_code":"PPLL",
    "gn:name":"Zona Industriale A.S.P.",
    "gn:population":5,
    "gn:timezone":"Europe/Rome",
    "iso:country":"IT",
    "wof:name":"Zona Industriale A.S.P.",
    "wof:placetype":"locality",
    "wof:population":5
},
  "geometry": {"coordinates":[13.2687,41.61379],"type":"Point"}
}