{
  "type": "Feature",
  "properties": {
    "gn:admin1_code":"5",
    "gn:admin2_code":"RE",
    "gn:admin3_code":"35034.0",
    "gn:asciiname":"Commenda",
    "gn:country_code":"IT",
    "gn:dem":23,
    "gn:feature_class":"P",
    "gn:feature_code":"PPL",
    "gn:name":"Commenda",
    "gn:population":22,
    "gn:timezone":"Europe/Rome",
    "iso:country":"IT",
    "wof:name":"Commenda",
    "wof:placetype":"locality",
    "wof:population":22
},
  "geometry": {"coordinates":[10.81296,44.83614],"type":"Point"}
}