{
  "type": "Feature",
  "properties": {
    "gn:admin1_code":"5",
    "gn:admin2_code":"PR",
    "gn:admin3_code":"34012.0",
    "gn:asciiname":"Curatico",
    "gn:country_code":"IT",
    "gn:dem":488,
    "gn:feature_class":"P",
    "gn:feature_code":"PPL",
    "gn:name":"Curatico",
    "gn:population":27,
    "gn:timezone":"Europe/Rome",
    "iso:country":"IT",
    "wof:name":"Curatico",
    "wof:placetype":"locality",
    "wof:population":27
},
  "geometry": {"coordinates":[10.13815,44.52648],"type":"Point"}
}