{
  "type": "Feature",
  "properties": {
    "gn:admin1_code":"19",
    "gn:admin2_code":"AO",
    "gn:admin3_code":"7047.0",
    "gn:asciiname":"Grenier",
    "gn:country_code":"IT",
    "gn:dem":1266,
    "gn:feature_class":"P",
    "gn:feature_code":"PPL",
    "gn:name":"Grenier",
    "gn:population":61,
    "gn:timezone":"Europe/Rome",
    "iso:country":"IT",
    "wof:name":"Grenier",
    "wof:placetype":"locality",
    "wof:population":61
},
  "geometry": {"coordinates":[7.38235,45.84678],"type":"Point"}
}