{
  "type": "Feature",
  "properties": {
    "gn:admin1_code":"16",
    "gn:admin2_code":"PI",
    "gn:admin3_code":"50023.0",
    "gn:asciiname":"Pieve Vecchia",
    "gn:country_code":"IT",
    "gn:dem":140,
    "gn:feature_class":"P",
    "gn:feature_code":"PPL",
    "gn:name":"Pieve Vecchia",
    "gn:population":25,
    "gn:timezone":"Europe/Rome",
    "iso:country":"IT",
    "wof:name":"Pieve Vecchia",
    "wof:placetype":"locality",
    "wof:population":25
},
  "geometry": {"coordinates":[10.48857,43.49941],"type":"Point"}
}