{
  "type": "Feature",
  "properties": {
    "gn:admin1_code":"5.0",
    "gn:admin2_code":"BO",
    "gn:admin3_code":"37062.0",
    "gn:asciiname":"Porretta Terme",
    "gn:country_code":"IT",
    "gn:dem":342,
    "gn:elevation":"349.0",
    "gn:feature_class":"P",
    "gn:feature_code":"PPLA3",
    "gn:name":"Porretta Terme",
    "gn:population":3632,
    "gn:timezone":"Europe/Rome",
    "iso:country":"IT",
    "name:deu_x_preferred":[
        "Porretta Terme"
    ],
    "name:eng_x_preferred":[
        "Porretta Terme"
    ],
    "name:epo_x_preferred":[
        "Porretta Terme"
    ],
    "name:fra_x_preferred":[
        "Porretta Terme"
    ],
    "name:ita_x_preferred":[
        "Porretta Terme"
    ],
    "name:nap_x_preferred":[
        "Porretta Terme"
    ],
    "name:nld_x_preferred":[
        "Porretta Terme"
    ],
    "name:pol_x_preferred":[
        "Porretta Terme"
    ],
    "name:por_x_preferred":[
        "Porretta Terme"
    ],
    "name:rgn_x_preferred":[
        "Puratta"
    ],
    "name:und_x_variant":[
        "Bagni della Porretta"
    ],
    "wof:name":"Porretta Terme",
    "wof:placetype":"locality",
    "wof:population":3632
},
  "geometry": {"coordinates":[10.97432,44.16325],"type":"Point"}
}