{
  "type": "Feature",
  "properties": {
    "gn:admin1_code":"9",
    "gn:admin2_code":"MI",
    "gn:admin3_code":"15195.0",
    "gn:asciiname":"Cascina Rancate",
    "gn:country_code":"IT",
    "gn:dem":97,
    "gn:feature_class":"P",
    "gn:feature_code":"PPL",
    "gn:name":"Cascina Rancate",
    "gn:population":34,
    "gn:timezone":"Europe/Rome",
    "iso:country":"IT",
    "wof:name":"Cascina Rancate",
    "wof:placetype":"locality",
    "wof:population":34
},
  "geometry": {"coordinates":[9.26567,45.37814],"type":"Point"}
}