{
  "type": "Feature",
  "properties": {
    "gn:admin1_code":"17",
    "gn:admin2_code":"TN",
    "gn:admin3_code":"22009.0",
    "gn:asciiname":"Fiore",
    "gn:country_code":"IT",
    "gn:dem":1119,
    "gn:elevation":"1122.0",
    "gn:feature_class":"P",
    "gn:feature_code":"PPL",
    "gn:name":"Fior\u00e8",
    "gn:population":21,
    "gn:timezone":"Europe/Rome",
    "iso:country":"IT",
    "name:deu_x_preferred":[
        "Fiore"
    ],
    "name:fra_x_preferred":[
        "Fiore"
    ],
    "name:ita_x_preferred":[
        "Fiore"
    ],
    "name:jpn_x_preferred":[
        "\u30d5\u30a3\u30aa\u30fc\u30ec"
    ],
    "name:nds_x_preferred":[
        "Fiore"
    ],
    "name:rus_x_preferred":[
        "\u0424\u0438\u043e\u0440\u0435"
    ],
    "name:und_x_variant":[
        "Fior\u00e8"
    ],
    "wof:name":"Fiore",
    "wof:placetype":"locality",
    "wof:population":21
},
  "geometry": {"coordinates":[11.26521,46.12018],"type":"Point"}
}