{
  "type": "Feature",
  "properties": {
    "gn:admin1_code":"12",
    "gn:admin2_code":"AT",
    "gn:admin3_code":"5034.0",
    "gn:asciiname":"Boschetto",
    "gn:country_code":"IT",
    "gn:dem":165,
    "gn:feature_class":"P",
    "gn:feature_code":"PPL",
    "gn:name":"Boschetto",
    "gn:population":15,
    "gn:timezone":"Europe/Rome",
    "iso:country":"IT",
    "wof:name":"Boschetto",
    "wof:placetype":"locality",
    "wof:population":15
},
  "geometry": {"coordinates":[8.10923,44.85306],"type":"Point"}
}