{
  "type": "Feature",
  "properties": {
    "gn:admin1_code":"8.0",
    "gn:admin2_code":"SV",
    "gn:admin3_code":"9023.0",
    "gn:asciiname":"Pertite",
    "gn:country_code":"IT",
    "gn:dem":438,
    "gn:feature_class":"P",
    "gn:feature_code":"PPLL",
    "gn:name":"Pertite",
    "gn:population":0,
    "gn:timezone":"Europe/Rome",
    "iso:country":"IT",
    "wof:name":"Pertite",
    "wof:placetype":"locality"
},
  "geometry": {"coordinates":[8.20761,44.37708],"type":"Point"}
}