{
  "type": "Feature",
  "properties": {
    "gn:admin1_code":"16",
    "gn:admin2_code":"AR",
    "gn:admin3_code":"51008.0",
    "gn:asciiname":"Casa le Bizze",
    "gn:country_code":"IT",
    "gn:dem":317,
    "gn:feature_class":"P",
    "gn:feature_code":"PPL",
    "gn:name":"Casa le Bizze",
    "gn:population":45,
    "gn:timezone":"Europe/Rome",
    "iso:country":"IT",
    "wof:name":"Casa le Bizze",
    "wof:placetype":"locality",
    "wof:population":45
},
  "geometry": {"coordinates":[11.81968,43.62408],"type":"Point"}
}