{
  "type": "Feature",
  "properties": {
    "gn:admin1_code":"18.0",
    "gn:admin2_code":"TR",
    "gn:admin3_code":"55022.0",
    "gn:asciiname":"San Vito",
    "gn:country_code":"IT",
    "gn:dem":258,
    "gn:elevation":"267.0",
    "gn:feature_class":"P",
    "gn:feature_code":"PPL",
    "gn:name":"San Vito",
    "gn:population":138,
    "gn:timezone":"Europe/Rome",
    "iso:country":"IT",
    "wof:name":"San Vito",
    "wof:placetype":"locality",
    "wof:population":138
},
  "geometry": {"coordinates":[12.44238,42.44022],"type":"Point"}
}