{
  "type": "Feature",
  "properties": {
    "gn:country":"IT",
    "gn:fcode":"PPLA3",
    "gn:population":660,
    "iso:country":"IT",
    "name:azb_x_preferred":[
        "\u0648\u0642\u0644\u06cc\u0648"
    ],
    "name:bel_x_preferred":[
        "\u0412\u0435\u043b\u044c\u0451"
    ],
    "name:bul_x_preferred":[
        "\u0412\u0435\u043b\u044c\u043e"
    ],
    "name:cat_x_preferred":[
        "Veglio"
    ],
    "name:ceb_x_preferred":[
        "Veglio"
    ],
    "name:deu_x_preferred":[
        "Veglio"
    ],
    "name:eng_x_preferred":[
        "Veglio"
    ],
    "name:epo_x_preferred":[
        "Veglio"
    ],
    "name:eus_x_preferred":[
        "Veglio"
    ],
    "name:fas_x_preferred":[
        "\u0648\u06af\u0644\u06cc\u0648"
    ],
    "name:fra_x_preferred":[
        "Veglio"
    ],
    "name:hun_x_preferred":[
        "Veglio"
    ],
    "name:hye_x_preferred":[
        "\u054e\u0565\u056c\u056b\u0578"
    ],
    "name:ind_x_preferred":[
        "Veglio"
    ],
    "name:ita_x_preferred":[
        "Veglio"
    ],
    "name:jpn_x_preferred":[
        "\u30f4\u30a7\u30fc\u30ea\u30aa"
    ],
    "name:kaz_x_preferred":[
        "\u0412\u0435\u043b\u044c\u043e"
    ],
    "name:lat_x_preferred":[
        "Velium"
    ],
    "name:lmo_x_preferred":[
        "Veglio"
    ],
    "name:msa_x_preferred":[
        "Veglio"
    ],
    "name:nan_x_preferred":[
        "Veglio"
    ],
    "name:nap_x_preferred":[
        "Veglio"
    ],
    "name:nld_x_preferred":[
        "Veglio"
    ],
    "name:oci_x_preferred":[
        "Veglio"
    ],
    "name:pms_x_preferred":[
        "Vej"
    ],
    "name:pol_x_preferred":[
        "Veglio"
    ],
    "name:por_x_preferred":[
        "Veglio"
    ],
    "name:ron_x_preferred":[
        "Veglio"
    ],
    "name:rus_x_preferred":[
        "\u0412\u0435\u043b\u044c\u043e"
    ],
    "name:scn_x_preferred":[
        "Veglio"
    ],
    "name:spa_x_preferred":[
        "Veglio"
    ],
    "name:srp_x_preferred":[
        "Veglio"
    ],
    "name:tgl_x_preferred":[
        "Veglio"
    ],
    "name:ukr_x_preferred":[
        "\u0412\u0435\u043b\u044c\u0439\u043e"
    ],
    "name:uzb_x_preferred":[
        "Veglio"
    ],
    "name:vie_x_preferred":[
        "Veglio"
    ],
    "name:vol_x_preferred":[
        "Veglio"
    ],
    "name:war_x_preferred":[
        "Veglio"
    ],
    "name:zho_x_preferred":[
        "\u97e6\u5ed6"
    ],
    "qs_pg:aaroncc":"IT",
    "qs_pg:gn_country":"IT",
    "qs_pg:gn_fcode":"PPLA3",
    "qs_pg:gn_pop":660,
    "qs_pg:name":"Veglio",
    "qs_pg:name_adm0":"Italia",
    "qs_pg:name_adm1":"Piemonte",
    "qs_pg:photos":17,
    "qs_pg:photos_1k":3,
    "qs_pg:photos_9k":1,
    "qs_pg:photos_9r":1,
    "qs_pg:photos_all":17,
    "qs_pg:photos_sr":1,
    "qs_pg:pop_sr":2,
    "qs_pg:qs_pg_placetype":"locality",
    "qs_pg:qs_pg_placetype_gp":"Town",
    "qs_pg:woe_adm0":23424853,
    "woe:adm0_id":23424853,
    "woe:name_adm0":"Italia",
    "woe:name_adm1":"Piemonte",
    "woe:placetype":"Town",
    "wof:name":"Veglio",
    "wof:placetype":"locality",
    "wof:population":660
},
  "geometry": {"coordinates":[8.11412,45.64056],"type":"Point"}
}