{
  "type": "Feature",
  "properties": {
    "gn:admin1_code":"3.0",
    "gn:admin2_code":"CZ",
    "gn:admin3_code":"79023.0",
    "gn:asciiname":"Sant'Elia",
    "gn:country_code":"IT",
    "gn:dem":647,
    "gn:feature_class":"P",
    "gn:feature_code":"PPL",
    "gn:name":"Sant'Elia",
    "gn:population":1174,
    "gn:timezone":"Europe/Rome",
    "iso:country":"IT",
    "wof:name":"Sant'Elia",
    "wof:placetype":"locality",
    "wof:population":1174
},
  "geometry": {"coordinates":[16.58521,38.95788],"type":"Point"}
}