{
  "type": "Feature",
  "properties": {
    "gn:admin1_code":"19",
    "gn:admin2_code":"AO",
    "gn:admin3_code":"7065.0",
    "gn:asciiname":"Beigne",
    "gn:country_code":"IT",
    "gn:dem":656,
    "gn:feature_class":"P",
    "gn:feature_code":"PPL",
    "gn:name":"Beigne",
    "gn:population":14,
    "gn:timezone":"Europe/Rome",
    "iso:country":"IT",
    "wof:name":"Beigne",
    "wof:placetype":"locality",
    "wof:population":14
},
  "geometry": {"coordinates":[7.64264,45.75691],"type":"Point"}
}