{
  "type": "Feature",
  "properties": {
    "gn:admin1_code":"13",
    "gn:admin2_code":"LE",
    "gn:admin3_code":"75029.0",
    "gn:asciiname":"Contrada Spina",
    "gn:country_code":"IT",
    "gn:dem":62,
    "gn:feature_class":"P",
    "gn:feature_code":"PPLL",
    "gn:name":"Contrada Spina",
    "gn:population":10,
    "gn:timezone":"Europe/Rome",
    "iso:country":"IT",
    "wof:name":"Contrada Spina",
    "wof:placetype":"locality",
    "wof:population":10
},
  "geometry": {"coordinates":[18.11928,40.15505],"type":"Point"}
}