{
  "type": "Feature",
  "properties": {
    "gn:admin1_code":"16",
    "gn:admin2_code":"SI",
    "gn:admin3_code":"52015.0",
    "gn:asciiname":"Il Santo",
    "gn:country_code":"IT",
    "gn:dem":261,
    "gn:feature_class":"P",
    "gn:feature_code":"PPL",
    "gn:name":"Il Santo",
    "gn:population":33,
    "gn:timezone":"Europe/Rome",
    "iso:country":"IT",
    "wof:name":"Il Santo",
    "wof:placetype":"locality",
    "wof:population":33
},
  "geometry": {"coordinates":[11.86864,43.12186],"type":"Point"}
}