{
  "type": "Feature",
  "properties": {
    "gn:admin1_code":"3.0",
    "gn:admin2_code":"RC",
    "gn:admin3_code":"80040.0",
    "gn:asciiname":"Cambruso I",
    "gn:country_code":"IT",
    "gn:dem":316,
    "gn:feature_class":"P",
    "gn:feature_code":"PPL",
    "gn:name":"Cambruso I",
    "gn:population":35,
    "gn:timezone":"Europe/Rome",
    "iso:country":"IT",
    "wof:name":"Cambruso I",
    "wof:placetype":"locality",
    "wof:population":35
},
  "geometry": {"coordinates":[16.27124,38.36512000000001],"type":"Point"}
}