{
  "type": "Feature",
  "properties": {
    "gn:admin1_code":"20.0",
    "gn:admin2_code":"VE",
    "gn:admin3_code":"27037.0",
    "gn:asciiname":"Cappella",
    "gn:country_code":"IT",
    "gn:dem":10,
    "gn:elevation":"12.0",
    "gn:feature_class":"P",
    "gn:feature_code":"PPL",
    "gn:name":"Cappella",
    "gn:population":946,
    "gn:timezone":"Europe/Rome",
    "iso:country":"IT",
    "name:ita_x_preferred":[
        "Cappella"
    ],
    "wof:name":"Cappella",
    "wof:placetype":"locality",
    "wof:population":946
},
  "geometry": {"coordinates":[12.14038,45.56906],"type":"Point"}
}