{
  "type": "Feature",
  "properties": {
    "gn:admin1_code":"13",
    "gn:admin2_code":"LE",
    "gn:admin3_code":"75097.0",
    "gn:asciiname":"Torre Castiglione",
    "gn:country_code":"IT",
    "gn:dem":7,
    "gn:feature_class":"P",
    "gn:feature_code":"PPLL",
    "gn:name":"Torre Castiglione",
    "gn:population":6,
    "gn:timezone":"Europe/Rome",
    "iso:country":"IT",
    "wof:name":"Torre Castiglione",
    "wof:placetype":"locality",
    "wof:population":6
},
  "geometry": {"coordinates":[17.81486,40.29252],"type":"Point"}
}