{
  "type": "Feature",
  "properties": {
    "gn:admin1_code":"3",
    "gn:admin2_code":"KR",
    "gn:admin3_code":"101019.0",
    "gn:asciiname":"Setteporte",
    "gn:country_code":"IT",
    "gn:dem":32,
    "gn:feature_class":"P",
    "gn:feature_code":"PPL",
    "gn:name":"Setteporte",
    "gn:population":103,
    "gn:timezone":"Europe/Rome",
    "iso:country":"IT",
    "wof:name":"Setteporte",
    "wof:placetype":"locality",
    "wof:population":103
},
  "geometry": {"coordinates":[16.99937000000001,39.17837],"type":"Point"}
}