{
  "type": "Feature",
  "properties": {
    "gn:admin1_code":"8",
    "gn:admin2_code":"SP",
    "gn:admin3_code":"11008.0",
    "gn:asciiname":"Piano di Madrignano",
    "gn:country_code":"IT",
    "gn:dem":57,
    "gn:feature_class":"P",
    "gn:feature_code":"PPL",
    "gn:name":"Piano di Madrignano",
    "gn:population":87,
    "gn:timezone":"Europe/Rome",
    "iso:country":"IT",
    "wof:name":"Piano di Madrignano",
    "wof:placetype":"locality",
    "wof:population":87
},
  "geometry": {"coordinates":[9.84407,44.20096],"type":"Point"}
}