{
  "type": "Feature",
  "properties": {
    "gn:admin1_code":"7",
    "gn:admin2_code":"RM",
    "gn:admin3_code":"58074.0",
    "gn:asciiname":"Fontanavazza",
    "gn:country_code":"IT",
    "gn:dem":387,
    "gn:feature_class":"P",
    "gn:feature_code":"PPL",
    "gn:name":"Fontanavazza",
    "gn:population":48,
    "gn:timezone":"Europe/Rome",
    "iso:country":"IT",
    "wof:name":"Fontanavazza",
    "wof:placetype":"locality",
    "wof:population":48
},
  "geometry": {"coordinates":[12.87057,41.85235],"type":"Point"}
}