{
  "type": "Feature",
  "properties": {
    "gn:admin1_code":"10",
    "gn:admin2_code":"AP",
    "gn:admin3_code":"44054.0",
    "gn:asciiname":"Santa Maria Goretti",
    "gn:country_code":"IT",
    "gn:dem":127,
    "gn:feature_class":"P",
    "gn:feature_code":"PPL",
    "gn:name":"Santa Maria Goretti",
    "gn:population":300,
    "gn:timezone":"Europe/Rome",
    "iso:country":"IT",
    "wof:name":"Santa Maria Goretti",
    "wof:placetype":"locality",
    "wof:population":300
},
  "geometry": {"coordinates":[13.7181,42.97061],"type":"Point"}
}