{
  "type": "Feature",
  "properties": {
    "gn:admin1_code":"16",
    "gn:admin2_code":"PI",
    "gn:admin3_code":"50010.0",
    "gn:asciiname":"Le Conche",
    "gn:country_code":"IT",
    "gn:dem":32,
    "gn:feature_class":"P",
    "gn:feature_code":"PPL",
    "gn:name":"Le Conche",
    "gn:population":59,
    "gn:timezone":"Europe/Rome",
    "iso:country":"IT",
    "wof:name":"Le Conche",
    "wof:placetype":"locality",
    "wof:population":59
},
  "geometry": {"coordinates":[10.50116,43.39522],"type":"Point"}
}