{
  "type": "Feature",
  "properties": {
    "gn:admin1_code":"16",
    "gn:admin2_code":"SI",
    "gn:admin3_code":"52032.0",
    "gn:asciiname":"Abbadia",
    "gn:country_code":"IT",
    "gn:dem":235,
    "gn:feature_class":"P",
    "gn:feature_code":"PPL",
    "gn:name":"Abbadia",
    "gn:population":236,
    "gn:timezone":"Europe/Rome",
    "iso:country":"IT",
    "wof:name":"Abbadia",
    "wof:placetype":"locality",
    "wof:population":236
},
  "geometry": {"coordinates":[11.3799,43.29666],"type":"Point"}
}