{
  "type": "Feature",
  "properties": {
    "gn:admin1_code":"20",
    "gn:admin2_code":"VE",
    "gn:admin3_code":"27007.0",
    "gn:asciiname":"Case Doretto",
    "gn:country_code":"IT",
    "gn:dem":-1,
    "gn:feature_class":"P",
    "gn:feature_code":"PPL",
    "gn:name":"Case Doretto",
    "gn:population":66,
    "gn:timezone":"Europe/Rome",
    "iso:country":"IT",
    "wof:name":"Case Doretto",
    "wof:placetype":"locality",
    "wof:population":66
},
  "geometry": {"coordinates":[12.61619,45.68938],"type":"Point"}
}