{
  "type": "Feature",
  "properties": {
    "gn:admin1_code":"4",
    "gn:admin2_code":"AV",
    "gn:admin3_code":"64058.0",
    "gn:asciiname":"Casa Arsa",
    "gn:country_code":"IT",
    "gn:dem":475,
    "gn:feature_class":"P",
    "gn:feature_code":"PPL",
    "gn:name":"Casa Arsa",
    "gn:population":78,
    "gn:timezone":"Europe/Rome",
    "iso:country":"IT",
    "wof:name":"Casa Arsa",
    "wof:placetype":"locality",
    "wof:population":78
},
  "geometry": {"coordinates":[15.03617,40.91237],"type":"Point"}
}