{
  "type": "Feature",
  "properties": {
    "gn:admin1_code":"9",
    "gn:admin2_code":"SO",
    "gn:admin3_code":"14052.0",
    "gn:asciiname":"Casacce",
    "gn:country_code":"IT",
    "gn:dem":393,
    "gn:feature_class":"P",
    "gn:feature_code":"PPL",
    "gn:name":"Casacce",
    "gn:population":324,
    "gn:timezone":"Europe/Rome",
    "iso:country":"IT",
    "wof:name":"Casacce",
    "wof:placetype":"locality",
    "wof:population":324
},
  "geometry": {"coordinates":[9.97238,46.16358],"type":"Point"}
}