{
  "type": "Feature",
  "properties": {
    "gn:admin1_code":"7",
    "gn:admin2_code":"RM",
    "gn:admin3_code":"58117.0",
    "gn:asciiname":"Casale Rosa",
    "gn:country_code":"IT",
    "gn:dem":45,
    "gn:feature_class":"P",
    "gn:feature_code":"PPLL",
    "gn:name":"Casale Rosa",
    "gn:population":9,
    "gn:timezone":"Europe/Rome",
    "iso:country":"IT",
    "wof:name":"Casale Rosa",
    "wof:placetype":"locality",
    "wof:population":9
},
  "geometry": {"coordinates":[12.54951,41.64548],"type":"Point"}
}