{
  "type": "Feature",
  "properties": {
    "gn:admin1_code":"7",
    "gn:admin2_code":"FR",
    "gn:admin3_code":"60069.0",
    "gn:asciiname":"Pietraia",
    "gn:country_code":"IT",
    "gn:dem":476,
    "gn:feature_class":"P",
    "gn:feature_code":"PPL",
    "gn:name":"Pietraia",
    "gn:population":23,
    "gn:timezone":"Europe/Rome",
    "iso:country":"IT",
    "wof:name":"Pietraia",
    "wof:placetype":"locality",
    "wof:population":23
},
  "geometry": {"coordinates":[13.6558,41.6118],"type":"Point"}
}