{
  "type": "Feature",
  "properties": {
    "gn:admin1_code":"7",
    "gn:admin2_code":"FR",
    "gn:admin3_code":"60019.0",
    "gn:asciiname":"Fontana Livia-Solfegna",
    "gn:country_code":"IT",
    "gn:dem":72,
    "gn:feature_class":"P",
    "gn:feature_code":"PPL",
    "gn:name":"Fontana Livia-Solfegna",
    "gn:population":152,
    "gn:timezone":"Europe/Rome",
    "iso:country":"IT",
    "wof:name":"Fontana Livia-Solfegna",
    "wof:placetype":"locality",
    "wof:population":152
},
  "geometry": {"coordinates":[13.78878,41.4728],"type":"Point"}
}