{
  "type": "Feature",
  "properties": {
    "gn:country":"IT",
    "gn:fcode":"PPL",
    "gn:population":0,
    "iso:country":"IT",
    "name:amh_x_preferred":[
        "\u126c\u1271\u120e\u1292\u12eb"
    ],
    "name:bul_x_preferred":[
        "\u0412\u0435\u0442\u0443\u043b\u043e\u043d\u0438\u044f"
    ],
    "name:cat_x_preferred":[
        "Vetul\u00f2nia"
    ],
    "name:ceb_x_preferred":[
        "Vetulonia"
    ],
    "name:deu_x_preferred":[
        "Vetulonia"
    ],
    "name:eng_x_preferred":[
        "Vetulonia"
    ],
    "name:fas_x_preferred":[
        "\u0648\u062a\u0648\u0644\u0648\u0646\u06cc\u0627"
    ],
    "name:fin_x_preferred":[
        "Vetulonia"
    ],
    "name:fra_x_preferred":[
        "Vetulonia"
    ],
    "name:hun_x_preferred":[
        "Vetulonia"
    ],
    "name:ita_x_preferred":[
        "Vetulonia"
    ],
    "name:lat_x_preferred":[
        "Vetulonium"
    ],
    "name:nld_x_preferred":[
        "Vetulonia"
    ],
    "name:nob_x_preferred":[
        "Vetulonia"
    ],
    "name:pol_x_preferred":[
        "Vetulonia"
    ],
    "name:rus_x_preferred":[
        "\u0412\u0435\u0442\u0443\u043b\u043e\u043d\u0438\u044f"
    ],
    "name:spa_x_preferred":[
        "Vetulonia"
    ],
    "name:srp_x_preferred":[
        "Vetulonia"
    ],
    "name:srp_x_variant":[
        "\u0412\u0435\u0442\u0443\u043b\u043e\u043d\u0438\u0458\u0430"
    ],
    "name:swe_x_preferred":[
        "Vetulonia"
    ],
    "name:ukr_x_preferred":[
        "\u0412\u0435\u0442\u0443\u043b\u043e\u043d\u0456\u044f"
    ],
    "qs_pg:aaroncc":"IT",
    "qs_pg:gn_country":"IT",
    "qs_pg:gn_fcode":"PPL",
    "qs_pg:gn_pop":0,
    "qs_pg:name":"Vetulonia",
    "qs_pg:name_adm0":"Italia",
    "qs_pg:name_adm1":"Toscana",
    "qs_pg:photos":142,
    "qs_pg:photos_1k":29,
    "qs_pg:photos_9k":1,
    "qs_pg:photos_9r":3,
    "qs_pg:photos_all":142,
    "qs_pg:photos_sr":3,
    "qs_pg:pop_sr":0,
    "qs_pg:qs_pg_placetype":"locality",
    "qs_pg:qs_pg_placetype_gp":"Town",
    "qs_pg:woe_adm0":23424853,
    "woe:adm0_id":23424853,
    "woe:name_adm0":"Italia",
    "woe:name_adm1":"Toscana",
    "woe:placetype":"Town",
    "wof:name":"Vetulonia",
    "wof:placetype":"locality",
    "wof:population":254
},
  "geometry": {"coordinates":[10.96667,42.85],"type":"Point"}
}