{
  "type": "Feature",
  "properties": {
    "gn:admin1_code":"16.0",
    "gn:admin2_code":"FI",
    "gn:admin3_code":"48024.0",
    "gn:asciiname":"Quattro Strade",
    "gn:country_code":"IT",
    "gn:dem":154,
    "gn:feature_class":"P",
    "gn:feature_code":"PPL",
    "gn:name":"Quattro Strade",
    "gn:population":1233,
    "gn:timezone":"Europe/Rome",
    "iso:country":"IT",
    "wof:name":"Quattro Strade",
    "wof:placetype":"locality",
    "wof:population":1233
},
  "geometry": {"coordinates":[11.0807,43.74148],"type":"Point"}
}