{
  "type": "Feature",
  "properties": {
    "gn:admin1_code":"6",
    "gn:admin2_code":"UD",
    "gn:admin3_code":"30116.0",
    "gn:asciiname":"Case Anzil",
    "gn:country_code":"IT",
    "gn:dem":222,
    "gn:feature_class":"P",
    "gn:feature_code":"PPL",
    "gn:name":"Case Anzil",
    "gn:population":18,
    "gn:timezone":"Europe/Rome",
    "iso:country":"IT",
    "wof:name":"Case Anzil",
    "wof:placetype":"locality",
    "wof:population":18
},
  "geometry": {"coordinates":[13.18806,46.21557],"type":"Point"}
}