{
  "type": "Feature",
  "properties": {
    "gn:admin1_code":"12",
    "gn:admin2_code":"TO",
    "gn:admin3_code":"1192.0",
    "gn:asciiname":"Tetti Gariglio",
    "gn:country_code":"IT",
    "gn:dem":352,
    "gn:feature_class":"P",
    "gn:feature_code":"PPL",
    "gn:name":"Tetti Gariglio",
    "gn:population":21,
    "gn:timezone":"Europe/Rome",
    "iso:country":"IT",
    "wof:name":"Tetti Gariglio",
    "wof:placetype":"locality",
    "wof:population":21
},
  "geometry": {"coordinates":[7.80482,45.0352],"type":"Point"}
}