{
  "type": "Feature",
  "properties": {
    "gn:admin1_code":"20",
    "gn:admin2_code":"VR",
    "gn:admin3_code":"23046.0",
    "gn:asciiname":"Canzago",
    "gn:country_code":"IT",
    "gn:dem":315,
    "gn:feature_class":"P",
    "gn:feature_code":"PPL",
    "gn:name":"Canzago",
    "gn:population":22,
    "gn:timezone":"Europe/Rome",
    "iso:country":"IT",
    "wof:name":"Canzago",
    "wof:placetype":"locality",
    "wof:population":22
},
  "geometry": {"coordinates":[10.91411,45.55137],"type":"Point"}
}