{
  "type": "Feature",
  "properties": {
    "gn:admin1_code":"16",
    "gn:admin2_code":"MS",
    "gn:admin3_code":"45008.0",
    "gn:asciiname":"Monte Carboli",
    "gn:country_code":"IT",
    "gn:dem":576,
    "gn:feature_class":"P",
    "gn:feature_code":"PPL",
    "gn:name":"Monte Carboli",
    "gn:population":37,
    "gn:timezone":"Europe/Rome",
    "iso:country":"IT",
    "wof:name":"Monte Carboli",
    "wof:placetype":"locality",
    "wof:population":37
},
  "geometry": {"coordinates":[10.02642,44.14014],"type":"Point"}
}