{
  "type": "Feature",
  "properties": {
    "gn:admin1_code":"20.0",
    "gn:admin2_code":"VR",
    "gn:admin3_code":"23027.0",
    "gn:asciiname":"Sule",
    "gn:country_code":"IT",
    "gn:dem":22,
    "gn:feature_class":"P",
    "gn:feature_code":"PPL",
    "gn:name":"Sul\u00e8",
    "gn:population":487,
    "gn:timezone":"Europe/Rome",
    "iso:country":"IT",
    "name:ceb_x_preferred":[
        "Sule"
    ],
    "name:deu_x_preferred":[
        "Sule"
    ],
    "name:fra_x_preferred":[
        "Sule"
    ],
    "name:swe_x_preferred":[
        "Sule"
    ],
    "wof:name":"Sule",
    "wof:placetype":"locality",
    "wof:population":487
},
  "geometry": {"coordinates":[11.36294,45.3211],"type":"Point"}
}