{
  "type": "Feature",
  "properties": {
    "gn:gn_country":"IT",
    "gn:gn_fcode":"PPLA3",
    "gn:gn_pop":267,
    "gn:population":225,
    "iso:country":"IT",
    "name:ara_x_preferred":[
        "\u0641\u064a\u0627\u0644\u064a"
    ],
    "name:azb_x_preferred":[
        "\u0648\u06cc\u0627\u0644\u0647"
    ],
    "name:bel_x_preferred":[
        "\u0412'\u044f\u043b\u0435"
    ],
    "name:bul_x_preferred":[
        "\u0412\u0438\u0430\u043b\u0435"
    ],
    "name:cat_x_preferred":[
        "Viale"
    ],
    "name:ceb_x_preferred":[
        "Viale"
    ],
    "name:deu_x_preferred":[
        "Viale"
    ],
    "name:eng_x_preferred":[
        "Viale"
    ],
    "name:epo_x_preferred":[
        "Viale"
    ],
    "name:est_x_preferred":[
        "Viale"
    ],
    "name:eus_x_preferred":[
        "Viale"
    ],
    "name:fas_x_preferred":[
        "\u0648\u06cc\u0627\u0644\u0647"
    ],
    "name:fra_x_preferred":[
        "Viale"
    ],
    "name:hun_x_preferred":[
        "Viale"
    ],
    "name:hye_x_preferred":[
        "\u054e\u0575\u0561\u056c\u0565"
    ],
    "name:ind_x_preferred":[
        "Viale"
    ],
    "name:ita_x_preferred":[
        "Viale"
    ],
    "name:jpn_x_preferred":[
        "\u30f4\u30a3\u30a2\u30fc\u30ec"
    ],
    "name:kaz_x_preferred":[
        "\u0412\u044c\u044f\u043b\u0435"
    ],
    "name:lat_x_preferred":[
        "Viale"
    ],
    "name:lmo_x_preferred":[
        "Viale"
    ],
    "name:msa_x_preferred":[
        "Viale"
    ],
    "name:nan_x_preferred":[
        "Viale"
    ],
    "name:nap_x_preferred":[
        "Viale"
    ],
    "name:nld_x_preferred":[
        "Viale"
    ],
    "name:oci_x_preferred":[
        "Viale"
    ],
    "name:pms_x_preferred":[
        "Vial"
    ],
    "name:pol_x_preferred":[
        "Viale"
    ],
    "name:por_x_preferred":[
        "Viale"
    ],
    "name:ron_x_preferred":[
        "Viale"
    ],
    "name:rus_x_preferred":[
        "\u0412\u044c\u044f\u043b\u0435"
    ],
    "name:scn_x_preferred":[
        "Viale"
    ],
    "name:spa_x_preferred":[
        "Viale"
    ],
    "name:srp_x_preferred":[
        "Viale"
    ],
    "name:tgl_x_preferred":[
        "Viale"
    ],
    "name:ukr_x_preferred":[
        "\u0412'\u044f\u043b\u0435"
    ],
    "name:uzb_x_preferred":[
        "Viale"
    ],
    "name:vie_x_preferred":[
        "Viale"
    ],
    "name:vie_x_variant":[
        "Viale "
    ],
    "name:vol_x_preferred":[
        "Viale"
    ],
    "name:war_x_preferred":[
        "Viale"
    ],
    "name:zho_x_preferred":[
        "\u7ef4\u4e9a\u83b1"
    ],
    "qs_pg:aaroncc":"IT",
    "qs_pg:gn_country":"IT",
    "qs_pg:gn_fcode":"PPLA3",
    "qs_pg:gn_pop":267,
    "qs_pg:name":"Viale",
    "qs_pg:name_adm0":"Italia",
    "qs_pg:name_adm1":"Piemonte",
    "qs_pg:photos_9r":0,
    "qs_pg:photos_sr":0,
    "qs_pg:pop_sr":2,
    "qs_pg:qs_pg_placetype":"locality",
    "qs_pg:qs_pg_placetype_gp":"Town",
    "qs_pg:woe_adm0":23424853,
    "woe:adm0_id":23424853,
    "woe:name_adm0":"Italia",
    "woe:name_adm1":"Piemonte",
    "woe:placetype":"Town",
    "wof:name":"Viale",
    "wof:placetype":"locality",
    "wof:population":225
},
  "geometry": {"coordinates":[8.04993,45.00015],"type":"Point"}
}