{
  "type": "Feature",
  "properties": {
    "gn:admin1_code":"20.0",
    "gn:admin2_code":"RO",
    "gn:admin3_code":"29026.0",
    "gn:asciiname":"Chiavica Ferrarese",
    "gn:country_code":"IT",
    "gn:dem":-2,
    "gn:feature_class":"P",
    "gn:feature_code":"PPL",
    "gn:name":"Chiavica Ferrarese",
    "gn:population":0,
    "gn:timezone":"Europe/Rome",
    "iso:country":"IT",
    "wof:name":"Chiavica Ferrarese",
    "wof:placetype":"locality"
},
  "geometry": {"coordinates":[11.91667,45.01667],"type":"Point"}
}