{
  "type": "Feature",
  "properties": {
    "gn:admin1_code":"9",
    "gn:admin2_code":"CO",
    "gn:admin3_code":"13251.0",
    "gn:asciiname":"Bernaschina",
    "gn:country_code":"IT",
    "gn:dem":367,
    "gn:feature_class":"P",
    "gn:feature_code":"PPL",
    "gn:name":"Bernaschina",
    "gn:population":84,
    "gn:timezone":"Europe/Rome",
    "iso:country":"IT",
    "wof:name":"Bernaschina",
    "wof:placetype":"locality",
    "wof:population":84
},
  "geometry": {"coordinates":[8.98515,45.80474],"type":"Point"}
}