{
  "type": "Feature",
  "properties": {
    "gn:admin1_code":"5",
    "gn:admin2_code":"PR",
    "gn:admin3_code":"34049.0",
    "gn:asciiname":"San Nazzaro",
    "gn:country_code":"IT",
    "gn:dem":30,
    "gn:feature_class":"P",
    "gn:feature_code":"PPL",
    "gn:name":"San Nazzaro",
    "gn:population":122,
    "gn:timezone":"Europe/Rome",
    "iso:country":"IT",
    "wof:name":"San Nazzaro",
    "wof:placetype":"locality",
    "wof:population":122
},
  "geometry": {"coordinates":[10.29336,44.95406],"type":"Point"}
}