{
  "type": "Feature",
  "properties": {
    "gn:admin1_code":"5",
    "gn:admin2_code":"PR",
    "gn:admin3_code":"34049.0",
    "gn:asciiname":"San Nazzaro",
    "gn:country_code":"IT",
    "gn:dem":30,
    "gn:feature_class":"P",
    "gn:feature_code":"PPL",
    "gn:name":"San Nazzaro",
    "gn:population":122,
    "gn:timezone":"Europe/Rome",
    "iso:country":"IT",
    "name:ceb_x_preferred":[
        "San Nazzaro"
    ],
    "name:deu_x_preferred":[
        "San Nazzaro"
    ],
    "name:epo_x_preferred":[
        "San Nazzaro"
    ],
    "name:eus_x_preferred":[
        "San Nazzaro"
    ],
    "name:fra_x_preferred":[
        "San Nazzaro"
    ],
    "name:ita_x_preferred":[
        "San Nazzaro"
    ],
    "name:nap_x_preferred":[
        "San Nazzaro"
    ],
    "name:nld_x_preferred":[
        "San Nazzaro"
    ],
    "name:pms_x_preferred":[
        "San Nazzaro"
    ],
    "name:por_x_preferred":[
        "San Nazzaro"
    ],
    "name:roh_x_preferred":[
        "San Nazzaro"
    ],
    "name:srp_x_preferred":[
        "San Nacaro"
    ],
    "name:swe_x_preferred":[
        "San Nazzaro"
    ],
    "name:vol_x_preferred":[
        "San Nazzaro"
    ],
    "wof:name":"San Nazzaro",
    "wof:placetype":"locality",
    "wof:population":122
},
  "geometry": {"coordinates":[10.29336,44.95406],"type":"Point"}
}