{
  "type": "Feature",
  "properties": {
    "gn:admin1_code":"20",
    "gn:admin2_code":"VR",
    "gn:admin3_code":"23018.0",
    "gn:asciiname":"Ori-Vegerana",
    "gn:country_code":"IT",
    "gn:dem":350,
    "gn:feature_class":"P",
    "gn:feature_code":"PPL",
    "gn:name":"Ori-Vegerana",
    "gn:population":16,
    "gn:timezone":"Europe/Rome",
    "iso:country":"IT",
    "wof:name":"Ori-Vegerana",
    "wof:placetype":"locality",
    "wof:population":16
},
  "geometry": {"coordinates":[10.83103,45.61112],"type":"Point"}
}