{
  "type": "Feature",
  "properties": {
    "gn:admin1_code":"8",
    "gn:admin2_code":"SV",
    "gn:admin3_code":"9040.0",
    "gn:asciiname":"Valle",
    "gn:country_code":"IT",
    "gn:dem":560,
    "gn:feature_class":"P",
    "gn:feature_code":"PPL",
    "gn:name":"Valle",
    "gn:population":66,
    "gn:timezone":"Europe/Rome",
    "iso:country":"IT",
    "wof:name":"Valle",
    "wof:placetype":"locality",
    "wof:population":66
},
  "geometry": {"coordinates":[8.12204,44.30395],"type":"Point"}
}