{
  "type": "Feature",
  "properties": {
    "gn:admin1_code":"4",
    "gn:admin2_code":"AV",
    "gn:admin3_code":"64035.0",
    "gn:asciiname":"San Silvestro",
    "gn:country_code":"IT",
    "gn:dem":529,
    "gn:feature_class":"P",
    "gn:feature_code":"PPL",
    "gn:name":"San Silvestro",
    "gn:population":32,
    "gn:timezone":"Europe/Rome",
    "iso:country":"IT",
    "wof:name":"San Silvestro",
    "wof:placetype":"locality",
    "wof:population":32
},
  "geometry": {"coordinates":[15.08401,41.03395],"type":"Point"}
}