{
  "type": "Feature",
  "properties": {
    "gn:admin1_code":"1",
    "gn:admin2_code":"TE",
    "gn:admin3_code":"67045.0",
    "gn:asciiname":"Castelmaidetto",
    "gn:country_code":"IT",
    "gn:dem":369,
    "gn:feature_class":"P",
    "gn:feature_code":"PPL",
    "gn:name":"Castelmaidetto",
    "gn:population":51,
    "gn:timezone":"Europe/Rome",
    "iso:country":"IT",
    "wof:name":"Castelmaidetto",
    "wof:placetype":"locality",
    "wof:population":51
},
  "geometry": {"coordinates":[13.66069,42.55199],"type":"Point"}
}