{
  "type": "Feature",
  "properties": {
    "gn:admin1_code":"5.0",
    "gn:admin2_code":"MO",
    "gn:admin3_code":"36035.0",
    "gn:asciiname":"Cento Croci",
    "gn:country_code":"IT",
    "gn:dem":1202,
    "gn:feature_class":"P",
    "gn:feature_code":"PPLL",
    "gn:name":"Cento Croci",
    "gn:population":4,
    "gn:timezone":"Europe/Rome",
    "iso:country":"IT",
    "wof:name":"Cento Croci",
    "wof:placetype":"locality",
    "wof:population":4
},
  "geometry": {"coordinates":[10.61585,44.26058],"type":"Point"}
}