{
  "type": "Feature",
  "properties": {
    "gn:gn_country":"IT",
    "gn:gn_fcode":"PPLA3",
    "gn:gn_pop":565,
    "gn:population":183,
    "iso:country":"IT",
    "name:azb_x_preferred":[
        "\u0631\u0648\u0628\u0648\u0631\u0646\u062a"
    ],
    "name:bel_x_preferred":[
        "\u0420\u0430\u0431\u0443\u0440\u044d\u043d\u0442"
    ],
    "name:bul_x_preferred":[
        "\u0420\u043e\u0431\u0443\u0440\u0435\u043d\u0442"
    ],
    "name:cat_x_preferred":[
        "Roburent"
    ],
    "name:ceb_x_preferred":[
        "Roburent"
    ],
    "name:deu_x_preferred":[
        "Roburent"
    ],
    "name:eng_x_preferred":[
        "Roburent"
    ],
    "name:epo_x_preferred":[
        "Roburent"
    ],
    "name:eus_x_preferred":[
        "Roburent"
    ],
    "name:fas_x_preferred":[
        "\u0631\u0648\u0628\u0648\u0631\u0646\u062a"
    ],
    "name:fra_x_preferred":[
        "Roburent"
    ],
    "name:hun_x_preferred":[
        "Roburent"
    ],
    "name:hye_x_preferred":[
        "\u054c\u0578\u0562\u0578\u0582\u0580\u0565\u0576\u057f"
    ],
    "name:ind_x_preferred":[
        "Roburent"
    ],
    "name:ita_x_preferred":[
        "Roburent"
    ],
    "name:jpn_x_preferred":[
        "\u30ed\u30d6\u30ec\u30f3\u30c8"
    ],
    "name:kaz_x_preferred":[
        "\u0420\u043e\u0431\u0443\u0440\u0435\u043d\u0442"
    ],
    "name:lat_x_preferred":[
        "Roboretum"
    ],
    "name:lmo_x_preferred":[
        "Roburent"
    ],
    "name:msa_x_preferred":[
        "Roburent"
    ],
    "name:nan_x_preferred":[
        "Roburent"
    ],
    "name:nap_x_preferred":[
        "Roburent"
    ],
    "name:nld_x_preferred":[
        "Roburent"
    ],
    "name:oci_x_preferred":[
        "Roburent"
    ],
    "name:pms_x_preferred":[
        "Arburent"
    ],
    "name:pol_x_preferred":[
        "Roburent"
    ],
    "name:por_x_preferred":[
        "Roburent"
    ],
    "name:ron_x_preferred":[
        "Roburent"
    ],
    "name:rus_x_preferred":[
        "\u0420\u043e\u0431\u0443\u0440\u0435\u043d\u0442"
    ],
    "name:scn_x_preferred":[
        "Roburent"
    ],
    "name:spa_x_preferred":[
        "Roburent"
    ],
    "name:srp_x_preferred":[
        "Roburent"
    ],
    "name:tgl_x_preferred":[
        "Roburent"
    ],
    "name:ukr_x_preferred":[
        "\u0420\u043e\u0431\u0443\u0440\u0435\u043d\u0442"
    ],
    "name:uzb_x_preferred":[
        "Roburent"
    ],
    "name:vie_x_preferred":[
        "Roburent"
    ],
    "name:vol_x_preferred":[
        "Roburent"
    ],
    "name:war_x_preferred":[
        "Roburent"
    ],
    "name:zho_x_preferred":[
        "\u7f57\u5e03\u4f26\u7279"
    ],
    "qs_pg:aaroncc":"IT",
    "qs_pg:gn_country":"IT",
    "qs_pg:gn_fcode":"PPLA3",
    "qs_pg:gn_pop":565,
    "qs_pg:name":"Roburent",
    "qs_pg:name_adm0":"Italia",
    "qs_pg:name_adm1":"Piemonte",
    "qs_pg:photos_9k":1,
    "qs_pg:photos_9r":1,
    "qs_pg:photos_all":1,
    "qs_pg:photos_sr":0,
    "qs_pg:pop_sr":2,
    "qs_pg:qs_pg_placetype":"locality",
    "qs_pg:qs_pg_placetype_gp":"Town",
    "qs_pg:woe_adm0":23424853,
    "woe:adm0_id":23424853,
    "woe:name_adm0":"Italia",
    "woe:name_adm1":"Piemonte",
    "woe:placetype":"Town",
    "wof:name":"Roburent",
    "wof:placetype":"locality",
    "wof:population":183
},
  "geometry": {"coordinates":[7.89224,44.30633],"type":"Point"}
}