{
  "type": "Feature",
  "properties": {
    "gn:admin1_code":"8",
    "gn:admin2_code":"SV",
    "gn:admin3_code":"9023.0",
    "gn:asciiname":"Costa",
    "gn:country_code":"IT",
    "gn:dem":539,
    "gn:feature_class":"P",
    "gn:feature_code":"PPL",
    "gn:name":"Costa",
    "gn:population":25,
    "gn:timezone":"Europe/Rome",
    "iso:country":"IT",
    "wof:name":"Costa",
    "wof:placetype":"locality",
    "wof:population":25
},
  "geometry": {"coordinates":[8.18525,44.37951],"type":"Point"}
}