{
  "type": "Feature",
  "properties": {
    "gn:admin1_code":"5.0",
    "gn:admin2_code":"FC",
    "gn:admin3_code":"40046.0",
    "gn:asciiname":"Montegelli",
    "gn:country_code":"IT",
    "gn:dem":428,
    "gn:elevation":"421.0",
    "gn:feature_class":"P",
    "gn:feature_code":"PPL",
    "gn:name":"Montegelli",
    "gn:population":46,
    "gn:timezone":"Europe/Rome",
    "iso:country":"IT",
    "wof:name":"Montegelli",
    "wof:placetype":"locality",
    "wof:population":46
},
  "geometry": {"coordinates":[12.24615,43.97912],"type":"Point"}
}