{
  "type": "Feature",
  "properties": {
    "iso:country":"IT",
    "qs_pg:aaroncc":"IT",
    "qs_pg:name":"Singlin di Sotto",
    "qs_pg:name_adm0":"Italia",
    "qs_pg:name_adm1":"Valle d'Aosta",
    "qs_pg:photos":15,
    "qs_pg:photos_1k":3,
    "qs_pg:photos_9k":1,
    "qs_pg:photos_9r":1,
    "qs_pg:photos_all":15,
    "qs_pg:photos_sr":1,
    "qs_pg:pop_sr":0,
    "qs_pg:qs_pg_placetype":"locality",
    "qs_pg:qs_pg_placetype_gp":"Town",
    "qs_pg:woe_adm0":23424853,
    "woe:adm0_id":23424853,
    "woe:name_adm0":"Italia",
    "woe:name_adm1":"Valle d'Aosta",
    "woe:placetype":"Town",
    "wof:name":"Singlin di Sotto",
    "wof:placetype":"locality"
},
  "geometry": {"coordinates":[7.624962,45.891502],"type":"Point"}
}