{
  "type": "Feature",
  "properties": {
    "gn:admin1_code":"9",
    "gn:admin2_code":"BS",
    "gn:admin3_code":"17073.0",
    "gn:asciiname":"Corvione",
    "gn:country_code":"IT",
    "gn:dem":47,
    "gn:feature_class":"P",
    "gn:feature_code":"PPL",
    "gn:name":"Corvione",
    "gn:population":129,
    "gn:timezone":"Europe/Rome",
    "iso:country":"IT",
    "wof:name":"Corvione",
    "wof:placetype":"locality",
    "wof:population":129
},
  "geometry": {"coordinates":[10.3347,45.27172],"type":"Point"}
}