{
  "type": "Feature",
  "properties": {
    "gn:admin1_code":"11",
    "gn:admin2_code":"IS",
    "gn:admin3_code":"94020.0",
    "gn:asciiname":"Masserie Lotto",
    "gn:country_code":"IT",
    "gn:dem":451,
    "gn:feature_class":"P",
    "gn:feature_code":"PPL",
    "gn:name":"Masserie Lotto",
    "gn:population":33,
    "gn:timezone":"Europe/Rome",
    "iso:country":"IT",
    "wof:name":"Masserie Lotto",
    "wof:placetype":"locality",
    "wof:population":33
},
  "geometry": {"coordinates":[14.19909,41.66832],"type":"Point"}
}