{
  "type": "Feature",
  "properties": {
    "gn:admin1_code":"4",
    "gn:admin2_code":"SA",
    "gn:admin3_code":"65099.0",
    "gn:asciiname":"Casa Colucci",
    "gn:country_code":"IT",
    "gn:dem":18,
    "gn:feature_class":"P",
    "gn:feature_code":"PPL",
    "gn:name":"Casa Colucci",
    "gn:population":95,
    "gn:timezone":"Europe/Rome",
    "iso:country":"IT",
    "wof:name":"Casa Colucci",
    "wof:placetype":"locality",
    "wof:population":95
},
  "geometry": {"coordinates":[14.86916,40.63528],"type":"Point"}
}