{
  "type": "Feature",
  "properties": {
    "gn:admin1_code":"18.0",
    "gn:admin2_code":"TR",
    "gn:admin3_code":"55023.0",
    "gn:asciiname":"Villa Felici",
    "gn:country_code":"IT",
    "gn:dem":333,
    "gn:feature_class":"P",
    "gn:feature_code":"PPLL",
    "gn:name":"Villa Felici",
    "gn:population":4,
    "gn:timezone":"Europe/Rome",
    "iso:country":"IT",
    "wof:name":"Villa Felici",
    "wof:placetype":"locality",
    "wof:population":4
},
  "geometry": {"coordinates":[12.13501,42.70807],"type":"Point"}
}