{
  "type": "Feature",
  "properties": {
    "gn:gn_country":"IT",
    "gn:gn_fcode":"PPL",
    "gn:gn_pop":0,
    "gn:population":123,
    "iso:country":"IT",
    "name:arm_x_preferred":[
        "\u0544\u0561\u0580\u0565\u0562\u0565"
    ],
    "name:aze_x_preferred":[
        "Mareo"
    ],
    "name:baq_x_preferred":[
        "Marebbe"
    ],
    "name:bel_x_preferred":[
        "\u041c\u0430\u0440\u044d\u0431\u044d"
    ],
    "name:bul_x_preferred":[
        "\u041c\u0430\u0440\u0435\u0431\u0435"
    ],
    "name:cat_x_preferred":[
        "Mareo"
    ],
    "name:chi_x_preferred":[
        "\u9a6c\u96f7\u8d1d"
    ],
    "name:deu_x_preferred":[
        "Enneberg Pfarre"
    ],
    "name:dut_x_preferred":[
        "Mareo"
    ],
    "name:eng_x_preferred":[
        "Mareo"
    ],
    "name:epo_x_preferred":[
        "Marebbe"
    ],
    "name:est_x_preferred":[
        "Mareo vald"
    ],
    "name:fra_x_preferred":[
        "Marebbe"
    ],
    "name:fre_x_preferred":[
        "Marebbe"
    ],
    "name:ger_x_preferred":[
        "Enneberg"
    ],
    "name:hun_x_preferred":[
        "Marebbe"
    ],
    "name:ina_x_preferred":[
        "Marebbe"
    ],
    "name:ita_x_preferred":[
        "Marebbe"
    ],
    "name:jpn_x_preferred":[
        "\u30de\u30ec\u30c3\u30d9"
    ],
    "name:kaz_x_preferred":[
        "\u041c\u0430\u0440\u0435\u0431\u0431\u0435"
    ],
    "name:lat_x_preferred":[
        "Marebum"
    ],
    "name:lmo_x_preferred":[
        "Marebbe"
    ],
    "name:may_x_preferred":[
        "Mareo"
    ],
    "name:nap_x_preferred":[
        "Marebbe"
    ],
    "name:nld_x_preferred":[
        "Mareo"
    ],
    "name:nob_x_preferred":[
        "Mareo"
    ],
    "name:pms_x_preferred":[
        "Mareo"
    ],
    "name:pol_x_preferred":[
        "Marebbe"
    ],
    "name:por_x_preferred":[
        "Marebbe"
    ],
    "name:rum_x_preferred":[
        "Marebbe"
    ],
    "name:rus_x_preferred":[
        "\u041c\u0430\u0440\u0435\u0431\u0431\u0435"
    ],
    "name:scn_x_preferred":[
        "Marebbe"
    ],
    "name:spa_x_preferred":[
        "Marebbe"
    ],
    "name:srp_x_preferred":[
        "Pieve di Marebbe"
    ],
    "name:tgl_x_preferred":[
        "Mareo"
    ],
    "name:ukr_x_preferred":[
        "\u041c\u0430\u0440\u0435\u0431\u0431\u0435"
    ],
    "name:unk_x_variant":[
        "Marebbe"
    ],
    "name:uzb_x_preferred":[
        "Marebbe"
    ],
    "name:vie_x_preferred":[
        "Marebbe"
    ],
    "name:vol_x_preferred":[
        "Marebbe"
    ],
    "name:war_x_preferred":[
        "Mareo"
    ],
    "qs_pg:aaroncc":"IT",
    "qs_pg:gn_country":"IT",
    "qs_pg:gn_fcode":"PPL",
    "qs_pg:gn_pop":0,
    "qs_pg:name":"Pieve di Marebbe",
    "qs_pg:name_adm0":"Italia",
    "qs_pg:name_adm1":"Trentino-Alto Adige",
    "qs_pg:photos":55,
    "qs_pg:photos_1k":11,
    "qs_pg:photos_9k":1,
    "qs_pg:photos_9r":2,
    "qs_pg:photos_all":55,
    "qs_pg:photos_sr":2,
    "qs_pg:pop_sr":0,
    "qs_pg:qs_pg_placetype":"locality",
    "qs_pg:qs_pg_placetype_gp":"Town",
    "qs_pg:woe_adm0":23424853,
    "woe:adm0_id":23424853,
    "woe:name_adm0":"Italia",
    "woe:name_adm1":"Trentino-Alto Adige",
    "woe:placetype":"Town",
    "wof:name":"Pieve di Marebbe",
    "wof:placetype":"locality",
    "wof:population":123
},
  "geometry": {"coordinates":[11.91978,46.71877],"type":"Point"}
}