{
  "type": "Feature",
  "properties": {
    "gn:admin1_code":"12.0",
    "gn:admin2_code":"TO",
    "gn:admin3_code":"1302.0",
    "gn:asciiname":"Corbiglia",
    "gn:country_code":"IT",
    "gn:dem":352,
    "gn:feature_class":"P",
    "gn:feature_code":"PPL",
    "gn:name":"Corbiglia",
    "gn:population":565,
    "gn:timezone":"Europe/Rome",
    "iso:country":"IT",
    "wof:name":"Corbiglia",
    "wof:placetype":"locality",
    "wof:population":565
},
  "geometry": {"coordinates":[7.49346,45.04885],"type":"Point"}
}