{
  "type": "Feature",
  "properties": {
    "gn:admin1_code":"20",
    "gn:admin2_code":"VR",
    "gn:admin3_code":"23091.0",
    "gn:asciiname":"Castiglione",
    "gn:country_code":"IT",
    "gn:dem":42,
    "gn:feature_class":"P",
    "gn:feature_code":"PPL",
    "gn:name":"Castiglione",
    "gn:population":270,
    "gn:timezone":"Europe/Rome",
    "iso:country":"IT",
    "wof:name":"Castiglione",
    "wof:placetype":"locality",
    "wof:population":270
},
  "geometry": {"coordinates":[11.05799,45.41474],"type":"Point"}
}