{
  "type": "Feature",
  "properties": {
    "gn:admin1_code":"20",
    "gn:admin2_code":"VR",
    "gn:admin3_code":"23091.0",
    "gn:asciiname":"Castiglione",
    "gn:country_code":"IT",
    "gn:dem":42,
    "gn:feature_class":"P",
    "gn:feature_code":"PPL",
    "gn:name":"Castiglione",
    "gn:population":270,
    "gn:timezone":"Europe/Rome",
    "iso:country":"IT",
    "name:bul_x_preferred":[
        "\u041a\u0430\u0441\u0442\u0438\u043b\u044c\u043e\u043d\u0435"
    ],
    "name:ceb_x_preferred":[
        "Castiglione"
    ],
    "name:deu_x_preferred":[
        "Castiglione"
    ],
    "name:fra_x_preferred":[
        "Castiglione"
    ],
    "name:ita_x_preferred":[
        "Castiglione"
    ],
    "name:jpn_x_preferred":[
        "\u30ab\u30b9\u30c6\u30a3\u30ea\u30aa\u30fc\u30cd"
    ],
    "name:kor_x_preferred":[
        "\uce74\uc2a4\ud2f8\ub9ac\uc624\ub124"
    ],
    "name:lat_x_preferred":[
        "Castillio"
    ],
    "name:nld_x_preferred":[
        "Castiglione"
    ],
    "name:por_x_preferred":[
        "Castiglione"
    ],
    "name:rus_x_preferred":[
        "\u041a\u0430\u0441\u0442\u0438\u043b\u044c\u043e\u043d\u0435"
    ],
    "name:sco_x_preferred":[
        "Castiglione"
    ],
    "name:spa_x_preferred":[
        "Castiglione"
    ],
    "name:srp_x_preferred":[
        "Kastiljone"
    ],
    "name:swe_x_preferred":[
        "Castiglione"
    ],
    "name:ukr_x_preferred":[
        "\u041a\u0430\u0441\u0442\u0456\u043b\u044c\u0439\u043e\u043d\u0435"
    ],
    "wof:name":"Castiglione",
    "wof:placetype":"locality",
    "wof:population":270
},
  "geometry": {"coordinates":[11.05799,45.41474],"type":"Point"}
}