{
  "type": "Feature",
  "properties": {
    "gn:admin1_code":"19",
    "gn:admin2_code":"AO",
    "gn:admin3_code":"7072.0",
    "gn:asciiname":"Baravete",
    "gn:country_code":"IT",
    "gn:dem":953,
    "gn:feature_class":"P",
    "gn:feature_code":"PPL",
    "gn:name":"Baravete",
    "gn:population":12,
    "gn:timezone":"Europe/Rome",
    "iso:country":"IT",
    "wof:name":"Baravete",
    "wof:placetype":"locality",
    "wof:population":12
},
  "geometry": {"coordinates":[7.52698,45.7594],"type":"Point"}
}