{
  "type": "Feature",
  "properties": {
    "gn:admin1_code":"9",
    "gn:admin2_code":"MI",
    "gn:admin3_code":"15026.0",
    "gn:asciiname":"Follone-Magnana",
    "gn:country_code":"IT",
    "gn:dem":119,
    "gn:feature_class":"P",
    "gn:feature_code":"PPL",
    "gn:name":"Follone-Magnana",
    "gn:population":161,
    "gn:timezone":"Europe/Rome",
    "iso:country":"IT",
    "wof:name":"Follone-Magnana",
    "wof:placetype":"locality",
    "wof:population":161
},
  "geometry": {"coordinates":[8.82287,45.4564],"type":"Point"}
}