{
  "type": "Feature",
  "properties": {
    "gn:admin1_code":"15.0",
    "gn:admin2_code":"TP",
    "gn:admin3_code":"81012.0",
    "gn:asciiname":"Casa Catalano",
    "gn:country_code":"IT",
    "gn:dem":124,
    "gn:feature_class":"P",
    "gn:feature_code":"PPL",
    "gn:name":"Casa Catalano",
    "gn:population":0,
    "gn:timezone":"Europe/Rome",
    "iso:country":"IT",
    "wof:name":"Casa Catalano",
    "wof:placetype":"locality"
},
  "geometry": {"coordinates":[12.58333,37.75],"type":"Point"}
}