{
  "type": "Feature",
  "properties": {
    "iso:country":"IT",
    "name:eng_x_preferred":[
        "Portiglioni"
    ],
    "name:fra_x_preferred":[
        "Portiglioni"
    ],
    "name:hun_x_preferred":[
        "Portiglioni"
    ],
    "name:ita_x_preferred":[
        "Portiglioni"
    ],
    "name:nld_x_preferred":[
        "Portiglioni"
    ],
    "qs_pg:aaroncc":"IT",
    "qs_pg:name":"Portiglioni",
    "qs_pg:name_adm0":"Italia",
    "qs_pg:name_adm1":"Toscana",
    "qs_pg:photos":63,
    "qs_pg:photos_1k":13,
    "qs_pg:photos_9k":1,
    "qs_pg:photos_9r":2,
    "qs_pg:photos_all":63,
    "qs_pg:photos_sr":2,
    "qs_pg:pop_sr":0,
    "qs_pg:qs_pg_placetype":"locality",
    "qs_pg:qs_pg_placetype_gp":"Town",
    "qs_pg:woe_adm0":23424853,
    "woe:adm0_id":23424853,
    "woe:name_adm0":"Italia",
    "woe:name_adm1":"Toscana",
    "woe:placetype":"Town",
    "wof:name":"Portiglioni",
    "wof:placetype":"locality"
},
  "geometry": {"coordinates":[10.785055,42.886844],"type":"Point"}
}