{
  "type": "Feature",
  "properties": {
    "gn:admin1_code":"12",
    "gn:admin2_code":"TO",
    "gn:admin3_code":"1281.0",
    "gn:asciiname":"Balboutet",
    "gn:country_code":"IT",
    "gn:dem":1579,
    "gn:feature_class":"P",
    "gn:feature_code":"PPL",
    "gn:name":"Balboutet",
    "gn:population":30,
    "gn:timezone":"Europe/Rome",
    "iso:country":"IT",
    "wof:name":"Balboutet",
    "wof:placetype":"locality",
    "wof:population":30
},
  "geometry": {"coordinates":[7.01304,45.05127],"type":"Point"}
}