{
  "type": "Feature",
  "properties": {
    "gn:admin1_code":"5",
    "gn:admin2_code":"PR",
    "gn:admin3_code":"34025.0",
    "gn:asciiname":"Ca' Dottore",
    "gn:country_code":"IT",
    "gn:dem":136,
    "gn:feature_class":"P",
    "gn:feature_code":"PPL",
    "gn:name":"Ca' Dottore",
    "gn:population":11,
    "gn:timezone":"Europe/Rome",
    "iso:country":"IT",
    "wof:name":"Ca' Dottore",
    "wof:placetype":"locality",
    "wof:population":11
},
  "geometry": {"coordinates":[10.09849,44.80465],"type":"Point"}
}