{
  "type": "Feature",
  "properties": {
    "gn:admin1_code":"15.0",
    "gn:admin2_code":"SR",
    "gn:admin3_code":"89001.0",
    "gn:asciiname":"Camera II",
    "gn:country_code":"IT",
    "gn:dem":68,
    "gn:feature_class":"P",
    "gn:feature_code":"PPL",
    "gn:name":"Camera II",
    "gn:population":28,
    "gn:timezone":"Europe/Rome",
    "iso:country":"IT",
    "wof:name":"Camera II",
    "wof:placetype":"locality",
    "wof:population":28
},
  "geometry": {"coordinates":[15.1713,37.26973],"type":"Point"}
}