{
  "type": "Feature",
  "properties": {
    "gn:admin1_code":"12",
    "gn:admin2_code":"AL",
    "gn:admin3_code":"6148.0",
    "gn:asciiname":"Celio",
    "gn:country_code":"IT",
    "gn:dem":517,
    "gn:feature_class":"P",
    "gn:feature_code":"PPLL",
    "gn:name":"Celio",
    "gn:population":10,
    "gn:timezone":"Europe/Rome",
    "iso:country":"IT",
    "name:bre_x_preferred":[
        "Celio"
    ],
    "name:ceb_x_preferred":[
        "Celio"
    ],
    "name:deu_x_preferred":[
        "Celio"
    ],
    "name:fra_x_preferred":[
        "Celio"
    ],
    "name:ita_x_preferred":[
        "Celio"
    ],
    "name:jpn_x_preferred":[
        "\u30c1\u30a7\u30ea\u30aa"
    ],
    "name:kor_x_preferred":[
        "\uccbc\ub9ac\uc624"
    ],
    "name:pol_x_preferred":[
        "Celio"
    ],
    "name:rus_x_preferred":[
        "\u0427\u0435\u043b\u0438\u043e"
    ],
    "name:spa_x_preferred":[
        "Celio"
    ],
    "name:swe_x_preferred":[
        "Celio"
    ],
    "wof:name":"Celio",
    "wof:placetype":"locality",
    "wof:population":10
},
  "geometry": {"coordinates":[9.07972,44.67968],"type":"Point"}
}