{
  "type": "Feature",
  "properties": {
    "gn:admin1_code":"7.0",
    "gn:admin2_code":"RM",
    "gn:admin3_code":"58093.0",
    "gn:asciiname":"Monte Caminetto",
    "gn:country_code":"IT",
    "gn:dem":108,
    "gn:feature_class":"P",
    "gn:feature_code":"PPL",
    "gn:name":"Monte Caminetto",
    "gn:population":1451,
    "gn:timezone":"Europe/Rome",
    "iso:country":"IT",
    "wof:name":"Monte Caminetto",
    "wof:placetype":"locality",
    "wof:population":1451
},
  "geometry": {"coordinates":[12.47358,42.0665],"type":"Point"}
}