{
  "type": "Feature",
  "properties": {
    "gn:admin1_code":"5",
    "gn:admin2_code":"BO",
    "gn:admin3_code":"37051.0",
    "gn:asciiname":"Valdirosa",
    "gn:country_code":"IT",
    "gn:dem":877,
    "gn:feature_class":"P",
    "gn:feature_code":"PPL",
    "gn:name":"Valdirosa",
    "gn:population":12,
    "gn:timezone":"Europe/Rome",
    "iso:country":"IT",
    "wof:name":"Valdirosa",
    "wof:placetype":"locality",
    "wof:population":12
},
  "geometry": {"coordinates":[11.28703,44.17498],"type":"Point"}
}