{
  "type": "Feature",
  "properties": {
    "gn:admin1_code":"12",
    "gn:admin2_code":"AT",
    "gn:admin3_code":"5059.0",
    "gn:asciiname":"Bricco San Giovanni",
    "gn:country_code":"IT",
    "gn:dem":223,
    "gn:feature_class":"P",
    "gn:feature_code":"PPL",
    "gn:name":"Bricco San Giovanni",
    "gn:population":22,
    "gn:timezone":"Europe/Rome",
    "iso:country":"IT",
    "wof:name":"Bricco San Giovanni",
    "wof:placetype":"locality",
    "wof:population":22
},
  "geometry": {"coordinates":[8.17844,44.81547],"type":"Point"}
}