{
  "type": "Feature",
  "properties": {
    "gn:admin1_code":"4.0",
    "gn:admin3_code":"63055.0",
    "gn:asciiname":"Fornillo",
    "gn:country_code":"IT",
    "gn:dem":40,
    "gn:feature_class":"P",
    "gn:feature_code":"PPL",
    "gn:name":"Fornillo",
    "gn:population":857,
    "gn:timezone":"Europe/Rome",
    "iso:country":"IT",
    "wof:name":"Fornillo",
    "wof:placetype":"locality",
    "wof:population":857
},
  "geometry": {"coordinates":[14.52417,40.79891],"type":"Point"}
}