{
  "type": "Feature",
  "properties": {
    "gn:admin1_code":"20",
    "gn:admin2_code":"VI",
    "gn:admin3_code":"24004.0",
    "gn:asciiname":"Sant'Agostino",
    "gn:country_code":"IT",
    "gn:dem":34,
    "gn:feature_class":"P",
    "gn:feature_code":"PPL",
    "gn:name":"Sant'Agostino",
    "gn:population":288,
    "gn:timezone":"Europe/Rome",
    "iso:country":"IT",
    "name:ceb_x_preferred":[
        "Sant'Agostino"
    ],
    "name:deu_x_preferred":[
        "Sant\u2019Agostino"
    ],
    "name:fra_x_preferred":[
        "Sant'Agostino"
    ],
    "name:ita_x_preferred":[
        "Sant'Agostino"
    ],
    "name:nld_x_preferred":[
        "Sant'Agostino"
    ],
    "name:nor_x_preferred":[
        "Sant'Agostino"
    ],
    "name:srp_x_preferred":[
        "Sant'Agostino"
    ],
    "name:swe_x_preferred":[
        "Sant'Agostino"
    ],
    "wof:name":"Sant'Agostino",
    "wof:placetype":"locality",
    "wof:population":288
},
  "geometry": {"coordinates":[11.50657,45.511],"type":"Point"}
}