{
  "type": "Feature",
  "properties": {
    "gn:admin1_code":"14",
    "gn:admin2_code":"CA",
    "gn:admin3_code":"92003.0",
    "gn:asciiname":"Sant'Andrea",
    "gn:country_code":"IT",
    "gn:dem":12,
    "gn:feature_class":"P",
    "gn:feature_code":"PPL",
    "gn:name":"Sant'Andrea",
    "gn:population":51,
    "gn:timezone":"Europe/Rome",
    "iso:country":"IT",
    "name:ceb_x_preferred":[
        "Sant'Andrea"
    ],
    "name:deu_x_preferred":[
        "Sant\u2019Andrea"
    ],
    "name:fra_x_preferred":[
        "Sant'Andrea"
    ],
    "name:ita_x_preferred":[
        "Sant'Andrea"
    ],
    "name:por_x_preferred":[
        "Sant'Andrea"
    ],
    "name:sco_x_preferred":[
        "Sant'Andrea"
    ],
    "name:slv_x_preferred":[
        "Sant'Andrea"
    ],
    "name:srp_x_preferred":[
        "Sant'Andrea"
    ],
    "name:swe_x_preferred":[
        "Sant'Andrea"
    ],
    "wof:name":"Sant'Andrea",
    "wof:placetype":"locality",
    "wof:population":51
},
  "geometry": {"coordinates":[9.01546,39.29294],"type":"Point"}
}