{
  "type": "Feature",
  "properties": {
    "gn:admin1_code":"12",
    "gn:admin2_code":"CN",
    "gn:admin3_code":"4117.0",
    "gn:asciiname":"Mondini",
    "gn:country_code":"IT",
    "gn:dem":322,
    "gn:feature_class":"P",
    "gn:feature_code":"PPL",
    "gn:name":"Mondini",
    "gn:population":40,
    "gn:timezone":"Europe/Rome",
    "iso:country":"IT",
    "wof:name":"Mondini",
    "wof:placetype":"locality",
    "wof:population":40
},
  "geometry": {"coordinates":[7.73098,44.64034],"type":"Point"}
}