{
  "type": "Feature",
  "properties": {
    "gn:admin1_code":"13",
    "gn:admin2_code":"FG",
    "gn:admin3_code":"71043.0",
    "gn:asciiname":"Santa Barbara-Ripa",
    "gn:country_code":"IT",
    "gn:dem":37,
    "gn:feature_class":"P",
    "gn:feature_code":"PPLL",
    "gn:name":"Santa Barbara-Ripa",
    "gn:population":10,
    "gn:timezone":"Europe/Rome",
    "iso:country":"IT",
    "wof:name":"Santa Barbara-Ripa",
    "wof:placetype":"locality",
    "wof:population":10
},
  "geometry": {"coordinates":[15.8628,41.92571],"type":"Point"}
}