{
  "type": "Feature",
  "properties": {
    "gn:admin1_code":"16.0",
    "gn:admin2_code":"SI",
    "gn:admin3_code":"52019.0",
    "gn:asciiname":"Bagnaia",
    "gn:country_code":"IT",
    "gn:dem":237,
    "gn:feature_class":"P",
    "gn:feature_code":"PPL",
    "gn:name":"Bagnaia",
    "gn:population":16,
    "gn:timezone":"Europe/Rome",
    "iso:country":"IT",
    "wof:name":"Bagnaia",
    "wof:placetype":"locality",
    "wof:population":16
},
  "geometry": {"coordinates":[11.29321,43.21746],"type":"Point"}
}