{
  "type": "Feature",
  "properties": {
    "gn:admin1_code":"20.0",
    "gn:admin2_code":"TV",
    "gn:admin3_code":"26052.0",
    "gn:asciiname":"Galvagna",
    "gn:country_code":"IT",
    "gn:dem":13,
    "gn:feature_class":"P",
    "gn:feature_code":"PPL",
    "gn:name":"Galvagna",
    "gn:population":30,
    "gn:timezone":"Europe/Rome",
    "iso:country":"IT",
    "name:und_x_variant":[
        "Casale Galvagna",
        "Casa Galvagna"
    ],
    "wof:name":"Galvagna",
    "wof:placetype":"locality",
    "wof:population":30
},
  "geometry": {"coordinates":[12.443,45.77371],"type":"Point"}
}