{
  "type": "Feature",
  "properties": {
    "gn:admin1_code":"18",
    "gn:admin2_code":"PG",
    "gn:admin3_code":"54034.0",
    "gn:asciiname":"Schiagni",
    "gn:country_code":"IT",
    "gn:dem":596,
    "gn:feature_class":"P",
    "gn:feature_code":"PPL",
    "gn:name":"Schiagni",
    "gn:population":13,
    "gn:timezone":"Europe/Rome",
    "iso:country":"IT",
    "wof:name":"Schiagni",
    "wof:placetype":"locality",
    "wof:population":13
},
  "geometry": {"coordinates":[12.81671,43.11879],"type":"Point"}
}