{
  "type": "Feature",
  "properties": {
    "gn:admin1_code":"7",
    "gn:admin2_code":"RM",
    "gn:admin3_code":"58091.0",
    "gn:admin4_code":"5809109.0",
    "gn:asciiname":"Santa Fumia II",
    "gn:country_code":"IT",
    "gn:dem":152,
    "gn:feature_class":"P",
    "gn:feature_code":"PPL",
    "gn:name":"Santa Fumia II",
    "gn:population":78,
    "gn:timezone":"Europe/Rome",
    "iso:country":"IT",
    "wof:name":"Santa Fumia II",
    "wof:placetype":"locality",
    "wof:population":78
},
  "geometry": {"coordinates":[12.59284,41.73715],"type":"Point"}
}