{
  "type": "Feature",
  "properties": {
    "gn:admin1_code":"9",
    "gn:admin2_code":"CO",
    "gn:admin3_code":"13236.0",
    "gn:asciiname":"Erno",
    "gn:country_code":"IT",
    "gn:dem":727,
    "gn:feature_class":"P",
    "gn:feature_code":"PPL",
    "gn:name":"Erno",
    "gn:population":55,
    "gn:timezone":"Europe/Rome",
    "iso:country":"IT",
    "wof:name":"Erno",
    "wof:placetype":"locality",
    "wof:population":55
},
  "geometry": {"coordinates":[9.17197,45.91087],"type":"Point"}
}