{
  "type": "Feature",
  "properties": {
    "gn:admin1_code":"12",
    "gn:admin2_code":"BI",
    "gn:admin3_code":"96070.0",
    "gn:asciiname":"Zoccolo",
    "gn:country_code":"IT",
    "gn:dem":629,
    "gn:feature_class":"P",
    "gn:feature_code":"PPL",
    "gn:name":"Zoccolo",
    "gn:population":64,
    "gn:timezone":"Europe/Rome",
    "iso:country":"IT",
    "wof:name":"Zoccolo",
    "wof:placetype":"locality",
    "wof:population":64
},
  "geometry": {"coordinates":[8.17316,45.66995],"type":"Point"}
}