{
  "type": "Feature",
  "properties": {
    "gn:admin1_code":"5.0",
    "gn:admin2_code":"RE",
    "gn:admin3_code":"35045.0",
    "gn:asciiname":"Minozzo",
    "gn:country_code":"IT",
    "gn:dem":782,
    "gn:feature_class":"P",
    "gn:feature_code":"PPL",
    "gn:name":"Minozzo",
    "gn:population":269,
    "gn:timezone":"Europe/Rome",
    "iso:country":"IT",
    "wof:name":"Minozzo",
    "wof:placetype":"locality",
    "wof:population":269
},
  "geometry": {"coordinates":[10.43426,44.35773],"type":"Point"}
}