{
  "type": "Feature",
  "properties": {
    "gn:admin1_code":"9.0",
    "gn:admin2_code":"CR",
    "gn:admin3_code":"19103.0",
    "gn:asciiname":"Brancere",
    "gn:country_code":"IT",
    "gn:dem":34,
    "gn:elevation":"36.0",
    "gn:feature_class":"P",
    "gn:feature_code":"PPL",
    "gn:name":"Brancere",
    "gn:population":113,
    "gn:timezone":"Europe/Rome",
    "iso:country":"IT",
    "wof:name":"Brancere",
    "wof:placetype":"locality",
    "wof:population":113
},
  "geometry": {"coordinates":[10.06933,45.06763],"type":"Point"}
}