{
  "type": "Feature",
  "properties": {
    "gn:admin1_code":"5",
    "gn:admin2_code":"PC",
    "gn:admin3_code":"33008.0",
    "gn:asciiname":"Soprarivo",
    "gn:country_code":"IT",
    "gn:dem":52,
    "gn:feature_class":"P",
    "gn:feature_code":"PPL",
    "gn:name":"Soprarivo",
    "gn:population":16,
    "gn:timezone":"Europe/Rome",
    "iso:country":"IT",
    "wof:name":"Soprarivo",
    "wof:placetype":"locality",
    "wof:population":16
},
  "geometry": {"coordinates":[9.57669,45.09808],"type":"Point"}
}