{
  "type": "Feature",
  "properties": {
    "gn:admin1_code":"16.0",
    "gn:admin2_code":"AR",
    "gn:admin3_code":"51001.0",
    "gn:asciiname":"Catigliano",
    "gn:country_code":"IT",
    "gn:dem":353,
    "gn:feature_class":"P",
    "gn:feature_code":"PPL",
    "gn:name":"Catigliano",
    "gn:population":39,
    "gn:timezone":"Europe/Rome",
    "iso:country":"IT",
    "wof:name":"Catigliano",
    "wof:placetype":"locality",
    "wof:population":39
},
  "geometry": {"coordinates":[12.07022,43.50179],"type":"Point"}
}