{
  "type": "Feature",
  "properties": {
    "gn:admin1_code":"12",
    "gn:admin2_code":"AL",
    "gn:admin3_code":"6003.0",
    "gn:asciiname":"Porrona",
    "gn:country_code":"IT",
    "gn:dem":119,
    "gn:feature_class":"P",
    "gn:feature_code":"PPL",
    "gn:name":"Porrona",
    "gn:population":78,
    "gn:timezone":"Europe/Rome",
    "iso:country":"IT",
    "name:deu_x_preferred":[
        "Porrona"
    ],
    "name:ita_x_preferred":[
        "Porrona"
    ],
    "name:nld_x_preferred":[
        "Porrona"
    ],
    "name:srp_x_preferred":[
        "\u041f\u043e\u0440\u043e\u043d\u0430"
    ],
    "wof:name":"Porrona",
    "wof:placetype":"locality",
    "wof:population":78
},
  "geometry": {"coordinates":[8.7567,44.87192],"type":"Point"}
}