{
  "type": "Feature",
  "properties": {
    "gn:admin1_code":"12",
    "gn:admin2_code":"VC",
    "gn:admin3_code":"2158.0",
    "gn:asciiname":"Cascine Stra",
    "gn:country_code":"IT",
    "gn:dem":142,
    "gn:feature_class":"P",
    "gn:feature_code":"PPL",
    "gn:name":"Cascine Str\u00e0",
    "gn:population":18,
    "gn:timezone":"Europe/Rome",
    "iso:country":"IT",
    "name:und_x_variant":[
        "Cascine Str\u00e0"
    ],
    "wof:name":"Cascine Stra",
    "wof:placetype":"locality",
    "wof:population":18
},
  "geometry": {"coordinates":[8.33758,45.32516],"type":"Point"}
}