{
  "type": "Feature",
  "properties": {
    "gn:admin1_code":"4",
    "gn:admin2_code":"CE",
    "gn:admin3_code":"61041.0",
    "gn:asciiname":"Madonna del Bagno",
    "gn:country_code":"IT",
    "gn:dem":168,
    "gn:feature_class":"P",
    "gn:feature_code":"PPL",
    "gn:name":"Madonna del Bagno",
    "gn:population":29,
    "gn:timezone":"Europe/Rome",
    "iso:country":"IT",
    "wof:name":"Madonna del Bagno",
    "wof:placetype":"locality",
    "wof:population":29
},
  "geometry": {"coordinates":[14.41654,41.30021],"type":"Point"}
}