{
  "type": "Feature",
  "properties": {
    "gn:country":"IT",
    "gn:fcode":"PPL",
    "gn:population":0,
    "iso:country":"IT",
    "name:ceb_x_preferred":[
        "Fontane Bianche"
    ],
    "name:ita_x_preferred":[
        "Fontane Bianche"
    ],
    "name:scn_x_preferred":[
        "Funtani Janchi"
    ],
    "name:srp_x_preferred":[
        "\u0424\u043e\u043d\u0442\u0430\u043d\u0435 \u0411\u0458\u0430\u043d\u043a\u0435"
    ],
    "qs_pg:aaroncc":"IT",
    "qs_pg:gn_country":"IT",
    "qs_pg:gn_fcode":"PPL",
    "qs_pg:gn_pop":0,
    "qs_pg:name":"Fontane Bianche",
    "qs_pg:name_adm0":"Italia",
    "qs_pg:name_adm1":"Sicilia",
    "qs_pg:photos":274,
    "qs_pg:photos_1k":56,
    "qs_pg:photos_9k":1,
    "qs_pg:photos_9r":4,
    "qs_pg:photos_all":274,
    "qs_pg:photos_sr":5,
    "qs_pg:pop_sr":0,
    "qs_pg:qs_pg_placetype":"locality",
    "qs_pg:qs_pg_placetype_gp":"Town",
    "qs_pg:woe_adm0":23424853,
    "woe:adm0_id":23424853,
    "woe:name_adm0":"Italia",
    "woe:name_adm1":"Sicilia",
    "woe:placetype":"Town",
    "wof:name":"Fontane Bianche",
    "wof:placetype":"locality",
    "wof:population":889
},
  "geometry": {"coordinates":[15.20929,36.96628],"type":"Point"}
}