{
  "type": "Feature",
  "properties": {
    "gn:admin1_code":"1.0",
    "gn:admin2_code":"CH",
    "gn:admin3_code":"69017.0",
    "gn:asciiname":"Zona Industriale Casoli Est",
    "gn:country_code":"IT",
    "gn:dem":134,
    "gn:feature_class":"P",
    "gn:feature_code":"PPL",
    "gn:name":"Zona Industriale Casoli Est",
    "gn:population":0,
    "gn:timezone":"Europe/Rome",
    "iso:country":"IT",
    "wof:name":"Zona Industriale Casoli Est",
    "wof:placetype":"locality"
},
  "geometry": {"coordinates":[14.32146,42.12337],"type":"Point"}
}