{
  "type": "Feature",
  "properties": {
    "gn:admin1_code":"12.0",
    "gn:admin2_code":"VB",
    "gn:admin3_code":"103071.0",
    "gn:asciiname":"Coate",
    "gn:country_code":"IT",
    "gn:dem":1939,
    "gn:feature_class":"P",
    "gn:feature_code":"PPL",
    "gn:name":"Coat\u00e9",
    "gn:population":0,
    "gn:timezone":"Europe/Rome",
    "iso:country":"IT",
    "wof:name":"Coate",
    "wof:placetype":"locality"
},
  "geometry": {"coordinates":[8.23333,46.25],"type":"Point"}
}