{
  "type": "Feature",
  "properties": {
    "gn:admin1_code":"10",
    "gn:admin2_code":"MC",
    "gn:admin3_code":"43032.0",
    "gn:asciiname":"Bivio Gallo",
    "gn:country_code":"IT",
    "gn:dem":427,
    "gn:feature_class":"P",
    "gn:feature_code":"PPL",
    "gn:name":"Bivio Gallo",
    "gn:population":20,
    "gn:timezone":"Europe/Rome",
    "iso:country":"IT",
    "wof:name":"Bivio Gallo",
    "wof:placetype":"locality",
    "wof:population":20
},
  "geometry": {"coordinates":[13.44889,43.03461],"type":"Point"}
}