{
  "type": "Feature",
  "properties": {
    "gn:admin1_code":"12.0",
    "gn:admin2_code":"CN",
    "gn:admin3_code":"4132.0",
    "gn:asciiname":"Ornati",
    "gn:country_code":"IT",
    "gn:dem":346,
    "gn:feature_class":"P",
    "gn:feature_code":"PPL",
    "gn:name":"Ornati",
    "gn:population":15,
    "gn:timezone":"Europe/Rome",
    "iso:country":"IT",
    "wof:name":"Ornati",
    "wof:placetype":"locality",
    "wof:population":15
},
  "geometry": {"coordinates":[7.95676,44.5755],"type":"Point"}
}