{
  "type": "Feature",
  "properties": {
    "gn:admin1_code":"16",
    "gn:admin2_code":"LU",
    "gn:admin3_code":"46020.0",
    "gn:asciiname":"Promiana",
    "gn:country_code":"IT",
    "gn:dem":570,
    "gn:feature_class":"P",
    "gn:feature_code":"PPLL",
    "gn:name":"Promiana",
    "gn:population":7,
    "gn:timezone":"Europe/Rome",
    "iso:country":"IT",
    "wof:name":"Promiana",
    "wof:placetype":"locality",
    "wof:population":7
},
  "geometry": {"coordinates":[10.4137,44.0703],"type":"Point"}
}