{
  "type": "Feature",
  "properties": {
    "gn:admin1_code":"12",
    "gn:admin2_code":"CN",
    "gn:admin3_code":"4245.0",
    "gn:asciiname":"Pratoferrero",
    "gn:country_code":"IT",
    "gn:dem":481,
    "gn:feature_class":"P",
    "gn:feature_code":"PPL",
    "gn:name":"Pratoferrero",
    "gn:population":27,
    "gn:timezone":"Europe/Rome",
    "iso:country":"IT",
    "wof:name":"Pratoferrero",
    "wof:placetype":"locality",
    "wof:population":27
},
  "geometry": {"coordinates":[7.72595,44.37469],"type":"Point"}
}