{
  "type": "Feature",
  "properties": {
    "gn:admin1_code":"5.0",
    "gn:admin2_code":"BO",
    "gn:admin3_code":"37044.0",
    "gn:asciiname":"Valle",
    "gn:country_code":"IT",
    "gn:dem":425,
    "gn:elevation":"433.0",
    "gn:feature_class":"P",
    "gn:feature_code":"PPL",
    "gn:name":"Valle",
    "gn:population":39,
    "gn:timezone":"Europe/Rome",
    "iso:country":"IT",
    "wof:name":"Valle",
    "wof:placetype":"locality",
    "wof:population":39
},
  "geometry": {"coordinates":[11.22546,44.24084000000001],"type":"Point"}
}