{
  "type": "Feature",
  "properties": {
    "gn:admin1_code":"1",
    "gn:admin2_code":"CH",
    "gn:admin3_code":"69035.0",
    "gn:asciiname":"Piattelli",
    "gn:country_code":"IT",
    "gn:dem":55,
    "gn:feature_class":"P",
    "gn:feature_code":"PPL",
    "gn:name":"Piattelli",
    "gn:population":176,
    "gn:timezone":"Europe/Rome",
    "iso:country":"IT",
    "wof:name":"Piattelli",
    "wof:placetype":"locality",
    "wof:population":176
},
  "geometry": {"coordinates":[14.29512,42.3968],"type":"Point"}
}