{
  "type": "Feature",
  "properties": {
    "gn:admin1_code":"7",
    "gn:admin2_code":"VT",
    "gn:admin3_code":"56008.0",
    "gn:asciiname":"Sant'Antonio",
    "gn:country_code":"IT",
    "gn:dem":340,
    "gn:feature_class":"P",
    "gn:feature_code":"PPL",
    "gn:name":"Sant'Antonio",
    "gn:population":31,
    "gn:timezone":"Europe/Rome",
    "iso:country":"IT",
    "wof:name":"Sant'Antonio",
    "wof:placetype":"locality",
    "wof:population":31
},
  "geometry": {"coordinates":[11.99932,42.60243],"type":"Point"}
}