{
  "type": "Feature",
  "properties": {
    "gn:admin1_code":"12",
    "gn:admin2_code":"CN",
    "gn:admin3_code":"4214.0",
    "gn:asciiname":"Valle dei Lunghi",
    "gn:country_code":"IT",
    "gn:dem":223,
    "gn:feature_class":"P",
    "gn:feature_code":"PPL",
    "gn:name":"Valle dei Lunghi",
    "gn:population":119,
    "gn:timezone":"Europe/Rome",
    "iso:country":"IT",
    "wof:name":"Valle dei Lunghi",
    "wof:placetype":"locality",
    "wof:population":119
},
  "geometry": {"coordinates":[7.96722,44.78617],"type":"Point"}
}