{
  "type": "Feature",
  "properties": {
    "gn:admin1_code":"17.0",
    "gn:admin2_code":"TN",
    "gn:admin3_code":"22205.0",
    "gn:asciiname":"Gardolo di Mezzo",
    "gn:country_code":"IT",
    "gn:dem":347,
    "gn:elevation":"363.0",
    "gn:feature_class":"P",
    "gn:feature_code":"PPL",
    "gn:name":"Gardolo di Mezzo",
    "gn:population":290,
    "gn:timezone":"Europe/Rome",
    "iso:country":"IT",
    "wof:name":"Gardolo di Mezzo",
    "wof:placetype":"locality",
    "wof:population":290
},
  "geometry": {"coordinates":[11.11623,46.11536],"type":"Point"}
}