{
  "type": "Feature",
  "properties": {
    "gn:admin1_code":"12",
    "gn:admin2_code":"CN",
    "gn:admin3_code":"4207.0",
    "gn:asciiname":"Saretto",
    "gn:country_code":"IT",
    "gn:dem":1330,
    "gn:feature_class":"P",
    "gn:feature_code":"PPLL",
    "gn:name":"Saretto",
    "gn:population":6,
    "gn:timezone":"Europe/Rome",
    "iso:country":"IT",
    "wof:name":"Saretto",
    "wof:placetype":"locality",
    "wof:population":6
},
  "geometry": {"coordinates":[7.21772,44.45993],"type":"Point"}
}