{
  "type": "Feature",
  "properties": {
    "gn:admin1_code":"8",
    "gn:admin2_code":"IM",
    "gn:admin3_code":"8011.0",
    "gn:asciiname":"Magauda",
    "gn:country_code":"IT",
    "gn:dem":268,
    "gn:feature_class":"P",
    "gn:feature_code":"PPL",
    "gn:name":"Magauda",
    "gn:population":29,
    "gn:timezone":"Europe/Rome",
    "iso:country":"IT",
    "wof:name":"Magauda",
    "wof:placetype":"locality",
    "wof:population":29
},
  "geometry": {"coordinates":[7.59993,43.82427],"type":"Point"}
}