{
  "type": "Feature",
  "properties": {
    "gn:admin1_code":"5",
    "gn:admin2_code":"PR",
    "gn:admin3_code":"34026.0",
    "gn:asciiname":"Valcieca",
    "gn:country_code":"IT",
    "gn:dem":898,
    "gn:feature_class":"P",
    "gn:feature_code":"PPL",
    "gn:name":"Valcieca",
    "gn:population":44,
    "gn:timezone":"Europe/Rome",
    "iso:country":"IT",
    "wof:name":"Valcieca",
    "wof:placetype":"locality",
    "wof:population":44
},
  "geometry": {"coordinates":[10.16989,44.39079],"type":"Point"}
}