{
  "type": "Feature",
  "properties": {
    "gn:admin1_code":"18.0",
    "gn:admin2_code":"PG",
    "gn:admin3_code":"54011.0",
    "gn:asciiname":"Pistrino di Sopra",
    "gn:country_code":"IT",
    "gn:dem":294,
    "gn:feature_class":"P",
    "gn:feature_code":"PPL",
    "gn:name":"Pistrino di Sopra",
    "gn:population":44,
    "gn:timezone":"Europe/Rome",
    "iso:country":"IT",
    "wof:name":"Pistrino di Sopra",
    "wof:placetype":"locality",
    "wof:population":44
},
  "geometry": {"coordinates":[12.13775,43.51335],"type":"Point"}
}