{
  "type": "Feature",
  "properties": {
    "gn:admin1_code":"3",
    "gn:admin2_code":"CZ",
    "gn:admin3_code":"79116.0",
    "gn:asciiname":"Lacco",
    "gn:country_code":"IT",
    "gn:dem":24,
    "gn:feature_class":"P",
    "gn:feature_code":"PPL",
    "gn:name":"Lacco",
    "gn:population":80,
    "gn:timezone":"Europe/Rome",
    "iso:country":"IT",
    "wof:name":"Lacco",
    "wof:placetype":"locality",
    "wof:population":80
},
  "geometry": {"coordinates":[16.54466,38.64512],"type":"Point"}
}