{
  "type": "Feature",
  "properties": {
    "gn:admin1_code":"9",
    "gn:admin2_code":"CO",
    "gn:admin3_code":"13062.0",
    "gn:asciiname":"Mondrago",
    "gn:country_code":"IT",
    "gn:dem":1134,
    "gn:feature_class":"P",
    "gn:feature_code":"PPLL",
    "gn:name":"Mondrago",
    "gn:population":9,
    "gn:timezone":"Europe/Rome",
    "iso:country":"IT",
    "wof:name":"Mondrago",
    "wof:placetype":"locality",
    "wof:population":9
},
  "geometry": {"coordinates":[9.10993,46.10101],"type":"Point"}
}