{
  "type": "Feature",
  "properties": {
    "iso:country":"IT",
    "name:eng_x_preferred":[
        "Apice"
    ],
    "name:epo_x_preferred":[
        "Apice"
    ],
    "name:fra_x_preferred":[
        "Apice"
    ],
    "name:ita_x_preferred":[
        "Apice"
    ],
    "name:nap_x_preferred":[
        "Apice"
    ],
    "name:nld_x_preferred":[
        "Apice"
    ],
    "name:pol_x_preferred":[
        "Apice"
    ],
    "name:por_x_preferred":[
        "Apice"
    ],
    "qs:a0":"Italia",
    "qs:a1":"*Benevento",
    "qs:a1r":"0Campania",
    "qs:adm0":"Italia",
    "qs:la_lc":"*",
    "qs:level":"locality",
    "qs:loc":"Apice Vecchio",
    "qs:loc_alt":"Apice Vecchio",
    "qs:pop":0,
    "qs:type":"buffered point",
    "wof:name":"Apice Vecchio",
    "wof:placetype":"locality"
},
  "geometry": {"coordinates":[14.93167,41.120831],"type":"Point"}
}