{
  "type": "Feature",
  "properties": {
    "gn:admin1_code":"10.0",
    "gn:admin2_code":"PU",
    "gn:admin3_code":"41003.0",
    "gn:asciiname":"Casinina",
    "gn:country_code":"IT",
    "gn:dem":188,
    "gn:feature_class":"P",
    "gn:feature_code":"PPL",
    "gn:name":"Casinina",
    "gn:population":1152,
    "gn:timezone":"Europe/Rome",
    "iso:country":"IT",
    "wof:name":"Casinina",
    "wof:placetype":"locality",
    "wof:population":1152
},
  "geometry": {"coordinates":[12.58333,43.81667],"type":"Point"}
}