{
  "type": "Feature",
  "properties": {
    "gn:admin1_code":"20",
    "gn:admin2_code":"BL",
    "gn:admin3_code":"25026.0",
    "gn:asciiname":"Pezze",
    "gn:country_code":"IT",
    "gn:dem":680,
    "gn:feature_class":"P",
    "gn:feature_code":"PPL",
    "gn:name":"Pezz\u00e8",
    "gn:population":110,
    "gn:timezone":"Europe/Rome",
    "iso:country":"IT",
    "name:und_x_variant":[
        "Pezz\u00e8"
    ],
    "wof:name":"Pezze",
    "wof:placetype":"locality",
    "wof:population":110
},
  "geometry": {"coordinates":[11.73543,46.04681],"type":"Point"}
}