{
  "type": "Feature",
  "properties": {
    "gn:admin1_code":"19",
    "gn:admin2_code":"AO",
    "gn:admin3_code":"7070.0",
    "gn:asciiname":"Bien",
    "gn:country_code":"IT",
    "gn:dem":1625,
    "gn:feature_class":"P",
    "gn:feature_code":"PPL",
    "gn:name":"Bien",
    "gn:population":17,
    "gn:timezone":"Europe/Rome",
    "iso:country":"IT",
    "name:ceb_x_preferred":[
        "Bien"
    ],
    "name:deu_x_preferred":[
        "Bien"
    ],
    "name:fra_x_preferred":[
        "Bien"
    ],
    "name:spa_x_preferred":[
        "Bien"
    ],
    "name:swe_x_preferred":[
        "Bien"
    ],
    "wof:name":"Bien",
    "wof:placetype":"locality",
    "wof:population":17
},
  "geometry": {"coordinates":[7.21272,45.57429000000001],"type":"Point"}
}