{
  "type": "Feature",
  "properties": {
    "gn:admin1_code":"8",
    "gn:admin2_code":"SV",
    "gn:admin3_code":"9058.0",
    "gn:asciiname":"Sigurella II",
    "gn:country_code":"IT",
    "gn:dem":371,
    "gn:feature_class":"P",
    "gn:feature_code":"PPL",
    "gn:name":"Sigurella II",
    "gn:population":27,
    "gn:timezone":"Europe/Rome",
    "iso:country":"IT",
    "wof:name":"Sigurella II",
    "wof:placetype":"locality",
    "wof:population":27
},
  "geometry": {"coordinates":[8.48558,44.4129],"type":"Point"}
}