{
  "type": "Feature",
  "properties": {
    "gn:admin1_code":"1",
    "gn:admin2_code":"CH",
    "gn:admin3_code":"69013.0",
    "gn:asciiname":"Sant'Angelo",
    "gn:country_code":"IT",
    "gn:dem":400,
    "gn:feature_class":"P",
    "gn:feature_code":"PPL",
    "gn:name":"Sant'Angelo",
    "gn:population":283,
    "gn:timezone":"Europe/Rome",
    "iso:country":"IT",
    "wof:name":"Sant'Angelo",
    "wof:placetype":"locality",
    "wof:population":283
},
  "geometry": {"coordinates":[14.20463,42.25369],"type":"Point"}
}