{
  "type": "Feature",
  "properties": {
    "gn:admin1_code":"5",
    "gn:admin2_code":"PC",
    "gn:admin3_code":"33039.0",
    "gn:asciiname":"Colombarola",
    "gn:country_code":"IT",
    "gn:dem":63,
    "gn:feature_class":"P",
    "gn:feature_code":"PPL",
    "gn:name":"Colombarola",
    "gn:population":26,
    "gn:timezone":"Europe/Rome",
    "iso:country":"IT",
    "wof:name":"Colombarola",
    "wof:placetype":"locality",
    "wof:population":26
},
  "geometry": {"coordinates":[9.53714,45.05722],"type":"Point"}
}