{
  "type": "Feature",
  "properties": {
    "gn:admin1_code":"4",
    "gn:admin2_code":"AV",
    "gn:admin3_code":"64035.0",
    "gn:asciiname":"Pila Ai Piani",
    "gn:country_code":"IT",
    "gn:dem":409,
    "gn:feature_class":"P",
    "gn:feature_code":"PPL",
    "gn:name":"Pila Ai Piani",
    "gn:population":75,
    "gn:timezone":"Europe/Rome",
    "iso:country":"IT",
    "wof:name":"Pila Ai Piani",
    "wof:placetype":"locality",
    "wof:population":75
},
  "geometry": {"coordinates":[15.10489,41.04009],"type":"Point"}
}