{
  "type": "Feature",
  "properties": {
    "gn:admin1_code":"7",
    "gn:admin2_code":"FR",
    "gn:admin3_code":"60071.0",
    "gn:asciiname":"Primo Ponte",
    "gn:country_code":"IT",
    "gn:dem":304,
    "gn:feature_class":"P",
    "gn:feature_code":"PPL",
    "gn:name":"Primo Ponte",
    "gn:population":41,
    "gn:timezone":"Europe/Rome",
    "iso:country":"IT",
    "wof:name":"Primo Ponte",
    "wof:placetype":"locality",
    "wof:population":41
},
  "geometry": {"coordinates":[13.06983,41.83003],"type":"Point"}
}