{
  "type": "Feature",
  "properties": {
    "gn:admin1_code":"5",
    "gn:admin2_code":"PR",
    "gn:admin3_code":"34002.0",
    "gn:asciiname":"Frassineto",
    "gn:country_code":"IT",
    "gn:dem":809,
    "gn:feature_class":"P",
    "gn:feature_code":"PPLL",
    "gn:name":"Frassineto",
    "gn:population":7,
    "gn:timezone":"Europe/Rome",
    "iso:country":"IT",
    "wof:name":"Frassineto",
    "wof:placetype":"locality",
    "wof:population":7
},
  "geometry": {"coordinates":[9.58568,44.58099],"type":"Point"}
}