{
  "type": "Feature",
  "properties": {
    "gn:admin1_code":"16.0",
    "gn:admin2_code":"LU",
    "gn:admin3_code":"46001.0",
    "gn:asciiname":"Ponte ai Pini-Capanna",
    "gn:country_code":"IT",
    "gn:dem":18,
    "gn:feature_class":"P",
    "gn:feature_code":"PPL",
    "gn:name":"Ponte ai Pini-Capanna",
    "gn:population":16,
    "gn:timezone":"Europe/Rome",
    "iso:country":"IT",
    "wof:name":"Ponte ai Pini-Capanna",
    "wof:placetype":"locality",
    "wof:population":16
},
  "geometry": {"coordinates":[10.71445,43.8264],"type":"Point"}
}