{
  "type": "Feature",
  "properties": {
    "gn:admin1_code":"15",
    "gn:admin2_code":"ME",
    "gn:admin3_code":"83027.0",
    "gn:asciiname":"Ciccattali",
    "gn:country_code":"IT",
    "gn:dem":425,
    "gn:feature_class":"P",
    "gn:feature_code":"PPL",
    "gn:name":"Ciccattali",
    "gn:population":96,
    "gn:timezone":"Europe/Rome",
    "iso:country":"IT",
    "wof:name":"Ciccattali",
    "wof:placetype":"locality",
    "wof:population":96
},
  "geometry": {"coordinates":[15.2927,37.98628],"type":"Point"}
}