{
  "type": "Feature",
  "properties": {
    "gn:admin1_code":"20.0",
    "gn:admin2_code":"BL",
    "gn:admin3_code":"25060.0",
    "gn:asciiname":"Broz",
    "gn:country_code":"IT",
    "gn:dem":962,
    "gn:feature_class":"P",
    "gn:feature_code":"PPL",
    "gn:name":"Broz",
    "gn:population":204,
    "gn:timezone":"Europe/Rome",
    "iso:country":"IT",
    "wof:name":"Broz",
    "wof:placetype":"locality",
    "wof:population":204
},
  "geometry": {"coordinates":[12.40657,46.11674],"type":"Point"}
}