{
  "type": "Feature",
  "properties": {
    "gn:admin1_code":"5.0",
    "gn:admin2_code":"FC",
    "gn:admin3_code":"40007.0",
    "gn:asciiname":"Case Venzi",
    "gn:country_code":"IT",
    "gn:dem":346,
    "gn:feature_class":"P",
    "gn:feature_code":"PPL",
    "gn:name":"Case Venzi",
    "gn:population":30,
    "gn:timezone":"Europe/Rome",
    "iso:country":"IT",
    "wof:name":"Case Venzi",
    "wof:placetype":"locality",
    "wof:population":30
},
  "geometry": {"coordinates":[12.14167,44.04222],"type":"Point"}
}