{
  "type": "Feature",
  "properties": {
    "gn:admin1_code":"9",
    "gn:admin2_code":"LO",
    "gn:admin3_code":"98054.0",
    "gn:asciiname":"Cascina Careggio",
    "gn:country_code":"IT",
    "gn:dem":63,
    "gn:feature_class":"P",
    "gn:feature_code":"PPL",
    "gn:name":"Cascina Careggio",
    "gn:population":29,
    "gn:timezone":"Europe/Rome",
    "iso:country":"IT",
    "wof:name":"Cascina Careggio",
    "wof:placetype":"locality",
    "wof:population":29
},
  "geometry": {"coordinates":[9.6345,45.16023],"type":"Point"}
}