{
  "type": "Feature",
  "properties": {
    "gn:admin1_code":"8",
    "gn:admin2_code":"GE",
    "gn:admin3_code":"10053.0",
    "gn:asciiname":"Micheloni",
    "gn:country_code":"IT",
    "gn:dem":48,
    "gn:feature_class":"P",
    "gn:feature_code":"PPL",
    "gn:name":"Micheloni",
    "gn:population":111,
    "gn:timezone":"Europe/Rome",
    "iso:country":"IT",
    "wof:name":"Micheloni",
    "wof:placetype":"locality",
    "wof:population":111
},
  "geometry": {"coordinates":[9.29982,44.37444],"type":"Point"}
}