{
  "type": "Feature",
  "properties": {
    "gn:admin1_code":"4",
    "gn:admin2_code":"BN",
    "gn:admin3_code":"62054.0",
    "gn:asciiname":"Case Santillo",
    "gn:country_code":"IT",
    "gn:dem":557,
    "gn:feature_class":"P",
    "gn:feature_code":"PPL",
    "gn:name":"Case Santillo",
    "gn:population":15,
    "gn:timezone":"Europe/Rome",
    "iso:country":"IT",
    "wof:name":"Case Santillo",
    "wof:placetype":"locality",
    "wof:population":15
},
  "geometry": {"coordinates":[14.70521,41.30688],"type":"Point"}
}