{
  "type": "Feature",
  "properties": {
    "gn:admin1_code":"10",
    "gn:admin2_code":"MC",
    "gn:admin3_code":"43047.0",
    "gn:asciiname":"Cappella",
    "gn:country_code":"IT",
    "gn:dem":366,
    "gn:feature_class":"P",
    "gn:feature_code":"PPL",
    "gn:name":"Cappella",
    "gn:population":17,
    "gn:timezone":"Europe/Rome",
    "iso:country":"IT",
    "name:ceb_x_preferred":[
        "Cappella"
    ],
    "name:deu_x_preferred":[
        "Cappella"
    ],
    "name:fra_x_preferred":[
        "Cappella"
    ],
    "name:ita_x_preferred":[
        "Cappella"
    ],
    "name:nld_x_preferred":[
        "Cappella"
    ],
    "name:por_x_preferred":[
        "Cappella"
    ],
    "name:srp_x_preferred":[
        "Cappella"
    ],
    "name:swe_x_preferred":[
        "Cappella"
    ],
    "wof:name":"Cappella",
    "wof:placetype":"locality",
    "wof:population":17
},
  "geometry": {"coordinates":[13.22879,43.27183],"type":"Point"}
}