{
  "type": "Feature",
  "properties": {
    "gn:admin1_code":"12",
    "gn:admin2_code":"CN",
    "gn:admin3_code":"4230.0",
    "gn:asciiname":"Canta",
    "gn:country_code":"IT",
    "gn:dem":461,
    "gn:feature_class":"P",
    "gn:feature_code":"PPL",
    "gn:name":"Canta",
    "gn:population":18,
    "gn:timezone":"Europe/Rome",
    "iso:country":"IT",
    "name:aym_x_preferred":[
        "Kanta"
    ],
    "name:nld_x_preferred":[
        "Canta"
    ],
    "name:por_x_preferred":[
        "Canta"
    ],
    "name:que_x_preferred":[
        "Kanta"
    ],
    "name:ron_x_preferred":[
        "Canta"
    ],
    "name:spa_x_preferred":[
        "Canta"
    ],
    "name:war_x_preferred":[
        "Canta"
    ],
    "wof:name":"Canta",
    "wof:placetype":"locality",
    "wof:population":18
},
  "geometry": {"coordinates":[8.09285,44.67741],"type":"Point"}
}