{
  "type": "Feature",
  "properties": {
    "gn:admin1_code":"9",
    "gn:admin2_code":"CR",
    "gn:admin3_code":"19026.0",
    "gn:asciiname":"Breda de' Bugni",
    "gn:country_code":"IT",
    "gn:dem":49,
    "gn:feature_class":"P",
    "gn:feature_code":"PPL",
    "gn:name":"Breda de' Bugni",
    "gn:population":36,
    "gn:timezone":"Europe/Rome",
    "iso:country":"IT",
    "wof:name":"Breda de' Bugni",
    "wof:placetype":"locality",
    "wof:population":36
},
  "geometry": {"coordinates":[9.98867,45.17786],"type":"Point"}
}