{
  "type": "Feature",
  "properties": {
    "gn:admin1_code":"5",
    "gn:admin2_code":"BO",
    "gn:admin3_code":"37015.0",
    "gn:asciiname":"Casola",
    "gn:country_code":"IT",
    "gn:dem":605,
    "gn:feature_class":"P",
    "gn:feature_code":"PPL",
    "gn:name":"Casola",
    "gn:population":27,
    "gn:timezone":"Europe/Rome",
    "iso:country":"IT",
    "wof:name":"Casola",
    "wof:placetype":"locality",
    "wof:population":27
},
  "geometry": {"coordinates":[10.99661,44.16506],"type":"Point"}
}