{
  "type": "Feature",
  "properties": {
    "gn:admin1_code":"12",
    "gn:admin2_code":"AL",
    "gn:admin3_code":"6154.0",
    "gn:asciiname":"Frescondino",
    "gn:country_code":"IT",
    "gn:dem":192,
    "gn:feature_class":"P",
    "gn:feature_code":"PPL",
    "gn:name":"Frescondino",
    "gn:population":42,
    "gn:timezone":"Europe/Rome",
    "iso:country":"IT",
    "wof:name":"Frescondino",
    "wof:placetype":"locality",
    "wof:population":42
},
  "geometry": {"coordinates":[8.59291,44.99648],"type":"Point"}
}