{
  "type": "Feature",
  "properties": {
    "gn:admin1_code":"20",
    "gn:admin2_code":"TV",
    "gn:admin3_code":"26009.0",
    "gn:asciiname":"Tegolone",
    "gn:country_code":"IT",
    "gn:dem":6,
    "gn:feature_class":"P",
    "gn:feature_code":"PPL",
    "gn:name":"Tegolone",
    "gn:population":34,
    "gn:timezone":"Europe/Rome",
    "iso:country":"IT",
    "wof:name":"Tegolone",
    "wof:placetype":"locality",
    "wof:population":34
},
  "geometry": {"coordinates":[12.30779,45.62286],"type":"Point"}
}