{
  "type": "Feature",
  "properties": {
    "gn:admin1_code":"4",
    "gn:admin2_code":"SA",
    "gn:admin3_code":"65027.0",
    "gn:asciiname":"Chiapponi",
    "gn:country_code":"IT",
    "gn:dem":747,
    "gn:feature_class":"P",
    "gn:feature_code":"PPL",
    "gn:name":"Chiapponi",
    "gn:population":17,
    "gn:timezone":"Europe/Rome",
    "iso:country":"IT",
    "wof:name":"Chiapponi",
    "wof:placetype":"locality",
    "wof:population":17
},
  "geometry": {"coordinates":[15.6831,40.17413],"type":"Point"}
}