{
  "type": "Feature",
  "properties": {
    "gn:admin1_code":"20",
    "gn:admin2_code":"VR",
    "gn:admin3_code":"23044.0",
    "gn:asciiname":"Gattina Alta",
    "gn:country_code":"IT",
    "gn:dem":13,
    "gn:feature_class":"P",
    "gn:feature_code":"PPL",
    "gn:name":"Gattina Alta",
    "gn:population":34,
    "gn:timezone":"Europe/Rome",
    "iso:country":"IT",
    "wof:name":"Gattina Alta",
    "wof:placetype":"locality",
    "wof:population":34
},
  "geometry": {"coordinates":[11.33388,45.21394],"type":"Point"}
}