{
  "type": "Feature",
  "properties": {
    "gn:admin1_code":"5",
    "gn:admin2_code":"PR",
    "gn:admin3_code":"34002.0",
    "gn:asciiname":"Cantiga",
    "gn:country_code":"IT",
    "gn:dem":714,
    "gn:feature_class":"P",
    "gn:feature_code":"PPLL",
    "gn:name":"Cantiga",
    "gn:population":10,
    "gn:timezone":"Europe/Rome",
    "iso:country":"IT",
    "name:cat_x_preferred":[
        "Cantiga"
    ],
    "name:epo_x_preferred":[
        "Kantigo"
    ],
    "name:eus_x_preferred":[
        "Kantika"
    ],
    "name:fra_x_preferred":[
        "Cantiga"
    ],
    "name:glg_x_preferred":[
        "Cantiga"
    ],
    "name:ita_x_preferred":[
        "Cantiga"
    ],
    "name:jpn_x_preferred":[
        "\u30ab\u30f3\u30c6\u30a3\u30ac"
    ],
    "name:oci_x_preferred":[
        "Cantiga"
    ],
    "name:pol_x_preferred":[
        "Cantiga"
    ],
    "name:rus_x_preferred":[
        "\u041a\u0430\u043d\u0442\u0438\u0433\u0430"
    ],
    "name:spa_x_preferred":[
        "Cantiga"
    ],
    "name:ukr_x_preferred":[
        "\u041a\u0430\u043d\u0442\u0438\u0433\u0430\u0441"
    ],
    "wof:name":"Cantiga",
    "wof:placetype":"locality",
    "wof:population":10
},
  "geometry": {"coordinates":[9.64911,44.62028],"type":"Point"}
}