{
  "type": "Feature",
  "properties": {
    "gn:admin1_code":"12.0",
    "gn:admin2_code":"NO",
    "gn:admin3_code":"3149.0",
    "gn:asciiname":"Cascina Pozzaccio Vecchio",
    "gn:country_code":"IT",
    "gn:dem":134,
    "gn:feature_class":"P",
    "gn:feature_code":"PPL",
    "gn:name":"Cascina Pozzaccio Vecchio",
    "gn:population":18,
    "gn:timezone":"Europe/Rome",
    "iso:country":"IT",
    "wof:name":"Cascina Pozzaccio Vecchio",
    "wof:placetype":"locality",
    "wof:population":18
},
  "geometry": {"coordinates":[8.76062,45.42923],"type":"Point"}
}