{
  "type": "Feature",
  "properties": {
    "gn:admin1_code":"5",
    "gn:admin2_code":"RN",
    "gn:admin3_code":"99003.0",
    "gn:asciiname":"Case Cattani",
    "gn:country_code":"IT",
    "gn:dem":44,
    "gn:feature_class":"P",
    "gn:feature_code":"PPL",
    "gn:name":"Case Cattani",
    "gn:population":92,
    "gn:timezone":"Europe/Rome",
    "iso:country":"IT",
    "wof:name":"Case Cattani",
    "wof:placetype":"locality",
    "wof:population":92
},
  "geometry": {"coordinates":[12.60755,43.98521],"type":"Point"}
}