{
  "type": "Feature",
  "properties": {
    "gn:admin1_code":"3",
    "gn:admin2_code":"CS",
    "gn:admin3_code":"78154.0",
    "gn:asciiname":"Imbreci",
    "gn:country_code":"IT",
    "gn:dem":93,
    "gn:feature_class":"P",
    "gn:feature_code":"PPL",
    "gn:name":"Imbreci",
    "gn:population":19,
    "gn:timezone":"Europe/Rome",
    "iso:country":"IT",
    "wof:name":"Imbreci",
    "wof:placetype":"locality",
    "wof:population":19
},
  "geometry": {"coordinates":[16.46541,39.83349000000001],"type":"Point"}
}