{
  "type": "Feature",
  "properties": {
    "gn:admin1_code":"9",
    "gn:admin2_code":"LO",
    "gn:admin3_code":"98059.0",
    "gn:asciiname":"Cascina Canova",
    "gn:country_code":"IT",
    "gn:dem":79,
    "gn:feature_class":"P",
    "gn:feature_code":"PPL",
    "gn:name":"Cascina Canova",
    "gn:population":13,
    "gn:timezone":"Europe/Rome",
    "iso:country":"IT",
    "wof:name":"Cascina Canova",
    "wof:placetype":"locality",
    "wof:population":13
},
  "geometry": {"coordinates":[9.34434,45.26129],"type":"Point"}
}