{
  "type": "Feature",
  "properties": {
    "gn:admin1_code":"17",
    "gn:admin2_code":"BZ",
    "gn:admin3_code":"21001.0",
    "gn:asciiname":"Stadt",
    "gn:country_code":"IT",
    "gn:dem":1568,
    "gn:feature_class":"P",
    "gn:feature_code":"PPL",
    "gn:name":"Stadt",
    "gn:population":45,
    "gn:timezone":"Europe/Rome",
    "iso:country":"IT",
    "wof:name":"Stadt",
    "wof:placetype":"locality",
    "wof:population":45
},
  "geometry": {"coordinates":[11.40634,46.34937],"type":"Point"}
}