{
  "type": "Feature",
  "properties": {
    "gn:admin1_code":"15",
    "gn:admin2_code":"SR",
    "gn:admin3_code":"89001.0",
    "gn:asciiname":"Torre II",
    "gn:country_code":"IT",
    "gn:dem":45,
    "gn:feature_class":"P",
    "gn:feature_code":"PPL",
    "gn:name":"Torre II",
    "gn:population":87,
    "gn:timezone":"Europe/Rome",
    "iso:country":"IT",
    "wof:name":"Torre II",
    "wof:placetype":"locality",
    "wof:population":87
},
  "geometry": {"coordinates":[15.19311,37.25644000000001],"type":"Point"}
}