{
  "type": "Feature",
  "properties": {
    "gn:admin1_code":"7",
    "gn:admin2_code":"RM",
    "gn:admin3_code":"58071.0",
    "gn:asciiname":"Pitirolo",
    "gn:country_code":"IT",
    "gn:dem":308,
    "gn:feature_class":"P",
    "gn:feature_code":"PPL",
    "gn:name":"Pitirolo",
    "gn:population":35,
    "gn:timezone":"Europe/Rome",
    "iso:country":"IT",
    "wof:name":"Pitirolo",
    "wof:placetype":"locality",
    "wof:population":35
},
  "geometry": {"coordinates":[12.77559,42.16629],"type":"Point"}
}