{
  "type": "Feature",
  "properties": {
    "gn:admin1_code":"15.0",
    "gn:admin2_code":"CT",
    "gn:admin3_code":"87012.0",
    "gn:asciiname":"Zona Artigianale",
    "gn:country_code":"IT",
    "gn:dem":305,
    "gn:feature_class":"P",
    "gn:feature_code":"PPLL",
    "gn:name":"Zona Artigianale",
    "gn:population":0,
    "gn:timezone":"Europe/Rome",
    "iso:country":"IT",
    "wof:name":"Zona Artigianale",
    "wof:placetype":"locality"
},
  "geometry": {"coordinates":[14.99473,37.54946],"type":"Point"}
}