{
  "type": "Feature",
  "properties": {
    "gn:admin1_code":"5",
    "gn:admin2_code":"BO",
    "gn:admin3_code":"37010.0",
    "gn:asciiname":"Capanne-Vigaia",
    "gn:country_code":"IT",
    "gn:dem":468,
    "gn:feature_class":"P",
    "gn:feature_code":"PPL",
    "gn:name":"Capanne-Vigaia",
    "gn:population":28,
    "gn:timezone":"Europe/Rome",
    "iso:country":"IT",
    "wof:name":"Capanne-Vigaia",
    "wof:placetype":"locality",
    "wof:population":28
},
  "geometry": {"coordinates":[11.06826,44.19905],"type":"Point"}
}