{
  "type": "Feature",
  "properties": {
    "gn:admin1_code":"12",
    "gn:admin2_code":"AT",
    "gn:admin3_code":"5005.0",
    "gn:asciiname":"Bramairate",
    "gn:country_code":"IT",
    "gn:dem":169,
    "gn:feature_class":"P",
    "gn:feature_code":"PPL",
    "gn:name":"Bramairate",
    "gn:population":142,
    "gn:timezone":"Europe/Rome",
    "iso:country":"IT",
    "wof:name":"Bramairate",
    "wof:placetype":"locality",
    "wof:population":142
},
  "geometry": {"coordinates":[8.12585,44.89881],"type":"Point"}
}