{
  "type": "Feature",
  "properties": {
    "gn:admin1_code":"1",
    "gn:admin2_code":"PE",
    "gn:admin3_code":"68027.0",
    "gn:asciiname":"Colle Stella",
    "gn:country_code":"IT",
    "gn:dem":263,
    "gn:feature_class":"P",
    "gn:feature_code":"PPL",
    "gn:name":"Colle Stella",
    "gn:population":92,
    "gn:timezone":"Europe/Rome",
    "iso:country":"IT",
    "wof:name":"Colle Stella",
    "wof:placetype":"locality",
    "wof:population":92
},
  "geometry": {"coordinates":[13.96635,42.45556],"type":"Point"}
}