{
  "type": "Feature",
  "properties": {
    "gn:admin1_code":"4",
    "gn:admin2_code":"AV",
    "gn:admin3_code":"64050.0",
    "gn:asciiname":"Chiocche del Forno",
    "gn:country_code":"IT",
    "gn:dem":427,
    "gn:feature_class":"P",
    "gn:feature_code":"PPL",
    "gn:name":"Chiocche del Forno",
    "gn:population":82,
    "gn:timezone":"Europe/Rome",
    "iso:country":"IT",
    "wof:name":"Chiocche del Forno",
    "wof:placetype":"locality",
    "wof:population":82
},
  "geometry": {"coordinates":[14.99891,41.03099],"type":"Point"}
}