{
  "type": "Feature",
  "properties": {
    "gn:admin1_code":"20",
    "gn:admin2_code":"VR",
    "gn:admin3_code":"23064.0",
    "gn:asciiname":"Ponzilovo",
    "gn:country_code":"IT",
    "gn:dem":20,
    "gn:feature_class":"P",
    "gn:feature_code":"PPL",
    "gn:name":"Ponzilovo",
    "gn:population":88,
    "gn:timezone":"Europe/Rome",
    "iso:country":"IT",
    "wof:name":"Ponzilovo",
    "wof:placetype":"locality",
    "wof:population":88
},
  "geometry": {"coordinates":[11.21106,45.33491],"type":"Point"}
}