{
  "type": "Feature",
  "properties": {
    "gn:admin1_code":"6.0",
    "gn:admin2_code":"PN",
    "gn:admin3_code":"93012.0",
    "gn:asciiname":"Orgnese",
    "gn:country_code":"IT",
    "gn:dem":376,
    "gn:elevation":"254.0",
    "gn:feature_class":"P",
    "gn:feature_code":"PPL",
    "gn:name":"Orgnese",
    "gn:population":30,
    "gn:timezone":"Europe/Rome",
    "iso:country":"IT",
    "wof:name":"Orgnese",
    "wof:placetype":"locality",
    "wof:population":30
},
  "geometry": {"coordinates":[12.76974,46.20669],"type":"Point"}
}