{
  "type": "Feature",
  "properties": {
    "gn:admin1_code":"5",
    "gn:admin2_code":"FC",
    "gn:admin3_code":"40013.0",
    "gn:asciiname":"Villa Paolucci",
    "gn:country_code":"IT",
    "gn:dem":37,
    "gn:feature_class":"P",
    "gn:feature_code":"PPL",
    "gn:name":"Villa Paolucci",
    "gn:population":17,
    "gn:timezone":"Europe/Rome",
    "iso:country":"IT",
    "wof:name":"Villa Paolucci",
    "wof:placetype":"locality",
    "wof:population":17
},
  "geometry": {"coordinates":[12.09963,44.16986],"type":"Point"}
}