{
  "type": "Feature",
  "properties": {
    "gn:admin1_code":"3.0",
    "gn:admin2_code":"RC",
    "gn:admin3_code":"80063.0",
    "gn:asciiname":"Occhio",
    "gn:country_code":"IT",
    "gn:dem":-9999,
    "gn:feature_class":"P",
    "gn:feature_code":"PPL",
    "gn:name":"Occhio",
    "gn:population":0,
    "gn:timezone":"Europe/Rome",
    "iso:country":"IT",
    "wof:name":"Occhio",
    "wof:placetype":"locality"
},
  "geometry": {"coordinates":[15.65,38.05],"type":"Point"}
}