{
  "type": "Feature",
  "properties": {
    "gn:admin1_code":"20",
    "gn:admin2_code":"PD",
    "gn:admin3_code":"28055.0",
    "gn:asciiname":"Cavallino",
    "gn:country_code":"IT",
    "gn:dem":5,
    "gn:feature_class":"P",
    "gn:feature_code":"PPL",
    "gn:name":"Cavallino",
    "gn:population":34,
    "gn:timezone":"Europe/Rome",
    "iso:country":"IT",
    "wof:name":"Cavallino",
    "wof:placetype":"locality",
    "wof:population":34
},
  "geometry": {"coordinates":[11.78457,45.24103],"type":"Point"}
}