{
  "type": "Feature",
  "properties": {
    "gn:admin1_code":"20",
    "gn:admin2_code":"PD",
    "gn:admin3_code":"28055.0",
    "gn:asciiname":"Cavallino",
    "gn:country_code":"IT",
    "gn:dem":5,
    "gn:feature_class":"P",
    "gn:feature_code":"PPL",
    "gn:name":"Cavallino",
    "gn:population":34,
    "gn:timezone":"Europe/Rome",
    "iso:country":"IT",
    "name:ara_x_preferred":[
        "\u0643\u0627\u0641\u0627\u0644\u064a\u0646\u0648"
    ],
    "name:azb_x_preferred":[
        "\u06a9\u0648\u0644\u06cc\u0646\u0648"
    ],
    "name:bel_x_preferred":[
        "\u041a\u0430\u0432\u0430\u043b\u0456\u043d\u0430"
    ],
    "name:bul_x_preferred":[
        "\u041a\u0430\u0432\u0430\u043b\u0438\u043d\u043e"
    ],
    "name:ceb_x_preferred":[
        "Cavallino"
    ],
    "name:ces_x_preferred":[
        "Cavallino"
    ],
    "name:deu_x_preferred":[
        "Cavallino"
    ],
    "name:epo_x_preferred":[
        "Cavallino"
    ],
    "name:eus_x_preferred":[
        "Cavallino"
    ],
    "name:fas_x_preferred":[
        "\u06a9\u0648\u0644\u06cc\u0646\u0648"
    ],
    "name:fra_x_preferred":[
        "Cavallino"
    ],
    "name:hun_x_preferred":[
        "Cavallino"
    ],
    "name:hye_x_preferred":[
        "\u053f\u0561\u057e\u0561\u056c\u056b\u0576\u0578"
    ],
    "name:ina_x_preferred":[
        "Cavallino"
    ],
    "name:ita_x_preferred":[
        "Cavallino"
    ],
    "name:jpn_x_preferred":[
        "\u30ab\u30f4\u30a1\u30c3\u30ea\u30fc\u30ce"
    ],
    "name:kaz_x_preferred":[
        "\u041a\u0430\u0432\u0430\u043b\u043b\u0438\u043d\u043e"
    ],
    "name:lat_x_preferred":[
        "Caballinum"
    ],
    "name:lmo_x_preferred":[
        "Cavallino"
    ],
    "name:msa_x_preferred":[
        "Cavallino"
    ],
    "name:nap_x_preferred":[
        "Cavallino"
    ],
    "name:nld_x_preferred":[
        "Cavallino"
    ],
    "name:pms_x_preferred":[
        "Cavallino"
    ],
    "name:pol_x_preferred":[
        "Cavallino"
    ],
    "name:por_x_preferred":[
        "Cavallino"
    ],
    "name:ron_x_preferred":[
        "Cavallino"
    ],
    "name:rus_x_preferred":[
        "\u041a\u0430\u0432\u0430\u043b\u043b\u0438\u043d\u043e"
    ],
    "name:scn_x_preferred":[
        "Caddhrinu"
    ],
    "name:spa_x_preferred":[
        "Cavallino"
    ],
    "name:srp_x_preferred":[
        "\u041a\u0430\u0432\u0430\u043b\u0438\u043d\u043e"
    ],
    "name:szl_x_preferred":[
        "Cavallino"
    ],
    "name:tgl_x_preferred":[
        "Cavallino"
    ],
    "name:ukr_x_preferred":[
        "\u041a\u0430\u0432\u0430\u043b\u043b\u0456\u043d\u043e"
    ],
    "name:uzb_x_preferred":[
        "Cavallino"
    ],
    "name:vie_x_preferred":[
        "Cavallino"
    ],
    "name:vol_x_preferred":[
        "Cavallino"
    ],
    "name:war_x_preferred":[
        "Cavallino"
    ],
    "name:zho_x_preferred":[
        "\u5361\u74e6\u5229\u8bfa"
    ],
    "wof:name":"Cavallino",
    "wof:placetype":"locality",
    "wof:population":34
},
  "geometry": {"coordinates":[11.78457,45.24103],"type":"Point"}
}