{
  "type": "Feature",
  "properties": {
    "gn:admin1_code":"17",
    "gn:admin2_code":"BZ",
    "gn:admin3_code":"21069.0",
    "gn:asciiname":"Mair",
    "gn:country_code":"IT",
    "gn:dem":1379,
    "gn:feature_class":"P",
    "gn:feature_code":"PPL",
    "gn:name":"Mair",
    "gn:population":20,
    "gn:timezone":"Europe/Rome",
    "iso:country":"IT",
    "name:bre_x_preferred":[
        "Mair"
    ],
    "name:ces_x_preferred":[
        "Mair"
    ],
    "name:cym_x_preferred":[
        "Mair"
    ],
    "name:deu_x_preferred":[
        "Mair"
    ],
    "name:fra_x_preferred":[
        "Mair"
    ],
    "name:ita_x_preferred":[
        "Mair"
    ],
    "name:pol_x_preferred":[
        "Mair"
    ],
    "wof:name":"Mair",
    "wof:placetype":"locality",
    "wof:population":20
},
  "geometry": {"coordinates":[11.02561,46.48426],"type":"Point"}
}