{
  "type": "Feature",
  "properties": {
    "gn:admin1_code":"13",
    "gn:admin2_code":"BA",
    "gn:admin3_code":"72027.0",
    "gn:asciiname":"Capo Scardicchio",
    "gn:country_code":"IT",
    "gn:dem":55,
    "gn:feature_class":"P",
    "gn:feature_code":"PPL",
    "gn:name":"Capo Scardicchio",
    "gn:population":308,
    "gn:timezone":"Europe/Rome",
    "iso:country":"IT",
    "wof:name":"Capo Scardicchio",
    "wof:placetype":"locality",
    "wof:population":308
},
  "geometry": {"coordinates":[16.78155,41.11717],"type":"Point"}
}