{
  "type": "Feature",
  "properties": {
    "gn:admin1_code":"9",
    "gn:admin2_code":"BG",
    "gn:admin3_code":"16141.0",
    "gn:asciiname":"Zona Industriale Baraccone Ovest",
    "gn:country_code":"IT",
    "gn:dem":171,
    "gn:feature_class":"P",
    "gn:feature_code":"PPLL",
    "gn:name":"Zona Industriale Baraccone Ovest",
    "gn:population":8,
    "gn:timezone":"Europe/Rome",
    "iso:country":"IT",
    "wof:name":"Zona Industriale Baraccone Ovest",
    "wof:placetype":"locality",
    "wof:population":8
},
  "geometry": {"coordinates":[9.80517,45.6026],"type":"Point"}
}