{
  "type": "Feature",
  "properties": {
    "gn:admin1_code":"5",
    "gn:admin2_code":"MO",
    "gn:admin3_code":"36033.0",
    "gn:asciiname":"La Pioppa",
    "gn:country_code":"IT",
    "gn:dem":305,
    "gn:feature_class":"P",
    "gn:feature_code":"PPL",
    "gn:name":"La Pioppa",
    "gn:population":107,
    "gn:timezone":"Europe/Rome",
    "iso:country":"IT",
    "wof:name":"La Pioppa",
    "wof:placetype":"locality",
    "wof:population":107
},
  "geometry": {"coordinates":[10.68637,44.41335],"type":"Point"}
}