{
  "type": "Feature",
  "properties": {
    "gn:admin1_code":"9",
    "gn:admin2_code":"CO",
    "gn:admin3_code":"13052.0",
    "gn:asciiname":"Cascina Bianca",
    "gn:country_code":"IT",
    "gn:dem":355,
    "gn:feature_class":"P",
    "gn:feature_code":"PPL",
    "gn:name":"Cascina Bianca",
    "gn:population":61,
    "gn:timezone":"Europe/Rome",
    "iso:country":"IT",
    "wof:name":"Cascina Bianca",
    "wof:placetype":"locality",
    "wof:population":61
},
  "geometry": {"coordinates":[9.24954,45.84491],"type":"Point"}
}