{
  "type": "Feature",
  "properties": {
    "gn:admin1_code":"8.0",
    "gn:admin2_code":"IM",
    "gn:admin3_code":"8031.0",
    "gn:asciiname":"Borgo Sant'Agata",
    "gn:country_code":"IT",
    "gn:dem":321,
    "gn:feature_class":"P",
    "gn:feature_code":"PPL",
    "gn:name":"Borgo Sant'Agata",
    "gn:population":624,
    "gn:timezone":"Europe/Rome",
    "iso:country":"IT",
    "wof:name":"Borgo Sant'Agata",
    "wof:placetype":"locality",
    "wof:population":624
},
  "geometry": {"coordinates":[8.00957,43.90353],"type":"Point"}
}