{
  "type": "Feature",
  "properties": {
    "gn:admin1_code":"12",
    "gn:admin2_code":"TO",
    "gn:admin3_code":"1215.0",
    "gn:asciiname":"Cascina Argentero",
    "gn:country_code":"IT",
    "gn:dem":267,
    "gn:feature_class":"P",
    "gn:feature_code":"PPL",
    "gn:name":"Cascina Argentero",
    "gn:population":16,
    "gn:timezone":"Europe/Rome",
    "iso:country":"IT",
    "wof:name":"Cascina Argentero",
    "wof:placetype":"locality",
    "wof:population":16
},
  "geometry": {"coordinates":[7.91377,44.98478],"type":"Point"}
}