{
  "type": "Feature",
  "properties": {
    "gn:admin1_code":"5",
    "gn:admin2_code":"PR",
    "gn:admin3_code":"34036.0",
    "gn:asciiname":"Pongennaro",
    "gn:country_code":"IT",
    "gn:dem":47,
    "gn:feature_class":"P",
    "gn:feature_code":"PPL",
    "gn:name":"Pongennaro",
    "gn:population":14,
    "gn:timezone":"Europe/Rome",
    "iso:country":"IT",
    "wof:name":"Pongennaro",
    "wof:placetype":"locality",
    "wof:population":14
},
  "geometry": {"coordinates":[10.11326,44.90625],"type":"Point"}
}