{
  "type": "Feature",
  "properties": {
    "gn:admin1_code":"20",
    "gn:admin2_code":"TV",
    "gn:admin3_code":"26012.0",
    "gn:asciiname":"Stradazza",
    "gn:country_code":"IT",
    "gn:dem":32,
    "gn:feature_class":"P",
    "gn:feature_code":"PPL",
    "gn:name":"Stradazza",
    "gn:population":139,
    "gn:timezone":"Europe/Rome",
    "iso:country":"IT",
    "wof:name":"Stradazza",
    "wof:placetype":"locality",
    "wof:population":139
},
  "geometry": {"coordinates":[11.90483,45.63683],"type":"Point"}
}