{
  "type": "Feature",
  "properties": {
    "gn:admin1_code":"9.0",
    "gn:admin2_code":"MN",
    "gn:admin3_code":"20047.0",
    "gn:asciiname":"San Rocco",
    "gn:country_code":"IT",
    "gn:dem":14,
    "gn:elevation":"16.0",
    "gn:feature_class":"P",
    "gn:feature_code":"PPL",
    "gn:name":"San Rocco",
    "gn:population":213,
    "gn:timezone":"Europe/Rome",
    "iso:country":"IT",
    "wof:name":"San Rocco",
    "wof:placetype":"locality",
    "wof:population":213
},
  "geometry": {"coordinates":[11.01658,44.99678],"type":"Point"}
}