{
  "type": "Feature",
  "properties": {
    "gn:admin1_code":"14.0",
    "gn:admin2_code":"SU",
    "gn:admin3_code":"111044.0",
    "gn:asciiname":"Porcu Mannu",
    "gn:country_code":"IT",
    "gn:dem":120,
    "gn:feature_class":"P",
    "gn:feature_code":"PPL",
    "gn:name":"Porcu Mannu",
    "gn:population":0,
    "gn:timezone":"Europe/Rome",
    "iso:country":"IT",
    "wof:name":"Porcu Mannu",
    "wof:placetype":"locality"
},
  "geometry": {"coordinates":[8.65,39.16667],"type":"Point"}
}