{
  "type": "Feature",
  "properties": {
    "gn:admin1_code":"15",
    "gn:admin2_code":"ME",
    "gn:admin3_code":"83099.0",
    "gn:asciiname":"Pullo",
    "gn:country_code":"IT",
    "gn:dem":725,
    "gn:feature_class":"P",
    "gn:feature_code":"PPL",
    "gn:name":"Pullo",
    "gn:population":14,
    "gn:timezone":"Europe/Rome",
    "iso:country":"IT",
    "wof:name":"Pullo",
    "wof:placetype":"locality",
    "wof:population":14
},
  "geometry": {"coordinates":[14.80569,38.04538],"type":"Point"}
}