{
  "type": "Feature",
  "properties": {
    "gn:admin1_code":"9",
    "gn:admin2_code":"BG",
    "gn:admin3_code":"16211.0",
    "gn:asciiname":"Campodosso",
    "gn:country_code":"IT",
    "gn:dem":430,
    "gn:feature_class":"P",
    "gn:feature_code":"PPL",
    "gn:name":"Campodosso",
    "gn:population":16,
    "gn:timezone":"Europe/Rome",
    "iso:country":"IT",
    "wof:name":"Campodosso",
    "wof:placetype":"locality",
    "wof:population":16
},
  "geometry": {"coordinates":[10.03315,45.70743],"type":"Point"}
}