{
  "type": "Feature",
  "properties": {
    "gn:admin1_code":"1",
    "gn:admin2_code":"CH",
    "gn:admin3_code":"69051.0",
    "gn:asciiname":"Fonte San Giovanni",
    "gn:country_code":"IT",
    "gn:dem":528,
    "gn:feature_class":"P",
    "gn:feature_code":"PPL",
    "gn:name":"Fonte San Giovanni",
    "gn:population":188,
    "gn:timezone":"Europe/Rome",
    "iso:country":"IT",
    "wof:name":"Fonte San Giovanni",
    "wof:placetype":"locality",
    "wof:population":188
},
  "geometry": {"coordinates":[14.43798,41.96604],"type":"Point"}
}