{
  "type": "Feature",
  "properties": {
    "gn:admin1_code":"9",
    "gn:admin2_code":"MN",
    "gn:admin3_code":"20018.0",
    "gn:asciiname":"Mirardi",
    "gn:country_code":"IT",
    "gn:dem":107,
    "gn:feature_class":"P",
    "gn:feature_code":"PPL",
    "gn:name":"Mirardi",
    "gn:population":25,
    "gn:timezone":"Europe/Rome",
    "iso:country":"IT",
    "wof:name":"Mirardi",
    "wof:placetype":"locality",
    "wof:population":25
},
  "geometry": {"coordinates":[10.57491,45.35241],"type":"Point"}
}