{
  "type": "Feature",
  "properties": {
    "gn:admin1_code":"20",
    "gn:admin2_code":"VI",
    "gn:admin3_code":"24072.0",
    "gn:asciiname":"Casara",
    "gn:country_code":"IT",
    "gn:dem":622,
    "gn:feature_class":"P",
    "gn:feature_code":"PPL",
    "gn:name":"Casara",
    "gn:population":22,
    "gn:timezone":"Europe/Rome",
    "iso:country":"IT",
    "wof:name":"Casara",
    "wof:placetype":"locality",
    "wof:population":22
},
  "geometry": {"coordinates":[11.27557,45.59032],"type":"Point"}
}