{
  "type": "Feature",
  "properties": {
    "gn:admin1_code":"7",
    "gn:admin2_code":"RM",
    "gn:admin3_code":"58064.0",
    "gn:asciiname":"San Marco",
    "gn:country_code":"IT",
    "gn:dem":336,
    "gn:feature_class":"P",
    "gn:feature_code":"PPL",
    "gn:name":"San Marco",
    "gn:population":104,
    "gn:timezone":"Europe/Rome",
    "iso:country":"IT",
    "wof:name":"San Marco",
    "wof:placetype":"locality",
    "wof:population":104
},
  "geometry": {"coordinates":[12.69676,41.81619],"type":"Point"}
}