{
  "type": "Feature",
  "properties": {
    "gn:admin1_code":"7",
    "gn:admin2_code":"RM",
    "gn:admin3_code":"58064.0",
    "gn:asciiname":"San Marco",
    "gn:country_code":"IT",
    "gn:dem":336,
    "gn:feature_class":"P",
    "gn:feature_code":"PPL",
    "gn:name":"San Marco",
    "gn:population":104,
    "gn:timezone":"Europe/Rome",
    "iso:country":"IT",
    "name:dan_x_preferred":[
        "San Marco"
    ],
    "name:eus_x_preferred":[
        "San Marco"
    ],
    "name:fra_x_preferred":[
        "San Marco"
    ],
    "name:heb_x_preferred":[
        "\u05e1\u05df \u05de\u05e8\u05e7\u05d5"
    ],
    "name:hrv_x_preferred":[
        "San Marco"
    ],
    "name:hun_x_preferred":[
        "San Marco"
    ],
    "name:kor_x_preferred":[
        "\uc0b0\ub9c8\ub974\ucf54"
    ],
    "name:lat_x_preferred":[
        "Sextarius Sancti Marci"
    ],
    "name:nld_x_preferred":[
        "San Marco"
    ],
    "name:por_x_preferred":[
        "San Marco"
    ],
    "name:rus_x_preferred":[
        "\u0421\u0430\u043d-\u041c\u0430\u0440\u043a\u043e"
    ],
    "name:spa_x_preferred":[
        "San Marco"
    ],
    "name:tur_x_preferred":[
        "San Marco"
    ],
    "name:ukr_x_preferred":[
        "\u0421\u0430\u043d-\u041c\u0430\u0440\u043a\u043e"
    ],
    "name:vec_x_preferred":[
        "San Marco"
    ],
    "name:zho_x_preferred":[
        "\u5723\u9a6c\u53ef\u533a"
    ],
    "wof:name":"San Marco",
    "wof:placetype":"locality",
    "wof:population":104
},
  "geometry": {"coordinates":[12.69676,41.81619],"type":"Point"}
}