{
  "type": "Feature",
  "properties": {
    "gn:admin1_code":"12.0",
    "gn:admin2_code":"VB",
    "gn:admin3_code":"103024.0",
    "gn:asciiname":"In Re",
    "gn:country_code":"IT",
    "gn:dem":811,
    "gn:feature_class":"P",
    "gn:feature_code":"PPL",
    "gn:name":"In Re",
    "gn:population":29,
    "gn:timezone":"Europe/Rome",
    "iso:country":"IT",
    "wof:name":"In Re",
    "wof:placetype":"locality",
    "wof:population":29
},
  "geometry": {"coordinates":[8.48771,46.13716],"type":"Point"}
}