{
  "type": "Feature",
  "properties": {
    "gn:admin1_code":"17",
    "gn:admin2_code":"BZ",
    "gn:admin3_code":"21080.0",
    "gn:asciiname":"Sant'Orsola",
    "gn:country_code":"IT",
    "gn:dem":663,
    "gn:feature_class":"P",
    "gn:feature_code":"PPL",
    "gn:name":"Sant'Orsola",
    "gn:population":25,
    "gn:timezone":"Europe/Rome",
    "iso:country":"IT",
    "name:deu_x_preferred":[
        "Schweinsteg"
    ],
    "name:ita_x_preferred":[
        "Sant'Orsola"
    ],
    "wof:name":"Sant'Orsola",
    "wof:placetype":"locality",
    "wof:population":25
},
  "geometry": {"coordinates":[11.21031,46.73926],"type":"Point"}
}