{
  "type": "Feature",
  "properties": {
    "gn:admin1_code":"6.0",
    "gn:admin2_code":"UD",
    "gn:admin3_code":"30114.0",
    "gn:asciiname":"Sant'Andrat",
    "gn:country_code":"IT",
    "gn:dem":27,
    "gn:feature_class":"P",
    "gn:feature_code":"PPL",
    "gn:name":"Sant'Andr\u00e0t",
    "gn:population":0,
    "gn:timezone":"Europe/Rome",
    "iso:country":"IT",
    "wof:name":"Sant'Andrat",
    "wof:placetype":"locality"
},
  "geometry": {"coordinates":[13.15611,45.91944],"type":"Point"}
}