{
  "type": "Feature",
  "properties": {
    "gn:admin1_code":"20",
    "gn:admin2_code":"VI",
    "gn:admin3_code":"24091.0",
    "gn:asciiname":"Villa Giaretta",
    "gn:country_code":"IT",
    "gn:dem":51,
    "gn:feature_class":"P",
    "gn:feature_code":"PPL",
    "gn:name":"Villa Giaretta",
    "gn:population":20,
    "gn:timezone":"Europe/Rome",
    "iso:country":"IT",
    "wof:name":"Villa Giaretta",
    "wof:placetype":"locality",
    "wof:population":20
},
  "geometry": {"coordinates":[11.6007,45.63038],"type":"Point"}
}