{
  "type": "Feature",
  "properties": {
    "gn:admin1_code":"5.0",
    "gn:admin2_code":"FE",
    "gn:admin3_code":"38005.0",
    "gn:asciiname":"Casa Fronte",
    "gn:cc2":"IT",
    "gn:country_code":"IT",
    "gn:dem":2,
    "gn:feature_class":"P",
    "gn:feature_code":"PPL",
    "gn:name":"Casa Fronte",
    "gn:population":0,
    "gn:timezone":"Europe/Rome",
    "iso:country":"IT",
    "name:und_x_variant":[
        "Fronte",
        "Tenuta Fronte",
        "Casa Fronte"
    ],
    "wof:name":"Casa Fronte",
    "wof:placetype":"locality"
},
  "geometry": {"coordinates":[12.14611,44.88528],"type":"Point"}
}