{
  "type": "Feature",
  "properties": {
    "gn:admin1_code":"16.0",
    "gn:admin2_code":"PO",
    "gn:admin3_code":"100004.0",
    "gn:asciiname":"Santa Cristina in Pilli",
    "gn:country_code":"IT",
    "gn:dem":72,
    "gn:feature_class":"P",
    "gn:feature_code":"PPL",
    "gn:name":"Santa Cristina in Pilli",
    "gn:population":77,
    "gn:timezone":"Europe/Rome",
    "iso:country":"IT",
    "wof:name":"Santa Cristina in Pilli",
    "wof:placetype":"locality",
    "wof:population":77
},
  "geometry": {"coordinates":[11.04948,43.80615],"type":"Point"}
}