{
  "type": "Feature",
  "properties": {
    "gn:admin1_code":"5",
    "gn:admin2_code":"MO",
    "gn:admin3_code":"36008.0",
    "gn:asciiname":"Villa Santa",
    "gn:country_code":"IT",
    "gn:dem":128,
    "gn:feature_class":"P",
    "gn:feature_code":"PPL",
    "gn:name":"Villa Santa",
    "gn:population":114,
    "gn:timezone":"Europe/Rome",
    "iso:country":"IT",
    "wof:name":"Villa Santa",
    "wof:placetype":"locality",
    "wof:population":114
},
  "geometry": {"coordinates":[10.91867,44.5231],"type":"Point"}
}