{
  "type": "Feature",
  "properties": {
    "gn:admin1_code":"9",
    "gn:admin2_code":"BG",
    "gn:admin3_code":"16202.0",
    "gn:asciiname":"Boscalgisi",
    "gn:country_code":"IT",
    "gn:dem":431,
    "gn:feature_class":"P",
    "gn:feature_code":"PPL",
    "gn:name":"Boscalgisi",
    "gn:population":11,
    "gn:timezone":"Europe/Rome",
    "iso:country":"IT",
    "wof:name":"Boscalgisi",
    "wof:placetype":"locality",
    "wof:population":11
},
  "geometry": {"coordinates":[9.64379,45.75145],"type":"Point"}
}