{
  "type": "Feature",
  "properties": {
    "gn:admin1_code":"10",
    "gn:admin2_code":"PU",
    "gn:admin3_code":"41029.0",
    "gn:asciiname":"Valle del Pozzo",
    "gn:country_code":"IT",
    "gn:dem":44,
    "gn:feature_class":"P",
    "gn:feature_code":"PPL",
    "gn:name":"Valle del Pozzo",
    "gn:population":36,
    "gn:timezone":"Europe/Rome",
    "iso:country":"IT",
    "wof:name":"Valle del Pozzo",
    "wof:placetype":"locality",
    "wof:population":36
},
  "geometry": {"coordinates":[13.11285,43.74421],"type":"Point"}
}