{
  "type": "Feature",
  "properties": {
    "gn:admin1_code":"8",
    "gn:admin2_code":"SV",
    "gn:admin3_code":"9020.0",
    "gn:asciiname":"Vesallo",
    "gn:country_code":"IT",
    "gn:dem":301,
    "gn:feature_class":"P",
    "gn:feature_code":"PPL",
    "gn:name":"Vesallo",
    "gn:population":67,
    "gn:timezone":"Europe/Rome",
    "iso:country":"IT",
    "wof:name":"Vesallo",
    "wof:placetype":"locality",
    "wof:population":67
},
  "geometry": {"coordinates":[8.08053,44.10874],"type":"Point"}
}