{
  "type": "Feature",
  "properties": {
    "gn:admin1_code":"2",
    "gn:admin2_code":"PZ",
    "gn:admin3_code":"76063.0",
    "gn:asciiname":"Case Capoiazzo I",
    "gn:country_code":"IT",
    "gn:dem":1003,
    "gn:feature_class":"P",
    "gn:feature_code":"PPL",
    "gn:name":"Case Capoiazzo I",
    "gn:population":114,
    "gn:timezone":"Europe/Rome",
    "iso:country":"IT",
    "wof:name":"Case Capoiazzo I",
    "wof:placetype":"locality",
    "wof:population":114
},
  "geometry": {"coordinates":[15.76087,40.68481],"type":"Point"}
}