{
  "type": "Feature",
  "properties": {
    "iso:country":"IT",
    "name:ceb_x_preferred":[
        "Cesano"
    ],
    "name:deu_x_preferred":[
        "Cesano"
    ],
    "name:ita_x_preferred":[
        "Cesano"
    ],
    "name:lmo_x_preferred":[
        "Cesan"
    ],
    "name:srp_x_preferred":[
        "\u010cezano"
    ],
    "name:swe_x_preferred":[
        "Cesano"
    ],
    "wof:name":"Cesano",
    "wof:placetype":"neighbourhood"
},
  "geometry": {"coordinates":[12.33906228982154,42.07516963928894],"type":"Point"}
}