{
  "type": "Feature",
  "properties": {
    "iso:country":"IT",
    "name:ceb_x_preferred":[
        "San Pietro"
    ],
    "name:deu_x_preferred":[
        "San Pietro"
    ],
    "name:epo_x_preferred":[
        "San Pietro"
    ],
    "name:fra_x_preferred":[
        "San Pietro"
    ],
    "name:ita_x_preferred":[
        "San Pietro"
    ],
    "name:pol_x_preferred":[
        "San Pietro"
    ],
    "name:por_x_preferred":[
        "San Pietro"
    ],
    "name:sco_x_preferred":[
        "San Pietro"
    ],
    "name:srp_x_preferred":[
        "San Pjetro"
    ],
    "name:swe_x_preferred":[
        "San Pietro"
    ],
    "wof:name":"San Pietro",
    "wof:placetype":"neighbourhood"
},
  "geometry": {"coordinates":[9.15309666319875,45.47017288068787],"type":"Point"}
}