{
  "type": "Feature",
  "properties": {
    "gn:admin1_code":"10",
    "gn:admin2_code":"PU",
    "gn:admin3_code":"41017.0",
    "gn:asciiname":"Ponte Nuovo",
    "gn:country_code":"IT",
    "gn:dem":400,
    "gn:feature_class":"P",
    "gn:feature_code":"PPL",
    "gn:name":"Ponte Nuovo",
    "gn:population":35,
    "gn:timezone":"Europe/Rome",
    "iso:country":"IT",
    "name:ceb_x_preferred":[
        "Ponte Nuovo"
    ],
    "name:srp_x_preferred":[
        "\u041f\u043e\u043d\u0442\u0435 \u041d\u0443\u043e\u0432\u043e"
    ],
    "wof:name":"Ponte Nuovo",
    "wof:placetype":"locality",
    "wof:population":35
},
  "geometry": {"coordinates":[12.38358,43.76423],"type":"Point"}
}