{
  "type": "Feature",
  "properties": {
    "gn:admin1_code":"20",
    "gn:admin2_code":"VR",
    "gn:admin3_code":"23052.0",
    "gn:asciiname":"Rionda",
    "gn:country_code":"IT",
    "gn:dem":237,
    "gn:feature_class":"P",
    "gn:feature_code":"PPL",
    "gn:name":"Rionda",
    "gn:population":31,
    "gn:timezone":"Europe/Rome",
    "iso:country":"IT",
    "wof:name":"Rionda",
    "wof:placetype":"locality",
    "wof:population":31
},
  "geometry": {"coordinates":[10.9541,45.52677],"type":"Point"}
}