{
  "type": "Feature",
  "properties": {
    "gn:admin1_code":"10.0",
    "gn:admin2_code":"FM",
    "gn:admin3_code":"109037.0",
    "gn:asciiname":"Santa Caterina I",
    "gn:country_code":"IT",
    "gn:dem":108,
    "gn:feature_class":"P",
    "gn:feature_code":"PPL",
    "gn:name":"Santa Caterina I",
    "gn:population":463,
    "gn:timezone":"Europe/Rome",
    "iso:country":"IT",
    "wof:name":"Santa Caterina I",
    "wof:placetype":"locality",
    "wof:population":463
},
  "geometry": {"coordinates":[13.70297,43.21568],"type":"Point"}
}