{
  "type": "Feature",
  "properties": {
    "gn:admin1_code":"5",
    "gn:admin2_code":"RA",
    "gn:admin3_code":"39001.0",
    "gn:asciiname":"C.Fabione",
    "gn:country_code":"IT",
    "gn:dem":0,
    "gn:feature_class":"P",
    "gn:feature_code":"PPL",
    "gn:name":"C.Fabione",
    "gn:population":28,
    "gn:timezone":"Europe/Rome",
    "iso:country":"IT",
    "wof:name":"C.Fabione",
    "wof:placetype":"locality",
    "wof:population":28
},
  "geometry": {"coordinates":[12.00579,44.51956],"type":"Point"}
}