{
  "type": "Feature",
  "properties": {
    "gn:admin1_code":"12",
    "gn:admin2_code":"VC",
    "gn:admin3_code":"2156.0",
    "gn:asciiname":"Morca",
    "gn:country_code":"IT",
    "gn:dem":500,
    "gn:feature_class":"P",
    "gn:feature_code":"PPL",
    "gn:name":"Morca",
    "gn:population":42,
    "gn:timezone":"Europe/Rome",
    "iso:country":"IT",
    "wof:name":"Morca",
    "wof:placetype":"locality",
    "wof:population":42
},
  "geometry": {"coordinates":[8.21076,45.82104],"type":"Point"}
}