{
  "type": "Feature",
  "properties": {
    "gn:admin1_code":"20",
    "gn:admin2_code":"VR",
    "gn:admin3_code":"23011.0",
    "gn:asciiname":"Pezzo",
    "gn:country_code":"IT",
    "gn:dem":1079,
    "gn:feature_class":"P",
    "gn:feature_code":"PPLL",
    "gn:name":"Pezzo",
    "gn:population":10,
    "gn:timezone":"Europe/Rome",
    "iso:country":"IT",
    "wof:name":"Pezzo",
    "wof:placetype":"locality",
    "wof:population":10
},
  "geometry": {"coordinates":[11.04468,45.62997],"type":"Point"}
}