{
  "type": "Feature",
  "properties": {
    "gn:admin1_code":"6.0",
    "gn:admin2_code":"UD",
    "gn:admin3_code":"30004.0",
    "gn:asciiname":"Monastero",
    "gn:country_code":"IT",
    "gn:dem":1,
    "gn:feature_class":"P",
    "gn:feature_code":"PPL",
    "gn:name":"Monastero",
    "gn:population":0,
    "gn:timezone":"Europe/Rome",
    "iso:country":"IT",
    "wof:name":"Monastero",
    "wof:placetype":"locality"
},
  "geometry": {"coordinates":[13.36194,45.78194000000001],"type":"Point"}
}