{
  "type": "Feature",
  "properties": {
    "gn:admin1_code":"20",
    "gn:admin2_code":"VI",
    "gn:admin3_code":"24002.0",
    "gn:asciiname":"Castello",
    "gn:country_code":"IT",
    "gn:dem":20,
    "gn:feature_class":"P",
    "gn:feature_code":"PPL",
    "gn:name":"Castello",
    "gn:population":111,
    "gn:timezone":"Europe/Rome",
    "iso:country":"IT",
    "wof:name":"Castello",
    "wof:placetype":"locality",
    "wof:population":111
},
  "geometry": {"coordinates":[11.62226,45.34563],"type":"Point"}
}