{
  "type": "Feature",
  "properties": {
    "gn:admin1_code":"20",
    "gn:admin2_code":"VI",
    "gn:admin3_code":"24002.0",
    "gn:asciiname":"Castello",
    "gn:country_code":"IT",
    "gn:dem":20,
    "gn:feature_class":"P",
    "gn:feature_code":"PPL",
    "gn:name":"Castello",
    "gn:population":111,
    "gn:timezone":"Europe/Rome",
    "iso:country":"IT",
    "name:ast_x_preferred":[
        "Castello"
    ],
    "name:ben_x_preferred":[
        "\u0995\u09be\u09b8\u09cd\u099f\u09c7\u09b2\u09cd\u09b2\u09cb"
    ],
    "name:ceb_x_preferred":[
        "Castello"
    ],
    "name:deu_x_preferred":[
        "Castello"
    ],
    "name:epo_x_preferred":[
        "Castello"
    ],
    "name:fra_x_preferred":[
        "Castello"
    ],
    "name:heb_x_preferred":[
        "\u05e7\u05e1\u05d8\u05dc\u05d5"
    ],
    "name:hin_x_preferred":[
        "\u0915\u0948\u0938\u094d\u091f\u0947\u0932\u094b"
    ],
    "name:ita_x_preferred":[
        "Castello"
    ],
    "name:nld_x_preferred":[
        "Castello"
    ],
    "name:por_x_preferred":[
        "Castello"
    ],
    "name:rus_x_preferred":[
        "\u041a\u0430\u0441\u0442\u0435\u043b\u043b\u043e"
    ],
    "name:spa_x_preferred":[
        "Castello"
    ],
    "name:srp_x_preferred":[
        "\u041a\u0430\u0441\u0442\u0435\u043b\u043e"
    ],
    "name:swe_x_preferred":[
        "Castello"
    ],
    "wof:name":"Castello",
    "wof:placetype":"locality",
    "wof:population":111
},
  "geometry": {"coordinates":[11.62226,45.34563],"type":"Point"}
}