{
  "type": "Feature",
  "properties": {
    "gn:admin1_code":"16",
    "gn:admin2_code":"LI",
    "gn:admin3_code":"49006.0",
    "gn:asciiname":"Casone",
    "gn:country_code":"IT",
    "gn:dem":5,
    "gn:feature_class":"P",
    "gn:feature_code":"PPL",
    "gn:name":"Casone",
    "gn:population":75,
    "gn:timezone":"Europe/Rome",
    "iso:country":"IT",
    "name:ceb_x_preferred":[
        "Il Casone"
    ],
    "name:ita_x_preferred":[
        "Casone"
    ],
    "name:nld_x_preferred":[
        "Casone"
    ],
    "name:srp_x_preferred":[
        "\u0418\u043b \u041a\u0430\u0437\u043e\u043d\u0435"
    ],
    "wof:name":"Casone",
    "wof:placetype":"locality",
    "wof:population":75
},
  "geometry": {"coordinates":[10.56072,43.18699],"type":"Point"}
}