{
  "type": "Feature",
  "properties": {
    "gn:admin1_code":"16",
    "gn:admin2_code":"PI",
    "gn:admin3_code":"50012.0",
    "gn:asciiname":"La Pieve",
    "gn:country_code":"IT",
    "gn:dem":206,
    "gn:feature_class":"P",
    "gn:feature_code":"PPL",
    "gn:name":"La Pieve",
    "gn:population":54,
    "gn:timezone":"Europe/Rome",
    "iso:country":"IT",
    "wof:name":"La Pieve",
    "wof:placetype":"locality",
    "wof:population":54
},
  "geometry": {"coordinates":[10.63909,43.50023],"type":"Point"}
}