{
  "type": "Feature",
  "properties": {
    "gn:admin1_code":"2.0",
    "gn:admin2_code":"PZ",
    "gn:admin3_code":"76046.0",
    "gn:asciiname":"Villa d'Agri",
    "gn:country_code":"IT",
    "gn:dem":597,
    "gn:feature_class":"P",
    "gn:feature_code":"PPL",
    "gn:name":"Villa d'Agri",
    "gn:population":3595,
    "gn:timezone":"Europe/Rome",
    "iso:country":"IT",
    "wof:name":"Villa d'Agri",
    "wof:placetype":"locality",
    "wof:population":3595
},
  "geometry": {"coordinates":[15.8277,40.35426],"type":"Point"}
}