{
  "type": "Feature",
  "properties": {
    "gn:admin1_code":"18",
    "gn:admin2_code":"TR",
    "gn:admin3_code":"55019.0",
    "gn:asciiname":"I Monti",
    "gn:country_code":"IT",
    "gn:dem":459,
    "gn:feature_class":"P",
    "gn:feature_code":"PPL",
    "gn:name":"I Monti",
    "gn:population":36,
    "gn:timezone":"Europe/Rome",
    "iso:country":"IT",
    "wof:name":"I Monti",
    "wof:placetype":"locality",
    "wof:population":36
},
  "geometry": {"coordinates":[12.74268,42.60285],"type":"Point"}
}