{
  "type": "Feature",
  "properties": {
    "gn:admin1_code":"12.0",
    "gn:admin2_code":"AL",
    "gn:admin3_code":"6100.0",
    "gn:asciiname":"Montemanno",
    "gn:country_code":"IT",
    "gn:dem":627,
    "gn:feature_class":"P",
    "gn:feature_code":"PPLL",
    "gn:name":"Montemanno",
    "gn:population":5,
    "gn:timezone":"Europe/Rome",
    "iso:country":"IT",
    "wof:name":"Montemanno",
    "wof:placetype":"locality",
    "wof:population":5
},
  "geometry": {"coordinates":[9.04555,44.66077],"type":"Point"}
}