{
  "type": "Feature",
  "properties": {
    "gn:admin1_code":"9.0",
    "gn:admin2_code":"MI",
    "gn:admin3_code":"15230.0",
    "gn:asciiname":"Via Cavallasco",
    "gn:country_code":"IT",
    "gn:dem":169,
    "gn:feature_class":"P",
    "gn:feature_code":"PPL",
    "gn:name":"Via Cavallasco",
    "gn:population":30,
    "gn:timezone":"Europe/Rome",
    "iso:country":"IT",
    "wof:name":"Via Cavallasco",
    "wof:placetype":"locality",
    "wof:population":30
},
  "geometry": {"coordinates":[9.51539,45.58408],"type":"Point"}
}