{
  "type": "Feature",
  "properties": {
    "gn:admin1_code":"19.0",
    "gn:admin2_code":"AO",
    "gn:admin3_code":"7035.0",
    "gn:asciiname":"Buillet",
    "gn:country_code":"IT",
    "gn:dem":1031,
    "gn:feature_class":"P",
    "gn:feature_code":"PPL",
    "gn:name":"Buillet",
    "gn:population":24,
    "gn:timezone":"Europe/Rome",
    "iso:country":"IT",
    "wof:name":"Buillet",
    "wof:placetype":"locality",
    "wof:population":24
},
  "geometry": {"coordinates":[7.18986,45.68338],"type":"Point"}
}