{
  "type": "Feature",
  "properties": {
    "gn:admin1_code":"5",
    "gn:admin2_code":"FE",
    "gn:admin3_code":"38005.0",
    "gn:asciiname":"Tenuta Schiavina",
    "gn:country_code":"IT",
    "gn:dem":-5,
    "gn:feature_class":"P",
    "gn:feature_code":"PPL",
    "gn:name":"Tenuta Schiavina",
    "gn:population":36,
    "gn:timezone":"Europe/Rome",
    "iso:country":"IT",
    "wof:name":"Tenuta Schiavina",
    "wof:placetype":"locality",
    "wof:population":36
},
  "geometry": {"coordinates":[12.1295,44.88961],"type":"Point"}
}