{
  "type": "Feature",
  "properties": {
    "gn:admin1_code":"12.0",
    "gn:admin2_code":"AL",
    "gn:admin3_code":"6067.0",
    "gn:asciiname":"Fabbrica Curone",
    "gn:country_code":"IT",
    "gn:dem":471,
    "gn:elevation":"471.0",
    "gn:feature_class":"P",
    "gn:feature_code":"PPL",
    "gn:name":"Fabbrica Curone",
    "gn:population":117,
    "gn:timezone":"Europe/Rome",
    "iso:country":"IT",
    "wof:name":"Fabbrica Curone",
    "wof:placetype":"locality",
    "wof:population":117
},
  "geometry": {"coordinates":[9.14756,44.78495],"type":"Point"}
}