{
  "type": "Feature",
  "properties": {
    "gn:admin1_code":"16.0",
    "gn:admin2_code":"AR",
    "gn:admin3_code":"51021.0",
    "gn:asciiname":"Croce",
    "gn:country_code":"IT",
    "gn:dem":284,
    "gn:feature_class":"P",
    "gn:feature_code":"PPL",
    "gn:name":"Croce",
    "gn:population":354,
    "gn:timezone":"Europe/Rome",
    "iso:country":"IT",
    "name:ceb_x_preferred":[
        "Croce"
    ],
    "name:deu_x_preferred":[
        "Croce"
    ],
    "name:fra_x_preferred":[
        "Croce"
    ],
    "name:ita_x_preferred":[
        "Croce"
    ],
    "name:nld_x_preferred":[
        "Croce"
    ],
    "name:pol_x_preferred":[
        "Croce"
    ],
    "name:rus_x_preferred":[
        "\u041a\u0440\u043e\u0447\u0435"
    ],
    "name:spa_x_preferred":[
        "Croce"
    ],
    "name:srp_x_preferred":[
        "Croce"
    ],
    "name:swe_x_preferred":[
        "Croce"
    ],
    "wof:name":"Croce",
    "wof:placetype":"locality",
    "wof:population":354
},
  "geometry": {"coordinates":[11.75291,43.26054],"type":"Point"}
}