{
  "type": "Feature",
  "properties": {
    "gn:admin1_code":"20",
    "gn:admin2_code":"PD",
    "gn:admin3_code":"28049.0",
    "gn:asciiname":"Fienile Canetti",
    "gn:country_code":"IT",
    "gn:dem":8,
    "gn:feature_class":"P",
    "gn:feature_code":"PPL",
    "gn:name":"Fienile Canetti",
    "gn:population":36,
    "gn:timezone":"Europe/Rome",
    "iso:country":"IT",
    "wof:name":"Fienile Canetti",
    "wof:placetype":"locality",
    "wof:population":36
},
  "geometry": {"coordinates":[11.51931,45.12626],"type":"Point"}
}