{
  "type": "Feature",
  "properties": {
    "gn:admin1_code":"9",
    "gn:admin2_code":"PV",
    "gn:admin3_code":"18173.0",
    "gn:asciiname":"Rebecchino",
    "gn:country_code":"IT",
    "gn:dem":92,
    "gn:feature_class":"P",
    "gn:feature_code":"PPL",
    "gn:name":"Rebecchino",
    "gn:population":24,
    "gn:timezone":"Europe/Rome",
    "iso:country":"IT",
    "name:ita_x_preferred":[
        "Rebecchino"
    ],
    "wof:name":"Rebecchino",
    "wof:placetype":"locality",
    "wof:population":24
},
  "geometry": {"coordinates":[9.0897,45.27626],"type":"Point"}
}