{
  "type": "Feature",
  "properties": {
    "gn:admin1_code":"7",
    "gn:admin2_code":"FR",
    "gn:admin3_code":"60062.0",
    "gn:asciiname":"Folingaro",
    "gn:country_code":"IT",
    "gn:dem":560,
    "gn:feature_class":"P",
    "gn:feature_code":"PPL",
    "gn:name":"Folingaro",
    "gn:population":14,
    "gn:timezone":"Europe/Rome",
    "iso:country":"IT",
    "wof:name":"Folingaro",
    "wof:placetype":"locality",
    "wof:population":14
},
  "geometry": {"coordinates":[13.81272,41.70057],"type":"Point"}
}