{
  "type": "Feature",
  "properties": {
    "gn:admin1_code":"10.0",
    "gn:admin2_code":"PU",
    "gn:asciiname":"Torricella",
    "gn:country_code":"IT",
    "gn:dem":426,
    "gn:feature_class":"P",
    "gn:feature_code":"PPL",
    "gn:name":"Torricella",
    "gn:population":0,
    "gn:timezone":"Europe/Rome",
    "iso:country":"IT",
    "name:ceb_x_preferred":[
        "Torricella"
    ],
    "name:deu_x_preferred":[
        "Torricella"
    ],
    "name:epo_x_preferred":[
        "Torricella"
    ],
    "name:ita_x_preferred":[
        "Torricella"
    ],
    "name:lat_x_preferred":[
        "Turricella"
    ],
    "name:pms_x_preferred":[
        "Torricella"
    ],
    "name:por_x_preferred":[
        "Torricella"
    ],
    "name:rus_x_preferred":[
        "\u0422\u043e\u0440\u0440\u0438\u0447\u0435\u043b\u043b\u0430"
    ],
    "name:srp_x_preferred":[
        "Tori\u010dela"
    ],
    "name:swe_x_preferred":[
        "Torricella"
    ],
    "wof:name":"Torricella",
    "wof:placetype":"locality"
},
  "geometry": {"coordinates":[12.26667,43.86667],"type":"Point"}
}