{
  "type": "Feature",
  "properties": {
    "gn:admin1_code":"10.0",
    "gn:admin2_code":"PU",
    "gn:asciiname":"Torricella",
    "gn:country_code":"IT",
    "gn:dem":426,
    "gn:feature_class":"P",
    "gn:feature_code":"PPL",
    "gn:name":"Torricella",
    "gn:population":0,
    "gn:timezone":"Europe/Rome",
    "iso:country":"IT",
    "wof:name":"Torricella",
    "wof:placetype":"locality"
},
  "geometry": {"coordinates":[12.26667,43.86667],"type":"Point"}
}