{
  "type": "Feature",
  "properties": {
    "gn:admin1_code":"9",
    "gn:admin2_code":"MN",
    "gn:admin3_code":"20068.0",
    "gn:asciiname":"Vallano",
    "gn:country_code":"IT",
    "gn:dem":17,
    "gn:feature_class":"P",
    "gn:feature_code":"PPL",
    "gn:name":"Vallano",
    "gn:population":30,
    "gn:timezone":"Europe/Rome",
    "iso:country":"IT",
    "wof:name":"Vallano",
    "wof:placetype":"locality",
    "wof:population":30
},
  "geometry": {"coordinates":[11.02763,45.1546],"type":"Point"}
}