{
  "type": "Feature",
  "properties": {
    "gn:admin1_code":"1.0",
    "gn:admin2_code":"PE",
    "gn:admin3_code":"68011.0",
    "gn:asciiname":"Rapattoni Vecchio",
    "gn:country_code":"IT",
    "gn:dem":119,
    "gn:feature_class":"P",
    "gn:feature_code":"PPL",
    "gn:name":"Rapattoni Vecchio",
    "gn:population":377,
    "gn:timezone":"Europe/Rome",
    "iso:country":"IT",
    "wof:name":"Rapattoni Vecchio",
    "wof:placetype":"locality",
    "wof:population":377
},
  "geometry": {"coordinates":[14.07827,42.35728],"type":"Point"}
}