{
  "type": "Feature",
  "properties": {
    "iso:country":"IT",
    "wof:name":"Borgo Po",
    "wof:placetype":"neighbourhood"
},
  "geometry": {"coordinates":[7.70392642535097,45.06054839876081],"type":"Point"}
}