{
  "type": "Feature",
  "properties": {
    "gn:admin1_code":"17",
    "gn:admin2_code":"BZ",
    "gn:admin3_code":"21007.0",
    "gn:asciiname":"Zona Artigianale Santa Gertrude",
    "gn:country_code":"IT",
    "gn:dem":492,
    "gn:feature_class":"P",
    "gn:feature_code":"PPL",
    "gn:name":"Zona Artigianale Santa Gertrude",
    "gn:population":37,
    "gn:timezone":"Europe/Rome",
    "iso:country":"IT",
    "wof:name":"Zona Artigianale Santa Gertrude",
    "wof:placetype":"locality",
    "wof:population":37
},
  "geometry": {"coordinates":[11.5321,46.60566],"type":"Point"}
}