{
  "type": "Feature",
  "properties": {
    "gn:admin1_code":"20.0",
    "gn:admin2_code":"BL",
    "gn:admin3_code":"25010.0",
    "gn:asciiname":"Bastiani",
    "gn:country_code":"IT",
    "gn:dem":961,
    "gn:elevation":"950.0",
    "gn:feature_class":"P",
    "gn:feature_code":"PPL",
    "gn:name":"Bastiani",
    "gn:population":24,
    "gn:timezone":"Europe/Rome",
    "iso:country":"IT",
    "name:cos_x_preferred":[
        "Bastiani"
    ],
    "name:fra_x_preferred":[
        "Bastiani"
    ],
    "name:ita_x_preferred":[
        "Bastiani"
    ],
    "wof:name":"Bastiani",
    "wof:placetype":"locality",
    "wof:population":24
},
  "geometry": {"coordinates":[11.97913,46.35673],"type":"Point"}
}