{
  "type": "Feature",
  "properties": {
    "gn:admin1_code":"6.0",
    "gn:admin2_code":"UD",
    "gn:admin3_code":"30027.0",
    "gn:asciiname":"San Pietro",
    "gn:country_code":"IT",
    "gn:dem":27,
    "gn:elevation":"28.0",
    "gn:feature_class":"P",
    "gn:feature_code":"PPL",
    "gn:name":"San Pietro",
    "gn:population":37,
    "gn:timezone":"Europe/Rome",
    "iso:country":"IT",
    "name:ceb_x_preferred":[
        "San Pietro"
    ],
    "name:deu_x_preferred":[
        "San Pietro"
    ],
    "name:epo_x_preferred":[
        "San Pietro"
    ],
    "name:fra_x_preferred":[
        "San Pietro"
    ],
    "name:ita_x_preferred":[
        "San Pietro"
    ],
    "name:pol_x_preferred":[
        "San Pietro"
    ],
    "name:por_x_preferred":[
        "San Pietro"
    ],
    "name:sco_x_preferred":[
        "San Pietro"
    ],
    "name:srp_x_preferred":[
        "San Pjetro"
    ],
    "name:swe_x_preferred":[
        "San Pietro"
    ],
    "wof:name":"San Pietro",
    "wof:placetype":"locality",
    "wof:population":37
},
  "geometry": {"coordinates":[12.96957,45.91977],"type":"Point"}
}