{
  "type": "Feature",
  "properties": {
    "gn:admin1_code":"20",
    "gn:admin2_code":"BL",
    "gn:admin3_code":"25004.0",
    "gn:asciiname":"Col Perer",
    "gn:country_code":"IT",
    "gn:dem":1015,
    "gn:feature_class":"P",
    "gn:feature_code":"PPLL",
    "gn:name":"Col Perer",
    "gn:population":7,
    "gn:timezone":"Europe/Rome",
    "iso:country":"IT",
    "wof:name":"Col Perer",
    "wof:placetype":"locality",
    "wof:population":7
},
  "geometry": {"coordinates":[11.734,46.01022],"type":"Point"}
}