{
  "type": "Feature",
  "properties": {
    "gn:admin1_code":"3.0",
    "gn:admin2_code":"CS",
    "gn:admin3_code":"78137.0",
    "gn:asciiname":"La Palazzina",
    "gn:country_code":"IT",
    "gn:dem":572,
    "gn:feature_class":"P",
    "gn:feature_code":"PPL",
    "gn:name":"La Palazzina",
    "gn:population":0,
    "gn:timezone":"Europe/Rome",
    "iso:country":"IT",
    "wof:name":"La Palazzina",
    "wof:placetype":"locality"
},
  "geometry": {"coordinates":[16.85,39.45],"type":"Point"}
}