{
  "type": "Feature",
  "properties": {
    "gn:admin1_code":"5",
    "gn:admin2_code":"PR",
    "gn:admin3_code":"34018.0",
    "gn:asciiname":"Quinzano",
    "gn:country_code":"IT",
    "gn:dem":526,
    "gn:feature_class":"P",
    "gn:feature_code":"PPL",
    "gn:name":"Quinzano",
    "gn:population":73,
    "gn:timezone":"Europe/Rome",
    "iso:country":"IT",
    "wof:name":"Quinzano",
    "wof:placetype":"locality",
    "wof:population":73
},
  "geometry": {"coordinates":[10.23012,44.58951],"type":"Point"}
}