{
  "type": "Feature",
  "properties": {
    "gn:admin1_code":"18",
    "gn:admin2_code":"PG",
    "gn:admin3_code":"54022.0",
    "gn:asciiname":"Centrale Enel",
    "gn:country_code":"IT",
    "gn:dem":254,
    "gn:feature_class":"P",
    "gn:feature_code":"PPLL",
    "gn:name":"Centrale Enel",
    "gn:population":10,
    "gn:timezone":"Europe/Rome",
    "iso:country":"IT",
    "wof:name":"Centrale Enel",
    "wof:placetype":"locality",
    "wof:population":10
},
  "geometry": {"coordinates":[12.53915,42.89672],"type":"Point"}
}