{
  "type": "Feature",
  "properties": {
    "gn:admin1_code":"9.0",
    "gn:admin2_code":"BG",
    "gn:admin3_code":"16213.0",
    "gn:asciiname":"Baccanello",
    "gn:country_code":"IT",
    "gn:dem":254,
    "gn:feature_class":"P",
    "gn:feature_code":"PPLL",
    "gn:name":"Baccanello",
    "gn:population":0,
    "gn:timezone":"Europe/Rome",
    "iso:country":"IT",
    "wof:name":"Baccanello",
    "wof:placetype":"locality"
},
  "geometry": {"coordinates":[9.51083,45.68812],"type":"Point"}
}