{
  "type": "Feature",
  "properties": {
    "gn:admin1_code":"16",
    "gn:admin2_code":"SI",
    "gn:admin3_code":"52012.0",
    "gn:asciiname":"Collalto",
    "gn:country_code":"IT",
    "gn:dem":255,
    "gn:feature_class":"P",
    "gn:feature_code":"PPL",
    "gn:name":"Collalto",
    "gn:population":34,
    "gn:timezone":"Europe/Rome",
    "iso:country":"IT",
    "name:ceb_x_preferred":[
        "Collalto"
    ],
    "name:deu_x_preferred":[
        "Collalto"
    ],
    "name:ita_x_preferred":[
        "Collalto"
    ],
    "name:srp_x_preferred":[
        "Kolalto"
    ],
    "name:swe_x_preferred":[
        "Collalto"
    ],
    "wof:name":"Collalto",
    "wof:placetype":"locality",
    "wof:population":34
},
  "geometry": {"coordinates":[11.10633,43.34837],"type":"Point"}
}