{
  "type": "Feature",
  "properties": {
    "gn:admin1_code":"14.0",
    "gn:admin2_code":"SS",
    "gn:admin3_code":"90064.0",
    "gn:asciiname":"Siniscola",
    "gn:country_code":"IT",
    "gn:dem":113,
    "gn:feature_class":"P",
    "gn:feature_code":"PPL",
    "gn:name":"Siniscola",
    "gn:population":0,
    "gn:timezone":"Europe/Rome",
    "iso:country":"IT",
    "name:arg_x_preferred":[
        "Thiniscole"
    ],
    "name:azb_x_preferred":[
        "\u0633\u06cc\u0646\u06cc\u0633\u06a9\u0648\u0644\u0627"
    ],
    "name:bul_x_preferred":[
        "\u0421\u0438\u043d\u0438\u0441\u043a\u043e\u043b\u0430"
    ],
    "name:cat_x_preferred":[
        "Siniscola"
    ],
    "name:ceb_x_preferred":[
        "Siniscola"
    ],
    "name:ces_x_preferred":[
        "Siniscola"
    ],
    "name:dan_x_preferred":[
        "Siniscola"
    ],
    "name:deu_x_preferred":[
        "Siniscola"
    ],
    "name:epo_x_preferred":[
        "Siniscola"
    ],
    "name:eus_x_preferred":[
        "Siniscola"
    ],
    "name:fas_x_preferred":[
        "\u0633\u06cc\u0646\u06cc\u0633\u06a9\u0648\u0644\u0627"
    ],
    "name:fin_x_preferred":[
        "Siniscola"
    ],
    "name:fra_x_preferred":[
        "Siniscola"
    ],
    "name:glg_x_preferred":[
        "Siniscola"
    ],
    "name:hrv_x_preferred":[
        "Siniscola"
    ],
    "name:hun_x_preferred":[
        "Siniscola"
    ],
    "name:hye_x_preferred":[
        "\u054d\u056b\u0576\u056b\u057d\u056f\u0578\u056c\u0561"
    ],
    "name:ind_x_preferred":[
        "Siniscola"
    ],
    "name:ita_x_preferred":[
        "Siniscola"
    ],
    "name:jpn_x_preferred":[
        "\u30b7\u30cb\u30b9\u30b3\u30fc\u30e9"
    ],
    "name:kaz_x_preferred":[
        "\u0421\u0438\u043d\u0438\u0441\u043a\u043e\u043b\u0430"
    ],
    "name:lat_x_preferred":[
        "Sinischola"
    ],
    "name:lmo_x_preferred":[
        "Siniscola"
    ],
    "name:msa_x_preferred":[
        "Siniscola"
    ],
    "name:nap_x_preferred":[
        "Siniscola"
    ],
    "name:nld_x_preferred":[
        "Siniscola"
    ],
    "name:nno_x_preferred":[
        "Siniscola"
    ],
    "name:nor_x_preferred":[
        "Siniscola"
    ],
    "name:pms_x_preferred":[
        "Siniscola"
    ],
    "name:pol_x_preferred":[
        "Siniscola"
    ],
    "name:por_x_preferred":[
        "Siniscola"
    ],
    "name:ron_x_preferred":[
        "Siniscola"
    ],
    "name:rus_x_preferred":[
        "\u0421\u0438\u043d\u0438\u0441\u043a\u043e\u043b\u0430"
    ],
    "name:scn_x_preferred":[
        "Siniscola"
    ],
    "name:spa_x_preferred":[
        "Siniscola"
    ],
    "name:sqi_x_preferred":[
        "Siniscola"
    ],
    "name:srd_x_preferred":[
        "Thiniscole"
    ],
    "name:srp_x_preferred":[
        "\u0421\u0438\u043d\u0438\u0441\u043a\u043e\u043b\u0430"
    ],
    "name:tgl_x_preferred":[
        "Siniscola"
    ],
    "name:tur_x_preferred":[
        "Siniscola"
    ],
    "name:ukr_x_preferred":[
        "\u0421\u0456\u043d\u0456\u0441\u043a\u043e\u043b\u0430"
    ],
    "name:uzb_x_preferred":[
        "Siniscola"
    ],
    "name:vec_x_preferred":[
        "Siniscola"
    ],
    "name:vie_x_preferred":[
        "Siniscola"
    ],
    "name:vol_x_preferred":[
        "Siniscola"
    ],
    "name:war_x_preferred":[
        "Siniscola"
    ],
    "name:zho_x_preferred":[
        "\u897f\u5c3c\u65af\u79d1\u62c9"
    ],
    "wof:name":"Siniscola",
    "wof:placetype":"locality"
},
  "geometry": {"coordinates":[8.20528,40.7625],"type":"Point"}
}