{
  "type": "Feature",
  "properties": {
    "gn:admin1_code":"20.0",
    "gn:admin2_code":"VE",
    "gn:admin3_code":"27028.0",
    "gn:asciiname":"Baluello",
    "gn:country_code":"IT",
    "gn:dem":4,
    "gn:feature_class":"P",
    "gn:feature_code":"PPL",
    "gn:name":"Baluello",
    "gn:population":180,
    "gn:timezone":"Europe/Rome",
    "iso:country":"IT",
    "wof:name":"Baluello",
    "wof:placetype":"locality",
    "wof:population":180
},
  "geometry": {"coordinates":[12.05152,45.45359000000001],"type":"Point"}
}