{
  "type": "Feature",
  "properties": {
    "gn:admin1_code":"4",
    "gn:admin2_code":"BN",
    "gn:admin3_code":"62017.0",
    "gn:asciiname":"Masseria Germani",
    "gn:country_code":"IT",
    "gn:dem":624,
    "gn:feature_class":"P",
    "gn:feature_code":"PPL",
    "gn:name":"Masseria Germani",
    "gn:population":25,
    "gn:timezone":"Europe/Rome",
    "iso:country":"IT",
    "wof:name":"Masseria Germani",
    "wof:placetype":"locality",
    "wof:population":25
},
  "geometry": {"coordinates":[14.79111,41.40241],"type":"Point"}
}