{
  "type": "Feature",
  "properties": {
    "gn:admin1_code":"20.0",
    "gn:admin2_code":"TV",
    "gn:admin3_code":"26019.0",
    "gn:asciiname":"Capo di Sopra",
    "gn:country_code":"IT",
    "gn:dem":24,
    "gn:feature_class":"P",
    "gn:feature_code":"PPL",
    "gn:name":"Capo di Sopra",
    "gn:population":0,
    "gn:timezone":"Europe/Rome",
    "iso:country":"IT",
    "wof:name":"Capo di Sopra",
    "wof:placetype":"locality"
},
  "geometry": {"coordinates":[12.41667,45.86667],"type":"Point"}
}