{
  "type": "Feature",
  "properties": {
    "gn:admin1_code":"10.0",
    "gn:admin2_code":"MC",
    "gn:admin3_code":"43005.0",
    "gn:asciiname":"Villa Pepoli",
    "gn:cc2":"IT",
    "gn:country_code":"IT",
    "gn:dem":1054,
    "gn:feature_class":"P",
    "gn:feature_code":"PPL",
    "gn:name":"Villa Pepoli",
    "gn:population":0,
    "gn:timezone":"Europe/Rome",
    "iso:country":"IT",
    "name:und_x_variant":[
        "Villa di mezzo",
        "Villa Pepoli"
    ],
    "wof:name":"Villa Pepoli",
    "wof:placetype":"locality"
},
  "geometry": {"coordinates":[13.22934,42.99209000000001],"type":"Point"}
}