{
  "type": "Feature",
  "properties": {
    "iso:country":"IT",
    "name:eng_x_preferred":[
        "Maddalena"
    ],
    "name:ita_x_preferred":[
        "Maddalena"
    ],
    "name:nld_x_preferred":[
        "Maddalena"
    ],
    "wof:name":"Maddalena",
    "wof:placetype":"neighbourhood"
},
  "geometry": {"coordinates":[8.93280644059609,44.41074845834885],"type":"Point"}
}