{
  "type": "Feature",
  "properties": {
    "gn:admin1_code":"19",
    "gn:admin2_code":"AO",
    "gn:admin3_code":"7067.0",
    "gn:asciiname":"Champagnod",
    "gn:country_code":"IT",
    "gn:dem":1339,
    "gn:feature_class":"P",
    "gn:feature_code":"PPL",
    "gn:name":"Champagnod",
    "gn:population":28,
    "gn:timezone":"Europe/Rome",
    "iso:country":"IT",
    "wof:name":"Champagnod",
    "wof:placetype":"locality",
    "wof:population":28
},
  "geometry": {"coordinates":[7.57193,45.79522],"type":"Point"}
}