{
  "type": "Feature",
  "properties": {
    "gn:admin1_code":"3.0",
    "gn:admin2_code":"CS",
    "gn:admin3_code":"78081.0",
    "gn:asciiname":"Salerni",
    "gn:country_code":"IT",
    "gn:dem":236,
    "gn:feature_class":"P",
    "gn:feature_code":"PPL",
    "gn:name":"Salerni",
    "gn:population":898,
    "gn:timezone":"Europe/Rome",
    "iso:country":"IT",
    "wof:name":"Salerni",
    "wof:placetype":"locality",
    "wof:population":898
},
  "geometry": {"coordinates":[16.22904,39.3878],"type":"Point"}
}