{
  "type": "Feature",
  "properties": {
    "gn:admin1_code":"12",
    "gn:admin2_code":"TO",
    "gn:admin3_code":"1222.0",
    "gn:asciiname":"Rivetti",
    "gn:country_code":"IT",
    "gn:dem":336,
    "gn:feature_class":"P",
    "gn:feature_code":"PPL",
    "gn:name":"Rivetti",
    "gn:population":29,
    "gn:timezone":"Europe/Rome",
    "iso:country":"IT",
    "wof:name":"Rivetti",
    "wof:placetype":"locality",
    "wof:population":29
},
  "geometry": {"coordinates":[7.35664,44.90638],"type":"Point"}
}