{
  "type": "Feature",
  "properties": {
    "gn:admin1_code":"4",
    "gn:admin2_code":"SA",
    "gn:admin3_code":"65100.0",
    "gn:asciiname":"Laurito",
    "gn:country_code":"IT",
    "gn:dem":137,
    "gn:feature_class":"P",
    "gn:feature_code":"PPL",
    "gn:name":"Laurito",
    "gn:population":75,
    "gn:timezone":"Europe/Rome",
    "iso:country":"IT",
    "wof:name":"Laurito",
    "wof:placetype":"locality",
    "wof:population":75
},
  "geometry": {"coordinates":[14.5057,40.62392],"type":"Point"}
}