{
  "type": "Feature",
  "properties": {
    "gn:admin1_code":"4",
    "gn:admin2_code":"SA",
    "gn:admin3_code":"65100.0",
    "gn:asciiname":"Laurito",
    "gn:country_code":"IT",
    "gn:dem":137,
    "gn:feature_class":"P",
    "gn:feature_code":"PPL",
    "gn:name":"Laurito",
    "gn:population":75,
    "gn:timezone":"Europe/Rome",
    "iso:country":"IT",
    "name:azb_x_preferred":[
        "\u0644\u0627\u0648\u0631\u06cc\u062a\u0648"
    ],
    "name:bar_x_preferred":[
        "Laurito"
    ],
    "name:bel_x_preferred":[
        "\u041b\u0430\u045e\u0440\u044b\u0442\u0430"
    ],
    "name:bul_x_preferred":[
        "\u041b\u0430\u0443\u0440\u0438\u0442\u043e"
    ],
    "name:cat_x_preferred":[
        "Laurito"
    ],
    "name:ceb_x_preferred":[
        "Laurito"
    ],
    "name:deu_x_preferred":[
        "Laurito"
    ],
    "name:epo_x_preferred":[
        "Laurito"
    ],
    "name:eus_x_preferred":[
        "Laurito"
    ],
    "name:fas_x_preferred":[
        "\u0644\u0627\u0648\u0631\u06cc\u062a\u0648"
    ],
    "name:fra_x_preferred":[
        "Laurito"
    ],
    "name:hun_x_preferred":[
        "Laurito"
    ],
    "name:hye_x_preferred":[
        "\u053c\u0561\u0578\u0582\u0580\u056b\u057f\u0578"
    ],
    "name:ina_x_preferred":[
        "Laurito"
    ],
    "name:ind_x_preferred":[
        "Laurito"
    ],
    "name:ita_x_preferred":[
        "Laurito"
    ],
    "name:jpn_x_preferred":[
        "\u30e9\u30a6\u30ea\u30fc\u30c8"
    ],
    "name:kaz_x_preferred":[
        "\u041b\u0430\u0443\u0440\u0438\u0442\u043e"
    ],
    "name:kor_x_preferred":[
        "\ub77c\uc6b0\ub9ac\ud1a0"
    ],
    "name:lat_x_preferred":[
        "Lauretus"
    ],
    "name:lmo_x_preferred":[
        "Laurito"
    ],
    "name:msa_x_preferred":[
        "Laurito"
    ],
    "name:nap_x_preferred":[
        "Laurito"
    ],
    "name:nld_x_preferred":[
        "Laurito"
    ],
    "name:pms_x_preferred":[
        "Laurito"
    ],
    "name:pol_x_preferred":[
        "Laurito"
    ],
    "name:por_x_preferred":[
        "Laurito"
    ],
    "name:ron_x_preferred":[
        "Laurito"
    ],
    "name:rus_x_preferred":[
        "\u041b\u0430\u0443\u0440\u0438\u0442\u043e"
    ],
    "name:scn_x_preferred":[
        "Lauritu"
    ],
    "name:spa_x_preferred":[
        "Laurito"
    ],
    "name:srp_x_preferred":[
        "\u041b\u0430\u0443\u0440\u0438\u0442\u043e"
    ],
    "name:tgl_x_preferred":[
        "Laurito"
    ],
    "name:ukr_x_preferred":[
        "\u041b\u0430\u0443\u0440\u0438\u0442\u043e"
    ],
    "name:uzb_x_preferred":[
        "Laurito"
    ],
    "name:vec_x_preferred":[
        "Laurito"
    ],
    "name:vie_x_preferred":[
        "Laurito"
    ],
    "name:vol_x_preferred":[
        "Laurito"
    ],
    "name:war_x_preferred":[
        "Laurito"
    ],
    "name:zho_x_preferred":[
        "\u52b3\u91cc\u6258"
    ],
    "wof:name":"Laurito",
    "wof:placetype":"locality",
    "wof:population":75
},
  "geometry": {"coordinates":[14.5057,40.62392],"type":"Point"}
}