{
  "type": "Feature",
  "properties": {
    "gn:gn_country":"IT",
    "gn:gn_fcode":"PPLA3",
    "gn:gn_pop":980,
    "gn:population":724,
    "iso:country":"IT",
    "name:arm_x_preferred":[
        "\u053f\u0578\u0580\u0581\u0561\u0576\u0578"
    ],
    "name:baq_x_preferred":[
        "Corzano"
    ],
    "name:bul_x_preferred":[
        "\u041a\u043e\u0440\u0446\u0430\u043d\u043e"
    ],
    "name:cat_x_preferred":[
        "Corzano"
    ],
    "name:chi_x_preferred":[
        "\u79d1\u5c14\u624e\u8bfa"
    ],
    "name:dut_x_preferred":[
        "Corzano"
    ],
    "name:eng_x_preferred":[
        "Corzano"
    ],
    "name:epo_x_preferred":[
        "Corzano"
    ],
    "name:fre_x_preferred":[
        "Corzano"
    ],
    "name:ger_x_preferred":[
        "Corzano"
    ],
    "name:hun_x_preferred":[
        "Corzano"
    ],
    "name:ita_x_preferred":[
        "Corzano"
    ],
    "name:jpn_x_preferred":[
        "\u30b3\u30eb\u30c4\u30a1\u30fc\u30ce"
    ],
    "name:kaz_x_preferred":[
        "\u041a\u043e\u0440\u0446\u0430\u043d\u043e"
    ],
    "name:lat_x_preferred":[
        "Corzanum"
    ],
    "name:lmo_x_preferred":[
        "Cors\u00e0"
    ],
    "name:may_x_preferred":[
        "Corzano"
    ],
    "name:nap_x_preferred":[
        "Corzano"
    ],
    "name:oci_x_preferred":[
        "Corzano"
    ],
    "name:pms_x_preferred":[
        "Corzano"
    ],
    "name:pol_x_preferred":[
        "Corzano"
    ],
    "name:por_x_preferred":[
        "Corzano"
    ],
    "name:rum_x_preferred":[
        "Corzano"
    ],
    "name:rus_x_preferred":[
        "\u041a\u043e\u0440\u0446\u0430\u043d\u043e"
    ],
    "name:scn_x_preferred":[
        "Corzano"
    ],
    "name:spa_x_preferred":[
        "Corzano"
    ],
    "name:srp_x_preferred":[
        "Corzano"
    ],
    "name:tgl_x_preferred":[
        "Corzano"
    ],
    "name:ukr_x_preferred":[
        "\u041a\u043e\u0440\u0446\u0430\u043d\u043e"
    ],
    "name:uzb_x_preferred":[
        "Corzano"
    ],
    "name:vie_x_preferred":[
        "Corzano"
    ],
    "name:vol_x_preferred":[
        "Corzano"
    ],
    "name:war_x_preferred":[
        "Corzano"
    ],
    "qs_pg:aaroncc":"IT",
    "qs_pg:gn_country":"IT",
    "qs_pg:gn_fcode":"PPLA3",
    "qs_pg:gn_pop":980,
    "qs_pg:name":"Corzano",
    "qs_pg:name_adm0":"Italia",
    "qs_pg:name_adm1":"Lombardia",
    "qs_pg:photos_9r":0,
    "qs_pg:photos_sr":0,
    "qs_pg:pop_sr":2,
    "qs_pg:qs_pg_placetype":"locality",
    "qs_pg:qs_pg_placetype_gp":"Town",
    "qs_pg:woe_adm0":23424853,
    "woe:adm0_id":23424853,
    "woe:name_adm0":"Italia",
    "woe:name_adm1":"Lombardia",
    "woe:placetype":"Town",
    "wof:name":"Corzano",
    "wof:placetype":"locality",
    "wof:population":724
},
  "geometry": {"coordinates":[10.00737,45.44378],"type":"Point"}
}