{
  "type": "Feature",
  "properties": {
    "gn:admin1_code":"17",
    "gn:admin2_code":"BZ",
    "gn:admin3_code":"21016.0",
    "gn:asciiname":"Castelpietra",
    "gn:country_code":"IT",
    "gn:dem":1006,
    "gn:feature_class":"P",
    "gn:feature_code":"PPL",
    "gn:name":"Castelpietra",
    "gn:population":47,
    "gn:timezone":"Europe/Rome",
    "iso:country":"IT",
    "wof:name":"Castelpietra",
    "wof:placetype":"locality",
    "wof:population":47
},
  "geometry": {"coordinates":[11.45732,46.88296],"type":"Point"}
}