{
  "type": "Feature",
  "properties": {
    "gn:admin1_code":"20",
    "gn:admin2_code":"TV",
    "gn:admin3_code":"26049.0",
    "gn:asciiname":"Calnova",
    "gn:country_code":"IT",
    "gn:dem":5,
    "gn:feature_class":"P",
    "gn:feature_code":"PPL",
    "gn:name":"Calnova",
    "gn:population":267,
    "gn:timezone":"Europe/Rome",
    "iso:country":"IT",
    "wof:name":"Calnova",
    "wof:placetype":"locality",
    "wof:population":267
},
  "geometry": {"coordinates":[12.61402,45.75153],"type":"Point"}
}