{
  "type": "Feature",
  "properties": {
    "gn:admin1_code":"9.0",
    "gn:admin2_code":"MN",
    "gn:admin3_code":"20012.0",
    "gn:asciiname":"Fontanella Grazioli",
    "gn:country_code":"IT",
    "gn:dem":39,
    "gn:feature_class":"P",
    "gn:feature_code":"PPL",
    "gn:name":"Fontanella Grazioli",
    "gn:population":377,
    "gn:timezone":"Europe/Rome",
    "iso:country":"IT",
    "wof:name":"Fontanella Grazioli",
    "wof:placetype":"locality",
    "wof:population":377
},
  "geometry": {"coordinates":[10.32833,45.19502],"type":"Point"}
}