{
  "type": "Feature",
  "properties": {
    "gn:admin1_code":"11.0",
    "gn:admin2_code":"IS",
    "gn:admin3_code":"94007.0",
    "gn:asciiname":"Castiglione",
    "gn:cc2":"IT",
    "gn:country_code":"IT",
    "gn:dem":922,
    "gn:elevation":"919.0",
    "gn:feature_class":"P",
    "gn:feature_code":"PPL",
    "gn:name":"Castiglione",
    "gn:population":196,
    "gn:timezone":"Europe/Rome",
    "iso:country":"IT",
    "name:bul_x_preferred":[
        "\u041a\u0430\u0441\u0442\u0438\u043b\u044c\u043e\u043d\u0435"
    ],
    "name:ceb_x_preferred":[
        "Castiglione"
    ],
    "name:deu_x_preferred":[
        "Castiglione"
    ],
    "name:fra_x_preferred":[
        "Castiglione"
    ],
    "name:ita_x_preferred":[
        "Castiglione"
    ],
    "name:jpn_x_preferred":[
        "\u30ab\u30b9\u30c6\u30a3\u30ea\u30aa\u30fc\u30cd"
    ],
    "name:kor_x_preferred":[
        "\uce74\uc2a4\ud2f8\ub9ac\uc624\ub124"
    ],
    "name:lat_x_preferred":[
        "Castillio"
    ],
    "name:nld_x_preferred":[
        "Castiglione"
    ],
    "name:por_x_preferred":[
        "Castiglione"
    ],
    "name:rus_x_preferred":[
        "\u041a\u0430\u0441\u0442\u0438\u043b\u044c\u043e\u043d\u0435"
    ],
    "name:sco_x_preferred":[
        "Castiglione"
    ],
    "name:spa_x_preferred":[
        "Castiglione"
    ],
    "name:srp_x_preferred":[
        "Kastiljone"
    ],
    "name:swe_x_preferred":[
        "Castiglione"
    ],
    "name:ukr_x_preferred":[
        "\u041a\u0430\u0441\u0442\u0456\u043b\u044c\u0439\u043e\u043d\u0435"
    ],
    "name:und_x_variant":[
        "Castiglion"
    ],
    "wof:name":"Castiglione",
    "wof:placetype":"locality",
    "wof:population":196
},
  "geometry": {"coordinates":[14.30564,41.72584000000001],"type":"Point"}
}