{
  "type": "Feature",
  "properties": {
    "gn:admin1_code":"11.0",
    "gn:admin2_code":"IS",
    "gn:admin3_code":"94007.0",
    "gn:asciiname":"Castiglione",
    "gn:cc2":"IT",
    "gn:country_code":"IT",
    "gn:dem":922,
    "gn:elevation":"919.0",
    "gn:feature_class":"P",
    "gn:feature_code":"PPL",
    "gn:name":"Castiglione",
    "gn:population":196,
    "gn:timezone":"Europe/Rome",
    "iso:country":"IT",
    "name:und_x_variant":[
        "Castiglion",
        "Castiglione"
    ],
    "wof:name":"Castiglione",
    "wof:placetype":"locality",
    "wof:population":196
},
  "geometry": {"coordinates":[14.30564,41.72584000000001],"type":"Point"}
}