{
  "type": "Feature",
  "properties": {
    "gn:admin1_code":"12",
    "gn:admin2_code":"TO",
    "gn:admin3_code":"1147.0",
    "gn:asciiname":"Piccole Tanze-Vallone",
    "gn:country_code":"IT",
    "gn:dem":643,
    "gn:feature_class":"P",
    "gn:feature_code":"PPL",
    "gn:name":"Piccole Tanze-Vallone",
    "gn:population":29,
    "gn:timezone":"Europe/Rome",
    "iso:country":"IT",
    "wof:name":"Piccole Tanze-Vallone",
    "wof:placetype":"locality",
    "wof:population":29
},
  "geometry": {"coordinates":[7.10545,45.12237],"type":"Point"}
}