{
  "type": "Feature",
  "properties": {
    "gn:admin1_code":"16",
    "gn:admin2_code":"MS",
    "gn:admin3_code":"45004.0",
    "gn:asciiname":"Ugliancaldo",
    "gn:country_code":"IT",
    "gn:dem":728,
    "gn:feature_class":"P",
    "gn:feature_code":"PPL",
    "gn:name":"Ugliancaldo",
    "gn:population":18,
    "gn:timezone":"Europe/Rome",
    "iso:country":"IT",
    "wof:name":"Ugliancaldo",
    "wof:placetype":"locality",
    "wof:population":18
},
  "geometry": {"coordinates":[10.18258,44.17447],"type":"Point"}
}