{
  "type": "Feature",
  "properties": {
    "gn:admin1_code":"3",
    "gn:admin2_code":"CS",
    "gn:admin3_code":"78070.0",
    "gn:asciiname":"Valleleotta Superiore",
    "gn:country_code":"IT",
    "gn:dem":186,
    "gn:feature_class":"P",
    "gn:feature_code":"PPL",
    "gn:name":"Valleleotta Superiore",
    "gn:population":167,
    "gn:timezone":"Europe/Rome",
    "iso:country":"IT",
    "wof:name":"Valleleotta Superiore",
    "wof:placetype":"locality",
    "wof:population":167
},
  "geometry": {"coordinates":[16.2724,39.47258],"type":"Point"}
}