{
  "type": "Feature",
  "properties": {
    "gn:admin1_code":"4",
    "gn:admin2_code":"AV",
    "gn:admin3_code":"64008.0",
    "gn:asciiname":"Pennini",
    "gn:country_code":"IT",
    "gn:dem":454,
    "gn:feature_class":"P",
    "gn:feature_code":"PPL",
    "gn:name":"Pennini",
    "gn:population":28,
    "gn:timezone":"Europe/Rome",
    "iso:country":"IT",
    "wof:name":"Pennini",
    "wof:placetype":"locality",
    "wof:population":28
},
  "geometry": {"coordinates":[14.77148,40.92708],"type":"Point"}
}