{
  "type": "Feature",
  "properties": {
    "gn:admin1_code":"1",
    "gn:admin2_code":"CH",
    "gn:admin3_code":"69087.0",
    "gn:asciiname":"Reliscia",
    "gn:country_code":"IT",
    "gn:dem":203,
    "gn:feature_class":"P",
    "gn:feature_code":"PPL",
    "gn:name":"Reliscia",
    "gn:population":42,
    "gn:timezone":"Europe/Rome",
    "iso:country":"IT",
    "wof:name":"Reliscia",
    "wof:placetype":"locality",
    "wof:population":42
},
  "geometry": {"coordinates":[14.59873,42.11081],"type":"Point"}
}