{
  "type": "Feature",
  "properties": {
    "gn:admin1_code":"16.0",
    "gn:admin2_code":"PI",
    "gn:admin3_code":"50032.0",
    "gn:asciiname":"Corazzano",
    "gn:country_code":"IT",
    "gn:dem":56,
    "gn:feature_class":"P",
    "gn:feature_code":"PPL",
    "gn:name":"Corazzano",
    "gn:population":360,
    "gn:timezone":"Europe/Rome",
    "iso:country":"IT",
    "name:ceb_x_preferred":[
        "Corazzano"
    ],
    "name:fas_x_preferred":[
        "\u06a9\u0648\u0631\u0627\u0632\u0627\u0646\u0648"
    ],
    "name:ita_x_preferred":[
        "Corazzano"
    ],
    "name:srp_x_preferred":[
        "\u041a\u043e\u0440\u0430\u0446\u0430\u043d\u043e"
    ],
    "wof:name":"Corazzano",
    "wof:placetype":"locality",
    "wof:population":360
},
  "geometry": {"coordinates":[10.8705,43.61928],"type":"Point"}
}