{
  "type": "Feature",
  "properties": {
    "gn:admin1_code":"9",
    "gn:admin2_code":"BS",
    "gn:admin3_code":"17143.0",
    "gn:asciiname":"Baibo-Morosino",
    "gn:country_code":"IT",
    "gn:dem":190,
    "gn:feature_class":"P",
    "gn:feature_code":"PPL",
    "gn:name":"Baib\u00f2-Morosino",
    "gn:population":45,
    "gn:timezone":"Europe/Rome",
    "iso:country":"IT",
    "name:und_x_variant":[
        "Baib\u00f2-Morosino"
    ],
    "wof:name":"Baibo-Morosino",
    "wof:placetype":"locality",
    "wof:population":45
},
  "geometry": {"coordinates":[10.12301,45.82878],"type":"Point"}
}