{
  "type": "Feature",
  "properties": {
    "gn:admin1_code":"20",
    "gn:admin2_code":"TV",
    "gn:admin3_code":"26076.0",
    "gn:asciiname":"Chiarini",
    "gn:country_code":"IT",
    "gn:dem":45,
    "gn:feature_class":"P",
    "gn:feature_code":"PPL",
    "gn:name":"Chiarini",
    "gn:population":74,
    "gn:timezone":"Europe/Rome",
    "iso:country":"IT",
    "wof:name":"Chiarini",
    "wof:placetype":"locality",
    "wof:population":74
},
  "geometry": {"coordinates":[12.36282,45.89587],"type":"Point"}
}