{
  "type": "Feature",
  "properties": {
    "gn:admin1_code":"5",
    "gn:admin2_code":"RA",
    "gn:admin3_code":"39012.0",
    "gn:asciiname":"Ciribella",
    "gn:country_code":"IT",
    "gn:dem":4,
    "gn:feature_class":"P",
    "gn:feature_code":"PPL",
    "gn:name":"Ciribella",
    "gn:population":62,
    "gn:timezone":"Europe/Rome",
    "iso:country":"IT",
    "wof:name":"Ciribella",
    "wof:placetype":"locality",
    "wof:population":62
},
  "geometry": {"coordinates":[11.90748,44.52469],"type":"Point"}
}