{
  "type": "Feature",
  "properties": {
    "gn:admin1_code":"4",
    "gn:admin2_code":"CE",
    "gn:admin3_code":"61035.0",
    "gn:asciiname":"Lautoni",
    "gn:country_code":"IT",
    "gn:dem":257,
    "gn:feature_class":"P",
    "gn:feature_code":"PPL",
    "gn:name":"Lautoni",
    "gn:population":128,
    "gn:timezone":"Europe/Rome",
    "iso:country":"IT",
    "wof:name":"Lautoni",
    "wof:placetype":"locality",
    "wof:population":128
},
  "geometry": {"coordinates":[14.22465,41.21777],"type":"Point"}
}