{
  "type": "Feature",
  "properties": {
    "gn:admin1_code":"7",
    "gn:admin2_code":"VT",
    "gn:admin3_code":"56039.0",
    "gn:asciiname":"Manetti",
    "gn:country_code":"IT",
    "gn:dem":244,
    "gn:feature_class":"P",
    "gn:feature_code":"PPL",
    "gn:name":"Manetti",
    "gn:population":47,
    "gn:timezone":"Europe/Rome",
    "iso:country":"IT",
    "wof:name":"Manetti",
    "wof:placetype":"locality",
    "wof:population":47
},
  "geometry": {"coordinates":[12.29522,42.24733],"type":"Point"}
}