{
  "type": "Feature",
  "properties": {
    "gn:admin1_code":"15.0",
    "gn:admin2_code":"AG",
    "gn:admin3_code":"84023.0",
    "gn:asciiname":"Porto Palo Est",
    "gn:country_code":"IT",
    "gn:dem":12,
    "gn:feature_class":"P",
    "gn:feature_code":"PPL",
    "gn:name":"Porto Palo Est",
    "gn:population":17,
    "gn:timezone":"Europe/Rome",
    "iso:country":"IT",
    "wof:name":"Porto Palo Est",
    "wof:placetype":"locality",
    "wof:population":17
},
  "geometry": {"coordinates":[12.91389,37.57861],"type":"Point"}
}