{
  "type": "Feature",
  "properties": {
    "gn:admin1_code":"12.0",
    "gn:admin2_code":"TO",
    "gn:admin3_code":"1190.0",
    "gn:asciiname":"Bert",
    "gn:country_code":"IT",
    "gn:dem":793,
    "gn:feature_class":"P",
    "gn:feature_code":"PPL",
    "gn:name":"Bert",
    "gn:population":12,
    "gn:timezone":"Europe/Rome",
    "iso:country":"IT",
    "name:ceb_x_preferred":[
        "Bert"
    ],
    "name:fra_x_preferred":[
        "Bert"
    ],
    "name:ind_x_preferred":[
        "Bert"
    ],
    "name:nld_x_preferred":[
        "Bert"
    ],
    "name:rus_x_preferred":[
        "\u0411\u0435\u0440\u0442"
    ],
    "name:spa_x_preferred":[
        "Bert"
    ],
    "name:swe_x_preferred":[
        "Bert"
    ],
    "wof:name":"Bert",
    "wof:placetype":"locality",
    "wof:population":12
},
  "geometry": {"coordinates":[7.24006,44.94623],"type":"Point"}
}