{
  "type": "Feature",
  "properties": {
    "gn:admin1_code":"9",
    "gn:admin2_code":"BS",
    "gn:admin3_code":"17145.0",
    "gn:asciiname":"Borrine",
    "gn:country_code":"IT",
    "gn:dem":157,
    "gn:feature_class":"P",
    "gn:feature_code":"PPL",
    "gn:name":"Borrine",
    "gn:population":25,
    "gn:timezone":"Europe/Rome",
    "iso:country":"IT",
    "wof:name":"Borrine",
    "wof:placetype":"locality",
    "wof:population":25
},
  "geometry": {"coordinates":[10.5118,45.55137],"type":"Point"}
}