{
  "type": "Feature",
  "properties": {
    "gn:admin1_code":"20.0",
    "gn:admin2_code":"TV",
    "gn:admin3_code":"26022.0",
    "gn:asciiname":"San Rocco",
    "gn:country_code":"IT",
    "gn:dem":69,
    "gn:feature_class":"P",
    "gn:feature_code":"PPL",
    "gn:name":"San Rocco",
    "gn:population":0,
    "gn:timezone":"Europe/Rome",
    "iso:country":"IT",
    "wof:name":"San Rocco",
    "wof:placetype":"locality"
},
  "geometry": {"coordinates":[12.38333,45.95],"type":"Point"}
}