{
  "type": "Feature",
  "properties": {
    "gn:admin1_code":"8",
    "gn:admin2_code":"SV",
    "gn:admin3_code":"9031.0",
    "gn:asciiname":"Cappelletta-Borri",
    "gn:country_code":"IT",
    "gn:dem":141,
    "gn:feature_class":"P",
    "gn:feature_code":"PPL",
    "gn:name":"Cappelletta-Borri",
    "gn:population":35,
    "gn:timezone":"Europe/Rome",
    "iso:country":"IT",
    "wof:name":"Cappelletta-Borri",
    "wof:placetype":"locality",
    "wof:population":35
},
  "geometry": {"coordinates":[8.25386,44.16546],"type":"Point"}
}