{
  "type": "Feature",
  "properties": {
    "gn:admin1_code":"18.0",
    "gn:admin2_code":"PG",
    "gn:admin3_code":"54039.0",
    "gn:asciiname":"Fosso del Diavolo",
    "gn:country_code":"IT",
    "gn:dem":216,
    "gn:feature_class":"P",
    "gn:feature_code":"PPL",
    "gn:name":"Fosso del Diavolo",
    "gn:population":305,
    "gn:timezone":"Europe/Rome",
    "iso:country":"IT",
    "wof:name":"Fosso del Diavolo",
    "wof:placetype":"locality",
    "wof:population":305
},
  "geometry": {"coordinates":[12.46612,43.15931],"type":"Point"}
}