{
  "type": "Feature",
  "properties": {
    "gn:admin1_code":"3",
    "gn:admin2_code":"KR",
    "gn:admin3_code":"101024.0",
    "gn:asciiname":"Timperosso",
    "gn:country_code":"IT",
    "gn:dem":62,
    "gn:feature_class":"P",
    "gn:feature_code":"PPL",
    "gn:name":"Timperosso",
    "gn:population":25,
    "gn:timezone":"Europe/Rome",
    "iso:country":"IT",
    "wof:name":"Timperosso",
    "wof:placetype":"locality",
    "wof:population":25
},
  "geometry": {"coordinates":[17.0304,39.1501],"type":"Point"}
}