{
  "type": "Feature",
  "properties": {
    "gn:admin1_code":"1.0",
    "gn:admin2_code":"AQ",
    "gn:admin3_code":"66052.0",
    "gn:asciiname":"Santa Croce",
    "gn:country_code":"IT",
    "gn:dem":923,
    "gn:feature_class":"P",
    "gn:feature_code":"PPL",
    "gn:name":"Santa Croce",
    "gn:population":0,
    "gn:timezone":"Europe/Rome",
    "iso:country":"IT",
    "name:bul_x_preferred":[
        "\u0421\u0430\u043d\u0442\u0430 \u041a\u0440\u043e\u0447\u0435"
    ],
    "name:ceb_x_preferred":[
        "Santa Croce"
    ],
    "name:ces_x_preferred":[
        "Santa Croce"
    ],
    "name:deu_x_preferred":[
        "Santa Croce"
    ],
    "name:fra_x_preferred":[
        "Santa Croce"
    ],
    "name:heb_x_preferred":[
        "\u05e1\u05e0\u05d8\u05d4 \u05e7\u05e8\u05d5\u05e6'\u05d4"
    ],
    "name:hun_x_preferred":[
        "Santa Croce"
    ],
    "name:ita_x_preferred":[
        "Santa Croce"
    ],
    "name:nld_x_preferred":[
        "Santa Croce"
    ],
    "name:por_x_preferred":[
        "Santa Croce"
    ],
    "name:rus_x_preferred":[
        "\u0421\u0430\u043d\u0442\u0430-\u041a\u0440\u043e\u0447\u0435"
    ],
    "name:srp_x_preferred":[
        "\u0421\u0430\u043d\u0442\u0430 \u041a\u0440\u043e\u0447\u0435"
    ],
    "name:swe_x_preferred":[
        "Santa Croce"
    ],
    "wof:name":"Santa Croce",
    "wof:placetype":"locality"
},
  "geometry": {"coordinates":[13.31873,42.30416],"type":"Point"}
}