{
  "type": "Feature",
  "properties": {
    "gn:admin1_code":"1.0",
    "gn:admin2_code":"AQ",
    "gn:admin3_code":"66052.0",
    "gn:asciiname":"Santa Croce",
    "gn:country_code":"IT",
    "gn:dem":923,
    "gn:feature_class":"P",
    "gn:feature_code":"PPL",
    "gn:name":"Santa Croce",
    "gn:population":0,
    "gn:timezone":"Europe/Rome",
    "iso:country":"IT",
    "wof:name":"Santa Croce",
    "wof:placetype":"locality"
},
  "geometry": {"coordinates":[13.31873,42.30416],"type":"Point"}
}