{
  "type": "Feature",
  "properties": {
    "gn:admin1_code":"16.0",
    "gn:admin2_code":"FI",
    "gn:admin3_code":"48044.0",
    "gn:asciiname":"Lecore",
    "gn:country_code":"IT",
    "gn:dem":41,
    "gn:elevation":"40.0",
    "gn:feature_class":"P",
    "gn:feature_code":"PPL",
    "gn:name":"Lecore",
    "gn:population":402,
    "gn:timezone":"Europe/Rome",
    "iso:country":"IT",
    "wof:name":"Lecore",
    "wof:placetype":"locality",
    "wof:population":402
},
  "geometry": {"coordinates":[11.07422,43.79978],"type":"Point"}
}