{
  "type": "Feature",
  "properties": {
    "gn:admin1_code":"9.0",
    "gn:admin2_code":"PV",
    "gn:admin3_code":"18098.0",
    "gn:asciiname":"Case del Molino",
    "gn:country_code":"IT",
    "gn:dem":289,
    "gn:elevation":"293.0",
    "gn:feature_class":"P",
    "gn:feature_code":"PPL",
    "gn:name":"Case del Molino",
    "gn:population":61,
    "gn:timezone":"Europe/Rome",
    "iso:country":"IT",
    "wof:name":"Case del Molino",
    "wof:placetype":"locality",
    "wof:population":61
},
  "geometry": {"coordinates":[9.131,44.91273],"type":"Point"}
}