{
  "type": "Feature",
  "properties": {
    "gn:admin1_code":"12",
    "gn:admin2_code":"CN",
    "gn:admin3_code":"4188.0",
    "gn:asciiname":"Bozzola",
    "gn:country_code":"IT",
    "gn:dem":530,
    "gn:feature_class":"P",
    "gn:feature_code":"PPL",
    "gn:name":"Bozzola",
    "gn:population":12,
    "gn:timezone":"Europe/Rome",
    "iso:country":"IT",
    "wof:name":"Bozzola",
    "wof:placetype":"locality",
    "wof:population":12
},
  "geometry": {"coordinates":[7.93731,44.45684],"type":"Point"}
}