{
  "type": "Feature",
  "properties": {
    "gn:admin1_code":"12.0",
    "gn:admin2_code":"CN",
    "gn:admin3_code":"4157.0",
    "gn:asciiname":"Gari",
    "gn:country_code":"IT",
    "gn:dem":995,
    "gn:feature_class":"P",
    "gn:feature_code":"PPLL",
    "gn:name":"Gari",
    "gn:population":1,
    "gn:timezone":"Europe/Rome",
    "iso:country":"IT",
    "name:bul_x_preferred":[
        "\u0413\u0430\u0440\u0438"
    ],
    "name:ceb_x_preferred":[
        "Gari"
    ],
    "name:deu_x_preferred":[
        "Gari"
    ],
    "name:eus_x_preferred":[
        "Gari"
    ],
    "name:fra_x_preferred":[
        "Gari"
    ],
    "name:ita_x_preferred":[
        "Gari"
    ],
    "name:jpn_x_preferred":[
        "\u30ac\u30ea"
    ],
    "name:nld_x_preferred":[
        "Gari"
    ],
    "name:por_x_preferred":[
        "Gari"
    ],
    "name:rus_x_preferred":[
        "\u0413\u0430\u0440\u0438"
    ],
    "name:spa_x_preferred":[
        "Gari"
    ],
    "name:srp_x_preferred":[
        "\u0413\u0430\u0440\u0438"
    ],
    "name:swe_x_preferred":[
        "Gari"
    ],
    "name:ukr_x_preferred":[
        "\u0413\u0430\u0440\u0456"
    ],
    "name:vie_x_preferred":[
        "Gari"
    ],
    "wof:name":"Gari",
    "wof:placetype":"locality",
    "wof:population":1
},
  "geometry": {"coordinates":[7.26354,44.64821],"type":"Point"}
}