{
  "type": "Feature",
  "properties": {
    "gn:admin1_code":"12.0",
    "gn:admin2_code":"CN",
    "gn:admin3_code":"4157.0",
    "gn:asciiname":"Gari",
    "gn:country_code":"IT",
    "gn:dem":995,
    "gn:feature_class":"P",
    "gn:feature_code":"PPLL",
    "gn:name":"Gari",
    "gn:population":1,
    "gn:timezone":"Europe/Rome",
    "iso:country":"IT",
    "wof:name":"Gari",
    "wof:placetype":"locality",
    "wof:population":1
},
  "geometry": {"coordinates":[7.26354,44.64821],"type":"Point"}
}