{
  "type": "Feature",
  "properties": {
    "gn:admin1_code":"9.0",
    "gn:admin2_code":"BS",
    "gn:admin3_code":"17062.0",
    "gn:asciiname":"Borgonato",
    "gn:country_code":"IT",
    "gn:dem":208,
    "gn:elevation":"215.0",
    "gn:feature_class":"P",
    "gn:feature_code":"PPL",
    "gn:name":"Borgonato",
    "gn:population":532,
    "gn:timezone":"Europe/Rome",
    "iso:country":"IT",
    "wof:name":"Borgonato",
    "wof:placetype":"locality",
    "wof:population":532
},
  "geometry": {"coordinates":[10.0182,45.6207],"type":"Point"}
}