{
  "type": "Feature",
  "properties": {
    "gn:admin1_code":"6.0",
    "gn:admin2_code":"UD",
    "gn:admin3_code":"30136.0",
    "gn:asciiname":"Fielis",
    "gn:country_code":"IT",
    "gn:dem":824,
    "gn:elevation":"825.0",
    "gn:feature_class":"P",
    "gn:feature_code":"PPL",
    "gn:name":"Fielis",
    "gn:population":73,
    "gn:timezone":"Europe/Rome",
    "iso:country":"IT",
    "wof:name":"Fielis",
    "wof:placetype":"locality",
    "wof:population":73
},
  "geometry": {"coordinates":[13.00662,46.47182],"type":"Point"}
}