{
  "type": "Feature",
  "properties": {
    "gn:admin1_code":"14.0",
    "gn:admin2_code":"NU",
    "gn:admin3_code":"91016.0",
    "gn:asciiname":"Ovolaccio",
    "gn:country_code":"IT",
    "gn:dem":1272,
    "gn:feature_class":"P",
    "gn:feature_code":"PPL",
    "gn:name":"Ovolaccio",
    "gn:population":0,
    "gn:timezone":"Europe/Rome",
    "iso:country":"IT",
    "wof:name":"Ovolaccio",
    "wof:placetype":"locality"
},
  "geometry": {"coordinates":[9.21667,40.01667],"type":"Point"}
}