{
  "type": "Feature",
  "properties": {
    "gn:admin1_code":"9.0",
    "gn:admin2_code":"LC",
    "gn:admin3_code":"97048.0",
    "gn:asciiname":"Pomeo",
    "gn:country_code":"IT",
    "gn:dem":341,
    "gn:feature_class":"P",
    "gn:feature_code":"PPL",
    "gn:name":"Pomeo",
    "gn:population":0,
    "gn:timezone":"Europe/Rome",
    "iso:country":"IT",
    "wof:name":"Pomeo",
    "wof:placetype":"locality"
},
  "geometry": {"coordinates":[9.41667,45.71667],"type":"Point"}
}