{
  "type": "Feature",
  "properties": {
    "gn:admin1_code":"16",
    "gn:admin2_code":"LU",
    "gn:admin3_code":"46004.0",
    "gn:asciiname":"Piano della Rocca",
    "gn:country_code":"IT",
    "gn:dem":114,
    "gn:feature_class":"P",
    "gn:feature_code":"PPL",
    "gn:name":"Piano della Rocca",
    "gn:population":326,
    "gn:timezone":"Europe/Rome",
    "iso:country":"IT",
    "wof:name":"Piano della Rocca",
    "wof:placetype":"locality",
    "wof:population":326
},
  "geometry": {"coordinates":[10.54524,44.00574],"type":"Point"}
}