{
  "type": "Feature",
  "properties": {
    "gn:admin1_code":"7",
    "gn:admin2_code":"RI",
    "gn:admin3_code":"57002.0",
    "gn:asciiname":"Nommisci",
    "gn:country_code":"IT",
    "gn:dem":1151,
    "gn:feature_class":"P",
    "gn:feature_code":"PPL",
    "gn:name":"Nommisci",
    "gn:population":56,
    "gn:timezone":"Europe/Rome",
    "iso:country":"IT",
    "wof:name":"Nommisci",
    "wof:placetype":"locality",
    "wof:population":56
},
  "geometry": {"coordinates":[13.27769,42.60182],"type":"Point"}
}