{
  "type": "Feature",
  "properties": {
    "iso:country":"IT",
    "name:cat_x_preferred":[
        "Bussana Vecchia"
    ],
    "name:dut_x_preferred":[
        "Bussana Vecchia"
    ],
    "name:eng_x_preferred":[
        "Bussana Vecchia"
    ],
    "name:fre_x_preferred":[
        "Bussana Vecchia"
    ],
    "name:ger_x_preferred":[
        "Bussana Vecchia"
    ],
    "name:hrv_x_preferred":[
        "Bussana Vecchia"
    ],
    "name:hun_x_preferred":[
        "Bussana Vecchia"
    ],
    "name:ita_x_preferred":[
        "Bussana Vecchia"
    ],
    "name:spa_x_preferred":[
        "Bussana Vecchia"
    ],
    "name:srp_x_preferred":[
        "Busana Vekija"
    ],
    "name:swe_x_preferred":[
        "Bussana Vecchia"
    ],
    "qs_pg:aaroncc":"IT",
    "qs_pg:name":"Bussana Vecchia",
    "qs_pg:name_adm0":"Italia",
    "qs_pg:name_adm1":"Liguria",
    "qs_pg:photos":710,
    "qs_pg:photos_1k":144,
    "qs_pg:photos_9k":3,
    "qs_pg:photos_9r":5,
    "qs_pg:photos_all":710,
    "qs_pg:photos_sr":8,
    "qs_pg:pop_sr":0,
    "qs_pg:qs_pg_placetype":"locality",
    "qs_pg:qs_pg_placetype_gp":"Town",
    "qs_pg:woe_adm0":23424853,
    "woe:adm0_id":23424853,
    "woe:name_adm0":"Italia",
    "woe:name_adm1":"Liguria",
    "woe:placetype":"Town",
    "wof:name":"Bussana Vecchia",
    "wof:placetype":"locality"
},
  "geometry": {"coordinates":[7.829432,43.837188],"type":"Point"}
}