{
  "type": "Feature",
  "properties": {
    "gn:admin1_code":"9",
    "gn:admin2_code":"BS",
    "gn:admin3_code":"17166.0",
    "gn:asciiname":"Fossato",
    "gn:country_code":"IT",
    "gn:dem":137,
    "gn:feature_class":"P",
    "gn:feature_code":"PPL",
    "gn:name":"Fossato",
    "gn:population":82,
    "gn:timezone":"Europe/Rome",
    "iso:country":"IT",
    "wof:name":"Fossato",
    "wof:placetype":"locality",
    "wof:population":82
},
  "geometry": {"coordinates":[9.98929,45.52646],"type":"Point"}
}