{
  "type": "Feature",
  "properties": {
    "gn:admin1_code":"3.0",
    "gn:admin2_code":"CS",
    "gn:admin3_code":"78003.0",
    "gn:asciiname":"Pagania Vallonecupo",
    "gn:country_code":"IT",
    "gn:dem":634,
    "gn:feature_class":"P",
    "gn:feature_code":"PPL",
    "gn:name":"Pagania Vallonecupo",
    "gn:population":117,
    "gn:timezone":"Europe/Rome",
    "iso:country":"IT",
    "wof:name":"Pagania Vallonecupo",
    "wof:placetype":"locality",
    "wof:population":117
},
  "geometry": {"coordinates":[16.39742,39.55873],"type":"Point"}
}