{
  "type": "Feature",
  "properties": {
    "gn:admin1_code":"17",
    "gn:admin2_code":"TN",
    "gn:admin3_code":"22180.0",
    "gn:asciiname":"Castel Belfort",
    "gn:country_code":"IT",
    "gn:dem":715,
    "gn:feature_class":"P",
    "gn:feature_code":"PPL",
    "gn:name":"Castel Belfort",
    "gn:population":26,
    "gn:timezone":"Europe/Rome",
    "iso:country":"IT",
    "wof:name":"Castel Belfort",
    "wof:placetype":"locality",
    "wof:population":26
},
  "geometry": {"coordinates":[11.0412,46.20482],"type":"Point"}
}