{
  "type": "Feature",
  "properties": {
    "gn:gn_country":"IT",
    "gn:gn_fcode":"PPL",
    "gn:gn_pop":0,
    "gn:population":127,
    "iso:country":"IT",
    "name:bul_x_preferred":[
        "\u0422\u0435\u0440\u0430\u043d\u0435\u0440\u0430"
    ],
    "name:dut_x_preferred":[
        "Terranera"
    ],
    "name:eng_x_preferred":[
        "Terranera"
    ],
    "name:fre_x_preferred":[
        "Terranera"
    ],
    "name:hun_x_preferred":[
        "Terranera"
    ],
    "name:ita_x_preferred":[
        "Terranera"
    ],
    "name:srp_x_preferred":[
        "Terranera"
    ],
    "qs_pg:aaroncc":"IT",
    "qs_pg:gn_country":"IT",
    "qs_pg:gn_fcode":"PPL",
    "qs_pg:gn_pop":0,
    "qs_pg:name":"Terranera",
    "qs_pg:name_adm0":"Italia",
    "qs_pg:name_adm1":"Abruzzo",
    "qs_pg:photos":58,
    "qs_pg:photos_1k":12,
    "qs_pg:photos_9k":1,
    "qs_pg:photos_9r":2,
    "qs_pg:photos_all":58,
    "qs_pg:photos_sr":2,
    "qs_pg:pop_sr":0,
    "qs_pg:qs_pg_placetype":"locality",
    "qs_pg:qs_pg_placetype_gp":"Town",
    "qs_pg:woe_adm0":23424853,
    "woe:adm0_id":23424853,
    "woe:name_adm0":"Italia",
    "woe:name_adm1":"Abruzzo",
    "woe:placetype":"Town",
    "wof:name":"Terranera",
    "wof:placetype":"locality",
    "wof:population":127
},
  "geometry": {"coordinates":[13.53333,42.23333],"type":"Point"}
}