{
  "type": "Feature",
  "properties": {
    "gn:admin1_code":"12",
    "gn:admin2_code":"VB",
    "gn:admin3_code":"103014.0",
    "gn:asciiname":"Pecciola",
    "gn:country_code":"IT",
    "gn:dem":574,
    "gn:feature_class":"P",
    "gn:feature_code":"PPL",
    "gn:name":"Pecciola",
    "gn:population":27,
    "gn:timezone":"Europe/Rome",
    "iso:country":"IT",
    "wof:name":"Pecciola",
    "wof:placetype":"locality",
    "wof:population":27
},
  "geometry": {"coordinates":[8.21025,46.01741],"type":"Point"}
}