{
  "type": "Feature",
  "properties": {
    "gn:admin1_code":"5",
    "gn:admin2_code":"RE",
    "gn:admin3_code":"35045.0",
    "gn:asciiname":"Secchio Sotto",
    "gn:country_code":"IT",
    "gn:dem":761,
    "gn:feature_class":"P",
    "gn:feature_code":"PPL",
    "gn:name":"Secchio Sotto",
    "gn:population":44,
    "gn:timezone":"Europe/Rome",
    "iso:country":"IT",
    "wof:name":"Secchio Sotto",
    "wof:placetype":"locality",
    "wof:population":44
},
  "geometry": {"coordinates":[10.46988,44.33803],"type":"Point"}
}