{
  "type": "Feature",
  "properties": {
    "gn:admin1_code":"12",
    "gn:admin2_code":"CN",
    "gn:admin3_code":"4167.0",
    "gn:asciiname":"Castello",
    "gn:country_code":"IT",
    "gn:dem":1328,
    "gn:feature_class":"P",
    "gn:feature_code":"PPLL",
    "gn:name":"Castello",
    "gn:population":6,
    "gn:timezone":"Europe/Rome",
    "iso:country":"IT",
    "wof:name":"Castello",
    "wof:placetype":"locality",
    "wof:population":6
},
  "geometry": {"coordinates":[7.03551,44.34689],"type":"Point"}
}