{
  "type": "Feature",
  "properties": {
    "gn:admin1_code":"17",
    "gn:admin2_code":"TN",
    "gn:admin3_code":"22062.0",
    "gn:asciiname":"Localita Produttiva II",
    "gn:country_code":"IT",
    "gn:dem":606,
    "gn:feature_class":"P",
    "gn:feature_code":"PPL",
    "gn:name":"Localit\u00e0 Produttiva II",
    "gn:population":30,
    "gn:timezone":"Europe/Rome",
    "iso:country":"IT",
    "name:und_x_variant":[
        "Localit\u00e0 Produttiva II"
    ],
    "wof:name":"Localita Produttiva II",
    "wof:placetype":"locality",
    "wof:population":30
},
  "geometry": {"coordinates":[11.04434,46.3529],"type":"Point"}
}