{
  "type": "Feature",
  "properties": {
    "gn:admin1_code":"20",
    "gn:admin2_code":"VI",
    "gn:admin3_code":"24105.0",
    "gn:asciiname":"Pra' Novelli",
    "gn:country_code":"IT",
    "gn:dem":107,
    "gn:feature_class":"P",
    "gn:feature_code":"PPL",
    "gn:name":"Pra' Novelli",
    "gn:population":27,
    "gn:timezone":"Europe/Rome",
    "iso:country":"IT",
    "wof:name":"Pra' Novelli",
    "wof:placetype":"locality",
    "wof:population":27
},
  "geometry": {"coordinates":[11.49278,45.68531],"type":"Point"}
}