{
  "type": "Feature",
  "properties": {
    "gn:admin1_code":"9",
    "gn:admin2_code":"MN",
    "gn:admin3_code":"20026.0",
    "gn:asciiname":"Corte Merlesco",
    "gn:country_code":"IT",
    "gn:dem":41,
    "gn:feature_class":"P",
    "gn:feature_code":"PPL",
    "gn:name":"Corte Merlesco",
    "gn:population":16,
    "gn:timezone":"Europe/Rome",
    "iso:country":"IT",
    "wof:name":"Corte Merlesco",
    "wof:placetype":"locality",
    "wof:population":16
},
  "geometry": {"coordinates":[10.70165,45.27589],"type":"Point"}
}