{
  "type": "Feature",
  "properties": {
    "gn:admin1_code":"1.0",
    "gn:admin2_code":"TE",
    "gn:admin3_code":"67036.0",
    "gn:asciiname":"Ciarelli",
    "gn:country_code":"IT",
    "gn:dem":949,
    "gn:elevation":"953.0",
    "gn:feature_class":"P",
    "gn:feature_code":"PPL",
    "gn:name":"Ciarelli",
    "gn:population":39,
    "gn:timezone":"Europe/Rome",
    "iso:country":"IT",
    "wof:name":"Ciarelli",
    "wof:placetype":"locality",
    "wof:population":39
},
  "geometry": {"coordinates":[13.50496,42.69199],"type":"Point"}
}