{
  "type": "Feature",
  "properties": {
    "gn:admin1_code":"20",
    "gn:admin2_code":"PD",
    "gn:admin3_code":"28015.0",
    "gn:asciiname":"Via Ardoneghe III",
    "gn:country_code":"IT",
    "gn:dem":6,
    "gn:feature_class":"P",
    "gn:feature_code":"PPL",
    "gn:name":"Via Ardoneghe III",
    "gn:population":39,
    "gn:timezone":"Europe/Rome",
    "iso:country":"IT",
    "wof:name":"Via Ardoneghe III",
    "wof:placetype":"locality",
    "wof:population":39
},
  "geometry": {"coordinates":[11.98829,45.31928],"type":"Point"}
}