{
  "type": "Feature",
  "properties": {
    "gn:admin1_code":"5",
    "gn:admin2_code":"RN",
    "gn:admin3_code":"99020.0",
    "gn:asciiname":"Bonina",
    "gn:country_code":"IT",
    "gn:dem":174,
    "gn:feature_class":"P",
    "gn:feature_code":"PPL",
    "gn:name":"Bonina",
    "gn:population":23,
    "gn:timezone":"Europe/Rome",
    "iso:country":"IT",
    "wof:name":"Bonina",
    "wof:placetype":"locality",
    "wof:population":23
},
  "geometry": {"coordinates":[12.41415,43.97505],"type":"Point"}
}