{
  "type": "Feature",
  "properties": {
    "gn:admin1_code":"7.0",
    "gn:admin2_code":"RI",
    "gn:admin3_code":"57002.0",
    "gn:asciiname":"Pasciano",
    "gn:country_code":"IT",
    "gn:dem":1081,
    "gn:elevation":"1085.0",
    "gn:feature_class":"P",
    "gn:feature_code":"PPL",
    "gn:name":"Pasciano",
    "gn:population":19,
    "gn:timezone":"Europe/Rome",
    "iso:country":"IT",
    "wof:name":"Pasciano",
    "wof:placetype":"locality",
    "wof:population":19
},
  "geometry": {"coordinates":[13.20845,42.63928],"type":"Point"}
}