{
  "type": "Feature",
  "properties": {
    "gn:admin1_code":"13",
    "gn:admin2_code":"BA",
    "gn:admin3_code":"72011.0",
    "gn:asciiname":"Consped - Italian Leather",
    "gn:country_code":"IT",
    "gn:dem":84,
    "gn:feature_class":"P",
    "gn:feature_code":"PPLL",
    "gn:name":"Consped - Italian Leather",
    "gn:population":6,
    "gn:timezone":"Europe/Rome",
    "iso:country":"IT",
    "wof:name":"Consped - Italian Leather",
    "wof:placetype":"locality",
    "wof:population":6
},
  "geometry": {"coordinates":[16.73483,41.09913],"type":"Point"}
}