{
  "type": "Feature",
  "properties": {
    "gn:admin1_code":"20",
    "gn:admin2_code":"PD",
    "gn:admin3_code":"28015.0",
    "gn:asciiname":"Zona Arzerini I",
    "gn:country_code":"IT",
    "gn:dem":1,
    "gn:feature_class":"P",
    "gn:feature_code":"PPL",
    "gn:name":"Zona Arzerini I",
    "gn:population":34,
    "gn:timezone":"Europe/Rome",
    "iso:country":"IT",
    "wof:name":"Zona Arzerini I",
    "wof:placetype":"locality",
    "wof:population":34
},
  "geometry": {"coordinates":[11.97223,45.28961],"type":"Point"}
}