{
  "type": "Feature",
  "properties": {
    "gn:admin1_code":"9",
    "gn:admin2_code":"MI",
    "gn:admin3_code":"15191.0",
    "gn:asciiname":"Mariotto",
    "gn:country_code":"IT",
    "gn:dem":63,
    "gn:feature_class":"P",
    "gn:feature_code":"PPL",
    "gn:name":"Mariotto",
    "gn:population":32,
    "gn:timezone":"Europe/Rome",
    "iso:country":"IT",
    "wof:name":"Mariotto",
    "wof:placetype":"locality",
    "wof:population":32
},
  "geometry": {"coordinates":[9.52251,45.16612],"type":"Point"}
}