{
  "type": "Feature",
  "properties": {
    "gn:admin1_code":"9",
    "gn:admin2_code":"MN",
    "gn:admin3_code":"20003.0",
    "gn:asciiname":"Campione",
    "gn:country_code":"IT",
    "gn:dem":20,
    "gn:feature_class":"P",
    "gn:feature_code":"PPL",
    "gn:name":"Campione",
    "gn:population":121,
    "gn:timezone":"Europe/Rome",
    "iso:country":"IT",
    "wof:name":"Campione",
    "wof:placetype":"locality",
    "wof:population":121
},
  "geometry": {"coordinates":[10.82244,45.07989],"type":"Point"}
}