{
  "type": "Feature",
  "properties": {
    "gn:admin1_code":"20",
    "gn:admin2_code":"VI",
    "gn:admin3_code":"24088.0",
    "gn:asciiname":"Bodi",
    "gn:country_code":"IT",
    "gn:dem":80,
    "gn:feature_class":"P",
    "gn:feature_code":"PPL",
    "gn:name":"Bodi",
    "gn:population":65,
    "gn:timezone":"Europe/Rome",
    "iso:country":"IT",
    "wof:name":"Bodi",
    "wof:placetype":"locality",
    "wof:population":65
},
  "geometry": {"coordinates":[11.8193,45.72292],"type":"Point"}
}