{
  "type": "Feature",
  "properties": {
    "gn:admin1_code":"5",
    "gn:admin2_code":"RE",
    "gn:admin3_code":"35020.0",
    "gn:asciiname":"Villaggio Industriale",
    "gn:country_code":"IT",
    "gn:dem":28,
    "gn:feature_class":"P",
    "gn:feature_code":"PPL",
    "gn:name":"Villaggio Industriale",
    "gn:population":125,
    "gn:timezone":"Europe/Rome",
    "iso:country":"IT",
    "wof:name":"Villaggio Industriale",
    "wof:placetype":"locality",
    "wof:population":125
},
  "geometry": {"coordinates":[10.82201,44.77],"type":"Point"}
}