{
  "type": "Feature",
  "properties": {
    "gn:admin1_code":"19",
    "gn:admin2_code":"AO",
    "gn:admin3_code":"7031.0",
    "gn:asciiname":"Gerdaz",
    "gn:country_code":"IT",
    "gn:dem":1371,
    "gn:feature_class":"P",
    "gn:feature_code":"PPL",
    "gn:name":"Gerdaz",
    "gn:population":15,
    "gn:timezone":"Europe/Rome",
    "iso:country":"IT",
    "wof:name":"Gerdaz",
    "wof:placetype":"locality",
    "wof:population":15
},
  "geometry": {"coordinates":[7.31184,45.70238],"type":"Point"}
}