{
  "type": "Feature",
  "properties": {
    "gn:admin1_code":"1",
    "gn:admin2_code":"TE",
    "gn:admin3_code":"67019.0",
    "gn:asciiname":"Civita",
    "gn:country_code":"IT",
    "gn:dem":219,
    "gn:feature_class":"P",
    "gn:feature_code":"PPL",
    "gn:name":"Civita",
    "gn:population":41,
    "gn:timezone":"Europe/Rome",
    "iso:country":"IT",
    "wof:name":"Civita",
    "wof:placetype":"locality",
    "wof:population":41
},
  "geometry": {"coordinates":[13.89143,42.86527],"type":"Point"}
}