{
  "type": "Feature",
  "properties": {
    "gn:admin1_code":"13",
    "gn:admin2_code":"BR",
    "gn:admin3_code":"74005.0",
    "gn:asciiname":"Pico-San Donato",
    "gn:country_code":"IT",
    "gn:dem":325,
    "gn:feature_class":"P",
    "gn:feature_code":"PPL",
    "gn:name":"Pico-San Donato",
    "gn:population":54,
    "gn:timezone":"Europe/Rome",
    "iso:country":"IT",
    "wof:name":"Pico-San Donato",
    "wof:placetype":"locality",
    "wof:population":54
},
  "geometry": {"coordinates":[17.44671,40.72662],"type":"Point"}
}