{
  "type": "Feature",
  "properties": {
    "gn:admin1_code":"11",
    "gn:admin2_code":"IS",
    "gn:admin3_code":"94023.0",
    "gn:asciiname":"Acqua Solfa",
    "gn:country_code":"IT",
    "gn:dem":498,
    "gn:feature_class":"P",
    "gn:feature_code":"PPL",
    "gn:name":"Acqua Solfa",
    "gn:population":90,
    "gn:timezone":"Europe/Rome",
    "iso:country":"IT",
    "wof:name":"Acqua Solfa",
    "wof:placetype":"locality",
    "wof:population":90
},
  "geometry": {"coordinates":[14.23302,41.62015],"type":"Point"}
}