{
  "type": "Feature",
  "properties": {
    "gn:admin1_code":"8.0",
    "gn:admin2_code":"SP",
    "gn:admin3_code":"11018.0",
    "gn:asciiname":"Colli",
    "gn:country_code":"IT",
    "gn:dem":693,
    "gn:elevation":"697.0",
    "gn:feature_class":"P",
    "gn:feature_code":"PPL",
    "gn:name":"Colli",
    "gn:population":10,
    "gn:timezone":"Europe/Rome",
    "iso:country":"IT",
    "name:ceb_x_preferred":[
        "Colli"
    ],
    "name:deu_x_preferred":[
        "Colli"
    ],
    "name:ita_x_preferred":[
        "Colli"
    ],
    "name:nld_x_preferred":[
        "Colli"
    ],
    "name:por_x_preferred":[
        "Colli"
    ],
    "name:rus_x_preferred":[
        "\u041a\u043e\u043b\u043b\u0438"
    ],
    "name:swe_x_preferred":[
        "Colli"
    ],
    "wof:name":"Colli",
    "wof:placetype":"locality",
    "wof:population":10
},
  "geometry": {"coordinates":[9.53502,44.32511],"type":"Point"}
}