{
  "type": "Feature",
  "properties": {
    "gn:admin1_code":"12",
    "gn:admin2_code":"CN",
    "gn:admin3_code":"4163.0",
    "gn:asciiname":"Cascina Paschi",
    "gn:country_code":"IT",
    "gn:dem":499,
    "gn:feature_class":"P",
    "gn:feature_code":"PPL",
    "gn:name":"Cascina Paschi",
    "gn:population":57,
    "gn:timezone":"Europe/Rome",
    "iso:country":"IT",
    "wof:name":"Cascina Paschi",
    "wof:placetype":"locality",
    "wof:population":57
},
  "geometry": {"coordinates":[7.63232,44.35661],"type":"Point"}
}