{
  "type": "Feature",
  "properties": {
    "gn:admin1_code":"7",
    "gn:admin2_code":"FR",
    "gn:admin3_code":"60036.0",
    "gn:asciiname":"Alefana",
    "gn:country_code":"IT",
    "gn:dem":370,
    "gn:feature_class":"P",
    "gn:feature_code":"PPL",
    "gn:name":"Alefana",
    "gn:population":45,
    "gn:timezone":"Europe/Rome",
    "iso:country":"IT",
    "wof:name":"Alefana",
    "wof:placetype":"locality",
    "wof:population":45
},
  "geometry": {"coordinates":[13.58065,41.61114],"type":"Point"}
}