{
  "type": "Feature",
  "properties": {
    "gn:admin1_code":"3.0",
    "gn:admin2_code":"VV",
    "gn:admin3_code":"102024.0",
    "gn:asciiname":"Cassari",
    "gn:country_code":"IT",
    "gn:dem":1102,
    "gn:feature_class":"P",
    "gn:feature_code":"PPL",
    "gn:name":"Cassari",
    "gn:population":476,
    "gn:timezone":"Europe/Rome",
    "iso:country":"IT",
    "wof:name":"Cassari",
    "wof:placetype":"locality",
    "wof:population":476
},
  "geometry": {"coordinates":[16.2957,38.44079],"type":"Point"}
}