{
  "type": "Feature",
  "properties": {
    "gn:admin1_code":"5.0",
    "gn:admin2_code":"PR",
    "gn:admin3_code":"34023.0",
    "gn:asciiname":"Convento",
    "gn:country_code":"IT",
    "gn:dem":110,
    "gn:feature_class":"P",
    "gn:feature_code":"PPLL",
    "gn:name":"Convento",
    "gn:population":4,
    "gn:timezone":"Europe/Rome",
    "iso:country":"IT",
    "wof:name":"Convento",
    "wof:placetype":"locality",
    "wof:population":4
},
  "geometry": {"coordinates":[10.41811,44.6988],"type":"Point"}
}