{
  "type": "Feature",
  "properties": {
    "gn:admin1_code":"3.0",
    "gn:admin2_code":"CS",
    "gn:admin3_code":"78091.0",
    "gn:asciiname":"Castagnelle",
    "gn:country_code":"IT",
    "gn:dem":301,
    "gn:feature_class":"P",
    "gn:feature_code":"PPL",
    "gn:name":"Castagnelle",
    "gn:population":30,
    "gn:timezone":"Europe/Rome",
    "iso:country":"IT",
    "wof:name":"Castagnelle",
    "wof:placetype":"locality",
    "wof:population":30
},
  "geometry": {"coordinates":[16.05399,39.34365],"type":"Point"}
}