{
  "type": "Feature",
  "properties": {
    "gn:admin1_code":"9.0",
    "gn:admin2_code":"SO",
    "gn:admin3_code":"14071.0",
    "gn:asciiname":"Producena-Teola",
    "gn:country_code":"IT",
    "gn:dem":1532,
    "gn:elevation":"1540.0",
    "gn:feature_class":"P",
    "gn:feature_code":"PPL",
    "gn:name":"Producena-Teola",
    "gn:population":158,
    "gn:timezone":"Europe/Rome",
    "iso:country":"IT",
    "wof:name":"Producena-Teola",
    "wof:placetype":"locality",
    "wof:population":158
},
  "geometry": {"coordinates":[10.26297,46.48297],"type":"Point"}
}