{
  "type": "Feature",
  "properties": {
    "gn:admin1_code":"1",
    "gn:admin2_code":"TE",
    "gn:admin3_code":"67004.0",
    "gn:asciiname":"Colle Petitto",
    "gn:country_code":"IT",
    "gn:dem":390,
    "gn:feature_class":"P",
    "gn:feature_code":"PPL",
    "gn:name":"Colle Petitto",
    "gn:population":94,
    "gn:timezone":"Europe/Rome",
    "iso:country":"IT",
    "wof:name":"Colle Petitto",
    "wof:placetype":"locality",
    "wof:population":94
},
  "geometry": {"coordinates":[13.99437,42.5601],"type":"Point"}
}