{
  "type": "Feature",
  "properties": {
    "gn:admin1_code":"5.0",
    "gn:admin2_code":"RE",
    "gn:admin3_code":"35036.0",
    "gn:asciiname":"Fontana",
    "gn:country_code":"IT",
    "gn:dem":45,
    "gn:feature_class":"P",
    "gn:feature_code":"PPL",
    "gn:name":"Fontana",
    "gn:population":542,
    "gn:timezone":"Europe/Rome",
    "iso:country":"IT",
    "wof:name":"Fontana",
    "wof:placetype":"locality",
    "wof:population":542
},
  "geometry": {"coordinates":[10.80238,44.67764],"type":"Point"}
}