{
  "type": "Feature",
  "properties": {
    "gn:gn_country":"IT",
    "gn:gn_fcode":"PPLA3",
    "gn:gn_pop":1520,
    "gn:population":1520,
    "iso:country":"IT",
    "name:arm_x_preferred":[
        "\u0532\u0561\u0580\u0562\u056b\u0561\u0576\u0578"
    ],
    "name:baq_x_preferred":[
        "Barbiano"
    ],
    "name:bar_x_preferred":[
        "Barmen"
    ],
    "name:bel_x_preferred":[
        "\u0411\u0430\u0440\u0431'\u044f\u043d\u0430"
    ],
    "name:bul_x_preferred":[
        "\u0411\u0430\u0440\u0431\u0438\u0430\u043d\u043e"
    ],
    "name:cat_x_preferred":[
        "Barbian"
    ],
    "name:chi_x_preferred":[
        "\u5df4\u5c14\u6bd4\u4e9a\u8bfa"
    ],
    "name:dut_x_preferred":[
        "Barbian"
    ],
    "name:eng_x_preferred":[
        "Barbian"
    ],
    "name:epo_x_preferred":[
        "Barbian"
    ],
    "name:est_x_preferred":[
        "Barbiani vald"
    ],
    "name:fre_x_preferred":[
        "Barbiano"
    ],
    "name:ger_x_preferred":[
        "Barbian"
    ],
    "name:gre_x_preferred":[
        "\u039c\u03c0\u03b1\u03c1\u03bc\u03c0\u03b9\u03ac\u03bd\u03bf"
    ],
    "name:hun_x_preferred":[
        "Barbiano"
    ],
    "name:ina_x_preferred":[
        "Barbiano"
    ],
    "name:ita_x_preferred":[
        "Barbiano"
    ],
    "name:jpn_x_preferred":[
        "\u30d0\u30eb\u30d3\u30a2\u30fc\u30ce"
    ],
    "name:kaz_x_preferred":[
        "\u0411\u0430\u0440\u0431\u044c\u044f\u043d\u043e"
    ],
    "name:lat_x_preferred":[
        "Barbianum"
    ],
    "name:lmo_x_preferred":[
        "Barbiano"
    ],
    "name:may_x_preferred":[
        "Barbian"
    ],
    "name:nap_x_preferred":[
        "Barbiano"
    ],
    "name:nob_x_preferred":[
        "Barbian"
    ],
    "name:per_x_preferred":[
        "\u0628\u0627\u0631\u0628\u06cc\u0627\u0646\u0648"
    ],
    "name:pms_x_preferred":[
        "Barbian"
    ],
    "name:pol_x_preferred":[
        "Barbian"
    ],
    "name:por_x_preferred":[
        "Barbiano"
    ],
    "name:rum_x_preferred":[
        "Barbiano"
    ],
    "name:rus_x_preferred":[
        "\u0411\u0430\u0440\u0431\u044c\u044f\u043d\u043e"
    ],
    "name:scn_x_preferred":[
        "Barbiano"
    ],
    "name:spa_x_preferred":[
        "Barbiano"
    ],
    "name:srp_x_preferred":[
        "\u0411\u0430\u0440\u0431\u0438\u0458\u0430\u043d\u043e"
    ],
    "name:tgl_x_preferred":[
        "Barbian"
    ],
    "name:ukr_x_preferred":[
        "\u0411\u0430\u0440\u0431'\u044f\u043d\u043e"
    ],
    "name:vol_x_preferred":[
        "Barbiano"
    ],
    "name:war_x_preferred":[
        "Barbian"
    ],
    "qs_pg:aaroncc":"IT",
    "qs_pg:gn_country":"IT",
    "qs_pg:gn_fcode":"PPLA3",
    "qs_pg:gn_pop":1520,
    "qs_pg:name":"Barbiano - Barbian",
    "qs_pg:photos_9r":0,
    "qs_pg:photos_sr":0,
    "qs_pg:pop_sr":3,
    "qs_pg:qs_pg_placetype":"locality",
    "wof:name":"Barbiano - Barbian",
    "wof:placetype":"locality",
    "wof:population":1520
},
  "geometry": {"coordinates":[11.52138,46.60332],"type":"Point"}
}