{
  "type": "Feature",
  "properties": {
    "gn:admin1_code":"1.0",
    "gn:admin2_code":"CH",
    "gn:admin3_code":"69059.0",
    "gn:asciiname":"Padicagne di Colle Martino",
    "gn:country_code":"IT",
    "gn:dem":28,
    "gn:feature_class":"P",
    "gn:feature_code":"PPL",
    "gn:name":"Padicagne di Colle Martino",
    "gn:population":0,
    "gn:timezone":"Europe/Rome",
    "iso:country":"IT",
    "wof:name":"Padicagne di Colle Martino",
    "wof:placetype":"locality"
},
  "geometry": {"coordinates":[14.50632,42.19151],"type":"Point"}
}