{
  "type": "Feature",
  "properties": {
    "gn:admin1_code":"20",
    "gn:admin2_code":"PD",
    "gn:admin3_code":"28010.0",
    "gn:asciiname":"Arzerini",
    "gn:country_code":"IT",
    "gn:dem":5,
    "gn:feature_class":"P",
    "gn:feature_code":"PPL",
    "gn:name":"Arzerini",
    "gn:population":21,
    "gn:timezone":"Europe/Rome",
    "iso:country":"IT",
    "wof:name":"Arzerini",
    "wof:placetype":"locality",
    "wof:population":21
},
  "geometry": {"coordinates":[11.69124,45.10913],"type":"Point"}
}