{
  "type": "Feature",
  "properties": {
    "gn:admin1_code":"7",
    "gn:admin2_code":"RM",
    "gn:admin3_code":"58069.0",
    "gn:asciiname":"Collecarafa-Filaccianese",
    "gn:country_code":"IT",
    "gn:dem":222,
    "gn:feature_class":"P",
    "gn:feature_code":"PPL",
    "gn:name":"Collecarafa-Filaccianese",
    "gn:population":161,
    "gn:timezone":"Europe/Rome",
    "iso:country":"IT",
    "wof:name":"Collecarafa-Filaccianese",
    "wof:placetype":"locality",
    "wof:population":161
},
  "geometry": {"coordinates":[12.59595,42.23476],"type":"Point"}
}