{
  "type": "Feature",
  "properties": {
    "gn:admin1_code":"20",
    "gn:admin2_code":"TV",
    "gn:admin3_code":"26093.0",
    "gn:asciiname":"Belvedere",
    "gn:country_code":"IT",
    "gn:dem":66,
    "gn:feature_class":"P",
    "gn:feature_code":"PPL",
    "gn:name":"Belvedere",
    "gn:population":39,
    "gn:timezone":"Europe/Rome",
    "iso:country":"IT",
    "wof:name":"Belvedere",
    "wof:placetype":"locality",
    "wof:population":39
},
  "geometry": {"coordinates":[12.14704,45.75063],"type":"Point"}
}