{
  "type": "Feature",
  "properties": {
    "gn:admin1_code":"3",
    "gn:admin2_code":"RC",
    "gn:admin3_code":"80041.0",
    "gn:asciiname":"Lucia",
    "gn:country_code":"IT",
    "gn:dem":403,
    "gn:feature_class":"P",
    "gn:feature_code":"PPL",
    "gn:name":"Lucia",
    "gn:population":167,
    "gn:timezone":"Europe/Rome",
    "iso:country":"IT",
    "name:ceb_x_preferred":[
        "Lucia"
    ],
    "name:dan_x_preferred":[
        "Lucia"
    ],
    "name:deu_x_preferred":[
        "Luc\u00eda"
    ],
    "name:fra_x_preferred":[
        "Lucia"
    ],
    "name:ita_x_preferred":[
        "Lucia"
    ],
    "name:jpn_x_preferred":[
        "\u30eb\u30c1\u30a2"
    ],
    "name:lat_x_preferred":[
        "Lucia"
    ],
    "name:nld_x_preferred":[
        "Lucia"
    ],
    "name:ron_x_preferred":[
        "Lucia"
    ],
    "name:slk_x_preferred":[
        "Lucia"
    ],
    "name:spa_x_preferred":[
        "Lucia"
    ],
    "name:swe_x_preferred":[
        "Lucia"
    ],
    "wof:name":"Lucia",
    "wof:placetype":"locality",
    "wof:population":167
},
  "geometry": {"coordinates":[15.75786,38.20564],"type":"Point"}
}