{
  "type": "Feature",
  "properties": {
    "gn:admin1_code":"3",
    "gn:admin2_code":"RC",
    "gn:admin3_code":"80041.0",
    "gn:asciiname":"Lucia",
    "gn:country_code":"IT",
    "gn:dem":403,
    "gn:feature_class":"P",
    "gn:feature_code":"PPL",
    "gn:name":"Lucia",
    "gn:population":167,
    "gn:timezone":"Europe/Rome",
    "iso:country":"IT",
    "wof:name":"Lucia",
    "wof:placetype":"locality",
    "wof:population":167
},
  "geometry": {"coordinates":[15.75786,38.20564],"type":"Point"}
}