{
  "type": "Feature",
  "properties": {
    "gn:admin1_code":"20",
    "gn:admin2_code":"VR",
    "gn:admin3_code":"23076.0",
    "gn:asciiname":"Quar",
    "gn:country_code":"IT",
    "gn:dem":89,
    "gn:feature_class":"P",
    "gn:feature_code":"PPL",
    "gn:name":"Quar",
    "gn:population":73,
    "gn:timezone":"Europe/Rome",
    "iso:country":"IT",
    "wof:name":"Quar",
    "wof:placetype":"locality",
    "wof:population":73
},
  "geometry": {"coordinates":[10.924,45.49165],"type":"Point"}
}