{
  "type": "Feature",
  "properties": {
    "gn:admin1_code":"20",
    "gn:admin2_code":"PD",
    "gn:admin3_code":"28080.0",
    "gn:asciiname":"Ballan",
    "gn:country_code":"IT",
    "gn:dem":21,
    "gn:feature_class":"P",
    "gn:feature_code":"PPL",
    "gn:name":"Ballan",
    "gn:population":89,
    "gn:timezone":"Europe/Rome",
    "iso:country":"IT",
    "name:ceb_x_preferred":[
        "Ballan"
    ],
    "name:deu_x_preferred":[
        "Ballan"
    ],
    "name:fra_x_preferred":[
        "Ballan"
    ],
    "name:ita_x_preferred":[
        "Ballan"
    ],
    "name:nld_x_preferred":[
        "Ballan"
    ],
    "name:rus_x_preferred":[
        "\u0411\u0430\u043b\u043b\u0430\u043d"
    ],
    "name:spa_x_preferred":[
        "Ballan"
    ],
    "wof:name":"Ballan",
    "wof:placetype":"locality",
    "wof:population":89
},
  "geometry": {"coordinates":[11.91551,45.56031],"type":"Point"}
}