{
  "type": "Feature",
  "properties": {
    "gn:admin1_code":"20",
    "gn:admin2_code":"VE",
    "gn:admin3_code":"27019.0",
    "gn:asciiname":"Ca' Cappellari",
    "gn:country_code":"IT",
    "gn:dem":-2,
    "gn:feature_class":"P",
    "gn:feature_code":"PPL",
    "gn:name":"Ca' Cappellari",
    "gn:population":52,
    "gn:timezone":"Europe/Rome",
    "iso:country":"IT",
    "wof:name":"Ca' Cappellari",
    "wof:placetype":"locality",
    "wof:population":52
},
  "geometry": {"coordinates":[12.68469,45.54285],"type":"Point"}
}