{
  "type": "Feature",
  "properties": {
    "gn:admin1_code":"20",
    "gn:admin2_code":"VI",
    "gn:admin3_code":"24062.0",
    "gn:asciiname":"Zona Artigianale Astichello",
    "gn:country_code":"IT",
    "gn:dem":74,
    "gn:feature_class":"P",
    "gn:feature_code":"PPL",
    "gn:name":"Zona Artigianale Astichello",
    "gn:population":80,
    "gn:timezone":"Europe/Rome",
    "iso:country":"IT",
    "wof:name":"Zona Artigianale Astichello",
    "wof:placetype":"locality",
    "wof:population":80
},
  "geometry": {"coordinates":[11.56529,45.65514],"type":"Point"}
}