{
  "type": "Feature",
  "properties": {
    "gn:admin1_code":"17",
    "gn:admin2_code":"BZ",
    "gn:admin3_code":"21038.0",
    "gn:asciiname":"Plars di Sopra",
    "gn:country_code":"IT",
    "gn:dem":518,
    "gn:feature_class":"P",
    "gn:feature_code":"PPL",
    "gn:name":"Plars di Sopra",
    "gn:population":110,
    "gn:timezone":"Europe/Rome",
    "iso:country":"IT",
    "wof:name":"Plars di Sopra",
    "wof:placetype":"locality",
    "wof:population":110
},
  "geometry": {"coordinates":[11.10183,46.6861],"type":"Point"}
}