{
  "type": "Feature",
  "properties": {
    "gn:admin1_code":"9.0",
    "gn:admin2_code":"MN",
    "gn:admin3_code":"20056.0",
    "gn:asciiname":"Casate Stoffi",
    "gn:country_code":"IT",
    "gn:dem":18,
    "gn:feature_class":"P",
    "gn:feature_code":"PPL",
    "gn:name":"Casate Stoffi",
    "gn:population":0,
    "gn:timezone":"Europe/Rome",
    "iso:country":"IT",
    "wof:name":"Casate Stoffi",
    "wof:placetype":"locality"
},
  "geometry": {"coordinates":[10.97105,44.94612],"type":"Point"}
}