{
  "type": "Feature",
  "properties": {
    "gn:admin1_code":"3",
    "gn:admin2_code":"VV",
    "gn:admin3_code":"102016.0",
    "gn:asciiname":"San Sebastiano",
    "gn:country_code":"IT",
    "gn:dem":671,
    "gn:feature_class":"P",
    "gn:feature_code":"PPL",
    "gn:name":"San Sebastiano",
    "gn:population":122,
    "gn:timezone":"Europe/Rome",
    "iso:country":"IT",
    "wof:name":"San Sebastiano",
    "wof:placetype":"locality",
    "wof:population":122
},
  "geometry": {"coordinates":[16.24345,38.56695],"type":"Point"}
}