{
  "type": "Feature",
  "properties": {
    "gn:admin1_code":"1",
    "gn:admin2_code":"PE",
    "gn:admin3_code":"68041.0",
    "gn:asciiname":"Case Valle Carbone",
    "gn:country_code":"IT",
    "gn:dem":118,
    "gn:feature_class":"P",
    "gn:feature_code":"PPL",
    "gn:name":"Case Valle Carbone",
    "gn:population":23,
    "gn:timezone":"Europe/Rome",
    "iso:country":"IT",
    "wof:name":"Case Valle Carbone",
    "wof:placetype":"locality",
    "wof:population":23
},
  "geometry": {"coordinates":[14.15724,42.46214000000001],"type":"Point"}
}