{
  "type": "Feature",
  "properties": {
    "gn:admin1_code":"12",
    "gn:admin2_code":"CN",
    "gn:admin3_code":"4225.0",
    "gn:asciiname":"Santa Cristina",
    "gn:country_code":"IT",
    "gn:dem":450,
    "gn:feature_class":"P",
    "gn:feature_code":"PPL",
    "gn:name":"Santa Cristina",
    "gn:population":36,
    "gn:timezone":"Europe/Rome",
    "iso:country":"IT",
    "wof:name":"Santa Cristina",
    "wof:placetype":"locality",
    "wof:population":36
},
  "geometry": {"coordinates":[7.53777,44.51802],"type":"Point"}
}