{
  "type": "Feature",
  "properties": {
    "gn:admin1_code":"18",
    "gn:admin2_code":"PG",
    "gn:admin3_code":"54052.0",
    "gn:asciiname":"Colvalenza Palombara",
    "gn:country_code":"IT",
    "gn:dem":307,
    "gn:feature_class":"P",
    "gn:feature_code":"PPL",
    "gn:name":"Colvalenza Palombara",
    "gn:population":110,
    "gn:timezone":"Europe/Rome",
    "iso:country":"IT",
    "wof:name":"Colvalenza Palombara",
    "wof:placetype":"locality",
    "wof:population":110
},
  "geometry": {"coordinates":[12.45927,42.74975],"type":"Point"}
}