{
  "type": "Feature",
  "properties": {
    "gn:admin1_code":"12",
    "gn:admin2_code":"NO",
    "gn:admin3_code":"3108.0",
    "gn:asciiname":"Cascine Bellaria",
    "gn:country_code":"IT",
    "gn:dem":192,
    "gn:feature_class":"P",
    "gn:feature_code":"PPL",
    "gn:name":"Cascine Bellaria",
    "gn:population":40,
    "gn:timezone":"Europe/Rome",
    "iso:country":"IT",
    "wof:name":"Cascine Bellaria",
    "wof:placetype":"locality",
    "wof:population":40
},
  "geometry": {"coordinates":[8.66893,45.59672],"type":"Point"}
}