{
  "type": "Feature",
  "properties": {
    "gn:admin1_code":"5.0",
    "gn:admin2_code":"RA",
    "gn:admin3_code":"39007.0",
    "gn:asciiname":"Borgo Pipa",
    "gn:country_code":"IT",
    "gn:dem":13,
    "gn:feature_class":"P",
    "gn:feature_code":"PPL",
    "gn:name":"Borgo Pipa",
    "gn:population":69,
    "gn:timezone":"Europe/Rome",
    "iso:country":"IT",
    "wof:name":"Borgo Pipa",
    "wof:placetype":"locality",
    "wof:population":69
},
  "geometry": {"coordinates":[12.24172,44.22682],"type":"Point"}
}