{
  "type": "Feature",
  "properties": {
    "gn:admin1_code":"4",
    "gn:admin2_code":"AV",
    "gn:admin3_code":"64105.0",
    "gn:asciiname":"Embriciera",
    "gn:country_code":"IT",
    "gn:dem":509,
    "gn:feature_class":"P",
    "gn:feature_code":"PPL",
    "gn:name":"Embriciera",
    "gn:population":95,
    "gn:timezone":"Europe/Rome",
    "iso:country":"IT",
    "wof:name":"Embriciera",
    "wof:placetype":"locality",
    "wof:population":95
},
  "geometry": {"coordinates":[14.76706,40.95652000000001],"type":"Point"}
}