{
  "type": "Feature",
  "properties": {
    "gn:admin1_code":"7.0",
    "gn:admin2_code":"RI",
    "gn:admin3_code":"57016.0",
    "gn:asciiname":"Micciani",
    "gn:country_code":"IT",
    "gn:dem":434,
    "gn:elevation":"450.0",
    "gn:feature_class":"P",
    "gn:feature_code":"PPL",
    "gn:name":"Micciani",
    "gn:population":27,
    "gn:timezone":"Europe/Rome",
    "iso:country":"IT",
    "wof:name":"Micciani",
    "wof:placetype":"locality",
    "wof:population":27
},
  "geometry": {"coordinates":[12.99802,42.36072],"type":"Point"}
}