{
  "type": "Feature",
  "properties": {
    "gn:admin1_code":"9",
    "gn:admin2_code":"BG",
    "gn:admin3_code":"16144.0",
    "gn:asciiname":"Salmezza",
    "gn:country_code":"IT",
    "gn:dem":1024,
    "gn:feature_class":"P",
    "gn:feature_code":"PPLL",
    "gn:name":"Salmezza",
    "gn:population":8,
    "gn:timezone":"Europe/Rome",
    "iso:country":"IT",
    "wof:name":"Salmezza",
    "wof:placetype":"locality",
    "wof:population":8
},
  "geometry": {"coordinates":[9.732,45.7821],"type":"Point"}
}