{
  "type": "Feature",
  "properties": {
    "gn:admin1_code":"4",
    "gn:admin2_code":"AV",
    "gn:admin3_code":"64057.0",
    "gn:asciiname":"Localita Sotto Monticchio",
    "gn:country_code":"IT",
    "gn:dem":496,
    "gn:feature_class":"P",
    "gn:feature_code":"PPL",
    "gn:name":"Localit\u00e0 Sotto Monticchio",
    "gn:population":31,
    "gn:timezone":"Europe/Rome",
    "iso:country":"IT",
    "name:und_x_variant":[
        "Localit\u00e0 Sotto Monticchio"
    ],
    "wof:name":"Localita Sotto Monticchio",
    "wof:placetype":"locality",
    "wof:population":31
},
  "geometry": {"coordinates":[15.03773,40.85767],"type":"Point"}
}