{
  "type": "Feature",
  "properties": {
    "gn:admin1_code":"12",
    "gn:admin2_code":"CN",
    "gn:admin3_code":"4063.0",
    "gn:asciiname":"Pedaggera",
    "gn:country_code":"IT",
    "gn:dem":721,
    "gn:feature_class":"P",
    "gn:feature_code":"PPL",
    "gn:name":"Pedaggera",
    "gn:population":109,
    "gn:timezone":"Europe/Rome",
    "iso:country":"IT",
    "wof:name":"Pedaggera",
    "wof:placetype":"locality",
    "wof:population":109
},
  "geometry": {"coordinates":[8.07057,44.57666],"type":"Point"}
}