{
  "type": "Feature",
  "properties": {
    "gn:admin1_code":"1.0",
    "gn:admin2_code":"AQ",
    "gn:admin3_code":"66095.0",
    "gn:asciiname":"Civitatomassa",
    "gn:country_code":"IT",
    "gn:dem":732,
    "gn:elevation":"739.0",
    "gn:feature_class":"P",
    "gn:feature_code":"PPL",
    "gn:name":"Civitatomassa",
    "gn:population":398,
    "gn:timezone":"Europe/Rome",
    "iso:country":"IT",
    "wof:name":"Civitatomassa",
    "wof:placetype":"locality",
    "wof:population":398
},
  "geometry": {"coordinates":[13.27865,42.35429],"type":"Point"}
}