{
  "type": "Feature",
  "properties": {
    "gn:admin1_code":"20.0",
    "gn:admin2_code":"PD",
    "gn:admin3_code":"28074.0",
    "gn:asciiname":"Comuna",
    "gn:country_code":"IT",
    "gn:dem":9,
    "gn:feature_class":"P",
    "gn:feature_code":"PPL",
    "gn:name":"Comuna",
    "gn:population":11,
    "gn:timezone":"Europe/Rome",
    "iso:country":"IT",
    "wof:name":"Comuna",
    "wof:placetype":"locality",
    "wof:population":11
},
  "geometry": {"coordinates":[11.56037,45.25353],"type":"Point"}
}