{
  "type": "Feature",
  "properties": {
    "gn:admin1_code":"12",
    "gn:admin2_code":"CN",
    "gn:admin3_code":"4183.0",
    "gn:asciiname":"Tetto San Bernardo",
    "gn:country_code":"IT",
    "gn:dem":763,
    "gn:feature_class":"P",
    "gn:feature_code":"PPLL",
    "gn:name":"Tetto San Bernardo",
    "gn:population":5,
    "gn:timezone":"Europe/Rome",
    "iso:country":"IT",
    "wof:name":"Tetto San Bernardo",
    "wof:placetype":"locality",
    "wof:population":5
},
  "geometry": {"coordinates":[7.44388,44.27796],"type":"Point"}
}