{
  "type": "Feature",
  "properties": {
    "gn:gn_country":"IT",
    "gn:gn_fcode":"PPLA3",
    "gn:gn_pop":4342,
    "gn:population":810,
    "iso:country":"IT",
    "name:bul_x_preferred":[
        "\u0414\u0437\u0438\u043c\u0435\u043b\u0430"
    ],
    "name:cat_x_preferred":[
        "Zimella"
    ],
    "name:deu_x_preferred":[
        "Zimella"
    ],
    "name:eng_x_preferred":[
        "Zimella"
    ],
    "name:epo_x_preferred":[
        "Zimella"
    ],
    "name:eus_x_preferred":[
        "Zimella"
    ],
    "name:fas_x_preferred":[
        "\u0632\u06cc\u0645\u0644\u0627"
    ],
    "name:fra_x_preferred":[
        "Zimella"
    ],
    "name:hun_x_preferred":[
        "Zimella"
    ],
    "name:hye_x_preferred":[
        "\u0541\u056b\u0574\u0565\u056c\u0561"
    ],
    "name:ita_x_preferred":[
        "Zimella"
    ],
    "name:jpn_x_preferred":[
        "\u30b8\u30e1\u30c3\u30e9"
    ],
    "name:kaz_x_preferred":[
        "\u0426\u0438\u043c\u0435\u043b\u043b\u0430"
    ],
    "name:lat_x_preferred":[
        "Geminula"
    ],
    "name:lmo_x_preferred":[
        "Zimella"
    ],
    "name:msa_x_preferred":[
        "Zimella"
    ],
    "name:nan_x_preferred":[
        "Zimella"
    ],
    "name:nap_x_preferred":[
        "Zimella"
    ],
    "name:nld_x_preferred":[
        "Zimella"
    ],
    "name:oci_x_preferred":[
        "Zimella"
    ],
    "name:pms_x_preferred":[
        "Zimella"
    ],
    "name:pol_x_preferred":[
        "Zimella"
    ],
    "name:por_x_preferred":[
        "Zimella"
    ],
    "name:ron_x_preferred":[
        "Zimella"
    ],
    "name:rus_x_preferred":[
        "\u0426\u0438\u043c\u0435\u043b\u043b\u0430"
    ],
    "name:scn_x_preferred":[
        "Zimella"
    ],
    "name:spa_x_preferred":[
        "Zimella"
    ],
    "name:srp_x_preferred":[
        "Zimella"
    ],
    "name:tgl_x_preferred":[
        "Zimella"
    ],
    "name:ukr_x_preferred":[
        "\u0426\u0438\u043c\u0435\u043b\u043b\u0430"
    ],
    "name:uzb_x_preferred":[
        "Zimella"
    ],
    "name:vec_x_preferred":[
        "Zimela"
    ],
    "name:vie_x_preferred":[
        "Zimella"
    ],
    "name:vol_x_preferred":[
        "Zimella"
    ],
    "name:war_x_preferred":[
        "Zimella"
    ],
    "name:zho_x_preferred":[
        "\u9f50\u6885\u62c9"
    ],
    "qs_pg:aaroncc":"IT",
    "qs_pg:gn_country":"IT",
    "qs_pg:gn_fcode":"PPLA3",
    "qs_pg:gn_pop":4342,
    "qs_pg:name":"Zimella",
    "qs_pg:name_adm0":"Italia",
    "qs_pg:name_adm1":"Veneto",
    "qs_pg:photos_9r":0,
    "qs_pg:photos_sr":0,
    "qs_pg:pop_sr":4,
    "qs_pg:qs_pg_placetype":"locality",
    "qs_pg:qs_pg_placetype_gp":"Town",
    "qs_pg:woe_adm0":23424853,
    "woe:adm0_id":23424853,
    "woe:name_adm0":"Italia",
    "woe:name_adm1":"Veneto",
    "woe:placetype":"Town",
    "wof:name":"Zimella",
    "wof:placetype":"locality",
    "wof:population":810
},
  "geometry": {"coordinates":[11.3753,45.33219],"type":"Point"}
}