{
  "type": "Feature",
  "properties": {
    "gn:admin1_code":"1",
    "gn:admin2_code":"AQ",
    "gn:admin3_code":"66095.0",
    "gn:asciiname":"Occhibelli",
    "gn:country_code":"IT",
    "gn:dem":749,
    "gn:feature_class":"P",
    "gn:feature_code":"PPL",
    "gn:name":"Occhibelli",
    "gn:population":20,
    "gn:timezone":"Europe/Rome",
    "iso:country":"IT",
    "wof:name":"Occhibelli",
    "wof:placetype":"locality",
    "wof:population":20
},
  "geometry": {"coordinates":[13.24968,42.34587],"type":"Point"}
}