{
  "type": "Feature",
  "properties": {
    "gn:admin1_code":"10",
    "gn:admin2_code":"PU",
    "gn:admin3_code":"41044.0",
    "gn:asciiname":"Trebbio della Sconfitta",
    "gn:country_code":"IT",
    "gn:dem":138,
    "gn:feature_class":"P",
    "gn:feature_code":"PPL",
    "gn:name":"Trebbio della Sconfitta",
    "gn:population":65,
    "gn:timezone":"Europe/Rome",
    "iso:country":"IT",
    "wof:name":"Trebbio della Sconfitta",
    "wof:placetype":"locality",
    "wof:population":65
},
  "geometry": {"coordinates":[12.87659,43.85707],"type":"Point"}
}