{
  "type": "Feature",
  "properties": {
    "gn:admin1_code":"5.0",
    "gn:admin2_code":"RN",
    "gn:admin3_code":"99017.0",
    "gn:asciiname":"Cinque Quattrini",
    "gn:country_code":"IT",
    "gn:dem":58,
    "gn:feature_class":"P",
    "gn:feature_code":"PPL",
    "gn:name":"Cinque Quattrini",
    "gn:population":24,
    "gn:timezone":"Europe/Rome",
    "iso:country":"IT",
    "wof:name":"Cinque Quattrini",
    "wof:placetype":"locality",
    "wof:population":24
},
  "geometry": {"coordinates":[12.67591,43.91999000000001],"type":"Point"}
}