{
  "type": "Feature",
  "properties": {
    "gn:admin1_code":"9",
    "gn:admin2_code":"MN",
    "gn:admin3_code":"20061.0",
    "gn:asciiname":"Sabbioni",
    "gn:country_code":"IT",
    "gn:dem":9,
    "gn:feature_class":"P",
    "gn:feature_code":"PPL",
    "gn:name":"Sabbioni",
    "gn:population":29,
    "gn:timezone":"Europe/Rome",
    "iso:country":"IT",
    "wof:name":"Sabbioni",
    "wof:placetype":"locality",
    "wof:population":29
},
  "geometry": {"coordinates":[11.34229,44.98462],"type":"Point"}
}