{
  "type": "Feature",
  "properties": {
    "gn:admin1_code":"1.0",
    "gn:admin2_code":"TE",
    "gn:admin3_code":"67026.0",
    "gn:asciiname":"Fano a Corno",
    "gn:country_code":"IT",
    "gn:dem":646,
    "gn:elevation":"652.0",
    "gn:feature_class":"P",
    "gn:feature_code":"PPL",
    "gn:name":"Fano a Corno",
    "gn:population":377,
    "gn:timezone":"Europe/Rome",
    "iso:country":"IT",
    "wof:name":"Fano a Corno",
    "wof:placetype":"locality",
    "wof:population":377
},
  "geometry": {"coordinates":[13.61695,42.48993],"type":"Point"}
}