{
  "type": "Feature",
  "properties": {
    "gn:admin1_code":"9.0",
    "gn:admin2_code":"VA",
    "gn:admin3_code":"12065.0",
    "gn:asciiname":"Vignone II",
    "gn:country_code":"IT",
    "gn:dem":557,
    "gn:feature_class":"P",
    "gn:feature_code":"PPL",
    "gn:name":"Vignone II",
    "gn:population":15,
    "gn:timezone":"Europe/Rome",
    "iso:country":"IT",
    "wof:name":"Vignone II",
    "wof:placetype":"locality",
    "wof:population":15
},
  "geometry": {"coordinates":[8.77874,46.02704],"type":"Point"}
}