{
  "type": "Feature",
  "properties": {
    "gn:admin1_code":"20",
    "gn:admin2_code":"VI",
    "gn:admin3_code":"24079.0",
    "gn:asciiname":"Contellena-Lovato",
    "gn:country_code":"IT",
    "gn:dem":16,
    "gn:feature_class":"P",
    "gn:feature_code":"PPL",
    "gn:name":"Contellena-Lovato",
    "gn:population":59,
    "gn:timezone":"Europe/Rome",
    "iso:country":"IT",
    "wof:name":"Contellena-Lovato",
    "wof:placetype":"locality",
    "wof:population":59
},
  "geometry": {"coordinates":[11.50546,45.31979000000001],"type":"Point"}
}