{
  "type": "Feature",
  "properties": {
    "gn:admin1_code":"7",
    "gn:admin2_code":"LT",
    "gn:admin3_code":"59026.0",
    "gn:asciiname":"Manuli",
    "gn:country_code":"IT",
    "gn:dem":8,
    "gn:feature_class":"P",
    "gn:feature_code":"PPL",
    "gn:name":"Manuli",
    "gn:population":85,
    "gn:timezone":"Europe/Rome",
    "iso:country":"IT",
    "wof:name":"Manuli",
    "wof:placetype":"locality",
    "wof:population":85
},
  "geometry": {"coordinates":[13.79045,41.25189],"type":"Point"}
}