{
  "type": "Feature",
  "properties": {
    "gn:admin1_code":"9.0",
    "gn:admin2_code":"MI",
    "gn:admin3_code":"15192.0",
    "gn:asciiname":"San Donato Milanese",
    "gn:country_code":"IT",
    "gn:dem":107,
    "gn:elevation":"102.0",
    "gn:feature_class":"P",
    "gn:feature_code":"PPLA3",
    "gn:name":"San Donato Milanese",
    "gn:population":28351,
    "gn:timezone":"Europe/Rome",
    "iso:country":"IT",
    "name:eng_x_preferred":[
        "San Donato Milanese"
    ],
    "name:epo_x_preferred":[
        "San Donato Milanese"
    ],
    "name:fra_x_preferred":[
        "San Donato Milanese"
    ],
    "name:ita_x_preferred":[
        "San Donato Milanese"
    ],
    "name:jpn_x_preferred":[
        "\u30b5\u30f3\u30fb\u30c9\u30ca\u30fc\u30c8\u30fb\u30df\u30e9\u30cd\u30fc\u30bc"
    ],
    "name:nap_x_preferred":[
        "San Donato Milanese"
    ],
    "name:nld_x_preferred":[
        "San Donato Milanese"
    ],
    "name:pol_x_preferred":[
        "San Donato Milanese"
    ],
    "name:por_x_preferred":[
        "San Donato Milanese"
    ],
    "name:spa_x_preferred":[
        "San Donato Milanese"
    ],
    "wof:name":"San Donato Milanese",
    "wof:placetype":"locality",
    "wof:population":28351
},
  "geometry": {"coordinates":[9.26838,45.41047],"type":"Point"}
}