{
  "type": "Feature",
  "properties": {
    "gn:admin1_code":"6.0",
    "gn:admin2_code":"UD",
    "gn:admin3_code":"30032.0",
    "gn:asciiname":"Vidulis",
    "gn:country_code":"IT",
    "gn:dem":120,
    "gn:feature_class":"P",
    "gn:feature_code":"PPL",
    "gn:name":"Vidulis",
    "gn:population":376,
    "gn:timezone":"Europe/Rome",
    "iso:country":"IT",
    "wof:name":"Vidulis",
    "wof:placetype":"locality",
    "wof:population":376
},
  "geometry": {"coordinates":[12.9475,46.09861],"type":"Point"}
}