{
  "type": "Feature",
  "properties": {
    "gn:admin1_code":"9",
    "gn:admin2_code":"BG",
    "gn:admin3_code":"16006.0",
    "gn:asciiname":"Albelasco",
    "gn:country_code":"IT",
    "gn:dem":634,
    "gn:feature_class":"P",
    "gn:feature_code":"PPL",
    "gn:name":"Albelasco",
    "gn:population":13,
    "gn:timezone":"Europe/Rome",
    "iso:country":"IT",
    "wof:name":"Albelasco",
    "wof:placetype":"locality",
    "wof:population":13
},
  "geometry": {"coordinates":[9.55277,45.76175],"type":"Point"}
}