{
  "type": "Feature",
  "properties": {
    "gn:admin1_code":"12",
    "gn:admin2_code":"VB",
    "gn:admin3_code":"103075.0",
    "gn:asciiname":"Boschetto-Casa dei Conti",
    "gn:country_code":"IT",
    "gn:dem":473,
    "gn:feature_class":"P",
    "gn:feature_code":"PPL",
    "gn:name":"Boschetto-Casa dei Conti",
    "gn:population":155,
    "gn:timezone":"Europe/Rome",
    "iso:country":"IT",
    "wof:name":"Boschetto-Casa dei Conti",
    "wof:placetype":"locality",
    "wof:population":155
},
  "geometry": {"coordinates":[8.24216,46.06566],"type":"Point"}
}