{
  "type": "Feature",
  "properties": {
    "gn:gn_country":"IT",
    "gn:gn_fcode":"PPL",
    "gn:gn_pop":0,
    "gn:population":36,
    "iso:country":"IT",
    "name:baq_x_preferred":[
        "Montetiffi"
    ],
    "name:cat_x_preferred":[
        "Montetiffi"
    ],
    "name:cze_x_preferred":[
        "Montetiffi"
    ],
    "name:dan_x_preferred":[
        "Montetiffi"
    ],
    "name:dut_x_preferred":[
        "Montetiffi"
    ],
    "name:eng_x_preferred":[
        "Montetiffi"
    ],
    "name:fin_x_preferred":[
        "Montetiffi"
    ],
    "name:fre_x_preferred":[
        "Montetiffi"
    ],
    "name:ind_x_preferred":[
        "Montetiffi"
    ],
    "name:ita_x_preferred":[
        "Montetiffi"
    ],
    "name:nno_x_preferred":[
        "Montetiffi"
    ],
    "name:nob_x_preferred":[
        "Montetiffi"
    ],
    "name:oci_x_preferred":[
        "Montetiffi"
    ],
    "name:pol_x_preferred":[
        "Montetiffi"
    ],
    "name:por_x_preferred":[
        "Montetiffi"
    ],
    "name:rum_x_preferred":[
        "Montetiffi"
    ],
    "name:slo_x_preferred":[
        "Montetiffi"
    ],
    "name:slv_x_preferred":[
        "Montetiffi"
    ],
    "name:spa_x_preferred":[
        "Montetiffi"
    ],
    "name:srp_x_preferred":[
        "Montetiffi"
    ],
    "name:swe_x_preferred":[
        "Montetiffi"
    ],
    "name:tgl_x_preferred":[
        "Montetiffi"
    ],
    "name:tur_x_preferred":[
        "Montetiffi"
    ],
    "name:war_x_preferred":[
        "Montetiffi"
    ],
    "qs_pg:aaroncc":"IT",
    "qs_pg:gn_country":"IT",
    "qs_pg:gn_fcode":"PPL",
    "qs_pg:gn_pop":0,
    "qs_pg:name":"Montetiffi",
    "qs_pg:name_adm0":"Italia",
    "qs_pg:name_adm1":"Emilia Romagna",
    "qs_pg:photos":73,
    "qs_pg:photos_1k":15,
    "qs_pg:photos_9k":1,
    "qs_pg:photos_9r":2,
    "qs_pg:photos_all":73,
    "qs_pg:photos_sr":2,
    "qs_pg:pop_sr":0,
    "qs_pg:qs_pg_placetype":"locality",
    "qs_pg:qs_pg_placetype_gp":"Town",
    "qs_pg:woe_adm0":23424853,
    "woe:adm0_id":23424853,
    "woe:name_adm0":"Italia",
    "woe:name_adm1":"Emilia Romagna",
    "woe:placetype":"Town",
    "wof:name":"Montetiffi",
    "wof:placetype":"locality",
    "wof:population":36
},
  "geometry": {"coordinates":[12.28333,43.95],"type":"Point"}
}