{
  "type": "Feature",
  "properties": {
    "gn:admin1_code":"16.0",
    "gn:admin2_code":"LI",
    "gn:admin3_code":"49002.0",
    "gn:asciiname":"Casalappi",
    "gn:country_code":"IT",
    "gn:dem":30,
    "gn:feature_class":"P",
    "gn:feature_code":"PPL",
    "gn:name":"Casalappi",
    "gn:population":27,
    "gn:timezone":"Europe/Rome",
    "iso:country":"IT",
    "wof:name":"Casalappi",
    "wof:placetype":"locality",
    "wof:population":27
},
  "geometry": {"coordinates":[10.68394,43.02302],"type":"Point"}
}