{
  "type": "Feature",
  "properties": {
    "gn:admin1_code":"12",
    "gn:admin2_code":"AL",
    "gn:admin3_code":"6050.0",
    "gn:asciiname":"San Giuseppe",
    "gn:country_code":"IT",
    "gn:dem":204,
    "gn:feature_class":"P",
    "gn:feature_code":"PPL",
    "gn:name":"San Giuseppe",
    "gn:population":65,
    "gn:timezone":"Europe/Rome",
    "iso:country":"IT",
    "wof:name":"San Giuseppe",
    "wof:placetype":"locality",
    "wof:population":65
},
  "geometry": {"coordinates":[8.24498,45.06452],"type":"Point"}
}