{
  "type": "Feature",
  "properties": {
    "gn:admin1_code":"20",
    "gn:admin2_code":"RO",
    "gn:admin3_code":"29021.0",
    "gn:asciiname":"Colombara",
    "gn:country_code":"IT",
    "gn:dem":6,
    "gn:feature_class":"P",
    "gn:feature_code":"PPL",
    "gn:name":"Colombara",
    "gn:population":22,
    "gn:timezone":"Europe/Rome",
    "iso:country":"IT",
    "wof:name":"Colombara",
    "wof:placetype":"locality",
    "wof:population":22
},
  "geometry": {"coordinates":[11.43435,44.97531],"type":"Point"}
}