{
  "type": "Feature",
  "properties": {
    "gn:admin1_code":"5",
    "gn:admin2_code":"RA",
    "gn:admin3_code":"39005.0",
    "gn:asciiname":"Sant'Apolinnare",
    "gn:country_code":"IT",
    "gn:dem":319,
    "gn:feature_class":"P",
    "gn:feature_code":"PPL",
    "gn:name":"Sant'Apolinnare",
    "gn:population":23,
    "gn:timezone":"Europe/Rome",
    "iso:country":"IT",
    "wof:name":"Sant'Apolinnare",
    "wof:placetype":"locality",
    "wof:population":23
},
  "geometry": {"coordinates":[11.58797,44.16227],"type":"Point"}
}