{
  "type": "Feature",
  "properties": {
    "gn:admin1_code":"5",
    "gn:admin2_code":"BO",
    "gn:admin3_code":"37015.0",
    "gn:asciiname":"Pida",
    "gn:country_code":"IT",
    "gn:dem":566,
    "gn:feature_class":"P",
    "gn:feature_code":"PPL",
    "gn:name":"Pida",
    "gn:population":12,
    "gn:timezone":"Europe/Rome",
    "iso:country":"IT",
    "wof:name":"Pida",
    "wof:placetype":"locality",
    "wof:population":12
},
  "geometry": {"coordinates":[11.03091,44.13245],"type":"Point"}
}