{
  "type": "Feature",
  "properties": {
    "gn:admin1_code":"16",
    "gn:admin2_code":"PI",
    "gn:admin3_code":"50006.0",
    "gn:asciiname":"Montaleo",
    "gn:country_code":"IT",
    "gn:dem":168,
    "gn:feature_class":"P",
    "gn:feature_code":"PPL",
    "gn:name":"Montaleo",
    "gn:population":12,
    "gn:timezone":"Europe/Rome",
    "iso:country":"IT",
    "wof:name":"Montaleo",
    "wof:placetype":"locality",
    "wof:population":12
},
  "geometry": {"coordinates":[10.60766,43.30254],"type":"Point"}
}