{
  "type": "Feature",
  "properties": {
    "gn:admin1_code":"12",
    "gn:admin2_code":"CN",
    "gn:admin3_code":"4090.0",
    "gn:asciiname":"Lanza Serra",
    "gn:country_code":"IT",
    "gn:dem":1008,
    "gn:feature_class":"P",
    "gn:feature_code":"PPL",
    "gn:name":"Lanza Serra",
    "gn:population":26,
    "gn:timezone":"Europe/Rome",
    "iso:country":"IT",
    "wof:name":"Lanza Serra",
    "wof:placetype":"locality",
    "wof:population":26
},
  "geometry": {"coordinates":[7.82175,44.27351],"type":"Point"}
}