{
  "type": "Feature",
  "properties": {
    "gn:admin1_code":"5",
    "gn:admin2_code":"RE",
    "gn:admin3_code":"35022.0",
    "gn:asciiname":"Olmo",
    "gn:country_code":"IT",
    "gn:dem":34,
    "gn:feature_class":"P",
    "gn:feature_code":"PPL",
    "gn:name":"Olmo",
    "gn:population":43,
    "gn:timezone":"Europe/Rome",
    "iso:country":"IT",
    "name:ceb_x_preferred":[
        "Olmo"
    ],
    "name:deu_x_preferred":[
        "Olmo"
    ],
    "name:ita_x_preferred":[
        "Olmo"
    ],
    "name:nds_x_preferred":[
        "Olmo"
    ],
    "name:nld_x_preferred":[
        "Olmo"
    ],
    "name:por_x_preferred":[
        "Olmo"
    ],
    "name:rus_x_preferred":[
        "\u041e\u043b\u044c\u043c\u043e"
    ],
    "name:spa_x_preferred":[
        "Olmo"
    ],
    "name:srp_x_preferred":[
        "Olmo"
    ],
    "name:swe_x_preferred":[
        "Olmo"
    ],
    "wof:name":"Olmo",
    "wof:placetype":"locality",
    "wof:population":43
},
  "geometry": {"coordinates":[10.49479,44.82035],"type":"Point"}
}