{
  "type": "Feature",
  "properties": {
    "gn:admin1_code":"20.0",
    "gn:admin2_code":"BL",
    "gn:admin3_code":"25055.0",
    "gn:asciiname":"Caupo",
    "gn:country_code":"IT",
    "gn:dem":324,
    "gn:feature_class":"P",
    "gn:feature_code":"PPL",
    "gn:name":"Caupo",
    "gn:population":349,
    "gn:timezone":"Europe/Rome",
    "iso:country":"IT",
    "wof:name":"Caupo",
    "wof:placetype":"locality",
    "wof:population":349
},
  "geometry": {"coordinates":[11.83846,45.99903],"type":"Point"}
}