{
  "type": "Feature",
  "properties": {
    "gn:admin1_code":"16",
    "gn:admin2_code":"FI",
    "gn:admin3_code":"48030.0",
    "gn:asciiname":"Fornace",
    "gn:country_code":"IT",
    "gn:dem":61,
    "gn:feature_class":"P",
    "gn:feature_code":"PPL",
    "gn:name":"Fornace",
    "gn:population":69,
    "gn:timezone":"Europe/Rome",
    "iso:country":"IT",
    "wof:name":"Fornace",
    "wof:placetype":"locality",
    "wof:population":69
},
  "geometry": {"coordinates":[11.06806,43.70311],"type":"Point"}
}