{
  "type": "Feature",
  "properties": {
    "gn:admin1_code":"9",
    "gn:admin2_code":"BG",
    "gn:admin3_code":"16004.0",
    "gn:asciiname":"Ca' del Colle",
    "gn:country_code":"IT",
    "gn:dem":451,
    "gn:feature_class":"P",
    "gn:feature_code":"PPL",
    "gn:name":"Ca' del Colle",
    "gn:population":156,
    "gn:timezone":"Europe/Rome",
    "iso:country":"IT",
    "wof:name":"Ca' del Colle",
    "wof:placetype":"locality",
    "wof:population":156
},
  "geometry": {"coordinates":[9.82616,45.76963],"type":"Point"}
}