{
  "type": "Feature",
  "properties": {
    "gn:admin1_code":"6.0",
    "gn:admin2_code":"UD",
    "gn:admin3_code":"30061.0",
    "gn:asciiname":"Flaipano",
    "gn:country_code":"IT",
    "gn:dem":575,
    "gn:elevation":"583.0",
    "gn:feature_class":"P",
    "gn:feature_code":"PPL",
    "gn:name":"Flaipano",
    "gn:population":19,
    "gn:timezone":"Europe/Rome",
    "iso:country":"IT",
    "wof:name":"Flaipano",
    "wof:placetype":"locality",
    "wof:population":19
},
  "geometry": {"coordinates":[13.21838,46.26722],"type":"Point"}
}