{
  "type": "Feature",
  "properties": {
    "gn:admin1_code":"17",
    "gn:admin2_code":"TN",
    "gn:admin3_code":"22033.0",
    "gn:asciiname":"Bozzana",
    "gn:country_code":"IT",
    "gn:dem":645,
    "gn:feature_class":"P",
    "gn:feature_code":"PPL",
    "gn:name":"Bozzana",
    "gn:population":222,
    "gn:timezone":"Europe/Rome",
    "iso:country":"IT",
    "wof:name":"Bozzana",
    "wof:placetype":"locality",
    "wof:population":222
},
  "geometry": {"coordinates":[10.98709,46.38879],"type":"Point"}
}