{
  "type": "Feature",
  "properties": {
    "gn:admin1_code":"3.0",
    "gn:admin2_code":"CZ",
    "gn:admin3_code":"79148.0",
    "gn:asciiname":"Casellone",
    "gn:country_code":"IT",
    "gn:dem":792,
    "gn:feature_class":"P",
    "gn:feature_code":"PPL",
    "gn:name":"Casellone",
    "gn:population":0,
    "gn:timezone":"Europe/Rome",
    "iso:country":"IT",
    "wof:name":"Casellone",
    "wof:placetype":"locality"
},
  "geometry": {"coordinates":[16.35,38.66667],"type":"Point"}
}