{
  "type": "Feature",
  "properties": {
    "gn:country":"IT",
    "gn:fcode":"PPL",
    "gn:population":0,
    "iso:country":"IT",
    "name:ceb_x_preferred":[
        "Latignano"
    ],
    "name:fas_x_preferred":[
        "\u0644\u0627\u062a\u06cc\u06af\u0646\u0627\u0646\u0648"
    ],
    "name:ita_x_preferred":[
        "Latignano"
    ],
    "name:srp_x_preferred":[
        "\u041b\u0430\u0442\u0438\u045a\u0430\u043d\u043e"
    ],
    "qs_pg:aaroncc":"IT",
    "qs_pg:gn_country":"IT",
    "qs_pg:gn_fcode":"PPL",
    "qs_pg:gn_pop":0,
    "qs_pg:name":"Latignano",
    "qs_pg:name_adm0":"Italia",
    "qs_pg:name_adm1":"Toscana",
    "qs_pg:photos":21,
    "qs_pg:photos_1k":4,
    "qs_pg:photos_9k":1,
    "qs_pg:photos_9r":1,
    "qs_pg:photos_all":21,
    "qs_pg:photos_sr":1,
    "qs_pg:pop_sr":0,
    "qs_pg:qs_pg_placetype":"locality",
    "qs_pg:qs_pg_placetype_gp":"Town",
    "qs_pg:woe_adm0":23424853,
    "woe:adm0_id":23424853,
    "woe:name_adm0":"Italia",
    "woe:name_adm1":"Toscana",
    "woe:placetype":"Town",
    "wof:name":"Latignano",
    "wof:placetype":"locality",
    "wof:population":775
},
  "geometry": {"coordinates":[10.56667,43.65],"type":"Point"}
}