{
  "type": "Feature",
  "properties": {
    "gn:admin1_code":"9",
    "gn:admin2_code":"BS",
    "gn:admin3_code":"17038.0",
    "gn:asciiname":"Porto",
    "gn:country_code":"IT",
    "gn:dem":174,
    "gn:feature_class":"P",
    "gn:feature_code":"PPL",
    "gn:name":"Porto",
    "gn:population":15,
    "gn:timezone":"Europe/Rome",
    "iso:country":"IT",
    "wof:name":"Porto",
    "wof:placetype":"locality",
    "wof:population":15
},
  "geometry": {"coordinates":[9.91775,45.64821],"type":"Point"}
}