{
  "type": "Feature",
  "properties": {
    "gn:gn_country":"IT",
    "gn:gn_fcode":"PPL",
    "gn:gn_pop":0,
    "gn:population":461,
    "iso:country":"IT",
    "name:arg_x_preferred":[
        "Salce"
    ],
    "name:ast_x_preferred":[
        "Salce"
    ],
    "name:cat_x_preferred":[
        "Salce"
    ],
    "name:ceb_x_preferred":[
        "Salce"
    ],
    "name:eus_x_preferred":[
        "Salce"
    ],
    "name:fra_x_preferred":[
        "Salce"
    ],
    "name:haw_x_preferred":[
        "Salce"
    ],
    "name:hun_x_preferred":[
        "Salce"
    ],
    "name:ile_x_preferred":[
        "Salce"
    ],
    "name:ina_x_preferred":[
        "Salce"
    ],
    "name:ita_x_preferred":[
        "Salce"
    ],
    "name:msa_x_preferred":[
        "Salce"
    ],
    "name:nld_x_preferred":[
        "Salce"
    ],
    "name:oci_x_preferred":[
        "Salce"
    ],
    "name:pol_x_preferred":[
        "Salce"
    ],
    "name:por_x_preferred":[
        "Salce"
    ],
    "name:rus_x_preferred":[
        "\u0421\u0430\u043b\u044c\u0441\u0435"
    ],
    "name:spa_x_preferred":[
        "Salce"
    ],
    "name:swe_x_preferred":[
        "Salce"
    ],
    "name:ukr_x_preferred":[
        "\u0421\u0430\u043b\u044c\u0441\u0435"
    ],
    "name:vie_x_preferred":[
        "Salce"
    ],
    "name:war_x_preferred":[
        "Salce"
    ],
    "name:zho_x_preferred":[
        "\u8428\u5c14\u585e"
    ],
    "qs_pg:aaroncc":"IT",
    "qs_pg:gn_country":"IT",
    "qs_pg:gn_fcode":"PPL",
    "qs_pg:gn_pop":0,
    "qs_pg:name":"Salce",
    "qs_pg:name_adm0":"Italia",
    "qs_pg:name_adm1":"Veneto",
    "qs_pg:photos_9r":0,
    "qs_pg:photos_sr":0,
    "qs_pg:pop_sr":0,
    "qs_pg:qs_pg_placetype":"locality",
    "qs_pg:qs_pg_placetype_gp":"Town",
    "qs_pg:woe_adm0":23424853,
    "woe:adm0_id":23424853,
    "woe:name_adm0":"Italia",
    "woe:name_adm1":"Veneto",
    "woe:placetype":"Town",
    "wof:name":"Salce",
    "wof:placetype":"locality",
    "wof:population":461
},
  "geometry": {"coordinates":[12.195,46.11667],"type":"Point"}
}