{
  "type": "Feature",
  "properties": {
    "gn:admin1_code":"10",
    "gn:admin2_code":"PU",
    "gn:admin3_code":"41064.0",
    "gn:asciiname":"Valle Fuini",
    "gn:country_code":"IT",
    "gn:dem":299,
    "gn:feature_class":"P",
    "gn:feature_code":"PPL",
    "gn:name":"Valle Fuini",
    "gn:population":43,
    "gn:timezone":"Europe/Rome",
    "iso:country":"IT",
    "wof:name":"Valle Fuini",
    "wof:placetype":"locality",
    "wof:population":43
},
  "geometry": {"coordinates":[12.55037,43.84899],"type":"Point"}
}