{
  "type": "Feature",
  "properties": {
    "gn:admin1_code":"20.0",
    "gn:admin2_code":"TV",
    "gn:admin3_code":"26085.0",
    "gn:asciiname":"Falze-Signoressa",
    "gn:country_code":"IT",
    "gn:dem":80,
    "gn:feature_class":"P",
    "gn:feature_code":"PPLA3",
    "gn:name":"Falz\u00e8-Signoressa",
    "gn:population":3417,
    "gn:timezone":"Europe/Rome",
    "iso:country":"IT",
    "wof:name":"Falze-Signoressa",
    "wof:placetype":"locality",
    "wof:population":3417
},
  "geometry": {"coordinates":[12.10722,45.75028],"type":"Point"}
}