{
  "type": "Feature",
  "properties": {
    "gn:admin1_code":"12.0",
    "gn:admin2_code":"NO",
    "gn:admin3_code":"3044.0",
    "gn:asciiname":"Cascina Monastero",
    "gn:country_code":"IT",
    "gn:dem":238,
    "gn:feature_class":"P",
    "gn:feature_code":"PPL",
    "gn:name":"Cascina Monastero",
    "gn:population":26,
    "gn:timezone":"Europe/Rome",
    "iso:country":"IT",
    "wof:name":"Cascina Monastero",
    "wof:placetype":"locality",
    "wof:population":26
},
  "geometry": {"coordinates":[8.4949,45.60657],"type":"Point"}
}