{
  "type": "Feature",
  "properties": {
    "gn:admin1_code":"1.0",
    "gn:admin2_code":"AQ",
    "gn:admin3_code":"66025.0",
    "gn:asciiname":"Villetta",
    "gn:cc2":"IT",
    "gn:country_code":"IT",
    "gn:dem":806,
    "gn:elevation":"806.0",
    "gn:feature_class":"P",
    "gn:feature_code":"PPL",
    "gn:name":"Villetta",
    "gn:population":29,
    "gn:timezone":"Europe/Rome",
    "iso:country":"IT",
    "name:und_x_variant":[
        "Villa"
    ],
    "wof:name":"Villetta",
    "wof:placetype":"locality",
    "wof:population":29
},
  "geometry": {"coordinates":[13.10656,42.15585],"type":"Point"}
}