{
  "type": "Feature",
  "properties": {
    "gn:admin1_code":"20",
    "gn:admin2_code":"TV",
    "gn:admin3_code":"26068.0",
    "gn:asciiname":"Case Fraccaro",
    "gn:country_code":"IT",
    "gn:dem":54,
    "gn:feature_class":"P",
    "gn:feature_code":"PPL",
    "gn:name":"Case Fraccaro",
    "gn:population":50,
    "gn:timezone":"Europe/Rome",
    "iso:country":"IT",
    "wof:name":"Case Fraccaro",
    "wof:placetype":"locality",
    "wof:population":50
},
  "geometry": {"coordinates":[11.90513,45.71027],"type":"Point"}
}