{
  "type": "Feature",
  "properties": {
    "gn:admin1_code":"9.0",
    "gn:admin2_code":"MI",
    "gn:admin3_code":"15172.0",
    "gn:asciiname":"Cascina Lodola",
    "gn:country_code":"IT",
    "gn:dem":143,
    "gn:feature_class":"P",
    "gn:feature_code":"PPL",
    "gn:name":"Cascina Lodola",
    "gn:population":31,
    "gn:timezone":"Europe/Rome",
    "iso:country":"IT",
    "wof:name":"Cascina Lodola",
    "wof:placetype":"locality",
    "wof:population":31
},
  "geometry": {"coordinates":[9.40893,45.54835],"type":"Point"}
}