{
  "type": "Feature",
  "properties": {
    "gn:admin1_code":"6",
    "gn:admin2_code":"PN",
    "gn:admin3_code":"93013.0",
    "gn:asciiname":"Galilea",
    "gn:country_code":"IT",
    "gn:dem":10,
    "gn:feature_class":"P",
    "gn:feature_code":"PPL",
    "gn:name":"Galilea",
    "gn:population":18,
    "gn:timezone":"Europe/Rome",
    "iso:country":"IT",
    "wof:name":"Galilea",
    "wof:placetype":"locality",
    "wof:population":18
},
  "geometry": {"coordinates":[12.71094,45.8538],"type":"Point"}
}