{
  "type": "Feature",
  "properties": {
    "gn:admin1_code":"16.0",
    "gn:admin2_code":"GR",
    "gn:admin3_code":"53003.0",
    "gn:asciiname":"Centro B",
    "gn:country_code":"IT",
    "gn:dem":11,
    "gn:feature_class":"P",
    "gn:feature_code":"PPL",
    "gn:name":"Centro B",
    "gn:population":23,
    "gn:timezone":"Europe/Rome",
    "iso:country":"IT",
    "wof:name":"Centro B",
    "wof:placetype":"locality",
    "wof:population":23
},
  "geometry": {"coordinates":[11.40774,42.40526],"type":"Point"}
}