{
  "type": "Feature",
  "properties": {
    "gn:admin1_code":"18",
    "gn:admin2_code":"TR",
    "gn:admin3_code":"55013.0",
    "gn:asciiname":"San Cristoforo",
    "gn:country_code":"IT",
    "gn:dem":467,
    "gn:feature_class":"P",
    "gn:feature_code":"PPL",
    "gn:name":"San Cristoforo",
    "gn:population":142,
    "gn:timezone":"Europe/Rome",
    "iso:country":"IT",
    "name:ara_x_preferred":[
        "\u0633\u0627\u0646 \u0643\u0631\u064a\u0633\u062a\u0648\u0641\u0648\u0631\u0648"
    ],
    "name:azb_x_preferred":[
        "\u0633\u0646 \u06a9\u0631\u06cc\u0633\u062a\u0648\u0641\u0648\u0631\u0648"
    ],
    "name:bel_x_preferred":[
        "\u0421\u0430\u043d-\u041a\u0440\u044b\u0441\u0442\u0430\u0444\u043e\u0440\u0430"
    ],
    "name:bul_x_preferred":[
        "\u0421\u0430\u043d \u041a\u0440\u0438\u0441\u0442\u043e\u0444\u043e\u0440\u043e"
    ],
    "name:cat_x_preferred":[
        "San Cristoforo"
    ],
    "name:ceb_x_preferred":[
        "San Cristoforo"
    ],
    "name:deu_x_preferred":[
        "San Cristoforo"
    ],
    "name:epo_x_preferred":[
        "San Cristoforo"
    ],
    "name:eus_x_preferred":[
        "San Cristoforo"
    ],
    "name:fas_x_preferred":[
        "\u0633\u0646 \u06a9\u0631\u06cc\u0633\u062a\u0648\u0641\u0648\u0631\u0648"
    ],
    "name:fra_x_preferred":[
        "San Cristoforo"
    ],
    "name:hun_x_preferred":[
        "San Cristoforo"
    ],
    "name:hye_x_preferred":[
        "\u054d\u0561\u0576 \u0554\u0580\u056b\u057d\u057f\u0578\u0586\u0578\u0580\u0578"
    ],
    "name:ind_x_preferred":[
        "San Cristoforo"
    ],
    "name:ita_x_preferred":[
        "San Cristoforo"
    ],
    "name:jpn_x_preferred":[
        "\u30b5\u30f3\u30fb\u30af\u30ea\u30b9\u30c8\u30fc\u30d5\u30a9\u30ed"
    ],
    "name:lat_x_preferred":[
        "Fanum Sancti Christophori"
    ],
    "name:lmo_x_preferred":[
        "San Cristoforo"
    ],
    "name:msa_x_preferred":[
        "San Cristoforo"
    ],
    "name:nap_x_preferred":[
        "San Cristoforo"
    ],
    "name:nld_x_preferred":[
        "San Cristoforo"
    ],
    "name:pms_x_preferred":[
        "San Crist\u00f2fi"
    ],
    "name:pol_x_preferred":[
        "San Cristoforo"
    ],
    "name:por_x_preferred":[
        "San Cristoforo"
    ],
    "name:ron_x_preferred":[
        "San Cristoforo"
    ],
    "name:rus_x_preferred":[
        "\u0421\u0430\u043d-\u041a\u0440\u0438\u0441\u0442\u043e\u0444\u043e\u0440\u043e"
    ],
    "name:scn_x_preferred":[
        "San Cristoforo"
    ],
    "name:spa_x_preferred":[
        "San Cristoforo"
    ],
    "name:srp_x_preferred":[
        "\u0421\u0430\u043d \u041a\u0440\u0438\u0441\u0442\u043e\u0444\u043e\u0440\u043e"
    ],
    "name:tgl_x_preferred":[
        "San Cristoforo"
    ],
    "name:ukr_x_preferred":[
        "\u0421\u0430\u043d-\u041a\u0440\u0438\u0441\u0442\u043e\u0444\u043e\u0440\u043e"
    ],
    "name:uzb_x_preferred":[
        "San Cristoforo"
    ],
    "name:vie_x_preferred":[
        "San Cristoforo"
    ],
    "name:vol_x_preferred":[
        "San Cristoforo"
    ],
    "name:war_x_preferred":[
        "San Cristoforo"
    ],
    "name:zho_x_preferred":[
        "\u5723\u514b\u91cc\u65af\u6258\u798f\u7f57"
    ],
    "wof:name":"San Cristoforo",
    "wof:placetype":"locality",
    "wof:population":142
},
  "geometry": {"coordinates":[12.06779,42.84716],"type":"Point"}
}