{
  "type": "Feature",
  "properties": {
    "gn:admin1_code":"18",
    "gn:admin2_code":"TR",
    "gn:admin3_code":"55013.0",
    "gn:asciiname":"San Cristoforo",
    "gn:country_code":"IT",
    "gn:dem":467,
    "gn:feature_class":"P",
    "gn:feature_code":"PPL",
    "gn:name":"San Cristoforo",
    "gn:population":142,
    "gn:timezone":"Europe/Rome",
    "iso:country":"IT",
    "wof:name":"San Cristoforo",
    "wof:placetype":"locality",
    "wof:population":142
},
  "geometry": {"coordinates":[12.06779,42.84716],"type":"Point"}
}