{
  "type": "Feature",
  "properties": {
    "gn:admin1_code":"9",
    "gn:admin2_code":"BS",
    "gn:admin3_code":"17007.0",
    "gn:asciiname":"Piazze",
    "gn:country_code":"IT",
    "gn:dem":690,
    "gn:feature_class":"P",
    "gn:feature_code":"PPL",
    "gn:name":"Piazze",
    "gn:population":170,
    "gn:timezone":"Europe/Rome",
    "iso:country":"IT",
    "wof:name":"Piazze",
    "wof:placetype":"locality",
    "wof:population":170
},
  "geometry": {"coordinates":[10.18097,45.85038],"type":"Point"}
}