{
  "type": "Feature",
  "properties": {
    "gn:admin1_code":"12",
    "gn:admin2_code":"TO",
    "gn:admin3_code":"1183.0",
    "gn:asciiname":"San Luca",
    "gn:country_code":"IT",
    "gn:dem":649,
    "gn:feature_class":"P",
    "gn:feature_code":"PPL",
    "gn:name":"San Luca",
    "gn:population":132,
    "gn:timezone":"Europe/Rome",
    "iso:country":"IT",
    "name:ara_x_preferred":[
        "\u0633\u0627\u0646 \u0644\u0648\u0643\u0627"
    ],
    "name:azb_x_preferred":[
        "\u0633\u0646 \u0644\u0648\u06a9\u0627"
    ],
    "name:bcl_x_preferred":[
        "San Luca"
    ],
    "name:bul_x_preferred":[
        "\u0421\u0430\u043d \u041b\u0443\u043a\u0430"
    ],
    "name:ceb_x_preferred":[
        "San Luca"
    ],
    "name:deu_x_preferred":[
        "San Luca"
    ],
    "name:epo_x_preferred":[
        "San Luca"
    ],
    "name:eus_x_preferred":[
        "San Luca"
    ],
    "name:fas_x_preferred":[
        "\u0633\u0646 \u0644\u0648\u06a9\u0627"
    ],
    "name:fra_x_preferred":[
        "San Luca"
    ],
    "name:hun_x_preferred":[
        "San Luca"
    ],
    "name:hye_x_preferred":[
        "\u054d\u0561\u0576 \u053c\u0578\u0582\u056f\u0561"
    ],
    "name:ina_x_preferred":[
        "San Luca"
    ],
    "name:ita_x_preferred":[
        "San Luca"
    ],
    "name:jpn_x_preferred":[
        "\u30b5\u30f3\u30fb\u30eb\u30fc\u30ab"
    ],
    "name:kaz_x_preferred":[
        "\u0421\u0430\u043d-\u041b\u0443\u043a\u0430"
    ],
    "name:lat_x_preferred":[
        "Fanum Sancti Lucae"
    ],
    "name:lmo_x_preferred":[
        "San Luca"
    ],
    "name:msa_x_preferred":[
        "San Luca"
    ],
    "name:nap_x_preferred":[
        "San Luca"
    ],
    "name:nld_x_preferred":[
        "San Luca"
    ],
    "name:pms_x_preferred":[
        "San Luca"
    ],
    "name:pol_x_preferred":[
        "San Luca"
    ],
    "name:por_x_preferred":[
        "San Luca"
    ],
    "name:ron_x_preferred":[
        "San Luca"
    ],
    "name:rus_x_preferred":[
        "\u0421\u0430\u043d-\u041b\u0443\u043a\u0430"
    ],
    "name:scn_x_preferred":[
        "Santu Luca"
    ],
    "name:spa_x_preferred":[
        "San Luca"
    ],
    "name:srp_x_preferred":[
        "\u0421\u0430\u043d \u041b\u0443\u043a\u0430"
    ],
    "name:ukr_x_preferred":[
        "\u0421\u0430\u043d-\u041b\u0443\u043a\u0430"
    ],
    "name:uzb_x_preferred":[
        "San Luca"
    ],
    "name:vie_x_preferred":[
        "San Luca"
    ],
    "name:vol_x_preferred":[
        "San Luca"
    ],
    "name:war_x_preferred":[
        "San Luca"
    ],
    "name:zho_x_preferred":[
        "\u5723\u5362\u5361"
    ],
    "wof:name":"San Luca",
    "wof:placetype":"locality",
    "wof:population":132
},
  "geometry": {"coordinates":[7.73623,45.03248],"type":"Point"}
}