{
  "type": "Feature",
  "properties": {
    "gn:admin1_code":"12",
    "gn:admin2_code":"TO",
    "gn:admin3_code":"1183.0",
    "gn:asciiname":"San Luca",
    "gn:country_code":"IT",
    "gn:dem":649,
    "gn:feature_class":"P",
    "gn:feature_code":"PPL",
    "gn:name":"San Luca",
    "gn:population":132,
    "gn:timezone":"Europe/Rome",
    "iso:country":"IT",
    "wof:name":"San Luca",
    "wof:placetype":"locality",
    "wof:population":132
},
  "geometry": {"coordinates":[7.73623,45.03248],"type":"Point"}
}