{
  "type": "Feature",
  "properties": {
    "gn:admin1_code":"1",
    "gn:admin2_code":"AQ",
    "gn:admin3_code":"66016.0",
    "gn:asciiname":"Case Isaia",
    "gn:country_code":"IT",
    "gn:dem":1331,
    "gn:feature_class":"P",
    "gn:feature_code":"PPLL",
    "gn:name":"Case Isaia",
    "gn:population":9,
    "gn:timezone":"Europe/Rome",
    "iso:country":"IT",
    "wof:name":"Case Isaia",
    "wof:placetype":"locality",
    "wof:population":9
},
  "geometry": {"coordinates":[13.40998,42.53204],"type":"Point"}
}