{
  "type": "Feature",
  "properties": {
    "gn:admin1_code":"4",
    "gn:admin2_code":"AV",
    "gn:admin3_code":"64066.0",
    "gn:asciiname":"Fiorentino I",
    "gn:country_code":"IT",
    "gn:dem":648,
    "gn:feature_class":"P",
    "gn:feature_code":"PPL",
    "gn:name":"Fiorentino I",
    "gn:population":11,
    "gn:timezone":"Europe/Rome",
    "iso:country":"IT",
    "wof:name":"Fiorentino I",
    "wof:placetype":"locality",
    "wof:population":11
},
  "geometry": {"coordinates":[15.1454,40.87416],"type":"Point"}
}