{
  "type": "Feature",
  "properties": {
    "gn:admin1_code":"5.0",
    "gn:admin2_code":"RE",
    "gn:admin3_code":"35034.0",
    "gn:asciiname":"Ponte Vettigano",
    "gn:country_code":"IT",
    "gn:dem":23,
    "gn:elevation":"26.0",
    "gn:feature_class":"P",
    "gn:feature_code":"PPL",
    "gn:name":"Ponte Vettigano",
    "gn:population":20,
    "gn:timezone":"Europe/Rome",
    "iso:country":"IT",
    "wof:name":"Ponte Vettigano",
    "wof:placetype":"locality",
    "wof:population":20
},
  "geometry": {"coordinates":[10.78037,44.83153],"type":"Point"}
}