{
  "type": "Feature",
  "properties": {
    "gn:gn_country":"IT",
    "gn:gn_fcode":"PPL",
    "gn:gn_pop":0,
    "iso:country":"IT",
    "name:unk_x_variant":[
        "Casa Buffalotta"
    ],
    "qs_pg:aaroncc":"IT",
    "qs_pg:gn_country":"IT",
    "qs_pg:gn_fcode":"PPL",
    "qs_pg:gn_pop":0,
    "qs_pg:name":"Casale Bufalotta",
    "qs_pg:name_adm0":"Italia",
    "qs_pg:name_adm1":"Lazio",
    "qs_pg:photos":7,
    "qs_pg:photos_1k":1,
    "qs_pg:photos_9k":1,
    "qs_pg:photos_9r":1,
    "qs_pg:photos_all":7,
    "qs_pg:photos_sr":1,
    "qs_pg:pop_sr":0,
    "qs_pg:qs_pg_placetype":"locality",
    "qs_pg:qs_pg_placetype_gp":"Town",
    "qs_pg:woe_adm0":23424853,
    "woe:adm0_id":23424853,
    "woe:name_adm0":"Italia",
    "woe:name_adm1":"Lazio",
    "woe:placetype":"Town",
    "wof:name":"Casale Bufalotta",
    "wof:placetype":"locality"
},
  "geometry": {"coordinates":[12.55,41.98333],"type":"Point"}
}