{
  "type": "Feature",
  "properties": {
    "iso:country":"IT",
    "wof:name":"Monteverde",
    "wof:placetype":"neighbourhood"
},
  "geometry": {"coordinates":[12.45410408049329,41.87979214357465],"type":"Point"}
}