{
  "type": "Feature",
  "properties": {
    "iso:country":"IT",
    "name:fas_x_preferred":[
        "\u0645\u0648\u0646\u062a\u0647\u200c\u0648\u0631\u062f\u0647"
    ],
    "name:fra_x_preferred":[
        "Monteverde"
    ],
    "name:ind_x_preferred":[
        "Monteverde"
    ],
    "name:ita_x_preferred":[
        "Monteverde"
    ],
    "name:nld_x_preferred":[
        "Monteverde"
    ],
    "name:nor_x_preferred":[
        "Monteverde"
    ],
    "name:spa_x_preferred":[
        "Monteverde"
    ],
    "name:vie_x_preferred":[
        "Monteverde"
    ],
    "name:zho_x_preferred":[
        "\u8499\u6cf0\u97cb\u723e\u5fb7\u5340"
    ],
    "wof:name":"Monteverde",
    "wof:placetype":"neighbourhood"
},
  "geometry": {"coordinates":[12.45410408049329,41.87979214357465],"type":"Point"}
}