{
  "type": "Feature",
  "properties": {
    "gn:admin1_code":"12",
    "gn:admin2_code":"CN",
    "gn:admin3_code":"4101.0",
    "gn:asciiname":"Curato",
    "gn:country_code":"IT",
    "gn:dem":202,
    "gn:feature_class":"P",
    "gn:feature_code":"PPL",
    "gn:name":"Curato",
    "gn:population":26,
    "gn:timezone":"Europe/Rome",
    "iso:country":"IT",
    "wof:name":"Curato",
    "wof:placetype":"locality",
    "wof:population":26
},
  "geometry": {"coordinates":[8.04741,44.74073],"type":"Point"}
}