{
  "type": "Feature",
  "properties": {
    "gn:admin1_code":"7",
    "gn:admin2_code":"RM",
    "gn:admin3_code":"58023.0",
    "gn:asciiname":"Monitola",
    "gn:country_code":"IT",
    "gn:dem":245,
    "gn:feature_class":"P",
    "gn:feature_code":"PPL",
    "gn:name":"Monitola",
    "gn:population":173,
    "gn:timezone":"Europe/Rome",
    "iso:country":"IT",
    "wof:name":"Monitola",
    "wof:placetype":"locality",
    "wof:population":173
},
  "geometry": {"coordinates":[12.82813,41.95188],"type":"Point"}
}