{
  "type": "Feature",
  "properties": {
    "gn:admin1_code":"1.0",
    "gn:admin2_code":"AQ",
    "gn:admin3_code":"66056.0",
    "gn:asciiname":"Cesariano",
    "gn:country_code":"IT",
    "gn:dem":867,
    "gn:feature_class":"P",
    "gn:feature_code":"PPL",
    "gn:name":"Cesariano",
    "gn:population":0,
    "gn:timezone":"Europe/Rome",
    "iso:country":"IT",
    "wof:name":"Cesariano",
    "wof:placetype":"locality"
},
  "geometry": {"coordinates":[13.26667,42.53333],"type":"Point"}
}