{
  "type": "Feature",
  "properties": {
    "gn:admin1_code":"17",
    "gn:admin2_code":"TN",
    "gn:admin3_code":"22205.0",
    "gn:asciiname":"San Lazzaro",
    "gn:country_code":"IT",
    "gn:dem":233,
    "gn:feature_class":"P",
    "gn:feature_code":"PPL",
    "gn:name":"San Lazzaro",
    "gn:population":237,
    "gn:timezone":"Europe/Rome",
    "iso:country":"IT",
    "wof:name":"San Lazzaro",
    "wof:placetype":"locality",
    "wof:population":237
},
  "geometry": {"coordinates":[11.11445,46.13605],"type":"Point"}
}