{
  "type": "Feature",
  "properties": {
    "gn:admin1_code":"3.0",
    "gn:admin2_code":"CS",
    "gn:admin3_code":"78122.0",
    "gn:asciiname":"Deuda I",
    "gn:country_code":"IT",
    "gn:dem":12,
    "gn:feature_class":"P",
    "gn:feature_code":"PPL",
    "gn:name":"Deuda I",
    "gn:population":32,
    "gn:timezone":"Europe/Rome",
    "iso:country":"IT",
    "wof:name":"Deuda I",
    "wof:placetype":"locality",
    "wof:population":32
},
  "geometry": {"coordinates":[16.04516,39.3204],"type":"Point"}
}