{
  "type": "Feature",
  "properties": {
    "gn:admin1_code":"17",
    "gn:admin2_code":"TN",
    "gn:admin3_code":"22196.0",
    "gn:asciiname":"Piera",
    "gn:country_code":"IT",
    "gn:dem":994,
    "gn:feature_class":"P",
    "gn:feature_code":"PPL",
    "gn:name":"Piera",
    "gn:population":54,
    "gn:timezone":"Europe/Rome",
    "iso:country":"IT",
    "wof:name":"Piera",
    "wof:placetype":"locality",
    "wof:population":54
},
  "geometry": {"coordinates":[11.49218,46.29119],"type":"Point"}
}