{
  "type": "Feature",
  "properties": {
    "gn:admin1_code":"17",
    "gn:admin2_code":"TN",
    "gn:admin3_code":"22196.0",
    "gn:asciiname":"Piera",
    "gn:country_code":"IT",
    "gn:dem":994,
    "gn:feature_class":"P",
    "gn:feature_code":"PPL",
    "gn:name":"Piera",
    "gn:population":54,
    "gn:timezone":"Europe/Rome",
    "iso:country":"IT",
    "name:ara_x_preferred":[
        "\u0628\u0627\u064a\u0631\u0627"
    ],
    "name:arg_x_preferred":[
        "Piera"
    ],
    "name:ast_x_preferred":[
        "Piera"
    ],
    "name:azb_x_preferred":[
        "\u067e\u06cc\u0631\u0627"
    ],
    "name:cat_x_preferred":[
        "Piera"
    ],
    "name:ceb_x_preferred":[
        "Piera"
    ],
    "name:deu_x_preferred":[
        "Piera"
    ],
    "name:eus_x_preferred":[
        "Piera"
    ],
    "name:fas_x_preferred":[
        "\u067e\u06cc\u0631\u0627"
    ],
    "name:fra_x_preferred":[
        "Piera"
    ],
    "name:hun_x_preferred":[
        "Piera"
    ],
    "name:hye_x_preferred":[
        "\u054a\u056b\u0565\u0580\u0561"
    ],
    "name:ita_x_preferred":[
        "Piera"
    ],
    "name:kaz_x_preferred":[
        "\u041f\u044c\u0435\u0440\u0430"
    ],
    "name:lat_x_preferred":[
        "Piera"
    ],
    "name:msa_x_preferred":[
        "Piera"
    ],
    "name:nld_x_preferred":[
        "Piera"
    ],
    "name:oci_x_preferred":[
        "Piera"
    ],
    "name:pol_x_preferred":[
        "Piera"
    ],
    "name:por_x_preferred":[
        "Piera"
    ],
    "name:ron_x_preferred":[
        "Piera"
    ],
    "name:rus_x_preferred":[
        "\u041f\u044c\u0435\u0440\u0430"
    ],
    "name:sco_x_preferred":[
        "Piera"
    ],
    "name:spa_x_preferred":[
        "Piera"
    ],
    "name:sqi_x_preferred":[
        "Piera"
    ],
    "name:swe_x_preferred":[
        "Piera"
    ],
    "name:ukr_x_preferred":[
        "\u041f\u0456\u0454\u0440\u0430"
    ],
    "name:uzb_x_preferred":[
        "Piera"
    ],
    "name:vie_x_preferred":[
        "Piera"
    ],
    "name:war_x_preferred":[
        "Piera"
    ],
    "wof:name":"Piera",
    "wof:placetype":"locality",
    "wof:population":54
},
  "geometry": {"coordinates":[11.49218,46.29119],"type":"Point"}
}