{
  "type": "Feature",
  "properties": {
    "gn:admin1_code":"18.0",
    "gn:admin2_code":"TR",
    "gn:admin3_code":"55030.0",
    "gn:asciiname":"Pornello",
    "gn:country_code":"IT",
    "gn:dem":423,
    "gn:elevation":"426.0",
    "gn:feature_class":"P",
    "gn:feature_code":"PPL",
    "gn:name":"Pornello",
    "gn:population":13,
    "gn:timezone":"Europe/Rome",
    "iso:country":"IT",
    "wof:name":"Pornello",
    "wof:placetype":"locality",
    "wof:population":13
},
  "geometry": {"coordinates":[12.18562,42.88752],"type":"Point"}
}