{
  "type": "Feature",
  "properties": {
    "gn:admin1_code":"16.0",
    "gn:admin2_code":"LU",
    "gn:admin3_code":"46037.0",
    "gn:asciiname":"Dalli Sopra",
    "gn:country_code":"IT",
    "gn:dem":1002,
    "gn:feature_class":"P",
    "gn:feature_code":"PPL",
    "gn:name":"Dalli Sopra",
    "gn:population":47,
    "gn:timezone":"Europe/Rome",
    "iso:country":"IT",
    "wof:name":"Dalli Sopra",
    "wof:placetype":"locality",
    "wof:population":47
},
  "geometry": {"coordinates":[10.28487,44.23396],"type":"Point"}
}