{
  "type": "Feature",
  "properties": {
    "gn:admin1_code":"10",
    "gn:admin2_code":"MC",
    "gn:admin3_code":"43053.0",
    "gn:asciiname":"Case San Martino",
    "gn:country_code":"IT",
    "gn:dem":208,
    "gn:feature_class":"P",
    "gn:feature_code":"PPL",
    "gn:name":"Case San Martino",
    "gn:population":33,
    "gn:timezone":"Europe/Rome",
    "iso:country":"IT",
    "wof:name":"Case San Martino",
    "wof:placetype":"locality",
    "wof:population":33
},
  "geometry": {"coordinates":[13.26985,43.19904],"type":"Point"}
}