{
  "type": "Feature",
  "properties": {
    "iso:country":"IT",
    "wof:name":"Spallette",
    "wof:placetype":"neighbourhood"
},
  "geometry": {"coordinates":[12.35691508200735,41.83534140635372],"type":"Point"}
}