{
  "type": "Feature",
  "properties": {
    "gn:admin1_code":"16.0",
    "gn:admin2_code":"PI",
    "gn:admin3_code":"50032.0",
    "gn:asciiname":"Fondo Scesa Balconevisi",
    "gn:country_code":"IT",
    "gn:dem":48,
    "gn:feature_class":"P",
    "gn:feature_code":"PPL",
    "gn:name":"Fondo Scesa Balconevisi",
    "gn:population":44,
    "gn:timezone":"Europe/Rome",
    "iso:country":"IT",
    "wof:name":"Fondo Scesa Balconevisi",
    "wof:placetype":"locality",
    "wof:population":44
},
  "geometry": {"coordinates":[10.83418,43.63945],"type":"Point"}
}