{
  "type": "Feature",
  "properties": {
    "gn:admin1_code":"20",
    "gn:admin2_code":"VR",
    "gn:admin3_code":"23038.0",
    "gn:asciiname":"Rupiano",
    "gn:country_code":"IT",
    "gn:dem":402,
    "gn:feature_class":"P",
    "gn:feature_code":"PPL",
    "gn:name":"Rupiano",
    "gn:population":88,
    "gn:timezone":"Europe/Rome",
    "iso:country":"IT",
    "wof:name":"Rupiano",
    "wof:placetype":"locality",
    "wof:population":88
},
  "geometry": {"coordinates":[10.98574,45.54385],"type":"Point"}
}