{
  "type": "Feature",
  "properties": {
    "gn:admin1_code":"4",
    "gn:admin2_code":"SA",
    "gn:admin3_code":"65106.0",
    "gn:asciiname":"Case Conforti",
    "gn:country_code":"IT",
    "gn:dem":96,
    "gn:feature_class":"P",
    "gn:feature_code":"PPL",
    "gn:name":"Case Conforti",
    "gn:population":45,
    "gn:timezone":"Europe/Rome",
    "iso:country":"IT",
    "wof:name":"Case Conforti",
    "wof:placetype":"locality",
    "wof:population":45
},
  "geometry": {"coordinates":[15.12226,40.45949],"type":"Point"}
}