{
  "type": "Feature",
  "properties": {
    "gn:admin1_code":"16",
    "gn:admin2_code":"MS",
    "gn:admin3_code":"45012.0",
    "gn:asciiname":"Parana",
    "gn:country_code":"IT",
    "gn:dem":669,
    "gn:feature_class":"P",
    "gn:feature_code":"PPL",
    "gn:name":"Parana",
    "gn:population":44,
    "gn:timezone":"Europe/Rome",
    "iso:country":"IT",
    "wof:name":"Parana",
    "wof:placetype":"locality",
    "wof:population":44
},
  "geometry": {"coordinates":[9.86104,44.28208],"type":"Point"}
}