{
  "type": "Feature",
  "properties": {
    "gn:admin1_code":"4",
    "gn:admin3_code":"63035.0",
    "gn:asciiname":"Castello",
    "gn:country_code":"IT",
    "gn:dem":289,
    "gn:feature_class":"P",
    "gn:feature_code":"PPL",
    "gn:name":"Castello",
    "gn:population":334,
    "gn:timezone":"Europe/Rome",
    "iso:country":"IT",
    "wof:name":"Castello",
    "wof:placetype":"locality",
    "wof:population":334
},
  "geometry": {"coordinates":[14.53659,40.67928],"type":"Point"}
}