{
  "type": "Feature",
  "properties": {
    "gn:admin1_code":"11",
    "gn:admin2_code":"CB",
    "gn:admin3_code":"70008.0",
    "gn:asciiname":"Cataniello III",
    "gn:country_code":"IT",
    "gn:dem":569,
    "gn:feature_class":"P",
    "gn:feature_code":"PPL",
    "gn:name":"Cataniello III",
    "gn:population":243,
    "gn:timezone":"Europe/Rome",
    "iso:country":"IT",
    "wof:name":"Cataniello III",
    "wof:placetype":"locality",
    "wof:population":243
},
  "geometry": {"coordinates":[14.71314,41.56509000000001],"type":"Point"}
}