{
  "type": "Feature",
  "properties": {
    "gn:admin1_code":"7.0",
    "gn:admin2_code":"RM",
    "gn:admin3_code":"58047.0",
    "gn:asciiname":"Pichini",
    "gn:country_code":"IT",
    "gn:dem":117,
    "gn:feature_class":"P",
    "gn:feature_code":"PPL",
    "gn:name":"Pichini",
    "gn:population":780,
    "gn:timezone":"Europe/Rome",
    "iso:country":"IT",
    "wof:name":"Pichini",
    "wof:placetype":"locality",
    "wof:population":780
},
  "geometry": {"coordinates":[12.6826,42.00172],"type":"Point"}
}