{
  "type": "Feature",
  "properties": {
    "iso:country":"IT",
    "qs_pg:aaroncc":"IT",
    "qs_pg:name":"Su Tilio'",
    "qs_pg:name_adm0":"Italia",
    "qs_pg:name_adm1":"Sardegna",
    "qs_pg:photos":18,
    "qs_pg:photos_1k":4,
    "qs_pg:photos_9k":1,
    "qs_pg:photos_9r":1,
    "qs_pg:photos_all":18,
    "qs_pg:photos_sr":1,
    "qs_pg:pop_sr":0,
    "qs_pg:qs_pg_placetype":"locality",
    "qs_pg:qs_pg_placetype_gp":"Town",
    "qs_pg:woe_adm0":23424853,
    "woe:adm0_id":23424853,
    "woe:name_adm0":"Italia",
    "woe:name_adm1":"Sardegna",
    "woe:placetype":"Town",
    "wof:name":"Su Tilio'",
    "wof:placetype":"locality"
},
  "geometry": {"coordinates":[9.79135,40.5455855],"type":"Point"}
}