{
  "type": "Feature",
  "properties": {
    "gn:admin1_code":"3",
    "gn:admin2_code":"RC",
    "gn:admin3_code":"80088.0",
    "gn:asciiname":"Ferraro",
    "gn:country_code":"IT",
    "gn:dem":174,
    "gn:feature_class":"P",
    "gn:feature_code":"PPL",
    "gn:name":"Ferraro",
    "gn:population":140,
    "gn:timezone":"Europe/Rome",
    "iso:country":"IT",
    "wof:name":"Ferraro",
    "wof:placetype":"locality",
    "wof:population":140
},
  "geometry": {"coordinates":[16.27781,38.3107],"type":"Point"}
}