{
  "type": "Feature",
  "properties": {
    "gn:admin1_code":"20.0",
    "gn:admin2_code":"VR",
    "gn:admin3_code":"23058.0",
    "gn:asciiname":"Campagna",
    "gn:country_code":"IT",
    "gn:dem":104,
    "gn:feature_class":"P",
    "gn:feature_code":"PPL",
    "gn:name":"Campagna",
    "gn:population":11,
    "gn:timezone":"Europe/Rome",
    "iso:country":"IT",
    "name:azb_x_preferred":[
        "\u06a9\u0627\u0645\u067e\u0627\u0646\u06cc\u0627"
    ],
    "name:bel_x_preferred":[
        "\u041a\u0430\u043c\u043f\u0430\u043d\u044c\u044f"
    ],
    "name:bul_x_preferred":[
        "\u041a\u0430\u043c\u043f\u0430\u043d\u044f"
    ],
    "name:cat_x_preferred":[
        "Campagna"
    ],
    "name:ceb_x_preferred":[
        "Campagna"
    ],
    "name:ces_x_preferred":[
        "Campagna"
    ],
    "name:deu_x_preferred":[
        "Campagna"
    ],
    "name:epo_x_preferred":[
        "Campagna"
    ],
    "name:eus_x_preferred":[
        "Campagna"
    ],
    "name:fas_x_preferred":[
        "\u06a9\u0627\u0645\u067e\u0627\u0646\u06cc\u0627"
    ],
    "name:fra_x_preferred":[
        "Campagna"
    ],
    "name:hun_x_preferred":[
        "Campagna"
    ],
    "name:hye_x_preferred":[
        "\u053f\u0561\u0574\u057a\u0561\u0576\u0575\u0561"
    ],
    "name:ina_x_preferred":[
        "Campagna"
    ],
    "name:ind_x_preferred":[
        "Campagna"
    ],
    "name:ita_x_preferred":[
        "Campagna"
    ],
    "name:jpn_x_preferred":[
        "\u30ab\u30f3\u30d1\u30fc\u30cb\u30e3"
    ],
    "name:kor_x_preferred":[
        "\uce84\ud30c\ub0d0"
    ],
    "name:lat_x_preferred":[
        "Campania"
    ],
    "name:lmo_x_preferred":[
        "Campagna"
    ],
    "name:msa_x_preferred":[
        "Campagna"
    ],
    "name:nap_x_preferred":[
        "Campagna"
    ],
    "name:nld_x_preferred":[
        "Campagna"
    ],
    "name:nno_x_preferred":[
        "Campagna"
    ],
    "name:nor_x_preferred":[
        "Campagna"
    ],
    "name:pms_x_preferred":[
        "Campagna"
    ],
    "name:pol_x_preferred":[
        "Campagna"
    ],
    "name:por_x_preferred":[
        "Campagna"
    ],
    "name:ron_x_preferred":[
        "Campagna"
    ],
    "name:rus_x_preferred":[
        "\u041a\u0430\u043c\u043f\u0430\u043d\u044c\u044f"
    ],
    "name:scn_x_preferred":[
        "Campagna"
    ],
    "name:spa_x_preferred":[
        "Campagna"
    ],
    "name:srp_x_preferred":[
        "\u041a\u0430\u043c\u043f\u0430\u045a\u0430"
    ],
    "name:swe_x_preferred":[
        "Campagna"
    ],
    "name:tgl_x_preferred":[
        "Campagna"
    ],
    "name:tur_x_preferred":[
        "Campagna"
    ],
    "name:ukr_x_preferred":[
        "\u041a\u0430\u043c\u043f\u0430\u043d\u044c\u044f"
    ],
    "name:uzb_x_preferred":[
        "Campagna"
    ],
    "name:vec_x_preferred":[
        "Campagna"
    ],
    "name:vie_x_preferred":[
        "Campagna"
    ],
    "name:vol_x_preferred":[
        "Campagna"
    ],
    "name:war_x_preferred":[
        "Campagna"
    ],
    "wof:name":"Campagna",
    "wof:placetype":"locality",
    "wof:population":11
},
  "geometry": {"coordinates":[10.87563,45.49257],"type":"Point"}
}