{
  "type": "Feature",
  "properties": {
    "gn:admin1_code":"20.0",
    "gn:admin2_code":"VR",
    "gn:admin3_code":"23058.0",
    "gn:asciiname":"Campagna",
    "gn:country_code":"IT",
    "gn:dem":104,
    "gn:feature_class":"P",
    "gn:feature_code":"PPL",
    "gn:name":"Campagna",
    "gn:population":11,
    "gn:timezone":"Europe/Rome",
    "iso:country":"IT",
    "wof:name":"Campagna",
    "wof:placetype":"locality",
    "wof:population":11
},
  "geometry": {"coordinates":[10.87563,45.49257],"type":"Point"}
}