{
  "type": "Feature",
  "properties": {
    "gn:admin1_code":"3.0",
    "gn:admin2_code":"CZ",
    "gn:admin3_code":"79133.0",
    "gn:asciiname":"Roccani",
    "gn:country_code":"IT",
    "gn:dem":38,
    "gn:feature_class":"P",
    "gn:feature_code":"PPL",
    "gn:name":"Roccani",
    "gn:population":342,
    "gn:timezone":"Europe/Rome",
    "iso:country":"IT",
    "wof:name":"Roccani",
    "wof:placetype":"locality",
    "wof:population":342
},
  "geometry": {"coordinates":[16.69223,38.87228],"type":"Point"}
}