{
  "type": "Feature",
  "properties": {
    "gn:admin1_code":"6",
    "gn:admin2_code":"PN",
    "gn:admin3_code":"93016.0",
    "gn:asciiname":"Bulian",
    "gn:country_code":"IT",
    "gn:dem":421,
    "gn:feature_class":"P",
    "gn:feature_code":"PPLL",
    "gn:name":"Bulian",
    "gn:population":9,
    "gn:timezone":"Europe/Rome",
    "iso:country":"IT",
    "wof:name":"Bulian",
    "wof:placetype":"locality",
    "wof:population":9
},
  "geometry": {"coordinates":[12.91357,46.21932],"type":"Point"}
}