{
  "type": "Feature",
  "properties": {
    "gn:admin1_code":"6.0",
    "gn:admin2_code":"UD",
    "gn:admin3_code":"30117.0",
    "gn:asciiname":"Coccau di Sopra",
    "gn:country_code":"IT",
    "gn:dem":786,
    "gn:feature_class":"P",
    "gn:feature_code":"PPL",
    "gn:name":"Coccau di Sopra",
    "gn:population":40,
    "gn:timezone":"Europe/Rome",
    "iso:country":"IT",
    "wof:name":"Coccau di Sopra",
    "wof:placetype":"locality",
    "wof:population":40
},
  "geometry": {"coordinates":[13.60878,46.5178],"type":"Point"}
}