{
  "type": "Feature",
  "properties": {
    "gn:admin1_code":"12",
    "gn:admin2_code":"TO",
    "gn:admin3_code":"1171.0",
    "gn:asciiname":"Sanatorio San Luigi",
    "gn:country_code":"IT",
    "gn:dem":283,
    "gn:feature_class":"P",
    "gn:feature_code":"PPLL",
    "gn:name":"Sanatorio San Luigi",
    "gn:population":8,
    "gn:timezone":"Europe/Rome",
    "iso:country":"IT",
    "wof:name":"Sanatorio San Luigi",
    "wof:placetype":"locality",
    "wof:population":8
},
  "geometry": {"coordinates":[7.55635,45.02954],"type":"Point"}
}