{
  "type": "Feature",
  "properties": {
    "gn:admin1_code":"6",
    "gn:admin2_code":"UD",
    "gn:admin3_code":"30103.0",
    "gn:asciiname":"Puoie",
    "gn:country_code":"IT",
    "gn:dem":361,
    "gn:feature_class":"P",
    "gn:feature_code":"PPL",
    "gn:name":"Puoie",
    "gn:population":21,
    "gn:timezone":"Europe/Rome",
    "iso:country":"IT",
    "wof:name":"Puoie",
    "wof:placetype":"locality",
    "wof:population":21
},
  "geometry": {"coordinates":[13.51756,46.15866],"type":"Point"}
}