{
  "type": "Feature",
  "properties": {
    "gn:admin1_code":"12",
    "gn:admin2_code":"TO",
    "gn:admin3_code":"1201.0",
    "gn:asciiname":"Duc A Valle e A Monte",
    "gn:country_code":"IT",
    "gn:dem":1740,
    "gn:feature_class":"P",
    "gn:feature_code":"PPL",
    "gn:name":"Duc A Valle e A Monte",
    "gn:population":13,
    "gn:timezone":"Europe/Rome",
    "iso:country":"IT",
    "wof:name":"Duc A Valle e A Monte",
    "wof:placetype":"locality",
    "wof:population":13
},
  "geometry": {"coordinates":[6.91312,44.98801],"type":"Point"}
}