{
  "type": "Feature",
  "properties": {
    "gn:admin1_code":"18",
    "gn:admin2_code":"PG",
    "gn:admin3_code":"54020.0",
    "gn:asciiname":"Stazione",
    "gn:country_code":"IT",
    "gn:dem":168,
    "gn:feature_class":"P",
    "gn:feature_code":"PPL",
    "gn:name":"Stazione",
    "gn:population":129,
    "gn:timezone":"Europe/Rome",
    "iso:country":"IT",
    "wof:name":"Stazione",
    "wof:placetype":"locality",
    "wof:population":129
},
  "geometry": {"coordinates":[12.38329,42.84845],"type":"Point"}
}