{
  "type": "Feature",
  "properties": {
    "gn:admin1_code":"5",
    "gn:admin2_code":"PR",
    "gn:admin3_code":"34035.0",
    "gn:asciiname":"Zibel",
    "gn:country_code":"IT",
    "gn:dem":308,
    "gn:feature_class":"P",
    "gn:feature_code":"PPL",
    "gn:name":"Zibel",
    "gn:population":18,
    "gn:timezone":"Europe/Rome",
    "iso:country":"IT",
    "wof:name":"Zibel",
    "wof:placetype":"locality",
    "wof:population":18
},
  "geometry": {"coordinates":[9.90843,44.67563],"type":"Point"}
}