{
  "type": "Feature",
  "properties": {
    "gn:admin1_code":"9.0",
    "gn:admin2_code":"MN",
    "gn:admin3_code":"20056.0",
    "gn:asciiname":"Loghino Speranza",
    "gn:country_code":"IT",
    "gn:dem":12,
    "gn:feature_class":"P",
    "gn:feature_code":"PPL",
    "gn:name":"Loghino Speranza",
    "gn:population":0,
    "gn:timezone":"Europe/Rome",
    "iso:country":"IT",
    "wof:name":"Loghino Speranza",
    "wof:placetype":"locality"
},
  "geometry": {"coordinates":[11.03333,44.98333],"type":"Point"}
}