{
  "type": "Feature",
  "properties": {
    "gn:admin1_code":"12.0",
    "gn:admin2_code":"AL",
    "gn:admin3_code":"6159.0",
    "gn:asciiname":"Serra",
    "gn:country_code":"IT",
    "gn:dem":197,
    "gn:feature_class":"P",
    "gn:feature_code":"PPL",
    "gn:name":"Serra",
    "gn:population":35,
    "gn:timezone":"Europe/Rome",
    "iso:country":"IT",
    "name:cat_x_preferred":[
        "Serra"
    ],
    "name:ceb_x_preferred":[
        "Serra"
    ],
    "name:ces_x_preferred":[
        "Serra"
    ],
    "name:deu_x_preferred":[
        "Serra"
    ],
    "name:epo_x_preferred":[
        "Serra"
    ],
    "name:eus_x_preferred":[
        "Serra"
    ],
    "name:fas_x_preferred":[
        "\u0633\u0631\u0627"
    ],
    "name:fra_x_preferred":[
        "Serra"
    ],
    "name:glg_x_preferred":[
        "Serra"
    ],
    "name:hun_x_preferred":[
        "Serra"
    ],
    "name:hye_x_preferred":[
        "\u054d\u0565\u057c\u0561"
    ],
    "name:ita_x_preferred":[
        "Serra"
    ],
    "name:nld_x_preferred":[
        "Serra"
    ],
    "name:nor_x_preferred":[
        "Serra"
    ],
    "name:por_x_preferred":[
        "Serra"
    ],
    "name:rus_x_preferred":[
        "\u0421\u0435\u0440\u0440\u0430"
    ],
    "name:scn_x_preferred":[
        "Serra"
    ],
    "name:srp_x_preferred":[
        "Serra"
    ],
    "name:swe_x_preferred":[
        "Serra"
    ],
    "name:tur_x_preferred":[
        "Serra"
    ],
    "name:ukr_x_preferred":[
        "\u0421\u0435\u0440\u0440\u0430"
    ],
    "wof:name":"Serra",
    "wof:placetype":"locality",
    "wof:population":35
},
  "geometry": {"coordinates":[8.29778,45.09769],"type":"Point"}
}