{
  "type": "Feature",
  "properties": {
    "gn:admin1_code":"12.0",
    "gn:admin2_code":"AL",
    "gn:admin3_code":"6159.0",
    "gn:asciiname":"Serra",
    "gn:country_code":"IT",
    "gn:dem":197,
    "gn:feature_class":"P",
    "gn:feature_code":"PPL",
    "gn:name":"Serra",
    "gn:population":35,
    "gn:timezone":"Europe/Rome",
    "iso:country":"IT",
    "wof:name":"Serra",
    "wof:placetype":"locality",
    "wof:population":35
},
  "geometry": {"coordinates":[8.29778,45.09769],"type":"Point"}
}