{
  "type": "Feature",
  "properties": {
    "gn:admin1_code":"12",
    "gn:admin2_code":"TO",
    "gn:admin3_code":"1128.0",
    "gn:asciiname":"Ovairo",
    "gn:country_code":"IT",
    "gn:dem":658,
    "gn:feature_class":"P",
    "gn:feature_code":"PPL",
    "gn:name":"Ovairo",
    "gn:population":30,
    "gn:timezone":"Europe/Rome",
    "iso:country":"IT",
    "wof:name":"Ovairo",
    "wof:placetype":"locality",
    "wof:population":30
},
  "geometry": {"coordinates":[7.46175,45.28471],"type":"Point"}
}