{
  "type": "Feature",
  "properties": {
    "iso:country":"IT",
    "name:ast_x_preferred":[
        "Rosa"
    ],
    "name:bar_x_preferred":[
        "Rosa"
    ],
    "name:bos_x_preferred":[
        "Rosa"
    ],
    "name:cat_x_preferred":[
        "Rosa"
    ],
    "name:ceb_x_preferred":[
        "Rosa"
    ],
    "name:ces_x_preferred":[
        "Rosa"
    ],
    "name:dan_x_preferred":[
        "Rosa"
    ],
    "name:deu_x_preferred":[
        "Rosa"
    ],
    "name:epo_x_preferred":[
        "Rosa"
    ],
    "name:fas_x_preferred":[
        "\u0631\u0632\u0627"
    ],
    "name:fin_x_preferred":[
        "Rosa"
    ],
    "name:fra_x_preferred":[
        "Rosa"
    ],
    "name:glg_x_preferred":[
        "Rosa"
    ],
    "name:hrv_x_preferred":[
        "Rosa"
    ],
    "name:ind_x_preferred":[
        "Rosa"
    ],
    "name:ita_x_preferred":[
        "Rosa"
    ],
    "name:jpn_x_preferred":[
        "\u30ed\u30fc\u30b6"
    ],
    "name:lat_x_preferred":[
        "Rosa"
    ],
    "name:lav_x_preferred":[
        "Rosa"
    ],
    "name:nld_x_preferred":[
        "Rosa"
    ],
    "name:nor_x_preferred":[
        "Rosa"
    ],
    "name:oci_x_preferred":[
        "R\u00f2sa"
    ],
    "name:pol_x_preferred":[
        "Rosa"
    ],
    "name:por_x_preferred":[
        "Rosa"
    ],
    "name:ron_x_preferred":[
        "Rosa"
    ],
    "name:rus_x_preferred":[
        "Rosa"
    ],
    "name:scn_x_preferred":[
        "Rosa"
    ],
    "name:slk_x_preferred":[
        "Rosa"
    ],
    "name:slv_x_preferred":[
        "Rosa"
    ],
    "name:spa_x_preferred":[
        "Rosa"
    ],
    "name:srp_x_preferred":[
        "Rosa"
    ],
    "name:swe_x_preferred":[
        "Rosa"
    ],
    "name:vie_x_preferred":[
        "Rosa"
    ],
    "name:vol_x_preferred":[
        "Rosa"
    ],
    "wof:name":"Rosa",
    "wof:placetype":"neighbourhood"
},
  "geometry": {"coordinates":[7.72927510143527,45.08802617859147],"type":"Point"}
}