{
  "type": "Feature",
  "properties": {
    "iso:country":"IT",
    "wof:name":"Rosa",
    "wof:placetype":"neighbourhood"
},
  "geometry": {"coordinates":[7.72927510143527,45.08802617859147],"type":"Point"}
}