{
  "type": "Feature",
  "properties": {
    "gn:admin1_code":"1.0",
    "gn:admin2_code":"AQ",
    "gn:admin3_code":"66049.0",
    "gn:asciiname":"Sassa Scalo",
    "gn:country_code":"IT",
    "gn:dem":669,
    "gn:elevation":"664.0",
    "gn:feature_class":"P",
    "gn:feature_code":"PPL",
    "gn:name":"Sassa Scalo",
    "gn:population":225,
    "gn:timezone":"Europe/Rome",
    "iso:country":"IT",
    "wof:name":"Sassa Scalo",
    "wof:placetype":"locality",
    "wof:population":225
},
  "geometry": {"coordinates":[13.29354,42.36064],"type":"Point"}
}