{
  "type": "Feature",
  "properties": {
    "gn:admin1_code":"10",
    "gn:admin2_code":"PU",
    "gn:admin3_code":"41013.0",
    "gn:asciiname":"Fosso Sejore",
    "gn:country_code":"IT",
    "gn:dem":5,
    "gn:feature_class":"P",
    "gn:feature_code":"PPL",
    "gn:name":"Fosso Sejore",
    "gn:population":110,
    "gn:timezone":"Europe/Rome",
    "iso:country":"IT",
    "wof:name":"Fosso Sejore",
    "wof:placetype":"locality",
    "wof:population":110
},
  "geometry": {"coordinates":[12.96432,43.87902],"type":"Point"}
}