{
  "type": "Feature",
  "properties": {
    "gn:elevation":980,
    "gn:population":85,
    "iso:country":"IT",
    "name:cat_x_preferred":[
        "San Lorenzo"
    ],
    "name:ceb_x_preferred":[
        "San Lorenzo"
    ],
    "name:ces_x_preferred":[
        "San Lorenzo"
    ],
    "name:dan_x_preferred":[
        "San Lorenzo"
    ],
    "name:eng_x_preferred":[
        "San Lorenzo"
    ],
    "name:eus_x_preferred":[
        "San Lorenzo"
    ],
    "name:fin_x_preferred":[
        "San Lorenzo"
    ],
    "name:fra_x_preferred":[
        "San Lorenzo"
    ],
    "name:ind_x_preferred":[
        "San Lorenzo"
    ],
    "name:ita_x_preferred":[
        "San Lorenzo"
    ],
    "name:ita_x_variant":[
        "S Lorenzo",
        "S. Lorenzo"
    ],
    "name:nld_x_preferred":[
        "San Lorenzo"
    ],
    "name:nno_x_preferred":[
        "San Lorenzo"
    ],
    "name:nob_x_preferred":[
        "San Lorenzo"
    ],
    "name:oci_x_preferred":[
        "San Lorenzo"
    ],
    "name:pol_x_preferred":[
        "San Lorenzo"
    ],
    "name:por_x_preferred":[
        "San Lorenzo"
    ],
    "name:ron_x_preferred":[
        "San Lorenzo"
    ],
    "name:slk_x_preferred":[
        "San Lorenzo"
    ],
    "name:slv_x_preferred":[
        "San Lorenzo"
    ],
    "name:spa_x_preferred":[
        "San Lorenzo"
    ],
    "name:srp_x_preferred":[
        "San Lorenzo"
    ],
    "name:swe_x_preferred":[
        "San Lorenzo"
    ],
    "name:tgl_x_preferred":[
        "San Lorenzo"
    ],
    "name:tur_x_preferred":[
        "San Lorenzo"
    ],
    "name:war_x_preferred":[
        "San Lorenzo"
    ],
    "qs:a0":"Italia",
    "qs:a1":"*Verbano-Cusio-Ossola",
    "qs:a1r":"0Piemonte",
    "qs:adm0":"Italia",
    "qs:la_lc":"*",
    "qs:level":"locality",
    "qs:loc":"San Lorenzo",
    "qs:loc_alt":"San Lorenzo",
    "qs:pop":0,
    "qs:type":"buffered point",
    "wof:lang":[
        "ita"
    ],
    "wof:name":"San Lorenzo",
    "wof:placetype":"locality",
    "wof:population":85
},
  "geometry": {"coordinates":[8.19821,46.129071],"type":"Point"}
}