{
  "type": "Feature",
  "properties": {
    "gn:admin1_code":"8",
    "gn:admin2_code":"GE",
    "gn:admin3_code":"10025.0",
    "gn:asciiname":"Vignolo",
    "gn:country_code":"IT",
    "gn:dem":136,
    "gn:feature_class":"P",
    "gn:feature_code":"PPL",
    "gn:name":"Vignolo",
    "gn:population":21,
    "gn:timezone":"Europe/Rome",
    "iso:country":"IT",
    "name:azb_x_preferred":[
        "\u0648\u06cc\u0646\u06cc\u0648\u0644\u0648"
    ],
    "name:bel_x_preferred":[
        "\u0412\u0456\u043d\u044c\u0451\u043b\u0430"
    ],
    "name:bul_x_preferred":[
        "\u0412\u0438\u043d\u044c\u043e\u043b\u043e"
    ],
    "name:cat_x_preferred":[
        "Vinh\u00f2l"
    ],
    "name:ceb_x_preferred":[
        "Vignolo"
    ],
    "name:deu_x_preferred":[
        "Vignolo"
    ],
    "name:epo_x_preferred":[
        "Vignolo"
    ],
    "name:est_x_preferred":[
        "Vignolo"
    ],
    "name:eus_x_preferred":[
        "Vignolo"
    ],
    "name:fas_x_preferred":[
        "\u0648\u06cc\u0646\u06cc\u0648\u0644\u0648"
    ],
    "name:fra_x_preferred":[
        "Vignolo"
    ],
    "name:hun_x_preferred":[
        "Vignolo"
    ],
    "name:hye_x_preferred":[
        "\u054e\u056b\u0576\u0575\u0578\u056c\u0578"
    ],
    "name:ind_x_preferred":[
        "Vignolo"
    ],
    "name:ita_x_preferred":[
        "Vignolo"
    ],
    "name:jpn_x_preferred":[
        "\u30f4\u30a3\u30cb\u30e7\u30fc\u30ed"
    ],
    "name:kaz_x_preferred":[
        "\u0412\u0438\u043d\u044c\u043e\u043b\u043e"
    ],
    "name:lat_x_preferred":[
        "Vineolum"
    ],
    "name:lmo_x_preferred":[
        "Vignolo"
    ],
    "name:msa_x_preferred":[
        "Vignolo"
    ],
    "name:nap_x_preferred":[
        "Vignolo"
    ],
    "name:nld_x_preferred":[
        "Vignolo"
    ],
    "name:oci_x_preferred":[
        "Vinh\u00f2l"
    ],
    "name:pms_x_preferred":[
        "Vigneul"
    ],
    "name:pol_x_preferred":[
        "Vignolo"
    ],
    "name:por_x_preferred":[
        "Vignolo"
    ],
    "name:ron_x_preferred":[
        "Vignolo"
    ],
    "name:rus_x_preferred":[
        "\u0412\u0438\u043d\u044c\u043e\u043b\u043e"
    ],
    "name:scn_x_preferred":[
        "Vignolo"
    ],
    "name:spa_x_preferred":[
        "Vignolo"
    ],
    "name:srp_x_preferred":[
        "\u0412\u0438\u045a\u043e\u043b\u043e"
    ],
    "name:tgl_x_preferred":[
        "Vignolo"
    ],
    "name:tur_x_preferred":[
        "Vignolo"
    ],
    "name:ukr_x_preferred":[
        "\u0412\u0456\u043d\u044c\u0439\u043e\u043b\u043e"
    ],
    "name:uzb_x_preferred":[
        "Vignolo"
    ],
    "name:vie_x_preferred":[
        "Villafalletto"
    ],
    "name:vol_x_preferred":[
        "Vignolo"
    ],
    "name:war_x_preferred":[
        "Vignolo"
    ],
    "name:zho_x_preferred":[
        "\u7ef4\u5c3c\u5965\u6d1b"
    ],
    "wof:name":"Vignolo",
    "wof:placetype":"locality",
    "wof:population":21
},
  "geometry": {"coordinates":[8.79737,44.43517],"type":"Point"}
}