{
  "type": "Feature",
  "properties": {
    "gn:admin1_code":"8",
    "gn:admin2_code":"GE",
    "gn:admin3_code":"10025.0",
    "gn:asciiname":"Vignolo",
    "gn:country_code":"IT",
    "gn:dem":136,
    "gn:feature_class":"P",
    "gn:feature_code":"PPL",
    "gn:name":"Vignolo",
    "gn:population":21,
    "gn:timezone":"Europe/Rome",
    "iso:country":"IT",
    "wof:name":"Vignolo",
    "wof:placetype":"locality",
    "wof:population":21
},
  "geometry": {"coordinates":[8.79737,44.43517],"type":"Point"}
}