{
  "type": "Feature",
  "properties": {
    "gn:admin1_code":"7",
    "gn:admin2_code":"RI",
    "gn:admin3_code":"57001.0",
    "gn:asciiname":"San Giovanni",
    "gn:country_code":"IT",
    "gn:dem":1008,
    "gn:feature_class":"P",
    "gn:feature_code":"PPL",
    "gn:name":"San Giovanni",
    "gn:population":12,
    "gn:timezone":"Europe/Rome",
    "iso:country":"IT",
    "wof:name":"San Giovanni",
    "wof:placetype":"locality",
    "wof:population":12
},
  "geometry": {"coordinates":[13.20744,42.69329000000001],"type":"Point"}
}