{
  "type": "Feature",
  "properties": {
    "gn:admin1_code":"12",
    "gn:admin2_code":"AT",
    "gn:admin3_code":"5096.0",
    "gn:asciiname":"Morona",
    "gn:country_code":"IT",
    "gn:dem":142,
    "gn:feature_class":"P",
    "gn:feature_code":"PPL",
    "gn:name":"Morona",
    "gn:population":39,
    "gn:timezone":"Europe/Rome",
    "iso:country":"IT",
    "name:epo_x_preferred":[
        "Morona"
    ],
    "name:fra_x_preferred":[
        "R\u00edo Morona"
    ],
    "name:ita_x_preferred":[
        "Rio Morona"
    ],
    "name:nno_x_preferred":[
        "Morona"
    ],
    "name:nor_x_preferred":[
        "Morona"
    ],
    "name:pnb_x_preferred":[
        "\u0645\u0648\u0631\u0648\u0646 \u062f\u0631\u06cc\u0627"
    ],
    "name:spa_x_preferred":[
        "R\u00edo Morona"
    ],
    "name:zho_x_preferred":[
        "\u83ab\u7f85\u7d0d\u6cb3"
    ],
    "wof:name":"Morona",
    "wof:placetype":"locality",
    "wof:population":39
},
  "geometry": {"coordinates":[8.32744,44.86706],"type":"Point"}
}