{
  "type": "Feature",
  "properties": {
    "gn:admin1_code":"8.0",
    "gn:admin2_code":"IM",
    "gn:admin3_code":"8035.0",
    "gn:asciiname":"Vignago",
    "gn:cc2":"IT",
    "gn:country_code":"IT",
    "gn:dem":823,
    "gn:feature_class":"P",
    "gn:feature_code":"PPL",
    "gn:name":"Vignago",
    "gn:population":0,
    "gn:timezone":"Europe/Rome",
    "iso:country":"IT",
    "name:und_x_variant":[
        "Casa Vignago",
        "Vignago"
    ],
    "wof:name":"Vignago",
    "wof:placetype":"locality"
},
  "geometry": {"coordinates":[7.76667,44.01667],"type":"Point"}
}