{
  "type": "Feature",
  "properties": {
    "gn:admin1_code":"1.0",
    "gn:admin2_code":"TE",
    "gn:admin3_code":"67023.0",
    "gn:asciiname":"Piano Vomano",
    "gn:country_code":"IT",
    "gn:dem":859,
    "gn:elevation":"863.0",
    "gn:feature_class":"P",
    "gn:feature_code":"PPL",
    "gn:name":"Piano Vomano",
    "gn:population":33,
    "gn:timezone":"Europe/Rome",
    "iso:country":"IT",
    "wof:name":"Piano Vomano",
    "wof:placetype":"locality",
    "wof:population":33
},
  "geometry": {"coordinates":[13.51017,42.555],"type":"Point"}
}