{
  "type": "Feature",
  "properties": {
    "gn:admin1_code":"12",
    "gn:admin2_code":"CN",
    "gn:admin3_code":"4028.0",
    "gn:asciiname":"Castellar",
    "gn:country_code":"IT",
    "gn:dem":753,
    "gn:feature_class":"P",
    "gn:feature_code":"PPL",
    "gn:name":"Castellar",
    "gn:population":141,
    "gn:timezone":"Europe/Rome",
    "iso:country":"IT",
    "name:arg_x_preferred":[
        "Castellar"
    ],
    "name:bel_x_preferred":[
        "\u041a\u0430\u0441\u0442\u044d\u043b\u0430\u0440"
    ],
    "name:cat_x_preferred":[
        "Castellar"
    ],
    "name:ceb_x_preferred":[
        "Castellar"
    ],
    "name:deu_x_preferred":[
        "Castellar"
    ],
    "name:epo_x_preferred":[
        "Castellar"
    ],
    "name:eus_x_preferred":[
        "Castellar"
    ],
    "name:fra_x_preferred":[
        "Castellar"
    ],
    "name:glg_x_preferred":[
        "Castellar"
    ],
    "name:hun_x_preferred":[
        "Castellar"
    ],
    "name:ita_x_preferred":[
        "Castellar"
    ],
    "name:msa_x_preferred":[
        "Castellar"
    ],
    "name:nds_x_preferred":[
        "Castellar"
    ],
    "name:nld_x_preferred":[
        "Castellar"
    ],
    "name:pol_x_preferred":[
        "Castellar"
    ],
    "name:por_x_preferred":[
        "Castellar"
    ],
    "name:ron_x_preferred":[
        "Castellar"
    ],
    "name:sco_x_preferred":[
        "Castellar"
    ],
    "name:spa_x_preferred":[
        "Castellar"
    ],
    "name:srp_x_preferred":[
        "\u041a\u0430\u0441\u0442\u0435\u043b\u0430\u0440"
    ],
    "name:swe_x_preferred":[
        "Castellar"
    ],
    "name:tur_x_preferred":[
        "Castellar"
    ],
    "name:uzb_x_preferred":[
        "Castellar"
    ],
    "name:vie_x_preferred":[
        "Castellar"
    ],
    "name:vol_x_preferred":[
        "Castellar"
    ],
    "name:war_x_preferred":[
        "Castellar"
    ],
    "wof:name":"Castellar",
    "wof:placetype":"locality",
    "wof:population":141
},
  "geometry": {"coordinates":[7.57388,44.29717],"type":"Point"}
}