{
  "type": "Feature",
  "properties": {
    "gn:admin1_code":"9.0",
    "gn:admin2_code":"SO",
    "gn:admin3_code":"14032.0",
    "gn:asciiname":"Barzena",
    "gn:country_code":"IT",
    "gn:dem":941,
    "gn:feature_class":"P",
    "gn:feature_code":"PPLL",
    "gn:name":"Barzena",
    "gn:population":0,
    "gn:timezone":"Europe/Rome",
    "iso:country":"IT",
    "name:fas_x_preferred":[
        "\u0628\u0631\u0632\u0646\u0627"
    ],
    "name:msa_x_preferred":[
        "Barzena"
    ],
    "name:ukr_x_preferred":[
        "\u0411\u0430\u0440\u0437\u0435\u043d\u0430"
    ],
    "wof:name":"Barzena",
    "wof:placetype":"locality"
},
  "geometry": {"coordinates":[9.34264,46.27896],"type":"Point"}
}