{
  "type": "Feature",
  "properties": {
    "gn:admin1_code":"7.0",
    "gn:admin2_code":"LT",
    "gn:admin3_code":"59004.0",
    "gn:asciiname":"Forme di Suio-San Cataldo",
    "gn:country_code":"IT",
    "gn:dem":48,
    "gn:feature_class":"P",
    "gn:feature_code":"PPL",
    "gn:name":"Forme di Suio-San Cataldo",
    "gn:population":988,
    "gn:timezone":"Europe/Rome",
    "iso:country":"IT",
    "name:srp_x_preferred":[
        "\u0424\u043e\u0440\u043c\u0435 \u0434\u0438 \u0421\u0443\u0458\u043e \u041a\u0430\u0442\u0430\u043b\u0434\u043e"
    ],
    "name:und_x_variant":[
        "Suio"
    ],
    "wof:name":"Forme di Suio-San Cataldo",
    "wof:placetype":"locality",
    "wof:population":988
},
  "geometry": {"coordinates":[13.85738,41.29466],"type":"Point"}
}