{
  "type": "Feature",
  "properties": {
    "gn:admin1_code":"12",
    "gn:admin2_code":"AT",
    "gn:admin3_code":"5074.0",
    "gn:asciiname":"Croce",
    "gn:country_code":"IT",
    "gn:dem":260,
    "gn:feature_class":"P",
    "gn:feature_code":"PPL",
    "gn:name":"Croce",
    "gn:population":35,
    "gn:timezone":"Europe/Rome",
    "iso:country":"IT",
    "wof:name":"Croce",
    "wof:placetype":"locality",
    "wof:population":35
},
  "geometry": {"coordinates":[8.25233,44.82808],"type":"Point"}
}