{
  "type": "Feature",
  "properties": {
    "gn:admin1_code":"12",
    "gn:admin2_code":"AT",
    "gn:admin3_code":"5074.0",
    "gn:asciiname":"Croce",
    "gn:country_code":"IT",
    "gn:dem":260,
    "gn:feature_class":"P",
    "gn:feature_code":"PPL",
    "gn:name":"Croce",
    "gn:population":35,
    "gn:timezone":"Europe/Rome",
    "iso:country":"IT",
    "name:ceb_x_preferred":[
        "Croce"
    ],
    "name:deu_x_preferred":[
        "Croce"
    ],
    "name:fra_x_preferred":[
        "Croce"
    ],
    "name:ita_x_preferred":[
        "Croce"
    ],
    "name:nld_x_preferred":[
        "Croce"
    ],
    "name:pol_x_preferred":[
        "Croce"
    ],
    "name:rus_x_preferred":[
        "\u041a\u0440\u043e\u0447\u0435"
    ],
    "name:spa_x_preferred":[
        "Croce"
    ],
    "name:srp_x_preferred":[
        "Croce"
    ],
    "name:swe_x_preferred":[
        "Croce"
    ],
    "wof:name":"Croce",
    "wof:placetype":"locality",
    "wof:population":35
},
  "geometry": {"coordinates":[8.25233,44.82808],"type":"Point"}
}