{
  "type": "Feature",
  "properties": {
    "gn:admin1_code":"5",
    "gn:admin2_code":"RE",
    "gn:admin3_code":"35001.0",
    "gn:asciiname":"Ca' dei Duchi",
    "gn:country_code":"IT",
    "gn:dem":156,
    "gn:feature_class":"P",
    "gn:feature_code":"PPL",
    "gn:name":"Ca' dei Duchi",
    "gn:population":51,
    "gn:timezone":"Europe/Rome",
    "iso:country":"IT",
    "wof:name":"Ca' dei Duchi",
    "wof:placetype":"locality",
    "wof:population":51
},
  "geometry": {"coordinates":[10.64375,44.60006],"type":"Point"}
}