{
  "type": "Feature",
  "properties": {
    "gn:admin1_code":"12.0",
    "gn:admin2_code":"CN",
    "gn:admin3_code":"4064.0",
    "gn:asciiname":"San Defendente",
    "gn:country_code":"IT",
    "gn:dem":567,
    "gn:feature_class":"P",
    "gn:feature_code":"PPL",
    "gn:name":"San Defendente",
    "gn:population":1113,
    "gn:timezone":"Europe/Rome",
    "iso:country":"IT",
    "wof:name":"San Defendente",
    "wof:placetype":"locality",
    "wof:population":1113
},
  "geometry": {"coordinates":[7.49091,44.39088],"type":"Point"}
}