{
  "type": "Feature",
  "properties": {
    "gn:admin1_code":"12.0",
    "gn:admin2_code":"AT",
    "gn:admin3_code":"5005.0",
    "gn:asciiname":"Valleandona",
    "gn:country_code":"IT",
    "gn:dem":174,
    "gn:elevation":"166.0",
    "gn:feature_class":"P",
    "gn:feature_code":"PPL",
    "gn:name":"Valleandona",
    "gn:population":147,
    "gn:timezone":"Europe/Rome",
    "iso:country":"IT",
    "wof:name":"Valleandona",
    "wof:placetype":"locality",
    "wof:population":147
},
  "geometry": {"coordinates":[8.11598,44.91243],"type":"Point"}
}