{
  "type": "Feature",
  "properties": {
    "gn:admin1_code":"12",
    "gn:admin2_code":"AT",
    "gn:admin3_code":"5097.0",
    "gn:asciiname":"Valle d'Orta",
    "gn:country_code":"IT",
    "gn:dem":197,
    "gn:feature_class":"P",
    "gn:feature_code":"PPL",
    "gn:name":"Valle d'Orta",
    "gn:population":82,
    "gn:timezone":"Europe/Rome",
    "iso:country":"IT",
    "wof:name":"Valle d'Orta",
    "wof:placetype":"locality",
    "wof:population":82
},
  "geometry": {"coordinates":[8.02739,44.84088],"type":"Point"}
}