{
  "type": "Feature",
  "properties": {
    "gn:admin1_code":"20",
    "gn:admin2_code":"PD",
    "gn:admin3_code":"28081.0",
    "gn:asciiname":"Taglie",
    "gn:country_code":"IT",
    "gn:dem":5,
    "gn:feature_class":"P",
    "gn:feature_code":"PPL",
    "gn:name":"Taglie",
    "gn:population":22,
    "gn:timezone":"Europe/Rome",
    "iso:country":"IT",
    "wof:name":"Taglie",
    "wof:placetype":"locality",
    "wof:population":22
},
  "geometry": {"coordinates":[11.5612,45.19278],"type":"Point"}
}