{
  "type": "Feature",
  "properties": {
    "gn:admin1_code":"3.0",
    "gn:admin2_code":"RC",
    "gn:admin3_code":"80025.0",
    "gn:asciiname":"Foca",
    "gn:country_code":"IT",
    "gn:dem":70,
    "gn:elevation":"60.0",
    "gn:feature_class":"P",
    "gn:feature_code":"PPL",
    "gn:name":"Foc\u00e0",
    "gn:population":437,
    "gn:timezone":"Europe/Rome",
    "iso:country":"IT",
    "name:ceb_x_preferred":[
        "Foca"
    ],
    "name:fra_x_preferred":[
        "Foca"
    ],
    "name:glg_x_preferred":[
        "Foca"
    ],
    "name:ita_x_preferred":[
        "Foca"
    ],
    "name:nld_x_preferred":[
        "Foca"
    ],
    "name:por_x_preferred":[
        "Foca"
    ],
    "name:ron_x_preferred":[
        "Foca"
    ],
    "name:rus_x_preferred":[
        "\u0424\u043e\u0447\u0430"
    ],
    "name:spa_x_preferred":[
        "Foca"
    ],
    "name:swe_x_preferred":[
        "Foca"
    ],
    "wof:name":"Foca",
    "wof:placetype":"locality",
    "wof:population":437
},
  "geometry": {"coordinates":[16.46448,38.36302],"type":"Point"}
}