{
  "type": "Feature",
  "properties": {
    "gn:admin1_code":"4.0",
    "gn:admin2_code":"SA",
    "gn:admin3_code":"65073.0",
    "gn:asciiname":"Macchia",
    "gn:country_code":"IT",
    "gn:dem":138,
    "gn:feature_class":"P",
    "gn:feature_code":"PPL",
    "gn:name":"Macchia",
    "gn:population":1933,
    "gn:timezone":"Europe/Rome",
    "iso:country":"IT",
    "wof:name":"Macchia",
    "wof:placetype":"locality",
    "wof:population":1933
},
  "geometry": {"coordinates":[14.97879,40.65353],"type":"Point"}
}