{
  "type": "Feature",
  "properties": {
    "gn:admin1_code":"16.0",
    "gn:admin2_code":"GR",
    "gn:admin3_code":"53026.0",
    "gn:asciiname":"Elmo",
    "gn:country_code":"IT",
    "gn:dem":506,
    "gn:elevation":"510.0",
    "gn:feature_class":"P",
    "gn:feature_code":"PPL",
    "gn:name":"Elmo",
    "gn:population":44,
    "gn:timezone":"Europe/Rome",
    "iso:country":"IT",
    "name:deu_x_preferred":[
        "Elmo"
    ],
    "name:ita_x_preferred":[
        "Elmo"
    ],
    "name:nld_x_preferred":[
        "Elmo"
    ],
    "name:srp_x_preferred":[
        "\u0415\u043b\u043c\u043e"
    ],
    "wof:name":"Elmo",
    "wof:placetype":"locality",
    "wof:population":44
},
  "geometry": {"coordinates":[11.69852,42.7084],"type":"Point"}
}