{
  "type": "Feature",
  "properties": {
    "gn:admin1_code":"9",
    "gn:admin2_code":"BS",
    "gn:admin3_code":"17156.0",
    "gn:asciiname":"Persaga",
    "gn:country_code":"IT",
    "gn:dem":280,
    "gn:feature_class":"P",
    "gn:feature_code":"PPL",
    "gn:name":"Persaga",
    "gn:population":38,
    "gn:timezone":"Europe/Rome",
    "iso:country":"IT",
    "wof:name":"Persaga",
    "wof:placetype":"locality",
    "wof:population":38
},
  "geometry": {"coordinates":[10.08312,45.63685],"type":"Point"}
}