{
  "type": "Feature",
  "properties": {
    "gn:admin1_code":"12.0",
    "gn:admin2_code":"TO",
    "gn:admin3_code":"1069.0",
    "gn:asciiname":"Punto Verde",
    "gn:country_code":"IT",
    "gn:dem":222,
    "gn:elevation":"227.0",
    "gn:feature_class":"P",
    "gn:feature_code":"PPL",
    "gn:name":"Punto Verde",
    "gn:population":34,
    "gn:timezone":"Europe/Rome",
    "iso:country":"IT",
    "wof:name":"Punto Verde",
    "wof:placetype":"locality",
    "wof:population":34
},
  "geometry": {"coordinates":[8.0288,45.13916],"type":"Point"}
}