{
  "type": "Feature",
  "properties": {
    "gn:admin1_code":"3",
    "gn:admin2_code":"CS",
    "gn:admin3_code":"78155.0",
    "gn:asciiname":"Vence Grande",
    "gn:country_code":"IT",
    "gn:dem":298,
    "gn:feature_class":"P",
    "gn:feature_code":"PPL",
    "gn:name":"Vence Grande",
    "gn:population":105,
    "gn:timezone":"Europe/Rome",
    "iso:country":"IT",
    "wof:name":"Vence Grande",
    "wof:placetype":"locality",
    "wof:population":105
},
  "geometry": {"coordinates":[16.26534,39.32156],"type":"Point"}
}