{
  "type": "Feature",
  "properties": {
    "gn:admin1_code":"9.0",
    "gn:admin2_code":"SO",
    "gn:admin3_code":"14050.0",
    "gn:asciiname":"Dasile",
    "gn:country_code":"IT",
    "gn:dem":1059,
    "gn:feature_class":"P",
    "gn:feature_code":"PPLL",
    "gn:name":"Dasile",
    "gn:population":0,
    "gn:timezone":"Europe/Rome",
    "iso:country":"IT",
    "wof:name":"Dasile",
    "wof:placetype":"locality"
},
  "geometry": {"coordinates":[9.4374,46.33802],"type":"Point"}
}