{
  "type": "Feature",
  "properties": {
    "gn:admin1_code":"16.0",
    "gn:admin2_code":"GR",
    "gn:admin3_code":"53003.0",
    "gn:asciiname":"Nunziatella",
    "gn:country_code":"IT",
    "gn:dem":14,
    "gn:feature_class":"P",
    "gn:feature_code":"PPL",
    "gn:name":"Nunziatella",
    "gn:population":0,
    "gn:timezone":"Europe/Rome",
    "iso:country":"IT",
    "wof:name":"Nunziatella",
    "wof:placetype":"locality"
},
  "geometry": {"coordinates":[11.34836,42.41535],"type":"Point"}
}