{
  "type": "Feature",
  "properties": {
    "gn:admin1_code":"16",
    "gn:admin2_code":"PT",
    "gn:admin3_code":"47023.0",
    "gn:asciiname":"Serretto",
    "gn:country_code":"IT",
    "gn:dem":1223,
    "gn:feature_class":"P",
    "gn:feature_code":"PPL",
    "gn:name":"Serretto",
    "gn:population":87,
    "gn:timezone":"Europe/Rome",
    "iso:country":"IT",
    "wof:name":"Serretto",
    "wof:placetype":"locality",
    "wof:population":87
},
  "geometry": {"coordinates":[10.64941,44.15474],"type":"Point"}
}