{
  "type": "Feature",
  "properties": {
    "gn:admin1_code":"12.0",
    "gn:admin2_code":"CN",
    "gn:admin3_code":"4143.0",
    "gn:asciiname":"Brasse Piccolo",
    "gn:country_code":"IT",
    "gn:dem":255,
    "gn:feature_class":"P",
    "gn:feature_code":"PPL",
    "gn:name":"Brasse Piccolo",
    "gn:population":24,
    "gn:timezone":"Europe/Rome",
    "iso:country":"IT",
    "wof:name":"Brasse Piccolo",
    "wof:placetype":"locality",
    "wof:population":24
},
  "geometry": {"coordinates":[7.51438,44.75199],"type":"Point"}
}