{
  "type": "Feature",
  "properties": {
    "gn:admin1_code":"8.0",
    "gn:admin2_code":"GE",
    "gn:admin3_code":"10014.0",
    "gn:asciiname":"Ferriera-Pontasso",
    "gn:country_code":"IT",
    "gn:dem":161,
    "gn:feature_class":"P",
    "gn:feature_code":"PPL",
    "gn:name":"Ferriera-Pontasso",
    "gn:population":664,
    "gn:timezone":"Europe/Rome",
    "iso:country":"IT",
    "wof:name":"Ferriera-Pontasso",
    "wof:placetype":"locality",
    "wof:population":664
},
  "geometry": {"coordinates":[8.87729,44.51239],"type":"Point"}
}