{
  "type": "Feature",
  "properties": {
    "gn:admin1_code":"13",
    "gn:admin2_code":"LE",
    "gn:admin3_code":"75076.0",
    "gn:asciiname":"Zona Industriale Rivola",
    "gn:country_code":"IT",
    "gn:dem":59,
    "gn:feature_class":"P",
    "gn:feature_code":"PPLL",
    "gn:name":"Zona Industriale Rivola",
    "gn:population":10,
    "gn:timezone":"Europe/Rome",
    "iso:country":"IT",
    "wof:name":"Zona Industriale Rivola",
    "wof:placetype":"locality",
    "wof:population":10
},
  "geometry": {"coordinates":[18.16804,40.2005],"type":"Point"}
}