{
  "type": "Feature",
  "properties": {
    "gn:admin1_code":"20",
    "gn:admin2_code":"BL",
    "gn:admin3_code":"25026.0",
    "gn:asciiname":"Cies",
    "gn:country_code":"IT",
    "gn:dem":472,
    "gn:feature_class":"P",
    "gn:feature_code":"PPL",
    "gn:name":"Cies",
    "gn:population":51,
    "gn:timezone":"Europe/Rome",
    "iso:country":"IT",
    "wof:name":"Cies",
    "wof:placetype":"locality",
    "wof:population":51
},
  "geometry": {"coordinates":[11.75867,46.03887],"type":"Point"}
}