{
  "type": "Feature",
  "properties": {
    "gn:admin1_code":"12",
    "gn:admin2_code":"CN",
    "gn:admin3_code":"4233.0",
    "gn:asciiname":"Tetti Gaina",
    "gn:country_code":"IT",
    "gn:dem":1063,
    "gn:feature_class":"P",
    "gn:feature_code":"PPL",
    "gn:name":"Tetti Gaina",
    "gn:population":12,
    "gn:timezone":"Europe/Rome",
    "iso:country":"IT",
    "wof:name":"Tetti Gaina",
    "wof:placetype":"locality",
    "wof:population":12
},
  "geometry": {"coordinates":[7.31424,44.23382],"type":"Point"}
}