{
  "type": "Feature",
  "properties": {
    "gn:admin1_code":"7",
    "gn:admin2_code":"RM",
    "gn:admin3_code":"58013.0",
    "gn:asciiname":"Lungolago",
    "gn:country_code":"IT",
    "gn:dem":166,
    "gn:feature_class":"P",
    "gn:feature_code":"PPL",
    "gn:name":"Lungolago",
    "gn:population":212,
    "gn:timezone":"Europe/Rome",
    "iso:country":"IT",
    "wof:name":"Lungolago",
    "wof:placetype":"locality",
    "wof:population":212
},
  "geometry": {"coordinates":[12.1794,42.11084],"type":"Point"}
}