{
  "type": "Feature",
  "properties": {
    "gn:admin1_code":"3",
    "gn:admin2_code":"CS",
    "gn:admin3_code":"78015.0",
    "gn:asciiname":"Livorni",
    "gn:country_code":"IT",
    "gn:dem":89,
    "gn:feature_class":"P",
    "gn:feature_code":"PPL",
    "gn:name":"Livorni",
    "gn:population":95,
    "gn:timezone":"Europe/Rome",
    "iso:country":"IT",
    "wof:name":"Livorni",
    "wof:placetype":"locality",
    "wof:population":95
},
  "geometry": {"coordinates":[15.86046,39.62618],"type":"Point"}
}