{
  "type": "Feature",
  "properties": {
    "gn:admin1_code":"20",
    "gn:admin2_code":"VI",
    "gn:admin3_code":"24063.0",
    "gn:asciiname":"Porra",
    "gn:country_code":"IT",
    "gn:dem":294,
    "gn:feature_class":"P",
    "gn:feature_code":"PPL",
    "gn:name":"Porra",
    "gn:population":24,
    "gn:timezone":"Europe/Rome",
    "iso:country":"IT",
    "wof:name":"Porra",
    "wof:placetype":"locality",
    "wof:population":24
},
  "geometry": {"coordinates":[11.38331,45.63208],"type":"Point"}
}