{
  "type": "Feature",
  "properties": {
    "gn:admin1_code":"4",
    "gn:admin2_code":"BN",
    "gn:admin3_code":"62054.0",
    "gn:asciiname":"Perugini II",
    "gn:country_code":"IT",
    "gn:dem":729,
    "gn:feature_class":"P",
    "gn:feature_code":"PPLL",
    "gn:name":"Perugini II",
    "gn:population":9,
    "gn:timezone":"Europe/Rome",
    "iso:country":"IT",
    "wof:name":"Perugini II",
    "wof:placetype":"locality",
    "wof:population":9
},
  "geometry": {"coordinates":[14.66072,41.30113],"type":"Point"}
}