{
  "type": "Feature",
  "properties": {
    "gn:admin1_code":"16.0",
    "gn:admin2_code":"AR",
    "gn:admin3_code":"51007.0",
    "gn:asciiname":"Faggeto",
    "gn:country_code":"IT",
    "gn:dem":1207,
    "gn:feature_class":"P",
    "gn:feature_code":"PPLL",
    "gn:name":"Faggeto",
    "gn:population":5,
    "gn:timezone":"Europe/Rome",
    "iso:country":"IT",
    "wof:name":"Faggeto",
    "wof:placetype":"locality",
    "wof:population":5
},
  "geometry": {"coordinates":[11.95344,43.61866],"type":"Point"}
}