{
  "type": "Feature",
  "properties": {
    "gn:admin1_code":"20",
    "gn:admin2_code":"VI",
    "gn:admin3_code":"24028.0",
    "gn:asciiname":"Rossetti",
    "gn:country_code":"IT",
    "gn:dem":74,
    "gn:feature_class":"P",
    "gn:feature_code":"PPL",
    "gn:name":"Rossetti",
    "gn:population":25,
    "gn:timezone":"Europe/Rome",
    "iso:country":"IT",
    "wof:name":"Rossetti",
    "wof:placetype":"locality",
    "wof:population":25
},
  "geometry": {"coordinates":[11.41461,45.59066],"type":"Point"}
}