{
  "type": "Feature",
  "properties": {
    "gn:admin1_code":"10.0",
    "gn:admin2_code":"MC",
    "gn:admin3_code":"43013.0",
    "gn:asciiname":"Filippanto'-Vallon Faggiano",
    "gn:country_code":"IT",
    "gn:dem":39,
    "gn:elevation":"39.0",
    "gn:feature_class":"P",
    "gn:feature_code":"PPL",
    "gn:name":"Filippanto'-Vallon Faggiano",
    "gn:population":61,
    "gn:timezone":"Europe/Rome",
    "iso:country":"IT",
    "wof:name":"Filippanto'-Vallon Faggiano",
    "wof:placetype":"locality",
    "wof:population":61
},
  "geometry": {"coordinates":[13.67212,43.29071],"type":"Point"}
}