{
  "type": "Feature",
  "properties": {
    "gn:admin1_code":"4",
    "gn:admin3_code":"63042.0",
    "gn:asciiname":"Masseria Castellana",
    "gn:country_code":"IT",
    "gn:dem":38,
    "gn:feature_class":"P",
    "gn:feature_code":"PPL",
    "gn:name":"Masseria Castellana",
    "gn:population":77,
    "gn:timezone":"Europe/Rome",
    "iso:country":"IT",
    "wof:name":"Masseria Castellana",
    "wof:placetype":"locality",
    "wof:population":77
},
  "geometry": {"coordinates":[14.43371,40.91228],"type":"Point"}
}