{
  "type": "Feature",
  "properties": {
    "gn:admin1_code":"10.0",
    "gn:admin2_code":"MC",
    "gn:admin3_code":"43019.0",
    "gn:asciiname":"Massa",
    "gn:country_code":"IT",
    "gn:dem":464,
    "gn:elevation":"479.0",
    "gn:feature_class":"P",
    "gn:feature_code":"PPLA3",
    "gn:name":"Massa",
    "gn:population":681,
    "gn:timezone":"Europe/Rome",
    "iso:country":"IT",
    "wof:name":"Massa",
    "wof:placetype":"locality",
    "wof:population":681
},
  "geometry": {"coordinates":[12.93142,43.18803],"type":"Point"}
}