{
  "type": "Feature",
  "properties": {
    "gn:admin1_code":"9",
    "gn:admin2_code":"BG",
    "gn:admin3_code":"16200.0",
    "gn:asciiname":"Via degli Apostoli",
    "gn:country_code":"IT",
    "gn:dem":449,
    "gn:feature_class":"P",
    "gn:feature_code":"PPL",
    "gn:name":"Via degli Apostoli",
    "gn:population":222,
    "gn:timezone":"Europe/Rome",
    "iso:country":"IT",
    "wof:name":"Via degli Apostoli",
    "wof:placetype":"locality",
    "wof:population":222
},
  "geometry": {"coordinates":[10.04141,45.78491],"type":"Point"}
}