{
  "type": "Feature",
  "properties": {
    "gn:admin1_code":"16.0",
    "gn:admin2_code":"PT",
    "gn:admin3_code":"47005.0",
    "gn:asciiname":"Nardini",
    "gn:country_code":"IT",
    "gn:dem":380,
    "gn:elevation":"384.0",
    "gn:feature_class":"P",
    "gn:feature_code":"PPL",
    "gn:name":"Nardini",
    "gn:population":18,
    "gn:timezone":"Europe/Rome",
    "iso:country":"IT",
    "name:deu_x_preferred":[
        "Nardini"
    ],
    "name:ita_x_preferred":[
        "Nardini"
    ],
    "name:rus_x_preferred":[
        "\u041d\u0430\u0440\u0434\u0438\u043d\u0438"
    ],
    "name:spa_x_preferred":[
        "Nardini"
    ],
    "wof:name":"Nardini",
    "wof:placetype":"locality",
    "wof:population":18
},
  "geometry": {"coordinates":[10.91153,43.84264],"type":"Point"}
}