{
  "type": "Feature",
  "properties": {
    "gn:admin1_code":"1",
    "gn:admin2_code":"TE",
    "gn:admin3_code":"67041.0",
    "gn:asciiname":"Villa Romita",
    "gn:country_code":"IT",
    "gn:dem":458,
    "gn:feature_class":"P",
    "gn:feature_code":"PPL",
    "gn:name":"Villa Romita",
    "gn:population":157,
    "gn:timezone":"Europe/Rome",
    "iso:country":"IT",
    "wof:name":"Villa Romita",
    "wof:placetype":"locality",
    "wof:population":157
},
  "geometry": {"coordinates":[13.69648,42.64033],"type":"Point"}
}