{
  "type": "Feature",
  "properties": {
    "gn:elevation":321,
    "gn:population":459,
    "iso:country":"IT",
    "name:bul_x_preferred":[
        "\u041c\u043e\u043d\u0442\u0438\u0433\u043b\u0438\u043e"
    ],
    "name:cat_x_preferred":[
        "Montiglio"
    ],
    "name:ceb_x_preferred":[
        "Montiglio"
    ],
    "name:ces_x_preferred":[
        "Montiglio"
    ],
    "name:dan_x_preferred":[
        "Montiglio"
    ],
    "name:eng_x_preferred":[
        "Montiglio"
    ],
    "name:eus_x_preferred":[
        "Montiglio"
    ],
    "name:fin_x_preferred":[
        "Montiglio"
    ],
    "name:fra_x_preferred":[
        "Montiglio"
    ],
    "name:ind_x_preferred":[
        "Montiglio"
    ],
    "name:ita_x_preferred":[
        "Montiglio"
    ],
    "name:nld_x_preferred":[
        "Montiglio"
    ],
    "name:nno_x_preferred":[
        "Montiglio"
    ],
    "name:nob_x_preferred":[
        "Montiglio"
    ],
    "name:oci_x_preferred":[
        "Montiglio"
    ],
    "name:pol_x_preferred":[
        "Montiglio"
    ],
    "name:por_x_preferred":[
        "Montiglio"
    ],
    "name:ron_x_preferred":[
        "Montiglio"
    ],
    "name:slk_x_preferred":[
        "Montiglio"
    ],
    "name:slv_x_preferred":[
        "Montiglio"
    ],
    "name:spa_x_preferred":[
        "Montiglio"
    ],
    "name:srp_x_preferred":[
        "Montiglio"
    ],
    "name:swe_x_preferred":[
        "Montiglio"
    ],
    "name:tgl_x_preferred":[
        "Montiglio"
    ],
    "name:tur_x_preferred":[
        "Montiglio"
    ],
    "name:war_x_preferred":[
        "Montiglio"
    ],
    "qs:a0":"Italia",
    "qs:a1":"*Asti",
    "qs:a1r":"0Piemonte",
    "qs:adm0":"Italia",
    "qs:la_lc":"*",
    "qs:level":"locality",
    "qs:loc":"Montiglio",
    "qs:loc_alt":"Montiglio",
    "qs:pop":0,
    "qs:type":"buffered point",
    "wof:lang":[
        "ita"
    ],
    "wof:name":"Montiglio",
    "wof:placetype":"locality",
    "wof:population":459
},
  "geometry": {"coordinates":[8.09802,45.06427],"type":"Point"}
}