{
  "type": "Feature",
  "properties": {
    "gn:admin1_code":"12",
    "gn:admin2_code":"TO",
    "gn:admin3_code":"1217.0",
    "gn:asciiname":"Cascina Vittoria",
    "gn:country_code":"IT",
    "gn:dem":245,
    "gn:feature_class":"P",
    "gn:feature_code":"PPL",
    "gn:name":"Cascina Vittoria",
    "gn:population":81,
    "gn:timezone":"Europe/Rome",
    "iso:country":"IT",
    "wof:name":"Cascina Vittoria",
    "wof:placetype":"locality",
    "wof:population":81
},
  "geometry": {"coordinates":[7.74465,45.26623],"type":"Point"}
}