{
  "type": "Feature",
  "properties": {
    "gn:admin1_code":"10.0",
    "gn:admin2_code":"PU",
    "gn:asciiname":"La Pieve",
    "gn:country_code":"IT",
    "gn:dem":186,
    "gn:feature_class":"P",
    "gn:feature_code":"PPL",
    "gn:name":"La Pieve",
    "gn:population":0,
    "gn:timezone":"Europe/Rome",
    "iso:country":"IT",
    "wof:name":"La Pieve",
    "wof:placetype":"locality"
},
  "geometry": {"coordinates":[12.33333,43.93333],"type":"Point"}
}