{
  "type": "Feature",
  "properties": {
    "gn:admin1_code":"1",
    "gn:admin2_code":"CH",
    "gn:admin3_code":"69075.0",
    "gn:asciiname":"Aia di Rocco",
    "gn:country_code":"IT",
    "gn:dem":510,
    "gn:feature_class":"P",
    "gn:feature_code":"PPL",
    "gn:name":"Aia di Rocco",
    "gn:population":192,
    "gn:timezone":"Europe/Rome",
    "iso:country":"IT",
    "wof:name":"Aia di Rocco",
    "wof:placetype":"locality",
    "wof:population":192
},
  "geometry": {"coordinates":[14.31517,42.059],"type":"Point"}
}