{
  "type": "Feature",
  "properties": {
    "gn:gn_country":"IT",
    "gn:gn_fcode":"PPL",
    "gn:gn_pop":0,
    "gn:population":30,
    "iso:country":"IT",
    "name:eng_x_preferred":[
        "Ginostra"
    ],
    "name:fas_x_preferred":[
        "\u062c\u06cc\u0646\u0648\u0633\u062a\u0631\u0627"
    ],
    "name:fra_x_preferred":[
        "Ginostra"
    ],
    "name:hun_x_preferred":[
        "Ginostra"
    ],
    "name:ita_x_preferred":[
        "Ginostra"
    ],
    "name:jpn_x_preferred":[
        "\u30b8\u30ce\u30b9\u30c8\u30e9"
    ],
    "name:nld_x_preferred":[
        "Ginostra"
    ],
    "name:scn_x_preferred":[
        "Ginostra"
    ],
    "name:srp_x_preferred":[
        "Ginostra"
    ],
    "qs_pg:aaroncc":"IT",
    "qs_pg:gn_country":"IT",
    "qs_pg:gn_fcode":"PPL",
    "qs_pg:gn_pop":0,
    "qs_pg:name":"Ginostra",
    "qs_pg:name_adm0":"Italia",
    "qs_pg:name_adm1":"Sicilia",
    "qs_pg:photos":1019,
    "qs_pg:photos_1k":206,
    "qs_pg:photos_9k":5,
    "qs_pg:photos_9r":7,
    "qs_pg:photos_all":1019,
    "qs_pg:photos_sr":11,
    "qs_pg:pop_sr":0,
    "qs_pg:qs_pg_placetype":"locality",
    "qs_pg:qs_pg_placetype_gp":"Town",
    "qs_pg:woe_adm0":23424853,
    "woe:adm0_id":23424853,
    "woe:name_adm0":"Italia",
    "woe:name_adm1":"Sicilia",
    "woe:placetype":"Town",
    "wof:name":"Ginostra",
    "wof:placetype":"locality",
    "wof:population":30
},
  "geometry": {"coordinates":[15.22714,38.80868],"type":"Point"}
}