{
  "type": "Feature",
  "properties": {
    "gn:admin1_code":"20",
    "gn:admin2_code":"RO",
    "gn:admin3_code":"29025.0",
    "gn:asciiname":"Fortini",
    "gn:country_code":"IT",
    "gn:dem":6,
    "gn:feature_class":"P",
    "gn:feature_code":"PPL",
    "gn:name":"Fortini",
    "gn:population":14,
    "gn:timezone":"Europe/Rome",
    "iso:country":"IT",
    "wof:name":"Fortini",
    "wof:placetype":"locality",
    "wof:population":14
},
  "geometry": {"coordinates":[11.47346,44.95249],"type":"Point"}
}