{
  "type": "Feature",
  "properties": {
    "gn:admin1_code":"9",
    "gn:admin2_code":"LO",
    "gn:admin3_code":"98020.0",
    "gn:asciiname":"Bocchi",
    "gn:country_code":"IT",
    "gn:dem":95,
    "gn:feature_class":"P",
    "gn:feature_code":"PPL",
    "gn:name":"Bocchi",
    "gn:population":158,
    "gn:timezone":"Europe/Rome",
    "iso:country":"IT",
    "wof:name":"Bocchi",
    "wof:placetype":"locality",
    "wof:population":158
},
  "geometry": {"coordinates":[9.45678,45.42785],"type":"Point"}
}