{
  "type": "Feature",
  "properties": {
    "gn:admin1_code":"20.0",
    "gn:admin2_code":"VI",
    "gn:admin3_code":"24069.0",
    "gn:asciiname":"Ponte di Mossano",
    "gn:country_code":"IT",
    "gn:dem":18,
    "gn:feature_class":"P",
    "gn:feature_code":"PPL",
    "gn:name":"Ponte di Mossano",
    "gn:population":482,
    "gn:timezone":"Europe/Rome",
    "iso:country":"IT",
    "wof:name":"Ponte di Mossano",
    "wof:placetype":"locality",
    "wof:population":482
},
  "geometry": {"coordinates":[11.58606,45.41007000000001],"type":"Point"}
}