{
  "type": "Feature",
  "properties": {
    "gn:population":11,
    "iso:country":"IT",
    "name:cat_x_preferred":[
        "Scalo Romagnano al Monte"
    ],
    "name:ceb_x_preferred":[
        "Scalo Romagnano al Monte"
    ],
    "name:ces_x_preferred":[
        "Scalo Romagnano al Monte"
    ],
    "name:dan_x_preferred":[
        "Scalo Romagnano al Monte"
    ],
    "name:eng_x_preferred":[
        "Romagnano al Monte"
    ],
    "name:eng_x_variant":[
        "Scalo Romagnano al Monte"
    ],
    "name:epo_x_preferred":[
        "Romagnano al Monte"
    ],
    "name:eus_x_preferred":[
        "Scalo Romagnano al Monte"
    ],
    "name:fin_x_preferred":[
        "Scalo Romagnano al Monte"
    ],
    "name:fra_x_preferred":[
        "Romagnano al Monte"
    ],
    "name:fra_x_variant":[
        "Scalo Romagnano al Monte"
    ],
    "name:ind_x_preferred":[
        "Scalo Romagnano al Monte"
    ],
    "name:ita_x_preferred":[
        "Romagnano al Monte"
    ],
    "name:ita_x_variant":[
        "Scalo Romagnano al Monte"
    ],
    "name:nap_x_preferred":[
        "Romagnano al Monte"
    ],
    "name:nld_x_preferred":[
        "Romagnano al Monte"
    ],
    "name:nld_x_variant":[
        "Scalo Romagnano al Monte"
    ],
    "name:nno_x_preferred":[
        "Scalo Romagnano al Monte"
    ],
    "name:nob_x_preferred":[
        "Scalo Romagnano al Monte"
    ],
    "name:oci_x_preferred":[
        "Scalo Romagnano al Monte"
    ],
    "name:pol_x_preferred":[
        "Romagnano al Monte"
    ],
    "name:pol_x_variant":[
        "Scalo Romagnano al Monte"
    ],
    "name:por_x_preferred":[
        "Romagnano al Monte"
    ],
    "name:por_x_variant":[
        "Scalo Romagnano al Monte"
    ],
    "name:ron_x_preferred":[
        "Scalo Romagnano al Monte"
    ],
    "name:slk_x_preferred":[
        "Scalo Romagnano al Monte"
    ],
    "name:slv_x_preferred":[
        "Scalo Romagnano al Monte"
    ],
    "name:spa_x_preferred":[
        "Scalo Romagnano al Monte"
    ],
    "name:srp_x_preferred":[
        "Scalo Romagnano al Monte"
    ],
    "name:swe_x_preferred":[
        "Scalo Romagnano al Monte"
    ],
    "name:tgl_x_preferred":[
        "Scalo Romagnano al Monte"
    ],
    "name:tur_x_preferred":[
        "Scalo Romagnano al Monte"
    ],
    "name:war_x_preferred":[
        "Scalo Romagnano al Monte"
    ],
    "qs:a0":"Italia",
    "qs:a1":"*Salerno",
    "qs:a1r":"0Campania",
    "qs:adm0":"Italia",
    "qs:la_lc":"*",
    "qs:level":"locality",
    "qs:loc":"Romagnano al Monte",
    "qs:loc_alt":"Romagnano al Monte",
    "qs:pop":0,
    "qs:type":"buffered point",
    "wof:lang":[
        "ita"
    ],
    "wof:name":"Romagnano al Monte",
    "wof:placetype":"locality",
    "wof:population":11
},
  "geometry": {"coordinates":[15.45694,40.628891],"type":"Point"}
}