{
  "type": "Feature",
  "properties": {
    "gn:admin1_code":"1.0",
    "gn:admin2_code":"TE",
    "gn:admin3_code":"67018.0",
    "gn:asciiname":"Cola",
    "gn:country_code":"IT",
    "gn:dem":388,
    "gn:feature_class":"P",
    "gn:feature_code":"PPL",
    "gn:name":"Cola",
    "gn:population":0,
    "gn:timezone":"Europe/Rome",
    "iso:country":"IT",
    "wof:name":"Cola",
    "wof:placetype":"locality"
},
  "geometry": {"coordinates":[13.66667,42.55],"type":"Point"}
}