{
  "type": "Feature",
  "properties": {
    "gn:admin1_code":"7",
    "gn:admin2_code":"LT",
    "gn:admin3_code":"59027.0",
    "gn:asciiname":"Piazza lunga",
    "gn:country_code":"IT",
    "gn:dem":22,
    "gn:feature_class":"P",
    "gn:feature_code":"PPL",
    "gn:name":"Piazza lunga",
    "gn:population":214,
    "gn:timezone":"Europe/Rome",
    "iso:country":"IT",
    "wof:name":"Piazza lunga",
    "wof:placetype":"locality",
    "wof:population":214
},
  "geometry": {"coordinates":[12.94123,41.54776],"type":"Point"}
}