{
  "type": "Feature",
  "properties": {
    "gn:admin1_code":"14",
    "gn:admin2_code":"OR",
    "gn:admin3_code":"95050.0",
    "gn:asciiname":"Mandriola",
    "gn:country_code":"IT",
    "gn:dem":4,
    "gn:feature_class":"P",
    "gn:feature_code":"PPL",
    "gn:name":"Mandriola",
    "gn:population":82,
    "gn:timezone":"Europe/Rome",
    "iso:country":"IT",
    "wof:name":"Mandriola",
    "wof:placetype":"locality",
    "wof:population":82
},
  "geometry": {"coordinates":[8.395,40.03288],"type":"Point"}
}