{
  "type": "Feature",
  "properties": {
    "gn:admin1_code":"20",
    "gn:admin2_code":"TV",
    "gn:admin3_code":"26030.0",
    "gn:asciiname":"Tonus",
    "gn:country_code":"IT",
    "gn:dem":291,
    "gn:feature_class":"P",
    "gn:feature_code":"PPL",
    "gn:name":"Tonus",
    "gn:population":18,
    "gn:timezone":"Europe/Rome",
    "iso:country":"IT",
    "name:ceb_x_preferred":[
        "Tonus"
    ],
    "name:deu_x_preferred":[
        "Tonus"
    ],
    "name:fra_x_preferred":[
        "Tonus"
    ],
    "wof:name":"Tonus",
    "wof:placetype":"locality",
    "wof:population":18
},
  "geometry": {"coordinates":[12.34419,46.00591],"type":"Point"}
}