{
  "type": "Feature",
  "properties": {
    "gn:admin1_code":"12",
    "gn:admin2_code":"CN",
    "gn:admin3_code":"4200.0",
    "gn:asciiname":"Luschetti",
    "gn:country_code":"IT",
    "gn:dem":601,
    "gn:feature_class":"P",
    "gn:feature_code":"PPL",
    "gn:name":"Luschetti",
    "gn:population":19,
    "gn:timezone":"Europe/Rome",
    "iso:country":"IT",
    "wof:name":"Luschetti",
    "wof:placetype":"locality",
    "wof:population":19
},
  "geometry": {"coordinates":[8.06931,44.39833],"type":"Point"}
}