{
  "type": "Feature",
  "properties": {
    "gn:admin1_code":"3",
    "gn:admin2_code":"CS",
    "gn:admin3_code":"78019.0",
    "gn:asciiname":"Telegrafo",
    "gn:country_code":"IT",
    "gn:dem":31,
    "gn:feature_class":"P",
    "gn:feature_code":"PPL",
    "gn:name":"Telegrafo",
    "gn:population":83,
    "gn:timezone":"Europe/Rome",
    "iso:country":"IT",
    "wof:name":"Telegrafo",
    "wof:placetype":"locality",
    "wof:population":83
},
  "geometry": {"coordinates":[15.88668,39.54356],"type":"Point"}
}