{
  "type": "Feature",
  "properties": {
    "gn:admin1_code":"16",
    "gn:admin2_code":"FI",
    "gn:admin3_code":"48053.0",
    "gn:asciiname":"Bagnatoio",
    "gn:country_code":"IT",
    "gn:dem":433,
    "gn:feature_class":"P",
    "gn:feature_code":"PPL",
    "gn:name":"Bagnatoio",
    "gn:population":29,
    "gn:timezone":"Europe/Rome",
    "iso:country":"IT",
    "wof:name":"Bagnatoio",
    "wof:placetype":"locality",
    "wof:population":29
},
  "geometry": {"coordinates":[11.30151,44.04365],"type":"Point"}
}