{
  "type": "Feature",
  "properties": {
    "gn:admin1_code":"10",
    "gn:admin2_code":"AP",
    "gn:admin3_code":"44064.0",
    "gn:asciiname":"Meschia",
    "gn:country_code":"IT",
    "gn:dem":766,
    "gn:feature_class":"P",
    "gn:feature_code":"PPL",
    "gn:name":"Meschia",
    "gn:population":18,
    "gn:timezone":"Europe/Rome",
    "iso:country":"IT",
    "wof:name":"Meschia",
    "wof:placetype":"locality",
    "wof:population":18
},
  "geometry": {"coordinates":[13.38858,42.85106],"type":"Point"}
}