{
  "type": "Feature",
  "properties": {
    "gn:admin1_code":"11",
    "gn:admin2_code":"IS",
    "gn:admin3_code":"94019.0",
    "gn:asciiname":"Valerio",
    "gn:country_code":"IT",
    "gn:dem":457,
    "gn:feature_class":"P",
    "gn:feature_code":"PPL",
    "gn:name":"Valerio",
    "gn:population":17,
    "gn:timezone":"Europe/Rome",
    "iso:country":"IT",
    "name:deu_x_preferred":[
        "Valerio"
    ],
    "name:ita_x_preferred":[
        "Valerio"
    ],
    "name:rus_x_preferred":[
        "\u0412\u0430\u043b\u0435\u0440\u0438\u043e"
    ],
    "name:spa_x_preferred":[
        "Valerio"
    ],
    "name:srp_x_preferred":[
        "Valerio"
    ],
    "wof:name":"Valerio",
    "wof:placetype":"locality",
    "wof:population":17
},
  "geometry": {"coordinates":[14.06076,41.54096],"type":"Point"}
}