{
  "type": "Feature",
  "properties": {
    "iso:country":"IT",
    "wof:name":"Santo Venere",
    "wof:placetype":"neighbourhood"
},
  "geometry": {"coordinates":[13.32388185618815,38.09432341217514],"type":"Point"}
}