{
  "type": "Feature",
  "properties": {
    "gn:admin1_code":"4",
    "gn:admin2_code":"SA",
    "gn:admin3_code":"65146.0",
    "gn:asciiname":"Pozzale",
    "gn:country_code":"IT",
    "gn:dem":567,
    "gn:feature_class":"P",
    "gn:feature_code":"PPL",
    "gn:name":"Pozzale",
    "gn:population":106,
    "gn:timezone":"Europe/Rome",
    "iso:country":"IT",
    "name:ceb_x_preferred":[
        "Pozzale-Case Nuove"
    ],
    "name:ita_x_preferred":[
        "Pozzale"
    ],
    "name:srp_x_preferred":[
        "\u041f\u043e\u0446\u0430\u043b\u0435-\u041a\u0430\u0437\u0435 \u041d\u0443\u043e\u0432\u0435"
    ],
    "wof:name":"Pozzale",
    "wof:placetype":"locality",
    "wof:population":106
},
  "geometry": {"coordinates":[15.49,40.38653],"type":"Point"}
}