{
  "type": "Feature",
  "properties": {
    "gn:admin1_code":"20",
    "gn:admin2_code":"BL",
    "gn:admin3_code":"25026.0",
    "gn:asciiname":"Geronemoni",
    "gn:country_code":"IT",
    "gn:dem":611,
    "gn:feature_class":"P",
    "gn:feature_code":"PPL",
    "gn:name":"Geronemoni",
    "gn:population":23,
    "gn:timezone":"Europe/Rome",
    "iso:country":"IT",
    "wof:name":"Geronemoni",
    "wof:placetype":"locality",
    "wof:population":23
},
  "geometry": {"coordinates":[11.71543,46.0392],"type":"Point"}
}