{
  "type": "Feature",
  "properties": {
    "gn:gn_country":"IT",
    "gn:gn_fcode":"PPLA3",
    "gn:gn_pop":4010,
    "gn:population":4010,
    "iso:country":"IT",
    "name:cat_x_preferred":[
        "Racines - Ratschings"
    ],
    "name:ces_x_preferred":[
        "Racines - Ratschings"
    ],
    "name:dan_x_preferred":[
        "Racines - Ratschings"
    ],
    "name:eng_x_preferred":[
        "Racines - Ratschings"
    ],
    "name:eus_x_preferred":[
        "Racines - Ratschings"
    ],
    "name:fin_x_preferred":[
        "Racines - Ratschings"
    ],
    "name:fra_x_preferred":[
        "Racines - Ratschings"
    ],
    "name:ind_x_preferred":[
        "Racines - Ratschings"
    ],
    "name:ita_x_preferred":[
        "Racines - Ratschings"
    ],
    "name:nld_x_preferred":[
        "Racines - Ratschings"
    ],
    "name:nno_x_preferred":[
        "Racines - Ratschings"
    ],
    "name:nob_x_preferred":[
        "Racines - Ratschings"
    ],
    "name:oci_x_preferred":[
        "Racines - Ratschings"
    ],
    "name:pol_x_preferred":[
        "Racines - Ratschings"
    ],
    "name:por_x_preferred":[
        "Racines - Ratschings"
    ],
    "name:ron_x_preferred":[
        "Racines - Ratschings"
    ],
    "name:slk_x_preferred":[
        "Racines - Ratschings"
    ],
    "name:slv_x_preferred":[
        "Racines - Ratschings"
    ],
    "name:spa_x_preferred":[
        "Racines - Ratschings"
    ],
    "name:srp_x_preferred":[
        "Racines - Ratschings"
    ],
    "name:swe_x_preferred":[
        "Racines - Ratschings"
    ],
    "name:tgl_x_preferred":[
        "Racines - Ratschings"
    ],
    "name:tur_x_preferred":[
        "Racines - Ratschings"
    ],
    "name:war_x_preferred":[
        "Racines - Ratschings"
    ],
    "qs_pg:aaroncc":"IT",
    "qs_pg:gn_country":"IT",
    "qs_pg:gn_fcode":"PPLA3",
    "qs_pg:gn_pop":4010,
    "qs_pg:name":"Racines - Ratschings",
    "qs_pg:photos_9r":0,
    "qs_pg:photos_sr":0,
    "qs_pg:pop_sr":4,
    "qs_pg:qs_pg_placetype":"locality",
    "wof:name":"Racines - Ratschings",
    "wof:placetype":"locality",
    "wof:population":4010
},
  "geometry": {"coordinates":[11.37827,46.88183],"type":"Point"}
}