{
  "type": "Feature",
  "properties": {
    "gn:admin1_code":"11",
    "gn:admin2_code":"IS",
    "gn:admin3_code":"94003.0",
    "gn:asciiname":"Macchia la Cerva",
    "gn:country_code":"IT",
    "gn:dem":652,
    "gn:feature_class":"P",
    "gn:feature_code":"PPL",
    "gn:name":"Macchia la Cerva",
    "gn:population":19,
    "gn:timezone":"Europe/Rome",
    "iso:country":"IT",
    "wof:name":"Macchia la Cerva",
    "wof:placetype":"locality",
    "wof:population":19
},
  "geometry": {"coordinates":[14.50991,41.71815],"type":"Point"}
}