{
  "type": "Feature",
  "properties": {
    "gn:admin1_code":"12.0",
    "gn:admin2_code":"TO",
    "gn:admin3_code":"1093.0",
    "gn:asciiname":"Airassa",
    "gn:country_code":"IT",
    "gn:dem":1190,
    "gn:feature_class":"P",
    "gn:feature_code":"PPLL",
    "gn:name":"Airassa",
    "gn:population":1,
    "gn:timezone":"Europe/Rome",
    "iso:country":"IT",
    "wof:name":"Airassa",
    "wof:placetype":"locality",
    "wof:population":1
},
  "geometry": {"coordinates":[7.25104,45.13686],"type":"Point"}
}