{
  "type": "Feature",
  "properties": {
    "gn:admin1_code":"11",
    "gn:admin2_code":"IS",
    "gn:admin3_code":"94005.0",
    "gn:asciiname":"Cese",
    "gn:country_code":"IT",
    "gn:dem":564,
    "gn:feature_class":"P",
    "gn:feature_code":"PPL",
    "gn:name":"Cese",
    "gn:population":15,
    "gn:timezone":"Europe/Rome",
    "iso:country":"IT",
    "wof:name":"Cese",
    "wof:placetype":"locality",
    "wof:population":15
},
  "geometry": {"coordinates":[14.3844,41.52739],"type":"Point"}
}