{
  "type": "Feature",
  "properties": {
    "gn:admin1_code":"15.0",
    "gn:admin2_code":"EN",
    "gn:admin3_code":"86001.0",
    "gn:asciiname":"Masseria Speciale",
    "gn:country_code":"IT",
    "gn:dem":245,
    "gn:feature_class":"P",
    "gn:feature_code":"PPL",
    "gn:name":"Masseria Speciale",
    "gn:population":0,
    "gn:timezone":"Europe/Rome",
    "iso:country":"IT",
    "wof:name":"Masseria Speciale",
    "wof:placetype":"locality"
},
  "geometry": {"coordinates":[14.61667,37.55],"type":"Point"}
}