{
  "type": "Feature",
  "properties": {
    "gn:admin1_code":"20.0",
    "gn:admin2_code":"PD",
    "gn:admin3_code":"28073.0",
    "gn:asciiname":"Canton Madonna",
    "gn:country_code":"IT",
    "gn:dem":15,
    "gn:feature_class":"P",
    "gn:feature_code":"PPL",
    "gn:name":"Canton Madonna",
    "gn:population":520,
    "gn:timezone":"Europe/Rome",
    "iso:country":"IT",
    "wof:name":"Canton Madonna",
    "wof:placetype":"locality",
    "wof:population":520
},
  "geometry": {"coordinates":[11.76581,45.42314],"type":"Point"}
}