{
  "type": "Feature",
  "properties": {
    "gn:admin1_code":"20",
    "gn:admin2_code":"PD",
    "gn:admin3_code":"28017.0",
    "gn:asciiname":"Case Rosa",
    "gn:country_code":"IT",
    "gn:dem":15,
    "gn:feature_class":"P",
    "gn:feature_code":"PPL",
    "gn:name":"Case Rosa",
    "gn:population":59,
    "gn:timezone":"Europe/Rome",
    "iso:country":"IT",
    "wof:name":"Case Rosa",
    "wof:placetype":"locality",
    "wof:population":59
},
  "geometry": {"coordinates":[11.89938,45.51689],"type":"Point"}
}