{
  "type": "Feature",
  "properties": {
    "gn:admin1_code":"6.0",
    "gn:admin2_code":"UD",
    "gn:admin3_code":"30029.0",
    "gn:asciiname":"Maranzanis",
    "gn:country_code":"IT",
    "gn:dem":629,
    "gn:elevation":"614.0",
    "gn:feature_class":"P",
    "gn:feature_code":"PPL",
    "gn:name":"Maranzanis",
    "gn:population":44,
    "gn:timezone":"Europe/Rome",
    "iso:country":"IT",
    "wof:name":"Maranzanis",
    "wof:placetype":"locality",
    "wof:population":44
},
  "geometry": {"coordinates":[12.87473,46.51517],"type":"Point"}
}