{
  "type": "Feature",
  "properties": {
    "gn:admin1_code":"6",
    "gn:admin2_code":"UD",
    "gn:admin3_code":"30110.0",
    "gn:asciiname":"Nonta",
    "gn:country_code":"IT",
    "gn:dem":443,
    "gn:feature_class":"P",
    "gn:feature_code":"PPL",
    "gn:name":"Nonta",
    "gn:population":23,
    "gn:timezone":"Europe/Rome",
    "iso:country":"IT",
    "wof:name":"Nonta",
    "wof:placetype":"locality",
    "wof:population":23
},
  "geometry": {"coordinates":[12.83891,46.39851],"type":"Point"}
}