{
  "type": "Feature",
  "properties": {
    "gn:admin1_code":"20.0",
    "gn:admin2_code":"VE",
    "gn:admin3_code":"27044.0",
    "gn:asciiname":"Cavallino",
    "gn:country_code":"IT",
    "gn:dem":1,
    "gn:feature_class":"P",
    "gn:feature_code":"PPL",
    "gn:name":"Cavallino",
    "gn:population":2881,
    "gn:timezone":"Europe/Rome",
    "iso:country":"IT",
    "wof:name":"Cavallino",
    "wof:placetype":"locality",
    "wof:population":2881
},
  "geometry": {"coordinates":[12.54855,45.47456],"type":"Point"}
}