{
  "type": "Feature",
  "properties": {
    "gn:admin1_code":"8",
    "gn:admin2_code":"SV",
    "gn:admin3_code":"9059.0",
    "gn:asciiname":"San Damiano",
    "gn:country_code":"IT",
    "gn:dem":390,
    "gn:feature_class":"P",
    "gn:feature_code":"PPL",
    "gn:name":"San Damiano",
    "gn:population":58,
    "gn:timezone":"Europe/Rome",
    "iso:country":"IT",
    "wof:name":"San Damiano",
    "wof:placetype":"locality",
    "wof:population":58
},
  "geometry": {"coordinates":[8.07151,44.01354],"type":"Point"}
}