{
  "type": "Feature",
  "properties": {
    "gn:admin1_code":"8",
    "gn:admin2_code":"SV",
    "gn:admin3_code":"9059.0",
    "gn:asciiname":"San Damiano",
    "gn:country_code":"IT",
    "gn:dem":390,
    "gn:feature_class":"P",
    "gn:feature_code":"PPL",
    "gn:name":"San Damiano",
    "gn:population":58,
    "gn:timezone":"Europe/Rome",
    "iso:country":"IT",
    "name:fas_x_preferred":[
        "\u0633\u0627\u0646 \u062f\u0627\u0645\u06cc\u0627\u0646\u0648"
    ],
    "name:fra_x_preferred":[
        "San Damiano"
    ],
    "name:ita_x_preferred":[
        "San Damiano"
    ],
    "name:jpn_x_preferred":[
        "\u30b5\u30f3\u30fb\u30c0\u30df\u30a2\u30fc\u30ce"
    ],
    "name:pms_x_preferred":[
        "San Damiano"
    ],
    "name:por_x_preferred":[
        "San Damiano"
    ],
    "name:srp_x_preferred":[
        "San Damijano"
    ],
    "wof:name":"San Damiano",
    "wof:placetype":"locality",
    "wof:population":58
},
  "geometry": {"coordinates":[8.07151,44.01354],"type":"Point"}
}