{
  "type": "Feature",
  "properties": {
    "iso:country":"IT",
    "name:cat_x_preferred":[
        "Verdeggia"
    ],
    "name:ceb_x_preferred":[
        "Verdeggia"
    ],
    "name:ces_x_preferred":[
        "Verdeggia"
    ],
    "name:dan_x_preferred":[
        "Verdeggia"
    ],
    "name:eng_x_preferred":[
        "Verdeggia"
    ],
    "name:eus_x_preferred":[
        "Verdeggia"
    ],
    "name:fin_x_preferred":[
        "Verdeggia"
    ],
    "name:fra_x_preferred":[
        "Verdeggia"
    ],
    "name:ind_x_preferred":[
        "Verdeggia"
    ],
    "name:ita_x_preferred":[
        "Verdeggia"
    ],
    "name:nld_x_preferred":[
        "Verdeggia"
    ],
    "name:nno_x_preferred":[
        "Verdeggia"
    ],
    "name:nob_x_preferred":[
        "Verdeggia"
    ],
    "name:oci_x_preferred":[
        "Verdeggia"
    ],
    "name:pol_x_preferred":[
        "Verdeggia"
    ],
    "name:por_x_preferred":[
        "Verdeggia"
    ],
    "name:ron_x_preferred":[
        "Verdeggia"
    ],
    "name:slk_x_preferred":[
        "Verdeggia"
    ],
    "name:slv_x_preferred":[
        "Verdeggia"
    ],
    "name:spa_x_preferred":[
        "Verdeggia"
    ],
    "name:srp_x_preferred":[
        "Verdeggia"
    ],
    "name:swe_x_preferred":[
        "Verdeggia"
    ],
    "name:tgl_x_preferred":[
        "Verdeggia"
    ],
    "name:tur_x_preferred":[
        "Verdeggia"
    ],
    "name:war_x_preferred":[
        "Verdeggia"
    ],
    "qs_pg:aaroncc":"IT",
    "qs_pg:name":"Verdeggia",
    "qs_pg:name_adm0":"Italia",
    "qs_pg:name_adm1":"Liguria",
    "qs_pg:photos":86,
    "qs_pg:photos_1k":17,
    "qs_pg:photos_9k":1,
    "qs_pg:photos_9r":3,
    "qs_pg:photos_all":86,
    "qs_pg:photos_sr":3,
    "qs_pg:pop_sr":0,
    "qs_pg:qs_pg_placetype":"locality",
    "qs_pg:qs_pg_placetype_gp":"Town",
    "qs_pg:woe_adm0":23424853,
    "woe:adm0_id":23424853,
    "woe:name_adm0":"Italia",
    "woe:name_adm1":"Liguria",
    "woe:placetype":"Town",
    "wof:name":"Verdeggia",
    "wof:placetype":"locality"
},
  "geometry": {"coordinates":[7.7127215,44.061436],"type":"Point"}
}