{
  "type": "Feature",
  "properties": {
    "gn:admin1_code":"18",
    "gn:admin2_code":"TR",
    "gn:admin3_code":"55032.0",
    "gn:asciiname":"Pozzo Azzuano",
    "gn:country_code":"IT",
    "gn:dem":453,
    "gn:feature_class":"P",
    "gn:feature_code":"PPL",
    "gn:name":"Pozzo Azzuano",
    "gn:population":21,
    "gn:timezone":"Europe/Rome",
    "iso:country":"IT",
    "wof:name":"Pozzo Azzuano",
    "wof:placetype":"locality",
    "wof:population":21
},
  "geometry": {"coordinates":[12.56779,42.62468],"type":"Point"}
}