{
  "type": "Feature",
  "properties": {
    "gn:admin1_code":"20.0",
    "gn:admin2_code":"VI",
    "gn:admin3_code":"24029.0",
    "gn:asciiname":"Motti",
    "gn:country_code":"IT",
    "gn:dem":367,
    "gn:feature_class":"P",
    "gn:feature_code":"PPL",
    "gn:name":"Motti",
    "gn:population":15,
    "gn:timezone":"Europe/Rome",
    "iso:country":"IT",
    "wof:name":"Motti",
    "wof:placetype":"locality",
    "wof:population":15
},
  "geometry": {"coordinates":[11.26063,45.54238],"type":"Point"}
}