{
  "type": "Feature",
  "properties": {
    "gn:admin1_code":"16",
    "gn:admin2_code":"PT",
    "gn:admin3_code":"47006.0",
    "gn:asciiname":"Luacchi",
    "gn:country_code":"IT",
    "gn:dem":24,
    "gn:feature_class":"P",
    "gn:feature_code":"PPL",
    "gn:name":"Luacchi",
    "gn:population":26,
    "gn:timezone":"Europe/Rome",
    "iso:country":"IT",
    "wof:name":"Luacchi",
    "wof:placetype":"locality",
    "wof:population":26
},
  "geometry": {"coordinates":[10.85933,43.82041],"type":"Point"}
}