{
  "type": "Feature",
  "properties": {
    "gn:admin1_code":"20.0",
    "gn:admin2_code":"TV",
    "gn:admin3_code":"26074.0",
    "gn:asciiname":"Cornadella",
    "gn:country_code":"IT",
    "gn:dem":25,
    "gn:feature_class":"P",
    "gn:feature_code":"PPL",
    "gn:name":"Cornadella",
    "gn:population":24,
    "gn:timezone":"Europe/Rome",
    "iso:country":"IT",
    "wof:name":"Cornadella",
    "wof:placetype":"locality",
    "wof:population":24
},
  "geometry": {"coordinates":[12.37579,45.77762],"type":"Point"}
}