{
  "type": "Feature",
  "properties": {
    "gn:admin1_code":"4",
    "gn:admin2_code":"CE",
    "gn:admin3_code":"61102.0",
    "gn:asciiname":"La Crocella",
    "gn:country_code":"IT",
    "gn:dem":17,
    "gn:feature_class":"P",
    "gn:feature_code":"PPL",
    "gn:name":"La Crocella",
    "gn:population":22,
    "gn:timezone":"Europe/Rome",
    "iso:country":"IT",
    "wof:name":"La Crocella",
    "wof:placetype":"locality",
    "wof:population":22
},
  "geometry": {"coordinates":[13.84627,41.21419],"type":"Point"}
}