{
  "type": "Feature",
  "properties": {
    "gn:admin1_code":"8",
    "gn:admin2_code":"IM",
    "gn:admin3_code":"8055.0",
    "gn:asciiname":"Casa Serena",
    "gn:country_code":"IT",
    "gn:dem":210,
    "gn:feature_class":"P",
    "gn:feature_code":"PPL",
    "gn:name":"Casa Serena",
    "gn:population":168,
    "gn:timezone":"Europe/Rome",
    "iso:country":"IT",
    "wof:name":"Casa Serena",
    "wof:placetype":"locality",
    "wof:population":168
},
  "geometry": {"coordinates":[7.80911,43.83361],"type":"Point"}
}