{
  "type": "Feature",
  "properties": {
    "gn:admin1_code":"18.0",
    "gn:admin2_code":"TR",
    "gn:admin3_code":"55005.0",
    "gn:asciiname":"Buonacquisto",
    "gn:cc2":"IT",
    "gn:country_code":"IT",
    "gn:dem":682,
    "gn:elevation":"692.0",
    "gn:feature_class":"P",
    "gn:feature_code":"PPL",
    "gn:name":"Buonacquisto",
    "gn:population":221,
    "gn:timezone":"Europe/Rome",
    "iso:country":"IT",
    "name:und_x_variant":[
        "Bonacquisto"
    ],
    "wof:name":"Buonacquisto",
    "wof:placetype":"locality",
    "wof:population":221
},
  "geometry": {"coordinates":[12.80858,42.54761],"type":"Point"}
}