{
  "type": "Feature",
  "properties": {
    "gn:admin1_code":"20.0",
    "gn:admin2_code":"VI",
    "gn:admin3_code":"24080.0",
    "gn:asciiname":"Zona Artigianale Zanchi",
    "gn:country_code":"IT",
    "gn:dem":439,
    "gn:feature_class":"P",
    "gn:feature_code":"PPLL",
    "gn:name":"Zona Artigianale Zanchi",
    "gn:population":5,
    "gn:timezone":"Europe/Rome",
    "iso:country":"IT",
    "wof:name":"Zona Artigianale Zanchi",
    "wof:placetype":"locality",
    "wof:population":5
},
  "geometry": {"coordinates":[11.30069,45.80767],"type":"Point"}
}