{
  "type": "Feature",
  "properties": {
    "gn:admin1_code":"14.0",
    "gn:admin2_code":"SU",
    "gn:admin3_code":"111066.0",
    "gn:asciiname":"San Priamo",
    "gn:cc2":"IT",
    "gn:country_code":"IT",
    "gn:dem":14,
    "gn:elevation":"9.0",
    "gn:feature_class":"P",
    "gn:feature_code":"PPL",
    "gn:name":"San Priamo",
    "gn:population":110,
    "gn:timezone":"Europe/Rome",
    "iso:country":"IT",
    "name:und_x_variant":[
        "Villaggio Giuriati",
        "San Priamo"
    ],
    "wof:name":"San Priamo",
    "wof:placetype":"locality",
    "wof:population":110
},
  "geometry": {"coordinates":[9.56148,39.35875],"type":"Point"}
}