{
  "type": "Feature",
  "properties": {
    "gn:admin1_code":"16",
    "gn:admin2_code":"MS",
    "gn:admin3_code":"45007.0",
    "gn:asciiname":"Casetta",
    "gn:country_code":"IT",
    "gn:dem":186,
    "gn:feature_class":"P",
    "gn:feature_code":"PPL",
    "gn:name":"Casetta",
    "gn:population":47,
    "gn:timezone":"Europe/Rome",
    "iso:country":"IT",
    "wof:name":"Casetta",
    "wof:placetype":"locality",
    "wof:population":47
},
  "geometry": {"coordinates":[10.12409,44.1979],"type":"Point"}
}