{
  "type": "Feature",
  "properties": {
    "gn:admin1_code":"1.0",
    "gn:admin2_code":"CH",
    "gn:admin3_code":"69099.0",
    "gn:asciiname":"Sant'Onofrio",
    "gn:country_code":"IT",
    "gn:dem":171,
    "gn:feature_class":"P",
    "gn:feature_code":"PPL",
    "gn:name":"Sant'Onofrio",
    "gn:population":360,
    "gn:timezone":"Europe/Rome",
    "iso:country":"IT",
    "wof:name":"Sant'Onofrio",
    "wof:placetype":"locality",
    "wof:population":360
},
  "geometry": {"coordinates":[14.69691,42.11118],"type":"Point"}
}