{
  "type": "Feature",
  "properties": {
    "gn:admin1_code":"9",
    "gn:admin2_code":"MB",
    "gn:admin3_code":"108009.0",
    "gn:asciiname":"San Giorgio",
    "gn:country_code":"IT",
    "gn:dem":176,
    "gn:feature_class":"P",
    "gn:feature_code":"PPL",
    "gn:name":"San Giorgio",
    "gn:population":339,
    "gn:timezone":"Europe/Rome",
    "iso:country":"IT",
    "wof:name":"San Giorgio",
    "wof:placetype":"locality",
    "wof:population":339
},
  "geometry": {"coordinates":[9.29624,45.61464],"type":"Point"}
}