{
  "type": "Feature",
  "properties": {
    "gn:admin1_code":"7",
    "gn:admin2_code":"FR",
    "gn:admin3_code":"60085.0",
    "gn:asciiname":"Santa Maria Amaseno",
    "gn:country_code":"IT",
    "gn:dem":546,
    "gn:feature_class":"P",
    "gn:feature_code":"PPL",
    "gn:name":"Santa Maria Amaseno",
    "gn:population":150,
    "gn:timezone":"Europe/Rome",
    "iso:country":"IT",
    "wof:name":"Santa Maria Amaseno",
    "wof:placetype":"locality",
    "wof:population":150
},
  "geometry": {"coordinates":[13.43492,41.73195],"type":"Point"}
}