{
  "type": "Feature",
  "properties": {
    "gn:admin1_code":"13",
    "gn:admin2_code":"BR",
    "gn:admin3_code":"74005.0",
    "gn:asciiname":"Colapriore",
    "gn:country_code":"IT",
    "gn:dem":333,
    "gn:feature_class":"P",
    "gn:feature_code":"PPL",
    "gn:name":"Colapriore",
    "gn:population":28,
    "gn:timezone":"Europe/Rome",
    "iso:country":"IT",
    "wof:name":"Colapriore",
    "wof:placetype":"locality",
    "wof:population":28
},
  "geometry": {"coordinates":[17.42298,40.7573],"type":"Point"}
}