{
  "type": "Feature",
  "properties": {
    "gn:admin1_code":"8.0",
    "gn:admin2_code":"GE",
    "gn:admin3_code":"10053.0",
    "gn:asciiname":"Costa di Cichero",
    "gn:country_code":"IT",
    "gn:dem":438,
    "gn:feature_class":"P",
    "gn:feature_code":"PPL",
    "gn:name":"Costa di Cichero",
    "gn:population":15,
    "gn:timezone":"Europe/Rome",
    "iso:country":"IT",
    "wof:name":"Costa di Cichero",
    "wof:placetype":"locality",
    "wof:population":15
},
  "geometry": {"coordinates":[9.33004,44.41341],"type":"Point"}
}