{
  "type": "Feature",
  "properties": {
    "gn:elevation":662,
    "gn:population":658,
    "iso:country":"IT",
    "name:arm_x_preferred":[
        "\u0533\u0561\u0580\u0571\u0565\u0576\u0578"
    ],
    "name:baq_x_preferred":[
        "Garzeno"
    ],
    "name:bel_x_preferred":[
        "\u0413\u0430\u0440\u0446\u044d\u043d\u0430"
    ],
    "name:cat_x_preferred":[
        "Garzeno"
    ],
    "name:chi_x_preferred":[
        "\u52a0\u5c14\u6cfd\u8bfa"
    ],
    "name:deu_x_preferred":[
        "Garzeno"
    ],
    "name:dut_x_preferred":[
        "Garzeno"
    ],
    "name:eng_x_preferred":[
        "Garzeno"
    ],
    "name:epo_x_preferred":[
        "Garzeno"
    ],
    "name:eus_x_preferred":[
        "Garzeno"
    ],
    "name:fra_x_preferred":[
        "Garzeno"
    ],
    "name:fre_x_preferred":[
        "Garzeno"
    ],
    "name:ger_x_preferred":[
        "Garzeno"
    ],
    "name:hbs_x_preferred":[
        "Garzeno"
    ],
    "name:hun_x_preferred":[
        "Garzeno"
    ],
    "name:hye_x_preferred":[
        "\u0533\u0561\u0580\u0571\u0565\u0576\u0578"
    ],
    "name:ita_x_preferred":[
        "Garzeno"
    ],
    "name:jpn_x_preferred":[
        "\u30ac\u30eb\u30c4\u30a7\u30fc\u30ce"
    ],
    "name:kaz_x_preferred":[
        "\u0413\u0430\u0440\u0446\u0435\u043d\u043e"
    ],
    "name:lat_x_preferred":[
        "Garzenum"
    ],
    "name:lmo_x_preferred":[
        "Garzee"
    ],
    "name:may_x_preferred":[
        "Garzeno"
    ],
    "name:msa_x_preferred":[
        "Garzeno"
    ],
    "name:nap_x_preferred":[
        "Garzeno"
    ],
    "name:nld_x_preferred":[
        "Garzeno"
    ],
    "name:oci_x_preferred":[
        "Garzeno"
    ],
    "name:pms_x_preferred":[
        "Garzeno"
    ],
    "name:pol_x_preferred":[
        "Garzeno"
    ],
    "name:por_x_preferred":[
        "Garzeno"
    ],
    "name:ron_x_preferred":[
        "Garzeno"
    ],
    "name:rum_x_preferred":[
        "Garzeno"
    ],
    "name:rus_x_preferred":[
        "\u0413\u0430\u0440\u0434\u0437\u0435\u043d\u043e"
    ],
    "name:scn_x_preferred":[
        "Garzeno"
    ],
    "name:spa_x_preferred":[
        "Garzeno"
    ],
    "name:srp_x_preferred":[
        "\u0413\u0430\u0440\u0446\u0435\u043d\u043e"
    ],
    "name:tgl_x_preferred":[
        "Garzeno"
    ],
    "name:ukr_x_preferred":[
        "\u0413\u0430\u0440\u0446\u0435\u043d\u043e"
    ],
    "name:uzb_x_preferred":[
        "Garzeno"
    ],
    "name:vie_x_preferred":[
        "Garzeno"
    ],
    "name:vol_x_preferred":[
        "Garzeno"
    ],
    "name:war_x_preferred":[
        "Garzeno"
    ],
    "name:zho_x_preferred":[
        "\u52a0\u5c14\u6cfd\u8bfa"
    ],
    "qs:a0":"Italia",
    "qs:a1":"*Como",
    "qs:a1r":"0Lombardia",
    "qs:adm0":"Italia",
    "qs:la_lc":"*",
    "qs:level":"locality",
    "qs:loc":"Garzeno",
    "qs:loc_alt":"Garzeno",
    "qs:pop":0,
    "qs:type":"buffered point",
    "wd:wordcount":89,
    "wof:lang":[
        "ita"
    ],
    "wof:name":"Garzeno",
    "wof:placetype":"locality",
    "wof:population":658
},
  "geometry": {"coordinates":[9.24822,46.134041],"type":"Point"}
}