{
  "type": "Feature",
  "properties": {
    "gn:admin1_code":"8",
    "gn:admin2_code":"SP",
    "gn:admin3_code":"11009.0",
    "gn:asciiname":"Pera",
    "gn:country_code":"IT",
    "gn:dem":579,
    "gn:feature_class":"P",
    "gn:feature_code":"PPL",
    "gn:name":"Pera",
    "gn:population":14,
    "gn:timezone":"Europe/Rome",
    "iso:country":"IT",
    "name:bul_x_preferred":[
        "\u041f\u0435\u0440\u0430"
    ],
    "name:cat_x_preferred":[
        "Pera"
    ],
    "name:ceb_x_preferred":[
        "Pera"
    ],
    "name:deu_x_preferred":[
        "Pera"
    ],
    "name:fra_x_preferred":[
        "Pera"
    ],
    "name:ita_x_preferred":[
        "Pera"
    ],
    "name:nld_x_preferred":[
        "Pera"
    ],
    "name:por_x_preferred":[
        "Pera"
    ],
    "name:rus_x_preferred":[
        "\u041f\u0435\u0440\u0430"
    ],
    "name:spa_x_preferred":[
        "Pera"
    ],
    "name:srp_x_preferred":[
        "Pera"
    ],
    "name:swa_x_preferred":[
        "Pera"
    ],
    "name:swe_x_preferred":[
        "Pera"
    ],
    "name:ukr_x_preferred":[
        "\u041f\u0435\u0440\u0430"
    ],
    "wof:name":"Pera",
    "wof:placetype":"locality",
    "wof:population":14
},
  "geometry": {"coordinates":[9.58258,44.307],"type":"Point"}
}