{
  "type": "Feature",
  "properties": {
    "gn:admin1_code":"9.0",
    "gn:admin2_code":"LC",
    "gn:admin3_code":"97041.0",
    "gn:asciiname":"Monte Lavade",
    "gn:country_code":"IT",
    "gn:dem":1320,
    "gn:feature_class":"P",
    "gn:feature_code":"PPLL",
    "gn:name":"Monte Lavad\u00e8",
    "gn:population":0,
    "gn:timezone":"Europe/Rome",
    "iso:country":"IT",
    "name:und_x_variant":[
        "Monte Lavad\u00e8"
    ],
    "wof:name":"Monte Lavade",
    "wof:placetype":"locality"
},
  "geometry": {"coordinates":[9.36655,46.0915],"type":"Point"}
}