{
  "type": "Feature",
  "properties": {
    "gn:admin1_code":"20.0",
    "gn:admin2_code":"PD",
    "gn:admin3_code":"28085.0",
    "gn:asciiname":"Brentasecca-Sabbioncello",
    "gn:country_code":"IT",
    "gn:dem":6,
    "gn:feature_class":"P",
    "gn:feature_code":"PPL",
    "gn:name":"Brentasecca-Sabbioncello",
    "gn:population":489,
    "gn:timezone":"Europe/Rome",
    "iso:country":"IT",
    "wof:name":"Brentasecca-Sabbioncello",
    "wof:placetype":"locality",
    "wof:population":489
},
  "geometry": {"coordinates":[11.98991,45.37616],"type":"Point"}
}