{
  "type": "Feature",
  "properties": {
    "gn:admin1_code":"12",
    "gn:admin2_code":"AL",
    "gn:admin3_code":"6022.0",
    "gn:asciiname":"Ponassi",
    "gn:country_code":"IT",
    "gn:dem":295,
    "gn:feature_class":"P",
    "gn:feature_code":"PPL",
    "gn:name":"Ponassi",
    "gn:population":11,
    "gn:timezone":"Europe/Rome",
    "iso:country":"IT",
    "wof:name":"Ponassi",
    "wof:placetype":"locality",
    "wof:population":11
},
  "geometry": {"coordinates":[8.76573,44.65863],"type":"Point"}
}