{
  "type": "Feature",
  "properties": {
    "gn:admin1_code":"10",
    "gn:admin2_code":"PU",
    "gn:admin3_code":"41043.0",
    "gn:asciiname":"Pian dell'Abate",
    "gn:country_code":"IT",
    "gn:dem":466,
    "gn:feature_class":"P",
    "gn:feature_code":"PPL",
    "gn:name":"Pian dell'Abate",
    "gn:population":11,
    "gn:timezone":"Europe/Rome",
    "iso:country":"IT",
    "wof:name":"Pian dell'Abate",
    "wof:placetype":"locality",
    "wof:population":11
},
  "geometry": {"coordinates":[12.77078,43.55737],"type":"Point"}
}