{
  "type": "Feature",
  "properties": {
    "gn:admin1_code":"5",
    "gn:admin2_code":"PR",
    "gn:admin3_code":"34039.0",
    "gn:asciiname":"Case Ballana",
    "gn:country_code":"IT",
    "gn:dem":773,
    "gn:feature_class":"P",
    "gn:feature_code":"PPLL",
    "gn:name":"Case Ballana",
    "gn:population":10,
    "gn:timezone":"Europe/Rome",
    "iso:country":"IT",
    "wof:name":"Case Ballana",
    "wof:placetype":"locality",
    "wof:population":10
},
  "geometry": {"coordinates":[10.1578,44.51024],"type":"Point"}
}