{
  "type": "Feature",
  "properties": {
    "gn:admin1_code":"12",
    "gn:admin2_code":"CN",
    "gn:admin3_code":"4237.0",
    "gn:asciiname":"Raffana",
    "gn:country_code":"IT",
    "gn:dem":548,
    "gn:feature_class":"P",
    "gn:feature_code":"PPL",
    "gn:name":"Raffana",
    "gn:population":13,
    "gn:timezone":"Europe/Rome",
    "iso:country":"IT",
    "wof:name":"Raffana",
    "wof:placetype":"locality",
    "wof:population":13
},
  "geometry": {"coordinates":[7.41007,44.55885],"type":"Point"}
}