{
  "type": "Feature",
  "properties": {
    "gn:admin1_code":"5.0",
    "gn:admin2_code":"FE",
    "gn:admin3_code":"38028.0",
    "gn:asciiname":"Area Indust. Ceramica Sant'Agostino",
    "gn:country_code":"IT",
    "gn:dem":12,
    "gn:feature_class":"P",
    "gn:feature_code":"PPL",
    "gn:name":"Area Indust. Ceramica Sant'Agostino",
    "gn:population":25,
    "gn:timezone":"Europe/Rome",
    "iso:country":"IT",
    "wof:name":"Area Indust. Ceramica Sant'Agostino",
    "wof:placetype":"locality",
    "wof:population":25
},
  "geometry": {"coordinates":[11.37121,44.79051],"type":"Point"}
}