{
  "type": "Feature",
  "properties": {
    "gn:admin1_code":"16",
    "gn:admin2_code":"LU",
    "gn:admin3_code":"46009.0",
    "gn:asciiname":"Croce-Stazzana",
    "gn:country_code":"IT",
    "gn:dem":884,
    "gn:feature_class":"P",
    "gn:feature_code":"PPL",
    "gn:name":"Croce-Stazzana",
    "gn:population":62,
    "gn:timezone":"Europe/Rome",
    "iso:country":"IT",
    "wof:name":"Croce-Stazzana",
    "wof:placetype":"locality",
    "wof:population":62
},
  "geometry": {"coordinates":[10.36151,44.10437],"type":"Point"}
}