{
  "type": "Feature",
  "properties": {
    "gn:admin1_code":"10",
    "gn:admin2_code":"AN",
    "gn:admin3_code":"42017.0",
    "gn:asciiname":"Grotte-Sotto le Noci",
    "gn:country_code":"IT",
    "gn:dem":400,
    "gn:feature_class":"P",
    "gn:feature_code":"PPL",
    "gn:name":"Grotte-Sotto le Noci",
    "gn:population":83,
    "gn:timezone":"Europe/Rome",
    "iso:country":"IT",
    "wof:name":"Grotte-Sotto le Noci",
    "wof:placetype":"locality",
    "wof:population":83
},
  "geometry": {"coordinates":[13.0276,43.39689],"type":"Point"}
}