{
  "type": "Feature",
  "properties": {
    "iso:country":"IT",
    "wof:name":"Conca del Naviglio",
    "wof:placetype":"neighbourhood"
},
  "geometry": {"coordinates":[9.17127847318923,45.46125381360667],"type":"Point"}
}