{
  "type": "Feature",
  "properties": {
    "gn:admin1_code":"9.0",
    "gn:admin2_code":"BS",
    "gn:admin3_code":"17181.0",
    "gn:asciiname":"Val Malga",
    "gn:country_code":"IT",
    "gn:dem":1150,
    "gn:feature_class":"P",
    "gn:feature_code":"PPLL",
    "gn:name":"Val Malga",
    "gn:population":0,
    "gn:timezone":"Europe/Rome",
    "iso:country":"IT",
    "wof:name":"Val Malga",
    "wof:placetype":"locality"
},
  "geometry": {"coordinates":[10.37979,46.13635],"type":"Point"}
}