{
  "type": "Feature",
  "properties": {
    "gn:admin1_code":"4.0",
    "gn:admin2_code":"AV",
    "gn:admin3_code":"64008.0",
    "gn:asciiname":"Ospedale Maffucci",
    "gn:country_code":"IT",
    "gn:dem":441,
    "gn:feature_class":"P",
    "gn:feature_code":"PPLL",
    "gn:name":"Ospedale Maffucci",
    "gn:population":0,
    "gn:timezone":"Europe/Rome",
    "iso:country":"IT",
    "wof:name":"Ospedale Maffucci",
    "wof:placetype":"locality"
},
  "geometry": {"coordinates":[14.77187,40.92321],"type":"Point"}
}