{
  "type": "Feature",
  "properties": {
    "gn:admin1_code":"20",
    "gn:admin2_code":"PD",
    "gn:admin3_code":"28105.0",
    "gn:asciiname":"Trattoria Alla Stella",
    "gn:country_code":"IT",
    "gn:dem":22,
    "gn:feature_class":"P",
    "gn:feature_code":"PPL",
    "gn:name":"Trattoria Alla Stella",
    "gn:population":68,
    "gn:timezone":"Europe/Rome",
    "iso:country":"IT",
    "wof:name":"Trattoria Alla Stella",
    "wof:placetype":"locality",
    "wof:population":68
},
  "geometry": {"coordinates":[11.64162,45.34825],"type":"Point"}
}