{
  "type": "Feature",
  "properties": {
    "gn:admin1_code":"20",
    "gn:admin2_code":"VR",
    "gn:admin3_code":"23042.0",
    "gn:asciiname":"Progni",
    "gn:country_code":"IT",
    "gn:dem":77,
    "gn:feature_class":"P",
    "gn:feature_code":"PPL",
    "gn:name":"Progni",
    "gn:population":54,
    "gn:timezone":"Europe/Rome",
    "iso:country":"IT",
    "wof:name":"Progni",
    "wof:placetype":"locality",
    "wof:population":54
},
  "geometry": {"coordinates":[11.14351,45.44364],"type":"Point"}
}