{
  "type": "Feature",
  "properties": {
    "gn:admin1_code":"16.0",
    "gn:admin2_code":"GR",
    "gn:admin3_code":"53003.0",
    "gn:asciiname":"Centro L",
    "gn:country_code":"IT",
    "gn:dem":16,
    "gn:feature_class":"P",
    "gn:feature_code":"PPL",
    "gn:name":"Centro L",
    "gn:population":39,
    "gn:timezone":"Europe/Rome",
    "iso:country":"IT",
    "wof:name":"Centro L",
    "wof:placetype":"locality",
    "wof:population":39
},
  "geometry": {"coordinates":[11.45072,42.4029],"type":"Point"}
}