{
  "type": "Feature",
  "properties": {
    "gn:admin1_code":"3",
    "gn:admin2_code":"CS",
    "gn:admin3_code":"78012.0",
    "gn:asciiname":"Quaresima",
    "gn:country_code":"IT",
    "gn:dem":1307,
    "gn:feature_class":"P",
    "gn:feature_code":"PPL",
    "gn:name":"Quaresima",
    "gn:population":20,
    "gn:timezone":"Europe/Rome",
    "iso:country":"IT",
    "wof:name":"Quaresima",
    "wof:placetype":"locality",
    "wof:population":20
},
  "geometry": {"coordinates":[16.44993,39.21522],"type":"Point"}
}