{
  "type": "Feature",
  "properties": {
    "gn:admin1_code":"19",
    "gn:admin2_code":"AO",
    "gn:admin3_code":"7064.0",
    "gn:asciiname":"Ronc",
    "gn:country_code":"IT",
    "gn:dem":1731,
    "gn:feature_class":"P",
    "gn:feature_code":"PPL",
    "gn:name":"Ronc",
    "gn:population":15,
    "gn:timezone":"Europe/Rome",
    "iso:country":"IT",
    "wof:name":"Ronc",
    "wof:placetype":"locality",
    "wof:population":15
},
  "geometry": {"coordinates":[7.16882,45.82292],"type":"Point"}
}