{
  "type": "Feature",
  "properties": {
    "gn:admin1_code":"5",
    "gn:admin2_code":"MO",
    "gn:admin3_code":"36023.0",
    "gn:asciiname":"Casa Zuccoli",
    "gn:country_code":"IT",
    "gn:dem":31,
    "gn:feature_class":"P",
    "gn:feature_code":"PPL",
    "gn:name":"Casa Zuccoli",
    "gn:population":25,
    "gn:timezone":"Europe/Rome",
    "iso:country":"IT",
    "wof:name":"Casa Zuccoli",
    "wof:placetype":"locality",
    "wof:population":25
},
  "geometry": {"coordinates":[10.9492,44.70008],"type":"Point"}
}