{
  "type": "Feature",
  "properties": {
    "gn:admin1_code":"15",
    "gn:admin2_code":"CT",
    "gn:admin3_code":"87057.0",
    "gn:asciiname":"Zirilli",
    "gn:country_code":"IT",
    "gn:dem":748,
    "gn:feature_class":"P",
    "gn:feature_code":"PPL",
    "gn:name":"Zirilli",
    "gn:population":97,
    "gn:timezone":"Europe/Rome",
    "iso:country":"IT",
    "wof:name":"Zirilli",
    "wof:placetype":"locality",
    "wof:population":97
},
  "geometry": {"coordinates":[14.83222,37.86592],"type":"Point"}
}