{
  "type": "Feature",
  "properties": {
    "gn:admin1_code":"1",
    "gn:admin2_code":"CH",
    "gn:admin3_code":"69027.0",
    "gn:asciiname":"Casino Vezzani",
    "gn:country_code":"IT",
    "gn:dem":173,
    "gn:feature_class":"P",
    "gn:feature_code":"PPL",
    "gn:name":"Casino Vezzani",
    "gn:population":101,
    "gn:timezone":"Europe/Rome",
    "iso:country":"IT",
    "wof:name":"Casino Vezzani",
    "wof:placetype":"locality",
    "wof:population":101
},
  "geometry": {"coordinates":[14.34303,42.31703],"type":"Point"}
}