{
  "type": "Feature",
  "properties": {
    "gn:admin1_code":"20",
    "gn:admin2_code":"VR",
    "gn:admin3_code":"23067.0",
    "gn:asciiname":"Vazzi",
    "gn:country_code":"IT",
    "gn:dem":915,
    "gn:feature_class":"P",
    "gn:feature_code":"PPL",
    "gn:name":"Vazzi",
    "gn:population":25,
    "gn:timezone":"Europe/Rome",
    "iso:country":"IT",
    "wof:name":"Vazzi",
    "wof:placetype":"locality",
    "wof:population":25
},
  "geometry": {"coordinates":[11.08467,45.58854],"type":"Point"}
}