{
  "type": "Feature",
  "properties": {
    "gn:admin1_code":"5",
    "gn:admin2_code":"PC",
    "gn:admin3_code":"33028.0",
    "gn:asciiname":"Perotti",
    "gn:country_code":"IT",
    "gn:dem":660,
    "gn:feature_class":"P",
    "gn:feature_code":"PPL",
    "gn:name":"Perotti",
    "gn:population":16,
    "gn:timezone":"Europe/Rome",
    "iso:country":"IT",
    "wof:name":"Perotti",
    "wof:placetype":"locality",
    "wof:population":16
},
  "geometry": {"coordinates":[9.73591,44.70181],"type":"Point"}
}