{
  "type": "Feature",
  "properties": {
    "iso:country":"IT",
    "wof:name":"Politeama",
    "wof:placetype":"neighbourhood"
},
  "geometry": {"coordinates":[13.35414270325642,38.12610825637104],"type":"Point"}
}