{
  "type": "Feature",
  "properties": {
    "gn:admin1_code":"16",
    "gn:admin2_code":"MS",
    "gn:admin3_code":"45007.0",
    "gn:asciiname":"Folegnano",
    "gn:country_code":"IT",
    "gn:dem":260,
    "gn:feature_class":"P",
    "gn:feature_code":"PPL",
    "gn:name":"Folegnano",
    "gn:population":55,
    "gn:timezone":"Europe/Rome",
    "iso:country":"IT",
    "wof:name":"Folegnano",
    "wof:placetype":"locality",
    "wof:population":55
},
  "geometry": {"coordinates":[10.12098,44.18247],"type":"Point"}
}