{
  "type": "Feature",
  "properties": {
    "gn:admin1_code":"5",
    "gn:admin2_code":"BO",
    "gn:admin3_code":"37022.0",
    "gn:asciiname":"Bagucci",
    "gn:country_code":"IT",
    "gn:dem":832,
    "gn:feature_class":"P",
    "gn:feature_code":"PPL",
    "gn:name":"Bagucci",
    "gn:population":26,
    "gn:timezone":"Europe/Rome",
    "iso:country":"IT",
    "wof:name":"Bagucci",
    "wof:placetype":"locality",
    "wof:population":26
},
  "geometry": {"coordinates":[11.16313,44.12343],"type":"Point"}
}