{
  "type": "Feature",
  "properties": {
    "gn:admin1_code":"8.0",
    "gn:admin2_code":"GE",
    "gn:admin3_code":"10059.0",
    "gn:asciiname":"Santa Margherita di Fossalupara",
    "gn:country_code":"IT",
    "gn:dem":35,
    "gn:feature_class":"P",
    "gn:feature_code":"PPL",
    "gn:name":"Santa Margherita di Fossalupara",
    "gn:population":0,
    "gn:timezone":"Europe/Rome",
    "iso:country":"IT",
    "wof:name":"Santa Margherita di Fossalupara",
    "wof:placetype":"locality"
},
  "geometry": {"coordinates":[9.42219,44.2765],"type":"Point"}
}