{
  "type": "Feature",
  "properties": {
    "gn:admin1_code":"19.0",
    "gn:admin2_code":"AO",
    "gn:admin3_code":"7031.0",
    "gn:asciiname":"La Cerise",
    "gn:country_code":"IT",
    "gn:dem":1467,
    "gn:feature_class":"P",
    "gn:feature_code":"PPL",
    "gn:name":"La Cerise",
    "gn:population":28,
    "gn:timezone":"Europe/Rome",
    "iso:country":"IT",
    "wof:name":"La Cerise",
    "wof:placetype":"locality",
    "wof:population":28
},
  "geometry": {"coordinates":[7.30696,45.69851],"type":"Point"}
}