{
  "type": "Feature",
  "properties": {
    "gn:admin1_code":"5",
    "gn:admin2_code":"FC",
    "gn:admin3_code":"40001.0",
    "gn:asciiname":"Ensini",
    "gn:country_code":"IT",
    "gn:dem":593,
    "gn:feature_class":"P",
    "gn:feature_code":"PPL",
    "gn:name":"Ensini",
    "gn:population":13,
    "gn:timezone":"Europe/Rome",
    "iso:country":"IT",
    "wof:name":"Ensini",
    "wof:placetype":"locality",
    "wof:population":13
},
  "geometry": {"coordinates":[12.00061,43.85869],"type":"Point"}
}