{
  "type": "Feature",
  "properties": {
    "gn:admin1_code":"12",
    "gn:admin2_code":"CN",
    "gn:admin3_code":"4205.0",
    "gn:asciiname":"Para",
    "gn:country_code":"IT",
    "gn:dem":1231,
    "gn:feature_class":"P",
    "gn:feature_code":"PPLL",
    "gn:name":"Para",
    "gn:population":8,
    "gn:timezone":"Europe/Rome",
    "iso:country":"IT",
    "name:bel_x_preferred":[
        "\u041f\u0430\u0440\u0430"
    ],
    "name:bre_x_preferred":[
        "Para"
    ],
    "name:bul_x_preferred":[
        "\u041f\u0430\u0440\u0430"
    ],
    "name:cat_x_preferred":[
        "Para"
    ],
    "name:ceb_x_preferred":[
        "Para"
    ],
    "name:dan_x_preferred":[
        "Para"
    ],
    "name:deu_x_preferred":[
        "Para"
    ],
    "name:est_x_preferred":[
        "Para"
    ],
    "name:fin_x_preferred":[
        "Para"
    ],
    "name:fra_x_preferred":[
        "Para"
    ],
    "name:heb_x_preferred":[
        "\u05e4\u05d0\u05e8\u05d4"
    ],
    "name:hrv_x_preferred":[
        "Para"
    ],
    "name:hun_x_preferred":[
        "Para"
    ],
    "name:ind_x_preferred":[
        "Para"
    ],
    "name:ita_x_preferred":[
        "Para"
    ],
    "name:lav_x_preferred":[
        "Para"
    ],
    "name:lit_x_preferred":[
        "Para"
    ],
    "name:nld_x_preferred":[
        "Para"
    ],
    "name:pol_x_preferred":[
        "Para"
    ],
    "name:por_x_preferred":[
        "Para"
    ],
    "name:ron_x_preferred":[
        "Para"
    ],
    "name:rus_x_preferred":[
        "\u041f\u0430\u0440\u0430"
    ],
    "name:slk_x_preferred":[
        "Para"
    ],
    "name:slv_x_preferred":[
        "Para"
    ],
    "name:spa_x_preferred":[
        "Para"
    ],
    "name:srp_x_preferred":[
        "\u041f\u0430\u0440\u0430"
    ],
    "name:swe_x_preferred":[
        "Para"
    ],
    "name:tgl_x_preferred":[
        "Para"
    ],
    "name:tha_x_preferred":[
        "\u0e1e\u0e32\u0e23\u0e32"
    ],
    "name:tur_x_preferred":[
        "Para"
    ],
    "name:ukr_x_preferred":[
        "\u041f\u0430\u0440\u0430"
    ],
    "name:urd_x_preferred":[
        "Para"
    ],
    "name:zho_x_preferred":[
        "\u5e15\u62c9"
    ],
    "wof:name":"Para",
    "wof:placetype":"locality",
    "wof:population":8
},
  "geometry": {"coordinates":[7.21625,44.58974],"type":"Point"}
}