{
  "type": "Feature",
  "properties": {
    "gn:admin1_code":"12",
    "gn:admin2_code":"CN",
    "gn:admin3_code":"4205.0",
    "gn:asciiname":"Para",
    "gn:country_code":"IT",
    "gn:dem":1231,
    "gn:feature_class":"P",
    "gn:feature_code":"PPLL",
    "gn:name":"Para",
    "gn:population":8,
    "gn:timezone":"Europe/Rome",
    "iso:country":"IT",
    "wof:name":"Para",
    "wof:placetype":"locality",
    "wof:population":8
},
  "geometry": {"coordinates":[7.21625,44.58974],"type":"Point"}
}