{
  "type": "Feature",
  "properties": {
    "gn:admin1_code":"10",
    "gn:admin2_code":"AN",
    "gn:admin3_code":"42002.0",
    "gn:asciiname":"Gallignano",
    "gn:country_code":"IT",
    "gn:dem":206,
    "gn:feature_class":"P",
    "gn:feature_code":"PPL",
    "gn:name":"Gallignano",
    "gn:population":165,
    "gn:timezone":"Europe/Rome",
    "iso:country":"IT",
    "wof:name":"Gallignano",
    "wof:placetype":"locality",
    "wof:population":165
},
  "geometry": {"coordinates":[13.4244,43.56201],"type":"Point"}
}