{
  "type": "Feature",
  "properties": {
    "gn:admin1_code":"2",
    "gn:admin2_code":"MT",
    "gn:admin3_code":"77013.0",
    "gn:asciiname":"Taccone",
    "gn:country_code":"IT",
    "gn:dem":256,
    "gn:feature_class":"P",
    "gn:feature_code":"PPL",
    "gn:name":"Taccone",
    "gn:population":34,
    "gn:timezone":"Europe/Rome",
    "iso:country":"IT",
    "wof:name":"Taccone",
    "wof:placetype":"locality",
    "wof:population":34
},
  "geometry": {"coordinates":[16.16219,40.79804],"type":"Point"}
}