{
  "type": "Feature",
  "properties": {
    "gn:admin1_code":"14",
    "gn:admin2_code":"SS",
    "gn:admin3_code":"90013.0",
    "gn:asciiname":"Santa Barbara",
    "gn:country_code":"IT",
    "gn:dem":484,
    "gn:feature_class":"P",
    "gn:feature_code":"PPL",
    "gn:name":"Santa Barbara",
    "gn:population":14,
    "gn:timezone":"Europe/Rome",
    "iso:country":"IT",
    "wof:name":"Santa Barbara",
    "wof:placetype":"locality",
    "wof:population":14
},
  "geometry": {"coordinates":[8.75279,40.40955],"type":"Point"}
}