{
  "type": "Feature",
  "properties": {
    "gn:admin1_code":"1",
    "gn:admin2_code":"TE",
    "gn:admin3_code":"67036.0",
    "gn:asciiname":"Paranesi",
    "gn:country_code":"IT",
    "gn:dem":1031,
    "gn:feature_class":"P",
    "gn:feature_code":"PPL",
    "gn:name":"Paranesi",
    "gn:population":94,
    "gn:timezone":"Europe/Rome",
    "iso:country":"IT",
    "wof:name":"Paranesi",
    "wof:placetype":"locality",
    "wof:population":94
},
  "geometry": {"coordinates":[13.50073,42.68719],"type":"Point"}
}