{
  "type": "Feature",
  "properties": {
    "gn:admin1_code":"4.0",
    "gn:admin2_code":"AV",
    "gn:admin3_code":"64057.0",
    "gn:asciiname":"Fontana",
    "gn:country_code":"IT",
    "gn:dem":754,
    "gn:feature_class":"P",
    "gn:feature_code":"PPL",
    "gn:name":"Fontana",
    "gn:population":0,
    "gn:timezone":"Europe/Rome",
    "iso:country":"IT",
    "name:bel_x_preferred":[
        "\u0424\u0430\u043d\u0442\u0430\u043d\u0430"
    ],
    "name:bos_x_preferred":[
        "Fontana"
    ],
    "name:cat_x_preferred":[
        "Fontana"
    ],
    "name:ceb_x_preferred":[
        "Fontana"
    ],
    "name:ces_x_preferred":[
        "Fontana"
    ],
    "name:deu_x_preferred":[
        "Fontana"
    ],
    "name:epo_x_preferred":[
        "Fontana"
    ],
    "name:fin_x_preferred":[
        "Fontana"
    ],
    "name:fra_x_preferred":[
        "Fontana"
    ],
    "name:heb_x_preferred":[
        "\u05e4\u05d5\u05e0\u05d8\u05e0\u05d4"
    ],
    "name:ita_x_preferred":[
        "Fontana"
    ],
    "name:jpn_x_preferred":[
        "\u30d5\u30a9\u30f3\u30bf\u30ca"
    ],
    "name:kor_x_preferred":[
        "\ud3f0\ud0c0\ub098"
    ],
    "name:lat_x_preferred":[
        "Fontana"
    ],
    "name:lit_x_preferred":[
        "Fontana"
    ],
    "name:nld_x_preferred":[
        "Fontana"
    ],
    "name:pol_x_preferred":[
        "Fontana"
    ],
    "name:por_x_preferred":[
        "Fontana"
    ],
    "name:rus_x_preferred":[
        "\u0424\u043e\u043d\u0442\u0430\u043d\u0430"
    ],
    "name:sco_x_preferred":[
        "Fontana"
    ],
    "name:slv_x_preferred":[
        "Fontana"
    ],
    "name:spa_x_preferred":[
        "Fontana"
    ],
    "name:srp_x_preferred":[
        "\u0424\u043e\u043d\u0442\u0430\u043d\u0430"
    ],
    "name:swe_x_preferred":[
        "Fontana"
    ],
    "name:ukr_x_preferred":[
        "\u0424\u043e\u043d\u0442\u0430\u043d\u0430"
    ],
    "name:urd_x_preferred":[
        "\u0641\u0648\u0646\u0679\u06cc\u0646\u0627"
    ],
    "name:vol_x_preferred":[
        "Fontana"
    ],
    "wof:name":"Fontana",
    "wof:placetype":"locality"
},
  "geometry": {"coordinates":[15.01667,40.83333],"type":"Point"}
}