{
  "type": "Feature",
  "properties": {
    "gn:admin1_code":"1",
    "gn:admin2_code":"CH",
    "gn:admin3_code":"69046.0",
    "gn:asciiname":"Fontanelle",
    "gn:country_code":"IT",
    "gn:dem":253,
    "gn:feature_class":"P",
    "gn:feature_code":"PPL",
    "gn:name":"Fontanelle",
    "gn:population":45,
    "gn:timezone":"Europe/Rome",
    "iso:country":"IT",
    "wof:name":"Fontanelle",
    "wof:placetype":"locality",
    "wof:population":45
},
  "geometry": {"coordinates":[14.38552,42.18129],"type":"Point"}
}