{
  "type": "Feature",
  "properties": {
    "gn:admin1_code":"7.0",
    "gn:admin2_code":"RI",
    "gn:admin3_code":"57057.0",
    "gn:asciiname":"Laculo",
    "gn:country_code":"IT",
    "gn:dem":988,
    "gn:elevation":"986.0",
    "gn:feature_class":"P",
    "gn:feature_code":"PPL",
    "gn:name":"Laculo",
    "gn:population":17,
    "gn:timezone":"Europe/Rome",
    "iso:country":"IT",
    "wof:name":"Laculo",
    "wof:placetype":"locality",
    "wof:population":17
},
  "geometry": {"coordinates":[13.10088,42.49064],"type":"Point"}
}