{
  "type": "Feature",
  "properties": {
    "gn:admin1_code":"5",
    "gn:admin2_code":"RE",
    "gn:admin3_code":"35003.0",
    "gn:asciiname":"Caliceto",
    "gn:country_code":"IT",
    "gn:dem":435,
    "gn:feature_class":"P",
    "gn:feature_code":"PPL",
    "gn:name":"Caliceto",
    "gn:population":34,
    "gn:timezone":"Europe/Rome",
    "iso:country":"IT",
    "wof:name":"Caliceto",
    "wof:placetype":"locality",
    "wof:population":34
},
  "geometry": {"coordinates":[10.63958,44.46239],"type":"Point"}
}