{
  "type": "Feature",
  "properties": {
    "gn:admin1_code":"19",
    "gn:admin2_code":"AO",
    "gn:admin3_code":"7014.0",
    "gn:asciiname":"Villa-Nabian",
    "gn:country_code":"IT",
    "gn:dem":775,
    "gn:feature_class":"P",
    "gn:feature_code":"PPLA3",
    "gn:name":"Villa-Nabian",
    "gn:population":280,
    "gn:timezone":"Europe/Rome",
    "iso:country":"IT",
    "wof:name":"Villa-Nabian",
    "wof:placetype":"locality",
    "wof:population":280
},
  "geometry": {"coordinates":[7.7047,45.6897],"type":"Point"}
}