{
  "type": "Feature",
  "properties": {
    "gn:admin1_code":"12",
    "gn:admin2_code":"CN",
    "gn:admin3_code":"4148.0",
    "gn:asciiname":"Gallina",
    "gn:country_code":"IT",
    "gn:dem":223,
    "gn:feature_class":"P",
    "gn:feature_code":"PPL",
    "gn:name":"Gallina",
    "gn:population":34,
    "gn:timezone":"Europe/Rome",
    "iso:country":"IT",
    "name:fin_x_preferred":[
        "Gallinan kulttuuri"
    ],
    "wof:name":"Gallina",
    "wof:placetype":"locality",
    "wof:population":34
},
  "geometry": {"coordinates":[8.10219,44.72919],"type":"Point"}
}