{
  "type": "Feature",
  "properties": {
    "gn:admin1_code":"7",
    "gn:admin2_code":"LT",
    "gn:admin3_code":"59017.0",
    "gn:asciiname":"Codarda",
    "gn:country_code":"IT",
    "gn:dem":6,
    "gn:feature_class":"P",
    "gn:feature_code":"PPL",
    "gn:name":"Codarda",
    "gn:population":128,
    "gn:timezone":"Europe/Rome",
    "iso:country":"IT",
    "wof:name":"Codarda",
    "wof:placetype":"locality",
    "wof:population":128
},
  "geometry": {"coordinates":[13.14906,41.42439],"type":"Point"}
}