{
  "type": "Feature",
  "properties": {
    "gn:admin1_code":"20.0",
    "gn:admin2_code":"VI",
    "gn:admin3_code":"24048.0",
    "gn:asciiname":"Torreselle",
    "gn:country_code":"IT",
    "gn:dem":345,
    "gn:feature_class":"P",
    "gn:feature_code":"PPL",
    "gn:name":"Torreselle",
    "gn:population":58,
    "gn:timezone":"Europe/Rome",
    "iso:country":"IT",
    "wof:name":"Torreselle",
    "wof:placetype":"locality",
    "wof:population":58
},
  "geometry": {"coordinates":[11.42526,45.60982],"type":"Point"}
}