{
  "type": "Feature",
  "properties": {
    "gn:country":"IT",
    "gn:fcode":"PPL",
    "gn:population":0,
    "iso:country":"IT",
    "qs_pg:aaroncc":"IT",
    "qs_pg:gn_country":"IT",
    "qs_pg:gn_fcode":"PPL",
    "qs_pg:gn_pop":0,
    "qs_pg:name":"Albergo del Ghertele",
    "qs_pg:name_adm0":"Italia",
    "qs_pg:name_adm1":"Veneto",
    "qs_pg:photos":22,
    "qs_pg:photos_1k":4,
    "qs_pg:photos_9k":1,
    "qs_pg:photos_9r":1,
    "qs_pg:photos_all":22,
    "qs_pg:photos_sr":1,
    "qs_pg:pop_sr":0,
    "qs_pg:qs_pg_placetype":"locality",
    "qs_pg:qs_pg_placetype_gp":"Town",
    "qs_pg:woe_adm0":23424853,
    "woe:adm0_id":23424853,
    "woe:name_adm0":"Italia",
    "woe:name_adm1":"Veneto",
    "woe:placetype":"Town",
    "wof:name":"Albergo del Ghertele",
    "wof:placetype":"locality"
},
  "geometry": {"coordinates":[11.43333,45.93333],"type":"Point"}
}