{
  "type": "Feature",
  "properties": {
    "gn:admin1_code":"5.0",
    "gn:admin2_code":"PC",
    "gn:admin3_code":"33013.0",
    "gn:asciiname":"Fontana Pradosa",
    "gn:country_code":"IT",
    "gn:dem":80,
    "gn:elevation":"82.0",
    "gn:feature_class":"P",
    "gn:feature_code":"PPL",
    "gn:name":"Fontana Pradosa",
    "gn:population":623,
    "gn:timezone":"Europe/Rome",
    "iso:country":"IT",
    "wof:name":"Fontana Pradosa",
    "wof:placetype":"locality",
    "wof:population":623
},
  "geometry": {"coordinates":[9.46265,45.06154],"type":"Point"}
}