{
  "type": "Feature",
  "properties": {
    "gn:admin1_code":"8",
    "gn:admin2_code":"IM",
    "gn:admin3_code":"8009.0",
    "gn:asciiname":"Montecalvo",
    "gn:country_code":"IT",
    "gn:dem":523,
    "gn:feature_class":"P",
    "gn:feature_code":"PPL",
    "gn:name":"Montecalvo",
    "gn:population":15,
    "gn:timezone":"Europe/Rome",
    "iso:country":"IT",
    "wof:name":"Montecalvo",
    "wof:placetype":"locality",
    "wof:population":15
},
  "geometry": {"coordinates":[7.9762,44.0394],"type":"Point"}
}