{
  "type": "Feature",
  "properties": {
    "gn:admin1_code":"8",
    "gn:admin2_code":"IM",
    "gn:admin3_code":"8009.0",
    "gn:asciiname":"Montecalvo",
    "gn:country_code":"IT",
    "gn:dem":523,
    "gn:feature_class":"P",
    "gn:feature_code":"PPL",
    "gn:name":"Montecalvo",
    "gn:population":15,
    "gn:timezone":"Europe/Rome",
    "iso:country":"IT",
    "name:ceb_x_preferred":[
        "Montecalvo"
    ],
    "name:glg_x_preferred":[
        "Montecalvo"
    ],
    "name:ita_x_preferred":[
        "Montecalvo"
    ],
    "name:por_x_preferred":[
        "Montecalvo"
    ],
    "name:rus_x_preferred":[
        "\u041c\u043e\u043d\u0442\u0435\u043a\u0430\u043b\u044c\u0432\u043e"
    ],
    "name:scn_x_preferred":[
        "Montecalvo"
    ],
    "name:srp_x_preferred":[
        "Montekalvo"
    ],
    "name:swe_x_preferred":[
        "Montecalvo"
    ],
    "wof:name":"Montecalvo",
    "wof:placetype":"locality",
    "wof:population":15
},
  "geometry": {"coordinates":[7.9762,44.0394],"type":"Point"}
}