{
  "type": "Feature",
  "properties": {
    "gn:admin1_code":"11",
    "gn:admin2_code":"CB",
    "gn:admin3_code":"70026.0",
    "gn:asciiname":"Piano Bernardino",
    "gn:country_code":"IT",
    "gn:dem":612,
    "gn:feature_class":"P",
    "gn:feature_code":"PPL",
    "gn:name":"Piano Bernardino",
    "gn:population":20,
    "gn:timezone":"Europe/Rome",
    "iso:country":"IT",
    "wof:name":"Piano Bernardino",
    "wof:placetype":"locality",
    "wof:population":20
},
  "geometry": {"coordinates":[14.72953,41.50308],"type":"Point"}
}