{
  "type": "Feature",
  "properties": {
    "gn:admin1_code":"17",
    "gn:admin2_code":"TN",
    "gn:admin3_code":"22001.0",
    "gn:asciiname":"Brustolotti",
    "gn:country_code":"IT",
    "gn:dem":241,
    "gn:feature_class":"P",
    "gn:feature_code":"PPL",
    "gn:name":"Brustolotti",
    "gn:population":51,
    "gn:timezone":"Europe/Rome",
    "iso:country":"IT",
    "wof:name":"Brustolotti",
    "wof:placetype":"locality",
    "wof:population":51
},
  "geometry": {"coordinates":[11.01726,45.75577],"type":"Point"}
}