{
  "type": "Feature",
  "properties": {
    "iso:country":"IT",
    "qs:a0":"Italia",
    "qs:a1":"*Reggio di Calabria",
    "qs:a1r":"0Calabria",
    "qs:adm0":"Italia",
    "qs:la_lc":"*",
    "qs:level":"locality",
    "qs:loc":"Sambatello",
    "qs:loc_alt":"Sambatello",
    "qs:pop":0,
    "qs:type":"buffered point",
    "wof:name":"Sambatello",
    "wof:placetype":"locality"
},
  "geometry": {"coordinates":[15.69313,38.178901],"type":"Point"}
}