{
  "type": "Feature",
  "properties": {
    "gn:admin1_code":"4",
    "gn:admin2_code":"BN",
    "gn:admin3_code":"62076.0",
    "gn:asciiname":"Pezzepagliara",
    "gn:country_code":"IT",
    "gn:dem":267,
    "gn:feature_class":"P",
    "gn:feature_code":"PPL",
    "gn:name":"Pezzepagliara",
    "gn:population":13,
    "gn:timezone":"Europe/Rome",
    "iso:country":"IT",
    "wof:name":"Pezzepagliara",
    "wof:placetype":"locality",
    "wof:population":13
},
  "geometry": {"coordinates":[14.69693,41.19226],"type":"Point"}
}