{
  "type": "Feature",
  "properties": {
    "gn:gn_country":"IT",
    "gn:gn_fcode":"PPL",
    "gn:gn_pop":0,
    "gn:population":799,
    "iso:country":"IT",
    "name:cat_x_preferred":[
        "Villa Inferno"
    ],
    "name:ceb_x_preferred":[
        "Villa Inferno"
    ],
    "name:ces_x_preferred":[
        "Villa Inferno"
    ],
    "name:dan_x_preferred":[
        "Villa Inferno"
    ],
    "name:eng_x_preferred":[
        "Villa Inferno"
    ],
    "name:eus_x_preferred":[
        "Villa Inferno"
    ],
    "name:fin_x_preferred":[
        "Villa Inferno"
    ],
    "name:fra_x_preferred":[
        "Villa Inferno"
    ],
    "name:ind_x_preferred":[
        "Villa Inferno"
    ],
    "name:ita_x_preferred":[
        "Villa Inferno"
    ],
    "name:nld_x_preferred":[
        "Villa Inferno"
    ],
    "name:nno_x_preferred":[
        "Villa Inferno"
    ],
    "name:nob_x_preferred":[
        "Villa Inferno"
    ],
    "name:oci_x_preferred":[
        "Villa Inferno"
    ],
    "name:pol_x_preferred":[
        "Villa Inferno"
    ],
    "name:por_x_preferred":[
        "Villa Inferno"
    ],
    "name:ron_x_preferred":[
        "Villa Inferno"
    ],
    "name:slk_x_preferred":[
        "Villa Inferno"
    ],
    "name:slv_x_preferred":[
        "Villa Inferno"
    ],
    "name:spa_x_preferred":[
        "Villa Inferno"
    ],
    "name:srp_x_preferred":[
        "Villa Inferno"
    ],
    "name:swe_x_preferred":[
        "Villa Inferno"
    ],
    "name:tgl_x_preferred":[
        "Villa Inferno"
    ],
    "name:tur_x_preferred":[
        "Villa Inferno"
    ],
    "name:war_x_preferred":[
        "Villa Inferno"
    ],
    "qs_pg:aaroncc":"IT",
    "qs_pg:gn_country":"IT",
    "qs_pg:gn_fcode":"PPL",
    "qs_pg:gn_pop":0,
    "qs_pg:name":"Villa Inferno",
    "qs_pg:name_adm0":"Italia",
    "qs_pg:name_adm1":"Emilia Romagna",
    "qs_pg:photos_9k":1,
    "qs_pg:photos_9r":1,
    "qs_pg:photos_all":1,
    "qs_pg:photos_sr":0,
    "qs_pg:pop_sr":0,
    "qs_pg:qs_pg_placetype":"locality",
    "qs_pg:qs_pg_placetype_gp":"Town",
    "qs_pg:woe_adm0":23424853,
    "woe:adm0_id":23424853,
    "woe:name_adm0":"Italia",
    "woe:name_adm1":"Emilia Romagna",
    "woe:placetype":"Town",
    "wof:name":"Villa Inferno",
    "wof:placetype":"locality",
    "wof:population":799
},
  "geometry": {"coordinates":[12.31667,44.23333],"type":"Point"}
}