{
  "type": "Feature",
  "properties": {
    "gn:admin1_code":"1",
    "gn:admin2_code":"TE",
    "gn:admin3_code":"67027.0",
    "gn:asciiname":"Contrada Marri",
    "gn:country_code":"IT",
    "gn:dem":235,
    "gn:feature_class":"P",
    "gn:feature_code":"PPL",
    "gn:name":"Contrada Marri",
    "gn:population":29,
    "gn:timezone":"Europe/Rome",
    "iso:country":"IT",
    "wof:name":"Contrada Marri",
    "wof:placetype":"locality",
    "wof:population":29
},
  "geometry": {"coordinates":[13.91714,42.56678],"type":"Point"}
}