{
  "type": "Feature",
  "properties": {
    "gn:admin1_code":"20.0",
    "gn:admin2_code":"PD",
    "gn:admin3_code":"28081.0",
    "gn:asciiname":"Chiesa Nuova",
    "gn:country_code":"IT",
    "gn:dem":5,
    "gn:feature_class":"P",
    "gn:feature_code":"PPL",
    "gn:name":"Chiesa Nuova",
    "gn:population":359,
    "gn:timezone":"Europe/Rome",
    "iso:country":"IT",
    "name:ceb_x_preferred":[
        "Chiesa Nuova"
    ],
    "name:deu_x_preferred":[
        "Chiesa Nuova"
    ],
    "name:ita_x_preferred":[
        "Chiesa Nuova"
    ],
    "name:srp_x_preferred":[
        "Chiesa Nuova"
    ],
    "name:swe_x_preferred":[
        "Chiesa Nuova"
    ],
    "wof:name":"Chiesa Nuova",
    "wof:placetype":"locality",
    "wof:population":359
},
  "geometry": {"coordinates":[11.56363,45.1971],"type":"Point"}
}