{
  "type": "Feature",
  "properties": {
    "gn:admin1_code":"3",
    "gn:admin2_code":"CZ",
    "gn:admin3_code":"79129.0",
    "gn:asciiname":"Palmatico",
    "gn:country_code":"IT",
    "gn:dem":598,
    "gn:feature_class":"P",
    "gn:feature_code":"PPL",
    "gn:name":"Palmatico",
    "gn:population":71,
    "gn:timezone":"Europe/Rome",
    "iso:country":"IT",
    "wof:name":"Palmatico",
    "wof:placetype":"locality",
    "wof:population":71
},
  "geometry": {"coordinates":[16.36192999999999,38.98203],"type":"Point"}
}