{
  "type": "Feature",
  "properties": {
    "gn:admin1_code":"3",
    "gn:admin2_code":"CS",
    "gn:admin3_code":"78138.0",
    "gn:asciiname":"Sant'Angelo",
    "gn:country_code":"IT",
    "gn:dem":23,
    "gn:feature_class":"P",
    "gn:feature_code":"PPL",
    "gn:name":"Sant'Angelo",
    "gn:population":70,
    "gn:timezone":"Europe/Rome",
    "iso:country":"IT",
    "wof:name":"Sant'Angelo",
    "wof:placetype":"locality",
    "wof:population":70
},
  "geometry": {"coordinates":[15.82352,39.78685],"type":"Point"}
}