{
  "type": "Feature",
  "properties": {
    "gn:admin1_code":"16.0",
    "gn:asciiname":"Cittadella La Rocchetta",
    "gn:country_code":"IT",
    "gn:dem":-9999,
    "gn:feature_class":"P",
    "gn:feature_code":"PPL",
    "gn:name":"Cittadella La Rocchetta",
    "gn:population":0,
    "gn:timezone":"Europe/Rome",
    "iso:country":"IT",
    "wof:name":"Cittadella La Rocchetta",
    "wof:placetype":"locality"
},
  "geometry": {"coordinates":[10.55,42.93333],"type":"Point"}
}