{
  "type": "Feature",
  "properties": {
    "gn:admin1_code":"9",
    "gn:admin2_code":"PV",
    "gn:admin3_code":"18187.0",
    "gn:asciiname":"Cascina Vecchia",
    "gn:country_code":"IT",
    "gn:dem":158,
    "gn:feature_class":"P",
    "gn:feature_code":"PPL",
    "gn:name":"Cascina Vecchia",
    "gn:population":31,
    "gn:timezone":"Europe/Rome",
    "iso:country":"IT",
    "wof:name":"Cascina Vecchia",
    "wof:placetype":"locality",
    "wof:population":31
},
  "geometry": {"coordinates":[9.33757,45.0541],"type":"Point"}
}