{
  "type": "Feature",
  "properties": {
    "gn:admin1_code":"16.0",
    "gn:admin2_code":"LU",
    "gn:admin3_code":"46037.0",
    "gn:asciiname":"Magliano",
    "gn:country_code":"IT",
    "gn:dem":866,
    "gn:elevation":"834.0",
    "gn:feature_class":"P",
    "gn:feature_code":"PPL",
    "gn:name":"Magliano",
    "gn:population":208,
    "gn:timezone":"Europe/Rome",
    "iso:country":"IT",
    "wof:name":"Magliano",
    "wof:placetype":"locality",
    "wof:population":208
},
  "geometry": {"coordinates":[10.2558,44.21829],"type":"Point"}
}