{
  "type": "Feature",
  "properties": {
    "gn:admin1_code":"9",
    "gn:admin2_code":"PV",
    "gn:admin3_code":"18049.0",
    "gn:asciiname":"Rivara",
    "gn:country_code":"IT",
    "gn:dem":78,
    "gn:feature_class":"P",
    "gn:feature_code":"PPL",
    "gn:name":"Rivara",
    "gn:population":39,
    "gn:timezone":"Europe/Rome",
    "iso:country":"IT",
    "wof:name":"Rivara",
    "wof:placetype":"locality",
    "wof:population":39
},
  "geometry": {"coordinates":[9.22989,45.04594],"type":"Point"}
}