{
  "type": "Feature",
  "properties": {
    "gn:admin1_code":"6",
    "gn:admin2_code":"UD",
    "gn:admin3_code":"30074.0",
    "gn:asciiname":"Cortello",
    "gn:country_code":"IT",
    "gn:dem":69,
    "gn:feature_class":"P",
    "gn:feature_code":"PPL",
    "gn:name":"Cortello",
    "gn:population":33,
    "gn:timezone":"Europe/Rome",
    "iso:country":"IT",
    "wof:name":"Cortello",
    "wof:placetype":"locality",
    "wof:population":33
},
  "geometry": {"coordinates":[13.26068,45.99168],"type":"Point"}
}