{
  "type": "Feature",
  "properties": {
    "gn:admin1_code":"1.0",
    "gn:admin2_code":"TE",
    "gn:admin3_code":"67011.0",
    "gn:asciiname":"L.P. Casemolino",
    "gn:country_code":"IT",
    "gn:dem":112,
    "gn:feature_class":"P",
    "gn:feature_code":"PPL",
    "gn:name":"L.P. Casemolino",
    "gn:population":0,
    "gn:timezone":"Europe/Rome",
    "iso:country":"IT",
    "wof:name":"L.P. Casemolino",
    "wof:placetype":"locality"
},
  "geometry": {"coordinates":[13.81381,42.69443],"type":"Point"}
}