{
  "type": "Feature",
  "properties": {
    "gn:elevation":275,
    "gn:population":617,
    "iso:country":"IT",
    "name:ara_x_preferred":[
        "\u0643\u0627\u0633\u0648\u0631\u0632\u0648"
    ],
    "name:bel_x_preferred":[
        "\u041a\u0430\u0437\u043e\u0440\u0446\u0430"
    ],
    "name:bul_x_preferred":[
        "\u041a\u0430\u0437\u043e\u0440\u0446\u043e"
    ],
    "name:cat_x_preferred":[
        "Casorzo"
    ],
    "name:deu_x_preferred":[
        "Casorzo"
    ],
    "name:eng_x_preferred":[
        "Casorzo"
    ],
    "name:epo_x_preferred":[
        "Casorzo"
    ],
    "name:est_x_preferred":[
        "Casorzo"
    ],
    "name:eus_x_preferred":[
        "Casorzo"
    ],
    "name:fas_x_preferred":[
        "\u06a9\u0627\u0633\u0648\u062a\u0632\u0648"
    ],
    "name:fra_x_preferred":[
        "Casorzo"
    ],
    "name:hbs_x_preferred":[
        "Casorzo"
    ],
    "name:hun_x_preferred":[
        "Casorzo"
    ],
    "name:hye_x_preferred":[
        "\u053f\u0561\u0566\u0578\u0580\u0581\u0578"
    ],
    "name:ind_x_preferred":[
        "Casorzo"
    ],
    "name:ita_x_preferred":[
        "Casorzo"
    ],
    "name:jpn_x_preferred":[
        "\u30ab\u30be\u30eb\u30c4\u30a9"
    ],
    "name:kaz_x_preferred":[
        "\u041a\u0430\u0437\u043e\u0440\u0446\u043e"
    ],
    "name:lat_x_preferred":[
        "Casortium"
    ],
    "name:lmo_x_preferred":[
        "Casorzo"
    ],
    "name:msa_x_preferred":[
        "Casorzo"
    ],
    "name:nan_x_preferred":[
        "Casorzo"
    ],
    "name:nap_x_preferred":[
        "Casorzo"
    ],
    "name:nld_x_preferred":[
        "Casorzo"
    ],
    "name:oci_x_preferred":[
        "Casorzo"
    ],
    "name:pms_x_preferred":[
        "Casors"
    ],
    "name:pol_x_preferred":[
        "Casorzo"
    ],
    "name:por_x_preferred":[
        "Casorzo"
    ],
    "name:ron_x_preferred":[
        "Casorzo"
    ],
    "name:rus_x_preferred":[
        "\u041a\u0430\u0437\u043e\u0440\u0446\u043e"
    ],
    "name:scn_x_preferred":[
        "Casorzo"
    ],
    "name:spa_x_preferred":[
        "Casorzo"
    ],
    "name:srp_x_preferred":[
        "\u041a\u0430\u0437\u043e\u0440\u0446\u043e"
    ],
    "name:tgl_x_preferred":[
        "Casorzo"
    ],
    "name:ukr_x_preferred":[
        "\u041a\u0430\u0437\u043e\u0440\u0446\u043e"
    ],
    "name:uzb_x_preferred":[
        "Casorzo"
    ],
    "name:vie_x_preferred":[
        "Casorzo"
    ],
    "name:vol_x_preferred":[
        "Casorzo"
    ],
    "name:war_x_preferred":[
        "Casorzo"
    ],
    "name:zho_min_nan_x_preferred":[
        "Casorzo"
    ],
    "name:zho_x_preferred":[
        "\u5361\u7d22\u5c14\u4f50"
    ],
    "qs:a0":"Italia",
    "qs:a1":"*Asti",
    "qs:a1r":"0Piemonte",
    "qs:adm0":"Italia",
    "qs:la_lc":"*",
    "qs:level":"locality",
    "qs:loc":"Casorzo",
    "qs:loc_alt":"Casorzo",
    "qs:pop":0,
    "qs:type":"buffered point",
    "wd:wordcount":58,
    "wof:lang":[
        "ita"
    ],
    "wof:name":"Casorzo",
    "wof:placetype":"locality",
    "wof:population":617
},
  "geometry": {"coordinates":[8.33806,45.023331],"type":"Point"}
}