{
  "type": "Feature",
  "properties": {
    "gn:admin1_code":"4",
    "gn:admin2_code":"SA",
    "gn:admin3_code":"65047.0",
    "gn:asciiname":"Casamola",
    "gn:country_code":"IT",
    "gn:dem":135,
    "gn:feature_class":"P",
    "gn:feature_code":"PPL",
    "gn:name":"Casamola",
    "gn:population":38,
    "gn:timezone":"Europe/Rome",
    "iso:country":"IT",
    "wof:name":"Casamola",
    "wof:placetype":"locality",
    "wof:population":38
},
  "geometry": {"coordinates":[14.5852,40.72416],"type":"Point"}
}