{
  "type": "Feature",
  "properties": {
    "gn:admin1_code":"7",
    "gn:admin2_code":"LT",
    "gn:admin3_code":"59032.0",
    "gn:asciiname":"Campo Soriano",
    "gn:country_code":"IT",
    "gn:dem":346,
    "gn:feature_class":"P",
    "gn:feature_code":"PPL",
    "gn:name":"Campo Soriano",
    "gn:population":61,
    "gn:timezone":"Europe/Rome",
    "iso:country":"IT",
    "wof:name":"Campo Soriano",
    "wof:placetype":"locality",
    "wof:population":61
},
  "geometry": {"coordinates":[13.24378,41.35564],"type":"Point"}
}