{
  "type": "Feature",
  "properties": {
    "gn:admin1_code":"20",
    "gn:admin2_code":"VR",
    "gn:admin3_code":"23022.0",
    "gn:asciiname":"Zuccotti",
    "gn:country_code":"IT",
    "gn:dem":101,
    "gn:feature_class":"P",
    "gn:feature_code":"PPL",
    "gn:name":"Zuccotti",
    "gn:population":28,
    "gn:timezone":"Europe/Rome",
    "iso:country":"IT",
    "name:deu_x_preferred":[
        "Zuccotti"
    ],
    "name:ita_x_preferred":[
        "Zuccotti"
    ],
    "name:spa_x_preferred":[
        "Zuccotti"
    ],
    "wof:name":"Zuccotti",
    "wof:placetype":"locality",
    "wof:population":28
},
  "geometry": {"coordinates":[10.72649,45.42189000000001],"type":"Point"}
}