{
  "type": "Feature",
  "properties": {
    "gn:admin1_code":"5",
    "gn:admin2_code":"PR",
    "gn:admin3_code":"34025.0",
    "gn:asciiname":"Borghetto delle Ghiaie",
    "gn:country_code":"IT",
    "gn:dem":83,
    "gn:feature_class":"P",
    "gn:feature_code":"PPL",
    "gn:name":"Borghetto delle Ghiaie",
    "gn:population":25,
    "gn:timezone":"Europe/Rome",
    "iso:country":"IT",
    "wof:name":"Borghetto delle Ghiaie",
    "wof:placetype":"locality",
    "wof:population":25
},
  "geometry": {"coordinates":[10.1772,44.77937],"type":"Point"}
}