{
  "type": "Feature",
  "properties": {
    "gn:admin1_code":"15",
    "gn:admin2_code":"AG",
    "gn:admin3_code":"84001.0",
    "gn:asciiname":"Timpa dei Palombi",
    "gn:country_code":"IT",
    "gn:dem":76,
    "gn:feature_class":"P",
    "gn:feature_code":"PPL",
    "gn:name":"Timpa dei Palombi",
    "gn:population":79,
    "gn:timezone":"Europe/Rome",
    "iso:country":"IT",
    "wof:name":"Timpa dei Palombi",
    "wof:placetype":"locality",
    "wof:population":79
},
  "geometry": {"coordinates":[13.63501,37.26586],"type":"Point"}
}