{
  "type": "Feature",
  "properties": {
    "gn:gn_country":"IT",
    "gn:gn_fcode":"PPL",
    "gn:gn_pop":0,
    "gn:population":721,
    "iso:country":"IT",
    "name:bul_x_preferred":[
        "\u041b\u0430\u0433\u043e\u043f\u0435\u0441\u043e\u043b\u0435"
    ],
    "name:ceb_x_preferred":[
        "Lagopesole"
    ],
    "name:eng_x_preferred":[
        "Castel Lagopesole"
    ],
    "name:fra_x_preferred":[
        "Castel Lagopesole"
    ],
    "name:hun_x_preferred":[
        "Castel Lagopesole"
    ],
    "name:ita_x_preferred":[
        "Castel Lagopesole"
    ],
    "name:jpn_x_preferred":[
        "\u30e9\u30fc\u30b4\u30da\u30be\u30fc\u30ec"
    ],
    "name:nld_x_preferred":[
        "Castel Lagopesole"
    ],
    "name:spa_x_preferred":[
        "Castel Lagopesole"
    ],
    "name:srp_x_preferred":[
        "Lagopesole"
    ],
    "name:unk_x_variant":[
        "Castello di Lago Pesole"
    ],
    "qs_pg:aaroncc":"IT",
    "qs_pg:gn_country":"IT",
    "qs_pg:gn_fcode":"PPL",
    "qs_pg:gn_pop":0,
    "qs_pg:name":"Lagopesole",
    "qs_pg:name_adm0":"Italia",
    "qs_pg:name_adm1":"Basilicata",
    "qs_pg:photos":36,
    "qs_pg:photos_1k":7,
    "qs_pg:photos_9k":1,
    "qs_pg:photos_9r":2,
    "qs_pg:photos_all":36,
    "qs_pg:photos_sr":2,
    "qs_pg:pop_sr":0,
    "qs_pg:qs_pg_placetype":"locality",
    "qs_pg:qs_pg_placetype_gp":"Town",
    "qs_pg:woe_adm0":23424853,
    "woe:adm0_id":23424853,
    "woe:name_adm0":"Italia",
    "woe:name_adm1":"Basilicata",
    "woe:placetype":"Town",
    "wof:name":"Lagopesole",
    "wof:placetype":"locality",
    "wof:population":721
},
  "geometry": {"coordinates":[15.73333,40.81667],"type":"Point"}
}