{
  "type": "Feature",
  "properties": {
    "gn:admin1_code":"4.0",
    "gn:admin2_code":"SA",
    "gn:admin3_code":"65056.0",
    "gn:asciiname":"Curti",
    "gn:country_code":"IT",
    "gn:dem":415,
    "gn:feature_class":"P",
    "gn:feature_code":"PPL",
    "gn:name":"Curti",
    "gn:population":514,
    "gn:timezone":"Europe/Rome",
    "iso:country":"IT",
    "wof:name":"Curti",
    "wof:placetype":"locality",
    "wof:population":514
},
  "geometry": {"coordinates":[14.92135,40.75099],"type":"Point"}
}