{
  "type": "Feature",
  "properties": {
    "gn:admin1_code":"4.0",
    "gn:admin2_code":"SA",
    "gn:admin3_code":"65056.0",
    "gn:asciiname":"Curti",
    "gn:country_code":"IT",
    "gn:dem":415,
    "gn:feature_class":"P",
    "gn:feature_code":"PPL",
    "gn:name":"Curti",
    "gn:population":514,
    "gn:timezone":"Europe/Rome",
    "iso:country":"IT",
    "name:cat_x_preferred":[
        "Curti"
    ],
    "name:ceb_x_preferred":[
        "Curti"
    ],
    "name:deu_x_preferred":[
        "Curti"
    ],
    "name:fra_x_preferred":[
        "Curti"
    ],
    "name:ita_x_preferred":[
        "Curti"
    ],
    "name:pol_x_preferred":[
        "Curti"
    ],
    "name:rus_x_preferred":[
        "\u041a\u0443\u0440\u0442\u0438"
    ],
    "name:srp_x_preferred":[
        "Curti"
    ],
    "name:swe_x_preferred":[
        "Curti"
    ],
    "name:ukr_x_preferred":[
        "\u041a\u0443\u0440\u0442\u0456"
    ],
    "wof:name":"Curti",
    "wof:placetype":"locality",
    "wof:population":514
},
  "geometry": {"coordinates":[14.92135,40.75099],"type":"Point"}
}