{
  "type": "Feature",
  "properties": {
    "iso:country":"IT",
    "wof:name":"Villaggio Prenestino",
    "wof:placetype":"neighbourhood"
},
  "geometry": {"coordinates":[12.68360830439805,41.90193671888105],"type":"Point"}
}