{
  "type": "Feature",
  "properties": {
    "gn:admin1_code":"12",
    "gn:admin2_code":"TO",
    "gn:admin3_code":"1189.0",
    "gn:asciiname":"Cascina Merli",
    "gn:country_code":"IT",
    "gn:dem":304,
    "gn:feature_class":"P",
    "gn:feature_code":"PPL",
    "gn:name":"Cascina Merli",
    "gn:population":25,
    "gn:timezone":"Europe/Rome",
    "iso:country":"IT",
    "wof:name":"Cascina Merli",
    "wof:placetype":"locality",
    "wof:population":25
},
  "geometry": {"coordinates":[7.56271,45.11893],"type":"Point"}
}