{
  "type": "Feature",
  "properties": {
    "gn:admin1_code":"5",
    "gn:admin2_code":"MO",
    "gn:admin3_code":"36012.0",
    "gn:asciiname":"Macchioni",
    "gn:country_code":"IT",
    "gn:dem":12,
    "gn:feature_class":"P",
    "gn:feature_code":"PPL",
    "gn:name":"Macchioni",
    "gn:population":24,
    "gn:timezone":"Europe/Rome",
    "iso:country":"IT",
    "wof:name":"Macchioni",
    "wof:placetype":"locality",
    "wof:population":24
},
  "geometry": {"coordinates":[11.21617,44.83298],"type":"Point"}
}