{
  "type": "Feature",
  "properties": {
    "gn:admin1_code":"20",
    "gn:admin2_code":"VI",
    "gn:admin3_code":"24034.0",
    "gn:asciiname":"Belvedere-Tezze",
    "gn:country_code":"IT",
    "gn:dem":240,
    "gn:feature_class":"P",
    "gn:feature_code":"PPL",
    "gn:name":"Belvedere-Tezze",
    "gn:population":85,
    "gn:timezone":"Europe/Rome",
    "iso:country":"IT",
    "wof:name":"Belvedere-Tezze",
    "wof:placetype":"locality",
    "wof:population":85
},
  "geometry": {"coordinates":[11.35313,45.6104],"type":"Point"}
}