{
  "type": "Feature",
  "properties": {
    "gn:admin1_code":"9",
    "gn:admin2_code":"PV",
    "gn:admin3_code":"18155.0",
    "gn:asciiname":"Trebbio",
    "gn:country_code":"IT",
    "gn:dem":328,
    "gn:feature_class":"P",
    "gn:feature_code":"PPL",
    "gn:name":"Trebbio",
    "gn:population":22,
    "gn:timezone":"Europe/Rome",
    "iso:country":"IT",
    "wof:name":"Trebbio",
    "wof:placetype":"locality",
    "wof:population":22
},
  "geometry": {"coordinates":[9.09705,44.94075],"type":"Point"}
}