{
  "type": "Feature",
  "properties": {
    "gn:admin1_code":"12",
    "gn:admin2_code":"BI",
    "gn:admin3_code":"96080.0",
    "gn:asciiname":"Casa Albert",
    "gn:country_code":"IT",
    "gn:dem":314,
    "gn:feature_class":"P",
    "gn:feature_code":"PPL",
    "gn:name":"Casa Albert",
    "gn:population":70,
    "gn:timezone":"Europe/Rome",
    "iso:country":"IT",
    "wof:name":"Casa Albert",
    "wof:placetype":"locality",
    "wof:population":70
},
  "geometry": {"coordinates":[8.04329,45.43346],"type":"Point"}
}