{
  "type": "Feature",
  "properties": {
    "gn:admin1_code":"9",
    "gn:admin2_code":"BS",
    "gn:admin3_code":"17113.0",
    "gn:asciiname":"Madonnina",
    "gn:country_code":"IT",
    "gn:dem":97,
    "gn:feature_class":"P",
    "gn:feature_code":"PPL",
    "gn:name":"Madonnina",
    "gn:population":94,
    "gn:timezone":"Europe/Rome",
    "iso:country":"IT",
    "wof:name":"Madonnina",
    "wof:placetype":"locality",
    "wof:population":94
},
  "geometry": {"coordinates":[10.39734,45.39545],"type":"Point"}
}