{
  "type": "Feature",
  "properties": {
    "gn:admin1_code":"16.0",
    "gn:admin2_code":"LU",
    "gn:admin3_code":"46019.0",
    "gn:asciiname":"Agliano",
    "gn:country_code":"IT",
    "gn:dem":728,
    "gn:feature_class":"P",
    "gn:feature_code":"PPL",
    "gn:name":"Agliano",
    "gn:population":113,
    "gn:timezone":"Europe/Rome",
    "iso:country":"IT",
    "name:ceb_x_preferred":[
        "Agliano"
    ],
    "name:ita_x_preferred":[
        "Agliano"
    ],
    "name:srp_x_preferred":[
        "Aljano"
    ],
    "name:swe_x_preferred":[
        "Agliano"
    ],
    "wof:name":"Agliano",
    "wof:placetype":"locality",
    "wof:population":113
},
  "geometry": {"coordinates":[10.24337,44.1702],"type":"Point"}
}