{
  "type": "Feature",
  "properties": {
    "gn:gn_country":"IT",
    "gn:gn_fcode":"PPLA3",
    "gn:gn_pop":184,
    "gn:population":170,
    "iso:country":"IT",
    "name:bel_x_preferred":[
        "\u041b\u0430\u0440\u0434\u0430\u0440\u0430"
    ],
    "name:cat_x_preferred":[
        "Lardaro"
    ],
    "name:deu_x_preferred":[
        "Lardaro"
    ],
    "name:ell_x_preferred":[
        "\u039b\u03b1\u03c1\u03bd\u03c4\u03ac\u03c1\u03bf"
    ],
    "name:eng_x_preferred":[
        "Lardaro"
    ],
    "name:epo_x_preferred":[
        "Lardaro"
    ],
    "name:eus_x_preferred":[
        "Lardaro"
    ],
    "name:fas_x_preferred":[
        "\u0644\u0627\u0631\u062f\u0627\u0631\u0648"
    ],
    "name:fra_x_preferred":[
        "Lardaro"
    ],
    "name:hun_x_preferred":[
        "Lardaro"
    ],
    "name:hye_x_preferred":[
        "\u053c\u0561\u0580\u0564\u0561\u0580\u0578"
    ],
    "name:ind_x_preferred":[
        "Lardaro"
    ],
    "name:ita_x_preferred":[
        "Lardaro"
    ],
    "name:jpn_x_preferred":[
        "\u30e9\u30eb\u30c0\u30fc\u30ed"
    ],
    "name:kaz_x_preferred":[
        "\u041b\u0430\u0440\u0434\u0430\u0440\u043e"
    ],
    "name:lat_x_preferred":[
        "Lardarium"
    ],
    "name:lmo_x_preferred":[
        "Lard\u00e9r"
    ],
    "name:msa_x_preferred":[
        "Lardaro"
    ],
    "name:nap_x_preferred":[
        "Lardaro"
    ],
    "name:nld_x_preferred":[
        "Lardaro"
    ],
    "name:oci_x_preferred":[
        "Lardaro"
    ],
    "name:pms_x_preferred":[
        "Lardaro"
    ],
    "name:pol_x_preferred":[
        "Lardaro"
    ],
    "name:por_x_preferred":[
        "Lardaro"
    ],
    "name:ron_x_preferred":[
        "Lardaro"
    ],
    "name:rus_x_preferred":[
        "\u041b\u0430\u0440\u0434\u0430\u0440\u043e"
    ],
    "name:scn_x_preferred":[
        "Lardaro"
    ],
    "name:spa_x_preferred":[
        "Lardaro"
    ],
    "name:srp_x_preferred":[
        "Lardaro"
    ],
    "name:tgl_x_preferred":[
        "Lardaro"
    ],
    "name:ukr_x_preferred":[
        "\u041b\u0430\u0440\u0434\u0430\u0440\u043e"
    ],
    "name:uzb_x_preferred":[
        "Lardaro"
    ],
    "name:vie_x_preferred":[
        "Lardaro"
    ],
    "name:vol_x_preferred":[
        "Lardaro"
    ],
    "name:war_x_preferred":[
        "Lardaro"
    ],
    "name:zho_x_preferred":[
        "\u62c9\u5c14\u8fbe\u7f57"
    ],
    "qs_pg:aaroncc":"IT",
    "qs_pg:gn_country":"IT",
    "qs_pg:gn_fcode":"PPLA3",
    "qs_pg:gn_pop":184,
    "qs_pg:name":"Lardaro",
    "qs_pg:name_adm0":"Italia",
    "qs_pg:name_adm1":"Trentino-Alto Adige",
    "qs_pg:photos_9r":0,
    "qs_pg:photos_sr":0,
    "qs_pg:pop_sr":1,
    "qs_pg:qs_pg_placetype":"locality",
    "qs_pg:qs_pg_placetype_gp":"Town",
    "qs_pg:woe_adm0":23424853,
    "woe:adm0_id":23424853,
    "woe:name_adm0":"Italia",
    "woe:name_adm1":"Trentino-Alto Adige",
    "woe:placetype":"Town",
    "wof:name":"Lardaro",
    "wof:placetype":"locality",
    "wof:population":170
},
  "geometry": {"coordinates":[10.66117,45.9702],"type":"Point"}
}