{
  "type": "Feature",
  "properties": {
    "gn:admin1_code":"4",
    "gn:admin2_code":"AV",
    "gn:admin3_code":"64003.0",
    "gn:asciiname":"Arenara",
    "gn:country_code":"IT",
    "gn:dem":852,
    "gn:feature_class":"P",
    "gn:feature_code":"PPL",
    "gn:name":"Arenara",
    "gn:population":34,
    "gn:timezone":"Europe/Rome",
    "iso:country":"IT",
    "wof:name":"Arenara",
    "wof:placetype":"locality",
    "wof:population":34
},
  "geometry": {"coordinates":[15.3279,40.94993],"type":"Point"}
}