{
  "type": "Feature",
  "properties": {
    "gn:gn_country":"IT",
    "gn:gn_fcode":"PPLX",
    "gn:gn_pop":0,
    "gn:population":17,
    "iso:country":"IT",
    "name:cat_x_preferred":[
        "Torre Mozza"
    ],
    "name:ces_x_preferred":[
        "Torre Mozza"
    ],
    "name:dan_x_preferred":[
        "Torre Mozza"
    ],
    "name:eng_x_preferred":[
        "Torre Mozza"
    ],
    "name:eus_x_preferred":[
        "Torre Mozza"
    ],
    "name:fin_x_preferred":[
        "Torre Mozza"
    ],
    "name:fra_x_preferred":[
        "Torre Mozza"
    ],
    "name:ind_x_preferred":[
        "Torre Mozza"
    ],
    "name:ita_x_preferred":[
        "Torre Mozza"
    ],
    "name:nld_x_preferred":[
        "Torre Mozza"
    ],
    "name:nno_x_preferred":[
        "Torre Mozza"
    ],
    "name:nob_x_preferred":[
        "Torre Mozza"
    ],
    "name:oci_x_preferred":[
        "Torre Mozza"
    ],
    "name:pol_x_preferred":[
        "Torre Mozza"
    ],
    "name:por_x_preferred":[
        "Torre Mozza"
    ],
    "name:ron_x_preferred":[
        "Torre Mozza"
    ],
    "name:slk_x_preferred":[
        "Torre Mozza"
    ],
    "name:slv_x_preferred":[
        "Torre Mozza"
    ],
    "name:spa_x_preferred":[
        "Torre Mozza"
    ],
    "name:srp_x_preferred":[
        "Torre Mozza"
    ],
    "name:swe_x_preferred":[
        "Torre Mozza"
    ],
    "name:tgl_x_preferred":[
        "Torre Mozza"
    ],
    "name:tur_x_preferred":[
        "Torre Mozza"
    ],
    "name:war_x_preferred":[
        "Torre Mozza"
    ],
    "qs_pg:aaroncc":"IT",
    "qs_pg:gn_country":"IT",
    "qs_pg:gn_fcode":"PPLX",
    "qs_pg:gn_pop":0,
    "qs_pg:name":"Torre Mozza",
    "qs_pg:name_adm0":"Italia",
    "qs_pg:name_adm1":"Puglia",
    "qs_pg:photos":186,
    "qs_pg:photos_1k":38,
    "qs_pg:photos_9k":1,
    "qs_pg:photos_9r":4,
    "qs_pg:photos_all":186,
    "qs_pg:photos_sr":4,
    "qs_pg:pop_sr":0,
    "qs_pg:qs_pg_placetype":"locality_gp_neighbourhood_gn",
    "qs_pg:qs_pg_placetype_gp":"Town",
    "qs_pg:woe_adm0":23424853,
    "woe:adm0_id":23424853,
    "woe:name_adm0":"Italia",
    "woe:name_adm1":"Puglia",
    "woe:placetype":"Town",
    "wof:name":"Torre Mozza",
    "wof:placetype":"locality",
    "wof:population":17
},
  "geometry": {"coordinates":[18.1616,39.86074],"type":"Point"}
}