{
  "type": "Feature",
  "properties": {
    "gn:admin1_code":"5.0",
    "gn:admin2_code":"PR",
    "gn:admin3_code":"34027.0",
    "gn:asciiname":"Alberi",
    "gn:country_code":"IT",
    "gn:dem":85,
    "gn:feature_class":"P",
    "gn:feature_code":"PPL",
    "gn:name":"Alberi",
    "gn:population":1110,
    "gn:timezone":"Europe/Rome",
    "iso:country":"IT",
    "wof:name":"Alberi",
    "wof:placetype":"locality",
    "wof:population":1110
},
  "geometry": {"coordinates":[10.33045,44.74837],"type":"Point"}
}