{
  "type": "Feature",
  "properties": {
    "gn:admin1_code":"9.0",
    "gn:admin2_code":"SO",
    "gn:admin3_code":"14023.0",
    "gn:asciiname":"Poira",
    "gn:country_code":"IT",
    "gn:dem":287,
    "gn:elevation":"294.0",
    "gn:feature_class":"P",
    "gn:feature_code":"PPL",
    "gn:name":"Poira",
    "gn:population":123,
    "gn:timezone":"Europe/Rome",
    "iso:country":"IT",
    "wof:name":"Poira",
    "wof:placetype":"locality",
    "wof:population":123
},
  "geometry": {"coordinates":[9.7426,46.14899000000001],"type":"Point"}
}