{
  "type": "Feature",
  "properties": {
    "gn:admin1_code":"12",
    "gn:admin2_code":"TO",
    "gn:admin3_code":"1094.0",
    "gn:asciiname":"Case Aris",
    "gn:country_code":"IT",
    "gn:dem":618,
    "gn:feature_class":"P",
    "gn:feature_code":"PPL",
    "gn:name":"Case Aris",
    "gn:population":25,
    "gn:timezone":"Europe/Rome",
    "iso:country":"IT",
    "wof:name":"Case Aris",
    "wof:placetype":"locality",
    "wof:population":25
},
  "geometry": {"coordinates":[7.52641,45.30932],"type":"Point"}
}