{
  "type": "Feature",
  "properties": {
    "gn:admin1_code":"10",
    "gn:admin2_code":"PU",
    "gn:admin3_code":"41059.0",
    "gn:asciiname":"Fontanelle",
    "gn:country_code":"IT",
    "gn:dem":152,
    "gn:feature_class":"P",
    "gn:feature_code":"PPL",
    "gn:name":"Fontanelle",
    "gn:population":69,
    "gn:timezone":"Europe/Rome",
    "iso:country":"IT",
    "wof:name":"Fontanelle",
    "wof:placetype":"locality",
    "wof:population":69
},
  "geometry": {"coordinates":[12.55355,43.81103],"type":"Point"}
}