{
  "type": "Feature",
  "properties": {
    "gn:admin1_code":"2.0",
    "gn:admin2_code":"PZ",
    "gn:admin3_code":"76006.0",
    "gn:asciiname":"Contrada Catena",
    "gn:country_code":"IT",
    "gn:dem":467,
    "gn:feature_class":"P",
    "gn:feature_code":"PPL",
    "gn:name":"Contrada Catena",
    "gn:population":15,
    "gn:timezone":"Europe/Rome",
    "iso:country":"IT",
    "wof:name":"Contrada Catena",
    "wof:placetype":"locality",
    "wof:population":15
},
  "geometry": {"coordinates":[15.66948,40.83913],"type":"Point"}
}