{
  "type": "Feature",
  "properties": {
    "gn:admin1_code":"7",
    "gn:admin2_code":"FR",
    "gn:admin3_code":"60036.0",
    "gn:asciiname":"Napoleone",
    "gn:country_code":"IT",
    "gn:dem":354,
    "gn:feature_class":"P",
    "gn:feature_code":"PPL",
    "gn:name":"Napoleone",
    "gn:population":29,
    "gn:timezone":"Europe/Rome",
    "iso:country":"IT",
    "name:hun_x_preferred":[
        "Nap\u00f3leon"
    ],
    "name:ita_x_preferred":[
        "Napoleone"
    ],
    "wof:name":"Napoleone",
    "wof:placetype":"locality",
    "wof:population":29
},
  "geometry": {"coordinates":[13.56664,41.63188],"type":"Point"}
}