{
  "type": "Feature",
  "properties": {
    "gn:admin1_code":"6",
    "gn:admin2_code":"UD",
    "gn:admin3_code":"30078.0",
    "gn:asciiname":"Marsure di Sotto-Nuova",
    "gn:country_code":"IT",
    "gn:dem":136,
    "gn:feature_class":"P",
    "gn:feature_code":"PPL",
    "gn:name":"Marsure di Sotto-Nuova",
    "gn:population":331,
    "gn:timezone":"Europe/Rome",
    "iso:country":"IT",
    "wof:name":"Marsure di Sotto-Nuova",
    "wof:placetype":"locality",
    "wof:population":331
},
  "geometry": {"coordinates":[13.30007,46.12948],"type":"Point"}
}