{
  "type": "Feature",
  "properties": {
    "gn:admin1_code":"20",
    "gn:admin2_code":"PD",
    "gn:admin3_code":"28077.0",
    "gn:asciiname":"Del Folo",
    "gn:country_code":"IT",
    "gn:dem":31,
    "gn:feature_class":"P",
    "gn:feature_code":"PPL",
    "gn:name":"Del Folo",
    "gn:population":18,
    "gn:timezone":"Europe/Rome",
    "iso:country":"IT",
    "wof:name":"Del Folo",
    "wof:placetype":"locality",
    "wof:population":18
},
  "geometry": {"coordinates":[11.85831,45.61828],"type":"Point"}
}