{
  "type": "Feature",
  "properties": {
    "gn:admin1_code":"12.0",
    "gn:admin2_code":"AL",
    "gn:admin3_code":"6059.0",
    "gn:asciiname":"Fontanina",
    "gn:country_code":"IT",
    "gn:dem":185,
    "gn:feature_class":"P",
    "gn:feature_code":"PPL",
    "gn:name":"Fontanina",
    "gn:population":23,
    "gn:timezone":"Europe/Rome",
    "iso:country":"IT",
    "wof:name":"Fontanina",
    "wof:placetype":"locality",
    "wof:population":23
},
  "geometry": {"coordinates":[8.19418,45.10115],"type":"Point"}
}