{
  "type": "Feature",
  "properties": {
    "gn:admin1_code":"20",
    "gn:admin2_code":"VR",
    "gn:admin3_code":"23094.0",
    "gn:asciiname":"Corte Vaccaldo",
    "gn:country_code":"IT",
    "gn:dem":35,
    "gn:feature_class":"P",
    "gn:feature_code":"PPL",
    "gn:name":"Corte Vaccaldo",
    "gn:population":20,
    "gn:timezone":"Europe/Rome",
    "iso:country":"IT",
    "wof:name":"Corte Vaccaldo",
    "wof:placetype":"locality",
    "wof:population":20
},
  "geometry": {"coordinates":[10.95226,45.33637],"type":"Point"}
}