{
  "type": "Feature",
  "properties": {
    "gn:admin1_code":"8",
    "gn:admin2_code":"SV",
    "gn:admin3_code":"9019.0",
    "gn:asciiname":"Marmoreo",
    "gn:country_code":"IT",
    "gn:dem":371,
    "gn:feature_class":"P",
    "gn:feature_code":"PPL",
    "gn:name":"Marmoreo",
    "gn:population":90,
    "gn:timezone":"Europe/Rome",
    "iso:country":"IT",
    "wof:name":"Marmoreo",
    "wof:placetype":"locality",
    "wof:population":90
},
  "geometry": {"coordinates":[8.05752,44.04376],"type":"Point"}
}