{
  "type": "Feature",
  "properties": {
    "gn:admin1_code":"10",
    "gn:admin2_code":"PU",
    "gn:admin3_code":"41067.0",
    "gn:asciiname":"Ca' la Lagia",
    "gn:country_code":"IT",
    "gn:dem":441,
    "gn:feature_class":"P",
    "gn:feature_code":"PPL",
    "gn:name":"Ca' la Lagia",
    "gn:population":41,
    "gn:timezone":"Europe/Rome",
    "iso:country":"IT",
    "wof:name":"Ca' la Lagia",
    "wof:placetype":"locality",
    "wof:population":41
},
  "geometry": {"coordinates":[12.55105,43.69659],"type":"Point"}
}