{
  "type": "Feature",
  "properties": {
    "gn:admin1_code":"20.0",
    "gn:admin2_code":"VI",
    "gn:admin3_code":"24006.0",
    "gn:asciiname":"Lapio",
    "gn:country_code":"IT",
    "gn:dem":167,
    "gn:elevation":"177.0",
    "gn:feature_class":"P",
    "gn:feature_code":"PPL",
    "gn:name":"Lapio",
    "gn:population":156,
    "gn:timezone":"Europe/Rome",
    "iso:country":"IT",
    "name:azb_x_preferred":[
        "\u0644\u0627\u067e\u06cc\u0648"
    ],
    "name:bul_x_preferred":[
        "\u041b\u0430\u043f\u0438\u043e"
    ],
    "name:ceb_x_preferred":[
        "Lapio"
    ],
    "name:deu_x_preferred":[
        "Lapio"
    ],
    "name:epo_x_preferred":[
        "Lapio"
    ],
    "name:eus_x_preferred":[
        "Lapio"
    ],
    "name:fas_x_preferred":[
        "\u0644\u0627\u067e\u06cc\u0648"
    ],
    "name:fra_x_preferred":[
        "Lapio"
    ],
    "name:hun_x_preferred":[
        "Lapio"
    ],
    "name:hye_x_preferred":[
        "\u053c\u0561\u057a\u056b\u0578"
    ],
    "name:ina_x_preferred":[
        "Lapio"
    ],
    "name:ita_x_preferred":[
        "Lapio"
    ],
    "name:jpn_x_preferred":[
        "\u30e9\u30fc\u30d4\u30aa"
    ],
    "name:kaz_x_preferred":[
        "\u041b\u0430\u043f\u044c\u043e"
    ],
    "name:kor_x_preferred":[
        "\ub77c\ud53c\uc624"
    ],
    "name:lat_x_preferred":[
        "Lapigium"
    ],
    "name:lmo_x_preferred":[
        "Lapio"
    ],
    "name:mkd_x_preferred":[
        "\u041b\u0430\u043f\u0438\u043e"
    ],
    "name:msa_x_preferred":[
        "Lapio"
    ],
    "name:nap_x_preferred":[
        "Lapio"
    ],
    "name:nld_x_preferred":[
        "Lapio"
    ],
    "name:pms_x_preferred":[
        "Lapio"
    ],
    "name:pol_x_preferred":[
        "Lapio"
    ],
    "name:por_x_preferred":[
        "Lapio"
    ],
    "name:ron_x_preferred":[
        "Lapio"
    ],
    "name:rus_x_preferred":[
        "\u041b\u0430\u043f\u044c\u043e"
    ],
    "name:scn_x_preferred":[
        "Lapiu"
    ],
    "name:spa_x_preferred":[
        "Lapio"
    ],
    "name:srp_x_preferred":[
        "\u041b\u0430\u043f\u0438\u043e"
    ],
    "name:tgl_x_preferred":[
        "Lapio"
    ],
    "name:ukr_x_preferred":[
        "\u041b\u0430\u043f\u0456\u043e"
    ],
    "name:uzb_x_preferred":[
        "Lapio"
    ],
    "name:vec_x_preferred":[
        "Lapio"
    ],
    "name:vol_x_preferred":[
        "Lapio"
    ],
    "name:war_x_preferred":[
        "Lapio"
    ],
    "name:zho_x_preferred":[
        "\u62c9\u76ae\u5965"
    ],
    "wof:name":"Lapio",
    "wof:placetype":"locality",
    "wof:population":156
},
  "geometry": {"coordinates":[11.53568,45.47449],"type":"Point"}
}