{
  "type": "Feature",
  "properties": {
    "gn:admin1_code":"20.0",
    "gn:admin2_code":"VI",
    "gn:admin3_code":"24006.0",
    "gn:asciiname":"Lapio",
    "gn:country_code":"IT",
    "gn:dem":167,
    "gn:elevation":"177.0",
    "gn:feature_class":"P",
    "gn:feature_code":"PPL",
    "gn:name":"Lapio",
    "gn:population":156,
    "gn:timezone":"Europe/Rome",
    "iso:country":"IT",
    "wof:name":"Lapio",
    "wof:placetype":"locality",
    "wof:population":156
},
  "geometry": {"coordinates":[11.53568,45.47449],"type":"Point"}
}