{
  "type": "Feature",
  "properties": {
    "gn:admin1_code":"15.0",
    "gn:admin2_code":"TP",
    "gn:admin3_code":"81011.0",
    "gn:asciiname":"Posidonie",
    "gn:country_code":"IT",
    "gn:dem":5,
    "gn:feature_class":"P",
    "gn:feature_code":"PPLL",
    "gn:name":"Posidonie",
    "gn:population":0,
    "gn:timezone":"Europe/Rome",
    "iso:country":"IT",
    "wof:name":"Posidonie",
    "wof:placetype":"locality"
},
  "geometry": {"coordinates":[12.48499,37.92866],"type":"Point"}
}