{
  "type": "Feature",
  "properties": {
    "gn:admin1_code":"10.0",
    "gn:admin2_code":"PU",
    "gn:admin3_code":"41044.0",
    "gn:asciiname":"Pozzo Alto",
    "gn:country_code":"IT",
    "gn:dem":134,
    "gn:elevation":"157.0",
    "gn:feature_class":"P",
    "gn:feature_code":"PPL",
    "gn:name":"Pozzo Alto",
    "gn:population":316,
    "gn:timezone":"Europe/Rome",
    "iso:country":"IT",
    "wof:name":"Pozzo Alto",
    "wof:placetype":"locality",
    "wof:population":316
},
  "geometry": {"coordinates":[12.78566,43.88388],"type":"Point"}
}