{
  "type": "Feature",
  "properties": {
    "gn:admin1_code":"16",
    "gn:admin2_code":"PI",
    "gn:admin3_code":"50011.0",
    "gn:asciiname":"Bagno A Morbo",
    "gn:country_code":"IT",
    "gn:dem":455,
    "gn:feature_class":"P",
    "gn:feature_code":"PPL",
    "gn:name":"Bagno A Morbo",
    "gn:population":29,
    "gn:timezone":"Europe/Rome",
    "iso:country":"IT",
    "wof:name":"Bagno A Morbo",
    "wof:placetype":"locality",
    "wof:population":29
},
  "geometry": {"coordinates":[10.88716,43.22755],"type":"Point"}
}