{
  "type": "Feature",
  "properties": {
    "gn:admin1_code":"16.0",
    "gn:admin2_code":"SI",
    "gn:admin3_code":"52036.0",
    "gn:asciiname":"Sant'Ambrogio",
    "gn:country_code":"IT",
    "gn:dem":406,
    "gn:feature_class":"P",
    "gn:feature_code":"PPL",
    "gn:name":"Sant'Ambrogio",
    "gn:population":0,
    "gn:timezone":"Europe/Rome",
    "iso:country":"IT",
    "wof:name":"Sant'Ambrogio",
    "wof:placetype":"locality"
},
  "geometry": {"coordinates":[11.68333,43.11667],"type":"Point"}
}