{
  "type": "Feature",
  "properties": {
    "gn:admin1_code":"10",
    "gn:admin2_code":"PU",
    "gn:admin3_code":"41038.0",
    "gn:asciiname":"Padana",
    "gn:country_code":"IT",
    "gn:dem":44,
    "gn:feature_class":"P",
    "gn:feature_code":"PPL",
    "gn:name":"Padana",
    "gn:population":41,
    "gn:timezone":"Europe/Rome",
    "iso:country":"IT",
    "wof:name":"Padana",
    "wof:placetype":"locality",
    "wof:population":41
},
  "geometry": {"coordinates":[13.09229,43.72186],"type":"Point"}
}