{
  "type": "Feature",
  "properties": {
    "gn:admin1_code":"18.0",
    "gn:admin2_code":"TR",
    "gn:admin3_code":"55022.0",
    "gn:asciiname":"Guadamello",
    "gn:country_code":"IT",
    "gn:dem":268,
    "gn:elevation":"275.0",
    "gn:feature_class":"P",
    "gn:feature_code":"PPL",
    "gn:name":"Guadamello",
    "gn:population":203,
    "gn:timezone":"Europe/Rome",
    "iso:country":"IT",
    "wof:name":"Guadamello",
    "wof:placetype":"locality",
    "wof:population":203
},
  "geometry": {"coordinates":[12.44386,42.44836],"type":"Point"}
}