{
  "type": "Feature",
  "properties": {
    "gn:admin1_code":"6",
    "gn:admin2_code":"PN",
    "gn:admin3_code":"93010.0",
    "gn:asciiname":"Sile",
    "gn:country_code":"IT",
    "gn:dem":29,
    "gn:feature_class":"P",
    "gn:feature_code":"PPL",
    "gn:name":"Sile",
    "gn:population":102,
    "gn:timezone":"Europe/Rome",
    "iso:country":"IT",
    "wof:name":"Sile",
    "wof:placetype":"locality",
    "wof:population":102
},
  "geometry": {"coordinates":[12.79934,45.94631],"type":"Point"}
}