{
  "type": "Feature",
  "properties": {
    "gn:admin1_code":"1.0",
    "gn:admin2_code":"CH",
    "gn:admin3_code":"69073.0",
    "gn:asciiname":"Cappuccini",
    "gn:country_code":"IT",
    "gn:dem":560,
    "gn:feature_class":"P",
    "gn:feature_code":"PPL",
    "gn:name":"Cappuccini",
    "gn:population":3,
    "gn:timezone":"Europe/Rome",
    "iso:country":"IT",
    "wof:name":"Cappuccini",
    "wof:placetype":"locality",
    "wof:population":3
},
  "geometry": {"coordinates":[14.12311,42.24054],"type":"Point"}
}