{
  "type": "Feature",
  "properties": {
    "gn:admin1_code":"12.0",
    "gn:admin2_code":"AT",
    "gn:admin3_code":"5112.0",
    "gn:asciiname":"Villata",
    "gn:country_code":"IT",
    "gn:dem":322,
    "gn:elevation":"325.0",
    "gn:feature_class":"P",
    "gn:feature_code":"PPL",
    "gn:name":"Villata",
    "gn:population":128,
    "gn:timezone":"Europe/Rome",
    "iso:country":"IT",
    "name:ara_x_preferred":[
        "\u0641\u064a\u0644\u0627\u062a\u0627"
    ],
    "name:azb_x_preferred":[
        "\u0648\u06cc\u0644\u0627\u062a\u0627"
    ],
    "name:bar_x_preferred":[
        "Villata"
    ],
    "name:bul_x_preferred":[
        "\u0412\u0438\u043b\u0430\u0442\u0430"
    ],
    "name:ceb_x_preferred":[
        "Villata"
    ],
    "name:ces_x_preferred":[
        "Villata"
    ],
    "name:deu_x_preferred":[
        "Villata"
    ],
    "name:epo_x_preferred":[
        "Villata"
    ],
    "name:eus_x_preferred":[
        "Villata"
    ],
    "name:fas_x_preferred":[
        "\u0648\u06cc\u0644\u0627\u062a\u0627"
    ],
    "name:fra_x_preferred":[
        "Villata"
    ],
    "name:hun_x_preferred":[
        "Villata"
    ],
    "name:hye_x_preferred":[
        "\u054e\u056b\u056c\u0561\u057f\u0561"
    ],
    "name:ind_x_preferred":[
        "Villata"
    ],
    "name:ita_x_preferred":[
        "Villata"
    ],
    "name:jpn_x_preferred":[
        "\u30f4\u30a3\u30c3\u30e9\u30fc\u30bf"
    ],
    "name:lat_x_preferred":[
        "Villata"
    ],
    "name:lmo_x_preferred":[
        "La Vilata"
    ],
    "name:msa_x_preferred":[
        "Villata"
    ],
    "name:nap_x_preferred":[
        "Villata"
    ],
    "name:nld_x_preferred":[
        "Villata"
    ],
    "name:pms_x_preferred":[
        "La Vilata"
    ],
    "name:pol_x_preferred":[
        "Villata"
    ],
    "name:por_x_preferred":[
        "Villata"
    ],
    "name:ron_x_preferred":[
        "Villata"
    ],
    "name:scn_x_preferred":[
        "Villata"
    ],
    "name:spa_x_preferred":[
        "Villata"
    ],
    "name:srp_x_preferred":[
        "\u0412\u0438\u043b\u0430\u0442\u0430"
    ],
    "name:swe_x_preferred":[
        "Villata"
    ],
    "name:tgl_x_preferred":[
        "Villata"
    ],
    "name:ukr_x_preferred":[
        "\u0412\u0456\u043b\u043b\u0430\u0442\u0430"
    ],
    "name:vie_x_preferred":[
        "Villata"
    ],
    "name:vol_x_preferred":[
        "Villata"
    ],
    "name:war_x_preferred":[
        "Villata"
    ],
    "name:zho_x_preferred":[
        "\u7ef4\u62c9\u5854"
    ],
    "wof:name":"Villata",
    "wof:placetype":"locality",
    "wof:population":128
},
  "geometry": {"coordinates":[7.96598,44.86868],"type":"Point"}
}