{
  "type": "Feature",
  "properties": {
    "gn:admin1_code":"12.0",
    "gn:admin2_code":"AT",
    "gn:admin3_code":"5112.0",
    "gn:asciiname":"Villata",
    "gn:country_code":"IT",
    "gn:dem":322,
    "gn:elevation":"325.0",
    "gn:feature_class":"P",
    "gn:feature_code":"PPL",
    "gn:name":"Villata",
    "gn:population":128,
    "gn:timezone":"Europe/Rome",
    "iso:country":"IT",
    "wof:name":"Villata",
    "wof:placetype":"locality",
    "wof:population":128
},
  "geometry": {"coordinates":[7.96598,44.86868],"type":"Point"}
}