{
  "type": "Feature",
  "properties": {
    "gn:admin1_code":"16.0",
    "gn:admin2_code":"AR",
    "gn:admin3_code":"51002.0",
    "gn:asciiname":"Santa Firmina",
    "gn:country_code":"IT",
    "gn:dem":272,
    "gn:feature_class":"P",
    "gn:feature_code":"PPL",
    "gn:name":"Santa Firmina",
    "gn:population":0,
    "gn:timezone":"Europe/Rome",
    "iso:country":"IT",
    "wof:name":"Santa Firmina",
    "wof:placetype":"locality"
},
  "geometry": {"coordinates":[11.88333,43.43333],"type":"Point"}
}