{
  "type": "Feature",
  "properties": {
    "gn:admin1_code":"6.0",
    "gn:admin2_code":"PN",
    "gn:admin3_code":"93009.0",
    "gn:asciiname":"Stavena",
    "gn:country_code":"IT",
    "gn:dem":49,
    "gn:feature_class":"P",
    "gn:feature_code":"PPL",
    "gn:name":"Staven\u00e0",
    "gn:population":0,
    "gn:timezone":"Europe/Rome",
    "iso:country":"IT",
    "wof:name":"Stavena",
    "wof:placetype":"locality"
},
  "geometry": {"coordinates":[12.43167,45.96444],"type":"Point"}
}