{
  "type": "Feature",
  "properties": {
    "gn:admin1_code":"9",
    "gn:admin2_code":"MN",
    "gn:admin3_code":"20015.0",
    "gn:asciiname":"Villa",
    "gn:country_code":"IT",
    "gn:dem":49,
    "gn:feature_class":"P",
    "gn:feature_code":"PPL",
    "gn:name":"Villa",
    "gn:population":49,
    "gn:timezone":"Europe/Rome",
    "iso:country":"IT",
    "wof:name":"Villa",
    "wof:placetype":"locality",
    "wof:population":49
},
  "geometry": {"coordinates":[10.43662,45.27958],"type":"Point"}
}