{
  "type": "Feature",
  "properties": {
    "gn:admin1_code":"5",
    "gn:admin2_code":"FE",
    "gn:admin3_code":"38010.0",
    "gn:asciiname":"Giovanna",
    "gn:country_code":"IT",
    "gn:dem":-3,
    "gn:feature_class":"P",
    "gn:feature_code":"PPL",
    "gn:name":"Giovanna",
    "gn:population":22,
    "gn:timezone":"Europe/Rome",
    "iso:country":"IT",
    "name:bre_x_preferred":[
        "Giovanna"
    ],
    "name:deu_x_preferred":[
        "Giovanna"
    ],
    "name:ita_x_preferred":[
        "Giovanna"
    ],
    "name:jpn_x_preferred":[
        "\u30b8\u30e7\u30f4\u30a1\u30f3\u30ca"
    ],
    "name:spa_x_preferred":[
        "Giovanna"
    ],
    "name:swe_x_preferred":[
        "Giovanna"
    ],
    "wof:name":"Giovanna",
    "wof:placetype":"locality",
    "wof:population":22
},
  "geometry": {"coordinates":[11.99437,44.90836],"type":"Point"}
}