{
  "type": "Feature",
  "properties": {
    "gn:admin1_code":"5",
    "gn:admin2_code":"BO",
    "gn:admin3_code":"37037.0",
    "gn:asciiname":"Tombazza",
    "gn:country_code":"IT",
    "gn:dem":13,
    "gn:feature_class":"P",
    "gn:feature_code":"PPL",
    "gn:name":"Tombazza",
    "gn:population":11,
    "gn:timezone":"Europe/Rome",
    "iso:country":"IT",
    "wof:name":"Tombazza",
    "wof:placetype":"locality",
    "wof:population":11
},
  "geometry": {"coordinates":[11.66908,44.50264],"type":"Point"}
}