{
  "type": "Feature",
  "properties": {
    "gn:admin1_code":"3.0",
    "gn:admin2_code":"RC",
    "gn:admin3_code":"80092.0",
    "gn:asciiname":"Case Acelli",
    "gn:country_code":"IT",
    "gn:dem":854,
    "gn:feature_class":"P",
    "gn:feature_code":"PPL",
    "gn:name":"Case Acelli",
    "gn:population":0,
    "gn:timezone":"Europe/Rome",
    "iso:country":"IT",
    "wof:name":"Case Acelli",
    "wof:placetype":"locality"
},
  "geometry": {"coordinates":[16.41667,38.53333],"type":"Point"}
}