{
  "type": "Feature",
  "properties": {
    "gn:admin1_code":"12.0",
    "gn:admin2_code":"TO",
    "gn:admin3_code":"1063.0",
    "gn:asciiname":"Mercatone",
    "gn:country_code":"IT",
    "gn:dem":245,
    "gn:feature_class":"P",
    "gn:feature_code":"PPLL",
    "gn:name":"Mercatone",
    "gn:population":2,
    "gn:timezone":"Europe/Rome",
    "iso:country":"IT",
    "wof:name":"Mercatone",
    "wof:placetype":"locality",
    "wof:population":2
},
  "geometry": {"coordinates":[7.70298,45.1615],"type":"Point"}
}