{
  "type": "Feature",
  "properties": {
    "gn:admin1_code":"5",
    "gn:admin2_code":"FE",
    "gn:admin3_code":"38009.0",
    "gn:asciiname":"Naldine",
    "gn:country_code":"IT",
    "gn:dem":-1,
    "gn:feature_class":"P",
    "gn:feature_code":"PPL",
    "gn:name":"Naldine",
    "gn:population":17,
    "gn:timezone":"Europe/Rome",
    "iso:country":"IT",
    "wof:name":"Naldine",
    "wof:placetype":"locality",
    "wof:population":17
},
  "geometry": {"coordinates":[11.8545,44.85059],"type":"Point"}
}