{
  "type": "Feature",
  "properties": {
    "gn:admin1_code":"10",
    "gn:admin2_code":"MC",
    "gn:admin3_code":"43023.0",
    "gn:asciiname":"Santo Stefano",
    "gn:country_code":"IT",
    "gn:dem":234,
    "gn:feature_class":"P",
    "gn:feature_code":"PPL",
    "gn:name":"Santo Stefano",
    "gn:population":12,
    "gn:timezone":"Europe/Rome",
    "iso:country":"IT",
    "wof:name":"Santo Stefano",
    "wof:placetype":"locality",
    "wof:population":12
},
  "geometry": {"coordinates":[13.45305,43.30837],"type":"Point"}
}