{
  "type": "Feature",
  "properties": {
    "gn:admin1_code":"10",
    "gn:admin2_code":"MC",
    "gn:admin3_code":"43023.0",
    "gn:asciiname":"Santo Stefano",
    "gn:country_code":"IT",
    "gn:dem":234,
    "gn:feature_class":"P",
    "gn:feature_code":"PPL",
    "gn:name":"Santo Stefano",
    "gn:population":12,
    "gn:timezone":"Europe/Rome",
    "iso:country":"IT",
    "name:ceb_x_preferred":[
        "Santo Stefano"
    ],
    "name:ces_x_preferred":[
        "Santo Stefano"
    ],
    "name:deu_x_preferred":[
        "Santo Stefano"
    ],
    "name:epo_x_preferred":[
        "Santo Stefano"
    ],
    "name:fra_x_preferred":[
        "Santo Stefano"
    ],
    "name:ita_x_preferred":[
        "Santo Stefano"
    ],
    "name:nld_x_preferred":[
        "Santo Stefano"
    ],
    "name:pms_x_preferred":[
        "San St\u00e9o"
    ],
    "name:pol_x_preferred":[
        "Santo Stefano"
    ],
    "name:por_x_preferred":[
        "Santo Stefano"
    ],
    "name:rus_x_preferred":[
        "\u0421\u0430\u043d\u0442\u043e-\u0421\u0442\u0435\u0444\u0430\u043d\u043e"
    ],
    "name:srp_x_preferred":[
        "\u0421\u0430\u043d\u0442\u043e \u0421\u0442\u0435\u0444\u0430\u043d\u043e"
    ],
    "name:swe_x_preferred":[
        "Santo Stefano"
    ],
    "wof:name":"Santo Stefano",
    "wof:placetype":"locality",
    "wof:population":12
},
  "geometry": {"coordinates":[13.45305,43.30837],"type":"Point"}
}