{
  "type": "Feature",
  "properties": {
    "gn:admin1_code":"5",
    "gn:admin2_code":"PR",
    "gn:admin3_code":"34040.0",
    "gn:asciiname":"Torre",
    "gn:country_code":"IT",
    "gn:dem":926,
    "gn:feature_class":"P",
    "gn:feature_code":"PPL",
    "gn:name":"Torre",
    "gn:population":17,
    "gn:timezone":"Europe/Rome",
    "iso:country":"IT",
    "wof:name":"Torre",
    "wof:placetype":"locality",
    "wof:population":17
},
  "geometry": {"coordinates":[9.48383,44.45378],"type":"Point"}
}