{
  "type": "Feature",
  "properties": {
    "gn:admin1_code":"8",
    "gn:admin2_code":"IM",
    "gn:admin3_code":"8047.0",
    "gn:asciiname":"Canneto",
    "gn:country_code":"IT",
    "gn:dem":275,
    "gn:feature_class":"P",
    "gn:feature_code":"PPL",
    "gn:name":"Canneto",
    "gn:population":23,
    "gn:timezone":"Europe/Rome",
    "iso:country":"IT",
    "name:ceb_x_preferred":[
        "Canneto"
    ],
    "name:deu_x_preferred":[
        "Canneto"
    ],
    "name:fra_x_preferred":[
        "Canneto"
    ],
    "name:ita_x_preferred":[
        "Canneto"
    ],
    "name:pms_x_preferred":[
        "Canneto"
    ],
    "name:srp_x_preferred":[
        "Kaneto"
    ],
    "name:swe_x_preferred":[
        "Canneto"
    ],
    "wof:name":"Canneto",
    "wof:placetype":"locality",
    "wof:population":23
},
  "geometry": {"coordinates":[7.93176,43.93157],"type":"Point"}
}