{
  "type": "Feature",
  "properties": {
    "gn:admin1_code":"5",
    "gn:admin2_code":"BO",
    "gn:admin3_code":"37051.0",
    "gn:asciiname":"Pian di Balestra",
    "gn:country_code":"IT",
    "gn:dem":1031,
    "gn:feature_class":"P",
    "gn:feature_code":"PPL",
    "gn:name":"Pian di Balestra",
    "gn:population":28,
    "gn:timezone":"Europe/Rome",
    "iso:country":"IT",
    "wof:name":"Pian di Balestra",
    "wof:placetype":"locality",
    "wof:population":28
},
  "geometry": {"coordinates":[11.25621,44.16427],"type":"Point"}
}