{
  "type": "Feature",
  "properties": {
    "iso:country":"IT",
    "name:dut_x_preferred":[
        "Isola"
    ],
    "name:eng_x_preferred":[
        "Isola"
    ],
    "name:fre_x_preferred":[
        "Isola"
    ],
    "name:ita_x_preferred":[
        "Isola"
    ],
    "name:lat_x_preferred":[
        "Insula"
    ],
    "name:spa_x_preferred":[
        "Isola"
    ],
    "wof:name":"Isola",
    "wof:placetype":"neighbourhood"
},
  "geometry": {"coordinates":[9.18861628098505,45.48942081264214],"type":"Point"}
}