{
  "type": "Feature",
  "properties": {
    "iso:country":"IT",
    "name:eng_x_preferred":[
        "Isola"
    ],
    "name:fra_x_preferred":[
        "Isola"
    ],
    "name:ita_x_preferred":[
        "Isola"
    ],
    "name:lat_x_preferred":[
        "Insula"
    ],
    "name:lmo_x_preferred":[
        "L'Isola"
    ],
    "name:nld_x_preferred":[
        "Isola"
    ],
    "name:spa_x_preferred":[
        "Isola"
    ],
    "wof:name":"Isola",
    "wof:placetype":"neighbourhood"
},
  "geometry": {"coordinates":[9.188616,45.489421],"type":"Point"}
}