{
  "type": "Feature",
  "properties": {
    "gn:admin1_code":"8.0",
    "gn:admin2_code":"SV",
    "gn:admin3_code":"9040.0",
    "gn:asciiname":"Piano",
    "gn:country_code":"IT",
    "gn:dem":520,
    "gn:feature_class":"P",
    "gn:feature_code":"PPLA3",
    "gn:name":"Piano",
    "gn:population":386,
    "gn:timezone":"Europe/Rome",
    "iso:country":"IT",
    "wof:name":"Piano",
    "wof:placetype":"locality",
    "wof:population":386
},
  "geometry": {"coordinates":[8.16639,44.3168],"type":"Point"}
}