{
  "type": "Feature",
  "properties": {
    "gn:admin1_code":"11",
    "gn:admin2_code":"CB",
    "gn:admin3_code":"70002.0",
    "gn:asciiname":"Canale",
    "gn:country_code":"IT",
    "gn:dem":694,
    "gn:feature_class":"P",
    "gn:feature_code":"PPL",
    "gn:name":"Canale",
    "gn:population":13,
    "gn:timezone":"Europe/Rome",
    "iso:country":"IT",
    "name:bel_x_preferred":[
        "\u041a\u0430\u043d\u0430\u043b\u0435"
    ],
    "name:ceb_x_preferred":[
        "Canale"
    ],
    "name:deu_x_preferred":[
        "Canale"
    ],
    "name:eus_x_preferred":[
        "Canale"
    ],
    "name:fra_x_preferred":[
        "Canale"
    ],
    "name:ind_x_preferred":[
        "Canale"
    ],
    "name:ita_x_preferred":[
        "Canale"
    ],
    "name:por_x_preferred":[
        "Canale"
    ],
    "name:rus_x_preferred":[
        "\u041a\u0430\u043d\u0430\u043b\u0435"
    ],
    "name:srp_x_preferred":[
        "\u041a\u0430\u043d\u0430\u043b\u0435"
    ],
    "name:swe_x_preferred":[
        "Canale"
    ],
    "wof:name":"Canale",
    "wof:placetype":"locality",
    "wof:population":13
},
  "geometry": {"coordinates":[14.55379,41.51919],"type":"Point"}
}