{
  "type": "Feature",
  "properties": {
    "gn:admin1_code":"3.0",
    "gn:admin2_code":"CS",
    "gn:admin3_code":"78132.0",
    "gn:asciiname":"Pastina",
    "gn:country_code":"IT",
    "gn:dem":111,
    "gn:feature_class":"P",
    "gn:feature_code":"PPL",
    "gn:name":"Pastina",
    "gn:population":403,
    "gn:timezone":"Europe/Rome",
    "iso:country":"IT",
    "name:ara_x_preferred":[
        "\u0628\u0627\u0633\u062a\u064a\u0646\u0627"
    ],
    "name:cat_x_preferred":[
        "\u015eehriye"
    ],
    "name:diq_x_preferred":[
        "\u015eahriyevan"
    ],
    "name:jpn_x_preferred":[
        "\u30d1\u30b9\u30c6\u30a3\u30fc\u30ca"
    ],
    "name:kor_x_preferred":[
        "\ud30c\uc2a4\ud2f0\ub098"
    ],
    "name:tur_x_preferred":[
        "\u015eehriye"
    ],
    "wof:name":"Pastina",
    "wof:placetype":"locality",
    "wof:population":403
},
  "geometry": {"coordinates":[15.84579,39.75974],"type":"Point"}
}