{
  "type": "Feature",
  "properties": {
    "gn:admin1_code":"3.0",
    "gn:admin2_code":"CS",
    "gn:admin3_code":"78132.0",
    "gn:asciiname":"Pastina",
    "gn:country_code":"IT",
    "gn:dem":111,
    "gn:feature_class":"P",
    "gn:feature_code":"PPL",
    "gn:name":"Pastina",
    "gn:population":403,
    "gn:timezone":"Europe/Rome",
    "iso:country":"IT",
    "wof:name":"Pastina",
    "wof:placetype":"locality",
    "wof:population":403
},
  "geometry": {"coordinates":[15.84579,39.75974],"type":"Point"}
}