{
  "type": "Feature",
  "properties": {
    "gn:admin1_code":"9",
    "gn:admin2_code":"SO",
    "gn:admin3_code":"14070.0",
    "gn:asciiname":"Fiorenza",
    "gn:country_code":"IT",
    "gn:dem":441,
    "gn:feature_class":"P",
    "gn:feature_code":"PPL",
    "gn:name":"Fiorenza",
    "gn:population":18,
    "gn:timezone":"Europe/Rome",
    "iso:country":"IT",
    "wof:name":"Fiorenza",
    "wof:placetype":"locality",
    "wof:population":18
},
  "geometry": {"coordinates":[9.95684,46.16955],"type":"Point"}
}