{
  "type": "Feature",
  "properties": {
    "gn:admin1_code":"12",
    "gn:admin2_code":"CN",
    "gn:admin3_code":"4024.0",
    "gn:asciiname":"Villaro",
    "gn:country_code":"IT",
    "gn:dem":595,
    "gn:feature_class":"P",
    "gn:feature_code":"PPL",
    "gn:name":"Villaro",
    "gn:population":25,
    "gn:timezone":"Europe/Rome",
    "iso:country":"IT",
    "wof:name":"Villaro",
    "wof:placetype":"locality",
    "wof:population":25
},
  "geometry": {"coordinates":[8.12322,44.62801],"type":"Point"}
}