{
  "type": "Feature",
  "properties": {
    "gn:admin1_code":"10",
    "gn:admin2_code":"PU",
    "gn:admin3_code":"41007.0",
    "gn:asciiname":"Naro",
    "gn:country_code":"IT",
    "gn:dem":272,
    "gn:feature_class":"P",
    "gn:feature_code":"PPL",
    "gn:name":"Naro",
    "gn:population":42,
    "gn:timezone":"Europe/Rome",
    "iso:country":"IT",
    "name:ara_x_preferred":[
        "\u0646\u0627\u0631\u0648"
    ],
    "name:azb_x_preferred":[
        "\u0646\u0627\u0631\u0648"
    ],
    "name:bul_x_preferred":[
        "\u041d\u0430\u0440\u043e"
    ],
    "name:cat_x_preferred":[
        "Naro"
    ],
    "name:ceb_x_preferred":[
        "Naro"
    ],
    "name:deu_x_preferred":[
        "Naro"
    ],
    "name:epo_x_preferred":[
        "Naro"
    ],
    "name:eus_x_preferred":[
        "Naro"
    ],
    "name:fas_x_preferred":[
        "\u0646\u0627\u0631\u0648"
    ],
    "name:fra_x_preferred":[
        "Naro"
    ],
    "name:hun_x_preferred":[
        "Naro"
    ],
    "name:hye_x_preferred":[
        "\u0546\u0561\u0580\u0578"
    ],
    "name:ind_x_preferred":[
        "Naro"
    ],
    "name:ita_x_preferred":[
        "Naro"
    ],
    "name:jpn_x_preferred":[
        "\u30ca\u30fc\u30ed"
    ],
    "name:kat_x_preferred":[
        "\u10dc\u10d0\u10e0\u10dd"
    ],
    "name:kaz_x_preferred":[
        "\u041d\u0430\u0440\u043e"
    ],
    "name:kor_x_preferred":[
        "\ub098\ub85c"
    ],
    "name:lat_x_preferred":[
        "Narum"
    ],
    "name:lmo_x_preferred":[
        "Naro"
    ],
    "name:msa_x_preferred":[
        "Naro"
    ],
    "name:nap_x_preferred":[
        "Naro"
    ],
    "name:nld_x_preferred":[
        "Naro"
    ],
    "name:pms_x_preferred":[
        "Naro"
    ],
    "name:pol_x_preferred":[
        "Naro"
    ],
    "name:por_x_preferred":[
        "Naro"
    ],
    "name:ron_x_preferred":[
        "Naro"
    ],
    "name:rus_x_preferred":[
        "\u041d\u0430\u0440\u043e"
    ],
    "name:scn_x_preferred":[
        "Naru"
    ],
    "name:spa_x_preferred":[
        "Naro"
    ],
    "name:srp_x_preferred":[
        "\u041d\u0430\u0440\u043e"
    ],
    "name:swe_x_preferred":[
        "Naro"
    ],
    "name:tgl_x_preferred":[
        "Naro"
    ],
    "name:ukr_x_preferred":[
        "\u041d\u0430\u0440\u043e"
    ],
    "name:uzb_x_preferred":[
        "Naro"
    ],
    "name:vie_x_preferred":[
        "Naro"
    ],
    "name:vol_x_preferred":[
        "Naro"
    ],
    "name:war_x_preferred":[
        "Naro"
    ],
    "wof:name":"Naro",
    "wof:placetype":"locality",
    "wof:population":42
},
  "geometry": {"coordinates":[12.5885,43.60183],"type":"Point"}
}