{
  "type": "Feature",
  "properties": {
    "gn:admin1_code":"10",
    "gn:admin2_code":"PU",
    "gn:admin3_code":"41007.0",
    "gn:asciiname":"Naro",
    "gn:country_code":"IT",
    "gn:dem":272,
    "gn:feature_class":"P",
    "gn:feature_code":"PPL",
    "gn:name":"Naro",
    "gn:population":42,
    "gn:timezone":"Europe/Rome",
    "iso:country":"IT",
    "wof:name":"Naro",
    "wof:placetype":"locality",
    "wof:population":42
},
  "geometry": {"coordinates":[12.5885,43.60183],"type":"Point"}
}