{
  "type": "Feature",
  "properties": {
    "gn:admin1_code":"10",
    "gn:admin2_code":"PU",
    "gn:admin3_code":"41007.0",
    "gn:asciiname":"Via Stratta",
    "gn:country_code":"IT",
    "gn:dem":545,
    "gn:feature_class":"P",
    "gn:feature_code":"PPLL",
    "gn:name":"Via Stratta",
    "gn:population":8,
    "gn:timezone":"Europe/Rome",
    "iso:country":"IT",
    "wof:name":"Via Stratta",
    "wof:placetype":"locality",
    "wof:population":8
},
  "geometry": {"coordinates":[12.59564,43.54606],"type":"Point"}
}