{
  "type": "Feature",
  "properties": {
    "gn:admin1_code":"12",
    "gn:admin2_code":"TO",
    "gn:admin3_code":"1039.0",
    "gn:asciiname":"Casa Coppa",
    "gn:country_code":"IT",
    "gn:dem":372,
    "gn:feature_class":"P",
    "gn:feature_code":"PPL",
    "gn:name":"Casa Coppa",
    "gn:population":25,
    "gn:timezone":"Europe/Rome",
    "iso:country":"IT",
    "wof:name":"Casa Coppa",
    "wof:placetype":"locality",
    "wof:population":25
},
  "geometry": {"coordinates":[8.08036,45.13117],"type":"Point"}
}