{
  "type": "Feature",
  "properties": {
    "gn:admin1_code":"3",
    "gn:admin2_code":"CS",
    "gn:admin3_code":"78070.0",
    "gn:asciiname":"Pirito di Pescara",
    "gn:country_code":"IT",
    "gn:dem":135,
    "gn:feature_class":"P",
    "gn:feature_code":"PPL",
    "gn:name":"Pirito di Pescara",
    "gn:population":88,
    "gn:timezone":"Europe/Rome",
    "iso:country":"IT",
    "wof:name":"Pirito di Pescara",
    "wof:placetype":"locality",
    "wof:population":88
},
  "geometry": {"coordinates":[16.26296,39.42136],"type":"Point"}
}