{
  "type": "Feature",
  "properties": {
    "gn:admin1_code":"13",
    "gn:admin2_code":"LE",
    "gn:admin3_code":"75036.0",
    "gn:asciiname":"Donadeo",
    "gn:country_code":"IT",
    "gn:dem":42,
    "gn:feature_class":"P",
    "gn:feature_code":"PPLL",
    "gn:name":"Donadeo",
    "gn:population":7,
    "gn:timezone":"Europe/Rome",
    "iso:country":"IT",
    "wof:name":"Donadeo",
    "wof:placetype":"locality",
    "wof:population":7
},
  "geometry": {"coordinates":[18.12895,40.31001],"type":"Point"}
}