{
  "type": "Feature",
  "properties": {
    "gn:admin1_code":"12",
    "gn:admin2_code":"TO",
    "gn:admin3_code":"1216.0",
    "gn:asciiname":"Le Moie",
    "gn:country_code":"IT",
    "gn:dem":565,
    "gn:feature_class":"P",
    "gn:feature_code":"PPL",
    "gn:name":"Le Moie",
    "gn:population":38,
    "gn:timezone":"Europe/Rome",
    "iso:country":"IT",
    "wof:name":"Le Moie",
    "wof:placetype":"locality",
    "wof:population":38
},
  "geometry": {"coordinates":[7.58809,45.35129000000001],"type":"Point"}
}