{
  "type": "Feature",
  "properties": {
    "gn:admin1_code":"12",
    "gn:admin2_code":"VB",
    "gn:admin3_code":"103054.0",
    "gn:asciiname":"Rumianca",
    "gn:country_code":"IT",
    "gn:dem":230,
    "gn:feature_class":"P",
    "gn:feature_code":"PPL",
    "gn:name":"Rumianca",
    "gn:population":319,
    "gn:timezone":"Europe/Rome",
    "iso:country":"IT",
    "wof:name":"Rumianca",
    "wof:placetype":"locality",
    "wof:population":319
},
  "geometry": {"coordinates":[8.28835,45.99339000000001],"type":"Point"}
}