{
  "type": "Feature",
  "properties": {
    "gn:admin1_code":"6",
    "gn:admin2_code":"UD",
    "gn:admin3_code":"30063.0",
    "gn:asciiname":"Borgo Marano Alto",
    "gn:country_code":"IT",
    "gn:dem":150,
    "gn:feature_class":"P",
    "gn:feature_code":"PPL",
    "gn:name":"Borgo Marano Alto",
    "gn:population":24,
    "gn:timezone":"Europe/Rome",
    "iso:country":"IT",
    "wof:name":"Borgo Marano Alto",
    "wof:placetype":"locality",
    "wof:population":24
},
  "geometry": {"coordinates":[13.17108,46.11045],"type":"Point"}
}