{
  "type": "Feature",
  "properties": {
    "gn:admin1_code":"13.0",
    "gn:admin2_code":"FG",
    "gn:admin3_code":"71008.0",
    "gn:asciiname":"Cagnano Varano",
    "gn:cc2":"IT",
    "gn:country_code":"IT",
    "gn:dem":156,
    "gn:elevation":"165.0",
    "gn:feature_class":"P",
    "gn:feature_code":"PPLA3",
    "gn:name":"Cagnano Varano",
    "gn:population":7309,
    "gn:timezone":"Europe/Rome",
    "iso:country":"IT",
    "name:eng_x_preferred":[
        "Cagnano Varano"
    ],
    "name:epo_x_preferred":[
        "Cagnano Varano"
    ],
    "name:fra_x_preferred":[
        "Cagnano Varano"
    ],
    "name:ita_x_preferred":[
        "Cagnano Varano"
    ],
    "name:nap_x_preferred":[
        "Cagnano Varano"
    ],
    "name:nld_x_preferred":[
        "Cagnano Varano"
    ],
    "name:pol_x_preferred":[
        "Cagnano Varano"
    ],
    "name:por_x_preferred":[
        "Cagnano Varano"
    ],
    "name:und_x_variant":[
        "Gagnano Varano"
    ],
    "wof:name":"Cagnano Varano",
    "wof:placetype":"locality",
    "wof:population":7309
},
  "geometry": {"coordinates":[15.77203,41.82832],"type":"Point"}
}