{
  "type": "Feature",
  "properties": {
    "gn:admin1_code":"7",
    "gn:admin2_code":"RI",
    "gn:admin3_code":"57027.0",
    "gn:asciiname":"Fonteluna",
    "gn:country_code":"IT",
    "gn:dem":215,
    "gn:feature_class":"P",
    "gn:feature_code":"PPL",
    "gn:name":"Fonteluna",
    "gn:population":41,
    "gn:timezone":"Europe/Rome",
    "iso:country":"IT",
    "wof:name":"Fonteluna",
    "wof:placetype":"locality",
    "wof:population":41
},
  "geometry": {"coordinates":[12.71355,42.20349],"type":"Point"}
}