{
  "type": "Feature",
  "properties": {
    "gn:admin1_code":"8",
    "gn:admin2_code":"IM",
    "gn:admin3_code":"8009.0",
    "gn:asciiname":"Lerici",
    "gn:country_code":"IT",
    "gn:dem":466,
    "gn:feature_class":"P",
    "gn:feature_code":"PPL",
    "gn:name":"Lerici",
    "gn:population":14,
    "gn:timezone":"Europe/Rome",
    "iso:country":"IT",
    "wof:name":"Lerici",
    "wof:placetype":"locality",
    "wof:population":14
},
  "geometry": {"coordinates":[7.9702,44.06399],"type":"Point"}
}