{
  "type": "Feature",
  "properties": {
    "gn:admin1_code":"8",
    "gn:admin2_code":"IM",
    "gn:admin3_code":"8009.0",
    "gn:asciiname":"Lerici",
    "gn:country_code":"IT",
    "gn:dem":466,
    "gn:feature_class":"P",
    "gn:feature_code":"PPL",
    "gn:name":"Lerici",
    "gn:population":14,
    "gn:timezone":"Europe/Rome",
    "iso:country":"IT",
    "name:azb_x_preferred":[
        "\u0644\u0631\u06cc\u06a9\u06cc"
    ],
    "name:bel_x_preferred":[
        "\u041b\u0435\u0440\u044b\u0447\u044b"
    ],
    "name:bul_x_preferred":[
        "\u041b\u0435\u0440\u0438\u0447\u0438"
    ],
    "name:cat_x_preferred":[
        "Lerici"
    ],
    "name:ceb_x_preferred":[
        "Lerici"
    ],
    "name:cym_x_preferred":[
        "Lerici"
    ],
    "name:deu_x_preferred":[
        "Lerici"
    ],
    "name:epo_x_preferred":[
        "Lerici"
    ],
    "name:eus_x_preferred":[
        "Lerici"
    ],
    "name:fas_x_preferred":[
        "\u0644\u0631\u06cc\u06a9\u06cc"
    ],
    "name:fra_x_preferred":[
        "Lerici"
    ],
    "name:hun_x_preferred":[
        "Lerici"
    ],
    "name:hye_x_preferred":[
        "\u053c\u0565\u0580\u056b\u0579\u056b"
    ],
    "name:ina_x_preferred":[
        "Lerici"
    ],
    "name:ita_x_preferred":[
        "Lerici"
    ],
    "name:jpn_x_preferred":[
        "\u30ec\u30fc\u30ea\u30c1"
    ],
    "name:kaz_x_preferred":[
        "\u041b\u0435\u0440\u0438\u0447\u0438"
    ],
    "name:lat_x_preferred":[
        "Erix"
    ],
    "name:lij_x_preferred":[
        "Lerze"
    ],
    "name:lmo_x_preferred":[
        "Lerici"
    ],
    "name:msa_x_preferred":[
        "Lerici"
    ],
    "name:nap_x_preferred":[
        "Lerici"
    ],
    "name:nld_x_preferred":[
        "Lerici"
    ],
    "name:nor_x_preferred":[
        "Lerici"
    ],
    "name:oci_x_preferred":[
        "Lerici"
    ],
    "name:pms_x_preferred":[
        "Lerici"
    ],
    "name:pol_x_preferred":[
        "Lerici"
    ],
    "name:por_x_preferred":[
        "Lerici"
    ],
    "name:ron_x_preferred":[
        "Lerici"
    ],
    "name:rus_x_preferred":[
        "\u041b\u0435\u0440\u0438\u0447\u0438"
    ],
    "name:scn_x_preferred":[
        "Lerici"
    ],
    "name:spa_x_preferred":[
        "Lerici"
    ],
    "name:srp_x_preferred":[
        "\u041b\u0435\u0440\u0438\u0447\u0438"
    ],
    "name:tur_x_preferred":[
        "Lerici"
    ],
    "name:ukr_x_preferred":[
        "\u041b\u0435\u0440\u0438\u0447\u0456"
    ],
    "name:uzb_x_preferred":[
        "Lerici"
    ],
    "name:vie_x_preferred":[
        "Lerici"
    ],
    "name:vol_x_preferred":[
        "Lerici"
    ],
    "name:war_x_preferred":[
        "Lerici"
    ],
    "name:zho_x_preferred":[
        "\u83b1\u91cc\u5947"
    ],
    "wof:name":"Lerici",
    "wof:placetype":"locality",
    "wof:population":14
},
  "geometry": {"coordinates":[7.9702,44.06399],"type":"Point"}
}