{
  "type": "Feature",
  "properties": {
    "gn:admin1_code":"12",
    "gn:admin2_code":"BI",
    "gn:admin3_code":"96058.0",
    "gn:asciiname":"Brianco",
    "gn:country_code":"IT",
    "gn:dem":228,
    "gn:feature_class":"P",
    "gn:feature_code":"PPL",
    "gn:name":"Brianco",
    "gn:population":17,
    "gn:timezone":"Europe/Rome",
    "iso:country":"IT",
    "wof:name":"Brianco",
    "wof:placetype":"locality",
    "wof:population":17
},
  "geometry": {"coordinates":[8.14134,45.4252],"type":"Point"}
}