{
  "type": "Feature",
  "properties": {
    "gn:admin1_code":"5.0",
    "gn:admin2_code":"RE",
    "gn:admin3_code":"35045.0",
    "gn:asciiname":"Cervarolo",
    "gn:country_code":"IT",
    "gn:dem":990,
    "gn:elevation":"977.0",
    "gn:feature_class":"P",
    "gn:feature_code":"PPL",
    "gn:name":"Cervarolo",
    "gn:population":35,
    "gn:timezone":"Europe/Rome",
    "iso:country":"IT",
    "wof:name":"Cervarolo",
    "wof:placetype":"locality",
    "wof:population":35
},
  "geometry": {"coordinates":[10.47887,44.27612],"type":"Point"}
}