{
  "type": "Feature",
  "properties": {
    "gn:admin1_code":"12",
    "gn:admin2_code":"AT",
    "gn:admin3_code":"5062.0",
    "gn:asciiname":"Campia",
    "gn:country_code":"IT",
    "gn:dem":252,
    "gn:feature_class":"P",
    "gn:feature_code":"PPL",
    "gn:name":"Campia",
    "gn:population":24,
    "gn:timezone":"Europe/Rome",
    "iso:country":"IT",
    "wof:name":"Campia",
    "wof:placetype":"locality",
    "wof:population":24
},
  "geometry": {"coordinates":[8.04345,44.95724000000001],"type":"Point"}
}