{
  "type": "Feature",
  "properties": {
    "gn:elevation":250,
    "gn:population":136,
    "iso:country":"IT",
    "name:arg_x_preferred":[
        "Soddie"
    ],
    "name:arm_x_preferred":[
        "\u054d\u0578\u0564\u056b"
    ],
    "name:baq_x_preferred":[
        "Soddi"
    ],
    "name:bel_x_preferred":[
        "\u0421\u043e\u0434\u0437\u0456"
    ],
    "name:bul_x_preferred":[
        "\u0421\u043e\u0434\u0438"
    ],
    "name:cat_x_preferred":[
        "Sodd\u00ec"
    ],
    "name:chi_x_preferred":[
        "\u7d22\u5fb7\u4f0a"
    ],
    "name:deu_x_preferred":[
        "Sodd\u00ec"
    ],
    "name:dut_x_preferred":[
        "Sodd\u00ec"
    ],
    "name:eng_x_preferred":[
        "Sodd\u00ec"
    ],
    "name:epo_x_preferred":[
        "Sodd\u00ec"
    ],
    "name:est_x_preferred":[
        "Sodd\u00ec"
    ],
    "name:eus_x_preferred":[
        "Sodd\u00ec"
    ],
    "name:eus_x_variant":[
        "Soddi"
    ],
    "name:fra_x_preferred":[
        "Sodd\u00ec"
    ],
    "name:fre_x_preferred":[
        "Sodd\u00ec"
    ],
    "name:ger_x_preferred":[
        "Sodd\u00ec"
    ],
    "name:hun_x_preferred":[
        "Sodd\u00ec"
    ],
    "name:ita_x_preferred":[
        "Sodd\u00ec"
    ],
    "name:ita_x_variant":[
        "Soddi"
    ],
    "name:jpn_x_preferred":[
        "\u30bd\u30c3\u30c7\u30a3"
    ],
    "name:kaz_x_preferred":[
        "\u0421\u043e\u0434\u0434\u0438"
    ],
    "name:lat_x_preferred":[
        "Soddinum"
    ],
    "name:lmo_x_preferred":[
        "Sodd\u00ec"
    ],
    "name:may_x_preferred":[
        "Sodd\u00ec"
    ],
    "name:nan_x_preferred":[
        "Sodd\u00ec"
    ],
    "name:nap_x_preferred":[
        "Sodd\u00ec"
    ],
    "name:nld_x_preferred":[
        "Sodd\u00ec"
    ],
    "name:per_x_preferred":[
        "\u0633\u0648\u062f\u06cc"
    ],
    "name:pms_x_preferred":[
        "Sodd\u00ec"
    ],
    "name:pol_x_preferred":[
        "Sodd\u00ec"
    ],
    "name:por_x_preferred":[
        "Sodd\u00ec"
    ],
    "name:rum_x_preferred":[
        "Sodd\u00ec"
    ],
    "name:rus_x_preferred":[
        "\u0421\u043e\u0434\u0434\u0438"
    ],
    "name:scn_x_preferred":[
        "Sodd\u00ec"
    ],
    "name:spa_x_preferred":[
        "Sodd\u00ec"
    ],
    "name:srd_x_preferred":[
        "Soddie"
    ],
    "name:srp_x_preferred":[
        "Sodd\u00ec"
    ],
    "name:tgl_x_preferred":[
        "Sodd\u00ec"
    ],
    "name:ukr_x_preferred":[
        "\u0421\u043e\u0434\u0434\u0456"
    ],
    "name:uzb_x_preferred":[
        "Sodd\u00ec"
    ],
    "name:vie_x_preferred":[
        "Sodd\u00ec"
    ],
    "name:vol_x_preferred":[
        "Sodd\u00ec"
    ],
    "name:war_x_preferred":[
        "Sodd\u00ec"
    ],
    "qs:a0":"Italia",
    "qs:a1":"*Oristano",
    "qs:a1r":"0Sardegna",
    "qs:adm0":"Italia",
    "qs:la_lc":"*",
    "qs:level":"locality",
    "qs:loc":"Soddi",
    "qs:loc_alt":"Soddi",
    "qs:pop":0,
    "qs:type":"buffered point",
    "wd:wordcount":73,
    "wof:lang":[
        "ita"
    ],
    "wof:name":"Soddi",
    "wof:placetype":"locality",
    "wof:population":136
},
  "geometry": {"coordinates":[8.87917,40.131389],"type":"Point"}
}