{
  "type": "Feature",
  "properties": {
    "gn:admin1_code":"3",
    "gn:admin2_code":"CS",
    "gn:admin3_code":"78020.0",
    "gn:asciiname":"Ficobianco",
    "gn:country_code":"IT",
    "gn:dem":302,
    "gn:feature_class":"P",
    "gn:feature_code":"PPL",
    "gn:name":"Ficobianco",
    "gn:population":204,
    "gn:timezone":"Europe/Rome",
    "iso:country":"IT",
    "wof:name":"Ficobianco",
    "wof:placetype":"locality",
    "wof:population":204
},
  "geometry": {"coordinates":[15.847,39.67474],"type":"Point"}
}