{
  "type": "Feature",
  "properties": {
    "gn:admin1_code":"5",
    "gn:admin2_code":"BO",
    "gn:admin3_code":"37050.0",
    "gn:asciiname":"Stelloni",
    "gn:country_code":"IT",
    "gn:dem":27,
    "gn:feature_class":"P",
    "gn:feature_code":"PPL",
    "gn:name":"Stelloni",
    "gn:population":77,
    "gn:timezone":"Europe/Rome",
    "iso:country":"IT",
    "wof:name":"Stelloni",
    "wof:placetype":"locality",
    "wof:population":77
},
  "geometry": {"coordinates":[11.24884,44.58318],"type":"Point"}
}