{
  "type": "Feature",
  "properties": {
    "gn:admin1_code":"1.0",
    "gn:admin2_code":"CH",
    "gn:admin3_code":"69039.0",
    "gn:asciiname":"Casale Panicotti",
    "gn:country_code":"IT",
    "gn:dem":878,
    "gn:feature_class":"P",
    "gn:feature_code":"PPL",
    "gn:name":"Casale Panicotti",
    "gn:population":16,
    "gn:timezone":"Europe/Rome",
    "iso:country":"IT",
    "wof:name":"Casale Panicotti",
    "wof:placetype":"locality",
    "wof:population":16
},
  "geometry": {"coordinates":[14.23135,41.89459],"type":"Point"}
}