{
  "type": "Feature",
  "properties": {
    "gn:admin1_code":"14.0",
    "gn:admin2_code":"NU",
    "gn:admin3_code":"91094.0",
    "gn:asciiname":"Su Cossu",
    "gn:cc2":"IT",
    "gn:country_code":"IT",
    "gn:dem":357,
    "gn:elevation":"348.0",
    "gn:feature_class":"P",
    "gn:feature_code":"PPL",
    "gn:name":"Su Cossu",
    "gn:population":84,
    "gn:timezone":"Europe/Rome",
    "iso:country":"IT",
    "name:und_x_variant":[
        "Cossu",
        "Su Cossu"
    ],
    "wof:name":"Su Cossu",
    "wof:placetype":"locality",
    "wof:population":84
},
  "geometry": {"coordinates":[9.60061,40.67429],"type":"Point"}
}