{
  "type": "Feature",
  "properties": {
    "gn:admin1_code":"5",
    "gn:admin2_code":"PC",
    "gn:admin3_code":"33030.0",
    "gn:asciiname":"Moglia",
    "gn:country_code":"IT",
    "gn:dem":715,
    "gn:feature_class":"P",
    "gn:feature_code":"PPL",
    "gn:name":"Moglia",
    "gn:population":17,
    "gn:timezone":"Europe/Rome",
    "iso:country":"IT",
    "name:azb_x_preferred":[
        "\u0645\u0648\u0644\u06cc\u0627"
    ],
    "name:bul_x_preferred":[
        "\u041c\u043e\u043b\u044f"
    ],
    "name:cat_x_preferred":[
        "Moglia"
    ],
    "name:ceb_x_preferred":[
        "Moglia"
    ],
    "name:cos_x_preferred":[
        "Moglia"
    ],
    "name:deu_x_preferred":[
        "Moglia"
    ],
    "name:eml_x_preferred":[
        "La M\u00f2ja"
    ],
    "name:epo_x_preferred":[
        "Moglia"
    ],
    "name:eus_x_preferred":[
        "Moglia"
    ],
    "name:fas_x_preferred":[
        "\u0645\u0648\u0644\u06cc\u0627"
    ],
    "name:fra_x_preferred":[
        "Moglia"
    ],
    "name:hun_x_preferred":[
        "Moglia"
    ],
    "name:hye_x_preferred":[
        "\u0544\u0578\u056c\u056b\u0561"
    ],
    "name:ind_x_preferred":[
        "Moglia"
    ],
    "name:ita_x_preferred":[
        "Moglia"
    ],
    "name:jpn_x_preferred":[
        "\u30e2\u30fc\u30ea\u30a2"
    ],
    "name:kaz_x_preferred":[
        "\u041c\u043e\u043b\u044c\u044f"
    ],
    "name:lat_x_preferred":[
        "Molea"
    ],
    "name:lmo_x_preferred":[
        "M\u00f2ia"
    ],
    "name:msa_x_preferred":[
        "Mogila"
    ],
    "name:nap_x_preferred":[
        "Moglia"
    ],
    "name:nld_x_preferred":[
        "Moglia"
    ],
    "name:oci_x_preferred":[
        "Moglia"
    ],
    "name:pms_x_preferred":[
        "Moglia"
    ],
    "name:pol_x_preferred":[
        "Moglia"
    ],
    "name:por_x_preferred":[
        "Moglia"
    ],
    "name:ron_x_preferred":[
        "Moglia"
    ],
    "name:rus_x_preferred":[
        "\u041c\u043e\u043b\u044c\u044f"
    ],
    "name:scn_x_preferred":[
        "Moglia"
    ],
    "name:spa_x_preferred":[
        "Moglia"
    ],
    "name:tgl_x_preferred":[
        "Moglia"
    ],
    "name:ukr_x_preferred":[
        "\u041c\u043e\u043b\u044c\u044f"
    ],
    "name:uzb_x_preferred":[
        "Moglia"
    ],
    "name:vie_x_preferred":[
        "Moglia"
    ],
    "name:vol_x_preferred":[
        "Moglia"
    ],
    "name:war_x_preferred":[
        "Moglia"
    ],
    "name:zho_x_preferred":[
        "\u83ab\u5229\u4e9a"
    ],
    "wof:name":"Moglia",
    "wof:placetype":"locality",
    "wof:population":17
},
  "geometry": {"coordinates":[9.34543,44.61293],"type":"Point"}
}