{
  "type": "Feature",
  "properties": {
    "gn:admin1_code":"7.0",
    "gn:admin2_code":"RI",
    "gn:admin3_code":"57002.0",
    "gn:asciiname":"San Lorenzo e Flaviano",
    "gn:country_code":"IT",
    "gn:dem":926,
    "gn:feature_class":"P",
    "gn:feature_code":"PPL",
    "gn:name":"San Lorenzo e Flaviano",
    "gn:population":48,
    "gn:timezone":"Europe/Rome",
    "iso:country":"IT",
    "wof:name":"San Lorenzo e Flaviano",
    "wof:placetype":"locality",
    "wof:population":48
},
  "geometry": {"coordinates":[13.28676,42.6648],"type":"Point"}
}