{
  "type": "Feature",
  "properties": {
    "gn:admin1_code":"16.0",
    "gn:admin2_code":"SI",
    "gn:admin3_code":"52031.0",
    "gn:asciiname":"Castiglioncello del Trinoro",
    "gn:country_code":"IT",
    "gn:dem":788,
    "gn:elevation":"786.0",
    "gn:feature_class":"P",
    "gn:feature_code":"PPL",
    "gn:name":"Castiglioncello del Trinoro",
    "gn:population":13,
    "gn:timezone":"Europe/Rome",
    "iso:country":"IT",
    "wof:name":"Castiglioncello del Trinoro",
    "wof:placetype":"locality",
    "wof:population":13
},
  "geometry": {"coordinates":[11.81315,42.99156],"type":"Point"}
}