{
  "type": "Feature",
  "properties": {
    "gn:admin1_code":"9",
    "gn:admin2_code":"PV",
    "gn:admin3_code":"18111.0",
    "gn:asciiname":"Cerrone",
    "gn:country_code":"IT",
    "gn:dem":254,
    "gn:feature_class":"P",
    "gn:feature_code":"PPL",
    "gn:name":"Cerrone",
    "gn:population":18,
    "gn:timezone":"Europe/Rome",
    "iso:country":"IT",
    "name:bul_x_preferred":[
        "\u041c\u0430\u0440\u043a \u0421\u0435\u0440\u043e\u043d"
    ],
    "name:deu_x_preferred":[
        "Cerrone"
    ],
    "name:fra_x_preferred":[
        "Marc Cerrone"
    ],
    "name:hun_x_preferred":[
        "Cerrone"
    ],
    "name:ido_x_preferred":[
        "Jean-Marc Cerrone"
    ],
    "name:ita_x_preferred":[
        "Cerrone"
    ],
    "name:nld_x_preferred":[
        "Cerrone"
    ],
    "name:por_x_preferred":[
        "Cerrone"
    ],
    "name:spa_x_preferred":[
        "Cerrone"
    ],
    "name:swe_x_preferred":[
        "Cerrone"
    ],
    "name:tur_x_preferred":[
        "Cerrone"
    ],
    "wof:name":"Cerrone",
    "wof:placetype":"locality",
    "wof:population":18
},
  "geometry": {"coordinates":[9.24842,45.00412],"type":"Point"}
}