{
  "type": "Feature",
  "properties": {
    "gn:admin1_code":"12.0",
    "gn:admin2_code":"TO",
    "gn:admin3_code":"1019.0",
    "gn:asciiname":"Chialambertetto",
    "gn:country_code":"IT",
    "gn:dem":1364,
    "gn:feature_class":"P",
    "gn:feature_code":"PPLL",
    "gn:name":"Chialambertetto",
    "gn:population":4,
    "gn:timezone":"Europe/Rome",
    "iso:country":"IT",
    "wof:name":"Chialambertetto",
    "wof:placetype":"locality",
    "wof:population":4
},
  "geometry": {"coordinates":[7.2324,45.305],"type":"Point"}
}