{
  "type": "Feature",
  "properties": {
    "gn:admin1_code":"5",
    "gn:admin2_code":"PR",
    "gn:admin3_code":"34027.0",
    "gn:asciiname":"Osteria San Martino",
    "gn:country_code":"IT",
    "gn:dem":35,
    "gn:feature_class":"P",
    "gn:feature_code":"PPL",
    "gn:name":"Osteria San Martino",
    "gn:population":43,
    "gn:timezone":"Europe/Rome",
    "iso:country":"IT",
    "wof:name":"Osteria San Martino",
    "wof:placetype":"locality",
    "wof:population":43
},
  "geometry": {"coordinates":[10.3452,44.86016],"type":"Point"}
}