{
  "type": "Feature",
  "properties": {
    "gn:admin1_code":"9.0",
    "gn:admin2_code":"MI",
    "gn:admin3_code":"15166.0",
    "gn:asciiname":"Paderno Dugnano",
    "gn:country_code":"IT",
    "gn:dem":166,
    "gn:elevation":"163.0",
    "gn:feature_class":"P",
    "gn:feature_code":"PPLA3",
    "gn:name":"Paderno Dugnano",
    "gn:population":46235,
    "gn:timezone":"Europe/Rome",
    "iso:country":"IT",
    "name:ara_x_preferred":[
        "\u0628\u0627\u062f\u064a\u0631\u0646\u0648 \u062f\u0648\u0646\u064a\u0627\u0646\u0648"
    ],
    "name:azb_x_preferred":[
        "\u067e\u0627\u062f\u0631\u0646\u0648 \u062f\u0648\u0646\u06cc\u0627\u0646\u0648"
    ],
    "name:bar_x_preferred":[
        "Paderno Dugnano"
    ],
    "name:bul_x_preferred":[
        "\u041f\u0430\u0434\u0435\u0440\u043d\u043e \u0414\u0443\u043d\u044f\u043d\u043e"
    ],
    "name:cat_x_preferred":[
        "Paderno Dugnano"
    ],
    "name:ceb_x_preferred":[
        "Paderno Dugnano"
    ],
    "name:deu_x_preferred":[
        "Paderno Dugnano"
    ],
    "name:eng_x_preferred":[
        "Paderno Dugnano"
    ],
    "name:epo_x_preferred":[
        "Paderno Dugnano"
    ],
    "name:eus_x_preferred":[
        "Paderno Dugnano"
    ],
    "name:fas_x_preferred":[
        "\u067e\u0627\u062f\u0631\u0646\u0648 \u062f\u0648\u0646\u06cc\u0627\u0646\u0648"
    ],
    "name:fra_x_preferred":[
        "Paderno Dugnano"
    ],
    "name:hun_x_preferred":[
        "Paderno Dugnano"
    ],
    "name:hye_x_preferred":[
        "\u054a\u0561\u0564\u0565\u0580\u0576\u0578 \u0534\u0578\u0582\u0576\u0575\u0561\u0576\u0578"
    ],
    "name:ita_x_preferred":[
        "Paderno Dugnano"
    ],
    "name:jpn_x_preferred":[
        "\u30d1\u30c7\u30eb\u30ce\u30fb\u30c9\u30a5\u30cb\u30e3\u30fc\u30ce"
    ],
    "name:kaz_x_preferred":[
        "\u041f\u0430\u0434\u0435\u0440\u043d\u043e-\u0414\u0443\u043d\u044c\u044f\u043d\u043e"
    ],
    "name:lat_x_preferred":[
        "Padernum Dugnanum"
    ],
    "name:lit_x_preferred":[
        "Paderno Dunjanas"
    ],
    "name:lmo_x_preferred":[
        "Paderna Dugnan"
    ],
    "name:msa_x_preferred":[
        "Paderno Dugnano"
    ],
    "name:nap_x_preferred":[
        "Paderno Dugnano"
    ],
    "name:nld_x_preferred":[
        "Paderno Dugnano"
    ],
    "name:pms_x_preferred":[
        "Paderno Dugnano"
    ],
    "name:pol_x_preferred":[
        "Paderno Dugnano"
    ],
    "name:por_x_preferred":[
        "Paderno Dugnano"
    ],
    "name:ron_x_preferred":[
        "Paderno Dugnano"
    ],
    "name:rus_x_preferred":[
        "\u041f\u0430\u0434\u0435\u0440\u043d\u043e-\u0414\u0443\u043d\u044c\u044f\u043d\u043e"
    ],
    "name:scn_x_preferred":[
        "Paderno Dugnano"
    ],
    "name:sco_x_preferred":[
        "Paderno Dugnano"
    ],
    "name:spa_x_preferred":[
        "Paderno Dugnano"
    ],
    "name:srp_x_preferred":[
        "\u041f\u0430\u0434\u0435\u0440\u043d\u043e \u0414\u0443\u045a\u0430\u043d\u043e"
    ],
    "name:tgl_x_preferred":[
        "Paderno Dugnano"
    ],
    "name:tur_x_preferred":[
        "Paderno Dugnano"
    ],
    "name:ukr_x_preferred":[
        "\u041f\u0430\u0434\u0435\u0440\u043d\u043e-\u0414\u0443\u043d\u044c\u044f\u043d\u043e"
    ],
    "name:uzb_x_preferred":[
        "Paderno Dugnano"
    ],
    "name:vie_x_preferred":[
        "Paderno Dugnano"
    ],
    "name:vol_x_preferred":[
        "Paderno Dugnano"
    ],
    "name:war_x_preferred":[
        "Paderno Dugnano"
    ],
    "wof:name":"Paderno Dugnano",
    "wof:placetype":"locality",
    "wof:population":46235
},
  "geometry": {"coordinates":[9.16483,45.56899],"type":"Point"}
}