{
  "type": "Feature",
  "properties": {
    "gn:admin1_code":"9.0",
    "gn:admin2_code":"MI",
    "gn:admin3_code":"15166.0",
    "gn:asciiname":"Paderno Dugnano",
    "gn:country_code":"IT",
    "gn:dem":166,
    "gn:elevation":"163.0",
    "gn:feature_class":"P",
    "gn:feature_code":"PPLA3",
    "gn:name":"Paderno Dugnano",
    "gn:population":46235,
    "gn:timezone":"Europe/Rome",
    "iso:country":"IT",
    "name:eng_x_preferred":[
        "Paderno Dugnano"
    ],
    "name:epo_x_preferred":[
        "Paderno Dugnano"
    ],
    "name:fra_x_preferred":[
        "Paderno Dugnano"
    ],
    "name:ita_x_preferred":[
        "Paderno Dugnano"
    ],
    "name:jpn_x_preferred":[
        "\u30d1\u30c7\u30eb\u30ce\u30fb\u30c9\u30a5\u30cb\u30e3\u30fc\u30ce"
    ],
    "name:nap_x_preferred":[
        "Paderno Dugnano"
    ],
    "name:nld_x_preferred":[
        "Paderno Dugnano"
    ],
    "name:pol_x_preferred":[
        "Paderno Dugnano"
    ],
    "name:por_x_preferred":[
        "Paderno Dugnano"
    ],
    "wof:name":"Paderno Dugnano",
    "wof:placetype":"locality",
    "wof:population":46235
},
  "geometry": {"coordinates":[9.16483,45.56899],"type":"Point"}
}