{
  "type": "Feature",
  "properties": {
    "gn:admin1_code":"9",
    "gn:admin2_code":"LC",
    "gn:admin3_code":"97015.0",
    "gn:asciiname":"Paglio",
    "gn:country_code":"IT",
    "gn:dem":1361,
    "gn:feature_class":"P",
    "gn:feature_code":"PPLL",
    "gn:name":"Paglio",
    "gn:population":7,
    "gn:timezone":"Europe/Rome",
    "iso:country":"IT",
    "wof:name":"Paglio",
    "wof:placetype":"locality",
    "wof:population":7
},
  "geometry": {"coordinates":[9.40391,46.0413],"type":"Point"}
}