{
  "type": "Feature",
  "properties": {
    "gn:admin1_code":"8.0",
    "gn:admin2_code":"IM",
    "gn:admin3_code":"8064.0",
    "gn:asciiname":"Pianavia",
    "gn:country_code":"IT",
    "gn:dem":389,
    "gn:elevation":"392.0",
    "gn:feature_class":"P",
    "gn:feature_code":"PPL",
    "gn:name":"Pianavia",
    "gn:population":33,
    "gn:timezone":"Europe/Rome",
    "iso:country":"IT",
    "wof:name":"Pianavia",
    "wof:placetype":"locality",
    "wof:population":33
},
  "geometry": {"coordinates":[7.94432,43.94522],"type":"Point"}
}