{
  "type": "Feature",
  "properties": {
    "gn:admin1_code":"16",
    "gn:admin2_code":"PI",
    "gn:admin3_code":"50014.0",
    "gn:asciiname":"Villa Petri (Montalto)",
    "gn:country_code":"IT",
    "gn:dem":77,
    "gn:feature_class":"P",
    "gn:feature_code":"PPLL",
    "gn:name":"Villa Petri (Montalto)",
    "gn:population":7,
    "gn:timezone":"Europe/Rome",
    "iso:country":"IT",
    "wof:name":"Villa Petri (Montalto)",
    "wof:placetype":"locality",
    "wof:population":7
},
  "geometry": {"coordinates":[10.52605,43.56681],"type":"Point"}
}