{
  "type": "Feature",
  "properties": {
    "gn:admin1_code":"4.0",
    "gn:admin2_code":"SA",
    "gn:admin3_code":"65098.0",
    "gn:asciiname":"Cannicchio",
    "gn:country_code":"IT",
    "gn:dem":250,
    "gn:elevation":"230.0",
    "gn:feature_class":"P",
    "gn:feature_code":"PPL",
    "gn:name":"Cannicchio",
    "gn:population":149,
    "gn:timezone":"Europe/Rome",
    "iso:country":"IT",
    "wof:name":"Cannicchio",
    "wof:placetype":"locality",
    "wof:population":149
},
  "geometry": {"coordinates":[15.04295,40.19146],"type":"Point"}
}