{
  "type": "Feature",
  "properties": {
    "gn:admin1_code":"20",
    "gn:admin2_code":"VI",
    "gn:admin3_code":"24112.0",
    "gn:asciiname":"Righele",
    "gn:country_code":"IT",
    "gn:dem":390,
    "gn:feature_class":"P",
    "gn:feature_code":"PPL",
    "gn:name":"Righele",
    "gn:population":48,
    "gn:timezone":"Europe/Rome",
    "iso:country":"IT",
    "wof:name":"Righele",
    "wof:placetype":"locality",
    "wof:population":48
},
  "geometry": {"coordinates":[11.36294,45.87745],"type":"Point"}
}