{
  "type": "Feature",
  "properties": {
    "gn:admin1_code":"16",
    "gn:admin2_code":"FI",
    "gn:admin3_code":"48015.0",
    "gn:asciiname":"Ponte alla Badia",
    "gn:country_code":"IT",
    "gn:dem":85,
    "gn:feature_class":"P",
    "gn:feature_code":"PPL",
    "gn:name":"Ponte alla Badia",
    "gn:population":96,
    "gn:timezone":"Europe/Rome",
    "iso:country":"IT",
    "wof:name":"Ponte alla Badia",
    "wof:placetype":"locality",
    "wof:population":96
},
  "geometry": {"coordinates":[11.2797,43.8039],"type":"Point"}
}