{
  "type": "Feature",
  "properties": {
    "gn:admin1_code":"12",
    "gn:admin2_code":"TO",
    "gn:admin3_code":"1140.0",
    "gn:asciiname":"Possetti",
    "gn:country_code":"IT",
    "gn:dem":538,
    "gn:feature_class":"P",
    "gn:feature_code":"PPL",
    "gn:name":"Possetti",
    "gn:population":57,
    "gn:timezone":"Europe/Rome",
    "iso:country":"IT",
    "wof:name":"Possetti",
    "wof:placetype":"locality",
    "wof:population":57
},
  "geometry": {"coordinates":[7.23531,44.8019],"type":"Point"}
}