{
  "type": "Feature",
  "properties": {
    "gn:admin1_code":"5.0",
    "gn:admin2_code":"FC",
    "gn:admin3_code":"40003.0",
    "gn:asciiname":"Bracciano",
    "gn:country_code":"IT",
    "gn:dem":154,
    "gn:elevation":"152.0",
    "gn:feature_class":"P",
    "gn:feature_code":"PPL",
    "gn:name":"Bracciano",
    "gn:population":64,
    "gn:timezone":"Europe/Rome",
    "iso:country":"IT",
    "name:ara_x_preferred":[
        "\u0628\u0631\u0627\u062a\u0634\u064a\u0627\u0646\u0648"
    ],
    "name:azb_x_preferred":[
        "\u0628\u0631\u0627\u0686\u06cc\u0627\u0646\u0648"
    ],
    "name:bcl_x_preferred":[
        "Bracciano"
    ],
    "name:bre_x_preferred":[
        "Bracciano"
    ],
    "name:bul_x_preferred":[
        "\u0411\u0440\u0430\u0447\u0430\u043d\u043e"
    ],
    "name:cat_x_preferred":[
        "Bracciano"
    ],
    "name:ceb_x_preferred":[
        "Bracciano"
    ],
    "name:deu_x_preferred":[
        "Bracciano"
    ],
    "name:epo_x_preferred":[
        "Bracciano"
    ],
    "name:eus_x_preferred":[
        "Bracciano"
    ],
    "name:fas_x_preferred":[
        "\u0628\u0631\u0627\u0686\u06cc\u0627\u0646\u0648"
    ],
    "name:fra_x_preferred":[
        "Bracciano"
    ],
    "name:hun_x_preferred":[
        "Bracciano"
    ],
    "name:hye_x_preferred":[
        "\u0532\u0580\u0561\u0579\u056b\u0561\u0576\u0578"
    ],
    "name:ina_x_preferred":[
        "Bracciano"
    ],
    "name:ita_x_preferred":[
        "Bracciano"
    ],
    "name:jpn_x_preferred":[
        "\u30d6\u30e9\u30c3\u30c1\u30e3\u30fc\u30ce"
    ],
    "name:kor_x_preferred":[
        "\ube0c\ub77c\ucc28\ub178"
    ],
    "name:lat_x_preferred":[
        "Brachianum"
    ],
    "name:lmo_x_preferred":[
        "Bracciano"
    ],
    "name:msa_x_preferred":[
        "Bracciano"
    ],
    "name:nap_x_preferred":[
        "Bracciano"
    ],
    "name:nld_x_preferred":[
        "Bracciano"
    ],
    "name:pms_x_preferred":[
        "Bracciano"
    ],
    "name:pol_x_preferred":[
        "Bracciano"
    ],
    "name:por_x_preferred":[
        "Bracciano"
    ],
    "name:ron_x_preferred":[
        "Bracciano"
    ],
    "name:rus_x_preferred":[
        "\u0411\u0440\u0430\u0447\u0447\u0430\u043d\u043e"
    ],
    "name:scn_x_preferred":[
        "Braccianu"
    ],
    "name:sco_x_preferred":[
        "Bracciano"
    ],
    "name:spa_x_preferred":[
        "Bracciano"
    ],
    "name:srp_x_preferred":[
        "\u0411\u0440\u0430\u0447\u0430\u043d\u043e"
    ],
    "name:swe_x_preferred":[
        "Bracciano"
    ],
    "name:tur_x_preferred":[
        "Bracciano"
    ],
    "name:ukr_x_preferred":[
        "\u0411\u0440\u0430\u0447\u0447\u0430\u043d\u043e"
    ],
    "name:urd_x_preferred":[
        "\u0628\u0631\u0627\u0686\u06cc\u0627\u0646\u0648"
    ],
    "name:vol_x_preferred":[
        "Bracciano"
    ],
    "name:war_x_preferred":[
        "Bracciano"
    ],
    "name:zho_x_preferred":[
        "\u5e03\u62c9\u6070\u8bfa"
    ],
    "wof:name":"Bracciano",
    "wof:placetype":"locality",
    "wof:population":64
},
  "geometry": {"coordinates":[12.15958,44.13313],"type":"Point"}
}