{
  "type": "Feature",
  "properties": {
    "gn:admin1_code":"5.0",
    "gn:admin2_code":"FC",
    "gn:admin3_code":"40003.0",
    "gn:asciiname":"Bracciano",
    "gn:country_code":"IT",
    "gn:dem":154,
    "gn:elevation":"152.0",
    "gn:feature_class":"P",
    "gn:feature_code":"PPL",
    "gn:name":"Bracciano",
    "gn:population":64,
    "gn:timezone":"Europe/Rome",
    "iso:country":"IT",
    "wof:name":"Bracciano",
    "wof:placetype":"locality",
    "wof:population":64
},
  "geometry": {"coordinates":[12.15958,44.13313],"type":"Point"}
}