{
  "type": "Feature",
  "properties": {
    "gn:admin1_code":"7",
    "gn:admin2_code":"FR",
    "gn:admin3_code":"60042.0",
    "gn:asciiname":"Valle Careta",
    "gn:country_code":"IT",
    "gn:dem":503,
    "gn:feature_class":"P",
    "gn:feature_code":"PPL",
    "gn:name":"Valle Careta",
    "gn:population":34,
    "gn:timezone":"Europe/Rome",
    "iso:country":"IT",
    "wof:name":"Valle Careta",
    "wof:placetype":"locality",
    "wof:population":34
},
  "geometry": {"coordinates":[13.31425,41.78313],"type":"Point"}
}