{
  "type": "Feature",
  "properties": {
    "gn:admin1_code":"20.0",
    "gn:admin2_code":"TV",
    "gn:admin3_code":"26028.0",
    "gn:asciiname":"Colfrancui",
    "gn:country_code":"IT",
    "gn:dem":11,
    "gn:feature_class":"P",
    "gn:feature_code":"PPL",
    "gn:name":"Colfrancui",
    "gn:population":0,
    "gn:timezone":"Europe/Rome",
    "iso:country":"IT",
    "wof:name":"Colfrancui",
    "wof:placetype":"locality"
},
  "geometry": {"coordinates":[12.47,45.78722],"type":"Point"}
}