{
  "type": "Feature",
  "properties": {
    "gn:admin1_code":"20.0",
    "gn:admin2_code":"TV",
    "gn:admin3_code":"26056.0",
    "gn:asciiname":"Pieve",
    "gn:country_code":"IT",
    "gn:dem":156,
    "gn:feature_class":"P",
    "gn:feature_code":"PPL",
    "gn:name":"Pieve",
    "gn:population":0,
    "gn:timezone":"Europe/Rome",
    "iso:country":"IT",
    "name:cat_x_preferred":[
        "Pieve"
    ],
    "name:cos_x_preferred":[
        "Pieve"
    ],
    "name:deu_x_preferred":[
        "Pieve"
    ],
    "name:epo_x_preferred":[
        "Pievo"
    ],
    "name:fra_x_preferred":[
        "Pi\u00e8ve"
    ],
    "name:ita_x_preferred":[
        "Pieve"
    ],
    "name:lmo_x_preferred":[
        "Pi\u00e9f"
    ],
    "wof:name":"Pieve",
    "wof:placetype":"locality"
},
  "geometry": {"coordinates":[11.98333,45.86667],"type":"Point"}
}