{
  "type": "Feature",
  "properties": {
    "gn:admin1_code":"20",
    "gn:admin2_code":"TV",
    "gn:admin3_code":"26071.0",
    "gn:asciiname":"Borgo Verde (Bivio Cavrie)",
    "gn:country_code":"IT",
    "gn:dem":13,
    "gn:feature_class":"P",
    "gn:feature_code":"PPL",
    "gn:name":"Borgo Verde (Bivio Cavri\u00e8)",
    "gn:population":165,
    "gn:timezone":"Europe/Rome",
    "iso:country":"IT",
    "name:und_x_variant":[
        "Borgo Verde (Bivio Cavri\u00e8)"
    ],
    "wof:name":"Borgo Verde (Bivio Cavrie)",
    "wof:placetype":"locality",
    "wof:population":165
},
  "geometry": {"coordinates":[12.35837,45.68217],"type":"Point"}
}