{
  "type": "Feature",
  "properties": {
    "gn:admin1_code":"20",
    "gn:admin2_code":"VE",
    "gn:admin3_code":"27019.0",
    "gn:asciiname":"Ca' Costantini",
    "gn:country_code":"IT",
    "gn:dem":1,
    "gn:feature_class":"P",
    "gn:feature_code":"PPL",
    "gn:name":"Ca' Costantini",
    "gn:population":40,
    "gn:timezone":"Europe/Rome",
    "iso:country":"IT",
    "wof:name":"Ca' Costantini",
    "wof:placetype":"locality",
    "wof:population":40
},
  "geometry": {"coordinates":[12.58853,45.4883],"type":"Point"}
}