{
  "type": "Feature",
  "properties": {
    "gn:admin1_code":"3.0",
    "gn:admin2_code":"RC",
    "gn:admin3_code":"80025.0",
    "gn:asciiname":"Campoli Rupetti",
    "gn:country_code":"IT",
    "gn:dem":536,
    "gn:feature_class":"P",
    "gn:feature_code":"PPL",
    "gn:name":"Campoli Rupetti",
    "gn:population":109,
    "gn:timezone":"Europe/Rome",
    "iso:country":"IT",
    "wof:name":"Campoli Rupetti",
    "wof:placetype":"locality",
    "wof:population":109
},
  "geometry": {"coordinates":[16.40006,38.44668],"type":"Point"}
}