{
  "type": "Feature",
  "properties": {
    "gn:admin1_code":"5",
    "gn:admin2_code":"MO",
    "gn:admin3_code":"36022.0",
    "gn:asciiname":"Nocedella",
    "gn:country_code":"IT",
    "gn:dem":13,
    "gn:feature_class":"P",
    "gn:feature_code":"PPL",
    "gn:name":"Nocedella",
    "gn:population":53,
    "gn:timezone":"Europe/Rome",
    "iso:country":"IT",
    "wof:name":"Nocedella",
    "wof:placetype":"locality",
    "wof:population":53
},
  "geometry": {"coordinates":[11.05492,44.92362],"type":"Point"}
}