{
  "type": "Feature",
  "properties": {
    "gn:admin1_code":"5",
    "gn:admin2_code":"RA",
    "gn:admin3_code":"39017.0",
    "gn:asciiname":"Giardino",
    "gn:country_code":"IT",
    "gn:dem":10,
    "gn:feature_class":"P",
    "gn:feature_code":"PPL",
    "gn:name":"Giardino",
    "gn:population":15,
    "gn:timezone":"Europe/Rome",
    "iso:country":"IT",
    "name:deu_x_preferred":[
        "Giardino"
    ],
    "name:fra_x_preferred":[
        "Giardino"
    ],
    "name:ita_x_preferred":[
        "Giardino"
    ],
    "name:srp_x_preferred":[
        "Giardino"
    ],
    "wof:name":"Giardino",
    "wof:placetype":"locality",
    "wof:population":15
},
  "geometry": {"coordinates":[11.85109,44.44703],"type":"Point"}
}