{
  "type": "Feature",
  "properties": {
    "gn:admin1_code":"16.0",
    "gn:admin2_code":"LU",
    "gn:admin3_code":"46007.0",
    "gn:asciiname":"San Gennaro II-Lappato",
    "gn:country_code":"IT",
    "gn:dem":117,
    "gn:feature_class":"P",
    "gn:feature_code":"PPL",
    "gn:name":"San Gennaro II-Lappato",
    "gn:population":50,
    "gn:timezone":"Europe/Rome",
    "iso:country":"IT",
    "wof:name":"San Gennaro II-Lappato",
    "wof:placetype":"locality",
    "wof:population":50
},
  "geometry": {"coordinates":[10.65676,43.88985],"type":"Point"}
}