{
  "type": "Feature",
  "properties": {
    "gn:admin1_code":"4",
    "gn:admin2_code":"AV",
    "gn:admin3_code":"64046.0",
    "gn:asciiname":"Calzisi",
    "gn:country_code":"IT",
    "gn:dem":437,
    "gn:feature_class":"P",
    "gn:feature_code":"PPL",
    "gn:name":"Calzisi",
    "gn:population":44,
    "gn:timezone":"Europe/Rome",
    "iso:country":"IT",
    "wof:name":"Calzisi",
    "wof:placetype":"locality",
    "wof:population":44
},
  "geometry": {"coordinates":[14.84803,40.93646],"type":"Point"}
}