{
  "type": "Feature",
  "properties": {
    "gn:admin1_code":"3",
    "gn:admin2_code":"CS",
    "gn:admin3_code":"78091.0",
    "gn:asciiname":"Mulattiera",
    "gn:country_code":"IT",
    "gn:dem":230,
    "gn:feature_class":"P",
    "gn:feature_code":"PPL",
    "gn:name":"Mulattiera",
    "gn:population":23,
    "gn:timezone":"Europe/Rome",
    "iso:country":"IT",
    "wof:name":"Mulattiera",
    "wof:placetype":"locality",
    "wof:population":23
},
  "geometry": {"coordinates":[16.05589,39.33647],"type":"Point"}
}