{
  "type": "Feature",
  "properties": {
    "gn:admin1_code":"9",
    "gn:admin2_code":"VA",
    "gn:admin3_code":"12036.0",
    "gn:asciiname":"Fabricco",
    "gn:country_code":"IT",
    "gn:dem":256,
    "gn:feature_class":"P",
    "gn:feature_code":"PPL",
    "gn:name":"Fabricco",
    "gn:population":40,
    "gn:timezone":"Europe/Rome",
    "iso:country":"IT",
    "wof:name":"Fabricco",
    "wof:placetype":"locality",
    "wof:population":40
},
  "geometry": {"coordinates":[8.72341,45.77315],"type":"Point"}
}