{
  "type": "Feature",
  "properties": {
    "gn:admin1_code":"10",
    "gn:admin2_code":"PU",
    "gn:admin3_code":"41068.0",
    "gn:asciiname":"Ca' Labalia",
    "gn:country_code":"IT",
    "gn:dem":110,
    "gn:feature_class":"P",
    "gn:feature_code":"PPL",
    "gn:name":"Ca' Labalia",
    "gn:population":31,
    "gn:timezone":"Europe/Rome",
    "iso:country":"IT",
    "wof:name":"Ca' Labalia",
    "wof:placetype":"locality",
    "wof:population":31
},
  "geometry": {"coordinates":[12.72021,43.79476],"type":"Point"}
}