{
  "type": "Feature",
  "properties": {
    "gn:admin1_code":"15",
    "gn:admin2_code":"CL",
    "gn:admin3_code":"85014.0",
    "gn:asciiname":"Ciolino",
    "gn:country_code":"IT",
    "gn:dem":662,
    "gn:feature_class":"P",
    "gn:feature_code":"PPL",
    "gn:name":"Ciolino",
    "gn:population":21,
    "gn:timezone":"Europe/Rome",
    "iso:country":"IT",
    "wof:name":"Ciolino",
    "wof:placetype":"locality",
    "wof:population":21
},
  "geometry": {"coordinates":[14.0585,37.63974],"type":"Point"}
}