{
  "type": "Feature",
  "properties": {
    "gn:admin1_code":"19.0",
    "gn:admin2_code":"AO",
    "gn:admin3_code":"7020.0",
    "gn:asciiname":"Bellecombe",
    "gn:country_code":"IT",
    "gn:dem":1013,
    "gn:feature_class":"P",
    "gn:feature_code":"PPLL",
    "gn:name":"Bellecombe",
    "gn:population":4,
    "gn:timezone":"Europe/Rome",
    "iso:country":"IT",
    "wof:name":"Bellecombe",
    "wof:placetype":"locality",
    "wof:population":4
},
  "geometry": {"coordinates":[7.63135,45.72947],"type":"Point"}
}