{
  "type": "Feature",
  "properties": {
    "gn:admin1_code":"20",
    "gn:admin2_code":"PD",
    "gn:admin3_code":"28065.0",
    "gn:asciiname":"Cristo",
    "gn:country_code":"IT",
    "gn:dem":5,
    "gn:feature_class":"P",
    "gn:feature_code":"PPL",
    "gn:name":"Cristo",
    "gn:population":97,
    "gn:timezone":"Europe/Rome",
    "iso:country":"IT",
    "name:ceb_x_preferred":[
        "Cristo"
    ],
    "name:deu_x_preferred":[
        "Cristo"
    ],
    "name:ita_x_preferred":[
        "Cristo"
    ],
    "name:srp_x_preferred":[
        "Cristo"
    ],
    "name:swe_x_preferred":[
        "Cristo"
    ],
    "wof:name":"Cristo",
    "wof:placetype":"locality",
    "wof:population":97
},
  "geometry": {"coordinates":[12.01361,45.27451],"type":"Point"}
}