{
  "type": "Feature",
  "properties": {
    "gn:admin1_code":"8",
    "gn:admin2_code":"SV",
    "gn:admin3_code":"9023.0",
    "gn:asciiname":"Montaldo",
    "gn:country_code":"IT",
    "gn:dem":463,
    "gn:feature_class":"P",
    "gn:feature_code":"PPL",
    "gn:name":"Montaldo",
    "gn:population":83,
    "gn:timezone":"Europe/Rome",
    "iso:country":"IT",
    "name:ceb_x_preferred":[
        "Montaldo"
    ],
    "name:deu_x_preferred":[
        "Montaldo"
    ],
    "name:fra_x_preferred":[
        "Montaldo"
    ],
    "name:ita_x_preferred":[
        "Montaldo"
    ],
    "name:pms_x_preferred":[
        "Montad"
    ],
    "name:por_x_preferred":[
        "Montaldo"
    ],
    "name:rus_x_preferred":[
        "\u041c\u043e\u043d\u0442\u0430\u043b\u044c\u0434\u043e"
    ],
    "name:sco_x_preferred":[
        "Montaldo"
    ],
    "name:srp_x_preferred":[
        "Montaldo"
    ],
    "name:swe_x_preferred":[
        "Montaldo"
    ],
    "wof:name":"Montaldo",
    "wof:placetype":"locality",
    "wof:population":83
},
  "geometry": {"coordinates":[8.20741,44.39502],"type":"Point"}
}