{
  "type": "Feature",
  "properties": {
    "gn:admin1_code":"20",
    "gn:admin2_code":"TV",
    "gn:admin3_code":"26001.0",
    "gn:asciiname":"Baldin e Perer",
    "gn:country_code":"IT",
    "gn:dem":79,
    "gn:feature_class":"P",
    "gn:feature_code":"PPL",
    "gn:name":"Baldin e Perer",
    "gn:population":210,
    "gn:timezone":"Europe/Rome",
    "iso:country":"IT",
    "wof:name":"Baldin e Perer",
    "wof:placetype":"locality",
    "wof:population":210
},
  "geometry": {"coordinates":[11.94695,45.74566],"type":"Point"}
}