{
  "type": "Feature",
  "properties": {
    "gn:admin1_code":"9",
    "gn:admin2_code":"BS",
    "gn:admin3_code":"17178.0",
    "gn:asciiname":"Berana",
    "gn:country_code":"IT",
    "gn:dem":372,
    "gn:feature_class":"P",
    "gn:feature_code":"PPL",
    "gn:name":"Berana",
    "gn:population":307,
    "gn:timezone":"Europe/Rome",
    "iso:country":"IT",
    "wof:name":"Berana",
    "wof:placetype":"locality",
    "wof:population":307
},
  "geometry": {"coordinates":[10.37666,45.55726],"type":"Point"}
}