{
  "type": "Feature",
  "properties": {
    "gn:admin1_code":"13",
    "gn:admin2_code":"BR",
    "gn:admin3_code":"74005.0",
    "gn:asciiname":"Padulamenta",
    "gn:country_code":"IT",
    "gn:dem":304,
    "gn:feature_class":"P",
    "gn:feature_code":"PPL",
    "gn:name":"Padulamenta",
    "gn:population":25,
    "gn:timezone":"Europe/Rome",
    "iso:country":"IT",
    "wof:name":"Padulamenta",
    "wof:placetype":"locality",
    "wof:population":25
},
  "geometry": {"coordinates":[17.46329,40.74896],"type":"Point"}
}