{
  "type": "Feature",
  "properties": {
    "gn:admin1_code":"11",
    "gn:admin2_code":"CB",
    "gn:admin3_code":"70081.0",
    "gn:asciiname":"Morricina",
    "gn:country_code":"IT",
    "gn:dem":730,
    "gn:feature_class":"P",
    "gn:feature_code":"PPL",
    "gn:name":"Morricina",
    "gn:population":16,
    "gn:timezone":"Europe/Rome",
    "iso:country":"IT",
    "wof:name":"Morricina",
    "wof:placetype":"locality",
    "wof:population":16
},
  "geometry": {"coordinates":[14.54755,41.74294],"type":"Point"}
}