{
  "type": "Feature",
  "properties": {
    "gn:admin1_code":"5",
    "gn:admin2_code":"RE",
    "gn:admin3_code":"35011.0",
    "gn:asciiname":"Velluciana",
    "gn:country_code":"IT",
    "gn:dem":436,
    "gn:feature_class":"P",
    "gn:feature_code":"PPL",
    "gn:name":"Velluciana",
    "gn:population":39,
    "gn:timezone":"Europe/Rome",
    "iso:country":"IT",
    "wof:name":"Velluciana",
    "wof:placetype":"locality",
    "wof:population":39
},
  "geometry": {"coordinates":[10.49983,44.40903],"type":"Point"}
}