{
  "type": "Feature",
  "properties": {
    "gn:admin1_code":"20",
    "gn:admin2_code":"TV",
    "gn:admin3_code":"26059.0",
    "gn:asciiname":"Picciol",
    "gn:country_code":"IT",
    "gn:dem":30,
    "gn:feature_class":"P",
    "gn:feature_code":"PPL",
    "gn:name":"Picciol",
    "gn:population":31,
    "gn:timezone":"Europe/Rome",
    "iso:country":"IT",
    "wof:name":"Picciol",
    "wof:placetype":"locality",
    "wof:population":31
},
  "geometry": {"coordinates":[12.23131,45.72448],"type":"Point"}
}