{
  "type": "Feature",
  "properties": {
    "gn:admin1_code":"20",
    "gn:admin2_code":"RO",
    "gn:admin3_code":"29001.0",
    "gn:asciiname":"Fienile Santissimo",
    "gn:country_code":"IT",
    "gn:dem":3,
    "gn:feature_class":"P",
    "gn:feature_code":"PPL",
    "gn:name":"Fienile Santissimo",
    "gn:population":27,
    "gn:timezone":"Europe/Rome",
    "iso:country":"IT",
    "wof:name":"Fienile Santissimo",
    "wof:placetype":"locality",
    "wof:population":27
},
  "geometry": {"coordinates":[12.00518,45.0125],"type":"Point"}
}