{
  "type": "Feature",
  "properties": {
    "gn:admin1_code":"7",
    "gn:admin2_code":"LT",
    "gn:admin3_code":"59029.0",
    "gn:asciiname":"Cascano",
    "gn:country_code":"IT",
    "gn:dem":186,
    "gn:feature_class":"P",
    "gn:feature_code":"PPL",
    "gn:name":"Cascano",
    "gn:population":29,
    "gn:timezone":"Europe/Rome",
    "iso:country":"IT",
    "wof:name":"Cascano",
    "wof:placetype":"locality",
    "wof:population":29
},
  "geometry": {"coordinates":[13.22707,41.36833],"type":"Point"}
}