{
  "type": "Feature",
  "properties": {
    "gn:admin1_code":"16",
    "gn:admin2_code":"MS",
    "gn:admin3_code":"45014.0",
    "gn:asciiname":"Molinello",
    "gn:country_code":"IT",
    "gn:dem":388,
    "gn:feature_class":"P",
    "gn:feature_code":"PPL",
    "gn:name":"Molinello",
    "gn:population":21,
    "gn:timezone":"Europe/Rome",
    "iso:country":"IT",
    "wof:name":"Molinello",
    "wof:placetype":"locality",
    "wof:population":21
},
  "geometry": {"coordinates":[9.92314,44.42388],"type":"Point"}
}