{
  "type": "Feature",
  "properties": {
    "gn:admin1_code":"7",
    "gn:admin2_code":"RI",
    "gn:admin3_code":"57017.0",
    "gn:asciiname":"Sacco",
    "gn:country_code":"IT",
    "gn:dem":796,
    "gn:feature_class":"P",
    "gn:feature_code":"PPL",
    "gn:name":"Sacco",
    "gn:population":15,
    "gn:timezone":"Europe/Rome",
    "iso:country":"IT",
    "wof:name":"Sacco",
    "wof:placetype":"locality",
    "wof:population":15
},
  "geometry": {"coordinates":[13.14439,42.56632000000001],"type":"Point"}
}