{
  "type": "Feature",
  "properties": {
    "gn:admin1_code":"9",
    "gn:admin2_code":"MI",
    "gn:admin3_code":"15011.0",
    "gn:asciiname":"Bazzana Superiore",
    "gn:country_code":"IT",
    "gn:dem":109,
    "gn:feature_class":"P",
    "gn:feature_code":"PPL",
    "gn:name":"Bazzana Superiore",
    "gn:population":33,
    "gn:timezone":"Europe/Rome",
    "iso:country":"IT",
    "wof:name":"Bazzana Superiore",
    "wof:placetype":"locality",
    "wof:population":33
},
  "geometry": {"coordinates":[9.14219,45.41093],"type":"Point"}
}