{
  "type": "Feature",
  "properties": {
    "gn:admin1_code":"4.0",
    "gn:admin2_code":"CE",
    "gn:admin3_code":"61074.0",
    "gn:asciiname":"San Cipriano d'Aversa",
    "gn:country_code":"IT",
    "gn:dem":23,
    "gn:elevation":"20.0",
    "gn:feature_class":"P",
    "gn:feature_code":"PPLA3",
    "gn:name":"San Cipriano d'Aversa",
    "gn:population":13416,
    "gn:timezone":"Europe/Rome",
    "iso:country":"IT",
    "wof:name":"San Cipriano d'Aversa",
    "wof:placetype":"locality",
    "wof:population":13416
},
  "geometry": {"coordinates":[14.13173,40.99881],"type":"Point"}
}