{
  "type": "Feature",
  "properties": {
    "gn:admin1_code":"9.0",
    "gn:admin2_code":"CR",
    "gn:admin3_code":"19089.0",
    "gn:asciiname":"Isola Pescaroli",
    "gn:country_code":"IT",
    "gn:dem":32,
    "gn:elevation":"32.0",
    "gn:feature_class":"P",
    "gn:feature_code":"PPL",
    "gn:name":"Isola Pescaroli",
    "gn:population":107,
    "gn:timezone":"Europe/Rome",
    "iso:country":"IT",
    "wof:name":"Isola Pescaroli",
    "wof:placetype":"locality",
    "wof:population":107
},
  "geometry": {"coordinates":[10.1856,45.0422],"type":"Point"}
}