{
  "type": "Feature",
  "properties": {
    "gn:admin1_code":"16",
    "gn:admin2_code":"SI",
    "gn:admin3_code":"52027.0",
    "gn:asciiname":"Sasso",
    "gn:country_code":"IT",
    "gn:dem":321,
    "gn:feature_class":"P",
    "gn:feature_code":"PPL",
    "gn:name":"Sasso",
    "gn:population":18,
    "gn:timezone":"Europe/Rome",
    "iso:country":"IT",
    "wof:name":"Sasso",
    "wof:placetype":"locality",
    "wof:population":18
},
  "geometry": {"coordinates":[11.94041,42.89656],"type":"Point"}
}