{
  "type": "Feature",
  "properties": {
    "gn:admin1_code":"9.0",
    "gn:admin2_code":"LO",
    "gn:admin3_code":"98020.0",
    "gn:asciiname":"Lavagna",
    "gn:country_code":"IT",
    "gn:dem":104,
    "gn:feature_class":"P",
    "gn:feature_code":"PPL",
    "gn:name":"Lavagna",
    "gn:population":607,
    "gn:timezone":"Europe/Rome",
    "iso:country":"IT",
    "name:azb_x_preferred":[
        "\u0644\u0627\u0648\u0627\u0646\u0627"
    ],
    "name:bel_x_preferred":[
        "\u041b\u0430\u0432\u0430\u043d\u044c\u044f"
    ],
    "name:bul_x_preferred":[
        "\u041b\u0430\u0432\u0430\u043d\u044f"
    ],
    "name:cat_x_preferred":[
        "Lavagna"
    ],
    "name:ceb_x_preferred":[
        "Lavagna"
    ],
    "name:ces_x_preferred":[
        "Lavagna"
    ],
    "name:dan_x_preferred":[
        "Lavagna"
    ],
    "name:deu_x_preferred":[
        "Lavagna"
    ],
    "name:epo_x_preferred":[
        "Lavagna"
    ],
    "name:eus_x_preferred":[
        "Lavagna"
    ],
    "name:fas_x_preferred":[
        "\u0644\u0627\u0648\u0627\u0646\u0627"
    ],
    "name:fra_x_preferred":[
        "Lavagna"
    ],
    "name:hun_x_preferred":[
        "Lavagna"
    ],
    "name:hye_x_preferred":[
        "\u053c\u0561\u057e\u0561\u0576\u0575\u0561"
    ],
    "name:ina_x_preferred":[
        "Lavagna"
    ],
    "name:ita_x_preferred":[
        "Lavagna"
    ],
    "name:jpn_x_preferred":[
        "\u30e9\u30f4\u30a1\u30fc\u30cb\u30e3"
    ],
    "name:kaz_x_preferred":[
        "\u041b\u0430\u0432\u0430\u043d\u044c\u044f"
    ],
    "name:lat_x_preferred":[
        "Lavania"
    ],
    "name:lij_x_preferred":[
        "Lavagna"
    ],
    "name:lmo_x_preferred":[
        "Lavagna"
    ],
    "name:msa_x_preferred":[
        "Lavagna"
    ],
    "name:nap_x_preferred":[
        "Lavagna"
    ],
    "name:nld_x_preferred":[
        "Lavagna"
    ],
    "name:pms_x_preferred":[
        "Lavagna"
    ],
    "name:pol_x_preferred":[
        "Lavagna"
    ],
    "name:por_x_preferred":[
        "Lavagna"
    ],
    "name:roh_x_preferred":[
        "Lavagna"
    ],
    "name:ron_x_preferred":[
        "Lavagna"
    ],
    "name:rus_x_preferred":[
        "\u041b\u0430\u0432\u0430\u043d\u044c\u044f"
    ],
    "name:scn_x_preferred":[
        "Lavagna"
    ],
    "name:spa_x_preferred":[
        "Lavagna"
    ],
    "name:srd_x_preferred":[
        "Lavagna"
    ],
    "name:srp_x_preferred":[
        "\u041b\u0430\u0432\u0430\u045a\u0430"
    ],
    "name:swe_x_preferred":[
        "Lavagna"
    ],
    "name:tur_x_preferred":[
        "Lavagna"
    ],
    "name:ukr_x_preferred":[
        "\u041b\u0430\u0432\u0430\u043d\u044c\u044f"
    ],
    "name:uzb_x_preferred":[
        "Lavagna"
    ],
    "name:vol_x_preferred":[
        "Lavagna"
    ],
    "name:war_x_preferred":[
        "Lavagna"
    ],
    "name:zho_x_preferred":[
        "\u62c9\u74e6\u5c3c\u4e9a"
    ],
    "wof:name":"Lavagna",
    "wof:placetype":"locality",
    "wof:population":607
},
  "geometry": {"coordinates":[9.44429,45.46183],"type":"Point"}
}