{
  "type": "Feature",
  "properties": {
    "gn:admin1_code":"9.0",
    "gn:admin2_code":"LO",
    "gn:admin3_code":"98020.0",
    "gn:asciiname":"Lavagna",
    "gn:country_code":"IT",
    "gn:dem":104,
    "gn:feature_class":"P",
    "gn:feature_code":"PPL",
    "gn:name":"Lavagna",
    "gn:population":607,
    "gn:timezone":"Europe/Rome",
    "iso:country":"IT",
    "wof:name":"Lavagna",
    "wof:placetype":"locality",
    "wof:population":607
},
  "geometry": {"coordinates":[9.44429,45.46183],"type":"Point"}
}