{
  "type": "Feature",
  "properties": {
    "gn:admin1_code":"16.0",
    "gn:admin2_code":"PI",
    "gn:admin3_code":"50024.0",
    "gn:asciiname":"Molino del Roglio",
    "gn:country_code":"IT",
    "gn:dem":40,
    "gn:feature_class":"P",
    "gn:feature_code":"PPL",
    "gn:name":"Molino del Roglio",
    "gn:population":0,
    "gn:timezone":"Europe/Rome",
    "iso:country":"IT",
    "wof:name":"Molino del Roglio",
    "wof:placetype":"locality"
},
  "geometry": {"coordinates":[10.71667,43.58333],"type":"Point"}
}