{
  "type": "Feature",
  "properties": {
    "gn:admin1_code":"3",
    "gn:admin2_code":"CZ",
    "gn:admin3_code":"79029.0",
    "gn:asciiname":"Gatto",
    "gn:country_code":"IT",
    "gn:dem":614,
    "gn:feature_class":"P",
    "gn:feature_code":"PPL",
    "gn:name":"Gatto",
    "gn:population":15,
    "gn:timezone":"Europe/Rome",
    "iso:country":"IT",
    "name:spa_x_preferred":[
        "Gatto"
    ],
    "wof:name":"Gatto",
    "wof:placetype":"locality",
    "wof:population":15
},
  "geometry": {"coordinates":[16.38195,38.7024],"type":"Point"}
}