{
  "type": "Feature",
  "properties": {
    "gn:admin1_code":"20.0",
    "gn:admin2_code":"RO",
    "gn:admin3_code":"29010.0",
    "gn:asciiname":"Localita Madonna dei Cuori",
    "gn:country_code":"IT",
    "gn:dem":1,
    "gn:feature_class":"P",
    "gn:feature_code":"PPLL",
    "gn:name":"Localit\u00e0 Madonna dei Cuori",
    "gn:population":3,
    "gn:timezone":"Europe/Rome",
    "iso:country":"IT",
    "name:und_x_variant":[
        "Localit\u00e0 Madonna dei Cuori"
    ],
    "wof:name":"Localita Madonna dei Cuori",
    "wof:placetype":"locality",
    "wof:population":3
},
  "geometry": {"coordinates":[11.53111,45.05219],"type":"Point"}
}