{
  "type": "Feature",
  "properties": {
    "gn:admin1_code":"5",
    "gn:admin2_code":"RE",
    "gn:admin3_code":"35013.0",
    "gn:asciiname":"Giandeto Straduzzi",
    "gn:country_code":"IT",
    "gn:dem":642,
    "gn:feature_class":"P",
    "gn:feature_code":"PPL",
    "gn:name":"Giandeto Straduzzi",
    "gn:population":21,
    "gn:timezone":"Europe/Rome",
    "iso:country":"IT",
    "wof:name":"Giandeto Straduzzi",
    "wof:placetype":"locality",
    "wof:population":21
},
  "geometry": {"coordinates":[10.5326,44.49729],"type":"Point"}
}