{
  "type": "Feature",
  "properties": {
    "gn:admin1_code":"12",
    "gn:admin2_code":"TO",
    "gn:admin3_code":"1061.0",
    "gn:asciiname":"Via Boves",
    "gn:country_code":"IT",
    "gn:dem":237,
    "gn:feature_class":"P",
    "gn:feature_code":"PPL",
    "gn:name":"Via Boves",
    "gn:population":13,
    "gn:timezone":"Europe/Rome",
    "iso:country":"IT",
    "wof:name":"Via Boves",
    "wof:placetype":"locality",
    "wof:population":13
},
  "geometry": {"coordinates":[7.90658,45.47233],"type":"Point"}
}