{
  "type": "Feature",
  "properties": {
    "gn:admin1_code":"3",
    "gn:admin2_code":"CZ",
    "gn:admin3_code":"79160.0",
    "gn:asciiname":"Lamezia Golfo",
    "gn:country_code":"IT",
    "gn:dem":8,
    "gn:feature_class":"P",
    "gn:feature_code":"PPL",
    "gn:name":"Lamezia Golfo",
    "gn:population":20,
    "gn:timezone":"Europe/Rome",
    "iso:country":"IT",
    "wof:name":"Lamezia Golfo",
    "wof:placetype":"locality",
    "wof:population":20
},
  "geometry": {"coordinates":[16.22857,38.8968],"type":"Point"}
}