{
  "type": "Feature",
  "properties": {
    "gn:admin1_code":"4",
    "gn:admin2_code":"CE",
    "gn:admin3_code":"61048.0",
    "gn:asciiname":"Rinchiusa",
    "gn:country_code":"IT",
    "gn:dem":41,
    "gn:feature_class":"P",
    "gn:feature_code":"PPL",
    "gn:name":"Rinchiusa",
    "gn:population":78,
    "gn:timezone":"Europe/Rome",
    "iso:country":"IT",
    "wof:name":"Rinchiusa",
    "wof:placetype":"locality",
    "wof:population":78
},
  "geometry": {"coordinates":[14.41729,41.01037],"type":"Point"}
}