{
  "type": "Feature",
  "properties": {
    "gn:admin1_code":"16",
    "gn:admin2_code":"SI",
    "gn:admin3_code":"52015.0",
    "gn:asciiname":"Ascianello",
    "gn:country_code":"IT",
    "gn:dem":327,
    "gn:feature_class":"P",
    "gn:feature_code":"PPL",
    "gn:name":"Ascianello",
    "gn:population":16,
    "gn:timezone":"Europe/Rome",
    "iso:country":"IT",
    "wof:name":"Ascianello",
    "wof:placetype":"locality",
    "wof:population":16
},
  "geometry": {"coordinates":[11.79666,43.14014],"type":"Point"}
}