{
  "type": "Feature",
  "properties": {
    "gn:gn_country":"IT",
    "gn:gn_fcode":"PPLA3",
    "gn:gn_pop":155,
    "gn:population":45,
    "iso:country":"IT",
    "name:bel_x_preferred":[
        "\u041f\u0440\u0430\u043f\u0430\u0442\u0430"
    ],
    "name:bul_x_preferred":[
        "\u041f\u0440\u043e\u043f\u0430\u0442\u0430"
    ],
    "name:cat_x_preferred":[
        "Propata"
    ],
    "name:deu_x_preferred":[
        "Propata"
    ],
    "name:eng_x_preferred":[
        "Propata"
    ],
    "name:epo_x_preferred":[
        "Propata"
    ],
    "name:eus_x_preferred":[
        "Propata"
    ],
    "name:fas_x_preferred":[
        "\u067e\u0631\u0648\u067e\u0627\u062a\u0627"
    ],
    "name:fra_x_preferred":[
        "Propata"
    ],
    "name:hun_x_preferred":[
        "Propata"
    ],
    "name:hye_x_preferred":[
        "\u054a\u0580\u0578\u057a\u0561\u057f\u0561"
    ],
    "name:ina_x_preferred":[
        "Propata"
    ],
    "name:ita_x_preferred":[
        "Propata"
    ],
    "name:jpn_x_preferred":[
        "\u30d7\u30ed\u30d1\u30fc\u30bf"
    ],
    "name:kaz_x_preferred":[
        "\u041f\u0440\u043e\u043f\u0430\u0442\u0430"
    ],
    "name:lat_x_preferred":[
        "Propata"
    ],
    "name:lij_x_preferred":[
        "Prop\u00e2"
    ],
    "name:lmo_x_preferred":[
        "Propata"
    ],
    "name:msa_x_preferred":[
        "Propata"
    ],
    "name:nan_x_preferred":[
        "Propata"
    ],
    "name:nap_x_preferred":[
        "Propata"
    ],
    "name:nld_x_preferred":[
        "Propata"
    ],
    "name:pms_x_preferred":[
        "Propata"
    ],
    "name:pol_x_preferred":[
        "Propata"
    ],
    "name:por_x_preferred":[
        "Propata"
    ],
    "name:ron_x_preferred":[
        "Propata"
    ],
    "name:rus_x_preferred":[
        "\u041f\u0440\u043e\u043f\u0430\u0442\u0430"
    ],
    "name:scn_x_preferred":[
        "Propata"
    ],
    "name:spa_x_preferred":[
        "Propata"
    ],
    "name:srd_x_preferred":[
        "Propata"
    ],
    "name:srp_x_preferred":[
        "Propata"
    ],
    "name:ukr_x_preferred":[
        "\u041f\u0440\u043e\u043f\u0430\u0442\u0430"
    ],
    "name:uzb_x_preferred":[
        "Propata"
    ],
    "name:vie_x_preferred":[
        "Propata"
    ],
    "name:vol_x_preferred":[
        "Propata"
    ],
    "name:war_x_preferred":[
        "Propata"
    ],
    "name:zho_x_preferred":[
        "\u666e\u7f57\u5e15\u5854"
    ],
    "qs_pg:aaroncc":"IT",
    "qs_pg:gn_country":"IT",
    "qs_pg:gn_fcode":"PPLA3",
    "qs_pg:gn_pop":155,
    "qs_pg:name":"Propata",
    "qs_pg:name_adm0":"Italia",
    "qs_pg:name_adm1":"Liguria",
    "qs_pg:photos_9r":0,
    "qs_pg:photos_sr":0,
    "qs_pg:pop_sr":1,
    "qs_pg:qs_pg_placetype":"locality",
    "qs_pg:qs_pg_placetype_gp":"Town",
    "qs_pg:woe_adm0":23424853,
    "woe:adm0_id":23424853,
    "woe:name_adm0":"Italia",
    "woe:name_adm1":"Liguria",
    "woe:placetype":"Town",
    "wof:name":"Propata",
    "wof:placetype":"locality",
    "wof:population":45
},
  "geometry": {"coordinates":[9.18566,44.56565],"type":"Point"}
}