{
  "type": "Feature",
  "properties": {
    "gn:admin1_code":"8.0",
    "gn:admin2_code":"GE",
    "gn:admin3_code":"10053.0",
    "gn:asciiname":"Calvari",
    "gn:country_code":"IT",
    "gn:dem":51,
    "gn:feature_class":"P",
    "gn:feature_code":"PPL",
    "gn:name":"Calvari",
    "gn:population":435,
    "gn:timezone":"Europe/Rome",
    "iso:country":"IT",
    "wof:name":"Calvari",
    "wof:placetype":"locality",
    "wof:population":435
},
  "geometry": {"coordinates":[9.28515,44.3817],"type":"Point"}
}