{
  "type": "Feature",
  "properties": {
    "gn:admin1_code":"17",
    "gn:admin2_code":"TN",
    "gn:admin3_code":"22163.0",
    "gn:asciiname":"Corte Superiore",
    "gn:country_code":"IT",
    "gn:dem":1023,
    "gn:feature_class":"P",
    "gn:feature_code":"PPL",
    "gn:name":"Corte Superiore",
    "gn:population":52,
    "gn:timezone":"Europe/Rome",
    "iso:country":"IT",
    "wof:name":"Corte Superiore",
    "wof:placetype":"locality",
    "wof:population":52
},
  "geometry": {"coordinates":[11.01311,46.44808],"type":"Point"}
}