{
  "type": "Feature",
  "properties": {
    "gn:admin1_code":"20",
    "gn:admin2_code":"VR",
    "gn:admin3_code":"23015.0",
    "gn:asciiname":"Villa Serena",
    "gn:country_code":"IT",
    "gn:dem":103,
    "gn:feature_class":"P",
    "gn:feature_code":"PPL",
    "gn:name":"Villa Serena",
    "gn:population":23,
    "gn:timezone":"Europe/Rome",
    "iso:country":"IT",
    "wof:name":"Villa Serena",
    "wof:placetype":"locality",
    "wof:population":23
},
  "geometry": {"coordinates":[10.86809,45.46637],"type":"Point"}
}