{
  "type": "Feature",
  "properties": {
    "gn:admin1_code":"5.0",
    "gn:admin2_code":"PC",
    "gn:admin3_code":"33043.0",
    "gn:asciiname":"Fradegola",
    "gn:country_code":"IT",
    "gn:dem":337,
    "gn:feature_class":"P",
    "gn:feature_code":"PPL",
    "gn:name":"Fradegola",
    "gn:population":0,
    "gn:timezone":"Europe/Rome",
    "iso:country":"IT",
    "wof:name":"Fradegola",
    "wof:placetype":"locality"
},
  "geometry": {"coordinates":[9.53333,44.88333],"type":"Point"}
}