{
  "type": "Feature",
  "properties": {
    "gn:admin1_code":"7",
    "gn:admin2_code":"RI",
    "gn:admin3_code":"57027.0",
    "gn:asciiname":"Fonte Schieta",
    "gn:country_code":"IT",
    "gn:dem":220,
    "gn:feature_class":"P",
    "gn:feature_code":"PPL",
    "gn:name":"Fonte Schieta",
    "gn:population":13,
    "gn:timezone":"Europe/Rome",
    "iso:country":"IT",
    "wof:name":"Fonte Schieta",
    "wof:placetype":"locality",
    "wof:population":13
},
  "geometry": {"coordinates":[12.72425,42.18433],"type":"Point"}
}