{
  "type": "Feature",
  "properties": {
    "gn:admin1_code":"12",
    "gn:admin2_code":"BI",
    "gn:admin3_code":"96015.0",
    "gn:asciiname":"Cagna",
    "gn:country_code":"IT",
    "gn:dem":215,
    "gn:feature_class":"P",
    "gn:feature_code":"PPL",
    "gn:name":"Cagna",
    "gn:population":65,
    "gn:timezone":"Europe/Rome",
    "iso:country":"IT",
    "wof:name":"Cagna",
    "wof:placetype":"locality",
    "wof:population":65
},
  "geometry": {"coordinates":[8.23892,45.51765],"type":"Point"}
}