{
  "type": "Feature",
  "properties": {
    "gn:admin1_code":"5.0",
    "gn:admin2_code":"PR",
    "gn:admin3_code":"34024.0",
    "gn:asciiname":"La Costa",
    "gn:country_code":"IT",
    "gn:dem":471,
    "gn:feature_class":"P",
    "gn:feature_code":"PPL",
    "gn:name":"La Costa",
    "gn:population":0,
    "gn:timezone":"Europe/Rome",
    "iso:country":"IT",
    "wof:name":"La Costa",
    "wof:placetype":"locality"
},
  "geometry": {"coordinates":[10.36667,44.56667],"type":"Point"}
}