{
  "type": "Feature",
  "properties": {
    "gn:admin1_code":"16",
    "gn:admin2_code":"SI",
    "gn:admin3_code":"52022.0",
    "gn:asciiname":"Campomaggio",
    "gn:country_code":"IT",
    "gn:dem":133,
    "gn:feature_class":"P",
    "gn:feature_code":"PPL",
    "gn:name":"Campomaggio",
    "gn:population":24,
    "gn:timezone":"Europe/Rome",
    "iso:country":"IT",
    "wof:name":"Campomaggio",
    "wof:placetype":"locality",
    "wof:population":24
},
  "geometry": {"coordinates":[11.1571,43.48786],"type":"Point"}
}