{
  "type": "Feature",
  "properties": {
    "gn:admin1_code":"3.0",
    "gn:admin2_code":"CZ",
    "gn:admin3_code":"79043.0",
    "gn:asciiname":"Palinudo",
    "gn:cc2":"IT",
    "gn:country_code":"IT",
    "gn:dem":946,
    "gn:feature_class":"P",
    "gn:feature_code":"PPL",
    "gn:name":"Palinudo",
    "gn:population":0,
    "gn:timezone":"Europe/Rome",
    "iso:country":"IT",
    "name:und_x_variant":[
        "Paoli",
        "Palinudo"
    ],
    "wof:name":"Palinudo",
    "wof:placetype":"locality"
},
  "geometry": {"coordinates":[16.33333,39.06667],"type":"Point"}
}