{
  "type": "Feature",
  "properties": {
    "gn:admin1_code":"5.0",
    "gn:admin2_code":"FE",
    "gn:admin3_code":"38007.0",
    "gn:asciiname":"Coccanile-Cesta",
    "gn:country_code":"IT",
    "gn:dem":0,
    "gn:feature_class":"P",
    "gn:feature_code":"PPL",
    "gn:name":"Coccanile-Cesta",
    "gn:population":1262,
    "gn:timezone":"Europe/Rome",
    "iso:country":"IT",
    "wof:name":"Coccanile-Cesta",
    "wof:placetype":"locality",
    "wof:population":1262
},
  "geometry": {"coordinates":[11.86667,44.91667],"type":"Point"}
}