{
  "type": "Feature",
  "properties": {
    "gn:country":"IT",
    "gn:fcode":"PPL",
    "gn:population":0,
    "iso:country":"IT",
    "name:ceb_x_preferred":[
        "Gris"
    ],
    "name:dan_x_preferred":[
        "Gris"
    ],
    "name:deu_x_preferred":[
        "Gris"
    ],
    "name:fra_x_preferred":[
        "Gris"
    ],
    "name:glg_x_preferred":[
        "Gris"
    ],
    "name:heb_x_preferred":[
        "\u05d2\u05e8\u05d9\u05e1"
    ],
    "name:lmo_x_preferred":[
        "Gris"
    ],
    "name:por_x_preferred":[
        "Gris"
    ],
    "name:spa_x_preferred":[
        "Gris"
    ],
    "name:srp_x_preferred":[
        "Gris"
    ],
    "name:swe_x_preferred":[
        "Gris"
    ],
    "qs_pg:aaroncc":"IT",
    "qs_pg:gn_country":"IT",
    "qs_pg:gn_fcode":"PPL",
    "qs_pg:gn_pop":0,
    "qs_pg:name":"Gris",
    "qs_pg:name_adm0":"Italia",
    "qs_pg:name_adm1":"Friuli-Venezia Giulia",
    "qs_pg:photos_9r":0,
    "qs_pg:photos_sr":0,
    "qs_pg:pop_sr":0,
    "qs_pg:qs_pg_placetype":"locality",
    "qs_pg:qs_pg_placetype_gp":"Town",
    "qs_pg:woe_adm0":23424853,
    "woe:adm0_id":23424853,
    "woe:name_adm0":"Italia",
    "woe:name_adm1":"Friuli-Venezia Giulia",
    "woe:placetype":"Town",
    "wof:name":"Gris",
    "wof:placetype":"locality",
    "wof:population":364
},
  "geometry": {"coordinates":[13.23361,45.92861],"type":"Point"}
}