{
  "type": "Feature",
  "properties": {
    "gn:admin1_code":"20",
    "gn:admin2_code":"VR",
    "gn:admin3_code":"23078.0",
    "gn:asciiname":"Giare",
    "gn:country_code":"IT",
    "gn:dem":686,
    "gn:feature_class":"P",
    "gn:feature_code":"PPL",
    "gn:name":"Giare",
    "gn:population":104,
    "gn:timezone":"Europe/Rome",
    "iso:country":"IT",
    "wof:name":"Giare",
    "wof:placetype":"locality",
    "wof:population":104
},
  "geometry": {"coordinates":[10.97396,45.59641],"type":"Point"}
}