{
  "type": "Feature",
  "properties": {
    "gn:admin1_code":"9",
    "gn:admin2_code":"BG",
    "gn:admin3_code":"16068.0",
    "gn:asciiname":"Perani",
    "gn:country_code":"IT",
    "gn:dem":370,
    "gn:feature_class":"P",
    "gn:feature_code":"PPL",
    "gn:name":"Perani",
    "gn:population":32,
    "gn:timezone":"Europe/Rome",
    "iso:country":"IT",
    "wof:name":"Perani",
    "wof:placetype":"locality",
    "wof:population":32
},
  "geometry": {"coordinates":[9.82332,45.71642],"type":"Point"}
}