{
  "type": "Feature",
  "properties": {
    "gn:admin1_code":"16",
    "gn:admin2_code":"LU",
    "gn:admin3_code":"46034.0",
    "gn:asciiname":"Pontoro",
    "gn:country_code":"IT",
    "gn:dem":341,
    "gn:feature_class":"P",
    "gn:feature_code":"PPL",
    "gn:name":"Pontoro",
    "gn:population":21,
    "gn:timezone":"Europe/Rome",
    "iso:country":"IT",
    "wof:name":"Pontoro",
    "wof:placetype":"locality",
    "wof:population":21
},
  "geometry": {"coordinates":[10.64813,43.93992],"type":"Point"}
}