{
  "type": "Feature",
  "properties": {
    "gn:admin1_code":"20",
    "gn:admin2_code":"PD",
    "gn:admin3_code":"28094.0",
    "gn:asciiname":"Bianco",
    "gn:country_code":"IT",
    "gn:dem":2,
    "gn:feature_class":"P",
    "gn:feature_code":"PPL",
    "gn:name":"Bianco",
    "gn:population":41,
    "gn:timezone":"Europe/Rome",
    "iso:country":"IT",
    "name:ara_x_preferred":[
        "\u0628\u064a\u0627\u0646\u0643\u0648"
    ],
    "name:azb_x_preferred":[
        "\u0628\u06cc\u0627\u0646\u06a9\u0648"
    ],
    "name:bcl_x_preferred":[
        "Bianco"
    ],
    "name:bul_x_preferred":[
        "\u0411\u0438\u0430\u043d\u043a\u043e"
    ],
    "name:ceb_x_preferred":[
        "Bianco"
    ],
    "name:deu_x_preferred":[
        "Bianco"
    ],
    "name:epo_x_preferred":[
        "Bianco"
    ],
    "name:eus_x_preferred":[
        "Bianco"
    ],
    "name:fas_x_preferred":[
        "\u0628\u06cc\u0627\u0646\u06a9\u0648"
    ],
    "name:fra_x_preferred":[
        "Bianco"
    ],
    "name:hun_x_preferred":[
        "Bianco"
    ],
    "name:hye_x_preferred":[
        "\u0532\u056b\u0561\u0576\u056f\u0578"
    ],
    "name:ina_x_preferred":[
        "Bianco"
    ],
    "name:ita_x_preferred":[
        "Bianco"
    ],
    "name:jpn_x_preferred":[
        "\u30d3\u30a2\u30f3\u30b3"
    ],
    "name:kaz_x_preferred":[
        "\u0411\u044c\u044f\u043d\u043a\u043e"
    ],
    "name:lat_x_preferred":[
        "Blancum"
    ],
    "name:lmo_x_preferred":[
        "Bianco"
    ],
    "name:msa_x_preferred":[
        "Bianco"
    ],
    "name:nap_x_preferred":[
        "Bianco"
    ],
    "name:nld_x_preferred":[
        "Bianco"
    ],
    "name:pms_x_preferred":[
        "Bianco"
    ],
    "name:pol_x_preferred":[
        "Bianco"
    ],
    "name:por_x_preferred":[
        "Bianco"
    ],
    "name:ron_x_preferred":[
        "Bianco"
    ],
    "name:rus_x_preferred":[
        "\u0411\u044c\u044f\u043d\u043a\u043e"
    ],
    "name:scn_x_preferred":[
        "Biancu"
    ],
    "name:spa_x_preferred":[
        "Bianco"
    ],
    "name:srp_x_preferred":[
        "\u0411\u0438\u0458\u0430\u043d\u043a\u043e"
    ],
    "name:ukr_x_preferred":[
        "\u0411'\u044f\u043d\u043a\u043e"
    ],
    "name:uzb_x_preferred":[
        "Bianco"
    ],
    "name:vol_x_preferred":[
        "Bianco"
    ],
    "name:war_x_preferred":[
        "Bianco"
    ],
    "name:zho_x_preferred":[
        "\u6bd4\u4e9a\u6069\u79d1"
    ],
    "wof:name":"Bianco",
    "wof:placetype":"locality",
    "wof:population":41
},
  "geometry": {"coordinates":[11.84734,45.18279],"type":"Point"}
}