{
  "type": "Feature",
  "properties": {
    "gn:admin1_code":"20",
    "gn:admin2_code":"PD",
    "gn:admin3_code":"28094.0",
    "gn:asciiname":"Bianco",
    "gn:country_code":"IT",
    "gn:dem":2,
    "gn:feature_class":"P",
    "gn:feature_code":"PPL",
    "gn:name":"Bianco",
    "gn:population":41,
    "gn:timezone":"Europe/Rome",
    "iso:country":"IT",
    "wof:name":"Bianco",
    "wof:placetype":"locality",
    "wof:population":41
},
  "geometry": {"coordinates":[11.84734,45.18279],"type":"Point"}
}