{
  "type": "Feature",
  "properties": {
    "gn:admin1_code":"6",
    "gn:admin2_code":"UD",
    "gn:admin3_code":"30083.0",
    "gn:asciiname":"Casali Braide",
    "gn:country_code":"IT",
    "gn:dem":111,
    "gn:feature_class":"P",
    "gn:feature_code":"PPL",
    "gn:name":"Casali Braide",
    "gn:population":30,
    "gn:timezone":"Europe/Rome",
    "iso:country":"IT",
    "wof:name":"Casali Braide",
    "wof:placetype":"locality",
    "wof:population":30
},
  "geometry": {"coordinates":[13.42309,46.05051],"type":"Point"}
}