{
  "type": "Feature",
  "properties": {
    "gn:admin1_code":"9.0",
    "gn:admin2_code":"BS",
    "gn:admin3_code":"17029.0",
    "gn:asciiname":"Cascina Il Nuovo",
    "gn:country_code":"IT",
    "gn:dem":120,
    "gn:feature_class":"P",
    "gn:feature_code":"PPL",
    "gn:name":"Cascina Il Nuovo",
    "gn:population":11,
    "gn:timezone":"Europe/Rome",
    "iso:country":"IT",
    "wof:name":"Cascina Il Nuovo",
    "wof:placetype":"locality",
    "wof:population":11
},
  "geometry": {"coordinates":[10.25362,45.49643],"type":"Point"}
}