{
  "type": "Feature",
  "properties": {
    "gn:admin1_code":"12",
    "gn:admin2_code":"TO",
    "gn:admin3_code":"1265.0",
    "gn:asciiname":"Peroda",
    "gn:country_code":"IT",
    "gn:dem":192,
    "gn:feature_class":"P",
    "gn:feature_code":"PPL",
    "gn:name":"Peroda",
    "gn:population":49,
    "gn:timezone":"Europe/Rome",
    "iso:country":"IT",
    "wof:name":"Peroda",
    "wof:placetype":"locality",
    "wof:population":49
},
  "geometry": {"coordinates":[7.82206,45.15237],"type":"Point"}
}