{
  "type": "Feature",
  "properties": {
    "gn:admin1_code":"9.0",
    "gn:admin2_code":"BG",
    "gn:admin3_code":"16177.0",
    "gn:asciiname":"Cascina Gandina",
    "gn:country_code":"IT",
    "gn:dem":106,
    "gn:feature_class":"P",
    "gn:feature_code":"PPL",
    "gn:name":"Cascina Gandina",
    "gn:population":16,
    "gn:timezone":"Europe/Rome",
    "iso:country":"IT",
    "wof:name":"Cascina Gandina",
    "wof:placetype":"locality",
    "wof:population":16
},
  "geometry": {"coordinates":[9.85099,45.4732],"type":"Point"}
}