{
  "type": "Feature",
  "properties": {
    "gn:admin1_code":"9",
    "gn:admin2_code":"CO",
    "gn:admin3_code":"13245.0",
    "gn:asciiname":"Pian Meraccio",
    "gn:country_code":"IT",
    "gn:dem":365,
    "gn:feature_class":"P",
    "gn:feature_code":"PPL",
    "gn:name":"Pian Meraccio",
    "gn:population":56,
    "gn:timezone":"Europe/Rome",
    "iso:country":"IT",
    "wof:name":"Pian Meraccio",
    "wof:placetype":"locality",
    "wof:population":56
},
  "geometry": {"coordinates":[9.00561,45.78557],"type":"Point"}
}