{
  "type": "Feature",
  "properties": {
    "gn:elevation":69,
    "gn:population":2390,
    "iso:country":"IT",
    "name:eng_x_preferred":[
        "Magugnano"
    ],
    "name:ita_x_preferred":[
        "Magugnano-Marniga"
    ],
    "name:unk_x_variant":[
        "Magugnano-Marniga"
    ],
    "qs:a0":"Italia",
    "qs:a1":"*Verona",
    "qs:a1r":"0Veneto",
    "qs:adm0":"Italia",
    "qs:la_lc":"*",
    "qs:level":"locality",
    "qs:loc":"Magugnano",
    "qs:loc_alt":"Magugnano",
    "qs:pop":0,
    "qs:type":"buffered point",
    "wof:lang":[
        "ita"
    ],
    "wof:name":"Magugnano",
    "wof:placetype":"locality",
    "wof:population":2390
},
  "geometry": {"coordinates":[10.76305,45.699829],"type":"Point"}
}