{
  "type": "Feature",
  "properties": {
    "gn:elevation":69,
    "gn:population":2390,
    "iso:country":"IT",
    "name:bul_x_preferred":[
        "\u041c\u0430\u0433\u0443\u0433\u043d\u0430\u043d\u043e"
    ],
    "name:cat_x_preferred":[
        "Magugnano"
    ],
    "name:ceb_x_preferred":[
        "Magugnano"
    ],
    "name:ces_x_preferred":[
        "Magugnano"
    ],
    "name:dan_x_preferred":[
        "Magugnano"
    ],
    "name:eng_x_preferred":[
        "Magugnano"
    ],
    "name:eus_x_preferred":[
        "Magugnano"
    ],
    "name:fin_x_preferred":[
        "Magugnano"
    ],
    "name:fra_x_preferred":[
        "Magugnano"
    ],
    "name:ind_x_preferred":[
        "Magugnano"
    ],
    "name:ita_x_preferred":[
        "Magugnano-Marniga"
    ],
    "name:ita_x_variant":[
        "Magugnano"
    ],
    "name:nld_x_preferred":[
        "Magugnano"
    ],
    "name:nno_x_preferred":[
        "Magugnano"
    ],
    "name:nob_x_preferred":[
        "Magugnano"
    ],
    "name:oci_x_preferred":[
        "Magugnano"
    ],
    "name:pol_x_preferred":[
        "Magugnano"
    ],
    "name:por_x_preferred":[
        "Magugnano"
    ],
    "name:ron_x_preferred":[
        "Magugnano"
    ],
    "name:slk_x_preferred":[
        "Magugnano"
    ],
    "name:slv_x_preferred":[
        "Magugnano"
    ],
    "name:spa_x_preferred":[
        "Magugnano"
    ],
    "name:srp_x_preferred":[
        "Magugnano"
    ],
    "name:swe_x_preferred":[
        "Magugnano"
    ],
    "name:tgl_x_preferred":[
        "Magugnano"
    ],
    "name:tur_x_preferred":[
        "Magugnano"
    ],
    "name:war_x_preferred":[
        "Magugnano"
    ],
    "qs:a0":"Italia",
    "qs:a1":"*Verona",
    "qs:a1r":"0Veneto",
    "qs:adm0":"Italia",
    "qs:la_lc":"*",
    "qs:level":"locality",
    "qs:loc":"Magugnano",
    "qs:loc_alt":"Magugnano",
    "qs:pop":0,
    "qs:type":"buffered point",
    "wof:lang":[
        "ita"
    ],
    "wof:name":"Magugnano",
    "wof:placetype":"locality",
    "wof:population":2390
},
  "geometry": {"coordinates":[10.76305,45.699829],"type":"Point"}
}