{
  "type": "Feature",
  "properties": {
    "gn:admin1_code":"12",
    "gn:admin2_code":"AT",
    "gn:admin3_code":"5055.0",
    "gn:asciiname":"Bricco Morra",
    "gn:country_code":"IT",
    "gn:dem":250,
    "gn:feature_class":"P",
    "gn:feature_code":"PPL",
    "gn:name":"Bricco Morra",
    "gn:population":33,
    "gn:timezone":"Europe/Rome",
    "iso:country":"IT",
    "wof:name":"Bricco Morra",
    "wof:placetype":"locality",
    "wof:population":33
},
  "geometry": {"coordinates":[8.17896,44.99506],"type":"Point"}
}