{
  "type": "Feature",
  "properties": {
    "gn:gn_country":"IT",
    "gn:gn_fcode":"PPLA3",
    "gn:gn_pop":1319,
    "gn:population":309,
    "iso:country":"IT",
    "name:azb_x_preferred":[
        "\u067e\u0648\u0644\u06cc\u0627"
    ],
    "name:bcl_x_preferred":[
        "Polia"
    ],
    "name:bul_x_preferred":[
        "\u041f\u043e\u043b\u0438\u044f"
    ],
    "name:cat_x_preferred":[
        "Polia"
    ],
    "name:ceb_x_preferred":[
        "Polia"
    ],
    "name:deu_x_preferred":[
        "Polia"
    ],
    "name:eng_x_preferred":[
        "Polia"
    ],
    "name:epo_x_preferred":[
        "Polia"
    ],
    "name:eus_x_preferred":[
        "Polia"
    ],
    "name:fas_x_preferred":[
        "\u067e\u0648\u0644\u06cc\u0627"
    ],
    "name:fra_x_preferred":[
        "Polia"
    ],
    "name:hun_x_preferred":[
        "Polia"
    ],
    "name:hye_x_preferred":[
        "\u054a\u0578\u056c\u056b\u0561"
    ],
    "name:ina_x_preferred":[
        "Polia"
    ],
    "name:ita_x_preferred":[
        "Polia"
    ],
    "name:jpn_x_preferred":[
        "\u30dd\u30ea\u30fc\u30a2"
    ],
    "name:kaz_x_preferred":[
        "\u041f\u043e\u043b\u0438\u044f"
    ],
    "name:lat_x_preferred":[
        "Polia"
    ],
    "name:lmo_x_preferred":[
        "Polia"
    ],
    "name:ltz_x_preferred":[
        "Polia"
    ],
    "name:msa_x_preferred":[
        "Polia"
    ],
    "name:nan_x_preferred":[
        "Polia"
    ],
    "name:nap_x_preferred":[
        "Polia"
    ],
    "name:nld_x_preferred":[
        "Polia"
    ],
    "name:oci_x_preferred":[
        "Polia"
    ],
    "name:pol_x_preferred":[
        "Polia"
    ],
    "name:por_x_preferred":[
        "Polia"
    ],
    "name:ron_x_preferred":[
        "Polia"
    ],
    "name:rus_x_preferred":[
        "\u041f\u043e\u043b\u0438\u044f"
    ],
    "name:scn_x_preferred":[
        "Pulia"
    ],
    "name:sco_x_preferred":[
        "Polia"
    ],
    "name:spa_x_preferred":[
        "Polia"
    ],
    "name:srp_x_preferred":[
        "Polia"
    ],
    "name:ukr_x_preferred":[
        "\u041f\u043e\u043b\u0456\u044f"
    ],
    "name:uzb_x_preferred":[
        "Polia"
    ],
    "name:vie_x_preferred":[
        "Polia"
    ],
    "name:vol_x_preferred":[
        "Polia"
    ],
    "name:war_x_preferred":[
        "Polia"
    ],
    "qs_pg:aaroncc":"IT",
    "qs_pg:gn_country":"IT",
    "qs_pg:gn_fcode":"PPLA3",
    "qs_pg:gn_pop":1319,
    "qs_pg:name":"Polia",
    "qs_pg:name_adm0":"Italia",
    "qs_pg:name_adm1":"Calabria",
    "qs_pg:photos_9k":1,
    "qs_pg:photos_9r":1,
    "qs_pg:photos_all":5,
    "qs_pg:photos_sr":0,
    "qs_pg:pop_sr":3,
    "qs_pg:qs_pg_placetype":"locality",
    "qs_pg:qs_pg_placetype_gp":"Town",
    "qs_pg:woe_adm0":23424853,
    "woe:adm0_id":23424853,
    "woe:name_adm0":"Italia",
    "woe:name_adm1":"Calabria",
    "woe:placetype":"Town",
    "wof:name":"Polia",
    "wof:placetype":"locality",
    "wof:population":309
},
  "geometry": {"coordinates":[16.3122,38.75118],"type":"Point"}
}