{
  "type": "Feature",
  "properties": {
    "gn:admin1_code":"9.0",
    "gn:admin2_code":"BG",
    "gn:admin3_code":"16066.0",
    "gn:asciiname":"Triangolo di Cavernago",
    "gn:country_code":"IT",
    "gn:dem":187,
    "gn:feature_class":"P",
    "gn:feature_code":"PPL",
    "gn:name":"Triangolo di Cavernago",
    "gn:population":1,
    "gn:timezone":"Europe/Rome",
    "iso:country":"IT",
    "wof:name":"Triangolo di Cavernago",
    "wof:placetype":"locality",
    "wof:population":1
},
  "geometry": {"coordinates":[9.77654,45.617],"type":"Point"}
}