{
  "type": "Feature",
  "properties": {
    "gn:admin1_code":"4",
    "gn:admin2_code":"CE",
    "gn:admin3_code":"61050.0",
    "gn:asciiname":"Cardoni",
    "gn:country_code":"IT",
    "gn:dem":359,
    "gn:feature_class":"P",
    "gn:feature_code":"PPL",
    "gn:name":"Cardoni",
    "gn:population":45,
    "gn:timezone":"Europe/Rome",
    "iso:country":"IT",
    "wof:name":"Cardoni",
    "wof:placetype":"locality",
    "wof:population":45
},
  "geometry": {"coordinates":[14.03348,41.31996],"type":"Point"}
}