{
  "type": "Feature",
  "properties": {
    "gn:admin1_code":"5",
    "gn:admin2_code":"RE",
    "gn:admin3_code":"35018.0",
    "gn:asciiname":"Dirotte",
    "gn:country_code":"IT",
    "gn:dem":208,
    "gn:feature_class":"P",
    "gn:feature_code":"PPL",
    "gn:name":"Dirotte",
    "gn:population":26,
    "gn:timezone":"Europe/Rome",
    "iso:country":"IT",
    "wof:name":"Dirotte",
    "wof:placetype":"locality",
    "wof:population":26
},
  "geometry": {"coordinates":[10.40345,44.57825],"type":"Point"}
}