{
  "type": "Feature",
  "properties": {
    "gn:admin1_code":"12",
    "gn:admin2_code":"AT",
    "gn:admin3_code":"5118.0",
    "gn:asciiname":"Santa Filomena",
    "gn:country_code":"IT",
    "gn:dem":257,
    "gn:feature_class":"P",
    "gn:feature_code":"PPL",
    "gn:name":"Santa Filomena",
    "gn:population":12,
    "gn:timezone":"Europe/Rome",
    "iso:country":"IT",
    "name:ceb_x_preferred":[
        "Santa Filomena"
    ],
    "name:deu_x_preferred":[
        "Santa Filomena"
    ],
    "name:fra_x_preferred":[
        "Santa Filomena"
    ],
    "name:ita_x_preferred":[
        "Santa Filomena"
    ],
    "name:nld_x_preferred":[
        "Santa Filomena"
    ],
    "name:nor_x_preferred":[
        "Santa Filomena"
    ],
    "name:por_x_preferred":[
        "Santa Filomena"
    ],
    "name:rus_x_preferred":[
        "\u0421\u0430\u043d\u0442\u0430-\u0424\u0438\u043b\u043e\u043c\u0435\u043d\u0430"
    ],
    "name:spa_x_preferred":[
        "Santa Filomena"
    ],
    "name:srp_x_preferred":[
        "\u0421\u0430\u043d\u0442\u0430 \u0424\u0438\u043b\u043e\u043c\u0435\u043d\u0430"
    ],
    "name:swe_x_preferred":[
        "Santa Filomena"
    ],
    "name:vie_x_preferred":[
        "Santa Filomena"
    ],
    "name:vol_x_preferred":[
        "Santa Filomena"
    ],
    "wof:name":"Santa Filomena",
    "wof:placetype":"locality",
    "wof:population":12
},
  "geometry": {"coordinates":[7.9226,44.94171],"type":"Point"}
}