{
  "type": "Feature",
  "properties": {
    "gn:admin1_code":"16",
    "gn:admin2_code":"LU",
    "gn:admin3_code":"46003.0",
    "gn:asciiname":"Frascone",
    "gn:country_code":"IT",
    "gn:dem":176,
    "gn:feature_class":"P",
    "gn:feature_code":"PPL",
    "gn:name":"Frascone",
    "gn:population":54,
    "gn:timezone":"Europe/Rome",
    "iso:country":"IT",
    "wof:name":"Frascone",
    "wof:placetype":"locality",
    "wof:population":54
},
  "geometry": {"coordinates":[10.45589,44.05745],"type":"Point"}
}