{
  "type": "Feature",
  "properties": {
    "gn:admin1_code":"13.0",
    "gn:admin2_code":"BR",
    "gn:admin3_code":"74001.0",
    "gn:asciiname":"Localita Produttiva",
    "gn:country_code":"IT",
    "gn:dem":16,
    "gn:feature_class":"P",
    "gn:feature_code":"PPLL",
    "gn:name":"Localit\u00e0 Produttiva",
    "gn:population":0,
    "gn:timezone":"Europe/Rome",
    "iso:country":"IT",
    "name:und_x_variant":[
        "Localit\u00e0 Produttiva"
    ],
    "wof:name":"Localita Produttiva",
    "wof:placetype":"locality"
},
  "geometry": {"coordinates":[18.03044,40.56421],"type":"Point"}
}