{
  "type": "Feature",
  "properties": {
    "gn:admin1_code":"12",
    "gn:admin2_code":"TO",
    "gn:admin3_code":"1097.0",
    "gn:asciiname":"Faraudi",
    "gn:country_code":"IT",
    "gn:dem":482,
    "gn:feature_class":"P",
    "gn:feature_code":"PPL",
    "gn:name":"Faraudi",
    "gn:population":44,
    "gn:timezone":"Europe/Rome",
    "iso:country":"IT",
    "wof:name":"Faraudi",
    "wof:placetype":"locality",
    "wof:population":44
},
  "geometry": {"coordinates":[7.36901,44.99578],"type":"Point"}
}