{
  "type": "Feature",
  "properties": {
    "gn:admin1_code":"20",
    "gn:admin2_code":"VI",
    "gn:admin3_code":"24104.0",
    "gn:asciiname":"Scopel",
    "gn:country_code":"IT",
    "gn:dem":64,
    "gn:feature_class":"P",
    "gn:feature_code":"PPL",
    "gn:name":"Scopel",
    "gn:population":34,
    "gn:timezone":"Europe/Rome",
    "iso:country":"IT",
    "wof:name":"Scopel",
    "wof:placetype":"locality",
    "wof:population":34
},
  "geometry": {"coordinates":[11.74663,45.6802],"type":"Point"}
}