{
  "type": "Feature",
  "properties": {
    "gn:admin1_code":"5",
    "gn:admin2_code":"BO",
    "gn:admin3_code":"37006.0",
    "gn:admin4_code":"3700612.0",
    "gn:asciiname":"Fornace",
    "gn:country_code":"IT",
    "gn:dem":33,
    "gn:feature_class":"P",
    "gn:feature_code":"PPL",
    "gn:name":"Fornace",
    "gn:population":56,
    "gn:timezone":"Europe/Rome",
    "iso:country":"IT",
    "wof:name":"Fornace",
    "wof:placetype":"locality",
    "wof:population":56
},
  "geometry": {"coordinates":[11.37517,44.53259],"type":"Point"}
}