{
  "type": "Feature",
  "properties": {
    "iso:country":"IT",
    "qs_pg:aaroncc":"IT",
    "qs_pg:name":"Lago Sirino",
    "qs_pg:name_adm0":"Italia",
    "qs_pg:name_adm1":"Basilicata",
    "qs_pg:photos":41,
    "qs_pg:photos_1k":8,
    "qs_pg:photos_9k":1,
    "qs_pg:photos_9r":2,
    "qs_pg:photos_all":41,
    "qs_pg:photos_sr":2,
    "qs_pg:pop_sr":0,
    "qs_pg:qs_pg_placetype":"locality",
    "qs_pg:qs_pg_placetype_gp":"Town",
    "qs_pg:woe_adm0":23424853,
    "woe:adm0_id":23424853,
    "woe:name_adm0":"Italia",
    "woe:name_adm1":"Basilicata",
    "woe:placetype":"Town",
    "wof:name":"Lago Sirino",
    "wof:placetype":"locality"
},
  "geometry": {"coordinates":[15.80805,40.09173],"type":"Point"}
}