{
  "type": "Feature",
  "properties": {
    "gn:admin1_code":"1",
    "gn:admin2_code":"TE",
    "gn:admin3_code":"67006.0",
    "gn:asciiname":"Case Ippoliti",
    "gn:country_code":"IT",
    "gn:dem":228,
    "gn:feature_class":"P",
    "gn:feature_code":"PPL",
    "gn:name":"Case Ippoliti",
    "gn:population":19,
    "gn:timezone":"Europe/Rome",
    "iso:country":"IT",
    "wof:name":"Case Ippoliti",
    "wof:placetype":"locality",
    "wof:population":19
},
  "geometry": {"coordinates":[13.84409,42.74185],"type":"Point"}
}