{
  "type": "Feature",
  "properties": {
    "gn:admin1_code":"7",
    "gn:admin2_code":"FR",
    "gn:admin3_code":"60032.0",
    "gn:asciiname":"Colle Mancino",
    "gn:country_code":"IT",
    "gn:dem":115,
    "gn:feature_class":"P",
    "gn:feature_code":"PPL",
    "gn:name":"Colle Mancino",
    "gn:population":46,
    "gn:timezone":"Europe/Rome",
    "iso:country":"IT",
    "wof:name":"Colle Mancino",
    "wof:placetype":"locality",
    "wof:population":46
},
  "geometry": {"coordinates":[13.51943,41.51186],"type":"Point"}
}