{
  "type": "Feature",
  "properties": {
    "gn:admin1_code":"9.0",
    "gn:admin2_code":"SO",
    "gn:admin3_code":"14071.0",
    "gn:asciiname":"Semogo",
    "gn:country_code":"IT",
    "gn:dem":1479,
    "gn:elevation":"1370.0",
    "gn:feature_class":"P",
    "gn:feature_code":"PPL",
    "gn:name":"Semogo",
    "gn:population":760,
    "gn:timezone":"Europe/Rome",
    "iso:country":"IT",
    "wof:name":"Semogo",
    "wof:placetype":"locality",
    "wof:population":760
},
  "geometry": {"coordinates":[10.27005,46.48499],"type":"Point"}
}