{
  "type": "Feature",
  "properties": {
    "gn:admin1_code":"5.0",
    "gn:admin2_code":"BO",
    "gn:admin3_code":"37032.0",
    "gn:asciiname":"Casa Mantesana",
    "gn:country_code":"IT",
    "gn:dem":14,
    "gn:feature_class":"P",
    "gn:feature_code":"PPL",
    "gn:name":"Casa Mantesana",
    "gn:population":0,
    "gn:timezone":"Europe/Rome",
    "iso:country":"IT",
    "wof:name":"Casa Mantesana",
    "wof:placetype":"locality"
},
  "geometry": {"coordinates":[11.76667,44.43333],"type":"Point"}
}