{
  "type": "Feature",
  "properties": {
    "gn:admin1_code":"3.0",
    "gn:admin2_code":"CS",
    "gn:admin3_code":"78107.0",
    "gn:asciiname":"Villaggio Borgo Roseto",
    "gn:country_code":"IT",
    "gn:dem":123,
    "gn:feature_class":"P",
    "gn:feature_code":"PPLL",
    "gn:name":"Villaggio Borgo Roseto",
    "gn:population":3,
    "gn:timezone":"Europe/Rome",
    "iso:country":"IT",
    "wof:name":"Villaggio Borgo Roseto",
    "wof:placetype":"locality",
    "wof:population":3
},
  "geometry": {"coordinates":[16.60659,39.97845],"type":"Point"}
}