{
  "type": "Feature",
  "properties": {
    "gn:admin1_code":"4.0",
    "gn:admin2_code":"SA",
    "gn:admin3_code":"65003.0",
    "gn:asciiname":"San Cesareo II",
    "gn:country_code":"IT",
    "gn:dem":23,
    "gn:feature_class":"P",
    "gn:feature_code":"PPL",
    "gn:name":"San Cesareo II",
    "gn:population":28,
    "gn:timezone":"Europe/Rome",
    "iso:country":"IT",
    "wof:name":"San Cesareo II",
    "wof:placetype":"locality",
    "wof:population":28
},
  "geometry": {"coordinates":[15.03509,40.50319],"type":"Point"}
}