{
  "type": "Feature",
  "properties": {
    "gn:admin1_code":"5",
    "gn:admin2_code":"PC",
    "gn:admin3_code":"33002.0",
    "gn:asciiname":"Case Boccelli",
    "gn:country_code":"IT",
    "gn:dem":105,
    "gn:feature_class":"P",
    "gn:feature_code":"PPL",
    "gn:name":"Case Boccelli",
    "gn:population":25,
    "gn:timezone":"Europe/Rome",
    "iso:country":"IT",
    "wof:name":"Case Boccelli",
    "wof:placetype":"locality",
    "wof:population":25
},
  "geometry": {"coordinates":[9.98927,44.87413],"type":"Point"}
}