{
  "type": "Feature",
  "properties": {
    "gn:admin1_code":"5",
    "gn:admin2_code":"PC",
    "gn:admin3_code":"33026.0",
    "gn:asciiname":"Tabiano",
    "gn:country_code":"IT",
    "gn:dem":222,
    "gn:feature_class":"P",
    "gn:feature_code":"PPL",
    "gn:name":"Tabiano",
    "gn:population":23,
    "gn:timezone":"Europe/Rome",
    "iso:country":"IT",
    "wof:name":"Tabiano",
    "wof:placetype":"locality",
    "wof:population":23
},
  "geometry": {"coordinates":[9.76702,44.84416],"type":"Point"}
}