{
  "type": "Feature",
  "properties": {
    "gn:admin1_code":"16",
    "gn:admin2_code":"GR",
    "gn:admin3_code":"53025.0",
    "gn:asciiname":"Altori",
    "gn:country_code":"IT",
    "gn:dem":854,
    "gn:feature_class":"P",
    "gn:feature_code":"PPL",
    "gn:name":"Altori",
    "gn:population":26,
    "gn:timezone":"Europe/Rome",
    "iso:country":"IT",
    "wof:name":"Altori",
    "wof:placetype":"locality",
    "wof:population":26
},
  "geometry": {"coordinates":[11.61983,42.92802],"type":"Point"}
}