{
  "type": "Feature",
  "properties": {
    "gn:admin1_code":"12",
    "gn:admin2_code":"AL",
    "gn:admin3_code":"6119.0",
    "gn:asciiname":"San Quirico",
    "gn:country_code":"IT",
    "gn:dem":306,
    "gn:feature_class":"P",
    "gn:feature_code":"PPL",
    "gn:name":"San Quirico",
    "gn:population":102,
    "gn:timezone":"Europe/Rome",
    "iso:country":"IT",
    "wof:name":"San Quirico",
    "wof:placetype":"locality",
    "wof:population":102
},
  "geometry": {"coordinates":[8.56929,44.68618],"type":"Point"}
}