{
  "type": "Feature",
  "properties": {
    "gn:admin1_code":"5",
    "gn:admin2_code":"MO",
    "gn:admin3_code":"36046.0",
    "gn:asciiname":"Due Ponti",
    "gn:country_code":"IT",
    "gn:dem":138,
    "gn:feature_class":"P",
    "gn:feature_code":"PPL",
    "gn:name":"Due Ponti",
    "gn:population":44,
    "gn:timezone":"Europe/Rome",
    "iso:country":"IT",
    "wof:name":"Due Ponti",
    "wof:placetype":"locality",
    "wof:population":44
},
  "geometry": {"coordinates":[10.98092,44.48286],"type":"Point"}
}