{
  "type": "Feature",
  "properties": {
    "gn:admin1_code":"12.0",
    "gn:admin2_code":"VC",
    "gn:admin3_code":"2002.0",
    "gn:asciiname":"Alpe Campo Sup.",
    "gn:country_code":"IT",
    "gn:dem":1913,
    "gn:elevation":"1923.0",
    "gn:feature_class":"P",
    "gn:feature_code":"PPL",
    "gn:name":"Alpe Campo Sup.",
    "gn:population":0,
    "gn:timezone":"Europe/Rome",
    "iso:country":"IT",
    "wof:name":"Alpe Campo Sup.",
    "wof:placetype":"locality"
},
  "geometry": {"coordinates":[7.95412,45.86097],"type":"Point"}
}