{
  "type": "Feature",
  "properties": {
    "gn:admin1_code":"12",
    "gn:admin2_code":"TO",
    "gn:admin3_code":"1073.0",
    "gn:asciiname":"Prese-Montone",
    "gn:country_code":"IT",
    "gn:dem":1534,
    "gn:feature_class":"P",
    "gn:feature_code":"PPL",
    "gn:name":"Prese-Montone",
    "gn:population":83,
    "gn:timezone":"Europe/Rome",
    "iso:country":"IT",
    "wof:name":"Prese-Montone",
    "wof:placetype":"locality",
    "wof:population":83
},
  "geometry": {"coordinates":[7.25076,45.43278],"type":"Point"}
}