{
  "type": "Feature",
  "properties": {
    "gn:admin1_code":"15.0",
    "gn:admin2_code":"ME",
    "gn:admin3_code":"83092.0",
    "gn:asciiname":"Saponara Marittima",
    "gn:country_code":"IT",
    "gn:dem":43,
    "gn:feature_class":"P",
    "gn:feature_code":"PPL",
    "gn:name":"Saponara Marittima",
    "gn:population":1594,
    "gn:timezone":"Europe/Rome",
    "iso:country":"IT",
    "wof:name":"Saponara Marittima",
    "wof:placetype":"locality",
    "wof:population":1594
},
  "geometry": {"coordinates":[15.42621,38.23121],"type":"Point"}
}