{
  "type": "Feature",
  "properties": {
    "gn:admin1_code":"20",
    "gn:admin2_code":"VI",
    "gn:admin3_code":"24028.0",
    "gn:asciiname":"Grumi",
    "gn:country_code":"IT",
    "gn:dem":245,
    "gn:feature_class":"P",
    "gn:feature_code":"PPL",
    "gn:name":"Grumi",
    "gn:population":63,
    "gn:timezone":"Europe/Rome",
    "iso:country":"IT",
    "wof:name":"Grumi",
    "wof:placetype":"locality",
    "wof:population":63
},
  "geometry": {"coordinates":[11.40151,45.57812],"type":"Point"}
}