{
  "type": "Feature",
  "properties": {
    "gn:admin1_code":"7",
    "gn:admin2_code":"RM",
    "gn:admin3_code":"58038.0",
    "gn:asciiname":"Macere",
    "gn:country_code":"IT",
    "gn:dem":144,
    "gn:feature_class":"P",
    "gn:feature_code":"PPL",
    "gn:name":"Macere",
    "gn:population":119,
    "gn:timezone":"Europe/Rome",
    "iso:country":"IT",
    "wof:name":"Macere",
    "wof:placetype":"locality",
    "wof:population":119
},
  "geometry": {"coordinates":[12.40472,42.05638],"type":"Point"}
}