{
  "type": "Feature",
  "properties": {
    "gn:admin1_code":"18",
    "gn:admin2_code":"TR",
    "gn:admin3_code":"55030.0",
    "gn:asciiname":"Vesca",
    "gn:country_code":"IT",
    "gn:dem":304,
    "gn:feature_class":"P",
    "gn:feature_code":"PPL",
    "gn:name":"Vesca",
    "gn:population":27,
    "gn:timezone":"Europe/Rome",
    "iso:country":"IT",
    "name:bos_x_preferred":[
        "Vesca"
    ],
    "name:bul_x_preferred":[
        "\u0412\u0435\u0441\u0446\u0430"
    ],
    "name:nld_x_preferred":[
        "Vesca"
    ],
    "name:pol_x_preferred":[
        "Vesca"
    ],
    "name:ron_x_preferred":[
        "Vesca"
    ],
    "name:slv_x_preferred":[
        "Vesca"
    ],
    "name:ukr_x_preferred":[
        "\u0412\u0435\u0441\u0446\u0430"
    ],
    "wof:name":"Vesca",
    "wof:placetype":"locality",
    "wof:population":27
},
  "geometry": {"coordinates":[12.30416,42.90235],"type":"Point"}
}