{
  "type": "Feature",
  "properties": {
    "gn:admin1_code":"19",
    "gn:admin2_code":"AO",
    "gn:admin3_code":"7018.0",
    "gn:asciiname":"Grand Rosier",
    "gn:country_code":"IT",
    "gn:dem":1462,
    "gn:feature_class":"P",
    "gn:feature_code":"PPL",
    "gn:name":"Grand Rosier",
    "gn:population":23,
    "gn:timezone":"Europe/Rome",
    "iso:country":"IT",
    "wof:name":"Grand Rosier",
    "wof:placetype":"locality",
    "wof:population":23
},
  "geometry": {"coordinates":[7.65143,45.62665],"type":"Point"}
}