{
  "type": "Feature",
  "properties": {
    "gn:admin1_code":"12",
    "gn:admin2_code":"TO",
    "gn:admin3_code":"1041.0",
    "gn:asciiname":"Via Paglieri",
    "gn:country_code":"IT",
    "gn:dem":304,
    "gn:feature_class":"P",
    "gn:feature_code":"PPL",
    "gn:name":"Via Paglieri",
    "gn:population":40,
    "gn:timezone":"Europe/Rome",
    "iso:country":"IT",
    "wof:name":"Via Paglieri",
    "wof:placetype":"locality",
    "wof:population":40
},
  "geometry": {"coordinates":[7.40527,44.86995],"type":"Point"}
}