{
  "type": "Feature",
  "properties": {
    "gn:admin1_code":"6.0",
    "gn:admin2_code":"UD",
    "gn:admin3_code":"30013.0",
    "gn:asciiname":"Santo Stefano",
    "gn:country_code":"IT",
    "gn:dem":214,
    "gn:feature_class":"P",
    "gn:feature_code":"PPLA3",
    "gn:name":"Santo Stefano",
    "gn:population":0,
    "gn:timezone":"Europe/Rome",
    "iso:country":"IT",
    "wof:name":"Santo Stefano",
    "wof:placetype":"locality"
},
  "geometry": {"coordinates":[13.12626,46.20865],"type":"Point"}
}