{
  "type": "Feature",
  "properties": {
    "gn:admin1_code":"8",
    "gn:admin2_code":"SP",
    "gn:admin3_code":"11012.0",
    "gn:asciiname":"Ghiaia",
    "gn:country_code":"IT",
    "gn:dem":65,
    "gn:feature_class":"P",
    "gn:feature_code":"PPL",
    "gn:name":"Ghiaia",
    "gn:population":36,
    "gn:timezone":"Europe/Rome",
    "iso:country":"IT",
    "wof:name":"Ghiaia",
    "wof:placetype":"locality",
    "wof:population":36
},
  "geometry": {"coordinates":[9.54965,44.22634],"type":"Point"}
}