{
  "type": "Feature",
  "properties": {
    "gn:admin1_code":"20.0",
    "gn:admin2_code":"VI",
    "gn:admin3_code":"24106.0",
    "gn:asciiname":"Valle II",
    "gn:country_code":"IT",
    "gn:dem":1048,
    "gn:feature_class":"P",
    "gn:feature_code":"PPL",
    "gn:name":"Valle II",
    "gn:population":3,
    "gn:timezone":"Europe/Rome",
    "iso:country":"IT",
    "wof:name":"Valle II",
    "wof:placetype":"locality",
    "wof:population":3
},
  "geometry": {"coordinates":[11.32071,45.86067],"type":"Point"}
}