{
  "type": "Feature",
  "properties": {
    "gn:admin1_code":"4.0",
    "gn:admin2_code":"SA",
    "gn:admin3_code":"65025.0",
    "gn:asciiname":"Queglia",
    "gn:country_code":"IT",
    "gn:dem":4,
    "gn:feature_class":"P",
    "gn:feature_code":"PPL",
    "gn:name":"Queglia",
    "gn:population":46,
    "gn:timezone":"Europe/Rome",
    "iso:country":"IT",
    "wof:name":"Queglia",
    "wof:placetype":"locality",
    "wof:population":46
},
  "geometry": {"coordinates":[14.98943,40.45775],"type":"Point"}
}