{
  "type": "Feature",
  "properties": {
    "gn:admin1_code":"5",
    "gn:admin2_code":"PC",
    "gn:admin3_code":"33044.0",
    "gn:asciiname":"Franchini",
    "gn:country_code":"IT",
    "gn:dem":193,
    "gn:feature_class":"P",
    "gn:feature_code":"PPL",
    "gn:name":"Franchini",
    "gn:population":21,
    "gn:timezone":"Europe/Rome",
    "iso:country":"IT",
    "wof:name":"Franchini",
    "wof:placetype":"locality",
    "wof:population":21
},
  "geometry": {"coordinates":[9.87976,44.82706],"type":"Point"}
}