{
  "type": "Feature",
  "properties": {
    "gn:admin1_code":"18",
    "gn:admin2_code":"PG",
    "gn:admin3_code":"54042.0",
    "gn:asciiname":"Roccatamburo",
    "gn:country_code":"IT",
    "gn:dem":790,
    "gn:feature_class":"P",
    "gn:feature_code":"PPL",
    "gn:name":"Roccatamburo",
    "gn:population":34,
    "gn:timezone":"Europe/Rome",
    "iso:country":"IT",
    "wof:name":"Roccatamburo",
    "wof:placetype":"locality",
    "wof:population":34
},
  "geometry": {"coordinates":[12.93607,42.73661],"type":"Point"}
}