{
  "type": "Feature",
  "properties": {
    "gn:admin1_code":"20",
    "gn:admin2_code":"PD",
    "gn:admin3_code":"28013.0",
    "gn:asciiname":"Pelosa",
    "gn:country_code":"IT",
    "gn:dem":14,
    "gn:feature_class":"P",
    "gn:feature_code":"PPL",
    "gn:name":"Pelosa",
    "gn:population":58,
    "gn:timezone":"Europe/Rome",
    "iso:country":"IT",
    "wof:name":"Pelosa",
    "wof:placetype":"locality",
    "wof:population":58
},
  "geometry": {"coordinates":[11.99542,45.53844],"type":"Point"}
}