{
  "type": "Feature",
  "properties": {
    "gn:elevation":575,
    "gn:population":45,
    "iso:country":"IT",
    "name:bel_x_preferred":[
        "\u041c\u0430\u0439\u0441\u0430\u043d\u0430"
    ],
    "name:bul_x_preferred":[
        "\u041c\u0430\u0439\u0441\u0430\u043d\u0430"
    ],
    "name:deu_x_preferred":[
        "Maissana"
    ],
    "name:eng_x_preferred":[
        "Maissana"
    ],
    "name:epo_x_preferred":[
        "Maissana"
    ],
    "name:eus_x_preferred":[
        "Maissana"
    ],
    "name:fas_x_preferred":[
        "\u0645\u0627\u06cc\u0633\u0627\u0646\u0627"
    ],
    "name:fra_x_preferred":[
        "Maissana"
    ],
    "name:hbs_x_preferred":[
        "Maissana"
    ],
    "name:hun_x_preferred":[
        "Maissana"
    ],
    "name:hye_x_preferred":[
        "\u0544\u0561\u0575\u057d\u0561\u0576\u0561"
    ],
    "name:ina_x_preferred":[
        "Maissana"
    ],
    "name:ita_x_preferred":[
        "Maissana"
    ],
    "name:jpn_x_preferred":[
        "\u30de\u30a4\u30c3\u30b5\u30fc\u30ca"
    ],
    "name:kaz_x_preferred":[
        "\u041c\u0430\u0439\u0441\u0441\u0430\u043d\u0430"
    ],
    "name:lat_x_preferred":[
        "Masiana"
    ],
    "name:lij_x_preferred":[
        "Maissann-a"
    ],
    "name:lmo_x_preferred":[
        "Maissana"
    ],
    "name:msa_x_preferred":[
        "Maissana"
    ],
    "name:nan_x_preferred":[
        "Maissana"
    ],
    "name:nap_x_preferred":[
        "Maissana"
    ],
    "name:nld_x_preferred":[
        "Maissana"
    ],
    "name:pms_x_preferred":[
        "Maissana"
    ],
    "name:pol_x_preferred":[
        "Maissana"
    ],
    "name:por_x_preferred":[
        "Maissana"
    ],
    "name:ron_x_preferred":[
        "Maissana"
    ],
    "name:rus_x_preferred":[
        "\u041c\u0430\u0439\u0441\u0441\u0430\u043d\u0430"
    ],
    "name:scn_x_preferred":[
        "Maissana"
    ],
    "name:spa_x_preferred":[
        "Maissana"
    ],
    "name:srp_x_preferred":[
        "\u041c\u0430\u0438\u0441\u0430\u043d\u0430"
    ],
    "name:ukr_x_preferred":[
        "\u041c\u0430\u0457\u0441\u0441\u0430\u043d\u0430"
    ],
    "name:uzb_x_preferred":[
        "Maissana"
    ],
    "name:vie_x_preferred":[
        "Maissana"
    ],
    "name:vol_x_preferred":[
        "Maissana"
    ],
    "name:war_x_preferred":[
        "Maissana"
    ],
    "name:zho_min_nan_x_preferred":[
        "Maissana"
    ],
    "name:zho_x_preferred":[
        "\u9a6c\u4f0a\u8428\u7eb3"
    ],
    "qs:a0":"Italia",
    "qs:a1":"*La Spezia",
    "qs:a1r":"0Liguria",
    "qs:adm0":"Italia",
    "qs:la_lc":"*",
    "qs:level":"locality",
    "qs:loc":"Maissana",
    "qs:loc_alt":"Maissana",
    "qs:pop":0,
    "qs:type":"buffered point",
    "wd:wordcount":110,
    "wof:lang":[
        "ita"
    ],
    "wof:name":"Maissana",
    "wof:placetype":"locality",
    "wof:population":45
},
  "geometry": {"coordinates":[9.536669,44.337501],"type":"Point"}
}