{
  "type": "Feature",
  "properties": {
    "gn:admin1_code":"5",
    "gn:admin2_code":"PC",
    "gn:admin3_code":"33029.0",
    "gn:asciiname":"Casa Roveda",
    "gn:country_code":"IT",
    "gn:dem":166,
    "gn:feature_class":"P",
    "gn:feature_code":"PPL",
    "gn:name":"Casa Roveda",
    "gn:population":33,
    "gn:timezone":"Europe/Rome",
    "iso:country":"IT",
    "wof:name":"Casa Roveda",
    "wof:placetype":"locality",
    "wof:population":33
},
  "geometry": {"coordinates":[9.4249,44.95106],"type":"Point"}
}