{
  "type": "Feature",
  "properties": {
    "gn:admin1_code":"16",
    "gn:admin2_code":"PT",
    "gn:admin3_code":"47005.0",
    "gn:asciiname":"La Berga",
    "gn:country_code":"IT",
    "gn:dem":89,
    "gn:feature_class":"P",
    "gn:feature_code":"PPL",
    "gn:name":"La Berga",
    "gn:population":37,
    "gn:timezone":"Europe/Rome",
    "iso:country":"IT",
    "wof:name":"La Berga",
    "wof:placetype":"locality",
    "wof:population":37
},
  "geometry": {"coordinates":[10.90977,43.81024],"type":"Point"}
}