{
  "type": "Feature",
  "properties": {
    "gn:admin1_code":"12.0",
    "gn:admin2_code":"VB",
    "gn:admin3_code":"103072.0",
    "gn:asciiname":"Pallanza",
    "gn:country_code":"IT",
    "gn:dem":211,
    "gn:feature_class":"P",
    "gn:feature_code":"PPL",
    "gn:name":"Pallanza",
    "gn:population":0,
    "gn:timezone":"Europe/Rome",
    "iso:country":"IT",
    "name:fra_x_preferred":[
        "Pallanza"
    ],
    "name:ita_x_preferred":[
        "Pallanza"
    ],
    "name:lat_x_preferred":[
        "Pallantia"
    ],
    "name:lmo_x_preferred":[
        "Palanza"
    ],
    "name:ukr_x_preferred":[
        "\u041f\u0430\u043b\u043b\u0430\u043d\u0446\u0430"
    ],
    "wof:name":"Pallanza",
    "wof:placetype":"locality"
},
  "geometry": {"coordinates":[8.55045,45.92298],"type":"Point"}
}