{
  "type": "Feature",
  "properties": {
    "gn:admin1_code":"5",
    "gn:admin2_code":"PR",
    "gn:admin3_code":"34044.0",
    "gn:asciiname":"Lennova",
    "gn:country_code":"IT",
    "gn:dem":728,
    "gn:feature_class":"P",
    "gn:feature_code":"PPL",
    "gn:name":"Lennova",
    "gn:population":11,
    "gn:timezone":"Europe/Rome",
    "iso:country":"IT",
    "wof:name":"Lennova",
    "wof:placetype":"locality",
    "wof:population":11
},
  "geometry": {"coordinates":[9.88668,44.59461],"type":"Point"}
}