{
  "type": "Feature",
  "properties": {
    "gn:admin1_code":"9",
    "gn:admin2_code":"BG",
    "gn:admin3_code":"16006.0",
    "gn:asciiname":"Capreti",
    "gn:country_code":"IT",
    "gn:dem":497,
    "gn:feature_class":"P",
    "gn:feature_code":"PPL",
    "gn:name":"Capreti",
    "gn:population":16,
    "gn:timezone":"Europe/Rome",
    "iso:country":"IT",
    "wof:name":"Capreti",
    "wof:placetype":"locality",
    "wof:population":16
},
  "geometry": {"coordinates":[9.55298,45.75714],"type":"Point"}
}