{
  "type": "Feature",
  "properties": {
    "gn:admin1_code":"5.0",
    "gn:admin2_code":"RE",
    "gn:admin3_code":"35032.0",
    "gn:asciiname":"Villanova",
    "gn:country_code":"IT",
    "gn:dem":19,
    "gn:feature_class":"P",
    "gn:feature_code":"PPL",
    "gn:name":"Villanova",
    "gn:population":438,
    "gn:timezone":"Europe/Rome",
    "iso:country":"IT",
    "name:ast_x_preferred":[
        "Villanova"
    ],
    "name:bar_x_preferred":[
        "Villanova"
    ],
    "name:bre_x_preferred":[
        "Villanova"
    ],
    "name:bul_x_preferred":[
        "\u0412\u0438\u043b\u0430\u043d\u043e\u0432\u0430"
    ],
    "name:ceb_x_preferred":[
        "Villanova"
    ],
    "name:deu_x_preferred":[
        "Villanova"
    ],
    "name:fra_x_preferred":[
        "Villanova"
    ],
    "name:ita_x_preferred":[
        "Villanova"
    ],
    "name:lat_x_preferred":[
        "Villa Nova"
    ],
    "name:nld_x_preferred":[
        "Villanova"
    ],
    "name:oci_x_preferred":[
        "Vilanova"
    ],
    "name:pms_x_preferred":[
        "Vilaneuva"
    ],
    "name:pol_x_preferred":[
        "Villanova"
    ],
    "name:por_x_preferred":[
        "Villanova"
    ],
    "name:rus_x_preferred":[
        "\u0412\u0438\u043b\u043b\u0430\u043d\u043e\u0432\u0430"
    ],
    "name:slk_x_preferred":[
        "Villanova"
    ],
    "name:spa_x_preferred":[
        "Villanova"
    ],
    "name:swe_x_preferred":[
        "Villanova"
    ],
    "wof:name":"Villanova",
    "wof:placetype":"locality",
    "wof:population":438
},
  "geometry": {"coordinates":[10.86118,44.91638],"type":"Point"}
}