{
  "type": "Feature",
  "properties": {
    "gn:admin1_code":"5.0",
    "gn:admin2_code":"RE",
    "gn:admin3_code":"35032.0",
    "gn:asciiname":"Villanova",
    "gn:country_code":"IT",
    "gn:dem":19,
    "gn:feature_class":"P",
    "gn:feature_code":"PPL",
    "gn:name":"Villanova",
    "gn:population":438,
    "gn:timezone":"Europe/Rome",
    "iso:country":"IT",
    "wof:name":"Villanova",
    "wof:placetype":"locality",
    "wof:population":438
},
  "geometry": {"coordinates":[10.86118,44.91638],"type":"Point"}
}