{
  "type": "Feature",
  "properties": {
    "gn:admin1_code":"20",
    "gn:admin2_code":"VR",
    "gn:admin3_code":"23049.0",
    "gn:asciiname":"Danesi di Sopra",
    "gn:country_code":"IT",
    "gn:dem":188,
    "gn:feature_class":"P",
    "gn:feature_code":"PPL",
    "gn:name":"Danesi di Sopra",
    "gn:population":92,
    "gn:timezone":"Europe/Rome",
    "iso:country":"IT",
    "wof:name":"Danesi di Sopra",
    "wof:placetype":"locality",
    "wof:population":92
},
  "geometry": {"coordinates":[11.26283,45.49841],"type":"Point"}
}