{
  "type": "Feature",
  "properties": {
    "gn:admin1_code":"14.0",
    "gn:admin2_code":"OR",
    "gn:admin3_code":"95056.0",
    "gn:asciiname":"Pardu Nou III",
    "gn:country_code":"IT",
    "gn:dem":9,
    "gn:feature_class":"P",
    "gn:feature_code":"PPL",
    "gn:name":"Pardu Nou III",
    "gn:population":26,
    "gn:timezone":"Europe/Rome",
    "iso:country":"IT",
    "wof:name":"Pardu Nou III",
    "wof:placetype":"locality",
    "wof:population":26
},
  "geometry": {"coordinates":[8.64061,39.93372],"type":"Point"}
}