{
  "type": "Feature",
  "properties": {
    "gn:admin1_code":"9.0",
    "gn:admin2_code":"SO",
    "gn:admin3_code":"14045.0",
    "gn:asciiname":"Porcido",
    "gn:country_code":"IT",
    "gn:dem":580,
    "gn:feature_class":"P",
    "gn:feature_code":"PPLL",
    "gn:name":"Porcido",
    "gn:population":0,
    "gn:timezone":"Europe/Rome",
    "iso:country":"IT",
    "wof:name":"Porcido",
    "wof:placetype":"locality"
},
  "geometry": {"coordinates":[9.61699,46.14929],"type":"Point"}
}