{
  "type": "Feature",
  "properties": {
    "gn:admin1_code":"20",
    "gn:admin2_code":"VR",
    "gn:admin3_code":"23089.0",
    "gn:asciiname":"Gusci",
    "gn:country_code":"IT",
    "gn:dem":99,
    "gn:feature_class":"P",
    "gn:feature_code":"PPL",
    "gn:name":"Gusci",
    "gn:population":13,
    "gn:timezone":"Europe/Rome",
    "iso:country":"IT",
    "wof:name":"Gusci",
    "wof:placetype":"locality",
    "wof:population":13
},
  "geometry": {"coordinates":[10.69583,45.34584],"type":"Point"}
}