{
  "type": "Feature",
  "properties": {
    "gn:admin1_code":"16",
    "gn:admin2_code":"PT",
    "gn:admin3_code":"47014.0",
    "gn:asciiname":"Valdi",
    "gn:country_code":"IT",
    "gn:dem":886,
    "gn:feature_class":"P",
    "gn:feature_code":"PPLL",
    "gn:name":"Valdi",
    "gn:population":6,
    "gn:timezone":"Europe/Rome",
    "iso:country":"IT",
    "wof:name":"Valdi",
    "wof:placetype":"locality",
    "wof:population":6
},
  "geometry": {"coordinates":[10.87944,44.08328],"type":"Point"}
}