{
  "type": "Feature",
  "properties": {
    "gn:admin1_code":"20",
    "gn:admin2_code":"TV",
    "gn:admin3_code":"26049.0",
    "gn:asciiname":"Zona Industriale Nord",
    "gn:country_code":"IT",
    "gn:dem":7,
    "gn:feature_class":"P",
    "gn:feature_code":"PPL",
    "gn:name":"Zona Industriale Nord",
    "gn:population":45,
    "gn:timezone":"Europe/Rome",
    "iso:country":"IT",
    "wof:name":"Zona Industriale Nord",
    "wof:placetype":"locality",
    "wof:population":45
},
  "geometry": {"coordinates":[12.59115,45.78305],"type":"Point"}
}