{
  "type": "Feature",
  "properties": {
    "gn:admin1_code":"17",
    "gn:admin2_code":"BZ",
    "gn:admin3_code":"21024.0",
    "gn:asciiname":"Breitbach",
    "gn:country_code":"IT",
    "gn:dem":222,
    "gn:feature_class":"P",
    "gn:feature_code":"PPL",
    "gn:name":"Breitbach",
    "gn:population":83,
    "gn:timezone":"Europe/Rome",
    "iso:country":"IT",
    "name:ceb_x_preferred":[
        "Breitbach"
    ],
    "name:deu_x_preferred":[
        "Breitbach"
    ],
    "name:swe_x_preferred":[
        "Breitbach"
    ],
    "wof:name":"Breitbach",
    "wof:placetype":"locality",
    "wof:population":83
},
  "geometry": {"coordinates":[11.22065,46.30456],"type":"Point"}
}