{
  "type": "Feature",
  "properties": {
    "gn:admin1_code":"8",
    "gn:admin2_code":"GE",
    "gn:admin3_code":"10003.0",
    "gn:asciiname":"Viganego",
    "gn:country_code":"IT",
    "gn:dem":400,
    "gn:feature_class":"P",
    "gn:feature_code":"PPL",
    "gn:name":"Viganego",
    "gn:population":186,
    "gn:timezone":"Europe/Rome",
    "iso:country":"IT",
    "wof:name":"Viganego",
    "wof:placetype":"locality",
    "wof:population":186
},
  "geometry": {"coordinates":[9.062,44.43104],"type":"Point"}
}