{
  "type": "Feature",
  "properties": {
    "gn:admin1_code":"16",
    "gn:admin2_code":"PT",
    "gn:admin3_code":"47014.0",
    "gn:asciiname":"Corsini Bianchi",
    "gn:country_code":"IT",
    "gn:dem":254,
    "gn:feature_class":"P",
    "gn:feature_code":"PPL",
    "gn:name":"Corsini Bianchi",
    "gn:population":28,
    "gn:timezone":"Europe/Rome",
    "iso:country":"IT",
    "wof:name":"Corsini Bianchi",
    "wof:placetype":"locality",
    "wof:population":28
},
  "geometry": {"coordinates":[10.93687,43.96424],"type":"Point"}
}