{
  "type": "Feature",
  "properties": {
    "gn:admin1_code":"10",
    "gn:admin2_code":"PU",
    "gn:admin3_code":"41070.0",
    "gn:asciiname":"Tre Ponti",
    "gn:country_code":"IT",
    "gn:dem":205,
    "gn:feature_class":"P",
    "gn:feature_code":"PPL",
    "gn:name":"Tre Ponti",
    "gn:population":19,
    "gn:timezone":"Europe/Rome",
    "iso:country":"IT",
    "wof:name":"Tre Ponti",
    "wof:placetype":"locality",
    "wof:population":19
},
  "geometry": {"coordinates":[12.94662,43.68407],"type":"Point"}
}