{
  "type": "Feature",
  "properties": {
    "gn:admin1_code":"9.0",
    "gn:admin2_code":"VA",
    "gn:admin3_code":"12103.0",
    "gn:asciiname":"Verbano",
    "gn:country_code":"IT",
    "gn:dem":466,
    "gn:feature_class":"P",
    "gn:feature_code":"PPL",
    "gn:name":"Verbano",
    "gn:population":64,
    "gn:timezone":"Europe/Rome",
    "iso:country":"IT",
    "name:ita_x_preferred":[
        "Verbano"
    ],
    "wof:name":"Verbano",
    "wof:placetype":"locality",
    "wof:population":64
},
  "geometry": {"coordinates":[8.7635,45.97967],"type":"Point"}
}