{
  "type": "Feature",
  "properties": {
    "gn:admin1_code":"13",
    "gn:admin2_code":"BR",
    "gn:admin3_code":"74012.0",
    "gn:asciiname":"Lamardilla",
    "gn:country_code":"IT",
    "gn:dem":202,
    "gn:feature_class":"P",
    "gn:feature_code":"PPL",
    "gn:name":"Lamardilla",
    "gn:population":117,
    "gn:timezone":"Europe/Rome",
    "iso:country":"IT",
    "wof:name":"Lamardilla",
    "wof:placetype":"locality",
    "wof:population":117
},
  "geometry": {"coordinates":[17.57095,40.71481],"type":"Point"}
}