{
  "type": "Feature",
  "properties": {
    "gn:admin1_code":"20",
    "gn:admin2_code":"TV",
    "gn:admin3_code":"26088.0",
    "gn:asciiname":"Monte Grappa",
    "gn:country_code":"IT",
    "gn:dem":23,
    "gn:feature_class":"P",
    "gn:feature_code":"PPL",
    "gn:name":"Monte Grappa",
    "gn:population":23,
    "gn:timezone":"Europe/Rome",
    "iso:country":"IT",
    "name:cat_x_preferred":[
        "Mont Grappa"
    ],
    "name:ceb_x_preferred":[
        "Monte Grappa"
    ],
    "name:ces_x_preferred":[
        "Monte Grappa"
    ],
    "name:deu_x_preferred":[
        "Monte Grappa"
    ],
    "name:fra_x_preferred":[
        "Monte Grappa"
    ],
    "name:ita_x_preferred":[
        "Monte Grappa"
    ],
    "name:jpn_x_preferred":[
        "\u30e2\u30f3\u30c6\u30fb\u30b0\u30e9\u30c3\u30d1"
    ],
    "name:kor_x_preferred":[
        "\uadf8\ub77c\ud30c\uc0b0"
    ],
    "name:nld_x_preferred":[
        "Monte Grappa"
    ],
    "name:nno_x_preferred":[
        "Monte Grappa"
    ],
    "name:ron_x_preferred":[
        "Monte Grappa"
    ],
    "name:spa_x_preferred":[
        "Monte Grappa"
    ],
    "name:vec_x_preferred":[
        "Monte Grapa"
    ],
    "wof:name":"Monte Grappa",
    "wof:placetype":"locality",
    "wof:population":23
},
  "geometry": {"coordinates":[12.39904,45.82129000000001],"type":"Point"}
}