{
  "type": "Feature",
  "properties": {
    "gn:admin1_code":"20",
    "gn:admin2_code":"TV",
    "gn:admin3_code":"26088.0",
    "gn:asciiname":"Monte Grappa",
    "gn:country_code":"IT",
    "gn:dem":23,
    "gn:feature_class":"P",
    "gn:feature_code":"PPL",
    "gn:name":"Monte Grappa",
    "gn:population":23,
    "gn:timezone":"Europe/Rome",
    "iso:country":"IT",
    "wof:name":"Monte Grappa",
    "wof:placetype":"locality",
    "wof:population":23
},
  "geometry": {"coordinates":[12.39904,45.82129000000001],"type":"Point"}
}