{
  "type": "Feature",
  "properties": {
    "gn:admin1_code":"16.0",
    "gn:admin2_code":"FI",
    "gn:admin3_code":"48053.0",
    "gn:asciiname":"Cerliano",
    "gn:country_code":"IT",
    "gn:dem":350,
    "gn:feature_class":"P",
    "gn:feature_code":"PPL",
    "gn:name":"Cerliano",
    "gn:population":0,
    "gn:timezone":"Europe/Rome",
    "iso:country":"IT",
    "wof:name":"Cerliano",
    "wof:placetype":"locality"
},
  "geometry": {"coordinates":[11.36667,44.01667],"type":"Point"}
}