{
  "type": "Feature",
  "properties": {
    "gn:admin1_code":"16",
    "gn:admin2_code":"PT",
    "gn:admin3_code":"47022.0",
    "gn:asciiname":"La Lama",
    "gn:country_code":"IT",
    "gn:dem":23,
    "gn:feature_class":"P",
    "gn:feature_code":"PPL",
    "gn:name":"La Lama",
    "gn:population":21,
    "gn:timezone":"Europe/Rome",
    "iso:country":"IT",
    "wof:name":"La Lama",
    "wof:placetype":"locality",
    "wof:population":21
},
  "geometry": {"coordinates":[10.72741,43.84526],"type":"Point"}
}