{
  "type": "Feature",
  "properties": {
    "gn:admin1_code":"1",
    "gn:admin2_code":"TE",
    "gn:admin3_code":"67015.0",
    "gn:asciiname":"Molino del Papa",
    "gn:country_code":"IT",
    "gn:dem":384,
    "gn:feature_class":"P",
    "gn:feature_code":"PPL",
    "gn:name":"Molino del Papa",
    "gn:population":35,
    "gn:timezone":"Europe/Rome",
    "iso:country":"IT",
    "wof:name":"Molino del Papa",
    "wof:placetype":"locality",
    "wof:population":35
},
  "geometry": {"coordinates":[13.85209,42.58361],"type":"Point"}
}