{
  "type": "Feature",
  "properties": {
    "gn:admin1_code":"11",
    "gn:admin2_code":"CB",
    "gn:admin3_code":"70009.0",
    "gn:asciiname":"Martina",
    "gn:country_code":"IT",
    "gn:dem":796,
    "gn:feature_class":"P",
    "gn:feature_code":"PPLL",
    "gn:name":"Martina",
    "gn:population":9,
    "gn:timezone":"Europe/Rome",
    "iso:country":"IT",
    "name:bos_x_preferred":[
        "Martina"
    ],
    "name:ceb_x_preferred":[
        "Martina"
    ],
    "name:deu_x_preferred":[
        "Martina"
    ],
    "name:est_x_preferred":[
        "Martina"
    ],
    "name:fra_x_preferred":[
        "Martina"
    ],
    "name:hun_x_preferred":[
        "Martina"
    ],
    "name:ita_x_preferred":[
        "Martina"
    ],
    "name:nld_x_preferred":[
        "Martina"
    ],
    "name:por_x_preferred":[
        "Martina"
    ],
    "name:ron_x_preferred":[
        "Martina"
    ],
    "name:rus_x_preferred":[
        "\u041c\u0430\u0440\u0442\u0438\u043d\u0430"
    ],
    "name:slk_x_preferred":[
        "Martina"
    ],
    "name:slv_x_preferred":[
        "Martina"
    ],
    "name:spa_x_preferred":[
        "Martina"
    ],
    "name:srp_x_preferred":[
        "\u041c\u0430\u0440\u0442\u0438\u043d\u0430"
    ],
    "name:swe_x_preferred":[
        "Martina"
    ],
    "wof:name":"Martina",
    "wof:placetype":"locality",
    "wof:population":9
},
  "geometry": {"coordinates":[14.74464,41.62686],"type":"Point"}
}