{
  "type": "Feature",
  "properties": {
    "gn:admin1_code":"16",
    "gn:admin2_code":"LI",
    "gn:admin3_code":"49008.0",
    "gn:asciiname":"La Casa",
    "gn:country_code":"IT",
    "gn:dem":120,
    "gn:feature_class":"P",
    "gn:feature_code":"PPL",
    "gn:name":"La Casa",
    "gn:population":41,
    "gn:timezone":"Europe/Rome",
    "iso:country":"IT",
    "name:ceb_x_preferred":[
        "La Casa"
    ],
    "name:ita_x_preferred":[
        "La casa"
    ],
    "name:spa_x_preferred":[
        "La casa"
    ],
    "name:srp_x_preferred":[
        "La Casa"
    ],
    "name:swe_x_preferred":[
        "La Casa"
    ],
    "wof:name":"La Casa",
    "wof:placetype":"locality",
    "wof:population":41
},
  "geometry": {"coordinates":[10.43722,43.5449],"type":"Point"}
}