{
  "type": "Feature",
  "properties": {
    "gn:admin1_code":"9.0",
    "gn:admin2_code":"BS",
    "gn:admin3_code":"17153.0",
    "gn:asciiname":"Gazzane",
    "gn:country_code":"IT",
    "gn:dem":337,
    "gn:feature_class":"P",
    "gn:feature_code":"PPL",
    "gn:name":"Gazzane",
    "gn:population":536,
    "gn:timezone":"Europe/Rome",
    "iso:country":"IT",
    "wof:name":"Gazzane",
    "wof:placetype":"locality",
    "wof:population":536
},
  "geometry": {"coordinates":[10.37942,45.65758],"type":"Point"}
}