{
  "type": "Feature",
  "properties": {
    "gn:admin1_code":"9.0",
    "gn:admin2_code":"SO",
    "gn:admin3_code":"14035.0",
    "gn:asciiname":"Pianello",
    "gn:country_code":"IT",
    "gn:dem":1765,
    "gn:feature_class":"P",
    "gn:feature_code":"PPLL",
    "gn:name":"Pianello",
    "gn:population":0,
    "gn:timezone":"Europe/Rome",
    "iso:country":"IT",
    "wof:name":"Pianello",
    "wof:placetype":"locality"
},
  "geometry": {"coordinates":[9.36808,46.43536],"type":"Point"}
}