{
  "type": "Feature",
  "properties": {
    "gn:admin1_code":"5",
    "gn:admin2_code":"PC",
    "gn:admin3_code":"33011.0",
    "gn:asciiname":"Mirandola",
    "gn:country_code":"IT",
    "gn:dem":332,
    "gn:feature_class":"P",
    "gn:feature_code":"PPL",
    "gn:name":"Mirandola",
    "gn:population":27,
    "gn:timezone":"Europe/Rome",
    "iso:country":"IT",
    "wof:name":"Mirandola",
    "wof:placetype":"locality",
    "wof:population":27
},
  "geometry": {"coordinates":[9.75061,44.83396],"type":"Point"}
}