{
  "type": "Feature",
  "properties": {
    "gn:admin1_code":"1",
    "gn:admin2_code":"CH",
    "gn:admin3_code":"69040.0",
    "gn:asciiname":"Pincianesi I",
    "gn:country_code":"IT",
    "gn:dem":632,
    "gn:feature_class":"P",
    "gn:feature_code":"PPL",
    "gn:name":"Pincianesi I",
    "gn:population":66,
    "gn:timezone":"Europe/Rome",
    "iso:country":"IT",
    "wof:name":"Pincianesi I",
    "wof:placetype":"locality",
    "wof:population":66
},
  "geometry": {"coordinates":[14.25908,42.05659],"type":"Point"}
}