{
  "type": "Feature",
  "properties": {
    "gn:admin1_code":"20.0",
    "gn:admin2_code":"VR",
    "gn:admin3_code":"23052.0",
    "gn:asciiname":"Montericco",
    "gn:country_code":"IT",
    "gn:dem":260,
    "gn:feature_class":"P",
    "gn:feature_code":"PPL",
    "gn:name":"Montericco",
    "gn:population":734,
    "gn:timezone":"Europe/Rome",
    "iso:country":"IT",
    "wof:name":"Montericco",
    "wof:placetype":"locality",
    "wof:population":734
},
  "geometry": {"coordinates":[10.95658,45.49213],"type":"Point"}
}