{
  "type": "Feature",
  "properties": {
    "gn:admin1_code":"7.0",
    "gn:admin2_code":"RM",
    "gn:admin3_code":"58075.0",
    "gn:asciiname":"Marzolanella",
    "gn:country_code":"IT",
    "gn:dem":56,
    "gn:feature_class":"P",
    "gn:feature_code":"PPL",
    "gn:name":"Marzolanella",
    "gn:population":347,
    "gn:timezone":"Europe/Rome",
    "iso:country":"IT",
    "wof:name":"Marzolanella",
    "wof:placetype":"locality",
    "wof:population":347
},
  "geometry": {"coordinates":[12.64218,42.09554],"type":"Point"}
}