{
  "type": "Feature",
  "properties": {
    "gn:admin1_code":"12",
    "gn:admin2_code":"AT",
    "gn:admin3_code":"5086.0",
    "gn:asciiname":"Via Primavera",
    "gn:country_code":"IT",
    "gn:dem":251,
    "gn:feature_class":"P",
    "gn:feature_code":"PPL",
    "gn:name":"Via Primavera",
    "gn:population":22,
    "gn:timezone":"Europe/Rome",
    "iso:country":"IT",
    "wof:name":"Via Primavera",
    "wof:placetype":"locality",
    "wof:population":22
},
  "geometry": {"coordinates":[8.04338,45.04132],"type":"Point"}
}