{
  "type": "Feature",
  "properties": {
    "gn:admin1_code":"4.0",
    "gn:admin2_code":"SA",
    "gn:admin3_code":"65073.0",
    "gn:asciiname":"Cannito Pezze",
    "gn:country_code":"IT",
    "gn:dem":317,
    "gn:feature_class":"P",
    "gn:feature_code":"PPL",
    "gn:name":"Cannito Pezze",
    "gn:population":37,
    "gn:timezone":"Europe/Rome",
    "iso:country":"IT",
    "wof:name":"Cannito Pezze",
    "wof:placetype":"locality",
    "wof:population":37
},
  "geometry": {"coordinates":[14.99267,40.6893],"type":"Point"}
}