{
  "type": "Feature",
  "properties": {
    "gn:admin1_code":"9",
    "gn:admin2_code":"MN",
    "gn:admin3_code":"20033.0",
    "gn:asciiname":"Corte Casella",
    "gn:country_code":"IT",
    "gn:dem":32,
    "gn:feature_class":"P",
    "gn:feature_code":"PPL",
    "gn:name":"Corte Casella",
    "gn:population":42,
    "gn:timezone":"Europe/Rome",
    "iso:country":"IT",
    "wof:name":"Corte Casella",
    "wof:placetype":"locality",
    "wof:population":42
},
  "geometry": {"coordinates":[10.74053,45.24086],"type":"Point"}
}