{
  "type": "Feature",
  "properties": {
    "gn:admin1_code":"10.0",
    "gn:admin2_code":"PU",
    "gn:admin3_code":"41015.0",
    "gn:asciiname":"Santa Maria della Valle",
    "gn:country_code":"IT",
    "gn:dem":186,
    "gn:feature_class":"P",
    "gn:feature_code":"PPL",
    "gn:name":"Santa Maria della Valle",
    "gn:population":0,
    "gn:timezone":"Europe/Rome",
    "iso:country":"IT",
    "wof:name":"Santa Maria della Valle",
    "wof:placetype":"locality"
},
  "geometry": {"coordinates":[12.83333,43.66667],"type":"Point"}
}