{
  "type": "Feature",
  "properties": {
    "gn:admin1_code":"5.0",
    "gn:admin2_code":"PC",
    "gn:admin3_code":"33010.0",
    "gn:asciiname":"Centrale Termonucleare",
    "gn:country_code":"IT",
    "gn:dem":48,
    "gn:feature_class":"P",
    "gn:feature_code":"PPLL",
    "gn:name":"Centrale Termonucleare",
    "gn:population":0,
    "gn:timezone":"Europe/Rome",
    "iso:country":"IT",
    "wof:name":"Centrale Termonucleare",
    "wof:placetype":"locality"
},
  "geometry": {"coordinates":[9.87069,45.07182],"type":"Point"}
}