{
  "type": "Feature",
  "properties": {
    "gn:admin1_code":"16.0",
    "gn:admin2_code":"LU",
    "gn:admin3_code":"46007.0",
    "gn:asciiname":"Parezzana",
    "gn:country_code":"IT",
    "gn:dem":11,
    "gn:feature_class":"P",
    "gn:feature_code":"PPL",
    "gn:name":"Parezzana",
    "gn:population":0,
    "gn:timezone":"Europe/Rome",
    "iso:country":"IT",
    "wof:name":"Parezzana",
    "wof:placetype":"locality"
},
  "geometry": {"coordinates":[10.53333,43.81667],"type":"Point"}
}