{
  "type": "Feature",
  "properties": {
    "gn:admin1_code":"4",
    "gn:admin3_code":"63034.0",
    "gn:asciiname":"Cantoncello",
    "gn:country_code":"IT",
    "gn:dem":28,
    "gn:feature_class":"P",
    "gn:feature_code":"PPL",
    "gn:name":"Cantoncello",
    "gn:population":91,
    "gn:timezone":"Europe/Rome",
    "iso:country":"IT",
    "wof:name":"Cantoncello",
    "wof:placetype":"locality",
    "wof:population":91
},
  "geometry": {"coordinates":[14.05103,40.93259000000001],"type":"Point"}
}