{
  "type": "Feature",
  "properties": {
    "gn:admin1_code":"7",
    "gn:admin2_code":"FR",
    "gn:admin3_code":"60062.0",
    "gn:asciiname":"Selva",
    "gn:country_code":"IT",
    "gn:dem":510,
    "gn:feature_class":"P",
    "gn:feature_code":"PPL",
    "gn:name":"Selva",
    "gn:population":54,
    "gn:timezone":"Europe/Rome",
    "iso:country":"IT",
    "wof:name":"Selva",
    "wof:placetype":"locality",
    "wof:population":54
},
  "geometry": {"coordinates":[13.80188,41.70116],"type":"Point"}
}