{
  "type": "Feature",
  "properties": {
    "gn:admin1_code":"12",
    "gn:admin2_code":"AL",
    "gn:admin3_code":"6179.0",
    "gn:asciiname":"Davino",
    "gn:country_code":"IT",
    "gn:dem":241,
    "gn:feature_class":"P",
    "gn:feature_code":"PPL",
    "gn:name":"Davino",
    "gn:population":73,
    "gn:timezone":"Europe/Rome",
    "iso:country":"IT",
    "name:deu_x_preferred":[
        "Davino"
    ],
    "name:ita_x_preferred":[
        "Davino"
    ],
    "wof:name":"Davino",
    "wof:placetype":"locality",
    "wof:population":73
},
  "geometry": {"coordinates":[8.41676,45.00267],"type":"Point"}
}