{
  "type": "Feature",
  "properties": {
    "gn:admin1_code":"4",
    "gn:admin2_code":"SA",
    "gn:admin3_code":"65087.0",
    "gn:asciiname":"Contrada Noce del Conte",
    "gn:country_code":"IT",
    "gn:dem":502,
    "gn:feature_class":"P",
    "gn:feature_code":"PPL",
    "gn:name":"Contrada Noce del Conte",
    "gn:population":131,
    "gn:timezone":"Europe/Rome",
    "iso:country":"IT",
    "wof:name":"Contrada Noce del Conte",
    "wof:placetype":"locality",
    "wof:population":131
},
  "geometry": {"coordinates":[15.64512,40.32188],"type":"Point"}
}