{
  "type": "Feature",
  "properties": {
    "gn:admin1_code":"15",
    "gn:admin2_code":"TP",
    "gn:admin3_code":"81014.0",
    "gn:asciiname":"Garitte Karuscia",
    "gn:country_code":"IT",
    "gn:dem":44,
    "gn:feature_class":"P",
    "gn:feature_code":"PPL",
    "gn:name":"Garitte Karuscia",
    "gn:population":24,
    "gn:timezone":"Europe/Rome",
    "iso:country":"IT",
    "wof:name":"Garitte Karuscia",
    "wof:placetype":"locality",
    "wof:population":24
},
  "geometry": {"coordinates":[11.96633,36.83516],"type":"Point"}
}