{
  "type": "Feature",
  "properties": {
    "gn:admin1_code":"10",
    "gn:admin2_code":"MC",
    "gn:admin3_code":"43033.0",
    "gn:asciiname":"Molinetto",
    "gn:country_code":"IT",
    "gn:dem":46,
    "gn:feature_class":"P",
    "gn:feature_code":"PPL",
    "gn:name":"Molinetto",
    "gn:population":220,
    "gn:timezone":"Europe/Rome",
    "iso:country":"IT",
    "wof:name":"Molinetto",
    "wof:placetype":"locality",
    "wof:population":220
},
  "geometry": {"coordinates":[13.61429,43.27946],"type":"Point"}
}