{
  "type": "Feature",
  "properties": {
    "gn:admin1_code":"12",
    "gn:admin2_code":"TO",
    "gn:admin3_code":"1115.0",
    "gn:asciiname":"Via Caduti sul Lavoro",
    "gn:country_code":"IT",
    "gn:dem":486,
    "gn:feature_class":"P",
    "gn:feature_code":"PPL",
    "gn:name":"Via Caduti sul Lavoro",
    "gn:population":64,
    "gn:timezone":"Europe/Rome",
    "iso:country":"IT",
    "wof:name":"Via Caduti sul Lavoro",
    "wof:placetype":"locality",
    "wof:population":64
},
  "geometry": {"coordinates":[7.35528,45.03242],"type":"Point"}
}