{
  "type": "Feature",
  "properties": {
    "gn:admin1_code":"20",
    "gn:admin2_code":"TV",
    "gn:admin3_code":"26046.0",
    "gn:asciiname":"Martinella I-Picciol",
    "gn:country_code":"IT",
    "gn:dem":89,
    "gn:feature_class":"P",
    "gn:feature_code":"PPL",
    "gn:name":"Martinella I-Picciol",
    "gn:population":96,
    "gn:timezone":"Europe/Rome",
    "iso:country":"IT",
    "wof:name":"Martinella I-Picciol",
    "wof:placetype":"locality",
    "wof:population":96
},
  "geometry": {"coordinates":[12.02869,45.7573],"type":"Point"}
}