{
  "type": "Feature",
  "properties": {
    "gn:admin1_code":"10",
    "gn:admin2_code":"AN",
    "gn:admin3_code":"42002.0",
    "gn:asciiname":"Casine di Paterno",
    "gn:country_code":"IT",
    "gn:dem":49,
    "gn:feature_class":"P",
    "gn:feature_code":"PPL",
    "gn:name":"Casine di Paterno",
    "gn:population":126,
    "gn:timezone":"Europe/Rome",
    "iso:country":"IT",
    "wof:name":"Casine di Paterno",
    "wof:placetype":"locality",
    "wof:population":126
},
  "geometry": {"coordinates":[13.42571,43.57368],"type":"Point"}
}