{
  "type": "Feature",
  "properties": {
    "gn:admin1_code":"12",
    "gn:admin2_code":"NO",
    "gn:admin3_code":"3044.0",
    "gn:asciiname":"San Michele",
    "gn:country_code":"IT",
    "gn:dem":242,
    "gn:feature_class":"P",
    "gn:feature_code":"PPL",
    "gn:name":"San Michele",
    "gn:population":39,
    "gn:timezone":"Europe/Rome",
    "iso:country":"IT",
    "wof:name":"San Michele",
    "wof:placetype":"locality",
    "wof:population":39
},
  "geometry": {"coordinates":[8.49458,45.61167],"type":"Point"}
}