{
  "type": "Feature",
  "properties": {
    "gn:admin1_code":"10.0",
    "gn:admin2_code":"AN",
    "gn:admin3_code":"42044.0",
    "gn:asciiname":"Zona Industriale Berbentina",
    "gn:country_code":"IT",
    "gn:dem":330,
    "gn:feature_class":"P",
    "gn:feature_code":"PPL",
    "gn:name":"Zona Industriale Berbentina",
    "gn:population":0,
    "gn:timezone":"Europe/Rome",
    "iso:country":"IT",
    "wof:name":"Zona Industriale Berbentina",
    "wof:placetype":"locality"
},
  "geometry": {"coordinates":[12.84801,43.4071],"type":"Point"}
}