{
  "type": "Feature",
  "properties": {
    "gn:admin1_code":"6.0",
    "gn:admin2_code":"UD",
    "gn:admin3_code":"30113.0",
    "gn:asciiname":"Platischis",
    "gn:country_code":"IT",
    "gn:dem":653,
    "gn:elevation":"663.0",
    "gn:feature_class":"P",
    "gn:feature_code":"PPL",
    "gn:name":"Platischis",
    "gn:population":58,
    "gn:timezone":"Europe/Rome",
    "iso:country":"IT",
    "wof:name":"Platischis",
    "wof:placetype":"locality",
    "wof:population":58
},
  "geometry": {"coordinates":[13.38338,46.24195],"type":"Point"}
}