{
  "type": "Feature",
  "properties": {
    "gn:admin1_code":"20",
    "gn:admin2_code":"TV",
    "gn:admin3_code":"26045.0",
    "gn:asciiname":"Costa Mattia",
    "gn:country_code":"IT",
    "gn:dem":198,
    "gn:feature_class":"P",
    "gn:feature_code":"PPL",
    "gn:name":"Costa Mattia",
    "gn:population":21,
    "gn:timezone":"Europe/Rome",
    "iso:country":"IT",
    "wof:name":"Costa Mattia",
    "wof:placetype":"locality",
    "wof:population":21
},
  "geometry": {"coordinates":[11.94748,45.84491],"type":"Point"}
}