{
  "type": "Feature",
  "properties": {
    "gn:admin1_code":"12.0",
    "gn:admin2_code":"CN",
    "gn:admin3_code":"4248.0",
    "gn:asciiname":"Bagni di Vinadio",
    "gn:cc2":"IT",
    "gn:country_code":"IT",
    "gn:dem":1287,
    "gn:elevation":"1305.0",
    "gn:feature_class":"P",
    "gn:feature_code":"PPL",
    "gn:name":"Bagni di Vinadio",
    "gn:population":41,
    "gn:timezone":"Europe/Rome",
    "iso:country":"IT",
    "name:und_x_variant":[
        "Bagni",
        "Bagni di Vinadio"
    ],
    "wof:name":"Bagni di Vinadio",
    "wof:placetype":"locality",
    "wof:population":41
},
  "geometry": {"coordinates":[7.07515,44.28888],"type":"Point"}
}