{
  "type": "Feature",
  "properties": {
    "gn:admin1_code":"5",
    "gn:admin2_code":"PC",
    "gn:admin3_code":"33019.0",
    "gn:asciiname":"Villa",
    "gn:country_code":"IT",
    "gn:dem":800,
    "gn:feature_class":"P",
    "gn:feature_code":"PPLL",
    "gn:name":"Villa",
    "gn:population":9,
    "gn:timezone":"Europe/Rome",
    "iso:country":"IT",
    "wof:name":"Villa",
    "wof:placetype":"locality",
    "wof:population":9
},
  "geometry": {"coordinates":[9.59581,44.70902],"type":"Point"}
}