{
  "type": "Feature",
  "properties": {
    "gn:admin1_code":"5",
    "gn:admin2_code":"PC",
    "gn:admin3_code":"33019.0",
    "gn:asciiname":"Villa",
    "gn:country_code":"IT",
    "gn:dem":800,
    "gn:feature_class":"P",
    "gn:feature_code":"PPLL",
    "gn:name":"Villa",
    "gn:population":9,
    "gn:timezone":"Europe/Rome",
    "iso:country":"IT",
    "name:ara_x_preferred":[
        "\u0641\u064a\u0644\u0627"
    ],
    "name:bel_x_preferred":[
        "\u0412\u0456\u043b\u0430"
    ],
    "name:bre_x_preferred":[
        "Villas"
    ],
    "name:bul_x_preferred":[
        "\u0412\u0438\u043b\u0430"
    ],
    "name:ces_x_preferred":[
        "Vila"
    ],
    "name:dan_x_preferred":[
        "Villa"
    ],
    "name:deu_x_preferred":[
        "Villa"
    ],
    "name:epo_x_preferred":[
        "Vilao"
    ],
    "name:est_x_preferred":[
        "Villa"
    ],
    "name:fas_x_preferred":[
        "\u0648\u06cc\u0644\u0627"
    ],
    "name:fin_x_preferred":[
        "Huvila"
    ],
    "name:fra_x_preferred":[
        "Villa"
    ],
    "name:heb_x_preferred":[
        "\u05d5\u05d9\u05dc\u05d4"
    ],
    "name:hrv_x_preferred":[
        "Vila"
    ],
    "name:ita_x_preferred":[
        "Villa"
    ],
    "name:jpn_x_preferred":[
        "\u30f4\u30a3\u30e9"
    ],
    "name:kat_x_preferred":[
        "\u10d5\u10d8\u10da\u10d0"
    ],
    "name:kaz_x_preferred":[
        "\u0412\u0438\u043b\u043b\u0430"
    ],
    "name:kir_x_preferred":[
        "\u0412\u0438\u043b\u043b\u0430"
    ],
    "name:lat_x_preferred":[
        "Villa"
    ],
    "name:lav_x_preferred":[
        "Villa"
    ],
    "name:nld_x_preferred":[
        "Villa"
    ],
    "name:nno_x_preferred":[
        "Villa"
    ],
    "name:nor_x_preferred":[
        "Villa"
    ],
    "name:pol_x_preferred":[
        "Willa"
    ],
    "name:por_x_preferred":[
        "Villa"
    ],
    "name:ron_x_preferred":[
        "Villa"
    ],
    "name:rus_x_preferred":[
        "\u0412\u0438\u043b\u043b\u0430"
    ],
    "name:srp_x_preferred":[
        "\u0412\u0438\u043b\u0430"
    ],
    "name:swe_x_preferred":[
        "Villa"
    ],
    "name:ukr_x_preferred":[
        "\u0412\u0456\u043b\u043b\u0430"
    ],
    "name:uzb_x_preferred":[
        "Villa"
    ],
    "name:vec_x_preferred":[
        "Vila"
    ],
    "name:vie_x_preferred":[
        "Bi\u1ec7t th\u1ef1"
    ],
    "name:wln_x_preferred":[
        "M\u00e5jhon rominne"
    ],
    "wof:name":"Villa",
    "wof:placetype":"locality",
    "wof:population":9
},
  "geometry": {"coordinates":[9.59581,44.70902],"type":"Point"}
}