{
  "type": "Feature",
  "properties": {
    "gn:admin1_code":"12",
    "gn:admin2_code":"CN",
    "gn:admin3_code":"4203.0",
    "gn:asciiname":"Le Prese",
    "gn:country_code":"IT",
    "gn:dem":366,
    "gn:feature_class":"P",
    "gn:feature_code":"PPL",
    "gn:name":"Le Prese",
    "gn:population":17,
    "gn:timezone":"Europe/Rome",
    "iso:country":"IT",
    "name:deu_x_preferred":[
        "Le Prese"
    ],
    "name:swe_x_preferred":[
        "Le Prese"
    ],
    "wof:name":"Le Prese",
    "wof:placetype":"locality",
    "wof:population":17
},
  "geometry": {"coordinates":[7.51653,44.62801],"type":"Point"}
}