{
  "type": "Feature",
  "properties": {
    "gn:admin1_code":"3.0",
    "gn:admin2_code":"CS",
    "gn:admin3_code":"78029.0",
    "gn:asciiname":"I Casoni",
    "gn:country_code":"IT",
    "gn:dem":1,
    "gn:feature_class":"P",
    "gn:feature_code":"PPL",
    "gn:name":"I Casoni",
    "gn:population":0,
    "gn:timezone":"Europe/Rome",
    "iso:country":"IT",
    "wof:name":"I Casoni",
    "wof:placetype":"locality"
},
  "geometry": {"coordinates":[16.48333,39.73333],"type":"Point"}
}