{
  "type": "Feature",
  "properties": {
    "gn:admin1_code":"1",
    "gn:admin2_code":"CH",
    "gn:admin3_code":"69073.0",
    "gn:asciiname":"Pomaro",
    "gn:country_code":"IT",
    "gn:dem":324,
    "gn:feature_class":"P",
    "gn:feature_code":"PPL",
    "gn:name":"Pomaro",
    "gn:population":51,
    "gn:timezone":"Europe/Rome",
    "iso:country":"IT",
    "wof:name":"Pomaro",
    "wof:placetype":"locality",
    "wof:population":51
},
  "geometry": {"coordinates":[14.15305,42.26381],"type":"Point"}
}