{
  "type": "Feature",
  "properties": {
    "gn:admin1_code":"4",
    "gn:admin2_code":"SA",
    "gn:admin3_code":"65056.0",
    "gn:asciiname":"Ornito",
    "gn:country_code":"IT",
    "gn:dem":269,
    "gn:feature_class":"P",
    "gn:feature_code":"PPL",
    "gn:name":"Ornito",
    "gn:population":302,
    "gn:timezone":"Europe/Rome",
    "iso:country":"IT",
    "wof:name":"Ornito",
    "wof:placetype":"locality",
    "wof:population":302
},
  "geometry": {"coordinates":[14.92644,40.69034],"type":"Point"}
}