{
  "type": "Feature",
  "properties": {
    "gn:admin1_code":"12.0",
    "gn:admin2_code":"TO",
    "gn:admin3_code":"1184.0",
    "gn:asciiname":"Sinchette",
    "gn:country_code":"IT",
    "gn:dem":812,
    "gn:feature_class":"P",
    "gn:feature_code":"PPL",
    "gn:name":"Sinchette",
    "gn:population":0,
    "gn:timezone":"Europe/Rome",
    "iso:country":"IT",
    "wof:name":"Sinchette",
    "wof:placetype":"locality"
},
  "geometry": {"coordinates":[7.19974,44.96654],"type":"Point"}
}