{
  "type": "Feature",
  "properties": {
    "gn:admin1_code":"3",
    "gn:admin2_code":"CZ",
    "gn:admin3_code":"79129.0",
    "gn:asciiname":"Accaria Rosaria",
    "gn:country_code":"IT",
    "gn:dem":564,
    "gn:feature_class":"P",
    "gn:feature_code":"PPL",
    "gn:name":"Accaria Rosaria",
    "gn:population":308,
    "gn:timezone":"Europe/Rome",
    "iso:country":"IT",
    "wof:name":"Accaria Rosaria",
    "wof:placetype":"locality",
    "wof:population":308
},
  "geometry": {"coordinates":[16.36806,38.97599],"type":"Point"}
}