{
  "type": "Feature",
  "properties": {
    "gn:admin1_code":"7",
    "gn:admin2_code":"RM",
    "gn:admin3_code":"58074.0",
    "gn:asciiname":"Colle dell'Oro",
    "gn:country_code":"IT",
    "gn:dem":313,
    "gn:feature_class":"P",
    "gn:feature_code":"PPL",
    "gn:name":"Colle dell'Oro",
    "gn:population":236,
    "gn:timezone":"Europe/Rome",
    "iso:country":"IT",
    "wof:name":"Colle dell'Oro",
    "wof:placetype":"locality",
    "wof:population":236
},
  "geometry": {"coordinates":[12.83992,41.84645],"type":"Point"}
}