{
  "type": "Feature",
  "properties": {
    "gn:admin1_code":"7.0",
    "gn:admin2_code":"RI",
    "gn:admin3_code":"57069.0",
    "gn:asciiname":"Ornaro",
    "gn:country_code":"IT",
    "gn:dem":583,
    "gn:elevation":"607.0",
    "gn:feature_class":"P",
    "gn:feature_code":"PPL",
    "gn:name":"Ornaro",
    "gn:population":95,
    "gn:timezone":"Europe/Rome",
    "iso:country":"IT",
    "wof:name":"Ornaro",
    "wof:placetype":"locality",
    "wof:population":95
},
  "geometry": {"coordinates":[12.85143,42.28158],"type":"Point"}
}