{
  "type": "Feature",
  "properties": {
    "gn:admin1_code":"12.0",
    "gn:admin2_code":"TO",
    "gn:admin3_code":"1074.0",
    "gn:asciiname":"Colombiere",
    "gn:cc2":"IT",
    "gn:country_code":"IT",
    "gn:dem":1529,
    "gn:feature_class":"P",
    "gn:feature_code":"PPL",
    "gn:name":"Colombiere",
    "gn:population":0,
    "gn:timezone":"Europe/Rome",
    "iso:country":"IT",
    "name:und_x_variant":[
        "Colombieres",
        "Colombiere"
    ],
    "wof:name":"Colombiere",
    "wof:placetype":"locality"
},
  "geometry": {"coordinates":[6.81667,44.98333],"type":"Point"}
}