{
  "type": "Feature",
  "properties": {
    "gn:admin1_code":"5.0",
    "gn:admin2_code":"FC",
    "gn:admin3_code":"40019.0",
    "gn:asciiname":"Montevescovo",
    "gn:country_code":"IT",
    "gn:dem":247,
    "gn:elevation":"265.0",
    "gn:feature_class":"P",
    "gn:feature_code":"PPL",
    "gn:name":"Montevescovo",
    "gn:population":8,
    "gn:timezone":"Europe/Rome",
    "iso:country":"IT",
    "wof:name":"Montevescovo",
    "wof:placetype":"locality",
    "wof:population":8
},
  "geometry": {"coordinates":[12.06283,44.08555],"type":"Point"}
}