{
  "type": "Feature",
  "properties": {
    "gn:admin1_code":"8",
    "gn:admin2_code":"GE",
    "gn:admin3_code":"10030.0",
    "gn:asciiname":"Ballano",
    "gn:country_code":"IT",
    "gn:dem":405,
    "gn:feature_class":"P",
    "gn:feature_code":"PPL",
    "gn:name":"Ballano",
    "gn:population":20,
    "gn:timezone":"Europe/Rome",
    "iso:country":"IT",
    "wof:name":"Ballano",
    "wof:placetype":"locality",
    "wof:population":20
},
  "geometry": {"coordinates":[9.24564,44.42115],"type":"Point"}
}