{
  "type": "Feature",
  "properties": {
    "gn:admin1_code":"7",
    "gn:admin2_code":"FR",
    "gn:admin3_code":"60055.0",
    "gn:asciiname":"Castagneto",
    "gn:country_code":"IT",
    "gn:dem":159,
    "gn:feature_class":"P",
    "gn:feature_code":"PPL",
    "gn:name":"Castagneto",
    "gn:population":65,
    "gn:timezone":"Europe/Rome",
    "iso:country":"IT",
    "name:ceb_x_preferred":[
        "Castagneto"
    ],
    "name:fra_x_preferred":[
        "Castagneto"
    ],
    "name:ita_x_preferred":[
        "Castagneto"
    ],
    "name:nld_x_preferred":[
        "Castagneto"
    ],
    "name:srp_x_preferred":[
        "\u041a\u0430\u0441\u0442\u0430\u045a\u0435\u0442\u043e"
    ],
    "wof:name":"Castagneto",
    "wof:placetype":"locality",
    "wof:population":65
},
  "geometry": {"coordinates":[13.42492,41.5573],"type":"Point"}
}