{
  "type": "Feature",
  "properties": {
    "gn:admin1_code":"12",
    "gn:admin2_code":"TO",
    "gn:admin3_code":"1310.0",
    "gn:asciiname":"Cascina Gorre",
    "gn:country_code":"IT",
    "gn:dem":245,
    "gn:feature_class":"P",
    "gn:feature_code":"PPL",
    "gn:name":"Cascina Gorre",
    "gn:population":28,
    "gn:timezone":"Europe/Rome",
    "iso:country":"IT",
    "wof:name":"Cascina Gorre",
    "wof:placetype":"locality",
    "wof:population":28
},
  "geometry": {"coordinates":[7.60037,44.85893],"type":"Point"}
}