{
  "type": "Feature",
  "properties": {
    "gn:admin1_code":"4.0",
    "gn:admin2_code":"SA",
    "gn:admin3_code":"65120.0",
    "gn:asciiname":"Filette",
    "gn:country_code":"IT",
    "gn:dem":474,
    "gn:feature_class":"P",
    "gn:feature_code":"PPL",
    "gn:name":"Filette",
    "gn:population":54,
    "gn:timezone":"Europe/Rome",
    "iso:country":"IT",
    "wof:name":"Filette",
    "wof:placetype":"locality",
    "wof:population":54
},
  "geometry": {"coordinates":[15.35554,40.66798],"type":"Point"}
}