{
  "type": "Feature",
  "properties": {
    "gn:admin1_code":"5",
    "gn:admin2_code":"BO",
    "gn:admin3_code":"37031.0",
    "gn:asciiname":"Puzzola",
    "gn:country_code":"IT",
    "gn:dem":297,
    "gn:feature_class":"P",
    "gn:feature_code":"PPL",
    "gn:name":"Puzzola",
    "gn:population":30,
    "gn:timezone":"Europe/Rome",
    "iso:country":"IT",
    "wof:name":"Puzzola",
    "wof:placetype":"locality",
    "wof:population":30
},
  "geometry": {"coordinates":[11.18535,44.26867],"type":"Point"}
}