{
  "type": "Feature",
  "properties": {
    "gn:admin1_code":"12",
    "gn:admin2_code":"TO",
    "gn:admin3_code":"1069.0",
    "gn:asciiname":"Casa Porta",
    "gn:country_code":"IT",
    "gn:dem":276,
    "gn:feature_class":"P",
    "gn:feature_code":"PPL",
    "gn:name":"Casa Porta",
    "gn:population":37,
    "gn:timezone":"Europe/Rome",
    "iso:country":"IT",
    "wof:name":"Casa Porta",
    "wof:placetype":"locality",
    "wof:population":37
},
  "geometry": {"coordinates":[8.03221,45.14843],"type":"Point"}
}