{
  "type": "Feature",
  "properties": {
    "gn:admin1_code":"16",
    "gn:admin2_code":"AR",
    "gn:admin3_code":"51035.0",
    "gn:asciiname":"Palazzi",
    "gn:country_code":"IT",
    "gn:dem":583,
    "gn:feature_class":"P",
    "gn:feature_code":"PPL",
    "gn:name":"Palazzi",
    "gn:population":48,
    "gn:timezone":"Europe/Rome",
    "iso:country":"IT",
    "wof:name":"Palazzi",
    "wof:placetype":"locality",
    "wof:population":48
},
  "geometry": {"coordinates":[12.20845,43.70899],"type":"Point"}
}