{
  "type": "Feature",
  "properties": {
    "gn:admin1_code":"17",
    "gn:admin2_code":"TN",
    "gn:admin3_code":"22061.0",
    "gn:asciiname":"Rovere",
    "gn:country_code":"IT",
    "gn:dem":566,
    "gn:feature_class":"P",
    "gn:feature_code":"PPL",
    "gn:name":"Rover\u00e8",
    "gn:population":78,
    "gn:timezone":"Europe/Rome",
    "iso:country":"IT",
    "name:ceb_x_preferred":[
        "Rovere"
    ],
    "name:deu_x_preferred":[
        "Rovere"
    ],
    "name:ita_x_preferred":[
        "Rovere"
    ],
    "name:por_x_preferred":[
        "Rovere"
    ],
    "name:rus_x_preferred":[
        "\u0420\u043e\u0432\u0435\u0440\u0435"
    ],
    "name:srp_x_preferred":[
        "Rovere"
    ],
    "name:swe_x_preferred":[
        "Rovere"
    ],
    "name:ukr_x_preferred":[
        "\u0420\u043e\u0432\u0435\u0440\u0435"
    ],
    "name:und_x_variant":[
        "Rover\u00e8"
    ],
    "wof:name":"Rovere",
    "wof:placetype":"locality",
    "wof:population":78
},
  "geometry": {"coordinates":[11.19374,46.09069],"type":"Point"}
}