{
  "type": "Feature",
  "properties": {
    "iso:country":"IT",
    "qs_pg:aaroncc":"IT",
    "qs_pg:name":"S. Giovanni Inferiore",
    "qs_pg:name_adm0":"Italia",
    "qs_pg:name_adm1":"Friuli-Venezia Giulia",
    "qs_pg:photos":11,
    "qs_pg:photos_1k":2,
    "qs_pg:photos_9k":1,
    "qs_pg:photos_9r":1,
    "qs_pg:photos_all":11,
    "qs_pg:photos_sr":1,
    "qs_pg:pop_sr":0,
    "qs_pg:qs_pg_placetype":"neighbourhood",
    "qs_pg:qs_pg_placetype_gp":"Suburb",
    "qs_pg:woe_adm0":23424853,
    "woe:adm0_id":23424853,
    "woe:name_adm0":"Italia",
    "woe:name_adm1":"Friuli-Venezia Giulia",
    "woe:placetype":"Suburb",
    "wof:name":"S. Giovanni Inferiore",
    "wof:placetype":"neighbourhood"
},
  "geometry": {"coordinates":[13.804192,45.654945],"type":"Point"}
}