{
  "type": "Feature",
  "properties": {
    "gn:admin1_code":"12",
    "gn:admin2_code":"CN",
    "gn:admin3_code":"4009.0",
    "gn:asciiname":"Piccata",
    "gn:country_code":"IT",
    "gn:dem":403,
    "gn:feature_class":"P",
    "gn:feature_code":"PPL",
    "gn:name":"Piccata",
    "gn:population":37,
    "gn:timezone":"Europe/Rome",
    "iso:country":"IT",
    "wof:name":"Piccata",
    "wof:placetype":"locality",
    "wof:population":37
},
  "geometry": {"coordinates":[7.31163,44.75208],"type":"Point"}
}