{
  "type": "Feature",
  "properties": {
    "gn:admin1_code":"12",
    "gn:admin2_code":"CN",
    "gn:admin3_code":"4009.0",
    "gn:asciiname":"Piccata",
    "gn:country_code":"IT",
    "gn:dem":403,
    "gn:feature_class":"P",
    "gn:feature_code":"PPL",
    "gn:name":"Piccata",
    "gn:population":37,
    "gn:timezone":"Europe/Rome",
    "iso:country":"IT",
    "name:ara_x_preferred":[
        "\u0628\u064a\u0643\u0627\u062a\u0627"
    ],
    "name:cat_x_preferred":[
        "Piccata"
    ],
    "name:deu_x_preferred":[
        "Piccata"
    ],
    "name:fin_x_preferred":[
        "Piccatta"
    ],
    "name:fra_x_preferred":[
        "Piccata"
    ],
    "name:jpn_x_preferred":[
        "\u30d4\u30ab\u30bf"
    ],
    "name:kor_x_preferred":[
        "\ud53c\uce74\ud0c0"
    ],
    "name:spa_x_preferred":[
        "Piccata"
    ],
    "name:swe_x_preferred":[
        "Piccata"
    ],
    "wof:name":"Piccata",
    "wof:placetype":"locality",
    "wof:population":37
},
  "geometry": {"coordinates":[7.31163,44.75208],"type":"Point"}
}