{
  "type": "Feature",
  "properties": {
    "gn:admin1_code":"9",
    "gn:admin2_code":"SO",
    "gn:admin3_code":"14015.0",
    "gn:asciiname":"Moroni",
    "gn:country_code":"IT",
    "gn:dem":524,
    "gn:feature_class":"P",
    "gn:feature_code":"PPL",
    "gn:name":"Moroni",
    "gn:population":46,
    "gn:timezone":"Europe/Rome",
    "iso:country":"IT",
    "name:ceb_x_preferred":[
        "Moroni"
    ],
    "name:deu_x_preferred":[
        "Moroni"
    ],
    "name:fra_x_preferred":[
        "Moroni"
    ],
    "name:ind_x_preferred":[
        "Moroni"
    ],
    "name:ita_x_preferred":[
        "Moroni"
    ],
    "name:jpn_x_preferred":[
        "\u30e2\u30ed\u30ca\u30a4"
    ],
    "name:kor_x_preferred":[
        "\ubaa8\ub85c\ub2c8"
    ],
    "name:nds_x_preferred":[
        "Moroni"
    ],
    "name:nld_x_preferred":[
        "Moroni"
    ],
    "name:pol_x_preferred":[
        "Moroni"
    ],
    "name:por_x_preferred":[
        "Moroni"
    ],
    "name:rus_x_preferred":[
        "\u041c\u043e\u0440\u043e\u043d\u0438"
    ],
    "name:spa_x_preferred":[
        "Moroni"
    ],
    "name:swe_x_preferred":[
        "Moroni"
    ],
    "name:ukr_x_preferred":[
        "\u041c\u043e\u0440\u043e\u043d\u0456"
    ],
    "name:vie_x_preferred":[
        "Moroni"
    ],
    "name:vol_x_preferred":[
        "Moroni"
    ],
    "wof:name":"Moroni",
    "wof:placetype":"locality",
    "wof:population":46
},
  "geometry": {"coordinates":[9.81287,46.17198],"type":"Point"}
}