{
  "type": "Feature",
  "properties": {
    "gn:admin1_code":"8.0",
    "gn:admin2_code":"IM",
    "gn:admin3_code":"8055.0",
    "gn:asciiname":"San Giovanni Battista",
    "gn:cc2":"IT",
    "gn:country_code":"IT",
    "gn:dem":158,
    "gn:feature_class":"P",
    "gn:feature_code":"PPL",
    "gn:name":"San Giovanni Battista",
    "gn:population":0,
    "gn:timezone":"Europe/Rome",
    "iso:country":"IT",
    "name:und_x_variant":[
        "San Giovanni",
        "San Giovanni Battista"
    ],
    "wof:name":"San Giovanni Battista",
    "wof:placetype":"locality"
},
  "geometry": {"coordinates":[7.75,43.83333],"type":"Point"}
}