{
  "type": "Feature",
  "properties": {
    "gn:admin1_code":"5",
    "gn:admin2_code":"PR",
    "gn:admin3_code":"34042.0",
    "gn:asciiname":"Borgo Bottone",
    "gn:country_code":"IT",
    "gn:dem":165,
    "gn:feature_class":"P",
    "gn:feature_code":"PPL",
    "gn:name":"Borgo Bottone",
    "gn:population":16,
    "gn:timezone":"Europe/Rome",
    "iso:country":"IT",
    "wof:name":"Borgo Bottone",
    "wof:placetype":"locality",
    "wof:population":16
},
  "geometry": {"coordinates":[10.40766,44.64632],"type":"Point"}
}