{
  "type": "Feature",
  "properties": {
    "gn:admin1_code":"6.0",
    "gn:admin2_code":"PN",
    "gn:admin3_code":"93053.0",
    "gn:asciiname":"San Lorenzo",
    "gn:country_code":"IT",
    "gn:dem":44,
    "gn:elevation":"48.0",
    "gn:feature_class":"P",
    "gn:feature_code":"PPL",
    "gn:name":"San Lorenzo",
    "gn:population":374,
    "gn:timezone":"Europe/Rome",
    "iso:country":"IT",
    "wof:name":"San Lorenzo",
    "wof:placetype":"locality",
    "wof:population":374
},
  "geometry": {"coordinates":[12.83156,45.98113],"type":"Point"}
}