{
  "type": "Feature",
  "properties": {
    "gn:admin1_code":"11",
    "gn:admin2_code":"IS",
    "gn:admin3_code":"94012.0",
    "gn:asciiname":"La Cartiera",
    "gn:country_code":"IT",
    "gn:dem":524,
    "gn:feature_class":"P",
    "gn:feature_code":"PPL",
    "gn:name":"La Cartiera",
    "gn:population":99,
    "gn:timezone":"Europe/Rome",
    "iso:country":"IT",
    "wof:name":"La Cartiera",
    "wof:placetype":"locality",
    "wof:population":99
},
  "geometry": {"coordinates":[14.07965,41.65516],"type":"Point"}
}