{
  "type": "Feature",
  "properties": {
    "gn:admin1_code":"9",
    "gn:admin2_code":"MN",
    "gn:admin3_code":"20011.0",
    "gn:asciiname":"Bellaria",
    "gn:country_code":"IT",
    "gn:dem":45,
    "gn:feature_class":"P",
    "gn:feature_code":"PPL",
    "gn:name":"Bellaria",
    "gn:population":30,
    "gn:timezone":"Europe/Rome",
    "iso:country":"IT",
    "wof:name":"Bellaria",
    "wof:placetype":"locality",
    "wof:population":30
},
  "geometry": {"coordinates":[10.49277,45.26098],"type":"Point"}
}