{
  "type": "Feature",
  "properties": {
    "gn:admin1_code":"20",
    "gn:admin2_code":"VE",
    "gn:admin3_code":"27032.0",
    "gn:asciiname":"Sant'Elena II",
    "gn:country_code":"IT",
    "gn:dem":8,
    "gn:feature_class":"P",
    "gn:feature_code":"PPL",
    "gn:name":"Sant'Elena II",
    "gn:population":50,
    "gn:timezone":"Europe/Rome",
    "iso:country":"IT",
    "wof:name":"Sant'Elena II",
    "wof:placetype":"locality",
    "wof:population":50
},
  "geometry": {"coordinates":[12.13399,45.54936],"type":"Point"}
}