{
  "type": "Feature",
  "properties": {
    "gn:admin1_code":"5",
    "gn:admin2_code":"PC",
    "gn:admin3_code":"33026.0",
    "gn:asciiname":"Verdelli",
    "gn:country_code":"IT",
    "gn:dem":498,
    "gn:feature_class":"P",
    "gn:feature_code":"PPLL",
    "gn:name":"Verdelli",
    "gn:population":8,
    "gn:timezone":"Europe/Rome",
    "iso:country":"IT",
    "wof:name":"Verdelli",
    "wof:placetype":"locality",
    "wof:population":8
},
  "geometry": {"coordinates":[9.75893,44.80972],"type":"Point"}
}