{
  "type": "Feature",
  "properties": {
    "gn:admin1_code":"16",
    "gn:admin2_code":"PT",
    "gn:admin3_code":"47014.0",
    "gn:asciiname":"La Mora",
    "gn:country_code":"IT",
    "gn:dem":42,
    "gn:feature_class":"P",
    "gn:feature_code":"PPL",
    "gn:name":"La Mora",
    "gn:population":16,
    "gn:timezone":"Europe/Rome",
    "iso:country":"IT",
    "wof:name":"La Mora",
    "wof:placetype":"locality",
    "wof:population":16
},
  "geometry": {"coordinates":[10.96745,43.88],"type":"Point"}
}