{
  "type": "Feature",
  "properties": {
    "gn:admin1_code":"2",
    "gn:admin2_code":"MT",
    "gn:admin3_code":"77021.0",
    "gn:asciiname":"Cerchiarito",
    "gn:country_code":"IT",
    "gn:dem":50,
    "gn:feature_class":"P",
    "gn:feature_code":"PPL",
    "gn:name":"Cerchiarito",
    "gn:population":27,
    "gn:timezone":"Europe/Rome",
    "iso:country":"IT",
    "wof:name":"Cerchiarito",
    "wof:placetype":"locality",
    "wof:population":27
},
  "geometry": {"coordinates":[16.64902,40.22179000000001],"type":"Point"}
}