{
  "type": "Feature",
  "properties": {
    "gn:admin1_code":"16.0",
    "gn:admin2_code":"AR",
    "gn:admin3_code":"51026.0",
    "gn:asciiname":"Ricasoli",
    "gn:country_code":"IT",
    "gn:dem":233,
    "gn:feature_class":"P",
    "gn:feature_code":"PPL",
    "gn:name":"Ricasoli",
    "gn:population":115,
    "gn:timezone":"Europe/Rome",
    "iso:country":"IT",
    "name:deu_x_preferred":[
        "Ricasoli"
    ],
    "name:ita_x_preferred":[
        "Ricasoli"
    ],
    "wof:name":"Ricasoli",
    "wof:placetype":"locality",
    "wof:population":115
},
  "geometry": {"coordinates":[11.53908,43.52774],"type":"Point"}
}