{
  "type": "Feature",
  "properties": {
    "gn:admin1_code":"14.0",
    "gn:admin2_code":"SS",
    "gn:admin3_code":"90089.0",
    "gn:asciiname":"Pozzo San Nicola",
    "gn:cc2":"IT",
    "gn:country_code":"IT",
    "gn:dem":41,
    "gn:feature_class":"P",
    "gn:feature_code":"PPL",
    "gn:name":"Pozzo San Nicola",
    "gn:population":145,
    "gn:timezone":"Europe/Rome",
    "iso:country":"IT",
    "name:und_x_variant":[
        "Casteddu",
        "Borgata Pozzo San Nicola"
    ],
    "wof:name":"Pozzo San Nicola",
    "wof:placetype":"locality",
    "wof:population":145
},
  "geometry": {"coordinates":[8.24378,40.83705],"type":"Point"}
}