{
  "type": "Feature",
  "properties": {
    "gn:admin1_code":"7",
    "gn:admin2_code":"RM",
    "gn:admin3_code":"58081.0",
    "gn:asciiname":"Colle delle Rose",
    "gn:country_code":"IT",
    "gn:dem":143,
    "gn:feature_class":"P",
    "gn:feature_code":"PPL",
    "gn:name":"Colle delle Rose",
    "gn:population":200,
    "gn:timezone":"Europe/Rome",
    "iso:country":"IT",
    "wof:name":"Colle delle Rose",
    "wof:placetype":"locality",
    "wof:population":200
},
  "geometry": {"coordinates":[12.48781,42.07809],"type":"Point"}
}