{
  "type": "Feature",
  "properties": {
    "gn:admin1_code":"9.0",
    "gn:admin2_code":"SO",
    "gn:admin3_code":"14073.0",
    "gn:asciiname":"Plazzola",
    "gn:country_code":"IT",
    "gn:dem":1510,
    "gn:feature_class":"P",
    "gn:feature_code":"PPL",
    "gn:name":"Plazzola",
    "gn:population":342,
    "gn:timezone":"Europe/Rome",
    "iso:country":"IT",
    "wof:name":"Plazzola",
    "wof:placetype":"locality",
    "wof:population":342
},
  "geometry": {"coordinates":[10.42287,46.46407],"type":"Point"}
}