{
  "type": "Feature",
  "properties": {
    "gn:admin1_code":"20",
    "gn:admin2_code":"TV",
    "gn:admin3_code":"26021.0",
    "gn:asciiname":"Santissima Trinita",
    "gn:country_code":"IT",
    "gn:dem":97,
    "gn:feature_class":"P",
    "gn:feature_code":"PPL",
    "gn:name":"Santissima Trinit\u00e0",
    "gn:population":16,
    "gn:timezone":"Europe/Rome",
    "iso:country":"IT",
    "name:und_x_variant":[
        "Santissima Trinit\u00e0"
    ],
    "wof:name":"Santissima Trinita",
    "wof:placetype":"locality",
    "wof:population":16
},
  "geometry": {"coordinates":[12.31575,45.91534],"type":"Point"}
}