{
  "type": "Feature",
  "properties": {
    "gn:admin1_code":"8",
    "gn:admin2_code":"SV",
    "gn:admin3_code":"9040.0",
    "gn:asciiname":"Azzini",
    "gn:country_code":"IT",
    "gn:dem":592,
    "gn:feature_class":"P",
    "gn:feature_code":"PPLL",
    "gn:name":"Azzini",
    "gn:population":8,
    "gn:timezone":"Europe/Rome",
    "iso:country":"IT",
    "wof:name":"Azzini",
    "wof:placetype":"locality",
    "wof:population":8
},
  "geometry": {"coordinates":[8.16274,44.31154],"type":"Point"}
}