{
  "type": "Feature",
  "properties": {
    "gn:admin1_code":"9",
    "gn:admin2_code":"LC",
    "gn:admin3_code":"97082.0",
    "gn:asciiname":"Ganza",
    "gn:country_code":"IT",
    "gn:dem":275,
    "gn:feature_class":"P",
    "gn:feature_code":"PPLL",
    "gn:name":"Ganza",
    "gn:population":10,
    "gn:timezone":"Europe/Rome",
    "iso:country":"IT",
    "wof:name":"Ganza",
    "wof:placetype":"locality",
    "wof:population":10
},
  "geometry": {"coordinates":[9.41641,45.7776],"type":"Point"}
}