{
  "type": "Feature",
  "properties": {
    "gn:admin1_code":"12",
    "gn:admin2_code":"AT",
    "gn:admin3_code":"5079.0",
    "gn:asciiname":"Vallenervi",
    "gn:country_code":"IT",
    "gn:dem":263,
    "gn:feature_class":"P",
    "gn:feature_code":"PPL",
    "gn:name":"Vallenervi",
    "gn:population":36,
    "gn:timezone":"Europe/Rome",
    "iso:country":"IT",
    "wof:name":"Vallenervi",
    "wof:placetype":"locality",
    "wof:population":36
},
  "geometry": {"coordinates":[8.03593,45.12648],"type":"Point"}
}