{
  "type": "Feature",
  "properties": {
    "gn:admin1_code":"3",
    "gn:admin2_code":"CS",
    "gn:admin3_code":"78044.0",
    "gn:asciiname":"Casachelle",
    "gn:country_code":"IT",
    "gn:dem":38,
    "gn:feature_class":"P",
    "gn:feature_code":"PPL",
    "gn:name":"Casachelle",
    "gn:population":34,
    "gn:timezone":"Europe/Rome",
    "iso:country":"IT",
    "wof:name":"Casachelle",
    "wof:placetype":"locality",
    "wof:population":34
},
  "geometry": {"coordinates":[16.44996,39.65607],"type":"Point"}
}