{
  "type": "Feature",
  "properties": {
    "gn:admin1_code":"12.0",
    "gn:admin2_code":"CN",
    "gn:admin3_code":"4095.0",
    "gn:asciiname":"Frazione Cerisola Villa Roa",
    "gn:country_code":"IT",
    "gn:dem":512,
    "gn:feature_class":"P",
    "gn:feature_code":"PPL",
    "gn:name":"Frazione Cerisola Villa Ro\u00e0",
    "gn:population":9,
    "gn:timezone":"Europe/Rome",
    "iso:country":"IT",
    "name:und_x_variant":[
        "Frazione Cerisola Villa Ro\u00e0"
    ],
    "wof:name":"Frazione Cerisola Villa Roa",
    "wof:placetype":"locality",
    "wof:population":9
},
  "geometry": {"coordinates":[8.06724,44.15235],"type":"Point"}
}