{
  "type": "Feature",
  "properties": {
    "gn:admin1_code":"11.0",
    "gn:admin2_code":"IS",
    "gn:admin3_code":"94023.0",
    "gn:asciiname":"Colle Croce Secondo",
    "gn:country_code":"IT",
    "gn:dem":607,
    "gn:feature_class":"P",
    "gn:feature_code":"PPL",
    "gn:name":"Colle Croce Secondo",
    "gn:population":33,
    "gn:timezone":"Europe/Rome",
    "iso:country":"IT",
    "wof:name":"Colle Croce Secondo",
    "wof:placetype":"locality",
    "wof:population":33
},
  "geometry": {"coordinates":[14.21662,41.63395],"type":"Point"}
}