{
  "type": "Feature",
  "properties": {
    "gn:gn_country":"IT",
    "gn:gn_fcode":"PPLA3",
    "gn:gn_pop":396,
    "gn:population":320,
    "iso:country":"IT",
    "name:arm_x_preferred":[
        "\u053f\u0561\u057e\u0561\u056c\u0565\u0569\u0578"
    ],
    "name:baq_x_preferred":[
        "Cavaglietto"
    ],
    "name:bel_x_preferred":[
        "\u041a\u0430\u0432\u0430\u043b\u044c\u0435\u0442\u0430"
    ],
    "name:bul_x_preferred":[
        "\u041a\u0430\u0432\u0430\u043b\u0438\u0435\u0442\u043e"
    ],
    "name:cat_x_preferred":[
        "Cavaglietto"
    ],
    "name:chi_x_preferred":[
        "\u5361\u74e6\u5217\u6258"
    ],
    "name:dut_x_preferred":[
        "Cavaglietto"
    ],
    "name:eng_x_preferred":[
        "Cavaglietto"
    ],
    "name:epo_x_preferred":[
        "Cavaglietto"
    ],
    "name:fre_x_preferred":[
        "Cavaglietto"
    ],
    "name:ger_x_preferred":[
        "Cavaglietto"
    ],
    "name:hun_x_preferred":[
        "Cavaglietto"
    ],
    "name:ind_x_preferred":[
        "Cavaglietto"
    ],
    "name:ita_x_preferred":[
        "Cavaglietto"
    ],
    "name:jpn_x_preferred":[
        "\u30ab\u30f4\u30a1\u30ea\u30a8\u30c3\u30c8"
    ],
    "name:kaz_x_preferred":[
        "\u041a\u0430\u0432\u0430\u043b\u044c\u0435\u0442\u0442\u043e"
    ],
    "name:lat_x_preferred":[
        "Caballiacum Inferius"
    ],
    "name:lmo_x_preferred":[
        "Cavajet"
    ],
    "name:may_x_preferred":[
        "Cavaglietto"
    ],
    "name:nan_x_preferred":[
        "Cavaglietto"
    ],
    "name:nap_x_preferred":[
        "Cavaglietto"
    ],
    "name:oci_x_preferred":[
        "Cavaglietto"
    ],
    "name:per_x_preferred":[
        "\u06a9\u0627\u0648\u0627\u0644\u06cc\u062a\u0648"
    ],
    "name:pms_x_preferred":[
        "Cavajet"
    ],
    "name:pol_x_preferred":[
        "Cavaglietto"
    ],
    "name:por_x_preferred":[
        "Cavaglietto"
    ],
    "name:rum_x_preferred":[
        "Cavaglietto"
    ],
    "name:rus_x_preferred":[
        "\u041a\u0430\u0432\u0430\u043b\u044c\u0435\u0442\u0442\u043e"
    ],
    "name:scn_x_preferred":[
        "Cavaglietto"
    ],
    "name:spa_x_preferred":[
        "Cavaglietto"
    ],
    "name:srp_x_preferred":[
        "Cavaglietto"
    ],
    "name:tgl_x_preferred":[
        "Cavaglietto"
    ],
    "name:ukr_x_preferred":[
        "\u041a\u0430\u0432\u0430\u043b\u044c\u0454\u0442\u0442\u043e"
    ],
    "name:uzb_x_preferred":[
        "Cavaglietto"
    ],
    "name:vie_x_preferred":[
        "Cavaglietto"
    ],
    "name:vol_x_preferred":[
        "Cavaglietto"
    ],
    "name:war_x_preferred":[
        "Cavaglietto"
    ],
    "qs_pg:aaroncc":"IT",
    "qs_pg:gn_country":"IT",
    "qs_pg:gn_fcode":"PPLA3",
    "qs_pg:gn_pop":396,
    "qs_pg:name":"Cavaglietto",
    "qs_pg:name_adm0":"Italia",
    "qs_pg:name_adm1":"Piemonte",
    "qs_pg:photos_9r":0,
    "qs_pg:photos_sr":0,
    "qs_pg:pop_sr":2,
    "qs_pg:qs_pg_placetype":"locality",
    "qs_pg:qs_pg_placetype_gp":"Town",
    "qs_pg:woe_adm0":23424853,
    "woe:adm0_id":23424853,
    "woe:name_adm0":"Italia",
    "woe:name_adm1":"Piemonte",
    "woe:placetype":"Town",
    "wof:name":"Cavaglietto",
    "wof:placetype":"locality",
    "wof:population":320
},
  "geometry": {"coordinates":[8.50213,45.60217],"type":"Point"}
}