{
  "type": "Feature",
  "properties": {
    "gn:gn_country":"IT",
    "gn:gn_fcode":"PPL",
    "gn:gn_pop":0,
    "gn:population":780,
    "iso:country":"IT",
    "name:ita_x_preferred":[
        "Padriciano"
    ],
    "name:slv_x_preferred":[
        "Padri\u010de"
    ],
    "qs_pg:aaroncc":"IT",
    "qs_pg:gn_country":"IT",
    "qs_pg:gn_fcode":"PPL",
    "qs_pg:gn_pop":0,
    "qs_pg:name":"Padriciano",
    "qs_pg:name_adm0":"Italia",
    "qs_pg:name_adm1":"Friuli-Venezia Giulia",
    "qs_pg:photos":39,
    "qs_pg:photos_1k":8,
    "qs_pg:photos_9k":1,
    "qs_pg:photos_9r":2,
    "qs_pg:photos_all":39,
    "qs_pg:photos_sr":2,
    "qs_pg:pop_sr":0,
    "qs_pg:qs_pg_placetype":"locality",
    "qs_pg:qs_pg_placetype_gp":"Town",
    "qs_pg:woe_adm0":23424853,
    "woe:adm0_id":23424853,
    "woe:name_adm0":"Italia",
    "woe:name_adm1":"Friuli-Venezia Giulia",
    "woe:placetype":"Town",
    "wof:name":"Padriciano",
    "wof:placetype":"locality",
    "wof:population":780
},
  "geometry": {"coordinates":[13.83936,45.65843],"type":"Point"}
}