{
  "type": "Feature",
  "properties": {
    "gn:admin1_code":"9.0",
    "gn:admin2_code":"PV",
    "gn:admin3_code":"18021.0",
    "gn:asciiname":"Bralello",
    "gn:country_code":"IT",
    "gn:dem":999,
    "gn:feature_class":"P",
    "gn:feature_code":"PPL",
    "gn:name":"Bralello",
    "gn:population":41,
    "gn:timezone":"Europe/Rome",
    "iso:country":"IT",
    "wof:name":"Bralello",
    "wof:placetype":"locality",
    "wof:population":41
},
  "geometry": {"coordinates":[9.2741,44.73672],"type":"Point"}
}