{
  "type": "Feature",
  "properties": {
    "gn:admin1_code":"5",
    "gn:admin2_code":"PC",
    "gn:admin3_code":"33032.0",
    "gn:asciiname":"Croce Grossa",
    "gn:country_code":"IT",
    "gn:dem":51,
    "gn:feature_class":"P",
    "gn:feature_code":"PPL",
    "gn:name":"Croce Grossa",
    "gn:population":12,
    "gn:timezone":"Europe/Rome",
    "iso:country":"IT",
    "wof:name":"Croce Grossa",
    "wof:placetype":"locality",
    "wof:population":12
},
  "geometry": {"coordinates":[9.77049,45.03846],"type":"Point"}
}