{
  "type": "Feature",
  "properties": {
    "gn:admin1_code":"9",
    "gn:admin2_code":"LC",
    "gn:admin3_code":"97057.0",
    "gn:asciiname":"Brughello",
    "gn:country_code":"IT",
    "gn:dem":272,
    "gn:feature_class":"P",
    "gn:feature_code":"PPL",
    "gn:name":"Brughello",
    "gn:population":28,
    "gn:timezone":"Europe/Rome",
    "iso:country":"IT",
    "wof:name":"Brughello",
    "wof:placetype":"locality",
    "wof:population":28
},
  "geometry": {"coordinates":[9.31664,45.78497],"type":"Point"}
}