{
  "type": "Feature",
  "properties": {
    "gn:admin1_code":"5",
    "gn:admin2_code":"PC",
    "gn:admin3_code":"33040.0",
    "gn:asciiname":"Ribera",
    "gn:country_code":"IT",
    "gn:dem":114,
    "gn:feature_class":"P",
    "gn:feature_code":"PPLL",
    "gn:name":"Ribera",
    "gn:population":10,
    "gn:timezone":"Europe/Rome",
    "iso:country":"IT",
    "name:arg_x_preferred":[
        "Ribera"
    ],
    "name:cat_x_preferred":[
        "Ribera"
    ],
    "name:ceb_x_preferred":[
        "Ribera"
    ],
    "name:deu_x_preferred":[
        "Ribera"
    ],
    "name:eus_x_preferred":[
        "Erribera"
    ],
    "name:fra_x_preferred":[
        "Ribera"
    ],
    "name:glg_x_preferred":[
        "Ribera"
    ],
    "name:ita_x_preferred":[
        "Ribera"
    ],
    "name:nds_x_preferred":[
        "Ribera"
    ],
    "name:rus_x_preferred":[
        "\u0420\u0438\u0431\u0435\u0440\u0430"
    ],
    "name:sco_x_preferred":[
        "Ribera"
    ],
    "name:spa_x_preferred":[
        "Ribera"
    ],
    "name:srp_x_preferred":[
        "\u0420\u0438\u0431\u0435\u0440\u0430"
    ],
    "name:swe_x_preferred":[
        "Ribera"
    ],
    "wof:name":"Ribera",
    "wof:placetype":"locality",
    "wof:population":10
},
  "geometry": {"coordinates":[9.74142,44.9304],"type":"Point"}
}