{
  "type": "Feature",
  "properties": {
    "gn:admin1_code":"2",
    "gn:admin2_code":"PZ",
    "gn:admin3_code":"76076.0",
    "gn:asciiname":"Cecci",
    "gn:country_code":"IT",
    "gn:dem":574,
    "gn:feature_class":"P",
    "gn:feature_code":"PPL",
    "gn:name":"Cecci",
    "gn:population":79,
    "gn:timezone":"Europe/Rome",
    "iso:country":"IT",
    "wof:name":"Cecci",
    "wof:placetype":"locality",
    "wof:population":79
},
  "geometry": {"coordinates":[15.65475,40.82664000000001],"type":"Point"}
}