{
  "type": "Feature",
  "properties": {
    "gn:admin1_code":"18.0",
    "gn:admin2_code":"PG",
    "gn:admin3_code":"54015.0",
    "gn:asciiname":"Corciano Vecchio",
    "gn:country_code":"IT",
    "gn:dem":268,
    "gn:feature_class":"P",
    "gn:feature_code":"PPL",
    "gn:name":"Corciano Vecchio",
    "gn:population":70,
    "gn:timezone":"Europe/Rome",
    "iso:country":"IT",
    "wof:name":"Corciano Vecchio",
    "wof:placetype":"locality",
    "wof:population":70
},
  "geometry": {"coordinates":[12.27655,43.13504],"type":"Point"}
}