{
  "type": "Feature",
  "properties": {
    "gn:admin1_code":"20.0",
    "gn:admin2_code":"RO",
    "gn:admin3_code":"29033.0",
    "gn:asciiname":"Eurovo",
    "gn:country_code":"IT",
    "gn:dem":6,
    "gn:feature_class":"P",
    "gn:feature_code":"PPLL",
    "gn:name":"Eurovo",
    "gn:population":0,
    "gn:timezone":"Europe/Rome",
    "iso:country":"IT",
    "wof:name":"Eurovo",
    "wof:placetype":"locality"
},
  "geometry": {"coordinates":[11.61104,44.91564],"type":"Point"}
}