{
  "type": "Feature",
  "properties": {
    "gn:admin1_code":"10.0",
    "gn:admin2_code":"AN",
    "gn:admin3_code":"42034.0",
    "gn:asciiname":"Ponte dell'Aspio",
    "gn:country_code":"IT",
    "gn:dem":65,
    "gn:feature_class":"P",
    "gn:feature_code":"PPL",
    "gn:name":"Ponte dell'Aspio",
    "gn:population":503,
    "gn:timezone":"Europe/Rome",
    "iso:country":"IT",
    "wof:name":"Ponte dell'Aspio",
    "wof:placetype":"locality",
    "wof:population":503
},
  "geometry": {"coordinates":[13.49924,43.5294],"type":"Point"}
}