{
  "type": "Feature",
  "properties": {
    "gn:admin1_code":"1",
    "gn:admin2_code":"TE",
    "gn:admin3_code":"67032.0",
    "gn:asciiname":"Grasciano",
    "gn:country_code":"IT",
    "gn:dem":139,
    "gn:feature_class":"P",
    "gn:feature_code":"PPL",
    "gn:name":"Grasciano",
    "gn:population":92,
    "gn:timezone":"Europe/Rome",
    "iso:country":"IT",
    "wof:name":"Grasciano",
    "wof:placetype":"locality",
    "wof:population":92
},
  "geometry": {"coordinates":[13.91356,42.69049],"type":"Point"}
}