{
  "type": "Feature",
  "properties": {
    "gn:admin1_code":"9",
    "gn:admin2_code":"CO",
    "gn:admin3_code":"13154.0",
    "gn:asciiname":"Trivino",
    "gn:country_code":"IT",
    "gn:dem":363,
    "gn:feature_class":"P",
    "gn:feature_code":"PPL",
    "gn:name":"Trivino",
    "gn:population":84,
    "gn:timezone":"Europe/Rome",
    "iso:country":"IT",
    "wof:name":"Trivino",
    "wof:placetype":"locality",
    "wof:population":84
},
  "geometry": {"coordinates":[9.03466,45.79763],"type":"Point"}
}