{
  "type": "Feature",
  "properties": {
    "gn:admin1_code":"9",
    "gn:admin2_code":"MN",
    "gn:admin3_code":"20051.0",
    "gn:asciiname":"Le Corti",
    "gn:country_code":"IT",
    "gn:dem":32,
    "gn:feature_class":"P",
    "gn:feature_code":"PPL",
    "gn:name":"Le Corti",
    "gn:population":13,
    "gn:timezone":"Europe/Rome",
    "iso:country":"IT",
    "wof:name":"Le Corti",
    "wof:placetype":"locality",
    "wof:population":13
},
  "geometry": {"coordinates":[10.6337,45.19017],"type":"Point"}
}