{
  "type": "Feature",
  "properties": {
    "gn:admin1_code":"16.0",
    "gn:admin2_code":"MS",
    "gn:admin3_code":"45001.0",
    "gn:asciiname":"Stazione di Caprigliola-Albiano",
    "gn:country_code":"IT",
    "gn:dem":38,
    "gn:feature_class":"P",
    "gn:feature_code":"PPL",
    "gn:name":"Stazione di Caprigliola-Albiano",
    "gn:population":45,
    "gn:timezone":"Europe/Rome",
    "iso:country":"IT",
    "wof:name":"Stazione di Caprigliola-Albiano",
    "wof:placetype":"locality",
    "wof:population":45
},
  "geometry": {"coordinates":[9.92685,44.17302],"type":"Point"}
}