{
  "type": "Feature",
  "properties": {
    "gn:admin1_code":"12",
    "gn:admin2_code":"CN",
    "gn:admin3_code":"4190.0",
    "gn:asciiname":"Bertini",
    "gn:country_code":"IT",
    "gn:dem":633,
    "gn:feature_class":"P",
    "gn:feature_code":"PPL",
    "gn:name":"Bertini",
    "gn:population":26,
    "gn:timezone":"Europe/Rome",
    "iso:country":"IT",
    "name:deu_x_preferred":[
        "Bertini"
    ],
    "name:fra_x_preferred":[
        "Bertini"
    ],
    "name:ita_x_preferred":[
        "Bertini"
    ],
    "name:jpn_x_preferred":[
        "\u30d9\u30eb\u30c6\u30a3\u30fc\u30cb"
    ],
    "name:nds_x_preferred":[
        "Bertini"
    ],
    "name:rus_x_preferred":[
        "\u0411\u0435\u0440\u0442\u0438\u043d\u0438"
    ],
    "name:slv_x_preferred":[
        "Bertini"
    ],
    "name:spa_x_preferred":[
        "Bertini"
    ],
    "wof:name":"Bertini",
    "wof:placetype":"locality",
    "wof:population":26
},
  "geometry": {"coordinates":[7.74492,44.29968],"type":"Point"}
}