{
  "type": "Feature",
  "properties": {
    "gn:admin1_code":"20",
    "gn:admin2_code":"TV",
    "gn:admin3_code":"26059.0",
    "gn:asciiname":"Massolin",
    "gn:country_code":"IT",
    "gn:dem":42,
    "gn:feature_class":"P",
    "gn:feature_code":"PPL",
    "gn:name":"Massolin",
    "gn:population":74,
    "gn:timezone":"Europe/Rome",
    "iso:country":"IT",
    "wof:name":"Massolin",
    "wof:placetype":"locality",
    "wof:population":74
},
  "geometry": {"coordinates":[12.19197,45.72156],"type":"Point"}
}