{
  "type": "Feature",
  "properties": {
    "gn:admin1_code":"11",
    "gn:admin2_code":"CB",
    "gn:admin3_code":"70017.0",
    "gn:asciiname":"Convento",
    "gn:country_code":"IT",
    "gn:dem":734,
    "gn:feature_class":"P",
    "gn:feature_code":"PPL",
    "gn:name":"Convento",
    "gn:population":69,
    "gn:timezone":"Europe/Rome",
    "iso:country":"IT",
    "wof:name":"Convento",
    "wof:placetype":"locality",
    "wof:population":69
},
  "geometry": {"coordinates":[14.7086,41.45685],"type":"Point"}
}