{
  "type": "Feature",
  "properties": {
    "gn:admin1_code":"15",
    "gn:admin2_code":"TP",
    "gn:admin3_code":"81005.0",
    "gn:asciiname":"Villaggio Sporting",
    "gn:country_code":"IT",
    "gn:dem":58,
    "gn:feature_class":"P",
    "gn:feature_code":"PPL",
    "gn:name":"Villaggio Sporting",
    "gn:population":23,
    "gn:timezone":"Europe/Rome",
    "iso:country":"IT",
    "wof:name":"Villaggio Sporting",
    "wof:placetype":"locality",
    "wof:population":23
},
  "geometry": {"coordinates":[12.82629,38.05713],"type":"Point"}
}