{
  "type": "Feature",
  "properties": {
    "gn:admin1_code":"9",
    "gn:admin2_code":"VA",
    "gn:admin3_code":"12095.0",
    "gn:asciiname":"Costanza",
    "gn:country_code":"IT",
    "gn:dem":255,
    "gn:feature_class":"P",
    "gn:feature_code":"PPL",
    "gn:name":"Costanza",
    "gn:population":36,
    "gn:timezone":"Europe/Rome",
    "iso:country":"IT",
    "name:bre_x_preferred":[
        "Costanza"
    ],
    "name:ceb_x_preferred":[
        "Costanza"
    ],
    "name:deu_x_preferred":[
        "Costanza"
    ],
    "name:fra_x_preferred":[
        "Costanza"
    ],
    "name:glg_x_preferred":[
        "Costanza"
    ],
    "name:ita_x_preferred":[
        "Costanza"
    ],
    "name:jpn_x_preferred":[
        "\u30b3\u30b9\u30bf\u30f3\u30c4\u30a1"
    ],
    "name:lmo_x_preferred":[
        "Costanza"
    ],
    "name:rus_x_preferred":[
        "\u041a\u043e\u043d\u0441\u0442\u0430\u043d\u0446\u0430"
    ],
    "name:srp_x_preferred":[
        "Costanza"
    ],
    "name:swe_x_preferred":[
        "Costanza"
    ],
    "wof:name":"Costanza",
    "wof:placetype":"locality",
    "wof:population":36
},
  "geometry": {"coordinates":[8.67318,45.81982],"type":"Point"}
}