{
  "type": "Feature",
  "properties": {
    "gn:admin1_code":"1",
    "gn:admin2_code":"TE",
    "gn:admin3_code":"67015.0",
    "gn:asciiname":"Staiano",
    "gn:country_code":"IT",
    "gn:dem":349,
    "gn:feature_class":"P",
    "gn:feature_code":"PPL",
    "gn:name":"Staiano",
    "gn:population":62,
    "gn:timezone":"Europe/Rome",
    "iso:country":"IT",
    "wof:name":"Staiano",
    "wof:placetype":"locality",
    "wof:population":62
},
  "geometry": {"coordinates":[13.84563,42.59324],"type":"Point"}
}