{
  "type": "Feature",
  "properties": {
    "gn:admin1_code":"20",
    "gn:admin2_code":"VI",
    "gn:admin3_code":"24054.0",
    "gn:asciiname":"Valle di Sopra",
    "gn:country_code":"IT",
    "gn:dem":439,
    "gn:feature_class":"P",
    "gn:feature_code":"PPL",
    "gn:name":"Valle di Sopra",
    "gn:population":80,
    "gn:timezone":"Europe/Rome",
    "iso:country":"IT",
    "wof:name":"Valle di Sopra",
    "wof:placetype":"locality",
    "wof:population":80
},
  "geometry": {"coordinates":[11.55042,45.77413],"type":"Point"}
}