{
  "type": "Feature",
  "properties": {
    "gn:admin1_code":"20.0",
    "gn:admin2_code":"TV",
    "gn:admin3_code":"26053.0",
    "gn:asciiname":"Bavaroi",
    "gn:country_code":"IT",
    "gn:dem":36,
    "gn:feature_class":"P",
    "gn:feature_code":"PPL",
    "gn:name":"Bavaroi",
    "gn:population":0,
    "gn:timezone":"Europe/Rome",
    "iso:country":"IT",
    "wof:name":"Bavaroi",
    "wof:placetype":"locality"
},
  "geometry": {"coordinates":[12.44333,45.92833],"type":"Point"}
}