{
  "type": "Feature",
  "properties": {
    "gn:admin1_code":"1",
    "gn:admin2_code":"PE",
    "gn:admin3_code":"68030.0",
    "gn:asciiname":"Collecinciero",
    "gn:country_code":"IT",
    "gn:dem":268,
    "gn:feature_class":"P",
    "gn:feature_code":"PPL",
    "gn:name":"Collecinciero",
    "gn:population":54,
    "gn:timezone":"Europe/Rome",
    "iso:country":"IT",
    "wof:name":"Collecinciero",
    "wof:placetype":"locality",
    "wof:population":54
},
  "geometry": {"coordinates":[14.00802,42.38431],"type":"Point"}
}