{
  "type": "Feature",
  "properties": {
    "gn:admin1_code":"4",
    "gn:admin2_code":"AV",
    "gn:admin3_code":"64073.0",
    "gn:asciiname":"Furmo",
    "gn:country_code":"IT",
    "gn:dem":309,
    "gn:feature_class":"P",
    "gn:feature_code":"PPL",
    "gn:name":"Furmo",
    "gn:population":15,
    "gn:timezone":"Europe/Rome",
    "iso:country":"IT",
    "wof:name":"Furmo",
    "wof:placetype":"locality",
    "wof:population":15
},
  "geometry": {"coordinates":[14.7434,41.00754000000001],"type":"Point"}
}