{
  "type": "Feature",
  "properties": {
    "gn:admin1_code":"12",
    "gn:admin2_code":"BI",
    "gn:admin3_code":"96048.0",
    "gn:asciiname":"Castagnea",
    "gn:country_code":"IT",
    "gn:dem":758,
    "gn:feature_class":"P",
    "gn:feature_code":"PPL",
    "gn:name":"Castagnea",
    "gn:population":237,
    "gn:timezone":"Europe/Rome",
    "iso:country":"IT",
    "wof:name":"Castagnea",
    "wof:placetype":"locality",
    "wof:population":237
},
  "geometry": {"coordinates":[8.16535,45.67819],"type":"Point"}
}