{
  "type": "Feature",
  "properties": {
    "gn:admin1_code":"9.0",
    "gn:admin2_code":"CR",
    "gn:admin3_code":"19035.0",
    "gn:asciiname":"Cascina Dossena",
    "gn:country_code":"IT",
    "gn:dem":81,
    "gn:feature_class":"P",
    "gn:feature_code":"PPL",
    "gn:name":"Cascina Dossena",
    "gn:population":16,
    "gn:timezone":"Europe/Rome",
    "iso:country":"IT",
    "wof:name":"Cascina Dossena",
    "wof:placetype":"locality",
    "wof:population":16
},
  "geometry": {"coordinates":[9.67523,45.38892],"type":"Point"}
}