{
  "type": "Feature",
  "properties": {
    "gn:admin1_code":"12.0",
    "gn:admin2_code":"AL",
    "gn:admin3_code":"6099.0",
    "gn:asciiname":"Coggia",
    "gn:country_code":"IT",
    "gn:dem":259,
    "gn:feature_class":"P",
    "gn:feature_code":"PPL",
    "gn:name":"Coggia",
    "gn:population":20,
    "gn:timezone":"Europe/Rome",
    "iso:country":"IT",
    "wof:name":"Coggia",
    "wof:placetype":"locality",
    "wof:population":20
},
  "geometry": {"coordinates":[8.14667,45.15935],"type":"Point"}
}