{
  "type": "Feature",
  "properties": {
    "gn:admin1_code":"12.0",
    "gn:admin2_code":"AL",
    "gn:admin3_code":"6099.0",
    "gn:asciiname":"Coggia",
    "gn:country_code":"IT",
    "gn:dem":259,
    "gn:feature_class":"P",
    "gn:feature_code":"PPL",
    "gn:name":"Coggia",
    "gn:population":20,
    "gn:timezone":"Europe/Rome",
    "iso:country":"IT",
    "name:cat_x_preferred":[
        "Coggia"
    ],
    "name:ceb_x_preferred":[
        "Coggia"
    ],
    "name:cos_x_preferred":[
        "Coghja"
    ],
    "name:deu_x_preferred":[
        "Coggia"
    ],
    "name:eus_x_preferred":[
        "Coggia"
    ],
    "name:fra_x_preferred":[
        "Coggia"
    ],
    "name:hun_x_preferred":[
        "Coggia"
    ],
    "name:hye_x_preferred":[
        "\u053f\u0578\u057b\u0561"
    ],
    "name:ind_x_preferred":[
        "Coggia"
    ],
    "name:ita_x_preferred":[
        "Coggia"
    ],
    "name:kaz_x_preferred":[
        "\u041a\u043e\u0434\u0436\u0430"
    ],
    "name:lat_x_preferred":[
        "Coggia"
    ],
    "name:lmo_x_preferred":[
        "Coggia"
    ],
    "name:msa_x_preferred":[
        "Coggia"
    ],
    "name:nld_x_preferred":[
        "Coggia"
    ],
    "name:nor_x_preferred":[
        "Coggia"
    ],
    "name:oci_x_preferred":[
        "Coggia"
    ],
    "name:pol_x_preferred":[
        "Coggia"
    ],
    "name:por_x_preferred":[
        "Coggia"
    ],
    "name:rus_x_preferred":[
        "\u041a\u043e\u0434\u0436\u0430"
    ],
    "name:slk_x_preferred":[
        "Coggia"
    ],
    "name:slv_x_preferred":[
        "Coggia"
    ],
    "name:spa_x_preferred":[
        "Coggia"
    ],
    "name:srp_x_preferred":[
        "\u041a\u043e\u0452\u0430"
    ],
    "name:swe_x_preferred":[
        "Coggia"
    ],
    "name:ukr_x_preferred":[
        "\u041a\u043e\u0434\u0436\u0430"
    ],
    "name:vie_x_preferred":[
        "Coggia"
    ],
    "name:vol_x_preferred":[
        "Coggia"
    ],
    "name:war_x_preferred":[
        "Coggia"
    ],
    "wof:name":"Coggia",
    "wof:placetype":"locality",
    "wof:population":20
},
  "geometry": {"coordinates":[8.14667,45.15935],"type":"Point"}
}