{
  "type": "Feature",
  "properties": {
    "gn:admin1_code":"20",
    "gn:admin2_code":"VE",
    "gn:admin3_code":"27038.0",
    "gn:asciiname":"Villafranca",
    "gn:country_code":"IT",
    "gn:dem":4,
    "gn:feature_class":"P",
    "gn:feature_code":"PPL",
    "gn:name":"Villafranca",
    "gn:population":57,
    "gn:timezone":"Europe/Rome",
    "iso:country":"IT",
    "wof:name":"Villafranca",
    "wof:placetype":"locality",
    "wof:population":57
},
  "geometry": {"coordinates":[12.13508,45.48919],"type":"Point"}
}