{
  "type": "Feature",
  "properties": {
    "gn:admin1_code":"20",
    "gn:admin2_code":"VE",
    "gn:admin3_code":"27038.0",
    "gn:asciiname":"Villafranca",
    "gn:country_code":"IT",
    "gn:dem":4,
    "gn:feature_class":"P",
    "gn:feature_code":"PPL",
    "gn:name":"Villafranca",
    "gn:population":57,
    "gn:timezone":"Europe/Rome",
    "iso:country":"IT",
    "name:arg_x_preferred":[
        "Villafranca"
    ],
    "name:bre_x_preferred":[
        "Alesbes"
    ],
    "name:cat_x_preferred":[
        "Villafranca"
    ],
    "name:ceb_x_preferred":[
        "Villafranca"
    ],
    "name:eus_x_preferred":[
        "Alesbes"
    ],
    "name:fra_x_preferred":[
        "Villafranca"
    ],
    "name:glg_x_preferred":[
        "Villafranca"
    ],
    "name:hun_x_preferred":[
        "Villafranca"
    ],
    "name:ita_x_preferred":[
        "Villafranca"
    ],
    "name:msa_x_preferred":[
        "Villafranca"
    ],
    "name:nld_x_preferred":[
        "Villafranca"
    ],
    "name:oci_x_preferred":[
        "Villafranca"
    ],
    "name:pol_x_preferred":[
        "Villafranca"
    ],
    "name:por_x_preferred":[
        "Villafranca"
    ],
    "name:rus_x_preferred":[
        "\u0412\u0438\u043b\u044c\u044f\u0444\u0440\u0430\u043d\u043a\u0430"
    ],
    "name:spa_x_preferred":[
        "Villafranca"
    ],
    "name:sqi_x_preferred":[
        "Villafranca"
    ],
    "name:swe_x_preferred":[
        "Villafranca"
    ],
    "name:ukr_x_preferred":[
        "\u0412\u0456\u043b\u044c\u044f\u0444\u0440\u0430\u043d\u043a\u0430"
    ],
    "name:vie_x_preferred":[
        "Villafranca"
    ],
    "name:war_x_preferred":[
        "Villafranca"
    ],
    "wof:name":"Villafranca",
    "wof:placetype":"locality",
    "wof:population":57
},
  "geometry": {"coordinates":[12.13508,45.48919],"type":"Point"}
}