{
  "type": "Feature",
  "properties": {
    "gn:admin1_code":"6.0",
    "gn:admin2_code":"UD",
    "gn:admin3_code":"30025.0",
    "gn:asciiname":"Saletto",
    "gn:country_code":"IT",
    "gn:dem":510,
    "gn:elevation":"506.0",
    "gn:feature_class":"P",
    "gn:feature_code":"PPL",
    "gn:name":"Saletto",
    "gn:population":28,
    "gn:timezone":"Europe/Rome",
    "iso:country":"IT",
    "name:azb_x_preferred":[
        "\u0633\u0627\u0644\u062a\u0648"
    ],
    "name:bul_x_preferred":[
        "\u0421\u0430\u043b\u0435\u0442\u043e"
    ],
    "name:ceb_x_preferred":[
        "Saletto"
    ],
    "name:deu_x_preferred":[
        "Saletto"
    ],
    "name:epo_x_preferred":[
        "Saletto"
    ],
    "name:eus_x_preferred":[
        "Saletto"
    ],
    "name:fas_x_preferred":[
        "\u0633\u0627\u0644\u062a\u0648"
    ],
    "name:fra_x_preferred":[
        "Saletto"
    ],
    "name:hun_x_preferred":[
        "Saletto"
    ],
    "name:hye_x_preferred":[
        "\u054d\u0561\u056c\u0565\u057f\u0578"
    ],
    "name:ind_x_preferred":[
        "Saletto"
    ],
    "name:ita_x_preferred":[
        "Saletto"
    ],
    "name:jpn_x_preferred":[
        "\u30b5\u30ec\u30c3\u30c8"
    ],
    "name:kaz_x_preferred":[
        "\u0421\u0430\u043b\u0435\u0442\u0442\u043e"
    ],
    "name:lat_x_preferred":[
        "Saletum"
    ],
    "name:lmo_x_preferred":[
        "Saletto"
    ],
    "name:msa_x_preferred":[
        "Saletto"
    ],
    "name:nap_x_preferred":[
        "Saletto"
    ],
    "name:nld_x_preferred":[
        "Saletto"
    ],
    "name:pms_x_preferred":[
        "Saletto"
    ],
    "name:pol_x_preferred":[
        "Saletto"
    ],
    "name:por_x_preferred":[
        "Saletto"
    ],
    "name:ron_x_preferred":[
        "Saletto"
    ],
    "name:rus_x_preferred":[
        "\u0421\u0430\u043b\u0435\u0442\u0442\u043e"
    ],
    "name:scn_x_preferred":[
        "Saletto"
    ],
    "name:spa_x_preferred":[
        "Saletto"
    ],
    "name:srp_x_preferred":[
        "\u0421\u0430\u043b\u0435\u0442\u043e"
    ],
    "name:tgl_x_preferred":[
        "Saletto"
    ],
    "name:ukr_x_preferred":[
        "\u0421\u0430\u043b\u0435\u0442\u0442\u043e"
    ],
    "name:uzb_x_preferred":[
        "Saletto"
    ],
    "name:vec_x_preferred":[
        "Sa\u0142eto"
    ],
    "name:vie_x_preferred":[
        "Saletto"
    ],
    "name:vol_x_preferred":[
        "Saletto"
    ],
    "name:war_x_preferred":[
        "Saletto"
    ],
    "name:zho_x_preferred":[
        "\u8428\u83b1\u6258"
    ],
    "wof:name":"Saletto",
    "wof:placetype":"locality",
    "wof:population":28
},
  "geometry": {"coordinates":[13.37656,46.4032],"type":"Point"}
}