{
  "type": "Feature",
  "properties": {
    "gn:admin1_code":"6.0",
    "gn:admin2_code":"UD",
    "gn:admin3_code":"30025.0",
    "gn:asciiname":"Saletto",
    "gn:country_code":"IT",
    "gn:dem":510,
    "gn:elevation":"506.0",
    "gn:feature_class":"P",
    "gn:feature_code":"PPL",
    "gn:name":"Saletto",
    "gn:population":28,
    "gn:timezone":"Europe/Rome",
    "iso:country":"IT",
    "wof:name":"Saletto",
    "wof:placetype":"locality",
    "wof:population":28
},
  "geometry": {"coordinates":[13.37656,46.4032],"type":"Point"}
}