{
  "type": "Feature",
  "properties": {
    "gn:admin1_code":"12",
    "gn:admin2_code":"CN",
    "gn:admin3_code":"4079.0",
    "gn:asciiname":"Trinita",
    "gn:country_code":"IT",
    "gn:dem":1170,
    "gn:feature_class":"P",
    "gn:feature_code":"PPL",
    "gn:name":"Trinit\u00e0",
    "gn:population":24,
    "gn:timezone":"Europe/Rome",
    "iso:country":"IT",
    "name:und_x_variant":[
        "Trinit\u00e0"
    ],
    "wof:name":"Trinita",
    "wof:placetype":"locality",
    "wof:population":24
},
  "geometry": {"coordinates":[7.23514,44.33522],"type":"Point"}
}