{
  "type": "Feature",
  "properties": {
    "gn:admin1_code":"1",
    "gn:admin2_code":"TE",
    "gn:admin3_code":"67036.0",
    "gn:asciiname":"Belvedere",
    "gn:country_code":"IT",
    "gn:dem":1076,
    "gn:feature_class":"P",
    "gn:feature_code":"PPL",
    "gn:name":"Belvedere",
    "gn:population":48,
    "gn:timezone":"Europe/Rome",
    "iso:country":"IT",
    "wof:name":"Belvedere",
    "wof:placetype":"locality",
    "wof:population":48
},
  "geometry": {"coordinates":[13.52956,42.67667],"type":"Point"}
}