{
  "type": "Feature",
  "properties": {
    "gn:country":"IT",
    "gn:fcode":"PPLL",
    "gn:population":1,
    "iso:country":"IT",
    "qs_pg:aaroncc":"IT",
    "qs_pg:gn_country":"IT",
    "qs_pg:gn_fcode":"PPLL",
    "qs_pg:gn_pop":1,
    "qs_pg:name":"Alpisella",
    "qs_pg:photos_9r":0,
    "qs_pg:photos_sr":0,
    "qs_pg:pop_sr":1,
    "qs_pg:qs_pg_placetype":"locality",
    "wof:name":"Alpisella",
    "wof:placetype":"locality",
    "wof:population":1
},
  "geometry": {"coordinates":[7.92183,44.12881],"type":"Point"}
}