{
  "type": "Feature",
  "properties": {
    "gn:admin1_code":"5",
    "gn:admin2_code":"FE",
    "gn:admin3_code":"38008.0",
    "gn:asciiname":"Ca' Pevere",
    "gn:country_code":"IT",
    "gn:dem":9,
    "gn:feature_class":"P",
    "gn:feature_code":"PPL",
    "gn:name":"Ca' Pevere",
    "gn:population":23,
    "gn:timezone":"Europe/Rome",
    "iso:country":"IT",
    "wof:name":"Ca' Pevere",
    "wof:placetype":"locality",
    "wof:population":23
},
  "geometry": {"coordinates":[11.56762,44.84242],"type":"Point"}
}