{
  "type": "Feature",
  "properties": {
    "gn:admin1_code":"20",
    "gn:admin2_code":"PD",
    "gn:admin3_code":"28012.0",
    "gn:asciiname":"Vallazza",
    "gn:country_code":"IT",
    "gn:dem":3,
    "gn:feature_class":"P",
    "gn:feature_code":"PPL",
    "gn:name":"Vallazza",
    "gn:population":111,
    "gn:timezone":"Europe/Rome",
    "iso:country":"IT",
    "wof:name":"Vallazza",
    "wof:placetype":"locality",
    "wof:population":111
},
  "geometry": {"coordinates":[11.78961,45.12701],"type":"Point"}
}