{
  "type": "Feature",
  "properties": {
    "gn:admin1_code":"9",
    "gn:admin2_code":"PV",
    "gn:admin3_code":"18036.0",
    "gn:asciiname":"Ca' dei Rovati",
    "gn:country_code":"IT",
    "gn:dem":222,
    "gn:feature_class":"P",
    "gn:feature_code":"PPL",
    "gn:name":"Ca' dei Rovati",
    "gn:population":35,
    "gn:timezone":"Europe/Rome",
    "iso:country":"IT",
    "wof:name":"Ca' dei Rovati",
    "wof:placetype":"locality",
    "wof:population":35
},
  "geometry": {"coordinates":[9.26864,45.03711],"type":"Point"}
}