{
  "type": "Feature",
  "properties": {
    "gn:admin1_code":"20",
    "gn:admin2_code":"TV",
    "gn:admin3_code":"26035.0",
    "gn:asciiname":"Case Robazza",
    "gn:country_code":"IT",
    "gn:dem":55,
    "gn:feature_class":"P",
    "gn:feature_code":"PPL",
    "gn:name":"Case Robazza",
    "gn:population":40,
    "gn:timezone":"Europe/Rome",
    "iso:country":"IT",
    "wof:name":"Case Robazza",
    "wof:placetype":"locality",
    "wof:population":40
},
  "geometry": {"coordinates":[12.07803,45.70523],"type":"Point"}
}