{
  "type": "Feature",
  "properties": {
    "gn:admin1_code":"12",
    "gn:admin2_code":"TO",
    "gn:admin3_code":"1204.0",
    "gn:asciiname":"Clotti",
    "gn:country_code":"IT",
    "gn:dem":854,
    "gn:feature_class":"P",
    "gn:feature_code":"PPLL",
    "gn:name":"Clotti",
    "gn:population":10,
    "gn:timezone":"Europe/Rome",
    "iso:country":"IT",
    "wof:name":"Clotti",
    "wof:placetype":"locality",
    "wof:population":10
},
  "geometry": {"coordinates":[7.21119,44.90866],"type":"Point"}
}