{
  "type": "Feature",
  "properties": {
    "gn:admin1_code":"13.0",
    "gn:admin2_code":"FG",
    "gn:admin3_code":"71007.0",
    "gn:asciiname":"Ponte Bovino",
    "gn:country_code":"IT",
    "gn:dem":258,
    "gn:feature_class":"P",
    "gn:feature_code":"PPL",
    "gn:name":"Ponte Bovino",
    "gn:population":13,
    "gn:timezone":"Europe/Rome",
    "iso:country":"IT",
    "wof:name":"Ponte Bovino",
    "wof:placetype":"locality",
    "wof:population":13
},
  "geometry": {"coordinates":[15.37172,41.27434],"type":"Point"}
}