{
  "type": "Feature",
  "properties": {
    "gn:admin1_code":"16",
    "gn:admin2_code":"FI",
    "gn:admin3_code":"48001.0",
    "gn:asciiname":"Vacciano",
    "gn:country_code":"IT",
    "gn:dem":175,
    "gn:feature_class":"P",
    "gn:feature_code":"PPL",
    "gn:name":"Vacciano",
    "gn:population":89,
    "gn:timezone":"Europe/Rome",
    "iso:country":"IT",
    "wof:name":"Vacciano",
    "wof:placetype":"locality",
    "wof:population":89
},
  "geometry": {"coordinates":[11.27845,43.73544],"type":"Point"}
}