{
  "type": "Feature",
  "properties": {
    "gn:admin1_code":"20.0",
    "gn:admin2_code":"BL",
    "gn:admin3_code":"25006.0",
    "gn:asciiname":"Cusighe",
    "gn:country_code":"IT",
    "gn:dem":402,
    "gn:feature_class":"P",
    "gn:feature_code":"PPL",
    "gn:name":"Cusighe",
    "gn:population":0,
    "gn:timezone":"Europe/Rome",
    "iso:country":"IT",
    "wof:name":"Cusighe",
    "wof:placetype":"locality"
},
  "geometry": {"coordinates":[12.22361,46.16111],"type":"Point"}
}