{
  "type": "Feature",
  "properties": {
    "gn:admin1_code":"3.0",
    "gn:admin2_code":"KR",
    "gn:admin3_code":"101013.0",
    "gn:asciiname":"Torre Ritani",
    "gn:country_code":"IT",
    "gn:dem":102,
    "gn:feature_class":"P",
    "gn:feature_code":"PPL",
    "gn:name":"Torre Ritani",
    "gn:population":0,
    "gn:timezone":"Europe/Rome",
    "iso:country":"IT",
    "wof:name":"Torre Ritani",
    "wof:placetype":"locality"
},
  "geometry": {"coordinates":[17.05,38.95],"type":"Point"}
}