{
  "type": "Feature",
  "properties": {
    "gn:admin1_code":"7",
    "gn:admin2_code":"VT",
    "gn:admin3_code":"56003.0",
    "gn:asciiname":"Poggio Fabbrica",
    "gn:country_code":"IT",
    "gn:dem":575,
    "gn:feature_class":"P",
    "gn:feature_code":"PPL",
    "gn:name":"Poggio Fabbrica",
    "gn:population":16,
    "gn:timezone":"Europe/Rome",
    "iso:country":"IT",
    "wof:name":"Poggio Fabbrica",
    "wof:placetype":"locality",
    "wof:population":16
},
  "geometry": {"coordinates":[12.05813,42.60655],"type":"Point"}
}