{
  "type": "Feature",
  "properties": {
    "gn:admin1_code":"12",
    "gn:admin2_code":"AT",
    "gn:admin3_code":"5071.0",
    "gn:asciiname":"Terpone",
    "gn:country_code":"IT",
    "gn:dem":182,
    "gn:feature_class":"P",
    "gn:feature_code":"PPL",
    "gn:name":"Terpone",
    "gn:population":48,
    "gn:timezone":"Europe/Rome",
    "iso:country":"IT",
    "wof:name":"Terpone",
    "wof:placetype":"locality",
    "wof:population":48
},
  "geometry": {"coordinates":[8.23699,44.86011],"type":"Point"}
}