{
  "type": "Feature",
  "properties": {
    "gn:admin1_code":"18.0",
    "gn:admin2_code":"PG",
    "gn:admin3_code":"54057.0",
    "gn:asciiname":"Schifanoia",
    "gn:country_code":"IT",
    "gn:dem":375,
    "gn:feature_class":"P",
    "gn:feature_code":"PPL",
    "gn:name":"Schifanoia",
    "gn:population":0,
    "gn:timezone":"Europe/Rome",
    "iso:country":"IT",
    "wof:name":"Schifanoia",
    "wof:placetype":"locality"
},
  "geometry": {"coordinates":[12.66667,43.21667],"type":"Point"}
}