{
  "type": "Feature",
  "properties": {
    "gn:admin1_code":"9.0",
    "gn:admin2_code":"PV",
    "gn:admin3_code":"18054.0",
    "gn:asciiname":"Ghiaie",
    "gn:country_code":"IT",
    "gn:dem":71,
    "gn:feature_class":"P",
    "gn:feature_code":"PPL",
    "gn:name":"Ghiaie",
    "gn:population":413,
    "gn:timezone":"Europe/Rome",
    "iso:country":"IT",
    "wof:name":"Ghiaie",
    "wof:placetype":"locality",
    "wof:population":413
},
  "geometry": {"coordinates":[8.95157,45.06551],"type":"Point"}
}