{
  "type": "Feature",
  "properties": {
    "gn:admin1_code":"20",
    "gn:admin2_code":"VE",
    "gn:admin3_code":"27028.0",
    "gn:asciiname":"Avogadro",
    "gn:country_code":"IT",
    "gn:dem":5,
    "gn:feature_class":"P",
    "gn:feature_code":"PPL",
    "gn:name":"Avogadro",
    "gn:population":29,
    "gn:timezone":"Europe/Rome",
    "iso:country":"IT",
    "wof:name":"Avogadro",
    "wof:placetype":"locality",
    "wof:population":29
},
  "geometry": {"coordinates":[12.03454,45.46486],"type":"Point"}
}