{
  "type": "Feature",
  "properties": {
    "gn:admin1_code":"20",
    "gn:admin2_code":"VE",
    "gn:admin3_code":"27028.0",
    "gn:asciiname":"Avogadro",
    "gn:country_code":"IT",
    "gn:dem":5,
    "gn:feature_class":"P",
    "gn:feature_code":"PPL",
    "gn:name":"Avogadro",
    "gn:population":29,
    "gn:timezone":"Europe/Rome",
    "iso:country":"IT",
    "name:bel_x_preferred":[
        "\u0410\u0432\u0430\u0433\u0430\u0434\u0440\u0430"
    ],
    "name:deu_x_preferred":[
        "Avogadro"
    ],
    "name:fas_x_preferred":[
        "\u0622\u0648\u0648\u06af\u0627\u062f\u0631\u0648"
    ],
    "name:fra_x_preferred":[
        "Avogadro"
    ],
    "name:heb_x_preferred":[
        "\u05d0\u05d1\u05d5\u05d2\u05d3\u05e8\u05d5"
    ],
    "name:ita_x_preferred":[
        "Avogadro"
    ],
    "name:kor_x_preferred":[
        "\uc544\ubcf4\uac00\ub4dc\ub85c"
    ],
    "name:rus_x_preferred":[
        "\u0410\u0432\u043e\u0433\u0430\u0434\u0440\u043e"
    ],
    "name:slv_x_preferred":[
        "Avogadro"
    ],
    "name:srp_x_preferred":[
        "\u0410\u0432\u043e\u0433\u0430\u0434\u0440\u043e"
    ],
    "name:tur_x_preferred":[
        "Avogadro"
    ],
    "name:ukr_x_preferred":[
        "\u0410\u0432\u043e\u0433\u0430\u0434\u0440\u043e"
    ],
    "name:zho_x_preferred":[
        "\u4e9e\u4f5b\u52a0\u53a5"
    ],
    "wof:name":"Avogadro",
    "wof:placetype":"locality",
    "wof:population":29
},
  "geometry": {"coordinates":[12.03454,45.46486],"type":"Point"}
}