{
  "type": "Feature",
  "properties": {
    "gn:admin1_code":"16.0",
    "gn:admin2_code":"AR",
    "gn:admin3_code":"51035.0",
    "gn:asciiname":"Monterone",
    "gn:country_code":"IT",
    "gn:dem":410,
    "gn:elevation":"428.0",
    "gn:feature_class":"P",
    "gn:feature_code":"PPL",
    "gn:name":"Monterone",
    "gn:population":80,
    "gn:timezone":"Europe/Rome",
    "iso:country":"IT",
    "wof:name":"Monterone",
    "wof:placetype":"locality",
    "wof:population":80
},
  "geometry": {"coordinates":[12.35151,43.71017],"type":"Point"}
}