{
  "type": "Feature",
  "properties": {
    "gn:admin1_code":"9",
    "gn:admin2_code":"PV",
    "gn:admin3_code":"18128.0",
    "gn:asciiname":"Casa Rocchi-Crotta",
    "gn:country_code":"IT",
    "gn:dem":910,
    "gn:feature_class":"P",
    "gn:feature_code":"PPL",
    "gn:name":"Casa Rocchi-Crotta",
    "gn:population":100,
    "gn:timezone":"Europe/Rome",
    "iso:country":"IT",
    "wof:name":"Casa Rocchi-Crotta",
    "wof:placetype":"locality",
    "wof:population":100
},
  "geometry": {"coordinates":[9.30421,44.8383],"type":"Point"}
}