{
  "type": "Feature",
  "properties": {
    "gn:admin1_code":"20",
    "gn:admin2_code":"PD",
    "gn:admin3_code":"28078.0",
    "gn:asciiname":"Leva",
    "gn:country_code":"IT",
    "gn:dem":44,
    "gn:feature_class":"P",
    "gn:feature_code":"PPL",
    "gn:name":"Lev\u00e0",
    "gn:population":25,
    "gn:timezone":"Europe/Rome",
    "iso:country":"IT",
    "name:und_x_variant":[
        "Lev\u00e0"
    ],
    "wof:name":"Leva",
    "wof:placetype":"locality",
    "wof:population":25
},
  "geometry": {"coordinates":[11.64946,45.61357],"type":"Point"}
}