{
  "type": "Feature",
  "properties": {
    "gn:admin1_code":"7",
    "gn:admin2_code":"VT",
    "gn:admin3_code":"56039.0",
    "gn:asciiname":"Gabelletta",
    "gn:country_code":"IT",
    "gn:dem":248,
    "gn:feature_class":"P",
    "gn:feature_code":"PPL",
    "gn:name":"Gabelletta",
    "gn:population":98,
    "gn:timezone":"Europe/Rome",
    "iso:country":"IT",
    "wof:name":"Gabelletta",
    "wof:placetype":"locality",
    "wof:population":98
},
  "geometry": {"coordinates":[12.30591,42.20756],"type":"Point"}
}