{
  "type": "Feature",
  "properties": {
    "gn:admin1_code":"19",
    "gn:admin2_code":"AO",
    "gn:admin3_code":"7008.0",
    "gn:asciiname":"Pondel",
    "gn:country_code":"IT",
    "gn:dem":891,
    "gn:feature_class":"P",
    "gn:feature_code":"PPL",
    "gn:name":"Pondel",
    "gn:population":34,
    "gn:timezone":"Europe/Rome",
    "iso:country":"IT",
    "wof:name":"Pondel",
    "wof:placetype":"locality",
    "wof:population":34
},
  "geometry": {"coordinates":[7.22327,45.677],"type":"Point"}
}