{
  "type": "Feature",
  "properties": {
    "gn:admin1_code":"10.0",
    "gn:admin2_code":"AN",
    "gn:admin3_code":"42017.0",
    "gn:asciiname":"Cancelli",
    "gn:country_code":"IT",
    "gn:dem":422,
    "gn:elevation":"421.0",
    "gn:feature_class":"P",
    "gn:feature_code":"PPL",
    "gn:name":"Cancelli",
    "gn:population":285,
    "gn:timezone":"Europe/Rome",
    "iso:country":"IT",
    "wof:name":"Cancelli",
    "wof:placetype":"locality",
    "wof:population":285
},
  "geometry": {"coordinates":[12.83907,43.30096],"type":"Point"}
}