{
  "type": "Feature",
  "properties": {
    "gn:admin1_code":"4.0",
    "gn:admin2_code":"BN",
    "gn:admin3_code":"62054.0",
    "gn:asciiname":"Peppilongo",
    "gn:country_code":"IT",
    "gn:dem":527,
    "gn:feature_class":"P",
    "gn:feature_code":"PPL",
    "gn:name":"Peppilongo",
    "gn:population":11,
    "gn:timezone":"Europe/Rome",
    "iso:country":"IT",
    "wof:name":"Peppilongo",
    "wof:placetype":"locality",
    "wof:population":11
},
  "geometry": {"coordinates":[14.68999,41.3018],"type":"Point"}
}