{
  "type": "Feature",
  "properties": {
    "gn:admin1_code":"6.0",
    "gn:admin2_code":"UD",
    "gn:admin3_code":"30073.0",
    "gn:asciiname":"Casaso",
    "gn:country_code":"IT",
    "gn:dem":686,
    "gn:feature_class":"P",
    "gn:feature_code":"PPL",
    "gn:name":"Casaso",
    "gn:population":0,
    "gn:timezone":"Europe/Rome",
    "iso:country":"IT",
    "wof:name":"Casaso",
    "wof:placetype":"locality"
},
  "geometry": {"coordinates":[13.12361,46.52917],"type":"Point"}
}