{
  "type": "Feature",
  "properties": {
    "gn:admin1_code":"5",
    "gn:admin2_code":"BO",
    "gn:admin3_code":"37040.0",
    "gn:asciiname":"La Fossa",
    "gn:country_code":"IT",
    "gn:dem":809,
    "gn:feature_class":"P",
    "gn:feature_code":"PPL",
    "gn:name":"La Fossa",
    "gn:population":35,
    "gn:timezone":"Europe/Rome",
    "iso:country":"IT",
    "name:ita_x_preferred":[
        "La Fossa"
    ],
    "wof:name":"La Fossa",
    "wof:placetype":"locality",
    "wof:population":35
},
  "geometry": {"coordinates":[11.28883,44.19335],"type":"Point"}
}