{
  "type": "Feature",
  "properties": {
    "gn:admin1_code":"7.0",
    "gn:admin2_code":"RI",
    "gn:admin3_code":"57023.0",
    "gn:asciiname":"Cenciara",
    "gn:country_code":"IT",
    "gn:dem":702,
    "gn:elevation":"695.0",
    "gn:feature_class":"P",
    "gn:feature_code":"PPL",
    "gn:name":"Cenciara",
    "gn:population":36,
    "gn:timezone":"Europe/Rome",
    "iso:country":"IT",
    "wof:name":"Cenciara",
    "wof:placetype":"locality",
    "wof:population":36
},
  "geometry": {"coordinates":[12.93394,42.35202],"type":"Point"}
}