{
  "type": "Feature",
  "properties": {
    "gn:admin1_code":"2",
    "gn:admin2_code":"PZ",
    "gn:admin3_code":"76042.0",
    "gn:asciiname":"Murge",
    "gn:country_code":"IT",
    "gn:dem":698,
    "gn:feature_class":"P",
    "gn:feature_code":"PPL",
    "gn:name":"Murge",
    "gn:population":215,
    "gn:timezone":"Europe/Rome",
    "iso:country":"IT",
    "wof:name":"Murge",
    "wof:placetype":"locality",
    "wof:population":215
},
  "geometry": {"coordinates":[15.85438,40.05774],"type":"Point"}
}