{
  "type": "Feature",
  "properties": {
    "gn:admin1_code":"6.0",
    "gn:admin2_code":"TS",
    "gn:admin3_code":"32005.0",
    "gn:asciiname":"Bristie",
    "gn:country_code":"IT",
    "gn:dem":208,
    "gn:feature_class":"P",
    "gn:feature_code":"PPL",
    "gn:name":"Bristie",
    "gn:population":28,
    "gn:timezone":"Europe/Rome",
    "iso:country":"IT",
    "wof:name":"Bristie",
    "wof:placetype":"locality",
    "wof:population":28
},
  "geometry": {"coordinates":[13.71124,45.7412],"type":"Point"}
}