{
  "type": "Feature",
  "properties": {
    "gn:admin1_code":"20.0",
    "gn:admin2_code":"VI",
    "gn:admin3_code":"24031.0",
    "gn:asciiname":"Zanetti",
    "gn:country_code":"IT",
    "gn:dem":414,
    "gn:feature_class":"P",
    "gn:feature_code":"PPL",
    "gn:name":"Zanetti",
    "gn:population":0,
    "gn:timezone":"Europe/Rome",
    "iso:country":"IT",
    "wof:name":"Zanetti",
    "wof:placetype":"locality"
},
  "geometry": {"coordinates":[11.75,45.93333],"type":"Point"}
}