{
  "type": "Feature",
  "properties": {
    "gn:admin1_code":"4",
    "gn:admin2_code":"SA",
    "gn:admin3_code":"65027.0",
    "gn:asciiname":"Affonnatora",
    "gn:country_code":"IT",
    "gn:dem":817,
    "gn:feature_class":"P",
    "gn:feature_code":"PPL",
    "gn:name":"Affonnatora",
    "gn:population":36,
    "gn:timezone":"Europe/Rome",
    "iso:country":"IT",
    "wof:name":"Affonnatora",
    "wof:placetype":"locality",
    "wof:population":36
},
  "geometry": {"coordinates":[15.69539,40.13622],"type":"Point"}
}