{
  "type": "Feature",
  "properties": {
    "gn:admin1_code":"7.0",
    "gn:admin2_code":"RI",
    "gn:admin3_code":"57059.0",
    "gn:asciiname":"San Giovanni Reatino",
    "gn:cc2":"IT",
    "gn:country_code":"IT",
    "gn:dem":428,
    "gn:elevation":"450.0",
    "gn:feature_class":"P",
    "gn:feature_code":"PPL",
    "gn:name":"San Giovanni Reatino",
    "gn:population":435,
    "gn:timezone":"Europe/Rome",
    "iso:country":"IT",
    "name:und_x_variant":[
        "San Giovanni",
        "San Giovanni Reatino"
    ],
    "wof:name":"San Giovanni Reatino",
    "wof:placetype":"locality",
    "wof:population":435
},
  "geometry": {"coordinates":[12.85409,42.34482],"type":"Point"}
}