{
  "type": "Feature",
  "properties": {
    "gn:admin1_code":"5",
    "gn:admin2_code":"MO",
    "gn:admin3_code":"36025.0",
    "gn:asciiname":"Serradimigni",
    "gn:country_code":"IT",
    "gn:dem":985,
    "gn:feature_class":"P",
    "gn:feature_code":"PPL",
    "gn:name":"Serradimigni",
    "gn:population":42,
    "gn:timezone":"Europe/Rome",
    "iso:country":"IT",
    "wof:name":"Serradimigni",
    "wof:placetype":"locality",
    "wof:population":42
},
  "geometry": {"coordinates":[10.60095,44.32217],"type":"Point"}
}