{
  "type": "Feature",
  "properties": {
    "gn:admin1_code":"4",
    "gn:admin2_code":"CE",
    "gn:admin3_code":"61039.0",
    "gn:asciiname":"Cisterni",
    "gn:country_code":"IT",
    "gn:dem":322,
    "gn:feature_class":"P",
    "gn:feature_code":"PPL",
    "gn:name":"Cisterni",
    "gn:population":22,
    "gn:timezone":"Europe/Rome",
    "iso:country":"IT",
    "wof:name":"Cisterni",
    "wof:placetype":"locality",
    "wof:population":22
},
  "geometry": {"coordinates":[13.95089,41.35141],"type":"Point"}
}