{
  "type": "Feature",
  "properties": {
    "gn:admin1_code":"16",
    "gn:admin2_code":"PI",
    "gn:admin3_code":"50033.0",
    "gn:asciiname":"Castellare",
    "gn:country_code":"IT",
    "gn:dem":15,
    "gn:feature_class":"P",
    "gn:feature_code":"PPL",
    "gn:name":"Castellare",
    "gn:population":68,
    "gn:timezone":"Europe/Rome",
    "iso:country":"IT",
    "wof:name":"Castellare",
    "wof:placetype":"locality",
    "wof:population":68
},
  "geometry": {"coordinates":[10.78084,43.72991],"type":"Point"}
}