{
  "type": "Feature",
  "properties": {
    "gn:admin1_code":"9",
    "gn:admin2_code":"MN",
    "gn:admin3_code":"20054.0",
    "gn:asciiname":"Canova Fornace",
    "gn:country_code":"IT",
    "gn:dem":21,
    "gn:feature_class":"P",
    "gn:feature_code":"PPL",
    "gn:name":"Canova Fornace",
    "gn:population":18,
    "gn:timezone":"Europe/Rome",
    "iso:country":"IT",
    "wof:name":"Canova Fornace",
    "wof:placetype":"locality",
    "wof:population":18
},
  "geometry": {"coordinates":[10.53385,45.02178],"type":"Point"}
}