{
  "type": "Feature",
  "properties": {
    "gn:admin1_code":"12",
    "gn:admin2_code":"TO",
    "gn:admin3_code":"1094.0",
    "gn:asciiname":"Case Bulot",
    "gn:country_code":"IT",
    "gn:dem":521,
    "gn:feature_class":"P",
    "gn:feature_code":"PPL",
    "gn:name":"Case Bulot",
    "gn:population":16,
    "gn:timezone":"Europe/Rome",
    "iso:country":"IT",
    "wof:name":"Case Bulot",
    "wof:placetype":"locality",
    "wof:population":16
},
  "geometry": {"coordinates":[7.56156,45.30213],"type":"Point"}
}