{
  "type": "Feature",
  "properties": {
    "gn:admin1_code":"8.0",
    "gn:admin2_code":"SV",
    "gn:admin3_code":"9023.0",
    "gn:asciiname":"Bormida-Genepro",
    "gn:country_code":"IT",
    "gn:dem":407,
    "gn:feature_class":"P",
    "gn:feature_code":"PPLA3",
    "gn:name":"Bormida-Genepro",
    "gn:population":3407,
    "gn:timezone":"Europe/Rome",
    "iso:country":"IT",
    "wof:name":"Bormida-Genepro",
    "wof:placetype":"locality",
    "wof:population":3407
},
  "geometry": {"coordinates":[8.19952,44.39051],"type":"Point"}
}