{
  "type": "Feature",
  "properties": {
    "gn:admin1_code":"12",
    "gn:admin2_code":"AL",
    "gn:admin3_code":"6003.0",
    "gn:asciiname":"Molinetto",
    "gn:country_code":"IT",
    "gn:dem":96,
    "gn:feature_class":"P",
    "gn:feature_code":"PPL",
    "gn:name":"Molinetto",
    "gn:population":39,
    "gn:timezone":"Europe/Rome",
    "iso:country":"IT",
    "wof:name":"Molinetto",
    "wof:placetype":"locality",
    "wof:population":39
},
  "geometry": {"coordinates":[8.6502,44.87389],"type":"Point"}
}