{
  "type": "Feature",
  "properties": {
    "gn:admin1_code":"16.0",
    "gn:admin2_code":"LI",
    "gn:admin3_code":"49002.0",
    "gn:asciiname":"L.P. Montevalerio",
    "gn:country_code":"IT",
    "gn:dem":114,
    "gn:feature_class":"P",
    "gn:feature_code":"PPLL",
    "gn:name":"L.P. Montevalerio",
    "gn:population":0,
    "gn:timezone":"Europe/Rome",
    "iso:country":"IT",
    "wof:name":"L.P. Montevalerio",
    "wof:placetype":"locality"
},
  "geometry": {"coordinates":[10.59356,43.05037],"type":"Point"}
}