{
  "type": "Feature",
  "properties": {
    "gn:admin1_code":"8",
    "gn:admin2_code":"GE",
    "gn:admin3_code":"10017.0",
    "gn:asciiname":"Pratozanino",
    "gn:country_code":"IT",
    "gn:dem":170,
    "gn:feature_class":"P",
    "gn:feature_code":"PPL",
    "gn:name":"Pratozanino",
    "gn:population":257,
    "gn:timezone":"Europe/Rome",
    "iso:country":"IT",
    "wof:name":"Pratozanino",
    "wof:placetype":"locality",
    "wof:population":257
},
  "geometry": {"coordinates":[8.62295,44.39192],"type":"Point"}
}