{
  "type": "Feature",
  "properties": {
    "gn:admin1_code":"5.0",
    "gn:admin2_code":"RA",
    "gn:admin3_code":"39005.0",
    "gn:asciiname":"Oriolo",
    "gn:country_code":"IT",
    "gn:dem":237,
    "gn:feature_class":"P",
    "gn:feature_code":"PPL",
    "gn:name":"Oriolo",
    "gn:population":0,
    "gn:timezone":"Europe/Rome",
    "iso:country":"IT",
    "name:azb_x_preferred":[
        "\u0627\u0648\u0631\u06cc\u0648\u0644\u0648"
    ],
    "name:bcl_x_preferred":[
        "Oriolo"
    ],
    "name:bul_x_preferred":[
        "\u041e\u0440\u0438\u043e\u043b\u043e"
    ],
    "name:ceb_x_preferred":[
        "Oriolo"
    ],
    "name:deu_x_preferred":[
        "Oriolo"
    ],
    "name:epo_x_preferred":[
        "Oriolo"
    ],
    "name:eus_x_preferred":[
        "Oriolo"
    ],
    "name:fas_x_preferred":[
        "\u0627\u0648\u0631\u06cc\u0648\u0644\u0648"
    ],
    "name:fra_x_preferred":[
        "Oriolo"
    ],
    "name:hun_x_preferred":[
        "Oriolo"
    ],
    "name:hye_x_preferred":[
        "\u0555\u0580\u056b\u0578\u056c\u0578"
    ],
    "name:ina_x_preferred":[
        "Oriolo"
    ],
    "name:ita_x_preferred":[
        "Oriolo"
    ],
    "name:jpn_x_preferred":[
        "\u30aa\u30ea\u30aa\u30fc\u30ed"
    ],
    "name:kaz_x_preferred":[
        "\u041e\u0440\u0438\u043e\u043b\u043e"
    ],
    "name:lat_x_preferred":[
        "Oriolus"
    ],
    "name:lmo_x_preferred":[
        "Oriolo"
    ],
    "name:msa_x_preferred":[
        "Oriolo"
    ],
    "name:nap_x_preferred":[
        "Oriolo"
    ],
    "name:nld_x_preferred":[
        "Oriolo"
    ],
    "name:pms_x_preferred":[
        "Oriolo"
    ],
    "name:pol_x_preferred":[
        "Oriolo"
    ],
    "name:por_x_preferred":[
        "Oriolo"
    ],
    "name:ron_x_preferred":[
        "Oriolo"
    ],
    "name:rus_x_preferred":[
        "\u041e\u0440\u0438\u043e\u043b\u043e"
    ],
    "name:scn_x_preferred":[
        "Oriulu"
    ],
    "name:spa_x_preferred":[
        "Oriolo"
    ],
    "name:srp_x_preferred":[
        "\u041e\u0440\u0438\u043e\u043b\u043e"
    ],
    "name:ukr_x_preferred":[
        "\u041e\u0440\u0456\u043e\u043b\u043e"
    ],
    "name:uzb_x_preferred":[
        "Oriolo"
    ],
    "name:vol_x_preferred":[
        "Oriolo"
    ],
    "name:war_x_preferred":[
        "Oriolo"
    ],
    "name:zho_x_preferred":[
        "\u5965\u5ed6\u6d1b"
    ],
    "wof:name":"Oriolo",
    "wof:placetype":"locality"
},
  "geometry": {"coordinates":[11.61667,44.21667],"type":"Point"}
}