{
  "type": "Feature",
  "properties": {
    "gn:admin1_code":"16.0",
    "gn:admin2_code":"MS",
    "gn:admin3_code":"45007.0",
    "gn:asciiname":"Molina di Equi Terme",
    "gn:country_code":"IT",
    "gn:dem":252,
    "gn:feature_class":"P",
    "gn:feature_code":"PPL",
    "gn:name":"Molina di Equi Terme",
    "gn:population":82,
    "gn:timezone":"Europe/Rome",
    "iso:country":"IT",
    "wof:name":"Molina di Equi Terme",
    "wof:placetype":"locality",
    "wof:population":82
},
  "geometry": {"coordinates":[10.14449,44.16891],"type":"Point"}
}