{
  "type": "Feature",
  "properties": {
    "gn:admin1_code":"17.0",
    "gn:admin2_code":"BZ",
    "gn:admin3_code":"21046.0",
    "gn:asciiname":"Tarces",
    "gn:country_code":"IT",
    "gn:dem":1028,
    "gn:elevation":"1030.0",
    "gn:feature_class":"P",
    "gn:feature_code":"PPL",
    "gn:name":"Tarces",
    "gn:population":406,
    "gn:timezone":"Europe/Rome",
    "iso:country":"IT",
    "wof:name":"Tarces",
    "wof:placetype":"locality",
    "wof:population":406
},
  "geometry": {"coordinates":[10.56018,46.68151],"type":"Point"}
}