{
  "type": "Feature",
  "properties": {
    "gn:admin1_code":"17.0",
    "gn:admin2_code":"TN",
    "gn:admin3_code":"22007.0",
    "gn:asciiname":"Vo Sinistro",
    "gn:cc2":"IT",
    "gn:country_code":"IT",
    "gn:dem":129,
    "gn:feature_class":"P",
    "gn:feature_code":"PPL",
    "gn:name":"Vo Sinistro",
    "gn:population":0,
    "gn:timezone":"Europe/Rome",
    "iso:country":"IT",
    "name:und_x_variant":[
        "Vo",
        "Vo Sinistro"
    ],
    "wof:name":"Vo Sinistro",
    "wof:placetype":"locality"
},
  "geometry": {"coordinates":[10.95,45.73333],"type":"Point"}
}