{
  "type": "Feature",
  "properties": {
    "gn:admin1_code":"8",
    "gn:admin2_code":"GE",
    "gn:admin3_code":"10056.0",
    "gn:asciiname":"Costapelata",
    "gn:country_code":"IT",
    "gn:dem":1059,
    "gn:feature_class":"P",
    "gn:feature_code":"PPL",
    "gn:name":"Costapelata",
    "gn:population":27,
    "gn:timezone":"Europe/Rome",
    "iso:country":"IT",
    "wof:name":"Costapelata",
    "wof:placetype":"locality",
    "wof:population":27
},
  "geometry": {"coordinates":[9.45783,44.52994],"type":"Point"}
}