{
  "type": "Feature",
  "properties": {
    "gn:admin1_code":"1",
    "gn:admin2_code":"CH",
    "gn:admin3_code":"69008.0",
    "gn:asciiname":"Cervinelli",
    "gn:country_code":"IT",
    "gn:dem":304,
    "gn:feature_class":"P",
    "gn:feature_code":"PPL",
    "gn:name":"Cervinelli",
    "gn:population":19,
    "gn:timezone":"Europe/Rome",
    "iso:country":"IT",
    "wof:name":"Cervinelli",
    "wof:placetype":"locality",
    "wof:population":19
},
  "geometry": {"coordinates":[14.18393,42.27776],"type":"Point"}
}