{
  "type": "Feature",
  "properties": {
    "gn:admin1_code":"9.0",
    "gn:admin2_code":"CO",
    "gn:admin3_code":"13131.0",
    "gn:asciiname":"Ex Cifa",
    "gn:country_code":"IT",
    "gn:dem":269,
    "gn:feature_class":"P",
    "gn:feature_code":"PPLL",
    "gn:name":"Ex Cifa",
    "gn:population":0,
    "gn:timezone":"Europe/Rome",
    "iso:country":"IT",
    "wof:name":"Ex Cifa",
    "wof:placetype":"locality"
},
  "geometry": {"coordinates":[8.91833,45.68213],"type":"Point"}
}