{
  "type": "Feature",
  "properties": {
    "gn:admin1_code":"7",
    "gn:admin2_code":"FR",
    "gn:admin3_code":"60053.0",
    "gn:asciiname":"Castellano",
    "gn:country_code":"IT",
    "gn:dem":690,
    "gn:feature_class":"P",
    "gn:feature_code":"PPL",
    "gn:name":"Castellano",
    "gn:population":60,
    "gn:timezone":"Europe/Rome",
    "iso:country":"IT",
    "name:ceb_x_preferred":[
        "Castellano"
    ],
    "name:deu_x_preferred":[
        "Castellano"
    ],
    "name:fra_x_preferred":[
        "Castellano"
    ],
    "name:ita_x_preferred":[
        "Castellano"
    ],
    "name:nld_x_preferred":[
        "Castellano"
    ],
    "name:pol_x_preferred":[
        "Castellano"
    ],
    "name:rus_x_preferred":[
        "\u041a\u0430\u0441\u0442\u0435\u043b\u043b\u0430\u043d\u043e"
    ],
    "name:spa_x_preferred":[
        "Castellano"
    ],
    "name:srp_x_preferred":[
        "Kastelano"
    ],
    "name:swe_x_preferred":[
        "Castellano"
    ],
    "wof:name":"Castellano",
    "wof:placetype":"locality",
    "wof:population":60
},
  "geometry": {"coordinates":[13.13325,41.83202],"type":"Point"}
}