{
  "type": "Feature",
  "properties": {
    "gn:admin1_code":"7",
    "gn:admin2_code":"FR",
    "gn:admin3_code":"60053.0",
    "gn:asciiname":"Castellano",
    "gn:country_code":"IT",
    "gn:dem":690,
    "gn:feature_class":"P",
    "gn:feature_code":"PPL",
    "gn:name":"Castellano",
    "gn:population":60,
    "gn:timezone":"Europe/Rome",
    "iso:country":"IT",
    "wof:name":"Castellano",
    "wof:placetype":"locality",
    "wof:population":60
},
  "geometry": {"coordinates":[13.13325,41.83202],"type":"Point"}
}