{
  "type": "Feature",
  "properties": {
    "gn:admin1_code":"4",
    "gn:admin2_code":"AV",
    "gn:admin3_code":"64020.0",
    "gn:asciiname":"Mainardo",
    "gn:country_code":"IT",
    "gn:dem":741,
    "gn:feature_class":"P",
    "gn:feature_code":"PPL",
    "gn:name":"Mainardo",
    "gn:population":35,
    "gn:timezone":"Europe/Rome",
    "iso:country":"IT",
    "wof:name":"Mainardo",
    "wof:placetype":"locality",
    "wof:population":35
},
  "geometry": {"coordinates":[15.00221,41.24552],"type":"Point"}
}