{
  "type": "Feature",
  "properties": {
    "gn:admin1_code":"9",
    "gn:admin2_code":"CR",
    "gn:admin3_code":"19032.0",
    "gn:asciiname":"Cascina Cantonata",
    "gn:country_code":"IT",
    "gn:dem":56,
    "gn:feature_class":"P",
    "gn:feature_code":"PPL",
    "gn:name":"Cascina Cantonata",
    "gn:population":39,
    "gn:timezone":"Europe/Rome",
    "iso:country":"IT",
    "wof:name":"Cascina Cantonata",
    "wof:placetype":"locality",
    "wof:population":39
},
  "geometry": {"coordinates":[10.02046,45.26317],"type":"Point"}
}