{
  "type": "Feature",
  "properties": {
    "gn:admin1_code":"4",
    "gn:admin2_code":"AV",
    "gn:admin3_code":"64015.0",
    "gn:asciiname":"Isca",
    "gn:country_code":"IT",
    "gn:dem":357,
    "gn:feature_class":"P",
    "gn:feature_code":"PPL",
    "gn:name":"Isca",
    "gn:population":28,
    "gn:timezone":"Europe/Rome",
    "iso:country":"IT",
    "wof:name":"Isca",
    "wof:placetype":"locality",
    "wof:population":28
},
  "geometry": {"coordinates":[15.43897,40.88569],"type":"Point"}
}