{
  "type": "Feature",
  "properties": {
    "gn:admin1_code":"1",
    "gn:admin2_code":"CH",
    "gn:admin3_code":"69066.0",
    "gn:asciiname":"Colavi",
    "gn:country_code":"IT",
    "gn:dem":1019,
    "gn:feature_class":"P",
    "gn:feature_code":"PPL",
    "gn:name":"Colavi",
    "gn:population":23,
    "gn:timezone":"Europe/Rome",
    "iso:country":"IT",
    "wof:name":"Colavi",
    "wof:placetype":"locality",
    "wof:population":23
},
  "geometry": {"coordinates":[14.24044,41.94914],"type":"Point"}
}