{
  "type": "Feature",
  "properties": {
    "gn:admin1_code":"12.0",
    "gn:admin2_code":"AT",
    "gn:admin3_code":"5118.0",
    "gn:asciiname":"Casetto",
    "gn:country_code":"IT",
    "gn:dem":259,
    "gn:feature_class":"P",
    "gn:feature_code":"PPLL",
    "gn:name":"Casetto",
    "gn:population":0,
    "gn:timezone":"Europe/Rome",
    "iso:country":"IT",
    "wof:name":"Casetto",
    "wof:placetype":"locality"
},
  "geometry": {"coordinates":[7.92954,44.96497],"type":"Point"}
}