{
  "type": "Feature",
  "properties": {
    "gn:gn_country":"IT",
    "gn:gn_fcode":"PPLA3",
    "gn:gn_pop":908,
    "gn:population":593,
    "iso:country":"IT",
    "name:bel_x_preferred":[
        "\u0420\u043e\u0434\u044d\u043b\u0430"
    ],
    "name:bul_x_preferred":[
        "\u0420\u043e\u0434\u0435\u043b\u043e"
    ],
    "name:cat_x_preferred":[
        "Rodello"
    ],
    "name:deu_x_preferred":[
        "Rodello"
    ],
    "name:eng_x_preferred":[
        "Rodello"
    ],
    "name:epo_x_preferred":[
        "Rodello"
    ],
    "name:est_x_preferred":[
        "Rodello"
    ],
    "name:eus_x_preferred":[
        "Rodello"
    ],
    "name:fas_x_preferred":[
        "\u0631\u0648\u062f\u0644\u0648"
    ],
    "name:fra_x_preferred":[
        "Rodello"
    ],
    "name:hun_x_preferred":[
        "Rodello"
    ],
    "name:hye_x_preferred":[
        "\u054c\u0578\u0564\u0565\u056c\u056c\u0578"
    ],
    "name:ind_x_preferred":[
        "Rodello"
    ],
    "name:ita_x_preferred":[
        "Rodello"
    ],
    "name:jpn_x_preferred":[
        "\u30ed\u30c7\u30c3\u30ed"
    ],
    "name:kaz_x_preferred":[
        "\u0420\u043e\u0434\u0435\u043b\u043b\u043e"
    ],
    "name:lat_x_preferred":[
        "Rodellum"
    ],
    "name:lmo_x_preferred":[
        "Rodello"
    ],
    "name:msa_x_preferred":[
        "Rodello"
    ],
    "name:nan_x_preferred":[
        "Rodello"
    ],
    "name:nap_x_preferred":[
        "Rodello"
    ],
    "name:nld_x_preferred":[
        "Rodello"
    ],
    "name:oci_x_preferred":[
        "Rodello"
    ],
    "name:pms_x_preferred":[
        "Rodel"
    ],
    "name:pol_x_preferred":[
        "Rodello"
    ],
    "name:por_x_preferred":[
        "Rodello"
    ],
    "name:ron_x_preferred":[
        "Rodello"
    ],
    "name:rus_x_preferred":[
        "\u0420\u043e\u0434\u0435\u043b\u043b\u043e"
    ],
    "name:scn_x_preferred":[
        "Rodello"
    ],
    "name:spa_x_preferred":[
        "Rodello"
    ],
    "name:srp_x_preferred":[
        "Rodello"
    ],
    "name:tgl_x_preferred":[
        "Rodello"
    ],
    "name:ukr_x_preferred":[
        "\u0420\u043e\u0434\u0435\u043b\u043b\u043e"
    ],
    "name:uzb_x_preferred":[
        "Rodello"
    ],
    "name:vie_x_preferred":[
        "Rodello"
    ],
    "name:vol_x_preferred":[
        "Rodello"
    ],
    "name:war_x_preferred":[
        "Rodello"
    ],
    "name:zho_x_preferred":[
        "\u7f57\u5fb7\u6d1b"
    ],
    "qs_pg:aaroncc":"IT",
    "qs_pg:gn_country":"IT",
    "qs_pg:gn_fcode":"PPLA3",
    "qs_pg:gn_pop":908,
    "qs_pg:name":"Rodello",
    "qs_pg:name_adm0":"Italia",
    "qs_pg:name_adm1":"Piemonte",
    "qs_pg:photos_9k":1,
    "qs_pg:photos_9r":4,
    "qs_pg:photos_all":185,
    "qs_pg:photos_sr":0,
    "qs_pg:pop_sr":2,
    "qs_pg:qs_pg_placetype":"locality",
    "qs_pg:qs_pg_placetype_gp":"Town",
    "qs_pg:woe_adm0":23424853,
    "woe:adm0_id":23424853,
    "woe:name_adm0":"Italia",
    "woe:name_adm1":"Piemonte",
    "woe:placetype":"Town",
    "wof:name":"Rodello",
    "wof:placetype":"locality",
    "wof:population":593
},
  "geometry": {"coordinates":[8.05684,44.62854],"type":"Point"}
}