{
  "type": "Feature",
  "properties": {
    "gn:admin1_code":"12",
    "gn:admin2_code":"AL",
    "gn:admin3_code":"6048.0",
    "gn:asciiname":"Bricco",
    "gn:country_code":"IT",
    "gn:dem":433,
    "gn:feature_class":"P",
    "gn:feature_code":"PPL",
    "gn:name":"Bricco",
    "gn:population":19,
    "gn:timezone":"Europe/Rome",
    "iso:country":"IT",
    "wof:name":"Bricco",
    "wof:placetype":"locality",
    "wof:population":19
},
  "geometry": {"coordinates":[8.38145,44.64005],"type":"Point"}
}