{
  "type": "Feature",
  "properties": {
    "gn:admin1_code":"3",
    "gn:admin2_code":"CS",
    "gn:admin3_code":"78043.0",
    "gn:asciiname":"Carrano",
    "gn:country_code":"IT",
    "gn:dem":856,
    "gn:feature_class":"P",
    "gn:feature_code":"PPL",
    "gn:name":"Carrano",
    "gn:population":71,
    "gn:timezone":"Europe/Rome",
    "iso:country":"IT",
    "wof:name":"Carrano",
    "wof:placetype":"locality",
    "wof:population":71
},
  "geometry": {"coordinates":[16.36621,39.12308],"type":"Point"}
}