{
  "type": "Feature",
  "properties": {
    "gn:admin1_code":"5",
    "gn:admin2_code":"RE",
    "gn:admin3_code":"35045.0",
    "gn:asciiname":"Case Bondi",
    "gn:country_code":"IT",
    "gn:dem":763,
    "gn:feature_class":"P",
    "gn:feature_code":"PPL",
    "gn:name":"Case Bondi",
    "gn:population":32,
    "gn:timezone":"Europe/Rome",
    "iso:country":"IT",
    "wof:name":"Case Bondi",
    "wof:placetype":"locality",
    "wof:population":32
},
  "geometry": {"coordinates":[10.50608,44.3282],"type":"Point"}
}