{
  "type": "Feature",
  "properties": {
    "gn:admin1_code":"5.0",
    "gn:admin2_code":"FE",
    "gn:admin3_code":"38010.0",
    "gn:asciiname":"Ferrara",
    "gn:country_code":"IT",
    "gn:dem":-5,
    "gn:feature_class":"P",
    "gn:feature_code":"PPL",
    "gn:name":"Ferrara",
    "gn:population":43,
    "gn:timezone":"Europe/Rome",
    "iso:country":"IT",
    "wof:name":"Ferrara",
    "wof:placetype":"locality",
    "wof:population":43
},
  "geometry": {"coordinates":[12.00472,44.90343],"type":"Point"}
}