{
  "type": "Feature",
  "properties": {
    "gn:admin1_code":"16",
    "gn:admin2_code":"FI",
    "gn:admin3_code":"48019.0",
    "gn:asciiname":"San Bartolomeo",
    "gn:country_code":"IT",
    "gn:dem":19,
    "gn:feature_class":"P",
    "gn:feature_code":"PPL",
    "gn:name":"San Bartolomeo",
    "gn:population":25,
    "gn:timezone":"Europe/Rome",
    "iso:country":"IT",
    "wof:name":"San Bartolomeo",
    "wof:placetype":"locality",
    "wof:population":25
},
  "geometry": {"coordinates":[10.80437,43.70435],"type":"Point"}
}