{
  "type": "Feature",
  "properties": {
    "gn:admin1_code":"20",
    "gn:admin2_code":"TV",
    "gn:admin3_code":"26030.0",
    "gn:asciiname":"Case Martorel",
    "gn:country_code":"IT",
    "gn:dem":185,
    "gn:feature_class":"P",
    "gn:feature_code":"PPL",
    "gn:name":"Case Martorel",
    "gn:population":33,
    "gn:timezone":"Europe/Rome",
    "iso:country":"IT",
    "wof:name":"Case Martorel",
    "wof:placetype":"locality",
    "wof:population":33
},
  "geometry": {"coordinates":[12.35634,45.99817],"type":"Point"}
}