{
  "type": "Feature",
  "properties": {
    "gn:admin1_code":"17",
    "gn:admin2_code":"TN",
    "gn:admin3_code":"22104.0",
    "gn:asciiname":"Campiello",
    "gn:country_code":"IT",
    "gn:dem":478,
    "gn:feature_class":"P",
    "gn:feature_code":"PPL",
    "gn:name":"Campiello",
    "gn:population":120,
    "gn:timezone":"Europe/Rome",
    "iso:country":"IT",
    "wof:name":"Campiello",
    "wof:placetype":"locality",
    "wof:population":120
},
  "geometry": {"coordinates":[11.35411,46.02056],"type":"Point"}
}