{
  "type": "Feature",
  "properties": {
    "gn:admin1_code":"20",
    "gn:admin2_code":"PD",
    "gn:admin3_code":"28021.0",
    "gn:asciiname":"Menegazzo",
    "gn:country_code":"IT",
    "gn:dem":0,
    "gn:feature_class":"P",
    "gn:feature_code":"PPL",
    "gn:name":"Menegazzo",
    "gn:population":13,
    "gn:timezone":"Europe/Rome",
    "iso:country":"IT",
    "wof:name":"Menegazzo",
    "wof:placetype":"locality",
    "wof:population":13
},
  "geometry": {"coordinates":[12.00109,45.22754000000001],"type":"Point"}
}