{
  "type": "Feature",
  "properties": {
    "gn:country":"IT",
    "gn:fcode":"PPL",
    "gn:population":0,
    "iso:country":"IT",
    "name:bul_x_preferred":[
        "\u0411\u0443\u0440\u0438\u0430\u043d\u043e"
    ],
    "name:ceb_x_preferred":[
        "Buriano"
    ],
    "name:deu_x_preferred":[
        "Buriano"
    ],
    "name:eng_x_preferred":[
        "Buriano"
    ],
    "name:fra_x_preferred":[
        "Buriano"
    ],
    "name:hun_x_preferred":[
        "Buriano"
    ],
    "name:ita_x_preferred":[
        "Buriano"
    ],
    "name:nld_x_preferred":[
        "Buriano"
    ],
    "name:spa_x_preferred":[
        "Buriano"
    ],
    "name:srp_x_preferred":[
        "Buriano"
    ],
    "name:srp_x_variant":[
        "\u0411\u0443\u0440\u0438\u0458\u0430\u043d\u043e"
    ],
    "qs_pg:aaroncc":"IT",
    "qs_pg:gn_country":"IT",
    "qs_pg:gn_fcode":"PPL",
    "qs_pg:gn_pop":0,
    "qs_pg:name":"Buriano",
    "qs_pg:name_adm0":"Italia",
    "qs_pg:name_adm1":"Toscana",
    "qs_pg:photos":84,
    "qs_pg:photos_1k":17,
    "qs_pg:photos_9k":1,
    "qs_pg:photos_9r":3,
    "qs_pg:photos_all":84,
    "qs_pg:photos_sr":3,
    "qs_pg:pop_sr":0,
    "qs_pg:qs_pg_placetype":"locality",
    "qs_pg:qs_pg_placetype_gp":"Town",
    "qs_pg:woe_adm0":23424853,
    "woe:adm0_id":23424853,
    "woe:name_adm0":"Italia",
    "woe:name_adm1":"Toscana",
    "woe:placetype":"Town",
    "wof:name":"Buriano",
    "wof:placetype":"locality",
    "wof:population":257
},
  "geometry": {"coordinates":[10.98333,42.83333],"type":"Point"}
}