{
  "type": "Feature",
  "properties": {
    "gn:admin1_code":"3.0",
    "gn:admin2_code":"CS",
    "gn:admin3_code":"78108.0",
    "gn:asciiname":"Casello Martucci",
    "gn:cc2":"IT",
    "gn:country_code":"IT",
    "gn:dem":8,
    "gn:feature_class":"P",
    "gn:feature_code":"PPL",
    "gn:name":"Casello Martucci",
    "gn:population":0,
    "gn:timezone":"Europe/Rome",
    "iso:country":"IT",
    "name:und_x_variant":[
        "Conzo Martucci",
        "Casello Martucci"
    ],
    "wof:name":"Casello Martucci",
    "wof:placetype":"locality"
},
  "geometry": {"coordinates":[16.68333,39.61667],"type":"Point"}
}