{
  "type": "Feature",
  "properties": {
    "gn:admin1_code":"3",
    "gn:admin2_code":"CZ",
    "gn:admin3_code":"79029.0",
    "gn:asciiname":"Clemenze",
    "gn:country_code":"IT",
    "gn:dem":544,
    "gn:feature_class":"P",
    "gn:feature_code":"PPL",
    "gn:name":"Clemenze",
    "gn:population":104,
    "gn:timezone":"Europe/Rome",
    "iso:country":"IT",
    "wof:name":"Clemenze",
    "wof:placetype":"locality",
    "wof:population":104
},
  "geometry": {"coordinates":[16.38368,38.67865],"type":"Point"}
}