{
  "type": "Feature",
  "properties": {
    "gn:admin1_code":"20",
    "gn:admin2_code":"VE",
    "gn:admin3_code":"27019.0",
    "gn:asciiname":"Ca' Zottino",
    "gn:country_code":"IT",
    "gn:dem":-1,
    "gn:feature_class":"P",
    "gn:feature_code":"PPL",
    "gn:name":"Ca' Zottino",
    "gn:population":51,
    "gn:timezone":"Europe/Rome",
    "iso:country":"IT",
    "wof:name":"Ca' Zottino",
    "wof:placetype":"locality",
    "wof:population":51
},
  "geometry": {"coordinates":[12.63239,45.55046],"type":"Point"}
}