{
  "type": "Feature",
  "properties": {
    "gn:admin1_code":"10",
    "gn:admin2_code":"AP",
    "gn:admin3_code":"44038.0",
    "gn:asciiname":"Astorara",
    "gn:country_code":"IT",
    "gn:dem":997,
    "gn:feature_class":"P",
    "gn:feature_code":"PPL",
    "gn:name":"Astorara",
    "gn:population":19,
    "gn:timezone":"Europe/Rome",
    "iso:country":"IT",
    "wof:name":"Astorara",
    "wof:placetype":"locality",
    "wof:population":19
},
  "geometry": {"coordinates":[13.31174,42.83744],"type":"Point"}
}