{
  "type": "Feature",
  "properties": {
    "gn:admin1_code":"8",
    "gn:admin2_code":"GE",
    "gn:admin3_code":"10019.0",
    "gn:asciiname":"Canevale",
    "gn:country_code":"IT",
    "gn:dem":307,
    "gn:feature_class":"P",
    "gn:feature_code":"PPL",
    "gn:name":"Canevale",
    "gn:population":27,
    "gn:timezone":"Europe/Rome",
    "iso:country":"IT",
    "wof:name":"Canevale",
    "wof:placetype":"locality",
    "wof:population":27
},
  "geometry": {"coordinates":[9.26893,44.3788],"type":"Point"}
}