{
  "type": "Feature",
  "properties": {
    "gn:admin1_code":"15.0",
    "gn:admin2_code":"SR",
    "gn:admin3_code":"89013.0",
    "gn:asciiname":"Casale Savarino",
    "gn:country_code":"IT",
    "gn:dem":70,
    "gn:feature_class":"P",
    "gn:feature_code":"PPL",
    "gn:name":"Casale Savarino",
    "gn:population":0,
    "gn:timezone":"Europe/Rome",
    "iso:country":"IT",
    "wof:name":"Casale Savarino",
    "wof:placetype":"locality"
},
  "geometry": {"coordinates":[14.98333,36.81667],"type":"Point"}
}