{
  "type": "Feature",
  "properties": {
    "gn:admin1_code":"17",
    "gn:admin2_code":"TN",
    "gn:admin3_code":"22177.0",
    "gn:asciiname":"Slosseri",
    "gn:country_code":"IT",
    "gn:dem":1132,
    "gn:feature_class":"P",
    "gn:feature_code":"PPL",
    "gn:name":"Slosseri",
    "gn:population":14,
    "gn:timezone":"Europe/Rome",
    "iso:country":"IT",
    "wof:name":"Slosseri",
    "wof:placetype":"locality",
    "wof:population":14
},
  "geometry": {"coordinates":[11.32477,46.20545],"type":"Point"}
}