{
  "type": "Feature",
  "properties": {
    "gn:admin1_code":"9.0",
    "gn:admin2_code":"BG",
    "gn:admin3_code":"16086.0",
    "gn:asciiname":"Molino",
    "gn:country_code":"IT",
    "gn:dem":309,
    "gn:feature_class":"P",
    "gn:feature_code":"PPL",
    "gn:name":"Molino",
    "gn:population":16,
    "gn:timezone":"Europe/Rome",
    "iso:country":"IT",
    "name:ceb_x_preferred":[
        "Molino"
    ],
    "name:deu_x_preferred":[
        "Molino"
    ],
    "name:epo_x_preferred":[
        "Molino"
    ],
    "name:fra_x_preferred":[
        "Molino"
    ],
    "name:ita_x_preferred":[
        "Molino"
    ],
    "name:por_x_preferred":[
        "Molino"
    ],
    "name:spa_x_preferred":[
        "Molino"
    ],
    "name:srp_x_preferred":[
        "Molino"
    ],
    "name:swe_x_preferred":[
        "Molino"
    ],
    "name:tgl_x_preferred":[
        "Molino"
    ],
    "wof:name":"Molino",
    "wof:placetype":"locality",
    "wof:population":16
},
  "geometry": {"coordinates":[10.08806,45.83262],"type":"Point"}
}