{
  "type": "Feature",
  "properties": {
    "gn:admin1_code":"17",
    "gn:admin2_code":"TN",
    "gn:admin3_code":"22113.0",
    "gn:asciiname":"Fontanazzo",
    "gn:country_code":"IT",
    "gn:dem":1396,
    "gn:feature_class":"P",
    "gn:feature_code":"PPL",
    "gn:name":"Fontanazzo",
    "gn:population":158,
    "gn:timezone":"Europe/Rome",
    "iso:country":"IT",
    "wof:name":"Fontanazzo",
    "wof:placetype":"locality",
    "wof:population":158
},
  "geometry": {"coordinates":[11.72967,46.47058],"type":"Point"}
}