{
  "type": "Feature",
  "properties": {
    "gn:admin1_code":"20",
    "gn:admin2_code":"BL",
    "gn:admin3_code":"25022.0",
    "gn:asciiname":"Calderal",
    "gn:country_code":"IT",
    "gn:dem":304,
    "gn:feature_class":"P",
    "gn:feature_code":"PPL",
    "gn:name":"Calderal",
    "gn:population":32,
    "gn:timezone":"Europe/Rome",
    "iso:country":"IT",
    "wof:name":"Calderal",
    "wof:placetype":"locality",
    "wof:population":32
},
  "geometry": {"coordinates":[11.80526,46.00806],"type":"Point"}
}