{
  "type": "Feature",
  "properties": {
    "gn:admin1_code":"5",
    "gn:admin2_code":"FC",
    "gn:admin3_code":"40050.0",
    "gn:asciiname":"Ronco dell'Asino",
    "gn:country_code":"IT",
    "gn:dem":1075,
    "gn:feature_class":"P",
    "gn:feature_code":"PPL",
    "gn:name":"Ronco dell'Asino",
    "gn:population":13,
    "gn:timezone":"Europe/Rome",
    "iso:country":"IT",
    "wof:name":"Ronco dell'Asino",
    "wof:placetype":"locality",
    "wof:population":13
},
  "geometry": {"coordinates":[12.0163,43.81256],"type":"Point"}
}