{
  "type": "Feature",
  "properties": {
    "gn:admin1_code":"5",
    "gn:admin2_code":"PR",
    "gn:admin3_code":"34018.0",
    "gn:asciiname":"Vidiana",
    "gn:country_code":"IT",
    "gn:dem":311,
    "gn:feature_class":"P",
    "gn:feature_code":"PPL",
    "gn:name":"Vidiana",
    "gn:population":24,
    "gn:timezone":"Europe/Rome",
    "iso:country":"IT",
    "wof:name":"Vidiana",
    "wof:placetype":"locality",
    "wof:population":24
},
  "geometry": {"coordinates":[10.26407,44.6435],"type":"Point"}
}