{
  "type": "Feature",
  "properties": {
    "gn:admin1_code":"5",
    "gn:admin2_code":"MO",
    "gn:admin3_code":"36045.0",
    "gn:asciiname":"Colombarina",
    "gn:country_code":"IT",
    "gn:dem":75,
    "gn:feature_class":"P",
    "gn:feature_code":"PPL",
    "gn:name":"Colombarina",
    "gn:population":19,
    "gn:timezone":"Europe/Rome",
    "iso:country":"IT",
    "wof:name":"Colombarina",
    "wof:placetype":"locality",
    "wof:population":19
},
  "geometry": {"coordinates":[11.02771,44.5226],"type":"Point"}
}