{
  "type": "Feature",
  "properties": {
    "gn:admin1_code":"5.0",
    "gn:admin2_code":"BO",
    "gn:admin3_code":"37062.0",
    "gn:asciiname":"Corvella",
    "gn:country_code":"IT",
    "gn:dem":413,
    "gn:feature_class":"P",
    "gn:feature_code":"PPL",
    "gn:name":"Corvella",
    "gn:population":0,
    "gn:timezone":"Europe/Rome",
    "iso:country":"IT",
    "wof:name":"Corvella",
    "wof:placetype":"locality"
},
  "geometry": {"coordinates":[10.96667,44.16667],"type":"Point"}
}