{
  "type": "Feature",
  "properties": {
    "gn:admin1_code":"5.0",
    "gn:admin2_code":"BO",
    "gn:admin3_code":"37006.0",
    "gn:admin4_code":"3700612.0",
    "gn:asciiname":"San Vitale di Reno",
    "gn:country_code":"IT",
    "gn:dem":25,
    "gn:feature_class":"P",
    "gn:feature_code":"PPL",
    "gn:name":"San Vitale di Reno",
    "gn:population":0,
    "gn:timezone":"Europe/Rome",
    "iso:country":"IT",
    "wof:name":"San Vitale di Reno",
    "wof:placetype":"locality"
},
  "geometry": {"coordinates":[11.36667,44.55],"type":"Point"}
}