{
  "type": "Feature",
  "properties": {
    "iso:country":"IT",
    "name:eng_x_preferred":[
        "Lampugnano"
    ],
    "name:fra_x_preferred":[
        "Lampugnano"
    ],
    "name:ita_x_preferred":[
        "Lampugnano"
    ],
    "name:lat_x_preferred":[
        "Lampunianum"
    ],
    "name:lmo_x_preferred":[
        "Lampugnan"
    ],
    "name:nld_x_preferred":[
        "Lampugnano"
    ],
    "name:nob_x_preferred":[
        "Lampugnano"
    ],
    "name:urd_x_preferred":[
        "\u0644\u06cc\u0645\u067e\u0648\u06af\u0646\u0627\u0646\u0648"
    ],
    "qs_pg:aaroncc":"IT",
    "qs_pg:name":"Lampugnano",
    "qs_pg:name_adm0":"Italia",
    "qs_pg:name_adm1":"Lombardia",
    "qs_pg:photos":837,
    "qs_pg:photos_1k":170,
    "qs_pg:photos_9k":4,
    "qs_pg:photos_9r":6,
    "qs_pg:photos_all":837,
    "qs_pg:photos_sr":9,
    "qs_pg:pop_sr":0,
    "qs_pg:qs_pg_placetype":"locality",
    "qs_pg:qs_pg_placetype_gp":"Town",
    "qs_pg:woe_adm0":23424853,
    "woe:adm0_id":23424853,
    "woe:name_adm0":"Italia",
    "woe:name_adm1":"Lombardia",
    "woe:placetype":"Town",
    "wof:name":"Lampugnano",
    "wof:placetype":"locality"
},
  "geometry": {"coordinates":[9.145324,45.488027],"type":"Point"}
}