{
  "type": "Feature",
  "properties": {
    "gn:admin1_code":"16",
    "gn:admin2_code":"PO",
    "gn:admin3_code":"100007.0",
    "gn:asciiname":"La Storaia",
    "gn:country_code":"IT",
    "gn:dem":711,
    "gn:feature_class":"P",
    "gn:feature_code":"PPL",
    "gn:name":"La Storaia",
    "gn:population":125,
    "gn:timezone":"Europe/Rome",
    "iso:country":"IT",
    "wof:name":"La Storaia",
    "wof:placetype":"locality",
    "wof:population":125
},
  "geometry": {"coordinates":[11.16231,44.10679],"type":"Point"}
}