{
  "type": "Feature",
  "properties": {
    "gn:admin1_code":"20",
    "gn:admin2_code":"VI",
    "gn:admin3_code":"24034.0",
    "gn:asciiname":"Battilana",
    "gn:country_code":"IT",
    "gn:dem":461,
    "gn:feature_class":"P",
    "gn:feature_code":"PPLL",
    "gn:name":"Battilana",
    "gn:population":8,
    "gn:timezone":"Europe/Rome",
    "iso:country":"IT",
    "wof:name":"Battilana",
    "wof:placetype":"locality",
    "wof:population":8
},
  "geometry": {"coordinates":[11.34507,45.6277],"type":"Point"}
}