{
  "type": "Feature",
  "properties": {
    "gn:admin1_code":"1",
    "gn:admin2_code":"AQ",
    "gn:admin3_code":"66006.0",
    "gn:asciiname":"Faenza",
    "gn:country_code":"IT",
    "gn:dem":653,
    "gn:feature_class":"P",
    "gn:feature_code":"PPL",
    "gn:name":"Faenza",
    "gn:population":17,
    "gn:timezone":"Europe/Rome",
    "iso:country":"IT",
    "wof:name":"Faenza",
    "wof:placetype":"locality",
    "wof:population":17
},
  "geometry": {"coordinates":[13.49192,41.99741],"type":"Point"}
}