{
  "type": "Feature",
  "properties": {
    "gn:admin1_code":"12",
    "gn:admin2_code":"TO",
    "gn:admin3_code":"1070.0",
    "gn:asciiname":"Ruata Ribotta",
    "gn:country_code":"IT",
    "gn:dem":285,
    "gn:feature_class":"P",
    "gn:feature_code":"PPL",
    "gn:name":"Ruata Ribotta",
    "gn:population":19,
    "gn:timezone":"Europe/Rome",
    "iso:country":"IT",
    "wof:name":"Ruata Ribotta",
    "wof:placetype":"locality",
    "wof:population":19
},
  "geometry": {"coordinates":[7.385,44.76775],"type":"Point"}
}