{
  "type": "Feature",
  "properties": {
    "gn:admin1_code":"7",
    "gn:admin2_code":"RI",
    "gn:admin3_code":"57065.0",
    "gn:asciiname":"Collevico",
    "gn:country_code":"IT",
    "gn:dem":222,
    "gn:feature_class":"P",
    "gn:feature_code":"PPL",
    "gn:name":"Collevico",
    "gn:population":58,
    "gn:timezone":"Europe/Rome",
    "iso:country":"IT",
    "wof:name":"Collevico",
    "wof:placetype":"locality",
    "wof:population":58
},
  "geometry": {"coordinates":[12.62718,42.30716],"type":"Point"}
}