{
  "type": "Feature",
  "properties": {
    "gn:admin1_code":"1.0",
    "gn:admin2_code":"CH",
    "gn:admin3_code":"69005.0",
    "gn:asciiname":"Quercianera-Siberia",
    "gn:country_code":"IT",
    "gn:dem":338,
    "gn:feature_class":"P",
    "gn:feature_code":"PPL",
    "gn:name":"Quercianera-Siberia",
    "gn:population":46,
    "gn:timezone":"Europe/Rome",
    "iso:country":"IT",
    "wof:name":"Quercianera-Siberia",
    "wof:placetype":"locality",
    "wof:population":46
},
  "geometry": {"coordinates":[14.50719,42.0531],"type":"Point"}
}