{
  "type": "Feature",
  "properties": {
    "gn:admin1_code":"10.0",
    "gn:admin2_code":"MC",
    "gn:admin3_code":"43038.0",
    "gn:asciiname":"Appennino",
    "gn:country_code":"IT",
    "gn:dem":757,
    "gn:feature_class":"P",
    "gn:feature_code":"PPL",
    "gn:name":"Appennino",
    "gn:population":60,
    "gn:timezone":"Europe/Rome",
    "iso:country":"IT",
    "wof:name":"Appennino",
    "wof:placetype":"locality",
    "wof:population":60
},
  "geometry": {"coordinates":[13.08111,42.97795],"type":"Point"}
}