{
  "type": "Feature",
  "properties": {
    "gn:admin1_code":"16",
    "gn:admin2_code":"AR",
    "gn:admin3_code":"51037.0",
    "gn:asciiname":"Ponte Francese",
    "gn:country_code":"IT",
    "gn:dem":354,
    "gn:feature_class":"P",
    "gn:feature_code":"PPL",
    "gn:name":"Ponte Francese",
    "gn:population":15,
    "gn:timezone":"Europe/Rome",
    "iso:country":"IT",
    "wof:name":"Ponte Francese",
    "wof:placetype":"locality",
    "wof:population":15
},
  "geometry": {"coordinates":[11.94058,43.55279],"type":"Point"}
}