{
  "type": "Feature",
  "properties": {
    "gn:admin1_code":"6.0",
    "gn:admin2_code":"UD",
    "gn:admin3_code":"30107.0",
    "gn:asciiname":"Sauris di Sotto",
    "gn:country_code":"IT",
    "gn:dem":1202,
    "gn:feature_class":"P",
    "gn:feature_code":"PPLA3",
    "gn:name":"Sauris di Sotto",
    "gn:population":161,
    "gn:timezone":"Europe/Rome",
    "iso:country":"IT",
    "name:deu_x_preferred":[
        "Sauris"
    ],
    "name:eng_x_preferred":[
        "Sauris"
    ],
    "name:epo_x_preferred":[
        "Sauris"
    ],
    "name:fra_x_preferred":[
        "Sauris"
    ],
    "name:fur_x_preferred":[
        "Sauris"
    ],
    "name:ita_x_preferred":[
        "Sauris"
    ],
    "name:nap_x_preferred":[
        "Sauris"
    ],
    "name:nld_x_preferred":[
        "Sauris"
    ],
    "name:pol_x_preferred":[
        "Sauris"
    ],
    "name:por_x_preferred":[
        "Sauris"
    ],
    "name:und_x_variant":[
        "Zahre"
    ],
    "wof:name":"Sauris di Sotto",
    "wof:placetype":"locality",
    "wof:population":161
},
  "geometry": {"coordinates":[12.70852,46.46624],"type":"Point"}
}