{
  "type": "Feature",
  "properties": {
    "gn:admin1_code":"1",
    "gn:admin2_code":"CH",
    "gn:admin3_code":"69004.0",
    "gn:asciiname":"San Romano",
    "gn:country_code":"IT",
    "gn:dem":274,
    "gn:feature_class":"P",
    "gn:feature_code":"PPL",
    "gn:name":"San Romano",
    "gn:population":60,
    "gn:timezone":"Europe/Rome",
    "iso:country":"IT",
    "name:ceb_x_preferred":[
        "San Romano"
    ],
    "name:deu_x_preferred":[
        "San Romano"
    ],
    "name:ita_x_preferred":[
        "San Romano"
    ],
    "name:srp_x_preferred":[
        "San Romano"
    ],
    "name:swe_x_preferred":[
        "San Romano"
    ],
    "wof:name":"San Romano",
    "wof:placetype":"locality",
    "wof:population":60
},
  "geometry": {"coordinates":[14.31281,42.27361],"type":"Point"}
}