{
  "type": "Feature",
  "properties": {
    "gn:admin1_code":"12",
    "gn:admin2_code":"TO",
    "gn:admin3_code":"1168.0",
    "gn:asciiname":"Patagna",
    "gn:country_code":"IT",
    "gn:dem":253,
    "gn:feature_class":"P",
    "gn:feature_code":"PPL",
    "gn:name":"Patagna",
    "gn:population":31,
    "gn:timezone":"Europe/Rome",
    "iso:country":"IT",
    "wof:name":"Patagna",
    "wof:placetype":"locality",
    "wof:population":31
},
  "geometry": {"coordinates":[7.54394,44.97003],"type":"Point"}
}