{
  "type": "Feature",
  "properties": {
    "gn:admin1_code":"20.0",
    "gn:admin2_code":"VI",
    "gn:admin3_code":"24057.0",
    "gn:asciiname":"Placa",
    "gn:country_code":"IT",
    "gn:dem":138,
    "gn:elevation":"143.0",
    "gn:feature_class":"P",
    "gn:feature_code":"PPL",
    "gn:name":"Placa",
    "gn:population":133,
    "gn:timezone":"Europe/Rome",
    "iso:country":"IT",
    "name:und_x_variant":[
        "Placca",
        "Placa"
    ],
    "wof:name":"Placa",
    "wof:placetype":"locality",
    "wof:population":133
},
  "geometry": {"coordinates":[11.65069,45.77116],"type":"Point"}
}