{
  "type": "Feature",
  "properties": {
    "gn:admin1_code":"3.0",
    "gn:admin2_code":"CZ",
    "gn:admin3_code":"79134.0",
    "gn:asciiname":"Contrada Nero (Ind. Estrattiva)",
    "gn:country_code":"IT",
    "gn:dem":1139,
    "gn:feature_class":"P",
    "gn:feature_code":"PPL",
    "gn:name":"Contrada Nero (Ind. Estrattiva)",
    "gn:population":0,
    "gn:timezone":"Europe/Rome",
    "iso:country":"IT",
    "wof:name":"Contrada Nero (Ind. Estrattiva)",
    "wof:placetype":"locality"
},
  "geometry": {"coordinates":[16.48019,39.10064000000001],"type":"Point"}
}