{
  "type": "Feature",
  "properties": {
    "gn:admin1_code":"18.0",
    "gn:admin2_code":"PG",
    "gn:admin3_code":"54027.0",
    "gn:asciiname":"San Valentino",
    "gn:country_code":"IT",
    "gn:dem":309,
    "gn:elevation":"304.0",
    "gn:feature_class":"P",
    "gn:feature_code":"PPL",
    "gn:name":"San Valentino",
    "gn:population":127,
    "gn:timezone":"Europe/Rome",
    "iso:country":"IT",
    "name:ceb_x_preferred":[
        "San Valentino"
    ],
    "name:ita_x_preferred":[
        "San Valentino"
    ],
    "name:pms_x_preferred":[
        "San Valentino"
    ],
    "name:pol_x_preferred":[
        "\u015awi\u0119ty Walenty"
    ],
    "name:srp_x_preferred":[
        "San Valentino"
    ],
    "name:swe_x_preferred":[
        "San Valentino"
    ],
    "wof:name":"San Valentino",
    "wof:placetype":"locality",
    "wof:population":127
},
  "geometry": {"coordinates":[12.34004,42.97641],"type":"Point"}
}