{
  "type": "Feature",
  "properties": {
    "gn:admin1_code":"18",
    "gn:admin2_code":"PG",
    "gn:admin3_code":"54048.0",
    "gn:asciiname":"Villaggio Casale Ronchetti",
    "gn:country_code":"IT",
    "gn:dem":814,
    "gn:feature_class":"P",
    "gn:feature_code":"PPL",
    "gn:name":"Villaggio Casale Ronchetti",
    "gn:population":179,
    "gn:timezone":"Europe/Rome",
    "iso:country":"IT",
    "wof:name":"Villaggio Casale Ronchetti",
    "wof:placetype":"locality",
    "wof:population":179
},
  "geometry": {"coordinates":[12.8597,42.896],"type":"Point"}
}