{
  "type": "Feature",
  "properties": {
    "gn:admin1_code":"12",
    "gn:admin2_code":"NO",
    "gn:admin3_code":"3082.0",
    "gn:asciiname":"Barquedo",
    "gn:country_code":"IT",
    "gn:dem":386,
    "gn:feature_class":"P",
    "gn:feature_code":"PPLA3",
    "gn:name":"Barquedo",
    "gn:population":139,
    "gn:timezone":"Europe/Rome",
    "iso:country":"IT",
    "wof:name":"Barquedo",
    "wof:placetype":"locality",
    "wof:population":139
},
  "geometry": {"coordinates":[8.4963,45.74283],"type":"Point"}
}