{
  "type": "Feature",
  "properties": {
    "gn:admin1_code":"20",
    "gn:admin2_code":"VR",
    "gn:admin3_code":"23032.0",
    "gn:asciiname":"Valmala",
    "gn:country_code":"IT",
    "gn:dem":25,
    "gn:feature_class":"P",
    "gn:feature_code":"PPL",
    "gn:name":"Valmala",
    "gn:population":32,
    "gn:timezone":"Europe/Rome",
    "iso:country":"IT",
    "wof:name":"Valmala",
    "wof:placetype":"locality",
    "wof:population":32
},
  "geometry": {"coordinates":[10.96142,45.23588],"type":"Point"}
}