{
  "type": "Feature",
  "properties": {
    "gn:admin1_code":"20",
    "gn:admin2_code":"VR",
    "gn:admin3_code":"23032.0",
    "gn:asciiname":"Valmala",
    "gn:country_code":"IT",
    "gn:dem":25,
    "gn:feature_class":"P",
    "gn:feature_code":"PPL",
    "gn:name":"Valmala",
    "gn:population":32,
    "gn:timezone":"Europe/Rome",
    "iso:country":"IT",
    "name:arg_x_preferred":[
        "Valmala"
    ],
    "name:bre_x_preferred":[
        "Valmala"
    ],
    "name:cat_x_preferred":[
        "Valmala"
    ],
    "name:ceb_x_preferred":[
        "Valmala"
    ],
    "name:deu_x_preferred":[
        "Valmala"
    ],
    "name:eus_x_preferred":[
        "Valmala"
    ],
    "name:fra_x_preferred":[
        "Valmala"
    ],
    "name:glg_x_preferred":[
        "Valmala"
    ],
    "name:hun_x_preferred":[
        "Valmala"
    ],
    "name:ita_x_preferred":[
        "Valmala"
    ],
    "name:msa_x_preferred":[
        "Valmala"
    ],
    "name:nld_x_preferred":[
        "Valmala"
    ],
    "name:oci_x_preferred":[
        "Valmala"
    ],
    "name:pol_x_preferred":[
        "Valmala"
    ],
    "name:por_x_preferred":[
        "Valmala"
    ],
    "name:rus_x_preferred":[
        "\u0412\u0430\u043b\u044c\u043c\u0430\u043b\u0430"
    ],
    "name:spa_x_preferred":[
        "Valmala"
    ],
    "name:srp_x_preferred":[
        "Valmala"
    ],
    "name:swe_x_preferred":[
        "Valmala"
    ],
    "name:ukr_x_preferred":[
        "\u0412\u0430\u043b\u044c\u043c\u0430\u043b\u0430"
    ],
    "name:vie_x_preferred":[
        "Valmala"
    ],
    "name:war_x_preferred":[
        "Valmala"
    ],
    "wof:name":"Valmala",
    "wof:placetype":"locality",
    "wof:population":32
},
  "geometry": {"coordinates":[10.96142,45.23588],"type":"Point"}
}