{
  "type": "Feature",
  "properties": {
    "iso:country":"IT",
    "name:eng_x_preferred":[
        "Borzoli"
    ],
    "name:ita_x_preferred":[
        "Borzoli"
    ],
    "name:lij_x_preferred":[
        "Borzoi"
    ],
    "name:nld_x_preferred":[
        "Borzoli"
    ],
    "wof:name":"Borzoli",
    "wof:placetype":"neighbourhood"
},
  "geometry": {"coordinates":[8.86585846989938,44.43490057321232],"type":"Point"}
}