{
  "type": "Feature",
  "properties": {
    "gn:admin1_code":"5.0",
    "gn:admin2_code":"RA",
    "gn:admin3_code":"39008.0",
    "gn:asciiname":"Adriatica",
    "gn:country_code":"IT",
    "gn:dem":1,
    "gn:feature_class":"P",
    "gn:feature_code":"PPLL",
    "gn:name":"Adriatica",
    "gn:population":0,
    "gn:timezone":"Europe/Rome",
    "iso:country":"IT",
    "name:fra_x_preferred":[
        "Adriatica"
    ],
    "name:pol_x_preferred":[
        "Adriatica"
    ],
    "wof:name":"Adriatica",
    "wof:placetype":"locality"
},
  "geometry": {"coordinates":[11.88303,44.57092],"type":"Point"}
}