{
  "type": "Feature",
  "properties": {
    "iso:country":"IT",
    "name:bel_x_preferred":[
        "\u0427\u044d\u043b\u0435-\u0434\u0437\u0456-\u041c\u0430\u043a\u0440\u0430"
    ],
    "name:bul_x_preferred":[
        "\u0427\u0435\u043b\u0435 \u0434\u0438 \u041c\u0430\u043a\u0440\u0430"
    ],
    "name:cat_x_preferred":[
        "C\u00e8las"
    ],
    "name:deu_x_preferred":[
        "Celle di Macra"
    ],
    "name:epo_x_preferred":[
        "Celle di Macra"
    ],
    "name:eus_x_preferred":[
        "Celle di Macra"
    ],
    "name:fas_x_preferred":[
        "\u0686\u0644\u0647 \u062f\u06cc \u0645\u0627\u06a9\u0631\u0627"
    ],
    "name:fra_x_preferred":[
        "Celle di Macra"
    ],
    "name:hun_x_preferred":[
        "Celle di Macra"
    ],
    "name:hye_x_preferred":[
        "\u0549\u0565\u056c\u0565 \u0564\u056b \u0544\u0561\u056f\u0580\u0561"
    ],
    "name:ind_x_preferred":[
        "Celle di Macra"
    ],
    "name:ita_x_preferred":[
        "Celle di Macra"
    ],
    "name:jpn_x_preferred":[
        "\u30c1\u30a7\u30c3\u30ec\u30fb\u30c7\u30a3\u30fb\u30de\u30af\u30e9"
    ],
    "name:kaz_x_preferred":[
        "\u0427\u0435\u043b\u043b\u0435-\u0434\u0438-\u041c\u0430\u043a\u0440\u0430"
    ],
    "name:lat_x_preferred":[
        "Cellae Cuneenses"
    ],
    "name:lmo_x_preferred":[
        "Celle di Macra"
    ],
    "name:msa_x_preferred":[
        "Celle di Macra"
    ],
    "name:nap_x_preferred":[
        "Celle di Macra"
    ],
    "name:nld_x_preferred":[
        "Celle di Macra"
    ],
    "name:oci_x_preferred":[
        "C\u00e8las"
    ],
    "name:pms_x_preferred":[
        "Sele"
    ],
    "name:pol_x_preferred":[
        "Celle di Macra"
    ],
    "name:por_x_preferred":[
        "Celle di Macra"
    ],
    "name:ron_x_preferred":[
        "Celle di Macra"
    ],
    "name:rus_x_preferred":[
        "\u0427\u0435\u043b\u043b\u0435-\u0434\u0438-\u041c\u0430\u043a\u0440\u0430"
    ],
    "name:scn_x_preferred":[
        "Celle di Macra"
    ],
    "name:spa_x_preferred":[
        "Celle di Macra"
    ],
    "name:tgl_x_preferred":[
        "Celle di Macra"
    ],
    "name:ukr_x_preferred":[
        "\u0427\u0435\u043b\u043b\u0435-\u0434\u0456-\u041c\u0430\u043a\u0440\u0430"
    ],
    "name:uzb_x_preferred":[
        "Celle di Macra"
    ],
    "name:vie_x_preferred":[
        "Celle di Macra"
    ],
    "name:vol_x_preferred":[
        "Celle di Macra"
    ],
    "name:war_x_preferred":[
        "Celle di Macra"
    ],
    "name:zho_min_nan_x_preferred":[
        "Celle di Macra"
    ],
    "name:zho_x_preferred":[
        "\u5207\u83b1\u8fea\u9a6c\u514b\u62c9"
    ],
    "qs:a0":"Italia",
    "qs:a1":"*Cuneo",
    "qs:a1r":"0Piemonte",
    "qs:adm0":"Italia",
    "qs:la_lc":"*",
    "qs:level":"locality",
    "qs:loc":"Chiesa di Macra",
    "qs:loc_alt":"Chiesa di Macra",
    "qs:pop":0,
    "qs:type":"buffered point",
    "wd:wordcount":86,
    "wof:name":"Chiesa di Macra",
    "wof:placetype":"locality"
},
  "geometry": {"coordinates":[7.18167,44.483608],"type":"Point"}
}