{
  "type": "Feature",
  "properties": {
    "gn:admin1_code":"20.0",
    "gn:admin2_code":"VI",
    "gn:admin3_code":"24022.0",
    "gn:asciiname":"Campiglia dei Berici",
    "gn:country_code":"IT",
    "gn:dem":15,
    "gn:elevation":"16.0",
    "gn:feature_class":"P",
    "gn:feature_code":"PPLA3",
    "gn:name":"Campiglia dei Berici",
    "gn:population":935,
    "gn:timezone":"Europe/Rome",
    "iso:country":"IT",
    "wof:name":"Campiglia dei Berici",
    "wof:placetype":"locality",
    "wof:population":935
},
  "geometry": {"coordinates":[11.5421,45.33546],"type":"Point"}
}