{
  "type": "Feature",
  "properties": {
    "gn:admin1_code":"20.0",
    "gn:admin2_code":"VI",
    "gn:admin3_code":"24022.0",
    "gn:asciiname":"Campiglia dei Berici",
    "gn:country_code":"IT",
    "gn:dem":15,
    "gn:elevation":"16.0",
    "gn:feature_class":"P",
    "gn:feature_code":"PPLA3",
    "gn:name":"Campiglia dei Berici",
    "gn:population":935,
    "gn:timezone":"Europe/Rome",
    "iso:country":"IT",
    "name:azb_x_preferred":[
        "\u06a9\u0627\u0645\u067e\u06cc\u0644\u06cc\u0627 \u062f\u06cc \u0628\u0631\u06cc\u0686\u06cc"
    ],
    "name:bul_x_preferred":[
        "\u041a\u0430\u043c\u043f\u0438\u043b\u044f \u0434\u0435\u0439 \u0411\u0435\u0440\u0438\u0447\u0438"
    ],
    "name:ceb_x_preferred":[
        "Campiglia dei Berici"
    ],
    "name:deu_x_preferred":[
        "Campiglia dei Berici"
    ],
    "name:epo_x_preferred":[
        "Campiglia dei Berici"
    ],
    "name:eus_x_preferred":[
        "Campiglia dei Berici"
    ],
    "name:fas_x_preferred":[
        "\u06a9\u0627\u0645\u067e\u06cc\u0644\u06cc\u0627 \u062f\u06cc \u0628\u0631\u06cc\u0686\u06cc"
    ],
    "name:fra_x_preferred":[
        "Campiglia dei Berici"
    ],
    "name:hun_x_preferred":[
        "Campiglia dei Berici"
    ],
    "name:hye_x_preferred":[
        "\u053f\u0561\u0574\u057a\u056b\u056c\u056b\u0561 \u0564\u0565 \u0532\u0565\u0580\u056b\u0579\u056b"
    ],
    "name:ita_x_preferred":[
        "Campiglia dei Berici"
    ],
    "name:jpn_x_preferred":[
        "\u30ab\u30f3\u30d4\u30fc\u30ea\u30a2\u30fb\u30c7\u30a4\u30fb\u30d9\u30fc\u30ea\u30c1"
    ],
    "name:kaz_x_preferred":[
        "\u041a\u0430\u043c\u043f\u0438\u043b\u044c\u044f-\u0434\u0435-\u0411\u0435\u0440\u0438\u0447\u0438"
    ],
    "name:lat_x_preferred":[
        "Campilia"
    ],
    "name:lmo_x_preferred":[
        "Campiglia dei Berici"
    ],
    "name:msa_x_preferred":[
        "Campiglia dei Berici"
    ],
    "name:nap_x_preferred":[
        "Campiglia dei Berici"
    ],
    "name:nld_x_preferred":[
        "Campiglia dei Berici"
    ],
    "name:nor_x_preferred":[
        "Campiglia dei Berici"
    ],
    "name:pms_x_preferred":[
        "Campiglia dei Berici"
    ],
    "name:pol_x_preferred":[
        "Campiglia dei Berici"
    ],
    "name:por_x_preferred":[
        "Campiglia dei Berici"
    ],
    "name:ron_x_preferred":[
        "Campiglia dei Berici"
    ],
    "name:rus_x_preferred":[
        "\u041a\u0430\u043c\u043f\u0438\u043b\u044c\u044f-\u0434\u0435-\u0411\u0435\u0440\u0438\u0447\u0438"
    ],
    "name:scn_x_preferred":[
        "Campiglia dei Berici"
    ],
    "name:spa_x_preferred":[
        "Campiglia dei Berici"
    ],
    "name:srp_x_preferred":[
        "\u041a\u0430\u043c\u043f\u0438\u0459\u0430 \u0434\u0435\u0438 \u0411\u0435\u0440\u0438\u0447\u0438"
    ],
    "name:tgl_x_preferred":[
        "Campiglia dei Berici"
    ],
    "name:ukr_x_preferred":[
        "\u041a\u0430\u043c\u043f\u0456\u043b\u044c\u044f-\u0434\u0435\u0439-\u0411\u0435\u0440\u0438\u0447\u0456"
    ],
    "name:uzb_x_preferred":[
        "Campiglia dei Berici"
    ],
    "name:vec_x_preferred":[
        "Campija dei Berici"
    ],
    "name:vie_x_preferred":[
        "Campiglia dei Berici"
    ],
    "name:vol_x_preferred":[
        "Campiglia dei Berici"
    ],
    "name:war_x_preferred":[
        "Campiglia dei Berici"
    ],
    "name:zho_x_preferred":[
        "\u574e\u76ae\u5229\u4e9a\u5fb7\u4f0a\u8d1d\u91cc\u5947"
    ],
    "wof:name":"Campiglia dei Berici",
    "wof:placetype":"locality",
    "wof:population":935
},
  "geometry": {"coordinates":[11.5421,45.33546],"type":"Point"}
}