{
  "type": "Feature",
  "properties": {
    "gn:admin1_code":"5",
    "gn:admin2_code":"RE",
    "gn:admin3_code":"35027.0",
    "gn:asciiname":"Case Gambetti",
    "gn:country_code":"IT",
    "gn:dem":68,
    "gn:feature_class":"P",
    "gn:feature_code":"PPL",
    "gn:name":"Case Gambetti",
    "gn:population":45,
    "gn:timezone":"Europe/Rome",
    "iso:country":"IT",
    "wof:name":"Case Gambetti",
    "wof:placetype":"locality",
    "wof:population":45
},
  "geometry": {"coordinates":[10.47865,44.72141],"type":"Point"}
}