{
  "type": "Feature",
  "properties": {
    "gn:admin1_code":"16",
    "gn:admin2_code":"SI",
    "gn:admin3_code":"52006.0",
    "gn:asciiname":"San Piero",
    "gn:country_code":"IT",
    "gn:dem":266,
    "gn:feature_class":"P",
    "gn:feature_code":"PPL",
    "gn:name":"San Piero",
    "gn:population":140,
    "gn:timezone":"Europe/Rome",
    "iso:country":"IT",
    "wof:name":"San Piero",
    "wof:placetype":"locality",
    "wof:population":140
},
  "geometry": {"coordinates":[11.4381,43.35445],"type":"Point"}
}