{
  "type": "Feature",
  "properties": {
    "gn:admin1_code":"20",
    "gn:admin2_code":"PD",
    "gn:admin3_code":"28063.0",
    "gn:asciiname":"Carturo",
    "gn:country_code":"IT",
    "gn:dem":29,
    "gn:feature_class":"P",
    "gn:feature_code":"PPL",
    "gn:name":"Carturo",
    "gn:population":164,
    "gn:timezone":"Europe/Rome",
    "iso:country":"IT",
    "wof:name":"Carturo",
    "wof:placetype":"locality",
    "wof:population":164
},
  "geometry": {"coordinates":[11.7502,45.58769],"type":"Point"}
}