{
  "type": "Feature",
  "properties": {
    "gn:admin1_code":"5.0",
    "gn:admin2_code":"PC",
    "gn:admin3_code":"33026.0",
    "gn:asciiname":"Costa-Rustigazzo",
    "gn:country_code":"IT",
    "gn:dem":496,
    "gn:feature_class":"P",
    "gn:feature_code":"PPL",
    "gn:name":"Costa-Rustigazzo",
    "gn:population":35,
    "gn:timezone":"Europe/Rome",
    "iso:country":"IT",
    "wof:name":"Costa-Rustigazzo",
    "wof:placetype":"locality",
    "wof:population":35
},
  "geometry": {"coordinates":[9.74972,44.78776],"type":"Point"}
}