{
  "type": "Feature",
  "properties": {
    "gn:admin1_code":"16",
    "gn:admin2_code":"AR",
    "gn:admin3_code":"51001.0",
    "gn:asciiname":"Valialle",
    "gn:country_code":"IT",
    "gn:dem":380,
    "gn:feature_class":"P",
    "gn:feature_code":"PPL",
    "gn:name":"Valialle",
    "gn:population":27,
    "gn:timezone":"Europe/Rome",
    "iso:country":"IT",
    "wof:name":"Valialle",
    "wof:placetype":"locality",
    "wof:population":27
},
  "geometry": {"coordinates":[12.03374,43.52524],"type":"Point"}
}