{
  "type": "Feature",
  "properties": {
    "gn:admin1_code":"13",
    "gn:admin2_code":"LE",
    "gn:admin3_code":"75052.0",
    "gn:asciiname":"Torre Squillace",
    "gn:country_code":"IT",
    "gn:dem":6,
    "gn:feature_class":"P",
    "gn:feature_code":"PPL",
    "gn:name":"Torre Squillace",
    "gn:population":25,
    "gn:timezone":"Europe/Rome",
    "iso:country":"IT",
    "wof:name":"Torre Squillace",
    "wof:placetype":"locality",
    "wof:population":25
},
  "geometry": {"coordinates":[17.91936,40.2333],"type":"Point"}
}