{
  "type": "Feature",
  "properties": {
    "gn:admin1_code":"3",
    "gn:admin2_code":"RC",
    "gn:admin3_code":"80081.0",
    "gn:asciiname":"Badia",
    "gn:country_code":"IT",
    "gn:dem":518,
    "gn:feature_class":"P",
    "gn:feature_code":"PPL",
    "gn:name":"Badia",
    "gn:population":68,
    "gn:timezone":"Europe/Rome",
    "iso:country":"IT",
    "name:cat_x_preferred":[
        "Badia"
    ],
    "name:ceb_x_preferred":[
        "Badia"
    ],
    "name:deu_x_preferred":[
        "Badia"
    ],
    "name:fra_x_preferred":[
        "Badia"
    ],
    "name:ita_x_preferred":[
        "Badia"
    ],
    "name:nld_x_preferred":[
        "Badia"
    ],
    "name:pol_x_preferred":[
        "Badia"
    ],
    "name:por_x_preferred":[
        "Badia"
    ],
    "name:sco_x_preferred":[
        "Badia"
    ],
    "name:slv_x_preferred":[
        "Bad\u00eda"
    ],
    "name:spa_x_preferred":[
        "Bad\u00eda"
    ],
    "name:srp_x_preferred":[
        "Badija"
    ],
    "name:swe_x_preferred":[
        "Badia"
    ],
    "wof:name":"Badia",
    "wof:placetype":"locality",
    "wof:population":68
},
  "geometry": {"coordinates":[15.8384,38.26163],"type":"Point"}
}