{
  "type": "Feature",
  "properties": {
    "gn:admin1_code":"5",
    "gn:admin2_code":"PR",
    "gn:admin3_code":"34039.0",
    "gn:asciiname":"Casalina",
    "gn:country_code":"IT",
    "gn:dem":482,
    "gn:feature_class":"P",
    "gn:feature_code":"PPL",
    "gn:name":"Casalina",
    "gn:population":18,
    "gn:timezone":"Europe/Rome",
    "iso:country":"IT",
    "name:ceb_x_preferred":[
        "Casalina"
    ],
    "name:srp_x_preferred":[
        "\u041a\u0430\u0437\u0430\u043b\u0438\u043d\u0430"
    ],
    "wof:name":"Casalina",
    "wof:placetype":"locality",
    "wof:population":18
},
  "geometry": {"coordinates":[10.199,44.54896],"type":"Point"}
}