{
  "type": "Feature",
  "properties": {
    "gn:admin1_code":"9",
    "gn:admin2_code":"BS",
    "gn:admin3_code":"17198.0",
    "gn:asciiname":"Villaggio Turistico",
    "gn:country_code":"IT",
    "gn:dem":1098,
    "gn:feature_class":"P",
    "gn:feature_code":"PPLL",
    "gn:name":"Villaggio Turistico",
    "gn:population":9,
    "gn:timezone":"Europe/Rome",
    "iso:country":"IT",
    "wof:name":"Villaggio Turistico",
    "wof:placetype":"locality",
    "wof:population":9
},
  "geometry": {"coordinates":[10.4017,46.23286],"type":"Point"}
}