{
  "type": "Feature",
  "properties": {
    "gn:admin1_code":"9.0",
    "gn:admin2_code":"BG",
    "gn:admin3_code":"16246.0",
    "gn:asciiname":"Spino al Brembo",
    "gn:cc2":"IT",
    "gn:country_code":"IT",
    "gn:dem":533,
    "gn:feature_class":"P",
    "gn:feature_code":"PPL",
    "gn:name":"Spino al Brembo",
    "gn:population":0,
    "gn:timezone":"Europe/Rome",
    "iso:country":"IT",
    "name:und_x_variant":[
        "Spino sul Brembo",
        "Spino al Brembo"
    ],
    "wof:name":"Spino al Brembo",
    "wof:placetype":"locality"
},
  "geometry": {"coordinates":[9.66667,45.81667],"type":"Point"}
}