{
  "type": "Feature",
  "properties": {
    "gn:admin1_code":"10",
    "gn:admin2_code":"MC",
    "gn:admin3_code":"43025.0",
    "gn:asciiname":"San Grisogono",
    "gn:country_code":"IT",
    "gn:dem":235,
    "gn:feature_class":"P",
    "gn:feature_code":"PPL",
    "gn:name":"San Grisogono",
    "gn:population":153,
    "gn:timezone":"Europe/Rome",
    "iso:country":"IT",
    "wof:name":"San Grisogono",
    "wof:placetype":"locality",
    "wof:population":153
},
  "geometry": {"coordinates":[13.50267,43.19146],"type":"Point"}
}