{
  "type": "Feature",
  "properties": {
    "gn:admin1_code":"4",
    "gn:admin2_code":"BN",
    "gn:admin3_code":"62039.0",
    "gn:asciiname":"San Tammaro",
    "gn:country_code":"IT",
    "gn:dem":57,
    "gn:feature_class":"P",
    "gn:feature_code":"PPL",
    "gn:name":"San Tammaro",
    "gn:population":97,
    "gn:timezone":"Europe/Rome",
    "iso:country":"IT",
    "wof:name":"San Tammaro",
    "wof:placetype":"locality",
    "wof:population":97
},
  "geometry": {"coordinates":[14.48021,41.18051],"type":"Point"}
}