{
  "type": "Feature",
  "properties": {
    "gn:admin1_code":"4",
    "gn:admin2_code":"BN",
    "gn:admin3_code":"62039.0",
    "gn:asciiname":"San Tammaro",
    "gn:country_code":"IT",
    "gn:dem":57,
    "gn:feature_class":"P",
    "gn:feature_code":"PPL",
    "gn:name":"San Tammaro",
    "gn:population":97,
    "gn:timezone":"Europe/Rome",
    "iso:country":"IT",
    "name:azb_x_preferred":[
        "\u0633\u0646 \u062a\u0627\u0645\u0627\u0631\u0648"
    ],
    "name:bul_x_preferred":[
        "\u0421\u0430\u043d \u0422\u0430\u043c\u0430\u0440\u043e"
    ],
    "name:ceb_x_preferred":[
        "San Tammaro"
    ],
    "name:deu_x_preferred":[
        "San Tammaro"
    ],
    "name:epo_x_preferred":[
        "San Tammaro"
    ],
    "name:eus_x_preferred":[
        "San Tammaro"
    ],
    "name:fas_x_preferred":[
        "\u0633\u0646 \u062a\u0627\u0645\u0627\u0631\u0648"
    ],
    "name:fra_x_preferred":[
        "San Tammaro"
    ],
    "name:hun_x_preferred":[
        "San Tammaro"
    ],
    "name:hye_x_preferred":[
        "\u054d\u0561\u0576 \u054f\u0561\u0574\u0561\u0580\u0578"
    ],
    "name:ina_x_preferred":[
        "San Tammaro"
    ],
    "name:ita_x_preferred":[
        "San Tammaro"
    ],
    "name:jpn_x_preferred":[
        "\u30b5\u30f3\u30fb\u30bf\u30f3\u30de\u30ed"
    ],
    "name:kaz_x_preferred":[
        "\u0421\u0430\u043d-\u0422\u0430\u043c\u043c\u0430\u0440\u043e"
    ],
    "name:kor_x_preferred":[
        "\uc0b0\ud0d0\ub9c8\ub85c"
    ],
    "name:lat_x_preferred":[
        "Fanum Sancti Tammari"
    ],
    "name:lmo_x_preferred":[
        "San Tammaro"
    ],
    "name:mkd_x_preferred":[
        "\u0421\u0430\u043d \u0422\u0430\u043c\u0430\u0440\u043e"
    ],
    "name:msa_x_preferred":[
        "San Tammaro"
    ],
    "name:nap_x_preferred":[
        "San Tammaro"
    ],
    "name:nld_x_preferred":[
        "San Tammaro"
    ],
    "name:pms_x_preferred":[
        "San Tammaro"
    ],
    "name:pol_x_preferred":[
        "San Tammaro"
    ],
    "name:por_x_preferred":[
        "San Tammaro"
    ],
    "name:ron_x_preferred":[
        "San Tammaro"
    ],
    "name:rus_x_preferred":[
        "\u0421\u0430\u043d-\u0422\u0430\u043c\u043c\u0430\u0440\u043e"
    ],
    "name:scn_x_preferred":[
        "San Tammaru"
    ],
    "name:spa_x_preferred":[
        "San Tammaro"
    ],
    "name:srp_x_preferred":[
        "\u0421\u0430\u043d \u0422\u0430\u043c\u0430\u0440\u043e"
    ],
    "name:tgl_x_preferred":[
        "San Tammaro"
    ],
    "name:tur_x_preferred":[
        "San Tammaro"
    ],
    "name:ukr_x_preferred":[
        "\u0421\u0430\u043d-\u0422\u0430\u043c\u043c\u0430\u0440\u043e"
    ],
    "name:uzb_x_preferred":[
        "San Tammaro"
    ],
    "name:vec_x_preferred":[
        "San Tammaro"
    ],
    "name:vie_x_preferred":[
        "San Tammaro"
    ],
    "name:vol_x_preferred":[
        "San Tammaro"
    ],
    "name:war_x_preferred":[
        "San Tammaro"
    ],
    "name:zho_x_preferred":[
        "\u5723\u5854\u59c6\u9a6c\u7f57"
    ],
    "wof:name":"San Tammaro",
    "wof:placetype":"locality",
    "wof:population":97
},
  "geometry": {"coordinates":[14.48021,41.18051],"type":"Point"}
}