{
  "type": "Feature",
  "properties": {
    "gn:admin1_code":"1.0",
    "gn:admin2_code":"TE",
    "gn:admin3_code":"67015.0",
    "gn:asciiname":"Zona Industriale Stampalone",
    "gn:country_code":"IT",
    "gn:dem":93,
    "gn:feature_class":"P",
    "gn:feature_code":"PPL",
    "gn:name":"Zona Industriale Stampalone",
    "gn:population":0,
    "gn:timezone":"Europe/Rome",
    "iso:country":"IT",
    "wof:name":"Zona Industriale Stampalone",
    "wof:placetype":"locality"
},
  "geometry": {"coordinates":[13.88939,42.61278],"type":"Point"}
}