{
  "type": "Feature",
  "properties": {
    "gn:admin1_code":"20",
    "gn:admin2_code":"VE",
    "gn:admin3_code":"27037.0",
    "gn:asciiname":"Centrale Olmara",
    "gn:country_code":"IT",
    "gn:dem":11,
    "gn:feature_class":"P",
    "gn:feature_code":"PPL",
    "gn:name":"Centrale Olmara",
    "gn:population":172,
    "gn:timezone":"Europe/Rome",
    "iso:country":"IT",
    "wof:name":"Centrale Olmara",
    "wof:placetype":"locality",
    "wof:population":172
},
  "geometry": {"coordinates":[12.11651,45.55857],"type":"Point"}
}