{
  "type": "Feature",
  "properties": {
    "gn:admin1_code":"9",
    "gn:admin2_code":"BG",
    "gn:admin3_code":"16079.0",
    "gn:asciiname":"Fornasette",
    "gn:country_code":"IT",
    "gn:dem":157,
    "gn:feature_class":"P",
    "gn:feature_code":"PPL",
    "gn:name":"Fornasette",
    "gn:population":44,
    "gn:timezone":"Europe/Rome",
    "iso:country":"IT",
    "wof:name":"Fornasette",
    "wof:placetype":"locality",
    "wof:population":44
},
  "geometry": {"coordinates":[9.73972,45.57598],"type":"Point"}
}