{
  "type": "Feature",
  "properties": {
    "gn:admin1_code":"20",
    "gn:admin2_code":"BL",
    "gn:admin3_code":"25011.0",
    "gn:asciiname":"Fianema",
    "gn:country_code":"IT",
    "gn:dem":362,
    "gn:feature_class":"P",
    "gn:feature_code":"PPL",
    "gn:name":"Fianema",
    "gn:population":158,
    "gn:timezone":"Europe/Rome",
    "iso:country":"IT",
    "wof:name":"Fianema",
    "wof:placetype":"locality",
    "wof:population":158
},
  "geometry": {"coordinates":[11.94184,46.06421],"type":"Point"}
}