{
  "type": "Feature",
  "properties": {
    "gn:admin1_code":"16.0",
    "gn:admin2_code":"SI",
    "gn:admin3_code":"52027.0",
    "gn:asciiname":"Celle sul Rigo",
    "gn:cc2":"IT",
    "gn:country_code":"IT",
    "gn:dem":553,
    "gn:elevation":"598.0",
    "gn:feature_class":"P",
    "gn:feature_code":"PPL",
    "gn:name":"Celle sul Rigo",
    "gn:population":353,
    "gn:timezone":"Europe/Rome",
    "iso:country":"IT",
    "name:und_x_variant":[
        "Celle",
        "Celle sul Rigo"
    ],
    "wof:name":"Celle sul Rigo",
    "wof:placetype":"locality",
    "wof:population":353
},
  "geometry": {"coordinates":[11.82181,42.86268],"type":"Point"}
}