{
  "type": "Feature",
  "properties": {
    "gn:admin1_code":"10",
    "gn:admin2_code":"PU",
    "gn:admin3_code":"41015.0",
    "gn:asciiname":"Montalto Tarugo",
    "gn:country_code":"IT",
    "gn:dem":507,
    "gn:feature_class":"P",
    "gn:feature_code":"PPL",
    "gn:name":"Montalto Tarugo",
    "gn:population":44,
    "gn:timezone":"Europe/Rome",
    "iso:country":"IT",
    "wof:name":"Montalto Tarugo",
    "wof:placetype":"locality",
    "wof:population":44
},
  "geometry": {"coordinates":[12.80567,43.64876],"type":"Point"}
}