{
  "type": "Feature",
  "properties": {
    "gn:admin1_code":"5",
    "gn:admin2_code":"PC",
    "gn:admin3_code":"33003.0",
    "gn:asciiname":"Casa Bianca",
    "gn:country_code":"IT",
    "gn:dem":43,
    "gn:feature_class":"P",
    "gn:feature_code":"PPL",
    "gn:name":"Casa Bianca",
    "gn:population":18,
    "gn:timezone":"Europe/Rome",
    "iso:country":"IT",
    "wof:name":"Casa Bianca",
    "wof:placetype":"locality",
    "wof:population":18
},
  "geometry": {"coordinates":[9.99982,44.97212],"type":"Point"}
}