{
  "type": "Feature",
  "properties": {
    "gn:admin1_code":"5.0",
    "gn:admin2_code":"RA",
    "gn:admin3_code":"39014.0",
    "gn:asciiname":"Massa",
    "gn:country_code":"IT",
    "gn:dem":12,
    "gn:elevation":"16.0",
    "gn:feature_class":"P",
    "gn:feature_code":"PPL",
    "gn:name":"Massa",
    "gn:population":68,
    "gn:timezone":"Europe/Rome",
    "iso:country":"IT",
    "name:ara_x_preferred":[
        "\u0645\u0627\u0633\u0627"
    ],
    "name:azb_x_preferred":[
        "\u0645\u0627\u0633\u0627"
    ],
    "name:bre_x_preferred":[
        "Massa"
    ],
    "name:bul_x_preferred":[
        "\u041c\u0430\u0441\u0430"
    ],
    "name:cat_x_preferred":[
        "Massa"
    ],
    "name:ces_x_preferred":[
        "Massa"
    ],
    "name:cos_x_preferred":[
        "Massa"
    ],
    "name:deu_x_preferred":[
        "Massa"
    ],
    "name:ell_x_preferred":[
        "\u039c\u03ac\u03c3\u03c3\u03b1"
    ],
    "name:eml_x_preferred":[
        "Masa"
    ],
    "name:epo_x_preferred":[
        "Massa"
    ],
    "name:est_x_preferred":[
        "Massa"
    ],
    "name:eus_x_preferred":[
        "Massa"
    ],
    "name:fas_x_preferred":[
        "\u0645\u0627\u0633\u0627"
    ],
    "name:fra_x_preferred":[
        "Massa"
    ],
    "name:gle_x_preferred":[
        "Massa"
    ],
    "name:glg_x_preferred":[
        "Massa"
    ],
    "name:heb_x_preferred":[
        "\u05de\u05d0\u05e1\u05d4"
    ],
    "name:hun_x_preferred":[
        "Massa"
    ],
    "name:hye_x_preferred":[
        "\u0544\u0561\u057d\u057d\u0561"
    ],
    "name:ind_x_preferred":[
        "Massa"
    ],
    "name:ita_x_preferred":[
        "Massa"
    ],
    "name:jpn_x_preferred":[
        "\u30de\u30c3\u30b5"
    ],
    "name:kor_x_preferred":[
        "\ub9c8\uc0ac"
    ],
    "name:lat_x_preferred":[
        "Massa"
    ],
    "name:lit_x_preferred":[
        "Masa"
    ],
    "name:lmo_x_preferred":[
        "Massa"
    ],
    "name:msa_x_preferred":[
        "Massa"
    ],
    "name:nap_x_preferred":[
        "Massa"
    ],
    "name:nld_x_preferred":[
        "Massa"
    ],
    "name:nno_x_preferred":[
        "Massa"
    ],
    "name:nor_x_preferred":[
        "Massa"
    ],
    "name:pap_x_preferred":[
        "Massa"
    ],
    "name:pms_x_preferred":[
        "Massa"
    ],
    "name:pol_x_preferred":[
        "Massa"
    ],
    "name:por_x_preferred":[
        "Massa"
    ],
    "name:ron_x_preferred":[
        "Massa"
    ],
    "name:rus_x_preferred":[
        "\u041c\u0430\u0441\u0441\u0430"
    ],
    "name:san_x_preferred":[
        "\u092e\u093e\u0938\u094d\u0938\u093e"
    ],
    "name:scn_x_preferred":[
        "Massa"
    ],
    "name:sco_x_preferred":[
        "Massa"
    ],
    "name:slk_x_preferred":[
        "Massa"
    ],
    "name:spa_x_preferred":[
        "Massa"
    ],
    "name:srp_x_preferred":[
        "\u041c\u0430\u0441\u0430"
    ],
    "name:swe_x_preferred":[
        "Massa"
    ],
    "name:tat_x_preferred":[
        "\u041c\u0430\u0441\u0441\u0430"
    ],
    "name:tgl_x_preferred":[
        "Massa"
    ],
    "name:tur_x_preferred":[
        "Massa"
    ],
    "name:ukr_x_preferred":[
        "\u041c\u0430\u0441\u0441\u0430"
    ],
    "name:urd_x_preferred":[
        "\u0645\u0627\u0633\u0627"
    ],
    "name:vie_x_preferred":[
        "Massa"
    ],
    "name:vol_x_preferred":[
        "Massa"
    ],
    "name:war_x_preferred":[
        "Massa"
    ],
    "wof:name":"Massa",
    "wof:placetype":"locality",
    "wof:population":68
},
  "geometry": {"coordinates":[12.14357,44.26735],"type":"Point"}
}