{
  "type": "Feature",
  "properties": {
    "gn:admin1_code":"5.0",
    "gn:admin2_code":"RA",
    "gn:admin3_code":"39014.0",
    "gn:asciiname":"Massa",
    "gn:country_code":"IT",
    "gn:dem":12,
    "gn:elevation":"16.0",
    "gn:feature_class":"P",
    "gn:feature_code":"PPL",
    "gn:name":"Massa",
    "gn:population":68,
    "gn:timezone":"Europe/Rome",
    "iso:country":"IT",
    "wof:name":"Massa",
    "wof:placetype":"locality",
    "wof:population":68
},
  "geometry": {"coordinates":[12.14357,44.26735],"type":"Point"}
}