{
  "type": "Feature",
  "properties": {
    "gn:admin1_code":"2",
    "gn:admin2_code":"PZ",
    "gn:admin3_code":"76092.0",
    "gn:asciiname":"Foresta",
    "gn:country_code":"IT",
    "gn:dem":343,
    "gn:feature_class":"P",
    "gn:feature_code":"PPL",
    "gn:name":"Foresta",
    "gn:population":24,
    "gn:timezone":"Europe/Rome",
    "iso:country":"IT",
    "wof:name":"Foresta",
    "wof:placetype":"locality",
    "wof:population":24
},
  "geometry": {"coordinates":[15.79588,40.03008],"type":"Point"}
}