{
  "type": "Feature",
  "properties": {
    "gn:admin1_code":"10",
    "gn:admin2_code":"AP",
    "gn:admin3_code":"44013.0",
    "gn:asciiname":"Rocchetta",
    "gn:country_code":"IT",
    "gn:dem":248,
    "gn:feature_class":"P",
    "gn:feature_code":"PPL",
    "gn:name":"Rocchetta",
    "gn:population":56,
    "gn:timezone":"Europe/Rome",
    "iso:country":"IT",
    "wof:name":"Rocchetta",
    "wof:placetype":"locality",
    "wof:population":56
},
  "geometry": {"coordinates":[13.73318,42.90738],"type":"Point"}
}