{
  "type": "Feature",
  "properties": {
    "gn:admin1_code":"3",
    "gn:admin2_code":"RC",
    "gn:admin3_code":"80036.0",
    "gn:asciiname":"Monaci",
    "gn:country_code":"IT",
    "gn:dem":688,
    "gn:feature_class":"P",
    "gn:feature_code":"PPL",
    "gn:name":"Monaci",
    "gn:population":214,
    "gn:timezone":"Europe/Rome",
    "iso:country":"IT",
    "wof:name":"Monaci",
    "wof:placetype":"locality",
    "wof:population":214
},
  "geometry": {"coordinates":[16.1762,38.30192],"type":"Point"}
}