{
  "type": "Feature",
  "properties": {
    "gn:admin1_code":"3",
    "gn:admin2_code":"CS",
    "gn:admin3_code":"78020.0",
    "gn:asciiname":"Previtelio",
    "gn:country_code":"IT",
    "gn:dem":488,
    "gn:feature_class":"P",
    "gn:feature_code":"PPL",
    "gn:name":"Previtelio",
    "gn:population":59,
    "gn:timezone":"Europe/Rome",
    "iso:country":"IT",
    "wof:name":"Previtelio",
    "wof:placetype":"locality",
    "wof:population":59
},
  "geometry": {"coordinates":[15.8789,39.66938],"type":"Point"}
}