{
  "type": "Feature",
  "properties": {
    "gn:admin1_code":"9",
    "gn:admin2_code":"BS",
    "gn:admin3_code":"17152.0",
    "gn:asciiname":"Santa Maria degli Angeli",
    "gn:country_code":"IT",
    "gn:dem":53,
    "gn:feature_class":"P",
    "gn:feature_code":"PPL",
    "gn:name":"Santa Maria degli Angeli",
    "gn:population":18,
    "gn:timezone":"Europe/Rome",
    "iso:country":"IT",
    "name:cat_x_preferred":[
        "Santa Maria degli Angeli"
    ],
    "name:ces_x_preferred":[
        "Santa Maria degli Angeli"
    ],
    "name:deu_x_preferred":[
        "Sankt Maria von den Engeln"
    ],
    "name:ita_x_preferred":[
        "Santa Maria degli Angeli"
    ],
    "name:lat_x_preferred":[
        "Sancta Maria Angelorum"
    ],
    "name:slk_x_preferred":[
        "Santa Maria degli Angeli"
    ],
    "name:srp_x_preferred":[
        "Santa Maria degli Angeli"
    ],
    "name:swe_x_preferred":[
        "Santa Maria degli Angeli"
    ],
    "wof:name":"Santa Maria degli Angeli",
    "wof:placetype":"locality",
    "wof:population":18
},
  "geometry": {"coordinates":[10.24844,45.25572],"type":"Point"}
}