{
  "type": "Feature",
  "properties": {
    "gn:admin1_code":"20",
    "gn:admin2_code":"PD",
    "gn:admin3_code":"28065.0",
    "gn:asciiname":"Bernardon",
    "gn:country_code":"IT",
    "gn:dem":-1,
    "gn:feature_class":"P",
    "gn:feature_code":"PPL",
    "gn:name":"Bernardon",
    "gn:population":47,
    "gn:timezone":"Europe/Rome",
    "iso:country":"IT",
    "wof:name":"Bernardon",
    "wof:placetype":"locality",
    "wof:population":47
},
  "geometry": {"coordinates":[12.08211,45.31041],"type":"Point"}
}