{
  "type": "Feature",
  "properties": {
    "gn:admin1_code":"5",
    "gn:admin2_code":"PC",
    "gn:admin3_code":"33031.0",
    "gn:asciiname":"Morasco",
    "gn:country_code":"IT",
    "gn:dem":372,
    "gn:feature_class":"P",
    "gn:feature_code":"PPL",
    "gn:name":"Morasco",
    "gn:population":27,
    "gn:timezone":"Europe/Rome",
    "iso:country":"IT",
    "wof:name":"Morasco",
    "wof:placetype":"locality",
    "wof:population":27
},
  "geometry": {"coordinates":[9.34862,44.89421],"type":"Point"}
}