{
  "type": "Feature",
  "properties": {
    "gn:admin1_code":"9",
    "gn:admin2_code":"BG",
    "gn:admin3_code":"16037.0",
    "gn:asciiname":"Zona Stadio Crespi",
    "gn:country_code":"IT",
    "gn:dem":177,
    "gn:feature_class":"P",
    "gn:feature_code":"PPL",
    "gn:name":"Zona Stadio Crespi",
    "gn:population":96,
    "gn:timezone":"Europe/Rome",
    "iso:country":"IT",
    "wof:name":"Zona Stadio Crespi",
    "wof:placetype":"locality",
    "wof:population":96
},
  "geometry": {"coordinates":[9.54074,45.59965],"type":"Point"}
}