{
  "type": "Feature",
  "properties": {
    "gn:admin1_code":"20",
    "gn:admin2_code":"VR",
    "gn:admin3_code":"23091.0",
    "gn:asciiname":"La Costa",
    "gn:country_code":"IT",
    "gn:dem":366,
    "gn:feature_class":"P",
    "gn:feature_code":"PPL",
    "gn:name":"La Costa",
    "gn:population":35,
    "gn:timezone":"Europe/Rome",
    "iso:country":"IT",
    "wof:name":"La Costa",
    "wof:placetype":"locality",
    "wof:population":35
},
  "geometry": {"coordinates":[11.08461,45.4955],"type":"Point"}
}