{
  "type": "Feature",
  "properties": {
    "gn:admin1_code":"17",
    "gn:admin2_code":"BZ",
    "gn:admin3_code":"21038.0",
    "gn:asciiname":"Castello Plars",
    "gn:country_code":"IT",
    "gn:dem":456,
    "gn:feature_class":"P",
    "gn:feature_code":"PPL",
    "gn:name":"Castello Plars",
    "gn:population":37,
    "gn:timezone":"Europe/Rome",
    "iso:country":"IT",
    "wof:name":"Castello Plars",
    "wof:placetype":"locality",
    "wof:population":37
},
  "geometry": {"coordinates":[11.10783,46.68532],"type":"Point"}
}