{
  "type": "Feature",
  "properties": {
    "gn:admin1_code":"3.0",
    "gn:admin2_code":"CS",
    "gn:admin3_code":"78081.0",
    "gn:asciiname":"Stazione Montalto-Coretto",
    "gn:country_code":"IT",
    "gn:dem":152,
    "gn:feature_class":"P",
    "gn:feature_code":"PPL",
    "gn:name":"Stazione Montalto-Coretto",
    "gn:population":1712,
    "gn:timezone":"Europe/Rome",
    "iso:country":"IT",
    "wof:name":"Stazione Montalto-Coretto",
    "wof:placetype":"locality",
    "wof:population":1712
},
  "geometry": {"coordinates":[16.24312999999999,39.4072],"type":"Point"}
}