{
  "type": "Feature",
  "properties": {
    "gn:admin1_code":"13.0",
    "gn:admin2_code":"BA",
    "gn:admin3_code":"72006.0",
    "gn:asciiname":"Santo Spirito",
    "gn:country_code":"IT",
    "gn:dem":-9999,
    "gn:feature_class":"P",
    "gn:feature_code":"PPL",
    "gn:name":"Santo Spirito",
    "gn:population":1000,
    "gn:timezone":"Europe/Rome",
    "iso:country":"IT",
    "wof:name":"Santo Spirito",
    "wof:placetype":"locality",
    "wof:population":1000
},
  "geometry": {"coordinates":[16.75,41.16667],"type":"Point"}
}