{
  "type": "Feature",
  "properties": {
    "gn:admin1_code":"4.0",
    "gn:admin2_code":"CE",
    "gn:admin3_code":"61033.0",
    "gn:asciiname":"San Giorgio",
    "gn:country_code":"IT",
    "gn:dem":110,
    "gn:elevation":"130.0",
    "gn:feature_class":"P",
    "gn:feature_code":"PPLA3",
    "gn:name":"San Giorgio",
    "gn:population":1496,
    "gn:timezone":"Europe/Rome",
    "iso:country":"IT",
    "name:ceb_x_preferred":[
        "San Giorgio"
    ],
    "name:ces_x_preferred":[
        "San Giorgio"
    ],
    "name:deu_x_preferred":[
        "San Giorgio"
    ],
    "name:epo_x_preferred":[
        "San Giorgio"
    ],
    "name:fra_x_preferred":[
        "San Giorgio"
    ],
    "name:ita_x_preferred":[
        "San Giorgio"
    ],
    "name:pms_x_preferred":[
        "San Gi\u00f2rs"
    ],
    "name:pol_x_preferred":[
        "San Giorgio"
    ],
    "name:por_x_preferred":[
        "San Giorgio"
    ],
    "name:rus_x_preferred":[
        "\u0421\u0430\u043d-\u0414\u0436\u043e\u0440\u0434\u0436\u043e"
    ],
    "name:srp_x_preferred":[
        "San \u0110or\u0111o"
    ],
    "name:swe_x_preferred":[
        "San Giorgio"
    ],
    "name:ukr_x_preferred":[
        "\u0421\u0430\u043d-\u0414\u0436\u043e\u0440\u0434\u0436\u043e"
    ],
    "wof:name":"San Giorgio",
    "wof:placetype":"locality",
    "wof:population":1496
},
  "geometry": {"coordinates":[14.31278,41.27065],"type":"Point"}
}