{
  "type": "Feature",
  "properties": {
    "gn:admin1_code":"16.0",
    "gn:admin2_code":"GR",
    "gn:admin3_code":"53010.0",
    "gn:asciiname":"Casa Campo la Cantina",
    "gn:cc2":"IT",
    "gn:country_code":"IT",
    "gn:dem":63,
    "gn:feature_class":"P",
    "gn:feature_code":"PPL",
    "gn:name":"Casa Campo la Cantina",
    "gn:population":0,
    "gn:timezone":"Europe/Rome",
    "iso:country":"IT",
    "name:und_x_variant":[
        "Casale Campo Contina"
    ],
    "wof:name":"Casa Campo la Cantina",
    "wof:placetype":"locality"
},
  "geometry": {"coordinates":[10.96873,42.97853],"type":"Point"}
}