{
  "type": "Feature",
  "properties": {
    "gn:admin1_code":"1",
    "gn:admin2_code":"CH",
    "gn:admin3_code":"69099.0",
    "gn:asciiname":"Colli",
    "gn:country_code":"IT",
    "gn:dem":191,
    "gn:feature_class":"P",
    "gn:feature_code":"PPL",
    "gn:name":"Colli",
    "gn:population":27,
    "gn:timezone":"Europe/Rome",
    "iso:country":"IT",
    "name:ceb_x_preferred":[
        "Colli"
    ],
    "name:deu_x_preferred":[
        "Colli"
    ],
    "name:ita_x_preferred":[
        "Colli"
    ],
    "name:nld_x_preferred":[
        "Colli"
    ],
    "name:por_x_preferred":[
        "Colli"
    ],
    "name:rus_x_preferred":[
        "\u041a\u043e\u043b\u043b\u0438"
    ],
    "name:swe_x_preferred":[
        "Colli"
    ],
    "wof:name":"Colli",
    "wof:placetype":"locality",
    "wof:population":27
},
  "geometry": {"coordinates":[14.69297,42.1078],"type":"Point"}
}