{
  "type": "Feature",
  "properties": {
    "gn:admin1_code":"5",
    "gn:admin2_code":"FC",
    "gn:admin3_code":"40043.0",
    "gn:asciiname":"Lago",
    "gn:country_code":"IT",
    "gn:dem":534,
    "gn:feature_class":"P",
    "gn:feature_code":"PPL",
    "gn:name":"Lago",
    "gn:population":33,
    "gn:timezone":"Europe/Rome",
    "iso:country":"IT",
    "wof:name":"Lago",
    "wof:placetype":"locality",
    "wof:population":33
},
  "geometry": {"coordinates":[11.78544,43.90404],"type":"Point"}
}