{
  "type": "Feature",
  "properties": {
    "gn:gn_country":"IT",
    "gn:gn_fcode":"PPL",
    "gn:gn_pop":0,
    "gn:population":134,
    "iso:country":"IT",
    "name:eng_x_preferred":[
        "Copanello"
    ],
    "name:fra_x_preferred":[
        "Copanello"
    ],
    "name:hun_x_preferred":[
        "Copanello"
    ],
    "name:ita_x_preferred":[
        "Copanello"
    ],
    "name:nld_x_preferred":[
        "Copanello"
    ],
    "name:oci_x_preferred":[
        "Copanello"
    ],
    "qs_pg:aaroncc":"IT",
    "qs_pg:gn_country":"IT",
    "qs_pg:gn_fcode":"PPL",
    "qs_pg:gn_pop":0,
    "qs_pg:name":"Copanello",
    "qs_pg:name_adm0":"Italia",
    "qs_pg:name_adm1":"Calabria",
    "qs_pg:photos":129,
    "qs_pg:photos_1k":26,
    "qs_pg:photos_9k":1,
    "qs_pg:photos_9r":3,
    "qs_pg:photos_all":129,
    "qs_pg:photos_sr":3,
    "qs_pg:pop_sr":0,
    "qs_pg:qs_pg_placetype":"locality",
    "qs_pg:qs_pg_placetype_gp":"Town",
    "qs_pg:woe_adm0":23424853,
    "woe:adm0_id":23424853,
    "woe:name_adm0":"Italia",
    "woe:name_adm1":"Calabria",
    "woe:placetype":"Town",
    "wof:name":"Copanello",
    "wof:placetype":"locality",
    "wof:population":134
},
  "geometry": {"coordinates":[16.55,38.76667],"type":"Point"}
}