{
  "type": "Feature",
  "properties": {
    "gn:admin1_code":"5",
    "gn:admin2_code":"FC",
    "gn:admin3_code":"40007.0",
    "gn:asciiname":"Mesola",
    "gn:country_code":"IT",
    "gn:dem":20,
    "gn:feature_class":"P",
    "gn:feature_code":"PPL",
    "gn:name":"Mesola",
    "gn:population":98,
    "gn:timezone":"Europe/Rome",
    "iso:country":"IT",
    "wof:name":"Mesola",
    "wof:placetype":"locality",
    "wof:population":98
},
  "geometry": {"coordinates":[12.29069,44.15628],"type":"Point"}
}