{
  "type": "Feature",
  "properties": {
    "gn:admin1_code":"5",
    "gn:admin2_code":"FC",
    "gn:admin3_code":"40007.0",
    "gn:asciiname":"Mesola",
    "gn:country_code":"IT",
    "gn:dem":20,
    "gn:feature_class":"P",
    "gn:feature_code":"PPL",
    "gn:name":"Mesola",
    "gn:population":98,
    "gn:timezone":"Europe/Rome",
    "iso:country":"IT",
    "name:ara_x_preferred":[
        "\u0645\u064a\u0632\u0648\u0644\u0627"
    ],
    "name:azb_x_preferred":[
        "\u0645\u0632\u0648\u0644\u0627"
    ],
    "name:bul_x_preferred":[
        "\u041c\u0435\u0437\u043e\u043b\u0430"
    ],
    "name:ceb_x_preferred":[
        "Mesola"
    ],
    "name:deu_x_preferred":[
        "Mesola"
    ],
    "name:eml_x_preferred":[
        "La M\u00e9sula"
    ],
    "name:epo_x_preferred":[
        "Mesola"
    ],
    "name:eus_x_preferred":[
        "Mesola"
    ],
    "name:fas_x_preferred":[
        "\u0645\u0632\u0648\u0644\u0627"
    ],
    "name:fra_x_preferred":[
        "Mesola"
    ],
    "name:hun_x_preferred":[
        "Mesola"
    ],
    "name:hye_x_preferred":[
        "\u0544\u0565\u0566\u0578\u056c\u0561"
    ],
    "name:ina_x_preferred":[
        "Mesola"
    ],
    "name:ind_x_preferred":[
        "Mesola"
    ],
    "name:ita_x_preferred":[
        "Mesola"
    ],
    "name:jpn_x_preferred":[
        "\u30e1\u30be\u30fc\u30e9"
    ],
    "name:kaz_x_preferred":[
        "\u041c\u0435\u0437\u043e\u043b\u0430"
    ],
    "name:lat_x_preferred":[
        "Mesula"
    ],
    "name:lmo_x_preferred":[
        "Mesola"
    ],
    "name:msa_x_preferred":[
        "Mesola"
    ],
    "name:nap_x_preferred":[
        "Mesola"
    ],
    "name:nld_x_preferred":[
        "Mesola"
    ],
    "name:pms_x_preferred":[
        "Mesola"
    ],
    "name:pol_x_preferred":[
        "Mesola"
    ],
    "name:por_x_preferred":[
        "Mesola"
    ],
    "name:ron_x_preferred":[
        "Mesola"
    ],
    "name:rus_x_preferred":[
        "\u041c\u0435\u0437\u043e\u043b\u0430"
    ],
    "name:scn_x_preferred":[
        "Mesola"
    ],
    "name:spa_x_preferred":[
        "Mesola"
    ],
    "name:srp_x_preferred":[
        "\u041c\u0435\u0437\u043e\u043b\u0430"
    ],
    "name:ukr_x_preferred":[
        "\u041c\u0435\u0437\u043e\u043b\u0430"
    ],
    "name:uzb_x_preferred":[
        "Mesola"
    ],
    "name:vec_x_preferred":[
        "Mesola"
    ],
    "name:vie_x_preferred":[
        "Mesola"
    ],
    "name:vol_x_preferred":[
        "Mesola"
    ],
    "name:war_x_preferred":[
        "Mesola"
    ],
    "name:zho_x_preferred":[
        "\u6885\u7d22\u62c9"
    ],
    "wof:name":"Mesola",
    "wof:placetype":"locality",
    "wof:population":98
},
  "geometry": {"coordinates":[12.29069,44.15628],"type":"Point"}
}