{
  "type": "Feature",
  "properties": {
    "gn:admin1_code":"18.0",
    "gn:admin2_code":"PG",
    "gn:admin3_code":"54010.0",
    "gn:asciiname":"Fergino",
    "gn:country_code":"IT",
    "gn:dem":895,
    "gn:feature_class":"P",
    "gn:feature_code":"PPL",
    "gn:name":"Fergino",
    "gn:population":0,
    "gn:timezone":"Europe/Rome",
    "iso:country":"IT",
    "wof:name":"Fergino",
    "wof:placetype":"locality"
},
  "geometry": {"coordinates":[12.95,42.85],"type":"Point"}
}