{
  "type": "Feature",
  "properties": {
    "gn:admin1_code":"2",
    "gn:admin2_code":"PZ",
    "gn:admin3_code":"76042.0",
    "gn:asciiname":"Casale Civile",
    "gn:country_code":"IT",
    "gn:dem":755,
    "gn:feature_class":"P",
    "gn:feature_code":"PPL",
    "gn:name":"Casale Civile",
    "gn:population":19,
    "gn:timezone":"Europe/Rome",
    "iso:country":"IT",
    "wof:name":"Casale Civile",
    "wof:placetype":"locality",
    "wof:population":19
},
  "geometry": {"coordinates":[15.89457,40.01443],"type":"Point"}
}