{
  "type": "Feature",
  "properties": {
    "gn:admin1_code":"12",
    "gn:admin2_code":"TO",
    "gn:admin3_code":"1300.0",
    "gn:asciiname":"San Giovanni",
    "gn:country_code":"IT",
    "gn:dem":262,
    "gn:feature_class":"P",
    "gn:feature_code":"PPL",
    "gn:name":"San Giovanni",
    "gn:population":41,
    "gn:timezone":"Europe/Rome",
    "iso:country":"IT",
    "wof:name":"San Giovanni",
    "wof:placetype":"locality",
    "wof:population":41
},
  "geometry": {"coordinates":[7.46309,44.79682],"type":"Point"}
}