{
  "type": "Feature",
  "properties": {
    "gn:admin1_code":"20",
    "gn:admin2_code":"VI",
    "gn:admin3_code":"24040.0",
    "gn:asciiname":"Ca' Michelon-Poletti",
    "gn:country_code":"IT",
    "gn:dem":308,
    "gn:feature_class":"P",
    "gn:feature_code":"PPL",
    "gn:name":"Ca' Michelon-Poletti",
    "gn:population":52,
    "gn:timezone":"Europe/Rome",
    "iso:country":"IT",
    "wof:name":"Ca' Michelon-Poletti",
    "wof:placetype":"locality",
    "wof:population":52
},
  "geometry": {"coordinates":[11.57472,45.74572],"type":"Point"}
}