{
  "type": "Feature",
  "properties": {
    "gn:admin1_code":"12",
    "gn:admin2_code":"NO",
    "gn:admin3_code":"3066.0",
    "gn:asciiname":"Cacciana",
    "gn:country_code":"IT",
    "gn:dem":254,
    "gn:feature_class":"P",
    "gn:feature_code":"PPL",
    "gn:name":"Cacciana",
    "gn:population":309,
    "gn:timezone":"Europe/Rome",
    "iso:country":"IT",
    "wof:name":"Cacciana",
    "wof:placetype":"locality",
    "wof:population":309
},
  "geometry": {"coordinates":[8.49153,45.62876],"type":"Point"}
}