{
  "type": "Feature",
  "properties": {
    "gn:admin1_code":"14",
    "gn:admin2_code":"SS",
    "gn:admin3_code":"90092.0",
    "gn:asciiname":"Badualga",
    "gn:country_code":"IT",
    "gn:dem":28,
    "gn:feature_class":"P",
    "gn:feature_code":"PPL",
    "gn:name":"Badualga",
    "gn:population":247,
    "gn:timezone":"Europe/Rome",
    "iso:country":"IT",
    "wof:name":"Badualga",
    "wof:placetype":"locality",
    "wof:population":247
},
  "geometry": {"coordinates":[9.65382,40.76452000000001],"type":"Point"}
}