{
  "type": "Feature",
  "properties": {
    "gn:admin1_code":"20",
    "gn:admin2_code":"RO",
    "gn:admin3_code":"29013.0",
    "gn:asciiname":"Palazzi Vallicelli",
    "gn:country_code":"IT",
    "gn:dem":8,
    "gn:feature_class":"P",
    "gn:feature_code":"PPL",
    "gn:name":"Palazzi Vallicelli",
    "gn:population":41,
    "gn:timezone":"Europe/Rome",
    "iso:country":"IT",
    "wof:name":"Palazzi Vallicelli",
    "wof:placetype":"locality",
    "wof:population":41
},
  "geometry": {"coordinates":[11.28468,45.04451],"type":"Point"}
}