{
  "type": "Feature",
  "properties": {
    "gn:admin1_code":"16",
    "gn:admin2_code":"FI",
    "gn:admin3_code":"48021.0",
    "gn:asciiname":"Torsoli",
    "gn:country_code":"IT",
    "gn:dem":689,
    "gn:feature_class":"P",
    "gn:feature_code":"PPL",
    "gn:name":"Torsoli",
    "gn:population":13,
    "gn:timezone":"Europe/Rome",
    "iso:country":"IT",
    "wof:name":"Torsoli",
    "wof:placetype":"locality",
    "wof:population":13
},
  "geometry": {"coordinates":[11.39037,43.56049],"type":"Point"}
}