{
  "type": "Feature",
  "properties": {
    "gn:admin1_code":"1",
    "gn:admin2_code":"TE",
    "gn:admin3_code":"67021.0",
    "gn:asciiname":"Case Stagno",
    "gn:country_code":"IT",
    "gn:dem":85,
    "gn:feature_class":"P",
    "gn:feature_code":"PPL",
    "gn:name":"Case Stagn\u00f2",
    "gn:population":40,
    "gn:timezone":"Europe/Rome",
    "iso:country":"IT",
    "name:und_x_variant":[
        "Case Stagn\u00f2"
    ],
    "wof:name":"Case Stagno",
    "wof:placetype":"locality",
    "wof:population":40
},
  "geometry": {"coordinates":[13.84055,42.8086],"type":"Point"}
}