{
  "type": "Feature",
  "properties": {
    "gn:admin1_code":"20",
    "gn:admin2_code":"VI",
    "gn:admin3_code":"24052.0",
    "gn:asciiname":"Trassegno",
    "gn:country_code":"IT",
    "gn:dem":32,
    "gn:feature_class":"P",
    "gn:feature_code":"PPL",
    "gn:name":"Trassegno",
    "gn:population":53,
    "gn:timezone":"Europe/Rome",
    "iso:country":"IT",
    "wof:name":"Trassegno",
    "wof:placetype":"locality",
    "wof:population":53
},
  "geometry": {"coordinates":[11.35862,45.41121],"type":"Point"}
}