{
  "type": "Feature",
  "properties": {
    "gn:admin1_code":"4",
    "gn:admin2_code":"AV",
    "gn:admin3_code":"64039.0",
    "gn:asciiname":"Tropeani",
    "gn:country_code":"IT",
    "gn:dem":484,
    "gn:feature_class":"P",
    "gn:feature_code":"PPL",
    "gn:name":"Tropeani",
    "gn:population":210,
    "gn:timezone":"Europe/Rome",
    "iso:country":"IT",
    "wof:name":"Tropeani",
    "wof:placetype":"locality",
    "wof:population":210
},
  "geometry": {"coordinates":[14.79747,40.95708],"type":"Point"}
}