{
  "type": "Feature",
  "properties": {
    "gn:admin1_code":"20.0",
    "gn:admin2_code":"VR",
    "gn:admin3_code":"23018.0",
    "gn:asciiname":"Pesine Bisse",
    "gn:country_code":"IT",
    "gn:dem":259,
    "gn:feature_class":"P",
    "gn:feature_code":"PPL",
    "gn:name":"Pesine Bisse",
    "gn:population":740,
    "gn:timezone":"Europe/Rome",
    "iso:country":"IT",
    "wof:name":"Pesine Bisse",
    "wof:placetype":"locality",
    "wof:population":740
},
  "geometry": {"coordinates":[10.75248,45.59927],"type":"Point"}
}