{
  "type": "Feature",
  "properties": {
    "gn:admin1_code":"20",
    "gn:admin2_code":"RO",
    "gn:admin3_code":"29032.0",
    "gn:asciiname":"Della Chiesa",
    "gn:country_code":"IT",
    "gn:dem":10,
    "gn:feature_class":"P",
    "gn:feature_code":"PPL",
    "gn:name":"Della Chiesa",
    "gn:population":24,
    "gn:timezone":"Europe/Rome",
    "iso:country":"IT",
    "wof:name":"Della Chiesa",
    "wof:placetype":"locality",
    "wof:population":24
},
  "geometry": {"coordinates":[11.20617,45.07864],"type":"Point"}
}