{
  "type": "Feature",
  "properties": {
    "gn:admin1_code":"7",
    "gn:admin2_code":"FR",
    "gn:admin3_code":"60048.0",
    "gn:asciiname":"Lagoscillo",
    "gn:country_code":"IT",
    "gn:dem":175,
    "gn:feature_class":"P",
    "gn:feature_code":"PPL",
    "gn:name":"Lagoscillo",
    "gn:population":261,
    "gn:timezone":"Europe/Rome",
    "iso:country":"IT",
    "wof:name":"Lagoscillo",
    "wof:placetype":"locality",
    "wof:population":261
},
  "geometry": {"coordinates":[13.27528,41.59228],"type":"Point"}
}