{
  "type": "Feature",
  "properties": {
    "gn:admin1_code":"5",
    "gn:admin2_code":"RN",
    "gn:admin3_code":"99016.0",
    "gn:asciiname":"Il Poggio",
    "gn:country_code":"IT",
    "gn:dem":146,
    "gn:feature_class":"P",
    "gn:feature_code":"PPL",
    "gn:name":"Il Poggio",
    "gn:population":33,
    "gn:timezone":"Europe/Rome",
    "iso:country":"IT",
    "wof:name":"Il Poggio",
    "wof:placetype":"locality",
    "wof:population":33
},
  "geometry": {"coordinates":[12.63009,43.92052],"type":"Point"}
}