{
  "type": "Feature",
  "properties": {
    "gn:admin1_code":"1",
    "gn:admin2_code":"CH",
    "gn:admin3_code":"69017.0",
    "gn:asciiname":"Capoposta",
    "gn:country_code":"IT",
    "gn:dem":371,
    "gn:feature_class":"P",
    "gn:feature_code":"PPL",
    "gn:name":"Capoposta",
    "gn:population":35,
    "gn:timezone":"Europe/Rome",
    "iso:country":"IT",
    "wof:name":"Capoposta",
    "wof:placetype":"locality",
    "wof:population":35
},
  "geometry": {"coordinates":[14.27316,42.15804],"type":"Point"}
}