{
  "type": "Feature",
  "properties": {
    "gn:admin1_code":"7.0",
    "gn:admin2_code":"RM",
    "gn:admin3_code":"58117.0",
    "gn:asciiname":"Santa Procula Maggiore",
    "gn:country_code":"IT",
    "gn:dem":46,
    "gn:feature_class":"P",
    "gn:feature_code":"PPL",
    "gn:name":"Santa Procula Maggiore",
    "gn:population":0,
    "gn:timezone":"Europe/Rome",
    "iso:country":"IT",
    "wof:name":"Santa Procula Maggiore",
    "wof:placetype":"locality"
},
  "geometry": {"coordinates":[12.53333,41.65],"type":"Point"}
}