{
  "type": "Feature",
  "properties": {
    "gn:admin1_code":"20",
    "gn:admin2_code":"VR",
    "gn:admin3_code":"23071.0",
    "gn:asciiname":"Ca' dell'Ebreo",
    "gn:country_code":"IT",
    "gn:dem":33,
    "gn:feature_class":"P",
    "gn:feature_code":"PPL",
    "gn:name":"Ca' dell'Ebreo",
    "gn:population":13,
    "gn:timezone":"Europe/Rome",
    "iso:country":"IT",
    "wof:name":"Ca' dell'Ebreo",
    "wof:placetype":"locality",
    "wof:population":13
},
  "geometry": {"coordinates":[11.05648,45.34419000000001],"type":"Point"}
}