{
  "type": "Feature",
  "properties": {
    "gn:admin1_code":"16",
    "gn:admin2_code":"LI",
    "gn:admin3_code":"49008.0",
    "gn:asciiname":"Le Murelle",
    "gn:country_code":"IT",
    "gn:dem":9,
    "gn:feature_class":"P",
    "gn:feature_code":"PPL",
    "gn:name":"Le Murelle",
    "gn:population":38,
    "gn:timezone":"Europe/Rome",
    "iso:country":"IT",
    "wof:name":"Le Murelle",
    "wof:placetype":"locality",
    "wof:population":38
},
  "geometry": {"coordinates":[10.45465,43.6038],"type":"Point"}
}