{
  "type": "Feature",
  "properties": {
    "gn:admin1_code":"20",
    "gn:admin2_code":"PD",
    "gn:admin3_code":"28008.0",
    "gn:asciiname":"Cappelline",
    "gn:country_code":"IT",
    "gn:dem":2,
    "gn:feature_class":"P",
    "gn:feature_code":"PPL",
    "gn:name":"Cappelline",
    "gn:population":58,
    "gn:timezone":"Europe/Rome",
    "iso:country":"IT",
    "wof:name":"Cappelline",
    "wof:placetype":"locality",
    "wof:population":58
},
  "geometry": {"coordinates":[11.9216,45.19643],"type":"Point"}
}