{
  "type": "Feature",
  "properties": {
    "gn:admin1_code":"5",
    "gn:admin2_code":"FE",
    "gn:admin3_code":"38005.0",
    "gn:asciiname":"Corte Trieste",
    "gn:country_code":"IT",
    "gn:dem":-3,
    "gn:feature_class":"P",
    "gn:feature_code":"PPL",
    "gn:name":"Corte Trieste",
    "gn:population":24,
    "gn:timezone":"Europe/Rome",
    "iso:country":"IT",
    "wof:name":"Corte Trieste",
    "wof:placetype":"locality",
    "wof:population":24
},
  "geometry": {"coordinates":[12.07339,44.90943],"type":"Point"}
}