{
  "type": "Feature",
  "properties": {
    "gn:admin1_code":"16.0",
    "gn:admin2_code":"PO",
    "gn:admin3_code":"100005.0",
    "gn:asciiname":"Canneto",
    "gn:country_code":"IT",
    "gn:dem":108,
    "gn:elevation":"115.0",
    "gn:feature_class":"P",
    "gn:feature_code":"PPL",
    "gn:name":"Canneto",
    "gn:population":39,
    "gn:timezone":"Europe/Rome",
    "iso:country":"IT",
    "wof:name":"Canneto",
    "wof:placetype":"locality",
    "wof:population":39
},
  "geometry": {"coordinates":[11.12296,43.9096],"type":"Point"}
}