{
  "type": "Feature",
  "properties": {
    "gn:admin1_code":"5",
    "gn:admin2_code":"PR",
    "gn:admin3_code":"34003.0",
    "gn:asciiname":"Casaleto",
    "gn:country_code":"IT",
    "gn:dem":764,
    "gn:feature_class":"P",
    "gn:feature_code":"PPL",
    "gn:name":"Casaleto",
    "gn:population":20,
    "gn:timezone":"Europe/Rome",
    "iso:country":"IT",
    "wof:name":"Casaleto",
    "wof:placetype":"locality",
    "wof:population":20
},
  "geometry": {"coordinates":[9.60403,44.5608],"type":"Point"}
}