{
  "type": "Feature",
  "properties": {
    "gn:admin1_code":"1",
    "gn:admin2_code":"TE",
    "gn:admin3_code":"67023.0",
    "gn:asciiname":"Aprati",
    "gn:country_code":"IT",
    "gn:dem":736,
    "gn:feature_class":"P",
    "gn:feature_code":"PPL",
    "gn:name":"Aprati",
    "gn:population":16,
    "gn:timezone":"Europe/Rome",
    "iso:country":"IT",
    "wof:name":"Aprati",
    "wof:placetype":"locality",
    "wof:population":16
},
  "geometry": {"coordinates":[13.47745,42.55268],"type":"Point"}
}