{
  "type": "Feature",
  "properties": {
    "iso:country":"IT",
    "wof:name":"La Loggia",
    "wof:placetype":"neighbourhood"
},
  "geometry": {"coordinates":[13.36425091031339,38.11982975962286],"type":"Point"}
}