{
  "type": "Feature",
  "properties": {
    "iso:country":"IT",
    "name:azb_x_preferred":[
        "\u0644\u0627 \u0644\u0648\u062c\u06cc\u0627"
    ],
    "name:bel_x_preferred":[
        "\u041b\u0430-\u041b\u043e\u0434\u0436\u0430"
    ],
    "name:bul_x_preferred":[
        "\u041b\u0430 \u041b\u043e\u0434\u0436\u0430"
    ],
    "name:ceb_x_preferred":[
        "La Loggia"
    ],
    "name:deu_x_preferred":[
        "La Loggia"
    ],
    "name:epo_x_preferred":[
        "La Loggia"
    ],
    "name:eus_x_preferred":[
        "La Loggia"
    ],
    "name:fas_x_preferred":[
        "\u0644\u0627 \u0644\u0648\u062c\u06cc\u0627"
    ],
    "name:fra_x_preferred":[
        "La Loggia"
    ],
    "name:hun_x_preferred":[
        "La Loggia"
    ],
    "name:hye_x_preferred":[
        "\u053c\u0561 \u053c\u0578\u057b\u0561"
    ],
    "name:ind_x_preferred":[
        "La Loggia"
    ],
    "name:ita_x_preferred":[
        "La Loggia"
    ],
    "name:jpn_x_preferred":[
        "\u30e9\u30fb\u30ed\u30c3\u30b8\u30e3"
    ],
    "name:kaz_x_preferred":[
        "\u041b\u0430-\u041b\u043e\u0434\u0436\u0430"
    ],
    "name:lat_x_preferred":[
        "Logia"
    ],
    "name:lmo_x_preferred":[
        "La Loggia"
    ],
    "name:msa_x_preferred":[
        "La Loggia"
    ],
    "name:nap_x_preferred":[
        "La Loggia"
    ],
    "name:nld_x_preferred":[
        "La Loggia"
    ],
    "name:pms_x_preferred":[
        "La L\u00f2gia"
    ],
    "name:pol_x_preferred":[
        "La Loggia"
    ],
    "name:por_x_preferred":[
        "La Loggia"
    ],
    "name:ron_x_preferred":[
        "La Loggia"
    ],
    "name:rus_x_preferred":[
        "\u041b\u0430-\u041b\u043e\u0434\u0436\u0430"
    ],
    "name:scn_x_preferred":[
        "La Loggia"
    ],
    "name:spa_x_preferred":[
        "La Loggia"
    ],
    "name:srp_x_preferred":[
        "\u041b\u0430 \u041b\u043e\u0452\u0430"
    ],
    "name:swe_x_preferred":[
        "La Loggia"
    ],
    "name:tgl_x_preferred":[
        "La Loggia"
    ],
    "name:ukr_x_preferred":[
        "\u041b\u0430-\u041b\u043e\u0434\u0436\u0430"
    ],
    "name:uzb_x_preferred":[
        "La Loggia"
    ],
    "name:vie_x_preferred":[
        "La Loggia"
    ],
    "name:vol_x_preferred":[
        "La Loggia"
    ],
    "name:war_x_preferred":[
        "La Loggia"
    ],
    "name:zho_x_preferred":[
        "\u62c9\u6d1b\u8d3e"
    ],
    "wof:name":"La Loggia",
    "wof:placetype":"neighbourhood"
},
  "geometry": {"coordinates":[13.36425091031339,38.11982975962286],"type":"Point"}
}