{
  "type": "Feature",
  "properties": {
    "gn:admin1_code":"16",
    "gn:admin2_code":"PT",
    "gn:admin3_code":"47016.0",
    "gn:asciiname":"Giardino",
    "gn:country_code":"IT",
    "gn:dem":17,
    "gn:feature_class":"P",
    "gn:feature_code":"PPL",
    "gn:name":"Giardino",
    "gn:population":11,
    "gn:timezone":"Europe/Rome",
    "iso:country":"IT",
    "name:deu_x_preferred":[
        "Giardino"
    ],
    "name:fra_x_preferred":[
        "Giardino"
    ],
    "name:ita_x_preferred":[
        "Giardino"
    ],
    "name:srp_x_preferred":[
        "Giardino"
    ],
    "wof:name":"Giardino",
    "wof:placetype":"locality",
    "wof:population":11
},
  "geometry": {"coordinates":[10.77332,43.83696],"type":"Point"}
}