{
  "type": "Feature",
  "properties": {
    "gn:admin1_code":"5",
    "gn:admin2_code":"RE",
    "gn:admin3_code":"35046.0",
    "gn:asciiname":"Marmoreto",
    "gn:country_code":"IT",
    "gn:dem":703,
    "gn:feature_class":"P",
    "gn:feature_code":"PPL",
    "gn:name":"Marmoreto",
    "gn:population":91,
    "gn:timezone":"Europe/Rome",
    "iso:country":"IT",
    "wof:name":"Marmoreto",
    "wof:placetype":"locality",
    "wof:population":91
},
  "geometry": {"coordinates":[10.32216,44.36391],"type":"Point"}
}