{
  "type": "Feature",
  "properties": {
    "gn:admin1_code":"20.0",
    "gn:admin2_code":"VI",
    "gn:admin3_code":"24070.0",
    "gn:asciiname":"Orso-Bortignon",
    "gn:country_code":"IT",
    "gn:dem":112,
    "gn:feature_class":"P",
    "gn:feature_code":"PPL",
    "gn:name":"Orso-Bortignon",
    "gn:population":18,
    "gn:timezone":"Europe/Rome",
    "iso:country":"IT",
    "wof:name":"Orso-Bortignon",
    "wof:placetype":"locality",
    "wof:population":18
},
  "geometry": {"coordinates":[11.79859,45.77161],"type":"Point"}
}