{
  "type": "Feature",
  "properties": {
    "gn:admin1_code":"1.0",
    "gn:admin2_code":"TE",
    "gn:admin3_code":"67017.0",
    "gn:asciiname":"Ripe",
    "gn:country_code":"IT",
    "gn:dem":588,
    "gn:elevation":"611.0",
    "gn:feature_class":"P",
    "gn:feature_code":"PPL",
    "gn:name":"Ripe",
    "gn:population":129,
    "gn:timezone":"Europe/Rome",
    "iso:country":"IT",
    "name:und_x_variant":[
        "Le Ripe"
    ],
    "wof:name":"Ripe",
    "wof:placetype":"locality",
    "wof:population":129
},
  "geometry": {"coordinates":[13.63712,42.75615],"type":"Point"}
}