{
  "type": "Feature",
  "properties": {
    "gn:admin1_code":"12",
    "gn:admin2_code":"VB",
    "gn:admin3_code":"103046.0",
    "gn:asciiname":"Roledo",
    "gn:country_code":"IT",
    "gn:dem":317,
    "gn:feature_class":"P",
    "gn:feature_code":"PPL",
    "gn:name":"Roledo",
    "gn:population":72,
    "gn:timezone":"Europe/Rome",
    "iso:country":"IT",
    "wof:name":"Roledo",
    "wof:placetype":"locality",
    "wof:population":72
},
  "geometry": {"coordinates":[8.31351,46.16688],"type":"Point"}
}