{
  "type": "Feature",
  "properties": {
    "gn:admin1_code":"4",
    "gn:admin2_code":"AV",
    "gn:admin3_code":"64005.0",
    "gn:asciiname":"Tranzano",
    "gn:country_code":"IT",
    "gn:dem":564,
    "gn:feature_class":"P",
    "gn:feature_code":"PPL",
    "gn:name":"Tranzano",
    "gn:population":21,
    "gn:timezone":"Europe/Rome",
    "iso:country":"IT",
    "wof:name":"Tranzano",
    "wof:placetype":"locality",
    "wof:population":21
},
  "geometry": {"coordinates":[15.11545,41.16971],"type":"Point"}
}