{
  "type": "Feature",
  "properties": {
    "gn:admin1_code":"9",
    "gn:admin2_code":"PV",
    "gn:admin3_code":"18017.0",
    "gn:asciiname":"Ca' Facchini",
    "gn:country_code":"IT",
    "gn:dem":270,
    "gn:feature_class":"P",
    "gn:feature_code":"PPL",
    "gn:name":"Ca' Facchini",
    "gn:population":22,
    "gn:timezone":"Europe/Rome",
    "iso:country":"IT",
    "wof:name":"Ca' Facchini",
    "wof:placetype":"locality",
    "wof:population":22
},
  "geometry": {"coordinates":[9.18364,44.94093],"type":"Point"}
}