{
  "type": "Feature",
  "properties": {
    "gn:admin1_code":"6.0",
    "gn:admin2_code":"PN",
    "gn:admin3_code":"93044.0",
    "gn:asciiname":"Barbeano",
    "gn:cc2":"IT",
    "gn:country_code":"IT",
    "gn:dem":110,
    "gn:elevation":"111.0",
    "gn:feature_class":"P",
    "gn:feature_code":"PPL",
    "gn:name":"Barbeano",
    "gn:population":574,
    "gn:timezone":"Europe/Rome",
    "iso:country":"IT",
    "name:und_x_variant":[
        "Montagnolo",
        "Barbeano"
    ],
    "wof:name":"Barbeano",
    "wof:placetype":"locality",
    "wof:population":574
},
  "geometry": {"coordinates":[12.86884,46.08725],"type":"Point"}
}