{
  "type": "Feature",
  "properties": {
    "gn:admin1_code":"8",
    "gn:admin2_code":"SV",
    "gn:admin3_code":"9029.0",
    "gn:asciiname":"Selva",
    "gn:country_code":"IT",
    "gn:dem":118,
    "gn:feature_class":"P",
    "gn:feature_code":"PPL",
    "gn:name":"Selva",
    "gn:population":15,
    "gn:timezone":"Europe/Rome",
    "iso:country":"IT",
    "wof:name":"Selva",
    "wof:placetype":"locality",
    "wof:population":15
},
  "geometry": {"coordinates":[8.37418,44.18122],"type":"Point"}
}