{
  "type": "Feature",
  "properties": {
    "gn:admin1_code":"13",
    "gn:admin2_code":"LE",
    "gn:admin3_code":"75016.0",
    "gn:asciiname":"Parati",
    "gn:country_code":"IT",
    "gn:dem":54,
    "gn:feature_class":"P",
    "gn:feature_code":"PPL",
    "gn:name":"Parati",
    "gn:population":11,
    "gn:timezone":"Europe/Rome",
    "iso:country":"IT",
    "wof:name":"Parati",
    "wof:placetype":"locality",
    "wof:population":11
},
  "geometry": {"coordinates":[18.14289,39.9865],"type":"Point"}
}