{
  "type": "Feature",
  "properties": {
    "gn:admin1_code":"12",
    "gn:admin2_code":"TO",
    "gn:admin3_code":"1052.0",
    "gn:asciiname":"Sombeila",
    "gn:country_code":"IT",
    "gn:dem":787,
    "gn:feature_class":"P",
    "gn:feature_code":"PPL",
    "gn:name":"Sombeila",
    "gn:population":19,
    "gn:timezone":"Europe/Rome",
    "iso:country":"IT",
    "wof:name":"Sombeila",
    "wof:placetype":"locality",
    "wof:population":19
},
  "geometry": {"coordinates":[7.589,45.3799],"type":"Point"}
}