{
  "type": "Feature",
  "properties": {
    "gn:admin1_code":"12",
    "gn:admin2_code":"CN",
    "gn:admin3_code":"4068.0",
    "gn:asciiname":"Fiolera",
    "gn:country_code":"IT",
    "gn:dem":775,
    "gn:feature_class":"P",
    "gn:feature_code":"PPL",
    "gn:name":"Fiolera",
    "gn:population":40,
    "gn:timezone":"Europe/Rome",
    "iso:country":"IT",
    "wof:name":"Fiolera",
    "wof:placetype":"locality",
    "wof:population":40
},
  "geometry": {"coordinates":[7.67098,44.27551],"type":"Point"}
}