{
  "type": "Feature",
  "properties": {
    "gn:admin1_code":"4.0",
    "gn:admin2_code":"AV",
    "gn:admin3_code":"64034.0",
    "gn:asciiname":"Celzi",
    "gn:country_code":"IT",
    "gn:dem":396,
    "gn:feature_class":"P",
    "gn:feature_code":"PPL",
    "gn:name":"Celzi",
    "gn:population":469,
    "gn:timezone":"Europe/Rome",
    "iso:country":"IT",
    "wof:name":"Celzi",
    "wof:placetype":"locality",
    "wof:population":469
},
  "geometry": {"coordinates":[14.75004,40.85515],"type":"Point"}
}