{
  "type": "Feature",
  "properties": {
    "gn:admin1_code":"10.0",
    "gn:admin2_code":"PU",
    "gn:admin3_code":"41070.0",
    "gn:asciiname":"La Figurina",
    "gn:country_code":"IT",
    "gn:dem":93,
    "gn:feature_class":"P",
    "gn:feature_code":"PPL",
    "gn:name":"La Figurina",
    "gn:population":0,
    "gn:timezone":"Europe/Rome",
    "iso:country":"IT",
    "wof:name":"La Figurina",
    "wof:placetype":"locality"
},
  "geometry": {"coordinates":[13.01667,43.71667],"type":"Point"}
}