{
  "type": "Feature",
  "properties": {
    "gn:admin1_code":"20",
    "gn:admin2_code":"VI",
    "gn:admin3_code":"24005.0",
    "gn:asciiname":"Santolini",
    "gn:country_code":"IT",
    "gn:dem":640,
    "gn:feature_class":"P",
    "gn:feature_code":"PPL",
    "gn:name":"Santolini",
    "gn:population":62,
    "gn:timezone":"Europe/Rome",
    "iso:country":"IT",
    "wof:name":"Santolini",
    "wof:placetype":"locality",
    "wof:population":62
},
  "geometry": {"coordinates":[11.25737,45.59935],"type":"Point"}
}