{
  "type": "Feature",
  "properties": {
    "gn:admin1_code":"5",
    "gn:admin2_code":"PC",
    "gn:admin3_code":"33016.0",
    "gn:asciiname":"Vezzera",
    "gn:country_code":"IT",
    "gn:dem":285,
    "gn:feature_class":"P",
    "gn:feature_code":"PPL",
    "gn:name":"Vezzera",
    "gn:population":21,
    "gn:timezone":"Europe/Rome",
    "iso:country":"IT",
    "wof:name":"Vezzera",
    "wof:placetype":"locality",
    "wof:population":21
},
  "geometry": {"coordinates":[9.49852,44.81637],"type":"Point"}
}