{
  "type": "Feature",
  "properties": {
    "gn:admin1_code":"16",
    "gn:admin2_code":"AR",
    "gn:admin3_code":"51006.0",
    "gn:asciiname":"Bibbiano",
    "gn:country_code":"IT",
    "gn:dem":483,
    "gn:feature_class":"P",
    "gn:feature_code":"PPL",
    "gn:name":"Bibbiano",
    "gn:population":55,
    "gn:timezone":"Europe/Rome",
    "iso:country":"IT",
    "wof:name":"Bibbiano",
    "wof:placetype":"locality",
    "wof:population":55
},
  "geometry": {"coordinates":[11.82206,43.57281],"type":"Point"}
}