{
  "type": "Feature",
  "properties": {
    "gn:admin1_code":"16",
    "gn:admin2_code":"AR",
    "gn:admin3_code":"51006.0",
    "gn:asciiname":"Bibbiano",
    "gn:country_code":"IT",
    "gn:dem":483,
    "gn:feature_class":"P",
    "gn:feature_code":"PPL",
    "gn:name":"Bibbiano",
    "gn:population":55,
    "gn:timezone":"Europe/Rome",
    "iso:country":"IT",
    "name:ara_x_preferred":[
        "\u0628\u064a\u0628\u064a\u0627\u0646\u0648"
    ],
    "name:azb_x_preferred":[
        "\u0628\u06cc\u0628\u06cc\u0627\u0646\u0648"
    ],
    "name:bul_x_preferred":[
        "\u0411\u0438\u0431\u0438\u0430\u043d\u043e"
    ],
    "name:ceb_x_preferred":[
        "Bibbiano"
    ],
    "name:deu_x_preferred":[
        "Bibbiano"
    ],
    "name:eml_x_preferred":[
        "Bibi\u00e2n"
    ],
    "name:epo_x_preferred":[
        "Bibbiano"
    ],
    "name:eus_x_preferred":[
        "Bibbiano"
    ],
    "name:fas_x_preferred":[
        "\u0628\u06cc\u0628\u06cc\u0627\u0646\u0648"
    ],
    "name:fra_x_preferred":[
        "Bibbiano"
    ],
    "name:glg_x_preferred":[
        "Bibbiano"
    ],
    "name:hun_x_preferred":[
        "Bibbiano"
    ],
    "name:hye_x_preferred":[
        "\u0532\u056b\u0562\u056b\u0561\u0576\u0578"
    ],
    "name:ina_x_preferred":[
        "Bibbiano"
    ],
    "name:ita_x_preferred":[
        "Bibbiano"
    ],
    "name:jpn_x_preferred":[
        "\u30d3\u30c3\u30d3\u30a2\u30fc\u30ce"
    ],
    "name:kaz_x_preferred":[
        "\u0411\u0438\u0431\u0431\u044c\u044f\u043d\u043e"
    ],
    "name:lat_x_preferred":[
        "Bibianum"
    ],
    "name:lmo_x_preferred":[
        "Bibbiano"
    ],
    "name:msa_x_preferred":[
        "Bibbiano"
    ],
    "name:nap_x_preferred":[
        "Bibbiano"
    ],
    "name:nld_x_preferred":[
        "Bibbiano"
    ],
    "name:pms_x_preferred":[
        "Bibbiano"
    ],
    "name:pol_x_preferred":[
        "Bibbiano"
    ],
    "name:por_x_preferred":[
        "Bibbiano"
    ],
    "name:ron_x_preferred":[
        "Bibbiano"
    ],
    "name:rus_x_preferred":[
        "\u0411\u0438\u0431\u0431\u044c\u044f\u043d\u043e"
    ],
    "name:spa_x_preferred":[
        "Bibbiano"
    ],
    "name:srp_x_preferred":[
        "\u0411\u0438\u0431\u0438\u0458\u0430\u043d\u043e"
    ],
    "name:ukr_x_preferred":[
        "\u0411\u0456\u0431\u0431'\u044f\u043d\u043e"
    ],
    "name:uzb_x_preferred":[
        "Bibbiano"
    ],
    "name:vie_x_preferred":[
        "Bibbiano"
    ],
    "name:vol_x_preferred":[
        "Bibbiano"
    ],
    "name:war_x_preferred":[
        "Bibbiano"
    ],
    "name:zho_x_preferred":[
        "\u6bd4\u6bd4\u4e9a\u8bfa"
    ],
    "wof:name":"Bibbiano",
    "wof:placetype":"locality",
    "wof:population":55
},
  "geometry": {"coordinates":[11.82206,43.57281],"type":"Point"}
}