{
  "type": "Feature",
  "properties": {
    "gn:admin1_code":"2",
    "gn:admin2_code":"PZ",
    "gn:admin3_code":"76042.0",
    "gn:asciiname":"Pisciolo Vetrano",
    "gn:country_code":"IT",
    "gn:dem":740,
    "gn:feature_class":"P",
    "gn:feature_code":"PPL",
    "gn:name":"Pisciolo Vetrano",
    "gn:population":35,
    "gn:timezone":"Europe/Rome",
    "iso:country":"IT",
    "wof:name":"Pisciolo Vetrano",
    "wof:placetype":"locality",
    "wof:population":35
},
  "geometry": {"coordinates":[15.85543,40.07001],"type":"Point"}
}