{
  "type": "Feature",
  "properties": {
    "gn:admin1_code":"20.0",
    "gn:admin2_code":"TV",
    "gn:admin3_code":"26086.0",
    "gn:asciiname":"San Pelagio",
    "gn:country_code":"IT",
    "gn:dem":20,
    "gn:feature_class":"P",
    "gn:feature_code":"PPL",
    "gn:name":"San Pelagio",
    "gn:population":0,
    "gn:timezone":"Europe/Rome",
    "iso:country":"IT",
    "wof:name":"San Pelagio",
    "wof:placetype":"locality"
},
  "geometry": {"coordinates":[12.22722,45.69639],"type":"Point"}
}