{
  "type": "Feature",
  "properties": {
    "gn:admin1_code":"20",
    "gn:admin2_code":"VE",
    "gn:admin3_code":"27035.0",
    "gn:asciiname":"Mazzacavallo",
    "gn:country_code":"IT",
    "gn:dem":12,
    "gn:feature_class":"P",
    "gn:feature_code":"PPL",
    "gn:name":"Mazzacavallo",
    "gn:population":31,
    "gn:timezone":"Europe/Rome",
    "iso:country":"IT",
    "wof:name":"Mazzacavallo",
    "wof:placetype":"locality",
    "wof:population":31
},
  "geometry": {"coordinates":[12.03386,45.53332],"type":"Point"}
}