{
  "type": "Feature",
  "properties": {
    "gn:admin1_code":"12",
    "gn:admin2_code":"AL",
    "gn:admin3_code":"6004.0",
    "gn:asciiname":"Casarello",
    "gn:country_code":"IT",
    "gn:dem":252,
    "gn:feature_class":"P",
    "gn:feature_code":"PPL",
    "gn:name":"Casarello",
    "gn:population":57,
    "gn:timezone":"Europe/Rome",
    "iso:country":"IT",
    "wof:name":"Casarello",
    "wof:placetype":"locality",
    "wof:population":57
},
  "geometry": {"coordinates":[8.19841,45.04671],"type":"Point"}
}