{
  "type": "Feature",
  "properties": {
    "gn:admin1_code":"9",
    "gn:admin2_code":"PV",
    "gn:admin3_code":"18111.0",
    "gn:asciiname":"Pecorara",
    "gn:country_code":"IT",
    "gn:dem":228,
    "gn:feature_class":"P",
    "gn:feature_code":"PPL",
    "gn:name":"Pecorara",
    "gn:population":36,
    "gn:timezone":"Europe/Rome",
    "iso:country":"IT",
    "wof:name":"Pecorara",
    "wof:placetype":"locality",
    "wof:population":36
},
  "geometry": {"coordinates":[9.22741,45.03421],"type":"Point"}
}