{
  "type": "Feature",
  "properties": {
    "gn:admin1_code":"9",
    "gn:admin2_code":"PV",
    "gn:admin3_code":"18111.0",
    "gn:asciiname":"Pecorara",
    "gn:country_code":"IT",
    "gn:dem":228,
    "gn:feature_class":"P",
    "gn:feature_code":"PPL",
    "gn:name":"Pecorara",
    "gn:population":36,
    "gn:timezone":"Europe/Rome",
    "iso:country":"IT",
    "name:ara_x_preferred":[
        "\u0628\u064a\u0643\u0648\u0631\u0627\u0631\u0627"
    ],
    "name:azb_x_preferred":[
        "\u067e\u06a9\u0648\u0631\u0627\u0631\u0627"
    ],
    "name:bel_x_preferred":[
        "\u041f\u0435\u043a\u0430\u0440\u0430\u0440\u0430"
    ],
    "name:bul_x_preferred":[
        "\u041f\u0435\u043a\u043e\u0440\u0430\u0440\u0430"
    ],
    "name:ceb_x_preferred":[
        "Pecorara"
    ],
    "name:deu_x_preferred":[
        "Pecorara"
    ],
    "name:eml_x_preferred":[
        "P\u00fcgr\u00e8ra"
    ],
    "name:epo_x_preferred":[
        "Pecorara"
    ],
    "name:eus_x_preferred":[
        "Pecorara"
    ],
    "name:fas_x_preferred":[
        "\u067e\u06a9\u0648\u0631\u0627\u0631\u0627"
    ],
    "name:fra_x_preferred":[
        "Pecorara"
    ],
    "name:hun_x_preferred":[
        "Pecorara"
    ],
    "name:hye_x_preferred":[
        "\u054a\u0565\u056f\u0578\u0580\u0561\u0580\u0561"
    ],
    "name:ina_x_preferred":[
        "Pecorara"
    ],
    "name:ita_x_preferred":[
        "Pecorara"
    ],
    "name:jpn_x_preferred":[
        "\u30da\u30b3\u30e9\u30fc\u30e9"
    ],
    "name:kaz_x_preferred":[
        "\u041f\u0435\u043a\u043e\u0440\u0430\u0440\u0430"
    ],
    "name:kik_x_preferred":[
        "Pecorara"
    ],
    "name:lat_x_preferred":[
        "Pecoraria"
    ],
    "name:lmo_x_preferred":[
        "Pecorara"
    ],
    "name:msa_x_preferred":[
        "Pecorara"
    ],
    "name:nap_x_preferred":[
        "Pecorara"
    ],
    "name:nld_x_preferred":[
        "Pecorara"
    ],
    "name:pms_x_preferred":[
        "Pecorara"
    ],
    "name:pol_x_preferred":[
        "Pecorara"
    ],
    "name:por_x_preferred":[
        "Pecorara"
    ],
    "name:ron_x_preferred":[
        "Pecorara"
    ],
    "name:rus_x_preferred":[
        "\u041f\u0435\u043a\u043e\u0440\u0430\u0440\u0430"
    ],
    "name:spa_x_preferred":[
        "Pecorara"
    ],
    "name:ukr_x_preferred":[
        "\u041f\u0435\u043a\u043e\u0440\u0430\u0440\u0430"
    ],
    "name:uzb_x_preferred":[
        "Pecorara"
    ],
    "name:vol_x_preferred":[
        "Pecorara"
    ],
    "name:war_x_preferred":[
        "Pecorara"
    ],
    "name:zho_x_preferred":[
        "\u4f69\u79d1\u62c9\u62c9"
    ],
    "wof:name":"Pecorara",
    "wof:placetype":"locality",
    "wof:population":36
},
  "geometry": {"coordinates":[9.22741,45.03421],"type":"Point"}
}