{
  "type": "Feature",
  "properties": {
    "gn:admin1_code":"12",
    "gn:admin2_code":"CN",
    "gn:admin3_code":"4078.0",
    "gn:asciiname":"Cascina Bonada",
    "gn:country_code":"IT",
    "gn:dem":468,
    "gn:feature_class":"P",
    "gn:feature_code":"PPL",
    "gn:name":"Cascina Bonada",
    "gn:population":20,
    "gn:timezone":"Europe/Rome",
    "iso:country":"IT",
    "wof:name":"Cascina Bonada",
    "wof:placetype":"locality",
    "wof:population":20
},
  "geometry": {"coordinates":[7.56886,44.44929000000001],"type":"Point"}
}