{
  "type": "Feature",
  "properties": {
    "gn:admin1_code":"12",
    "gn:admin2_code":"TO",
    "gn:admin3_code":"1278.0",
    "gn:asciiname":"Cappia",
    "gn:country_code":"IT",
    "gn:dem":1195,
    "gn:feature_class":"P",
    "gn:feature_code":"PPLL",
    "gn:name":"Cappia",
    "gn:population":8,
    "gn:timezone":"Europe/Rome",
    "iso:country":"IT",
    "wof:name":"Cappia",
    "wof:placetype":"locality",
    "wof:population":8
},
  "geometry": {"coordinates":[7.71519,45.52555],"type":"Point"}
}