{
  "type": "Feature",
  "properties": {
    "gn:admin1_code":"9",
    "gn:admin2_code":"VA",
    "gn:admin3_code":"12073.0",
    "gn:asciiname":"Roccolo",
    "gn:country_code":"IT",
    "gn:dem":422,
    "gn:feature_class":"P",
    "gn:feature_code":"PPL",
    "gn:name":"Roccolo",
    "gn:population":41,
    "gn:timezone":"Europe/Rome",
    "iso:country":"IT",
    "wof:name":"Roccolo",
    "wof:placetype":"locality",
    "wof:population":41
},
  "geometry": {"coordinates":[8.83239,45.77376],"type":"Point"}
}