{
  "type": "Feature",
  "properties": {
    "gn:admin1_code":"20",
    "gn:admin2_code":"BL",
    "gn:admin3_code":"25049.0",
    "gn:asciiname":"Pianezze-Val di Zat",
    "gn:country_code":"IT",
    "gn:dem":1261,
    "gn:feature_class":"P",
    "gn:feature_code":"PPL",
    "gn:name":"Pianezze-Val di Zat",
    "gn:population":29,
    "gn:timezone":"Europe/Rome",
    "iso:country":"IT",
    "wof:name":"Pianezze-Val di Zat",
    "wof:placetype":"locality",
    "wof:population":29
},
  "geometry": {"coordinates":[11.96248,46.38388],"type":"Point"}
}