{
  "type": "Feature",
  "properties": {
    "gn:admin1_code":"15",
    "gn:admin2_code":"RG",
    "gn:admin3_code":"88006.0",
    "gn:asciiname":"Cottonera",
    "gn:country_code":"IT",
    "gn:dem":525,
    "gn:feature_class":"P",
    "gn:feature_code":"PPL",
    "gn:name":"Cottonera",
    "gn:population":20,
    "gn:timezone":"Europe/Rome",
    "iso:country":"IT",
    "wof:name":"Cottonera",
    "wof:placetype":"locality",
    "wof:population":20
},
  "geometry": {"coordinates":[14.84071,37.03746],"type":"Point"}
}