{
  "type": "Feature",
  "properties": {
    "gn:admin1_code":"5",
    "gn:admin2_code":"BO",
    "gn:admin3_code":"37038.0",
    "gn:asciiname":"Il Melo",
    "gn:country_code":"IT",
    "gn:dem":15,
    "gn:feature_class":"P",
    "gn:feature_code":"PPL",
    "gn:name":"Il Melo",
    "gn:population":15,
    "gn:timezone":"Europe/Rome",
    "iso:country":"IT",
    "wof:name":"Il Melo",
    "wof:placetype":"locality",
    "wof:population":15
},
  "geometry": {"coordinates":[11.4759,44.60316],"type":"Point"}
}