{
  "type": "Feature",
  "properties": {
    "gn:admin1_code":"7",
    "gn:admin2_code":"RM",
    "gn:admin3_code":"58111.0",
    "gn:asciiname":"La Faiola",
    "gn:country_code":"IT",
    "gn:dem":358,
    "gn:feature_class":"P",
    "gn:feature_code":"PPL",
    "gn:name":"La Faiola",
    "gn:population":64,
    "gn:timezone":"Europe/Rome",
    "iso:country":"IT",
    "wof:name":"La Faiola",
    "wof:placetype":"locality",
    "wof:population":64
},
  "geometry": {"coordinates":[12.73215,41.69001],"type":"Point"}
}