{
  "type": "Feature",
  "properties": {
    "gn:admin1_code":"3.0",
    "gn:admin2_code":"CS",
    "gn:admin3_code":"78030.0",
    "gn:asciiname":"Valle la Fontana",
    "gn:country_code":"IT",
    "gn:dem":319,
    "gn:feature_class":"P",
    "gn:feature_code":"PPL",
    "gn:name":"Valle la Fontana",
    "gn:population":50,
    "gn:timezone":"Europe/Rome",
    "iso:country":"IT",
    "wof:name":"Valle la Fontana",
    "wof:placetype":"locality",
    "wof:population":50
},
  "geometry": {"coordinates":[16.27644,39.3575],"type":"Point"}
}