{
  "type": "Feature",
  "properties": {
    "gn:admin1_code":"9",
    "gn:admin2_code":"PV",
    "gn:admin3_code":"18117.0",
    "gn:asciiname":"Casa Minchino",
    "gn:country_code":"IT",
    "gn:dem":296,
    "gn:feature_class":"P",
    "gn:feature_code":"PPL",
    "gn:name":"Casa Minchino",
    "gn:population":67,
    "gn:timezone":"Europe/Rome",
    "iso:country":"IT",
    "wof:name":"Casa Minchino",
    "wof:placetype":"locality",
    "wof:population":67
},
  "geometry": {"coordinates":[9.11105,44.85893],"type":"Point"}
}