{
  "type": "Feature",
  "properties": {
    "gn:admin1_code":"10",
    "gn:admin2_code":"AN",
    "gn:admin3_code":"42006.0",
    "gn:asciiname":"Sbrozzola",
    "gn:country_code":"IT",
    "gn:dem":23,
    "gn:feature_class":"P",
    "gn:feature_code":"PPL",
    "gn:name":"Sbrozzola",
    "gn:population":27,
    "gn:timezone":"Europe/Rome",
    "iso:country":"IT",
    "wof:name":"Sbrozzola",
    "wof:placetype":"locality",
    "wof:population":27
},
  "geometry": {"coordinates":[13.52835,43.51878],"type":"Point"}
}