{
  "type": "Feature",
  "properties": {
    "gn:admin1_code":"12.0",
    "gn:admin2_code":"TO",
    "gn:admin3_code":"1259.0",
    "gn:asciiname":"Richardet",
    "gn:country_code":"IT",
    "gn:dem":2001,
    "gn:feature_class":"P",
    "gn:feature_code":"PPL",
    "gn:name":"Richardet",
    "gn:population":0,
    "gn:timezone":"Europe/Rome",
    "iso:country":"IT",
    "wof:name":"Richardet",
    "wof:placetype":"locality"
},
  "geometry": {"coordinates":[6.88333,45.03333],"type":"Point"}
}