{
  "type": "Feature",
  "properties": {
    "gn:admin1_code":"20.0",
    "gn:admin2_code":"VR",
    "gn:admin3_code":"23043.0",
    "gn:asciiname":"Colombare",
    "gn:country_code":"IT",
    "gn:dem":141,
    "gn:feature_class":"P",
    "gn:feature_code":"PPL",
    "gn:name":"Colombare",
    "gn:population":33,
    "gn:timezone":"Europe/Rome",
    "iso:country":"IT",
    "wof:name":"Colombare",
    "wof:placetype":"locality",
    "wof:population":33
},
  "geometry": {"coordinates":[10.77862,45.48856],"type":"Point"}
}