{
  "type": "Feature",
  "properties": {
    "gn:admin1_code":"5",
    "gn:admin2_code":"PR",
    "gn:admin3_code":"34006.0",
    "gn:asciiname":"Bozzi",
    "gn:country_code":"IT",
    "gn:dem":603,
    "gn:feature_class":"P",
    "gn:feature_code":"PPLL",
    "gn:name":"Bozzi",
    "gn:population":9,
    "gn:timezone":"Europe/Rome",
    "iso:country":"IT",
    "wof:name":"Bozzi",
    "wof:placetype":"locality",
    "wof:population":9
},
  "geometry": {"coordinates":[9.86946,44.51204],"type":"Point"}
}