{
  "type": "Feature",
  "properties": {
    "gn:admin1_code":"20",
    "gn:admin2_code":"PD",
    "gn:admin3_code":"28004.0",
    "gn:asciiname":"Pizzoni",
    "gn:country_code":"IT",
    "gn:dem":6,
    "gn:feature_class":"P",
    "gn:feature_code":"PPL",
    "gn:name":"Pizzoni",
    "gn:population":44,
    "gn:timezone":"Europe/Rome",
    "iso:country":"IT",
    "name:azb_x_preferred":[
        "\u067e\u06cc\u062a\u0632\u0648\u0646\u06cc"
    ],
    "name:bcl_x_preferred":[
        "Pizzoni"
    ],
    "name:bul_x_preferred":[
        "\u041f\u0438\u0446\u043e\u043d\u0438"
    ],
    "name:ceb_x_preferred":[
        "Pizzoni"
    ],
    "name:deu_x_preferred":[
        "Pizzoni"
    ],
    "name:epo_x_preferred":[
        "Pizzoni"
    ],
    "name:eus_x_preferred":[
        "Pizzoni"
    ],
    "name:fas_x_preferred":[
        "\u067e\u06cc\u062a\u0632\u0648\u0646\u06cc"
    ],
    "name:fra_x_preferred":[
        "Pizzoni"
    ],
    "name:hun_x_preferred":[
        "Pizzoni"
    ],
    "name:hye_x_preferred":[
        "\u054a\u056b\u0581\u0578\u0576\u056b"
    ],
    "name:ina_x_preferred":[
        "Pizzoni"
    ],
    "name:ita_x_preferred":[
        "Pizzoni"
    ],
    "name:jpn_x_preferred":[
        "\u30d4\u30c3\u30c4\u30a9\u30fc\u30cb"
    ],
    "name:kaz_x_preferred":[
        "\u041f\u0438\u0446\u0446\u043e\u043d\u0438"
    ],
    "name:lat_x_preferred":[
        "Pizzonum"
    ],
    "name:lmo_x_preferred":[
        "Pizzoni"
    ],
    "name:msa_x_preferred":[
        "Pizzoni"
    ],
    "name:nap_x_preferred":[
        "Pizzoni"
    ],
    "name:nld_x_preferred":[
        "Pizzoni"
    ],
    "name:pms_x_preferred":[
        "Pizzoni"
    ],
    "name:pol_x_preferred":[
        "Pizzoni"
    ],
    "name:por_x_preferred":[
        "Pizzoni"
    ],
    "name:ron_x_preferred":[
        "Pizzoni"
    ],
    "name:rus_x_preferred":[
        "\u041f\u0438\u0446\u0446\u043e\u043d\u0438"
    ],
    "name:scn_x_preferred":[
        "Pizzuni"
    ],
    "name:sco_x_preferred":[
        "Pizzoni"
    ],
    "name:spa_x_preferred":[
        "Pizzoni"
    ],
    "name:srp_x_preferred":[
        "\u041f\u0438\u0446\u043e\u043d\u0438"
    ],
    "name:ukr_x_preferred":[
        "\u041f\u0456\u0446\u0446\u043e\u043d\u0456"
    ],
    "name:uzb_x_preferred":[
        "Pizzoni"
    ],
    "name:vie_x_preferred":[
        "Pizzoni"
    ],
    "name:vol_x_preferred":[
        "Pizzoni"
    ],
    "name:war_x_preferred":[
        "Pizzoni"
    ],
    "name:zho_x_preferred":[
        "\u76ae\u4f50\u5c3c"
    ],
    "wof:name":"Pizzoni",
    "wof:placetype":"locality",
    "wof:population":44
},
  "geometry": {"coordinates":[11.85546,45.13291],"type":"Point"}
}