{
  "type": "Feature",
  "properties": {
    "gn:admin1_code":"20",
    "gn:admin2_code":"PD",
    "gn:admin3_code":"28004.0",
    "gn:asciiname":"Pizzoni",
    "gn:country_code":"IT",
    "gn:dem":6,
    "gn:feature_class":"P",
    "gn:feature_code":"PPL",
    "gn:name":"Pizzoni",
    "gn:population":44,
    "gn:timezone":"Europe/Rome",
    "iso:country":"IT",
    "wof:name":"Pizzoni",
    "wof:placetype":"locality",
    "wof:population":44
},
  "geometry": {"coordinates":[11.85546,45.13291],"type":"Point"}
}