{
  "type": "Feature",
  "properties": {
    "gn:admin1_code":"3",
    "gn:admin2_code":"CS",
    "gn:admin3_code":"78091.0",
    "gn:asciiname":"Scirocco",
    "gn:country_code":"IT",
    "gn:dem":21,
    "gn:feature_class":"P",
    "gn:feature_code":"PPL",
    "gn:name":"Scirocco",
    "gn:population":26,
    "gn:timezone":"Europe/Rome",
    "iso:country":"IT",
    "wof:name":"Scirocco",
    "wof:placetype":"locality",
    "wof:population":26
},
  "geometry": {"coordinates":[16.0422,39.3377],"type":"Point"}
}