{
  "type": "Feature",
  "properties": {
    "gn:admin1_code":"20",
    "gn:admin2_code":"VI",
    "gn:admin3_code":"24006.0",
    "gn:asciiname":"Marani (Mazzanta)",
    "gn:country_code":"IT",
    "gn:dem":354,
    "gn:feature_class":"P",
    "gn:feature_code":"PPL",
    "gn:name":"Marani (Mazzanta)",
    "gn:population":268,
    "gn:timezone":"Europe/Rome",
    "iso:country":"IT",
    "wof:name":"Marani (Mazzanta)",
    "wof:placetype":"locality",
    "wof:population":268
},
  "geometry": {"coordinates":[11.5043,45.45144000000001],"type":"Point"}
}