{
  "type": "Feature",
  "properties": {
    "gn:admin1_code":"12",
    "gn:admin2_code":"TO",
    "gn:admin3_code":"1013.0",
    "gn:asciiname":"Battagliotti",
    "gn:country_code":"IT",
    "gn:dem":487,
    "gn:feature_class":"P",
    "gn:feature_code":"PPL",
    "gn:name":"Battagliotti",
    "gn:population":35,
    "gn:timezone":"Europe/Rome",
    "iso:country":"IT",
    "wof:name":"Battagliotti",
    "wof:placetype":"locality",
    "wof:population":35
},
  "geometry": {"coordinates":[7.37954,45.04505],"type":"Point"}
}