{
  "type": "Feature",
  "properties": {
    "gn:admin1_code":"9",
    "gn:admin2_code":"SO",
    "gn:admin3_code":"14067.0",
    "gn:asciiname":"Tornadu",
    "gn:country_code":"IT",
    "gn:dem":701,
    "gn:feature_class":"P",
    "gn:feature_code":"PPL",
    "gn:name":"Tornad\u00f9",
    "gn:population":47,
    "gn:timezone":"Europe/Rome",
    "iso:country":"IT",
    "name:und_x_variant":[
        "Tornad\u00f9"
    ],
    "wof:name":"Tornadu",
    "wof:placetype":"locality",
    "wof:population":47
},
  "geometry": {"coordinates":[9.85644,46.22721],"type":"Point"}
}