{
  "type": "Feature",
  "properties": {
    "gn:admin1_code":"20",
    "gn:admin2_code":"PD",
    "gn:admin3_code":"28077.0",
    "gn:asciiname":"Case Neschi",
    "gn:country_code":"IT",
    "gn:dem":33,
    "gn:feature_class":"P",
    "gn:feature_code":"PPL",
    "gn:name":"Case Neschi",
    "gn:population":44,
    "gn:timezone":"Europe/Rome",
    "iso:country":"IT",
    "wof:name":"Case Neschi",
    "wof:placetype":"locality",
    "wof:population":44
},
  "geometry": {"coordinates":[11.85435,45.63027],"type":"Point"}
}