{
  "type": "Feature",
  "properties": {
    "gn:admin1_code":"8",
    "gn:admin2_code":"SV",
    "gn:admin3_code":"9051.0",
    "gn:asciiname":"Carmine-La Pineta-Vernetta",
    "gn:country_code":"IT",
    "gn:dem":494,
    "gn:feature_class":"P",
    "gn:feature_code":"PPL",
    "gn:name":"Carmine-La Pineta-Vernetta",
    "gn:population":131,
    "gn:timezone":"Europe/Rome",
    "iso:country":"IT",
    "wof:name":"Carmine-La Pineta-Vernetta",
    "wof:placetype":"locality",
    "wof:population":131
},
  "geometry": {"coordinates":[8.45045,44.43782],"type":"Point"}
}