{
  "type": "Feature",
  "properties": {
    "gn:admin1_code":"15",
    "gn:admin2_code":"SR",
    "gn:admin3_code":"89017.0",
    "gn:asciiname":"Villaggio Santa Lucia",
    "gn:country_code":"IT",
    "gn:dem":140,
    "gn:feature_class":"P",
    "gn:feature_code":"PPL",
    "gn:name":"Villaggio Santa Lucia",
    "gn:population":206,
    "gn:timezone":"Europe/Rome",
    "iso:country":"IT",
    "wof:name":"Villaggio Santa Lucia",
    "wof:placetype":"locality",
    "wof:population":206
},
  "geometry": {"coordinates":[15.18418,37.11074],"type":"Point"}
}