{
  "type": "Feature",
  "properties": {
    "gn:admin1_code":"5.0",
    "gn:admin2_code":"FE",
    "gn:admin3_code":"38010.0",
    "gn:asciiname":"Foscarina",
    "gn:country_code":"IT",
    "gn:dem":-5,
    "gn:feature_class":"P",
    "gn:feature_code":"PPL",
    "gn:name":"Foscarina",
    "gn:population":12,
    "gn:timezone":"Europe/Rome",
    "iso:country":"IT",
    "wof:name":"Foscarina",
    "wof:placetype":"locality",
    "wof:population":12
},
  "geometry": {"coordinates":[12.03101,44.93348],"type":"Point"}
}