{
  "type": "Feature",
  "properties": {
    "gn:admin1_code":"11.0",
    "gn:admin2_code":"CB",
    "gn:admin3_code":"70006.0",
    "gn:asciiname":"Feudo II",
    "gn:country_code":"IT",
    "gn:dem":633,
    "gn:feature_class":"P",
    "gn:feature_code":"PPL",
    "gn:name":"Feudo II",
    "gn:population":38,
    "gn:timezone":"Europe/Rome",
    "iso:country":"IT",
    "wof:name":"Feudo II",
    "wof:placetype":"locality",
    "wof:population":38
},
  "geometry": {"coordinates":[14.70355,41.57289],"type":"Point"}
}