{
  "type": "Feature",
  "properties": {
    "gn:admin1_code":"9",
    "gn:admin2_code":"BS",
    "gn:admin3_code":"17111.0",
    "gn:asciiname":"Olzano",
    "gn:country_code":"IT",
    "gn:dem":335,
    "gn:feature_class":"P",
    "gn:feature_code":"PPL",
    "gn:name":"Olzano",
    "gn:population":29,
    "gn:timezone":"Europe/Rome",
    "iso:country":"IT",
    "wof:name":"Olzano",
    "wof:placetype":"locality",
    "wof:population":29
},
  "geometry": {"coordinates":[10.08806,45.71569],"type":"Point"}
}