{
  "type": "Feature",
  "properties": {
    "gn:admin1_code":"20",
    "gn:admin2_code":"VR",
    "gn:admin3_code":"23018.0",
    "gn:asciiname":"Bran",
    "gn:country_code":"IT",
    "gn:dem":220,
    "gn:feature_class":"P",
    "gn:feature_code":"PPL",
    "gn:name":"Bran",
    "gn:population":11,
    "gn:timezone":"Europe/Rome",
    "iso:country":"IT",
    "wof:name":"Bran",
    "wof:placetype":"locality",
    "wof:population":11
},
  "geometry": {"coordinates":[10.77125,45.5847],"type":"Point"}
}