{
  "type": "Feature",
  "properties": {
    "gn:admin1_code":"20",
    "gn:admin2_code":"VR",
    "gn:admin3_code":"23018.0",
    "gn:asciiname":"Bran",
    "gn:country_code":"IT",
    "gn:dem":220,
    "gn:feature_class":"P",
    "gn:feature_code":"PPL",
    "gn:name":"Bran",
    "gn:population":11,
    "gn:timezone":"Europe/Rome",
    "iso:country":"IT",
    "name:ara_x_preferred":[
        "\u0646\u062e\u0627\u0644\u0629"
    ],
    "name:bar_x_preferred":[
        "Gleim"
    ],
    "name:bul_x_preferred":[
        "\u0422\u0440\u0438\u0446\u0438"
    ],
    "name:cat_x_preferred":[
        "Seg\u00f3"
    ],
    "name:ces_x_preferred":[
        "Otruby"
    ],
    "name:dan_x_preferred":[
        "Klid"
    ],
    "name:deu_x_preferred":[
        "Kleie"
    ],
    "name:epo_x_preferred":[
        "Brano"
    ],
    "name:est_x_preferred":[
        "Kliid"
    ],
    "name:eus_x_preferred":[
        "Zahi"
    ],
    "name:fas_x_preferred":[
        "\u0633\u0628\u0648\u0633"
    ],
    "name:fin_x_preferred":[
        "Leseet"
    ],
    "name:fra_x_preferred":[
        "Son"
    ],
    "name:gle_x_preferred":[
        "Bran"
    ],
    "name:glg_x_preferred":[
        "Farelo"
    ],
    "name:heb_x_preferred":[
        "\u05e1\u05d5\u05d1\u05d9\u05df"
    ],
    "name:hin_x_preferred":[
        "\u091a\u094b\u0915\u0930"
    ],
    "name:hun_x_preferred":[
        "Korpa"
    ],
    "name:ido_x_preferred":[
        "Brano"
    ],
    "name:ilo_x_preferred":[
        "Tuyo"
    ],
    "name:ind_x_preferred":[
        "Bekatul"
    ],
    "name:ita_x_preferred":[
        "Crusca"
    ],
    "name:kan_x_preferred":[
        "\u0ca4\u0ccc\u0ca1\u0cc1"
    ],
    "name:kaz_x_preferred":[
        "\u041a\u0435\u0431\u0435\u043a"
    ],
    "name:lit_x_preferred":[
        "S\u0117lenos"
    ],
    "name:mal_x_preferred":[
        "\u0d24\u0d35\u0d3f\u0d1f\u0d4d"
    ],
    "name:nld_x_preferred":[
        "Zemelen"
    ],
    "name:nor_x_preferred":[
        "Kli"
    ],
    "name:pol_x_preferred":[
        "Otr\u0119by"
    ],
    "name:por_x_preferred":[
        "Farelo"
    ],
    "name:que_x_preferred":[
        "Hamchi"
    ],
    "name:ron_x_preferred":[
        "T\u0103r\u00e2\u021b\u0103"
    ],
    "name:rus_x_preferred":[
        "\u041e\u0442\u0440\u0443\u0431\u0438"
    ],
    "name:scn_x_preferred":[
        "Canigghia"
    ],
    "name:slv_x_preferred":[
        "Otrobi"
    ],
    "name:snd_x_preferred":[
        "\u0687\u0627\u06bb"
    ],
    "name:spa_x_preferred":[
        "Salvado"
    ],
    "name:srd_x_preferred":[
        "Ghilingione"
    ],
    "name:srp_x_preferred":[
        "\u041c\u0435\u043a\u0438\u045a\u0435"
    ],
    "name:sun_x_preferred":[
        "Bakatul"
    ],
    "name:swe_x_preferred":[
        "Kli"
    ],
    "name:tel_x_preferred":[
        "\u0c24\u0c35\u0c41\u0c21\u0c41"
    ],
    "name:tgk_x_preferred":[
        "\u0421\u0430\u0431\u04ef\u0441"
    ],
    "name:tur_x_preferred":[
        "Kepek"
    ],
    "name:ukr_x_preferred":[
        "\u0412\u0438\u0441\u0456\u0432\u043a\u0438"
    ],
    "name:vie_x_preferred":[
        "C\u00e1m"
    ],
    "name:wln_x_preferred":[
        "Laton"
    ],
    "wof:name":"Bran",
    "wof:placetype":"locality",
    "wof:population":11
},
  "geometry": {"coordinates":[10.77125,45.5847],"type":"Point"}
}