{
  "type": "Feature",
  "properties": {
    "gn:admin1_code":"10.0",
    "gn:admin2_code":"PU",
    "gn:admin3_code":"41006.0",
    "gn:asciiname":"Sompiano",
    "gn:cc2":"IT",
    "gn:country_code":"IT",
    "gn:dem":527,
    "gn:elevation":"528.0",
    "gn:feature_class":"P",
    "gn:feature_code":"PPL",
    "gn:name":"Sompiano",
    "gn:population":42,
    "gn:timezone":"Europe/Rome",
    "iso:country":"IT",
    "name:und_x_variant":[
        "Sampiano"
    ],
    "wof:name":"Sompiano",
    "wof:placetype":"locality",
    "wof:population":42
},
  "geometry": {"coordinates":[12.27682,43.63557],"type":"Point"}
}