{
  "type": "Feature",
  "properties": {
    "gn:admin1_code":"16",
    "gn:admin2_code":"PI",
    "gn:admin3_code":"50031.0",
    "gn:asciiname":"Castelnuovo",
    "gn:country_code":"IT",
    "gn:dem":4,
    "gn:feature_class":"P",
    "gn:feature_code":"PPL",
    "gn:name":"Castelnuovo",
    "gn:population":111,
    "gn:timezone":"Europe/Rome",
    "iso:country":"IT",
    "name:bel_x_preferred":[
        "\u041a\u0430\u0441\u0442\u044d\u043b\u044c\u043d\u0443\u043e\u0432\u0430"
    ],
    "name:bul_x_preferred":[
        "\u041a\u0430\u0441\u0442\u0435\u043b\u043d\u0443\u043e\u0432\u043e"
    ],
    "name:cat_x_preferred":[
        "Castelnuovo"
    ],
    "name:ceb_x_preferred":[
        "Castelnuovo"
    ],
    "name:deu_x_preferred":[
        "Castelnuovo"
    ],
    "name:eml_x_preferred":[
        "Casteln\u00f6f"
    ],
    "name:fra_x_preferred":[
        "Castelnuovo"
    ],
    "name:hun_x_preferred":[
        "Castelnuovo"
    ],
    "name:ita_x_preferred":[
        "Castelnuovo"
    ],
    "name:lmo_x_preferred":[
        "Castelnuovo"
    ],
    "name:nld_x_preferred":[
        "Castelnuovo"
    ],
    "name:pms_x_preferred":[
        "Castelnuovo"
    ],
    "name:por_x_preferred":[
        "Castelnuovo"
    ],
    "name:rus_x_preferred":[
        "\u041a\u0430\u0441\u0442\u0435\u043b\u044c\u043d\u0443\u043e\u0432\u043e"
    ],
    "name:sco_x_preferred":[
        "Castelnuovo"
    ],
    "name:spa_x_preferred":[
        "Castelnuovo"
    ],
    "name:srp_x_preferred":[
        "Kastelnuovo"
    ],
    "name:swe_x_preferred":[
        "Castelnuovo"
    ],
    "wof:name":"Castelnuovo",
    "wof:placetype":"locality",
    "wof:population":111
},
  "geometry": {"coordinates":[10.36829,43.76324],"type":"Point"}
}