{
  "type": "Feature",
  "properties": {
    "gn:admin1_code":"20",
    "gn:admin2_code":"TV",
    "gn:admin3_code":"26010.0",
    "gn:asciiname":"Case Cadamuro",
    "gn:country_code":"IT",
    "gn:dem":9,
    "gn:feature_class":"P",
    "gn:feature_code":"PPL",
    "gn:name":"Case Cadamuro",
    "gn:population":29,
    "gn:timezone":"Europe/Rome",
    "iso:country":"IT",
    "wof:name":"Case Cadamuro",
    "wof:placetype":"locality",
    "wof:population":29
},
  "geometry": {"coordinates":[12.26935,45.63327],"type":"Point"}
}