{
  "type": "Feature",
  "properties": {
    "gn:admin1_code":"15.0",
    "gn:admin2_code":"TP",
    "gn:admin3_code":"81005.0",
    "gn:asciiname":"Scopello",
    "gn:country_code":"IT",
    "gn:dem":63,
    "gn:elevation":"106.0",
    "gn:feature_class":"P",
    "gn:feature_code":"PPL",
    "gn:name":"Scopello",
    "gn:population":81,
    "gn:timezone":"Europe/Rome",
    "iso:country":"IT",
    "name:ara_x_preferred":[
        "\u0633\u0643\u0648\u0628\u064a\u0644\u0648"
    ],
    "name:azb_x_preferred":[
        "\u0633\u06a9\u0648\u067e\u0644\u0648"
    ],
    "name:bar_x_preferred":[
        "Scopello"
    ],
    "name:bel_x_preferred":[
        "\u0421\u043a\u0430\u043f\u0435\u043b\u0430"
    ],
    "name:bul_x_preferred":[
        "\u0421\u043a\u043e\u043f\u0435\u043b\u043e"
    ],
    "name:ceb_x_preferred":[
        "Scopello"
    ],
    "name:ces_x_preferred":[
        "Scopello"
    ],
    "name:deu_x_preferred":[
        "Scopello"
    ],
    "name:epo_x_preferred":[
        "Scopello"
    ],
    "name:eus_x_preferred":[
        "Scopello"
    ],
    "name:fas_x_preferred":[
        "\u0633\u06a9\u0648\u067e\u0644\u0648"
    ],
    "name:fin_x_preferred":[
        "Scopello"
    ],
    "name:fra_x_preferred":[
        "Scopello"
    ],
    "name:hun_x_preferred":[
        "Scopello"
    ],
    "name:hye_x_preferred":[
        "\u054d\u056f\u0578\u057a\u0565\u056c\u0578"
    ],
    "name:ind_x_preferred":[
        "Scopello"
    ],
    "name:ita_x_preferred":[
        "Scopello"
    ],
    "name:jpn_x_preferred":[
        "\u30b9\u30b3\u30da\u30c3\u30ed"
    ],
    "name:kaz_x_preferred":[
        "\u0421\u043a\u043e\u043f\u0435\u043b\u043b\u043e"
    ],
    "name:lat_x_preferred":[
        "Scopellum"
    ],
    "name:lmo_x_preferred":[
        "Scupel"
    ],
    "name:msa_x_preferred":[
        "Scopello"
    ],
    "name:nap_x_preferred":[
        "Scopello"
    ],
    "name:nld_x_preferred":[
        "Scopello"
    ],
    "name:pms_x_preferred":[
        "Scop\u00e9l"
    ],
    "name:pol_x_preferred":[
        "Scopello"
    ],
    "name:por_x_preferred":[
        "Scopello"
    ],
    "name:ron_x_preferred":[
        "Scopello"
    ],
    "name:rus_x_preferred":[
        "\u0421\u043a\u043e\u043f\u0435\u043b\u043b\u043e"
    ],
    "name:scn_x_preferred":[
        "Scopello"
    ],
    "name:spa_x_preferred":[
        "Scopello"
    ],
    "name:srp_x_preferred":[
        "\u0421\u043a\u043e\u043f\u0435\u043b\u043e"
    ],
    "name:swe_x_preferred":[
        "Scopello"
    ],
    "name:tgl_x_preferred":[
        "Scopello"
    ],
    "name:ukr_x_preferred":[
        "\u0421\u043a\u043e\u043f\u0435\u043b\u043b\u043e"
    ],
    "name:uzb_x_preferred":[
        "Scopello"
    ],
    "name:vol_x_preferred":[
        "Scopello"
    ],
    "name:war_x_preferred":[
        "Scopello"
    ],
    "name:zho_x_preferred":[
        "\u65af\u79d1\u4f69\u6d1b"
    ],
    "wof:name":"Scopello",
    "wof:placetype":"locality",
    "wof:population":81
},
  "geometry": {"coordinates":[12.81387,38.07573],"type":"Point"}
}