{
  "type": "Feature",
  "properties": {
    "gn:admin1_code":"15.0",
    "gn:admin2_code":"TP",
    "gn:admin3_code":"81005.0",
    "gn:asciiname":"Scopello",
    "gn:country_code":"IT",
    "gn:dem":63,
    "gn:elevation":"106.0",
    "gn:feature_class":"P",
    "gn:feature_code":"PPL",
    "gn:name":"Scopello",
    "gn:population":81,
    "gn:timezone":"Europe/Rome",
    "iso:country":"IT",
    "wof:name":"Scopello",
    "wof:placetype":"locality",
    "wof:population":81
},
  "geometry": {"coordinates":[12.81387,38.07573],"type":"Point"}
}