{
  "type": "Feature",
  "properties": {
    "gn:admin1_code":"5.0",
    "gn:admin2_code":"FE",
    "gn:admin3_code":"38023.0",
    "gn:asciiname":"Montesanto",
    "gn:country_code":"IT",
    "gn:dem":0,
    "gn:elevation":"3.0",
    "gn:feature_class":"P",
    "gn:feature_code":"PPL",
    "gn:name":"Montesanto",
    "gn:population":301,
    "gn:timezone":"Europe/Rome",
    "iso:country":"IT",
    "wof:name":"Montesanto",
    "wof:placetype":"locality",
    "wof:population":301
},
  "geometry": {"coordinates":[11.72677,44.72957],"type":"Point"}
}