{
  "type": "Feature",
  "properties": {
    "gn:admin1_code":"13.0",
    "gn:admin2_code":"LE",
    "gn:admin3_code":"75035.0",
    "gn:asciiname":"Marangi",
    "gn:country_code":"IT",
    "gn:dem":29,
    "gn:feature_class":"P",
    "gn:feature_code":"PPL",
    "gn:name":"Marangi",
    "gn:population":92,
    "gn:timezone":"Europe/Rome",
    "iso:country":"IT",
    "wof:name":"Marangi",
    "wof:placetype":"locality",
    "wof:population":92
},
  "geometry": {"coordinates":[18.22983,40.36785],"type":"Point"}
}