{
  "type": "Feature",
  "properties": {
    "gn:admin1_code":"5.0",
    "gn:admin2_code":"RE",
    "gn:admin3_code":"35038.0",
    "gn:asciiname":"Villa Bonini",
    "gn:country_code":"IT",
    "gn:dem":167,
    "gn:feature_class":"P",
    "gn:feature_code":"PPL",
    "gn:name":"Villa Bonini",
    "gn:population":0,
    "gn:timezone":"Europe/Rome",
    "iso:country":"IT",
    "wof:name":"Villa Bonini",
    "wof:placetype":"locality"
},
  "geometry": {"coordinates":[10.43333,44.63333],"type":"Point"}
}