{
  "type": "Feature",
  "properties": {
    "gn:admin1_code":"3",
    "gn:admin2_code":"CZ",
    "gn:admin3_code":"79160.0",
    "gn:asciiname":"Vallericciardo Inferiore",
    "gn:country_code":"IT",
    "gn:dem":721,
    "gn:feature_class":"P",
    "gn:feature_code":"PPL",
    "gn:name":"Vallericciardo Inferiore",
    "gn:population":93,
    "gn:timezone":"Europe/Rome",
    "iso:country":"IT",
    "wof:name":"Vallericciardo Inferiore",
    "wof:placetype":"locality",
    "wof:population":93
},
  "geometry": {"coordinates":[16.2418,39.00533],"type":"Point"}
}