{
  "type": "Feature",
  "properties": {
    "gn:admin1_code":"11",
    "gn:admin2_code":"CB",
    "gn:admin3_code":"70022.0",
    "gn:asciiname":"Agostino",
    "gn:country_code":"IT",
    "gn:dem":602,
    "gn:feature_class":"P",
    "gn:feature_code":"PPL",
    "gn:name":"Agostino",
    "gn:population":16,
    "gn:timezone":"Europe/Rome",
    "iso:country":"IT",
    "wof:name":"Agostino",
    "wof:placetype":"locality",
    "wof:population":16
},
  "geometry": {"coordinates":[14.44125,41.65462],"type":"Point"}
}