{
  "type": "Feature",
  "properties": {
    "gn:admin1_code":"20",
    "gn:admin2_code":"PD",
    "gn:admin3_code":"28017.0",
    "gn:asciiname":"Case Chiarello",
    "gn:country_code":"IT",
    "gn:dem":16,
    "gn:feature_class":"P",
    "gn:feature_code":"PPL",
    "gn:name":"Case Chiarello",
    "gn:population":47,
    "gn:timezone":"Europe/Rome",
    "iso:country":"IT",
    "wof:name":"Case Chiarello",
    "wof:placetype":"locality",
    "wof:population":47
},
  "geometry": {"coordinates":[11.88271,45.50344000000001],"type":"Point"}
}