{
  "type": "Feature",
  "properties": {
    "gn:admin1_code":"4",
    "gn:admin2_code":"AV",
    "gn:admin3_code":"64018.0",
    "gn:asciiname":"Currieri",
    "gn:country_code":"IT",
    "gn:dem":506,
    "gn:feature_class":"P",
    "gn:feature_code":"PPL",
    "gn:name":"Currieri",
    "gn:population":48,
    "gn:timezone":"Europe/Rome",
    "iso:country":"IT",
    "wof:name":"Currieri",
    "wof:placetype":"locality",
    "wof:population":48
},
  "geometry": {"coordinates":[14.76669,40.95886],"type":"Point"}
}