{
  "type": "Feature",
  "properties": {
    "gn:admin1_code":"10",
    "gn:admin2_code":"AN",
    "gn:admin3_code":"42019.0",
    "gn:asciiname":"Marinuccia",
    "gn:country_code":"IT",
    "gn:dem":123,
    "gn:feature_class":"P",
    "gn:feature_code":"PPL",
    "gn:name":"Marinuccia",
    "gn:population":31,
    "gn:timezone":"Europe/Rome",
    "iso:country":"IT",
    "wof:name":"Marinuccia",
    "wof:placetype":"locality",
    "wof:population":31
},
  "geometry": {"coordinates":[13.37106,43.46161],"type":"Point"}
}