{
  "type": "Feature",
  "properties": {
    "gn:admin1_code":"9.0",
    "gn:admin2_code":"BS",
    "gn:admin3_code":"17170.0",
    "gn:asciiname":"Cunettone-Villa",
    "gn:country_code":"IT",
    "gn:dem":155,
    "gn:feature_class":"P",
    "gn:feature_code":"PPL",
    "gn:name":"Cunettone-Villa",
    "gn:population":1412,
    "gn:timezone":"Europe/Rome",
    "iso:country":"IT",
    "wof:name":"Cunettone-Villa",
    "wof:placetype":"locality",
    "wof:population":1412
},
  "geometry": {"coordinates":[10.51756,45.58789],"type":"Point"}
}