{
  "type": "Feature",
  "properties": {
    "gn:admin1_code":"9",
    "gn:admin2_code":"LO",
    "gn:admin3_code":"98011.0",
    "gn:asciiname":"Cascina Oratorio",
    "gn:country_code":"IT",
    "gn:dem":43,
    "gn:feature_class":"P",
    "gn:feature_code":"PPL",
    "gn:name":"Cascina Oratorio",
    "gn:population":22,
    "gn:timezone":"Europe/Rome",
    "iso:country":"IT",
    "wof:name":"Cascina Oratorio",
    "wof:placetype":"locality",
    "wof:population":22
},
  "geometry": {"coordinates":[9.79086,45.12148],"type":"Point"}
}