{
  "type": "Feature",
  "properties": {
    "iso:country":"IT",
    "name:deu_x_preferred":[
        "Certosa"
    ],
    "name:rus_x_preferred":[
        "\u0427\u0435\u0440\u0442\u043e\u0437\u0430"
    ],
    "name:srp_x_preferred":[
        "Certosa"
    ],
    "wof:name":"Certosa",
    "wof:placetype":"neighbourhood"
},
  "geometry": {"coordinates":[8.89446871378686,44.42926188600725],"type":"Point"}
}