{
  "type": "Feature",
  "properties": {
    "gn:admin1_code":"9.0",
    "gn:admin2_code":"PV",
    "gn:admin3_code":"18151.0",
    "gn:asciiname":"San Fedele",
    "gn:country_code":"IT",
    "gn:dem":65,
    "gn:feature_class":"P",
    "gn:feature_code":"PPL",
    "gn:name":"San Fedele",
    "gn:population":0,
    "gn:timezone":"Europe/Rome",
    "iso:country":"IT",
    "wof:name":"San Fedele",
    "wof:placetype":"locality"
},
  "geometry": {"coordinates":[9.08333,45.13333],"type":"Point"}
}