{
  "type": "Feature",
  "properties": {
    "gn:admin1_code":"3.0",
    "gn:admin2_code":"CZ",
    "gn:admin3_code":"79147.0",
    "gn:asciiname":"Gagliano",
    "gn:country_code":"IT",
    "gn:dem":124,
    "gn:feature_class":"P",
    "gn:feature_code":"PPL",
    "gn:name":"Gagliano",
    "gn:population":0,
    "gn:timezone":"Europe/Rome",
    "iso:country":"IT",
    "name:ceb_x_preferred":[
        "Gagliano"
    ],
    "name:deu_x_preferred":[
        "Gagliano"
    ],
    "name:fra_x_preferred":[
        "Gagliano"
    ],
    "name:ita_x_preferred":[
        "Gagliano"
    ],
    "name:kor_x_preferred":[
        "\uac08\ub9ac\uc544\ub178"
    ],
    "name:srp_x_preferred":[
        "Galjano"
    ],
    "name:swe_x_preferred":[
        "Gagliano"
    ],
    "wof:name":"Gagliano",
    "wof:placetype":"locality"
},
  "geometry": {"coordinates":[16.55,38.91667],"type":"Point"}
}