{
  "type": "Feature",
  "properties": {
    "gn:admin1_code":"2.0",
    "gn:admin2_code":"PZ",
    "gn:admin3_code":"76042.0",
    "gn:asciiname":"Bivio Capraro",
    "gn:country_code":"IT",
    "gn:dem":673,
    "gn:feature_class":"P",
    "gn:feature_code":"PPL",
    "gn:name":"Bivio Capraro",
    "gn:population":23,
    "gn:timezone":"Europe/Rome",
    "iso:country":"IT",
    "wof:name":"Bivio Capraro",
    "wof:placetype":"locality",
    "wof:population":23
},
  "geometry": {"coordinates":[15.84877,40.0676],"type":"Point"}
}