{
  "type": "Feature",
  "properties": {
    "gn:admin1_code":"10.0",
    "gn:admin2_code":"AP",
    "gn:admin3_code":"44002.0",
    "gn:asciiname":"Sant'Angelo",
    "gn:country_code":"IT",
    "gn:dem":84,
    "gn:elevation":"75.0",
    "gn:feature_class":"P",
    "gn:feature_code":"PPL",
    "gn:name":"Sant'Angelo",
    "gn:population":21,
    "gn:timezone":"Europe/Rome",
    "iso:country":"IT",
    "name:cat_x_preferred":[
        "Sant'Angelo"
    ],
    "name:ceb_x_preferred":[
        "Sant'Angelo"
    ],
    "name:deu_x_preferred":[
        "Sant\u2019Angelo"
    ],
    "name:epo_x_preferred":[
        "Sant'Angelo"
    ],
    "name:heb_x_preferred":[
        "\u05e1\u05e0\u05d8\u05d0\u05e0\u05d2'\u05dc\u05d5"
    ],
    "name:hun_x_preferred":[
        "Sant\u2019Angelo"
    ],
    "name:ita_x_preferred":[
        "Sant'Angelo"
    ],
    "name:nor_x_preferred":[
        "Sant'Angelo"
    ],
    "name:por_x_preferred":[
        "Sant'Angelo"
    ],
    "name:ron_x_preferred":[
        "Sant'Angelo"
    ],
    "name:rus_x_preferred":[
        "\u0421\u0430\u043d\u0442-\u0410\u043d\u0434\u0436\u0435\u043b\u043e"
    ],
    "name:spa_x_preferred":[
        "Sant'Angelo"
    ],
    "name:srp_x_preferred":[
        "Sant'An\u0111elo"
    ],
    "name:swe_x_preferred":[
        "Sant'Angelo"
    ],
    "wof:name":"Sant'Angelo",
    "wof:placetype":"locality",
    "wof:population":21
},
  "geometry": {"coordinates":[13.82827,42.95796],"type":"Point"}
}