{
  "type": "Feature",
  "properties": {
    "gn:admin1_code":"10.0",
    "gn:admin2_code":"AP",
    "gn:admin3_code":"44002.0",
    "gn:asciiname":"Sant'Angelo",
    "gn:country_code":"IT",
    "gn:dem":84,
    "gn:elevation":"75.0",
    "gn:feature_class":"P",
    "gn:feature_code":"PPL",
    "gn:name":"Sant'Angelo",
    "gn:population":21,
    "gn:timezone":"Europe/Rome",
    "iso:country":"IT",
    "wof:name":"Sant'Angelo",
    "wof:placetype":"locality",
    "wof:population":21
},
  "geometry": {"coordinates":[13.82827,42.95796],"type":"Point"}
}