{
  "type": "Feature",
  "properties": {
    "gn:admin1_code":"3.0",
    "gn:admin2_code":"CZ",
    "gn:admin3_code":"79023.0",
    "gn:asciiname":"Barone",
    "gn:country_code":"IT",
    "gn:dem":35,
    "gn:feature_class":"P",
    "gn:feature_code":"PPL",
    "gn:name":"Barone",
    "gn:population":1077,
    "gn:timezone":"Europe/Rome",
    "iso:country":"IT",
    "name:ceb_x_preferred":[
        "Barone"
    ],
    "name:deu_x_preferred":[
        "Barone"
    ],
    "name:fra_x_preferred":[
        "Barone"
    ],
    "name:ita_x_preferred":[
        "Barone"
    ],
    "name:rus_x_preferred":[
        "\u0411\u0430\u0440\u043e\u043d\u0435"
    ],
    "name:slv_x_preferred":[
        "Barone"
    ],
    "name:spa_x_preferred":[
        "Barone"
    ],
    "name:srp_x_preferred":[
        "Barone"
    ],
    "name:swe_x_preferred":[
        "Barone"
    ],
    "wof:name":"Barone",
    "wof:placetype":"locality",
    "wof:population":1077
},
  "geometry": {"coordinates":[16.63927,38.85225],"type":"Point"}
}