{
  "type": "Feature",
  "properties": {
    "gn:admin1_code":"9",
    "gn:admin2_code":"CR",
    "gn:admin3_code":"19060.0",
    "gn:asciiname":"Cascina Marchesetti",
    "gn:country_code":"IT",
    "gn:dem":52,
    "gn:feature_class":"P",
    "gn:feature_code":"PPLL",
    "gn:name":"Cascina Marchesetti",
    "gn:population":7,
    "gn:timezone":"Europe/Rome",
    "iso:country":"IT",
    "wof:name":"Cascina Marchesetti",
    "wof:placetype":"locality",
    "wof:population":7
},
  "geometry": {"coordinates":[9.68313,45.2776],"type":"Point"}
}