{
  "type": "Feature",
  "properties": {
    "gn:admin1_code":"2.0",
    "gn:admin2_code":"PZ",
    "gn:admin3_code":"76046.0",
    "gn:asciiname":"Pedale",
    "gn:country_code":"IT",
    "gn:dem":587,
    "gn:feature_class":"P",
    "gn:feature_code":"PPL",
    "gn:name":"Pedale",
    "gn:population":0,
    "gn:timezone":"Europe/Rome",
    "iso:country":"IT",
    "wof:name":"Pedale",
    "wof:placetype":"locality"
},
  "geometry": {"coordinates":[15.81667,40.35],"type":"Point"}
}