{
  "type": "Feature",
  "properties": {
    "gn:admin1_code":"12",
    "gn:admin2_code":"TO",
    "gn:admin3_code":"1240.0",
    "gn:asciiname":"Bonina",
    "gn:country_code":"IT",
    "gn:dem":318,
    "gn:feature_class":"P",
    "gn:feature_code":"PPL",
    "gn:name":"Bonina",
    "gn:population":57,
    "gn:timezone":"Europe/Rome",
    "iso:country":"IT",
    "wof:name":"Bonina",
    "wof:placetype":"locality",
    "wof:population":57
},
  "geometry": {"coordinates":[7.63444,45.22819000000001],"type":"Point"}
}