{
  "type": "Feature",
  "properties": {
    "gn:admin1_code":"5.0",
    "gn:admin2_code":"MO",
    "gn:admin3_code":"36016.0",
    "gn:asciiname":"Boschi",
    "gn:country_code":"IT",
    "gn:dem":921,
    "gn:feature_class":"P",
    "gn:feature_code":"PPLL",
    "gn:name":"Boschi",
    "gn:population":4,
    "gn:timezone":"Europe/Rome",
    "iso:country":"IT",
    "wof:name":"Boschi",
    "wof:placetype":"locality",
    "wof:population":4
},
  "geometry": {"coordinates":[10.54694,44.32129000000001],"type":"Point"}
}