{
  "type": "Feature",
  "properties": {
    "gn:admin1_code":"10",
    "gn:admin2_code":"AN",
    "gn:admin3_code":"42044.0",
    "gn:asciiname":"Schioppetto",
    "gn:country_code":"IT",
    "gn:dem":443,
    "gn:feature_class":"P",
    "gn:feature_code":"PPL",
    "gn:name":"Schioppetto",
    "gn:population":20,
    "gn:timezone":"Europe/Rome",
    "iso:country":"IT",
    "wof:name":"Schioppetto",
    "wof:placetype":"locality",
    "wof:population":20
},
  "geometry": {"coordinates":[12.84386,43.48145],"type":"Point"}
}