{
  "type": "Feature",
  "properties": {
    "gn:admin1_code":"20.0",
    "gn:admin2_code":"VR",
    "gn:admin3_code":"23068.0",
    "gn:asciiname":"Alberetto",
    "gn:country_code":"IT",
    "gn:dem":18,
    "gn:feature_class":"P",
    "gn:feature_code":"PPL",
    "gn:name":"Alberetto",
    "gn:population":21,
    "gn:timezone":"Europe/Rome",
    "iso:country":"IT",
    "wof:name":"Alberetto",
    "wof:placetype":"locality",
    "wof:population":21
},
  "geometry": {"coordinates":[11.08338,45.2168],"type":"Point"}
}