{
  "type": "Feature",
  "properties": {
    "gn:admin1_code":"10",
    "gn:admin2_code":"PU",
    "gn:admin3_code":"41033.0",
    "gn:asciiname":"Rancaliccio",
    "gn:country_code":"IT",
    "gn:dem":793,
    "gn:feature_class":"P",
    "gn:feature_code":"PPL",
    "gn:name":"Rancaliccio",
    "gn:population":101,
    "gn:timezone":"Europe/Rome",
    "iso:country":"IT",
    "wof:name":"Rancaliccio",
    "wof:placetype":"locality",
    "wof:population":101
},
  "geometry": {"coordinates":[12.3575,43.87139000000001],"type":"Point"}
}