{
  "type": "Feature",
  "properties": {
    "gn:admin1_code":"5.0",
    "gn:admin2_code":"FE",
    "gn:admin3_code":"38010.0",
    "gn:asciiname":"Cisi",
    "gn:country_code":"IT",
    "gn:dem":-4,
    "gn:feature_class":"P",
    "gn:feature_code":"PPL",
    "gn:name":"Cisi",
    "gn:population":0,
    "gn:timezone":"Europe/Rome",
    "iso:country":"IT",
    "wof:name":"Cisi",
    "wof:placetype":"locality"
},
  "geometry": {"coordinates":[11.96667,44.85],"type":"Point"}
}