{
  "type": "Feature",
  "properties": {
    "gn:admin1_code":"4.0",
    "gn:admin2_code":"SA",
    "gn:admin3_code":"65009.0",
    "gn:asciiname":"Baia Tirrena",
    "gn:country_code":"IT",
    "gn:dem":5,
    "gn:feature_class":"P",
    "gn:feature_code":"PPLL",
    "gn:name":"Baia Tirrena",
    "gn:population":1,
    "gn:timezone":"Europe/Rome",
    "iso:country":"IT",
    "wof:name":"Baia Tirrena",
    "wof:placetype":"locality",
    "wof:population":1
},
  "geometry": {"coordinates":[15.1799,40.12932],"type":"Point"}
}