{
  "type": "Feature",
  "properties": {
    "gn:admin1_code":"20",
    "gn:admin2_code":"VE",
    "gn:admin3_code":"27013.0",
    "gn:asciiname":"Bambu",
    "gn:country_code":"IT",
    "gn:dem":3,
    "gn:feature_class":"P",
    "gn:feature_code":"PPL",
    "gn:name":"Bamb\u00f9",
    "gn:population":42,
    "gn:timezone":"Europe/Rome",
    "iso:country":"IT",
    "name:por_x_preferred":[
        "Bambu"
    ],
    "name:und_x_variant":[
        "Bamb\u00f9"
    ],
    "wof:name":"Bambu",
    "wof:placetype":"locality",
    "wof:population":42
},
  "geometry": {"coordinates":[12.65646,45.58106],"type":"Point"}
}