{
  "type": "Feature",
  "properties": {
    "iso:country":"IT",
    "wof:name":"Centro Storico",
    "wof:placetype":"neighbourhood"
},
  "geometry": {"coordinates":[9.18631758451979,45.46580571690405],"type":"Point"}
}