{
  "type": "Feature",
  "properties": {
    "gn:admin1_code":"5",
    "gn:admin2_code":"MO",
    "gn:admin3_code":"36033.0",
    "gn:asciiname":"Pedrocchio",
    "gn:country_code":"IT",
    "gn:dem":385,
    "gn:feature_class":"P",
    "gn:feature_code":"PPL",
    "gn:name":"Pedrocchio",
    "gn:population":17,
    "gn:timezone":"Europe/Rome",
    "iso:country":"IT",
    "wof:name":"Pedrocchio",
    "wof:placetype":"locality",
    "wof:population":17
},
  "geometry": {"coordinates":[10.7509,44.4698],"type":"Point"}
}