{
  "type": "Feature",
  "properties": {
    "gn:admin1_code":"19",
    "gn:admin2_code":"AO",
    "gn:admin3_code":"7005.0",
    "gn:asciiname":"Planaval",
    "gn:country_code":"IT",
    "gn:dem":1560,
    "gn:feature_class":"P",
    "gn:feature_code":"PPL",
    "gn:name":"Planaval",
    "gn:population":29,
    "gn:timezone":"Europe/Rome",
    "iso:country":"IT",
    "wof:name":"Planaval",
    "wof:placetype":"locality",
    "wof:population":29
},
  "geometry": {"coordinates":[7.07959,45.67303],"type":"Point"}
}