{
  "type": "Feature",
  "properties": {
    "gn:admin1_code":"12.0",
    "gn:admin2_code":"BI",
    "gn:admin3_code":"96085.0",
    "gn:asciiname":"Capovilla-Castello",
    "gn:country_code":"IT",
    "gn:dem":371,
    "gn:feature_class":"P",
    "gn:feature_code":"PPL",
    "gn:name":"Capovilla-Castello",
    "gn:population":751,
    "gn:timezone":"Europe/Rome",
    "iso:country":"IT",
    "wof:name":"Capovilla-Castello",
    "wof:placetype":"locality",
    "wof:population":751
},
  "geometry": {"coordinates":[8.19672,45.59485],"type":"Point"}
}