{
  "type": "Feature",
  "properties": {
    "gn:admin1_code":"15.0",
    "gn:admin2_code":"RG",
    "gn:admin3_code":"88010.0",
    "gn:asciiname":"Casazze",
    "gn:country_code":"IT",
    "gn:dem":41,
    "gn:feature_class":"P",
    "gn:feature_code":"PPL",
    "gn:name":"Casazze",
    "gn:population":0,
    "gn:timezone":"Europe/Rome",
    "iso:country":"IT",
    "wof:name":"Casazze",
    "wof:placetype":"locality"
},
  "geometry": {"coordinates":[14.5337,36.79901],"type":"Point"}
}