{
  "type": "Feature",
  "properties": {
    "gn:admin1_code":"9",
    "gn:admin2_code":"MN",
    "gn:admin3_code":"20049.0",
    "gn:asciiname":"Ronchi",
    "gn:country_code":"IT",
    "gn:dem":12,
    "gn:feature_class":"P",
    "gn:feature_code":"PPL",
    "gn:name":"Ronchi",
    "gn:population":20,
    "gn:timezone":"Europe/Rome",
    "iso:country":"IT",
    "wof:name":"Ronchi",
    "wof:placetype":"locality",
    "wof:population":20
},
  "geometry": {"coordinates":[11.14446,45.04492],"type":"Point"}
}