{
  "type": "Feature",
  "properties": {
    "gn:admin1_code":"3.0",
    "gn:admin2_code":"KR",
    "gn:admin3_code":"101013.0",
    "gn:asciiname":"Anastasi II",
    "gn:country_code":"IT",
    "gn:dem":31,
    "gn:feature_class":"P",
    "gn:feature_code":"PPL",
    "gn:name":"Anastasi II",
    "gn:population":27,
    "gn:timezone":"Europe/Rome",
    "iso:country":"IT",
    "wof:name":"Anastasi II",
    "wof:placetype":"locality",
    "wof:population":27
},
  "geometry": {"coordinates":[17.11235,38.9194],"type":"Point"}
}