{
  "type": "Feature",
  "properties": {
    "gn:admin1_code":"20.0",
    "gn:admin2_code":"RO",
    "gn:admin3_code":"29039.0",
    "gn:asciiname":"Centrale Enel",
    "gn:country_code":"IT",
    "gn:dem":20,
    "gn:feature_class":"P",
    "gn:feature_code":"PPLL",
    "gn:name":"Centrale Enel",
    "gn:population":0,
    "gn:timezone":"Europe/Rome",
    "iso:country":"IT",
    "wof:name":"Centrale Enel",
    "wof:placetype":"locality"
},
  "geometry": {"coordinates":[12.48802,44.95689],"type":"Point"}
}