{
  "type": "Feature",
  "properties": {
    "gn:admin1_code":"5.0",
    "gn:admin2_code":"MO",
    "gn:admin3_code":"36027.0",
    "gn:asciiname":"Redu",
    "gn:country_code":"IT",
    "gn:dem":27,
    "gn:feature_class":"P",
    "gn:feature_code":"PPL",
    "gn:name":"Red\u00f9",
    "gn:population":55,
    "gn:timezone":"Europe/Rome",
    "iso:country":"IT",
    "wof:name":"Redu",
    "wof:placetype":"locality",
    "wof:population":55
},
  "geometry": {"coordinates":[11.06961,44.6549],"type":"Point"}
}