{
  "type": "Feature",
  "properties": {
    "gn:admin1_code":"3.0",
    "gn:admin2_code":"CZ",
    "gn:admin3_code":"79043.0",
    "gn:asciiname":"Tomaini",
    "gn:country_code":"IT",
    "gn:dem":843,
    "gn:feature_class":"P",
    "gn:feature_code":"PPL",
    "gn:name":"Tomaini",
    "gn:population":0,
    "gn:timezone":"Europe/Rome",
    "iso:country":"IT",
    "wof:name":"Tomaini",
    "wof:placetype":"locality"
},
  "geometry": {"coordinates":[16.33967,39.04705],"type":"Point"}
}