{
  "type": "Feature",
  "properties": {
    "gn:admin1_code":"17",
    "gn:admin2_code":"TN",
    "gn:admin3_code":"22007.0",
    "gn:asciiname":"Masi d'Avio",
    "gn:country_code":"IT",
    "gn:dem":152,
    "gn:feature_class":"P",
    "gn:feature_code":"PPL",
    "gn:name":"Masi d'Avio",
    "gn:population":44,
    "gn:timezone":"Europe/Rome",
    "iso:country":"IT",
    "wof:name":"Masi d'Avio",
    "wof:placetype":"locality",
    "wof:population":44
},
  "geometry": {"coordinates":[10.93776,45.71156],"type":"Point"}
}