{
  "type": "Feature",
  "properties": {
    "gn:admin1_code":"1.0",
    "gn:admin2_code":"AQ",
    "gn:admin3_code":"66049.0",
    "gn:asciiname":"Montecristo",
    "gn:country_code":"IT",
    "gn:dem":1463,
    "gn:feature_class":"P",
    "gn:feature_code":"PPLL",
    "gn:name":"Montecristo",
    "gn:population":0,
    "gn:timezone":"Europe/Rome",
    "iso:country":"IT",
    "wof:name":"Montecristo",
    "wof:placetype":"locality"
},
  "geometry": {"coordinates":[13.55811,42.41458],"type":"Point"}
}