{
  "type": "Feature",
  "properties": {
    "gn:admin1_code":"17",
    "gn:admin2_code":"BZ",
    "gn:admin3_code":"21011.0",
    "gn:asciiname":"Scezze",
    "gn:country_code":"IT",
    "gn:dem":717,
    "gn:feature_class":"P",
    "gn:feature_code":"PPL",
    "gn:name":"Scezze",
    "gn:population":126,
    "gn:timezone":"Europe/Rome",
    "iso:country":"IT",
    "wof:name":"Scezze",
    "wof:placetype":"locality",
    "wof:population":126
},
  "geometry": {"coordinates":[11.63155,46.6921],"type":"Point"}
}