{
  "type": "Feature",
  "properties": {
    "gn:admin1_code":"4",
    "gn:admin2_code":"BN",
    "gn:admin3_code":"62075.0",
    "gn:asciiname":"Lotola",
    "gn:country_code":"IT",
    "gn:dem":571,
    "gn:feature_class":"P",
    "gn:feature_code":"PPL",
    "gn:name":"Lotola",
    "gn:population":19,
    "gn:timezone":"Europe/Rome",
    "iso:country":"IT",
    "wof:name":"Lotola",
    "wof:placetype":"locality",
    "wof:population":19
},
  "geometry": {"coordinates":[14.62604,41.1122],"type":"Point"}
}