{
  "type": "Feature",
  "properties": {
    "gn:admin1_code":"9.0",
    "gn:admin2_code":"MN",
    "gn:admin3_code":"20061.0",
    "gn:asciiname":"Lame II",
    "gn:country_code":"IT",
    "gn:dem":10,
    "gn:feature_class":"P",
    "gn:feature_code":"PPL",
    "gn:name":"Lame II",
    "gn:population":12,
    "gn:timezone":"Europe/Rome",
    "iso:country":"IT",
    "wof:name":"Lame II",
    "wof:placetype":"locality",
    "wof:population":12
},
  "geometry": {"coordinates":[11.326,44.98827],"type":"Point"}
}