{
  "type": "Feature",
  "properties": {
    "gn:admin1_code":"16",
    "gn:admin2_code":"PT",
    "gn:admin3_code":"47024.0",
    "gn:asciiname":"Campo Magno",
    "gn:country_code":"IT",
    "gn:dem":850,
    "gn:feature_class":"P",
    "gn:feature_code":"PPL",
    "gn:name":"Campo Magno",
    "gn:population":28,
    "gn:timezone":"Europe/Rome",
    "iso:country":"IT",
    "wof:name":"Campo Magno",
    "wof:placetype":"locality",
    "wof:population":28
},
  "geometry": {"coordinates":[10.84267,44.03286],"type":"Point"}
}