{
  "type": "Feature",
  "properties": {
    "gn:gn_country":"IT",
    "gn:gn_fcode":"PPL",
    "gn:gn_pop":0,
    "gn:population":663,
    "iso:country":"IT",
    "name:ara_x_preferred":[
        "\u0623\u062a\u0634\u0627\u0631\u0648\u0644\u064a"
    ],
    "name:eng_x_preferred":[
        "Acciaroli"
    ],
    "name:est_x_preferred":[
        "Acciaroli"
    ],
    "name:fra_x_preferred":[
        "Acciaroli"
    ],
    "name:hun_x_preferred":[
        "Acciaroli"
    ],
    "name:ita_x_preferred":[
        "Acciaroli"
    ],
    "name:nld_x_preferred":[
        "Acciaroli"
    ],
    "name:srp_x_preferred":[
        "Acciaroli"
    ],
    "qs_pg:aaroncc":"IT",
    "qs_pg:gn_country":"IT",
    "qs_pg:gn_fcode":"PPL",
    "qs_pg:gn_pop":0,
    "qs_pg:name":"Acciaroli",
    "qs_pg:name_adm0":"Italia",
    "qs_pg:name_adm1":"Campania",
    "qs_pg:photos":359,
    "qs_pg:photos_1k":73,
    "qs_pg:photos_9k":2,
    "qs_pg:photos_9r":5,
    "qs_pg:photos_all":359,
    "qs_pg:photos_sr":6,
    "qs_pg:pop_sr":0,
    "qs_pg:qs_pg_placetype":"locality",
    "qs_pg:qs_pg_placetype_gp":"Town",
    "qs_pg:woe_adm0":23424853,
    "woe:adm0_id":23424853,
    "woe:name_adm0":"Italia",
    "woe:name_adm1":"Campania",
    "woe:placetype":"Town",
    "wof:name":"Acciaroli",
    "wof:placetype":"locality",
    "wof:population":663
},
  "geometry": {"coordinates":[15.02724,40.18097],"type":"Point"}
}