{
  "type": "Feature",
  "properties": {
    "gn:elevation":445,
    "gn:population":580,
    "iso:country":"IT",
    "name:ara_x_preferred":[
        "\u0622\u0631\u0643\u064a"
    ],
    "name:azb_x_preferred":[
        "\u0622\u0631\u0686\u06cc"
    ],
    "name:bcl_x_preferred":[
        "Archi"
    ],
    "name:bul_x_preferred":[
        "\u0410\u0440\u043a\u0438"
    ],
    "name:ceb_x_preferred":[
        "Archi"
    ],
    "name:deu_x_preferred":[
        "Archi"
    ],
    "name:eng_x_preferred":[
        "Archi"
    ],
    "name:epo_x_preferred":[
        "Archi"
    ],
    "name:eus_x_preferred":[
        "Archi"
    ],
    "name:fas_x_preferred":[
        "\u0622\u0631\u0686\u06cc"
    ],
    "name:fin_x_preferred":[
        "Archi"
    ],
    "name:fra_x_preferred":[
        "Archi"
    ],
    "name:hbs_x_preferred":[
        "Archi"
    ],
    "name:hun_x_preferred":[
        "Archi"
    ],
    "name:hye_x_preferred":[
        "\u0531\u0580\u056f\u056b"
    ],
    "name:ina_x_preferred":[
        "Archi"
    ],
    "name:ind_x_preferred":[
        "Archi"
    ],
    "name:ita_x_preferred":[
        "Archi"
    ],
    "name:jav_x_preferred":[
        "Archi"
    ],
    "name:jpn_x_preferred":[
        "\u30a2\u30eb\u30ad"
    ],
    "name:kaz_x_preferred":[
        "\u0410\u0440\u043a\u0438"
    ],
    "name:kor_x_preferred":[
        "\uc544\ub974\ud0a4"
    ],
    "name:lat_x_preferred":[
        "Arcae"
    ],
    "name:lmo_x_preferred":[
        "Archi"
    ],
    "name:msa_x_preferred":[
        "Archi"
    ],
    "name:nan_x_preferred":[
        "Archi"
    ],
    "name:nap_x_preferred":[
        "Archi"
    ],
    "name:nld_x_preferred":[
        "Archi"
    ],
    "name:nob_x_preferred":[
        "Archi"
    ],
    "name:pms_x_preferred":[
        "Archi"
    ],
    "name:pol_x_preferred":[
        "Archi"
    ],
    "name:por_x_preferred":[
        "Archi"
    ],
    "name:ron_x_preferred":[
        "Archi"
    ],
    "name:rus_x_preferred":[
        "\u0410\u0440\u043a\u0438"
    ],
    "name:scn_x_preferred":[
        "Archi"
    ],
    "name:spa_x_preferred":[
        "Archi"
    ],
    "name:sqi_x_preferred":[
        "Archi"
    ],
    "name:srp_x_preferred":[
        "Arki"
    ],
    "name:srp_x_variant":[
        "Archi"
    ],
    "name:ukr_x_preferred":[
        "\u0410\u0440\u043a\u0456"
    ],
    "name:uzb_x_preferred":[
        "Archi"
    ],
    "name:vol_x_preferred":[
        "Archi"
    ],
    "name:war_x_preferred":[
        "Archi"
    ],
    "name:zho_x_preferred":[
        "\u963f\u5c14\u57fa"
    ],
    "qs:a0":"Italia",
    "qs:a1":"*Chieti",
    "qs:a1r":"0Abruzzo",
    "qs:adm0":"Italia",
    "qs:la_lc":"*",
    "qs:level":"locality",
    "qs:loc":"Archi",
    "qs:loc_alt":"Archi",
    "qs:pop":0,
    "qs:type":"buffered point",
    "wd:wordcount":91,
    "wof:lang":[
        "ita"
    ],
    "wof:name":"Archi",
    "wof:placetype":"locality",
    "wof:population":580
},
  "geometry": {"coordinates":[14.38156,42.089008],"type":"Point"}
}