{
  "type": "Feature",
  "properties": {
    "gn:admin1_code":"16",
    "gn:admin2_code":"LU",
    "gn:admin3_code":"46004.0",
    "gn:asciiname":"Dezza",
    "gn:country_code":"IT",
    "gn:dem":206,
    "gn:feature_class":"P",
    "gn:feature_code":"PPL",
    "gn:name":"Dezza",
    "gn:population":16,
    "gn:timezone":"Europe/Rome",
    "iso:country":"IT",
    "wof:name":"Dezza",
    "wof:placetype":"locality",
    "wof:population":16
},
  "geometry": {"coordinates":[10.48961,43.97347],"type":"Point"}
}