{
  "type": "Feature",
  "properties": {
    "gn:admin1_code":"2",
    "gn:admin2_code":"PZ",
    "gn:admin3_code":"76050.0",
    "gn:asciiname":"Rapolla",
    "gn:country_code":"IT",
    "gn:dem":823,
    "gn:feature_class":"P",
    "gn:feature_code":"PPL",
    "gn:name":"Rapolla",
    "gn:population":18,
    "gn:timezone":"Europe/Rome",
    "iso:country":"IT",
    "name:ara_x_preferred":[
        "\u0631\u0627\u0628\u0648\u0644\u0627"
    ],
    "name:azb_x_preferred":[
        "\u0631\u0627\u067e\u0648\u0644\u0627"
    ],
    "name:bul_x_preferred":[
        "\u0420\u0430\u043f\u043e\u043b\u0430"
    ],
    "name:ceb_x_preferred":[
        "Rapolla"
    ],
    "name:deu_x_preferred":[
        "Rapolla"
    ],
    "name:epo_x_preferred":[
        "Rapolla"
    ],
    "name:eus_x_preferred":[
        "Rapolla"
    ],
    "name:fas_x_preferred":[
        "\u0631\u0627\u067e\u0648\u0644\u0627"
    ],
    "name:fra_x_preferred":[
        "Rapolla"
    ],
    "name:hun_x_preferred":[
        "Rapolla"
    ],
    "name:hye_x_preferred":[
        "\u054c\u0561\u057a\u0578\u056c\u056c\u0561"
    ],
    "name:ina_x_preferred":[
        "Rapolla"
    ],
    "name:ita_x_preferred":[
        "Rapolla"
    ],
    "name:jpn_x_preferred":[
        "\u30e9\u30dd\u30c3\u30e9"
    ],
    "name:kaz_x_preferred":[
        "\u0420\u0430\u043f\u043e\u043b\u043b\u0430"
    ],
    "name:lat_x_preferred":[
        "Rapolla"
    ],
    "name:lmo_x_preferred":[
        "Rapolla"
    ],
    "name:msa_x_preferred":[
        "Rapolla"
    ],
    "name:nap_x_preferred":[
        "Rapolla"
    ],
    "name:nld_x_preferred":[
        "Rapolla"
    ],
    "name:pms_x_preferred":[
        "Rapolla"
    ],
    "name:pol_x_preferred":[
        "Rapolla"
    ],
    "name:por_x_preferred":[
        "Rapolla"
    ],
    "name:ron_x_preferred":[
        "Rapolla"
    ],
    "name:rus_x_preferred":[
        "\u0420\u0430\u043f\u043e\u043b\u043b\u0430"
    ],
    "name:scn_x_preferred":[
        "Rapolla"
    ],
    "name:spa_x_preferred":[
        "Rapolla"
    ],
    "name:srp_x_preferred":[
        "\u0420\u0430\u043f\u043e\u043b\u0430"
    ],
    "name:szl_x_preferred":[
        "Rapolla"
    ],
    "name:tur_x_preferred":[
        "Rapolla"
    ],
    "name:ukr_x_preferred":[
        "\u0420\u0430\u043f\u043e\u043b\u043b\u0430"
    ],
    "name:uzb_x_preferred":[
        "Rapolla"
    ],
    "name:vol_x_preferred":[
        "Rapolla"
    ],
    "name:war_x_preferred":[
        "Rapolla"
    ],
    "name:zho_x_preferred":[
        "\u62c9\u6ce2\u62c9"
    ],
    "wof:name":"Rapolla",
    "wof:placetype":"locality",
    "wof:population":18
},
  "geometry": {"coordinates":[15.87754,40.19621],"type":"Point"}
}