{
  "type": "Feature",
  "properties": {
    "gn:admin1_code":"12",
    "gn:admin2_code":"CN",
    "gn:admin3_code":"4078.0",
    "gn:asciiname":"Colombaro Ferraris",
    "gn:country_code":"IT",
    "gn:dem":490,
    "gn:feature_class":"P",
    "gn:feature_code":"PPL",
    "gn:name":"Colombaro Ferraris",
    "gn:population":20,
    "gn:timezone":"Europe/Rome",
    "iso:country":"IT",
    "wof:name":"Colombaro Ferraris",
    "wof:placetype":"locality",
    "wof:population":20
},
  "geometry": {"coordinates":[7.57298,44.42931],"type":"Point"}
}