{
  "type": "Feature",
  "properties": {
    "gn:admin1_code":"20",
    "gn:admin2_code":"PD",
    "gn:admin3_code":"28021.0",
    "gn:asciiname":"Motte",
    "gn:country_code":"IT",
    "gn:dem":2,
    "gn:feature_class":"P",
    "gn:feature_code":"PPL",
    "gn:name":"Motte",
    "gn:population":93,
    "gn:timezone":"Europe/Rome",
    "iso:country":"IT",
    "wof:name":"Motte",
    "wof:placetype":"locality",
    "wof:population":93
},
  "geometry": {"coordinates":[11.97719,45.22254],"type":"Point"}
}