{
  "type": "Feature",
  "properties": {
    "gn:admin1_code":"15.0",
    "gn:admin2_code":"PA",
    "gn:admin3_code":"82065.0",
    "gn:asciiname":"Botindari",
    "gn:country_code":"IT",
    "gn:dem":490,
    "gn:feature_class":"P",
    "gn:feature_code":"PPL",
    "gn:name":"Botindari",
    "gn:population":6,
    "gn:timezone":"Europe/Rome",
    "iso:country":"IT",
    "wof:name":"Botindari",
    "wof:placetype":"locality",
    "wof:population":6
},
  "geometry": {"coordinates":[14.2008,37.87746],"type":"Point"}
}