{
  "type": "Feature",
  "properties": {
    "gn:admin1_code":"3",
    "gn:admin2_code":"CZ",
    "gn:admin3_code":"79138.0",
    "gn:asciiname":"Cupa Soprana",
    "gn:country_code":"IT",
    "gn:dem":810,
    "gn:feature_class":"P",
    "gn:feature_code":"PPL",
    "gn:name":"Cupa Soprana",
    "gn:population":53,
    "gn:timezone":"Europe/Rome",
    "iso:country":"IT",
    "wof:name":"Cupa Soprana",
    "wof:placetype":"locality",
    "wof:population":53
},
  "geometry": {"coordinates":[16.42476,39.04052],"type":"Point"}
}