{
  "type": "Feature",
  "properties": {
    "gn:admin1_code":"5.0",
    "gn:admin2_code":"FE",
    "gn:admin3_code":"38002.0",
    "gn:asciiname":"Fienilone",
    "gn:country_code":"IT",
    "gn:dem":-5,
    "gn:feature_class":"P",
    "gn:feature_code":"PPL",
    "gn:name":"Fienilone",
    "gn:population":0,
    "gn:timezone":"Europe/Rome",
    "iso:country":"IT",
    "wof:name":"Fienilone",
    "wof:placetype":"locality"
},
  "geometry": {"coordinates":[12.04111,44.95889],"type":"Point"}
}