{
  "type": "Feature",
  "properties": {
    "gn:admin1_code":"20",
    "gn:admin2_code":"PD",
    "gn:admin3_code":"28095.0",
    "gn:asciiname":"Grompe",
    "gn:country_code":"IT",
    "gn:dem":13,
    "gn:feature_class":"P",
    "gn:feature_code":"PPL",
    "gn:name":"Grompe",
    "gn:population":23,
    "gn:timezone":"Europe/Rome",
    "iso:country":"IT",
    "wof:name":"Grompe",
    "wof:placetype":"locality",
    "wof:population":23
},
  "geometry": {"coordinates":[11.41617,45.21328],"type":"Point"}
}