{
  "type": "Feature",
  "properties": {
    "gn:admin1_code":"20",
    "gn:admin2_code":"VE",
    "gn:admin3_code":"27029.0",
    "gn:asciiname":"Borgo di Mezzo",
    "gn:country_code":"IT",
    "gn:dem":4,
    "gn:feature_class":"P",
    "gn:feature_code":"PPL",
    "gn:name":"Borgo di Mezzo",
    "gn:population":27,
    "gn:timezone":"Europe/Rome",
    "iso:country":"IT",
    "wof:name":"Borgo di Mezzo",
    "wof:placetype":"locality",
    "wof:population":27
},
  "geometry": {"coordinates":[12.91831,45.76114000000001],"type":"Point"}
}