{
  "type": "Feature",
  "properties": {
    "gn:admin1_code":"1.0",
    "gn:admin2_code":"TE",
    "gn:admin3_code":"67017.0",
    "gn:asciiname":"Sant'Andrea",
    "gn:country_code":"IT",
    "gn:dem":429,
    "gn:elevation":"431.0",
    "gn:feature_class":"P",
    "gn:feature_code":"PPL",
    "gn:name":"Sant'Andrea",
    "gn:population":304,
    "gn:timezone":"Europe/Rome",
    "iso:country":"IT",
    "wof:name":"Sant'Andrea",
    "wof:placetype":"locality",
    "wof:population":304
},
  "geometry": {"coordinates":[13.67669,42.77959],"type":"Point"}
}