{
  "type": "Feature",
  "properties": {
    "gn:admin1_code":"9",
    "gn:admin2_code":"CR",
    "gn:admin3_code":"19103.0",
    "gn:asciiname":"Salice",
    "gn:country_code":"IT",
    "gn:dem":37,
    "gn:feature_class":"P",
    "gn:feature_code":"PPLL",
    "gn:name":"Salice",
    "gn:population":6,
    "gn:timezone":"Europe/Rome",
    "iso:country":"IT",
    "name:cat_x_preferred":[
        "Salice"
    ],
    "name:ceb_x_preferred":[
        "Salice"
    ],
    "name:cos_x_preferred":[
        "U Salge"
    ],
    "name:deu_x_preferred":[
        "Salice"
    ],
    "name:eus_x_preferred":[
        "Salice"
    ],
    "name:fra_x_preferred":[
        "Salice"
    ],
    "name:hun_x_preferred":[
        "Salice"
    ],
    "name:hye_x_preferred":[
        "\u054d\u0561\u056c\u056b\u0579\u0565"
    ],
    "name:ind_x_preferred":[
        "Salice"
    ],
    "name:ita_x_preferred":[
        "Salice"
    ],
    "name:kaz_x_preferred":[
        "\u0421\u0430\u043b\u0438\u0447\u0435"
    ],
    "name:lat_x_preferred":[
        "Salice"
    ],
    "name:lmo_x_preferred":[
        "Salice"
    ],
    "name:msa_x_preferred":[
        "Salice"
    ],
    "name:nld_x_preferred":[
        "Salice"
    ],
    "name:nor_x_preferred":[
        "Salice"
    ],
    "name:oci_x_preferred":[
        "Salice"
    ],
    "name:pol_x_preferred":[
        "Salice"
    ],
    "name:por_x_preferred":[
        "Salice"
    ],
    "name:rus_x_preferred":[
        "\u0421\u0430\u043b\u0438\u0447\u0435"
    ],
    "name:slk_x_preferred":[
        "Salice"
    ],
    "name:slv_x_preferred":[
        "Salice"
    ],
    "name:spa_x_preferred":[
        "Salice"
    ],
    "name:swe_x_preferred":[
        "Salice"
    ],
    "name:ukr_x_preferred":[
        "\u0421\u0430\u043b\u0456\u0447\u0435"
    ],
    "name:vie_x_preferred":[
        "Salice"
    ],
    "name:vol_x_preferred":[
        "Salice"
    ],
    "name:war_x_preferred":[
        "Salice"
    ],
    "wof:name":"Salice",
    "wof:placetype":"locality",
    "wof:population":6
},
  "geometry": {"coordinates":[10.04811,45.06888],"type":"Point"}
}