{
  "type": "Feature",
  "properties": {
    "gn:admin1_code":"9",
    "gn:admin2_code":"CR",
    "gn:admin3_code":"19103.0",
    "gn:asciiname":"Salice",
    "gn:country_code":"IT",
    "gn:dem":37,
    "gn:feature_class":"P",
    "gn:feature_code":"PPLL",
    "gn:name":"Salice",
    "gn:population":6,
    "gn:timezone":"Europe/Rome",
    "iso:country":"IT",
    "wof:name":"Salice",
    "wof:placetype":"locality",
    "wof:population":6
},
  "geometry": {"coordinates":[10.04811,45.06888],"type":"Point"}
}