{
  "type": "Feature",
  "properties": {
    "gn:admin1_code":"20",
    "gn:admin2_code":"VI",
    "gn:admin3_code":"24017.0",
    "gn:asciiname":"Carlassara II",
    "gn:country_code":"IT",
    "gn:dem":310,
    "gn:feature_class":"P",
    "gn:feature_code":"PPL",
    "gn:name":"Carlassara II",
    "gn:population":40,
    "gn:timezone":"Europe/Rome",
    "iso:country":"IT",
    "wof:name":"Carlassara II",
    "wof:placetype":"locality",
    "wof:population":40
},
  "geometry": {"coordinates":[11.34044,45.59766],"type":"Point"}
}