{
  "type": "Feature",
  "properties": {
    "gn:admin1_code":"3",
    "gn:admin2_code":"CS",
    "gn:admin3_code":"78070.0",
    "gn:asciiname":"Destre",
    "gn:country_code":"IT",
    "gn:dem":255,
    "gn:feature_class":"P",
    "gn:feature_code":"PPL",
    "gn:name":"Destre",
    "gn:population":28,
    "gn:timezone":"Europe/Rome",
    "iso:country":"IT",
    "wof:name":"Destre",
    "wof:placetype":"locality",
    "wof:population":28
},
  "geometry": {"coordinates":[16.27386,39.46328],"type":"Point"}
}