{
  "type": "Feature",
  "properties": {
    "gn:admin1_code":"12",
    "gn:admin2_code":"TO",
    "gn:admin3_code":"1061.0",
    "gn:asciiname":"Via del Pero",
    "gn:country_code":"IT",
    "gn:dem":239,
    "gn:feature_class":"P",
    "gn:feature_code":"PPL",
    "gn:name":"Via del Pero",
    "gn:population":14,
    "gn:timezone":"Europe/Rome",
    "iso:country":"IT",
    "wof:name":"Via del Pero",
    "wof:placetype":"locality",
    "wof:population":14
},
  "geometry": {"coordinates":[7.91597,45.48014000000001],"type":"Point"}
}