{
  "type": "Feature",
  "properties": {
    "gn:admin1_code":"16.0",
    "gn:admin2_code":"FI",
    "gn:admin3_code":"48020.0",
    "gn:asciiname":"Bagni di Mommialla",
    "gn:country_code":"IT",
    "gn:dem":194,
    "gn:feature_class":"P",
    "gn:feature_code":"PPL",
    "gn:name":"Bagni di Mommialla",
    "gn:population":0,
    "gn:timezone":"Europe/Rome",
    "iso:country":"IT",
    "wof:name":"Bagni di Mommialla",
    "wof:placetype":"locality"
},
  "geometry": {"coordinates":[10.91667,43.46667],"type":"Point"}
}