{
  "type": "Feature",
  "properties": {
    "gn:admin1_code":"15",
    "gn:admin2_code":"PA",
    "gn:admin3_code":"82009.0",
    "gn:asciiname":"Alfieri Vittorio",
    "gn:country_code":"IT",
    "gn:dem":347,
    "gn:feature_class":"P",
    "gn:feature_code":"PPL",
    "gn:name":"Alfieri Vittorio",
    "gn:population":47,
    "gn:timezone":"Europe/Rome",
    "iso:country":"IT",
    "wof:name":"Alfieri Vittorio",
    "wof:placetype":"locality",
    "wof:population":47
},
  "geometry": {"coordinates":[13.40284,38.04701],"type":"Point"}
}