{
  "type": "Feature",
  "properties": {
    "gn:admin1_code":"16",
    "gn:admin2_code":"FI",
    "gn:admin3_code":"48032.0",
    "gn:asciiname":"Santa Lucia",
    "gn:country_code":"IT",
    "gn:dem":327,
    "gn:feature_class":"P",
    "gn:feature_code":"PPL",
    "gn:name":"Santa Lucia",
    "gn:population":22,
    "gn:timezone":"Europe/Rome",
    "iso:country":"IT",
    "wof:name":"Santa Lucia",
    "wof:placetype":"locality",
    "wof:population":22
},
  "geometry": {"coordinates":[11.48853,43.75196],"type":"Point"}
}