{
  "type": "Feature",
  "properties": {
    "gn:admin1_code":"20",
    "gn:admin2_code":"VE",
    "gn:admin3_code":"27003.0",
    "gn:asciiname":"Giare",
    "gn:country_code":"IT",
    "gn:dem":3,
    "gn:feature_class":"P",
    "gn:feature_code":"PPL",
    "gn:name":"Giare",
    "gn:population":78,
    "gn:timezone":"Europe/Rome",
    "iso:country":"IT",
    "wof:name":"Giare",
    "wof:placetype":"locality",
    "wof:population":78
},
  "geometry": {"coordinates":[12.06251,45.32638],"type":"Point"}
}