{
  "type": "Feature",
  "properties": {
    "gn:admin1_code":"9",
    "gn:admin2_code":"BG",
    "gn:admin3_code":"16069.0",
    "gn:asciiname":"Cerbello",
    "gn:country_code":"IT",
    "gn:dem":391,
    "gn:feature_class":"P",
    "gn:feature_code":"PPL",
    "gn:name":"Cerbello",
    "gn:population":31,
    "gn:timezone":"Europe/Rome",
    "iso:country":"IT",
    "wof:name":"Cerbello",
    "wof:placetype":"locality",
    "wof:population":31
},
  "geometry": {"coordinates":[9.79831,45.70833],"type":"Point"}
}