{
  "type": "Feature",
  "properties": {
    "gn:admin1_code":"20.0",
    "gn:admin2_code":"TV",
    "gn:admin3_code":"26055.0",
    "gn:asciiname":"Case Borsato",
    "gn:country_code":"IT",
    "gn:dem":43,
    "gn:feature_class":"P",
    "gn:feature_code":"PPL",
    "gn:name":"Case Borsato",
    "gn:population":26,
    "gn:timezone":"Europe/Rome",
    "iso:country":"IT",
    "wof:name":"Case Borsato",
    "wof:placetype":"locality",
    "wof:population":26
},
  "geometry": {"coordinates":[12.1135,45.69009000000001],"type":"Point"}
}