{
  "type": "Feature",
  "properties": {
    "gn:admin1_code":"9.0",
    "gn:admin2_code":"LO",
    "gn:admin3_code":"98043.0",
    "gn:asciiname":"Via Fermi-Marconi",
    "gn:country_code":"IT",
    "gn:dem":64,
    "gn:feature_class":"P",
    "gn:feature_code":"PPLL",
    "gn:name":"Via Fermi-Marconi",
    "gn:population":2,
    "gn:timezone":"Europe/Rome",
    "iso:country":"IT",
    "wof:name":"Via Fermi-Marconi",
    "wof:placetype":"locality",
    "wof:population":2
},
  "geometry": {"coordinates":[9.58621,45.17317],"type":"Point"}
}