{
  "type": "Feature",
  "properties": {
    "gn:admin1_code":"12.0",
    "gn:admin2_code":"TO",
    "gn:admin3_code":"1227.0",
    "gn:asciiname":"Noufliere",
    "gn:country_code":"IT",
    "gn:dem":885,
    "gn:feature_class":"P",
    "gn:feature_code":"PPLL",
    "gn:name":"Noufliere",
    "gn:population":1,
    "gn:timezone":"Europe/Rome",
    "iso:country":"IT",
    "wof:name":"Noufliere",
    "wof:placetype":"locality",
    "wof:population":1
},
  "geometry": {"coordinates":[7.15009,44.98695],"type":"Point"}
}