{
  "type": "Feature",
  "properties": {
    "gn:admin1_code":"8",
    "gn:admin2_code":"GE",
    "gn:admin3_code":"10048.0",
    "gn:asciiname":"Grupparolo",
    "gn:country_code":"IT",
    "gn:dem":836,
    "gn:feature_class":"P",
    "gn:feature_code":"PPL",
    "gn:name":"Grupparolo",
    "gn:population":16,
    "gn:timezone":"Europe/Rome",
    "iso:country":"IT",
    "wof:name":"Grupparolo",
    "wof:placetype":"locality",
    "wof:population":16
},
  "geometry": {"coordinates":[9.30866,44.48316],"type":"Point"}
}