{
  "type": "Feature",
  "properties": {
    "gn:admin1_code":"7.0",
    "gn:admin2_code":"RM",
    "gn:admin3_code":"58079.0",
    "gn:asciiname":"Borgo Santa Rita",
    "gn:country_code":"IT",
    "gn:dem":20,
    "gn:feature_class":"P",
    "gn:feature_code":"PPL",
    "gn:name":"Borgo Santa Rita",
    "gn:population":0,
    "gn:timezone":"Europe/Rome",
    "iso:country":"IT",
    "name:ita_x_preferred":[
        "Borgo Santa Rita"
    ],
    "name:nld_x_preferred":[
        "Borgo Santa Rita"
    ],
    "name:srp_x_preferred":[
        "\u0411\u043e\u0440\u0433\u043e \u0421\u0430\u043d\u0442\u0430 \u0420\u0438\u0442\u0430"
    ],
    "wof:name":"Borgo Santa Rita",
    "wof:placetype":"locality"
},
  "geometry": {"coordinates":[12.48333,41.63333],"type":"Point"}
}