{
  "type": "Feature",
  "properties": {
    "gn:admin1_code":"7",
    "gn:admin2_code":"RI",
    "gn:admin3_code":"57001.0",
    "gn:asciiname":"Cesa Ventre",
    "gn:country_code":"IT",
    "gn:dem":1053,
    "gn:feature_class":"P",
    "gn:feature_code":"PPL",
    "gn:name":"Cesa Ventre",
    "gn:population":15,
    "gn:timezone":"Europe/Rome",
    "iso:country":"IT",
    "wof:name":"Cesa Ventre",
    "wof:placetype":"locality",
    "wof:population":15
},
  "geometry": {"coordinates":[13.21492,42.66169],"type":"Point"}
}