{
  "type": "Feature",
  "properties": {
    "gn:admin1_code":"9",
    "gn:admin2_code":"VA",
    "gn:admin3_code":"12047.0",
    "gn:asciiname":"Collodri",
    "gn:country_code":"IT",
    "gn:dem":348,
    "gn:feature_class":"P",
    "gn:feature_code":"PPL",
    "gn:name":"Collodri",
    "gn:population":44,
    "gn:timezone":"Europe/Rome",
    "iso:country":"IT",
    "wof:name":"Collodri",
    "wof:placetype":"locality",
    "wof:population":44
},
  "geometry": {"coordinates":[8.80464,45.76536],"type":"Point"}
}