{
  "type": "Feature",
  "properties": {
    "gn:admin1_code":"16",
    "gn:admin2_code":"SI",
    "gn:admin3_code":"52034.0",
    "gn:asciiname":"Caggio",
    "gn:country_code":"IT",
    "gn:dem":248,
    "gn:feature_class":"P",
    "gn:feature_code":"PPL",
    "gn:name":"Caggio",
    "gn:population":80,
    "gn:timezone":"Europe/Rome",
    "iso:country":"IT",
    "wof:name":"Caggio",
    "wof:placetype":"locality",
    "wof:population":80
},
  "geometry": {"coordinates":[11.29034,43.26919],"type":"Point"}
}