{
  "type": "Feature",
  "properties": {
    "gn:admin1_code":"20",
    "gn:admin2_code":"VI",
    "gn:admin3_code":"24110.0",
    "gn:asciiname":"Selva",
    "gn:country_code":"IT",
    "gn:dem":540,
    "gn:feature_class":"P",
    "gn:feature_code":"PPL",
    "gn:name":"Selva",
    "gn:population":196,
    "gn:timezone":"Europe/Rome",
    "iso:country":"IT",
    "name:ara_x_preferred":[
        "\u0633\u064a\u0644\u0628\u0627"
    ],
    "name:arg_x_preferred":[
        "Selva"
    ],
    "name:cat_x_preferred":[
        "Selva"
    ],
    "name:deu_x_preferred":[
        "Selva"
    ],
    "name:eus_x_preferred":[
        "Selva"
    ],
    "name:fra_x_preferred":[
        "Selva"
    ],
    "name:glg_x_preferred":[
        "Selva"
    ],
    "name:hun_x_preferred":[
        "Selva"
    ],
    "name:ita_x_preferred":[
        "Selva"
    ],
    "name:kaz_x_preferred":[
        "\u0421\u0435\u043b\u044c\u0432\u0430"
    ],
    "name:nld_x_preferred":[
        "Selva"
    ],
    "name:oci_x_preferred":[
        "Selva"
    ],
    "name:pol_x_preferred":[
        "Selva"
    ],
    "name:por_x_preferred":[
        "Selva"
    ],
    "name:ron_x_preferred":[
        "Selva"
    ],
    "name:rus_x_preferred":[
        "\u0421\u0435\u043b\u044c\u0432\u0430"
    ],
    "name:sco_x_preferred":[
        "Selva"
    ],
    "name:spa_x_preferred":[
        "Selva"
    ],
    "name:sqi_x_preferred":[
        "Selva"
    ],
    "name:swe_x_preferred":[
        "Selva"
    ],
    "name:ukr_x_preferred":[
        "\u0421\u0435\u043b\u0431\u0430"
    ],
    "name:vie_x_preferred":[
        "Selva"
    ],
    "name:zho_x_preferred":[
        "\u585e\u5c14\u74e6\u53bf"
    ],
    "wof:name":"Selva",
    "wof:placetype":"locality",
    "wof:population":196
},
  "geometry": {"coordinates":[11.30894,45.58206],"type":"Point"}
}