{
  "type": "Feature",
  "properties": {
    "gn:admin1_code":"3",
    "gn:admin2_code":"CS",
    "gn:admin3_code":"78117.0",
    "gn:asciiname":"Cacciola",
    "gn:country_code":"IT",
    "gn:dem":91,
    "gn:feature_class":"P",
    "gn:feature_code":"PPL",
    "gn:name":"Cacciola",
    "gn:population":54,
    "gn:timezone":"Europe/Rome",
    "iso:country":"IT",
    "wof:name":"Cacciola",
    "wof:placetype":"locality",
    "wof:population":54
},
  "geometry": {"coordinates":[15.88162,39.59055],"type":"Point"}
}