{
  "type": "Feature",
  "properties": {
    "gn:admin1_code":"12",
    "gn:admin2_code":"AT",
    "gn:admin3_code":"5087.0",
    "gn:asciiname":"Castellazzo",
    "gn:country_code":"IT",
    "gn:dem":204,
    "gn:feature_class":"P",
    "gn:feature_code":"PPL",
    "gn:name":"Castellazzo",
    "gn:population":28,
    "gn:timezone":"Europe/Rome",
    "iso:country":"IT",
    "name:ceb_x_preferred":[
        "Castellazzo"
    ],
    "name:deu_x_preferred":[
        "Castellazzo"
    ],
    "name:ita_x_preferred":[
        "Castellazzo"
    ],
    "name:spa_x_preferred":[
        "Castellazzo"
    ],
    "name:srp_x_preferred":[
        "Kastelaco"
    ],
    "name:swe_x_preferred":[
        "Castellazzo"
    ],
    "wof:name":"Castellazzo",
    "wof:placetype":"locality",
    "wof:population":28
},
  "geometry": {"coordinates":[8.25762,44.94528],"type":"Point"}
}