{
  "type": "Feature",
  "properties": {
    "gn:admin1_code":"7",
    "gn:admin2_code":"FR",
    "gn:admin3_code":"60044.0",
    "gn:asciiname":"Campolato",
    "gn:country_code":"IT",
    "gn:dem":191,
    "gn:feature_class":"P",
    "gn:feature_code":"PPL",
    "gn:name":"Campolato",
    "gn:population":62,
    "gn:timezone":"Europe/Rome",
    "iso:country":"IT",
    "wof:name":"Campolato",
    "wof:placetype":"locality",
    "wof:population":62
},
  "geometry": {"coordinates":[13.53636,41.61238],"type":"Point"}
}