{
  "type": "Feature",
  "properties": {
    "iso:country":"IT",
    "name:baq_x_preferred":[
        "Codera"
    ],
    "name:cat_x_preferred":[
        "Codera"
    ],
    "name:cze_x_preferred":[
        "Codera"
    ],
    "name:dan_x_preferred":[
        "Codera"
    ],
    "name:dut_x_preferred":[
        "Codera"
    ],
    "name:eng_x_preferred":[
        "Codera"
    ],
    "name:fin_x_preferred":[
        "Codera"
    ],
    "name:fre_x_preferred":[
        "Codera"
    ],
    "name:ind_x_preferred":[
        "Codera"
    ],
    "name:ita_x_preferred":[
        "Codera"
    ],
    "name:nno_x_preferred":[
        "Codera"
    ],
    "name:nob_x_preferred":[
        "Codera"
    ],
    "name:oci_x_preferred":[
        "Codera"
    ],
    "name:pol_x_preferred":[
        "Codera"
    ],
    "name:por_x_preferred":[
        "Codera"
    ],
    "name:rum_x_preferred":[
        "Codera"
    ],
    "name:slo_x_preferred":[
        "Codera"
    ],
    "name:slv_x_preferred":[
        "Codera"
    ],
    "name:spa_x_preferred":[
        "Codera"
    ],
    "name:srp_x_preferred":[
        "Codera"
    ],
    "name:swe_x_preferred":[
        "Codera"
    ],
    "name:tgl_x_preferred":[
        "Codera"
    ],
    "name:tur_x_preferred":[
        "Codera"
    ],
    "name:war_x_preferred":[
        "Codera"
    ],
    "qs_pg:aaroncc":"IT",
    "qs_pg:name":"Codera",
    "qs_pg:name_adm0":"Italia",
    "qs_pg:name_adm1":"Lombardia",
    "qs_pg:photos":180,
    "qs_pg:photos_1k":36,
    "qs_pg:photos_9k":1,
    "qs_pg:photos_9r":4,
    "qs_pg:photos_all":180,
    "qs_pg:photos_sr":4,
    "qs_pg:pop_sr":0,
    "qs_pg:qs_pg_placetype":"locality",
    "qs_pg:qs_pg_placetype_gp":"Town",
    "qs_pg:woe_adm0":23424853,
    "woe:adm0_id":23424853,
    "woe:name_adm0":"Italia",
    "woe:name_adm1":"Lombardia",
    "woe:placetype":"Town",
    "wof:name":"Codera",
    "wof:placetype":"locality"
},
  "geometry": {"coordinates":[9.473862,46.239345],"type":"Point"}
}