{
  "type": "Feature",
  "properties": {
    "gn:admin1_code":"3.0",
    "gn:admin2_code":"CS",
    "gn:admin3_code":"78044.0",
    "gn:asciiname":"Thurio",
    "gn:cc2":"IT",
    "gn:country_code":"IT",
    "gn:dem":8,
    "gn:elevation":"8.0",
    "gn:feature_class":"P",
    "gn:feature_code":"PPL",
    "gn:name":"Thurio",
    "gn:population":98,
    "gn:timezone":"Europe/Rome",
    "iso:country":"IT",
    "name:und_x_variant":[
        "Villaggio Thurio",
        "Thurio"
    ],
    "wof:name":"Thurio",
    "wof:placetype":"locality",
    "wof:population":98
},
  "geometry": {"coordinates":[16.46992,39.69386],"type":"Point"}
}