{
  "type": "Feature",
  "properties": {
    "gn:admin1_code":"9",
    "gn:admin2_code":"SO",
    "gn:admin3_code":"14015.0",
    "gn:asciiname":"Artigianale-Commerciale",
    "gn:country_code":"IT",
    "gn:dem":274,
    "gn:feature_class":"P",
    "gn:feature_code":"PPL",
    "gn:name":"Artigianale-Commerciale",
    "gn:population":132,
    "gn:timezone":"Europe/Rome",
    "iso:country":"IT",
    "wof:name":"Artigianale-Commerciale",
    "wof:placetype":"locality",
    "wof:population":132
},
  "geometry": {"coordinates":[9.81274,46.16256],"type":"Point"}
}