{
  "type": "Feature",
  "properties": {
    "gn:admin1_code":"4",
    "gn:admin2_code":"CE",
    "gn:admin3_code":"61045.0",
    "gn:asciiname":"Cese",
    "gn:country_code":"IT",
    "gn:dem":445,
    "gn:feature_class":"P",
    "gn:feature_code":"PPL",
    "gn:name":"Cese",
    "gn:population":110,
    "gn:timezone":"Europe/Rome",
    "iso:country":"IT",
    "wof:name":"Cese",
    "wof:placetype":"locality",
    "wof:population":110
},
  "geometry": {"coordinates":[14.2767,41.22836],"type":"Point"}
}