{
  "type": "Feature",
  "properties": {
    "gn:admin1_code":"9",
    "gn:admin2_code":"MN",
    "gn:admin3_code":"20006.0",
    "gn:asciiname":"Capo di Villa",
    "gn:country_code":"IT",
    "gn:dem":12,
    "gn:feature_class":"P",
    "gn:feature_code":"PPL",
    "gn:name":"Capo di Villa",
    "gn:population":17,
    "gn:timezone":"Europe/Rome",
    "iso:country":"IT",
    "wof:name":"Capo di Villa",
    "wof:placetype":"locality",
    "wof:population":17
},
  "geometry": {"coordinates":[11.18545,45.0491],"type":"Point"}
}