{
  "type": "Feature",
  "properties": {
    "gn:admin1_code":"1",
    "gn:admin2_code":"CH",
    "gn:admin3_code":"69032.0",
    "gn:asciiname":"Colle di Sciore",
    "gn:country_code":"IT",
    "gn:dem":385,
    "gn:feature_class":"P",
    "gn:feature_code":"PPL",
    "gn:name":"Colle di Sciore",
    "gn:population":36,
    "gn:timezone":"Europe/Rome",
    "iso:country":"IT",
    "wof:name":"Colle di Sciore",
    "wof:placetype":"locality",
    "wof:population":36
},
  "geometry": {"coordinates":[14.24459,42.21985],"type":"Point"}
}