{
  "type": "Feature",
  "properties": {
    "gn:admin1_code":"20.0",
    "gn:admin2_code":"BL",
    "gn:admin3_code":"25018.0",
    "gn:asciiname":"I Romiti",
    "gn:country_code":"IT",
    "gn:dem":999,
    "gn:feature_class":"P",
    "gn:feature_code":"PPL",
    "gn:name":"I Romiti",
    "gn:population":0,
    "gn:timezone":"Europe/Rome",
    "iso:country":"IT",
    "wof:name":"I Romiti",
    "wof:placetype":"locality"
},
  "geometry": {"coordinates":[12.42639,46.45167],"type":"Point"}
}