{
  "type": "Feature",
  "properties": {
    "gn:admin1_code":"20",
    "gn:admin2_code":"VR",
    "gn:admin3_code":"23086.0",
    "gn:asciiname":"Crero",
    "gn:country_code":"IT",
    "gn:dem":212,
    "gn:feature_class":"P",
    "gn:feature_code":"PPL",
    "gn:name":"Crero",
    "gn:population":14,
    "gn:timezone":"Europe/Rome",
    "iso:country":"IT",
    "wof:name":"Crero",
    "wof:placetype":"locality",
    "wof:population":14
},
  "geometry": {"coordinates":[10.71181,45.63883],"type":"Point"}
}