{
  "type": "Feature",
  "properties": {
    "gn:admin1_code":"20",
    "gn:admin2_code":"BL",
    "gn:admin3_code":"25051.0",
    "gn:asciiname":"Dogana Vecchia",
    "gn:country_code":"IT",
    "gn:dem":1114,
    "gn:feature_class":"P",
    "gn:feature_code":"PPLL",
    "gn:name":"Dogana Vecchia",
    "gn:population":10,
    "gn:timezone":"Europe/Rome",
    "iso:country":"IT",
    "wof:name":"Dogana Vecchia",
    "wof:placetype":"locality",
    "wof:population":10
},
  "geometry": {"coordinates":[12.18266,46.49103],"type":"Point"}
}