{
  "type": "Feature",
  "properties": {
    "gn:admin1_code":"7.0",
    "gn:admin2_code":"FR",
    "gn:admin3_code":"60044.0",
    "gn:asciiname":"Porrino Vicolo",
    "gn:country_code":"IT",
    "gn:dem":271,
    "gn:feature_class":"P",
    "gn:feature_code":"PPL",
    "gn:name":"Porrino Vicolo",
    "gn:population":80,
    "gn:timezone":"Europe/Rome",
    "iso:country":"IT",
    "wof:name":"Porrino Vicolo",
    "wof:placetype":"locality",
    "wof:population":80
},
  "geometry": {"coordinates":[13.51404,41.66963],"type":"Point"}
}