{
  "type": "Feature",
  "properties": {
    "gn:admin1_code":"20",
    "gn:admin2_code":"VI",
    "gn:admin3_code":"24076.0",
    "gn:asciiname":"Ciechi",
    "gn:country_code":"IT",
    "gn:dem":487,
    "gn:feature_class":"P",
    "gn:feature_code":"PPL",
    "gn:name":"Ciechi",
    "gn:population":42,
    "gn:timezone":"Europe/Rome",
    "iso:country":"IT",
    "wof:name":"Ciechi",
    "wof:placetype":"locality",
    "wof:population":42
},
  "geometry": {"coordinates":[11.29165,45.91433],"type":"Point"}
}