{
  "type": "Feature",
  "properties": {
    "gn:admin1_code":"3.0",
    "gn:admin2_code":"CZ",
    "gn:admin3_code":"79068.0",
    "gn:asciiname":"Vincolise",
    "gn:country_code":"IT",
    "gn:dem":616,
    "gn:feature_class":"P",
    "gn:feature_code":"PPL",
    "gn:name":"Vincolise",
    "gn:population":80,
    "gn:timezone":"Europe/Rome",
    "iso:country":"IT",
    "wof:name":"Vincolise",
    "wof:placetype":"locality",
    "wof:population":80
},
  "geometry": {"coordinates":[16.61114,39.01828],"type":"Point"}
}