{
  "type": "Feature",
  "properties": {
    "gn:admin1_code":"5",
    "gn:admin2_code":"FE",
    "gn:admin3_code":"38017.0",
    "gn:asciiname":"Borgo Bordocchia",
    "gn:country_code":"IT",
    "gn:dem":-1,
    "gn:feature_class":"P",
    "gn:feature_code":"PPL",
    "gn:name":"Borgo Bordocchia",
    "gn:population":29,
    "gn:timezone":"Europe/Rome",
    "iso:country":"IT",
    "wof:name":"Borgo Bordocchia",
    "wof:placetype":"locality",
    "wof:population":29
},
  "geometry": {"coordinates":[11.88361,44.72763],"type":"Point"}
}