{
  "type": "Feature",
  "properties": {
    "gn:admin1_code":"6.0",
    "gn:admin2_code":"TS",
    "gn:admin3_code":"32004.0",
    "gn:asciiname":"Bagnoli della Rosandra",
    "gn:cc2":"IT",
    "gn:country_code":"IT",
    "gn:dem":60,
    "gn:elevation":"0.0",
    "gn:feature_class":"P",
    "gn:feature_code":"PPL",
    "gn:name":"Bagnoli della Rosandra",
    "gn:population":0,
    "gn:timezone":"Europe/Rome",
    "iso:country":"IT",
    "name:und_x_variant":[
        "Boljunec",
        "Bagnoli",
        "Bagnoli della Rosandra"
    ],
    "wof:name":"Bagnoli della Rosandra",
    "wof:placetype":"locality"
},
  "geometry": {"coordinates":[13.84946,45.61109],"type":"Point"}
}