{
  "type": "Feature",
  "properties": {
    "gn:admin1_code":"17.0",
    "gn:admin2_code":"BZ",
    "gn:admin3_code":"21071.0",
    "gn:asciiname":"Anterselva Bassa",
    "gn:country_code":"IT",
    "gn:dem":1198,
    "gn:feature_class":"P",
    "gn:feature_code":"PPL",
    "gn:name":"Anterselva Bassa",
    "gn:population":0,
    "gn:timezone":"Europe/Rome",
    "iso:country":"IT",
    "wof:name":"Anterselva Bassa",
    "wof:placetype":"locality"
},
  "geometry": {"coordinates":[12.08333,46.83333],"type":"Point"}
}