{
  "type": "Feature",
  "properties": {
    "gn:admin1_code":"7.0",
    "gn:admin2_code":"RM",
    "gn:admin3_code":"58079.0",
    "gn:asciiname":"Pomeziameteo",
    "gn:country_code":"IT",
    "gn:dem":84,
    "gn:elevation":"88.0",
    "gn:feature_class":"P",
    "gn:feature_code":"PPLL",
    "gn:name":"Pomeziameteo",
    "gn:population":0,
    "gn:timezone":"Europe/Rome",
    "iso:country":"IT",
    "wof:name":"Pomeziameteo",
    "wof:placetype":"locality"
},
  "geometry": {"coordinates":[12.50918,41.6682],"type":"Point"}
}