{
  "type": "Feature",
  "properties": {
    "gn:admin1_code":"3.0",
    "gn:admin2_code":"CS",
    "gn:admin3_code":"78013.0",
    "gn:asciiname":"Vadi",
    "gn:country_code":"IT",
    "gn:dem":371,
    "gn:elevation":"425.0",
    "gn:feature_class":"P",
    "gn:feature_code":"PPL",
    "gn:name":"Vadi",
    "gn:population":395,
    "gn:timezone":"Europe/Rome",
    "iso:country":"IT",
    "name:ceb_x_preferred":[
        "Vadi"
    ],
    "name:fra_x_preferred":[
        "Vadi"
    ],
    "name:ita_x_preferred":[
        "Vadi"
    ],
    "name:swe_x_preferred":[
        "Vadi"
    ],
    "name:tur_x_preferred":[
        "Vadi"
    ],
    "wof:name":"Vadi",
    "wof:placetype":"locality",
    "wof:population":395
},
  "geometry": {"coordinates":[16.10271,39.16173],"type":"Point"}
}