{
  "type": "Feature",
  "properties": {
    "gn:admin1_code":"4",
    "gn:admin3_code":"63034.0",
    "gn:asciiname":"Contrada Fellapane",
    "gn:country_code":"IT",
    "gn:dem":86,
    "gn:feature_class":"P",
    "gn:feature_code":"PPL",
    "gn:name":"Contrada Fellapane",
    "gn:population":220,
    "gn:timezone":"Europe/Rome",
    "iso:country":"IT",
    "wof:name":"Contrada Fellapane",
    "wof:placetype":"locality",
    "wof:population":220
},
  "geometry": {"coordinates":[14.13854,40.93089000000001],"type":"Point"}
}