{
  "type": "Feature",
  "properties": {
    "gn:admin1_code":"16",
    "gn:admin2_code":"GR",
    "gn:admin3_code":"53008.0",
    "gn:asciiname":"Casalmaggiore",
    "gn:country_code":"IT",
    "gn:dem":360,
    "gn:feature_class":"P",
    "gn:feature_code":"PPL",
    "gn:name":"Casalmaggiore",
    "gn:population":15,
    "gn:timezone":"Europe/Rome",
    "iso:country":"IT",
    "name:azb_x_preferred":[
        "\u06a9\u0627\u0633\u0627\u0644\u200c\u0645\u0627\u062c\u06cc\u0648\u0631\u0647"
    ],
    "name:bul_x_preferred":[
        "\u041a\u0430\u0437\u0430\u043b\u043c\u0430\u0434\u0436\u043e\u0440\u0435"
    ],
    "name:ceb_x_preferred":[
        "Casalmaggiore"
    ],
    "name:deu_x_preferred":[
        "Casalmaggiore"
    ],
    "name:epo_x_preferred":[
        "Casalmaggiore"
    ],
    "name:eus_x_preferred":[
        "Casalmaggiore"
    ],
    "name:fas_x_preferred":[
        "\u06a9\u0627\u0633\u0627\u0644\u200c\u0645\u0627\u062c\u06cc\u0648\u0631\u0647"
    ],
    "name:fra_x_preferred":[
        "Casalmaggiore"
    ],
    "name:heb_x_preferred":[
        "\u05e7\u05d0\u05d6\u05dc\u05de\u05d2'\u05d5\u05e8\u05d4"
    ],
    "name:hun_x_preferred":[
        "Casalmaggiore"
    ],
    "name:hye_x_preferred":[
        "\u053f\u0561\u0566\u0561\u056c\u0574\u0561\u057b\u056b\u0578\u0580\u0565"
    ],
    "name:ita_x_preferred":[
        "Casalmaggiore"
    ],
    "name:jpn_x_preferred":[
        "\u30ab\u30b6\u30eb\u30de\u30c3\u30b8\u30e7\u30fc\u30ec"
    ],
    "name:kaz_x_preferred":[
        "\u041a\u0430\u0437\u0430\u043b\u044c\u043c\u0430\u0434\u0436\u043e\u0440\u0435"
    ],
    "name:lat_x_preferred":[
        "Casale Maius"
    ],
    "name:lmo_x_preferred":[
        "Casalmagiur"
    ],
    "name:msa_x_preferred":[
        "Casalmaggiore"
    ],
    "name:nap_x_preferred":[
        "Casalmaggiore"
    ],
    "name:nld_x_preferred":[
        "Casalmaggiore"
    ],
    "name:pms_x_preferred":[
        "Casalmaggiore"
    ],
    "name:pol_x_preferred":[
        "Casalmaggiore"
    ],
    "name:por_x_preferred":[
        "Casalmaggiore"
    ],
    "name:ron_x_preferred":[
        "Casalmaggiore"
    ],
    "name:rus_x_preferred":[
        "\u041a\u0430\u0437\u0430\u043b\u044c\u043c\u0430\u0434\u0436\u043e\u0440\u0435"
    ],
    "name:scn_x_preferred":[
        "Casalmaggiore"
    ],
    "name:spa_x_preferred":[
        "Casalmaggiore"
    ],
    "name:srp_x_preferred":[
        "\u041a\u0430\u0437\u0430\u043b\u043c\u0430\u0452\u043e\u0440\u0435"
    ],
    "name:ukr_x_preferred":[
        "\u041a\u0430\u0437\u0430\u043b\u044c\u043c\u0430\u0434\u0436\u043e\u0440\u0435"
    ],
    "name:uzb_x_preferred":[
        "Casalmaggiore"
    ],
    "name:vie_x_preferred":[
        "Casalmaggiore"
    ],
    "name:vol_x_preferred":[
        "Casalmaggiore"
    ],
    "name:war_x_preferred":[
        "Casalmaggiore"
    ],
    "name:zho_x_preferred":[
        "\u5361\u8428\u5c14\u9a6c\u7126\u96f7"
    ],
    "wof:name":"Casalmaggiore",
    "wof:placetype":"locality",
    "wof:population":15
},
  "geometry": {"coordinates":[11.3155,43.07272],"type":"Point"}
}