{
  "type": "Feature",
  "properties": {
    "gn:admin1_code":"16",
    "gn:admin2_code":"GR",
    "gn:admin3_code":"53008.0",
    "gn:asciiname":"Casalmaggiore",
    "gn:country_code":"IT",
    "gn:dem":360,
    "gn:feature_class":"P",
    "gn:feature_code":"PPL",
    "gn:name":"Casalmaggiore",
    "gn:population":15,
    "gn:timezone":"Europe/Rome",
    "iso:country":"IT",
    "wof:name":"Casalmaggiore",
    "wof:placetype":"locality",
    "wof:population":15
},
  "geometry": {"coordinates":[11.3155,43.07272],"type":"Point"}
}