{
  "type": "Feature",
  "properties": {
    "gn:admin1_code":"3.0",
    "gn:admin2_code":"CZ",
    "gn:admin3_code":"79036.0",
    "gn:asciiname":"Casa San Filo",
    "gn:cc2":"IT",
    "gn:country_code":"IT",
    "gn:dem":182,
    "gn:feature_class":"P",
    "gn:feature_code":"PPL",
    "gn:name":"Casa San Filo",
    "gn:population":0,
    "gn:timezone":"Europe/Rome",
    "iso:country":"IT",
    "name:und_x_variant":[
        "San Fili",
        "Casa San Filo"
    ],
    "wof:name":"Casa San Filo",
    "wof:placetype":"locality"
},
  "geometry": {"coordinates":[16.78333,38.95],"type":"Point"}
}