{
  "type": "Feature",
  "properties": {
    "gn:admin1_code":"16",
    "gn:admin2_code":"GR",
    "gn:admin3_code":"53025.0",
    "gn:asciiname":"Casa Lichio",
    "gn:country_code":"IT",
    "gn:dem":790,
    "gn:feature_class":"P",
    "gn:feature_code":"PPL",
    "gn:name":"Casa Lichio",
    "gn:population":11,
    "gn:timezone":"Europe/Rome",
    "iso:country":"IT",
    "wof:name":"Casa Lichio",
    "wof:placetype":"locality",
    "wof:population":11
},
  "geometry": {"coordinates":[11.58546,42.91468],"type":"Point"}
}