{
  "type": "Feature",
  "properties": {
    "gn:admin1_code":"15.0",
    "gn:admin2_code":"CT",
    "gn:admin3_code":"87002.0",
    "gn:asciiname":"Cannizzaro",
    "gn:country_code":"IT",
    "gn:dem":13,
    "gn:feature_class":"P",
    "gn:feature_code":"PPL",
    "gn:name":"Cannizzaro",
    "gn:population":0,
    "gn:timezone":"Europe/Rome",
    "iso:country":"IT",
    "wof:name":"Cannizzaro",
    "wof:placetype":"locality"
},
  "geometry": {"coordinates":[15.13401,37.54068],"type":"Point"}
}