{
  "type": "Feature",
  "properties": {
    "gn:admin1_code":"3",
    "gn:admin2_code":"CS",
    "gn:admin3_code":"78029.0",
    "gn:asciiname":"Masseria Murata",
    "gn:country_code":"IT",
    "gn:dem":39,
    "gn:feature_class":"P",
    "gn:feature_code":"PPL",
    "gn:name":"Masseria Murata",
    "gn:population":143,
    "gn:timezone":"Europe/Rome",
    "iso:country":"IT",
    "wof:name":"Masseria Murata",
    "wof:placetype":"locality",
    "wof:population":143
},
  "geometry": {"coordinates":[16.40514,39.76608],"type":"Point"}
}