{
  "type": "Feature",
  "properties": {
    "gn:admin1_code":"9",
    "gn:admin2_code":"BS",
    "gn:admin3_code":"17187.0",
    "gn:asciiname":"Cabiana",
    "gn:country_code":"IT",
    "gn:dem":290,
    "gn:feature_class":"P",
    "gn:feature_code":"PPL",
    "gn:name":"Cabiana",
    "gn:population":97,
    "gn:timezone":"Europe/Rome",
    "iso:country":"IT",
    "wof:name":"Cabiana",
    "wof:placetype":"locality",
    "wof:population":97
},
  "geometry": {"coordinates":[10.62209,45.65945],"type":"Point"}
}