{
  "type": "Feature",
  "properties": {
    "gn:admin1_code":"7",
    "gn:admin2_code":"LT",
    "gn:admin3_code":"59029.0",
    "gn:asciiname":"Morgazzano Sant'Adamini",
    "gn:country_code":"IT",
    "gn:dem":124,
    "gn:feature_class":"P",
    "gn:feature_code":"PPL",
    "gn:name":"Morgazzano Sant'Adamini",
    "gn:population":80,
    "gn:timezone":"Europe/Rome",
    "iso:country":"IT",
    "wof:name":"Morgazzano Sant'Adamini",
    "wof:placetype":"locality",
    "wof:population":80
},
  "geometry": {"coordinates":[13.21375,41.42806],"type":"Point"}
}