{
  "type": "Feature",
  "properties": {
    "gn:admin1_code":"20.0",
    "gn:admin2_code":"PD",
    "gn:admin3_code":"28047.0",
    "gn:asciiname":"Chiavicone",
    "gn:country_code":"IT",
    "gn:dem":11,
    "gn:feature_class":"P",
    "gn:feature_code":"PPL",
    "gn:name":"Chiavicone",
    "gn:population":61,
    "gn:timezone":"Europe/Rome",
    "iso:country":"IT",
    "wof:name":"Chiavicone",
    "wof:placetype":"locality",
    "wof:population":61
},
  "geometry": {"coordinates":[11.61949,45.2607],"type":"Point"}
}