{
  "type": "Feature",
  "properties": {
    "gn:admin1_code":"1",
    "gn:admin2_code":"CH",
    "gn:admin3_code":"69074.0",
    "gn:asciiname":"Vallevo",
    "gn:country_code":"IT",
    "gn:dem":21,
    "gn:feature_class":"P",
    "gn:feature_code":"PPL",
    "gn:name":"Vallev\u00f2",
    "gn:population":229,
    "gn:timezone":"Europe/Rome",
    "iso:country":"IT",
    "name:und_x_variant":[
        "Vallev\u00f2"
    ],
    "wof:name":"Vallevo",
    "wof:placetype":"locality",
    "wof:population":229
},
  "geometry": {"coordinates":[14.47869,42.28721],"type":"Point"}
}