{
  "type": "Feature",
  "properties": {
    "gn:admin1_code":"12.0",
    "gn:admin2_code":"AT",
    "gn:admin3_code":"5014.0",
    "gn:asciiname":"Cascine Pietra",
    "gn:country_code":"IT",
    "gn:dem":156,
    "gn:feature_class":"P",
    "gn:feature_code":"PPL",
    "gn:name":"Cascine Pietra",
    "gn:population":35,
    "gn:timezone":"Europe/Rome",
    "iso:country":"IT",
    "wof:name":"Cascine Pietra",
    "wof:placetype":"locality",
    "wof:population":35
},
  "geometry": {"coordinates":[8.23851,44.9983],"type":"Point"}
}