{
  "type": "Feature",
  "properties": {
    "gn:admin1_code":"12",
    "gn:admin2_code":"AL",
    "gn:admin3_code":"6028.0",
    "gn:asciiname":"Pessinate",
    "gn:country_code":"IT",
    "gn:dem":599,
    "gn:feature_class":"P",
    "gn:feature_code":"PPL",
    "gn:name":"Pessinate",
    "gn:population":30,
    "gn:timezone":"Europe/Rome",
    "iso:country":"IT",
    "wof:name":"Pessinate",
    "wof:placetype":"locality",
    "wof:population":30
},
  "geometry": {"coordinates":[9.08318,44.74336],"type":"Point"}
}