{
  "type": "Feature",
  "properties": {
    "gn:admin1_code":"4",
    "gn:admin2_code":"BN",
    "gn:admin3_code":"62053.0",
    "gn:asciiname":"Staglio II",
    "gn:country_code":"IT",
    "gn:dem":293,
    "gn:feature_class":"P",
    "gn:feature_code":"PPL",
    "gn:name":"Staglio II",
    "gn:population":19,
    "gn:timezone":"Europe/Rome",
    "iso:country":"IT",
    "wof:name":"Staglio II",
    "wof:placetype":"locality",
    "wof:population":19
},
  "geometry": {"coordinates":[14.70266,41.23636],"type":"Point"}
}