{
  "type": "Feature",
  "properties": {
    "gn:admin1_code":"20.0",
    "gn:admin2_code":"VR",
    "gn:admin3_code":"23023.0",
    "gn:asciiname":"Torcolo",
    "gn:country_code":"IT",
    "gn:dem":153,
    "gn:feature_class":"P",
    "gn:feature_code":"PPL",
    "gn:name":"Torcolo",
    "gn:population":14,
    "gn:timezone":"Europe/Rome",
    "iso:country":"IT",
    "wof:name":"Torcolo",
    "wof:placetype":"locality",
    "wof:population":14
},
  "geometry": {"coordinates":[10.76424,45.52736],"type":"Point"}
}