{
  "type": "Feature",
  "properties": {
    "gn:admin1_code":"12",
    "gn:admin2_code":"AT",
    "gn:admin3_code":"5067.0",
    "gn:asciiname":"Mondrossa",
    "gn:country_code":"IT",
    "gn:dem":229,
    "gn:feature_class":"P",
    "gn:feature_code":"PPL",
    "gn:name":"Mondrossa",
    "gn:population":256,
    "gn:timezone":"Europe/Rome",
    "iso:country":"IT",
    "wof:name":"Mondrossa",
    "wof:placetype":"locality",
    "wof:population":256
},
  "geometry": {"coordinates":[8.08432,44.93752],"type":"Point"}
}