{
  "type": "Feature",
  "properties": {
    "gn:admin1_code":"20",
    "gn:admin2_code":"VI",
    "gn:admin3_code":"24015.0",
    "gn:asciiname":"Monti Comunali",
    "gn:country_code":"IT",
    "gn:dem":178,
    "gn:feature_class":"P",
    "gn:feature_code":"PPL",
    "gn:name":"Monti Comunali",
    "gn:population":29,
    "gn:timezone":"Europe/Rome",
    "iso:country":"IT",
    "wof:name":"Monti Comunali",
    "wof:placetype":"locality",
    "wof:population":29
},
  "geometry": {"coordinates":[11.45273,45.48262],"type":"Point"}
}