{
  "type": "Feature",
  "properties": {
    "gn:admin1_code":"17",
    "gn:admin2_code":"TN",
    "gn:admin3_code":"22087.0",
    "gn:asciiname":"Cueli-Liberi",
    "gn:country_code":"IT",
    "gn:dem":1129,
    "gn:feature_class":"P",
    "gn:feature_code":"PPL",
    "gn:name":"Cueli-Liberi",
    "gn:population":14,
    "gn:timezone":"Europe/Rome",
    "iso:country":"IT",
    "wof:name":"Cueli-Liberi",
    "wof:placetype":"locality",
    "wof:population":14
},
  "geometry": {"coordinates":[11.21745,45.92015],"type":"Point"}
}