{
  "type": "Feature",
  "properties": {
    "gn:admin1_code":"17",
    "gn:admin2_code":"TN",
    "gn:admin3_code":"22205.0",
    "gn:asciiname":"Ronchi",
    "gn:country_code":"IT",
    "gn:dem":187,
    "gn:feature_class":"P",
    "gn:feature_code":"PPL",
    "gn:name":"Ronchi",
    "gn:population":94,
    "gn:timezone":"Europe/Rome",
    "iso:country":"IT",
    "name:ceb_x_preferred":[
        "Ronchi"
    ],
    "name:deu_x_preferred":[
        "Ronchi"
    ],
    "name:epo_x_preferred":[
        "Ronchi"
    ],
    "name:ita_x_preferred":[
        "Ronchi"
    ],
    "name:lat_x_preferred":[
        "Ronches"
    ],
    "name:por_x_preferred":[
        "Ronchi"
    ],
    "name:scn_x_preferred":[
        "Ronchi"
    ],
    "name:srp_x_preferred":[
        "Ronki"
    ],
    "name:swe_x_preferred":[
        "Ronchi"
    ],
    "wof:name":"Ronchi",
    "wof:placetype":"locality",
    "wof:population":94
},
  "geometry": {"coordinates":[11.13219,46.01754],"type":"Point"}
}