{
  "type": "Feature",
  "properties": {
    "gn:admin1_code":"16",
    "gn:admin2_code":"GR",
    "gn:admin3_code":"53001.0",
    "gn:asciiname":"San Lorenzo",
    "gn:country_code":"IT",
    "gn:dem":686,
    "gn:feature_class":"P",
    "gn:feature_code":"PPL",
    "gn:name":"San Lorenzo",
    "gn:population":274,
    "gn:timezone":"Europe/Rome",
    "iso:country":"IT",
    "name:ara_x_preferred":[
        "\u0633\u0627\u0646 \u0644\u0648\u0631\u064a\u0646\u0632\u0648"
    ],
    "name:ben_x_preferred":[
        "\u09b8\u09be\u09a8 \u09b2\u09cb\u09b0\u09c7\u099e\u09cd\u099c\u09cb"
    ],
    "name:ceb_x_preferred":[
        "San Lorenzo"
    ],
    "name:ell_x_preferred":[
        "\u03a3\u03b1\u03bd \u039b\u03bf\u03c1\u03ad\u03bd\u03c4\u03b6\u03bf"
    ],
    "name:fas_x_preferred":[
        "\u0633\u0646 \u0644\u0648\u0631\u0646\u0632\u0648"
    ],
    "name:fra_x_preferred":[
        "San Lorenzo"
    ],
    "name:heb_x_preferred":[
        "\u05e1\u05df \u05dc\u05d5\u05e8\u05e0\u05e6\u05d5"
    ],
    "name:hin_x_preferred":[
        "\u0938\u0948\u0928 \u0932\u094b\u0930\u0947\u0902\u091c\u093c\u094b"
    ],
    "name:hun_x_preferred":[
        "San Lorenzo"
    ],
    "name:ind_x_preferred":[
        "San Lorenzo"
    ],
    "name:ita_x_preferred":[
        "San Lorenzo"
    ],
    "name:jpn_x_preferred":[
        "\u30b5\u30f3\u30ed\u30ec\u30f3\u30c4\u30a9"
    ],
    "name:kor_x_preferred":[
        "\uc0b0 \ub85c\ub80c\uc870"
    ],
    "name:nld_x_preferred":[
        "San Lorenzo"
    ],
    "name:pol_x_preferred":[
        "San Lorenzo"
    ],
    "name:por_x_preferred":[
        "San Lorenzo"
    ],
    "name:srp_x_preferred":[
        "\u0421\u0430\u043d \u041b\u043e\u0440\u0435\u043d\u0446\u043e"
    ],
    "name:swe_x_preferred":[
        "San Lorenzo"
    ],
    "name:tur_x_preferred":[
        "San Lorenzo"
    ],
    "name:ukr_x_preferred":[
        "\u0421\u0430\u043d-\u041b\u043e\u0440\u0435\u043d\u0441\u043e"
    ],
    "name:urd_x_preferred":[
        "\u0633\u0627\u0646 \u0644\u0648\u0631\u06cc\u0646\u0632\u0648"
    ],
    "name:vie_x_preferred":[
        "San Lorenzo"
    ],
    "name:zho_cn_x_preferred":[
        "\u5723\u6d1b\u4f26\u7d22"
    ],
    "name:zho_tw_x_preferred":[
        "\u8056\u6d1b\u502b\u7d22"
    ],
    "wof:name":"San Lorenzo",
    "wof:placetype":"locality",
    "wof:population":274
},
  "geometry": {"coordinates":[11.54247,42.88055],"type":"Point"}
}