{
  "type": "Feature",
  "properties": {
    "gn:admin1_code":"12",
    "gn:admin2_code":"VB",
    "gn:admin3_code":"103014.0",
    "gn:asciiname":"Duiamen",
    "gn:country_code":"IT",
    "gn:dem":499,
    "gn:feature_class":"P",
    "gn:feature_code":"PPL",
    "gn:name":"Duiamen",
    "gn:population":11,
    "gn:timezone":"Europe/Rome",
    "iso:country":"IT",
    "wof:name":"Duiamen",
    "wof:placetype":"locality",
    "wof:population":11
},
  "geometry": {"coordinates":[8.17899,46.00535],"type":"Point"}
}