{
  "type": "Feature",
  "properties": {
    "gn:admin1_code":"5.0",
    "gn:admin2_code":"PC",
    "gn:admin3_code":"33026.0",
    "gn:asciiname":"Chiavenna Rocchetta",
    "gn:country_code":"IT",
    "gn:dem":185,
    "gn:elevation":"185.0",
    "gn:feature_class":"P",
    "gn:feature_code":"PPL",
    "gn:name":"Chiavenna Rocchetta",
    "gn:population":27,
    "gn:timezone":"Europe/Rome",
    "iso:country":"IT",
    "wof:name":"Chiavenna Rocchetta",
    "wof:placetype":"locality",
    "wof:population":27
},
  "geometry": {"coordinates":[9.81975,44.84402],"type":"Point"}
}