{
  "type": "Feature",
  "properties": {
    "gn:admin1_code":"1.0",
    "gn:admin2_code":"AQ",
    "gn:admin3_code":"66049.0",
    "gn:asciiname":"Genzano di Sassa",
    "gn:country_code":"IT",
    "gn:dem":674,
    "gn:feature_class":"P",
    "gn:feature_code":"PPL",
    "gn:name":"Genzano di Sassa",
    "gn:population":0,
    "gn:timezone":"Europe/Rome",
    "iso:country":"IT",
    "wof:name":"Genzano di Sassa",
    "wof:placetype":"locality"
},
  "geometry": {"coordinates":[13.32379,42.35138],"type":"Point"}
}