{
  "type": "Feature",
  "properties": {
    "gn:admin1_code":"16",
    "gn:admin2_code":"SI",
    "gn:admin3_code":"52016.0",
    "gn:asciiname":"Bracciano",
    "gn:country_code":"IT",
    "gn:dem":346,
    "gn:feature_class":"P",
    "gn:feature_code":"PPL",
    "gn:name":"Bracciano",
    "gn:population":16,
    "gn:timezone":"Europe/Rome",
    "iso:country":"IT",
    "wof:name":"Bracciano",
    "wof:placetype":"locality",
    "wof:population":16
},
  "geometry": {"coordinates":[11.2344,43.37015],"type":"Point"}
}