{
  "type": "Feature",
  "properties": {
    "gn:admin1_code":"13",
    "gn:admin2_code":"FG",
    "gn:admin3_code":"71060.0",
    "gn:asciiname":"Macchia di Mauro",
    "gn:country_code":"IT",
    "gn:dem":6,
    "gn:feature_class":"P",
    "gn:feature_code":"PPL",
    "gn:name":"Macchia di Mauro",
    "gn:population":22,
    "gn:timezone":"Europe/Rome",
    "iso:country":"IT",
    "wof:name":"Macchia di Mauro",
    "wof:placetype":"locality",
    "wof:population":22
},
  "geometry": {"coordinates":[16.16738,41.86227],"type":"Point"}
}