{
  "type": "Feature",
  "properties": {
    "iso:country":"IT",
    "qs_pg:aaroncc":"IT",
    "qs_pg:name":"Sellere",
    "qs_pg:name_adm0":"Italia",
    "qs_pg:name_adm1":"Lombardia",
    "qs_pg:photos":27,
    "qs_pg:photos_1k":5,
    "qs_pg:photos_9k":1,
    "qs_pg:photos_9r":2,
    "qs_pg:photos_all":27,
    "qs_pg:photos_sr":2,
    "qs_pg:pop_sr":0,
    "qs_pg:qs_pg_placetype":"locality",
    "qs_pg:qs_pg_placetype_gp":"Town",
    "qs_pg:woe_adm0":23424853,
    "woe:adm0_id":23424853,
    "woe:name_adm0":"Italia",
    "woe:name_adm1":"Lombardia",
    "woe:placetype":"Town",
    "wof:name":"Sellere",
    "wof:placetype":"locality"
},
  "geometry": {"coordinates":[10.060781,45.817814],"type":"Point"}
}