{
  "type": "Feature",
  "properties": {
    "gn:admin1_code":"5",
    "gn:admin2_code":"MO",
    "gn:admin3_code":"36039.0",
    "gn:asciiname":"Castello Martinelli",
    "gn:country_code":"IT",
    "gn:dem":22,
    "gn:feature_class":"P",
    "gn:feature_code":"PPL",
    "gn:name":"Castello Martinelli",
    "gn:population":17,
    "gn:timezone":"Europe/Rome",
    "iso:country":"IT",
    "wof:name":"Castello Martinelli",
    "wof:placetype":"locality",
    "wof:population":17
},
  "geometry": {"coordinates":[11.00585,44.79675],"type":"Point"}
}