{
  "type": "Feature",
  "properties": {
    "gn:admin1_code":"8",
    "gn:admin2_code":"SV",
    "gn:admin3_code":"9015.0",
    "gn:asciiname":"Chinelli",
    "gn:country_code":"IT",
    "gn:dem":345,
    "gn:feature_class":"P",
    "gn:feature_code":"PPL",
    "gn:name":"Chinelli",
    "gn:population":44,
    "gn:timezone":"Europe/Rome",
    "iso:country":"IT",
    "wof:name":"Chinelli",
    "wof:placetype":"locality",
    "wof:population":44
},
  "geometry": {"coordinates":[8.28344,44.42773],"type":"Point"}
}