{
  "type": "Feature",
  "properties": {
    "gn:admin1_code":"14.0",
    "gn:admin2_code":"SU",
    "gn:admin3_code":"111105.0",
    "gn:asciiname":"Campulongu",
    "gn:country_code":"IT",
    "gn:dem":4,
    "gn:feature_class":"P",
    "gn:feature_code":"PPL",
    "gn:name":"Campulongu",
    "gn:population":11,
    "gn:timezone":"Europe/Rome",
    "iso:country":"IT",
    "wof:name":"Campulongu",
    "wof:placetype":"locality",
    "wof:population":11
},
  "geometry": {"coordinates":[9.50667,39.12833],"type":"Point"}
}