{
  "type": "Feature",
  "properties": {
    "gn:admin1_code":"10.0",
    "gn:admin2_code":"FM",
    "gn:admin3_code":"109037.0",
    "gn:asciiname":"La Luce",
    "gn:country_code":"IT",
    "gn:dem":38,
    "gn:feature_class":"P",
    "gn:feature_code":"PPL",
    "gn:name":"La Luce",
    "gn:population":683,
    "gn:timezone":"Europe/Rome",
    "iso:country":"IT",
    "wof:name":"La Luce",
    "wof:placetype":"locality",
    "wof:population":683
},
  "geometry": {"coordinates":[13.71883,43.20995],"type":"Point"}
}