{
  "type": "Feature",
  "properties": {
    "gn:admin1_code":"3.0",
    "gn:admin2_code":"RC",
    "gn:admin3_code":"80033.0",
    "gn:asciiname":"Canalello",
    "gn:country_code":"IT",
    "gn:dem":8,
    "gn:feature_class":"P",
    "gn:feature_code":"PPL",
    "gn:name":"Canalello",
    "gn:population":643,
    "gn:timezone":"Europe/Rome",
    "iso:country":"IT",
    "wof:name":"Canalello",
    "wof:placetype":"locality",
    "wof:population":643
},
  "geometry": {"coordinates":[16.13353,38.01849],"type":"Point"}
}