{
  "type": "Feature",
  "properties": {
    "gn:admin1_code":"9.0",
    "gn:admin2_code":"BG",
    "gn:admin3_code":"16116.0",
    "gn:asciiname":"Peroli Alti",
    "gn:country_code":"IT",
    "gn:dem":812,
    "gn:feature_class":"P",
    "gn:feature_code":"PPL",
    "gn:name":"Peroli Alti",
    "gn:population":9,
    "gn:timezone":"Europe/Rome",
    "iso:country":"IT",
    "wof:name":"Peroli Alti",
    "wof:placetype":"locality",
    "wof:population":9
},
  "geometry": {"coordinates":[9.83384,45.87033],"type":"Point"}
}