{
  "type": "Feature",
  "properties": {
    "gn:admin1_code":"16.0",
    "gn:admin2_code":"SI",
    "gn:admin3_code":"52006.0",
    "gn:asciiname":"Pianella",
    "gn:country_code":"IT",
    "gn:dem":223,
    "gn:feature_class":"P",
    "gn:feature_code":"PPL",
    "gn:name":"Pianella",
    "gn:population":567,
    "gn:timezone":"Europe/Rome",
    "iso:country":"IT",
    "wof:name":"Pianella",
    "wof:placetype":"locality",
    "wof:population":567
},
  "geometry": {"coordinates":[11.41624,43.35364000000001],"type":"Point"}
}