{
  "type": "Feature",
  "properties": {
    "gn:admin1_code":"16.0",
    "gn:admin2_code":"SI",
    "gn:admin3_code":"52006.0",
    "gn:asciiname":"Pianella",
    "gn:country_code":"IT",
    "gn:dem":223,
    "gn:feature_class":"P",
    "gn:feature_code":"PPL",
    "gn:name":"Pianella",
    "gn:population":567,
    "gn:timezone":"Europe/Rome",
    "iso:country":"IT",
    "name:ara_x_preferred":[
        "\u0628\u064a\u0627\u0646\u064a\u0644\u0627"
    ],
    "name:azb_x_preferred":[
        "\u067e\u06cc\u0627\u0646\u0644\u0627"
    ],
    "name:bcl_x_preferred":[
        "Pianella"
    ],
    "name:bul_x_preferred":[
        "\u041f\u0438\u0430\u043d\u0435\u043b\u0430"
    ],
    "name:ceb_x_preferred":[
        "Pianella"
    ],
    "name:deu_x_preferred":[
        "Pianella"
    ],
    "name:epo_x_preferred":[
        "Pianella"
    ],
    "name:est_x_preferred":[
        "Pianella"
    ],
    "name:eus_x_preferred":[
        "Pianella"
    ],
    "name:fas_x_preferred":[
        "\u067e\u06cc\u0627\u0646\u0644\u0627"
    ],
    "name:fra_x_preferred":[
        "Pianella"
    ],
    "name:hun_x_preferred":[
        "Pianella"
    ],
    "name:hye_x_preferred":[
        "\u054a\u056b\u0561\u0576\u0565\u056c\u0561"
    ],
    "name:ina_x_preferred":[
        "Pianella"
    ],
    "name:ita_x_preferred":[
        "Pianella"
    ],
    "name:jpn_x_preferred":[
        "\u30d4\u30a2\u30cd\u30c3\u30e9"
    ],
    "name:kaz_x_preferred":[
        "\u041f\u044c\u0430\u043d\u0435\u043b\u043b\u0430"
    ],
    "name:kor_x_preferred":[
        "\ud53c\uc544\ub12c\ub77c"
    ],
    "name:lat_x_preferred":[
        "Planella"
    ],
    "name:lmo_x_preferred":[
        "Pianella"
    ],
    "name:msa_x_preferred":[
        "Pianella"
    ],
    "name:nap_x_preferred":[
        "Pianella"
    ],
    "name:nld_x_preferred":[
        "Pianella"
    ],
    "name:pms_x_preferred":[
        "Pianella"
    ],
    "name:pol_x_preferred":[
        "Pianella"
    ],
    "name:por_x_preferred":[
        "Pianella"
    ],
    "name:ron_x_preferred":[
        "Pianella"
    ],
    "name:rus_x_preferred":[
        "\u041f\u044c\u044f\u043d\u0435\u043b\u043b\u0430"
    ],
    "name:scn_x_preferred":[
        "Pianella"
    ],
    "name:spa_x_preferred":[
        "Pianella"
    ],
    "name:srp_x_preferred":[
        "\u041f\u0458\u0430\u043d\u0435\u043b\u0430"
    ],
    "name:tgl_x_preferred":[
        "Pianella"
    ],
    "name:ukr_x_preferred":[
        "\u041f'\u044f\u043d\u0435\u043b\u043b\u0430"
    ],
    "name:uzb_x_preferred":[
        "Pianella"
    ],
    "name:vie_x_preferred":[
        "Pianella"
    ],
    "name:vol_x_preferred":[
        "Pianella"
    ],
    "name:war_x_preferred":[
        "Pianella"
    ],
    "name:zho_x_preferred":[
        "\u76ae\u4e9a\u5185\u62c9"
    ],
    "wof:name":"Pianella",
    "wof:placetype":"locality",
    "wof:population":567
},
  "geometry": {"coordinates":[11.41624,43.35364000000001],"type":"Point"}
}