{
  "type": "Feature",
  "properties": {
    "gn:admin1_code":"5",
    "gn:admin2_code":"RN",
    "gn:admin3_code":"99008.0",
    "gn:asciiname":"Ca' Severi",
    "gn:country_code":"IT",
    "gn:dem":316,
    "gn:feature_class":"P",
    "gn:feature_code":"PPL",
    "gn:name":"Ca' Severi",
    "gn:population":21,
    "gn:timezone":"Europe/Rome",
    "iso:country":"IT",
    "wof:name":"Ca' Severi",
    "wof:placetype":"locality",
    "wof:population":21
},
  "geometry": {"coordinates":[12.60809,43.87866],"type":"Point"}
}