{
  "type": "Feature",
  "properties": {
    "gn:admin1_code":"20.0",
    "gn:admin2_code":"BL",
    "gn:admin3_code":"25029.0",
    "gn:asciiname":"Triches",
    "gn:country_code":"IT",
    "gn:dem":435,
    "gn:feature_class":"P",
    "gn:feature_code":"PPL",
    "gn:name":"Triches",
    "gn:population":71,
    "gn:timezone":"Europe/Rome",
    "iso:country":"IT",
    "wof:name":"Triches",
    "wof:placetype":"locality",
    "wof:population":71
},
  "geometry": {"coordinates":[12.17889,46.07889],"type":"Point"}
}