{
  "type": "Feature",
  "properties": {
    "iso:country":"IT",
    "wof:name":"Brozzi",
    "wof:placetype":"neighbourhood"
},
  "geometry": {"coordinates":[11.16113405382693,43.79496047043702],"type":"Point"}
}