{
  "type": "Feature",
  "properties": {
    "gn:admin1_code":"8",
    "gn:admin2_code":"SV",
    "gn:admin3_code":"9042.0",
    "gn:asciiname":"Torbora",
    "gn:country_code":"IT",
    "gn:dem":14,
    "gn:feature_class":"P",
    "gn:feature_code":"PPL",
    "gn:name":"Torbora",
    "gn:population":57,
    "gn:timezone":"Europe/Rome",
    "iso:country":"IT",
    "wof:name":"Torbora",
    "wof:placetype":"locality",
    "wof:population":57
},
  "geometry": {"coordinates":[8.41492,44.21658],"type":"Point"}
}