{
  "type": "Feature",
  "properties": {
    "gn:admin1_code":"9",
    "gn:admin2_code":"VA",
    "gn:admin3_code":"12003.0",
    "gn:asciiname":"Montecatini",
    "gn:country_code":"IT",
    "gn:dem":208,
    "gn:feature_class":"P",
    "gn:feature_code":"PPL",
    "gn:name":"Montecatini",
    "gn:population":57,
    "gn:timezone":"Europe/Rome",
    "iso:country":"IT",
    "name:deu_x_preferred":[
        "Montecatini"
    ],
    "name:fin_x_preferred":[
        "Montecatini"
    ],
    "name:fra_x_preferred":[
        "Montecatini"
    ],
    "name:ita_x_preferred":[
        "Montecatini"
    ],
    "name:scn_x_preferred":[
        "Munticatini-Termi"
    ],
    "name:srp_x_preferred":[
        "\u041c\u043e\u043d\u0442\u0435\u043a\u0430\u0442\u0438\u043d\u0438"
    ],
    "wof:name":"Montecatini",
    "wof:placetype":"locality",
    "wof:population":57
},
  "geometry": {"coordinates":[8.60038,45.76002],"type":"Point"}
}