{
  "type": "Feature",
  "properties": {
    "gn:admin1_code":"9",
    "gn:admin2_code":"VA",
    "gn:admin3_code":"12003.0",
    "gn:asciiname":"Montecatini",
    "gn:country_code":"IT",
    "gn:dem":208,
    "gn:feature_class":"P",
    "gn:feature_code":"PPL",
    "gn:name":"Montecatini",
    "gn:population":57,
    "gn:timezone":"Europe/Rome",
    "iso:country":"IT",
    "wof:name":"Montecatini",
    "wof:placetype":"locality",
    "wof:population":57
},
  "geometry": {"coordinates":[8.60038,45.76002],"type":"Point"}
}