{
  "type": "Feature",
  "properties": {
    "gn:admin1_code":"9",
    "gn:admin2_code":"VA",
    "gn:admin3_code":"12142.0",
    "gn:asciiname":"Orascio",
    "gn:country_code":"IT",
    "gn:dem":338,
    "gn:feature_class":"P",
    "gn:feature_code":"PPLL",
    "gn:name":"Orascio",
    "gn:population":10,
    "gn:timezone":"Europe/Rome",
    "iso:country":"IT",
    "wof:name":"Orascio",
    "wof:placetype":"locality",
    "wof:population":10
},
  "geometry": {"coordinates":[8.73609,46.05601],"type":"Point"}
}