{
  "type": "Feature",
  "properties": {
    "gn:admin1_code":"15",
    "gn:admin2_code":"CT",
    "gn:admin3_code":"87013.0",
    "gn:asciiname":"Ragonese",
    "gn:country_code":"IT",
    "gn:dem":224,
    "gn:feature_class":"P",
    "gn:feature_code":"PPL",
    "gn:name":"Ragonese",
    "gn:population":116,
    "gn:timezone":"Europe/Rome",
    "iso:country":"IT",
    "wof:name":"Ragonese",
    "wof:placetype":"locality",
    "wof:population":116
},
  "geometry": {"coordinates":[14.65835,37.47621],"type":"Point"}
}