{
  "type": "Feature",
  "properties": {
    "gn:admin1_code":"9",
    "gn:admin2_code":"MN",
    "gn:admin3_code":"20036.0",
    "gn:asciiname":"Tarsi",
    "gn:country_code":"IT",
    "gn:dem":138,
    "gn:feature_class":"P",
    "gn:feature_code":"PPL",
    "gn:name":"Tarsi",
    "gn:population":17,
    "gn:timezone":"Europe/Rome",
    "iso:country":"IT",
    "wof:name":"Tarsi",
    "wof:placetype":"locality",
    "wof:population":17
},
  "geometry": {"coordinates":[10.66479,45.36338],"type":"Point"}
}