{
  "type": "Feature",
  "properties": {
    "gn:admin1_code":"14",
    "gn:admin2_code":"SS",
    "gn:admin3_code":"90064.0",
    "gn:asciiname":"Campanedda",
    "gn:country_code":"IT",
    "gn:dem":71,
    "gn:feature_class":"P",
    "gn:feature_code":"PPL",
    "gn:name":"Campanedda",
    "gn:population":128,
    "gn:timezone":"Europe/Rome",
    "iso:country":"IT",
    "wof:name":"Campanedda",
    "wof:placetype":"locality",
    "wof:population":128
},
  "geometry": {"coordinates":[8.34637,40.76075],"type":"Point"}
}