{
  "type": "Feature",
  "properties": {
    "gn:admin1_code":"20",
    "gn:admin2_code":"TV",
    "gn:admin3_code":"26071.0",
    "gn:asciiname":"Partisioni",
    "gn:country_code":"IT",
    "gn:dem":8,
    "gn:feature_class":"P",
    "gn:feature_code":"PPL",
    "gn:name":"Partisioni",
    "gn:population":91,
    "gn:timezone":"Europe/Rome",
    "iso:country":"IT",
    "wof:name":"Partisioni",
    "wof:placetype":"locality",
    "wof:population":91
},
  "geometry": {"coordinates":[12.45023,45.69144],"type":"Point"}
}