{
  "type": "Feature",
  "properties": {
    "gn:admin1_code":"7",
    "gn:admin2_code":"RI",
    "gn:admin3_code":"57025.0",
    "gn:asciiname":"Colle Casali",
    "gn:country_code":"IT",
    "gn:dem":423,
    "gn:feature_class":"P",
    "gn:feature_code":"PPL",
    "gn:name":"Colle Casali",
    "gn:population":20,
    "gn:timezone":"Europe/Rome",
    "iso:country":"IT",
    "wof:name":"Colle Casali",
    "wof:placetype":"locality",
    "wof:population":20
},
  "geometry": {"coordinates":[12.76883,42.37181],"type":"Point"}
}