{
  "type": "Feature",
  "properties": {
    "gn:admin1_code":"14.0",
    "gn:admin2_code":"SU",
    "gn:admin3_code":"111009.0",
    "gn:asciiname":"Serbariu di Sopra",
    "gn:country_code":"IT",
    "gn:dem":167,
    "gn:feature_class":"P",
    "gn:feature_code":"PPL",
    "gn:name":"Serbariu di Sopra",
    "gn:population":0,
    "gn:timezone":"Europe/Rome",
    "iso:country":"IT",
    "wof:name":"Serbariu di Sopra",
    "wof:placetype":"locality"
},
  "geometry": {"coordinates":[8.56667,39.15],"type":"Point"}
}