{
  "type": "Feature",
  "properties": {
    "gn:admin1_code":"7.0",
    "gn:admin2_code":"FR",
    "gn:admin3_code":"60023.0",
    "gn:asciiname":"Madonna del Piano",
    "gn:country_code":"IT",
    "gn:dem":137,
    "gn:feature_class":"P",
    "gn:feature_code":"PPL",
    "gn:name":"Madonna del Piano",
    "gn:population":720,
    "gn:timezone":"Europe/Rome",
    "iso:country":"IT",
    "wof:name":"Madonna del Piano",
    "wof:placetype":"locality",
    "wof:population":720
},
  "geometry": {"coordinates":[13.40415,41.51674000000001],"type":"Point"}
}