{
  "type": "Feature",
  "properties": {
    "gn:admin1_code":"5",
    "gn:admin2_code":"PC",
    "gn:admin3_code":"33044.0",
    "gn:asciiname":"Case Orsi",
    "gn:country_code":"IT",
    "gn:dem":271,
    "gn:feature_class":"P",
    "gn:feature_code":"PPL",
    "gn:name":"Case Orsi",
    "gn:population":23,
    "gn:timezone":"Europe/Rome",
    "iso:country":"IT",
    "wof:name":"Case Orsi",
    "wof:placetype":"locality",
    "wof:population":23
},
  "geometry": {"coordinates":[9.91103,44.82387],"type":"Point"}
}