{
  "type": "Feature",
  "properties": {
    "gn:admin1_code":"12",
    "gn:admin2_code":"NO",
    "gn:admin3_code":"3016.0",
    "gn:asciiname":"Cascina Pasquali",
    "gn:country_code":"IT",
    "gn:dem":175,
    "gn:feature_class":"P",
    "gn:feature_code":"PPL",
    "gn:name":"Cascina Pasquali",
    "gn:population":20,
    "gn:timezone":"Europe/Rome",
    "iso:country":"IT",
    "wof:name":"Cascina Pasquali",
    "wof:placetype":"locality",
    "wof:population":20
},
  "geometry": {"coordinates":[8.63576,45.53212],"type":"Point"}
}