{
  "type": "Feature",
  "properties": {
    "gn:admin1_code":"12",
    "gn:admin2_code":"VB",
    "gn:admin3_code":"103013.0",
    "gn:asciiname":"Brovello",
    "gn:country_code":"IT",
    "gn:dem":450,
    "gn:feature_class":"P",
    "gn:feature_code":"PPLA3",
    "gn:name":"Brovello",
    "gn:population":202,
    "gn:timezone":"Europe/Rome",
    "iso:country":"IT",
    "wof:name":"Brovello",
    "wof:placetype":"locality",
    "wof:population":202
},
  "geometry": {"coordinates":[8.53189,45.84246],"type":"Point"}
}