{
  "type": "Feature",
  "properties": {
    "gn:admin1_code":"1",
    "gn:admin2_code":"CH",
    "gn:admin3_code":"69058.0",
    "gn:asciiname":"San Nicola III",
    "gn:country_code":"IT",
    "gn:dem":92,
    "gn:feature_class":"P",
    "gn:feature_code":"PPL",
    "gn:name":"San Nicola III",
    "gn:population":23,
    "gn:timezone":"Europe/Rome",
    "iso:country":"IT",
    "wof:name":"San Nicola III",
    "wof:placetype":"locality",
    "wof:population":23
},
  "geometry": {"coordinates":[14.35868,42.35653],"type":"Point"}
}