{
  "type": "Feature",
  "properties": {
    "gn:admin1_code":"9",
    "gn:admin2_code":"VA",
    "gn:admin3_code":"12115.0",
    "gn:asciiname":"Cantevria",
    "gn:country_code":"IT",
    "gn:dem":267,
    "gn:feature_class":"P",
    "gn:feature_code":"PPL",
    "gn:name":"Cantevria",
    "gn:population":286,
    "gn:timezone":"Europe/Rome",
    "iso:country":"IT",
    "wof:name":"Cantevria",
    "wof:placetype":"locality",
    "wof:population":286
},
  "geometry": {"coordinates":[8.76229,45.91791],"type":"Point"}
}