{
  "type": "Feature",
  "properties": {
    "gn:admin1_code":"18.0",
    "gn:admin2_code":"PG",
    "gn:admin3_code":"54057.0",
    "gn:asciiname":"Casacastalda",
    "gn:country_code":"IT",
    "gn:dem":523,
    "gn:feature_class":"P",
    "gn:feature_code":"PPL",
    "gn:name":"Casacastalda",
    "gn:population":624,
    "gn:timezone":"Europe/Rome",
    "iso:country":"IT",
    "wof:name":"Casacastalda",
    "wof:placetype":"locality",
    "wof:population":624
},
  "geometry": {"coordinates":[12.64708,43.19734],"type":"Point"}
}