{
  "type": "Feature",
  "properties": {
    "gn:admin1_code":"17",
    "gn:admin2_code":"BZ",
    "gn:admin3_code":"21070.0",
    "gn:asciiname":"Vallettina",
    "gn:country_code":"IT",
    "gn:dem":1485,
    "gn:feature_class":"P",
    "gn:feature_code":"PPL",
    "gn:name":"Vallettina",
    "gn:population":21,
    "gn:timezone":"Europe/Rome",
    "iso:country":"IT",
    "wof:name":"Vallettina",
    "wof:placetype":"locality",
    "wof:population":21
},
  "geometry": {"coordinates":[11.25205,46.86843],"type":"Point"}
}