{
  "type": "Feature",
  "properties": {
    "gn:admin1_code":"11",
    "gn:admin2_code":"IS",
    "gn:admin3_code":"94003.0",
    "gn:asciiname":"Santo Ianni",
    "gn:country_code":"IT",
    "gn:dem":611,
    "gn:feature_class":"P",
    "gn:feature_code":"PPL",
    "gn:name":"Santo Ianni",
    "gn:population":27,
    "gn:timezone":"Europe/Rome",
    "iso:country":"IT",
    "wof:name":"Santo Ianni",
    "wof:placetype":"locality",
    "wof:population":27
},
  "geometry": {"coordinates":[14.50269,41.72335],"type":"Point"}
}