{
  "type": "Feature",
  "properties": {
    "gn:admin1_code":"12",
    "gn:admin2_code":"TO",
    "gn:admin3_code":"1307.0",
    "gn:asciiname":"Vincon",
    "gn:country_code":"IT",
    "gn:dem":630,
    "gn:feature_class":"P",
    "gn:feature_code":"PPL",
    "gn:name":"Vincon",
    "gn:population":21,
    "gn:timezone":"Europe/Rome",
    "iso:country":"IT",
    "wof:name":"Vincon",
    "wof:placetype":"locality",
    "wof:population":21
},
  "geometry": {"coordinates":[7.25865,44.91103],"type":"Point"}
}