{
  "type": "Feature",
  "properties": {
    "gn:admin1_code":"5",
    "gn:admin2_code":"FE",
    "gn:admin3_code":"38027.0",
    "gn:asciiname":"Cornacervina",
    "gn:country_code":"IT",
    "gn:dem":0,
    "gn:feature_class":"P",
    "gn:feature_code":"PPL",
    "gn:name":"Cornacervina",
    "gn:population":151,
    "gn:timezone":"Europe/Rome",
    "iso:country":"IT",
    "wof:name":"Cornacervina",
    "wof:placetype":"locality",
    "wof:population":151
},
  "geometry": {"coordinates":[11.92395,44.78029],"type":"Point"}
}