{
  "type": "Feature",
  "properties": {
    "gn:admin1_code":"9.0",
    "gn:admin2_code":"SO",
    "gn:admin3_code":"14067.0",
    "gn:asciiname":"Piasci",
    "gn:country_code":"IT",
    "gn:dem":1669,
    "gn:feature_class":"P",
    "gn:feature_code":"PPLL",
    "gn:name":"Piasci",
    "gn:population":0,
    "gn:timezone":"Europe/Rome",
    "iso:country":"IT",
    "wof:name":"Piasci",
    "wof:placetype":"locality"
},
  "geometry": {"coordinates":[9.82375,46.22979],"type":"Point"}
}