{
  "type": "Feature",
  "properties": {
    "gn:admin1_code":"12.0",
    "gn:admin2_code":"TO",
    "gn:admin3_code":"1201.0",
    "gn:asciiname":"Seytes",
    "gn:country_code":"IT",
    "gn:dem":1721,
    "gn:feature_class":"P",
    "gn:feature_code":"PPL",
    "gn:name":"Seytes",
    "gn:population":0,
    "gn:timezone":"Europe/Rome",
    "iso:country":"IT",
    "wof:name":"Seytes",
    "wof:placetype":"locality"
},
  "geometry": {"coordinates":[6.93333,44.96667],"type":"Point"}
}