{
  "type": "Feature",
  "properties": {
    "gn:admin1_code":"9.0",
    "gn:admin2_code":"PV",
    "gn:admin3_code":"18177.0",
    "gn:asciiname":"Morsella",
    "gn:country_code":"IT",
    "gn:dem":110,
    "gn:feature_class":"P",
    "gn:feature_code":"PPL",
    "gn:name":"Morsella",
    "gn:population":404,
    "gn:timezone":"Europe/Rome",
    "iso:country":"IT",
    "wof:name":"Morsella",
    "wof:placetype":"locality",
    "wof:population":404
},
  "geometry": {"coordinates":[8.81202,45.28282],"type":"Point"}
}