{
  "type": "Feature",
  "properties": {
    "gn:admin1_code":"12",
    "gn:admin2_code":"CN",
    "gn:admin3_code":"4133.0",
    "gn:asciiname":"Tucci",
    "gn:country_code":"IT",
    "gn:dem":334,
    "gn:feature_class":"P",
    "gn:feature_code":"PPL",
    "gn:name":"Tucci",
    "gn:population":74,
    "gn:timezone":"Europe/Rome",
    "iso:country":"IT",
    "wof:name":"Tucci",
    "wof:placetype":"locality",
    "wof:population":74
},
  "geometry": {"coordinates":[7.96212,44.84744],"type":"Point"}
}