{
  "type": "Feature",
  "properties": {
    "gn:admin1_code":"9.0",
    "gn:admin2_code":"BG",
    "gn:admin3_code":"16073.0",
    "gn:asciiname":"Comunita Emmaus",
    "gn:country_code":"IT",
    "gn:dem":255,
    "gn:feature_class":"P",
    "gn:feature_code":"PPLL",
    "gn:name":"Comunit\u00e0 Emmaus",
    "gn:population":5,
    "gn:timezone":"Europe/Rome",
    "iso:country":"IT",
    "name:und_x_variant":[
        "Comunit\u00e0 Emmaus"
    ],
    "wof:name":"Comunita Emmaus",
    "wof:placetype":"locality",
    "wof:population":5
},
  "geometry": {"coordinates":[9.86171,45.65984],"type":"Point"}
}