{
  "type": "Feature",
  "properties": {
    "gn:admin1_code":"8.0",
    "gn:admin2_code":"IM",
    "gn:admin3_code":"8030.0",
    "gn:asciiname":"Isolalunga",
    "gn:country_code":"IT",
    "gn:dem":153,
    "gn:elevation":"89.0",
    "gn:feature_class":"P",
    "gn:feature_code":"PPL",
    "gn:name":"Isolalunga",
    "gn:population":318,
    "gn:timezone":"Europe/Rome",
    "iso:country":"IT",
    "wof:name":"Isolalunga",
    "wof:placetype":"locality",
    "wof:population":318
},
  "geometry": {"coordinates":[7.96104,43.90287],"type":"Point"}
}