{
  "type": "Feature",
  "properties": {
    "gn:admin1_code":"18.0",
    "gn:admin2_code":"PG",
    "gn:admin3_code":"54021.0",
    "gn:asciiname":"Collemezzo",
    "gn:country_code":"IT",
    "gn:dem":390,
    "gn:feature_class":"P",
    "gn:feature_code":"PPL",
    "gn:name":"Collemezzo",
    "gn:population":0,
    "gn:timezone":"Europe/Rome",
    "iso:country":"IT",
    "wof:name":"Collemezzo",
    "wof:placetype":"locality"
},
  "geometry": {"coordinates":[12.58333,42.85],"type":"Point"}
}