{
  "type": "Feature",
  "properties": {
    "gn:admin1_code":"16.0",
    "gn:admin2_code":"FI",
    "gn:admin3_code":"48045.0",
    "gn:asciiname":"Fattoria Montecchio",
    "gn:cc2":"IT",
    "gn:country_code":"IT",
    "gn:dem":389,
    "gn:feature_class":"P",
    "gn:feature_code":"PPL",
    "gn:name":"Fattoria Montecchio",
    "gn:population":0,
    "gn:timezone":"Europe/Rome",
    "iso:country":"IT",
    "name:und_x_variant":[
        "Mont\u00e9cchio",
        "Fattoria Montecchio"
    ],
    "wof:name":"Fattoria Montecchio",
    "wof:placetype":"locality"
},
  "geometry": {"coordinates":[11.25,43.53333],"type":"Point"}
}