{
  "type": "Feature",
  "properties": {
    "gn:admin1_code":"20",
    "gn:admin2_code":"TV",
    "gn:admin3_code":"26046.0",
    "gn:asciiname":"Villette",
    "gn:country_code":"IT",
    "gn:dem":79,
    "gn:feature_class":"P",
    "gn:feature_code":"PPL",
    "gn:name":"Villette",
    "gn:population":14,
    "gn:timezone":"Europe/Rome",
    "iso:country":"IT",
    "name:ceb_x_preferred":[
        "Villette"
    ],
    "name:deu_x_preferred":[
        "Villette"
    ],
    "name:epo_x_preferred":[
        "Villette"
    ],
    "name:eus_x_preferred":[
        "Villette"
    ],
    "name:fin_x_preferred":[
        "Villette"
    ],
    "name:fra_x_preferred":[
        "Villette"
    ],
    "name:ita_x_preferred":[
        "Villette"
    ],
    "name:ltz_x_preferred":[
        "Vilette"
    ],
    "name:nds_x_preferred":[
        "Villette"
    ],
    "name:nld_x_preferred":[
        "Villette"
    ],
    "name:oci_x_preferred":[
        "Villette"
    ],
    "name:pol_x_preferred":[
        "Villette"
    ],
    "name:por_x_preferred":[
        "Villette"
    ],
    "name:rus_x_preferred":[
        "\u041a\u0430\u0442\u0435\u0433\u043e\u0440\u0438\u044f:\u041b\u0430-\u0412\u0438\u043b\u043b\u0435\u0442"
    ],
    "name:slk_x_preferred":[
        "Villette"
    ],
    "name:spa_x_preferred":[
        "Villette"
    ],
    "name:sqi_x_preferred":[
        "Villette"
    ],
    "name:srp_x_preferred":[
        "Vilete"
    ],
    "name:swe_x_preferred":[
        "Villette"
    ],
    "name:ukr_x_preferred":[
        "\u0412\u0456\u043b\u043b\u0435\u0442\u0442"
    ],
    "name:vol_x_preferred":[
        "Villette"
    ],
    "wof:name":"Villette",
    "wof:placetype":"locality",
    "wof:population":14
},
  "geometry": {"coordinates":[12.07214,45.75867],"type":"Point"}
}