{
  "type": "Feature",
  "properties": {
    "gn:admin1_code":"1.0",
    "gn:admin2_code":"CH",
    "gn:admin3_code":"69016.0",
    "gn:asciiname":"Malandra Nuova",
    "gn:country_code":"IT",
    "gn:dem":227,
    "gn:feature_class":"P",
    "gn:feature_code":"PPL",
    "gn:name":"Malandra Nuova",
    "gn:population":18,
    "gn:timezone":"Europe/Rome",
    "iso:country":"IT",
    "wof:name":"Malandra Nuova",
    "wof:placetype":"locality",
    "wof:population":18
},
  "geometry": {"coordinates":[14.1448,42.2864],"type":"Point"}
}