{
  "type": "Feature",
  "properties": {
    "gn:admin1_code":"16",
    "gn:admin2_code":"AR",
    "gn:admin3_code":"51017.0",
    "gn:asciiname":"Cortoreggio",
    "gn:country_code":"IT",
    "gn:dem":314,
    "gn:feature_class":"P",
    "gn:feature_code":"PPL",
    "gn:name":"Cortoreggio",
    "gn:population":63,
    "gn:timezone":"Europe/Rome",
    "iso:country":"IT",
    "wof:name":"Cortoreggio",
    "wof:placetype":"locality",
    "wof:population":63
},
  "geometry": {"coordinates":[12.02005,43.21834000000001],"type":"Point"}
}