{
  "type": "Feature",
  "properties": {
    "gn:admin1_code":"1.0",
    "gn:admin2_code":"TE",
    "gn:admin3_code":"67036.0",
    "gn:asciiname":"Cona Faiete",
    "gn:country_code":"IT",
    "gn:dem":977,
    "gn:feature_class":"P",
    "gn:feature_code":"PPL",
    "gn:name":"Cona Faiete",
    "gn:population":48,
    "gn:timezone":"Europe/Rome",
    "iso:country":"IT",
    "wof:name":"Cona Faiete",
    "wof:placetype":"locality",
    "wof:population":48
},
  "geometry": {"coordinates":[13.55078,42.66982],"type":"Point"}
}