{
  "type": "Feature",
  "properties": {
    "gn:admin1_code":"5",
    "gn:admin2_code":"PR",
    "gn:admin3_code":"34024.0",
    "gn:asciiname":"Case Campanari",
    "gn:country_code":"IT",
    "gn:dem":493,
    "gn:feature_class":"P",
    "gn:feature_code":"PPL",
    "gn:name":"Case Campanari",
    "gn:population":31,
    "gn:timezone":"Europe/Rome",
    "iso:country":"IT",
    "wof:name":"Case Campanari",
    "wof:placetype":"locality",
    "wof:population":31
},
  "geometry": {"coordinates":[10.31371,44.57787],"type":"Point"}
}