{
  "type": "Feature",
  "properties": {
    "gn:admin1_code":"9.0",
    "gn:admin2_code":"PV",
    "gn:admin3_code":"18099.0",
    "gn:asciiname":"Cantarana",
    "gn:country_code":"IT",
    "gn:dem":48,
    "gn:feature_class":"P",
    "gn:feature_code":"PPL",
    "gn:name":"Cantarana",
    "gn:population":15,
    "gn:timezone":"Europe/Rome",
    "iso:country":"IT",
    "wof:name":"Cantarana",
    "wof:placetype":"locality",
    "wof:population":15
},
  "geometry": {"coordinates":[9.48154,45.12046],"type":"Point"}
}