{
  "type": "Feature",
  "properties": {
    "gn:admin1_code":"9.0",
    "gn:admin2_code":"PV",
    "gn:admin3_code":"18099.0",
    "gn:asciiname":"Cantarana",
    "gn:country_code":"IT",
    "gn:dem":48,
    "gn:feature_class":"P",
    "gn:feature_code":"PPL",
    "gn:name":"Cantarana",
    "gn:population":15,
    "gn:timezone":"Europe/Rome",
    "iso:country":"IT",
    "name:ara_x_preferred":[
        "\u0643\u0627\u0646\u062a\u0627\u0631\u0627\u0646\u0627"
    ],
    "name:bel_x_preferred":[
        "\u041a\u0430\u043d\u0442\u0430\u0440\u0430\u043d\u0430"
    ],
    "name:bul_x_preferred":[
        "\u041a\u0430\u043d\u0442\u0430\u0440\u0430\u043d\u0430"
    ],
    "name:cat_x_preferred":[
        "Cantarana"
    ],
    "name:ceb_x_preferred":[
        "Cantarana"
    ],
    "name:ces_x_preferred":[
        "Cantarana"
    ],
    "name:deu_x_preferred":[
        "Cantarana"
    ],
    "name:epo_x_preferred":[
        "Cantarana"
    ],
    "name:eus_x_preferred":[
        "Cantarana"
    ],
    "name:fas_x_preferred":[
        "\u06a9\u0627\u0646\u062a\u0627\u0631\u0627\u0646\u0627"
    ],
    "name:fra_x_preferred":[
        "Cantarana"
    ],
    "name:hun_x_preferred":[
        "Cantarana"
    ],
    "name:hye_x_preferred":[
        "\u053f\u0561\u0576\u057f\u0561\u0580\u0561\u0576\u0561"
    ],
    "name:ind_x_preferred":[
        "Cantarana"
    ],
    "name:ita_x_preferred":[
        "Cantarana"
    ],
    "name:jpn_x_preferred":[
        "\u30ab\u30f3\u30bf\u30e9\u30fc\u30ca"
    ],
    "name:kaz_x_preferred":[
        "\u041a\u0430\u043d\u0442\u0430\u0440\u0430\u043d\u0430"
    ],
    "name:lat_x_preferred":[
        "Cantarana"
    ],
    "name:lmo_x_preferred":[
        "Cantarana"
    ],
    "name:msa_x_preferred":[
        "Cantarana"
    ],
    "name:nap_x_preferred":[
        "Cantarana"
    ],
    "name:nld_x_preferred":[
        "Cantarana"
    ],
    "name:pms_x_preferred":[
        "Cantaran-a"
    ],
    "name:pol_x_preferred":[
        "Cantarana"
    ],
    "name:por_x_preferred":[
        "Cantarana"
    ],
    "name:ron_x_preferred":[
        "Cantarana"
    ],
    "name:rus_x_preferred":[
        "\u041a\u0430\u043d\u0442\u0430\u0440\u0430\u043d\u0430"
    ],
    "name:scn_x_preferred":[
        "Cantarana"
    ],
    "name:spa_x_preferred":[
        "Cantarana d'Asti"
    ],
    "name:tgl_x_preferred":[
        "Cantarana"
    ],
    "name:ukr_x_preferred":[
        "\u041a\u0430\u043d\u0442\u0430\u0440\u0430\u043d\u0430"
    ],
    "name:uzb_x_preferred":[
        "Cantarana"
    ],
    "name:vie_x_preferred":[
        "Cantarana"
    ],
    "name:vol_x_preferred":[
        "Cantarana"
    ],
    "name:war_x_preferred":[
        "Cantarana"
    ],
    "name:zho_x_preferred":[
        "\u574e\u5854\u62c9\u7eb3"
    ],
    "wof:name":"Cantarana",
    "wof:placetype":"locality",
    "wof:population":15
},
  "geometry": {"coordinates":[9.48154,45.12046],"type":"Point"}
}