{
  "type": "Feature",
  "properties": {
    "gn:admin1_code":"5",
    "gn:admin2_code":"RE",
    "gn:admin3_code":"35044.0",
    "gn:asciiname":"Ca' de' Schiavino",
    "gn:country_code":"IT",
    "gn:dem":602,
    "gn:feature_class":"P",
    "gn:feature_code":"PPL",
    "gn:name":"Ca' de' Schiavino",
    "gn:population":22,
    "gn:timezone":"Europe/Rome",
    "iso:country":"IT",
    "wof:name":"Ca' de' Schiavino",
    "wof:placetype":"locality",
    "wof:population":22
},
  "geometry": {"coordinates":[10.5416,44.53018],"type":"Point"}
}