{
  "type": "Feature",
  "properties": {
    "gn:admin1_code":"10.0",
    "gn:admin2_code":"MC",
    "gn:admin3_code":"43048.0",
    "gn:asciiname":"L'Immacolata IV",
    "gn:country_code":"IT",
    "gn:dem":361,
    "gn:feature_class":"P",
    "gn:feature_code":"PPL",
    "gn:name":"L'Immacolata IV",
    "gn:population":27,
    "gn:timezone":"Europe/Rome",
    "iso:country":"IT",
    "wof:name":"L'Immacolata IV",
    "wof:placetype":"locality",
    "wof:population":27
},
  "geometry": {"coordinates":[13.38863,43.1162],"type":"Point"}
}