{
  "type": "Feature",
  "properties": {
    "gn:admin1_code":"8",
    "gn:admin2_code":"SV",
    "gn:admin3_code":"9067.0",
    "gn:asciiname":"Pian Lodola",
    "gn:country_code":"IT",
    "gn:dem":345,
    "gn:feature_class":"P",
    "gn:feature_code":"PPL",
    "gn:name":"Pian Lodola",
    "gn:population":14,
    "gn:timezone":"Europe/Rome",
    "iso:country":"IT",
    "wof:name":"Pian Lodola",
    "wof:placetype":"locality",
    "wof:population":14
},
  "geometry": {"coordinates":[8.36291,44.23372],"type":"Point"}
}