{
  "type": "Feature",
  "properties": {
    "gn:admin1_code":"9.0",
    "gn:admin2_code":"BG",
    "gn:admin3_code":"16035.0",
    "gn:asciiname":"Botta",
    "gn:country_code":"IT",
    "gn:dem":473,
    "gn:feature_class":"P",
    "gn:feature_code":"PPL",
    "gn:name":"Botta",
    "gn:population":26,
    "gn:timezone":"Europe/Rome",
    "iso:country":"IT",
    "wof:name":"Botta",
    "wof:placetype":"locality",
    "wof:population":26
},
  "geometry": {"coordinates":[9.68938,45.81104000000001],"type":"Point"}
}