{
  "type": "Feature",
  "properties": {
    "gn:admin1_code":"8",
    "gn:admin2_code":"GE",
    "gn:admin3_code":"10002.0",
    "gn:asciiname":"Arbora",
    "gn:country_code":"IT",
    "gn:dem":150,
    "gn:feature_class":"P",
    "gn:feature_code":"PPL",
    "gn:name":"Arbora",
    "gn:population":132,
    "gn:timezone":"Europe/Rome",
    "iso:country":"IT",
    "wof:name":"Arbora",
    "wof:placetype":"locality",
    "wof:population":132
},
  "geometry": {"coordinates":[9.14841,44.38684],"type":"Point"}
}