{
  "type": "Feature",
  "properties": {
    "gn:admin1_code":"20.0",
    "gn:admin2_code":"BL",
    "gn:admin3_code":"25010.0",
    "gn:asciiname":"Chenet",
    "gn:country_code":"IT",
    "gn:dem":901,
    "gn:elevation":"917.0",
    "gn:feature_class":"P",
    "gn:feature_code":"PPL",
    "gn:name":"Chenet",
    "gn:population":55,
    "gn:timezone":"Europe/Rome",
    "iso:country":"IT",
    "wof:name":"Chenet",
    "wof:placetype":"locality",
    "wof:population":55
},
  "geometry": {"coordinates":[11.976,46.35694],"type":"Point"}
}