{
  "type": "Feature",
  "properties": {
    "gn:admin1_code":"3",
    "gn:admin2_code":"RC",
    "gn:admin3_code":"80096.0",
    "gn:asciiname":"Piale",
    "gn:country_code":"IT",
    "gn:dem":134,
    "gn:feature_class":"P",
    "gn:feature_code":"PPL",
    "gn:name":"Piale",
    "gn:population":318,
    "gn:timezone":"Europe/Rome",
    "iso:country":"IT",
    "wof:name":"Piale",
    "wof:placetype":"locality",
    "wof:population":318
},
  "geometry": {"coordinates":[15.64819,38.22542],"type":"Point"}
}