{
  "type": "Feature",
  "properties": {
    "gn:admin1_code":"20",
    "gn:admin2_code":"VI",
    "gn:admin3_code":"24100.0",
    "gn:asciiname":"Sant'Ulderico",
    "gn:country_code":"IT",
    "gn:dem":700,
    "gn:feature_class":"P",
    "gn:feature_code":"PPL",
    "gn:name":"Sant'Ulderico",
    "gn:population":116,
    "gn:timezone":"Europe/Rome",
    "iso:country":"IT",
    "wof:name":"Sant'Ulderico",
    "wof:placetype":"locality",
    "wof:population":116
},
  "geometry": {"coordinates":[11.34753,45.74895],"type":"Point"}
}