{
  "type": "Feature",
  "properties": {
    "gn:admin1_code":"7",
    "gn:admin2_code":"RM",
    "gn:admin3_code":"58041.0",
    "gn:asciiname":"Santa Croce-San Valentino-Casavina-Rufani",
    "gn:country_code":"IT",
    "gn:dem":232,
    "gn:feature_class":"P",
    "gn:feature_code":"PPL",
    "gn:name":"Santa Croce-San Valentino-Casavina-Rufani",
    "gn:population":220,
    "gn:timezone":"Europe/Rome",
    "iso:country":"IT",
    "wof:name":"Santa Croce-San Valentino-Casavina-Rufani",
    "wof:placetype":"locality",
    "wof:population":220
},
  "geometry": {"coordinates":[13.07253,41.68835],"type":"Point"}
}