{
  "type": "Feature",
  "properties": {
    "gn:admin1_code":"12",
    "gn:admin2_code":"TO",
    "gn:admin3_code":"1171.0",
    "gn:asciiname":"Cascina Mellano",
    "gn:country_code":"IT",
    "gn:dem":260,
    "gn:feature_class":"P",
    "gn:feature_code":"PPL",
    "gn:name":"Cascina Mellano",
    "gn:population":59,
    "gn:timezone":"Europe/Rome",
    "iso:country":"IT",
    "wof:name":"Cascina Mellano",
    "wof:placetype":"locality",
    "wof:population":59
},
  "geometry": {"coordinates":[7.56521,45.01279],"type":"Point"}
}