{
  "type": "Feature",
  "properties": {
    "gn:admin1_code":"20",
    "gn:admin2_code":"VI",
    "gn:admin3_code":"24042.0",
    "gn:asciiname":"Sisemol",
    "gn:country_code":"IT",
    "gn:dem":1218,
    "gn:feature_class":"P",
    "gn:feature_code":"PPL",
    "gn:name":"Sisemol",
    "gn:population":16,
    "gn:timezone":"Europe/Rome",
    "iso:country":"IT",
    "wof:name":"Sisemol",
    "wof:placetype":"locality",
    "wof:population":16
},
  "geometry": {"coordinates":[11.55701,45.87701],"type":"Point"}
}