{
  "type": "Feature",
  "properties": {
    "gn:admin1_code":"8.0",
    "gn:admin2_code":"GE",
    "gn:admin3_code":"10011.0",
    "gn:asciiname":"Verici Superiore",
    "gn:country_code":"IT",
    "gn:dem":234,
    "gn:feature_class":"P",
    "gn:feature_code":"PPL",
    "gn:name":"Verici Superiore",
    "gn:population":0,
    "gn:timezone":"Europe/Rome",
    "iso:country":"IT",
    "wof:name":"Verici Superiore",
    "wof:placetype":"locality"
},
  "geometry": {"coordinates":[9.4429,44.27911],"type":"Point"}
}