{
  "type": "Feature",
  "properties": {
    "gn:admin1_code":"5",
    "gn:admin2_code":"RA",
    "gn:admin3_code":"39010.0",
    "gn:asciiname":"Graziola",
    "gn:country_code":"IT",
    "gn:dem":48,
    "gn:feature_class":"P",
    "gn:feature_code":"PPL",
    "gn:name":"Graziola",
    "gn:population":83,
    "gn:timezone":"Europe/Rome",
    "iso:country":"IT",
    "wof:name":"Graziola",
    "wof:placetype":"locality",
    "wof:population":83
},
  "geometry": {"coordinates":[11.8963,44.25976],"type":"Point"}
}