{
  "type": "Feature",
  "properties": {
    "gn:admin1_code":"12",
    "gn:admin2_code":"CN",
    "gn:admin3_code":"4159.0",
    "gn:asciiname":"Cattini",
    "gn:country_code":"IT",
    "gn:dem":993,
    "gn:feature_class":"P",
    "gn:feature_code":"PPL",
    "gn:name":"Cattini",
    "gn:population":11,
    "gn:timezone":"Europe/Rome",
    "iso:country":"IT",
    "wof:name":"Cattini",
    "wof:placetype":"locality",
    "wof:population":11
},
  "geometry": {"coordinates":[7.90905,44.29263],"type":"Point"}
}