{
  "type": "Feature",
  "properties": {
    "gn:gn_country":"IT",
    "gn:gn_fcode":"PPL",
    "gn:gn_pop":0,
    "gn:population":902,
    "iso:country":"IT",
    "qs_pg:aaroncc":"IT",
    "qs_pg:gn_country":"IT",
    "qs_pg:gn_fcode":"PPL",
    "qs_pg:gn_pop":0,
    "qs_pg:name":"Variano",
    "qs_pg:name_adm0":"Italia",
    "qs_pg:name_adm1":"Friuli-Venezia Giulia",
    "qs_pg:photos_9r":0,
    "qs_pg:photos_sr":0,
    "qs_pg:pop_sr":0,
    "qs_pg:qs_pg_placetype":"locality",
    "qs_pg:qs_pg_placetype_gp":"Town",
    "qs_pg:woe_adm0":23424853,
    "woe:adm0_id":23424853,
    "woe:name_adm0":"Italia",
    "woe:name_adm1":"Friuli-Venezia Giulia",
    "woe:placetype":"Town",
    "wof:name":"Variano",
    "wof:placetype":"locality",
    "wof:population":902
},
  "geometry": {"coordinates":[13.11861,46.0275],"type":"Point"}
}