{
  "type": "Feature",
  "properties": {
    "gn:admin1_code":"5",
    "gn:admin2_code":"FE",
    "gn:admin3_code":"38003.0",
    "gn:asciiname":"Zerbinate",
    "gn:country_code":"IT",
    "gn:dem":8,
    "gn:feature_class":"P",
    "gn:feature_code":"PPL",
    "gn:name":"Zerbinate",
    "gn:population":167,
    "gn:timezone":"Europe/Rome",
    "iso:country":"IT",
    "wof:name":"Zerbinate",
    "wof:placetype":"locality",
    "wof:population":167
},
  "geometry": {"coordinates":[11.37985,44.9521],"type":"Point"}
}