{
  "type": "Feature",
  "properties": {
    "gn:admin1_code":"15.0",
    "gn:admin2_code":"CL",
    "gn:admin3_code":"85010.0",
    "gn:asciiname":"Villaggio Grappa",
    "gn:country_code":"IT",
    "gn:dem":507,
    "gn:feature_class":"P",
    "gn:feature_code":"PPL",
    "gn:name":"Villaggio Grappa",
    "gn:population":25,
    "gn:timezone":"Europe/Rome",
    "iso:country":"IT",
    "wof:name":"Villaggio Grappa",
    "wof:placetype":"locality",
    "wof:population":25
},
  "geometry": {"coordinates":[13.7217,37.46591],"type":"Point"}
}