{
  "type": "Feature",
  "properties": {
    "gn:admin1_code":"3.0",
    "gn:admin2_code":"CS",
    "gn:admin3_code":"78119.0",
    "gn:asciiname":"Le Macchie",
    "gn:cc2":"IT",
    "gn:country_code":"IT",
    "gn:dem":1339,
    "gn:feature_class":"P",
    "gn:feature_code":"PPL",
    "gn:name":"Le Macchie",
    "gn:population":0,
    "gn:timezone":"Europe/Rome",
    "iso:country":"IT",
    "name:und_x_variant":[
        "Le M\u00e1cchie di Tancredi",
        "Le Macchie"
    ],
    "wof:name":"Le Macchie",
    "wof:placetype":"locality"
},
  "geometry": {"coordinates":[16.51667,39.25],"type":"Point"}
}