{
  "type": "Feature",
  "properties": {
    "gn:admin1_code":"12",
    "gn:admin2_code":"CN",
    "gn:admin3_code":"4186.0",
    "gn:asciiname":"Nasi",
    "gn:country_code":"IT",
    "gn:dem":886,
    "gn:feature_class":"P",
    "gn:feature_code":"PPLL",
    "gn:name":"Nasi",
    "gn:population":9,
    "gn:timezone":"Europe/Rome",
    "iso:country":"IT",
    "name:ceb_x_preferred":[
        "Nasi"
    ],
    "name:deu_x_preferred":[
        "Nasi"
    ],
    "name:fra_x_preferred":[
        "Nasi"
    ],
    "name:ita_x_preferred":[
        "Nasi"
    ],
    "name:lat_x_preferred":[
        "Nasi"
    ],
    "name:nld_x_preferred":[
        "Nasi"
    ],
    "name:rus_x_preferred":[
        "\u041d\u0430\u0441\u0438"
    ],
    "name:spa_x_preferred":[
        "Nasi"
    ],
    "name:swe_x_preferred":[
        "Nasi"
    ],
    "wof:name":"Nasi",
    "wof:placetype":"locality",
    "wof:population":9
},
  "geometry": {"coordinates":[7.89805,44.28866],"type":"Point"}
}