{
  "type": "Feature",
  "properties": {
    "gn:admin1_code":"12",
    "gn:admin2_code":"CN",
    "gn:admin3_code":"4203.0",
    "gn:asciiname":"San Lazzaro",
    "gn:country_code":"IT",
    "gn:dem":316,
    "gn:feature_class":"P",
    "gn:feature_code":"PPL",
    "gn:name":"San Lazzaro",
    "gn:population":67,
    "gn:timezone":"Europe/Rome",
    "iso:country":"IT",
    "wof:name":"San Lazzaro",
    "wof:placetype":"locality",
    "wof:population":67
},
  "geometry": {"coordinates":[7.46452,44.64275],"type":"Point"}
}