{
  "type": "Feature",
  "properties": {
    "gn:elevation":8,
    "gn:population":2391,
    "iso:country":"IT",
    "name:ita_x_preferred":[
        "Piangipane"
    ],
    "qs:a0":"Italia",
    "qs:a1":"*Ravenna",
    "qs:a1r":"0Emilia-Romagna",
    "qs:adm0":"Italia",
    "qs:la_lc":"*",
    "qs:level":"locality",
    "qs:loc":"Piangipane",
    "qs:loc_alt":"Piangipane",
    "qs:pop":0,
    "qs:type":"buffered point",
    "wof:lang":[
        "ita"
    ],
    "wof:name":"Piangipane",
    "wof:placetype":"locality",
    "wof:population":2391
},
  "geometry": {"coordinates":[12.08735,44.419689],"type":"Point"}
}