{
  "type": "Feature",
  "properties": {
    "gn:elevation":8,
    "gn:population":2391,
    "iso:country":"IT",
    "name:bul_x_preferred":[
        "\u041f\u0438\u0430\u043d\u0433\u0438\u043f\u0430\u043d\u0435"
    ],
    "name:cat_x_preferred":[
        "Piangipane"
    ],
    "name:ceb_x_preferred":[
        "Piangipane"
    ],
    "name:ces_x_preferred":[
        "Piangipane"
    ],
    "name:dan_x_preferred":[
        "Piangipane"
    ],
    "name:eng_x_preferred":[
        "Piangipane"
    ],
    "name:eus_x_preferred":[
        "Piangipane"
    ],
    "name:fin_x_preferred":[
        "Piangipane"
    ],
    "name:fra_x_preferred":[
        "Piangipane"
    ],
    "name:ind_x_preferred":[
        "Piangipane"
    ],
    "name:ita_x_preferred":[
        "Piangipane"
    ],
    "name:nld_x_preferred":[
        "Piangipane"
    ],
    "name:nno_x_preferred":[
        "Piangipane"
    ],
    "name:nob_x_preferred":[
        "Piangipane"
    ],
    "name:oci_x_preferred":[
        "Piangipane"
    ],
    "name:pol_x_preferred":[
        "Piangipane"
    ],
    "name:por_x_preferred":[
        "Piangipane"
    ],
    "name:ron_x_preferred":[
        "Piangipane"
    ],
    "name:slk_x_preferred":[
        "Piangipane"
    ],
    "name:slv_x_preferred":[
        "Piangipane"
    ],
    "name:spa_x_preferred":[
        "Piangipane"
    ],
    "name:srp_x_preferred":[
        "Piangipane"
    ],
    "name:swe_x_preferred":[
        "Piangipane"
    ],
    "name:tgl_x_preferred":[
        "Piangipane"
    ],
    "name:tur_x_preferred":[
        "Piangipane"
    ],
    "name:war_x_preferred":[
        "Piangipane"
    ],
    "qs:a0":"Italia",
    "qs:a1":"*Ravenna",
    "qs:a1r":"0Emilia-Romagna",
    "qs:adm0":"Italia",
    "qs:la_lc":"*",
    "qs:level":"locality",
    "qs:loc":"Piangipane",
    "qs:loc_alt":"Piangipane",
    "qs:pop":0,
    "qs:type":"buffered point",
    "wof:lang":[
        "ita"
    ],
    "wof:name":"Piangipane",
    "wof:placetype":"locality",
    "wof:population":2391
},
  "geometry": {"coordinates":[12.08735,44.419689],"type":"Point"}
}