{
  "type": "Feature",
  "properties": {
    "gn:admin1_code":"17",
    "gn:admin2_code":"TN",
    "gn:admin3_code":"22090.0",
    "gn:asciiname":"Laneri",
    "gn:country_code":"IT",
    "gn:dem":818,
    "gn:feature_class":"P",
    "gn:feature_code":"PPL",
    "gn:name":"Laneri",
    "gn:population":22,
    "gn:timezone":"Europe/Rome",
    "iso:country":"IT",
    "wof:name":"Laneri",
    "wof:placetype":"locality",
    "wof:population":22
},
  "geometry": {"coordinates":[11.29091,46.08371],"type":"Point"}
}