{
  "type": "Feature",
  "properties": {
    "gn:admin1_code":"5",
    "gn:admin2_code":"RE",
    "gn:admin3_code":"35011.0",
    "gn:asciiname":"Iatica",
    "gn:country_code":"IT",
    "gn:dem":497,
    "gn:feature_class":"P",
    "gn:feature_code":"PPL",
    "gn:name":"Iatica",
    "gn:population":20,
    "gn:timezone":"Europe/Rome",
    "iso:country":"IT",
    "wof:name":"Iatica",
    "wof:placetype":"locality",
    "wof:population":20
},
  "geometry": {"coordinates":[10.48524,44.41492],"type":"Point"}
}