{
  "type": "Feature",
  "properties": {
    "gn:admin1_code":"12",
    "gn:admin2_code":"TO",
    "gn:admin3_code":"1305.0",
    "gn:asciiname":"Borgata Grambosco",
    "gn:country_code":"IT",
    "gn:dem":486,
    "gn:feature_class":"P",
    "gn:feature_code":"PPL",
    "gn:name":"Borgata Grambosco",
    "gn:population":13,
    "gn:timezone":"Europe/Rome",
    "iso:country":"IT",
    "wof:name":"Borgata Grambosco",
    "wof:placetype":"locality",
    "wof:population":13
},
  "geometry": {"coordinates":[7.24036,45.10284],"type":"Point"}
}