{
  "type": "Feature",
  "properties": {
    "gn:admin1_code":"4",
    "gn:admin2_code":"CE",
    "gn:admin3_code":"61009.0",
    "gn:asciiname":"Papari O Liporti",
    "gn:country_code":"IT",
    "gn:dem":186,
    "gn:feature_class":"P",
    "gn:feature_code":"PPL",
    "gn:name":"Papari O Liporti",
    "gn:population":223,
    "gn:timezone":"Europe/Rome",
    "iso:country":"IT",
    "wof:name":"Papari O Liporti",
    "wof:placetype":"locality",
    "wof:population":223
},
  "geometry": {"coordinates":[14.36949,41.18772],"type":"Point"}
}