{
  "type": "Feature",
  "properties": {
    "gn:admin1_code":"16.0",
    "gn:admin2_code":"PT",
    "gn:admin3_code":"47017.0",
    "gn:asciiname":"Montemagno",
    "gn:country_code":"IT",
    "gn:dem":171,
    "gn:elevation":"164.0",
    "gn:feature_class":"P",
    "gn:feature_code":"PPL",
    "gn:name":"Montemagno",
    "gn:population":211,
    "gn:timezone":"Europe/Rome",
    "iso:country":"IT",
    "wof:name":"Montemagno",
    "wof:placetype":"locality",
    "wof:population":211
},
  "geometry": {"coordinates":[10.93949,43.84646],"type":"Point"}
}