{
  "type": "Feature",
  "properties": {
    "gn:admin1_code":"20",
    "gn:admin2_code":"VE",
    "gn:admin3_code":"27023.0",
    "gn:asciiname":"Soresina",
    "gn:country_code":"IT",
    "gn:dem":0,
    "gn:feature_class":"P",
    "gn:feature_code":"PPL",
    "gn:name":"Soresina",
    "gn:population":39,
    "gn:timezone":"Europe/Rome",
    "iso:country":"IT",
    "wof:name":"Soresina",
    "wof:placetype":"locality",
    "wof:population":39
},
  "geometry": {"coordinates":[12.1816,45.42647],"type":"Point"}
}