{
  "type": "Feature",
  "properties": {
    "gn:admin1_code":"20",
    "gn:admin2_code":"VE",
    "gn:admin3_code":"27023.0",
    "gn:asciiname":"Soresina",
    "gn:country_code":"IT",
    "gn:dem":0,
    "gn:feature_class":"P",
    "gn:feature_code":"PPL",
    "gn:name":"Soresina",
    "gn:population":39,
    "gn:timezone":"Europe/Rome",
    "iso:country":"IT",
    "name:bul_x_preferred":[
        "\u0421\u043e\u0440\u0435\u0437\u0438\u043d\u0430"
    ],
    "name:ceb_x_preferred":[
        "Soresina"
    ],
    "name:deu_x_preferred":[
        "Soresina"
    ],
    "name:epo_x_preferred":[
        "Soresina"
    ],
    "name:eus_x_preferred":[
        "Soresina"
    ],
    "name:fra_x_preferred":[
        "Soresina"
    ],
    "name:hun_x_preferred":[
        "Soresina"
    ],
    "name:hye_x_preferred":[
        "\u054d\u0578\u0580\u0565\u0566\u056b\u0576\u0561"
    ],
    "name:ita_x_preferred":[
        "Soresina"
    ],
    "name:jpn_x_preferred":[
        "\u30bd\u30ec\u30b8\u30fc\u30ca"
    ],
    "name:kaz_x_preferred":[
        "\u0421\u043e\u0440\u0435\u0437\u0438\u043d\u0430"
    ],
    "name:lat_x_preferred":[
        "Sorecina"
    ],
    "name:lmo_x_preferred":[
        "Suresina"
    ],
    "name:msa_x_preferred":[
        "Soresina"
    ],
    "name:nap_x_preferred":[
        "Soresina"
    ],
    "name:nld_x_preferred":[
        "Soresina"
    ],
    "name:pms_x_preferred":[
        "Soresina"
    ],
    "name:pol_x_preferred":[
        "Soresina"
    ],
    "name:por_x_preferred":[
        "Soresina"
    ],
    "name:ron_x_preferred":[
        "Soresina"
    ],
    "name:rus_x_preferred":[
        "\u0421\u043e\u0440\u0435\u0437\u0438\u043d\u0430"
    ],
    "name:scn_x_preferred":[
        "Soresina"
    ],
    "name:spa_x_preferred":[
        "Soresina"
    ],
    "name:srp_x_preferred":[
        "\u0421\u043e\u0440\u0435\u0437\u0438\u043d\u0430"
    ],
    "name:tur_x_preferred":[
        "Soresina"
    ],
    "name:twi_x_preferred":[
        "Soresina"
    ],
    "name:ukr_x_preferred":[
        "\u0421\u043e\u0440\u0435\u0437\u0456\u043d\u0430"
    ],
    "name:uzb_x_preferred":[
        "Soresina"
    ],
    "name:vie_x_preferred":[
        "Soresina"
    ],
    "name:vol_x_preferred":[
        "Soresina"
    ],
    "name:war_x_preferred":[
        "Soresina"
    ],
    "name:zho_x_preferred":[
        "\u7d22\u96f7\u897f\u7eb3"
    ],
    "wof:name":"Soresina",
    "wof:placetype":"locality",
    "wof:population":39
},
  "geometry": {"coordinates":[12.1816,45.42647],"type":"Point"}
}