{
  "type": "Feature",
  "properties": {
    "gn:admin1_code":"2",
    "gn:admin2_code":"PZ",
    "gn:admin3_code":"76040.0",
    "gn:asciiname":"Cerri",
    "gn:country_code":"IT",
    "gn:dem":708,
    "gn:feature_class":"P",
    "gn:feature_code":"PPL",
    "gn:name":"Cerri",
    "gn:population":82,
    "gn:timezone":"Europe/Rome",
    "iso:country":"IT",
    "wof:name":"Cerri",
    "wof:placetype":"locality",
    "wof:population":82
},
  "geometry": {"coordinates":[15.98022,40.07087],"type":"Point"}
}