{
  "type": "Feature",
  "properties": {
    "gn:admin1_code":"6.0",
    "gn:admin2_code":"PN",
    "gn:admin3_code":"93021.0",
    "gn:asciiname":"Via Malignan",
    "gn:country_code":"IT",
    "gn:dem":15,
    "gn:feature_class":"P",
    "gn:feature_code":"PPLL",
    "gn:name":"Via Malignan",
    "gn:population":0,
    "gn:timezone":"Europe/Rome",
    "iso:country":"IT",
    "wof:name":"Via Malignan",
    "wof:placetype":"locality"
},
  "geometry": {"coordinates":[12.72847,45.90033],"type":"Point"}
}