{
  "type": "Feature",
  "properties": {
    "gn:admin1_code":"16",
    "gn:admin2_code":"AR",
    "gn:admin3_code":"51004.0",
    "gn:asciiname":"Freggina",
    "gn:country_code":"IT",
    "gn:dem":615,
    "gn:feature_class":"P",
    "gn:feature_code":"PPL",
    "gn:name":"Freggina",
    "gn:population":38,
    "gn:timezone":"Europe/Rome",
    "iso:country":"IT",
    "wof:name":"Freggina",
    "wof:placetype":"locality",
    "wof:population":38
},
  "geometry": {"coordinates":[11.82025,43.75949],"type":"Point"}
}