{
  "type": "Feature",
  "properties": {
    "gn:admin1_code":"9.0",
    "gn:admin2_code":"CO",
    "gn:admin3_code":"13215.0",
    "gn:asciiname":"Concagno",
    "gn:country_code":"IT",
    "gn:dem":396,
    "gn:feature_class":"P",
    "gn:feature_code":"PPL",
    "gn:name":"Concagno",
    "gn:population":718,
    "gn:timezone":"Europe/Rome",
    "iso:country":"IT",
    "wof:name":"Concagno",
    "wof:placetype":"locality",
    "wof:population":718
},
  "geometry": {"coordinates":[8.90956,45.79914],"type":"Point"}
}