{
  "type": "Feature",
  "properties": {
    "gn:admin1_code":"20.0",
    "gn:admin2_code":"RO",
    "gn:admin3_code":"29039.0",
    "gn:asciiname":"Ca' Venier",
    "gn:cc2":"IT",
    "gn:country_code":"IT",
    "gn:dem":-1,
    "gn:feature_class":"P",
    "gn:feature_code":"PPL",
    "gn:name":"Ca' Venier",
    "gn:population":218,
    "gn:timezone":"Europe/Rome",
    "iso:country":"IT",
    "name:und_x_variant":[
        "Case Venier",
        "Ca Venier"
    ],
    "wof:name":"Ca' Venier",
    "wof:placetype":"locality",
    "wof:population":218
},
  "geometry": {"coordinates":[12.33528,44.95889],"type":"Point"}
}