{
  "type": "Feature",
  "properties": {
    "gn:admin1_code":"20",
    "gn:admin2_code":"VE",
    "gn:admin3_code":"27027.0",
    "gn:asciiname":"Ca Zorzi",
    "gn:country_code":"IT",
    "gn:dem":6,
    "gn:feature_class":"P",
    "gn:feature_code":"PPL",
    "gn:name":"C\u00e0 Zorzi",
    "gn:population":318,
    "gn:timezone":"Europe/Rome",
    "iso:country":"IT",
    "name:und_x_variant":[
        "C\u00e0 Zorzi"
    ],
    "wof:name":"Ca Zorzi",
    "wof:placetype":"locality",
    "wof:population":318
},
  "geometry": {"coordinates":[12.51335,45.66984],"type":"Point"}
}