{
  "type": "Feature",
  "properties": {
    "gn:admin1_code":"7.0",
    "gn:admin2_code":"FR",
    "gn:admin3_code":"60063.0",
    "gn:asciiname":"Torricelli Inferiore",
    "gn:country_code":"IT",
    "gn:dem":70,
    "gn:feature_class":"P",
    "gn:feature_code":"PPL",
    "gn:name":"Torricelli Inferiore",
    "gn:population":35,
    "gn:timezone":"Europe/Rome",
    "iso:country":"IT",
    "wof:name":"Torricelli Inferiore",
    "wof:placetype":"locality",
    "wof:population":35
},
  "geometry": {"coordinates":[13.73369,41.39975],"type":"Point"}
}