{
  "type": "Feature",
  "properties": {
    "gn:admin1_code":"16",
    "gn:admin2_code":"AR",
    "gn:admin3_code":"51017.0",
    "gn:asciiname":"Macchia della Madonna I",
    "gn:country_code":"IT",
    "gn:dem":279,
    "gn:feature_class":"P",
    "gn:feature_code":"PPL",
    "gn:name":"Macchia della Madonna I",
    "gn:population":81,
    "gn:timezone":"Europe/Rome",
    "iso:country":"IT",
    "wof:name":"Macchia della Madonna I",
    "wof:placetype":"locality",
    "wof:population":81
},
  "geometry": {"coordinates":[11.95001,43.22228],"type":"Point"}
}