{
  "type": "Feature",
  "properties": {
    "gn:admin1_code":"5.0",
    "gn:admin2_code":"PC",
    "gn:admin3_code":"33024.0",
    "gn:asciiname":"Campremoldo Sotto",
    "gn:country_code":"IT",
    "gn:dem":75,
    "gn:feature_class":"P",
    "gn:feature_code":"PPL",
    "gn:name":"Campremoldo Sotto",
    "gn:population":108,
    "gn:timezone":"Europe/Rome",
    "iso:country":"IT",
    "wof:name":"Campremoldo Sotto",
    "wof:placetype":"locality",
    "wof:population":108
},
  "geometry": {"coordinates":[9.5502,45.02618],"type":"Point"}
}