{
  "type": "Feature",
  "properties": {
    "iso:country":"IT",
    "name:fra_x_preferred":[
        "Alessia"
    ],
    "name:glg_x_preferred":[
        "Alexia"
    ],
    "name:ita_x_preferred":[
        "Alessia"
    ],
    "name:lat_x_preferred":[
        "Alessia"
    ],
    "name:lmo_x_preferred":[
        "Alessia"
    ],
    "name:slv_x_preferred":[
        "Aleksija"
    ],
    "name:srp_x_preferred":[
        "\u0410\u043b\u0435\u043a\u0441\u0438\u0458\u0430"
    ],
    "name:swe_x_preferred":[
        "Alessia"
    ],
    "qs_pg:aaroncc":"IT",
    "qs_pg:name":"Alessia",
    "qs_pg:name_adm0":"Italia",
    "qs_pg:name_adm1":"Campania",
    "qs_pg:photos":72,
    "qs_pg:photos_1k":15,
    "qs_pg:photos_9k":1,
    "qs_pg:photos_9r":2,
    "qs_pg:photos_all":72,
    "qs_pg:photos_sr":2,
    "qs_pg:pop_sr":0,
    "qs_pg:qs_pg_placetype":"locality",
    "qs_pg:qs_pg_placetype_gp":"Town",
    "qs_pg:woe_adm0":23424853,
    "woe:adm0_id":23424853,
    "woe:name_adm0":"Italia",
    "woe:name_adm1":"Campania",
    "woe:placetype":"Town",
    "wof:name":"Alessia",
    "wof:placetype":"locality"
},
  "geometry": {"coordinates":[14.742708,40.682981],"type":"Point"}
}