{
  "type": "Feature",
  "properties": {
    "gn:admin1_code":"20.0",
    "gn:admin2_code":"BL",
    "gn:admin3_code":"25011.0",
    "gn:asciiname":"Soranzen",
    "gn:country_code":"IT",
    "gn:dem":420,
    "gn:feature_class":"P",
    "gn:feature_code":"PPL",
    "gn:name":"Soranzen",
    "gn:population":350,
    "gn:timezone":"Europe/Rome",
    "iso:country":"IT",
    "wof:name":"Soranzen",
    "wof:placetype":"locality",
    "wof:population":350
},
  "geometry": {"coordinates":[11.94928,46.07347],"type":"Point"}
}