{
  "type": "Feature",
  "properties": {
    "gn:country":"IT",
    "gn:fcode":"PPL",
    "gn:population":0,
    "iso:country":"IT",
    "name:ceb_x_preferred":[
        "Ghizzano"
    ],
    "name:fas_x_preferred":[
        "\u062c\u06cc\u0632\u0627\u0646\u0648"
    ],
    "name:ita_x_preferred":[
        "Ghizzano"
    ],
    "name:srp_x_preferred":[
        "\u0413\u0438\u0446\u0430\u043d\u043e"
    ],
    "qs_pg:aaroncc":"IT",
    "qs_pg:gn_country":"IT",
    "qs_pg:gn_fcode":"PPL",
    "qs_pg:gn_pop":0,
    "qs_pg:name":"Ghizzano",
    "qs_pg:name_adm0":"Italia",
    "qs_pg:name_adm1":"Toscana",
    "qs_pg:photos":48,
    "qs_pg:photos_1k":10,
    "qs_pg:photos_9k":1,
    "qs_pg:photos_9r":2,
    "qs_pg:photos_all":48,
    "qs_pg:photos_sr":2,
    "qs_pg:pop_sr":0,
    "qs_pg:qs_pg_placetype":"locality",
    "qs_pg:qs_pg_placetype_gp":"Town",
    "qs_pg:woe_adm0":23424853,
    "woe:adm0_id":23424853,
    "woe:name_adm0":"Italia",
    "woe:name_adm1":"Toscana",
    "woe:placetype":"Town",
    "wof:name":"Ghizzano",
    "wof:placetype":"locality",
    "wof:population":349
},
  "geometry": {"coordinates":[10.78333,43.53333],"type":"Point"}
}