{
  "type": "Feature",
  "properties": {
    "gn:admin1_code":"7.0",
    "gn:admin2_code":"RM",
    "gn:admin3_code":"58117.0",
    "gn:asciiname":"Pian di Frasso I",
    "gn:country_code":"IT",
    "gn:dem":49,
    "gn:feature_class":"P",
    "gn:feature_code":"PPL",
    "gn:name":"Pian di Frasso I",
    "gn:population":51,
    "gn:timezone":"Europe/Rome",
    "iso:country":"IT",
    "wof:name":"Pian di Frasso I",
    "wof:placetype":"locality",
    "wof:population":51
},
  "geometry": {"coordinates":[12.54834,41.62923],"type":"Point"}
}