{
  "type": "Feature",
  "properties": {
    "gn:admin1_code":"9",
    "gn:admin2_code":"BG",
    "gn:admin3_code":"16219.0",
    "gn:asciiname":"Cascina Giuseppana",
    "gn:country_code":"IT",
    "gn:dem":140,
    "gn:feature_class":"P",
    "gn:feature_code":"PPL",
    "gn:name":"Cascina Giuseppana",
    "gn:population":59,
    "gn:timezone":"Europe/Rome",
    "iso:country":"IT",
    "wof:name":"Cascina Giuseppana",
    "wof:placetype":"locality",
    "wof:population":59
},
  "geometry": {"coordinates":[9.60474,45.55115],"type":"Point"}
}