{
  "type": "Feature",
  "properties": {
    "gn:admin1_code":"6.0",
    "gn:admin2_code":"UD",
    "gn:admin3_code":"30086.0",
    "gn:asciiname":"Mersino",
    "gn:country_code":"IT",
    "gn:dem":591,
    "gn:feature_class":"P",
    "gn:feature_code":"PPL",
    "gn:name":"Mersino",
    "gn:population":0,
    "gn:timezone":"Europe/Rome",
    "iso:country":"IT",
    "wof:name":"Mersino",
    "wof:placetype":"locality"
},
  "geometry": {"coordinates":[13.47992,46.19207],"type":"Point"}
}