{
  "type": "Feature",
  "properties": {
    "gn:admin1_code":"17",
    "gn:admin2_code":"TN",
    "gn:admin3_code":"22236.0",
    "gn:asciiname":"Tiecheri",
    "gn:country_code":"IT",
    "gn:dem":1027,
    "gn:feature_class":"P",
    "gn:feature_code":"PPLL",
    "gn:name":"Tiecheri",
    "gn:population":8,
    "gn:timezone":"Europe/Rome",
    "iso:country":"IT",
    "wof:name":"Tiecheri",
    "wof:placetype":"locality",
    "wof:population":8
},
  "geometry": {"coordinates":[11.22385,45.96726],"type":"Point"}
}