{
  "type": "Feature",
  "properties": {
    "gn:admin1_code":"12.0",
    "gn:admin2_code":"NO",
    "gn:admin3_code":"3106.0",
    "gn:asciiname":"Torrion Quartara",
    "gn:country_code":"IT",
    "gn:dem":148,
    "gn:feature_class":"P",
    "gn:feature_code":"PPL",
    "gn:name":"Torrion Quartara",
    "gn:population":1805,
    "gn:timezone":"Europe/Rome",
    "iso:country":"IT",
    "wof:name":"Torrion Quartara",
    "wof:placetype":"locality",
    "wof:population":1805
},
  "geometry": {"coordinates":[8.61472,45.41819],"type":"Point"}
}