{
  "type": "Feature",
  "properties": {
    "gn:admin1_code":"5",
    "gn:admin2_code":"PC",
    "gn:admin3_code":"33016.0",
    "gn:asciiname":"Aglio",
    "gn:country_code":"IT",
    "gn:dem":608,
    "gn:feature_class":"P",
    "gn:feature_code":"PPL",
    "gn:name":"Aglio",
    "gn:population":23,
    "gn:timezone":"Europe/Rome",
    "iso:country":"IT",
    "wof:name":"Aglio",
    "wof:placetype":"locality",
    "wof:population":23
},
  "geometry": {"coordinates":[9.49766,44.75008],"type":"Point"}
}