{
  "type": "Feature",
  "properties": {
    "gn:admin1_code":"5",
    "gn:admin2_code":"PC",
    "gn:admin3_code":"33030.0",
    "gn:asciiname":"Scravaggione-Busceto",
    "gn:country_code":"IT",
    "gn:dem":997,
    "gn:feature_class":"P",
    "gn:feature_code":"PPLL",
    "gn:name":"Scravaggione-Busceto",
    "gn:population":9,
    "gn:timezone":"Europe/Rome",
    "iso:country":"IT",
    "wof:name":"Scravaggione-Busceto",
    "wof:placetype":"locality",
    "wof:population":9
},
  "geometry": {"coordinates":[9.39109,44.59991],"type":"Point"}
}