{
  "type": "Feature",
  "properties": {
    "gn:admin1_code":"12",
    "gn:admin2_code":"TO",
    "gn:admin3_code":"1066.0",
    "gn:asciiname":"Case Vivario",
    "gn:country_code":"IT",
    "gn:dem":359,
    "gn:feature_class":"P",
    "gn:feature_code":"PPL",
    "gn:name":"Case Vivario",
    "gn:population":56,
    "gn:timezone":"Europe/Rome",
    "iso:country":"IT",
    "wof:name":"Case Vivario",
    "wof:placetype":"locality",
    "wof:population":56
},
  "geometry": {"coordinates":[7.72586,45.40366],"type":"Point"}
}