{
  "type": "Feature",
  "properties": {
    "gn:admin1_code":"5.0",
    "gn:admin2_code":"PR",
    "gn:admin3_code":"34042.0",
    "gn:asciiname":"Guardasone",
    "gn:country_code":"IT",
    "gn:dem":306,
    "gn:feature_class":"P",
    "gn:feature_code":"PPLL",
    "gn:name":"Guardasone",
    "gn:population":0,
    "gn:timezone":"Europe/Rome",
    "iso:country":"IT",
    "wof:name":"Guardasone",
    "wof:placetype":"locality"
},
  "geometry": {"coordinates":[10.39607,44.6267],"type":"Point"}
}