{
  "type": "Feature",
  "properties": {
    "gn:admin1_code":"15",
    "gn:admin2_code":"CT",
    "gn:admin3_code":"87053.0",
    "gn:asciiname":"Paternostro",
    "gn:country_code":"IT",
    "gn:dem":383,
    "gn:feature_class":"P",
    "gn:feature_code":"PPL",
    "gn:name":"Paternostro",
    "gn:population":80,
    "gn:timezone":"Europe/Rome",
    "iso:country":"IT",
    "wof:name":"Paternostro",
    "wof:placetype":"locality",
    "wof:population":80
},
  "geometry": {"coordinates":[15.09283,37.59817],"type":"Point"}
}