{
  "type": "Feature",
  "properties": {
    "gn:admin1_code":"12",
    "gn:admin2_code":"CN",
    "gn:admin3_code":"4192.0",
    "gn:asciiname":"Tetto Cherro",
    "gn:country_code":"IT",
    "gn:dem":704,
    "gn:feature_class":"P",
    "gn:feature_code":"PPL",
    "gn:name":"Tetto Cherro",
    "gn:population":29,
    "gn:timezone":"Europe/Rome",
    "iso:country":"IT",
    "wof:name":"Tetto Cherro",
    "wof:placetype":"locality",
    "wof:population":29
},
  "geometry": {"coordinates":[7.46559,44.30045],"type":"Point"}
}