{
  "type": "Feature",
  "properties": {
    "gn:admin1_code":"9",
    "gn:admin2_code":"BS",
    "gn:admin3_code":"17034.0",
    "gn:asciiname":"Case Zanoni",
    "gn:country_code":"IT",
    "gn:dem":78,
    "gn:feature_class":"P",
    "gn:feature_code":"PPL",
    "gn:name":"Case Zanoni",
    "gn:population":46,
    "gn:timezone":"Europe/Rome",
    "iso:country":"IT",
    "wof:name":"Case Zanoni",
    "wof:placetype":"locality",
    "wof:population":46
},
  "geometry": {"coordinates":[10.34764,45.37476],"type":"Point"}
}