{
  "type": "Feature",
  "properties": {
    "gn:admin1_code":"20.0",
    "gn:admin2_code":"BL",
    "gn:admin3_code":"25071.0",
    "gn:asciiname":"Casere Grisol",
    "gn:cc2":"IT",
    "gn:country_code":"IT",
    "gn:dem":778,
    "gn:feature_class":"P",
    "gn:feature_code":"PPL",
    "gn:name":"Casere Grisol",
    "gn:population":0,
    "gn:timezone":"Europe/Rome",
    "iso:country":"IT",
    "name:und_x_variant":[
        "Grisol",
        "Casere Grisol"
    ],
    "wof:name":"Casere Grisol",
    "wof:placetype":"locality"
},
  "geometry": {"coordinates":[12.23333,46.26667],"type":"Point"}
}