{
  "type": "Feature",
  "properties": {
    "gn:admin1_code":"20",
    "gn:admin2_code":"PD",
    "gn:admin3_code":"28052.0",
    "gn:asciiname":"Taschin",
    "gn:country_code":"IT",
    "gn:dem":8,
    "gn:feature_class":"P",
    "gn:feature_code":"PPLL",
    "gn:name":"Taschin",
    "gn:population":10,
    "gn:timezone":"Europe/Rome",
    "iso:country":"IT",
    "wof:name":"Taschin",
    "wof:placetype":"locality",
    "wof:population":10
},
  "geometry": {"coordinates":[11.53418,45.17989],"type":"Point"}
}