{
  "type": "Feature",
  "properties": {
    "gn:admin1_code":"9",
    "gn:admin2_code":"PV",
    "gn:admin3_code":"18005.0",
    "gn:asciiname":"Ca' dei Ratti",
    "gn:country_code":"IT",
    "gn:dem":90,
    "gn:feature_class":"P",
    "gn:feature_code":"PPL",
    "gn:name":"Ca' dei Ratti",
    "gn:population":12,
    "gn:timezone":"Europe/Rome",
    "iso:country":"IT",
    "wof:name":"Ca' dei Ratti",
    "wof:placetype":"locality",
    "wof:population":12
},
  "geometry": {"coordinates":[9.35102,45.07732],"type":"Point"}
}