{
  "type": "Feature",
  "properties": {
    "gn:admin1_code":"5.0",
    "gn:admin2_code":"FE",
    "gn:admin3_code":"38003.0",
    "gn:asciiname":"Arginelli",
    "gn:country_code":"IT",
    "gn:dem":9,
    "gn:feature_class":"P",
    "gn:feature_code":"PPL",
    "gn:name":"Arginelli",
    "gn:population":33,
    "gn:timezone":"Europe/Rome",
    "iso:country":"IT",
    "wof:name":"Arginelli",
    "wof:placetype":"locality",
    "wof:population":33
},
  "geometry": {"coordinates":[11.40829,44.92707],"type":"Point"}
}