{
  "type": "Feature",
  "properties": {
    "gn:admin1_code":"5",
    "gn:admin2_code":"PC",
    "gn:admin3_code":"33035.0",
    "gn:asciiname":"Verano",
    "gn:country_code":"IT",
    "gn:dem":120,
    "gn:feature_class":"P",
    "gn:feature_code":"PPL",
    "gn:name":"Verano",
    "gn:population":68,
    "gn:timezone":"Europe/Rome",
    "iso:country":"IT",
    "name:ceb_x_preferred":[
        "Verano"
    ],
    "name:deu_x_preferred":[
        "Verano"
    ],
    "name:fin_x_preferred":[
        "Verano"
    ],
    "name:ita_x_preferred":[
        "Verano"
    ],
    "name:lat_x_preferred":[
        "Veranum"
    ],
    "name:por_x_preferred":[
        "Verano"
    ],
    "name:spa_x_preferred":[
        "Verano"
    ],
    "name:srp_x_preferred":[
        "Verano"
    ],
    "name:swe_x_preferred":[
        "Verano"
    ],
    "wof:name":"Verano",
    "wof:placetype":"locality",
    "wof:population":68
},
  "geometry": {"coordinates":[9.66123,44.95336],"type":"Point"}
}