{
  "type": "Feature",
  "properties": {
    "iso:country":"IT",
    "wof:name":"Barriere di Chieri",
    "wof:placetype":"neighbourhood"
},
  "geometry": {"coordinates":[7.72887455802085,45.07170273766909],"type":"Point"}
}