{
  "type": "Feature",
  "properties": {
    "gn:admin1_code":"16.0",
    "gn:admin2_code":"FI",
    "gn:admin3_code":"48037.0",
    "gn:asciiname":"Scopeti",
    "gn:country_code":"IT",
    "gn:dem":144,
    "gn:feature_class":"P",
    "gn:feature_code":"PPL",
    "gn:name":"Scopeti",
    "gn:population":484,
    "gn:timezone":"Europe/Rome",
    "iso:country":"IT",
    "wof:name":"Scopeti",
    "wof:placetype":"locality",
    "wof:population":484
},
  "geometry": {"coordinates":[11.49974,43.84367],"type":"Point"}
}