{
  "type": "Feature",
  "properties": {
    "gn:admin1_code":"12",
    "gn:admin2_code":"TO",
    "gn:admin3_code":"1158.0",
    "gn:asciiname":"Tetti Gaffolo",
    "gn:country_code":"IT",
    "gn:dem":382,
    "gn:feature_class":"P",
    "gn:feature_code":"PPL",
    "gn:name":"Tetti Gaffolo",
    "gn:population":47,
    "gn:timezone":"Europe/Rome",
    "iso:country":"IT",
    "wof:name":"Tetti Gaffolo",
    "wof:placetype":"locality",
    "wof:population":47
},
  "geometry": {"coordinates":[7.85368,45.07327],"type":"Point"}
}