{
  "type": "Feature",
  "properties": {
    "gn:admin1_code":"4",
    "gn:admin2_code":"CE",
    "gn:admin3_code":"61072.0",
    "gn:asciiname":"Montanari",
    "gn:country_code":"IT",
    "gn:dem":119,
    "gn:feature_class":"P",
    "gn:feature_code":"PPL",
    "gn:name":"Montanari",
    "gn:population":147,
    "gn:timezone":"Europe/Rome",
    "iso:country":"IT",
    "wof:name":"Montanari",
    "wof:placetype":"locality",
    "wof:population":147
},
  "geometry": {"coordinates":[14.12318,41.24258],"type":"Point"}
}