{
  "type": "Feature",
  "properties": {
    "gn:admin1_code":"16",
    "gn:admin2_code":"LI",
    "gn:admin3_code":"49008.0",
    "gn:asciiname":"Pietreto",
    "gn:country_code":"IT",
    "gn:dem":126,
    "gn:feature_class":"P",
    "gn:feature_code":"PPL",
    "gn:name":"Pietreto",
    "gn:population":177,
    "gn:timezone":"Europe/Rome",
    "iso:country":"IT",
    "wof:name":"Pietreto",
    "wof:placetype":"locality",
    "wof:population":177
},
  "geometry": {"coordinates":[10.43838,43.54205],"type":"Point"}
}