{
  "type": "Feature",
  "properties": {
    "gn:admin1_code":"12",
    "gn:admin2_code":"CN",
    "gn:admin3_code":"4214.0",
    "gn:asciiname":"Gorrini",
    "gn:country_code":"IT",
    "gn:dem":256,
    "gn:feature_class":"P",
    "gn:feature_code":"PPL",
    "gn:name":"Gorrini",
    "gn:population":41,
    "gn:timezone":"Europe/Rome",
    "iso:country":"IT",
    "name:ita_x_preferred":[
        "Gorrini"
    ],
    "wof:name":"Gorrini",
    "wof:placetype":"locality",
    "wof:population":41
},
  "geometry": {"coordinates":[7.97088,44.7839],"type":"Point"}
}