{
  "type": "Feature",
  "properties": {
    "gn:admin1_code":"6",
    "gn:admin2_code":"GO",
    "gn:admin3_code":"31004.0",
    "gn:asciiname":"Restocina",
    "gn:country_code":"IT",
    "gn:dem":209,
    "gn:feature_class":"P",
    "gn:feature_code":"PPL",
    "gn:name":"Restocina",
    "gn:population":18,
    "gn:timezone":"Europe/Rome",
    "iso:country":"IT",
    "wof:name":"Restocina",
    "wof:placetype":"locality",
    "wof:population":18
},
  "geometry": {"coordinates":[13.50093,46.04254],"type":"Point"}
}