{
  "type": "Feature",
  "properties": {
    "gn:admin1_code":"4",
    "gn:admin2_code":"AV",
    "gn:admin3_code":"64044.0",
    "gn:asciiname":"Lago",
    "gn:country_code":"IT",
    "gn:dem":569,
    "gn:feature_class":"P",
    "gn:feature_code":"PPL",
    "gn:name":"Lago",
    "gn:population":28,
    "gn:timezone":"Europe/Rome",
    "iso:country":"IT",
    "name:ceb_x_preferred":[
        "Lago"
    ],
    "name:deu_x_preferred":[
        "Lago"
    ],
    "name:fra_x_preferred":[
        "Lago"
    ],
    "name:glg_x_preferred":[
        "Lago"
    ],
    "name:ita_x_preferred":[
        "Lago"
    ],
    "name:nld_x_preferred":[
        "Lago"
    ],
    "name:pap_x_preferred":[
        "Lago"
    ],
    "name:por_x_preferred":[
        "Lago"
    ],
    "name:rus_x_preferred":[
        "\u041b\u0430\u0433\u043e"
    ],
    "name:sco_x_preferred":[
        "Lago"
    ],
    "name:spa_x_preferred":[
        "Lago"
    ],
    "name:srp_x_preferred":[
        "\u041b\u0430\u0433\u043e"
    ],
    "name:swe_x_preferred":[
        "Lago"
    ],
    "name:vol_x_preferred":[
        "Lago"
    ],
    "wof:name":"Lago",
    "wof:placetype":"locality",
    "wof:population":28
},
  "geometry": {"coordinates":[15.18316,40.86027],"type":"Point"}
}