{
  "type": "Feature",
  "properties": {
    "gn:admin1_code":"4",
    "gn:admin2_code":"AV",
    "gn:admin3_code":"64044.0",
    "gn:asciiname":"Lago",
    "gn:country_code":"IT",
    "gn:dem":569,
    "gn:feature_class":"P",
    "gn:feature_code":"PPL",
    "gn:name":"Lago",
    "gn:population":28,
    "gn:timezone":"Europe/Rome",
    "iso:country":"IT",
    "wof:name":"Lago",
    "wof:placetype":"locality",
    "wof:population":28
},
  "geometry": {"coordinates":[15.18316,40.86027],"type":"Point"}
}