{
  "type": "Feature",
  "properties": {
    "gn:admin1_code":"6",
    "gn:admin2_code":"PN",
    "gn:admin3_code":"93029.0",
    "gn:asciiname":"Case Marcon",
    "gn:country_code":"IT",
    "gn:dem":11,
    "gn:feature_class":"P",
    "gn:feature_code":"PPL",
    "gn:name":"Case Marcon",
    "gn:population":24,
    "gn:timezone":"Europe/Rome",
    "iso:country":"IT",
    "wof:name":"Case Marcon",
    "wof:placetype":"locality",
    "wof:population":24
},
  "geometry": {"coordinates":[12.61777,45.88529000000001],"type":"Point"}
}