{
  "type": "Feature",
  "properties": {
    "gn:admin1_code":"1",
    "gn:admin2_code":"PE",
    "gn:admin3_code":"68026.0",
    "gn:asciiname":"Zubbitilli",
    "gn:country_code":"IT",
    "gn:dem":202,
    "gn:feature_class":"P",
    "gn:feature_code":"PPL",
    "gn:name":"Zubbitilli",
    "gn:population":74,
    "gn:timezone":"Europe/Rome",
    "iso:country":"IT",
    "wof:name":"Zubbitilli",
    "wof:placetype":"locality",
    "wof:population":74
},
  "geometry": {"coordinates":[14.0165,42.34351],"type":"Point"}
}