{
  "type": "Feature",
  "properties": {
    "gn:admin1_code":"16.0",
    "gn:admin2_code":"PI",
    "gn:admin3_code":"50014.0",
    "gn:asciiname":"Area Produttiva Acciaiolo",
    "gn:country_code":"IT",
    "gn:dem":28,
    "gn:feature_class":"P",
    "gn:feature_code":"PPL",
    "gn:name":"Area Produttiva Acciaiolo",
    "gn:population":0,
    "gn:timezone":"Europe/Rome",
    "iso:country":"IT",
    "wof:name":"Area Produttiva Acciaiolo",
    "wof:placetype":"locality"
},
  "geometry": {"coordinates":[10.49729,43.55128],"type":"Point"}
}