{
  "type": "Feature",
  "properties": {
    "gn:admin1_code":"15",
    "gn:admin2_code":"ME",
    "gn:admin3_code":"83007.0",
    "gn:asciiname":"Fosso Gelso",
    "gn:country_code":"IT",
    "gn:dem":92,
    "gn:feature_class":"P",
    "gn:feature_code":"PPL",
    "gn:name":"Fosso Gelso",
    "gn:population":56,
    "gn:timezone":"Europe/Rome",
    "iso:country":"IT",
    "wof:name":"Fosso Gelso",
    "wof:placetype":"locality",
    "wof:population":56
},
  "geometry": {"coordinates":[14.8305,38.14786],"type":"Point"}
}