{
  "type": "Feature",
  "properties": {
    "gn:admin1_code":"3.0",
    "gn:admin2_code":"RC",
    "gn:admin3_code":"80007.0",
    "gn:asciiname":"Ceramida-Pellegrina",
    "gn:country_code":"IT",
    "gn:dem":373,
    "gn:feature_class":"P",
    "gn:feature_code":"PPL",
    "gn:name":"Ceramida-Pellegrina",
    "gn:population":1418,
    "gn:timezone":"Europe/Rome",
    "iso:country":"IT",
    "wof:name":"Ceramida-Pellegrina",
    "wof:placetype":"locality",
    "wof:population":1418
},
  "geometry": {"coordinates":[15.82572,38.29667],"type":"Point"}
}