{
  "type": "Feature",
  "properties": {
    "gn:admin1_code":"20",
    "gn:admin2_code":"VE",
    "gn:admin3_code":"27027.0",
    "gn:asciiname":"Santa Teresina",
    "gn:country_code":"IT",
    "gn:dem":0,
    "gn:feature_class":"P",
    "gn:feature_code":"PPL",
    "gn:name":"Santa Teresina",
    "gn:population":231,
    "gn:timezone":"Europe/Rome",
    "iso:country":"IT",
    "wof:name":"Santa Teresina",
    "wof:placetype":"locality",
    "wof:population":231
},
  "geometry": {"coordinates":[12.57698,45.67912000000001],"type":"Point"}
}