{
  "type": "Feature",
  "properties": {
    "gn:admin1_code":"6.0",
    "gn:admin2_code":"UD",
    "gn:admin3_code":"30126.0",
    "gn:asciiname":"Zeglianutto",
    "gn:country_code":"IT",
    "gn:dem":206,
    "gn:feature_class":"P",
    "gn:feature_code":"PPL",
    "gn:name":"Zeglianutto",
    "gn:population":0,
    "gn:timezone":"Europe/Rome",
    "iso:country":"IT",
    "wof:name":"Zeglianutto",
    "wof:placetype":"locality"
},
  "geometry": {"coordinates":[13.15667,46.19944],"type":"Point"}
}