{
  "type": "Feature",
  "properties": {
    "gn:admin1_code":"8",
    "gn:admin2_code":"IM",
    "gn:admin3_code":"8025.0",
    "gn:asciiname":"Diano Evigno",
    "gn:country_code":"IT",
    "gn:dem":400,
    "gn:feature_class":"P",
    "gn:feature_code":"PPL",
    "gn:name":"Diano Evigno",
    "gn:population":83,
    "gn:timezone":"Europe/Rome",
    "iso:country":"IT",
    "wof:name":"Diano Evigno",
    "wof:placetype":"locality",
    "wof:population":83
},
  "geometry": {"coordinates":[8.03436,43.96665],"type":"Point"}
}