{
  "type": "Feature",
  "properties": {
    "gn:admin1_code":"3",
    "gn:admin2_code":"CS",
    "gn:admin3_code":"78010.0",
    "gn:asciiname":"Fravitte",
    "gn:country_code":"IT",
    "gn:dem":29,
    "gn:feature_class":"P",
    "gn:feature_code":"PPL",
    "gn:name":"Fravitte",
    "gn:population":31,
    "gn:timezone":"Europe/Rome",
    "iso:country":"IT",
    "wof:name":"Fravitte",
    "wof:placetype":"locality",
    "wof:population":31
},
  "geometry": {"coordinates":[16.10735,39.05803],"type":"Point"}
}