{
  "type": "Feature",
  "properties": {
    "gn:admin1_code":"20",
    "gn:admin2_code":"VR",
    "gn:admin3_code":"23062.0",
    "gn:asciiname":"Bezzo",
    "gn:country_code":"IT",
    "gn:dem":223,
    "gn:feature_class":"P",
    "gn:feature_code":"PPL",
    "gn:name":"Bezzo",
    "gn:population":48,
    "gn:timezone":"Europe/Rome",
    "iso:country":"IT",
    "wof:name":"Bezzo",
    "wof:placetype":"locality",
    "wof:population":48
},
  "geometry": {"coordinates":[10.7891,45.5793],"type":"Point"}
}