{
  "type": "Feature",
  "properties": {
    "gn:admin1_code":"4",
    "gn:admin2_code":"BN",
    "gn:admin3_code":"62008.0",
    "gn:asciiname":"Murata",
    "gn:country_code":"IT",
    "gn:dem":256,
    "gn:feature_class":"P",
    "gn:feature_code":"PPL",
    "gn:name":"Murata",
    "gn:population":13,
    "gn:timezone":"Europe/Rome",
    "iso:country":"IT",
    "wof:name":"Murata",
    "wof:placetype":"locality",
    "wof:population":13
},
  "geometry": {"coordinates":[14.77344,41.18329],"type":"Point"}
}