{
  "type": "Feature",
  "properties": {
    "gn:admin1_code":"5",
    "gn:admin2_code":"MO",
    "gn:admin3_code":"36023.0",
    "gn:asciiname":"Pedrazza",
    "gn:country_code":"IT",
    "gn:dem":33,
    "gn:feature_class":"P",
    "gn:feature_code":"PPL",
    "gn:name":"Pedrazza",
    "gn:population":40,
    "gn:timezone":"Europe/Rome",
    "iso:country":"IT",
    "wof:name":"Pedrazza",
    "wof:placetype":"locality",
    "wof:population":40
},
  "geometry": {"coordinates":[10.89824,44.7142],"type":"Point"}
}