{
  "type": "Feature",
  "properties": {
    "gn:admin1_code":"9.0",
    "gn:admin2_code":"MI",
    "gn:admin3_code":"15016.0",
    "gn:asciiname":"Cascina Rotta",
    "gn:country_code":"IT",
    "gn:dem":129,
    "gn:feature_class":"P",
    "gn:feature_code":"PPL",
    "gn:name":"Cascina Rotta",
    "gn:population":16,
    "gn:timezone":"Europe/Rome",
    "iso:country":"IT",
    "wof:name":"Cascina Rotta",
    "wof:placetype":"locality",
    "wof:population":16
},
  "geometry": {"coordinates":[9.45374,45.53578],"type":"Point"}
}