{
  "type": "Feature",
  "properties": {
    "gn:admin1_code":"4",
    "gn:admin2_code":"SA",
    "gn:admin3_code":"65014.0",
    "gn:asciiname":"Santa Rosa",
    "gn:country_code":"IT",
    "gn:dem":24,
    "gn:feature_class":"P",
    "gn:feature_code":"PPL",
    "gn:name":"Santa Rosa",
    "gn:population":17,
    "gn:timezone":"Europe/Rome",
    "iso:country":"IT",
    "wof:name":"Santa Rosa",
    "wof:placetype":"locality",
    "wof:population":17
},
  "geometry": {"coordinates":[14.93047,40.58084],"type":"Point"}
}