{
  "type": "Feature",
  "properties": {
    "gn:admin1_code":"10.0",
    "gn:admin2_code":"MC",
    "gn:admin3_code":"43047.0",
    "gn:asciiname":"Castel San Pietro",
    "gn:country_code":"IT",
    "gn:dem":523,
    "gn:elevation":"536.0",
    "gn:feature_class":"P",
    "gn:feature_code":"PPL",
    "gn:name":"Castel San Pietro",
    "gn:population":22,
    "gn:timezone":"Europe/Rome",
    "iso:country":"IT",
    "wof:name":"Castel San Pietro",
    "wof:placetype":"locality",
    "wof:population":22
},
  "geometry": {"coordinates":[13.13085,43.31994],"type":"Point"}
}