{
  "type": "Feature",
  "properties": {
    "gn:admin1_code":"10.0",
    "gn:admin2_code":"MC",
    "gn:admin3_code":"43047.0",
    "gn:asciiname":"Castel San Pietro",
    "gn:country_code":"IT",
    "gn:dem":523,
    "gn:elevation":"536.0",
    "gn:feature_class":"P",
    "gn:feature_code":"PPL",
    "gn:name":"Castel San Pietro",
    "gn:population":22,
    "gn:timezone":"Europe/Rome",
    "iso:country":"IT",
    "name:als_x_preferred":[
        "Castel San Pietro"
    ],
    "name:cat_x_preferred":[
        "Castel San Pietro"
    ],
    "name:deu_x_preferred":[
        "Castel San Pietro"
    ],
    "name:epo_x_preferred":[
        "Castel San Pietro"
    ],
    "name:eus_x_preferred":[
        "Castel San Pietro"
    ],
    "name:fra_x_preferred":[
        "Castel San Pietro"
    ],
    "name:ita_x_preferred":[
        "Castel San Pietro"
    ],
    "name:lmo_x_preferred":[
        "Castel San Pedru"
    ],
    "name:msa_x_preferred":[
        "Castel San Pietro"
    ],
    "name:nld_x_preferred":[
        "Castel San Pietro"
    ],
    "name:nno_x_preferred":[
        "Castel San Pietro"
    ],
    "name:por_x_preferred":[
        "Castel San Pietro"
    ],
    "name:roh_x_preferred":[
        "Castel San Pietro"
    ],
    "name:rus_x_preferred":[
        "\u041a\u0430\u0441\u0442\u0435\u043b\u044c-\u0421\u0430\u043d-\u041f\u044c\u0435\u0442\u0440\u043e"
    ],
    "name:spa_x_preferred":[
        "Castel San Pietro"
    ],
    "name:sqi_x_preferred":[
        "Castel San Pietro"
    ],
    "name:swe_x_preferred":[
        "Castel San Pietro"
    ],
    "name:vol_x_preferred":[
        "Castel San Pietro"
    ],
    "name:war_x_preferred":[
        "Castel San Pietro"
    ],
    "name:zho_x_preferred":[
        "\u8056\u5f7c\u5f97\u7f85\u5821"
    ],
    "wof:name":"Castel San Pietro",
    "wof:placetype":"locality",
    "wof:population":22
},
  "geometry": {"coordinates":[13.13085,43.31994],"type":"Point"}
}