{
  "type": "Feature",
  "properties": {
    "gn:admin1_code":"3",
    "gn:admin2_code":"CZ",
    "gn:admin3_code":"79160.0",
    "gn:asciiname":"Santa Eufemia Vetere",
    "gn:country_code":"IT",
    "gn:dem":68,
    "gn:feature_class":"P",
    "gn:feature_code":"PPL",
    "gn:name":"Santa Eufemia Vetere",
    "gn:population":108,
    "gn:timezone":"Europe/Rome",
    "iso:country":"IT",
    "wof:name":"Santa Eufemia Vetere",
    "wof:placetype":"locality",
    "wof:population":108
},
  "geometry": {"coordinates":[16.23867000000001,38.94353],"type":"Point"}
}