{
  "type": "Feature",
  "properties": {
    "iso:country":"IT",
    "qs_pg:aaroncc":"IT",
    "qs_pg:name":"Antica Erice",
    "qs_pg:name_adm0":"Italia",
    "qs_pg:name_adm1":"Sicilia",
    "qs_pg:photos":2780,
    "qs_pg:photos_1k":563,
    "qs_pg:photos_9k":12,
    "qs_pg:photos_9r":10,
    "qs_pg:photos_all":2780,
    "qs_pg:photos_sr":19,
    "qs_pg:pop_sr":0,
    "qs_pg:qs_pg_placetype":"locality",
    "qs_pg:qs_pg_placetype_gp":"Town",
    "qs_pg:woe_adm0":23424853,
    "woe:adm0_id":23424853,
    "woe:name_adm0":"Italia",
    "woe:name_adm1":"Sicilia",
    "woe:placetype":"Town",
    "wof:name":"Antica Erice",
    "wof:placetype":"locality"
},
  "geometry": {"coordinates":[12.586287,38.038002],"type":"Point"}
}