{
  "type": "Feature",
  "properties": {
    "gn:admin1_code":"17",
    "gn:admin2_code":"BZ",
    "gn:admin3_code":"21107.0",
    "gn:asciiname":"Riva",
    "gn:country_code":"IT",
    "gn:dem":1428,
    "gn:feature_class":"P",
    "gn:feature_code":"PPL",
    "gn:name":"Riva",
    "gn:population":47,
    "gn:timezone":"Europe/Rome",
    "iso:country":"IT",
    "wof:name":"Riva",
    "wof:placetype":"locality",
    "wof:population":47
},
  "geometry": {"coordinates":[11.56596,46.96283],"type":"Point"}
}