{
  "type": "Feature",
  "properties": {
    "gn:admin1_code":"17",
    "gn:admin2_code":"BZ",
    "gn:admin3_code":"21107.0",
    "gn:asciiname":"Riva",
    "gn:country_code":"IT",
    "gn:dem":1428,
    "gn:feature_class":"P",
    "gn:feature_code":"PPL",
    "gn:name":"Riva",
    "gn:population":47,
    "gn:timezone":"Europe/Rome",
    "iso:country":"IT",
    "name:ceb_x_preferred":[
        "Riva"
    ],
    "name:deu_x_preferred":[
        "Riva"
    ],
    "name:epo_x_preferred":[
        "Riva"
    ],
    "name:fin_x_preferred":[
        "Riva"
    ],
    "name:fra_x_preferred":[
        "Riva"
    ],
    "name:ita_x_preferred":[
        "Riva"
    ],
    "name:jpn_x_preferred":[
        "\u30ea\u30fc\u30d0"
    ],
    "name:nld_x_preferred":[
        "Riva"
    ],
    "name:nor_x_preferred":[
        "Riva"
    ],
    "name:pms_x_preferred":[
        "Riva"
    ],
    "name:pol_x_preferred":[
        "Riva"
    ],
    "name:por_x_preferred":[
        "Riva"
    ],
    "name:rus_x_preferred":[
        "\u0420\u0438\u0432\u0430"
    ],
    "name:srp_x_preferred":[
        "\u0420\u0438\u0432\u0430"
    ],
    "name:swe_x_preferred":[
        "Riva"
    ],
    "name:tur_x_preferred":[
        "Riva"
    ],
    "name:ukr_x_preferred":[
        "\u0420\u0456\u0432\u0430"
    ],
    "wof:name":"Riva",
    "wof:placetype":"locality",
    "wof:population":47
},
  "geometry": {"coordinates":[11.56596,46.96283],"type":"Point"}
}