{
  "type": "Feature",
  "properties": {
    "gn:admin1_code":"8.0",
    "gn:admin2_code":"IM",
    "gn:admin3_code":"8034.0",
    "gn:asciiname":"Pian dei Prati",
    "gn:country_code":"IT",
    "gn:dem":1172,
    "gn:feature_class":"P",
    "gn:feature_code":"PPLL",
    "gn:name":"Pian dei Prati",
    "gn:population":2,
    "gn:timezone":"Europe/Rome",
    "iso:country":"IT",
    "wof:name":"Pian dei Prati",
    "wof:placetype":"locality",
    "wof:population":2
},
  "geometry": {"coordinates":[7.78884,44.07695],"type":"Point"}
}