{
  "type": "Feature",
  "properties": {
    "gn:admin1_code":"16.0",
    "gn:admin2_code":"PT",
    "gn:admin3_code":"47014.0",
    "gn:asciiname":"Lupicciano",
    "gn:country_code":"IT",
    "gn:dem":382,
    "gn:feature_class":"P",
    "gn:feature_code":"PPL",
    "gn:name":"Lupicciano",
    "gn:population":249,
    "gn:timezone":"Europe/Rome",
    "iso:country":"IT",
    "wof:name":"Lupicciano",
    "wof:placetype":"locality",
    "wof:population":249
},
  "geometry": {"coordinates":[10.95269,43.97727],"type":"Point"}
}