{
  "type": "Feature",
  "properties": {
    "gn:admin1_code":"20.0",
    "gn:admin2_code":"PD",
    "gn:admin3_code":"28053.0",
    "gn:asciiname":"Minotte",
    "gn:country_code":"IT",
    "gn:dem":5,
    "gn:elevation":"10.0",
    "gn:feature_class":"P",
    "gn:feature_code":"PPL",
    "gn:name":"Minotte",
    "gn:population":79,
    "gn:timezone":"Europe/Rome",
    "iso:country":"IT",
    "name:und_x_variant":[
        "Casa Minotte"
    ],
    "wof:name":"Minotte",
    "wof:placetype":"locality",
    "wof:population":79
},
  "geometry": {"coordinates":[11.4744,45.15331],"type":"Point"}
}