{
  "type": "Feature",
  "properties": {
    "gn:admin1_code":"12.0",
    "gn:admin2_code":"CN",
    "gn:admin3_code":"4132.0",
    "gn:asciiname":"Perno",
    "gn:country_code":"IT",
    "gn:dem":386,
    "gn:elevation":"395.0",
    "gn:feature_class":"P",
    "gn:feature_code":"PPL",
    "gn:name":"Perno",
    "gn:population":69,
    "gn:timezone":"Europe/Rome",
    "iso:country":"IT",
    "wof:name":"Perno",
    "wof:placetype":"locality",
    "wof:population":69
},
  "geometry": {"coordinates":[7.97573,44.61283],"type":"Point"}
}