{
  "type": "Feature",
  "properties": {
    "gn:admin1_code":"3",
    "gn:admin2_code":"RC",
    "gn:admin3_code":"80022.0",
    "gn:asciiname":"Contrada Chiumputo",
    "gn:country_code":"IT",
    "gn:dem":964,
    "gn:feature_class":"P",
    "gn:feature_code":"PPL",
    "gn:name":"Contrada Chiumputo",
    "gn:population":21,
    "gn:timezone":"Europe/Rome",
    "iso:country":"IT",
    "wof:name":"Contrada Chiumputo",
    "wof:placetype":"locality",
    "wof:population":21
},
  "geometry": {"coordinates":[15.8133,38.09193],"type":"Point"}
}