{
  "type": "Feature",
  "properties": {
    "iso:country":"IT",
    "wof:name":"Case Rosse",
    "wof:placetype":"neighbourhood"
},
  "geometry": {"coordinates":[12.65036320100074,41.93297624396448],"type":"Point"}
}