{
  "type": "Feature",
  "properties": {
    "gn:country":"IT",
    "gn:fcode":"PPL",
    "gn:population":0,
    "iso:country":"IT",
    "qs_pg:aaroncc":"IT",
    "qs_pg:gn_country":"IT",
    "qs_pg:gn_fcode":"PPL",
    "qs_pg:gn_pop":0,
    "qs_pg:name":"Ciser",
    "qs_pg:name_adm0":"Italia",
    "qs_pg:name_adm1":"Veneto",
    "qs_pg:photos":41,
    "qs_pg:photos_1k":8,
    "qs_pg:photos_9k":1,
    "qs_pg:photos_9r":2,
    "qs_pg:photos_all":41,
    "qs_pg:photos_sr":2,
    "qs_pg:pop_sr":0,
    "qs_pg:qs_pg_placetype":"locality",
    "qs_pg:qs_pg_placetype_gp":"Town",
    "qs_pg:woe_adm0":23424853,
    "woe:adm0_id":23424853,
    "woe:name_adm0":"Italia",
    "woe:name_adm1":"Veneto",
    "woe:placetype":"Town",
    "wof:name":"Ciser",
    "wof:placetype":"locality",
    "wof:population":232
},
  "geometry": {"coordinates":[13.24611,46.23056],"type":"Point"}
}