{
  "type": "Feature",
  "properties": {
    "gn:admin1_code":"15",
    "gn:admin2_code":"ME",
    "gn:admin3_code":"83066.0",
    "gn:asciiname":"Locanda",
    "gn:country_code":"IT",
    "gn:dem":198,
    "gn:feature_class":"P",
    "gn:feature_code":"PPL",
    "gn:name":"Locanda",
    "gn:population":113,
    "gn:timezone":"Europe/Rome",
    "iso:country":"IT",
    "wof:name":"Locanda",
    "wof:placetype":"locality",
    "wof:population":113
},
  "geometry": {"coordinates":[15.04134,38.13756],"type":"Point"}
}