{
  "type": "Feature",
  "properties": {
    "gn:admin1_code":"20",
    "gn:admin2_code":"VR",
    "gn:admin3_code":"23073.0",
    "gn:asciiname":"Bonettiele",
    "gn:country_code":"IT",
    "gn:dem":52,
    "gn:feature_class":"P",
    "gn:feature_code":"PPL",
    "gn:name":"Bonettiele",
    "gn:population":16,
    "gn:timezone":"Europe/Rome",
    "iso:country":"IT",
    "wof:name":"Bonettiele",
    "wof:placetype":"locality",
    "wof:population":16
},
  "geometry": {"coordinates":[11.07593,45.43455],"type":"Point"}
}