{
  "type": "Feature",
  "properties": {
    "gn:admin1_code":"5",
    "gn:admin2_code":"FC",
    "gn:admin3_code":"40012.0",
    "gn:asciiname":"Decio Raggi",
    "gn:country_code":"IT",
    "gn:dem":32,
    "gn:feature_class":"P",
    "gn:feature_code":"PPL",
    "gn:name":"Decio Raggi",
    "gn:population":14,
    "gn:timezone":"Europe/Rome",
    "iso:country":"IT",
    "wof:name":"Decio Raggi",
    "wof:placetype":"locality",
    "wof:population":14
},
  "geometry": {"coordinates":[12.05681,44.19384],"type":"Point"}
}