{
  "type": "Feature",
  "properties": {
    "gn:admin1_code":"15",
    "gn:admin2_code":"TP",
    "gn:admin3_code":"81024.0",
    "gn:asciiname":"Citta",
    "gn:country_code":"IT",
    "gn:dem":8,
    "gn:feature_class":"P",
    "gn:feature_code":"PPL",
    "gn:name":"Citta",
    "gn:population":112,
    "gn:timezone":"Europe/Rome",
    "iso:country":"IT",
    "name:fra_x_preferred":[
        "Chitta"
    ],
    "name:hin_x_preferred":[
        "\u091a\u093f\u0924\u094d\u0924"
    ],
    "name:hye_x_preferred":[
        "\u0549\u056b\u057f\u057f\u0561"
    ],
    "name:jpn_x_preferred":[
        "\u5fc3"
    ],
    "name:kor_x_preferred":[
        "\ub9c8\uc74c"
    ],
    "name:lit_x_preferred":[
        "\u010cita"
    ],
    "name:pol_x_preferred":[
        "\u0106itta"
    ],
    "name:rus_x_preferred":[
        "\u0427\u0438\u0442\u0442\u0430"
    ],
    "name:srp_x_preferred":[
        "\u0423\u043c"
    ],
    "name:tha_x_preferred":[
        "\u0e08\u0e34\u0e15"
    ],
    "name:zho_x_preferred":[
        "\u5fc3"
    ],
    "wof:name":"Citta",
    "wof:placetype":"locality",
    "wof:population":112
},
  "geometry": {"coordinates":[12.48871,37.69404],"type":"Point"}
}