{
  "type": "Feature",
  "properties": {
    "gn:admin1_code":"15",
    "gn:admin2_code":"TP",
    "gn:admin3_code":"81024.0",
    "gn:asciiname":"Citta",
    "gn:country_code":"IT",
    "gn:dem":8,
    "gn:feature_class":"P",
    "gn:feature_code":"PPL",
    "gn:name":"Citta",
    "gn:population":112,
    "gn:timezone":"Europe/Rome",
    "iso:country":"IT",
    "wof:name":"Citta",
    "wof:placetype":"locality",
    "wof:population":112
},
  "geometry": {"coordinates":[12.48871,37.69404],"type":"Point"}
}