{
  "type": "Feature",
  "properties": {
    "gn:admin1_code":"4",
    "gn:admin2_code":"CE",
    "gn:admin3_code":"61008.0",
    "gn:asciiname":"Localita Boschetto",
    "gn:country_code":"IT",
    "gn:dem":181,
    "gn:feature_class":"P",
    "gn:feature_code":"PPL",
    "gn:name":"Localit\u00e0 Boschetto",
    "gn:population":52,
    "gn:timezone":"Europe/Rome",
    "iso:country":"IT",
    "name:und_x_variant":[
        "Localit\u00e0 Boschetto"
    ],
    "wof:name":"Localita Boschetto",
    "wof:placetype":"locality",
    "wof:population":52
},
  "geometry": {"coordinates":[14.10016,41.29369000000001],"type":"Point"}
}