{
  "type": "Feature",
  "properties": {
    "gn:admin1_code":"9",
    "gn:admin2_code":"LO",
    "gn:admin3_code":"98011.0",
    "gn:asciiname":"Bruzzelle",
    "gn:country_code":"IT",
    "gn:dem":43,
    "gn:feature_class":"P",
    "gn:feature_code":"PPL",
    "gn:name":"Bruzzelle",
    "gn:population":92,
    "gn:timezone":"Europe/Rome",
    "iso:country":"IT",
    "wof:name":"Bruzzelle",
    "wof:placetype":"locality",
    "wof:population":92
},
  "geometry": {"coordinates":[9.79762,45.12495],"type":"Point"}
}