{
  "type": "Feature",
  "properties": {
    "gn:admin1_code":"20.0",
    "gn:admin2_code":"VI",
    "gn:admin3_code":"24040.0",
    "gn:asciiname":"Crosara",
    "gn:country_code":"IT",
    "gn:dem":134,
    "gn:feature_class":"P",
    "gn:feature_code":"PPL",
    "gn:name":"Crosara",
    "gn:population":162,
    "gn:timezone":"Europe/Rome",
    "iso:country":"IT",
    "wof:name":"Crosara",
    "wof:placetype":"locality",
    "wof:population":162
},
  "geometry": {"coordinates":[11.54696,45.71047],"type":"Point"}
}