{
  "type": "Feature",
  "properties": {
    "gn:admin1_code":"20.0",
    "gn:admin2_code":"VR",
    "gn:admin3_code":"23061.0",
    "gn:asciiname":"Crosare",
    "gn:country_code":"IT",
    "gn:dem":15,
    "gn:elevation":"17.0",
    "gn:feature_class":"P",
    "gn:feature_code":"PPL",
    "gn:name":"Crosare",
    "gn:population":213,
    "gn:timezone":"Europe/Rome",
    "iso:country":"IT",
    "wof:name":"Crosare",
    "wof:placetype":"locality",
    "wof:population":213
},
  "geometry": {"coordinates":[11.43249,45.26603],"type":"Point"}
}