{
  "type": "Feature",
  "properties": {
    "gn:admin1_code":"12",
    "gn:admin2_code":"AL",
    "gn:admin3_code":"6039.0",
    "gn:asciiname":"Villa Sordi",
    "gn:country_code":"IT",
    "gn:dem":138,
    "gn:feature_class":"P",
    "gn:feature_code":"PPL",
    "gn:name":"Villa Sordi",
    "gn:population":26,
    "gn:timezone":"Europe/Rome",
    "iso:country":"IT",
    "wof:name":"Villa Sordi",
    "wof:placetype":"locality",
    "wof:population":26
},
  "geometry": {"coordinates":[8.39081,45.13931],"type":"Point"}
}