{
  "type": "Feature",
  "properties": {
    "gn:admin1_code":"5",
    "gn:admin2_code":"RN",
    "gn:admin3_code":"99029.0",
    "gn:asciiname":"Gaiano",
    "gn:country_code":"IT",
    "gn:dem":371,
    "gn:feature_class":"P",
    "gn:feature_code":"PPL",
    "gn:name":"Gaiano",
    "gn:population":17,
    "gn:timezone":"Europe/Rome",
    "iso:country":"IT",
    "wof:name":"Gaiano",
    "wof:placetype":"locality",
    "wof:population":17
},
  "geometry": {"coordinates":[12.5213,43.90607],"type":"Point"}
}