{
  "type": "Feature",
  "properties": {
    "gn:admin1_code":"12",
    "gn:admin2_code":"AT",
    "gn:admin3_code":"5039.0",
    "gn:asciiname":"Migliarine",
    "gn:country_code":"IT",
    "gn:dem":249,
    "gn:feature_class":"P",
    "gn:feature_code":"PPL",
    "gn:name":"Migliarine",
    "gn:population":24,
    "gn:timezone":"Europe/Rome",
    "iso:country":"IT",
    "wof:name":"Migliarine",
    "wof:placetype":"locality",
    "wof:population":24
},
  "geometry": {"coordinates":[8.09246,44.97412],"type":"Point"}
}