{
  "type": "Feature",
  "properties": {
    "gn:admin1_code":"10",
    "gn:admin2_code":"AP",
    "gn:admin3_code":"44002.0",
    "gn:asciiname":"Colle in Su",
    "gn:country_code":"IT",
    "gn:dem":178,
    "gn:feature_class":"P",
    "gn:feature_code":"PPL",
    "gn:name":"Colle in Su",
    "gn:population":30,
    "gn:timezone":"Europe/Rome",
    "iso:country":"IT",
    "wof:name":"Colle in Su",
    "wof:placetype":"locality",
    "wof:population":30
},
  "geometry": {"coordinates":[13.83779,42.94922],"type":"Point"}
}