{
  "type": "Feature",
  "properties": {
    "gn:admin1_code":"5",
    "gn:admin2_code":"RN",
    "gn:admin3_code":"99029.0",
    "gn:asciiname":"Chitarrara",
    "gn:country_code":"IT",
    "gn:dem":143,
    "gn:feature_class":"P",
    "gn:feature_code":"PPL",
    "gn:name":"Chitarrara",
    "gn:population":22,
    "gn:timezone":"Europe/Rome",
    "iso:country":"IT",
    "wof:name":"Chitarrara",
    "wof:placetype":"locality",
    "wof:population":22
},
  "geometry": {"coordinates":[12.56549,43.91591],"type":"Point"}
}