{
  "type": "Feature",
  "properties": {
    "gn:admin1_code":"20",
    "gn:admin2_code":"VR",
    "gn:admin3_code":"23001.0",
    "gn:asciiname":"Caorsa",
    "gn:country_code":"IT",
    "gn:dem":207,
    "gn:feature_class":"P",
    "gn:feature_code":"PPL",
    "gn:name":"Caorsa",
    "gn:population":79,
    "gn:timezone":"Europe/Rome",
    "iso:country":"IT",
    "wof:name":"Caorsa",
    "wof:placetype":"locality",
    "wof:population":79
},
  "geometry": {"coordinates":[10.7735,45.54634],"type":"Point"}
}