{
  "type": "Feature",
  "properties": {
    "gn:admin1_code":"20",
    "gn:admin2_code":"VR",
    "gn:admin3_code":"23018.0",
    "gn:asciiname":"Vilmezzano",
    "gn:country_code":"IT",
    "gn:dem":448,
    "gn:feature_class":"P",
    "gn:feature_code":"PPL",
    "gn:name":"Vilmezzano",
    "gn:population":101,
    "gn:timezone":"Europe/Rome",
    "iso:country":"IT",
    "wof:name":"Vilmezzano",
    "wof:placetype":"locality",
    "wof:population":101
},
  "geometry": {"coordinates":[10.81644,45.62161],"type":"Point"}
}