{
  "type": "Feature",
  "properties": {
    "gn:admin1_code":"12",
    "gn:admin2_code":"AL",
    "gn:admin3_code":"6188.0",
    "gn:asciiname":"Ca di Stringa",
    "gn:country_code":"IT",
    "gn:dem":308,
    "gn:feature_class":"P",
    "gn:feature_code":"PPL",
    "gn:name":"C\u00e0 di Stringa",
    "gn:population":18,
    "gn:timezone":"Europe/Rome",
    "iso:country":"IT",
    "name:und_x_variant":[
        "C\u00e0 di Stringa"
    ],
    "wof:name":"Ca di Stringa",
    "wof:placetype":"locality",
    "wof:population":18
},
  "geometry": {"coordinates":[9.01817,44.89423],"type":"Point"}
}