{
  "type": "Feature",
  "properties": {
    "gn:admin1_code":"12.0",
    "gn:admin2_code":"VB",
    "gn:admin3_code":"103069.0",
    "gn:asciiname":"Luzzogno",
    "gn:country_code":"IT",
    "gn:dem":711,
    "gn:feature_class":"P",
    "gn:feature_code":"PPL",
    "gn:name":"Luzzogno",
    "gn:population":402,
    "gn:timezone":"Europe/Rome",
    "iso:country":"IT",
    "wof:name":"Luzzogno",
    "wof:placetype":"locality",
    "wof:population":402
},
  "geometry": {"coordinates":[8.34397,45.91478],"type":"Point"}
}