{
  "type": "Feature",
  "properties": {
    "gn:admin1_code":"9",
    "gn:admin2_code":"CR",
    "gn:admin3_code":"19093.0",
    "gn:asciiname":"Fienile",
    "gn:country_code":"IT",
    "gn:dem":41,
    "gn:feature_class":"P",
    "gn:feature_code":"PPL",
    "gn:name":"Fienile",
    "gn:population":24,
    "gn:timezone":"Europe/Rome",
    "iso:country":"IT",
    "wof:name":"Fienile",
    "wof:placetype":"locality",
    "wof:population":24
},
  "geometry": {"coordinates":[10.16097,45.23355],"type":"Point"}
}