{
  "type": "Feature",
  "properties": {
    "gn:admin1_code":"10",
    "gn:admin2_code":"PU",
    "gn:admin3_code":"41007.0",
    "gn:asciiname":"Oriana",
    "gn:country_code":"IT",
    "gn:dem":309,
    "gn:feature_class":"P",
    "gn:feature_code":"PPL",
    "gn:name":"Oriana",
    "gn:population":21,
    "gn:timezone":"Europe/Rome",
    "iso:country":"IT",
    "wof:name":"Oriana",
    "wof:placetype":"locality",
    "wof:population":21
},
  "geometry": {"coordinates":[12.64459,43.55577],"type":"Point"}
}