{
  "type": "Feature",
  "properties": {
    "gn:admin1_code":"16.0",
    "gn:admin2_code":"LI",
    "gn:admin3_code":"49003.0",
    "gn:asciiname":"La Pila",
    "gn:country_code":"IT",
    "gn:dem":9,
    "gn:feature_class":"P",
    "gn:feature_code":"PPL",
    "gn:name":"La Pila",
    "gn:population":405,
    "gn:timezone":"Europe/Rome",
    "iso:country":"IT",
    "name:ceb_x_preferred":[
        "La Pila"
    ],
    "name:ita_x_preferred":[
        "La Pila"
    ],
    "name:srp_x_preferred":[
        "\u041b\u0430 \u041f\u0438\u043b\u0430"
    ],
    "wof:name":"La Pila",
    "wof:placetype":"locality",
    "wof:population":405
},
  "geometry": {"coordinates":[10.23479,42.7634],"type":"Point"}
}