{
  "type": "Feature",
  "properties": {
    "gn:admin1_code":"9",
    "gn:admin2_code":"VA",
    "gn:admin3_code":"12133.0",
    "gn:asciiname":"Caverzasio",
    "gn:country_code":"IT",
    "gn:dem":434,
    "gn:feature_class":"P",
    "gn:feature_code":"PPL",
    "gn:name":"Caverzasio",
    "gn:population":155,
    "gn:timezone":"Europe/Rome",
    "iso:country":"IT",
    "wof:name":"Caverzasio",
    "wof:placetype":"locality",
    "wof:population":155
},
  "geometry": {"coordinates":[8.86131,45.82784],"type":"Point"}
}