{
  "type": "Feature",
  "properties": {
    "gn:admin1_code":"16",
    "gn:admin2_code":"PT",
    "gn:admin3_code":"47020.0",
    "gn:asciiname":"Pierucciani",
    "gn:country_code":"IT",
    "gn:dem":46,
    "gn:feature_class":"P",
    "gn:feature_code":"PPL",
    "gn:name":"Pierucciani",
    "gn:population":23,
    "gn:timezone":"Europe/Rome",
    "iso:country":"IT",
    "wof:name":"Pierucciani",
    "wof:placetype":"locality",
    "wof:population":23
},
  "geometry": {"coordinates":[10.93083,43.88501],"type":"Point"}
}