{
  "type": "Feature",
  "properties": {
    "gn:admin1_code":"20",
    "gn:admin2_code":"VI",
    "gn:admin3_code":"24008.0",
    "gn:asciiname":"Bettega",
    "gn:country_code":"IT",
    "gn:dem":306,
    "gn:feature_class":"P",
    "gn:feature_code":"PPL",
    "gn:name":"Bettega",
    "gn:population":36,
    "gn:timezone":"Europe/Rome",
    "iso:country":"IT",
    "wof:name":"Bettega",
    "wof:placetype":"locality",
    "wof:population":36
},
  "geometry": {"coordinates":[11.32237,45.53683],"type":"Point"}
}