{
  "type": "Feature",
  "properties": {
    "gn:admin1_code":"5",
    "gn:admin2_code":"FC",
    "gn:admin3_code":"40044.0",
    "gn:asciiname":"Castel d'Alfero",
    "gn:country_code":"IT",
    "gn:dem":623,
    "gn:feature_class":"P",
    "gn:feature_code":"PPLL",
    "gn:name":"Castel d'Alfero",
    "gn:population":6,
    "gn:timezone":"Europe/Rome",
    "iso:country":"IT",
    "wof:name":"Castel d'Alfero",
    "wof:placetype":"locality",
    "wof:population":6
},
  "geometry": {"coordinates":[12.06186,43.84772],"type":"Point"}
}