{
  "type": "Feature",
  "properties": {
    "gn:admin1_code":"9.0",
    "gn:admin2_code":"VA",
    "gn:admin3_code":"12109.0",
    "gn:asciiname":"Polo Industriale Sud",
    "gn:country_code":"IT",
    "gn:dem":194,
    "gn:feature_class":"P",
    "gn:feature_code":"PPLL",
    "gn:name":"Polo Industriale Sud",
    "gn:population":0,
    "gn:timezone":"Europe/Rome",
    "iso:country":"IT",
    "wof:name":"Polo Industriale Sud",
    "wof:placetype":"locality"
},
  "geometry": {"coordinates":[9.00656,45.5815],"type":"Point"}
}