{
  "type": "Feature",
  "properties": {
    "gn:admin1_code":"9.0",
    "gn:admin2_code":"BG",
    "gn:admin3_code":"16177.0",
    "gn:asciiname":"Cascina Malpaga",
    "gn:country_code":"IT",
    "gn:dem":103,
    "gn:feature_class":"P",
    "gn:feature_code":"PPL",
    "gn:name":"Cascina Malpaga",
    "gn:population":43,
    "gn:timezone":"Europe/Rome",
    "iso:country":"IT",
    "wof:name":"Cascina Malpaga",
    "wof:placetype":"locality",
    "wof:population":43
},
  "geometry": {"coordinates":[9.87083,45.46192],"type":"Point"}
}