{
  "type": "Feature",
  "properties": {
    "gn:country":"IT",
    "gn:fcode":"PPL",
    "gn:population":0,
    "iso:country":"IT",
    "name:ceb_x_preferred":[
        "Serravalle"
    ],
    "name:eng_x_preferred":[
        "Serravalle"
    ],
    "name:fra_x_preferred":[
        "Serravalle"
    ],
    "name:ita_x_preferred":[
        "Serravalle"
    ],
    "name:nld_x_preferred":[
        "Serravalle"
    ],
    "name:spa_x_preferred":[
        "Serravalle"
    ],
    "name:srp_x_preferred":[
        "Serravalle"
    ],
    "qs_pg:aaroncc":"IT",
    "qs_pg:gn_country":"IT",
    "qs_pg:gn_fcode":"PPL",
    "qs_pg:gn_pop":0,
    "qs_pg:name":"Serravalle",
    "qs_pg:name_adm0":"Italia",
    "qs_pg:name_adm1":"Toscana",
    "qs_pg:photos_9r":0,
    "qs_pg:photos_sr":0,
    "qs_pg:pop_sr":0,
    "qs_pg:qs_pg_placetype":"locality",
    "qs_pg:qs_pg_placetype_gp":"Town",
    "qs_pg:woe_adm0":23424853,
    "woe:adm0_id":23424853,
    "woe:name_adm0":"Italia",
    "woe:name_adm1":"Toscana",
    "woe:placetype":"Town",
    "wof:name":"Serravalle",
    "wof:placetype":"locality",
    "wof:population":146
},
  "geometry": {"coordinates":[11.83333,43.76667],"type":"Point"}
}