{
  "type": "Feature",
  "properties": {
    "gn:country":"IT",
    "gn:fcode":"PPL",
    "gn:population":0,
    "iso:country":"IT",
    "name:bul_x_preferred":[
        "\u0413\u0430\u0438\u0431\u0430\u043d\u0430"
    ],
    "name:ceb_x_preferred":[
        "Gaibana"
    ],
    "name:eng_x_preferred":[
        "Gaibana"
    ],
    "name:fra_x_preferred":[
        "Gaibana"
    ],
    "name:hun_x_preferred":[
        "Gaibana"
    ],
    "name:ita_x_preferred":[
        "Gaibana"
    ],
    "name:nld_x_preferred":[
        "Gaibana"
    ],
    "name:srp_x_preferred":[
        "Gaibana"
    ],
    "qs_pg:aaroncc":"IT",
    "qs_pg:gn_country":"IT",
    "qs_pg:gn_fcode":"PPL",
    "qs_pg:gn_pop":0,
    "qs_pg:name":"Gaibana",
    "qs_pg:name_adm0":"Italia",
    "qs_pg:name_adm1":"Emilia Romagna",
    "qs_pg:photos":161,
    "qs_pg:photos_1k":33,
    "qs_pg:photos_9k":1,
    "qs_pg:photos_9r":4,
    "qs_pg:photos_all":161,
    "qs_pg:photos_sr":4,
    "qs_pg:pop_sr":0,
    "qs_pg:qs_pg_placetype":"locality",
    "qs_pg:qs_pg_placetype_gp":"Town",
    "qs_pg:woe_adm0":23424853,
    "woe:adm0_id":23424853,
    "woe:name_adm0":"Italia",
    "woe:name_adm1":"Emilia Romagna",
    "woe:placetype":"Town",
    "wof:name":"Gaibana",
    "wof:placetype":"locality",
    "wof:population":274
},
  "geometry": {"coordinates":[11.65,44.75],"type":"Point"}
}