{
  "type": "Feature",
  "properties": {
    "gn:admin1_code":"4.0",
    "gn:admin3_code":"63034.0",
    "gn:asciiname":"Marina di Varcaturo",
    "gn:country_code":"IT",
    "gn:dem":6,
    "gn:feature_class":"P",
    "gn:feature_code":"PPL",
    "gn:name":"Marina di Varcaturo",
    "gn:population":0,
    "gn:timezone":"Europe/Rome",
    "iso:country":"IT",
    "wof:name":"Marina di Varcaturo",
    "wof:placetype":"locality"
},
  "geometry": {"coordinates":[14.03761,40.90017],"type":"Point"}
}