{
  "type": "Feature",
  "properties": {
    "gn:admin1_code":"9.0",
    "gn:admin2_code":"VA",
    "gn:admin3_code":"12142.0",
    "gn:asciiname":"Zenna",
    "gn:country_code":"IT",
    "gn:dem":209,
    "gn:elevation":"197.0",
    "gn:feature_class":"P",
    "gn:feature_code":"PPL",
    "gn:name":"Zenna",
    "gn:population":49,
    "gn:timezone":"Europe/Rome",
    "iso:country":"IT",
    "wof:name":"Zenna",
    "wof:placetype":"locality",
    "wof:population":49
},
  "geometry": {"coordinates":[8.75396,46.1035],"type":"Point"}
}