{
  "type": "Feature",
  "properties": {
    "gn:admin1_code":"9",
    "gn:admin2_code":"BS",
    "gn:admin3_code":"17123.0",
    "gn:asciiname":"Fonte",
    "gn:country_code":"IT",
    "gn:dem":214,
    "gn:feature_class":"P",
    "gn:feature_code":"PPL",
    "gn:name":"Fonte",
    "gn:population":46,
    "gn:timezone":"Europe/Rome",
    "iso:country":"IT",
    "wof:name":"Fonte",
    "wof:placetype":"locality",
    "wof:population":46
},
  "geometry": {"coordinates":[10.10852,45.61668],"type":"Point"}
}