{
  "type": "Feature",
  "properties": {
    "gn:admin1_code":"9",
    "gn:admin2_code":"BS",
    "gn:admin3_code":"17123.0",
    "gn:asciiname":"Fonte",
    "gn:country_code":"IT",
    "gn:dem":214,
    "gn:feature_class":"P",
    "gn:feature_code":"PPL",
    "gn:name":"Fonte",
    "gn:population":46,
    "gn:timezone":"Europe/Rome",
    "iso:country":"IT",
    "name:azb_x_preferred":[
        "\u0641\u0648\u0646\u062a\u0647"
    ],
    "name:bul_x_preferred":[
        "\u0424\u043e\u043d\u0442\u0435"
    ],
    "name:ceb_x_preferred":[
        "Fonte"
    ],
    "name:deu_x_preferred":[
        "Fonte"
    ],
    "name:epo_x_preferred":[
        "Fonte"
    ],
    "name:eus_x_preferred":[
        "Fonte"
    ],
    "name:fas_x_preferred":[
        "\u0641\u0648\u0646\u062a\u0647"
    ],
    "name:fra_x_preferred":[
        "Fonte"
    ],
    "name:hun_x_preferred":[
        "Fonte"
    ],
    "name:hye_x_preferred":[
        "\u0556\u0578\u0576\u057f\u0565"
    ],
    "name:ita_x_preferred":[
        "Fonte"
    ],
    "name:jpn_x_preferred":[
        "\u30d5\u30a9\u30f3\u30c6"
    ],
    "name:kaz_x_preferred":[
        "\u0424\u043e\u043d\u0442\u0435"
    ],
    "name:lat_x_preferred":[
        "Fons"
    ],
    "name:lmo_x_preferred":[
        "Fonte"
    ],
    "name:msa_x_preferred":[
        "Fonte"
    ],
    "name:nap_x_preferred":[
        "Fonte"
    ],
    "name:nld_x_preferred":[
        "Fonte"
    ],
    "name:pms_x_preferred":[
        "Fonte"
    ],
    "name:pol_x_preferred":[
        "Fonte"
    ],
    "name:por_x_preferred":[
        "Fonte"
    ],
    "name:ron_x_preferred":[
        "Fonte"
    ],
    "name:rus_x_preferred":[
        "\u0424\u043e\u043d\u0442\u0435"
    ],
    "name:scn_x_preferred":[
        "Fonte"
    ],
    "name:spa_x_preferred":[
        "Fonte"
    ],
    "name:tgl_x_preferred":[
        "Fonte"
    ],
    "name:ukr_x_preferred":[
        "\u0424\u043e\u043d\u0442\u0435"
    ],
    "name:uzb_x_preferred":[
        "Fonte"
    ],
    "name:vec_x_preferred":[
        "Font"
    ],
    "name:vie_x_preferred":[
        "Fonte"
    ],
    "name:vol_x_preferred":[
        "Fonte"
    ],
    "name:war_x_preferred":[
        "Fonte"
    ],
    "wof:name":"Fonte",
    "wof:placetype":"locality",
    "wof:population":46
},
  "geometry": {"coordinates":[10.10852,45.61668],"type":"Point"}
}