{
  "type": "Feature",
  "properties": {
    "iso:country":"IT",
    "name:dut_x_preferred":[
        "Colonnata"
    ],
    "name:eng_x_preferred":[
        "Colonnata"
    ],
    "name:fre_x_preferred":[
        "Colonnata"
    ],
    "name:ger_x_preferred":[
        "Colonnata"
    ],
    "name:hun_x_preferred":[
        "Colonnata"
    ],
    "name:ita_x_preferred":[
        "Colonnata"
    ],
    "name:jpn_x_preferred":[
        "\u30b3\u30ed\u30f3\u30ca\u30fc\u30bf"
    ],
    "name:srp_x_preferred":[
        "Colonnata"
    ],
    "qs_pg:aaroncc":"IT",
    "qs_pg:name":"Colonnata",
    "qs_pg:name_adm0":"Italia",
    "qs_pg:name_adm1":"Toscana",
    "qs_pg:photos":219,
    "qs_pg:photos_1k":44,
    "qs_pg:photos_9k":1,
    "qs_pg:photos_9r":4,
    "qs_pg:photos_all":219,
    "qs_pg:photos_sr":4,
    "qs_pg:pop_sr":0,
    "qs_pg:qs_pg_placetype":"locality",
    "qs_pg:qs_pg_placetype_gp":"Town",
    "qs_pg:woe_adm0":23424853,
    "woe:adm0_id":23424853,
    "woe:name_adm0":"Italia",
    "woe:name_adm1":"Toscana",
    "woe:placetype":"Town",
    "wof:name":"Colonnata",
    "wof:placetype":"locality"
},
  "geometry": {"coordinates":[10.154159,44.085735],"type":"Point"}
}