{
  "type": "Feature",
  "properties": {
    "gn:admin1_code":"12.0",
    "gn:admin2_code":"AL",
    "gn:admin3_code":"6073.0",
    "gn:asciiname":"Frassineto Po",
    "gn:country_code":"IT",
    "gn:dem":106,
    "gn:elevation":"104.0",
    "gn:feature_class":"P",
    "gn:feature_code":"PPLA3",
    "gn:name":"Frassineto Po",
    "gn:population":1357,
    "gn:timezone":"Europe/Rome",
    "iso:country":"IT",
    "name:deu_x_preferred":[
        "Frassineto Po"
    ],
    "name:eng_x_preferred":[
        "Frassineto Po"
    ],
    "name:epo_x_preferred":[
        "Frassineto Po"
    ],
    "name:fra_x_preferred":[
        "Frassineto Po"
    ],
    "name:ita_x_preferred":[
        "Frassineto Po"
    ],
    "name:nap_x_preferred":[
        "Frassineto Po"
    ],
    "name:nld_x_preferred":[
        "Frassineto Po"
    ],
    "name:pol_x_preferred":[
        "Frassineto Po"
    ],
    "name:por_x_preferred":[
        "Frassineto Po"
    ],
    "wof:name":"Frassineto Po",
    "wof:placetype":"locality",
    "wof:population":1357
},
  "geometry": {"coordinates":[8.53525,45.13271],"type":"Point"}
}