{
  "type": "Feature",
  "properties": {
    "gn:admin1_code":"20",
    "gn:admin2_code":"TV",
    "gn:admin3_code":"26066.0",
    "gn:asciiname":"Santa Brigida",
    "gn:country_code":"IT",
    "gn:dem":28,
    "gn:feature_class":"P",
    "gn:feature_code":"PPL",
    "gn:name":"Santa Brigida",
    "gn:population":71,
    "gn:timezone":"Europe/Rome",
    "iso:country":"IT",
    "wof:name":"Santa Brigida",
    "wof:placetype":"locality",
    "wof:population":71
},
  "geometry": {"coordinates":[11.99586,45.63601],"type":"Point"}
}