{
  "type": "Feature",
  "properties": {
    "gn:admin1_code":"4",
    "gn:admin2_code":"AV",
    "gn:admin3_code":"64032.0",
    "gn:asciiname":"Candelaro",
    "gn:country_code":"IT",
    "gn:dem":593,
    "gn:feature_class":"P",
    "gn:feature_code":"PPL",
    "gn:name":"Candelaro",
    "gn:population":65,
    "gn:timezone":"Europe/Rome",
    "iso:country":"IT",
    "wof:name":"Candelaro",
    "wof:placetype":"locality",
    "wof:population":65
},
  "geometry": {"coordinates":[15.16336,41.06897],"type":"Point"}
}