{
  "type": "Feature",
  "properties": {
    "gn:admin1_code":"18.0",
    "gn:admin2_code":"TR",
    "gn:admin3_code":"55022.0",
    "gn:asciiname":"Zona Industriale San Liberato",
    "gn:country_code":"IT",
    "gn:dem":77,
    "gn:feature_class":"P",
    "gn:feature_code":"PPL",
    "gn:name":"Zona Industriale San Liberato",
    "gn:population":0,
    "gn:timezone":"Europe/Rome",
    "iso:country":"IT",
    "wof:name":"Zona Industriale San Liberato",
    "wof:placetype":"locality"
},
  "geometry": {"coordinates":[12.45024,42.48226],"type":"Point"}
}