{
  "type": "Feature",
  "properties": {
    "gn:admin1_code":"7.0",
    "gn:admin2_code":"RI",
    "gn:admin3_code":"57002.0",
    "gn:asciiname":"Pinaco Arafranca",
    "gn:country_code":"IT",
    "gn:dem":1001,
    "gn:feature_class":"P",
    "gn:feature_code":"PPL",
    "gn:name":"Pinaco Arafranca",
    "gn:population":0,
    "gn:timezone":"Europe/Rome",
    "iso:country":"IT",
    "wof:name":"Pinaco Arafranca",
    "wof:placetype":"locality"
},
  "geometry": {"coordinates":[13.29749,42.60538],"type":"Point"}
}