{
  "type": "Feature",
  "properties": {
    "gn:admin1_code":"5",
    "gn:admin2_code":"RE",
    "gn:admin3_code":"35033.0",
    "gn:asciiname":"Castel Baldo",
    "gn:country_code":"IT",
    "gn:dem":89,
    "gn:feature_class":"P",
    "gn:feature_code":"PPL",
    "gn:name":"Castel Baldo",
    "gn:population":55,
    "gn:timezone":"Europe/Rome",
    "iso:country":"IT",
    "wof:name":"Castel Baldo",
    "wof:placetype":"locality",
    "wof:population":55
},
  "geometry": {"coordinates":[10.56811,44.67189000000001],"type":"Point"}
}