{
  "type": "Feature",
  "properties": {
    "gn:admin1_code":"12",
    "gn:admin2_code":"CN",
    "gn:admin3_code":"4241.0",
    "gn:asciiname":"Socco Madernassa",
    "gn:country_code":"IT",
    "gn:dem":279,
    "gn:feature_class":"P",
    "gn:feature_code":"PPL",
    "gn:name":"Socco Madernassa",
    "gn:population":80,
    "gn:timezone":"Europe/Rome",
    "iso:country":"IT",
    "wof:name":"Socco Madernassa",
    "wof:placetype":"locality",
    "wof:population":80
},
  "geometry": {"coordinates":[8.01493,44.75049],"type":"Point"}
}