{
  "type": "Feature",
  "properties": {
    "gn:admin1_code":"16",
    "gn:admin2_code":"SI",
    "gn:admin3_code":"52033.0",
    "gn:asciiname":"Scrofiano",
    "gn:country_code":"IT",
    "gn:dem":357,
    "gn:feature_class":"P",
    "gn:feature_code":"PPL",
    "gn:name":"Scrofiano",
    "gn:population":247,
    "gn:timezone":"Europe/Rome",
    "iso:country":"IT",
    "name:ceb_x_preferred":[
        "Scrofiano"
    ],
    "name:deu_x_preferred":[
        "Scrofiano"
    ],
    "name:ita_x_preferred":[
        "Scrofiano"
    ],
    "name:nld_x_preferred":[
        "Scrofiano"
    ],
    "name:srp_x_preferred":[
        "\u0421\u043a\u0440\u043e\u0444\u0438\u0458\u0430\u043d\u043e"
    ],
    "wof:name":"Scrofiano",
    "wof:placetype":"locality",
    "wof:population":247
},
  "geometry": {"coordinates":[11.71478,43.23053],"type":"Point"}
}