{
  "type": "Feature",
  "properties": {
    "gn:admin1_code":"16",
    "gn:admin2_code":"SI",
    "gn:admin3_code":"52033.0",
    "gn:asciiname":"Scrofiano",
    "gn:country_code":"IT",
    "gn:dem":357,
    "gn:feature_class":"P",
    "gn:feature_code":"PPL",
    "gn:name":"Scrofiano",
    "gn:population":247,
    "gn:timezone":"Europe/Rome",
    "iso:country":"IT",
    "wof:name":"Scrofiano",
    "wof:placetype":"locality",
    "wof:population":247
},
  "geometry": {"coordinates":[11.71478,43.23053],"type":"Point"}
}