{
  "type": "Feature",
  "properties": {
    "gn:admin1_code":"16",
    "gn:admin2_code":"AR",
    "gn:admin3_code":"51012.0",
    "gn:asciiname":"Cappella Brocchi",
    "gn:country_code":"IT",
    "gn:dem":251,
    "gn:feature_class":"P",
    "gn:feature_code":"PPL",
    "gn:name":"Cappella Brocchi",
    "gn:population":60,
    "gn:timezone":"Europe/Rome",
    "iso:country":"IT",
    "wof:name":"Cappella Brocchi",
    "wof:placetype":"locality",
    "wof:population":60
},
  "geometry": {"coordinates":[11.90823,43.32691],"type":"Point"}
}