{
  "type": "Feature",
  "properties": {
    "gn:admin1_code":"16.0",
    "gn:admin2_code":"GR",
    "gn:admin3_code":"53017.0",
    "gn:asciiname":"Travale",
    "gn:country_code":"IT",
    "gn:dem":503,
    "gn:elevation":"520.0",
    "gn:feature_class":"P",
    "gn:feature_code":"PPL",
    "gn:name":"Travale",
    "gn:population":84,
    "gn:timezone":"Europe/Rome",
    "iso:country":"IT",
    "name:azb_x_preferred":[
        "\u062a\u0631\u0627\u0648\u0627\u0644\u0647"
    ],
    "name:fas_x_preferred":[
        "\u062a\u0631\u0627\u0648\u0627\u0644\u0647"
    ],
    "name:ita_x_preferred":[
        "Travale"
    ],
    "name:nld_x_preferred":[
        "Travale"
    ],
    "name:srp_x_preferred":[
        "\u0422\u0440\u0430\u0432\u0430\u043b\u0435"
    ],
    "wof:name":"Travale",
    "wof:placetype":"locality",
    "wof:population":84
},
  "geometry": {"coordinates":[11.00982,43.16719000000001],"type":"Point"}
}