{
  "type": "Feature",
  "properties": {
    "gn:admin1_code":"8",
    "gn:admin2_code":"SV",
    "gn:admin3_code":"9048.0",
    "gn:asciiname":"Gorra",
    "gn:country_code":"IT",
    "gn:dem":649,
    "gn:feature_class":"P",
    "gn:feature_code":"PPL",
    "gn:name":"Gorra",
    "gn:population":15,
    "gn:timezone":"Europe/Rome",
    "iso:country":"IT",
    "wof:name":"Gorra",
    "wof:placetype":"locality",
    "wof:population":15
},
  "geometry": {"coordinates":[8.2266,44.49448],"type":"Point"}
}