{
  "type": "Feature",
  "properties": {
    "gn:admin1_code":"7.0",
    "gn:admin2_code":"FR",
    "gn:admin3_code":"60060.0",
    "gn:asciiname":"Caprile",
    "gn:country_code":"IT",
    "gn:dem":253,
    "gn:feature_class":"P",
    "gn:feature_code":"PPL",
    "gn:name":"Caprile",
    "gn:population":103,
    "gn:timezone":"Europe/Rome",
    "iso:country":"IT",
    "name:ara_x_preferred":[
        "\u0643\u0627\u0628\u0631\u064a\u0644\u064a"
    ],
    "name:azb_x_preferred":[
        "\u06a9\u0627\u067e\u0631\u06cc\u0644\u0647"
    ],
    "name:bel_x_preferred":[
        "\u041a\u0430\u043f\u0440\u044b\u043b\u0435"
    ],
    "name:bul_x_preferred":[
        "\u041a\u0430\u043f\u0440\u0438\u043b\u0435"
    ],
    "name:ceb_x_preferred":[
        "Caprile"
    ],
    "name:dan_x_preferred":[
        "Caprile"
    ],
    "name:deu_x_preferred":[
        "Caprile"
    ],
    "name:epo_x_preferred":[
        "Caprile"
    ],
    "name:eus_x_preferred":[
        "Caprile"
    ],
    "name:fas_x_preferred":[
        "\u06a9\u0627\u067e\u0631\u06cc\u0644\u0647"
    ],
    "name:fra_x_preferred":[
        "Caprile"
    ],
    "name:hun_x_preferred":[
        "Caprile"
    ],
    "name:hye_x_preferred":[
        "\u053f\u0561\u057a\u0580\u056b\u056c\u0565"
    ],
    "name:ind_x_preferred":[
        "Caprile"
    ],
    "name:ita_x_preferred":[
        "Caprile"
    ],
    "name:jpn_x_preferred":[
        "\u30ab\u30d7\u30ea\u30fc\u30ec"
    ],
    "name:kaz_x_preferred":[
        "\u041a\u0430\u043f\u0440\u0438\u043b\u0435"
    ],
    "name:lat_x_preferred":[
        "Cavrili"
    ],
    "name:lmo_x_preferred":[
        "Caprile"
    ],
    "name:msa_x_preferred":[
        "Caprile"
    ],
    "name:nap_x_preferred":[
        "Caprile"
    ],
    "name:nld_x_preferred":[
        "Caprile"
    ],
    "name:pms_x_preferred":[
        "Cravin"
    ],
    "name:pol_x_preferred":[
        "Caprile"
    ],
    "name:por_x_preferred":[
        "Caprile"
    ],
    "name:ron_x_preferred":[
        "Caprile"
    ],
    "name:rus_x_preferred":[
        "\u041a\u0430\u043f\u0440\u0438\u043b\u0435"
    ],
    "name:scn_x_preferred":[
        "Caprile"
    ],
    "name:spa_x_preferred":[
        "Caprile"
    ],
    "name:tgl_x_preferred":[
        "Caprile"
    ],
    "name:ukr_x_preferred":[
        "\u041a\u0430\u043f\u0440\u0438\u043b\u0435"
    ],
    "name:uzb_x_preferred":[
        "Caprile"
    ],
    "name:vie_x_preferred":[
        "Caprile"
    ],
    "name:vol_x_preferred":[
        "Caprile"
    ],
    "name:war_x_preferred":[
        "Caprile"
    ],
    "name:zho_x_preferred":[
        "\u5361\u666e\u91cc\u83b1"
    ],
    "wof:name":"Caprile",
    "wof:placetype":"locality",
    "wof:population":103
},
  "geometry": {"coordinates":[13.67791,41.5438],"type":"Point"}
}