{
  "type": "Feature",
  "properties": {
    "gn:admin1_code":"7.0",
    "gn:admin2_code":"FR",
    "gn:admin3_code":"60060.0",
    "gn:asciiname":"Caprile",
    "gn:country_code":"IT",
    "gn:dem":253,
    "gn:feature_class":"P",
    "gn:feature_code":"PPL",
    "gn:name":"Caprile",
    "gn:population":103,
    "gn:timezone":"Europe/Rome",
    "iso:country":"IT",
    "wof:name":"Caprile",
    "wof:placetype":"locality",
    "wof:population":103
},
  "geometry": {"coordinates":[13.67791,41.5438],"type":"Point"}
}