{
  "type": "Feature",
  "properties": {
    "gn:admin1_code":"13.0",
    "gn:admin2_code":"BA",
    "gn:admin3_code":"72016.0",
    "gn:asciiname":"Borgo Incoronata-Lagogemolo",
    "gn:country_code":"IT",
    "gn:dem":400,
    "gn:feature_class":"P",
    "gn:feature_code":"PPL",
    "gn:name":"Borgo Incoronata-Lagogemolo",
    "gn:population":496,
    "gn:timezone":"Europe/Rome",
    "iso:country":"IT",
    "wof:name":"Borgo Incoronata-Lagogemolo",
    "wof:placetype":"locality",
    "wof:population":496
},
  "geometry": {"coordinates":[16.71245,40.89443],"type":"Point"}
}