{
  "type": "Feature",
  "properties": {
    "gn:admin1_code":"8.0",
    "gn:admin2_code":"SP",
    "gn:admin3_code":"11027.0",
    "gn:asciiname":"Area Intermarine",
    "gn:country_code":"IT",
    "gn:dem":3,
    "gn:feature_class":"P",
    "gn:feature_code":"PPLL",
    "gn:name":"Area Intermarine",
    "gn:population":0,
    "gn:timezone":"Europe/Rome",
    "iso:country":"IT",
    "wof:name":"Area Intermarine",
    "wof:placetype":"locality"
},
  "geometry": {"coordinates":[9.98077,44.07265],"type":"Point"}
}