{
  "type": "Feature",
  "properties": {
    "gn:admin1_code":"20",
    "gn:admin2_code":"VR",
    "gn:admin3_code":"23066.0",
    "gn:asciiname":"Roversello",
    "gn:country_code":"IT",
    "gn:dem":14,
    "gn:feature_class":"P",
    "gn:feature_code":"PPL",
    "gn:name":"Roversello",
    "gn:population":19,
    "gn:timezone":"Europe/Rome",
    "iso:country":"IT",
    "wof:name":"Roversello",
    "wof:placetype":"locality",
    "wof:population":19
},
  "geometry": {"coordinates":[11.45361,45.27425],"type":"Point"}
}