{
  "type": "Feature",
  "properties": {
    "gn:admin1_code":"20",
    "gn:admin2_code":"VR",
    "gn:admin3_code":"23052.0",
    "gn:asciiname":"Provale",
    "gn:country_code":"IT",
    "gn:dem":508,
    "gn:feature_class":"P",
    "gn:feature_code":"PPL",
    "gn:name":"Provale",
    "gn:population":68,
    "gn:timezone":"Europe/Rome",
    "iso:country":"IT",
    "wof:name":"Provale",
    "wof:placetype":"locality",
    "wof:population":68
},
  "geometry": {"coordinates":[10.95733,45.56898],"type":"Point"}
}