{
  "type": "Feature",
  "properties": {
    "gn:admin1_code":"17",
    "gn:admin2_code":"BZ",
    "gn:admin3_code":"21070.0",
    "gn:asciiname":"Caspineto",
    "gn:country_code":"IT",
    "gn:dem":1465,
    "gn:feature_class":"P",
    "gn:feature_code":"PPLL",
    "gn:name":"Caspineto",
    "gn:population":10,
    "gn:timezone":"Europe/Rome",
    "iso:country":"IT",
    "wof:name":"Caspineto",
    "wof:placetype":"locality",
    "wof:population":10
},
  "geometry": {"coordinates":[11.4182,46.86285],"type":"Point"}
}