{
  "type": "Feature",
  "properties": {
    "gn:admin1_code":"20",
    "gn:admin2_code":"BL",
    "gn:admin3_code":"25061.0",
    "gn:asciiname":"Cavaril",
    "gn:country_code":"IT",
    "gn:dem":645,
    "gn:feature_class":"P",
    "gn:feature_code":"PPL",
    "gn:name":"Cavaril",
    "gn:population":19,
    "gn:timezone":"Europe/Rome",
    "iso:country":"IT",
    "wof:name":"Cavaril",
    "wof:placetype":"locality",
    "wof:population":19
},
  "geometry": {"coordinates":[12.17495,46.04097],"type":"Point"}
}