{
  "type": "Feature",
  "properties": {
    "gn:admin1_code":"14.0",
    "gn:admin2_code":"NU",
    "gn:admin3_code":"91026.0",
    "gn:asciiname":"Marina di Gairo",
    "gn:country_code":"IT",
    "gn:dem":20,
    "gn:feature_class":"P",
    "gn:feature_code":"PPL",
    "gn:name":"Marina di Gairo",
    "gn:population":0,
    "gn:timezone":"Europe/Rome",
    "iso:country":"IT",
    "wof:name":"Marina di Gairo",
    "wof:placetype":"locality"
},
  "geometry": {"coordinates":[9.67449,39.74217],"type":"Point"}
}