{
  "type": "Feature",
  "properties": {
    "gn:admin1_code":"12.0",
    "gn:admin2_code":"AL",
    "gn:admin3_code":"6146.0",
    "gn:asciiname":"Borassi",
    "gn:country_code":"IT",
    "gn:dem":668,
    "gn:feature_class":"P",
    "gn:feature_code":"PPL",
    "gn:name":"Borassi",
    "gn:population":51,
    "gn:timezone":"Europe/Rome",
    "iso:country":"IT",
    "wof:name":"Borassi",
    "wof:placetype":"locality",
    "wof:population":51
},
  "geometry": {"coordinates":[9.03068,44.66591],"type":"Point"}
}