{
  "type": "Feature",
  "properties": {
    "gn:admin1_code":"6.0",
    "gn:admin2_code":"UD",
    "gn:admin3_code":"30029.0",
    "gn:asciiname":"Tualis",
    "gn:country_code":"IT",
    "gn:dem":875,
    "gn:elevation":"918.0",
    "gn:feature_class":"P",
    "gn:feature_code":"PPL",
    "gn:name":"Tualis",
    "gn:population":153,
    "gn:timezone":"Europe/Rome",
    "iso:country":"IT",
    "wof:name":"Tualis",
    "wof:placetype":"locality",
    "wof:population":153
},
  "geometry": {"coordinates":[12.88005,46.53256],"type":"Point"}
}