{
  "type": "Feature",
  "properties": {
    "gn:admin1_code":"5",
    "gn:admin2_code":"BO",
    "gn:admin3_code":"37028.0",
    "gn:asciiname":"La Bisana",
    "gn:country_code":"IT",
    "gn:dem":13,
    "gn:feature_class":"P",
    "gn:feature_code":"PPL",
    "gn:name":"La Bisana",
    "gn:population":15,
    "gn:timezone":"Europe/Rome",
    "iso:country":"IT",
    "wof:name":"La Bisana",
    "wof:placetype":"locality",
    "wof:population":15
},
  "geometry": {"coordinates":[11.39326,44.77104],"type":"Point"}
}