{
  "type": "Feature",
  "properties": {
    "gn:admin1_code":"4",
    "gn:admin2_code":"BN",
    "gn:admin3_code":"62044.0",
    "gn:asciiname":"Colle",
    "gn:country_code":"IT",
    "gn:dem":687,
    "gn:feature_class":"P",
    "gn:feature_code":"PPL",
    "gn:name":"Colle",
    "gn:population":19,
    "gn:timezone":"Europe/Rome",
    "iso:country":"IT",
    "name:ceb_x_preferred":[
        "Colle"
    ],
    "name:deu_x_preferred":[
        "Colle"
    ],
    "name:fra_x_preferred":[
        "Colle"
    ],
    "name:ita_x_preferred":[
        "Colle"
    ],
    "name:nld_x_preferred":[
        "Colle"
    ],
    "name:por_x_preferred":[
        "Colle"
    ],
    "name:swe_x_preferred":[
        "Colle"
    ],
    "wof:name":"Colle",
    "wof:placetype":"locality",
    "wof:population":19
},
  "geometry": {"coordinates":[14.68418,41.40595],"type":"Point"}
}