{
  "type": "Feature",
  "properties": {
    "gn:admin1_code":"4.0",
    "gn:admin2_code":"CE",
    "gn:admin3_code":"61048.0",
    "gn:asciiname":"Maddaloni Superiore",
    "gn:country_code":"IT",
    "gn:dem":151,
    "gn:feature_class":"P",
    "gn:feature_code":"PPL",
    "gn:name":"Maddaloni Superiore",
    "gn:population":36,
    "gn:timezone":"Europe/Rome",
    "iso:country":"IT",
    "wof:name":"Maddaloni Superiore",
    "wof:placetype":"locality",
    "wof:population":36
},
  "geometry": {"coordinates":[14.39646,41.05203],"type":"Point"}
}