{
  "type": "Feature",
  "properties": {
    "gn:admin1_code":"11",
    "gn:admin2_code":"CB",
    "gn:admin3_code":"70067.0",
    "gn:asciiname":"Fontana Cappella",
    "gn:country_code":"IT",
    "gn:dem":656,
    "gn:feature_class":"P",
    "gn:feature_code":"PPL",
    "gn:name":"Fontana Cappella",
    "gn:population":26,
    "gn:timezone":"Europe/Rome",
    "iso:country":"IT",
    "wof:name":"Fontana Cappella",
    "wof:placetype":"locality",
    "wof:population":26
},
  "geometry": {"coordinates":[14.62392,41.46479],"type":"Point"}
}