{
  "type": "Feature",
  "properties": {
    "gn:admin1_code":"4",
    "gn:admin2_code":"BN",
    "gn:admin3_code":"62012.0",
    "gn:asciiname":"Bosco Sant'Agnese",
    "gn:country_code":"IT",
    "gn:dem":262,
    "gn:feature_class":"P",
    "gn:feature_code":"PPL",
    "gn:name":"Bosco Sant'Agnese",
    "gn:population":25,
    "gn:timezone":"Europe/Rome",
    "iso:country":"IT",
    "wof:name":"Bosco Sant'Agnese",
    "wof:placetype":"locality",
    "wof:population":25
},
  "geometry": {"coordinates":[14.90032,41.08077],"type":"Point"}
}