{
  "type": "Feature",
  "properties": {
    "gn:admin1_code":"9",
    "gn:admin2_code":"LC",
    "gn:admin3_code":"97036.0",
    "gn:asciiname":"Le Terrazze",
    "gn:country_code":"IT",
    "gn:dem":517,
    "gn:feature_class":"P",
    "gn:feature_code":"PPL",
    "gn:name":"Le Terrazze",
    "gn:population":34,
    "gn:timezone":"Europe/Rome",
    "iso:country":"IT",
    "wof:name":"Le Terrazze",
    "wof:placetype":"locality",
    "wof:population":34
},
  "geometry": {"coordinates":[9.39094,45.80345],"type":"Point"}
}