{
  "type": "Feature",
  "properties": {
    "gn:admin1_code":"20",
    "gn:admin2_code":"VR",
    "gn:admin3_code":"23086.0",
    "gn:asciiname":"Le Camille",
    "gn:country_code":"IT",
    "gn:dem":541,
    "gn:feature_class":"P",
    "gn:feature_code":"PPL",
    "gn:name":"Le Camille",
    "gn:population":20,
    "gn:timezone":"Europe/Rome",
    "iso:country":"IT",
    "wof:name":"Le Camille",
    "wof:placetype":"locality",
    "wof:population":20
},
  "geometry": {"coordinates":[10.71831,45.62783],"type":"Point"}
}