{
  "type": "Feature",
  "properties": {
    "gn:admin1_code":"20",
    "gn:admin2_code":"TV",
    "gn:admin3_code":"26036.0",
    "gn:asciiname":"Case Marin",
    "gn:country_code":"IT",
    "gn:dem":74,
    "gn:feature_class":"P",
    "gn:feature_code":"PPL",
    "gn:name":"Case Marin",
    "gn:population":64,
    "gn:timezone":"Europe/Rome",
    "iso:country":"IT",
    "wof:name":"Case Marin",
    "wof:placetype":"locality",
    "wof:population":64
},
  "geometry": {"coordinates":[11.82852,45.7205],"type":"Point"}
}