{
  "type": "Feature",
  "properties": {
    "gn:admin1_code":"17.0",
    "gn:admin2_code":"BZ",
    "gn:admin3_code":"21088.0",
    "gn:asciiname":"Lappago di Sotto",
    "gn:country_code":"IT",
    "gn:dem":1277,
    "gn:feature_class":"P",
    "gn:feature_code":"PPL",
    "gn:name":"Lappago di Sotto",
    "gn:population":48,
    "gn:timezone":"Europe/Rome",
    "iso:country":"IT",
    "wof:name":"Lappago di Sotto",
    "wof:placetype":"locality",
    "wof:population":48
},
  "geometry": {"coordinates":[11.81441,46.90349000000001],"type":"Point"}
}