{
  "type": "Feature",
  "properties": {
    "gn:admin1_code":"16.0",
    "gn:admin2_code":"LU",
    "gn:admin3_code":"46002.0",
    "gn:asciiname":"Lugnano-Monti di Villa",
    "gn:country_code":"IT",
    "gn:dem":590,
    "gn:feature_class":"P",
    "gn:feature_code":"PPL",
    "gn:name":"Lugnano-Monti di Villa",
    "gn:population":58,
    "gn:timezone":"Europe/Rome",
    "iso:country":"IT",
    "wof:name":"Lugnano-Monti di Villa",
    "wof:placetype":"locality",
    "wof:population":58
},
  "geometry": {"coordinates":[10.57616,44.03477],"type":"Point"}
}