{
  "type": "Feature",
  "properties": {
    "gn:admin1_code":"7.0",
    "gn:admin2_code":"RM",
    "gn:admin3_code":"58034.0",
    "gn:asciiname":"Via Latina Iv Km",
    "gn:country_code":"IT",
    "gn:dem":233,
    "gn:feature_class":"P",
    "gn:feature_code":"PPL",
    "gn:name":"Via Latina Iv Km",
    "gn:population":755,
    "gn:timezone":"Europe/Rome",
    "iso:country":"IT",
    "wof:name":"Via Latina Iv Km",
    "wof:placetype":"locality",
    "wof:population":755
},
  "geometry": {"coordinates":[12.96163,41.73507],"type":"Point"}
}