{
  "type": "Feature",
  "properties": {
    "gn:admin1_code":"12",
    "gn:admin2_code":"CN",
    "gn:admin3_code":"4107.0",
    "gn:asciiname":"Costamagna",
    "gn:country_code":"IT",
    "gn:dem":339,
    "gn:feature_class":"P",
    "gn:feature_code":"PPL",
    "gn:name":"Costamagna",
    "gn:population":89,
    "gn:timezone":"Europe/Rome",
    "iso:country":"IT",
    "wof:name":"Costamagna",
    "wof:placetype":"locality",
    "wof:population":89
},
  "geometry": {"coordinates":[7.88507,44.54089000000001],"type":"Point"}
}