{
  "type": "Feature",
  "properties": {
    "gn:admin1_code":"20.0",
    "gn:admin2_code":"VR",
    "gn:admin3_code":"23087.0",
    "gn:asciiname":"Cogollo",
    "gn:country_code":"IT",
    "gn:dem":408,
    "gn:feature_class":"P",
    "gn:feature_code":"PPL",
    "gn:name":"Cogollo",
    "gn:population":583,
    "gn:timezone":"Europe/Rome",
    "iso:country":"IT",
    "wof:name":"Cogollo",
    "wof:placetype":"locality",
    "wof:population":583
},
  "geometry": {"coordinates":[11.15649,45.54585],"type":"Point"}
}