{
  "type": "Feature",
  "properties": {
    "gn:admin1_code":"12",
    "gn:admin2_code":"AL",
    "gn:admin3_code":"6136.0",
    "gn:asciiname":"Bric Berton",
    "gn:country_code":"IT",
    "gn:dem":732,
    "gn:feature_class":"P",
    "gn:feature_code":"PPL",
    "gn:name":"Bric Berton",
    "gn:population":22,
    "gn:timezone":"Europe/Rome",
    "iso:country":"IT",
    "wof:name":"Bric Berton",
    "wof:placetype":"locality",
    "wof:population":22
},
  "geometry": {"coordinates":[8.52936,44.51938],"type":"Point"}
}