{
  "type": "Feature",
  "properties": {
    "gn:admin1_code":"1.0",
    "gn:admin2_code":"CH",
    "gn:admin3_code":"69075.0",
    "gn:asciiname":"Macchie",
    "gn:country_code":"IT",
    "gn:dem":385,
    "gn:feature_class":"P",
    "gn:feature_code":"PPL",
    "gn:name":"Macchie",
    "gn:population":36,
    "gn:timezone":"Europe/Rome",
    "iso:country":"IT",
    "wof:name":"Macchie",
    "wof:placetype":"locality",
    "wof:population":36
},
  "geometry": {"coordinates":[14.31454,42.08126],"type":"Point"}
}