{
  "type": "Feature",
  "properties": {
    "gn:admin1_code":"5",
    "gn:admin2_code":"PC",
    "gn:admin3_code":"33019.0",
    "gn:asciiname":"Bruzzetti",
    "gn:country_code":"IT",
    "gn:dem":925,
    "gn:feature_class":"P",
    "gn:feature_code":"PPL",
    "gn:name":"Bruzzetti",
    "gn:population":19,
    "gn:timezone":"Europe/Rome",
    "iso:country":"IT",
    "wof:name":"Bruzzetti",
    "wof:placetype":"locality",
    "wof:population":19
},
  "geometry": {"coordinates":[9.60949,44.70858],"type":"Point"}
}