{
  "type": "Feature",
  "properties": {
    "gn:admin1_code":"1",
    "gn:admin2_code":"PE",
    "gn:admin3_code":"68041.0",
    "gn:asciiname":"Case Trufulone",
    "gn:country_code":"IT",
    "gn:dem":111,
    "gn:feature_class":"P",
    "gn:feature_code":"PPL",
    "gn:name":"Case Trufulone",
    "gn:population":34,
    "gn:timezone":"Europe/Rome",
    "iso:country":"IT",
    "wof:name":"Case Trufulone",
    "wof:placetype":"locality",
    "wof:population":34
},
  "geometry": {"coordinates":[14.15005,42.45582],"type":"Point"}
}