{
  "type": "Feature",
  "properties": {
    "gn:admin1_code":"12",
    "gn:admin2_code":"CN",
    "gn:admin3_code":"4155.0",
    "gn:asciiname":"Cantarana",
    "gn:country_code":"IT",
    "gn:dem":783,
    "gn:feature_class":"P",
    "gn:feature_code":"PPL",
    "gn:name":"Cantarana",
    "gn:population":16,
    "gn:timezone":"Europe/Rome",
    "iso:country":"IT",
    "wof:name":"Cantarana",
    "wof:placetype":"locality",
    "wof:population":16
},
  "geometry": {"coordinates":[7.89227,44.122],"type":"Point"}
}