{
  "type": "Feature",
  "properties": {
    "gn:admin1_code":"20.0",
    "gn:admin2_code":"VR",
    "gn:admin3_code":"23054.0",
    "gn:asciiname":"Zona Agro-Industriale Capoluogo",
    "gn:country_code":"IT",
    "gn:dem":33,
    "gn:feature_class":"P",
    "gn:feature_code":"PPLL",
    "gn:name":"Zona Agro-Industriale Capoluogo",
    "gn:population":0,
    "gn:timezone":"Europe/Rome",
    "iso:country":"IT",
    "wof:name":"Zona Agro-Industriale Capoluogo",
    "wof:placetype":"locality"
},
  "geometry": {"coordinates":[10.90376,45.29929],"type":"Point"}
}