{
  "type": "Feature",
  "properties": {
    "gn:admin1_code":"7",
    "gn:admin2_code":"FR",
    "gn:admin3_code":"60013.0",
    "gn:asciiname":"Vaccareccia",
    "gn:country_code":"IT",
    "gn:dem":489,
    "gn:feature_class":"P",
    "gn:feature_code":"PPL",
    "gn:name":"Vaccareccia",
    "gn:population":15,
    "gn:timezone":"Europe/Rome",
    "iso:country":"IT",
    "wof:name":"Vaccareccia",
    "wof:placetype":"locality",
    "wof:population":15
},
  "geometry": {"coordinates":[13.80098,41.59084],"type":"Point"}
}