{
  "type": "Feature",
  "properties": {
    "gn:admin1_code":"8.0",
    "gn:admin2_code":"SV",
    "gn:admin3_code":"9015.0",
    "gn:asciiname":"Montenotte Superiore",
    "gn:country_code":"IT",
    "gn:dem":658,
    "gn:feature_class":"P",
    "gn:feature_code":"PPL",
    "gn:name":"Montenotte Superiore",
    "gn:population":48,
    "gn:timezone":"Europe/Rome",
    "iso:country":"IT",
    "wof:name":"Montenotte Superiore",
    "wof:placetype":"locality",
    "wof:population":48
},
  "geometry": {"coordinates":[8.40052,44.38838],"type":"Point"}
}