{
  "type": "Feature",
  "properties": {
    "gn:admin1_code":"12",
    "gn:admin2_code":"TO",
    "gn:admin3_code":"1085.0",
    "gn:asciiname":"Torrazza",
    "gn:country_code":"IT",
    "gn:dem":412,
    "gn:feature_class":"P",
    "gn:feature_code":"PPL",
    "gn:name":"Torrazza",
    "gn:population":27,
    "gn:timezone":"Europe/Rome",
    "iso:country":"IT",
    "name:ceb_x_preferred":[
        "Torrazza"
    ],
    "name:ita_x_preferred":[
        "Torrazza"
    ],
    "name:srp_x_preferred":[
        "Toraca"
    ],
    "name:swe_x_preferred":[
        "Torrazza"
    ],
    "wof:name":"Torrazza",
    "wof:placetype":"locality",
    "wof:population":27
},
  "geometry": {"coordinates":[7.93198,45.0855],"type":"Point"}
}