{
  "type": "Feature",
  "properties": {
    "gn:admin1_code":"1",
    "gn:admin2_code":"CH",
    "gn:admin3_code":"69039.0",
    "gn:asciiname":"Casale Conicella",
    "gn:country_code":"IT",
    "gn:dem":956,
    "gn:feature_class":"P",
    "gn:feature_code":"PPL",
    "gn:name":"Casale Conicella",
    "gn:population":36,
    "gn:timezone":"Europe/Rome",
    "iso:country":"IT",
    "wof:name":"Casale Conicella",
    "wof:placetype":"locality",
    "wof:population":36
},
  "geometry": {"coordinates":[14.22686,41.89416],"type":"Point"}
}