{
  "type": "Feature",
  "properties": {
    "gn:admin1_code":"15.0",
    "gn:admin2_code":"TP",
    "gn:admin3_code":"81005.0",
    "gn:asciiname":"Case Di Bartolo",
    "gn:country_code":"IT",
    "gn:dem":117,
    "gn:feature_class":"P",
    "gn:feature_code":"PPL",
    "gn:name":"Case Di Bartolo",
    "gn:population":5,
    "gn:timezone":"Europe/Rome",
    "iso:country":"IT",
    "wof:name":"Case Di Bartolo",
    "wof:placetype":"locality",
    "wof:population":5
},
  "geometry": {"coordinates":[12.85122,38.035],"type":"Point"}
}