{
  "type": "Feature",
  "properties": {
    "gn:admin1_code":"5.0",
    "gn:admin2_code":"RN",
    "gn:admin3_code":"99002.0",
    "gn:asciiname":"Misano Marina",
    "gn:country_code":"IT",
    "gn:dem":1,
    "gn:feature_class":"P",
    "gn:feature_code":"PPL",
    "gn:name":"Misano Marina",
    "gn:population":0,
    "gn:timezone":"Europe/Rome",
    "iso:country":"IT",
    "wof:name":"Misano Marina",
    "wof:placetype":"locality"
},
  "geometry": {"coordinates":[12.71667,43.96667],"type":"Point"}
}