{
  "type": "Feature",
  "properties": {
    "gn:admin1_code":"7.0",
    "gn:admin2_code":"RM",
    "gn:admin3_code":"58009.0",
    "gn:asciiname":"Fontanaccio",
    "gn:country_code":"IT",
    "gn:dem":403,
    "gn:feature_class":"P",
    "gn:feature_code":"PPL",
    "gn:name":"Fontanaccio",
    "gn:population":33,
    "gn:timezone":"Europe/Rome",
    "iso:country":"IT",
    "wof:name":"Fontanaccio",
    "wof:placetype":"locality",
    "wof:population":33
},
  "geometry": {"coordinates":[12.67841,41.71528],"type":"Point"}
}