{
  "type": "Feature",
  "properties": {
    "gn:admin1_code":"7",
    "gn:admin2_code":"VT",
    "gn:admin3_code":"56023.0",
    "gn:asciiname":"Pantalone",
    "gn:country_code":"IT",
    "gn:dem":177,
    "gn:feature_class":"P",
    "gn:feature_code":"PPL",
    "gn:name":"Pantalone",
    "gn:population":58,
    "gn:timezone":"Europe/Rome",
    "iso:country":"IT",
    "wof:name":"Pantalone",
    "wof:placetype":"locality",
    "wof:population":58
},
  "geometry": {"coordinates":[12.38284,42.32541],"type":"Point"}
}