{
  "type": "Feature",
  "properties": {
    "gn:admin1_code":"7",
    "gn:admin2_code":"VT",
    "gn:admin3_code":"56023.0",
    "gn:asciiname":"Pantalone",
    "gn:country_code":"IT",
    "gn:dem":177,
    "gn:feature_class":"P",
    "gn:feature_code":"PPL",
    "gn:name":"Pantalone",
    "gn:population":58,
    "gn:timezone":"Europe/Rome",
    "iso:country":"IT",
    "name:bod_x_preferred":[
        "\u0f50\u0f44\u0f0b\u0f4f\u0f0b\u0f63\u0f7c\u0f0b\u0f53\u0f7a\u0f0d"
    ],
    "name:bre_x_preferred":[
        "Pantalone"
    ],
    "name:bul_x_preferred":[
        "\u041f\u0430\u043d\u0442\u0430\u043b\u043e\u043d\u0435"
    ],
    "name:cat_x_preferred":[
        "Pantalone"
    ],
    "name:dan_x_preferred":[
        "Pantalone"
    ],
    "name:deu_x_preferred":[
        "Pantalone"
    ],
    "name:ell_x_preferred":[
        "\u03a0\u03b1\u03bd\u03c4\u03b1\u03bb\u03cc\u03bd\u03b5"
    ],
    "name:fra_x_preferred":[
        "Pantalon"
    ],
    "name:glg_x_preferred":[
        "Pantalone"
    ],
    "name:heb_x_preferred":[
        "\u05e4\u05e0\u05d8\u05dc\u05d5\u05e0\u05d4"
    ],
    "name:ita_x_preferred":[
        "Pantalone"
    ],
    "name:nld_x_preferred":[
        "Pantalone"
    ],
    "name:nor_x_preferred":[
        "Pantalone"
    ],
    "name:pol_x_preferred":[
        "Pantalone"
    ],
    "name:ron_x_preferred":[
        "Pantalone"
    ],
    "name:rus_x_preferred":[
        "\u041f\u0430\u043d\u0442\u0430\u043b\u043e\u043d\u0435"
    ],
    "name:spa_x_preferred":[
        "Pantale\u00f3n"
    ],
    "name:swe_x_preferred":[
        "Pantalone"
    ],
    "name:ukr_x_preferred":[
        "\u041f\u0430\u043d\u0442\u0430\u043b\u043e\u043d\u0435"
    ],
    "wof:name":"Pantalone",
    "wof:placetype":"locality",
    "wof:population":58
},
  "geometry": {"coordinates":[12.38284,42.32541],"type":"Point"}
}