{
  "type": "Feature",
  "properties": {
    "gn:admin1_code":"5",
    "gn:admin2_code":"BO",
    "gn:admin3_code":"37040.0",
    "gn:asciiname":"Molino della Pergola",
    "gn:country_code":"IT",
    "gn:dem":459,
    "gn:feature_class":"P",
    "gn:feature_code":"PPL",
    "gn:name":"Molino della Pergola",
    "gn:population":48,
    "gn:timezone":"Europe/Rome",
    "iso:country":"IT",
    "wof:name":"Molino della Pergola",
    "wof:placetype":"locality",
    "wof:population":48
},
  "geometry": {"coordinates":[11.35296,44.2228],"type":"Point"}
}