{
  "type": "Feature",
  "properties": {
    "gn:elevation":330,
    "gn:population":362,
    "iso:country":"IT",
    "name:bcl_x_preferred":[
        "Sassetta"
    ],
    "name:bel_x_preferred":[
        "\u0413\u043e\u0440\u0430\u0434 \u0421\u0430\u0441\u0435\u0442\u0430"
    ],
    "name:bul_x_preferred":[
        "\u0421\u0430\u0441\u0435\u0442\u0430"
    ],
    "name:deu_x_preferred":[
        "Sassetta"
    ],
    "name:eng_x_preferred":[
        "Sassetta"
    ],
    "name:epo_x_preferred":[
        "Sassetta"
    ],
    "name:eus_x_preferred":[
        "Sassetta"
    ],
    "name:fas_x_preferred":[
        "\u0633\u0627\u0633\u062a\u0627"
    ],
    "name:fra_x_preferred":[
        "Sassetta"
    ],
    "name:hbs_x_preferred":[
        "Sassetta"
    ],
    "name:hun_x_preferred":[
        "Sassetta"
    ],
    "name:hye_x_preferred":[
        "\u054d\u0561\u057d\u0565\u057f\u0561"
    ],
    "name:ita_x_preferred":[
        "Sassetta"
    ],
    "name:jpn_x_preferred":[
        "\u30b5\u30c3\u30bb\u30c3\u30bf"
    ],
    "name:kor_x_preferred":[
        "\uc0ac\uc138\ud0c0"
    ],
    "name:lat_x_preferred":[
        "Saxseta"
    ],
    "name:lmo_x_preferred":[
        "Sassetta"
    ],
    "name:msa_x_preferred":[
        "Sassetta"
    ],
    "name:nap_x_preferred":[
        "Sassetta"
    ],
    "name:nld_x_preferred":[
        "Sassetta"
    ],
    "name:nob_x_preferred":[
        "Sassetta"
    ],
    "name:nor_x_preferred":[
        "Sassetta"
    ],
    "name:pms_x_preferred":[
        "Sassetta"
    ],
    "name:pol_x_preferred":[
        "Sassetta"
    ],
    "name:por_x_preferred":[
        "Sassetta"
    ],
    "name:ron_x_preferred":[
        "Sassetta"
    ],
    "name:rus_x_preferred":[
        "\u0421\u0430\u0441\u0441\u0435\u0442\u0442\u0430"
    ],
    "name:spa_x_preferred":[
        "Sassetta"
    ],
    "name:srp_x_preferred":[
        "Sassetta"
    ],
    "name:swe_x_preferred":[
        "Sassetta"
    ],
    "name:tgl_x_preferred":[
        "Sassetta"
    ],
    "name:ukr_x_preferred":[
        "\u0421\u0430\u0441\u0441\u0435\u0442\u0442\u0430"
    ],
    "name:uzb_x_preferred":[
        "Sassetta"
    ],
    "name:vie_x_preferred":[
        "Sassetta"
    ],
    "name:vol_x_preferred":[
        "Sassetta"
    ],
    "name:war_x_preferred":[
        "Sassetta"
    ],
    "name:zho_x_preferred":[
        "\u8428\u585e\u5854"
    ],
    "qs:a0":"Italia",
    "qs:a1":"*Livorno",
    "qs:a1r":"0Toscana",
    "qs:adm0":"Italia",
    "qs:la_lc":"*",
    "qs:level":"locality",
    "qs:loc":"Sassetta",
    "qs:loc_alt":"Sassetta",
    "qs:pop":0,
    "qs:type":"buffered point",
    "wd:wordcount":52,
    "wof:lang":[
        "ita"
    ],
    "wof:name":"Sassetta",
    "wof:placetype":"locality",
    "wof:population":362
},
  "geometry": {"coordinates":[10.643171,43.127029],"type":"Point"}
}