{
  "type": "Feature",
  "properties": {
    "gn:admin1_code":"9",
    "gn:admin2_code":"MN",
    "gn:admin3_code":"20015.0",
    "gn:asciiname":"Sant'Anna",
    "gn:country_code":"IT",
    "gn:dem":51,
    "gn:feature_class":"P",
    "gn:feature_code":"PPL",
    "gn:name":"Sant'Anna",
    "gn:population":87,
    "gn:timezone":"Europe/Rome",
    "iso:country":"IT",
    "wof:name":"Sant'Anna",
    "wof:placetype":"locality",
    "wof:population":87
},
  "geometry": {"coordinates":[10.5194,45.29476],"type":"Point"}
}