{
  "type": "Feature",
  "properties": {
    "gn:admin1_code":"9",
    "gn:admin2_code":"CO",
    "gn:admin3_code":"13215.0",
    "gn:asciiname":"Casale Casa Rossa",
    "gn:country_code":"IT",
    "gn:dem":398,
    "gn:feature_class":"P",
    "gn:feature_code":"PPL",
    "gn:name":"Casale Casa Rossa",
    "gn:population":33,
    "gn:timezone":"Europe/Rome",
    "iso:country":"IT",
    "wof:name":"Casale Casa Rossa",
    "wof:placetype":"locality",
    "wof:population":33
},
  "geometry": {"coordinates":[8.91261,45.794],"type":"Point"}
}