{
  "type": "Feature",
  "properties": {
    "gn:admin1_code":"16.0",
    "gn:admin2_code":"SI",
    "gn:admin3_code":"52004.0",
    "gn:asciiname":"Pieve a Scuola",
    "gn:cc2":"IT",
    "gn:country_code":"IT",
    "gn:dem":286,
    "gn:feature_class":"P",
    "gn:feature_code":"PPL",
    "gn:name":"Pieve a Scuola",
    "gn:population":0,
    "gn:timezone":"Europe/Rome",
    "iso:country":"IT",
    "name:und_x_variant":[
        "Pieve Scola",
        "Pieve a Scuola"
    ],
    "wof:name":"Pieve a Scuola",
    "wof:placetype":"locality"
},
  "geometry": {"coordinates":[11.13333,43.31667],"type":"Point"}
}