{
  "type": "Feature",
  "properties": {
    "gn:admin1_code":"3",
    "gn:admin2_code":"CS",
    "gn:admin3_code":"78026.0",
    "gn:asciiname":"Treti",
    "gn:country_code":"IT",
    "gn:dem":497,
    "gn:feature_class":"P",
    "gn:feature_code":"PPL",
    "gn:name":"Treti",
    "gn:population":33,
    "gn:timezone":"Europe/Rome",
    "iso:country":"IT",
    "wof:name":"Treti",
    "wof:placetype":"locality",
    "wof:population":33
},
  "geometry": {"coordinates":[16.20956,39.25755],"type":"Point"}
}