{
  "type": "Feature",
  "properties": {
    "gn:admin1_code":"9.0",
    "gn:admin2_code":"SO",
    "gn:admin3_code":"14035.0",
    "gn:asciiname":"Soste",
    "gn:country_code":"IT",
    "gn:dem":1928,
    "gn:feature_class":"P",
    "gn:feature_code":"PPL",
    "gn:name":"Soste",
    "gn:population":0,
    "gn:timezone":"Europe/Rome",
    "iso:country":"IT",
    "wof:name":"Soste",
    "wof:placetype":"locality"
},
  "geometry": {"coordinates":[9.31667,46.46667],"type":"Point"}
}