{
  "type": "Feature",
  "properties": {
    "gn:admin1_code":"5",
    "gn:admin2_code":"PR",
    "gn:admin3_code":"34008.0",
    "gn:asciiname":"Chiastre",
    "gn:country_code":"IT",
    "gn:dem":763,
    "gn:feature_class":"P",
    "gn:feature_code":"PPL",
    "gn:name":"Chiastre",
    "gn:population":22,
    "gn:timezone":"Europe/Rome",
    "iso:country":"IT",
    "wof:name":"Chiastre",
    "wof:placetype":"locality",
    "wof:population":22
},
  "geometry": {"coordinates":[10.05299,44.56616],"type":"Point"}
}