{
  "type": "Feature",
  "properties": {
    "gn:admin1_code":"12",
    "gn:admin2_code":"CN",
    "gn:admin3_code":"4152.0",
    "gn:asciiname":"Corini",
    "gn:country_code":"IT",
    "gn:dem":377,
    "gn:feature_class":"P",
    "gn:feature_code":"PPL",
    "gn:name":"Corini",
    "gn:population":20,
    "gn:timezone":"Europe/Rome",
    "iso:country":"IT",
    "wof:name":"Corini",
    "wof:placetype":"locality",
    "wof:population":20
},
  "geometry": {"coordinates":[7.92097,44.59876],"type":"Point"}
}