{
  "type": "Feature",
  "properties": {
    "gn:admin1_code":"19.0",
    "gn:admin2_code":"AO",
    "gn:admin3_code":"7013.0",
    "gn:asciiname":"Allesaz",
    "gn:country_code":"IT",
    "gn:dem":1126,
    "gn:feature_class":"P",
    "gn:feature_code":"PPL",
    "gn:name":"Allesaz",
    "gn:population":28,
    "gn:timezone":"Europe/Rome",
    "iso:country":"IT",
    "wof:name":"Allesaz",
    "wof:placetype":"locality",
    "wof:population":28
},
  "geometry": {"coordinates":[7.75145,45.72883],"type":"Point"}
}