{
  "type": "Feature",
  "properties": {
    "gn:admin1_code":"6.0",
    "gn:admin2_code":"UD",
    "gn:admin3_code":"30121.0",
    "gn:asciiname":"Illegio",
    "gn:country_code":"IT",
    "gn:dem":582,
    "gn:elevation":"570.0",
    "gn:feature_class":"P",
    "gn:feature_code":"PPL",
    "gn:name":"Illegio",
    "gn:population":353,
    "gn:timezone":"Europe/Rome",
    "iso:country":"IT",
    "wof:name":"Illegio",
    "wof:placetype":"locality",
    "wof:population":353
},
  "geometry": {"coordinates":[13.05657,46.4292],"type":"Point"}
}