{
  "type": "Feature",
  "properties": {
    "gn:admin1_code":"18.0",
    "gn:admin2_code":"PG",
    "gn:admin3_code":"54039.0",
    "gn:asciiname":"Sant'Egidio",
    "gn:country_code":"IT",
    "gn:dem":240,
    "gn:elevation":"262.0",
    "gn:feature_class":"P",
    "gn:feature_code":"PPL",
    "gn:name":"Sant'Egidio",
    "gn:population":901,
    "gn:timezone":"Europe/Rome",
    "iso:country":"IT",
    "name:bre_x_preferred":[
        "Sant'Egidio"
    ],
    "name:ceb_x_preferred":[
        "Sant'Egidio"
    ],
    "name:deu_x_preferred":[
        "Sant\u2019Egidio"
    ],
    "name:fra_x_preferred":[
        "Sant'Egidio"
    ],
    "name:hun_x_preferred":[
        "Sant\u2019Egidio"
    ],
    "name:ita_x_preferred":[
        "Sant'Egidio"
    ],
    "name:nld_x_preferred":[
        "Sant'Egidio"
    ],
    "name:srp_x_preferred":[
        "Sant\u2019E\u0111idio"
    ],
    "name:swe_x_preferred":[
        "Sant'Egidio"
    ],
    "wof:name":"Sant'Egidio",
    "wof:placetype":"locality",
    "wof:population":901
},
  "geometry": {"coordinates":[12.4908,43.10218],"type":"Point"}
}