{
  "type": "Feature",
  "properties": {
    "gn:admin1_code":"5",
    "gn:admin2_code":"FE",
    "gn:admin3_code":"38009.0",
    "gn:asciiname":"Borgo Candelosa",
    "gn:country_code":"IT",
    "gn:dem":0,
    "gn:feature_class":"P",
    "gn:feature_code":"PPL",
    "gn:name":"Borgo Candelosa",
    "gn:population":58,
    "gn:timezone":"Europe/Rome",
    "iso:country":"IT",
    "wof:name":"Borgo Candelosa",
    "wof:placetype":"locality",
    "wof:population":58
},
  "geometry": {"coordinates":[11.85667,44.83608],"type":"Point"}
}