{
  "type": "Feature",
  "properties": {
    "gn:admin1_code":"13",
    "gn:admin2_code":"FG",
    "gn:admin3_code":"71029.0",
    "gn:asciiname":"Sciali degli Zingari",
    "gn:country_code":"IT",
    "gn:dem":2,
    "gn:feature_class":"P",
    "gn:feature_code":"PPL",
    "gn:name":"Sciali degli Zingari",
    "gn:population":35,
    "gn:timezone":"Europe/Rome",
    "iso:country":"IT",
    "wof:name":"Sciali degli Zingari",
    "wof:placetype":"locality",
    "wof:population":35
},
  "geometry": {"coordinates":[15.89122,41.56229],"type":"Point"}
}