{
  "type": "Feature",
  "properties": {
    "gn:admin1_code":"15",
    "gn:admin2_code":"ME",
    "gn:admin3_code":"83076.0",
    "gn:asciiname":"Serrocondurri",
    "gn:country_code":"IT",
    "gn:dem":408,
    "gn:feature_class":"P",
    "gn:feature_code":"PPL",
    "gn:name":"Serrocondurri",
    "gn:population":12,
    "gn:timezone":"Europe/Rome",
    "iso:country":"IT",
    "wof:name":"Serrocondurri",
    "wof:placetype":"locality",
    "wof:population":12
},
  "geometry": {"coordinates":[15.41056,38.15382],"type":"Point"}
}