{
  "type": "Feature",
  "properties": {
    "gn:admin1_code":"16",
    "gn:admin2_code":"FI",
    "gn:admin3_code":"48005.0",
    "gn:asciiname":"Pratello",
    "gn:country_code":"IT",
    "gn:dem":83,
    "gn:feature_class":"P",
    "gn:feature_code":"PPL",
    "gn:name":"Pratello",
    "gn:population":21,
    "gn:timezone":"Europe/Rome",
    "iso:country":"IT",
    "wof:name":"Pratello",
    "wof:placetype":"locality",
    "wof:population":21
},
  "geometry": {"coordinates":[11.16144,43.87681],"type":"Point"}
}