{
  "type": "Feature",
  "properties": {
    "gn:admin1_code":"13.0",
    "gn:admin2_code":"LE",
    "gn:admin3_code":"75029.0",
    "gn:asciiname":"Contrada Scorpio-Galatina",
    "gn:country_code":"IT",
    "gn:dem":68,
    "gn:feature_class":"P",
    "gn:feature_code":"PPL",
    "gn:name":"Contrada Scorpio-Galatina",
    "gn:population":47,
    "gn:timezone":"Europe/Rome",
    "iso:country":"IT",
    "wof:name":"Contrada Scorpio-Galatina",
    "wof:placetype":"locality",
    "wof:population":47
},
  "geometry": {"coordinates":[18.14826,40.16263],"type":"Point"}
}