{
  "type": "Feature",
  "properties": {
    "gn:admin1_code":"16",
    "gn:admin2_code":"SI",
    "gn:admin3_code":"52002.0",
    "gn:asciiname":"Bollano",
    "gn:country_code":"IT",
    "gn:dem":284,
    "gn:feature_class":"P",
    "gn:feature_code":"PPL",
    "gn:name":"Bollano",
    "gn:population":17,
    "gn:timezone":"Europe/Rome",
    "iso:country":"IT",
    "wof:name":"Bollano",
    "wof:placetype":"locality",
    "wof:population":17
},
  "geometry": {"coordinates":[11.52304,43.17684000000001],"type":"Point"}
}