{
  "type": "Feature",
  "properties": {
    "gn:admin1_code":"20",
    "gn:admin2_code":"TV",
    "gn:admin3_code":"26040.0",
    "gn:asciiname":"Case Fanfani",
    "gn:country_code":"IT",
    "gn:dem":32,
    "gn:feature_class":"P",
    "gn:feature_code":"PPL",
    "gn:name":"Case Fanfani",
    "gn:population":38,
    "gn:timezone":"Europe/Rome",
    "iso:country":"IT",
    "wof:name":"Case Fanfani",
    "wof:placetype":"locality",
    "wof:population":38
},
  "geometry": {"coordinates":[12.29981,45.73746],"type":"Point"}
}