{
  "type": "Feature",
  "properties": {
    "gn:admin1_code":"14",
    "gn:admin2_code":"OR",
    "gn:admin3_code":"95006.0",
    "gn:asciiname":"S'Ungroni",
    "gn:country_code":"IT",
    "gn:dem":9,
    "gn:feature_class":"P",
    "gn:feature_code":"PPL",
    "gn:name":"S'Ungroni",
    "gn:population":38,
    "gn:timezone":"Europe/Rome",
    "iso:country":"IT",
    "wof:name":"S'Ungroni",
    "wof:placetype":"locality",
    "wof:population":38
},
  "geometry": {"coordinates":[8.57975,39.79692],"type":"Point"}
}