{
  "type": "Feature",
  "properties": {
    "gn:admin1_code":"20",
    "gn:admin2_code":"VR",
    "gn:admin3_code":"23062.0",
    "gn:asciiname":"Montalto Sotto I Brentegani",
    "gn:country_code":"IT",
    "gn:dem":199,
    "gn:feature_class":"P",
    "gn:feature_code":"PPL",
    "gn:name":"Montalto Sotto I Brentegani",
    "gn:population":23,
    "gn:timezone":"Europe/Rome",
    "iso:country":"IT",
    "wof:name":"Montalto Sotto I Brentegani",
    "wof:placetype":"locality",
    "wof:population":23
},
  "geometry": {"coordinates":[10.80915,45.54521],"type":"Point"}
}