{
  "type": "Feature",
  "properties": {
    "gn:admin1_code":"4",
    "gn:admin2_code":"AV",
    "gn:admin3_code":"64116.0",
    "gn:asciiname":"Cuorno",
    "gn:country_code":"IT",
    "gn:dem":346,
    "gn:feature_class":"P",
    "gn:feature_code":"PPL",
    "gn:name":"Cuorno",
    "gn:population":24,
    "gn:timezone":"Europe/Rome",
    "iso:country":"IT",
    "wof:name":"Cuorno",
    "wof:placetype":"locality",
    "wof:population":24
},
  "geometry": {"coordinates":[14.91492,41.05666],"type":"Point"}
}