{
  "type": "Feature",
  "properties": {
    "gn:admin1_code":"20.0",
    "gn:admin2_code":"BL",
    "gn:admin3_code":"25016.0",
    "gn:asciiname":"Campo di Sotto",
    "gn:country_code":"IT",
    "gn:dem":1128,
    "gn:feature_class":"P",
    "gn:feature_code":"PPL",
    "gn:name":"Campo di Sotto",
    "gn:population":40,
    "gn:timezone":"Europe/Rome",
    "iso:country":"IT",
    "wof:name":"Campo di Sotto",
    "wof:placetype":"locality",
    "wof:population":40
},
  "geometry": {"coordinates":[12.13044,46.51919],"type":"Point"}
}