{
  "type": "Feature",
  "properties": {
    "gn:admin1_code":"15.0",
    "gn:admin2_code":"ME",
    "gn:admin3_code":"83048.0",
    "gn:asciiname":"Massa San Giorgio",
    "gn:country_code":"IT",
    "gn:dem":261,
    "gn:feature_class":"P",
    "gn:feature_code":"PPL",
    "gn:name":"Massa San Giorgio",
    "gn:population":351,
    "gn:timezone":"Europe/Rome",
    "iso:country":"IT",
    "wof:name":"Massa San Giorgio",
    "wof:placetype":"locality",
    "wof:population":351
},
  "geometry": {"coordinates":[15.53668,38.27437000000001],"type":"Point"}
}