{
  "type": "Feature",
  "properties": {
    "gn:admin1_code":"1",
    "gn:admin2_code":"TE",
    "gn:admin3_code":"67014.0",
    "gn:asciiname":"Contrada Casabianca Sud",
    "gn:country_code":"IT",
    "gn:dem":277,
    "gn:feature_class":"P",
    "gn:feature_code":"PPL",
    "gn:name":"Contrada Casabianca Sud",
    "gn:population":130,
    "gn:timezone":"Europe/Rome",
    "iso:country":"IT",
    "wof:name":"Contrada Casabianca Sud",
    "wof:placetype":"locality",
    "wof:population":130
},
  "geometry": {"coordinates":[13.94709,42.52536],"type":"Point"}
}