{
  "type": "Feature",
  "properties": {
    "gn:admin1_code":"12",
    "gn:admin2_code":"AT",
    "gn:admin3_code":"5013.0",
    "gn:asciiname":"Bruciati",
    "gn:country_code":"IT",
    "gn:dem":280,
    "gn:feature_class":"P",
    "gn:feature_code":"PPL",
    "gn:name":"Bruciati",
    "gn:population":30,
    "gn:timezone":"Europe/Rome",
    "iso:country":"IT",
    "wof:name":"Bruciati",
    "wof:placetype":"locality",
    "wof:population":30
},
  "geometry": {"coordinates":[8.3415,44.72849],"type":"Point"}
}