{
  "type": "Feature",
  "properties": {
    "gn:admin1_code":"3.0",
    "gn:admin2_code":"VV",
    "gn:admin3_code":"102025.0",
    "gn:asciiname":"Preitoni",
    "gn:country_code":"IT",
    "gn:dem":285,
    "gn:elevation":"295.0",
    "gn:feature_class":"P",
    "gn:feature_code":"PPL",
    "gn:name":"Preitoni",
    "gn:population":332,
    "gn:timezone":"Europe/Rome",
    "iso:country":"IT",
    "wof:name":"Preitoni",
    "wof:placetype":"locality",
    "wof:population":332
},
  "geometry": {"coordinates":[15.92291,38.5754],"type":"Point"}
}