{
  "type": "Feature",
  "properties": {
    "gn:admin1_code":"10.0",
    "gn:admin2_code":"AP",
    "gn:admin3_code":"44054.0",
    "gn:asciiname":"San Giovanni",
    "gn:country_code":"IT",
    "gn:dem":252,
    "gn:feature_class":"P",
    "gn:feature_code":"PPL",
    "gn:name":"San Giovanni",
    "gn:population":25,
    "gn:timezone":"Europe/Rome",
    "iso:country":"IT",
    "wof:name":"San Giovanni",
    "wof:placetype":"locality",
    "wof:population":25
},
  "geometry": {"coordinates":[13.7331,42.96051],"type":"Point"}
}