{
  "type": "Feature",
  "properties": {
    "gn:admin1_code":"20",
    "gn:admin2_code":"BL",
    "gn:admin3_code":"25040.0",
    "gn:asciiname":"Pian di Vedoia",
    "gn:country_code":"IT",
    "gn:dem":420,
    "gn:feature_class":"P",
    "gn:feature_code":"PPL",
    "gn:name":"Pian di Vedoia",
    "gn:population":100,
    "gn:timezone":"Europe/Rome",
    "iso:country":"IT",
    "wof:name":"Pian di Vedoia",
    "wof:placetype":"locality",
    "wof:population":100
},
  "geometry": {"coordinates":[12.28489,46.19986],"type":"Point"}
}