{
  "type": "Feature",
  "properties": {
    "gn:admin1_code":"7.0",
    "gn:admin2_code":"LT",
    "gn:admin3_code":"59010.0",
    "gn:asciiname":"Stazione di Itri",
    "gn:country_code":"IT",
    "gn:dem":98,
    "gn:feature_class":"P",
    "gn:feature_code":"PPL",
    "gn:name":"Stazione di Itri",
    "gn:population":41,
    "gn:timezone":"Europe/Rome",
    "iso:country":"IT",
    "wof:name":"Stazione di Itri",
    "wof:placetype":"locality",
    "wof:population":41
},
  "geometry": {"coordinates":[13.5455,41.2718],"type":"Point"}
}