{
  "type": "Feature",
  "properties": {
    "gn:admin1_code":"12.0",
    "gn:admin2_code":"CN",
    "gn:admin3_code":"4155.0",
    "gn:asciiname":"Sen",
    "gn:country_code":"IT",
    "gn:dem":1201,
    "gn:feature_class":"P",
    "gn:feature_code":"PPLL",
    "gn:name":"Sen",
    "gn:population":2,
    "gn:timezone":"Europe/Rome",
    "iso:country":"IT",
    "name:bul_x_preferred":[
        "\u0421\u0435\u043d"
    ],
    "name:ceb_x_preferred":[
        "Sen"
    ],
    "name:deu_x_preferred":[
        "Sen"
    ],
    "name:eus_x_preferred":[
        "Sen"
    ],
    "name:fin_x_preferred":[
        "Sen"
    ],
    "name:fra_x_preferred":[
        "Sen"
    ],
    "name:hat_x_preferred":[
        "Sen"
    ],
    "name:hin_x_preferred":[
        "\u0938\u0947\u0928"
    ],
    "name:nno_x_preferred":[
        "Sen"
    ],
    "name:pol_x_preferred":[
        "Sen"
    ],
    "name:rus_x_preferred":[
        "\u0421\u0435\u043d"
    ],
    "name:swe_x_preferred":[
        "Sen"
    ],
    "name:tur_x_preferred":[
        "Sen"
    ],
    "name:ukr_x_preferred":[
        "\u0421\u0435\u043d"
    ],
    "name:vie_x_preferred":[
        "Sen"
    ],
    "wof:name":"Sen",
    "wof:placetype":"locality",
    "wof:population":2
},
  "geometry": {"coordinates":[7.86455,44.125],"type":"Point"}
}