{
  "type": "Feature",
  "properties": {
    "gn:admin1_code":"4",
    "gn:admin2_code":"AV",
    "gn:admin3_code":"64050.0",
    "gn:asciiname":"Pozzillo Muso",
    "gn:country_code":"IT",
    "gn:dem":473,
    "gn:feature_class":"P",
    "gn:feature_code":"PPL",
    "gn:name":"Pozzillo Muso",
    "gn:population":35,
    "gn:timezone":"Europe/Rome",
    "iso:country":"IT",
    "wof:name":"Pozzillo Muso",
    "wof:placetype":"locality",
    "wof:population":35
},
  "geometry": {"coordinates":[15.03169,41.05097],"type":"Point"}
}