{
  "type": "Feature",
  "properties": {
    "gn:admin1_code":"5",
    "gn:admin2_code":"RN",
    "gn:admin3_code":"99013.0",
    "gn:asciiname":"Case Chiesa Vecchia",
    "gn:country_code":"IT",
    "gn:dem":33,
    "gn:feature_class":"P",
    "gn:feature_code":"PPL",
    "gn:name":"Case Chiesa Vecchia",
    "gn:population":24,
    "gn:timezone":"Europe/Rome",
    "iso:country":"IT",
    "wof:name":"Case Chiesa Vecchia",
    "wof:placetype":"locality",
    "wof:population":24
},
  "geometry": {"coordinates":[12.67038,43.98306],"type":"Point"}
}