{
  "type": "Feature",
  "properties": {
    "gn:admin1_code":"16.0",
    "gn:admin2_code":"PT",
    "gn:admin3_code":"47009.0",
    "gn:asciiname":"Uggia-Pazzera-Bizzarrino",
    "gn:country_code":"IT",
    "gn:dem":21,
    "gn:feature_class":"P",
    "gn:feature_code":"PPL",
    "gn:name":"Uggia-Pazzera-Bizzarrino",
    "gn:population":1375,
    "gn:timezone":"Europe/Rome",
    "iso:country":"IT",
    "wof:name":"Uggia-Pazzera-Bizzarrino",
    "wof:placetype":"locality",
    "wof:population":1375
},
  "geometry": {"coordinates":[10.83154,43.83434000000001],"type":"Point"}
}