{
  "type": "Feature",
  "properties": {
    "gn:admin1_code":"20",
    "gn:admin2_code":"RO",
    "gn:admin3_code":"29049.0",
    "gn:asciiname":"Casino",
    "gn:country_code":"IT",
    "gn:dem":5,
    "gn:feature_class":"P",
    "gn:feature_code":"PPL",
    "gn:name":"Casino",
    "gn:population":12,
    "gn:timezone":"Europe/Rome",
    "iso:country":"IT",
    "wof:name":"Casino",
    "wof:placetype":"locality",
    "wof:population":12
},
  "geometry": {"coordinates":[11.66466,45.02458],"type":"Point"}
}