{
  "type": "Feature",
  "properties": {
    "gn:admin1_code":"4.0",
    "gn:admin2_code":"SA",
    "gn:admin3_code":"65109.0",
    "gn:asciiname":"Cerreto",
    "gn:country_code":"IT",
    "gn:dem":339,
    "gn:feature_class":"P",
    "gn:feature_code":"PPLL",
    "gn:name":"Cerreto",
    "gn:population":4,
    "gn:timezone":"Europe/Rome",
    "iso:country":"IT",
    "name:ceb_x_preferred":[
        "Cerreto"
    ],
    "name:ces_x_preferred":[
        "Cerreto"
    ],
    "name:deu_x_preferred":[
        "Cerreto"
    ],
    "name:ita_x_preferred":[
        "Cerreto"
    ],
    "name:lat_x_preferred":[
        "Cerretum"
    ],
    "name:nld_x_preferred":[
        "Cerreto"
    ],
    "name:pms_x_preferred":[
        "Cerreto"
    ],
    "name:por_x_preferred":[
        "Cerreto"
    ],
    "name:rus_x_preferred":[
        "\u0427\u0435\u0440\u0440\u0435\u0442\u043e"
    ],
    "name:srp_x_preferred":[
        "\u010cereto"
    ],
    "name:swe_x_preferred":[
        "Cerreto"
    ],
    "wof:name":"Cerreto",
    "wof:placetype":"locality",
    "wof:population":4
},
  "geometry": {"coordinates":[15.46741,40.16923],"type":"Point"}
}