{
  "type": "Feature",
  "properties": {
    "gn:admin1_code":"17",
    "gn:admin2_code":"BZ",
    "gn:admin3_code":"21028.0",
    "gn:asciiname":"Camping",
    "gn:country_code":"IT",
    "gn:dem":1179,
    "gn:feature_class":"P",
    "gn:feature_code":"PPL",
    "gn:name":"Camping",
    "gn:population":24,
    "gn:timezone":"Europe/Rome",
    "iso:country":"IT",
    "wof:name":"Camping",
    "wof:placetype":"locality",
    "wof:population":24
},
  "geometry": {"coordinates":[12.19612,46.73407],"type":"Point"}
}