{
  "type": "Feature",
  "properties": {
    "gn:admin1_code":"17",
    "gn:admin2_code":"BZ",
    "gn:admin3_code":"21028.0",
    "gn:asciiname":"Camping",
    "gn:country_code":"IT",
    "gn:dem":1179,
    "gn:feature_class":"P",
    "gn:feature_code":"PPL",
    "gn:name":"Camping",
    "gn:population":24,
    "gn:timezone":"Europe/Rome",
    "iso:country":"IT",
    "name:ara_x_preferred":[
        "\u062a\u062e\u064a\u064a\u0645"
    ],
    "name:bul_x_preferred":[
        "\u041a\u044a\u043c\u043f\u0438\u043d\u0433"
    ],
    "name:cat_x_preferred":[
        "Acampada"
    ],
    "name:ces_x_preferred":[
        "T\u00e1bo\u0159en\u00ed"
    ],
    "name:chy_x_preferred":[
        "Amo'xest\u00f4tse"
    ],
    "name:cym_x_preferred":[
        "Gwersylla"
    ],
    "name:dan_x_preferred":[
        "Camping"
    ],
    "name:deu_x_preferred":[
        "Camping"
    ],
    "name:ell_x_preferred":[
        "\u039a\u03b1\u03c4\u03b1\u03c3\u03ba\u03ae\u03bd\u03c9\u03c3\u03b7"
    ],
    "name:epo_x_preferred":[
        "Tendumo"
    ],
    "name:eus_x_preferred":[
        "Kanpin"
    ],
    "name:fas_x_preferred":[
        "\u06a9\u0645\u067e\u06cc\u0646\u06af"
    ],
    "name:fin_x_preferred":[
        "Camping"
    ],
    "name:fra_x_preferred":[
        "Camping"
    ],
    "name:fry_x_preferred":[
        "Kampearjen"
    ],
    "name:glg_x_preferred":[
        "Acampada"
    ],
    "name:heb_x_preferred":[
        "\u05de\u05d7\u05e0\u05d0\u05d5\u05ea"
    ],
    "name:hin_x_preferred":[
        "\u0915\u0948\u0902\u092a\u093f\u0902\u0917"
    ],
    "name:hrv_x_preferred":[
        "Kamp"
    ],
    "name:ind_x_preferred":[
        "Berkemah"
    ],
    "name:ita_x_preferred":[
        "Campeggio"
    ],
    "name:jpn_x_preferred":[
        "\u30ad\u30e3\u30f3\u30d7"
    ],
    "name:kan_x_preferred":[
        "\u0c95\u0ccd\u0caf\u0cbe\u0c82\u0caa\u0cbf\u0c82\u0c97\u0ccd"
    ],
    "name:nld_x_preferred":[
        "Kamperen"
    ],
    "name:nor_x_preferred":[
        "Camping"
    ],
    "name:oci_x_preferred":[
        "Campatge"
    ],
    "name:por_x_preferred":[
        "Acampamento"
    ],
    "name:ron_x_preferred":[
        "Camping"
    ],
    "name:rus_x_preferred":[
        "\u0422\u0443\u0440\u0438\u0441\u0442\u0438\u0447\u0435\u0441\u043a\u0438\u0439 \u043f\u043e\u0445\u043e\u0434"
    ],
    "name:scn_x_preferred":[
        "Campeggiu"
    ],
    "name:sco_x_preferred":[
        "Campin"
    ],
    "name:spa_x_preferred":[
        "Acampada"
    ],
    "name:srp_x_preferred":[
        "Kampovanje"
    ],
    "name:swa_x_preferred":[
        "Camping"
    ],
    "name:swe_x_preferred":[
        "Camping"
    ],
    "name:tur_x_preferred":[
        "Kamp"
    ],
    "name:ukr_x_preferred":[
        "\u0422\u0443\u0440\u0438\u0441\u0442\u0438\u0447\u043d\u0438\u0439 \u043f\u043e\u0445\u0456\u0434"
    ],
    "name:urd_x_preferred":[
        "\u062e\u06cc\u0645\u06c1\u200c\u0632\u0646\u06cc"
    ],
    "name:vie_x_preferred":[
        "C\u1eafm tr\u1ea1i"
    ],
    "wof:name":"Camping",
    "wof:placetype":"locality",
    "wof:population":24
},
  "geometry": {"coordinates":[12.19612,46.73407],"type":"Point"}
}