{
  "type": "Feature",
  "properties": {
    "gn:admin1_code":"1",
    "gn:admin2_code":"CH",
    "gn:admin3_code":"69036.0",
    "gn:asciiname":"Pozzi",
    "gn:country_code":"IT",
    "gn:dem":287,
    "gn:feature_class":"P",
    "gn:feature_code":"PPL",
    "gn:name":"Pozzi",
    "gn:population":32,
    "gn:timezone":"Europe/Rome",
    "iso:country":"IT",
    "wof:name":"Pozzi",
    "wof:placetype":"locality",
    "wof:population":32
},
  "geometry": {"coordinates":[14.66981,41.97602],"type":"Point"}
}