{
  "type": "Feature",
  "properties": {
    "gn:admin1_code":"20",
    "gn:admin2_code":"VR",
    "gn:admin3_code":"23067.0",
    "gn:asciiname":"Corlaiti",
    "gn:country_code":"IT",
    "gn:dem":821,
    "gn:feature_class":"P",
    "gn:feature_code":"PPL",
    "gn:name":"Corlaiti",
    "gn:population":11,
    "gn:timezone":"Europe/Rome",
    "iso:country":"IT",
    "wof:name":"Corlaiti",
    "wof:placetype":"locality",
    "wof:population":11
},
  "geometry": {"coordinates":[11.09374,45.58164],"type":"Point"}
}