{
  "type": "Feature",
  "properties": {
    "gn:admin1_code":"20",
    "gn:admin2_code":"PD",
    "gn:admin3_code":"28013.0",
    "gn:asciiname":"Bressanin",
    "gn:country_code":"IT",
    "gn:dem":16,
    "gn:feature_class":"P",
    "gn:feature_code":"PPL",
    "gn:name":"Bressanin",
    "gn:population":171,
    "gn:timezone":"Europe/Rome",
    "iso:country":"IT",
    "wof:name":"Bressanin",
    "wof:placetype":"locality",
    "wof:population":171
},
  "geometry": {"coordinates":[11.97043,45.54296],"type":"Point"}
}