{
  "type": "Feature",
  "properties": {
    "gn:admin1_code":"20",
    "gn:admin2_code":"TV",
    "gn:admin3_code":"26036.0",
    "gn:asciiname":"Della Croce",
    "gn:country_code":"IT",
    "gn:dem":62,
    "gn:feature_class":"P",
    "gn:feature_code":"PPL",
    "gn:name":"Della Croce",
    "gn:population":57,
    "gn:timezone":"Europe/Rome",
    "iso:country":"IT",
    "wof:name":"Della Croce",
    "wof:placetype":"locality",
    "wof:population":57
},
  "geometry": {"coordinates":[11.85622,45.71176],"type":"Point"}
}