{
  "type": "Feature",
  "properties": {
    "gn:admin1_code":"12",
    "gn:admin2_code":"TO",
    "gn:admin3_code":"1213.0",
    "gn:asciiname":"San Martino",
    "gn:country_code":"IT",
    "gn:dem":236,
    "gn:feature_class":"P",
    "gn:feature_code":"PPL",
    "gn:name":"San Martino",
    "gn:population":27,
    "gn:timezone":"Europe/Rome",
    "iso:country":"IT",
    "wof:name":"San Martino",
    "wof:placetype":"locality",
    "wof:population":27
},
  "geometry": {"coordinates":[7.8639,45.11916],"type":"Point"}
}