{
  "type": "Feature",
  "properties": {
    "gn:admin1_code":"15",
    "gn:admin2_code":"PA",
    "gn:admin3_code":"82050.0",
    "gn:asciiname":"Suvarelli",
    "gn:country_code":"IT",
    "gn:dem":597,
    "gn:feature_class":"P",
    "gn:feature_code":"PPL",
    "gn:name":"Suvarelli",
    "gn:population":87,
    "gn:timezone":"Europe/Rome",
    "iso:country":"IT",
    "wof:name":"Suvarelli",
    "wof:placetype":"locality",
    "wof:population":87
},
  "geometry": {"coordinates":[13.20791,38.07578],"type":"Point"}
}