{
  "type": "Feature",
  "properties": {
    "gn:admin1_code":"20.0",
    "gn:admin2_code":"VI",
    "gn:admin3_code":"24099.0",
    "gn:asciiname":"Roncaglia Vaccheria",
    "gn:country_code":"IT",
    "gn:dem":62,
    "gn:feature_class":"P",
    "gn:feature_code":"PPL",
    "gn:name":"Roncaglia Vaccheria",
    "gn:population":10,
    "gn:timezone":"Europe/Rome",
    "iso:country":"IT",
    "wof:name":"Roncaglia Vaccheria",
    "wof:placetype":"locality",
    "wof:population":10
},
  "geometry": {"coordinates":[11.66497,45.67149000000001],"type":"Point"}
}