{
  "type": "Feature",
  "properties": {
    "gn:admin1_code":"1",
    "gn:admin2_code":"PE",
    "gn:admin3_code":"68032.0",
    "gn:asciiname":"Valle Grazietti",
    "gn:country_code":"IT",
    "gn:dem":339,
    "gn:feature_class":"P",
    "gn:feature_code":"PPL",
    "gn:name":"Valle Grazietti",
    "gn:population":11,
    "gn:timezone":"Europe/Rome",
    "iso:country":"IT",
    "wof:name":"Valle Grazietti",
    "wof:placetype":"locality",
    "wof:population":11
},
  "geometry": {"coordinates":[13.92699,42.27375],"type":"Point"}
}