{
  "type": "Feature",
  "properties": {
    "gn:admin1_code":"10.0",
    "gn:admin2_code":"PU",
    "gn:admin3_code":"41044.0",
    "gn:asciiname":"Ghetto di Trebbiantico",
    "gn:country_code":"IT",
    "gn:dem":131,
    "gn:elevation":"135.0",
    "gn:feature_class":"P",
    "gn:feature_code":"PPL",
    "gn:name":"Ghetto di Trebbiantico",
    "gn:population":531,
    "gn:timezone":"Europe/Rome",
    "iso:country":"IT",
    "wof:name":"Ghetto di Trebbiantico",
    "wof:placetype":"locality",
    "wof:population":531
},
  "geometry": {"coordinates":[12.94872,43.87627],"type":"Point"}
}