{
  "type": "Feature",
  "properties": {
    "gn:admin1_code":"1",
    "gn:admin2_code":"CH",
    "gn:admin3_code":"69057.0",
    "gn:asciiname":"San Basile",
    "gn:country_code":"IT",
    "gn:dem":386,
    "gn:feature_class":"P",
    "gn:feature_code":"PPL",
    "gn:name":"San Basile",
    "gn:population":119,
    "gn:timezone":"Europe/Rome",
    "iso:country":"IT",
    "name:azb_x_preferred":[
        "\u0633\u0627\u0646 \u0628\u0627\u0632\u06cc\u0644\u0647"
    ],
    "name:bcl_x_preferred":[
        "San Basile"
    ],
    "name:bul_x_preferred":[
        "\u0421\u0430\u043d \u0411\u0430\u0437\u0438\u043b\u0435"
    ],
    "name:cat_x_preferred":[
        "San Basile"
    ],
    "name:ceb_x_preferred":[
        "San Basile"
    ],
    "name:deu_x_preferred":[
        "San Basile"
    ],
    "name:epo_x_preferred":[
        "San Basile"
    ],
    "name:eus_x_preferred":[
        "San Basile"
    ],
    "name:fas_x_preferred":[
        "\u0633\u0627\u0646 \u0628\u0627\u0632\u06cc\u0644\u0647"
    ],
    "name:fra_x_preferred":[
        "San Basile"
    ],
    "name:hun_x_preferred":[
        "San Basile"
    ],
    "name:hye_x_preferred":[
        "\u054d\u0561\u0576 \u0532\u0561\u0566\u056b\u056c\u0565"
    ],
    "name:ina_x_preferred":[
        "San Basile"
    ],
    "name:ita_x_preferred":[
        "San Basile"
    ],
    "name:jpn_x_preferred":[
        "\u30b5\u30f3\u30fb\u30d0\u30b8\u30fc\u30ec"
    ],
    "name:kaz_x_preferred":[
        "\u0421\u0430\u043d-\u0411\u0430\u0437\u0438\u043b\u0435"
    ],
    "name:lat_x_preferred":[
        "Fanum Sancti Basilii"
    ],
    "name:lmo_x_preferred":[
        "San Basile"
    ],
    "name:msa_x_preferred":[
        "San Basile"
    ],
    "name:nap_x_preferred":[
        "San Basile"
    ],
    "name:nld_x_preferred":[
        "San Basile"
    ],
    "name:pms_x_preferred":[
        "San Basile"
    ],
    "name:pol_x_preferred":[
        "San Basile"
    ],
    "name:por_x_preferred":[
        "San Basile"
    ],
    "name:ron_x_preferred":[
        "San Basile"
    ],
    "name:rus_x_preferred":[
        "\u0421\u0430\u043d-\u0411\u0430\u0437\u0438\u043b\u0435"
    ],
    "name:scn_x_preferred":[
        "San Vasile"
    ],
    "name:spa_x_preferred":[
        "San Basile"
    ],
    "name:srp_x_preferred":[
        "\u0421\u0430\u043d \u0411\u0430\u0437\u0438\u043b\u0435"
    ],
    "name:swe_x_preferred":[
        "San Basile"
    ],
    "name:ukr_x_preferred":[
        "\u0421\u0430\u043d-\u0411\u0430\u0437\u0456\u043b\u0435"
    ],
    "name:uzb_x_preferred":[
        "San Basile"
    ],
    "name:vie_x_preferred":[
        "San Basile"
    ],
    "name:vol_x_preferred":[
        "San Basile"
    ],
    "name:war_x_preferred":[
        "San Basile"
    ],
    "name:zho_x_preferred":[
        "\u5723\u5df4\u897f\u83b1"
    ],
    "wof:name":"San Basile",
    "wof:placetype":"locality",
    "wof:population":119
},
  "geometry": {"coordinates":[14.2643,42.23989],"type":"Point"}
}