{
  "type": "Feature",
  "properties": {
    "gn:admin1_code":"1",
    "gn:admin2_code":"CH",
    "gn:admin3_code":"69057.0",
    "gn:asciiname":"San Basile",
    "gn:country_code":"IT",
    "gn:dem":386,
    "gn:feature_class":"P",
    "gn:feature_code":"PPL",
    "gn:name":"San Basile",
    "gn:population":119,
    "gn:timezone":"Europe/Rome",
    "iso:country":"IT",
    "wof:name":"San Basile",
    "wof:placetype":"locality",
    "wof:population":119
},
  "geometry": {"coordinates":[14.2643,42.23989],"type":"Point"}
}