{
  "type": "Feature",
  "properties": {
    "gn:admin1_code":"11",
    "gn:admin2_code":"CB",
    "gn:admin3_code":"70049.0",
    "gn:asciiname":"Cerro-Cappella-Lammerti",
    "gn:country_code":"IT",
    "gn:dem":781,
    "gn:feature_class":"P",
    "gn:feature_code":"PPL",
    "gn:name":"Cerro-Cappella-Lammerti",
    "gn:population":301,
    "gn:timezone":"Europe/Rome",
    "iso:country":"IT",
    "wof:name":"Cerro-Cappella-Lammerti",
    "wof:placetype":"locality",
    "wof:population":301
},
  "geometry": {"coordinates":[14.61047,41.57857],"type":"Point"}
}