{
  "type": "Feature",
  "properties": {
    "gn:admin1_code":"20",
    "gn:admin2_code":"PD",
    "gn:admin3_code":"28035.0",
    "gn:asciiname":"San Fortunato",
    "gn:country_code":"IT",
    "gn:dem":-1,
    "gn:feature_class":"P",
    "gn:feature_code":"PPL",
    "gn:name":"San Fortunato",
    "gn:population":37,
    "gn:timezone":"Europe/Rome",
    "iso:country":"IT",
    "wof:name":"San Fortunato",
    "wof:placetype":"locality",
    "wof:population":37
},
  "geometry": {"coordinates":[12.09916,45.23111],"type":"Point"}
}