{
  "type": "Feature",
  "properties": {
    "gn:admin1_code":"14.0",
    "gn:admin2_code":"SS",
    "gn:admin3_code":"90087.0",
    "gn:asciiname":"Longareddu",
    "gn:country_code":"IT",
    "gn:dem":18,
    "gn:elevation":"24.0",
    "gn:feature_class":"P",
    "gn:feature_code":"PPL",
    "gn:name":"Longareddu",
    "gn:population":45,
    "gn:timezone":"Europe/Rome",
    "iso:country":"IT",
    "wof:name":"Longareddu",
    "wof:placetype":"locality",
    "wof:population":45
},
  "geometry": {"coordinates":[8.88155,40.90807],"type":"Point"}
}