{
  "type": "Feature",
  "properties": {
    "gn:admin1_code":"20.0",
    "gn:admin2_code":"VR",
    "gn:admin3_code":"23004.0",
    "gn:asciiname":"Gazzolo-Volpino",
    "gn:country_code":"IT",
    "gn:dem":28,
    "gn:feature_class":"P",
    "gn:feature_code":"PPL",
    "gn:name":"Gazzolo-Volpino",
    "gn:population":1636,
    "gn:timezone":"Europe/Rome",
    "iso:country":"IT",
    "wof:name":"Gazzolo-Volpino",
    "wof:placetype":"locality",
    "wof:population":1636
},
  "geometry": {"coordinates":[11.31319,45.37536],"type":"Point"}
}