{
  "type": "Feature",
  "properties": {
    "gn:admin1_code":"16",
    "gn:admin2_code":"FI",
    "gn:admin3_code":"48024.0",
    "gn:asciiname":"Capannuccia",
    "gn:country_code":"IT",
    "gn:dem":38,
    "gn:feature_class":"P",
    "gn:feature_code":"PPL",
    "gn:name":"Capannuccia",
    "gn:population":42,
    "gn:timezone":"Europe/Rome",
    "iso:country":"IT",
    "wof:name":"Capannuccia",
    "wof:placetype":"locality",
    "wof:population":42
},
  "geometry": {"coordinates":[11.12818,43.7685],"type":"Point"}
}