{
  "type": "Feature",
  "properties": {
    "gn:admin1_code":"17",
    "gn:admin2_code":"TN",
    "gn:admin3_code":"22114.0",
    "gn:asciiname":"Roncio",
    "gn:country_code":"IT",
    "gn:dem":1104,
    "gn:feature_class":"P",
    "gn:feature_code":"PPL",
    "gn:name":"Roncio",
    "gn:population":21,
    "gn:timezone":"Europe/Rome",
    "iso:country":"IT",
    "wof:name":"Roncio",
    "wof:placetype":"locality",
    "wof:population":21
},
  "geometry": {"coordinates":[10.80891,46.32133],"type":"Point"}
}