{
  "type": "Feature",
  "properties": {
    "gn:admin1_code":"20",
    "gn:admin2_code":"VI",
    "gn:admin3_code":"24063.0",
    "gn:asciiname":"Brunelli",
    "gn:country_code":"IT",
    "gn:dem":293,
    "gn:feature_class":"P",
    "gn:feature_code":"PPL",
    "gn:name":"Brunelli",
    "gn:population":26,
    "gn:timezone":"Europe/Rome",
    "iso:country":"IT",
    "name:deu_x_preferred":[
        "Brunelli"
    ],
    "name:ita_x_preferred":[
        "Brunelli"
    ],
    "name:rus_x_preferred":[
        "\u0411\u0440\u0443\u043d\u0435\u043b\u043b\u0438"
    ],
    "name:srp_x_preferred":[
        "Brunelli"
    ],
    "wof:name":"Brunelli",
    "wof:placetype":"locality",
    "wof:population":26
},
  "geometry": {"coordinates":[11.36888,45.6387],"type":"Point"}
}