{
  "type": "Feature",
  "properties": {
    "gn:admin1_code":"5",
    "gn:admin2_code":"RN",
    "gn:admin3_code":"99016.0",
    "gn:asciiname":"Molino Noce",
    "gn:country_code":"IT",
    "gn:dem":88,
    "gn:feature_class":"P",
    "gn:feature_code":"PPL",
    "gn:name":"Molino Noce",
    "gn:population":15,
    "gn:timezone":"Europe/Rome",
    "iso:country":"IT",
    "wof:name":"Molino Noce",
    "wof:placetype":"locality",
    "wof:population":15
},
  "geometry": {"coordinates":[12.62092,43.90643],"type":"Point"}
}