{
  "type": "Feature",
  "properties": {
    "gn:admin1_code":"15",
    "gn:admin2_code":"CT",
    "gn:admin3_code":"87012.0",
    "gn:asciiname":"Villaggio Sant'Antonio",
    "gn:country_code":"IT",
    "gn:dem":381,
    "gn:feature_class":"P",
    "gn:feature_code":"PPL",
    "gn:name":"Villaggio Sant'Antonio",
    "gn:population":209,
    "gn:timezone":"Europe/Rome",
    "iso:country":"IT",
    "wof:name":"Villaggio Sant'Antonio",
    "wof:placetype":"locality",
    "wof:population":209
},
  "geometry": {"coordinates":[15.0037,37.55579],"type":"Point"}
}