{
  "type": "Feature",
  "properties": {
    "gn:admin1_code":"20",
    "gn:admin2_code":"PD",
    "gn:admin3_code":"28049.0",
    "gn:asciiname":"Borgostorto",
    "gn:country_code":"IT",
    "gn:dem":8,
    "gn:feature_class":"P",
    "gn:feature_code":"PPL",
    "gn:name":"Borgostorto",
    "gn:population":29,
    "gn:timezone":"Europe/Rome",
    "iso:country":"IT",
    "wof:name":"Borgostorto",
    "wof:placetype":"locality",
    "wof:population":29
},
  "geometry": {"coordinates":[11.4907,45.11885],"type":"Point"}
}