{
  "type": "Feature",
  "properties": {
    "gn:admin1_code":"3",
    "gn:admin2_code":"CZ",
    "gn:admin3_code":"79039.0",
    "gn:asciiname":"Iencarella",
    "gn:country_code":"IT",
    "gn:dem":661,
    "gn:feature_class":"P",
    "gn:feature_code":"PPL",
    "gn:name":"Iencarella",
    "gn:population":47,
    "gn:timezone":"Europe/Rome",
    "iso:country":"IT",
    "wof:name":"Iencarella",
    "wof:placetype":"locality",
    "wof:population":47
},
  "geometry": {"coordinates":[16.35432,38.81419],"type":"Point"}
}