{
  "type": "Feature",
  "properties": {
    "gn:admin1_code":"12",
    "gn:admin2_code":"TO",
    "gn:admin3_code":"1224.0",
    "gn:asciiname":"Frazione Masonaie",
    "gn:country_code":"IT",
    "gn:dem":1209,
    "gn:feature_class":"P",
    "gn:feature_code":"PPLL",
    "gn:name":"Frazione Masonaie",
    "gn:population":5,
    "gn:timezone":"Europe/Rome",
    "iso:country":"IT",
    "wof:name":"Frazione Masonaie",
    "wof:placetype":"locality",
    "wof:population":5
},
  "geometry": {"coordinates":[7.53717,45.47039],"type":"Point"}
}