{
  "type": "Feature",
  "properties": {
    "gn:admin1_code":"8",
    "gn:admin2_code":"SV",
    "gn:admin3_code":"9056.0",
    "gn:asciiname":"Ciantagalletto",
    "gn:country_code":"IT",
    "gn:dem":137,
    "gn:feature_class":"P",
    "gn:feature_code":"PPL",
    "gn:name":"Ciantagalletto",
    "gn:population":37,
    "gn:timezone":"Europe/Rome",
    "iso:country":"IT",
    "wof:name":"Ciantagalletto",
    "wof:placetype":"locality",
    "wof:population":37
},
  "geometry": {"coordinates":[8.45313,44.32755],"type":"Point"}
}