{
  "type": "Feature",
  "properties": {
    "gn:admin1_code":"7.0",
    "gn:admin2_code":"LT",
    "gn:admin3_code":"59001.0",
    "gn:asciiname":"Pantanelle",
    "gn:country_code":"IT",
    "gn:dem":62,
    "gn:feature_class":"P",
    "gn:feature_code":"PPL",
    "gn:name":"Pantanelle",
    "gn:population":448,
    "gn:timezone":"Europe/Rome",
    "iso:country":"IT",
    "wof:name":"Pantanelle",
    "wof:placetype":"locality",
    "wof:population":448
},
  "geometry": {"coordinates":[12.67795,41.53125],"type":"Point"}
}