{
  "type": "Feature",
  "properties": {
    "gn:admin1_code":"5",
    "gn:admin2_code":"PC",
    "gn:admin3_code":"33020.0",
    "gn:asciiname":"Tornarezza",
    "gn:country_code":"IT",
    "gn:dem":873,
    "gn:feature_class":"P",
    "gn:feature_code":"PPL",
    "gn:name":"Tornarezza",
    "gn:population":46,
    "gn:timezone":"Europe/Rome",
    "iso:country":"IT",
    "wof:name":"Tornarezza",
    "wof:placetype":"locality",
    "wof:population":46
},
  "geometry": {"coordinates":[9.43492,44.64806],"type":"Point"}
}