{
  "type": "Feature",
  "properties": {
    "gn:admin1_code":"9.0",
    "gn:admin2_code":"PV",
    "gn:admin3_code":"18143.0",
    "gn:asciiname":"Santa Maria della Versa",
    "gn:country_code":"IT",
    "gn:dem":198,
    "gn:elevation":"199.0",
    "gn:feature_class":"P",
    "gn:feature_code":"PPLA3",
    "gn:name":"Santa Maria della Versa",
    "gn:population":1534,
    "gn:timezone":"Europe/Rome",
    "iso:country":"IT",
    "wof:name":"Santa Maria della Versa",
    "wof:placetype":"locality",
    "wof:population":1534
},
  "geometry": {"coordinates":[9.29976,44.98757],"type":"Point"}
}