{
  "type": "Feature",
  "properties": {
    "gn:admin1_code":"20",
    "gn:admin2_code":"VR",
    "gn:admin3_code":"23087.0",
    "gn:asciiname":"Barbarani",
    "gn:country_code":"IT",
    "gn:dem":383,
    "gn:feature_class":"P",
    "gn:feature_code":"PPL",
    "gn:name":"Barbarani",
    "gn:population":34,
    "gn:timezone":"Europe/Rome",
    "iso:country":"IT",
    "wof:name":"Barbarani",
    "wof:placetype":"locality",
    "wof:population":34
},
  "geometry": {"coordinates":[11.15704,45.53761],"type":"Point"}
}