{
  "type": "Feature",
  "properties": {
    "gn:admin1_code":"4.0",
    "gn:admin3_code":"63049.0",
    "gn:asciiname":"Coroglio",
    "gn:country_code":"IT",
    "gn:dem":11,
    "gn:feature_class":"P",
    "gn:feature_code":"PPL",
    "gn:name":"Coroglio",
    "gn:population":0,
    "gn:timezone":"Europe/Rome",
    "iso:country":"IT",
    "wof:name":"Coroglio",
    "wof:placetype":"locality"
},
  "geometry": {"coordinates":[14.17554,40.80816],"type":"Point"}
}