{
  "type": "Feature",
  "properties": {
    "gn:gn_country":"IT",
    "gn:gn_fcode":"PPLA3",
    "gn:gn_pop":578,
    "gn:population":451,
    "iso:country":"IT",
    "name:bel_x_preferred":[
        "\u0410\u043f\u0440\u044b\u043a\u0430\u043b\u0435"
    ],
    "name:bul_x_preferred":[
        "\u0410\u043f\u0440\u0438\u043a\u0430\u043b\u0435"
    ],
    "name:cat_x_preferred":[
        "Apricale"
    ],
    "name:deu_x_preferred":[
        "Apricale"
    ],
    "name:eng_x_preferred":[
        "Apricale"
    ],
    "name:epo_x_preferred":[
        "Apricale"
    ],
    "name:eus_x_preferred":[
        "Apricale"
    ],
    "name:fas_x_preferred":[
        "\u0622\u067e\u0631\u06cc\u06a9\u0627\u0644\u0647"
    ],
    "name:fra_x_preferred":[
        "Apricale"
    ],
    "name:hun_x_preferred":[
        "Apricale"
    ],
    "name:hye_x_preferred":[
        "\u0531\u057a\u0580\u056b\u056f\u0561\u056c\u0565"
    ],
    "name:ina_x_preferred":[
        "Apricale"
    ],
    "name:ita_x_preferred":[
        "Apricale"
    ],
    "name:jpn_x_preferred":[
        "\u30a2\u30d7\u30ea\u30ab\u30fc\u30ec"
    ],
    "name:kaz_x_preferred":[
        "\u0410\u043f\u0440\u0438\u043a\u0430\u043b\u0435"
    ],
    "name:lat_x_preferred":[
        "Apricalae"
    ],
    "name:lij_x_preferred":[
        "Brigar"
    ],
    "name:lmo_x_preferred":[
        "Apricale"
    ],
    "name:msa_x_preferred":[
        "Apricale"
    ],
    "name:nan_x_preferred":[
        "Apricale"
    ],
    "name:nap_x_preferred":[
        "Apricale"
    ],
    "name:nld_x_preferred":[
        "Apricale"
    ],
    "name:oci_x_preferred":[
        "Avrigar"
    ],
    "name:pms_x_preferred":[
        "Apricale"
    ],
    "name:pol_x_preferred":[
        "Apricale"
    ],
    "name:por_x_preferred":[
        "Apricale"
    ],
    "name:ron_x_preferred":[
        "Apricale"
    ],
    "name:rus_x_preferred":[
        "\u0410\u043f\u0440\u0438\u043a\u0430\u043b\u0435"
    ],
    "name:scn_x_preferred":[
        "Apricale"
    ],
    "name:spa_x_preferred":[
        "Apricale"
    ],
    "name:srp_x_preferred":[
        "Apricale"
    ],
    "name:ukr_x_preferred":[
        "\u0410\u043f\u0440\u0438\u043a\u0430\u043b\u0435"
    ],
    "name:uzb_x_preferred":[
        "Apricale"
    ],
    "name:vie_x_preferred":[
        "Apricale"
    ],
    "name:vol_x_preferred":[
        "Apricale"
    ],
    "name:war_x_preferred":[
        "Apricale"
    ],
    "name:zho_x_preferred":[
        "\u963f\u666e\u91cc\u5361\u83b1"
    ],
    "qs_pg:aaroncc":"IT",
    "qs_pg:gn_country":"IT",
    "qs_pg:gn_fcode":"PPLA3",
    "qs_pg:gn_pop":578,
    "qs_pg:name":"Apricale",
    "qs_pg:name_adm0":"Italia",
    "qs_pg:name_adm1":"Liguria",
    "qs_pg:photos":913,
    "qs_pg:photos_1k":185,
    "qs_pg:photos_9k":4,
    "qs_pg:photos_9r":6,
    "qs_pg:photos_all":913,
    "qs_pg:photos_sr":10,
    "qs_pg:pop_sr":2,
    "qs_pg:qs_pg_placetype":"locality",
    "qs_pg:qs_pg_placetype_gp":"Town",
    "qs_pg:woe_adm0":23424853,
    "woe:adm0_id":23424853,
    "woe:name_adm0":"Italia",
    "woe:name_adm1":"Liguria",
    "woe:placetype":"Town",
    "wof:name":"Apricale",
    "wof:placetype":"locality",
    "wof:population":451
},
  "geometry": {"coordinates":[7.65934,43.88062],"type":"Point"}
}