{
  "type": "Feature",
  "properties": {
    "gn:admin1_code":"6.0",
    "gn:admin2_code":"UD",
    "gn:admin3_code":"30117.0",
    "gn:asciiname":"Coccau Valico",
    "gn:country_code":"IT",
    "gn:dem":674,
    "gn:feature_class":"P",
    "gn:feature_code":"PPL",
    "gn:name":"Coccau Valico",
    "gn:population":12,
    "gn:timezone":"Europe/Rome",
    "iso:country":"IT",
    "wof:name":"Coccau Valico",
    "wof:placetype":"locality",
    "wof:population":12
},
  "geometry": {"coordinates":[13.63937,46.53459],"type":"Point"}
}