{
  "type": "Feature",
  "properties": {
    "gn:admin1_code":"20",
    "gn:admin2_code":"VI",
    "gn:admin3_code":"24017.0",
    "gn:asciiname":"Capitagni",
    "gn:country_code":"IT",
    "gn:dem":147,
    "gn:feature_class":"P",
    "gn:feature_code":"PPL",
    "gn:name":"Capitagni",
    "gn:population":25,
    "gn:timezone":"Europe/Rome",
    "iso:country":"IT",
    "wof:name":"Capitagni",
    "wof:placetype":"locality",
    "wof:population":25
},
  "geometry": {"coordinates":[11.37379,45.58154],"type":"Point"}
}