{
  "type": "Feature",
  "properties": {
    "gn:admin1_code":"4.0",
    "gn:admin2_code":"AV",
    "gn:admin3_code":"64031.0",
    "gn:asciiname":"Casola",
    "gn:country_code":"IT",
    "gn:dem":135,
    "gn:feature_class":"P",
    "gn:feature_code":"PPL",
    "gn:name":"Casola",
    "gn:population":444,
    "gn:timezone":"Europe/Rome",
    "iso:country":"IT",
    "wof:name":"Casola",
    "wof:placetype":"locality",
    "wof:population":444
},
  "geometry": {"coordinates":[14.59972,40.88854],"type":"Point"}
}