{
  "type": "Feature",
  "properties": {
    "gn:admin1_code":"17",
    "gn:admin2_code":"TN",
    "gn:admin3_code":"22041.0",
    "gn:asciiname":"Aguai",
    "gn:country_code":"IT",
    "gn:dem":977,
    "gn:feature_class":"P",
    "gn:feature_code":"PPL",
    "gn:name":"Aguai",
    "gn:population":65,
    "gn:timezone":"Europe/Rome",
    "iso:country":"IT",
    "wof:name":"Aguai",
    "wof:placetype":"locality",
    "wof:population":65
},
  "geometry": {"coordinates":[11.40419,46.30007],"type":"Point"}
}