{
  "type": "Feature",
  "properties": {
    "gn:elevation":281,
    "gn:population":2137,
    "iso:country":"IT",
    "name:bul_x_preferred":[
        "\u0414\u0436\u0430\u043d\u0438\u043a\u043e"
    ],
    "name:cat_x_preferred":[
        "Gianico"
    ],
    "name:deu_x_preferred":[
        "Gianico"
    ],
    "name:eng_x_preferred":[
        "Gianico"
    ],
    "name:epo_x_preferred":[
        "Gianico"
    ],
    "name:eus_x_preferred":[
        "Gianico"
    ],
    "name:fas_x_preferred":[
        "\u062c\u06cc\u0627\u0646\u06cc\u06a9\u0648"
    ],
    "name:fra_x_preferred":[
        "Gianico"
    ],
    "name:hbs_x_preferred":[
        "Gianico"
    ],
    "name:hun_x_preferred":[
        "Gianico"
    ],
    "name:hye_x_preferred":[
        "\u054b\u0561\u0576\u056b\u056f\u0578"
    ],
    "name:ita_x_preferred":[
        "Gianico"
    ],
    "name:jpn_x_preferred":[
        "\u30b8\u30e3\u30fc\u30cb\u30b3"
    ],
    "name:kaz_x_preferred":[
        "\u0414\u0436\u0430\u043d\u0438\u043a\u043e"
    ],
    "name:lat_x_preferred":[
        "Ianicum"
    ],
    "name:lmo_x_preferred":[
        "Gi\u00e0nech"
    ],
    "name:msa_x_preferred":[
        "Gianico"
    ],
    "name:nap_x_preferred":[
        "Gianico"
    ],
    "name:nld_x_preferred":[
        "Gianico"
    ],
    "name:oci_x_preferred":[
        "Gianico"
    ],
    "name:pms_x_preferred":[
        "Gianico"
    ],
    "name:pol_x_preferred":[
        "Gianico"
    ],
    "name:por_x_preferred":[
        "Gianico"
    ],
    "name:ron_x_preferred":[
        "Gianico"
    ],
    "name:rus_x_preferred":[
        "\u0414\u0436\u0430\u043d\u0438\u043a\u043e"
    ],
    "name:scn_x_preferred":[
        "Gianico"
    ],
    "name:spa_x_preferred":[
        "Gianico"
    ],
    "name:srp_x_preferred":[
        "\u040f\u0430\u043d\u0438\u043a\u043e"
    ],
    "name:tgl_x_preferred":[
        "Gianico"
    ],
    "name:ukr_x_preferred":[
        "\u0414\u0436\u0430\u043d\u0456\u043a\u043e"
    ],
    "name:uzb_x_preferred":[
        "Gianico"
    ],
    "name:vie_x_preferred":[
        "Gianico"
    ],
    "name:vol_x_preferred":[
        "Gianico"
    ],
    "name:war_x_preferred":[
        "Gianico"
    ],
    "name:zho_x_preferred":[
        "\u8d3e\u5c3c\u79d1"
    ],
    "qs:a0":"Italia",
    "qs:a1":"*Brescia",
    "qs:a1r":"0Lombardia",
    "qs:adm0":"Italia",
    "qs:la_lc":"*",
    "qs:level":"locality",
    "qs:loc":"Gianico",
    "qs:loc_alt":"Gianico",
    "qs:pop":0,
    "qs:type":"buffered point",
    "wd:wordcount":18,
    "wof:lang":[
        "ita"
    ],
    "wof:name":"Gianico",
    "wof:placetype":"locality",
    "wof:population":2137
},
  "geometry": {"coordinates":[10.173885,45.860758],"type":"Point"}
}