{
  "type": "Feature",
  "properties": {
    "gn:admin1_code":"10.0",
    "gn:admin2_code":"AP",
    "gn:admin3_code":"44007.0",
    "gn:asciiname":"Colle di Funti",
    "gn:country_code":"IT",
    "gn:dem":485,
    "gn:feature_class":"P",
    "gn:feature_code":"PPL",
    "gn:name":"Colle di Funti",
    "gn:population":9,
    "gn:timezone":"Europe/Rome",
    "iso:country":"IT",
    "wof:name":"Colle di Funti",
    "wof:placetype":"locality",
    "wof:population":9
},
  "geometry": {"coordinates":[13.51104,42.80763],"type":"Point"}
}