{
  "type": "Feature",
  "properties": {
    "gn:admin1_code":"8",
    "gn:admin2_code":"GE",
    "gn:admin3_code":"10056.0",
    "gn:asciiname":"Amborzasco",
    "gn:country_code":"IT",
    "gn:dem":878,
    "gn:feature_class":"P",
    "gn:feature_code":"PPL",
    "gn:name":"Amborzasco",
    "gn:population":94,
    "gn:timezone":"Europe/Rome",
    "iso:country":"IT",
    "wof:name":"Amborzasco",
    "wof:placetype":"locality",
    "wof:population":94
},
  "geometry": {"coordinates":[9.4566,44.51463],"type":"Point"}
}