{
  "type": "Feature",
  "properties": {
    "gn:gn_country":"IT",
    "gn:gn_fcode":"PPLA3",
    "gn:gn_pop":245,
    "gn:population":88,
    "iso:country":"IT",
    "name:ara_x_preferred":[
        "\u0633\u0648\u0644\u0646\u063a\u064a\u0644\u0648"
    ],
    "name:arm_x_preferred":[
        "\u054d\u0578\u056c\u0578\u0576\u0563\u0565\u056c\u0578"
    ],
    "name:baq_x_preferred":[
        "Solonghello"
    ],
    "name:bel_x_preferred":[
        "\u0421\u0430\u043b\u0430\u043d\u0433\u0435\u043b\u0430\u043e"
    ],
    "name:bul_x_preferred":[
        "\u0421\u043e\u043b\u043e\u043d\u0433\u0435\u043b\u043e"
    ],
    "name:cat_x_preferred":[
        "Solonghello"
    ],
    "name:chi_x_preferred":[
        "\u7d22\u9686\u76d6\u6d1b"
    ],
    "name:dut_x_preferred":[
        "Solonghello"
    ],
    "name:eng_x_preferred":[
        "Solonghello"
    ],
    "name:epo_x_preferred":[
        "Solonghello"
    ],
    "name:fre_x_preferred":[
        "Solonghello"
    ],
    "name:ger_x_preferred":[
        "Solonghello"
    ],
    "name:hun_x_preferred":[
        "Solonghello"
    ],
    "name:ind_x_preferred":[
        "Solonghello"
    ],
    "name:ita_x_preferred":[
        "Solonghello"
    ],
    "name:jpn_x_preferred":[
        "\u30bd\u30ed\u30f3\u30b2\u30c3\u30ed"
    ],
    "name:kaz_x_preferred":[
        "\u0421\u043e\u043b\u043e\u043d\u0433\u0435\u043b\u043b\u043e"
    ],
    "name:lat_x_preferred":[
        "Saulingellum"
    ],
    "name:lmo_x_preferred":[
        "Solonghello"
    ],
    "name:may_x_preferred":[
        "Solonghello"
    ],
    "name:nan_x_preferred":[
        "Solonghello"
    ],
    "name:nap_x_preferred":[
        "Solonghello"
    ],
    "name:oci_x_preferred":[
        "Solonghello"
    ],
    "name:per_x_preferred":[
        "\u0633\u0648\u0644\u0648\u0646\u06af\u0644\u0648"
    ],
    "name:pms_x_preferred":[
        "Slongh\u00e9"
    ],
    "name:pol_x_preferred":[
        "Solonghello"
    ],
    "name:por_x_preferred":[
        "Solonghello"
    ],
    "name:rum_x_preferred":[
        "Solonghello"
    ],
    "name:rus_x_preferred":[
        "\u0421\u043e\u043b\u043e\u043d\u0433\u0435\u043b\u043b\u043e"
    ],
    "name:scn_x_preferred":[
        "Solonghello"
    ],
    "name:spa_x_preferred":[
        "Solonghello"
    ],
    "name:srp_x_preferred":[
        "Solonghello"
    ],
    "name:tgl_x_preferred":[
        "Solonghello"
    ],
    "name:ukr_x_preferred":[
        "\u0421\u043e\u043b\u043e\u043d\u0433\u0435\u043b\u043b\u043e"
    ],
    "name:uzb_x_preferred":[
        "Solonghello"
    ],
    "name:vie_x_preferred":[
        "Solonghello"
    ],
    "name:vol_x_preferred":[
        "Solonghello"
    ],
    "name:war_x_preferred":[
        "Solonghello"
    ],
    "qs_pg:aaroncc":"IT",
    "qs_pg:gn_country":"IT",
    "qs_pg:gn_fcode":"PPLA3",
    "qs_pg:gn_pop":245,
    "qs_pg:name":"Solonghello",
    "qs_pg:name_adm0":"Italia",
    "qs_pg:name_adm1":"Piemonte",
    "qs_pg:photos_9r":0,
    "qs_pg:photos_sr":0,
    "qs_pg:pop_sr":2,
    "qs_pg:qs_pg_placetype":"locality",
    "qs_pg:qs_pg_placetype_gp":"Town",
    "qs_pg:woe_adm0":23424853,
    "woe:adm0_id":23424853,
    "woe:name_adm0":"Italia",
    "woe:name_adm1":"Piemonte",
    "woe:placetype":"Town",
    "wof:name":"Solonghello",
    "wof:placetype":"locality",
    "wof:population":88
},
  "geometry": {"coordinates":[8.28323,45.12905],"type":"Point"}
}