{
  "type": "Feature",
  "properties": {
    "gn:admin1_code":"12",
    "gn:admin2_code":"AT",
    "gn:admin3_code":"5005.0",
    "gn:asciiname":"Quaranta",
    "gn:country_code":"IT",
    "gn:dem":148,
    "gn:feature_class":"P",
    "gn:feature_code":"PPL",
    "gn:name":"Quaranta",
    "gn:population":25,
    "gn:timezone":"Europe/Rome",
    "iso:country":"IT",
    "name:deu_x_preferred":[
        "Quaranta"
    ],
    "wof:name":"Quaranta",
    "wof:placetype":"locality",
    "wof:population":25
},
  "geometry": {"coordinates":[8.15776,44.9157],"type":"Point"}
}