{
  "type": "Feature",
  "properties": {
    "gn:admin1_code":"20",
    "gn:admin2_code":"TV",
    "gn:admin3_code":"26073.0",
    "gn:asciiname":"San Michele",
    "gn:country_code":"IT",
    "gn:dem":138,
    "gn:feature_class":"P",
    "gn:feature_code":"PPL",
    "gn:name":"San Michele",
    "gn:population":270,
    "gn:timezone":"Europe/Rome",
    "iso:country":"IT",
    "wof:name":"San Michele",
    "wof:placetype":"locality",
    "wof:population":270
},
  "geometry": {"coordinates":[12.25028,45.88026],"type":"Point"}
}