{
  "type": "Feature",
  "properties": {
    "gn:admin1_code":"5",
    "gn:admin2_code":"PR",
    "gn:admin3_code":"34028.0",
    "gn:asciiname":"Mariano Case-Dell'Asta",
    "gn:country_code":"IT",
    "gn:dem":525,
    "gn:feature_class":"P",
    "gn:feature_code":"PPL",
    "gn:name":"Mariano Case-Dell'Asta",
    "gn:population":11,
    "gn:timezone":"Europe/Rome",
    "iso:country":"IT",
    "wof:name":"Mariano Case-Dell'Asta",
    "wof:placetype":"locality",
    "wof:population":11
},
  "geometry": {"coordinates":[9.96614,44.72766],"type":"Point"}
}