{
  "type": "Feature",
  "properties": {
    "gn:admin1_code":"9",
    "gn:admin2_code":"BG",
    "gn:admin3_code":"16035.0",
    "gn:asciiname":"Zubioni",
    "gn:country_code":"IT",
    "gn:dem":547,
    "gn:feature_class":"P",
    "gn:feature_code":"PPL",
    "gn:name":"Zubioni",
    "gn:population":31,
    "gn:timezone":"Europe/Rome",
    "iso:country":"IT",
    "wof:name":"Zubioni",
    "wof:placetype":"locality",
    "wof:population":31
},
  "geometry": {"coordinates":[9.69813,45.81421],"type":"Point"}
}