{
  "type": "Feature",
  "properties": {
    "gn:admin1_code":"17.0",
    "gn:admin2_code":"TN",
    "gn:admin3_code":"22062.0",
    "gn:asciiname":"Dres",
    "gn:country_code":"IT",
    "gn:dem":652,
    "gn:elevation":"661.0",
    "gn:feature_class":"P",
    "gn:feature_code":"PPLL",
    "gn:name":"Dres",
    "gn:population":237,
    "gn:timezone":"Europe/Rome",
    "iso:country":"IT",
    "name:ita_x_preferred":[
        "Dres"
    ],
    "wof:name":"Dres",
    "wof:placetype":"locality",
    "wof:population":237
},
  "geometry": {"coordinates":[11.03379,46.37308],"type":"Point"}
}