{
  "type": "Feature",
  "properties": {
    "iso:country":"IT",
    "qs_pg:aaroncc":"IT",
    "qs_pg:name":"Cipiccia",
    "qs_pg:name_adm0":"Italia",
    "qs_pg:name_adm1":"Umbria",
    "qs_pg:photos":1907,
    "qs_pg:photos_1k":386,
    "qs_pg:photos_9k":8,
    "qs_pg:photos_9r":9,
    "qs_pg:photos_all":1907,
    "qs_pg:photos_sr":15,
    "qs_pg:pop_sr":0,
    "qs_pg:qs_pg_placetype":"locality",
    "qs_pg:qs_pg_placetype_gp":"Town",
    "qs_pg:woe_adm0":23424853,
    "woe:adm0_id":23424853,
    "woe:name_adm0":"Italia",
    "woe:name_adm1":"Umbria",
    "woe:placetype":"Town",
    "wof:name":"Cipiccia",
    "wof:placetype":"locality"
},
  "geometry": {"coordinates":[12.57341,42.502998],"type":"Point"}
}