{
  "type": "Feature",
  "properties": {
    "gn:admin1_code":"5.0",
    "gn:admin2_code":"BO",
    "gn:admin3_code":"37061.0",
    "gn:asciiname":"Castelletto",
    "gn:country_code":"IT",
    "gn:dem":185,
    "gn:feature_class":"P",
    "gn:feature_code":"PPLA3",
    "gn:name":"Castelletto",
    "gn:population":2125,
    "gn:timezone":"Europe/Rome",
    "iso:country":"IT",
    "name:ceb_x_preferred":[
        "Castelletto"
    ],
    "name:deu_x_preferred":[
        "Castelletto"
    ],
    "name:ita_x_preferred":[
        "Castelletto"
    ],
    "name:lat_x_preferred":[
        "Castellettum"
    ],
    "name:pms_x_preferred":[
        "Castl\u00e8t"
    ],
    "name:por_x_preferred":[
        "Castelletto"
    ],
    "name:rus_x_preferred":[
        "\u041a\u0430\u0441\u0442\u0435\u043b\u043b\u0435\u0442\u0442\u043e"
    ],
    "name:sco_x_preferred":[
        "Castelletto"
    ],
    "name:srp_x_preferred":[
        "Kasteleto"
    ],
    "name:swe_x_preferred":[
        "Castelletto"
    ],
    "wof:name":"Castelletto",
    "wof:placetype":"locality",
    "wof:population":2125
},
  "geometry": {"coordinates":[11.06478,44.44015],"type":"Point"}
}