{
  "type": "Feature",
  "properties": {
    "gn:admin1_code":"6",
    "gn:admin2_code":"UD",
    "gn:admin3_code":"30085.0",
    "gn:asciiname":"Cras",
    "gn:country_code":"IT",
    "gn:dem":146,
    "gn:feature_class":"P",
    "gn:feature_code":"PPL",
    "gn:name":"Cras",
    "gn:population":18,
    "gn:timezone":"Europe/Rome",
    "iso:country":"IT",
    "wof:name":"Cras",
    "wof:placetype":"locality",
    "wof:population":18
},
  "geometry": {"coordinates":[13.51329,46.06375],"type":"Point"}
}