{
  "type": "Feature",
  "properties": {
    "gn:admin1_code":"6",
    "gn:admin2_code":"UD",
    "gn:admin3_code":"30085.0",
    "gn:asciiname":"Cras",
    "gn:country_code":"IT",
    "gn:dem":146,
    "gn:feature_class":"P",
    "gn:feature_code":"PPL",
    "gn:name":"Cras",
    "gn:population":18,
    "gn:timezone":"Europe/Rome",
    "iso:country":"IT",
    "name:cat_x_preferred":[
        "Cras"
    ],
    "name:ceb_x_preferred":[
        "Cras"
    ],
    "name:deu_x_preferred":[
        "Cras"
    ],
    "name:fra_x_preferred":[
        "Cras"
    ],
    "name:ita_x_preferred":[
        "Cras"
    ],
    "name:lmo_x_preferred":[
        "Cras"
    ],
    "name:nds_x_preferred":[
        "Cras"
    ],
    "name:nld_x_preferred":[
        "Cras"
    ],
    "name:pms_x_preferred":[
        "Cras"
    ],
    "name:pol_x_preferred":[
        "Cras"
    ],
    "name:por_x_preferred":[
        "Cras"
    ],
    "name:rus_x_preferred":[
        "\u041a\u0440\u0430\u0441"
    ],
    "name:scn_x_preferred":[
        "Cras"
    ],
    "name:slk_x_preferred":[
        "Cras"
    ],
    "name:spa_x_preferred":[
        "Cras"
    ],
    "name:swe_x_preferred":[
        "Cras"
    ],
    "name:ukr_x_preferred":[
        "\u041a\u0440\u0430\u0441"
    ],
    "wof:name":"Cras",
    "wof:placetype":"locality",
    "wof:population":18
},
  "geometry": {"coordinates":[13.51329,46.06375],"type":"Point"}
}