{
  "type": "Feature",
  "properties": {
    "gn:admin1_code":"12",
    "gn:admin2_code":"TO",
    "gn:admin3_code":"1119.0",
    "gn:asciiname":"Vigna",
    "gn:country_code":"IT",
    "gn:dem":423,
    "gn:feature_class":"P",
    "gn:feature_code":"PPL",
    "gn:name":"Vigna",
    "gn:population":30,
    "gn:timezone":"Europe/Rome",
    "iso:country":"IT",
    "wof:name":"Vigna",
    "wof:placetype":"locality",
    "wof:population":30
},
  "geometry": {"coordinates":[7.56673,45.26239],"type":"Point"}
}