{
  "type": "Feature",
  "properties": {
    "gn:admin1_code":"20.0",
    "gn:admin2_code":"TV",
    "gn:admin3_code":"26038.0",
    "gn:asciiname":"Borgo Dall'Armellina II",
    "gn:country_code":"IT",
    "gn:dem":43,
    "gn:feature_class":"P",
    "gn:feature_code":"PPL",
    "gn:name":"Borgo Dall'Armellina II",
    "gn:population":23,
    "gn:timezone":"Europe/Rome",
    "iso:country":"IT",
    "wof:name":"Borgo Dall'Armellina II",
    "wof:placetype":"locality",
    "wof:population":23
},
  "geometry": {"coordinates":[12.32956,45.83489],"type":"Point"}
}