{
  "type": "Feature",
  "properties": {
    "gn:admin1_code":"20",
    "gn:admin2_code":"VI",
    "gn:admin3_code":"24057.0",
    "gn:asciiname":"San Luca",
    "gn:country_code":"IT",
    "gn:dem":443,
    "gn:feature_class":"P",
    "gn:feature_code":"PPL",
    "gn:name":"San Luca",
    "gn:population":159,
    "gn:timezone":"Europe/Rome",
    "iso:country":"IT",
    "wof:name":"San Luca",
    "wof:placetype":"locality",
    "wof:population":159
},
  "geometry": {"coordinates":[11.60648,45.76159000000001],"type":"Point"}
}