{
  "type": "Feature",
  "properties": {
    "gn:admin1_code":"5.0",
    "gn:admin2_code":"PR",
    "gn:admin3_code":"34028.0",
    "gn:asciiname":"La Valle",
    "gn:country_code":"IT",
    "gn:dem":443,
    "gn:feature_class":"P",
    "gn:feature_code":"PPL",
    "gn:name":"La Valle",
    "gn:population":0,
    "gn:timezone":"Europe/Rome",
    "iso:country":"IT",
    "wof:name":"La Valle",
    "wof:placetype":"locality"
},
  "geometry": {"coordinates":[9.93333,44.78333],"type":"Point"}
}