{
  "type": "Feature",
  "properties": {
    "gn:admin1_code":"6.0",
    "gn:admin2_code":"UD",
    "gn:admin3_code":"30113.0",
    "gn:asciiname":"Cornappo",
    "gn:country_code":"IT",
    "gn:dem":494,
    "gn:elevation":"521.0",
    "gn:feature_class":"P",
    "gn:feature_code":"PPL",
    "gn:name":"Cornappo",
    "gn:population":46,
    "gn:timezone":"Europe/Rome",
    "iso:country":"IT",
    "wof:name":"Cornappo",
    "wof:placetype":"locality",
    "wof:population":46
},
  "geometry": {"coordinates":[13.33896,46.27196],"type":"Point"}
}