{
  "type": "Feature",
  "properties": {
    "gn:admin1_code":"7",
    "gn:admin2_code":"FR",
    "gn:admin3_code":"60024.0",
    "gn:asciiname":"Sindici",
    "gn:country_code":"IT",
    "gn:dem":133,
    "gn:feature_class":"P",
    "gn:feature_code":"PPL",
    "gn:name":"Sindici",
    "gn:population":50,
    "gn:timezone":"Europe/Rome",
    "iso:country":"IT",
    "wof:name":"Sindici",
    "wof:placetype":"locality",
    "wof:population":50
},
  "geometry": {"coordinates":[13.3016,41.5828],"type":"Point"}
}