{
  "type": "Feature",
  "properties": {
    "gn:admin1_code":"10",
    "gn:admin2_code":"MC",
    "gn:admin3_code":"43049.0",
    "gn:asciiname":"Bisio",
    "gn:country_code":"IT",
    "gn:dem":567,
    "gn:feature_class":"P",
    "gn:feature_code":"PPL",
    "gn:name":"Bisio",
    "gn:population":25,
    "gn:timezone":"Europe/Rome",
    "iso:country":"IT",
    "name:deu_x_preferred":[
        "Bisio"
    ],
    "name:epo_x_preferred":[
        "Bisio"
    ],
    "name:fra_x_preferred":[
        "Bisio"
    ],
    "name:ita_x_preferred":[
        "Bisio"
    ],
    "wof:name":"Bisio",
    "wof:placetype":"locality",
    "wof:population":25
},
  "geometry": {"coordinates":[13.28779,43.01476],"type":"Point"}
}