{
  "type": "Feature",
  "properties": {
    "gn:admin1_code":"20",
    "gn:admin2_code":"PD",
    "gn:admin3_code":"28030.0",
    "gn:asciiname":"Boccalara",
    "gn:country_code":"IT",
    "gn:dem":20,
    "gn:feature_class":"P",
    "gn:feature_code":"PPL",
    "gn:name":"Boccalara",
    "gn:population":67,
    "gn:timezone":"Europe/Rome",
    "iso:country":"IT",
    "wof:name":"Boccalara",
    "wof:placetype":"locality",
    "wof:population":67
},
  "geometry": {"coordinates":[11.69726,45.41722],"type":"Point"}
}