{
  "type": "Feature",
  "properties": {
    "gn:admin1_code":"9",
    "gn:admin2_code":"VA",
    "gn:admin3_code":"12092.0",
    "gn:asciiname":"Longhirolo",
    "gn:country_code":"IT",
    "gn:dem":431,
    "gn:feature_class":"P",
    "gn:feature_code":"PPL",
    "gn:name":"Longhirolo",
    "gn:population":235,
    "gn:timezone":"Europe/Rome",
    "iso:country":"IT",
    "wof:name":"Longhirolo",
    "wof:placetype":"locality",
    "wof:population":235
},
  "geometry": {"coordinates":[8.77327,46.00492],"type":"Point"}
}