{
  "type": "Feature",
  "properties": {
    "gn:admin1_code":"5",
    "gn:admin2_code":"BO",
    "gn:admin3_code":"37024.0",
    "gn:asciiname":"Vigna",
    "gn:country_code":"IT",
    "gn:dem":15,
    "gn:feature_class":"P",
    "gn:feature_code":"PPL",
    "gn:name":"Vigna",
    "gn:population":18,
    "gn:timezone":"Europe/Rome",
    "iso:country":"IT",
    "wof:name":"Vigna",
    "wof:placetype":"locality",
    "wof:population":18
},
  "geometry": {"coordinates":[11.233,44.7873],"type":"Point"}
}