{
  "type": "Feature",
  "properties": {
    "gn:admin1_code":"12",
    "gn:admin2_code":"AL",
    "gn:admin3_code":"6146.0",
    "gn:asciiname":"Villa",
    "gn:country_code":"IT",
    "gn:dem":698,
    "gn:feature_class":"P",
    "gn:feature_code":"PPL",
    "gn:name":"Villa",
    "gn:population":17,
    "gn:timezone":"Europe/Rome",
    "iso:country":"IT",
    "wof:name":"Villa",
    "wof:placetype":"locality",
    "wof:population":17
},
  "geometry": {"coordinates":[9.00417,44.67886],"type":"Point"}
}