{
  "type": "Feature",
  "properties": {
    "gn:admin1_code":"9",
    "gn:admin2_code":"CO",
    "gn:admin3_code":"13013.0",
    "gn:asciiname":"Mudronno",
    "gn:country_code":"IT",
    "gn:dem":629,
    "gn:feature_class":"P",
    "gn:feature_code":"PPL",
    "gn:name":"Mudronno",
    "gn:population":36,
    "gn:timezone":"Europe/Rome",
    "iso:country":"IT",
    "wof:name":"Mudronno",
    "wof:placetype":"locality",
    "wof:population":36
},
  "geometry": {"coordinates":[9.25423,45.87151],"type":"Point"}
}