{
  "type": "Feature",
  "properties": {
    "gn:admin1_code":"10",
    "gn:admin2_code":"AN",
    "gn:admin3_code":"42020.0",
    "gn:asciiname":"Colcello",
    "gn:country_code":"IT",
    "gn:dem":426,
    "gn:feature_class":"P",
    "gn:feature_code":"PPL",
    "gn:name":"Colcello",
    "gn:population":81,
    "gn:timezone":"Europe/Rome",
    "iso:country":"IT",
    "wof:name":"Colcello",
    "wof:placetype":"locality",
    "wof:population":81
},
  "geometry": {"coordinates":[12.92016,43.41409],"type":"Point"}
}