{
  "type": "Feature",
  "properties": {
    "gn:admin1_code":"10",
    "gn:admin2_code":"PU",
    "gn:admin3_code":"41007.0",
    "gn:asciiname":"Montione",
    "gn:country_code":"IT",
    "gn:dem":327,
    "gn:feature_class":"P",
    "gn:feature_code":"PPL",
    "gn:name":"Montione",
    "gn:population":13,
    "gn:timezone":"Europe/Rome",
    "iso:country":"IT",
    "name:ita_x_preferred":[
        "Montione"
    ],
    "wof:name":"Montione",
    "wof:placetype":"locality",
    "wof:population":13
},
  "geometry": {"coordinates":[12.66551,43.58967],"type":"Point"}
}