{
  "type": "Feature",
  "properties": {
    "gn:admin1_code":"12",
    "gn:admin2_code":"AT",
    "gn:admin3_code":"5084.0",
    "gn:asciiname":"Vallunga",
    "gn:country_code":"IT",
    "gn:dem":241,
    "gn:feature_class":"P",
    "gn:feature_code":"PPL",
    "gn:name":"Vallunga",
    "gn:population":116,
    "gn:timezone":"Europe/Rome",
    "iso:country":"IT",
    "wof:name":"Vallunga",
    "wof:placetype":"locality",
    "wof:population":116
},
  "geometry": {"coordinates":[8.0561,45.01459000000001],"type":"Point"}
}