{
  "type": "Feature",
  "properties": {
    "gn:admin1_code":"12.0",
    "gn:admin2_code":"AT",
    "gn:admin3_code":"5030.0",
    "gn:asciiname":"Preie",
    "gn:country_code":"IT",
    "gn:dem":231,
    "gn:elevation":"251.0",
    "gn:feature_class":"P",
    "gn:feature_code":"PPL",
    "gn:name":"Preie",
    "gn:population":63,
    "gn:timezone":"Europe/Rome",
    "iso:country":"IT",
    "wof:name":"Preie",
    "wof:placetype":"locality",
    "wof:population":63
},
  "geometry": {"coordinates":[8.28507,44.79214],"type":"Point"}
}