{
  "type": "Feature",
  "properties": {
    "gn:admin1_code":"3",
    "gn:admin2_code":"CZ",
    "gn:admin3_code":"79060.0",
    "gn:asciiname":"Maiolino",
    "gn:country_code":"IT",
    "gn:dem":55,
    "gn:feature_class":"P",
    "gn:feature_code":"PPL",
    "gn:name":"Maiolino",
    "gn:population":19,
    "gn:timezone":"Europe/Rome",
    "iso:country":"IT",
    "wof:name":"Maiolino",
    "wof:placetype":"locality",
    "wof:population":19
},
  "geometry": {"coordinates":[16.16017,38.96173],"type":"Point"}
}