{
  "type": "Feature",
  "properties": {
    "gn:admin1_code":"3",
    "gn:admin2_code":"CS",
    "gn:admin3_code":"78003.0",
    "gn:asciiname":"Pietremarine",
    "gn:country_code":"IT",
    "gn:dem":719,
    "gn:feature_class":"P",
    "gn:feature_code":"PPL",
    "gn:name":"Pietremarine",
    "gn:population":240,
    "gn:timezone":"Europe/Rome",
    "iso:country":"IT",
    "wof:name":"Pietremarine",
    "wof:placetype":"locality",
    "wof:population":240
},
  "geometry": {"coordinates":[16.40862000000001,39.51195],"type":"Point"}
}