{
  "type": "Feature",
  "properties": {
    "gn:admin1_code":"5",
    "gn:admin2_code":"PC",
    "gn:admin3_code":"33041.0",
    "gn:asciiname":"Torri di Sopra",
    "gn:country_code":"IT",
    "gn:dem":44,
    "gn:feature_class":"P",
    "gn:feature_code":"PPL",
    "gn:name":"Torri di Sopra",
    "gn:population":15,
    "gn:timezone":"Europe/Rome",
    "iso:country":"IT",
    "wof:name":"Torri di Sopra",
    "wof:placetype":"locality",
    "wof:population":15
},
  "geometry": {"coordinates":[9.93382,45.03576],"type":"Point"}
}