{
  "type": "Feature",
  "properties": {
    "gn:admin1_code":"5",
    "gn:admin2_code":"PR",
    "gn:admin3_code":"34018.0",
    "gn:asciiname":"Berzola",
    "gn:country_code":"IT",
    "gn:dem":305,
    "gn:feature_class":"P",
    "gn:feature_code":"PPL",
    "gn:name":"Berzola",
    "gn:population":37,
    "gn:timezone":"Europe/Rome",
    "iso:country":"IT",
    "wof:name":"Berzola",
    "wof:placetype":"locality",
    "wof:population":37
},
  "geometry": {"coordinates":[10.2471,44.58982],"type":"Point"}
}