{
  "type": "Feature",
  "properties": {
    "gn:admin1_code":"9.0",
    "gn:admin2_code":"VA",
    "gn:admin3_code":"12129.0",
    "gn:asciiname":"Monti di Bassano",
    "gn:country_code":"IT",
    "gn:dem":950,
    "gn:feature_class":"P",
    "gn:feature_code":"PPL",
    "gn:name":"Monti di Bassano",
    "gn:population":0,
    "gn:timezone":"Europe/Rome",
    "iso:country":"IT",
    "wof:name":"Monti di Bassano",
    "wof:placetype":"locality"
},
  "geometry": {"coordinates":[8.75137,46.08412],"type":"Point"}
}