{
  "type": "Feature",
  "properties": {
    "gn:admin1_code":"15",
    "gn:admin2_code":"CL",
    "gn:admin3_code":"85007.0",
    "gn:asciiname":"Piana del Signore",
    "gn:country_code":"IT",
    "gn:dem":10,
    "gn:feature_class":"P",
    "gn:feature_code":"PPL",
    "gn:name":"Piana del Signore",
    "gn:population":15,
    "gn:timezone":"Europe/Rome",
    "iso:country":"IT",
    "wof:name":"Piana del Signore",
    "wof:placetype":"locality",
    "wof:population":15
},
  "geometry": {"coordinates":[14.28361,37.05696],"type":"Point"}
}