{
  "type": "Feature",
  "properties": {
    "gn:admin1_code":"4.0",
    "gn:admin2_code":"SA",
    "gn:admin3_code":"65082.0",
    "gn:asciiname":"Salitto-Valle",
    "gn:country_code":"IT",
    "gn:dem":372,
    "gn:feature_class":"P",
    "gn:feature_code":"PPL",
    "gn:name":"Salitto-Valle",
    "gn:population":1557,
    "gn:timezone":"Europe/Rome",
    "iso:country":"IT",
    "wof:name":"Salitto-Valle",
    "wof:placetype":"locality",
    "wof:population":1557
},
  "geometry": {"coordinates":[15.02241,40.67412],"type":"Point"}
}