{
  "type": "Feature",
  "properties": {
    "gn:admin1_code":"1",
    "gn:admin2_code":"PE",
    "gn:admin3_code":"68005.0",
    "gn:asciiname":"Cirichiello",
    "gn:country_code":"IT",
    "gn:dem":328,
    "gn:feature_class":"P",
    "gn:feature_code":"PPL",
    "gn:name":"Cirichiello",
    "gn:population":23,
    "gn:timezone":"Europe/Rome",
    "iso:country":"IT",
    "wof:name":"Cirichiello",
    "wof:placetype":"locality",
    "wof:population":23
},
  "geometry": {"coordinates":[13.81237,42.24011],"type":"Point"}
}