{
  "type": "Feature",
  "properties": {
    "gn:admin1_code":"9",
    "gn:admin2_code":"CR",
    "gn:admin3_code":"19040.0",
    "gn:asciiname":"Ca' de' Cervi",
    "gn:country_code":"IT",
    "gn:dem":35,
    "gn:feature_class":"P",
    "gn:feature_code":"PPLL",
    "gn:name":"Ca' de' Cervi",
    "gn:population":8,
    "gn:timezone":"Europe/Rome",
    "iso:country":"IT",
    "wof:name":"Ca' de' Cervi",
    "wof:placetype":"locality",
    "wof:population":8
},
  "geometry": {"coordinates":[10.23995,45.12596],"type":"Point"}
}