{
  "type": "Feature",
  "properties": {
    "gn:admin1_code":"18",
    "gn:admin2_code":"TR",
    "gn:admin3_code":"55007.0",
    "gn:asciiname":"Ponte",
    "gn:country_code":"IT",
    "gn:dem":108,
    "gn:feature_class":"P",
    "gn:feature_code":"PPL",
    "gn:name":"Ponte",
    "gn:population":39,
    "gn:timezone":"Europe/Rome",
    "iso:country":"IT",
    "name:bul_x_preferred":[
        "\u041f\u043e\u043d\u0442\u0435"
    ],
    "name:cat_x_preferred":[
        "Ponte"
    ],
    "name:ceb_x_preferred":[
        "Ponte"
    ],
    "name:deu_x_preferred":[
        "Ponte"
    ],
    "name:epo_x_preferred":[
        "Ponte"
    ],
    "name:fas_x_preferred":[
        "\u067e\u0648\u0646\u062a\u0647"
    ],
    "name:fra_x_preferred":[
        "Ponte"
    ],
    "name:glg_x_preferred":[
        "Ponte"
    ],
    "name:heb_x_preferred":[
        "\u05e4\u05d5\u05e0\u05d8\u05d4"
    ],
    "name:hye_x_preferred":[
        "\u054a\u0578\u0576\u057f\u0565"
    ],
    "name:ita_x_preferred":[
        "Ponte"
    ],
    "name:jpn_x_preferred":[
        "\u30dd\u30f3\u30c6"
    ],
    "name:kaz_x_preferred":[
        "\u041f\u043e\u043d\u0442\u0435"
    ],
    "name:nld_x_preferred":[
        "Ponte"
    ],
    "name:pol_x_preferred":[
        "Ponte"
    ],
    "name:por_x_preferred":[
        "Ponte"
    ],
    "name:rus_x_preferred":[
        "\u041f\u043e\u043d\u0442\u0435"
    ],
    "name:spa_x_preferred":[
        "Ponte"
    ],
    "name:srp_x_preferred":[
        "Ponte"
    ],
    "name:swe_x_preferred":[
        "Ponte"
    ],
    "name:ukr_x_preferred":[
        "\u041f\u043e\u043d\u0442\u0435"
    ],
    "wof:name":"Ponte",
    "wof:placetype":"locality",
    "wof:population":39
},
  "geometry": {"coordinates":[12.20947,42.68903],"type":"Point"}
}