{
  "type": "Feature",
  "properties": {
    "gn:admin1_code":"12",
    "gn:admin2_code":"CN",
    "gn:admin3_code":"4126.0",
    "gn:asciiname":"Doni",
    "gn:country_code":"IT",
    "gn:dem":526,
    "gn:feature_class":"P",
    "gn:feature_code":"PPL",
    "gn:name":"Doni",
    "gn:population":35,
    "gn:timezone":"Europe/Rome",
    "iso:country":"IT",
    "name:deu_x_preferred":[
        "Doni"
    ],
    "name:fra_x_preferred":[
        "Doni"
    ],
    "name:ita_x_preferred":[
        "Doni"
    ],
    "name:nld_x_preferred":[
        "Doni"
    ],
    "name:por_x_preferred":[
        "Doni"
    ],
    "name:vie_x_preferred":[
        "Doni"
    ],
    "wof:name":"Doni",
    "wof:placetype":"locality",
    "wof:population":35
},
  "geometry": {"coordinates":[7.82365,44.33787],"type":"Point"}
}