{
  "type": "Feature",
  "properties": {
    "gn:admin1_code":"5",
    "gn:admin2_code":"RA",
    "gn:admin3_code":"39010.0",
    "gn:asciiname":"Crociaro",
    "gn:country_code":"IT",
    "gn:dem":12,
    "gn:feature_class":"P",
    "gn:feature_code":"PPL",
    "gn:name":"Crociaro",
    "gn:population":37,
    "gn:timezone":"Europe/Rome",
    "iso:country":"IT",
    "wof:name":"Crociaro",
    "wof:placetype":"locality",
    "wof:population":37
},
  "geometry": {"coordinates":[11.99753,44.31401],"type":"Point"}
}