{
  "type": "Feature",
  "properties": {
    "gn:admin1_code":"20",
    "gn:admin2_code":"VI",
    "gn:admin3_code":"24063.0",
    "gn:asciiname":"San Giorgio",
    "gn:country_code":"IT",
    "gn:dem":238,
    "gn:feature_class":"P",
    "gn:feature_code":"PPL",
    "gn:name":"San Giorgio",
    "gn:population":17,
    "gn:timezone":"Europe/Rome",
    "iso:country":"IT",
    "wof:name":"San Giorgio",
    "wof:placetype":"locality",
    "wof:population":17
},
  "geometry": {"coordinates":[11.37233,45.63996],"type":"Point"}
}