{
  "type": "Feature",
  "properties": {
    "gn:admin1_code":"16",
    "gn:admin2_code":"AR",
    "gn:admin3_code":"51001.0",
    "gn:asciiname":"Viaio",
    "gn:country_code":"IT",
    "gn:dem":329,
    "gn:feature_class":"P",
    "gn:feature_code":"PPL",
    "gn:name":"Viaio",
    "gn:population":94,
    "gn:timezone":"Europe/Rome",
    "iso:country":"IT",
    "wof:name":"Viaio",
    "wof:placetype":"locality",
    "wof:population":94
},
  "geometry": {"coordinates":[12.06422,43.56826],"type":"Point"}
}