{
  "type": "Feature",
  "properties": {
    "gn:admin1_code":"5",
    "gn:admin2_code":"PC",
    "gn:admin3_code":"33008.0",
    "gn:asciiname":"Torri",
    "gn:country_code":"IT",
    "gn:dem":57,
    "gn:feature_class":"P",
    "gn:feature_code":"PPLL",
    "gn:name":"Torri",
    "gn:population":9,
    "gn:timezone":"Europe/Rome",
    "iso:country":"IT",
    "name:ceb_x_preferred":[
        "Torri"
    ],
    "name:deu_x_preferred":[
        "Torri"
    ],
    "name:fra_x_preferred":[
        "Torri"
    ],
    "name:ita_x_preferred":[
        "Torri"
    ],
    "name:por_x_preferred":[
        "Torri"
    ],
    "name:swe_x_preferred":[
        "Torri"
    ],
    "wof:name":"Torri",
    "wof:placetype":"locality",
    "wof:population":9
},
  "geometry": {"coordinates":[9.62293,45.06618],"type":"Point"}
}