{
  "type": "Feature",
  "properties": {
    "gn:admin1_code":"5",
    "gn:admin2_code":"BO",
    "gn:admin3_code":"37031.0",
    "gn:asciiname":"Casetta",
    "gn:country_code":"IT",
    "gn:dem":178,
    "gn:feature_class":"P",
    "gn:feature_code":"PPL",
    "gn:name":"Casetta",
    "gn:population":20,
    "gn:timezone":"Europe/Rome",
    "iso:country":"IT",
    "wof:name":"Casetta",
    "wof:placetype":"locality",
    "wof:population":20
},
  "geometry": {"coordinates":[11.13528,44.29976],"type":"Point"}
}