{
  "type": "Feature",
  "properties": {
    "gn:admin1_code":"1.0",
    "gn:admin2_code":"CH",
    "gn:admin3_code":"69074.0",
    "gn:asciiname":"Bocache II",
    "gn:country_code":"IT",
    "gn:dem":143,
    "gn:feature_class":"P",
    "gn:feature_code":"PPL",
    "gn:name":"Bocache II",
    "gn:population":35,
    "gn:timezone":"Europe/Rome",
    "iso:country":"IT",
    "wof:name":"Bocache II",
    "wof:placetype":"locality",
    "wof:population":35
},
  "geometry": {"coordinates":[14.45664,42.25961],"type":"Point"}
}