{
  "type": "Feature",
  "properties": {
    "gn:admin1_code":"14",
    "gn:admin2_code":"SS",
    "gn:admin3_code":"90058.0",
    "gn:asciiname":"Serra Li Pozzi",
    "gn:country_code":"IT",
    "gn:dem":45,
    "gn:feature_class":"P",
    "gn:feature_code":"PPL",
    "gn:name":"Serra Li Pozzi",
    "gn:population":23,
    "gn:timezone":"Europe/Rome",
    "iso:country":"IT",
    "wof:name":"Serra Li Pozzi",
    "wof:placetype":"locality",
    "wof:population":23
},
  "geometry": {"coordinates":[8.42137,40.8152],"type":"Point"}
}