{
  "type": "Feature",
  "properties": {
    "gn:admin1_code":"20",
    "gn:admin2_code":"PD",
    "gn:admin3_code":"28032.0",
    "gn:asciiname":"Lazzaretto",
    "gn:country_code":"IT",
    "gn:dem":48,
    "gn:feature_class":"P",
    "gn:feature_code":"PPL",
    "gn:name":"Lazzaretto",
    "gn:population":39,
    "gn:timezone":"Europe/Rome",
    "iso:country":"IT",
    "wof:name":"Lazzaretto",
    "wof:placetype":"locality",
    "wof:population":39
},
  "geometry": {"coordinates":[11.75805,45.6463],"type":"Point"}
}