{
  "type": "Feature",
  "properties": {
    "gn:admin1_code":"16",
    "gn:admin2_code":"GR",
    "gn:admin3_code":"53023.0",
    "gn:asciiname":"La Croce",
    "gn:country_code":"IT",
    "gn:dem":510,
    "gn:feature_class":"P",
    "gn:feature_code":"PPL",
    "gn:name":"La Croce",
    "gn:population":29,
    "gn:timezone":"Europe/Rome",
    "iso:country":"IT",
    "wof:name":"La Croce",
    "wof:placetype":"locality",
    "wof:population":29
},
  "geometry": {"coordinates":[11.34409,42.69334],"type":"Point"}
}