{
  "type": "Feature",
  "properties": {
    "gn:admin1_code":"20",
    "gn:admin2_code":"RO",
    "gn:admin3_code":"29003.0",
    "gn:asciiname":"Corne",
    "gn:country_code":"IT",
    "gn:dem":6,
    "gn:feature_class":"P",
    "gn:feature_code":"PPL",
    "gn:name":"Corn\u00e8",
    "gn:population":327,
    "gn:timezone":"Europe/Rome",
    "iso:country":"IT",
    "name:und_x_variant":[
        "Corn\u00e8"
    ],
    "wof:name":"Corne",
    "wof:placetype":"locality",
    "wof:population":327
},
  "geometry": {"coordinates":[11.74467,45.02563],"type":"Point"}
}