{
  "type": "Feature",
  "properties": {
    "gn:admin1_code":"20.0",
    "gn:admin2_code":"PD",
    "gn:admin3_code":"28041.0",
    "gn:asciiname":"Gaianigo",
    "gn:country_code":"IT",
    "gn:dem":30,
    "gn:elevation":"32.0",
    "gn:feature_class":"P",
    "gn:feature_code":"PPL",
    "gn:name":"Gaianigo",
    "gn:population":260,
    "gn:timezone":"Europe/Rome",
    "iso:country":"IT",
    "wof:name":"Gaianigo",
    "wof:placetype":"locality",
    "wof:population":260
},
  "geometry": {"coordinates":[11.67928,45.55837],"type":"Point"}
}