{
  "type": "Feature",
  "properties": {
    "gn:gn_country":"IT",
    "gn:gn_fcode":"PPL",
    "gn:gn_pop":0,
    "gn:population":311,
    "iso:country":"IT",
    "name:dut_x_preferred":[
        "Aggio"
    ],
    "name:eng_x_preferred":[
        "Aggio"
    ],
    "name:fre_x_preferred":[
        "Aggio"
    ],
    "name:hun_x_preferred":[
        "Aggio"
    ],
    "name:ita_x_preferred":[
        "Aggio"
    ],
    "name:lij_x_preferred":[
        "Aggio"
    ],
    "name:srp_x_preferred":[
        "Aggio"
    ],
    "qs_pg:aaroncc":"IT",
    "qs_pg:gn_country":"IT",
    "qs_pg:gn_fcode":"PPL",
    "qs_pg:gn_pop":0,
    "qs_pg:name":"Aggio",
    "qs_pg:name_adm0":"Italia",
    "qs_pg:name_adm1":"Liguria",
    "qs_pg:photos":8,
    "qs_pg:photos_1k":2,
    "qs_pg:photos_9k":1,
    "qs_pg:photos_9r":1,
    "qs_pg:photos_all":8,
    "qs_pg:photos_sr":1,
    "qs_pg:pop_sr":0,
    "qs_pg:qs_pg_placetype":"locality",
    "qs_pg:qs_pg_placetype_gp":"Town",
    "qs_pg:woe_adm0":23424853,
    "woe:adm0_id":23424853,
    "woe:name_adm0":"Italia",
    "woe:name_adm1":"Liguria",
    "woe:placetype":"Town",
    "wof:name":"Aggio",
    "wof:placetype":"locality",
    "wof:population":311
},
  "geometry": {"coordinates":[9.01085,44.46601],"type":"Point"}
}