{
  "type": "Feature",
  "properties": {
    "gn:admin1_code":"5.0",
    "gn:admin2_code":"RN",
    "gn:admin3_code":"99005.0",
    "gn:asciiname":"Ca' Bastella",
    "gn:country_code":"IT",
    "gn:dem":57,
    "gn:feature_class":"P",
    "gn:feature_code":"PPL",
    "gn:name":"Ca' Bastella",
    "gn:population":38,
    "gn:timezone":"Europe/Rome",
    "iso:country":"IT",
    "wof:name":"Ca' Bastella",
    "wof:placetype":"locality",
    "wof:population":38
},
  "geometry": {"coordinates":[12.67141,43.93868],"type":"Point"}
}