{
  "type": "Feature",
  "properties": {
    "gn:admin1_code":"3",
    "gn:admin2_code":"CZ",
    "gn:admin3_code":"79048.0",
    "gn:asciiname":"Vigna Vecchia",
    "gn:country_code":"IT",
    "gn:dem":153,
    "gn:feature_class":"P",
    "gn:feature_code":"PPL",
    "gn:name":"Vigna Vecchia",
    "gn:population":39,
    "gn:timezone":"Europe/Rome",
    "iso:country":"IT",
    "wof:name":"Vigna Vecchia",
    "wof:placetype":"locality",
    "wof:population":39
},
  "geometry": {"coordinates":[16.36248,38.94947],"type":"Point"}
}