{
  "type": "Feature",
  "properties": {
    "gn:admin1_code":"15",
    "gn:admin2_code":"ME",
    "gn:admin3_code":"83099.0",
    "gn:asciiname":"Ilombati",
    "gn:country_code":"IT",
    "gn:dem":685,
    "gn:feature_class":"P",
    "gn:feature_code":"PPL",
    "gn:name":"Ilombati",
    "gn:population":286,
    "gn:timezone":"Europe/Rome",
    "iso:country":"IT",
    "wof:name":"Ilombati",
    "wof:placetype":"locality",
    "wof:population":286
},
  "geometry": {"coordinates":[14.83034,38.01065],"type":"Point"}
}