{
  "type": "Feature",
  "properties": {
    "gn:admin1_code":"5",
    "gn:admin2_code":"RN",
    "gn:admin3_code":"99028.0",
    "gn:asciiname":"Casetti",
    "gn:country_code":"IT",
    "gn:dem":88,
    "gn:feature_class":"P",
    "gn:feature_code":"PPL",
    "gn:name":"Casetti",
    "gn:population":30,
    "gn:timezone":"Europe/Rome",
    "iso:country":"IT",
    "wof:name":"Casetti",
    "wof:placetype":"locality",
    "wof:population":30
},
  "geometry": {"coordinates":[12.40171,44.00929],"type":"Point"}
}