{
  "type": "Feature",
  "properties": {
    "gn:admin1_code":"20",
    "gn:admin2_code":"PD",
    "gn:admin3_code":"28026.0",
    "gn:asciiname":"Gazzo",
    "gn:country_code":"IT",
    "gn:dem":2,
    "gn:feature_class":"P",
    "gn:feature_code":"PPL",
    "gn:name":"Gazzo",
    "gn:population":24,
    "gn:timezone":"Europe/Rome",
    "iso:country":"IT",
    "name:azb_x_preferred":[
        "\u0642\u0627\u062a\u0633\u0648"
    ],
    "name:bel_x_preferred":[
        "\u0413\u0430\u0446\u0446\u0430"
    ],
    "name:bul_x_preferred":[
        "\u0413\u0430\u0434\u0437\u043e"
    ],
    "name:ceb_x_preferred":[
        "Gazzo"
    ],
    "name:deu_x_preferred":[
        "Gazzo"
    ],
    "name:epo_x_preferred":[
        "Gazzo"
    ],
    "name:eus_x_preferred":[
        "Gazzo"
    ],
    "name:fas_x_preferred":[
        "\u06af\u0627\u062a\u0633\u0648"
    ],
    "name:fin_x_preferred":[
        "Gazzo"
    ],
    "name:fra_x_preferred":[
        "Gazzo"
    ],
    "name:hun_x_preferred":[
        "Gazzo"
    ],
    "name:hye_x_preferred":[
        "\u0533\u0561\u0581\u0578"
    ],
    "name:ind_x_preferred":[
        "Gazzo"
    ],
    "name:ita_x_preferred":[
        "Gazzo"
    ],
    "name:jpn_x_preferred":[
        "\u30ac\u30c3\u30c4\u30a9"
    ],
    "name:kaz_x_preferred":[
        "\u0413\u0430\u0446\u0446\u043e"
    ],
    "name:lat_x_preferred":[
        "Gadium"
    ],
    "name:lmo_x_preferred":[
        "Gazzo"
    ],
    "name:msa_x_preferred":[
        "Gazzo"
    ],
    "name:nap_x_preferred":[
        "Gazzo"
    ],
    "name:nld_x_preferred":[
        "Gazzo"
    ],
    "name:pms_x_preferred":[
        "Gazzo"
    ],
    "name:pol_x_preferred":[
        "Gazzo"
    ],
    "name:por_x_preferred":[
        "Gazzo"
    ],
    "name:ron_x_preferred":[
        "Gazzo"
    ],
    "name:rus_x_preferred":[
        "\u0413\u0430\u0446\u0446\u043e"
    ],
    "name:scn_x_preferred":[
        "Gazzo"
    ],
    "name:spa_x_preferred":[
        "Gazzo"
    ],
    "name:srp_x_preferred":[
        "\u0413\u0430\u0446\u043e"
    ],
    "name:tgl_x_preferred":[
        "Gazzo"
    ],
    "name:ukr_x_preferred":[
        "\u0413\u0430\u0446\u0446\u043e"
    ],
    "name:uzb_x_preferred":[
        "Gazzo"
    ],
    "name:vec_x_preferred":[
        "Gaxo"
    ],
    "name:vie_x_preferred":[
        "Gazzo"
    ],
    "name:vol_x_preferred":[
        "Gazzo"
    ],
    "name:war_x_preferred":[
        "Gazzo"
    ],
    "wof:name":"Gazzo",
    "wof:placetype":"locality",
    "wof:population":24
},
  "geometry": {"coordinates":[11.88274,45.28091],"type":"Point"}
}