{
  "type": "Feature",
  "properties": {
    "gn:admin1_code":"16.0",
    "gn:admin2_code":"LU",
    "gn:admin3_code":"46036.0",
    "gn:asciiname":"Vallico di Sopra",
    "gn:country_code":"IT",
    "gn:dem":642,
    "gn:feature_class":"P",
    "gn:feature_code":"PPL",
    "gn:name":"Vallico di Sopra",
    "gn:population":67,
    "gn:timezone":"Europe/Rome",
    "iso:country":"IT",
    "wof:name":"Vallico di Sopra",
    "wof:placetype":"locality",
    "wof:population":67
},
  "geometry": {"coordinates":[10.44611,44.01743],"type":"Point"}
}