{
  "type": "Feature",
  "properties": {
    "gn:admin1_code":"4",
    "gn:admin2_code":"BN",
    "gn:admin3_code":"62044.0",
    "gn:asciiname":"Masseria Fiorenza",
    "gn:country_code":"IT",
    "gn:dem":701,
    "gn:feature_class":"P",
    "gn:feature_code":"PPL",
    "gn:name":"Masseria Fiorenza",
    "gn:population":23,
    "gn:timezone":"Europe/Rome",
    "iso:country":"IT",
    "wof:name":"Masseria Fiorenza",
    "wof:placetype":"locality",
    "wof:population":23
},
  "geometry": {"coordinates":[14.75609,41.36338],"type":"Point"}
}