{
  "type": "Feature",
  "properties": {
    "gn:admin1_code":"2",
    "gn:admin2_code":"PZ",
    "gn:admin3_code":"76012.0",
    "gn:asciiname":"Braida",
    "gn:country_code":"IT",
    "gn:dem":729,
    "gn:feature_class":"P",
    "gn:feature_code":"PPL",
    "gn:name":"Braida",
    "gn:population":77,
    "gn:timezone":"Europe/Rome",
    "iso:country":"IT",
    "wof:name":"Braida",
    "wof:placetype":"locality",
    "wof:population":77
},
  "geometry": {"coordinates":[15.53132,40.76591],"type":"Point"}
}