{
  "type": "Feature",
  "properties": {
    "gn:admin1_code":"4",
    "gn:admin2_code":"BN",
    "gn:admin3_code":"62012.0",
    "gn:asciiname":"Europa",
    "gn:country_code":"IT",
    "gn:dem":269,
    "gn:feature_class":"P",
    "gn:feature_code":"PPL",
    "gn:name":"Europa",
    "gn:population":13,
    "gn:timezone":"Europe/Rome",
    "iso:country":"IT",
    "wof:name":"Europa",
    "wof:placetype":"locality",
    "wof:population":13
},
  "geometry": {"coordinates":[14.89962,41.07848],"type":"Point"}
}