{
  "type": "Feature",
  "properties": {
    "gn:admin1_code":"16",
    "gn:admin2_code":"FI",
    "gn:admin3_code":"48003.0",
    "gn:asciiname":"San Filippo a Ponzano",
    "gn:country_code":"IT",
    "gn:dem":281,
    "gn:feature_class":"P",
    "gn:feature_code":"PPL",
    "gn:name":"San Filippo a Ponzano",
    "gn:population":101,
    "gn:timezone":"Europe/Rome",
    "iso:country":"IT",
    "wof:name":"San Filippo a Ponzano",
    "wof:placetype":"locality",
    "wof:population":101
},
  "geometry": {"coordinates":[11.17005,43.52677],"type":"Point"}
}