{
  "type": "Feature",
  "properties": {
    "gn:admin1_code":"9",
    "gn:admin2_code":"BG",
    "gn:admin3_code":"16043.0",
    "gn:asciiname":"Bettole",
    "gn:country_code":"IT",
    "gn:dem":191,
    "gn:feature_class":"P",
    "gn:feature_code":"PPL",
    "gn:name":"Bettole",
    "gn:population":112,
    "gn:timezone":"Europe/Rome",
    "iso:country":"IT",
    "wof:name":"Bettole",
    "wof:placetype":"locality",
    "wof:population":112
},
  "geometry": {"coordinates":[9.77444,45.62245],"type":"Point"}
}