{
  "type": "Feature",
  "properties": {
    "gn:admin1_code":"12.0",
    "gn:admin2_code":"TO",
    "gn:admin3_code":"1186.0",
    "gn:asciiname":"Villasecca Inferiore",
    "gn:country_code":"IT",
    "gn:dem":851,
    "gn:feature_class":"P",
    "gn:feature_code":"PPL",
    "gn:name":"Villasecca Inferiore",
    "gn:population":10,
    "gn:timezone":"Europe/Rome",
    "iso:country":"IT",
    "wof:name":"Villasecca Inferiore",
    "wof:placetype":"locality",
    "wof:population":10
},
  "geometry": {"coordinates":[7.14615,44.9397],"type":"Point"}
}