{
  "type": "Feature",
  "properties": {
    "gn:admin1_code":"12",
    "gn:admin2_code":"TO",
    "gn:admin3_code":"1059.0",
    "gn:asciiname":"Bossola",
    "gn:country_code":"IT",
    "gn:dem":244,
    "gn:feature_class":"P",
    "gn:feature_code":"PPL",
    "gn:name":"Bossola",
    "gn:population":243,
    "gn:timezone":"Europe/Rome",
    "iso:country":"IT",
    "wof:name":"Bossola",
    "wof:placetype":"locality",
    "wof:population":243
},
  "geometry": {"coordinates":[7.71149,44.82737],"type":"Point"}
}