{
  "type": "Feature",
  "properties": {
    "gn:admin1_code":"1",
    "gn:admin2_code":"TE",
    "gn:admin3_code":"67003.0",
    "gn:asciiname":"Colle Mesole",
    "gn:country_code":"IT",
    "gn:dem":657,
    "gn:feature_class":"P",
    "gn:feature_code":"PPL",
    "gn:name":"Colle Mesole",
    "gn:population":13,
    "gn:timezone":"Europe/Rome",
    "iso:country":"IT",
    "wof:name":"Colle Mesole",
    "wof:placetype":"locality",
    "wof:population":13
},
  "geometry": {"coordinates":[13.77567,42.47105],"type":"Point"}
}