{
  "type": "Feature",
  "properties": {
    "iso:country":"IT",
    "wof:name":"Cagnola",
    "wof:placetype":"neighbourhood"
},
  "geometry": {"coordinates":[9.15215252515046,45.49446491196115],"type":"Point"}
}