{
  "type": "Feature",
  "properties": {
    "gn:admin1_code":"13.0",
    "gn:admin2_code":"FG",
    "gn:admin3_code":"71033.0",
    "gn:asciiname":"Studentato Padri Cappuccini",
    "gn:country_code":"IT",
    "gn:dem":7,
    "gn:feature_class":"P",
    "gn:feature_code":"PPLL",
    "gn:name":"Studentato Padri Cappuccini",
    "gn:population":3,
    "gn:timezone":"Europe/Rome",
    "iso:country":"IT",
    "wof:name":"Studentato Padri Cappuccini",
    "wof:placetype":"locality",
    "wof:population":3
},
  "geometry": {"coordinates":[15.93945,41.64055],"type":"Point"}
}