{
  "type": "Feature",
  "properties": {
    "gn:admin1_code":"12",
    "gn:admin2_code":"CN",
    "gn:admin3_code":"4099.0",
    "gn:asciiname":"Casanova Superiore",
    "gn:country_code":"IT",
    "gn:dem":222,
    "gn:feature_class":"P",
    "gn:feature_code":"PPL",
    "gn:name":"Casanova Superiore",
    "gn:population":15,
    "gn:timezone":"Europe/Rome",
    "iso:country":"IT",
    "wof:name":"Casanova Superiore",
    "wof:placetype":"locality",
    "wof:population":15
},
  "geometry": {"coordinates":[8.09808,44.81746],"type":"Point"}
}