{
  "type": "Feature",
  "properties": {
    "gn:admin1_code":"9",
    "gn:admin2_code":"VA",
    "gn:admin3_code":"12139.0",
    "gn:asciiname":"Viale Varese",
    "gn:country_code":"IT",
    "gn:dem":428,
    "gn:feature_class":"P",
    "gn:feature_code":"PPL",
    "gn:name":"Viale Varese",
    "gn:population":72,
    "gn:timezone":"Europe/Rome",
    "iso:country":"IT",
    "wof:name":"Viale Varese",
    "wof:placetype":"locality",
    "wof:population":72
},
  "geometry": {"coordinates":[8.90921,45.86225],"type":"Point"}
}