{
  "type": "Feature",
  "properties": {
    "gn:admin1_code":"9",
    "gn:admin2_code":"PV",
    "gn:admin3_code":"18117.0",
    "gn:asciiname":"Moglie",
    "gn:country_code":"IT",
    "gn:dem":439,
    "gn:feature_class":"P",
    "gn:feature_code":"PPL",
    "gn:name":"Moglie",
    "gn:population":22,
    "gn:timezone":"Europe/Rome",
    "iso:country":"IT",
    "wof:name":"Moglie",
    "wof:placetype":"locality",
    "wof:population":22
},
  "geometry": {"coordinates":[9.13157,44.86028],"type":"Point"}
}