{
  "type": "Feature",
  "properties": {
    "gn:elevation":698,
    "gn:population":925,
    "iso:country":"IT",
    "name:azb_x_preferred":[
        "\u0633\u067e\u06cc\u0646\u0648"
    ],
    "name:bel_x_preferred":[
        "\u0421\u0435\u043f\u0456\u043d\u0430"
    ],
    "name:bul_x_preferred":[
        "\u0421\u0435\u043f\u0438\u043d\u043e"
    ],
    "name:ceb_x_preferred":[
        "Sepino"
    ],
    "name:deu_x_preferred":[
        "Sepino"
    ],
    "name:eng_x_preferred":[
        "Sepino"
    ],
    "name:epo_x_preferred":[
        "Sepino"
    ],
    "name:eus_x_preferred":[
        "Sepino"
    ],
    "name:fas_x_preferred":[
        "\u0633\u067e\u06cc\u0646\u0648"
    ],
    "name:fra_x_preferred":[
        "Sepino"
    ],
    "name:hbs_x_preferred":[
        "Sepino"
    ],
    "name:hun_x_preferred":[
        "Sepino"
    ],
    "name:hye_x_preferred":[
        "\u054d\u0565\u057a\u056b\u0576\u0578"
    ],
    "name:ina_x_preferred":[
        "Sepino"
    ],
    "name:ita_x_preferred":[
        "Sepino"
    ],
    "name:jpn_x_preferred":[
        "\u30bb\u30d4\u30fc\u30ce"
    ],
    "name:kaz_x_preferred":[
        "\u0421\u0435\u043f\u0438\u043d\u043e"
    ],
    "name:kor_x_preferred":[
        "\uc138\ud53c\ub178"
    ],
    "name:lat_x_preferred":[
        "Saepinum"
    ],
    "name:lmo_x_preferred":[
        "Sepino"
    ],
    "name:msa_x_preferred":[
        "Sepino"
    ],
    "name:nan_x_preferred":[
        "Sepino"
    ],
    "name:nap_x_preferred":[
        "Sepino"
    ],
    "name:nld_x_preferred":[
        "Sepino"
    ],
    "name:pms_x_preferred":[
        "Sepino"
    ],
    "name:pol_x_preferred":[
        "Sepino"
    ],
    "name:por_x_preferred":[
        "Sepino"
    ],
    "name:ron_x_preferred":[
        "Sepino"
    ],
    "name:rus_x_preferred":[
        "\u0421\u0435\u043f\u0438\u043d\u043e"
    ],
    "name:scn_x_preferred":[
        "Sepinu"
    ],
    "name:spa_x_preferred":[
        "Sepino"
    ],
    "name:srp_x_preferred":[
        "\u0421\u0435\u043f\u0438\u043d\u043e"
    ],
    "name:srp_x_variant":[
        "Sepino"
    ],
    "name:tgl_x_preferred":[
        "Sepino"
    ],
    "name:ukr_x_preferred":[
        "\u0421\u0435\u043f\u0456\u043d\u043e"
    ],
    "name:uzb_x_preferred":[
        "Sepino"
    ],
    "name:vie_x_preferred":[
        "Sepino"
    ],
    "name:vol_x_preferred":[
        "Sepino"
    ],
    "name:war_x_preferred":[
        "Sepino"
    ],
    "name:zho_min_nan_x_preferred":[
        "Sepino"
    ],
    "name:zho_x_preferred":[
        "\u585e\u76ae\u8bfa"
    ],
    "qs:a0":"Italia",
    "qs:a1":"*Campobasso",
    "qs:a1r":"0Molise",
    "qs:adm0":"Italia",
    "qs:la_lc":"*",
    "qs:level":"locality",
    "qs:loc":"Sepino",
    "qs:loc_alt":"Sepino",
    "qs:pop":0,
    "qs:type":"buffered point",
    "wd:wordcount":120,
    "wof:name":"Sepino",
    "wof:placetype":"locality",
    "wof:population":925
},
  "geometry": {"coordinates":[14.61917,41.40889],"type":"Point"}
}