{
  "type": "Feature",
  "properties": {
    "gn:admin1_code":"6.0",
    "gn:admin2_code":"UD",
    "gn:admin3_code":"30043.0",
    "gn:asciiname":"Molino",
    "gn:country_code":"IT",
    "gn:dem":206,
    "gn:feature_class":"P",
    "gn:feature_code":"PPL",
    "gn:name":"Molino",
    "gn:population":0,
    "gn:timezone":"Europe/Rome",
    "iso:country":"IT",
    "name:ceb_x_preferred":[
        "Molino"
    ],
    "name:deu_x_preferred":[
        "Molino"
    ],
    "name:epo_x_preferred":[
        "Molino"
    ],
    "name:fra_x_preferred":[
        "Molino"
    ],
    "name:ita_x_preferred":[
        "Molino"
    ],
    "name:por_x_preferred":[
        "Molino"
    ],
    "name:spa_x_preferred":[
        "Molino"
    ],
    "name:srp_x_preferred":[
        "Molino"
    ],
    "name:swe_x_preferred":[
        "Molino"
    ],
    "name:tgl_x_preferred":[
        "Molino"
    ],
    "wof:name":"Molino",
    "wof:placetype":"locality"
},
  "geometry": {"coordinates":[13.12444,46.29194],"type":"Point"}
}