{
  "type": "Feature",
  "properties": {
    "iso:country":"IT",
    "wof:name":"Isola Farnese",
    "wof:placetype":"neighbourhood"
},
  "geometry": {"coordinates":[12.38581142833376,42.01997344135737],"type":"Point"}
}