{
  "type": "Feature",
  "properties": {
    "gn:admin1_code":"3",
    "gn:admin2_code":"CS",
    "gn:admin3_code":"78070.0",
    "gn:asciiname":"Tre Arie",
    "gn:country_code":"IT",
    "gn:dem":818,
    "gn:feature_class":"P",
    "gn:feature_code":"PPL",
    "gn:name":"Tre Arie",
    "gn:population":29,
    "gn:timezone":"Europe/Rome",
    "iso:country":"IT",
    "wof:name":"Tre Arie",
    "wof:placetype":"locality",
    "wof:population":29
},
  "geometry": {"coordinates":[16.32357,39.46476],"type":"Point"}
}