{
  "type": "Feature",
  "properties": {
    "gn:admin1_code":"3",
    "gn:admin2_code":"VV",
    "gn:admin3_code":"102009.0",
    "gn:asciiname":"Pissione",
    "gn:country_code":"IT",
    "gn:dem":280,
    "gn:feature_class":"P",
    "gn:feature_code":"PPL",
    "gn:name":"Pissione",
    "gn:population":24,
    "gn:timezone":"Europe/Rome",
    "iso:country":"IT",
    "wof:name":"Pissione",
    "wof:placetype":"locality",
    "wof:population":24
},
  "geometry": {"coordinates":[15.89563,38.66144],"type":"Point"}
}