{
  "type": "Feature",
  "properties": {
    "gn:admin1_code":"5.0",
    "gn:admin2_code":"FC",
    "gn:admin3_code":"40009.0",
    "gn:asciiname":"Collina",
    "gn:country_code":"IT",
    "gn:dem":614,
    "gn:elevation":"640.0",
    "gn:feature_class":"P",
    "gn:feature_code":"PPL",
    "gn:name":"Collina",
    "gn:population":15,
    "gn:timezone":"Europe/Rome",
    "iso:country":"IT",
    "name:ceb_x_preferred":[
        "Collina"
    ],
    "name:deu_x_preferred":[
        "Collina"
    ],
    "name:fra_x_preferred":[
        "Collina"
    ],
    "name:heb_x_preferred":[
        "\u05e7\u05d5\u05dc\u05d9\u05e0\u05d4"
    ],
    "name:ita_x_preferred":[
        "Collina"
    ],
    "name:nds_x_preferred":[
        "Collina"
    ],
    "name:srp_x_preferred":[
        "Kolina"
    ],
    "wof:name":"Collina",
    "wof:placetype":"locality",
    "wof:population":15
},
  "geometry": {"coordinates":[11.97293,43.97605],"type":"Point"}
}