{
  "type": "Feature",
  "properties": {
    "gn:admin1_code":"20",
    "gn:admin2_code":"PD",
    "gn:admin3_code":"28046.0",
    "gn:asciiname":"Beltrame-Longo",
    "gn:country_code":"IT",
    "gn:dem":25,
    "gn:feature_class":"P",
    "gn:feature_code":"PPL",
    "gn:name":"Beltrame-Longo",
    "gn:population":47,
    "gn:timezone":"Europe/Rome",
    "iso:country":"IT",
    "wof:name":"Beltrame-Longo",
    "wof:placetype":"locality",
    "wof:population":47
},
  "geometry": {"coordinates":[11.92559,45.61312],"type":"Point"}
}