{
  "type": "Feature",
  "properties": {
    "gn:admin1_code":"9.0",
    "gn:admin2_code":"MI",
    "gn:admin3_code":"15171.0",
    "gn:asciiname":"Bellaria",
    "gn:country_code":"IT",
    "gn:dem":96,
    "gn:feature_class":"P",
    "gn:feature_code":"PPL",
    "gn:name":"Bellaria",
    "gn:population":0,
    "gn:timezone":"Europe/Rome",
    "iso:country":"IT",
    "wof:name":"Bellaria",
    "wof:placetype":"locality"
},
  "geometry": {"coordinates":[9.30765,45.42397],"type":"Point"}
}