{
  "type": "Feature",
  "properties": {
    "gn:admin1_code":"1",
    "gn:admin2_code":"CH",
    "gn:admin3_code":"69072.0",
    "gn:asciiname":"Rosario",
    "gn:country_code":"IT",
    "gn:dem":176,
    "gn:feature_class":"P",
    "gn:feature_code":"PPL",
    "gn:name":"Rosario",
    "gn:population":57,
    "gn:timezone":"Europe/Rome",
    "iso:country":"IT",
    "wof:name":"Rosario",
    "wof:placetype":"locality",
    "wof:population":57
},
  "geometry": {"coordinates":[14.25219,42.35974],"type":"Point"}
}