{
  "type": "Feature",
  "properties": {
    "gn:admin1_code":"10",
    "gn:admin2_code":"MC",
    "gn:admin3_code":"43058.0",
    "gn:asciiname":"Frontillo",
    "gn:country_code":"IT",
    "gn:dem":581,
    "gn:feature_class":"P",
    "gn:feature_code":"PPL",
    "gn:name":"Frontillo",
    "gn:population":18,
    "gn:timezone":"Europe/Rome",
    "iso:country":"IT",
    "wof:name":"Frontillo",
    "wof:placetype":"locality",
    "wof:population":18
},
  "geometry": {"coordinates":[13.10046,43.05348],"type":"Point"}
}