{
  "type": "Feature",
  "properties": {
    "gn:admin1_code":"17",
    "gn:admin2_code":"BZ",
    "gn:admin3_code":"21115.0",
    "gn:asciiname":"Novale di Sopra",
    "gn:country_code":"IT",
    "gn:dem":1064,
    "gn:feature_class":"P",
    "gn:feature_code":"PPL",
    "gn:name":"Novale di Sopra",
    "gn:population":44,
    "gn:timezone":"Europe/Rome",
    "iso:country":"IT",
    "wof:name":"Novale di Sopra",
    "wof:placetype":"locality",
    "wof:population":44
},
  "geometry": {"coordinates":[11.45023,46.92234000000001],"type":"Point"}
}