{
  "type": "Feature",
  "properties": {
    "gn:admin1_code":"20",
    "gn:admin2_code":"VI",
    "gn:admin3_code":"24060.0",
    "gn:asciiname":"Fracanzana",
    "gn:country_code":"IT",
    "gn:dem":45,
    "gn:feature_class":"P",
    "gn:feature_code":"PPL",
    "gn:name":"Fracanzana",
    "gn:population":35,
    "gn:timezone":"Europe/Rome",
    "iso:country":"IT",
    "wof:name":"Fracanzana",
    "wof:placetype":"locality",
    "wof:population":35
},
  "geometry": {"coordinates":[11.37578,45.44165],"type":"Point"}
}