{
  "type": "Feature",
  "properties": {
    "gn:admin1_code":"9",
    "gn:admin2_code":"MN",
    "gn:admin3_code":"20052.0",
    "gn:asciiname":"San Casciano",
    "gn:country_code":"IT",
    "gn:dem":17,
    "gn:feature_class":"P",
    "gn:feature_code":"PPL",
    "gn:name":"San Casciano",
    "gn:population":30,
    "gn:timezone":"Europe/Rome",
    "iso:country":"IT",
    "wof:name":"San Casciano",
    "wof:placetype":"locality",
    "wof:population":30
},
  "geometry": {"coordinates":[10.97441,45.12274],"type":"Point"}
}