{
  "type": "Feature",
  "properties": {
    "gn:admin1_code":"20",
    "gn:admin2_code":"VR",
    "gn:admin3_code":"23078.0",
    "gn:asciiname":"Martellengo",
    "gn:country_code":"IT",
    "gn:dem":1017,
    "gn:feature_class":"P",
    "gn:feature_code":"PPL",
    "gn:name":"Martellengo",
    "gn:population":15,
    "gn:timezone":"Europe/Rome",
    "iso:country":"IT",
    "wof:name":"Martellengo",
    "wof:placetype":"locality",
    "wof:population":15
},
  "geometry": {"coordinates":[10.94068,45.65818],"type":"Point"}
}