{
  "type": "Feature",
  "properties": {
    "gn:admin1_code":"4",
    "gn:admin2_code":"CE",
    "gn:admin3_code":"61013.0",
    "gn:asciiname":"Musicile",
    "gn:country_code":"IT",
    "gn:dem":32,
    "gn:feature_class":"P",
    "gn:feature_code":"PPL",
    "gn:name":"Musicile",
    "gn:population":338,
    "gn:timezone":"Europe/Rome",
    "iso:country":"IT",
    "wof:name":"Musicile",
    "wof:placetype":"locality",
    "wof:population":338
},
  "geometry": {"coordinates":[14.28943,41.04989000000001],"type":"Point"}
}