{
  "type": "Feature",
  "properties": {
    "gn:admin1_code":"12",
    "gn:admin2_code":"TO",
    "gn:admin3_code":"1260.0",
    "gn:asciiname":"Murisenghi",
    "gn:country_code":"IT",
    "gn:dem":290,
    "gn:feature_class":"P",
    "gn:feature_code":"PPL",
    "gn:name":"Murisenghi",
    "gn:population":158,
    "gn:timezone":"Europe/Rome",
    "iso:country":"IT",
    "wof:name":"Murisenghi",
    "wof:placetype":"locality",
    "wof:population":158
},
  "geometry": {"coordinates":[7.42612,44.89443],"type":"Point"}
}