{
  "type": "Feature",
  "properties": {
    "gn:admin1_code":"20",
    "gn:admin2_code":"VR",
    "gn:admin3_code":"23025.0",
    "gn:asciiname":"Villaggio Dionisi",
    "gn:country_code":"IT",
    "gn:dem":16,
    "gn:feature_class":"P",
    "gn:feature_code":"PPL",
    "gn:name":"Villaggio Dionisi",
    "gn:population":22,
    "gn:timezone":"Europe/Rome",
    "iso:country":"IT",
    "wof:name":"Villaggio Dionisi",
    "wof:placetype":"locality",
    "wof:population":22
},
  "geometry": {"coordinates":[11.23181,45.22646],"type":"Point"}
}