{
  "type": "Feature",
  "properties": {
    "gn:admin1_code":"5.0",
    "gn:admin2_code":"RA",
    "gn:admin3_code":"39008.0",
    "gn:asciiname":"Unigra",
    "gn:country_code":"IT",
    "gn:dem":2,
    "gn:feature_class":"P",
    "gn:feature_code":"PPLL",
    "gn:name":"Unigr\u00e0",
    "gn:population":0,
    "gn:timezone":"Europe/Rome",
    "iso:country":"IT",
    "name:und_x_variant":[
        "Unigr\u00e0"
    ],
    "wof:name":"Unigra",
    "wof:placetype":"locality"
},
  "geometry": {"coordinates":[11.85905,44.53503],"type":"Point"}
}