{
  "type": "Feature",
  "properties": {
    "gn:admin1_code":"9",
    "gn:admin2_code":"BS",
    "gn:admin3_code":"17076.0",
    "gn:asciiname":"Musaga",
    "gn:country_code":"IT",
    "gn:dem":446,
    "gn:feature_class":"P",
    "gn:feature_code":"PPL",
    "gn:name":"Musaga",
    "gn:population":76,
    "gn:timezone":"Europe/Rome",
    "iso:country":"IT",
    "wof:name":"Musaga",
    "wof:placetype":"locality",
    "wof:population":76
},
  "geometry": {"coordinates":[10.65271,45.69173],"type":"Point"}
}