{
  "type": "Feature",
  "properties": {
    "gn:admin1_code":"12",
    "gn:admin2_code":"AL",
    "gn:admin3_code":"6049.0",
    "gn:asciiname":"Campo della Lepre",
    "gn:country_code":"IT",
    "gn:dem":162,
    "gn:feature_class":"P",
    "gn:feature_code":"PPL",
    "gn:name":"Campo della Lepre",
    "gn:population":29,
    "gn:timezone":"Europe/Rome",
    "iso:country":"IT",
    "wof:name":"Campo della Lepre",
    "wof:placetype":"locality",
    "wof:population":29
},
  "geometry": {"coordinates":[8.68488,44.70476],"type":"Point"}
}