{
  "type": "Feature",
  "properties": {
    "gn:admin1_code":"14.0",
    "gn:admin2_code":"SS",
    "gn:admin3_code":"90084.0",
    "gn:asciiname":"Vaccileddi",
    "gn:country_code":"IT",
    "gn:dem":16,
    "gn:feature_class":"P",
    "gn:feature_code":"PPL",
    "gn:name":"Vaccileddi",
    "gn:population":0,
    "gn:timezone":"Europe/Rome",
    "iso:country":"IT",
    "wof:name":"Vaccileddi",
    "wof:placetype":"locality"
},
  "geometry": {"coordinates":[9.64664,40.84674],"type":"Point"}
}