{
  "type": "Feature",
  "properties": {
    "gn:admin1_code":"10",
    "gn:admin2_code":"MC",
    "gn:admin3_code":"43046.0",
    "gn:asciiname":"Cerreto Alto",
    "gn:country_code":"IT",
    "gn:dem":598,
    "gn:feature_class":"P",
    "gn:feature_code":"PPL",
    "gn:name":"Cerreto Alto",
    "gn:population":21,
    "gn:timezone":"Europe/Rome",
    "iso:country":"IT",
    "wof:name":"Cerreto Alto",
    "wof:placetype":"locality",
    "wof:population":21
},
  "geometry": {"coordinates":[13.30104,43.07109000000001],"type":"Point"}
}