{
  "type": "Feature",
  "properties": {
    "gn:elevation":562,
    "gn:population":922,
    "iso:country":"IT",
    "name:ast_x_preferred":[
        "Bassiano"
    ],
    "name:bcl_x_preferred":[
        "Bassiano"
    ],
    "name:bul_x_preferred":[
        "\u0411\u0430\u0441\u0438\u0430\u043d\u043e"
    ],
    "name:cat_x_preferred":[
        "Bassiano"
    ],
    "name:ces_x_preferred":[
        "Bassiano"
    ],
    "name:deu_x_preferred":[
        "Bassiano"
    ],
    "name:ell_x_preferred":[
        "\u039c\u03c0\u03b1\u03c3\u03b9\u03ac\u03bd\u03bf"
    ],
    "name:eng_x_preferred":[
        "Bassiano"
    ],
    "name:epo_x_preferred":[
        "Bassiano"
    ],
    "name:eus_x_preferred":[
        "Bassiano"
    ],
    "name:fas_x_preferred":[
        "\u0628\u0627\u0633\u06cc\u0627\u0646\u0648"
    ],
    "name:fra_x_preferred":[
        "Bassiano"
    ],
    "name:hbs_x_preferred":[
        "Bassiano"
    ],
    "name:hun_x_preferred":[
        "Bassiano"
    ],
    "name:hye_x_preferred":[
        "\u0532\u0561\u057d\u056b\u0561\u0576\u0578"
    ],
    "name:ina_x_preferred":[
        "Bassiano"
    ],
    "name:ita_x_preferred":[
        "Bassiano"
    ],
    "name:jpn_x_preferred":[
        "\u30d0\u30c3\u30b7\u30a2\u30fc\u30ce"
    ],
    "name:kaz_x_preferred":[
        "\u0411\u0430\u0441\u0441\u0438\u0430\u043d\u043e"
    ],
    "name:kor_x_preferred":[
        "\ubc14\uc2dc\uc544\ub178"
    ],
    "name:lat_x_preferred":[
        "Bassianum"
    ],
    "name:lmo_x_preferred":[
        "Bassiano"
    ],
    "name:msa_x_preferred":[
        "Bassiano"
    ],
    "name:nan_x_preferred":[
        "Bassiano"
    ],
    "name:nap_x_preferred":[
        "Bassiano"
    ],
    "name:nld_x_preferred":[
        "Bassiano"
    ],
    "name:pms_x_preferred":[
        "Bassiano"
    ],
    "name:pol_x_preferred":[
        "Bassiano"
    ],
    "name:por_x_preferred":[
        "Bassiano"
    ],
    "name:ron_x_preferred":[
        "Bassiano"
    ],
    "name:rus_x_preferred":[
        "\u0411\u0430\u0441\u0441\u0438\u0430\u043d\u043e"
    ],
    "name:scn_x_preferred":[
        "Bassianu"
    ],
    "name:sco_x_preferred":[
        "Bassiano"
    ],
    "name:spa_x_preferred":[
        "Bassiano"
    ],
    "name:srp_x_preferred":[
        "\u0411\u0430\u0441\u0438\u0458\u0430\u043d\u043e"
    ],
    "name:ukr_x_preferred":[
        "\u0411\u0430\u0441\u0441\u0456\u0430\u043d\u043e"
    ],
    "name:uzb_x_preferred":[
        "Bassiano"
    ],
    "name:vie_x_preferred":[
        "Bassiano"
    ],
    "name:vol_x_preferred":[
        "Bassiano"
    ],
    "name:war_x_preferred":[
        "Bassiano"
    ],
    "name:zho_min_nan_x_preferred":[
        "Bassiano"
    ],
    "name:zho_x_preferred":[
        "\u5df4\u590f\u8bfa"
    ],
    "qs:a0":"Italia",
    "qs:a1":"*Latina",
    "qs:a1r":"0Lazio",
    "qs:adm0":"Italia",
    "qs:la_lc":"*",
    "qs:level":"locality",
    "qs:loc":"Bassiano",
    "qs:loc_alt":"Bassiano",
    "qs:pop":0,
    "qs:type":"buffered point",
    "wd:wordcount":75,
    "wof:lang":[
        "ita"
    ],
    "wof:name":"Bassiano",
    "wof:placetype":"locality",
    "wof:population":922
},
  "geometry": {"coordinates":[13.031141,41.550041],"type":"Point"}
}