{
  "type": "Feature",
  "properties": {
    "gn:admin1_code":"5",
    "gn:admin2_code":"RE",
    "gn:admin3_code":"35016.0",
    "gn:asciiname":"Virola",
    "gn:country_code":"IT",
    "gn:dem":719,
    "gn:feature_class":"P",
    "gn:feature_code":"PPL",
    "gn:name":"Virola",
    "gn:population":40,
    "gn:timezone":"Europe/Rome",
    "iso:country":"IT",
    "name:cat_x_preferred":[
        "Virola"
    ],
    "name:ceb_x_preferred":[
        "Virola"
    ],
    "name:fas_x_preferred":[
        "\u0648\u06cc\u0631\u0648\u0644\u0627"
    ],
    "name:fin_x_preferred":[
        "Virolat"
    ],
    "name:fra_x_preferred":[
        "Virola"
    ],
    "name:ita_x_preferred":[
        "Virola"
    ],
    "name:por_x_preferred":[
        "Virola"
    ],
    "name:rus_x_preferred":[
        "\u0412\u0438\u0440\u043e\u043b\u0430"
    ],
    "name:spa_x_preferred":[
        "Virola"
    ],
    "name:srn_x_preferred":[
        "Virola"
    ],
    "name:swe_x_preferred":[
        "Virola"
    ],
    "name:war_x_preferred":[
        "Virola"
    ],
    "wof:name":"Virola",
    "wof:placetype":"locality",
    "wof:population":40
},
  "geometry": {"coordinates":[10.3796,44.43229],"type":"Point"}
}