{
  "type": "Feature",
  "properties": {
    "gn:admin1_code":"12",
    "gn:admin2_code":"CN",
    "gn:admin3_code":"4139.0",
    "gn:asciiname":"Frise",
    "gn:country_code":"IT",
    "gn:dem":1221,
    "gn:feature_class":"P",
    "gn:feature_code":"PPLL",
    "gn:name":"Frise",
    "gn:population":8,
    "gn:timezone":"Europe/Rome",
    "iso:country":"IT",
    "name:bre_x_preferred":[
        "Frise"
    ],
    "name:deu_x_preferred":[
        "Frise"
    ],
    "name:fra_x_preferred":[
        "Frise"
    ],
    "wof:name":"Frise",
    "wof:placetype":"locality",
    "wof:population":8
},
  "geometry": {"coordinates":[7.28714,44.39386],"type":"Point"}
}