{
  "type": "Feature",
  "properties": {
    "gn:admin1_code":"9.0",
    "gn:admin2_code":"MN",
    "gn:admin3_code":"20052.0",
    "gn:asciiname":"Casale",
    "gn:country_code":"IT",
    "gn:dem":13,
    "gn:feature_class":"P",
    "gn:feature_code":"PPL",
    "gn:name":"Casale",
    "gn:population":340,
    "gn:timezone":"Europe/Rome",
    "iso:country":"IT",
    "wof:name":"Casale",
    "wof:placetype":"locality",
    "wof:population":340
},
  "geometry": {"coordinates":[10.99307,45.09269000000001],"type":"Point"}
}