{
  "type": "Feature",
  "properties": {
    "iso:country":"IT",
    "name:ben_x_preferred":[
        "\u0995\u09cd\u09af\u09be\u09b2\u09a6\u09c7\u09b0\u09be"
    ],
    "name:cat_x_preferred":[
        "Caldera"
    ],
    "name:ceb_x_preferred":[
        "Caldera"
    ],
    "name:ces_x_preferred":[
        "Caldera"
    ],
    "name:dan_x_preferred":[
        "Caldera"
    ],
    "name:ell_x_preferred":[
        "\u039a\u03b1\u03bb\u03b4\u03ad\u03c1\u03b1"
    ],
    "name:eng_x_preferred":[
        "Caldera"
    ],
    "name:eus_x_preferred":[
        "Caldera"
    ],
    "name:fin_x_preferred":[
        "Caldera"
    ],
    "name:fra_x_preferred":[
        "Caldera"
    ],
    "name:heb_x_preferred":[
        "\u05e7\u05dc\u05d3\u05e8\u05d4"
    ],
    "name:hin_x_preferred":[
        "\u0915\u0948\u0932\u0921\u0947\u0930\u093e"
    ],
    "name:hun_x_preferred":[
        "Caldera"
    ],
    "name:ind_x_preferred":[
        "Caldera"
    ],
    "name:ita_x_preferred":[
        "Caldera"
    ],
    "name:nld_x_preferred":[
        "Caldera"
    ],
    "name:nno_x_preferred":[
        "Caldera"
    ],
    "name:nob_x_preferred":[
        "Caldera"
    ],
    "name:oci_x_preferred":[
        "Caldera"
    ],
    "name:pol_x_preferred":[
        "Caldera"
    ],
    "name:por_x_preferred":[
        "Caldera"
    ],
    "name:ron_x_preferred":[
        "Caldera"
    ],
    "name:slk_x_preferred":[
        "Caldera"
    ],
    "name:slv_x_preferred":[
        "Caldera"
    ],
    "name:spa_x_preferred":[
        "Caldera"
    ],
    "name:srp_x_preferred":[
        "Caldera"
    ],
    "name:swe_x_preferred":[
        "Caldera"
    ],
    "name:tgl_x_preferred":[
        "Caldera"
    ],
    "name:tur_x_preferred":[
        "Caldera"
    ],
    "name:ukr_x_preferred":[
        "\u041a\u0430\u043b\u0434\u0435\u0440\u0430"
    ],
    "name:urd_x_preferred":[
        "\u06a9\u06cc\u0644\u0688\u06cc\u0631\u0627"
    ],
    "name:vie_x_preferred":[
        "Caldera"
    ],
    "name:war_x_preferred":[
        "Caldera"
    ],
    "qs_pg:aaroncc":"IT",
    "qs_pg:name":"Caldera",
    "qs_pg:name_adm0":"Italia",
    "qs_pg:name_adm1":"Lombardia",
    "qs_pg:photos":7,
    "qs_pg:photos_1k":1,
    "qs_pg:photos_9k":1,
    "qs_pg:photos_9r":1,
    "qs_pg:photos_all":7,
    "qs_pg:photos_sr":1,
    "qs_pg:pop_sr":0,
    "qs_pg:qs_pg_placetype":"locality",
    "qs_pg:qs_pg_placetype_gp":"Town",
    "qs_pg:woe_adm0":23424853,
    "woe:adm0_id":23424853,
    "woe:name_adm0":"Italia",
    "woe:name_adm1":"Lombardia",
    "woe:placetype":"Town",
    "wof:name":"Caldera",
    "wof:placetype":"locality"
},
  "geometry": {"coordinates":[9.214353,45.134465],"type":"Point"}
}