{
  "type": "Feature",
  "properties": {
    "gn:gn_country":"IT",
    "gn:gn_fcode":"PPLA3",
    "gn:gn_pop":278,
    "gn:population":250,
    "iso:country":"IT",
    "name:arm_x_preferred":[
        "\u0532\u0561\u0575\u0561\u0580\u0564\u0578"
    ],
    "name:baq_x_preferred":[
        "Bajardo"
    ],
    "name:bel_x_preferred":[
        "\u0411\u0430\u044f\u0440\u0434\u0430"
    ],
    "name:bul_x_preferred":[
        "\u0411\u0430\u044f\u0440\u0434\u043e"
    ],
    "name:cat_x_preferred":[
        "Bajardo"
    ],
    "name:chi_x_preferred":[
        "\u5df4\u4e9a\u5c14\u591a"
    ],
    "name:dut_x_preferred":[
        "Bajardo"
    ],
    "name:eng_x_preferred":[
        "Bajardo"
    ],
    "name:epo_x_preferred":[
        "Bajardo"
    ],
    "name:fre_x_preferred":[
        "Bajardo"
    ],
    "name:ger_x_preferred":[
        "Bajardo"
    ],
    "name:hun_x_preferred":[
        "Bajardo"
    ],
    "name:ina_x_preferred":[
        "Bajardo"
    ],
    "name:ita_x_preferred":[
        "Bajardo"
    ],
    "name:jpn_x_preferred":[
        "\u30d0\u30e4\u30eb\u30c9"
    ],
    "name:kaz_x_preferred":[
        "\u0411\u0430\u044f\u0440\u0434\u043e"
    ],
    "name:lat_x_preferred":[
        "Bajartum"
    ],
    "name:lij_x_preferred":[
        "Baiardo"
    ],
    "name:lmo_x_preferred":[
        "Bajardo"
    ],
    "name:may_x_preferred":[
        "Bajardo"
    ],
    "name:nan_x_preferred":[
        "Bajardo"
    ],
    "name:nap_x_preferred":[
        "Bajardo"
    ],
    "name:per_x_preferred":[
        "\u0628\u0627\u06cc\u0627\u0631\u062f\u0648"
    ],
    "name:pms_x_preferred":[
        "Bajardo"
    ],
    "name:pol_x_preferred":[
        "Bajardo"
    ],
    "name:por_x_preferred":[
        "Bajardo"
    ],
    "name:rum_x_preferred":[
        "Bajardo"
    ],
    "name:rus_x_preferred":[
        "\u0411\u0430\u044f\u0440\u0434\u043e"
    ],
    "name:scn_x_preferred":[
        "Bajardo"
    ],
    "name:spa_x_preferred":[
        "Bajardo"
    ],
    "name:srp_x_preferred":[
        "Bajardo"
    ],
    "name:ukr_x_preferred":[
        "\u0411\u0430\u044f\u0440\u0434\u043e"
    ],
    "name:uzb_x_preferred":[
        "Bajardo"
    ],
    "name:vie_x_preferred":[
        "Bajardo"
    ],
    "name:vol_x_preferred":[
        "Bajardo"
    ],
    "name:war_x_preferred":[
        "Bajardo"
    ],
    "qs_pg:aaroncc":"IT",
    "qs_pg:gn_country":"IT",
    "qs_pg:gn_fcode":"PPLA3",
    "qs_pg:gn_pop":278,
    "qs_pg:name":"Bajardo",
    "qs_pg:photos_9r":0,
    "qs_pg:photos_sr":0,
    "qs_pg:pop_sr":2,
    "qs_pg:qs_pg_placetype":"locality",
    "wof:name":"Bajardo",
    "wof:placetype":"locality",
    "wof:population":250
},
  "geometry": {"coordinates":[7.72534,43.90402],"type":"Point"}
}