{
  "type": "Feature",
  "properties": {
    "gn:admin1_code":"7.0",
    "gn:admin2_code":"RM",
    "gn:admin3_code":"58105.0",
    "gn:asciiname":"Bagni di Stigliano",
    "gn:country_code":"IT",
    "gn:dem":200,
    "gn:feature_class":"P",
    "gn:feature_code":"PPL",
    "gn:name":"Bagni di Stigliano",
    "gn:population":0,
    "gn:timezone":"Europe/Rome",
    "iso:country":"IT",
    "wof:name":"Bagni di Stigliano",
    "wof:placetype":"locality"
},
  "geometry": {"coordinates":[12.03333,42.11667],"type":"Point"}
}