{
  "type": "Feature",
  "properties": {
    "gn:admin1_code":"3.0",
    "gn:admin2_code":"RC",
    "gn:admin3_code":"80040.0",
    "gn:asciiname":"Maida I",
    "gn:country_code":"IT",
    "gn:dem":186,
    "gn:feature_class":"P",
    "gn:feature_code":"PPL",
    "gn:name":"Maida I",
    "gn:population":60,
    "gn:timezone":"Europe/Rome",
    "iso:country":"IT",
    "wof:name":"Maida I",
    "wof:placetype":"locality",
    "wof:population":60
},
  "geometry": {"coordinates":[16.26476,38.348],"type":"Point"}
}