{
  "type": "Feature",
  "properties": {
    "gn:admin1_code":"5",
    "gn:admin2_code":"FC",
    "gn:admin3_code":"40008.0",
    "gn:asciiname":"Pisciatello",
    "gn:country_code":"IT",
    "gn:dem":4,
    "gn:feature_class":"P",
    "gn:feature_code":"PPL",
    "gn:name":"Pisciatello",
    "gn:population":53,
    "gn:timezone":"Europe/Rome",
    "iso:country":"IT",
    "wof:name":"Pisciatello",
    "wof:placetype":"locality",
    "wof:population":53
},
  "geometry": {"coordinates":[12.39897,44.16561],"type":"Point"}
}