{
  "type": "Feature",
  "properties": {
    "gn:admin1_code":"1",
    "gn:admin2_code":"CH",
    "gn:admin3_code":"69005.0",
    "gn:asciiname":"Campanelle-Colle Comune",
    "gn:country_code":"IT",
    "gn:dem":94,
    "gn:feature_class":"P",
    "gn:feature_code":"PPL",
    "gn:name":"Campanelle-Colle Comune",
    "gn:population":42,
    "gn:timezone":"Europe/Rome",
    "iso:country":"IT",
    "wof:name":"Campanelle-Colle Comune",
    "wof:placetype":"locality",
    "wof:population":42
},
  "geometry": {"coordinates":[14.42333,42.12267],"type":"Point"}
}