{
  "type": "Feature",
  "properties": {
    "gn:admin1_code":"9.0",
    "gn:admin2_code":"SO",
    "gn:admin3_code":"14032.0",
    "gn:asciiname":"Prato Pincee",
    "gn:country_code":"IT",
    "gn:dem":919,
    "gn:feature_class":"P",
    "gn:feature_code":"PPLL",
    "gn:name":"Prato Pince\u00e8",
    "gn:population":0,
    "gn:timezone":"Europe/Rome",
    "iso:country":"IT",
    "name:und_x_variant":[
        "Prato Pince\u00e8"
    ],
    "wof:name":"Prato Pincee",
    "wof:placetype":"locality"
},
  "geometry": {"coordinates":[9.33259,46.27072],"type":"Point"}
}