{
  "type": "Feature",
  "properties": {
    "gn:admin1_code":"12",
    "gn:admin2_code":"TO",
    "gn:admin3_code":"1242.0",
    "gn:asciiname":"Ponte Palestro",
    "gn:country_code":"IT",
    "gn:dem":440,
    "gn:feature_class":"P",
    "gn:feature_code":"PPL",
    "gn:name":"Ponte Palestro",
    "gn:population":70,
    "gn:timezone":"Europe/Rome",
    "iso:country":"IT",
    "wof:name":"Ponte Palestro",
    "wof:placetype":"locality",
    "wof:population":70
},
  "geometry": {"coordinates":[7.25905,44.88908],"type":"Point"}
}