{
  "type": "Feature",
  "properties": {
    "gn:admin1_code":"8",
    "gn:admin2_code":"SP",
    "gn:admin3_code":"11023.0",
    "gn:asciiname":"Case Molinari",
    "gn:country_code":"IT",
    "gn:dem":157,
    "gn:feature_class":"P",
    "gn:feature_code":"PPL",
    "gn:name":"Case Molinari",
    "gn:population":17,
    "gn:timezone":"Europe/Rome",
    "iso:country":"IT",
    "wof:name":"Case Molinari",
    "wof:placetype":"locality",
    "wof:population":17
},
  "geometry": {"coordinates":[9.78741,44.14445],"type":"Point"}
}