{
  "type": "Feature",
  "properties": {
    "gn:admin1_code":"3.0",
    "gn:admin2_code":"CS",
    "gn:admin3_code":"78134.0",
    "gn:asciiname":"Vallegianno",
    "gn:country_code":"IT",
    "gn:dem":646,
    "gn:feature_class":"P",
    "gn:feature_code":"PPL",
    "gn:name":"Vallegianno",
    "gn:population":535,
    "gn:timezone":"Europe/Rome",
    "iso:country":"IT",
    "wof:name":"Vallegianno",
    "wof:placetype":"locality",
    "wof:population":535
},
  "geometry": {"coordinates":[16.30519,39.19922],"type":"Point"}
}