{
  "type": "Feature",
  "properties": {
    "gn:admin1_code":"5.0",
    "gn:admin2_code":"BO",
    "gn:admin3_code":"37028.0",
    "gn:asciiname":"Bosco",
    "gn:country_code":"IT",
    "gn:dem":12,
    "gn:feature_class":"P",
    "gn:feature_code":"PPL",
    "gn:name":"Bosco",
    "gn:population":14,
    "gn:timezone":"Europe/Rome",
    "iso:country":"IT",
    "wof:name":"Bosco",
    "wof:placetype":"locality",
    "wof:population":14
},
  "geometry": {"coordinates":[11.50717,44.73573],"type":"Point"}
}