{
  "type": "Feature",
  "properties": {
    "gn:admin1_code":"8",
    "gn:admin2_code":"SV",
    "gn:admin3_code":"9058.0",
    "gn:asciiname":"Sansobbia II",
    "gn:country_code":"IT",
    "gn:dem":179,
    "gn:feature_class":"P",
    "gn:feature_code":"PPL",
    "gn:name":"Sansobbia II",
    "gn:population":26,
    "gn:timezone":"Europe/Rome",
    "iso:country":"IT",
    "wof:name":"Sansobbia II",
    "wof:placetype":"locality",
    "wof:population":26
},
  "geometry": {"coordinates":[8.49452,44.39143],"type":"Point"}
}