{
  "type": "Feature",
  "properties": {
    "gn:admin1_code":"12",
    "gn:admin2_code":"AL",
    "gn:admin3_code":"6036.0",
    "gn:asciiname":"Gaini",
    "gn:country_code":"IT",
    "gn:dem":189,
    "gn:feature_class":"P",
    "gn:feature_code":"PPL",
    "gn:name":"Gaini",
    "gn:population":17,
    "gn:timezone":"Europe/Rome",
    "iso:country":"IT",
    "name:fra_x_preferred":[
        "Gaini"
    ],
    "name:ind_x_preferred":[
        "Suku Gaini"
    ],
    "wof:name":"Gaini",
    "wof:placetype":"locality",
    "wof:population":17
},
  "geometry": {"coordinates":[8.40798,44.61384],"type":"Point"}
}