{
  "type": "Feature",
  "properties": {
    "gn:admin1_code":"12.0",
    "gn:admin2_code":"BI",
    "gn:admin3_code":"96062.0",
    "gn:asciiname":"Cerreia",
    "gn:country_code":"IT",
    "gn:dem":551,
    "gn:feature_class":"P",
    "gn:feature_code":"PPL",
    "gn:name":"Cerreia",
    "gn:population":112,
    "gn:timezone":"Europe/Rome",
    "iso:country":"IT",
    "wof:name":"Cerreia",
    "wof:placetype":"locality",
    "wof:population":112
},
  "geometry": {"coordinates":[8.18487,45.64487],"type":"Point"}
}