{
  "type": "Feature",
  "properties": {
    "gn:admin1_code":"9",
    "gn:admin2_code":"SO",
    "gn:admin3_code":"14022.0",
    "gn:asciiname":"Serone",
    "gn:country_code":"IT",
    "gn:dem":724,
    "gn:feature_class":"P",
    "gn:feature_code":"PPLA3",
    "gn:name":"Serone",
    "gn:population":71,
    "gn:timezone":"Europe/Rome",
    "iso:country":"IT",
    "wof:name":"Serone",
    "wof:placetype":"locality",
    "wof:population":71
},
  "geometry": {"coordinates":[9.58171,46.15627],"type":"Point"}
}