{
  "type": "Feature",
  "properties": {
    "gn:admin1_code":"9",
    "gn:admin2_code":"LO",
    "gn:admin3_code":"98043.0",
    "gn:asciiname":"Cascina Mandella",
    "gn:country_code":"IT",
    "gn:dem":66,
    "gn:feature_class":"P",
    "gn:feature_code":"PPL",
    "gn:name":"Cascina Mandella",
    "gn:population":24,
    "gn:timezone":"Europe/Rome",
    "iso:country":"IT",
    "wof:name":"Cascina Mandella",
    "wof:placetype":"locality",
    "wof:population":24
},
  "geometry": {"coordinates":[9.59422,45.16772],"type":"Point"}
}