{
  "type": "Feature",
  "properties": {
    "gn:admin1_code":"8",
    "gn:admin2_code":"SV",
    "gn:admin3_code":"9059.0",
    "gn:asciiname":"Duranti",
    "gn:country_code":"IT",
    "gn:dem":386,
    "gn:feature_class":"P",
    "gn:feature_code":"PPL",
    "gn:name":"Duranti",
    "gn:population":15,
    "gn:timezone":"Europe/Rome",
    "iso:country":"IT",
    "wof:name":"Duranti",
    "wof:placetype":"locality",
    "wof:population":15
},
  "geometry": {"coordinates":[8.02164,43.99543],"type":"Point"}
}