{
  "type": "Feature",
  "properties": {
    "gn:admin1_code":"12",
    "gn:admin2_code":"CN",
    "gn:admin3_code":"4157.0",
    "gn:asciiname":"Pertus",
    "gn:country_code":"IT",
    "gn:dem":942,
    "gn:feature_class":"P",
    "gn:feature_code":"PPL",
    "gn:name":"Pertus",
    "gn:population":16,
    "gn:timezone":"Europe/Rome",
    "iso:country":"IT",
    "wof:name":"Pertus",
    "wof:placetype":"locality",
    "wof:population":16
},
  "geometry": {"coordinates":[7.22165,44.68722],"type":"Point"}
}