{
  "type": "Feature",
  "properties": {
    "gn:admin1_code":"12.0",
    "gn:admin2_code":"CN",
    "gn:admin3_code":"4207.0",
    "gn:asciiname":"Combamala",
    "gn:country_code":"IT",
    "gn:dem":1007,
    "gn:feature_class":"P",
    "gn:feature_code":"PPLL",
    "gn:name":"Combamala",
    "gn:population":3,
    "gn:timezone":"Europe/Rome",
    "iso:country":"IT",
    "wof:name":"Combamala",
    "wof:placetype":"locality",
    "wof:population":3
},
  "geometry": {"coordinates":[7.23211,44.47455],"type":"Point"}
}