{
  "type": "Feature",
  "properties": {
    "gn:admin1_code":"9",
    "gn:admin2_code":"MN",
    "gn:admin3_code":"20044.0",
    "gn:asciiname":"Centrale Termoelettrica",
    "gn:country_code":"IT",
    "gn:dem":67,
    "gn:feature_class":"P",
    "gn:feature_code":"PPL",
    "gn:name":"Centrale Termoelettrica",
    "gn:population":14,
    "gn:timezone":"Europe/Rome",
    "iso:country":"IT",
    "wof:name":"Centrale Termoelettrica",
    "wof:placetype":"locality",
    "wof:population":14
},
  "geometry": {"coordinates":[10.71553,45.40223],"type":"Point"}
}