{
  "type": "Feature",
  "properties": {
    "gn:admin1_code":"9.0",
    "gn:admin2_code":"SO",
    "gn:admin3_code":"14036.0",
    "gn:asciiname":"Alpe Acquanegra",
    "gn:cc2":"IT",
    "gn:country_code":"IT",
    "gn:dem":2077,
    "gn:feature_class":"P",
    "gn:feature_code":"PPL",
    "gn:name":"Alpe Acquanegra",
    "gn:population":0,
    "gn:timezone":"Europe/Rome",
    "iso:country":"IT",
    "name:und_x_variant":[
        "Alpe Acquanera",
        "Alpe Acquanegra"
    ],
    "wof:name":"Alpe Acquanegra",
    "wof:placetype":"locality"
},
  "geometry": {"coordinates":[9.91667,46.26667],"type":"Point"}
}