{
  "type": "Feature",
  "properties": {
    "gn:admin1_code":"12",
    "gn:admin2_code":"TO",
    "gn:admin3_code":"1209.0",
    "gn:asciiname":"Area Produttiva",
    "gn:country_code":"IT",
    "gn:dem":259,
    "gn:feature_class":"P",
    "gn:feature_code":"PPL",
    "gn:name":"Area Produttiva",
    "gn:population":15,
    "gn:timezone":"Europe/Rome",
    "iso:country":"IT",
    "wof:name":"Area Produttiva",
    "wof:placetype":"locality",
    "wof:population":15
},
  "geometry": {"coordinates":[7.83897,45.52484000000001],"type":"Point"}
}