{
  "type": "Feature",
  "properties": {
    "gn:admin1_code":"12",
    "gn:admin2_code":"TO",
    "gn:admin3_code":"1249.0",
    "gn:asciiname":"Area Produttiva",
    "gn:country_code":"IT",
    "gn:dem":213,
    "gn:feature_class":"P",
    "gn:feature_code":"PPL",
    "gn:name":"Area Produttiva",
    "gn:population":71,
    "gn:timezone":"Europe/Rome",
    "iso:country":"IT",
    "wof:name":"Area Produttiva",
    "wof:placetype":"locality",
    "wof:population":71
},
  "geometry": {"coordinates":[7.74473,45.11709000000001],"type":"Point"}
}