{
  "type": "Feature",
  "properties": {
    "gn:admin1_code":"20.0",
    "gn:admin2_code":"TV",
    "gn:admin3_code":"26074.0",
    "gn:asciiname":"Rai",
    "gn:country_code":"IT",
    "gn:dem":25,
    "gn:elevation":"26.0",
    "gn:feature_class":"P",
    "gn:feature_code":"PPL",
    "gn:name":"Rai",
    "gn:population":373,
    "gn:timezone":"Europe/Rome",
    "iso:country":"IT",
    "name:ara_x_preferred":[
        "\u0631\u0627\u064a"
    ],
    "name:ben_x_preferred":[
        "\u09b0\u09be\u0987"
    ],
    "name:ceb_x_preferred":[
        "Rai"
    ],
    "name:ces_x_preferred":[
        "Rai"
    ],
    "name:fin_x_preferred":[
        "Rai"
    ],
    "name:fra_x_preferred":[
        "Rai"
    ],
    "name:hun_x_preferred":[
        "Rai"
    ],
    "name:ita_x_preferred":[
        "RAI"
    ],
    "name:nld_x_preferred":[
        "Rai"
    ],
    "name:nor_x_preferred":[
        "Rai"
    ],
    "name:pol_x_preferred":[
        "Rai"
    ],
    "name:por_x_preferred":[
        "RAI"
    ],
    "name:ron_x_preferred":[
        "Rai"
    ],
    "name:slk_x_preferred":[
        "Rai"
    ],
    "name:spa_x_preferred":[
        "Rai"
    ],
    "name:srp_x_preferred":[
        "Rai"
    ],
    "name:swe_x_preferred":[
        "Rai"
    ],
    "wof:name":"Rai",
    "wof:placetype":"locality",
    "wof:population":373
},
  "geometry": {"coordinates":[12.3927,45.80789],"type":"Point"}
}