{
  "type": "Feature",
  "properties": {
    "gn:admin1_code":"20.0",
    "gn:admin2_code":"TV",
    "gn:admin3_code":"26074.0",
    "gn:asciiname":"Rai",
    "gn:country_code":"IT",
    "gn:dem":25,
    "gn:elevation":"26.0",
    "gn:feature_class":"P",
    "gn:feature_code":"PPL",
    "gn:name":"Rai",
    "gn:population":373,
    "gn:timezone":"Europe/Rome",
    "iso:country":"IT",
    "wof:name":"Rai",
    "wof:placetype":"locality",
    "wof:population":373
},
  "geometry": {"coordinates":[12.3927,45.80789],"type":"Point"}
}