{
  "type": "Feature",
  "properties": {
    "gn:admin1_code":"16",
    "gn:admin2_code":"GR",
    "gn:admin3_code":"53011.0",
    "gn:asciiname":"Nomadelfia",
    "gn:country_code":"IT",
    "gn:dem":86,
    "gn:feature_class":"P",
    "gn:feature_code":"PPL",
    "gn:name":"Nomadelfia",
    "gn:population":289,
    "gn:timezone":"Europe/Rome",
    "iso:country":"IT",
    "name:ceb_x_preferred":[
        "Nomadelfia"
    ],
    "name:ita_x_preferred":[
        "Nomadelfia"
    ],
    "name:nld_x_preferred":[
        "Nomadelfia"
    ],
    "name:por_x_preferred":[
        "Nomad\u00e9lfia"
    ],
    "name:srp_x_preferred":[
        "\u041d\u043e\u043c\u0430\u0434\u0435\u043b\u0444\u0438\u0458\u0430"
    ],
    "wof:name":"Nomadelfia",
    "wof:placetype":"locality",
    "wof:population":289
},
  "geometry": {"coordinates":[11.14314,42.84201],"type":"Point"}
}