{
  "type": "Feature",
  "properties": {
    "gn:admin1_code":"9",
    "gn:admin2_code":"PV",
    "gn:admin3_code":"18073.0",
    "gn:asciiname":"Gomo",
    "gn:country_code":"IT",
    "gn:dem":492,
    "gn:feature_class":"P",
    "gn:feature_code":"PPL",
    "gn:name":"Gomo",
    "gn:population":13,
    "gn:timezone":"Europe/Rome",
    "iso:country":"IT",
    "name:ceb_x_preferred":[
        "Gomo"
    ],
    "name:por_x_preferred":[
        "Gomo"
    ],
    "name:swe_x_preferred":[
        "Gomo"
    ],
    "wof:name":"Gomo",
    "wof:placetype":"locality",
    "wof:population":13
},
  "geometry": {"coordinates":[9.07049,44.90773],"type":"Point"}
}