{
  "type": "Feature",
  "properties": {
    "gn:admin1_code":"8",
    "gn:admin2_code":"SV",
    "gn:admin3_code":"9001.0",
    "gn:asciiname":"Vegliasco",
    "gn:country_code":"IT",
    "gn:dem":357,
    "gn:feature_class":"P",
    "gn:feature_code":"PPL",
    "gn:name":"Vegliasco",
    "gn:population":25,
    "gn:timezone":"Europe/Rome",
    "iso:country":"IT",
    "wof:name":"Vegliasco",
    "wof:placetype":"locality",
    "wof:population":25
},
  "geometry": {"coordinates":[8.1616,44.01931],"type":"Point"}
}