{
  "type": "Feature",
  "properties": {
    "gn:admin1_code":"20",
    "gn:admin2_code":"RO",
    "gn:admin3_code":"29029.0",
    "gn:asciiname":"Molinella",
    "gn:country_code":"IT",
    "gn:dem":3,
    "gn:feature_class":"P",
    "gn:feature_code":"PPL",
    "gn:name":"Molinella",
    "gn:population":52,
    "gn:timezone":"Europe/Rome",
    "iso:country":"IT",
    "wof:name":"Molinella",
    "wof:placetype":"locality",
    "wof:population":52
},
  "geometry": {"coordinates":[11.6084,45.04568],"type":"Point"}
}