{
  "type": "Feature",
  "properties": {
    "gn:admin1_code":"4",
    "gn:admin2_code":"BN",
    "gn:admin3_code":"62061.0",
    "gn:asciiname":"Cancello",
    "gn:country_code":"IT",
    "gn:dem":220,
    "gn:feature_class":"P",
    "gn:feature_code":"PPL",
    "gn:name":"Cancello",
    "gn:population":40,
    "gn:timezone":"Europe/Rome",
    "iso:country":"IT",
    "name:ceb_x_preferred":[
        "Cancello"
    ],
    "name:ita_x_preferred":[
        "Cancello"
    ],
    "name:nld_x_preferred":[
        "Cancello"
    ],
    "name:srp_x_preferred":[
        "Kan\u010delo"
    ],
    "name:swe_x_preferred":[
        "Cancello"
    ],
    "wof:name":"Cancello",
    "wof:placetype":"locality",
    "wof:population":40
},
  "geometry": {"coordinates":[14.53586,41.25294],"type":"Point"}
}