{
  "type": "Feature",
  "properties": {
    "gn:admin1_code":"9.0",
    "gn:admin2_code":"LO",
    "gn:admin3_code":"98012.0",
    "gn:asciiname":"Calvenzano",
    "gn:country_code":"IT",
    "gn:dem":77,
    "gn:feature_class":"P",
    "gn:feature_code":"PPL",
    "gn:name":"Calvenzano",
    "gn:population":668,
    "gn:timezone":"Europe/Rome",
    "iso:country":"IT",
    "wof:name":"Calvenzano",
    "wof:placetype":"locality",
    "wof:population":668
},
  "geometry": {"coordinates":[9.37966,45.26929000000001],"type":"Point"}
}