{
  "type": "Feature",
  "properties": {
    "gn:admin1_code":"9.0",
    "gn:admin2_code":"LO",
    "gn:admin3_code":"98012.0",
    "gn:asciiname":"Calvenzano",
    "gn:country_code":"IT",
    "gn:dem":77,
    "gn:feature_class":"P",
    "gn:feature_code":"PPL",
    "gn:name":"Calvenzano",
    "gn:population":668,
    "gn:timezone":"Europe/Rome",
    "iso:country":"IT",
    "name:azb_x_preferred":[
        "\u06a9\u0627\u0644\u0648\u0646\u062a\u0632\u0627\u0646\u0648"
    ],
    "name:ceb_x_preferred":[
        "Calvenzano"
    ],
    "name:deu_x_preferred":[
        "Calvenzano"
    ],
    "name:epo_x_preferred":[
        "Calvenzano"
    ],
    "name:eus_x_preferred":[
        "Calvenzano"
    ],
    "name:fas_x_preferred":[
        "\u06a9\u0627\u0644\u0648\u0646\u062a\u0632\u0627\u0646\u0648"
    ],
    "name:fra_x_preferred":[
        "Calvenzano"
    ],
    "name:hun_x_preferred":[
        "Calvenzano"
    ],
    "name:hye_x_preferred":[
        "\u053f\u0561\u056c\u057e\u0565\u0576\u0581\u0561\u0576\u0578"
    ],
    "name:ina_x_preferred":[
        "Calvenzano"
    ],
    "name:ita_x_preferred":[
        "Calvenzano"
    ],
    "name:jpn_x_preferred":[
        "\u30ab\u30eb\u30f4\u30a7\u30f3\u30c4\u30a1\u30fc\u30ce"
    ],
    "name:kaz_x_preferred":[
        "\u041a\u0430\u043b\u044c\u0432\u0435\u043d\u0446\u0430\u043d\u043e"
    ],
    "name:lat_x_preferred":[
        "Calventianum"
    ],
    "name:lmo_x_preferred":[
        "Carvens\u00e0"
    ],
    "name:msa_x_preferred":[
        "Calvenzano"
    ],
    "name:nap_x_preferred":[
        "Calvenzano"
    ],
    "name:nld_x_preferred":[
        "Calvenzano"
    ],
    "name:nor_x_preferred":[
        "Calvenzano"
    ],
    "name:pms_x_preferred":[
        "Calvenzano"
    ],
    "name:pol_x_preferred":[
        "Calvenzano"
    ],
    "name:por_x_preferred":[
        "Calvenzano"
    ],
    "name:ron_x_preferred":[
        "Calvenzano"
    ],
    "name:rus_x_preferred":[
        "\u041a\u0430\u043b\u044c\u0432\u0435\u043d\u0446\u0430\u043d\u043e"
    ],
    "name:scn_x_preferred":[
        "Calvenzano"
    ],
    "name:spa_x_preferred":[
        "Calvenzano"
    ],
    "name:srp_x_preferred":[
        "\u041a\u0430\u043b\u0432\u0435\u043d\u0446\u0430\u043d\u043e"
    ],
    "name:tgl_x_preferred":[
        "Calvenzano"
    ],
    "name:ukr_x_preferred":[
        "\u041a\u0430\u043b\u044c\u0432\u0435\u043d\u0446\u0430\u043d\u043e"
    ],
    "name:uzb_x_preferred":[
        "Calvenzano"
    ],
    "name:vie_x_preferred":[
        "Calvenzano"
    ],
    "name:vol_x_preferred":[
        "Calvenzano"
    ],
    "name:war_x_preferred":[
        "Calvenzano"
    ],
    "name:zho_x_preferred":[
        "\u5361\u5c14\u6587\u624e\u8bfa"
    ],
    "wof:name":"Calvenzano",
    "wof:placetype":"locality",
    "wof:population":668
},
  "geometry": {"coordinates":[9.37966,45.26929000000001],"type":"Point"}
}