{
  "type": "Feature",
  "properties": {
    "gn:admin1_code":"8",
    "gn:admin2_code":"SP",
    "gn:admin3_code":"11012.0",
    "gn:asciiname":"Ca' Miro",
    "gn:country_code":"IT",
    "gn:dem":62,
    "gn:feature_class":"P",
    "gn:feature_code":"PPL",
    "gn:name":"Ca' Mir\u00f2",
    "gn:population":226,
    "gn:timezone":"Europe/Rome",
    "iso:country":"IT",
    "name:und_x_variant":[
        "Ca' Mir\u00f2"
    ],
    "wof:name":"Ca' Miro",
    "wof:placetype":"locality",
    "wof:population":226
},
  "geometry": {"coordinates":[9.54167,44.2255],"type":"Point"}
}