{
  "type": "Feature",
  "properties": {
    "gn:admin1_code":"5",
    "gn:admin2_code":"PR",
    "gn:admin3_code":"34044.0",
    "gn:asciiname":"Castellaro",
    "gn:country_code":"IT",
    "gn:dem":904,
    "gn:feature_class":"P",
    "gn:feature_code":"PPLL",
    "gn:name":"Castellaro",
    "gn:population":10,
    "gn:timezone":"Europe/Rome",
    "iso:country":"IT",
    "wof:name":"Castellaro",
    "wof:placetype":"locality",
    "wof:population":10
},
  "geometry": {"coordinates":[9.84322,44.59918],"type":"Point"}
}