{
  "type": "Feature",
  "properties": {
    "gn:admin1_code":"4.0",
    "gn:admin2_code":"AV",
    "gn:admin3_code":"64099.0",
    "gn:asciiname":"Toppola",
    "gn:country_code":"IT",
    "gn:dem":605,
    "gn:feature_class":"P",
    "gn:feature_code":"PPL",
    "gn:name":"Toppola",
    "gn:population":21,
    "gn:timezone":"Europe/Rome",
    "iso:country":"IT",
    "wof:name":"Toppola",
    "wof:placetype":"locality",
    "wof:population":21
},
  "geometry": {"coordinates":[14.85015,40.84992],"type":"Point"}
}