{
  "type": "Feature",
  "properties": {
    "gn:admin1_code":"16",
    "gn:admin2_code":"AR",
    "gn:admin3_code":"51010.0",
    "gn:asciiname":"Castagneto",
    "gn:country_code":"IT",
    "gn:dem":583,
    "gn:feature_class":"P",
    "gn:feature_code":"PPL",
    "gn:name":"Castagneto",
    "gn:population":12,
    "gn:timezone":"Europe/Rome",
    "iso:country":"IT",
    "wof:name":"Castagneto",
    "wof:placetype":"locality",
    "wof:population":12
},
  "geometry": {"coordinates":[11.66164,43.71377],"type":"Point"}
}