{
  "type": "Feature",
  "properties": {
    "gn:admin1_code":"8",
    "gn:admin2_code":"SP",
    "gn:admin3_code":"11014.0",
    "gn:asciiname":"Foce",
    "gn:country_code":"IT",
    "gn:dem":350,
    "gn:feature_class":"P",
    "gn:feature_code":"PPL",
    "gn:name":"Foce",
    "gn:population":13,
    "gn:timezone":"Europe/Rome",
    "iso:country":"IT",
    "name:cat_x_preferred":[
        "Foce"
    ],
    "name:ceb_x_preferred":[
        "Foce"
    ],
    "name:deu_x_preferred":[
        "Foce"
    ],
    "name:eus_x_preferred":[
        "Foce"
    ],
    "name:fra_x_preferred":[
        "Foce"
    ],
    "name:hun_x_preferred":[
        "Foce"
    ],
    "name:hye_x_preferred":[
        "\u0556\u0578\u0579\u0565"
    ],
    "name:ind_x_preferred":[
        "Foce"
    ],
    "name:ita_x_preferred":[
        "Foce"
    ],
    "name:kaz_x_preferred":[
        "\u0424\u043e\u0447\u0435"
    ],
    "name:lat_x_preferred":[
        "Foce"
    ],
    "name:lmo_x_preferred":[
        "Foce"
    ],
    "name:msa_x_preferred":[
        "Foce"
    ],
    "name:nld_x_preferred":[
        "Foce"
    ],
    "name:nor_x_preferred":[
        "Foce"
    ],
    "name:oci_x_preferred":[
        "Foce"
    ],
    "name:pol_x_preferred":[
        "Foce"
    ],
    "name:por_x_preferred":[
        "Foce"
    ],
    "name:rus_x_preferred":[
        "\u0424\u043e\u0447\u0435"
    ],
    "name:slk_x_preferred":[
        "Foce"
    ],
    "name:slv_x_preferred":[
        "Foce"
    ],
    "name:spa_x_preferred":[
        "Foce"
    ],
    "name:swe_x_preferred":[
        "Foce"
    ],
    "name:ukr_x_preferred":[
        "\u0424\u043e\u0447\u0435"
    ],
    "name:vie_x_preferred":[
        "Foce"
    ],
    "name:vol_x_preferred":[
        "Foce"
    ],
    "name:war_x_preferred":[
        "Foce"
    ],
    "wof:name":"Foce",
    "wof:placetype":"locality",
    "wof:population":13
},
  "geometry": {"coordinates":[9.56476,44.20587],"type":"Point"}
}