{
  "type": "Feature",
  "properties": {
    "gn:admin1_code":"8",
    "gn:admin2_code":"SP",
    "gn:admin3_code":"11014.0",
    "gn:asciiname":"Foce",
    "gn:country_code":"IT",
    "gn:dem":350,
    "gn:feature_class":"P",
    "gn:feature_code":"PPL",
    "gn:name":"Foce",
    "gn:population":13,
    "gn:timezone":"Europe/Rome",
    "iso:country":"IT",
    "wof:name":"Foce",
    "wof:placetype":"locality",
    "wof:population":13
},
  "geometry": {"coordinates":[9.56476,44.20587],"type":"Point"}
}