{
  "type": "Feature",
  "properties": {
    "gn:admin1_code":"12.0",
    "gn:admin2_code":"TO",
    "gn:admin3_code":"1203.0",
    "gn:asciiname":"Benne del Cavallo",
    "gn:country_code":"IT",
    "gn:dem":285,
    "gn:feature_class":"P",
    "gn:feature_code":"PPL",
    "gn:name":"Benne del Cavallo",
    "gn:population":26,
    "gn:timezone":"Europe/Rome",
    "iso:country":"IT",
    "wof:name":"Benne del Cavallo",
    "wof:placetype":"locality",
    "wof:population":26
},
  "geometry": {"coordinates":[7.90089,44.83776],"type":"Point"}
}