{
  "type": "Feature",
  "properties": {
    "gn:admin1_code":"2",
    "gn:admin2_code":"MT",
    "gn:admin3_code":"77029.0",
    "gn:asciiname":"Ginnari",
    "gn:country_code":"IT",
    "gn:dem":185,
    "gn:feature_class":"P",
    "gn:feature_code":"PPL",
    "gn:name":"Ginnari",
    "gn:population":24,
    "gn:timezone":"Europe/Rome",
    "iso:country":"IT",
    "wof:name":"Ginnari",
    "wof:placetype":"locality",
    "wof:population":24
},
  "geometry": {"coordinates":[16.57653,40.2309],"type":"Point"}
}