{
  "type": "Feature",
  "properties": {
    "gn:admin1_code":"12",
    "gn:admin2_code":"CN",
    "gn:admin3_code":"4105.0",
    "gn:asciiname":"Mascarelli",
    "gn:country_code":"IT",
    "gn:dem":404,
    "gn:feature_class":"P",
    "gn:feature_code":"PPL",
    "gn:name":"Mascarelli",
    "gn:population":26,
    "gn:timezone":"Europe/Rome",
    "iso:country":"IT",
    "wof:name":"Mascarelli",
    "wof:placetype":"locality",
    "wof:population":26
},
  "geometry": {"coordinates":[7.91447,44.64457],"type":"Point"}
}