{
  "type": "Feature",
  "properties": {
    "gn:admin1_code":"7",
    "gn:admin2_code":"LT",
    "gn:admin3_code":"59032.0",
    "gn:asciiname":"Pietra Porci",
    "gn:country_code":"IT",
    "gn:dem":333,
    "gn:feature_class":"P",
    "gn:feature_code":"PPL",
    "gn:name":"Pietra Porci",
    "gn:population":35,
    "gn:timezone":"Europe/Rome",
    "iso:country":"IT",
    "wof:name":"Pietra Porci",
    "wof:placetype":"locality",
    "wof:population":35
},
  "geometry": {"coordinates":[13.25712,41.35128],"type":"Point"}
}