{
  "type": "Feature",
  "properties": {
    "gn:admin1_code":"18",
    "gn:admin2_code":"PG",
    "gn:admin3_code":"54012.0",
    "gn:asciiname":"Popoltaio-Schiacciato",
    "gn:country_code":"IT",
    "gn:dem":290,
    "gn:feature_class":"P",
    "gn:feature_code":"PPL",
    "gn:name":"Popoltaio-Schiacciato",
    "gn:population":30,
    "gn:timezone":"Europe/Rome",
    "iso:country":"IT",
    "wof:name":"Popoltaio-Schiacciato",
    "wof:placetype":"locality",
    "wof:population":30
},
  "geometry": {"coordinates":[12.02636,43.00712],"type":"Point"}
}