{
  "type": "Feature",
  "properties": {
    "gn:admin1_code":"9",
    "gn:admin2_code":"BG",
    "gn:admin3_code":"16080.0",
    "gn:asciiname":"Via Rezzo",
    "gn:country_code":"IT",
    "gn:dem":723,
    "gn:feature_class":"P",
    "gn:feature_code":"PPL",
    "gn:name":"Via Rezzo",
    "gn:population":44,
    "gn:timezone":"Europe/Rome",
    "iso:country":"IT",
    "wof:name":"Via Rezzo",
    "wof:placetype":"locality",
    "wof:population":44
},
  "geometry": {"coordinates":[9.85247,45.82916],"type":"Point"}
}