{
  "type": "Feature",
  "properties": {
    "gn:admin1_code":"20",
    "gn:admin2_code":"RO",
    "gn:admin3_code":"29041.0",
    "gn:asciiname":"Capolavia",
    "gn:country_code":"IT",
    "gn:dem":0,
    "gn:feature_class":"P",
    "gn:feature_code":"PPL",
    "gn:name":"Capolavia",
    "gn:population":25,
    "gn:timezone":"Europe/Rome",
    "iso:country":"IT",
    "wof:name":"Capolavia",
    "wof:placetype":"locality",
    "wof:population":25
},
  "geometry": {"coordinates":[11.73504,45.05348],"type":"Point"}
}