{
  "type": "Feature",
  "properties": {
    "gn:admin1_code":"12",
    "gn:admin2_code":"AT",
    "gn:admin3_code":"5013.0",
    "gn:asciiname":"San Vito",
    "gn:country_code":"IT",
    "gn:dem":161,
    "gn:feature_class":"P",
    "gn:feature_code":"PPL",
    "gn:name":"San Vito",
    "gn:population":72,
    "gn:timezone":"Europe/Rome",
    "iso:country":"IT",
    "wof:name":"San Vito",
    "wof:placetype":"locality",
    "wof:population":72
},
  "geometry": {"coordinates":[8.32658,44.72132],"type":"Point"}
}