{
  "type": "Feature",
  "properties": {
    "gn:admin1_code":"10",
    "gn:admin2_code":"MC",
    "gn:admin3_code":"43012.0",
    "gn:asciiname":"San Vittore",
    "gn:country_code":"IT",
    "gn:dem":207,
    "gn:feature_class":"P",
    "gn:feature_code":"PPL",
    "gn:name":"San Vittore",
    "gn:population":231,
    "gn:timezone":"Europe/Rome",
    "iso:country":"IT",
    "name:ceb_x_preferred":[
        "San Vittore"
    ],
    "name:deu_x_preferred":[
        "San Vittore"
    ],
    "name:epo_x_preferred":[
        "San Vittore"
    ],
    "name:eus_x_preferred":[
        "San Vittore"
    ],
    "name:ita_x_preferred":[
        "San Vittore"
    ],
    "name:por_x_preferred":[
        "San Vittore"
    ],
    "name:srp_x_preferred":[
        "San Vitore"
    ],
    "name:swe_x_preferred":[
        "San Vittore"
    ],
    "wof:name":"San Vittore",
    "wof:placetype":"locality",
    "wof:population":231
},
  "geometry": {"coordinates":[13.24351,43.43819000000001],"type":"Point"}
}