{
  "type": "Feature",
  "properties": {
    "gn:admin1_code":"10.0",
    "gn:admin2_code":"AN",
    "gn:admin3_code":"42047.0",
    "gn:asciiname":"Trivio",
    "gn:country_code":"IT",
    "gn:dem":461,
    "gn:feature_class":"P",
    "gn:feature_code":"PPL",
    "gn:name":"Trivio",
    "gn:population":18,
    "gn:timezone":"Europe/Rome",
    "iso:country":"IT",
    "wof:name":"Trivio",
    "wof:placetype":"locality",
    "wof:population":18
},
  "geometry": {"coordinates":[13.00101,43.46413],"type":"Point"}
}