{
  "type": "Feature",
  "properties": {
    "gn:admin1_code":"16",
    "gn:admin2_code":"FI",
    "gn:admin3_code":"48050.0",
    "gn:asciiname":"Valinardi",
    "gn:country_code":"IT",
    "gn:dem":43,
    "gn:feature_class":"P",
    "gn:feature_code":"PPL",
    "gn:name":"Valinardi",
    "gn:population":29,
    "gn:timezone":"Europe/Rome",
    "iso:country":"IT",
    "wof:name":"Valinardi",
    "wof:placetype":"locality",
    "wof:population":29
},
  "geometry": {"coordinates":[10.92807,43.77598],"type":"Point"}
}