{
  "type": "Feature",
  "properties": {
    "gn:admin1_code":"16",
    "gn:admin2_code":"MS",
    "gn:admin3_code":"45013.0",
    "gn:asciiname":"Calcinara",
    "gn:country_code":"IT",
    "gn:dem":124,
    "gn:feature_class":"P",
    "gn:feature_code":"PPL",
    "gn:name":"Calcinara",
    "gn:population":16,
    "gn:timezone":"Europe/Rome",
    "iso:country":"IT",
    "name:fas_x_preferred":[
        "\u06a9\u0627\u0644\u0633\u06cc\u0646\u0627\u0631\u0627"
    ],
    "name:ita_x_preferred":[
        "Torrente Calcinara"
    ],
    "name:nno_x_preferred":[
        "Calcinara"
    ],
    "name:por_x_preferred":[
        "Calcinara"
    ],
    "name:tgk_x_preferred":[
        "\u041a\u0430\u043b\u0441\u0438\u043d\u0430\u0440\u0430"
    ],
    "wof:name":"Calcinara",
    "wof:placetype":"locality",
    "wof:population":16
},
  "geometry": {"coordinates":[9.9615,44.20923],"type":"Point"}
}