{
  "type": "Feature",
  "properties": {
    "gn:admin1_code":"20.0",
    "gn:admin2_code":"VI",
    "gn:admin3_code":"24052.0",
    "gn:asciiname":"Monticello",
    "gn:country_code":"IT",
    "gn:dem":106,
    "gn:feature_class":"P",
    "gn:feature_code":"PPL",
    "gn:name":"Monticello",
    "gn:population":33,
    "gn:timezone":"Europe/Rome",
    "iso:country":"IT",
    "wof:name":"Monticello",
    "wof:placetype":"locality",
    "wof:population":33
},
  "geometry": {"coordinates":[11.41814,45.38383],"type":"Point"}
}