{
  "type": "Feature",
  "properties": {
    "gn:admin1_code":"20.0",
    "gn:admin2_code":"VI",
    "gn:admin3_code":"24052.0",
    "gn:asciiname":"Monticello",
    "gn:country_code":"IT",
    "gn:dem":106,
    "gn:feature_class":"P",
    "gn:feature_code":"PPL",
    "gn:name":"Monticello",
    "gn:population":33,
    "gn:timezone":"Europe/Rome",
    "iso:country":"IT",
    "name:ara_x_preferred":[
        "\u0645\u0648\u0646\u062a\u064a\u0633\u064a\u0644\u0648"
    ],
    "name:aze_x_preferred":[
        "Monti\u00e7ello"
    ],
    "name:bul_x_preferred":[
        "\u041c\u043e\u043d\u0442\u0438\u0447\u0435\u043b\u043e"
    ],
    "name:cat_x_preferred":[
        "Monticello"
    ],
    "name:dan_x_preferred":[
        "Monticello"
    ],
    "name:deu_x_preferred":[
        "Monticello"
    ],
    "name:epo_x_preferred":[
        "Monticello"
    ],
    "name:est_x_preferred":[
        "Monticello"
    ],
    "name:eus_x_preferred":[
        "Monticello"
    ],
    "name:fas_x_preferred":[
        "\u0645\u0627\u0646\u062a\u06cc\u0633\u0644\u0648"
    ],
    "name:fin_x_preferred":[
        "Monticello"
    ],
    "name:fra_x_preferred":[
        "Monticello"
    ],
    "name:heb_x_preferred":[
        "\u05de\u05d5\u05e0\u05d8\u05d9\u05e6'\u05dc\u05d5"
    ],
    "name:hrv_x_preferred":[
        "Monticello"
    ],
    "name:hun_x_preferred":[
        "Monticello"
    ],
    "name:ind_x_preferred":[
        "Monticello"
    ],
    "name:ita_x_preferred":[
        "Monticello"
    ],
    "name:jpn_x_preferred":[
        "\u30e2\u30f3\u30c6\u30a3\u30c1\u30a7\u30ed"
    ],
    "name:kat_x_preferred":[
        "\u10db\u10dd\u10dc\u10e2\u10d8\u10e9\u10d4\u10da\u10dd"
    ],
    "name:kor_x_preferred":[
        "\ubaac\ud2f0\uc140\ub85c"
    ],
    "name:lav_x_preferred":[
        "Monti\u010delo"
    ],
    "name:lfn_x_preferred":[
        "Monticello"
    ],
    "name:mal_x_preferred":[
        "\u0d2e\u0d4b\u0d23\u0d4d\u0d1f\u0d3f\u0d38\u0d46\u0d32\u0d4d\u0d32\u0d4a"
    ],
    "name:nld_x_preferred":[
        "Monticello"
    ],
    "name:nno_x_preferred":[
        "Monticello"
    ],
    "name:nor_x_preferred":[
        "Monticello"
    ],
    "name:pnb_x_preferred":[
        "\u0645\u0648\u0646\u0679\u06cc\u0633\u0644\u0648"
    ],
    "name:pol_x_preferred":[
        "Monticello"
    ],
    "name:por_x_preferred":[
        "Monticello"
    ],
    "name:rus_x_preferred":[
        "\u041c\u043e\u043d\u0442\u0438\u0447\u0435\u043b\u043b\u043e"
    ],
    "name:spa_x_preferred":[
        "Monticello"
    ],
    "name:swe_x_preferred":[
        "Monticello"
    ],
    "name:tur_x_preferred":[
        "Monticello"
    ],
    "name:ukr_x_preferred":[
        "\u041c\u043e\u043d\u0442\u0456\u0447\u0435\u043b\u043b\u043e"
    ],
    "name:vie_x_preferred":[
        "Monticello"
    ],
    "name:zho_x_preferred":[
        "\u8499\u8482\u585e\u6d1b"
    ],
    "wof:name":"Monticello",
    "wof:placetype":"locality",
    "wof:population":33
},
  "geometry": {"coordinates":[11.41814,45.38383],"type":"Point"}
}