{
  "type": "Feature",
  "properties": {
    "gn:admin1_code":"9.0",
    "gn:admin2_code":"CR",
    "gn:admin3_code":"19092.0",
    "gn:asciiname":"Scandolara Ravara",
    "gn:country_code":"IT",
    "gn:dem":31,
    "gn:elevation":"30.0",
    "gn:feature_class":"P",
    "gn:feature_code":"PPLA3",
    "gn:name":"Scandolara Ravara",
    "gn:population":1088,
    "gn:timezone":"Europe/Rome",
    "iso:country":"IT",
    "name:eng_x_preferred":[
        "Scandolara Ravara"
    ],
    "name:epo_x_preferred":[
        "Scandolara Ravara"
    ],
    "name:fra_x_preferred":[
        "Scandolara Ravara"
    ],
    "name:ita_x_preferred":[
        "Scandolara Ravara"
    ],
    "name:nap_x_preferred":[
        "Scandolara Ravara"
    ],
    "name:nld_x_preferred":[
        "Scandolara Ravara"
    ],
    "name:pol_x_preferred":[
        "Scandolara Ravara"
    ],
    "name:por_x_preferred":[
        "Scandolara Ravara"
    ],
    "wof:name":"Scandolara Ravara",
    "wof:placetype":"locality",
    "wof:population":1088
},
  "geometry": {"coordinates":[10.30215,45.05309000000001],"type":"Point"}
}