{
  "type": "Feature",
  "properties": {
    "gn:admin1_code":"9.0",
    "gn:admin2_code":"CR",
    "gn:admin3_code":"19092.0",
    "gn:asciiname":"Scandolara Ravara",
    "gn:country_code":"IT",
    "gn:dem":31,
    "gn:elevation":"30.0",
    "gn:feature_class":"P",
    "gn:feature_code":"PPLA3",
    "gn:name":"Scandolara Ravara",
    "gn:population":1088,
    "gn:timezone":"Europe/Rome",
    "iso:country":"IT",
    "name:bul_x_preferred":[
        "\u0421\u043a\u0430\u043d\u0434\u043e\u043b\u0430\u0440\u0430 \u0420\u0430\u0432\u0430\u0440\u0430"
    ],
    "name:ceb_x_preferred":[
        "Scandolara Ravara"
    ],
    "name:deu_x_preferred":[
        "Scandolara Ravara"
    ],
    "name:eng_x_preferred":[
        "Scandolara Ravara"
    ],
    "name:epo_x_preferred":[
        "Scandolara Ravara"
    ],
    "name:eus_x_preferred":[
        "Scandolara Ravara"
    ],
    "name:fra_x_preferred":[
        "Scandolara Ravara"
    ],
    "name:hun_x_preferred":[
        "Scandolara Ravara"
    ],
    "name:hye_x_preferred":[
        "\u054d\u056f\u0561\u0576\u0564\u0578\u056c\u0561\u0580\u0561 \u054c\u0561\u057e\u0561\u0580\u0561"
    ],
    "name:ita_x_preferred":[
        "Scandolara Ravara"
    ],
    "name:jpn_x_preferred":[
        "\u30b9\u30ab\u30f3\u30c9\u30e9\u30fc\u30e9\u30fb\u30e9\u30f4\u30a1\u30fc\u30e9"
    ],
    "name:kaz_x_preferred":[
        "\u0421\u043a\u0430\u043d\u0434\u043e\u043b\u0430\u0440\u0430-\u0420\u0430\u0432\u0430\u0440\u0430"
    ],
    "name:lmo_x_preferred":[
        "Scandul\u00e8ra"
    ],
    "name:msa_x_preferred":[
        "Scandolara Ravara"
    ],
    "name:nap_x_preferred":[
        "Scandolara Ravara"
    ],
    "name:nld_x_preferred":[
        "Scandolara Ravara"
    ],
    "name:pms_x_preferred":[
        "Scandolara Ravara"
    ],
    "name:pol_x_preferred":[
        "Scandolara Ravara"
    ],
    "name:por_x_preferred":[
        "Scandolara Ravara"
    ],
    "name:ron_x_preferred":[
        "Scandolara Ravara"
    ],
    "name:rus_x_preferred":[
        "\u0421\u043a\u0430\u043d\u0434\u043e\u043b\u0430\u0440\u0430-\u0420\u0430\u0432\u0430\u0440\u0430"
    ],
    "name:scn_x_preferred":[
        "Scandolara Ravara"
    ],
    "name:spa_x_preferred":[
        "Scandolara Ravara"
    ],
    "name:srp_x_preferred":[
        "\u0421\u043a\u0430\u043d\u0434\u043e\u043b\u0430\u0440\u0430 \u0420\u0430\u0432\u0430\u0440\u0430"
    ],
    "name:ukr_x_preferred":[
        "\u0421\u043a\u0430\u043d\u0434\u043e\u043b\u0430\u0440\u0430-\u0420\u0430\u0432\u0430\u0440\u0430"
    ],
    "name:uzb_x_preferred":[
        "Scandolara Ravara"
    ],
    "name:vie_x_preferred":[
        "Scandolara Ravara"
    ],
    "name:vol_x_preferred":[
        "Scandolara Ravara"
    ],
    "name:war_x_preferred":[
        "Scandolara Ravara"
    ],
    "name:zho_x_preferred":[
        "\u65af\u574e\u591a\u62c9\u62c9\u62c9\u74e6\u62c9"
    ],
    "wof:name":"Scandolara Ravara",
    "wof:placetype":"locality",
    "wof:population":1088
},
  "geometry": {"coordinates":[10.30215,45.05309000000001],"type":"Point"}
}