{
  "type": "Feature",
  "properties": {
    "gn:admin1_code":"12.0",
    "gn:admin2_code":"TO",
    "gn:admin3_code":"1190.0",
    "gn:asciiname":"Giborgo",
    "gn:country_code":"IT",
    "gn:dem":900,
    "gn:feature_class":"P",
    "gn:feature_code":"PPLL",
    "gn:name":"Giborgo",
    "gn:population":1,
    "gn:timezone":"Europe/Rome",
    "iso:country":"IT",
    "wof:name":"Giborgo",
    "wof:placetype":"locality",
    "wof:population":1
},
  "geometry": {"coordinates":[7.25361,44.94661],"type":"Point"}
}