{
  "type": "Feature",
  "properties": {
    "gn:admin1_code":"4",
    "gn:admin2_code":"BN",
    "gn:admin3_code":"62076.0",
    "gn:asciiname":"Fontanavecchia",
    "gn:country_code":"IT",
    "gn:dem":227,
    "gn:feature_class":"P",
    "gn:feature_code":"PPL",
    "gn:name":"Fontanavecchia",
    "gn:population":29,
    "gn:timezone":"Europe/Rome",
    "iso:country":"IT",
    "wof:name":"Fontanavecchia",
    "wof:placetype":"locality",
    "wof:population":29
},
  "geometry": {"coordinates":[14.70701,41.18793],"type":"Point"}
}