{
  "type": "Feature",
  "properties": {
    "gn:admin1_code":"20.0",
    "gn:admin2_code":"BL",
    "gn:admin3_code":"25021.0",
    "gn:asciiname":"Zona Industriale Villa Paiera",
    "gn:country_code":"IT",
    "gn:dem":240,
    "gn:feature_class":"P",
    "gn:feature_code":"PPLL",
    "gn:name":"Zona Industriale Villa Paiera",
    "gn:population":3,
    "gn:timezone":"Europe/Rome",
    "iso:country":"IT",
    "wof:name":"Zona Industriale Villa Paiera",
    "wof:placetype":"locality",
    "wof:population":3
},
  "geometry": {"coordinates":[11.96779,46.02054],"type":"Point"}
}