{
  "type": "Feature",
  "properties": {
    "gn:admin1_code":"1.0",
    "gn:admin2_code":"AQ",
    "gn:admin3_code":"66021.0",
    "gn:asciiname":"Sivignano",
    "gn:country_code":"IT",
    "gn:dem":917,
    "gn:elevation":"908.0",
    "gn:feature_class":"P",
    "gn:feature_code":"PPL",
    "gn:name":"Sivignano",
    "gn:population":89,
    "gn:timezone":"Europe/Rome",
    "iso:country":"IT",
    "wof:name":"Sivignano",
    "wof:placetype":"locality",
    "wof:population":89
},
  "geometry": {"coordinates":[13.2902,42.53297],"type":"Point"}
}