{
  "type": "Feature",
  "properties": {
    "gn:admin1_code":"15",
    "gn:admin2_code":"PA",
    "gn:admin3_code":"82044.0",
    "gn:asciiname":"Piane Vecchie",
    "gn:country_code":"IT",
    "gn:dem":9,
    "gn:feature_class":"P",
    "gn:feature_code":"PPL",
    "gn:name":"Piane Vecchie",
    "gn:population":339,
    "gn:timezone":"Europe/Rome",
    "iso:country":"IT",
    "wof:name":"Piane Vecchie",
    "wof:placetype":"locality",
    "wof:population":339
},
  "geometry": {"coordinates":[13.92945,38.01529],"type":"Point"}
}