{
  "type": "Feature",
  "properties": {
    "gn:admin1_code":"5.0",
    "gn:admin2_code":"BO",
    "gn:admin3_code":"37037.0",
    "gn:asciiname":"Fossatone",
    "gn:country_code":"IT",
    "gn:dem":24,
    "gn:feature_class":"P",
    "gn:feature_code":"PPL",
    "gn:name":"Fossatone",
    "gn:population":307,
    "gn:timezone":"Europe/Rome",
    "iso:country":"IT",
    "wof:name":"Fossatone",
    "wof:placetype":"locality",
    "wof:population":307
},
  "geometry": {"coordinates":[11.57015,44.49605],"type":"Point"}
}