{
  "type": "Feature",
  "properties": {
    "gn:admin1_code":"5",
    "gn:admin2_code":"MO",
    "gn:admin3_code":"36005.0",
    "gn:asciiname":"Case Nuove",
    "gn:country_code":"IT",
    "gn:dem":20,
    "gn:feature_class":"P",
    "gn:feature_code":"PPL",
    "gn:name":"Case Nuove",
    "gn:population":70,
    "gn:timezone":"Europe/Rome",
    "iso:country":"IT",
    "wof:name":"Case Nuove",
    "wof:placetype":"locality",
    "wof:population":70
},
  "geometry": {"coordinates":[10.91668,44.79054],"type":"Point"}
}