{
  "type": "Feature",
  "properties": {
    "gn:admin1_code":"20",
    "gn:admin2_code":"VI",
    "gn:admin3_code":"24093.0",
    "gn:asciiname":"San Marino",
    "gn:country_code":"IT",
    "gn:dem":187,
    "gn:feature_class":"P",
    "gn:feature_code":"PPL",
    "gn:name":"San Marino",
    "gn:population":156,
    "gn:timezone":"Europe/Rome",
    "iso:country":"IT",
    "wof:name":"San Marino",
    "wof:placetype":"locality",
    "wof:population":156
},
  "geometry": {"coordinates":[11.69232,45.89728],"type":"Point"}
}