{
  "type": "Feature",
  "properties": {
    "iso:country":"IT",
    "name:eng_x_preferred":[
        "San Sisto"
    ],
    "name:ita_x_preferred":[
        "San Sisto"
    ],
    "wof:name":"San Sisto",
    "wof:placetype":"neighbourhood"
},
  "geometry": {"coordinates":[11.40069791074247,44.51925808399006],"type":"Point"}
}