{
  "type": "Feature",
  "properties": {
    "gn:admin1_code":"9",
    "gn:admin2_code":"LO",
    "gn:admin3_code":"98054.0",
    "gn:asciiname":"Coste Fagioli",
    "gn:country_code":"IT",
    "gn:dem":63,
    "gn:feature_class":"P",
    "gn:feature_code":"PPL",
    "gn:name":"Coste Fagioli",
    "gn:population":33,
    "gn:timezone":"Europe/Rome",
    "iso:country":"IT",
    "wof:name":"Coste Fagioli",
    "wof:placetype":"locality",
    "wof:population":33
},
  "geometry": {"coordinates":[9.62611,45.17318],"type":"Point"}
}