{
  "type": "Feature",
  "properties": {
    "gn:admin1_code":"18",
    "gn:admin2_code":"PG",
    "gn:admin3_code":"54013.0",
    "gn:asciiname":"San Pietro a Monte",
    "gn:country_code":"IT",
    "gn:dem":290,
    "gn:feature_class":"P",
    "gn:feature_code":"PPL",
    "gn:name":"San Pietro a Monte",
    "gn:population":49,
    "gn:timezone":"Europe/Rome",
    "iso:country":"IT",
    "wof:name":"San Pietro a Monte",
    "wof:placetype":"locality",
    "wof:population":49
},
  "geometry": {"coordinates":[12.17811,43.33034],"type":"Point"}
}