{
  "type": "Feature",
  "properties": {
    "iso:country":"IT",
    "qs:a0":"Italia",
    "qs:a1":"*Salerno",
    "qs:a1r":"0Campania",
    "qs:adm0":"Italia",
    "qs:la_lc":"*",
    "qs:level":"locality",
    "qs:loc":"Pugliano",
    "qs:loc_alt":"Pugliano",
    "qs:pop":0,
    "qs:type":"buffered point",
    "wof:name":"Pugliano",
    "wof:placetype":"locality"
},
  "geometry": {"coordinates":[14.945561,40.68],"type":"Point"}
}