{
  "type": "Feature",
  "properties": {
    "gn:admin1_code":"10.0",
    "gn:admin2_code":"MC",
    "gn:admin3_code":"43056.0",
    "gn:asciiname":"Calcara",
    "gn:country_code":"IT",
    "gn:dem":808,
    "gn:elevation":"830.0",
    "gn:feature_class":"P",
    "gn:feature_code":"PPL",
    "gn:name":"Calcara",
    "gn:population":35,
    "gn:timezone":"Europe/Rome",
    "iso:country":"IT",
    "wof:name":"Calcara",
    "wof:placetype":"locality",
    "wof:population":35
},
  "geometry": {"coordinates":[13.1541,42.93561],"type":"Point"}
}