{
  "type": "Feature",
  "properties": {
    "gn:admin1_code":"12",
    "gn:admin2_code":"NO",
    "gn:admin3_code":"3143.0",
    "gn:asciiname":"Imperio",
    "gn:country_code":"IT",
    "gn:dem":252,
    "gn:feature_class":"P",
    "gn:feature_code":"PPL",
    "gn:name":"Imperio",
    "gn:population":19,
    "gn:timezone":"Europe/Rome",
    "iso:country":"IT",
    "wof:name":"Imperio",
    "wof:placetype":"locality",
    "wof:population":19
},
  "geometry": {"coordinates":[8.55721,45.62527],"type":"Point"}
}