{
  "type": "Feature",
  "properties": {
    "gn:admin1_code":"9.0",
    "gn:admin2_code":"BG",
    "gn:admin3_code":"16044.0",
    "gn:asciiname":"Cascina Motella",
    "gn:country_code":"IT",
    "gn:dem":126,
    "gn:feature_class":"P",
    "gn:feature_code":"PPL",
    "gn:name":"Cascina Motella",
    "gn:population":11,
    "gn:timezone":"Europe/Rome",
    "iso:country":"IT",
    "wof:name":"Cascina Motella",
    "wof:placetype":"locality",
    "wof:population":11
},
  "geometry": {"coordinates":[9.8454,45.52618],"type":"Point"}
}