{
  "type": "Feature",
  "properties": {
    "gn:admin1_code":"17",
    "gn:admin2_code":"TN",
    "gn:admin3_code":"22006.0",
    "gn:asciiname":"Localita Produttiva I",
    "gn:country_code":"IT",
    "gn:dem":84,
    "gn:feature_class":"P",
    "gn:feature_code":"PPL",
    "gn:name":"Localit\u00e0 Produttiva I",
    "gn:population":59,
    "gn:timezone":"Europe/Rome",
    "iso:country":"IT",
    "name:und_x_variant":[
        "Localit\u00e0 Produttiva I"
    ],
    "wof:name":"Localita Produttiva I",
    "wof:placetype":"locality",
    "wof:population":59
},
  "geometry": {"coordinates":[10.87771,45.90259],"type":"Point"}
}