{
  "type": "Feature",
  "properties": {
    "gn:admin1_code":"10.0",
    "gn:admin2_code":"PU",
    "gn:admin3_code":"41061.0",
    "gn:asciiname":"Coldorso",
    "gn:country_code":"IT",
    "gn:dem":449,
    "gn:feature_class":"P",
    "gn:feature_code":"PPL",
    "gn:name":"Coldorso",
    "gn:population":16,
    "gn:timezone":"Europe/Rome",
    "iso:country":"IT",
    "wof:name":"Coldorso",
    "wof:placetype":"locality",
    "wof:population":16
},
  "geometry": {"coordinates":[12.79865,43.50375],"type":"Point"}
}