{
  "type": "Feature",
  "properties": {
    "gn:admin1_code":"15.0",
    "gn:admin2_code":"CT",
    "gn:admin3_code":"87015.0",
    "gn:admin4_code":"870156.0",
    "gn:asciiname":"Primosole Est",
    "gn:country_code":"IT",
    "gn:dem":5,
    "gn:feature_class":"P",
    "gn:feature_code":"PPL",
    "gn:name":"Primosole Est",
    "gn:population":9,
    "gn:timezone":"Europe/Rome",
    "iso:country":"IT",
    "wof:name":"Primosole Est",
    "wof:placetype":"locality",
    "wof:population":9
},
  "geometry": {"coordinates":[15.08769,37.38925],"type":"Point"}
}