{
  "type": "Feature",
  "properties": {
    "gn:admin1_code":"7",
    "gn:admin2_code":"RI",
    "gn:admin3_code":"57024.0",
    "gn:asciiname":"Collemacina-Coscarone-Madonna di Loreto",
    "gn:country_code":"IT",
    "gn:dem":374,
    "gn:feature_class":"P",
    "gn:feature_code":"PPL",
    "gn:name":"Collemacina-Coscarone-Madonna di Loreto",
    "gn:population":75,
    "gn:timezone":"Europe/Rome",
    "iso:country":"IT",
    "wof:name":"Collemacina-Coscarone-Madonna di Loreto",
    "wof:placetype":"locality",
    "wof:population":75
},
  "geometry": {"coordinates":[12.62853,42.45728],"type":"Point"}
}