{
  "type": "Feature",
  "properties": {
    "gn:admin1_code":"12",
    "gn:admin2_code":"CN",
    "gn:admin3_code":"4212.0",
    "gn:asciiname":"Valentino",
    "gn:country_code":"IT",
    "gn:dem":271,
    "gn:feature_class":"P",
    "gn:feature_code":"PPL",
    "gn:name":"Valentino",
    "gn:population":26,
    "gn:timezone":"Europe/Rome",
    "iso:country":"IT",
    "wof:name":"Valentino",
    "wof:placetype":"locality",
    "wof:population":26
},
  "geometry": {"coordinates":[7.90462,44.70305],"type":"Point"}
}