{
  "type": "Feature",
  "properties": {
    "gn:admin1_code":"12",
    "gn:admin2_code":"CN",
    "gn:admin3_code":"4212.0",
    "gn:asciiname":"Valentino",
    "gn:country_code":"IT",
    "gn:dem":271,
    "gn:feature_class":"P",
    "gn:feature_code":"PPL",
    "gn:name":"Valentino",
    "gn:population":26,
    "gn:timezone":"Europe/Rome",
    "iso:country":"IT",
    "name:arz_x_preferred":[
        "\u0641\u0627\u0644\u0646\u062a\u064a\u0646\u0648"
    ],
    "name:ces_x_preferred":[
        "Valentino"
    ],
    "name:deu_x_preferred":[
        "Valentino"
    ],
    "name:eus_x_preferred":[
        "Valentino"
    ],
    "name:fas_x_preferred":[
        "\u0648\u0627\u0644\u0646\u062a\u06cc\u0646\u0648"
    ],
    "name:fin_x_preferred":[
        "Valentino"
    ],
    "name:fra_x_preferred":[
        "Valentino"
    ],
    "name:heb_x_preferred":[
        "\u05d5\u05dc\u05e0\u05d8\u05d9\u05e0\u05d5"
    ],
    "name:hrv_x_preferred":[
        "Valentino"
    ],
    "name:ita_x_preferred":[
        "Valentino"
    ],
    "name:jpn_x_preferred":[
        "\u30f4\u30a1\u30ec\u30f3\u30c6\u30a3\u30fc\u30ce"
    ],
    "name:kor_x_preferred":[
        "\ubc1c\ub80c\ud2f0\ub178"
    ],
    "name:nld_x_preferred":[
        "Valentino"
    ],
    "name:pol_x_preferred":[
        "Valentino"
    ],
    "name:por_x_preferred":[
        "Valentino"
    ],
    "name:ron_x_preferred":[
        "Valentino"
    ],
    "name:rus_x_preferred":[
        "\u0412\u0430\u043b\u0435\u043d\u0442\u0438\u043d\u043e"
    ],
    "name:spa_x_preferred":[
        "Valentino"
    ],
    "name:srp_x_preferred":[
        "\u0412\u0430\u043b\u0435\u043d\u0442\u0438\u043d\u043e"
    ],
    "wof:name":"Valentino",
    "wof:placetype":"locality",
    "wof:population":26
},
  "geometry": {"coordinates":[7.90462,44.70305],"type":"Point"}
}