{
  "type": "Feature",
  "properties": {
    "gn:admin1_code":"4",
    "gn:admin2_code":"BN",
    "gn:admin3_code":"62059.0",
    "gn:asciiname":"Calise",
    "gn:country_code":"IT",
    "gn:dem":327,
    "gn:feature_class":"P",
    "gn:feature_code":"PPL",
    "gn:name":"Calise",
    "gn:population":66,
    "gn:timezone":"Europe/Rome",
    "iso:country":"IT",
    "wof:name":"Calise",
    "wof:placetype":"locality",
    "wof:population":66
},
  "geometry": {"coordinates":[14.90029,41.26531],"type":"Point"}
}