{
  "type": "Feature",
  "properties": {
    "gn:admin1_code":"12",
    "gn:admin2_code":"AL",
    "gn:admin3_code":"6154.0",
    "gn:asciiname":"Piazzolo",
    "gn:country_code":"IT",
    "gn:dem":131,
    "gn:feature_class":"P",
    "gn:feature_code":"PPL",
    "gn:name":"Piazzolo",
    "gn:population":73,
    "gn:timezone":"Europe/Rome",
    "iso:country":"IT",
    "wof:name":"Piazzolo",
    "wof:placetype":"locality",
    "wof:population":73
},
  "geometry": {"coordinates":[8.56718,45.01274],"type":"Point"}
}