{
  "type": "Feature",
  "properties": {
    "gn:admin1_code":"12",
    "gn:admin2_code":"AL",
    "gn:admin3_code":"6154.0",
    "gn:asciiname":"Piazzolo",
    "gn:country_code":"IT",
    "gn:dem":131,
    "gn:feature_class":"P",
    "gn:feature_code":"PPL",
    "gn:name":"Piazzolo",
    "gn:population":73,
    "gn:timezone":"Europe/Rome",
    "iso:country":"IT",
    "name:azb_x_preferred":[
        "\u067e\u06cc\u0627\u062a\u0633\u0648\u0644\u0648"
    ],
    "name:bel_x_preferred":[
        "\u041f\u2019\u044f\u0446\u0446\u043e\u043b\u0430"
    ],
    "name:ceb_x_preferred":[
        "Piazzolo"
    ],
    "name:deu_x_preferred":[
        "Piazzolo"
    ],
    "name:epo_x_preferred":[
        "Piazzolo"
    ],
    "name:eus_x_preferred":[
        "Piazzolo"
    ],
    "name:fas_x_preferred":[
        "\u067e\u06cc\u0627\u062a\u0633\u0648\u0644\u0648"
    ],
    "name:fra_x_preferred":[
        "Piazzolo"
    ],
    "name:hun_x_preferred":[
        "Piazzolo"
    ],
    "name:hye_x_preferred":[
        "\u054a\u056b\u0561\u0581\u0578\u056c\u0578"
    ],
    "name:ina_x_preferred":[
        "Piazzolo"
    ],
    "name:ita_x_preferred":[
        "Piazzolo"
    ],
    "name:jpn_x_preferred":[
        "\u30d4\u30a2\u30c3\u30c4\u30a9\u30fc\u30ed"
    ],
    "name:kaz_x_preferred":[
        "\u041f\u044c\u044f\u0446\u0446\u043e\u043b\u043e"
    ],
    "name:lat_x_preferred":[
        "Plazolum"
    ],
    "name:lmo_x_preferred":[
        "Piass\u00f6l"
    ],
    "name:msa_x_preferred":[
        "Piazzolo"
    ],
    "name:nap_x_preferred":[
        "Piazzolo"
    ],
    "name:nld_x_preferred":[
        "Piazzolo"
    ],
    "name:pms_x_preferred":[
        "Piazzolo"
    ],
    "name:pol_x_preferred":[
        "Piazzolo"
    ],
    "name:por_x_preferred":[
        "Piazzolo"
    ],
    "name:ron_x_preferred":[
        "Piazzolo"
    ],
    "name:rus_x_preferred":[
        "\u041f\u044c\u044f\u0446\u0446\u043e\u043b\u043e"
    ],
    "name:scn_x_preferred":[
        "Piazzolo"
    ],
    "name:spa_x_preferred":[
        "Piazzolo"
    ],
    "name:srp_x_preferred":[
        "\u041f\u0458\u0430\u0446\u043e\u043b\u043e"
    ],
    "name:tgl_x_preferred":[
        "Piazzolo"
    ],
    "name:ukr_x_preferred":[
        "\u041f'\u044f\u0446\u0446\u043e\u043b\u043e"
    ],
    "name:uzb_x_preferred":[
        "Piazzolo"
    ],
    "name:vie_x_preferred":[
        "Piazzolo"
    ],
    "name:vol_x_preferred":[
        "Piazzolo"
    ],
    "name:war_x_preferred":[
        "Piazzolo"
    ],
    "name:zho_x_preferred":[
        "\u76ae\u4e9a\u4f50\u6d1b"
    ],
    "wof:name":"Piazzolo",
    "wof:placetype":"locality",
    "wof:population":73
},
  "geometry": {"coordinates":[8.56718,45.01274],"type":"Point"}
}