{
  "type": "Feature",
  "properties": {
    "gn:admin1_code":"17.0",
    "gn:admin2_code":"TN",
    "gn:admin3_code":"22051.0",
    "gn:asciiname":"Campi Golf",
    "gn:country_code":"IT",
    "gn:dem":1431,
    "gn:feature_class":"P",
    "gn:feature_code":"PPLL",
    "gn:name":"Campi Golf",
    "gn:population":1,
    "gn:timezone":"Europe/Rome",
    "iso:country":"IT",
    "wof:name":"Campi Golf",
    "wof:placetype":"locality",
    "wof:population":1
},
  "geometry": {"coordinates":[11.21083,46.40115],"type":"Point"}
}