{
  "type": "Feature",
  "properties": {
    "gn:admin1_code":"12",
    "gn:admin2_code":"AL",
    "gn:admin3_code":"6148.0",
    "gn:asciiname":"Sisola",
    "gn:country_code":"IT",
    "gn:dem":465,
    "gn:feature_class":"P",
    "gn:feature_code":"PPL",
    "gn:name":"Sisola",
    "gn:population":29,
    "gn:timezone":"Europe/Rome",
    "iso:country":"IT",
    "wof:name":"Sisola",
    "wof:placetype":"locality",
    "wof:population":29
},
  "geometry": {"coordinates":[9.05052,44.67478],"type":"Point"}
}