{
  "type": "Feature",
  "properties": {
    "gn:admin1_code":"4",
    "gn:admin2_code":"AV",
    "gn:admin3_code":"64005.0",
    "gn:asciiname":"Trimonti",
    "gn:country_code":"IT",
    "gn:dem":623,
    "gn:feature_class":"P",
    "gn:feature_code":"PPL",
    "gn:name":"Trimonti",
    "gn:population":14,
    "gn:timezone":"Europe/Rome",
    "iso:country":"IT",
    "wof:name":"Trimonti",
    "wof:placetype":"locality",
    "wof:population":14
},
  "geometry": {"coordinates":[15.07594,41.18673],"type":"Point"}
}