{
  "type": "Feature",
  "properties": {
    "gn:admin1_code":"20",
    "gn:admin2_code":"BL",
    "gn:admin3_code":"25073.0",
    "gn:asciiname":"Sottolerive",
    "gn:country_code":"IT",
    "gn:dem":879,
    "gn:feature_class":"P",
    "gn:feature_code":"PPL",
    "gn:name":"Sottolerive",
    "gn:population":27,
    "gn:timezone":"Europe/Rome",
    "iso:country":"IT",
    "wof:name":"Sottolerive",
    "wof:placetype":"locality",
    "wof:population":27
},
  "geometry": {"coordinates":[12.16677,46.34867],"type":"Point"}
}