{
  "type": "Feature",
  "properties": {
    "gn:admin1_code":"17",
    "gn:admin2_code":"BZ",
    "gn:admin3_code":"21114.0",
    "gn:asciiname":"Gravetsch",
    "gn:country_code":"IT",
    "gn:dem":996,
    "gn:feature_class":"P",
    "gn:feature_code":"PPL",
    "gn:name":"Gravetsch",
    "gn:population":81,
    "gn:timezone":"Europe/Rome",
    "iso:country":"IT",
    "wof:name":"Gravetsch",
    "wof:placetype":"locality",
    "wof:population":81
},
  "geometry": {"coordinates":[11.54579,46.64168],"type":"Point"}
}