{
  "type": "Feature",
  "properties": {
    "gn:admin1_code":"20",
    "gn:admin2_code":"VR",
    "gn:admin3_code":"23070.0",
    "gn:asciiname":"Luvi",
    "gn:country_code":"IT",
    "gn:dem":517,
    "gn:feature_class":"P",
    "gn:feature_code":"PPL",
    "gn:name":"Luvi",
    "gn:population":30,
    "gn:timezone":"Europe/Rome",
    "iso:country":"IT",
    "wof:name":"Luvi",
    "wof:placetype":"locality",
    "wof:population":30
},
  "geometry": {"coordinates":[11.2411,45.54802],"type":"Point"}
}