{
  "type": "Feature",
  "properties": {
    "gn:admin1_code":"4",
    "gn:admin2_code":"CE",
    "gn:admin3_code":"61030.0",
    "gn:asciiname":"Case Nuove-Quattro Stradoni",
    "gn:country_code":"IT",
    "gn:dem":162,
    "gn:feature_class":"P",
    "gn:feature_code":"PPL",
    "gn:name":"Case Nuove-Quattro Stradoni",
    "gn:population":80,
    "gn:timezone":"Europe/Rome",
    "iso:country":"IT",
    "wof:name":"Case Nuove-Quattro Stradoni",
    "wof:placetype":"locality",
    "wof:population":80
},
  "geometry": {"coordinates":[14.095,41.44554],"type":"Point"}
}