{
  "type": "Feature",
  "properties": {
    "gn:admin1_code":"17.0",
    "gn:admin2_code":"TN",
    "gn:admin3_code":"22131.0",
    "gn:asciiname":"Cusiano",
    "gn:country_code":"IT",
    "gn:dem":951,
    "gn:feature_class":"P",
    "gn:feature_code":"PPL",
    "gn:name":"Cusiano",
    "gn:population":393,
    "gn:timezone":"Europe/Rome",
    "iso:country":"IT",
    "wof:name":"Cusiano",
    "wof:placetype":"locality",
    "wof:population":393
},
  "geometry": {"coordinates":[10.74559,46.31098],"type":"Point"}
}