{
  "type": "Feature",
  "properties": {
    "gn:admin1_code":"15.0",
    "gn:admin2_code":"PA",
    "gn:admin3_code":"82049.0",
    "gn:asciiname":"Sirignano",
    "gn:country_code":"IT",
    "gn:dem":142,
    "gn:feature_class":"P",
    "gn:feature_code":"PPL",
    "gn:name":"Sirignano",
    "gn:population":0,
    "gn:timezone":"Europe/Rome",
    "iso:country":"IT",
    "name:azb_x_preferred":[
        "\u0633\u06cc\u0631\u06cc\u0646\u06cc\u0627\u0646\u0648"
    ],
    "name:bul_x_preferred":[
        "\u0421\u0438\u0440\u0438\u043d\u044f\u043d\u043e"
    ],
    "name:ceb_x_preferred":[
        "Sirignano"
    ],
    "name:deu_x_preferred":[
        "Sirignano"
    ],
    "name:epo_x_preferred":[
        "Sirignano"
    ],
    "name:est_x_preferred":[
        "Sirignano"
    ],
    "name:eus_x_preferred":[
        "Sirignano"
    ],
    "name:fas_x_preferred":[
        "\u0633\u06cc\u0631\u06cc\u0646\u06cc\u0627\u0646\u0648"
    ],
    "name:fra_x_preferred":[
        "Sirignano"
    ],
    "name:hun_x_preferred":[
        "Sirignano"
    ],
    "name:hye_x_preferred":[
        "\u054d\u056b\u0580\u056b\u0576\u0575\u0561\u0576\u0578"
    ],
    "name:ina_x_preferred":[
        "Sirignano"
    ],
    "name:ita_x_preferred":[
        "Sirignano"
    ],
    "name:jpn_x_preferred":[
        "\u30b7\u30ea\u30cb\u30e3\u30fc\u30ce"
    ],
    "name:kaz_x_preferred":[
        "\u0421\u0438\u0440\u0438\u043d\u044c\u044f\u043d\u043e"
    ],
    "name:kor_x_preferred":[
        "\uc2dc\ub9ac\ub0d0\ub178"
    ],
    "name:lat_x_preferred":[
        "Sirignanum"
    ],
    "name:lmo_x_preferred":[
        "Sirignano"
    ],
    "name:mkd_x_preferred":[
        "\u0421\u0438\u0440\u0438\u045a\u0430\u043d\u043e"
    ],
    "name:msa_x_preferred":[
        "Sirignano"
    ],
    "name:nap_x_preferred":[
        "Sirignano"
    ],
    "name:nld_x_preferred":[
        "Sirignano"
    ],
    "name:pms_x_preferred":[
        "Sirignano"
    ],
    "name:pol_x_preferred":[
        "Sirignano"
    ],
    "name:por_x_preferred":[
        "Sirignano"
    ],
    "name:ron_x_preferred":[
        "Sirignano"
    ],
    "name:rus_x_preferred":[
        "\u0421\u0438\u0440\u0438\u043d\u044c\u044f\u043d\u043e"
    ],
    "name:scn_x_preferred":[
        "Sirignanu"
    ],
    "name:spa_x_preferred":[
        "Sirignano"
    ],
    "name:srp_x_preferred":[
        "\u0421\u0438\u0440\u0438\u045a\u0430\u043d\u043e"
    ],
    "name:tgl_x_preferred":[
        "Sirignano"
    ],
    "name:ukr_x_preferred":[
        "\u0421\u0456\u0440\u0438\u043d\u044c\u044f\u043d\u043e"
    ],
    "name:uzb_x_preferred":[
        "Sirignano"
    ],
    "name:vec_x_preferred":[
        "Sirignano"
    ],
    "name:vie_x_preferred":[
        "Sirignano"
    ],
    "name:vol_x_preferred":[
        "Sirignano"
    ],
    "name:war_x_preferred":[
        "Sirignano"
    ],
    "name:zho_x_preferred":[
        "\u897f\u91cc\u5c3c\u4e9a\u8bfa"
    ],
    "wof:name":"Sirignano",
    "wof:placetype":"locality"
},
  "geometry": {"coordinates":[12.95,37.88333],"type":"Point"}
}