{
  "type": "Feature",
  "properties": {
    "gn:admin1_code":"15.0",
    "gn:admin2_code":"PA",
    "gn:admin3_code":"82049.0",
    "gn:asciiname":"Sirignano",
    "gn:country_code":"IT",
    "gn:dem":142,
    "gn:feature_class":"P",
    "gn:feature_code":"PPL",
    "gn:name":"Sirignano",
    "gn:population":0,
    "gn:timezone":"Europe/Rome",
    "iso:country":"IT",
    "wof:name":"Sirignano",
    "wof:placetype":"locality"
},
  "geometry": {"coordinates":[12.95,37.88333],"type":"Point"}
}