{
  "type": "Feature",
  "properties": {
    "gn:admin1_code":"4.0",
    "gn:admin2_code":"SA",
    "gn:admin3_code":"65029.0",
    "gn:asciiname":"Pellegrini",
    "gn:country_code":"IT",
    "gn:dem":496,
    "gn:feature_class":"P",
    "gn:feature_code":"PPL",
    "gn:name":"Pellegrini",
    "gn:population":0,
    "gn:timezone":"Europe/Rome",
    "iso:country":"IT",
    "wof:name":"Pellegrini",
    "wof:placetype":"locality"
},
  "geometry": {"coordinates":[15.53333,40.18333],"type":"Point"}
}