{
  "type": "Feature",
  "properties": {
    "gn:admin1_code":"4.0",
    "gn:admin2_code":"SA",
    "gn:admin3_code":"65029.0",
    "gn:asciiname":"Pellegrini",
    "gn:country_code":"IT",
    "gn:dem":496,
    "gn:feature_class":"P",
    "gn:feature_code":"PPL",
    "gn:name":"Pellegrini",
    "gn:population":0,
    "gn:timezone":"Europe/Rome",
    "iso:country":"IT",
    "name:ceb_x_preferred":[
        "Pellegrini"
    ],
    "name:ces_x_preferred":[
        "Pellegrini"
    ],
    "name:deu_x_preferred":[
        "Pellegrini"
    ],
    "name:fas_x_preferred":[
        "\u067e\u0644\u06af\u0631\u06cc\u0646\u06cc"
    ],
    "name:fra_x_preferred":[
        "Pellegrini"
    ],
    "name:heb_x_preferred":[
        "\u05e4\u05dc\u05d2\u05e8\u05d9\u05e0\u05d9"
    ],
    "name:ita_x_preferred":[
        "Pellegrini"
    ],
    "name:jpn_x_preferred":[
        "\u30da\u30ec\u30b0\u30ea\u30fc\u30cb"
    ],
    "name:nld_x_preferred":[
        "Pellegrini"
    ],
    "name:pol_x_preferred":[
        "Pellegrini"
    ],
    "name:por_x_preferred":[
        "Pellegrini"
    ],
    "name:rus_x_preferred":[
        "\u041f\u0435\u043b\u043b\u0435\u0433\u0440\u0438\u043d\u0438"
    ],
    "name:slk_x_preferred":[
        "Pellegrini"
    ],
    "name:spa_x_preferred":[
        "Pellegrini"
    ],
    "name:swe_x_preferred":[
        "Pellegrini"
    ],
    "name:ukr_x_preferred":[
        "\u041f\u0435\u043b\u043b\u0435\u0433\u0440\u0456\u043d\u0456"
    ],
    "wof:name":"Pellegrini",
    "wof:placetype":"locality"
},
  "geometry": {"coordinates":[15.53333,40.18333],"type":"Point"}
}