{
  "type": "Feature",
  "properties": {
    "gn:admin1_code":"4.0",
    "gn:admin2_code":"SA",
    "gn:admin3_code":"65119.0",
    "gn:asciiname":"Garigliano",
    "gn:country_code":"IT",
    "gn:dem":159,
    "gn:feature_class":"P",
    "gn:feature_code":"PPL",
    "gn:name":"Garigliano",
    "gn:population":0,
    "gn:timezone":"Europe/Rome",
    "iso:country":"IT",
    "wof:name":"Garigliano",
    "wof:placetype":"locality"
},
  "geometry": {"coordinates":[15.48333,40.05],"type":"Point"}
}