{
  "type": "Feature",
  "properties": {
    "gn:admin1_code":"4.0",
    "gn:admin2_code":"SA",
    "gn:admin3_code":"65119.0",
    "gn:asciiname":"Garigliano",
    "gn:country_code":"IT",
    "gn:dem":159,
    "gn:feature_class":"P",
    "gn:feature_code":"PPL",
    "gn:name":"Garigliano",
    "gn:population":0,
    "gn:timezone":"Europe/Rome",
    "iso:country":"IT",
    "name:ara_x_preferred":[
        "\u0646\u0647\u0631 \u063a\u0627\u0631\u064a\u0644\u064a\u0627\u0646\u0648"
    ],
    "name:bul_x_preferred":[
        "\u0413\u0430\u0440\u0438\u043b\u044f\u043d\u043e"
    ],
    "name:cat_x_preferred":[
        "Garigliano"
    ],
    "name:ceb_x_preferred":[
        "Fiume Garigliano"
    ],
    "name:chv_x_preferred":[
        "\u0413\u0430\u0440\u0438\u043b\u044c\u044f\u043d\u043e"
    ],
    "name:deu_x_preferred":[
        "Garigliano"
    ],
    "name:eus_x_preferred":[
        "Garigliano"
    ],
    "name:fra_x_preferred":[
        "Garigliano"
    ],
    "name:glg_x_preferred":[
        "R\u00edo Garigliano"
    ],
    "name:heb_x_preferred":[
        "\u05d2\u05e8\u05d9\u05dc\u05d9\u05d0\u05e0\u05d5"
    ],
    "name:hun_x_preferred":[
        "Garigliano"
    ],
    "name:ita_x_preferred":[
        "Garigliano"
    ],
    "name:jpn_x_preferred":[
        "\u30ac\u30ea\u30ea\u30e3\u30fc\u30ce\u5ddd"
    ],
    "name:kor_x_preferred":[
        "\uac00\ub9b4\ub9ac\uc544\ub178\uac15"
    ],
    "name:nld_x_preferred":[
        "Garigliano"
    ],
    "name:nno_x_preferred":[
        "Garigliano"
    ],
    "name:nor_x_preferred":[
        "Garigliano"
    ],
    "name:pol_x_preferred":[
        "Garigliano"
    ],
    "name:ron_x_preferred":[
        "Garigliano"
    ],
    "name:rus_x_preferred":[
        "\u0413\u0430\u0440\u0438\u043b\u044c\u044f\u043d\u043e"
    ],
    "name:scn_x_preferred":[
        "Gariglianu"
    ],
    "name:spa_x_preferred":[
        "Liri-Garigliano"
    ],
    "name:ukr_x_preferred":[
        "\u0413\u0430\u0440\u0456\u043b\u044c\u044f\u043d\u043e"
    ],
    "name:zho_x_preferred":[
        "\u52a0\u5229\u683c\u91cc\u963f\u8afe\u6cb3"
    ],
    "wof:name":"Garigliano",
    "wof:placetype":"locality"
},
  "geometry": {"coordinates":[15.48333,40.05],"type":"Point"}
}