{
  "type": "Feature",
  "properties": {
    "gn:admin1_code":"20.0",
    "gn:admin2_code":"RO",
    "gn:admin3_code":"29052.0",
    "gn:asciiname":"Ca' Contarini",
    "gn:country_code":"IT",
    "gn:dem":5,
    "gn:feature_class":"P",
    "gn:feature_code":"PPLL",
    "gn:name":"Ca' Contarini",
    "gn:population":0,
    "gn:timezone":"Europe/Rome",
    "iso:country":"IT",
    "wof:name":"Ca' Contarini",
    "wof:placetype":"locality"
},
  "geometry": {"coordinates":[12.24094,45.01547],"type":"Point"}
}