{
  "type": "Feature",
  "properties": {
    "gn:admin1_code":"5.0",
    "gn:admin2_code":"FC",
    "gn:admin3_code":"40045.0",
    "gn:asciiname":"Fiumicino-San Mauro",
    "gn:country_code":"IT",
    "gn:dem":15,
    "gn:feature_class":"P",
    "gn:feature_code":"PPL",
    "gn:name":"Fiumicino-San Mauro",
    "gn:population":45,
    "gn:timezone":"Europe/Rome",
    "iso:country":"IT",
    "wof:name":"Fiumicino-San Mauro",
    "wof:placetype":"locality",
    "wof:population":45
},
  "geometry": {"coordinates":[12.40058,44.12138],"type":"Point"}
}