{
  "type": "Feature",
  "properties": {
    "gn:admin1_code":"6",
    "gn:admin2_code":"UD",
    "gn:admin3_code":"30121.0",
    "gn:asciiname":"Cadunea",
    "gn:country_code":"IT",
    "gn:dem":392,
    "gn:feature_class":"P",
    "gn:feature_code":"PPL",
    "gn:name":"Cadunea",
    "gn:population":241,
    "gn:timezone":"Europe/Rome",
    "iso:country":"IT",
    "wof:name":"Cadunea",
    "wof:placetype":"locality",
    "wof:population":241
},
  "geometry": {"coordinates":[13.03642,46.45277],"type":"Point"}
}