{
  "type": "Feature",
  "properties": {
    "gn:admin1_code":"20",
    "gn:admin2_code":"VR",
    "gn:admin3_code":"23085.0",
    "gn:asciiname":"Brazzetto",
    "gn:country_code":"IT",
    "gn:dem":9,
    "gn:feature_class":"P",
    "gn:feature_code":"PPL",
    "gn:name":"Brazzetto",
    "gn:population":36,
    "gn:timezone":"Europe/Rome",
    "iso:country":"IT",
    "wof:name":"Brazzetto",
    "wof:placetype":"locality",
    "wof:population":36
},
  "geometry": {"coordinates":[11.39217,45.15775],"type":"Point"}
}