{
  "type": "Feature",
  "properties": {
    "gn:admin1_code":"7",
    "gn:admin2_code":"FR",
    "gn:admin3_code":"60007.0",
    "gn:asciiname":"Torre San Gregorio",
    "gn:country_code":"IT",
    "gn:dem":112,
    "gn:feature_class":"P",
    "gn:feature_code":"PPL",
    "gn:name":"Torre San Gregorio",
    "gn:population":62,
    "gn:timezone":"Europe/Rome",
    "iso:country":"IT",
    "wof:name":"Torre San Gregorio",
    "wof:placetype":"locality",
    "wof:population":62
},
  "geometry": {"coordinates":[13.7107,41.5053],"type":"Point"}
}