{
  "type": "Feature",
  "properties": {
    "gn:admin1_code":"12",
    "gn:admin2_code":"TO",
    "gn:admin3_code":"1029.0",
    "gn:asciiname":"Pianezze",
    "gn:country_code":"IT",
    "gn:dem":453,
    "gn:feature_class":"P",
    "gn:feature_code":"PPL",
    "gn:name":"Pianezze",
    "gn:population":30,
    "gn:timezone":"Europe/Rome",
    "iso:country":"IT",
    "wof:name":"Pianezze",
    "wof:placetype":"locality",
    "wof:population":30
},
  "geometry": {"coordinates":[7.66618,45.40779000000001],"type":"Point"}
}