{
  "type": "Feature",
  "properties": {
    "gn:admin1_code":"12",
    "gn:admin2_code":"TO",
    "gn:admin3_code":"1029.0",
    "gn:asciiname":"Pianezze",
    "gn:country_code":"IT",
    "gn:dem":453,
    "gn:feature_class":"P",
    "gn:feature_code":"PPL",
    "gn:name":"Pianezze",
    "gn:population":30,
    "gn:timezone":"Europe/Rome",
    "iso:country":"IT",
    "name:azb_x_preferred":[
        "\u067e\u06cc\u0627\u0646\u062a\u0632\u0647"
    ],
    "name:bul_x_preferred":[
        "\u041f\u0438\u0430\u043d\u0435\u0446\u0435"
    ],
    "name:ceb_x_preferred":[
        "Pianezze"
    ],
    "name:deu_x_preferred":[
        "Pianezze"
    ],
    "name:epo_x_preferred":[
        "Pianezze"
    ],
    "name:eus_x_preferred":[
        "Pianezze"
    ],
    "name:fas_x_preferred":[
        "\u067e\u06cc\u0627\u0646\u062a\u0632\u0647"
    ],
    "name:fra_x_preferred":[
        "Pianezze"
    ],
    "name:hun_x_preferred":[
        "Pianezze"
    ],
    "name:hye_x_preferred":[
        "\u054a\u056b\u0561\u0576\u0565\u0581\u0565"
    ],
    "name:ita_x_preferred":[
        "Pianezze"
    ],
    "name:jpn_x_preferred":[
        "\u30d4\u30a2\u30cd\u30c3\u30c4\u30a7"
    ],
    "name:kaz_x_preferred":[
        "\u041f\u044c\u044f\u043d\u0435\u0446\u0446\u0435"
    ],
    "name:lat_x_preferred":[
        "Planicies"
    ],
    "name:lmo_x_preferred":[
        "Pianezze"
    ],
    "name:msa_x_preferred":[
        "Pianezze"
    ],
    "name:nap_x_preferred":[
        "Pianezze"
    ],
    "name:nld_x_preferred":[
        "Pianezze"
    ],
    "name:nor_x_preferred":[
        "Pianezze"
    ],
    "name:pms_x_preferred":[
        "Pianezze"
    ],
    "name:pol_x_preferred":[
        "Pianezze"
    ],
    "name:por_x_preferred":[
        "Pianezze"
    ],
    "name:ron_x_preferred":[
        "Pianezze"
    ],
    "name:rus_x_preferred":[
        "\u041f\u044c\u044f\u043d\u0435\u0446\u0446\u0435"
    ],
    "name:scn_x_preferred":[
        "Pianezze"
    ],
    "name:spa_x_preferred":[
        "Pianezze"
    ],
    "name:srp_x_preferred":[
        "\u041f\u0458\u0430\u043d\u0435\u0446\u0435"
    ],
    "name:tgl_x_preferred":[
        "Pianezze"
    ],
    "name:ukr_x_preferred":[
        "\u041f'\u044f\u043d\u0435\u0446\u0446\u0435"
    ],
    "name:uzb_x_preferred":[
        "Pianezze"
    ],
    "name:vec_x_preferred":[
        "Pianeze"
    ],
    "name:vol_x_preferred":[
        "Pianezze"
    ],
    "name:war_x_preferred":[
        "Pianezze"
    ],
    "name:zho_x_preferred":[
        "\u76ae\u4e9a\u5185\u6cfd"
    ],
    "wof:name":"Pianezze",
    "wof:placetype":"locality",
    "wof:population":30
},
  "geometry": {"coordinates":[7.66618,45.40779000000001],"type":"Point"}
}