{
  "type": "Feature",
  "properties": {
    "gn:gn_country":"IT",
    "gn:gn_fcode":"PPL",
    "gn:gn_pop":0,
    "gn:population":44,
    "iso:country":"IT",
    "name:unk_x_variant":[
        "Quadro"
    ],
    "qs_pg:aaroncc":"IT",
    "qs_pg:gn_country":"IT",
    "qs_pg:gn_fcode":"PPL",
    "qs_pg:gn_pop":0,
    "qs_pg:name":"Quadro Vecchio",
    "qs_pg:name_adm0":"Italia",
    "qs_pg:name_adm1":"Umbria",
    "qs_pg:photos":80,
    "qs_pg:photos_1k":16,
    "qs_pg:photos_9k":1,
    "qs_pg:photos_9r":3,
    "qs_pg:photos_all":80,
    "qs_pg:photos_sr":3,
    "qs_pg:pop_sr":0,
    "qs_pg:qs_pg_placetype":"locality",
    "qs_pg:qs_pg_placetype_gp":"Town",
    "qs_pg:woe_adm0":23424853,
    "woe:adm0_id":23424853,
    "woe:name_adm0":"Italia",
    "woe:name_adm1":"Umbria",
    "woe:placetype":"Town",
    "wof:name":"Quadro Vecchio",
    "wof:placetype":"locality",
    "wof:population":44
},
  "geometry": {"coordinates":[12.31667,42.78333],"type":"Point"}
}