{
  "type": "Feature",
  "properties": {
    "gn:admin1_code":"6",
    "gn:admin2_code":"GO",
    "gn:admin3_code":"31019.0",
    "gn:asciiname":"Bucuie",
    "gn:country_code":"IT",
    "gn:dem":149,
    "gn:feature_class":"P",
    "gn:feature_code":"PPL",
    "gn:name":"Bucuie",
    "gn:population":31,
    "gn:timezone":"Europe/Rome",
    "iso:country":"IT",
    "wof:name":"Bucuie",
    "wof:placetype":"locality",
    "wof:population":31
},
  "geometry": {"coordinates":[13.5886,45.97066],"type":"Point"}
}