{
  "type": "Feature",
  "properties": {
    "gn:admin1_code":"1.0",
    "gn:admin2_code":"PE",
    "gn:admin3_code":"68035.0",
    "gn:asciiname":"Piano del Ciero",
    "gn:country_code":"IT",
    "gn:dem":258,
    "gn:feature_class":"P",
    "gn:feature_code":"PPL",
    "gn:name":"Piano del Ciero",
    "gn:population":50,
    "gn:timezone":"Europe/Rome",
    "iso:country":"IT",
    "wof:name":"Piano del Ciero",
    "wof:placetype":"locality",
    "wof:population":50
},
  "geometry": {"coordinates":[14.03456,42.32448],"type":"Point"}
}