{
  "type": "Feature",
  "properties": {
    "gn:admin1_code":"16",
    "gn:admin2_code":"PI",
    "gn:admin3_code":"50040.0",
    "gn:asciiname":"I Visconti",
    "gn:country_code":"IT",
    "gn:dem":28,
    "gn:feature_class":"P",
    "gn:feature_code":"PPL",
    "gn:name":"I Visconti",
    "gn:population":86,
    "gn:timezone":"Europe/Rome",
    "iso:country":"IT",
    "wof:name":"I Visconti",
    "wof:placetype":"locality",
    "wof:population":86
},
  "geometry": {"coordinates":[10.59079,43.59219],"type":"Point"}
}