{
  "type": "Feature",
  "properties": {
    "gn:admin1_code":"7",
    "gn:admin2_code":"FR",
    "gn:admin3_code":"60066.0",
    "gn:asciiname":"Sciattigli",
    "gn:country_code":"IT",
    "gn:dem":23,
    "gn:feature_class":"P",
    "gn:feature_code":"PPL",
    "gn:name":"Sciattigli",
    "gn:population":16,
    "gn:timezone":"Europe/Rome",
    "iso:country":"IT",
    "wof:name":"Sciattigli",
    "wof:placetype":"locality",
    "wof:population":16
},
  "geometry": {"coordinates":[13.8696,41.34758],"type":"Point"}
}