{
  "type": "Feature",
  "properties": {
    "gn:admin1_code":"20",
    "gn:admin2_code":"TV",
    "gn:admin3_code":"26068.0",
    "gn:asciiname":"Case Garbuio-Piccolo",
    "gn:country_code":"IT",
    "gn:dem":50,
    "gn:feature_class":"P",
    "gn:feature_code":"PPL",
    "gn:name":"Case Garbuio-Piccolo",
    "gn:population":74,
    "gn:timezone":"Europe/Rome",
    "iso:country":"IT",
    "wof:name":"Case Garbuio-Piccolo",
    "wof:placetype":"locality",
    "wof:population":74
},
  "geometry": {"coordinates":[11.92821,45.69546],"type":"Point"}
}