{
  "type": "Feature",
  "properties": {
    "gn:admin1_code":"5",
    "gn:admin2_code":"RE",
    "gn:admin3_code":"35042.0",
    "gn:asciiname":"Cola",
    "gn:country_code":"IT",
    "gn:dem":595,
    "gn:feature_class":"P",
    "gn:feature_code":"PPLL",
    "gn:name":"Cola",
    "gn:population":6,
    "gn:timezone":"Europe/Rome",
    "iso:country":"IT",
    "wof:name":"Cola",
    "wof:placetype":"locality",
    "wof:population":6
},
  "geometry": {"coordinates":[10.35898,44.45185],"type":"Point"}
}