{
  "type": "Feature",
  "properties": {
    "gn:admin1_code":"4.0",
    "gn:admin2_code":"CE",
    "gn:admin3_code":"61010.0",
    "gn:asciiname":"Calvi Vecchia",
    "gn:country_code":"IT",
    "gn:dem":90,
    "gn:elevation":"91.0",
    "gn:feature_class":"P",
    "gn:feature_code":"PPL",
    "gn:name":"Calvi Vecchia",
    "gn:population":38,
    "gn:timezone":"Europe/Rome",
    "iso:country":"IT",
    "wof:name":"Calvi Vecchia",
    "wof:placetype":"locality",
    "wof:population":38
},
  "geometry": {"coordinates":[14.13773,41.20287],"type":"Point"}
}