{
  "type": "Feature",
  "properties": {
    "gn:admin1_code":"20",
    "gn:admin2_code":"TV",
    "gn:admin3_code":"26009.0",
    "gn:asciiname":"Ongagna",
    "gn:country_code":"IT",
    "gn:dem":8,
    "gn:feature_class":"P",
    "gn:feature_code":"PPL",
    "gn:name":"Ongagna",
    "gn:population":51,
    "gn:timezone":"Europe/Rome",
    "iso:country":"IT",
    "wof:name":"Ongagna",
    "wof:placetype":"locality",
    "wof:population":51
},
  "geometry": {"coordinates":[12.28854,45.62096],"type":"Point"}
}