{
  "type": "Feature",
  "properties": {
    "gn:admin1_code":"7.0",
    "gn:admin2_code":"RM",
    "gn:admin3_code":"58120.0",
    "gn:asciiname":"Centro 22",
    "gn:country_code":"IT",
    "gn:dem":9,
    "gn:feature_class":"P",
    "gn:feature_code":"PPL",
    "gn:name":"Centro 22",
    "gn:population":12,
    "gn:timezone":"Europe/Rome",
    "iso:country":"IT",
    "wof:name":"Centro 22",
    "wof:placetype":"locality",
    "wof:population":12
},
  "geometry": {"coordinates":[12.26438,41.85104000000001],"type":"Point"}
}