{
  "type": "Feature",
  "properties": {
    "gn:admin1_code":"20.0",
    "gn:admin2_code":"RO",
    "gn:admin3_code":"29035.0",
    "gn:asciiname":"Fattoria Vecchia",
    "gn:country_code":"IT",
    "gn:dem":2,
    "gn:elevation":"5.0",
    "gn:feature_class":"P",
    "gn:feature_code":"PPL",
    "gn:name":"Fattoria Vecchia",
    "gn:population":34,
    "gn:timezone":"Europe/Rome",
    "iso:country":"IT",
    "wof:name":"Fattoria Vecchia",
    "wof:placetype":"locality",
    "wof:population":34
},
  "geometry": {"coordinates":[11.98804,45.12557],"type":"Point"}
}