{
  "type": "Feature",
  "properties": {
    "gn:admin1_code":"20",
    "gn:admin2_code":"TV",
    "gn:admin3_code":"26069.0",
    "gn:asciiname":"Case Bettiol",
    "gn:country_code":"IT",
    "gn:dem":7,
    "gn:feature_class":"P",
    "gn:feature_code":"PPL",
    "gn:name":"Case Bettiol",
    "gn:population":37,
    "gn:timezone":"Europe/Rome",
    "iso:country":"IT",
    "wof:name":"Case Bettiol",
    "wof:placetype":"locality",
    "wof:population":37
},
  "geometry": {"coordinates":[12.33972,45.64548],"type":"Point"}
}