{
  "type": "Feature",
  "properties": {
    "gn:admin1_code":"6.0",
    "gn:admin2_code":"GO",
    "gn:admin3_code":"31009.0",
    "gn:asciiname":"Fossalon-Via Valle 13-20",
    "gn:country_code":"IT",
    "gn:dem":-2,
    "gn:feature_class":"P",
    "gn:feature_code":"PPL",
    "gn:name":"Fossalon-Via Valle 13-20",
    "gn:population":27,
    "gn:timezone":"Europe/Rome",
    "iso:country":"IT",
    "wof:name":"Fossalon-Via Valle 13-20",
    "wof:placetype":"locality",
    "wof:population":27
},
  "geometry": {"coordinates":[13.44803,45.73945],"type":"Point"}
}