{
  "type": "Feature",
  "properties": {
    "gn:admin1_code":"9.0",
    "gn:admin2_code":"BS",
    "gn:admin3_code":"17007.0",
    "gn:asciiname":"Bassinale",
    "gn:country_code":"IT",
    "gn:dem":1748,
    "gn:feature_class":"P",
    "gn:feature_code":"PPLL",
    "gn:name":"Bassinale",
    "gn:population":0,
    "gn:timezone":"Europe/Rome",
    "iso:country":"IT",
    "wof:name":"Bassinale",
    "wof:placetype":"locality"
},
  "geometry": {"coordinates":[10.23855,45.83727],"type":"Point"}
}