{
  "type": "Feature",
  "properties": {
    "gn:admin1_code":"20",
    "gn:admin2_code":"PD",
    "gn:admin3_code":"28101.0",
    "gn:asciiname":"Vilnai",
    "gn:country_code":"IT",
    "gn:dem":29,
    "gn:feature_class":"P",
    "gn:feature_code":"PPL",
    "gn:name":"Vilnai",
    "gn:population":31,
    "gn:timezone":"Europe/Rome",
    "iso:country":"IT",
    "wof:name":"Vilnai",
    "wof:placetype":"locality",
    "wof:population":31
},
  "geometry": {"coordinates":[11.87582,45.6104],"type":"Point"}
}