{
  "type": "Feature",
  "properties": {
    "gn:admin1_code":"20",
    "gn:admin2_code":"PD",
    "gn:admin3_code":"28062.0",
    "gn:asciiname":"Campagnazza",
    "gn:country_code":"IT",
    "gn:dem":6,
    "gn:feature_class":"P",
    "gn:feature_code":"PPL",
    "gn:name":"Campagnazza",
    "gn:population":15,
    "gn:timezone":"Europe/Rome",
    "iso:country":"IT",
    "wof:name":"Campagnazza",
    "wof:placetype":"locality",
    "wof:population":15
},
  "geometry": {"coordinates":[11.5645,45.12512],"type":"Point"}
}