{
  "type": "Feature",
  "properties": {
    "gn:admin1_code":"14",
    "gn:admin2_code":"CA",
    "gn:admin3_code":"92015.0",
    "gn:asciiname":"Is Orrus",
    "gn:country_code":"IT",
    "gn:dem":7,
    "gn:feature_class":"P",
    "gn:feature_code":"PPL",
    "gn:name":"Is Orrus",
    "gn:population":48,
    "gn:timezone":"Europe/Rome",
    "iso:country":"IT",
    "wof:name":"Is Orrus",
    "wof:placetype":"locality",
    "wof:population":48
},
  "geometry": {"coordinates":[8.95403,39.31835],"type":"Point"}
}