{
  "type": "Feature",
  "properties": {
    "gn:admin1_code":"6",
    "gn:admin2_code":"GO",
    "gn:admin3_code":"31011.0",
    "gn:asciiname":"Fornaci Calce",
    "gn:country_code":"IT",
    "gn:dem":44,
    "gn:feature_class":"P",
    "gn:feature_code":"PPL",
    "gn:name":"Fornaci Calce",
    "gn:population":23,
    "gn:timezone":"Europe/Rome",
    "iso:country":"IT",
    "wof:name":"Fornaci Calce",
    "wof:placetype":"locality",
    "wof:population":23
},
  "geometry": {"coordinates":[13.44252,45.92608],"type":"Point"}
}