{
  "type": "Feature",
  "properties": {
    "gn:admin1_code":"12",
    "gn:admin2_code":"CN",
    "gn:admin3_code":"4247.0",
    "gn:asciiname":"Borgata Artesio",
    "gn:country_code":"IT",
    "gn:dem":569,
    "gn:feature_class":"P",
    "gn:feature_code":"PPL",
    "gn:name":"Borgata Artesio",
    "gn:population":27,
    "gn:timezone":"Europe/Rome",
    "iso:country":"IT",
    "wof:name":"Borgata Artesio",
    "wof:placetype":"locality",
    "wof:population":27
},
  "geometry": {"coordinates":[7.41964,44.49331],"type":"Point"}
}