{
  "type": "Feature",
  "properties": {
    "gn:admin1_code":"15",
    "gn:admin2_code":"CT",
    "gn:admin3_code":"87006.0",
    "gn:asciiname":"Sacro Cuore",
    "gn:country_code":"IT",
    "gn:dem":613,
    "gn:feature_class":"P",
    "gn:feature_code":"PPL",
    "gn:name":"Sacro Cuore",
    "gn:population":134,
    "gn:timezone":"Europe/Rome",
    "iso:country":"IT",
    "wof:name":"Sacro Cuore",
    "wof:placetype":"locality",
    "wof:population":134
},
  "geometry": {"coordinates":[14.84021,37.70041],"type":"Point"}
}