{
  "type": "Feature",
  "properties": {
    "gn:admin1_code":"9",
    "gn:admin2_code":"BS",
    "gn:admin3_code":"17003.0",
    "gn:asciiname":"Casale",
    "gn:country_code":"IT",
    "gn:dem":616,
    "gn:feature_class":"P",
    "gn:feature_code":"PPL",
    "gn:name":"Casale",
    "gn:population":35,
    "gn:timezone":"Europe/Rome",
    "iso:country":"IT",
    "name:ceb_x_preferred":[
        "Casale"
    ],
    "name:deu_x_preferred":[
        "Casale"
    ],
    "name:fra_x_preferred":[
        "Casale"
    ],
    "name:ita_x_preferred":[
        "Casale"
    ],
    "name:lat_x_preferred":[
        "Casale"
    ],
    "name:pol_x_preferred":[
        "Casale"
    ],
    "name:por_x_preferred":[
        "Casale"
    ],
    "name:rus_x_preferred":[
        "\u041a\u0430\u0437\u0430\u043b\u0435"
    ],
    "name:spa_x_preferred":[
        "Casale"
    ],
    "name:srp_x_preferred":[
        "\u041a\u0430\u0437\u0430\u043b\u0435"
    ],
    "name:swe_x_preferred":[
        "Casale"
    ],
    "wof:name":"Casale",
    "wof:placetype":"locality",
    "wof:population":35
},
  "geometry": {"coordinates":[10.34022,45.64812],"type":"Point"}
}