{
  "type": "Feature",
  "properties": {
    "gn:admin1_code":"12",
    "gn:admin2_code":"AT",
    "gn:admin3_code":"5076.0",
    "gn:asciiname":"Gorra",
    "gn:country_code":"IT",
    "gn:dem":230,
    "gn:feature_class":"P",
    "gn:feature_code":"PPL",
    "gn:name":"Gorra",
    "gn:population":72,
    "gn:timezone":"Europe/Rome",
    "iso:country":"IT",
    "wof:name":"Gorra",
    "wof:placetype":"locality",
    "wof:population":72
},
  "geometry": {"coordinates":[8.20551,44.80274],"type":"Point"}
}