{
  "type": "Feature",
  "properties": {
    "gn:admin1_code":"15.0",
    "gn:admin2_code":"ME",
    "gn:admin3_code":"83048.0",
    "gn:asciiname":"Bordonaro",
    "gn:country_code":"IT",
    "gn:dem":305,
    "gn:feature_class":"P",
    "gn:feature_code":"PPL",
    "gn:name":"Bordonaro",
    "gn:population":0,
    "gn:timezone":"Europe/Rome",
    "iso:country":"IT",
    "wof:name":"Bordonaro",
    "wof:placetype":"locality"
},
  "geometry": {"coordinates":[15.51667,38.18333],"type":"Point"}
}