{
  "type": "Feature",
  "properties": {
    "gn:gn_country":"IT",
    "gn:gn_fcode":"PPLA3",
    "gn:gn_pop":521,
    "gn:population":222,
    "iso:country":"IT",
    "name:arm_x_preferred":[
        "\u054f\u0578\u0580\u0576\u0561\u057f\u0561"
    ],
    "name:baq_x_preferred":[
        "Tornata"
    ],
    "name:bel_x_preferred":[
        "\u0422\u0430\u0440\u043d\u0430\u0442\u0430"
    ],
    "name:bul_x_preferred":[
        "\u0422\u043e\u0440\u043d\u0430\u0442\u0430"
    ],
    "name:cat_x_preferred":[
        "Tornata"
    ],
    "name:chi_x_preferred":[
        "\u6258\u5c14\u7eb3\u5854"
    ],
    "name:dut_x_preferred":[
        "Tornata"
    ],
    "name:eng_x_preferred":[
        "Tornata"
    ],
    "name:epo_x_preferred":[
        "Tornata"
    ],
    "name:est_x_preferred":[
        "Tornata vald"
    ],
    "name:fre_x_preferred":[
        "Tornata"
    ],
    "name:ger_x_preferred":[
        "Tornata"
    ],
    "name:hun_x_preferred":[
        "Tornata"
    ],
    "name:ita_x_preferred":[
        "Tornata"
    ],
    "name:jpn_x_preferred":[
        "\u30c8\u30eb\u30ca\u30fc\u30bf"
    ],
    "name:kaz_x_preferred":[
        "\u0422\u043e\u0440\u043d\u0430\u0442\u0430"
    ],
    "name:lat_x_preferred":[
        "Torna"
    ],
    "name:lmo_x_preferred":[
        "Turnada"
    ],
    "name:may_x_preferred":[
        "Tornata"
    ],
    "name:nan_x_preferred":[
        "Tornata"
    ],
    "name:nap_x_preferred":[
        "Tornata"
    ],
    "name:oci_x_preferred":[
        "Tornata"
    ],
    "name:per_x_preferred":[
        "\u062a\u0648\u0631\u0646\u0627\u062a\u0627"
    ],
    "name:pms_x_preferred":[
        "Tornata"
    ],
    "name:pol_x_preferred":[
        "Tornata"
    ],
    "name:por_x_preferred":[
        "Tornata"
    ],
    "name:rum_x_preferred":[
        "Tornata"
    ],
    "name:rus_x_preferred":[
        "\u0422\u043e\u0440\u043d\u0430\u0442\u0430"
    ],
    "name:scn_x_preferred":[
        "Tornata"
    ],
    "name:spa_x_preferred":[
        "Tornata"
    ],
    "name:srp_x_preferred":[
        "Tornata"
    ],
    "name:ukr_x_preferred":[
        "\u0422\u043e\u0440\u043d\u0430\u0442\u0430"
    ],
    "name:uzb_x_preferred":[
        "Tornata"
    ],
    "name:vie_x_preferred":[
        "Tornata"
    ],
    "name:vol_x_preferred":[
        "Tornata"
    ],
    "name:war_x_preferred":[
        "Tornata"
    ],
    "qs_pg:aaroncc":"IT",
    "qs_pg:gn_country":"IT",
    "qs_pg:gn_fcode":"PPLA3",
    "qs_pg:gn_pop":521,
    "qs_pg:name":"Tornata",
    "qs_pg:name_adm0":"Italia",
    "qs_pg:name_adm1":"Lombardia",
    "qs_pg:photos_9r":0,
    "qs_pg:photos_sr":0,
    "qs_pg:pop_sr":2,
    "qs_pg:qs_pg_placetype":"locality",
    "qs_pg:qs_pg_placetype_gp":"Town",
    "qs_pg:woe_adm0":23424853,
    "woe:adm0_id":23424853,
    "woe:name_adm0":"Italia",
    "woe:name_adm1":"Lombardia",
    "woe:placetype":"Town",
    "wof:name":"Tornata",
    "wof:placetype":"locality",
    "wof:population":222
},
  "geometry": {"coordinates":[10.43078,45.10437],"type":"Point"}
}