{
  "type": "Feature",
  "properties": {
    "gn:admin1_code":"20",
    "gn:admin2_code":"TV",
    "gn:admin3_code":"26003.0",
    "gn:asciiname":"Borgo Riformati",
    "gn:country_code":"IT",
    "gn:dem":168,
    "gn:feature_class":"P",
    "gn:feature_code":"PPL",
    "gn:name":"Borgo Riformati",
    "gn:population":23,
    "gn:timezone":"Europe/Rome",
    "iso:country":"IT",
    "wof:name":"Borgo Riformati",
    "wof:placetype":"locality",
    "wof:population":23
},
  "geometry": {"coordinates":[11.91346,45.80849],"type":"Point"}
}