{
  "type": "Feature",
  "properties": {
    "gn:admin1_code":"9",
    "gn:admin2_code":"SO",
    "gn:admin3_code":"14039.0",
    "gn:asciiname":"Ferzonico",
    "gn:country_code":"IT",
    "gn:dem":227,
    "gn:feature_class":"P",
    "gn:feature_code":"PPL",
    "gn:name":"Ferzonico",
    "gn:population":67,
    "gn:timezone":"Europe/Rome",
    "iso:country":"IT",
    "wof:name":"Ferzonico",
    "wof:placetype":"locality",
    "wof:population":67
},
  "geometry": {"coordinates":[9.46983,46.15298],"type":"Point"}
}