{
  "type": "Feature",
  "properties": {
    "gn:admin1_code":"15",
    "gn:admin2_code":"TP",
    "gn:admin3_code":"81009.0",
    "gn:asciiname":"Corso",
    "gn:country_code":"IT",
    "gn:dem":24,
    "gn:feature_class":"P",
    "gn:feature_code":"PPL",
    "gn:name":"Corso",
    "gn:population":36,
    "gn:timezone":"Europe/Rome",
    "iso:country":"IT",
    "name:deu_x_preferred":[
        "Corso"
    ],
    "name:fra_x_preferred":[
        "Corso"
    ],
    "name:glg_x_preferred":[
        "Corso"
    ],
    "name:ita_x_preferred":[
        "Corso"
    ],
    "name:nds_x_preferred":[
        "Corso"
    ],
    "name:nld_x_preferred":[
        "Corso"
    ],
    "name:por_x_preferred":[
        "Corso"
    ],
    "name:rus_x_preferred":[
        "\u041a\u043e\u0440\u0441\u043e"
    ],
    "name:scn_x_preferred":[
        "C\u00e0ssaru"
    ],
    "name:spa_x_preferred":[
        "Corso"
    ],
    "name:srp_x_preferred":[
        "Corso"
    ],
    "name:ukr_x_preferred":[
        "\u041a\u043e\u0440\u0441\u043e"
    ],
    "wof:name":"Corso",
    "wof:placetype":"locality",
    "wof:population":36
},
  "geometry": {"coordinates":[12.35591,37.91752],"type":"Point"}
}