{
  "type": "Feature",
  "properties": {
    "gn:admin1_code":"9",
    "gn:admin2_code":"MN",
    "gn:admin3_code":"20018.0",
    "gn:asciiname":"Campagnolo",
    "gn:country_code":"IT",
    "gn:dem":117,
    "gn:feature_class":"P",
    "gn:feature_code":"PPL",
    "gn:name":"Campagnolo",
    "gn:population":68,
    "gn:timezone":"Europe/Rome",
    "iso:country":"IT",
    "wof:name":"Campagnolo",
    "wof:placetype":"locality",
    "wof:population":68
},
  "geometry": {"coordinates":[10.63912,45.35354],"type":"Point"}
}