{
  "type": "Feature",
  "properties": {
    "gn:admin1_code":"9",
    "gn:admin2_code":"MN",
    "gn:admin3_code":"20018.0",
    "gn:asciiname":"Campagnolo",
    "gn:country_code":"IT",
    "gn:dem":117,
    "gn:feature_class":"P",
    "gn:feature_code":"PPL",
    "gn:name":"Campagnolo",
    "gn:population":68,
    "gn:timezone":"Europe/Rome",
    "iso:country":"IT",
    "name:ara_x_preferred":[
        "\u0643\u0627\u0645\u0628\u0627\u063a\u0646\u0648\u0644\u0648"
    ],
    "name:azb_x_preferred":[
        "\u06a9\u0627\u0645\u067e\u0627\u0646\u06cc\u0648\u0644\u0648"
    ],
    "name:cat_x_preferred":[
        "Campagnolo"
    ],
    "name:ces_x_preferred":[
        "Campagnolo"
    ],
    "name:dan_x_preferred":[
        "Campagnolo"
    ],
    "name:deu_x_preferred":[
        "Campagnolo"
    ],
    "name:fas_x_preferred":[
        "\u06a9\u0627\u0645\u067e\u0627\u0646\u06cc\u0648\u0644\u0648"
    ],
    "name:fin_x_preferred":[
        "Campagnolo"
    ],
    "name:fra_x_preferred":[
        "Campagnolo"
    ],
    "name:ita_x_preferred":[
        "Campagnolo"
    ],
    "name:jpn_x_preferred":[
        "\u30ab\u30f3\u30d1\u30cb\u30e7\u30fc\u30ed"
    ],
    "name:lav_x_preferred":[
        "Campagnolo"
    ],
    "name:nld_x_preferred":[
        "Campagnolo"
    ],
    "name:nor_x_preferred":[
        "Campagnolo"
    ],
    "name:pol_x_preferred":[
        "Campagnolo"
    ],
    "name:ron_x_preferred":[
        "Campagnolo"
    ],
    "name:rus_x_preferred":[
        "Campagnolo"
    ],
    "name:spa_x_preferred":[
        "Campagnolo"
    ],
    "name:tha_x_preferred":[
        "\u0e01\u0e31\u0e21\u0e1b\u0e32\u0e0d\u0e2d\u0e42\u0e25"
    ],
    "name:ukr_x_preferred":[
        "Campagnolo"
    ],
    "name:zho_x_preferred":[
        "\u5eb7\u5e15\u7d10\u7f85"
    ],
    "wof:name":"Campagnolo",
    "wof:placetype":"locality",
    "wof:population":68
},
  "geometry": {"coordinates":[10.63912,45.35354],"type":"Point"}
}