{
  "type": "Feature",
  "properties": {
    "gn:admin1_code":"9",
    "gn:admin2_code":"BS",
    "gn:admin3_code":"17183.0",
    "gn:asciiname":"Pezzoro",
    "gn:country_code":"IT",
    "gn:dem":902,
    "gn:feature_class":"P",
    "gn:feature_code":"PPL",
    "gn:name":"Pezzoro",
    "gn:population":95,
    "gn:timezone":"Europe/Rome",
    "iso:country":"IT",
    "wof:name":"Pezzoro",
    "wof:placetype":"locality",
    "wof:population":95
},
  "geometry": {"coordinates":[10.21649,45.76138],"type":"Point"}
}