{
  "type": "Feature",
  "properties": {
    "gn:admin1_code":"3.0",
    "gn:admin2_code":"RC",
    "gn:admin3_code":"80045.0",
    "gn:asciiname":"Camocelli Superiore",
    "gn:country_code":"IT",
    "gn:dem":119,
    "gn:feature_class":"P",
    "gn:feature_code":"PPL",
    "gn:name":"Camocelli Superiore",
    "gn:population":106,
    "gn:timezone":"Europe/Rome",
    "iso:country":"IT",
    "wof:name":"Camocelli Superiore",
    "wof:placetype":"locality",
    "wof:population":106
},
  "geometry": {"coordinates":[16.34332,38.335],"type":"Point"}
}