{
  "type": "Feature",
  "properties": {
    "gn:country":"IT",
    "gn:fcode":"PPL",
    "gn:population":0,
    "iso:country":"IT",
    "name:ceb_x_preferred":[
        "Santa Caterina"
    ],
    "name:deu_x_preferred":[
        "Santa Caterina Valfurva"
    ],
    "name:eng_x_preferred":[
        "Santa Caterina di Valfurva"
    ],
    "name:fra_x_preferred":[
        "Santa Caterina di Valfurva"
    ],
    "name:hun_x_preferred":[
        "Santa Caterina Valfurva"
    ],
    "name:ita_x_preferred":[
        "Santa Caterina Valfurva"
    ],
    "name:nld_x_preferred":[
        "Santa Caterina di Valfurva"
    ],
    "name:nob_x_preferred":[
        "Santa Caterina di Valfurva"
    ],
    "name:pol_x_preferred":[
        "Santa Caterina di Valfurva"
    ],
    "name:srp_x_preferred":[
        "Santa Caterina"
    ],
    "name:swe_x_preferred":[
        "Santa Caterina di Valfurva"
    ],
    "name:und_x_variant":[
        "Valturva"
    ],
    "qs_pg:aaroncc":"IT",
    "qs_pg:gn_country":"IT",
    "qs_pg:gn_fcode":"PPL",
    "qs_pg:gn_pop":0,
    "qs_pg:name":"Santa Caterina Valfurva",
    "qs_pg:name_adm0":"Italia",
    "qs_pg:name_adm1":"Lombardia",
    "qs_pg:photos":277,
    "qs_pg:photos_1k":56,
    "qs_pg:photos_9k":1,
    "qs_pg:photos_9r":4,
    "qs_pg:photos_all":277,
    "qs_pg:photos_sr":5,
    "qs_pg:pop_sr":0,
    "qs_pg:qs_pg_placetype":"locality",
    "qs_pg:qs_pg_placetype_gp":"Town",
    "qs_pg:woe_adm0":23424853,
    "woe:adm0_id":23424853,
    "woe:name_adm0":"Italia",
    "woe:name_adm1":"Lombardia",
    "woe:placetype":"Town",
    "wof:name":"Santa Caterina Valfurva",
    "wof:placetype":"locality",
    "wof:population":233
},
  "geometry": {"coordinates":[10.48333,46.41667],"type":"Point"}
}