{
  "type": "Feature",
  "properties": {
    "gn:admin1_code":"16",
    "gn:admin2_code":"FI",
    "gn:admin3_code":"48033.0",
    "gn:asciiname":"Doccia",
    "gn:country_code":"IT",
    "gn:dem":337,
    "gn:feature_class":"P",
    "gn:feature_code":"PPL",
    "gn:name":"Doccia",
    "gn:population":164,
    "gn:timezone":"Europe/Rome",
    "iso:country":"IT",
    "wof:name":"Doccia",
    "wof:placetype":"locality",
    "wof:population":164
},
  "geometry": {"coordinates":[11.42602,43.82297],"type":"Point"}
}