{
  "type": "Feature",
  "properties": {
    "gn:admin1_code":"6",
    "gn:admin2_code":"UD",
    "gn:admin3_code":"30083.0",
    "gn:asciiname":"Casali Pitassi",
    "gn:country_code":"IT",
    "gn:dem":88,
    "gn:feature_class":"P",
    "gn:feature_code":"PPL",
    "gn:name":"Casali Pitassi",
    "gn:population":21,
    "gn:timezone":"Europe/Rome",
    "iso:country":"IT",
    "wof:name":"Casali Pitassi",
    "wof:placetype":"locality",
    "wof:population":21
},
  "geometry": {"coordinates":[13.34522,46.03613],"type":"Point"}
}