{
  "type": "Feature",
  "properties": {
    "gn:admin1_code":"9",
    "gn:admin2_code":"CR",
    "gn:admin3_code":"19024.0",
    "gn:asciiname":"Fienili",
    "gn:country_code":"IT",
    "gn:dem":99,
    "gn:feature_class":"P",
    "gn:feature_code":"PPL",
    "gn:name":"Fienili",
    "gn:population":34,
    "gn:timezone":"Europe/Rome",
    "iso:country":"IT",
    "wof:name":"Fienili",
    "wof:placetype":"locality",
    "wof:population":34
},
  "geometry": {"coordinates":[9.73009,45.46892],"type":"Point"}
}