{
  "type": "Feature",
  "properties": {
    "gn:admin1_code":"12",
    "gn:admin2_code":"AL",
    "gn:admin3_code":"6062.0",
    "gn:asciiname":"Sarizzola",
    "gn:country_code":"IT",
    "gn:dem":326,
    "gn:feature_class":"P",
    "gn:feature_code":"PPL",
    "gn:name":"Sarizzola",
    "gn:population":59,
    "gn:timezone":"Europe/Rome",
    "iso:country":"IT",
    "wof:name":"Sarizzola",
    "wof:placetype":"locality",
    "wof:population":59
},
  "geometry": {"coordinates":[8.9484,44.8101],"type":"Point"}
}