{
  "type": "Feature",
  "properties": {
    "gn:admin1_code":"7",
    "gn:admin2_code":"RI",
    "gn:admin3_code":"57051.0",
    "gn:asciiname":"Villa Falilo",
    "gn:country_code":"IT",
    "gn:dem":507,
    "gn:feature_class":"P",
    "gn:feature_code":"PPL",
    "gn:name":"Villa Falil\u00f2",
    "gn:population":307,
    "gn:timezone":"Europe/Rome",
    "iso:country":"IT",
    "name:und_x_variant":[
        "Villa Falil\u00f2"
    ],
    "wof:name":"Villa Falilo",
    "wof:placetype":"locality",
    "wof:population":307
},
  "geometry": {"coordinates":[12.88278,42.4878],"type":"Point"}
}