{
  "type": "Feature",
  "properties": {
    "gn:admin1_code":"8.0",
    "gn:admin2_code":"IM",
    "gn:admin3_code":"8031.0",
    "gn:asciiname":"Poggi Inferiore Poggi Superiore",
    "gn:country_code":"IT",
    "gn:dem":150,
    "gn:feature_class":"P",
    "gn:feature_code":"PPL",
    "gn:name":"Poggi Inferiore Poggi Superiore",
    "gn:population":743,
    "gn:timezone":"Europe/Rome",
    "iso:country":"IT",
    "wof:name":"Poggi Inferiore Poggi Superiore",
    "wof:placetype":"locality",
    "wof:population":743
},
  "geometry": {"coordinates":[7.98397,43.8703],"type":"Point"}
}