{
  "type": "Feature",
  "properties": {
    "gn:admin1_code":"12.0",
    "gn:admin2_code":"CN",
    "gn:admin3_code":"4080.0",
    "gn:asciiname":"Ricca",
    "gn:country_code":"IT",
    "gn:dem":217,
    "gn:feature_class":"P",
    "gn:feature_code":"PPL",
    "gn:name":"Ricca",
    "gn:population":1220,
    "gn:timezone":"Europe/Rome",
    "iso:country":"IT",
    "wof:name":"Ricca",
    "wof:placetype":"locality",
    "wof:population":1220
},
  "geometry": {"coordinates":[8.04527,44.66127],"type":"Point"}
}