{
  "type": "Feature",
  "properties": {
    "gn:admin1_code":"19",
    "gn:admin2_code":"AO",
    "gn:admin3_code":"7028.0",
    "gn:asciiname":"Clapasson",
    "gn:country_code":"IT",
    "gn:dem":1095,
    "gn:feature_class":"P",
    "gn:feature_code":"PPL",
    "gn:name":"Clapasson",
    "gn:population":22,
    "gn:timezone":"Europe/Rome",
    "iso:country":"IT",
    "wof:name":"Clapasson",
    "wof:placetype":"locality",
    "wof:population":22
},
  "geometry": {"coordinates":[7.8677,45.64437],"type":"Point"}
}