{
  "type": "Feature",
  "properties": {
    "gn:admin1_code":"20",
    "gn:admin2_code":"VI",
    "gn:admin3_code":"24047.0",
    "gn:asciiname":"Scuole",
    "gn:country_code":"IT",
    "gn:dem":23,
    "gn:feature_class":"P",
    "gn:feature_code":"PPL",
    "gn:name":"Scuole",
    "gn:population":255,
    "gn:timezone":"Europe/Rome",
    "iso:country":"IT",
    "wof:name":"Scuole",
    "wof:placetype":"locality",
    "wof:population":255
},
  "geometry": {"coordinates":[11.66798,45.49597],"type":"Point"}
}