{
  "type": "Feature",
  "properties": {
    "gn:admin1_code":"20",
    "gn:admin2_code":"VE",
    "gn:admin3_code":"27042.0",
    "gn:asciiname":"Giotto Sud",
    "gn:country_code":"IT",
    "gn:dem":0,
    "gn:feature_class":"P",
    "gn:feature_code":"PPL",
    "gn:name":"Giotto Sud",
    "gn:population":68,
    "gn:timezone":"Europe/Rome",
    "iso:country":"IT",
    "wof:name":"Giotto Sud",
    "wof:placetype":"locality",
    "wof:population":68
},
  "geometry": {"coordinates":[12.18541,45.48809],"type":"Point"}
}