{
  "type": "Feature",
  "properties": {
    "gn:admin1_code":"8",
    "gn:admin2_code":"SV",
    "gn:admin3_code":"9040.0",
    "gn:asciiname":"Pallareto",
    "gn:country_code":"IT",
    "gn:dem":623,
    "gn:feature_class":"P",
    "gn:feature_code":"PPL",
    "gn:name":"Pallareto",
    "gn:population":46,
    "gn:timezone":"Europe/Rome",
    "iso:country":"IT",
    "wof:name":"Pallareto",
    "wof:placetype":"locality",
    "wof:population":46
},
  "geometry": {"coordinates":[8.12707,44.31098],"type":"Point"}
}