{
  "type": "Feature",
  "properties": {
    "gn:country":"IT",
    "gn:fcode":"PPL",
    "gn:population":0,
    "iso:country":"IT",
    "name:azb_x_preferred":[
        "\u0622\u0631\u0645\u0648"
    ],
    "name:bel_x_preferred":[
        "\u0410\u0440\u043c\u043e"
    ],
    "name:bul_x_preferred":[
        "\u0410\u0440\u043c\u043e"
    ],
    "name:cat_x_preferred":[
        "Armo"
    ],
    "name:ceb_x_preferred":[
        "Armo"
    ],
    "name:deu_x_preferred":[
        "Armo"
    ],
    "name:epo_x_preferred":[
        "Armo"
    ],
    "name:eus_x_preferred":[
        "Armo"
    ],
    "name:fas_x_preferred":[
        "\u0622\u0631\u0645\u0648"
    ],
    "name:fra_x_preferred":[
        "Armo"
    ],
    "name:hun_x_preferred":[
        "Armo"
    ],
    "name:hye_x_preferred":[
        "\u0531\u0580\u0574\u0578"
    ],
    "name:ina_x_preferred":[
        "Armo"
    ],
    "name:ita_x_preferred":[
        "Armo"
    ],
    "name:jpn_x_preferred":[
        "\u30a2\u30eb\u30e2"
    ],
    "name:kaz_x_preferred":[
        "\u0410\u0440\u043c\u043e"
    ],
    "name:lat_x_preferred":[
        "Armum"
    ],
    "name:lij_x_preferred":[
        "Armo"
    ],
    "name:lmo_x_preferred":[
        "Armo"
    ],
    "name:msa_x_preferred":[
        "Armo"
    ],
    "name:nap_x_preferred":[
        "Armo"
    ],
    "name:nld_x_preferred":[
        "Armo"
    ],
    "name:oci_x_preferred":[
        "Armo"
    ],
    "name:pms_x_preferred":[
        "Armo"
    ],
    "name:pol_x_preferred":[
        "Armo"
    ],
    "name:por_x_preferred":[
        "Armo"
    ],
    "name:ron_x_preferred":[
        "Armo"
    ],
    "name:rus_x_preferred":[
        "\u0410\u0440\u043c\u043e"
    ],
    "name:scn_x_preferred":[
        "Armo"
    ],
    "name:spa_x_preferred":[
        "Armo"
    ],
    "name:srp_x_preferred":[
        "\u0410\u0440\u043c\u043e"
    ],
    "name:ukr_x_preferred":[
        "\u0410\u0440\u043c\u043e"
    ],
    "name:uzb_x_preferred":[
        "Armo"
    ],
    "name:vie_x_preferred":[
        "Armo"
    ],
    "name:vol_x_preferred":[
        "Armo"
    ],
    "name:war_x_preferred":[
        "Armo"
    ],
    "qs_pg:aaroncc":"IT",
    "qs_pg:gn_country":"IT",
    "qs_pg:gn_fcode":"PPL",
    "qs_pg:gn_pop":0,
    "qs_pg:name":"Armo",
    "qs_pg:name_adm0":"Italia",
    "qs_pg:name_adm1":"Calabria",
    "qs_pg:photos":5,
    "qs_pg:photos_1k":1,
    "qs_pg:photos_9k":1,
    "qs_pg:photos_9r":1,
    "qs_pg:photos_all":5,
    "qs_pg:photos_sr":1,
    "qs_pg:pop_sr":0,
    "qs_pg:qs_pg_placetype":"locality",
    "qs_pg:qs_pg_placetype_gp":"Town",
    "qs_pg:woe_adm0":23424853,
    "woe:adm0_id":23424853,
    "woe:name_adm0":"Italia",
    "woe:name_adm1":"Calabria",
    "woe:placetype":"Town",
    "wof:name":"Armo",
    "wof:placetype":"locality",
    "wof:population":200
},
  "geometry": {"coordinates":[15.73333,38.08333],"type":"Point"}
}