{
  "type": "Feature",
  "properties": {
    "gn:admin1_code":"20",
    "gn:admin2_code":"TV",
    "gn:admin3_code":"26068.0",
    "gn:asciiname":"Palazzon",
    "gn:country_code":"IT",
    "gn:dem":69,
    "gn:feature_class":"P",
    "gn:feature_code":"PPL",
    "gn:name":"Palazzon",
    "gn:population":34,
    "gn:timezone":"Europe/Rome",
    "iso:country":"IT",
    "wof:name":"Palazzon",
    "wof:placetype":"locality",
    "wof:population":34
},
  "geometry": {"coordinates":[11.92095,45.73733],"type":"Point"}
}