{
  "type": "Feature",
  "properties": {
    "gn:admin1_code":"16.0",
    "gn:admin2_code":"FI",
    "gn:admin3_code":"48004.0",
    "gn:asciiname":"Rabatta",
    "gn:country_code":"IT",
    "gn:dem":199,
    "gn:elevation":"193.0",
    "gn:feature_class":"P",
    "gn:feature_code":"PPL",
    "gn:name":"Rabatta",
    "gn:population":508,
    "gn:timezone":"Europe/Rome",
    "iso:country":"IT",
    "wof:name":"Rabatta",
    "wof:placetype":"locality",
    "wof:population":508
},
  "geometry": {"coordinates":[11.41309,43.94396],"type":"Point"}
}