{
  "type": "Feature",
  "properties": {
    "gn:admin1_code":"15",
    "gn:admin2_code":"ME",
    "gn:admin3_code":"83051.0",
    "gn:asciiname":"Sant'Ippolito",
    "gn:country_code":"IT",
    "gn:dem":569,
    "gn:feature_class":"P",
    "gn:feature_code":"PPL",
    "gn:name":"Sant'Ippolito",
    "gn:population":20,
    "gn:timezone":"Europe/Rome",
    "iso:country":"IT",
    "wof:name":"Sant'Ippolito",
    "wof:placetype":"locality",
    "wof:population":20
},
  "geometry": {"coordinates":[14.7463,38.07451],"type":"Point"}
}