{
  "type": "Feature",
  "properties": {
    "gn:admin1_code":"15",
    "gn:admin2_code":"ME",
    "gn:admin3_code":"83051.0",
    "gn:asciiname":"Sant'Ippolito",
    "gn:country_code":"IT",
    "gn:dem":569,
    "gn:feature_class":"P",
    "gn:feature_code":"PPL",
    "gn:name":"Sant'Ippolito",
    "gn:population":20,
    "gn:timezone":"Europe/Rome",
    "iso:country":"IT",
    "name:bul_x_preferred":[
        "\u0421\u0430\u043d\u0442'\u0418\u043f\u043e\u043b\u0438\u0442\u043e"
    ],
    "name:ceb_x_preferred":[
        "Sant'Ippolito"
    ],
    "name:deu_x_preferred":[
        "Sant\u2019Ippolito"
    ],
    "name:epo_x_preferred":[
        "Sant'Ippolito"
    ],
    "name:eus_x_preferred":[
        "Sant'Ippolito"
    ],
    "name:fra_x_preferred":[
        "Sant'Ippolito"
    ],
    "name:hun_x_preferred":[
        "Sant\u2019Ippolito"
    ],
    "name:hye_x_preferred":[
        "\u054d\u0561\u0576\u057f \u053b\u057a\u0578\u056c\u056b\u057f\u0578"
    ],
    "name:ina_x_preferred":[
        "Sant'Ippolito"
    ],
    "name:ita_x_preferred":[
        "Sant'Ippolito"
    ],
    "name:jpn_x_preferred":[
        "\u30b5\u30f3\u30c6\u30a3\u30c3\u30dd\u30fc\u30ea\u30c8"
    ],
    "name:kaz_x_preferred":[
        "\u0421\u0430\u043d\u0442'\u0438\u043f\u043f\u043e\u043b\u0438\u0442\u043e"
    ],
    "name:lmo_x_preferred":[
        "Sant'Ippolito"
    ],
    "name:msa_x_preferred":[
        "Sant'Ippolito"
    ],
    "name:nap_x_preferred":[
        "Sant'Ippolito"
    ],
    "name:nld_x_preferred":[
        "Sant'Ippolito"
    ],
    "name:pms_x_preferred":[
        "Sant'Ippolito"
    ],
    "name:pol_x_preferred":[
        "Sant\u2019Ippolito"
    ],
    "name:por_x_preferred":[
        "Sant'Ippolito"
    ],
    "name:ron_x_preferred":[
        "Sant'Ippolito"
    ],
    "name:rus_x_preferred":[
        "\u0421\u0430\u043d\u0442-\u0418\u043f\u043f\u043e\u043b\u0438\u0442\u043e"
    ],
    "name:spa_x_preferred":[
        "Sant'Ippolito"
    ],
    "name:srp_x_preferred":[
        "\u0421\u0430\u043d\u0442'\u0418\u043f\u043e\u043b\u0438\u0442\u043e"
    ],
    "name:tgl_x_preferred":[
        "Sant'Ippolito"
    ],
    "name:ukr_x_preferred":[
        "\u0421\u0430\u043d\u0442'\u0406\u043f\u043f\u043e\u043b\u0456\u0442\u043e"
    ],
    "name:uzb_x_preferred":[
        "Sant'Ippolito"
    ],
    "name:vie_x_preferred":[
        "Sant'Ippolito"
    ],
    "name:vol_x_preferred":[
        "Sant'Ippolito"
    ],
    "name:war_x_preferred":[
        "Sant'Ippolito"
    ],
    "name:zho_x_preferred":[
        "\u5723\u4f0a\u6ce2\u5229\u6258"
    ],
    "wof:name":"Sant'Ippolito",
    "wof:placetype":"locality",
    "wof:population":20
},
  "geometry": {"coordinates":[14.7463,38.07451],"type":"Point"}
}