{
  "type": "Feature",
  "properties": {
    "gn:admin1_code":"16",
    "gn:admin2_code":"MS",
    "gn:admin3_code":"45012.0",
    "gn:asciiname":"Lusuolo",
    "gn:country_code":"IT",
    "gn:dem":190,
    "gn:feature_class":"P",
    "gn:feature_code":"PPL",
    "gn:name":"Lusuolo",
    "gn:population":21,
    "gn:timezone":"Europe/Rome",
    "iso:country":"IT",
    "wof:name":"Lusuolo",
    "wof:placetype":"locality",
    "wof:population":21
},
  "geometry": {"coordinates":[9.94664,44.26597],"type":"Point"}
}