{
  "type": "Feature",
  "properties": {
    "gn:admin1_code":"3",
    "gn:admin2_code":"VV",
    "gn:admin3_code":"102034.0",
    "gn:asciiname":"Regina Elena",
    "gn:country_code":"IT",
    "gn:dem":427,
    "gn:feature_class":"P",
    "gn:feature_code":"PPL",
    "gn:name":"Regina Elena",
    "gn:population":50,
    "gn:timezone":"Europe/Rome",
    "iso:country":"IT",
    "wof:name":"Regina Elena",
    "wof:placetype":"locality",
    "wof:population":50
},
  "geometry": {"coordinates":[16.10269,38.65598],"type":"Point"}
}