{
  "type": "Feature",
  "properties": {
    "gn:admin1_code":"8",
    "gn:admin2_code":"IM",
    "gn:admin3_code":"8066.0",
    "gn:asciiname":"Perinetti",
    "gn:country_code":"IT",
    "gn:dem":203,
    "gn:feature_class":"P",
    "gn:feature_code":"PPL",
    "gn:name":"Perinetti",
    "gn:population":22,
    "gn:timezone":"Europe/Rome",
    "iso:country":"IT",
    "wof:name":"Perinetti",
    "wof:placetype":"locality",
    "wof:population":22
},
  "geometry": {"coordinates":[7.94415,44.03835],"type":"Point"}
}