{
  "type": "Feature",
  "properties": {
    "gn:admin1_code":"4.0",
    "gn:admin2_code":"SA",
    "gn:admin3_code":"65123.0",
    "gn:asciiname":"Mezzatorre di San Mauro Cilento",
    "gn:country_code":"IT",
    "gn:dem":15,
    "gn:feature_class":"P",
    "gn:feature_code":"PPL",
    "gn:name":"Mezzatorre di San Mauro Cilento",
    "gn:population":39,
    "gn:timezone":"Europe/Rome",
    "iso:country":"IT",
    "wof:name":"Mezzatorre di San Mauro Cilento",
    "wof:placetype":"locality",
    "wof:population":39
},
  "geometry": {"coordinates":[15.01825,40.19622],"type":"Point"}
}