{
  "type": "Feature",
  "properties": {
    "gn:admin1_code":"12",
    "gn:admin2_code":"TO",
    "gn:admin3_code":"1082.0",
    "gn:asciiname":"Mosche",
    "gn:country_code":"IT",
    "gn:dem":202,
    "gn:feature_class":"P",
    "gn:feature_code":"PPL",
    "gn:name":"Mosche",
    "gn:population":304,
    "gn:timezone":"Europe/Rome",
    "iso:country":"IT",
    "wof:name":"Mosche",
    "wof:placetype":"locality",
    "wof:population":304
},
  "geometry": {"coordinates":[7.8976,45.22197],"type":"Point"}
}