{
  "type": "Feature",
  "properties": {
    "gn:admin1_code":"17.0",
    "gn:admin2_code":"TN",
    "gn:admin3_code":"22104.0",
    "gn:asciiname":"Santa Giuliana",
    "gn:country_code":"IT",
    "gn:dem":491,
    "gn:feature_class":"P",
    "gn:feature_code":"PPL",
    "gn:name":"Santa Giuliana",
    "gn:population":107,
    "gn:timezone":"Europe/Rome",
    "iso:country":"IT",
    "wof:name":"Santa Giuliana",
    "wof:placetype":"locality",
    "wof:population":107
},
  "geometry": {"coordinates":[11.31414,45.99129],"type":"Point"}
}