{
  "type": "Feature",
  "properties": {
    "gn:admin1_code":"7.0",
    "gn:admin2_code":"FR",
    "gn:admin3_code":"60022.0",
    "gn:asciiname":"Mattatoio Vessella",
    "gn:country_code":"IT",
    "gn:dem":114,
    "gn:feature_class":"P",
    "gn:feature_code":"PPLL",
    "gn:name":"Mattatoio Vessella",
    "gn:population":0,
    "gn:timezone":"Europe/Rome",
    "iso:country":"IT",
    "wof:name":"Mattatoio Vessella",
    "wof:placetype":"locality"
},
  "geometry": {"coordinates":[13.65496,41.50231],"type":"Point"}
}