{
  "type": "Feature",
  "properties": {
    "gn:admin1_code":"3",
    "gn:admin2_code":"KR",
    "gn:admin3_code":"101010.0",
    "gn:asciiname":"Gabella Vi",
    "gn:country_code":"IT",
    "gn:dem":4,
    "gn:feature_class":"P",
    "gn:feature_code":"PPL",
    "gn:name":"Gabella Vi",
    "gn:population":83,
    "gn:timezone":"Europe/Rome",
    "iso:country":"IT",
    "wof:name":"Gabella Vi",
    "wof:placetype":"locality",
    "wof:population":83
},
  "geometry": {"coordinates":[17.11294,39.15287],"type":"Point"}
}