{
  "type": "Feature",
  "properties": {
    "gn:admin1_code":"1",
    "gn:admin2_code":"TE",
    "gn:admin3_code":"67007.0",
    "gn:asciiname":"Zurritto",
    "gn:country_code":"IT",
    "gn:dem":382,
    "gn:feature_class":"P",
    "gn:feature_code":"PPL",
    "gn:name":"Zurritto",
    "gn:population":21,
    "gn:timezone":"Europe/Rome",
    "iso:country":"IT",
    "wof:name":"Zurritto",
    "wof:placetype":"locality",
    "wof:population":21
},
  "geometry": {"coordinates":[13.81448,42.54531],"type":"Point"}
}