{
  "type": "Feature",
  "properties": {
    "gn:admin1_code":"8",
    "gn:admin2_code":"GE",
    "gn:admin3_code":"10062.0",
    "gn:asciiname":"Vi Superiore",
    "gn:country_code":"IT",
    "gn:dem":751,
    "gn:feature_class":"P",
    "gn:feature_code":"PPL",
    "gn:name":"Vi Superiore",
    "gn:population":15,
    "gn:timezone":"Europe/Rome",
    "iso:country":"IT",
    "wof:name":"Vi Superiore",
    "wof:placetype":"locality",
    "wof:population":15
},
  "geometry": {"coordinates":[9.11515,44.50411],"type":"Point"}
}