{
  "type": "Feature",
  "properties": {
    "gn:admin1_code":"18",
    "gn:admin2_code":"PG",
    "gn:admin3_code":"54039.0",
    "gn:asciiname":"Tavernacce",
    "gn:country_code":"IT",
    "gn:dem":228,
    "gn:feature_class":"P",
    "gn:feature_code":"PPL",
    "gn:name":"Tavernacce",
    "gn:population":108,
    "gn:timezone":"Europe/Rome",
    "iso:country":"IT",
    "wof:name":"Tavernacce",
    "wof:placetype":"locality",
    "wof:population":108
},
  "geometry": {"coordinates":[12.41031,43.23086],"type":"Point"}
}