{
  "type": "Feature",
  "properties": {
    "gn:admin1_code":"4",
    "gn:admin2_code":"CE",
    "gn:admin3_code":"61050.0",
    "gn:asciiname":"Terracorpo",
    "gn:country_code":"IT",
    "gn:dem":425,
    "gn:feature_class":"P",
    "gn:feature_code":"PPL",
    "gn:name":"Terracorpo",
    "gn:population":140,
    "gn:timezone":"Europe/Rome",
    "iso:country":"IT",
    "wof:name":"Terracorpo",
    "wof:placetype":"locality",
    "wof:population":140
},
  "geometry": {"coordinates":[14.02997,41.31312],"type":"Point"}
}