{
  "type": "Feature",
  "properties": {
    "gn:admin1_code":"20",
    "gn:admin2_code":"VI",
    "gn:admin3_code":"24063.0",
    "gn:asciiname":"Festa di Sotto",
    "gn:country_code":"IT",
    "gn:dem":294,
    "gn:feature_class":"P",
    "gn:feature_code":"PPL",
    "gn:name":"Festa di Sotto",
    "gn:population":28,
    "gn:timezone":"Europe/Rome",
    "iso:country":"IT",
    "wof:name":"Festa di Sotto",
    "wof:placetype":"locality",
    "wof:population":28
},
  "geometry": {"coordinates":[11.37056,45.651],"type":"Point"}
}