{
  "type": "Feature",
  "properties": {
    "gn:admin1_code":"3",
    "gn:admin2_code":"CS",
    "gn:admin3_code":"78102.0",
    "gn:asciiname":"Santo Ianni",
    "gn:country_code":"IT",
    "gn:dem":461,
    "gn:feature_class":"P",
    "gn:feature_code":"PPL",
    "gn:name":"Santo Ianni",
    "gn:population":111,
    "gn:timezone":"Europe/Rome",
    "iso:country":"IT",
    "wof:name":"Santo Ianni",
    "wof:placetype":"locality",
    "wof:population":111
},
  "geometry": {"coordinates":[16.1665,39.31877],"type":"Point"}
}