{
  "type": "Feature",
  "properties": {
    "gn:admin1_code":"9",
    "gn:admin2_code":"CR",
    "gn:admin3_code":"19042.0",
    "gn:asciiname":"Castelfranco d'Oglio",
    "gn:country_code":"IT",
    "gn:dem":28,
    "gn:feature_class":"P",
    "gn:feature_code":"PPL",
    "gn:name":"Castelfranco d'Oglio",
    "gn:population":83,
    "gn:timezone":"Europe/Rome",
    "iso:country":"IT",
    "wof:name":"Castelfranco d'Oglio",
    "wof:placetype":"locality",
    "wof:population":83
},
  "geometry": {"coordinates":[10.36173,45.15623],"type":"Point"}
}