{
  "type": "Feature",
  "properties": {
    "gn:admin1_code":"5",
    "gn:admin2_code":"BO",
    "gn:admin3_code":"37060.0",
    "gn:asciiname":"Ca Molinetti",
    "gn:country_code":"IT",
    "gn:dem":76,
    "gn:feature_class":"P",
    "gn:feature_code":"PPL",
    "gn:name":"C\u00e0 Molinetti",
    "gn:population":71,
    "gn:timezone":"Europe/Rome",
    "iso:country":"IT",
    "name:und_x_variant":[
        "C\u00e0 Molinetti"
    ],
    "wof:name":"Ca Molinetti",
    "wof:placetype":"locality",
    "wof:population":71
},
  "geometry": {"coordinates":[11.18589,44.4908],"type":"Point"}
}