{
  "type": "Feature",
  "properties": {
    "gn:admin1_code":"14",
    "gn:admin2_code":"SU",
    "gn:admin3_code":"111041.0",
    "gn:asciiname":"Is Argiddas",
    "gn:country_code":"IT",
    "gn:dem":78,
    "gn:feature_class":"P",
    "gn:feature_code":"PPL",
    "gn:name":"Is Argiddas",
    "gn:population":20,
    "gn:timezone":"Europe/Rome",
    "iso:country":"IT",
    "wof:name":"Is Argiddas",
    "wof:placetype":"locality",
    "wof:population":20
},
  "geometry": {"coordinates":[9.0483,39.37281],"type":"Point"}
}