{
  "type": "Feature",
  "properties": {
    "gn:admin1_code":"5",
    "gn:admin2_code":"PC",
    "gn:admin3_code":"33020.0",
    "gn:asciiname":"Pronzali",
    "gn:country_code":"IT",
    "gn:dem":575,
    "gn:feature_class":"P",
    "gn:feature_code":"PPL",
    "gn:name":"Pronzali",
    "gn:population":25,
    "gn:timezone":"Europe/Rome",
    "iso:country":"IT",
    "wof:name":"Pronzali",
    "wof:placetype":"locality",
    "wof:population":25
},
  "geometry": {"coordinates":[9.54428,44.6588],"type":"Point"}
}