{
  "type": "Feature",
  "properties": {
    "gn:admin1_code":"20.0",
    "gn:admin2_code":"VR",
    "gn:admin3_code":"23026.0",
    "gn:asciiname":"Carcereri",
    "gn:country_code":"IT",
    "gn:dem":698,
    "gn:feature_class":"P",
    "gn:feature_code":"PPL",
    "gn:name":"Carcereri",
    "gn:population":0,
    "gn:timezone":"Europe/Rome",
    "iso:country":"IT",
    "wof:name":"Carcereri",
    "wof:placetype":"locality"
},
  "geometry": {"coordinates":[11.03333,45.58333],"type":"Point"}
}