{
  "type": "Feature",
  "properties": {
    "gn:admin1_code":"16.0",
    "gn:admin2_code":"LU",
    "gn:admin3_code":"46034.0",
    "gn:asciiname":"Colognora",
    "gn:country_code":"IT",
    "gn:dem":522,
    "gn:elevation":"562.0",
    "gn:feature_class":"P",
    "gn:feature_code":"PPL",
    "gn:name":"Colognora",
    "gn:population":109,
    "gn:timezone":"Europe/Rome",
    "iso:country":"IT",
    "wof:name":"Colognora",
    "wof:placetype":"locality",
    "wof:population":109
},
  "geometry": {"coordinates":[10.66078,43.9609],"type":"Point"}
}