{
  "type": "Feature",
  "properties": {
    "gn:admin1_code":"17",
    "gn:admin2_code":"BZ",
    "gn:admin3_code":"21117.0",
    "gn:asciiname":"Campo",
    "gn:country_code":"IT",
    "gn:dem":1472,
    "gn:feature_class":"P",
    "gn:feature_code":"PPL",
    "gn:name":"Campo",
    "gn:population":59,
    "gn:timezone":"Europe/Rome",
    "iso:country":"IT",
    "wof:name":"Campo",
    "wof:placetype":"locality",
    "wof:population":59
},
  "geometry": {"coordinates":[11.92125,46.66146],"type":"Point"}
}