{
  "type": "Feature",
  "properties": {
    "gn:admin1_code":"20",
    "gn:admin2_code":"VI",
    "gn:admin3_code":"24076.0",
    "gn:asciiname":"Brancafora",
    "gn:country_code":"IT",
    "gn:dem":498,
    "gn:feature_class":"P",
    "gn:feature_code":"PPL",
    "gn:name":"Brancafora",
    "gn:population":142,
    "gn:timezone":"Europe/Rome",
    "iso:country":"IT",
    "wof:name":"Brancafora",
    "wof:placetype":"locality",
    "wof:population":142
},
  "geometry": {"coordinates":[11.3029,45.91285],"type":"Point"}
}