{
  "type": "Feature",
  "properties": {
    "gn:admin1_code":"7.0",
    "gn:admin2_code":"FR",
    "gn:admin3_code":"60059.0",
    "gn:asciiname":"Fraioli Casilina",
    "gn:country_code":"IT",
    "gn:dem":289,
    "gn:feature_class":"P",
    "gn:feature_code":"PPL",
    "gn:name":"Fraioli Casilina",
    "gn:population":15,
    "gn:timezone":"Europe/Rome",
    "iso:country":"IT",
    "wof:name":"Fraioli Casilina",
    "wof:placetype":"locality",
    "wof:population":15
},
  "geometry": {"coordinates":[13.60972,41.58042],"type":"Point"}
}