{
  "type": "Feature",
  "properties": {
    "gn:admin1_code":"15",
    "gn:admin2_code":"PA",
    "gn:admin3_code":"82078.0",
    "gn:asciiname":"Santa Rosalia",
    "gn:country_code":"IT",
    "gn:dem":668,
    "gn:feature_class":"P",
    "gn:feature_code":"PPL",
    "gn:name":"Santa Rosalia",
    "gn:population":168,
    "gn:timezone":"Europe/Rome",
    "iso:country":"IT",
    "wof:name":"Santa Rosalia",
    "wof:placetype":"locality",
    "wof:population":168
},
  "geometry": {"coordinates":[13.59646,37.7518],"type":"Point"}
}