{
  "type": "Feature",
  "properties": {
    "gn:admin1_code":"16.0",
    "gn:admin2_code":"SI",
    "gn:admin3_code":"52034.0",
    "gn:asciiname":"Brucciano",
    "gn:country_code":"IT",
    "gn:dem":235,
    "gn:elevation":"237.0",
    "gn:feature_class":"P",
    "gn:feature_code":"PPL",
    "gn:name":"Brucciano",
    "gn:population":37,
    "gn:timezone":"Europe/Rome",
    "iso:country":"IT",
    "wof:name":"Brucciano",
    "wof:placetype":"locality",
    "wof:population":37
},
  "geometry": {"coordinates":[11.28863,43.24304],"type":"Point"}
}