{
  "type": "Feature",
  "properties": {
    "gn:admin1_code":"3.0",
    "gn:admin2_code":"RC",
    "gn:admin3_code":"80053.0",
    "gn:asciiname":"Fossato Ionico-Fossatello-San Luca Marcelluzzo",
    "gn:country_code":"IT",
    "gn:dem":565,
    "gn:feature_class":"P",
    "gn:feature_code":"PPL",
    "gn:name":"Fossato Ionico-Fossatello-San Luca Marcelluzzo",
    "gn:population":1062,
    "gn:timezone":"Europe/Rome",
    "iso:country":"IT",
    "wof:name":"Fossato Ionico-Fossatello-San Luca Marcelluzzo",
    "wof:placetype":"locality",
    "wof:population":1062
},
  "geometry": {"coordinates":[15.76302,38.01065],"type":"Point"}
}