{
  "type": "Feature",
  "properties": {
    "gn:admin1_code":"15.0",
    "gn:admin2_code":"PA",
    "gn:admin3_code":"82058.0",
    "gn:asciiname":"Contrada Campo",
    "gn:country_code":"IT",
    "gn:dem":895,
    "gn:feature_class":"P",
    "gn:feature_code":"PPLL",
    "gn:name":"Contrada Campo",
    "gn:population":0,
    "gn:timezone":"Europe/Rome",
    "iso:country":"IT",
    "wof:name":"Contrada Campo",
    "wof:placetype":"locality"
},
  "geometry": {"coordinates":[14.01678,37.79314],"type":"Point"}
}