{
  "type": "Feature",
  "properties": {
    "gn:admin1_code":"17.0",
    "gn:admin2_code":"BZ",
    "gn:admin3_code":"21038.0",
    "gn:asciiname":"Zona Laurin",
    "gn:country_code":"IT",
    "gn:dem":308,
    "gn:feature_class":"P",
    "gn:feature_code":"PPL",
    "gn:name":"Zona Laurin",
    "gn:population":793,
    "gn:timezone":"Europe/Rome",
    "iso:country":"IT",
    "wof:name":"Zona Laurin",
    "wof:placetype":"locality",
    "wof:population":793
},
  "geometry": {"coordinates":[11.14467,46.67821],"type":"Point"}
}