{
  "type": "Feature",
  "properties": {
    "gn:admin1_code":"16.0",
    "gn:admin2_code":"SI",
    "gn:admin3_code":"52015.0",
    "gn:asciiname":"Gracciano",
    "gn:country_code":"IT",
    "gn:dem":297,
    "gn:elevation":"290.0",
    "gn:feature_class":"P",
    "gn:feature_code":"PPL",
    "gn:name":"Gracciano",
    "gn:population":583,
    "gn:timezone":"Europe/Rome",
    "iso:country":"IT",
    "wof:name":"Gracciano",
    "wof:placetype":"locality",
    "wof:population":583
},
  "geometry": {"coordinates":[11.82896,43.13233],"type":"Point"}
}