{
  "type": "Feature",
  "properties": {
    "gn:admin1_code":"3.0",
    "gn:admin2_code":"CZ",
    "gn:admin3_code":"79087.0",
    "gn:asciiname":"Campodorato",
    "gn:country_code":"IT",
    "gn:dem":428,
    "gn:feature_class":"P",
    "gn:feature_code":"PPL",
    "gn:name":"Campodorato",
    "gn:population":415,
    "gn:timezone":"Europe/Rome",
    "iso:country":"IT",
    "wof:name":"Campodorato",
    "wof:placetype":"locality",
    "wof:population":415
},
  "geometry": {"coordinates":[16.15102000000001,39.02096],"type":"Point"}
}