{
  "type": "Feature",
  "properties": {
    "gn:admin1_code":"20",
    "gn:admin2_code":"VI",
    "gn:admin3_code":"24100.0",
    "gn:asciiname":"Bonolli",
    "gn:country_code":"IT",
    "gn:dem":718,
    "gn:feature_class":"P",
    "gn:feature_code":"PPLL",
    "gn:name":"Bonolli",
    "gn:population":10,
    "gn:timezone":"Europe/Rome",
    "iso:country":"IT",
    "wof:name":"Bonolli",
    "wof:placetype":"locality",
    "wof:population":10
},
  "geometry": {"coordinates":[11.30234,45.74449],"type":"Point"}
}