{
  "type": "Feature",
  "properties": {
    "gn:admin1_code":"20",
    "gn:admin2_code":"VI",
    "gn:admin3_code":"24121.0",
    "gn:asciiname":"Franceschini",
    "gn:country_code":"IT",
    "gn:dem":362,
    "gn:feature_class":"P",
    "gn:feature_code":"PPL",
    "gn:name":"Franceschini",
    "gn:population":27,
    "gn:timezone":"Europe/Rome",
    "iso:country":"IT",
    "wof:name":"Franceschini",
    "wof:placetype":"locality",
    "wof:population":27
},
  "geometry": {"coordinates":[11.4953,45.44886],"type":"Point"}
}