{
  "type": "Feature",
  "properties": {
    "gn:admin1_code":"4",
    "gn:admin2_code":"AV",
    "gn:admin3_code":"64095.0",
    "gn:asciiname":"Starze",
    "gn:country_code":"IT",
    "gn:dem":380,
    "gn:feature_class":"P",
    "gn:feature_code":"PPL",
    "gn:name":"Starze",
    "gn:population":32,
    "gn:timezone":"Europe/Rome",
    "iso:country":"IT",
    "wof:name":"Starze",
    "wof:placetype":"locality",
    "wof:population":32
},
  "geometry": {"coordinates":[14.86337,40.88565],"type":"Point"}
}