{
  "type": "Feature",
  "properties": {
    "gn:admin1_code":"9.0",
    "gn:admin2_code":"BS",
    "gn:admin3_code":"17020.0",
    "gn:asciiname":"Farfengo",
    "gn:country_code":"IT",
    "gn:dem":75,
    "gn:elevation":"75.0",
    "gn:feature_class":"P",
    "gn:feature_code":"PPL",
    "gn:name":"Farfengo",
    "gn:population":548,
    "gn:timezone":"Europe/Rome",
    "iso:country":"IT",
    "wof:name":"Farfengo",
    "wof:placetype":"locality",
    "wof:population":548
},
  "geometry": {"coordinates":[9.97949,45.36814],"type":"Point"}
}