{
  "type": "Feature",
  "properties": {
    "gn:admin1_code":"11.0",
    "gn:admin2_code":"IS",
    "gn:admin3_code":"94039.0",
    "gn:asciiname":"Casabona",
    "gn:country_code":"IT",
    "gn:dem":877,
    "gn:elevation":"843.0",
    "gn:feature_class":"P",
    "gn:feature_code":"PPL",
    "gn:name":"Casabona",
    "gn:population":36,
    "gn:timezone":"Europe/Rome",
    "iso:country":"IT",
    "wof:name":"Casabona",
    "wof:placetype":"locality",
    "wof:population":36
},
  "geometry": {"coordinates":[14.15903,41.71593],"type":"Point"}
}