{
  "type": "Feature",
  "properties": {
    "gn:admin1_code":"20",
    "gn:admin2_code":"VR",
    "gn:admin3_code":"23059.0",
    "gn:asciiname":"Lizzara-Vecchia",
    "gn:country_code":"IT",
    "gn:dem":79,
    "gn:feature_class":"P",
    "gn:feature_code":"PPL",
    "gn:name":"Lizzara-Vecchia",
    "gn:population":36,
    "gn:timezone":"Europe/Rome",
    "iso:country":"IT",
    "wof:name":"Lizzara-Vecchia",
    "wof:placetype":"locality",
    "wof:population":36
},
  "geometry": {"coordinates":[10.6593,45.44551],"type":"Point"}
}