{
  "type": "Feature",
  "properties": {
    "gn:admin1_code":"7",
    "gn:admin2_code":"FR",
    "gn:admin3_code":"60055.0",
    "gn:asciiname":"Colle Vampa",
    "gn:country_code":"IT",
    "gn:dem":139,
    "gn:feature_class":"P",
    "gn:feature_code":"PPL",
    "gn:name":"Colle Vampa",
    "gn:population":18,
    "gn:timezone":"Europe/Rome",
    "iso:country":"IT",
    "wof:name":"Colle Vampa",
    "wof:placetype":"locality",
    "wof:population":18
},
  "geometry": {"coordinates":[13.41773,41.54769],"type":"Point"}
}