{
  "type": "Feature",
  "properties": {
    "gn:admin1_code":"8",
    "gn:admin2_code":"GE",
    "gn:admin3_code":"10023.0",
    "gn:asciiname":"Castello",
    "gn:country_code":"IT",
    "gn:dem":418,
    "gn:feature_class":"P",
    "gn:feature_code":"PPL",
    "gn:name":"Castello",
    "gn:population":66,
    "gn:timezone":"Europe/Rome",
    "iso:country":"IT",
    "name:ast_x_preferred":[
        "Castello"
    ],
    "name:ceb_x_preferred":[
        "Castello"
    ],
    "name:deu_x_preferred":[
        "Castello"
    ],
    "name:epo_x_preferred":[
        "Castello"
    ],
    "name:fra_x_preferred":[
        "Castello"
    ],
    "name:heb_x_preferred":[
        "\u05e7\u05e1\u05d8\u05dc\u05d5"
    ],
    "name:ita_x_preferred":[
        "Castello"
    ],
    "name:nld_x_preferred":[
        "Castello"
    ],
    "name:por_x_preferred":[
        "Castello"
    ],
    "name:rus_x_preferred":[
        "\u041a\u0430\u0441\u0442\u0435\u043b\u043b\u043e"
    ],
    "name:spa_x_preferred":[
        "Castello"
    ],
    "name:srp_x_preferred":[
        "\u041a\u0430\u0441\u0442\u0435\u043b\u043e"
    ],
    "name:swe_x_preferred":[
        "Castello"
    ],
    "wof:name":"Castello",
    "wof:placetype":"locality",
    "wof:population":66
},
  "geometry": {"coordinates":[9.25464,44.45889],"type":"Point"}
}