{
  "type": "Feature",
  "properties": {
    "gn:admin1_code":"9",
    "gn:admin2_code":"BS",
    "gn:admin3_code":"17142.0",
    "gn:asciiname":"Minolfa",
    "gn:country_code":"IT",
    "gn:dem":243,
    "gn:feature_class":"P",
    "gn:feature_code":"PPL",
    "gn:name":"Minolfa",
    "gn:population":41,
    "gn:timezone":"Europe/Rome",
    "iso:country":"IT",
    "wof:name":"Minolfa",
    "wof:placetype":"locality",
    "wof:population":41
},
  "geometry": {"coordinates":[10.1471,45.83717],"type":"Point"}
}