{
  "type": "Feature",
  "properties": {
    "gn:admin1_code":"12",
    "gn:admin2_code":"VB",
    "gn:admin3_code":"103024.0",
    "gn:asciiname":"Prestinone",
    "gn:country_code":"IT",
    "gn:dem":808,
    "gn:feature_class":"P",
    "gn:feature_code":"PPL",
    "gn:name":"Prestinone",
    "gn:population":110,
    "gn:timezone":"Europe/Rome",
    "iso:country":"IT",
    "wof:name":"Prestinone",
    "wof:placetype":"locality",
    "wof:population":110
},
  "geometry": {"coordinates":[8.47827,46.13851],"type":"Point"}
}