{
  "type": "Feature",
  "properties": {
    "gn:admin1_code":"6",
    "gn:admin2_code":"PN",
    "gn:admin3_code":"93029.0",
    "gn:asciiname":"Case Vecchies",
    "gn:country_code":"IT",
    "gn:dem":14,
    "gn:feature_class":"P",
    "gn:feature_code":"PPL",
    "gn:name":"Case Vecchies",
    "gn:population":57,
    "gn:timezone":"Europe/Rome",
    "iso:country":"IT",
    "wof:name":"Case Vecchies",
    "wof:placetype":"locality",
    "wof:population":57
},
  "geometry": {"coordinates":[12.6197,45.89047],"type":"Point"}
}