{
  "type": "Feature",
  "properties": {
    "gn:admin1_code":"6.0",
    "gn:admin2_code":"UD",
    "gn:admin3_code":"30113.0",
    "gn:asciiname":"Debellis",
    "gn:country_code":"IT",
    "gn:dem":369,
    "gn:elevation":"352.0",
    "gn:feature_class":"P",
    "gn:feature_code":"PPL",
    "gn:name":"Debellis",
    "gn:population":25,
    "gn:timezone":"Europe/Rome",
    "iso:country":"IT",
    "wof:name":"Debellis",
    "wof:placetype":"locality",
    "wof:population":25
},
  "geometry": {"coordinates":[13.32465,46.25957],"type":"Point"}
}