{
  "type": "Feature",
  "properties": {
    "gn:population":826,
    "iso:country":"IT",
    "name:cat_x_preferred":[
        "Santa Valburga"
    ],
    "name:ceb_x_preferred":[
        "Santa Valburga"
    ],
    "name:ces_x_preferred":[
        "Santa Valburga"
    ],
    "name:dan_x_preferred":[
        "Santa Valburga"
    ],
    "name:deu_x_preferred":[
        "St. Walburg"
    ],
    "name:deu_x_variant":[
        "Ulten"
    ],
    "name:eng_x_preferred":[
        "Santa Valburga"
    ],
    "name:eus_x_preferred":[
        "Santa Valburga"
    ],
    "name:fin_x_preferred":[
        "Santa Valburga"
    ],
    "name:fra_x_preferred":[
        "Santa Valburga"
    ],
    "name:ind_x_preferred":[
        "Santa Valburga"
    ],
    "name:ita_x_preferred":[
        "Santa Valpurga"
    ],
    "name:ita_x_variant":[
        "Sankt Walburg",
        "Santa Valburga",
        "Santa Valburga in Ultimo",
        "Santa Valpurga d'Ultimo",
        "Skt Walburg",
        "Skt. Walburg",
        "St Walburg",
        "St. Walburg",
        "Sta Valburga",
        "Sta Valburga in Ultimo",
        "Sta Valpurga",
        "Sta Valpurga d'Ultimo",
        "Sta. Valburga",
        "Sta. Valburga in Ultimo",
        "Sta. Valpurga",
        "Sta. Valpurga d'Ultimo",
        "Comune di Ultimo",
        "Ultimo"
    ],
    "name:nld_x_preferred":[
        "Santa Valburga"
    ],
    "name:nno_x_preferred":[
        "Santa Valburga"
    ],
    "name:nob_x_preferred":[
        "Santa Valburga"
    ],
    "name:oci_x_preferred":[
        "Santa Valburga"
    ],
    "name:pol_x_preferred":[
        "Santa Valburga"
    ],
    "name:por_x_preferred":[
        "Santa Valburga"
    ],
    "name:ron_x_preferred":[
        "Santa Valburga"
    ],
    "name:slk_x_preferred":[
        "Santa Valburga"
    ],
    "name:slv_x_preferred":[
        "Santa Valburga"
    ],
    "name:spa_x_preferred":[
        "Santa Valburga"
    ],
    "name:srp_x_preferred":[
        "Santa Valburga"
    ],
    "name:swe_x_preferred":[
        "Santa Valburga"
    ],
    "name:tgl_x_preferred":[
        "Santa Valburga"
    ],
    "name:tur_x_preferred":[
        "Santa Valburga"
    ],
    "name:war_x_preferred":[
        "Santa Valburga"
    ],
    "qs:a0":"Italia",
    "qs:a1":"*Bolzano#Bozen",
    "qs:a1r":"0Trentino-Alto Adige/S\u00fcdtirol",
    "qs:adm0":"Italia",
    "qs:la_lc":"*",
    "qs:level":"locality",
    "qs:loc":"Santa Valburga",
    "qs:loc_alt":"Santa Valburga",
    "qs:pop":0,
    "qs:type":"buffered point",
    "wof:lang":[
        "ita"
    ],
    "wof:name":"Santa Valburga",
    "wof:placetype":"locality",
    "wof:population":826
},
  "geometry": {"coordinates":[11.005,46.549172],"type":"Point"}
}