{
  "type": "Feature",
  "properties": {
    "gn:admin1_code":"16.0",
    "gn:admin2_code":"SI",
    "gn:admin3_code":"52012.0",
    "gn:asciiname":"Quartaia",
    "gn:cc2":"IT",
    "gn:country_code":"IT",
    "gn:dem":258,
    "gn:elevation":"266.0",
    "gn:feature_class":"P",
    "gn:feature_code":"PPL",
    "gn:name":"Quartaia",
    "gn:population":487,
    "gn:timezone":"Europe/Rome",
    "iso:country":"IT",
    "name:und_x_variant":[
        "Quartaja",
        "Quartaia"
    ],
    "wof:name":"Quartaia",
    "wof:placetype":"locality",
    "wof:population":487
},
  "geometry": {"coordinates":[11.08671,43.38635],"type":"Point"}
}