{
  "type": "Feature",
  "properties": {
    "gn:admin1_code":"5",
    "gn:admin2_code":"BO",
    "gn:admin3_code":"37021.0",
    "gn:asciiname":"Veduro",
    "gn:country_code":"IT",
    "gn:dem":29,
    "gn:feature_class":"P",
    "gn:feature_code":"PPL",
    "gn:name":"Veduro",
    "gn:population":16,
    "gn:timezone":"Europe/Rome",
    "iso:country":"IT",
    "wof:name":"Veduro",
    "wof:placetype":"locality",
    "wof:population":16
},
  "geometry": {"coordinates":[11.47383,44.53901],"type":"Point"}
}