{
  "type": "Feature",
  "properties": {
    "gn:admin1_code":"9",
    "gn:admin2_code":"SO",
    "gn:admin3_code":"14020.0",
    "gn:asciiname":"Contrada Valle",
    "gn:country_code":"IT",
    "gn:dem":617,
    "gn:feature_class":"P",
    "gn:feature_code":"PPL",
    "gn:name":"Contrada Valle",
    "gn:population":70,
    "gn:timezone":"Europe/Rome",
    "iso:country":"IT",
    "wof:name":"Contrada Valle",
    "wof:placetype":"locality",
    "wof:population":70
},
  "geometry": {"coordinates":[10.01269,46.17483],"type":"Point"}
}