{
  "type": "Feature",
  "properties": {
    "gn:admin1_code":"3",
    "gn:admin2_code":"CS",
    "gn:admin3_code":"78123.0",
    "gn:asciiname":"Spinetto",
    "gn:country_code":"IT",
    "gn:dem":253,
    "gn:feature_class":"P",
    "gn:feature_code":"PPL",
    "gn:name":"Spinetto",
    "gn:population":230,
    "gn:timezone":"Europe/Rome",
    "iso:country":"IT",
    "wof:name":"Spinetto",
    "wof:placetype":"locality",
    "wof:population":230
},
  "geometry": {"coordinates":[16.16762,39.57165],"type":"Point"}
}