{
  "type": "Feature",
  "properties": {
    "gn:admin1_code":"5",
    "gn:admin2_code":"BO",
    "gn:admin3_code":"37008.0",
    "gn:asciiname":"San Leo",
    "gn:country_code":"IT",
    "gn:dem":18,
    "gn:feature_class":"P",
    "gn:feature_code":"PPL",
    "gn:name":"San Leo",
    "gn:population":15,
    "gn:timezone":"Europe/Rome",
    "iso:country":"IT",
    "wof:name":"San Leo",
    "wof:placetype":"locality",
    "wof:population":15
},
  "geometry": {"coordinates":[11.56386,44.55619],"type":"Point"}
}