{
  "type": "Feature",
  "properties": {
    "gn:admin1_code":"7",
    "gn:admin2_code":"FR",
    "gn:admin3_code":"60052.0",
    "gn:asciiname":"Ruscito",
    "gn:country_code":"IT",
    "gn:dem":98,
    "gn:feature_class":"P",
    "gn:feature_code":"PPL",
    "gn:name":"Ruscito",
    "gn:population":243,
    "gn:timezone":"Europe/Rome",
    "iso:country":"IT",
    "wof:name":"Ruscito",
    "wof:placetype":"locality",
    "wof:population":243
},
  "geometry": {"coordinates":[13.74116,41.45634],"type":"Point"}
}