{
  "type": "Feature",
  "properties": {
    "gn:gn_country":"IT",
    "gn:gn_fcode":"PPLL",
    "gn:gn_pop":0,
    "gn:population":298,
    "iso:country":"IT",
    "name:cat_x_preferred":[
        "Cornino"
    ],
    "name:ces_x_preferred":[
        "Cornino"
    ],
    "name:dan_x_preferred":[
        "Cornino"
    ],
    "name:eng_x_preferred":[
        "Cornino"
    ],
    "name:eus_x_preferred":[
        "Cornino"
    ],
    "name:fin_x_preferred":[
        "Cornino"
    ],
    "name:fra_x_preferred":[
        "Cornino"
    ],
    "name:ind_x_preferred":[
        "Cornino"
    ],
    "name:ita_x_preferred":[
        "Cornino"
    ],
    "name:nno_x_preferred":[
        "Cornino"
    ],
    "name:nob_x_preferred":[
        "Cornino"
    ],
    "name:oci_x_preferred":[
        "Cornino"
    ],
    "name:pol_x_preferred":[
        "Cornino"
    ],
    "name:por_x_preferred":[
        "Cornino"
    ],
    "name:ron_x_preferred":[
        "Cornino"
    ],
    "name:slk_x_preferred":[
        "Cornino"
    ],
    "name:slv_x_preferred":[
        "Cornino"
    ],
    "name:spa_x_preferred":[
        "Cornino"
    ],
    "name:srp_x_preferred":[
        "Cornino"
    ],
    "name:swe_x_preferred":[
        "Cornino"
    ],
    "name:tgl_x_preferred":[
        "Cornino"
    ],
    "name:tur_x_preferred":[
        "Cornino"
    ],
    "name:war_x_preferred":[
        "Cornino"
    ],
    "qs_pg:aaroncc":"IT",
    "qs_pg:gn_country":"IT",
    "qs_pg:gn_fcode":"PPLL",
    "qs_pg:gn_pop":0,
    "qs_pg:name":"Cornino",
    "qs_pg:name_adm0":"Italia",
    "qs_pg:name_adm1":"Sicilia",
    "qs_pg:photos":151,
    "qs_pg:photos_1k":31,
    "qs_pg:photos_9k":1,
    "qs_pg:photos_9r":4,
    "qs_pg:photos_all":151,
    "qs_pg:photos_sr":4,
    "qs_pg:pop_sr":0,
    "qs_pg:qs_pg_placetype":"locality",
    "qs_pg:qs_pg_placetype_gp":"Town",
    "qs_pg:woe_adm0":23424853,
    "woe:adm0_id":23424853,
    "woe:name_adm0":"Italia",
    "woe:name_adm1":"Sicilia",
    "woe:placetype":"Town",
    "wof:name":"Cornino",
    "wof:placetype":"locality",
    "wof:population":298
},
  "geometry": {"coordinates":[12.66282,38.09235],"type":"Point"}
}