{
  "type": "Feature",
  "properties": {
    "gn:admin1_code":"9",
    "gn:admin2_code":"BG",
    "gn:admin3_code":"16080.0",
    "gn:asciiname":"Bondo",
    "gn:country_code":"IT",
    "gn:dem":825,
    "gn:feature_class":"P",
    "gn:feature_code":"PPL",
    "gn:name":"Bondo",
    "gn:population":93,
    "gn:timezone":"Europe/Rome",
    "iso:country":"IT",
    "wof:name":"Bondo",
    "wof:placetype":"locality",
    "wof:population":93
},
  "geometry": {"coordinates":[9.85432,45.83893],"type":"Point"}
}