{
  "type": "Feature",
  "properties": {
    "gn:admin1_code":"8",
    "gn:admin2_code":"GE",
    "gn:admin3_code":"10053.0",
    "gn:asciiname":"Ferreccio",
    "gn:country_code":"IT",
    "gn:dem":607,
    "gn:feature_class":"P",
    "gn:feature_code":"PPL",
    "gn:name":"Ferreccio",
    "gn:population":20,
    "gn:timezone":"Europe/Rome",
    "iso:country":"IT",
    "wof:name":"Ferreccio",
    "wof:placetype":"locality",
    "wof:population":20
},
  "geometry": {"coordinates":[9.32243,44.42094],"type":"Point"}
}