{
  "type": "Feature",
  "properties": {
    "gn:elevation":333,
    "gn:population":117,
    "iso:country":"IT",
    "name:bul_x_preferred":[
        "\u041f\u0438\u0435\u0434\u0438\u043f\u0430\u0442\u0435\u0440\u043d\u043e"
    ],
    "name:ceb_x_preferred":[
        "Piedipaterno"
    ],
    "name:deu_x_preferred":[
        "Piedipaterno"
    ],
    "name:eng_x_preferred":[
        "Piedipaterno"
    ],
    "name:fra_x_preferred":[
        "Piedipaterno"
    ],
    "name:hun_x_preferred":[
        "Piedipaterno"
    ],
    "name:ita_x_preferred":[
        "Piedipaterno"
    ],
    "name:nld_x_preferred":[
        "Piedipaterno"
    ],
    "name:srp_x_preferred":[
        "Piedipaterno"
    ],
    "name:unk_x_variant":[
        "Piedipaterno sul Nera"
    ],
    "qs:a0":"Italia",
    "qs:a1":"*Perugia",
    "qs:a1r":"0Umbria",
    "qs:adm0":"Italia",
    "qs:la_lc":"*",
    "qs:level":"locality",
    "qs:loc":"Piedipaterno",
    "qs:loc_alt":"Piedipaterno",
    "qs:pop":0,
    "qs:type":"buffered point",
    "wof:lang":[
        "ita"
    ],
    "wof:name":"Piedipaterno",
    "wof:placetype":"locality",
    "wof:population":117
},
  "geometry": {"coordinates":[12.86333,42.769439],"type":"Point"}
}