{
  "type": "Feature",
  "properties": {
    "gn:admin1_code":"18",
    "gn:admin2_code":"PG",
    "gn:admin3_code":"54030.0",
    "gn:asciiname":"Rignano",
    "gn:country_code":"IT",
    "gn:dem":407,
    "gn:feature_class":"P",
    "gn:feature_code":"PPL",
    "gn:name":"Rignano",
    "gn:population":34,
    "gn:timezone":"Europe/Rome",
    "iso:country":"IT",
    "wof:name":"Rignano",
    "wof:placetype":"locality",
    "wof:population":34
},
  "geometry": {"coordinates":[12.63729,42.8856],"type":"Point"}
}