{
  "type": "Feature",
  "properties": {
    "gn:admin1_code":"16",
    "gn:admin2_code":"LU",
    "gn:admin3_code":"46023.0",
    "gn:asciiname":"Cimocroce",
    "gn:country_code":"IT",
    "gn:dem":548,
    "gn:feature_class":"P",
    "gn:feature_code":"PPL",
    "gn:name":"Cimocroce",
    "gn:population":31,
    "gn:timezone":"Europe/Rome",
    "iso:country":"IT",
    "wof:name":"Cimocroce",
    "wof:placetype":"locality",
    "wof:population":31
},
  "geometry": {"coordinates":[10.30383,44.18565],"type":"Point"}
}