{
  "type": "Feature",
  "properties": {
    "gn:admin1_code":"20",
    "gn:admin2_code":"PD",
    "gn:admin3_code":"28086.0",
    "gn:asciiname":"Calgaro",
    "gn:country_code":"IT",
    "gn:dem":13,
    "gn:feature_class":"P",
    "gn:feature_code":"PPL",
    "gn:name":"Calgaro",
    "gn:population":30,
    "gn:timezone":"Europe/Rome",
    "iso:country":"IT",
    "wof:name":"Calgaro",
    "wof:placetype":"locality",
    "wof:population":30
},
  "geometry": {"coordinates":[11.77168,45.40295],"type":"Point"}
}