{
  "type": "Feature",
  "properties": {
    "gn:admin1_code":"9",
    "gn:admin2_code":"PV",
    "gn:admin3_code":"18115.0",
    "gn:asciiname":"Il Luogo",
    "gn:country_code":"IT",
    "gn:dem":67,
    "gn:feature_class":"P",
    "gn:feature_code":"PPL",
    "gn:name":"Il Luogo",
    "gn:population":13,
    "gn:timezone":"Europe/Rome",
    "iso:country":"IT",
    "wof:name":"Il Luogo",
    "wof:placetype":"locality",
    "wof:population":13
},
  "geometry": {"coordinates":[9.16523,45.06101],"type":"Point"}
}