{
  "type": "Feature",
  "properties": {
    "gn:admin1_code":"9",
    "gn:admin2_code":"PV",
    "gn:admin3_code":"18007.0",
    "gn:asciiname":"Spizziro",
    "gn:country_code":"IT",
    "gn:dem":299,
    "gn:feature_class":"P",
    "gn:feature_code":"PPL",
    "gn:name":"Spizzir\u00f2",
    "gn:population":27,
    "gn:timezone":"Europe/Rome",
    "iso:country":"IT",
    "name:und_x_variant":[
        "Spizzir\u00f2"
    ],
    "wof:name":"Spizziro",
    "wof:placetype":"locality",
    "wof:population":27
},
  "geometry": {"coordinates":[9.11367,44.83761],"type":"Point"}
}