{
  "type": "Feature",
  "properties": {
    "gn:admin1_code":"20.0",
    "gn:admin2_code":"VI",
    "gn:admin3_code":"24051.0",
    "gn:asciiname":"Grancare",
    "gn:country_code":"IT",
    "gn:dem":291,
    "gn:feature_class":"P",
    "gn:feature_code":"PPL",
    "gn:name":"Grancare",
    "gn:population":0,
    "gn:timezone":"Europe/Rome",
    "iso:country":"IT",
    "wof:name":"Grancare",
    "wof:placetype":"locality"
},
  "geometry": {"coordinates":[11.56667,45.46667],"type":"Point"}
}