{
  "type": "Feature",
  "properties": {
    "gn:admin1_code":"1.0",
    "gn:admin2_code":"AQ",
    "gn:admin3_code":"66096.0",
    "gn:asciiname":"Cappelle",
    "gn:country_code":"IT",
    "gn:dem":711,
    "gn:elevation":"707.0",
    "gn:feature_class":"P",
    "gn:feature_code":"PPL",
    "gn:name":"Cappelle",
    "gn:population":910,
    "gn:timezone":"Europe/Rome",
    "iso:country":"IT",
    "wof:name":"Cappelle",
    "wof:placetype":"locality",
    "wof:population":910
},
  "geometry": {"coordinates":[13.37997,42.0668],"type":"Point"}
}