{
  "type": "Feature",
  "properties": {
    "gn:admin1_code":"9",
    "gn:admin2_code":"BS",
    "gn:admin3_code":"17113.0",
    "gn:asciiname":"Terminoni",
    "gn:country_code":"IT",
    "gn:dem":90,
    "gn:feature_class":"P",
    "gn:feature_code":"PPL",
    "gn:name":"Terminoni",
    "gn:population":54,
    "gn:timezone":"Europe/Rome",
    "iso:country":"IT",
    "wof:name":"Terminoni",
    "wof:placetype":"locality",
    "wof:population":54
},
  "geometry": {"coordinates":[10.33538,45.40359],"type":"Point"}
}