{
  "type": "Feature",
  "properties": {
    "gn:admin1_code":"12",
    "gn:admin2_code":"TO",
    "gn:admin3_code":"1089.0",
    "gn:asciiname":"Dirotto-Sangonetto",
    "gn:country_code":"IT",
    "gn:dem":728,
    "gn:feature_class":"P",
    "gn:feature_code":"PPL",
    "gn:name":"Dirotto-Sangonetto",
    "gn:population":43,
    "gn:timezone":"Europe/Rome",
    "iso:country":"IT",
    "wof:name":"Dirotto-Sangonetto",
    "wof:placetype":"locality",
    "wof:population":43
},
  "geometry": {"coordinates":[7.27799,45.05112],"type":"Point"}
}