{
  "type": "Feature",
  "properties": {
    "gn:admin1_code":"1.0",
    "gn:admin2_code":"TE",
    "gn:admin3_code":"67028.0",
    "gn:asciiname":"Leognano",
    "gn:country_code":"IT",
    "gn:dem":261,
    "gn:elevation":"287.0",
    "gn:feature_class":"P",
    "gn:feature_code":"PPL",
    "gn:name":"Leognano",
    "gn:population":128,
    "gn:timezone":"Europe/Rome",
    "iso:country":"IT",
    "wof:name":"Leognano",
    "wof:placetype":"locality",
    "wof:population":128
},
  "geometry": {"coordinates":[13.67968,42.58275],"type":"Point"}
}