{
  "type": "Feature",
  "properties": {
    "gn:country":"IT",
    "gn:fcode":"PPLA3",
    "gn:population":139,
    "iso:country":"IT",
    "name:azb_x_preferred":[
        "\u0627\u06cc\u0631\u0645\u0627"
    ],
    "name:bul_x_preferred":[
        "\u0418\u0440\u043c\u0430"
    ],
    "name:ceb_x_preferred":[
        "Irma"
    ],
    "name:deu_x_preferred":[
        "Irma"
    ],
    "name:eng_x_preferred":[
        "Irma"
    ],
    "name:epo_x_preferred":[
        "Irma"
    ],
    "name:est_x_preferred":[
        "Irma"
    ],
    "name:eus_x_preferred":[
        "Irma"
    ],
    "name:fas_x_preferred":[
        "\u0627\u06cc\u0631\u0645\u0627"
    ],
    "name:fra_x_preferred":[
        "Irma"
    ],
    "name:hun_x_preferred":[
        "Irma"
    ],
    "name:hye_x_preferred":[
        "\u053b\u0580\u0574\u0561"
    ],
    "name:ita_x_preferred":[
        "Irma"
    ],
    "name:jpn_x_preferred":[
        "\u30a4\u30eb\u30de"
    ],
    "name:kaz_x_preferred":[
        "\u0418\u0440\u043c\u0430"
    ],
    "name:lat_x_preferred":[
        "Hirmum"
    ],
    "name:lmo_x_preferred":[
        "\u00ccrma"
    ],
    "name:msa_x_preferred":[
        "Irma"
    ],
    "name:nap_x_preferred":[
        "Irma"
    ],
    "name:nld_x_preferred":[
        "Irma"
    ],
    "name:pms_x_preferred":[
        "Irma"
    ],
    "name:pol_x_preferred":[
        "Irma"
    ],
    "name:por_x_preferred":[
        "Irma"
    ],
    "name:ron_x_preferred":[
        "Irma"
    ],
    "name:rus_x_preferred":[
        "\u0418\u0440\u043c\u0430"
    ],
    "name:scn_x_preferred":[
        "Irma"
    ],
    "name:spa_x_preferred":[
        "Irma"
    ],
    "name:srp_x_preferred":[
        "Irma"
    ],
    "name:tgl_x_preferred":[
        "Irma"
    ],
    "name:ukr_x_preferred":[
        "\u0406\u0440\u043c\u0430"
    ],
    "name:uzb_x_preferred":[
        "Irma"
    ],
    "name:vie_x_preferred":[
        "Irma"
    ],
    "name:vol_x_preferred":[
        "Irma"
    ],
    "name:war_x_preferred":[
        "Irma"
    ],
    "name:zho_x_preferred":[
        "\u4f0a\u5c14\u9a6c"
    ],
    "qs_pg:aaroncc":"IT",
    "qs_pg:gn_country":"IT",
    "qs_pg:gn_fcode":"PPLA3",
    "qs_pg:gn_pop":139,
    "qs_pg:name":"Irma",
    "qs_pg:name_adm0":"Italia",
    "qs_pg:name_adm1":"Lombardia",
    "qs_pg:photos_9r":0,
    "qs_pg:photos_sr":0,
    "qs_pg:pop_sr":1,
    "qs_pg:qs_pg_placetype":"locality",
    "qs_pg:qs_pg_placetype_gp":"Town",
    "qs_pg:woe_adm0":23424853,
    "woe:adm0_id":23424853,
    "woe:name_adm0":"Italia",
    "woe:name_adm1":"Lombardia",
    "woe:placetype":"Town",
    "wof:name":"Irma",
    "wof:placetype":"locality",
    "wof:population":113
},
  "geometry": {"coordinates":[10.28457,45.77129],"type":"Point"}
}