{
  "type": "Feature",
  "properties": {
    "gn:admin1_code":"7",
    "gn:admin2_code":"RI",
    "gn:admin3_code":"57059.0",
    "gn:asciiname":"Montegambero",
    "gn:country_code":"IT",
    "gn:dem":383,
    "gn:feature_class":"P",
    "gn:feature_code":"PPL",
    "gn:name":"Montegambero",
    "gn:population":102,
    "gn:timezone":"Europe/Rome",
    "iso:country":"IT",
    "wof:name":"Montegambero",
    "wof:placetype":"locality",
    "wof:population":102
},
  "geometry": {"coordinates":[12.86035,42.44074000000001],"type":"Point"}
}