{
  "type": "Feature",
  "properties": {
    "gn:admin1_code":"3",
    "gn:admin2_code":"VV",
    "gn:admin3_code":"102034.0",
    "gn:asciiname":"Commessaria",
    "gn:country_code":"IT",
    "gn:dem":439,
    "gn:feature_class":"P",
    "gn:feature_code":"PPL",
    "gn:name":"Commessaria",
    "gn:population":34,
    "gn:timezone":"Europe/Rome",
    "iso:country":"IT",
    "wof:name":"Commessaria",
    "wof:placetype":"locality",
    "wof:population":34
},
  "geometry": {"coordinates":[16.09689,38.64799],"type":"Point"}
}