{
  "type": "Feature",
  "properties": {
    "gn:admin1_code":"18",
    "gn:admin2_code":"PG",
    "gn:admin3_code":"54037.0",
    "gn:asciiname":"San Pietro",
    "gn:country_code":"IT",
    "gn:dem":248,
    "gn:feature_class":"P",
    "gn:feature_code":"PPL",
    "gn:name":"San Pietro",
    "gn:population":270,
    "gn:timezone":"Europe/Rome",
    "iso:country":"IT",
    "name:ceb_x_preferred":[
        "San Pietro"
    ],
    "name:deu_x_preferred":[
        "San Pietro"
    ],
    "name:epo_x_preferred":[
        "San Pietro"
    ],
    "name:fra_x_preferred":[
        "San Pietro"
    ],
    "name:ita_x_preferred":[
        "San Pietro"
    ],
    "name:pol_x_preferred":[
        "San Pietro"
    ],
    "name:por_x_preferred":[
        "San Pietro"
    ],
    "name:sco_x_preferred":[
        "San Pietro"
    ],
    "name:srp_x_preferred":[
        "San Pjetro"
    ],
    "name:swe_x_preferred":[
        "San Pietro"
    ],
    "wof:name":"San Pietro",
    "wof:placetype":"locality",
    "wof:population":270
},
  "geometry": {"coordinates":[12.17362,43.00895],"type":"Point"}
}