{
  "type": "Feature",
  "properties": {
    "gn:admin1_code":"20",
    "gn:admin2_code":"VI",
    "gn:admin3_code":"24057.0",
    "gn:asciiname":"Marchetti",
    "gn:country_code":"IT",
    "gn:dem":264,
    "gn:feature_class":"P",
    "gn:feature_code":"PPL",
    "gn:name":"Marchetti",
    "gn:population":52,
    "gn:timezone":"Europe/Rome",
    "iso:country":"IT",
    "name:cos_x_preferred":[
        "Marchetti"
    ],
    "name:ita_x_preferred":[
        "Marchetti"
    ],
    "wof:name":"Marchetti",
    "wof:placetype":"locality",
    "wof:population":52
},
  "geometry": {"coordinates":[11.66433,45.77617],"type":"Point"}
}