{
  "type": "Feature",
  "properties": {
    "gn:admin1_code":"16",
    "gn:admin2_code":"AR",
    "gn:admin3_code":"51003.0",
    "gn:asciiname":"Fresciano",
    "gn:country_code":"IT",
    "gn:dem":798,
    "gn:feature_class":"P",
    "gn:feature_code":"PPL",
    "gn:name":"Fresciano",
    "gn:population":73,
    "gn:timezone":"Europe/Rome",
    "iso:country":"IT",
    "wof:name":"Fresciano",
    "wof:placetype":"locality",
    "wof:population":73
},
  "geometry": {"coordinates":[12.13613,43.72637],"type":"Point"}
}