{
  "type": "Feature",
  "properties": {
    "gn:admin1_code":"18.0",
    "gn:admin2_code":"TR",
    "gn:admin3_code":"55033.0",
    "gn:asciiname":"Dunarobba",
    "gn:country_code":"IT",
    "gn:dem":441,
    "gn:elevation":"448.0",
    "gn:feature_class":"P",
    "gn:feature_code":"PPL",
    "gn:name":"Dunarobba",
    "gn:population":203,
    "gn:timezone":"Europe/Rome",
    "iso:country":"IT",
    "wof:name":"Dunarobba",
    "wof:placetype":"locality",
    "wof:population":203
},
  "geometry": {"coordinates":[12.45069,42.67082],"type":"Point"}
}