{
  "type": "Feature",
  "properties": {
    "gn:admin1_code":"6.0",
    "gn:admin2_code":"UD",
    "gn:admin3_code":"30076.0",
    "gn:asciiname":"Studena Bassa",
    "gn:country_code":"IT",
    "gn:dem":659,
    "gn:feature_class":"P",
    "gn:feature_code":"PPL",
    "gn:name":"Studena Bassa",
    "gn:population":67,
    "gn:timezone":"Europe/Rome",
    "iso:country":"IT",
    "wof:name":"Studena Bassa",
    "wof:placetype":"locality",
    "wof:population":67
},
  "geometry": {"coordinates":[13.2725,46.52083],"type":"Point"}
}