{
  "type": "Feature",
  "properties": {
    "gn:admin1_code":"1.0",
    "gn:admin2_code":"AQ",
    "gn:admin3_code":"66082.0",
    "gn:asciiname":"Colle Ciaccio",
    "gn:country_code":"IT",
    "gn:dem":1281,
    "gn:feature_class":"P",
    "gn:feature_code":"PPLL",
    "gn:name":"Colle Ciaccio",
    "gn:population":4,
    "gn:timezone":"Europe/Rome",
    "iso:country":"IT",
    "wof:name":"Colle Ciaccio",
    "wof:placetype":"locality",
    "wof:population":4
},
  "geometry": {"coordinates":[13.51969,42.21707],"type":"Point"}
}