{
  "type": "Feature",
  "properties": {
    "gn:admin1_code":"12",
    "gn:admin2_code":"VC",
    "gn:admin3_code":"2078.0",
    "gn:asciiname":"Casacce",
    "gn:country_code":"IT",
    "gn:dem":961,
    "gn:feature_class":"P",
    "gn:feature_code":"PPLL",
    "gn:name":"Casacce",
    "gn:population":10,
    "gn:timezone":"Europe/Rome",
    "iso:country":"IT",
    "wof:name":"Casacce",
    "wof:placetype":"locality",
    "wof:population":10
},
  "geometry": {"coordinates":[8.02821,45.81993],"type":"Point"}
}