{
  "type": "Feature",
  "properties": {
    "gn:admin1_code":"15",
    "gn:admin2_code":"PA",
    "gn:admin3_code":"82030.0",
    "gn:asciiname":"Cappuccini",
    "gn:country_code":"IT",
    "gn:dem":448,
    "gn:feature_class":"P",
    "gn:feature_code":"PPL",
    "gn:name":"Cappuccini",
    "gn:population":19,
    "gn:timezone":"Europe/Rome",
    "iso:country":"IT",
    "wof:name":"Cappuccini",
    "wof:placetype":"locality",
    "wof:population":19
},
  "geometry": {"coordinates":[13.56877,37.90005],"type":"Point"}
}