{
  "type": "Feature",
  "properties": {
    "gn:admin1_code":"7",
    "gn:admin2_code":"RI",
    "gn:admin3_code":"57059.0",
    "gn:asciiname":"Piani Sant'Elia",
    "gn:country_code":"IT",
    "gn:dem":387,
    "gn:feature_class":"P",
    "gn:feature_code":"PPL",
    "gn:name":"Piani Sant'Elia",
    "gn:population":161,
    "gn:timezone":"Europe/Rome",
    "iso:country":"IT",
    "wof:name":"Piani Sant'Elia",
    "wof:placetype":"locality",
    "wof:population":161
},
  "geometry": {"coordinates":[12.81527,42.38982],"type":"Point"}
}