{
  "type": "Feature",
  "properties": {
    "gn:admin1_code":"7",
    "gn:admin2_code":"LT",
    "gn:admin3_code":"59005.0",
    "gn:asciiname":"Zona Prod. Meccano A.-Slim-Piscina",
    "gn:country_code":"IT",
    "gn:dem":40,
    "gn:feature_class":"P",
    "gn:feature_code":"PPL",
    "gn:name":"Zona Prod. Meccano A.-Slim-Piscina",
    "gn:population":52,
    "gn:timezone":"Europe/Rome",
    "iso:country":"IT",
    "wof:name":"Zona Prod. Meccano A.-Slim-Piscina",
    "wof:placetype":"locality",
    "wof:population":52
},
  "geometry": {"coordinates":[12.79394,41.54302],"type":"Point"}
}