{
  "type": "Feature",
  "properties": {
    "gn:admin1_code":"5.0",
    "gn:admin2_code":"RE",
    "gn:admin3_code":"35046.0",
    "gn:asciiname":"Ventasso",
    "gn:country_code":"IT",
    "gn:dem":1307,
    "gn:feature_class":"P",
    "gn:feature_code":"PPL",
    "gn:name":"Ventasso",
    "gn:population":10,
    "gn:timezone":"Europe/Rome",
    "iso:country":"IT",
    "name:deu_x_preferred":[
        "Ventasso"
    ],
    "name:epo_x_preferred":[
        "Ventasso"
    ],
    "name:fin_x_preferred":[
        "Ventasso"
    ],
    "name:fra_x_preferred":[
        "Ventasso"
    ],
    "name:ita_x_preferred":[
        "Ventasso"
    ],
    "name:jpn_x_preferred":[
        "\u30f4\u30a7\u30f3\u30bf\u30c3\u30bd"
    ],
    "name:lat_x_preferred":[
        "Ventassum"
    ],
    "name:ukr_x_preferred":[
        "\u0412\u0435\u043d\u0442\u0430\u0441\u0441\u043e"
    ],
    "wof:name":"Ventasso",
    "wof:placetype":"locality",
    "wof:population":10
},
  "geometry": {"coordinates":[10.27471,44.3873],"type":"Point"}
}