{
  "type": "Feature",
  "properties": {
    "gn:admin1_code":"1.0",
    "gn:admin2_code":"AQ",
    "gn:admin3_code":"66060.0",
    "gn:asciiname":"Frasca",
    "gn:country_code":"IT",
    "gn:dem":570,
    "gn:feature_class":"P",
    "gn:feature_code":"PPLL",
    "gn:name":"Frasca",
    "gn:population":2,
    "gn:timezone":"Europe/Rome",
    "iso:country":"IT",
    "wof:name":"Frasca",
    "wof:placetype":"locality",
    "wof:population":2
},
  "geometry": {"coordinates":[13.73459,42.30588],"type":"Point"}
}