{
  "type": "Feature",
  "properties": {
    "gn:admin1_code":"3",
    "gn:admin2_code":"CS",
    "gn:admin3_code":"78155.0",
    "gn:asciiname":"San Michele",
    "gn:country_code":"IT",
    "gn:dem":315,
    "gn:feature_class":"P",
    "gn:feature_code":"PPL",
    "gn:name":"San Michele",
    "gn:population":56,
    "gn:timezone":"Europe/Rome",
    "iso:country":"IT",
    "wof:name":"San Michele",
    "wof:placetype":"locality",
    "wof:population":56
},
  "geometry": {"coordinates":[16.27717,39.31821],"type":"Point"}
}