{
  "type": "Feature",
  "properties": {
    "gn:admin1_code":"8",
    "gn:admin2_code":"GE",
    "gn:admin3_code":"10050.0",
    "gn:asciiname":"Fontanasse",
    "gn:country_code":"IT",
    "gn:dem":890,
    "gn:feature_class":"P",
    "gn:feature_code":"PPLL",
    "gn:name":"Fontanasse",
    "gn:population":7,
    "gn:timezone":"Europe/Rome",
    "iso:country":"IT",
    "wof:name":"Fontanasse",
    "wof:placetype":"locality",
    "wof:population":7
},
  "geometry": {"coordinates":[9.19967,44.54126],"type":"Point"}
}