{
  "type": "Feature",
  "properties": {
    "gn:admin1_code":"5.0",
    "gn:admin2_code":"RA",
    "gn:admin3_code":"39008.0",
    "gn:asciiname":"Tarabina",
    "gn:country_code":"IT",
    "gn:dem":3,
    "gn:feature_class":"P",
    "gn:feature_code":"PPL",
    "gn:name":"Tarabina",
    "gn:population":0,
    "gn:timezone":"Europe/Rome",
    "iso:country":"IT",
    "wof:name":"Tarabina",
    "wof:placetype":"locality"
},
  "geometry": {"coordinates":[11.81667,44.53333],"type":"Point"}
}