{
  "type": "Feature",
  "properties": {
    "gn:admin1_code":"16.0",
    "gn:admin2_code":"FI",
    "gn:admin3_code":"48052.0",
    "gn:asciiname":"Palazzolo",
    "gn:country_code":"IT",
    "gn:dem":177,
    "gn:feature_class":"P",
    "gn:feature_code":"PPL",
    "gn:name":"Palazzolo",
    "gn:population":401,
    "gn:timezone":"Europe/Rome",
    "iso:country":"IT",
    "name:ceb_x_preferred":[
        "Palazzolo"
    ],
    "name:deu_x_preferred":[
        "Palazzolo"
    ],
    "name:fra_x_preferred":[
        "Palazzolo"
    ],
    "name:ita_x_preferred":[
        "Palazzolo"
    ],
    "name:pms_x_preferred":[
        "Palazzolo"
    ],
    "name:por_x_preferred":[
        "Palazzolo"
    ],
    "name:sco_x_preferred":[
        "Palazzolo"
    ],
    "name:srp_x_preferred":[
        "Palacolo"
    ],
    "name:swe_x_preferred":[
        "Palazzolo"
    ],
    "wof:name":"Palazzolo",
    "wof:placetype":"locality",
    "wof:population":401
},
  "geometry": {"coordinates":[11.43573,43.69029000000001],"type":"Point"}
}