{
  "type": "Feature",
  "properties": {
    "gn:admin1_code":"12",
    "gn:admin2_code":"VC",
    "gn:admin3_code":"2004.0",
    "gn:asciiname":"Massarotta",
    "gn:country_code":"IT",
    "gn:dem":226,
    "gn:feature_class":"P",
    "gn:feature_code":"PPL",
    "gn:name":"Massarotta",
    "gn:population":76,
    "gn:timezone":"Europe/Rome",
    "iso:country":"IT",
    "wof:name":"Massarotta",
    "wof:placetype":"locality",
    "wof:population":76
},
  "geometry": {"coordinates":[8.09807,45.36276],"type":"Point"}
}