{
  "type": "Feature",
  "properties": {
    "gn:admin1_code":"12",
    "gn:admin2_code":"TO",
    "gn:admin3_code":"1086.0",
    "gn:asciiname":"Carbone",
    "gn:country_code":"IT",
    "gn:dem":344,
    "gn:feature_class":"P",
    "gn:feature_code":"PPL",
    "gn:name":"Carbone",
    "gn:population":34,
    "gn:timezone":"Europe/Rome",
    "iso:country":"IT",
    "wof:name":"Carbone",
    "wof:placetype":"locality",
    "wof:population":34
},
  "geometry": {"coordinates":[7.57532,45.21787],"type":"Point"}
}