{
  "type": "Feature",
  "properties": {
    "gn:admin1_code":"17.0",
    "gn:admin2_code":"BZ",
    "gn:admin3_code":"21059.0",
    "gn:asciiname":"Madonna di Petralba",
    "gn:cc2":"IT",
    "gn:country_code":"IT",
    "gn:dem":1485,
    "gn:feature_class":"P",
    "gn:feature_code":"PPL",
    "gn:name":"Madonna di Petralba",
    "gn:population":0,
    "gn:timezone":"Europe/Rome",
    "iso:country":"IT",
    "name:und_x_variant":[
        "Madonna di Petrelba",
        "Madonna di Petralba"
    ],
    "wof:name":"Madonna di Petralba",
    "wof:placetype":"locality"
},
  "geometry": {"coordinates":[11.41667,46.38333],"type":"Point"}
}