{
  "type": "Feature",
  "properties": {
    "gn:admin1_code":"20",
    "gn:admin2_code":"VI",
    "gn:admin3_code":"24055.0",
    "gn:asciiname":"Tirondolo",
    "gn:country_code":"IT",
    "gn:dem":96,
    "gn:feature_class":"P",
    "gn:feature_code":"PPL",
    "gn:name":"Tirondolo",
    "gn:population":45,
    "gn:timezone":"Europe/Rome",
    "iso:country":"IT",
    "wof:name":"Tirondolo",
    "wof:placetype":"locality",
    "wof:population":45
},
  "geometry": {"coordinates":[11.41465,45.63066],"type":"Point"}
}