{
  "type": "Feature",
  "properties": {
    "gn:admin1_code":"20.0",
    "gn:admin2_code":"VI",
    "gn:admin3_code":"24034.0",
    "gn:asciiname":"Vigolo",
    "gn:country_code":"IT",
    "gn:dem":466,
    "gn:elevation":"457.0",
    "gn:feature_class":"P",
    "gn:feature_code":"PPL",
    "gn:name":"Vigolo",
    "gn:population":23,
    "gn:timezone":"Europe/Rome",
    "iso:country":"IT",
    "name:bel_x_preferred":[
        "\u0412\u0456\u0433\u043e\u043b\u0430"
    ],
    "name:ceb_x_preferred":[
        "Vigolo"
    ],
    "name:deu_x_preferred":[
        "Vigolo"
    ],
    "name:epo_x_preferred":[
        "Vigolo"
    ],
    "name:eus_x_preferred":[
        "Vigolo"
    ],
    "name:fra_x_preferred":[
        "Vigolo"
    ],
    "name:hun_x_preferred":[
        "Vigolo"
    ],
    "name:hye_x_preferred":[
        "\u054e\u056b\u0563\u0578\u056c\u0578"
    ],
    "name:ina_x_preferred":[
        "Vigolo"
    ],
    "name:ita_x_preferred":[
        "Vigolo"
    ],
    "name:jpn_x_preferred":[
        "\u30f4\u30a3\u30fc\u30b4\u30ed"
    ],
    "name:kaz_x_preferred":[
        "\u0412\u0438\u0433\u043e\u043b\u043e"
    ],
    "name:lat_x_preferred":[
        "Viculus Tabernulae"
    ],
    "name:lmo_x_preferred":[
        "\u00ccgol"
    ],
    "name:msa_x_preferred":[
        "Vigolo"
    ],
    "name:nap_x_preferred":[
        "Vigolo"
    ],
    "name:nld_x_preferred":[
        "Vigolo"
    ],
    "name:pms_x_preferred":[
        "Vigolo"
    ],
    "name:pol_x_preferred":[
        "Vigolo"
    ],
    "name:por_x_preferred":[
        "Vigolo"
    ],
    "name:ron_x_preferred":[
        "Vigolo"
    ],
    "name:rus_x_preferred":[
        "\u0412\u0438\u0433\u043e\u043b\u043e"
    ],
    "name:scn_x_preferred":[
        "Vigolo"
    ],
    "name:spa_x_preferred":[
        "Vigolo"
    ],
    "name:srp_x_preferred":[
        "\u0412\u0438\u0433\u043e\u043b\u043e"
    ],
    "name:tgl_x_preferred":[
        "Vigolo"
    ],
    "name:ukr_x_preferred":[
        "\u0412\u0456\u0433\u043e\u043b\u043e"
    ],
    "name:uzb_x_preferred":[
        "Vigolo"
    ],
    "name:vie_x_preferred":[
        "Vigolo"
    ],
    "name:vol_x_preferred":[
        "Vigolo"
    ],
    "name:war_x_preferred":[
        "Vigolo"
    ],
    "name:zho_x_preferred":[
        "\u7ef4\u6208\u6d1b"
    ],
    "wof:name":"Vigolo",
    "wof:placetype":"locality",
    "wof:population":23
},
  "geometry": {"coordinates":[11.34256,45.63042],"type":"Point"}
}