{
  "type": "Feature",
  "properties": {
    "gn:admin1_code":"12",
    "gn:admin2_code":"AL",
    "gn:admin3_code":"6017.0",
    "gn:asciiname":"Croce",
    "gn:country_code":"IT",
    "gn:dem":415,
    "gn:feature_class":"P",
    "gn:feature_code":"PPL",
    "gn:name":"Croce",
    "gn:population":14,
    "gn:timezone":"Europe/Rome",
    "iso:country":"IT",
    "wof:name":"Croce",
    "wof:placetype":"locality",
    "wof:population":14
},
  "geometry": {"coordinates":[8.36667,44.68364],"type":"Point"}
}