{
  "type": "Feature",
  "properties": {
    "gn:admin1_code":"19.0",
    "gn:admin2_code":"AO",
    "gn:admin3_code":"7066.0",
    "gn:asciiname":"Thouraz di Sopra",
    "gn:country_code":"IT",
    "gn:dem":1667,
    "gn:feature_class":"P",
    "gn:feature_code":"PPLL",
    "gn:name":"Thouraz di Sopra",
    "gn:population":2,
    "gn:timezone":"Europe/Rome",
    "iso:country":"IT",
    "wof:name":"Thouraz di Sopra",
    "wof:placetype":"locality",
    "wof:population":2
},
  "geometry": {"coordinates":[7.24758,45.74137],"type":"Point"}
}