{
  "type": "Feature",
  "properties": {
    "gn:admin1_code":"9",
    "gn:admin2_code":"BG",
    "gn:admin3_code":"16200.0",
    "gn:asciiname":"Cerrete",
    "gn:country_code":"IT",
    "gn:dem":577,
    "gn:feature_class":"P",
    "gn:feature_code":"PPL",
    "gn:name":"Cerrete",
    "gn:population":57,
    "gn:timezone":"Europe/Rome",
    "iso:country":"IT",
    "wof:name":"Cerrete",
    "wof:placetype":"locality",
    "wof:population":57
},
  "geometry": {"coordinates":[10.04518,45.79667],"type":"Point"}
}