{
  "type": "Feature",
  "properties": {
    "gn:admin1_code":"10",
    "gn:admin2_code":"MC",
    "gn:admin3_code":"43012.0",
    "gn:asciiname":"San Faustino",
    "gn:country_code":"IT",
    "gn:dem":122,
    "gn:feature_class":"P",
    "gn:feature_code":"PPL",
    "gn:name":"San Faustino",
    "gn:population":63,
    "gn:timezone":"Europe/Rome",
    "iso:country":"IT",
    "wof:name":"San Faustino",
    "wof:placetype":"locality",
    "wof:population":63
},
  "geometry": {"coordinates":[13.30936,43.39583],"type":"Point"}
}