{
  "type": "Feature",
  "properties": {
    "gn:admin1_code":"3",
    "gn:admin2_code":"RC",
    "gn:admin3_code":"80093.0",
    "gn:asciiname":"Monastria",
    "gn:country_code":"IT",
    "gn:dem":190,
    "gn:feature_class":"P",
    "gn:feature_code":"PPL",
    "gn:name":"Monastria",
    "gn:population":21,
    "gn:timezone":"Europe/Rome",
    "iso:country":"IT",
    "wof:name":"Monastria",
    "wof:placetype":"locality",
    "wof:population":21
},
  "geometry": {"coordinates":[16.0248,38.38637],"type":"Point"}
}