{
  "type": "Feature",
  "properties": {
    "gn:admin1_code":"16",
    "gn:admin2_code":"FI",
    "gn:admin3_code":"48015.0",
    "gn:asciiname":"Poggio Gherardo",
    "gn:country_code":"IT",
    "gn:dem":106,
    "gn:feature_class":"P",
    "gn:feature_code":"PPL",
    "gn:name":"Poggio Gherardo",
    "gn:population":171,
    "gn:timezone":"Europe/Rome",
    "iso:country":"IT",
    "wof:name":"Poggio Gherardo",
    "wof:placetype":"locality",
    "wof:population":171
},
  "geometry": {"coordinates":[11.30341,43.78378],"type":"Point"}
}