{
  "type": "Feature",
  "properties": {
    "gn:admin1_code":"3",
    "gn:admin2_code":"KR",
    "gn:admin3_code":"101013.0",
    "gn:asciiname":"Ventrarola",
    "gn:country_code":"IT",
    "gn:dem":153,
    "gn:feature_class":"P",
    "gn:feature_code":"PPL",
    "gn:name":"Ventrarola",
    "gn:population":37,
    "gn:timezone":"Europe/Rome",
    "iso:country":"IT",
    "wof:name":"Ventrarola",
    "wof:placetype":"locality",
    "wof:population":37
},
  "geometry": {"coordinates":[17.07936,38.97753],"type":"Point"}
}