{
  "type": "Feature",
  "properties": {
    "gn:gn_country":"IT",
    "gn:gn_fcode":"PPLA3",
    "gn:gn_pop":2082,
    "gn:population":2082,
    "iso:country":"IT",
    "name:arm_x_preferred":[
        "\u0549\u0565\u0576\u0561\u057f\u0578 \u054d\u0578\u057a\u0580\u0561"
    ],
    "name:baq_x_preferred":[
        "Cenate Sopra"
    ],
    "name:cat_x_preferred":[
        "Cenate Sopra"
    ],
    "name:chi_x_preferred":[
        "\u5207\u7eb3\u6cf0\u7d22\u666e\u62c9"
    ],
    "name:dut_x_preferred":[
        "Cenate Sopra"
    ],
    "name:eng_x_preferred":[
        "Cenate Sopra"
    ],
    "name:epo_x_preferred":[
        "Cenate Sopra"
    ],
    "name:fre_x_preferred":[
        "Cenate Sopra"
    ],
    "name:ger_x_preferred":[
        "Cenate Sopra"
    ],
    "name:hun_x_preferred":[
        "Cenate Sopra"
    ],
    "name:ina_x_preferred":[
        "Cenate Sopra"
    ],
    "name:ita_x_preferred":[
        "Cenate Sopra"
    ],
    "name:jpn_x_preferred":[
        "\u30c1\u30a7\u30ca\u30fc\u30c6\u30fb\u30bd\u30d7\u30e9"
    ],
    "name:kaz_x_preferred":[
        "\u0427\u0435\u043d\u0430\u0442\u043e-\u0421\u043e\u043f\u0440\u0430"
    ],
    "name:lat_x_preferred":[
        "Cenatum Sancti Leonis"
    ],
    "name:lmo_x_preferred":[
        "Cen\u00e0t Sura"
    ],
    "name:may_x_preferred":[
        "Cenate Sopra"
    ],
    "name:nap_x_preferred":[
        "Cenate Sopra"
    ],
    "name:oci_x_preferred":[
        "Cenate Sopra"
    ],
    "name:pms_x_preferred":[
        "Cenate Sopra"
    ],
    "name:pol_x_preferred":[
        "Cenate Sopra"
    ],
    "name:por_x_preferred":[
        "Cenate Sopra"
    ],
    "name:rum_x_preferred":[
        "Cenate Sopra"
    ],
    "name:rus_x_preferred":[
        "\u0427\u0435\u043d\u0430\u0442\u043e-\u0421\u043e\u043f\u0440\u0430"
    ],
    "name:scn_x_preferred":[
        "Cenate Sopra"
    ],
    "name:spa_x_preferred":[
        "Cenate Sopra"
    ],
    "name:srp_x_preferred":[
        "Cenate Sopra"
    ],
    "name:tgl_x_preferred":[
        "Cenate Sopra"
    ],
    "name:ukr_x_preferred":[
        "\u0427\u0435\u043d\u0430\u0442\u0435-\u0421\u043e\u043f\u0440\u0430"
    ],
    "name:uzb_x_preferred":[
        "Cenate Sopra"
    ],
    "name:vie_x_preferred":[
        "Cenate Sopra"
    ],
    "name:vol_x_preferred":[
        "Cenate Sopra"
    ],
    "name:war_x_preferred":[
        "Cenate Sopra"
    ],
    "qs_pg:aaroncc":"IT",
    "qs_pg:gn_country":"IT",
    "qs_pg:gn_fcode":"PPLA3",
    "qs_pg:gn_pop":2082,
    "qs_pg:name":"Cenate Sopra",
    "qs_pg:name_adm0":"Italia",
    "qs_pg:name_adm1":"Lombardia",
    "qs_pg:photos_9r":0,
    "qs_pg:photos_sr":0,
    "qs_pg:pop_sr":4,
    "qs_pg:qs_pg_placetype":"locality",
    "qs_pg:qs_pg_placetype_gp":"Town",
    "qs_pg:woe_adm0":23424853,
    "woe:adm0_id":23424853,
    "woe:name_adm0":"Italia",
    "woe:name_adm1":"Lombardia",
    "woe:placetype":"Town",
    "wof:name":"Cenate Sopra",
    "wof:placetype":"locality",
    "wof:population":2082
},
  "geometry": {"coordinates":[9.82216,45.71298],"type":"Point"}
}