{
  "type": "Feature",
  "properties": {
    "gn:admin1_code":"5.0",
    "gn:admin2_code":"RN",
    "gn:admin3_code":"99011.0",
    "gn:asciiname":"Abbazia del Moscolo",
    "gn:country_code":"IT",
    "gn:dem":63,
    "gn:feature_class":"P",
    "gn:feature_code":"PPL",
    "gn:name":"Abbazia del Moscolo",
    "gn:population":77,
    "gn:timezone":"Europe/Rome",
    "iso:country":"IT",
    "wof:name":"Abbazia del Moscolo",
    "wof:placetype":"locality",
    "wof:population":77
},
  "geometry": {"coordinates":[12.66548,43.92081],"type":"Point"}
}