{
  "type": "Feature",
  "properties": {
    "gn:admin1_code":"8.0",
    "gn:admin2_code":"SV",
    "gn:admin3_code":"9040.0",
    "gn:asciiname":"Piavata",
    "gn:country_code":"IT",
    "gn:dem":687,
    "gn:feature_class":"P",
    "gn:feature_code":"PPL",
    "gn:name":"Piavata",
    "gn:population":0,
    "gn:timezone":"Europe/Rome",
    "iso:country":"IT",
    "wof:name":"Piavata",
    "wof:placetype":"locality"
},
  "geometry": {"coordinates":[8.15,44.31667],"type":"Point"}
}