{
  "type": "Feature",
  "properties": {
    "gn:admin1_code":"20.0",
    "gn:admin2_code":"VR",
    "gn:admin3_code":"23020.0",
    "gn:asciiname":"Nogara II",
    "gn:country_code":"IT",
    "gn:dem":10,
    "gn:feature_class":"P",
    "gn:feature_code":"PPL",
    "gn:name":"Nogara II",
    "gn:population":38,
    "gn:timezone":"Europe/Rome",
    "iso:country":"IT",
    "wof:name":"Nogara II",
    "wof:placetype":"locality",
    "wof:population":38
},
  "geometry": {"coordinates":[11.44248,45.07956],"type":"Point"}
}