{
  "type": "Feature",
  "properties": {
    "gn:admin1_code":"7.0",
    "gn:admin2_code":"RI",
    "gn:admin3_code":"57002.0",
    "gn:asciiname":"Forcelle",
    "gn:country_code":"IT",
    "gn:dem":1144,
    "gn:elevation":"1146.0",
    "gn:feature_class":"P",
    "gn:feature_code":"PPL",
    "gn:name":"Forcelle",
    "gn:population":13,
    "gn:timezone":"Europe/Rome",
    "iso:country":"IT",
    "wof:name":"Forcelle",
    "wof:placetype":"locality",
    "wof:population":13
},
  "geometry": {"coordinates":[13.19753,42.64419],"type":"Point"}
}