{
  "type": "Feature",
  "properties": {
    "gn:admin1_code":"1.0",
    "gn:admin2_code":"TE",
    "gn:admin3_code":"67045.0",
    "gn:asciiname":"Flammignano",
    "gn:cc2":"IT",
    "gn:country_code":"IT",
    "gn:dem":580,
    "gn:elevation":"599.0",
    "gn:feature_class":"P",
    "gn:feature_code":"PPL",
    "gn:name":"Flammignano",
    "gn:population":18,
    "gn:timezone":"Europe/Rome",
    "iso:country":"IT",
    "name:und_x_variant":[
        "Flamignano",
        "Flammignano"
    ],
    "wof:name":"Flammignano",
    "wof:placetype":"locality",
    "wof:population":18
},
  "geometry": {"coordinates":[13.6255,42.5455],"type":"Point"}
}