{
  "type": "Feature",
  "properties": {
    "gn:admin1_code":"10",
    "gn:admin2_code":"PU",
    "gn:admin3_code":"41069.0",
    "gn:asciiname":"Bargni",
    "gn:country_code":"IT",
    "gn:dem":263,
    "gn:feature_class":"P",
    "gn:feature_code":"PPL",
    "gn:name":"Bargni",
    "gn:population":11,
    "gn:timezone":"Europe/Rome",
    "iso:country":"IT",
    "wof:name":"Bargni",
    "wof:placetype":"locality",
    "wof:population":11
},
  "geometry": {"coordinates":[12.85367,43.74975],"type":"Point"}
}