{
  "type": "Feature",
  "properties": {
    "gn:admin1_code":"9",
    "gn:admin2_code":"BS",
    "gn:admin3_code":"17029.0",
    "gn:asciiname":"Garzetta",
    "gn:country_code":"IT",
    "gn:dem":176,
    "gn:feature_class":"P",
    "gn:feature_code":"PPL",
    "gn:name":"Garzetta",
    "gn:population":25,
    "gn:timezone":"Europe/Rome",
    "iso:country":"IT",
    "wof:name":"Garzetta",
    "wof:placetype":"locality",
    "wof:population":25
},
  "geometry": {"coordinates":[10.24687,45.55871],"type":"Point"}
}