{
  "type": "Feature",
  "properties": {
    "gn:admin1_code":"12.0",
    "gn:admin2_code":"BI",
    "gn:admin3_code":"96023.0",
    "gn:asciiname":"Santa Maria",
    "gn:country_code":"IT",
    "gn:dem":481,
    "gn:feature_class":"P",
    "gn:feature_code":"PPL",
    "gn:name":"Santa Maria",
    "gn:population":19,
    "gn:timezone":"Europe/Rome",
    "iso:country":"IT",
    "wof:name":"Santa Maria",
    "wof:placetype":"locality",
    "wof:population":19
},
  "geometry": {"coordinates":[8.23994,45.64364000000001],"type":"Point"}
}