{
  "type": "Feature",
  "properties": {
    "gn:admin1_code":"12.0",
    "gn:admin2_code":"BI",
    "gn:admin3_code":"96023.0",
    "gn:asciiname":"Santa Maria",
    "gn:country_code":"IT",
    "gn:dem":481,
    "gn:feature_class":"P",
    "gn:feature_code":"PPL",
    "gn:name":"Santa Maria",
    "gn:population":19,
    "gn:timezone":"Europe/Rome",
    "iso:country":"IT",
    "name:als_x_preferred":[
        "Santa Maria"
    ],
    "name:bre_x_preferred":[
        "Santa Maria"
    ],
    "name:bul_x_preferred":[
        "\u0421\u0430\u043d\u0442\u0430 \u041c\u0430\u0440\u0438\u044f"
    ],
    "name:cat_x_preferred":[
        "Santa Maria"
    ],
    "name:ceb_x_preferred":[
        "Santa Maria"
    ],
    "name:ces_x_preferred":[
        "Santa Maria"
    ],
    "name:deu_x_preferred":[
        "Santa Maria"
    ],
    "name:epo_x_preferred":[
        "Santa Maria"
    ],
    "name:est_x_preferred":[
        "Santa Maria"
    ],
    "name:eus_x_preferred":[
        "Santa Maria"
    ],
    "name:fas_x_preferred":[
        "\u0633\u0627\u0646\u062a\u0627 \u0645\u0627\u0631\u06cc\u0627"
    ],
    "name:fin_x_preferred":[
        "Santa Maria"
    ],
    "name:fra_x_preferred":[
        "Santa Maria"
    ],
    "name:heb_x_preferred":[
        "\u05e1\u05e0\u05d8\u05d4 \u05de\u05e8\u05d9\u05d4"
    ],
    "name:hun_x_preferred":[
        "Santa Maria"
    ],
    "name:ilo_x_preferred":[
        "Santa Maria"
    ],
    "name:ind_x_preferred":[
        "Santa Maria"
    ],
    "name:ita_x_preferred":[
        "Santa Maria"
    ],
    "name:jpn_x_preferred":[
        "\u30b5\u30f3\u30bf\u30de\u30ea\u30a2"
    ],
    "name:kat_x_preferred":[
        "\u10e1\u10d0\u10dc\u10e2\u10d0-\u10db\u10d0\u10e0\u10d8\u10d0"
    ],
    "name:kor_x_preferred":[
        "\uc0b0\ud0c0\ub9c8\ub9ac\uc544"
    ],
    "name:lit_x_preferred":[
        "Santa Marija"
    ],
    "name:nld_x_preferred":[
        "Santa Maria"
    ],
    "name:nor_x_preferred":[
        "Santa Maria"
    ],
    "name:pol_x_preferred":[
        "Santa Maria"
    ],
    "name:por_x_preferred":[
        "Santa Maria"
    ],
    "name:ron_x_preferred":[
        "Santa Maria"
    ],
    "name:rus_x_preferred":[
        "\u0421\u0430\u043d\u0442\u0430-\u041c\u0430\u0440\u0438\u044f"
    ],
    "name:sco_x_preferred":[
        "Santa Maria"
    ],
    "name:slk_x_preferred":[
        "Santa Mar\u00eda"
    ],
    "name:srp_x_preferred":[
        "\u0421\u0430\u043d\u0442\u0430 \u041c\u0430\u0440\u0438\u0458\u0430"
    ],
    "name:swe_x_preferred":[
        "Santa Maria"
    ],
    "name:tgl_x_preferred":[
        "Santa Maria"
    ],
    "name:tur_x_preferred":[
        "Santa Maria"
    ],
    "name:ukr_x_preferred":[
        "\u0421\u0430\u043d\u0442\u0430-\u041c\u0430\u0440\u0456\u0430"
    ],
    "name:ukr_x_variant":[
        "\u0421\u0430\u043d\u0442\u0430-\u041c\u0430\u0440\u0456\u044f"
    ],
    "name:urd_x_preferred":[
        "\u0633\u0627\u0646\u062a\u0627 \u0645\u0627\u0631\u06cc\u0627"
    ],
    "name:vie_x_preferred":[
        "S\u00f4ng Santa Maria"
    ],
    "name:vol_x_preferred":[
        "Santa Maria"
    ],
    "name:war_x_preferred":[
        "Santa Maria"
    ],
    "name:zho_x_preferred":[
        "\u8056\u99ac\u5229\u4e9e"
    ],
    "wof:name":"Santa Maria",
    "wof:placetype":"locality",
    "wof:population":19
},
  "geometry": {"coordinates":[8.23994,45.64364],"type":"Point"}
}