{
  "type": "Feature",
  "properties": {
    "gn:admin1_code":"17",
    "gn:admin2_code":"TN",
    "gn:admin3_code":"22205.0",
    "gn:asciiname":"Celva",
    "gn:country_code":"IT",
    "gn:dem":658,
    "gn:feature_class":"P",
    "gn:feature_code":"PPL",
    "gn:name":"Celva",
    "gn:population":24,
    "gn:timezone":"Europe/Rome",
    "iso:country":"IT",
    "wof:name":"Celva",
    "wof:placetype":"locality",
    "wof:population":24
},
  "geometry": {"coordinates":[11.17614,46.0719],"type":"Point"}
}