{
  "type": "Feature",
  "properties": {
    "gn:admin1_code":"20",
    "gn:admin2_code":"VE",
    "gn:admin3_code":"27015.0",
    "gn:asciiname":"Ronche",
    "gn:country_code":"IT",
    "gn:dem":1,
    "gn:feature_class":"P",
    "gn:feature_code":"PPL",
    "gn:name":"Ronche",
    "gn:population":41,
    "gn:timezone":"Europe/Rome",
    "iso:country":"IT",
    "wof:name":"Ronche",
    "wof:placetype":"locality",
    "wof:population":41
},
  "geometry": {"coordinates":[12.49976,45.65067],"type":"Point"}
}