{
  "type": "Feature",
  "properties": {
    "gn:admin1_code":"20.0",
    "gn:admin2_code":"VI",
    "gn:admin3_code":"24074.0",
    "gn:asciiname":"Spinosa Nord",
    "gn:country_code":"IT",
    "gn:dem":13,
    "gn:feature_class":"P",
    "gn:feature_code":"PPL",
    "gn:name":"Spinosa Nord",
    "gn:population":23,
    "gn:timezone":"Europe/Rome",
    "iso:country":"IT",
    "wof:name":"Spinosa Nord",
    "wof:placetype":"locality",
    "wof:population":23
},
  "geometry": {"coordinates":[11.55212,45.30768],"type":"Point"}
}