{
  "type": "Feature",
  "properties": {
    "gn:admin1_code":"12",
    "gn:admin2_code":"AT",
    "gn:admin3_code":"5087.0",
    "gn:asciiname":"Miravalle",
    "gn:country_code":"IT",
    "gn:dem":219,
    "gn:feature_class":"P",
    "gn:feature_code":"PPLL",
    "gn:name":"Miravalle",
    "gn:population":9,
    "gn:timezone":"Europe/Rome",
    "iso:country":"IT",
    "wof:name":"Miravalle",
    "wof:placetype":"locality",
    "wof:population":9
},
  "geometry": {"coordinates":[8.27035,44.94704],"type":"Point"}
}