{
  "type": "Feature",
  "properties": {
    "gn:admin1_code":"15",
    "gn:admin2_code":"TP",
    "gn:admin3_code":"81014.0",
    "gn:asciiname":"Localita Cimillia",
    "gn:country_code":"IT",
    "gn:dem":54,
    "gn:feature_class":"P",
    "gn:feature_code":"PPLL",
    "gn:name":"Localit\u00e0 Cimillia",
    "gn:population":7,
    "gn:timezone":"Europe/Rome",
    "iso:country":"IT",
    "name:und_x_variant":[
        "Localit\u00e0 Cimillia"
    ],
    "wof:name":"Localita Cimillia",
    "wof:placetype":"locality",
    "wof:population":7
},
  "geometry": {"coordinates":[11.93846,36.79781],"type":"Point"}
}