{
  "type": "Feature",
  "properties": {
    "gn:admin1_code":"8",
    "gn:admin2_code":"GE",
    "gn:admin3_code":"10041.0",
    "gn:asciiname":"Carpeneto",
    "gn:country_code":"IT",
    "gn:dem":375,
    "gn:feature_class":"P",
    "gn:feature_code":"PPL",
    "gn:name":"Carpeneto",
    "gn:population":24,
    "gn:timezone":"Europe/Rome",
    "iso:country":"IT",
    "name:ara_x_preferred":[
        "\u0643\u0627\u0631\u0628\u064a\u0646\u064a\u062a\u0648"
    ],
    "name:azb_x_preferred":[
        "\u06a9\u0627\u0631\u067e\u0647\u200c\u0646\u062a\u0648"
    ],
    "name:bel_x_preferred":[
        "\u041a\u0430\u0440\u043f\u0435\u043d\u0435\u0442\u0430"
    ],
    "name:bul_x_preferred":[
        "\u041a\u0430\u0440\u043f\u0435\u043d\u0435\u0442\u043e"
    ],
    "name:cat_x_preferred":[
        "Carpeneto"
    ],
    "name:ceb_x_preferred":[
        "Carpeneto"
    ],
    "name:deu_x_preferred":[
        "Carpeneto"
    ],
    "name:epo_x_preferred":[
        "Carpeneto"
    ],
    "name:eus_x_preferred":[
        "Carpeneto"
    ],
    "name:fas_x_preferred":[
        "\u06a9\u0627\u0631\u067e\u0647\u200c\u0646\u062a\u0648"
    ],
    "name:fra_x_preferred":[
        "Carpeneto"
    ],
    "name:hun_x_preferred":[
        "Carpeneto"
    ],
    "name:hye_x_preferred":[
        "\u053f\u0561\u0580\u057a\u0565\u0576\u0565\u057f\u0578"
    ],
    "name:ind_x_preferred":[
        "Carpeneto"
    ],
    "name:ita_x_preferred":[
        "Carpeneto"
    ],
    "name:jpn_x_preferred":[
        "\u30ab\u30eb\u30da\u30cd\u30fc\u30c8"
    ],
    "name:kaz_x_preferred":[
        "\u041a\u0430\u0440\u043f\u0435\u043d\u0435\u0442\u043e"
    ],
    "name:lmo_x_preferred":[
        "Carpeneto"
    ],
    "name:msa_x_preferred":[
        "Carpeneto"
    ],
    "name:nap_x_preferred":[
        "Carpeneto"
    ],
    "name:nld_x_preferred":[
        "Carpeneto"
    ],
    "name:pms_x_preferred":[
        "Carpn\u00e8j"
    ],
    "name:pol_x_preferred":[
        "Carpeneto"
    ],
    "name:por_x_preferred":[
        "Carpeneto"
    ],
    "name:ron_x_preferred":[
        "Carpeneto"
    ],
    "name:rus_x_preferred":[
        "\u041a\u0430\u0440\u043f\u0435\u043d\u0435\u0442\u043e"
    ],
    "name:scn_x_preferred":[
        "Carpeneto"
    ],
    "name:spa_x_preferred":[
        "Carpeneto"
    ],
    "name:srp_x_preferred":[
        "\u041a\u0430\u0440\u043f\u0435\u043d\u0435\u0442\u043e"
    ],
    "name:tgl_x_preferred":[
        "Carpeneto"
    ],
    "name:ukr_x_preferred":[
        "\u041a\u0430\u0440\u043f\u0435\u043d\u0435\u0442\u043e"
    ],
    "name:uzb_x_preferred":[
        "Carpeneto"
    ],
    "name:vie_x_preferred":[
        "Carpeneto"
    ],
    "name:vol_x_preferred":[
        "Carpeneto"
    ],
    "name:war_x_preferred":[
        "Carpeneto"
    ],
    "name:zho_x_preferred":[
        "\u5361\u5c14\u4f69\u5185\u6258"
    ],
    "wof:name":"Carpeneto",
    "wof:placetype":"locality",
    "wof:population":24
},
  "geometry": {"coordinates":[9.19175,44.45168],"type":"Point"}
}