{
  "type": "Feature",
  "properties": {
    "gn:admin1_code":"8",
    "gn:admin2_code":"GE",
    "gn:admin3_code":"10041.0",
    "gn:asciiname":"Carpeneto",
    "gn:country_code":"IT",
    "gn:dem":375,
    "gn:feature_class":"P",
    "gn:feature_code":"PPL",
    "gn:name":"Carpeneto",
    "gn:population":24,
    "gn:timezone":"Europe/Rome",
    "iso:country":"IT",
    "wof:name":"Carpeneto",
    "wof:placetype":"locality",
    "wof:population":24
},
  "geometry": {"coordinates":[9.19175,44.45168],"type":"Point"}
}