{
  "type": "Feature",
  "properties": {
    "gn:admin1_code":"5.0",
    "gn:admin2_code":"PR",
    "gn:admin3_code":"34032.0",
    "gn:asciiname":"Castello di Contignaco",
    "gn:cc2":"IT",
    "gn:country_code":"IT",
    "gn:dem":305,
    "gn:feature_class":"P",
    "gn:feature_code":"PPL",
    "gn:name":"Castello di Contignaco",
    "gn:population":0,
    "gn:timezone":"Europe/Rome",
    "iso:country":"IT",
    "name:und_x_variant":[
        "Castello",
        "Castello di Contignaco"
    ],
    "wof:name":"Castello di Contignaco",
    "wof:placetype":"locality"
},
  "geometry": {"coordinates":[9.95,44.78333],"type":"Point"}
}