{
  "type": "Feature",
  "properties": {
    "gn:admin1_code":"18.0",
    "gn:admin2_code":"PG",
    "gn:admin3_code":"54012.0",
    "gn:asciiname":"Po' Bandino",
    "gn:country_code":"IT",
    "gn:dem":251,
    "gn:feature_class":"P",
    "gn:feature_code":"PPL",
    "gn:name":"Po' Bandino",
    "gn:population":994,
    "gn:timezone":"Europe/Rome",
    "iso:country":"IT",
    "wof:name":"Po' Bandino",
    "wof:placetype":"locality",
    "wof:population":994
},
  "geometry": {"coordinates":[11.97117,43.00187],"type":"Point"}
}