{
  "type": "Feature",
  "properties": {
    "gn:admin1_code":"17",
    "gn:admin2_code":"TN",
    "gn:admin3_code":"22209.0",
    "gn:asciiname":"Casanova",
    "gn:country_code":"IT",
    "gn:dem":1035,
    "gn:feature_class":"P",
    "gn:feature_code":"PPL",
    "gn:name":"Casanova",
    "gn:population":26,
    "gn:timezone":"Europe/Rome",
    "iso:country":"IT",
    "wof:name":"Casanova",
    "wof:placetype":"locality",
    "wof:population":26
},
  "geometry": {"coordinates":[11.34876,46.24106],"type":"Point"}
}