{
  "type": "Feature",
  "properties": {
    "gn:admin1_code":"17.0",
    "gn:admin2_code":"BZ",
    "gn:admin3_code":"21054.0",
    "gn:asciiname":"Al Gallo",
    "gn:country_code":"IT",
    "gn:dem":1486,
    "gn:feature_class":"P",
    "gn:feature_code":"PPL",
    "gn:name":"Al Gallo",
    "gn:population":0,
    "gn:timezone":"Europe/Rome",
    "iso:country":"IT",
    "name:und_x_variant":[
        "Ii Callo",
        "Al Gallo"
    ],
    "wof:name":"Al Gallo",
    "wof:placetype":"locality"
},
  "geometry": {"coordinates":[11.16667,46.85],"type":"Point"}
}