{
  "type": "Feature",
  "properties": {
    "gn:admin1_code":"7.0",
    "gn:admin2_code":"RM",
    "gn:admin3_code":"58091.0",
    "gn:admin4_code":"5809114.0",
    "gn:asciiname":"Marina",
    "gn:country_code":"IT",
    "gn:dem":107,
    "gn:feature_class":"P",
    "gn:feature_code":"PPL",
    "gn:name":"Marina",
    "gn:population":478,
    "gn:timezone":"Europe/Rome",
    "iso:country":"IT",
    "wof:name":"Marina",
    "wof:placetype":"locality",
    "wof:population":478
},
  "geometry": {"coordinates":[12.36277,41.97921],"type":"Point"}
}