{
  "type": "Feature",
  "properties": {
    "gn:admin1_code":"5",
    "gn:admin2_code":"RN",
    "gn:admin3_code":"99002.0",
    "gn:asciiname":"Ca' Fabbri",
    "gn:country_code":"IT",
    "gn:dem":15,
    "gn:feature_class":"P",
    "gn:feature_code":"PPL",
    "gn:name":"Ca' Fabbri",
    "gn:population":162,
    "gn:timezone":"Europe/Rome",
    "iso:country":"IT",
    "wof:name":"Ca' Fabbri",
    "wof:placetype":"locality",
    "wof:population":162
},
  "geometry": {"coordinates":[12.74029,43.94681],"type":"Point"}
}