{
  "type": "Feature",
  "properties": {
    "gn:admin1_code":"9",
    "gn:admin2_code":"MN",
    "gn:admin3_code":"20016.0",
    "gn:asciiname":"Carrobbio",
    "gn:country_code":"IT",
    "gn:dem":27,
    "gn:feature_class":"P",
    "gn:feature_code":"PPL",
    "gn:name":"Carrobbio",
    "gn:population":24,
    "gn:timezone":"Europe/Rome",
    "iso:country":"IT",
    "wof:name":"Carrobbio",
    "wof:placetype":"locality",
    "wof:population":24
},
  "geometry": {"coordinates":[10.61613,45.15111],"type":"Point"}
}