{
  "type": "Feature",
  "properties": {
    "gn:admin1_code":"20.0",
    "gn:admin2_code":"VI",
    "gn:admin3_code":"24101.0",
    "gn:asciiname":"Villaggio del Sole",
    "gn:country_code":"IT",
    "gn:dem":1159,
    "gn:feature_class":"P",
    "gn:feature_code":"PPLL",
    "gn:name":"Villaggio del Sole",
    "gn:population":1,
    "gn:timezone":"Europe/Rome",
    "iso:country":"IT",
    "wof:name":"Villaggio del Sole",
    "wof:placetype":"locality",
    "wof:population":1
},
  "geometry": {"coordinates":[11.72985,45.83983],"type":"Point"}
}