{
  "type": "Feature",
  "properties": {
    "gn:admin1_code":"15.0",
    "gn:admin2_code":"CT",
    "gn:admin3_code":"87033.0",
    "gn:asciiname":"Pietralunga",
    "gn:cc2":"IT",
    "gn:country_code":"IT",
    "gn:dem":98,
    "gn:feature_class":"P",
    "gn:feature_code":"PPL",
    "gn:name":"Pietralunga",
    "gn:population":0,
    "gn:timezone":"Europe/Rome",
    "iso:country":"IT",
    "name:und_x_variant":[
        "Tenuta Petralunga",
        "Pietralunga"
    ],
    "wof:name":"Pietralunga",
    "wof:placetype":"locality"
},
  "geometry": {"coordinates":[14.85,37.58333],"type":"Point"}
}