{
  "type": "Feature",
  "properties": {
    "gn:admin1_code":"15.0",
    "gn:admin2_code":"CT",
    "gn:admin3_code":"87033.0",
    "gn:asciiname":"Pietralunga",
    "gn:cc2":"IT",
    "gn:country_code":"IT",
    "gn:dem":98,
    "gn:feature_class":"P",
    "gn:feature_code":"PPL",
    "gn:name":"Pietralunga",
    "gn:population":0,
    "gn:timezone":"Europe/Rome",
    "iso:country":"IT",
    "name:ara_x_preferred":[
        "\u0628\u064a\u064a\u062a\u0631\u0627\u0644\u0648\u0646\u062c\u0627"
    ],
    "name:azb_x_preferred":[
        "\u067e\u06cc\u062a\u0631\u0627\u0644\u0648\u0646\u062c\u0627"
    ],
    "name:bul_x_preferred":[
        "\u041f\u0438\u0435\u0442\u0440\u0430\u043b\u0443\u043d\u0433\u0430"
    ],
    "name:cat_x_preferred":[
        "Pietralunga"
    ],
    "name:ceb_x_preferred":[
        "Pietralunga"
    ],
    "name:ces_x_preferred":[
        "Pietralunga"
    ],
    "name:deu_x_preferred":[
        "Pietralunga"
    ],
    "name:epo_x_preferred":[
        "Pietralunga"
    ],
    "name:eus_x_preferred":[
        "Pietralunga"
    ],
    "name:fas_x_preferred":[
        "\u067e\u06cc\u062a\u0631\u0627\u0644\u0648\u0646\u062c\u0627"
    ],
    "name:fra_x_preferred":[
        "Pietralunga"
    ],
    "name:hun_x_preferred":[
        "Pietralunga"
    ],
    "name:hye_x_preferred":[
        "\u054a\u056b\u0565\u057f\u0580\u0561\u056c\u0578\u0582\u0576\u0563\u0561"
    ],
    "name:ind_x_preferred":[
        "Pietralunga"
    ],
    "name:ita_x_preferred":[
        "Pietralunga"
    ],
    "name:jpn_x_preferred":[
        "\u30d4\u30a8\u30c8\u30e9\u30eb\u30f3\u30ac"
    ],
    "name:kaz_x_preferred":[
        "\u041f\u044c\u0435\u0442\u0440\u0430\u043b\u0443\u043d\u0433\u0430"
    ],
    "name:kor_x_preferred":[
        "\ud53c\uc5d0\ud2b8\ub784\ub8ec\uac00"
    ],
    "name:lmo_x_preferred":[
        "Pietralunga"
    ],
    "name:msa_x_preferred":[
        "Pietralunga"
    ],
    "name:nap_x_preferred":[
        "Pietralunga"
    ],
    "name:nld_x_preferred":[
        "Pietralunga"
    ],
    "name:pms_x_preferred":[
        "Pietralunga"
    ],
    "name:pol_x_preferred":[
        "Pietralunga"
    ],
    "name:por_x_preferred":[
        "Pietralunga"
    ],
    "name:ron_x_preferred":[
        "Pietralunga"
    ],
    "name:rus_x_preferred":[
        "\u041f\u044c\u0435\u0442\u0440\u0430\u043b\u0443\u043d\u0433\u0430"
    ],
    "name:scn_x_preferred":[
        "Pietralonca"
    ],
    "name:spa_x_preferred":[
        "Pietralunga"
    ],
    "name:srp_x_preferred":[
        "\u041f\u0458\u0435\u0442\u0440\u0430\u043b\u0443\u043d\u0433\u0430"
    ],
    "name:tgl_x_preferred":[
        "Pietralunga"
    ],
    "name:tur_x_preferred":[
        "Pietralunga"
    ],
    "name:ukr_x_preferred":[
        "\u041f'\u0454\u0442\u0440\u0430\u043b\u0443\u043d\u0433\u0430"
    ],
    "name:und_x_variant":[
        "Tenuta Petralunga",
        "Pietralunga"
    ],
    "name:uzb_x_preferred":[
        "Pietralunga"
    ],
    "name:vie_x_preferred":[
        "Pietralunga"
    ],
    "name:vol_x_preferred":[
        "Pietralunga"
    ],
    "name:war_x_preferred":[
        "Pietralunga"
    ],
    "name:zho_x_preferred":[
        "\u76ae\u8036\u7279\u62c9\u4f26\u52a0"
    ],
    "wof:name":"Pietralunga",
    "wof:placetype":"locality"
},
  "geometry": {"coordinates":[14.85,37.58333],"type":"Point"}
}