{
  "type": "Feature",
  "properties": {
    "gn:admin1_code":"9.0",
    "gn:admin2_code":"BG",
    "gn:admin3_code":"16190.0",
    "gn:asciiname":"Antea",
    "gn:country_code":"IT",
    "gn:dem":488,
    "gn:elevation":"540.0",
    "gn:feature_class":"P",
    "gn:feature_code":"PPL",
    "gn:name":"Antea",
    "gn:population":156,
    "gn:timezone":"Europe/Rome",
    "iso:country":"IT",
    "wof:name":"Antea",
    "wof:placetype":"locality",
    "wof:population":156
},
  "geometry": {"coordinates":[9.66796,45.85243],"type":"Point"}
}