{
  "type": "Feature",
  "properties": {
    "gn:admin1_code":"5",
    "gn:admin2_code":"RE",
    "gn:admin3_code":"35027.0",
    "gn:asciiname":"Aiola",
    "gn:country_code":"IT",
    "gn:dem":78,
    "gn:feature_class":"P",
    "gn:feature_code":"PPL",
    "gn:name":"Aiola",
    "gn:population":170,
    "gn:timezone":"Europe/Rome",
    "iso:country":"IT",
    "wof:name":"Aiola",
    "wof:placetype":"locality",
    "wof:population":170
},
  "geometry": {"coordinates":[10.478,44.71192],"type":"Point"}
}