{
  "type": "Feature",
  "properties": {
    "gn:admin1_code":"12",
    "gn:admin2_code":"AL",
    "gn:admin3_code":"6178.0",
    "gn:asciiname":"Rivalba",
    "gn:country_code":"IT",
    "gn:dem":94,
    "gn:feature_class":"P",
    "gn:feature_code":"PPL",
    "gn:name":"Rivalba",
    "gn:population":260,
    "gn:timezone":"Europe/Rome",
    "iso:country":"IT",
    "name:azb_x_preferred":[
        "\u0631\u06cc\u0648\u0627\u0644\u0628\u0627"
    ],
    "name:bel_x_preferred":[
        "\u0420\u044b\u0432\u0430\u043b\u044c\u0431\u0430"
    ],
    "name:bul_x_preferred":[
        "\u0420\u0438\u0432\u0430\u043b\u0431\u0430"
    ],
    "name:ceb_x_preferred":[
        "Rivalba"
    ],
    "name:deu_x_preferred":[
        "Rivalba"
    ],
    "name:epo_x_preferred":[
        "Rivalba"
    ],
    "name:est_x_preferred":[
        "Rivalba"
    ],
    "name:eus_x_preferred":[
        "Rivalba"
    ],
    "name:fas_x_preferred":[
        "\u0631\u06cc\u0648\u0627\u0644\u0628\u0627"
    ],
    "name:fra_x_preferred":[
        "Rivalba"
    ],
    "name:hun_x_preferred":[
        "Rivalba"
    ],
    "name:hye_x_preferred":[
        "\u054c\u056b\u057e\u0561\u056c\u0562\u0561"
    ],
    "name:ind_x_preferred":[
        "Rivalba"
    ],
    "name:ita_x_preferred":[
        "Rivalba"
    ],
    "name:jpn_x_preferred":[
        "\u30ea\u30f4\u30a1\u30eb\u30d0"
    ],
    "name:kaz_x_preferred":[
        "\u0420\u0438\u0432\u0430\u043b\u044c\u0431\u0430"
    ],
    "name:lat_x_preferred":[
        "Ripa Alba"
    ],
    "name:lmo_x_preferred":[
        "Rivalba"
    ],
    "name:msa_x_preferred":[
        "Rivalba"
    ],
    "name:nap_x_preferred":[
        "Rivalba"
    ],
    "name:nld_x_preferred":[
        "Rivalba"
    ],
    "name:pms_x_preferred":[
        "Rivalba"
    ],
    "name:pol_x_preferred":[
        "Rivalba"
    ],
    "name:por_x_preferred":[
        "Rivalba"
    ],
    "name:ron_x_preferred":[
        "Rivalba"
    ],
    "name:rus_x_preferred":[
        "\u0420\u0438\u0432\u0430\u043b\u044c\u0431\u0430"
    ],
    "name:scn_x_preferred":[
        "Rivalba"
    ],
    "name:sco_x_preferred":[
        "Rivalba"
    ],
    "name:spa_x_preferred":[
        "Rivalba"
    ],
    "name:swe_x_preferred":[
        "Rivalba"
    ],
    "name:tgl_x_preferred":[
        "Rivalba"
    ],
    "name:ukr_x_preferred":[
        "\u0420\u0438\u0432\u0430\u043b\u044c\u0431\u0430"
    ],
    "name:uzb_x_preferred":[
        "Rivalba"
    ],
    "name:vie_x_preferred":[
        "Rivalba"
    ],
    "name:vol_x_preferred":[
        "Rivalba"
    ],
    "name:war_x_preferred":[
        "Rivalba"
    ],
    "name:zho_x_preferred":[
        "\u91cc\u74e6\u5c14\u5df4"
    ],
    "wof:name":"Rivalba",
    "wof:placetype":"locality",
    "wof:population":260
},
  "geometry": {"coordinates":[8.59836,45.09001],"type":"Point"}
}