{
  "type": "Feature",
  "properties": {
    "gn:admin1_code":"12",
    "gn:admin2_code":"AL",
    "gn:admin3_code":"6178.0",
    "gn:asciiname":"Rivalba",
    "gn:country_code":"IT",
    "gn:dem":94,
    "gn:feature_class":"P",
    "gn:feature_code":"PPL",
    "gn:name":"Rivalba",
    "gn:population":260,
    "gn:timezone":"Europe/Rome",
    "iso:country":"IT",
    "wof:name":"Rivalba",
    "wof:placetype":"locality",
    "wof:population":260
},
  "geometry": {"coordinates":[8.59836,45.09001],"type":"Point"}
}