{
  "type": "Feature",
  "properties": {
    "gn:admin1_code":"16",
    "gn:admin2_code":"FI",
    "gn:admin3_code":"48012.0",
    "gn:asciiname":"Le Case di Sciano",
    "gn:country_code":"IT",
    "gn:dem":133,
    "gn:feature_class":"P",
    "gn:feature_code":"PPL",
    "gn:name":"Le Case di Sciano",
    "gn:population":160,
    "gn:timezone":"Europe/Rome",
    "iso:country":"IT",
    "wof:name":"Le Case di Sciano",
    "wof:placetype":"locality",
    "wof:population":160
},
  "geometry": {"coordinates":[11.07621,43.54811],"type":"Point"}
}