{
  "type": "Feature",
  "properties": {
    "gn:gn_country":"IT",
    "gn:gn_fcode":"PPLA3",
    "gn:gn_pop":311,
    "gn:population":252,
    "iso:country":"IT",
    "name:arm_x_preferred":[
        "\u054c\u0578\u0582\u0586\u056b\u0561"
    ],
    "name:baq_x_preferred":[
        "Ruffia"
    ],
    "name:bel_x_preferred":[
        "\u0420\u0443\u0444\u0456\u044f"
    ],
    "name:bul_x_preferred":[
        "\u0420\u0443\u0444\u0438\u044f"
    ],
    "name:cat_x_preferred":[
        "Ruffia"
    ],
    "name:chi_x_preferred":[
        "\u9c81\u83f2\u4e9a"
    ],
    "name:deu_x_preferred":[
        "Ruffia"
    ],
    "name:dut_x_preferred":[
        "Ruffia"
    ],
    "name:eng_x_preferred":[
        "Ruffia"
    ],
    "name:epo_x_preferred":[
        "Ruffia"
    ],
    "name:fra_x_preferred":[
        "Ruffia"
    ],
    "name:fre_x_preferred":[
        "Ruffia"
    ],
    "name:ger_x_preferred":[
        "Ruffia"
    ],
    "name:hun_x_preferred":[
        "Ruffia"
    ],
    "name:ind_x_preferred":[
        "Ruffia"
    ],
    "name:ita_x_preferred":[
        "Ruffia"
    ],
    "name:jpn_x_preferred":[
        "\u30eb\u30c3\u30d5\u30a3\u30fc\u30a2"
    ],
    "name:kaz_x_preferred":[
        "\u0420\u0443\u0444\u0444\u0438\u044f"
    ],
    "name:kor_x_preferred":[
        "\ub8e8\ud53c\uc544"
    ],
    "name:lat_x_preferred":[
        "Rodulphia"
    ],
    "name:lmo_x_preferred":[
        "Ruffia"
    ],
    "name:may_x_preferred":[
        "Ruffia"
    ],
    "name:nan_x_preferred":[
        "Ruffia"
    ],
    "name:nap_x_preferred":[
        "Ruffia"
    ],
    "name:nld_x_preferred":[
        "Ruffia"
    ],
    "name:oci_x_preferred":[
        "Ruffia"
    ],
    "name:per_x_preferred":[
        "\u0631\u0648\u0641\u06cc\u0627"
    ],
    "name:pms_x_preferred":[
        "Ruf\u00eca"
    ],
    "name:pol_x_preferred":[
        "Ruffia"
    ],
    "name:por_x_preferred":[
        "Ruffia"
    ],
    "name:rum_x_preferred":[
        "Ruffia"
    ],
    "name:rus_x_preferred":[
        "\u0420\u0443\u0444\u0444\u0438\u044f"
    ],
    "name:scn_x_preferred":[
        "Ruffia"
    ],
    "name:spa_x_preferred":[
        "Ruffia"
    ],
    "name:srp_x_preferred":[
        "Ruffia"
    ],
    "name:tgl_x_preferred":[
        "Ruffia"
    ],
    "name:ukr_x_preferred":[
        "\u0420\u0443\u0444\u0444\u0456\u044f"
    ],
    "name:uzb_x_preferred":[
        "Ruffia"
    ],
    "name:vie_x_preferred":[
        "Ruffia"
    ],
    "name:vol_x_preferred":[
        "Ruffia"
    ],
    "name:war_x_preferred":[
        "Ruffia"
    ],
    "qs_pg:aaroncc":"IT",
    "qs_pg:gn_country":"IT",
    "qs_pg:gn_fcode":"PPLA3",
    "qs_pg:gn_pop":311,
    "qs_pg:name":"Ruffia",
    "qs_pg:name_adm0":"Italia",
    "qs_pg:name_adm1":"Piemonte",
    "qs_pg:photos_9r":0,
    "qs_pg:photos_sr":0,
    "qs_pg:pop_sr":2,
    "qs_pg:qs_pg_placetype":"locality",
    "qs_pg:qs_pg_placetype_gp":"Town",
    "qs_pg:woe_adm0":23424853,
    "woe:adm0_id":23424853,
    "woe:name_adm0":"Italia",
    "woe:name_adm1":"Piemonte",
    "woe:placetype":"Town",
    "wof:name":"Ruffia",
    "wof:placetype":"locality",
    "wof:population":252
},
  "geometry": {"coordinates":[7.60403,44.70664],"type":"Point"}
}