{
  "type": "Feature",
  "properties": {
    "gn:admin1_code":"20",
    "gn:admin2_code":"BL",
    "gn:admin3_code":"25025.0",
    "gn:asciiname":"Lambroi",
    "gn:country_code":"IT",
    "gn:dem":715,
    "gn:feature_class":"P",
    "gn:feature_code":"PPL",
    "gn:name":"Lambroi",
    "gn:population":24,
    "gn:timezone":"Europe/Rome",
    "iso:country":"IT",
    "wof:name":"Lambroi",
    "wof:placetype":"locality",
    "wof:population":24
},
  "geometry": {"coordinates":[11.9954,46.22122],"type":"Point"}
}