{
  "type": "Feature",
  "properties": {
    "gn:admin1_code":"3.0",
    "gn:admin2_code":"CZ",
    "gn:admin3_code":"79099.0",
    "gn:asciiname":"Croce di Sambate",
    "gn:country_code":"IT",
    "gn:dem":955,
    "gn:feature_class":"P",
    "gn:feature_code":"PPL",
    "gn:name":"Croce di Sambate",
    "gn:population":23,
    "gn:timezone":"Europe/Rome",
    "iso:country":"IT",
    "wof:name":"Croce di Sambate",
    "wof:placetype":"locality",
    "wof:population":23
},
  "geometry": {"coordinates":[16.29186,39.01558],"type":"Point"}
}