{
  "type": "Feature",
  "properties": {
    "gn:admin1_code":"5",
    "gn:admin2_code":"PC",
    "gn:admin3_code":"33012.0",
    "gn:asciiname":"Montagnano",
    "gn:country_code":"IT",
    "gn:dem":160,
    "gn:feature_class":"P",
    "gn:feature_code":"PPL",
    "gn:name":"Montagnano",
    "gn:population":25,
    "gn:timezone":"Europe/Rome",
    "iso:country":"IT",
    "wof:name":"Montagnano",
    "wof:placetype":"locality",
    "wof:population":25
},
  "geometry": {"coordinates":[9.82452,44.85618],"type":"Point"}
}