{
  "type": "Feature",
  "properties": {
    "gn:admin1_code":"19.0",
    "gn:admin2_code":"AO",
    "gn:admin3_code":"7044.0",
    "gn:asciiname":"Chanton",
    "gn:country_code":"IT",
    "gn:dem":1945,
    "gn:feature_class":"P",
    "gn:feature_code":"PPL",
    "gn:name":"Chanton",
    "gn:population":0,
    "gn:timezone":"Europe/Rome",
    "iso:country":"IT",
    "wof:name":"Chanton",
    "wof:placetype":"locality"
},
  "geometry": {"coordinates":[7.05,45.78333],"type":"Point"}
}