{
  "type": "Feature",
  "properties": {
    "gn:admin1_code":"20",
    "gn:admin2_code":"BL",
    "gn:admin3_code":"25023.0",
    "gn:asciiname":"Tegosa",
    "gn:country_code":"IT",
    "gn:dem":1191,
    "gn:feature_class":"P",
    "gn:feature_code":"PPL",
    "gn:name":"Tegosa",
    "gn:population":22,
    "gn:timezone":"Europe/Rome",
    "iso:country":"IT",
    "name:ceb_x_preferred":[
        "Tegosa"
    ],
    "name:fra_x_preferred":[
        "Tegosa"
    ],
    "name:nor_x_preferred":[
        "Tegosa"
    ],
    "name:swe_x_preferred":[
        "Tegosa"
    ],
    "name:war_x_preferred":[
        "Tegosa"
    ],
    "name:zho_x_preferred":[
        "\u82d4\u86fa\u8776\u5c6c"
    ],
    "wof:name":"Tegosa",
    "wof:placetype":"locality",
    "wof:population":22
},
  "geometry": {"coordinates":[11.89427,46.37404],"type":"Point"}
}