{
  "type": "Feature",
  "properties": {
    "gn:admin1_code":"5",
    "gn:admin2_code":"RN",
    "gn:admin3_code":"99028.0",
    "gn:asciiname":"Case Pontaccio",
    "gn:country_code":"IT",
    "gn:dem":55,
    "gn:feature_class":"P",
    "gn:feature_code":"PPL",
    "gn:name":"Case Pontaccio",
    "gn:population":28,
    "gn:timezone":"Europe/Rome",
    "iso:country":"IT",
    "wof:name":"Case Pontaccio",
    "wof:placetype":"locality",
    "wof:population":28
},
  "geometry": {"coordinates":[12.41281,44.04277],"type":"Point"}
}