{
  "type": "Feature",
  "properties": {
    "gn:admin1_code":"7.0",
    "gn:admin2_code":"VT",
    "gn:admin3_code":"56049.0",
    "gn:asciiname":"Colle Diana",
    "gn:country_code":"IT",
    "gn:dem":378,
    "gn:feature_class":"P",
    "gn:feature_code":"PPL",
    "gn:name":"Colle Diana",
    "gn:population":618,
    "gn:timezone":"Europe/Rome",
    "iso:country":"IT",
    "wof:name":"Colle Diana",
    "wof:placetype":"locality",
    "wof:population":618
},
  "geometry": {"coordinates":[12.21362,42.26009000000001],"type":"Point"}
}