{
  "type": "Feature",
  "properties": {
    "gn:admin1_code":"17",
    "gn:admin2_code":"BZ",
    "gn:admin3_code":"21073.0",
    "gn:asciiname":"Gaveis",
    "gn:country_code":"IT",
    "gn:dem":1353,
    "gn:feature_class":"P",
    "gn:feature_code":"PPL",
    "gn:name":"Gaveis",
    "gn:population":24,
    "gn:timezone":"Europe/Rome",
    "iso:country":"IT",
    "wof:name":"Gaveis",
    "wof:placetype":"locality",
    "wof:population":24
},
  "geometry": {"coordinates":[11.16779,46.71653],"type":"Point"}
}