{
  "type": "Feature",
  "properties": {
    "gn:admin1_code":"12.0",
    "gn:admin2_code":"CN",
    "gn:admin3_code":"4155.0",
    "gn:asciiname":"Porcirette Sottane",
    "gn:country_code":"IT",
    "gn:dem":1100,
    "gn:feature_class":"P",
    "gn:feature_code":"PPLL",
    "gn:name":"Porcirette Sottane",
    "gn:population":4,
    "gn:timezone":"Europe/Rome",
    "iso:country":"IT",
    "wof:name":"Porcirette Sottane",
    "wof:placetype":"locality",
    "wof:population":4
},
  "geometry": {"coordinates":[7.8805,44.15315],"type":"Point"}
}