{
  "type": "Feature",
  "properties": {
    "gn:admin1_code":"8",
    "gn:admin2_code":"GE",
    "gn:admin3_code":"10025.0",
    "gn:asciiname":"Borgano",
    "gn:country_code":"IT",
    "gn:dem":391,
    "gn:feature_class":"P",
    "gn:feature_code":"PPLL",
    "gn:name":"Borgano",
    "gn:population":9,
    "gn:timezone":"Europe/Rome",
    "iso:country":"IT",
    "wof:name":"Borgano",
    "wof:placetype":"locality",
    "wof:population":9
},
  "geometry": {"coordinates":[9.03129,44.46103],"type":"Point"}
}