{
  "type": "Feature",
  "properties": {
    "gn:admin1_code":"16",
    "gn:admin2_code":"PI",
    "gn:admin3_code":"50014.0",
    "gn:asciiname":"Case Nuove",
    "gn:country_code":"IT",
    "gn:dem":88,
    "gn:feature_class":"P",
    "gn:feature_code":"PPL",
    "gn:name":"Case Nuove",
    "gn:population":22,
    "gn:timezone":"Europe/Rome",
    "iso:country":"IT",
    "wof:name":"Case Nuove",
    "wof:placetype":"locality",
    "wof:population":22
},
  "geometry": {"coordinates":[10.47501,43.52486],"type":"Point"}
}