{
  "type": "Feature",
  "properties": {
    "gn:admin1_code":"12",
    "gn:admin2_code":"TO",
    "gn:admin3_code":"1013.0",
    "gn:asciiname":"Garello",
    "gn:country_code":"IT",
    "gn:dem":364,
    "gn:feature_class":"P",
    "gn:feature_code":"PPL",
    "gn:name":"Garello",
    "gn:population":19,
    "gn:timezone":"Europe/Rome",
    "iso:country":"IT",
    "wof:name":"Garello",
    "wof:placetype":"locality",
    "wof:population":19
},
  "geometry": {"coordinates":[7.39058,45.05866],"type":"Point"}
}