{
  "type": "Feature",
  "properties": {
    "gn:admin1_code":"5",
    "gn:admin2_code":"PC",
    "gn:admin3_code":"33039.0",
    "gn:asciiname":"Bastia",
    "gn:country_code":"IT",
    "gn:dem":63,
    "gn:feature_class":"P",
    "gn:feature_code":"PPL",
    "gn:name":"Bastia",
    "gn:population":20,
    "gn:timezone":"Europe/Rome",
    "iso:country":"IT",
    "wof:name":"Bastia",
    "wof:placetype":"locality",
    "wof:population":20
},
  "geometry": {"coordinates":[9.56698,45.06846],"type":"Point"}
}