{
  "type": "Feature",
  "properties": {
    "gn:admin1_code":"16",
    "gn:admin2_code":"MS",
    "gn:admin3_code":"45013.0",
    "gn:asciiname":"Genicciola",
    "gn:country_code":"IT",
    "gn:dem":472,
    "gn:feature_class":"P",
    "gn:feature_code":"PPL",
    "gn:name":"Genicciola",
    "gn:population":13,
    "gn:timezone":"Europe/Rome",
    "iso:country":"IT",
    "wof:name":"Genicciola",
    "wof:placetype":"locality",
    "wof:population":13
},
  "geometry": {"coordinates":[9.87638,44.21817],"type":"Point"}
}