{
  "type": "Feature",
  "properties": {
    "gn:admin1_code":"9",
    "gn:admin2_code":"BS",
    "gn:admin3_code":"17197.0",
    "gn:asciiname":"Via Gargna",
    "gn:country_code":"IT",
    "gn:dem":329,
    "gn:feature_class":"P",
    "gn:feature_code":"PPL",
    "gn:name":"Via Gargn\u00e0",
    "gn:population":33,
    "gn:timezone":"Europe/Rome",
    "iso:country":"IT",
    "name:und_x_variant":[
        "Via Gargn\u00e0"
    ],
    "wof:name":"Via Gargna",
    "wof:placetype":"locality",
    "wof:population":33
},
  "geometry": {"coordinates":[10.42186,45.72084],"type":"Point"}
}