{
  "type": "Feature",
  "properties": {
    "gn:admin1_code":"19",
    "gn:admin2_code":"AO",
    "gn:admin3_code":"7040.0",
    "gn:asciiname":"Cheverel",
    "gn:country_code":"IT",
    "gn:dem":1493,
    "gn:feature_class":"P",
    "gn:feature_code":"PPL",
    "gn:name":"Cheverel",
    "gn:population":62,
    "gn:timezone":"Europe/Rome",
    "iso:country":"IT",
    "wof:name":"Cheverel",
    "wof:placetype":"locality",
    "wof:population":62
},
  "geometry": {"coordinates":[7.06955,45.764],"type":"Point"}
}