{
  "type": "Feature",
  "properties": {
    "gn:admin1_code":"16",
    "gn:admin2_code":"AR",
    "gn:admin3_code":"51040.0",
    "gn:asciiname":"Palagio",
    "gn:country_code":"IT",
    "gn:dem":284,
    "gn:feature_class":"P",
    "gn:feature_code":"PPL",
    "gn:name":"Palagio",
    "gn:population":83,
    "gn:timezone":"Europe/Rome",
    "iso:country":"IT",
    "wof:name":"Palagio",
    "wof:placetype":"locality",
    "wof:population":83
},
  "geometry": {"coordinates":[11.54416,43.63366],"type":"Point"}
}