{
  "type": "Feature",
  "properties": {
    "gn:admin1_code":"9",
    "gn:admin2_code":"MN",
    "gn:admin3_code":"20002.0",
    "gn:asciiname":"Baselle",
    "gn:country_code":"IT",
    "gn:dem":46,
    "gn:feature_class":"P",
    "gn:feature_code":"PPL",
    "gn:name":"Baselle",
    "gn:population":32,
    "gn:timezone":"Europe/Rome",
    "iso:country":"IT",
    "wof:name":"Baselle",
    "wof:placetype":"locality",
    "wof:population":32
},
  "geometry": {"coordinates":[10.44196,45.27274],"type":"Point"}
}