{
  "type": "Feature",
  "properties": {
    "gn:admin1_code":"7.0",
    "gn:admin2_code":"RI",
    "gn:admin3_code":"57060.0",
    "gn:asciiname":"Piedicolle",
    "gn:country_code":"IT",
    "gn:dem":401,
    "gn:feature_class":"P",
    "gn:feature_code":"PPL",
    "gn:name":"Piedicolle",
    "gn:population":448,
    "gn:timezone":"Europe/Rome",
    "iso:country":"IT",
    "wof:name":"Piedicolle",
    "wof:placetype":"locality",
    "wof:population":448
},
  "geometry": {"coordinates":[12.85712,42.50225],"type":"Point"}
}