{
  "type": "Feature",
  "properties": {
    "gn:admin1_code":"5",
    "gn:admin2_code":"RE",
    "gn:admin3_code":"35020.0",
    "gn:asciiname":"Case Nuove",
    "gn:country_code":"IT",
    "gn:dem":31,
    "gn:feature_class":"P",
    "gn:feature_code":"PPL",
    "gn:name":"Case Nuove",
    "gn:population":57,
    "gn:timezone":"Europe/Rome",
    "iso:country":"IT",
    "wof:name":"Case Nuove",
    "wof:placetype":"locality",
    "wof:population":57
},
  "geometry": {"coordinates":[10.75377,44.77511],"type":"Point"}
}