{
  "type": "Feature",
  "properties": {
    "gn:admin1_code":"7",
    "gn:admin2_code":"RM",
    "gn:admin3_code":"58076.0",
    "gn:asciiname":"Via Piana",
    "gn:country_code":"IT",
    "gn:dem":622,
    "gn:feature_class":"P",
    "gn:feature_code":"PPL",
    "gn:name":"Via Piana",
    "gn:population":20,
    "gn:timezone":"Europe/Rome",
    "iso:country":"IT",
    "wof:name":"Via Piana",
    "wof:placetype":"locality",
    "wof:population":20
},
  "geometry": {"coordinates":[12.91315,42.09166],"type":"Point"}
}