{
  "type": "Feature",
  "properties": {
    "gn:admin1_code":"1",
    "gn:admin2_code":"AQ",
    "gn:admin3_code":"66006.0",
    "gn:asciiname":"Pozzone",
    "gn:country_code":"IT",
    "gn:dem":657,
    "gn:feature_class":"P",
    "gn:feature_code":"PPL",
    "gn:name":"Pozzone",
    "gn:population":23,
    "gn:timezone":"Europe/Rome",
    "iso:country":"IT",
    "wof:name":"Pozzone",
    "wof:placetype":"locality",
    "wof:population":23
},
  "geometry": {"coordinates":[13.50155,42.04745],"type":"Point"}
}