{
  "type": "Feature",
  "properties": {
    "gn:admin1_code":"9",
    "gn:admin2_code":"VA",
    "gn:admin3_code":"12140.0",
    "gn:asciiname":"Sede Comunale",
    "gn:country_code":"IT",
    "gn:dem":207,
    "gn:feature_class":"P",
    "gn:feature_code":"PPL",
    "gn:name":"Sede Comunale",
    "gn:population":37,
    "gn:timezone":"Europe/Rome",
    "iso:country":"IT",
    "wof:name":"Sede Comunale",
    "wof:placetype":"locality",
    "wof:population":37
},
  "geometry": {"coordinates":[8.68634,45.63075],"type":"Point"}
}