{
  "type": "Feature",
  "properties": {
    "gn:admin1_code":"8",
    "gn:admin2_code":"IM",
    "gn:admin3_code":"8024.0",
    "gn:asciiname":"Arene",
    "gn:country_code":"IT",
    "gn:dem":51,
    "gn:feature_class":"P",
    "gn:feature_code":"PPL",
    "gn:name":"Arene",
    "gn:population":14,
    "gn:timezone":"Europe/Rome",
    "iso:country":"IT",
    "wof:name":"Arene",
    "wof:placetype":"locality",
    "wof:population":14
},
  "geometry": {"coordinates":[7.95503,43.85088],"type":"Point"}
}