{
  "type": "Feature",
  "properties": {
    "gn:admin1_code":"3.0",
    "gn:admin2_code":"CZ",
    "gn:admin3_code":"79095.0",
    "gn:asciiname":"Arietta",
    "gn:country_code":"IT",
    "gn:dem":376,
    "gn:elevation":"365.0",
    "gn:feature_class":"P",
    "gn:feature_code":"PPL",
    "gn:name":"Arietta",
    "gn:population":212,
    "gn:timezone":"Europe/Rome",
    "iso:country":"IT",
    "wof:name":"Arietta",
    "wof:placetype":"locality",
    "wof:population":212
},
  "geometry": {"coordinates":[16.78915,39.05198],"type":"Point"}
}