{
  "type": "Feature",
  "properties": {
    "gn:admin1_code":"5",
    "gn:admin2_code":"PC",
    "gn:admin3_code":"33002.0",
    "gn:asciiname":"Fellegara",
    "gn:country_code":"IT",
    "gn:dem":170,
    "gn:feature_class":"P",
    "gn:feature_code":"PPL",
    "gn:name":"Fellegara",
    "gn:population":42,
    "gn:timezone":"Europe/Rome",
    "iso:country":"IT",
    "wof:name":"Fellegara",
    "wof:placetype":"locality",
    "wof:population":42
},
  "geometry": {"coordinates":[9.92573,44.86258],"type":"Point"}
}