{
  "type": "Feature",
  "properties": {
    "gn:admin1_code":"12",
    "gn:admin2_code":"CN",
    "gn:admin3_code":"4039.0",
    "gn:asciiname":"Chiazzuola",
    "gn:country_code":"IT",
    "gn:dem":1009,
    "gn:feature_class":"P",
    "gn:feature_code":"PPL",
    "gn:name":"Chiazzuola",
    "gn:population":21,
    "gn:timezone":"Europe/Rome",
    "iso:country":"IT",
    "wof:name":"Chiazzuola",
    "wof:placetype":"locality",
    "wof:population":21
},
  "geometry": {"coordinates":[7.9506,44.1132],"type":"Point"}
}