{
  "type": "Feature",
  "properties": {
    "gn:admin1_code":"6",
    "gn:admin2_code":"UD",
    "gn:admin3_code":"30036.0",
    "gn:asciiname":"Borgo Scubla",
    "gn:country_code":"IT",
    "gn:dem":192,
    "gn:feature_class":"P",
    "gn:feature_code":"PPL",
    "gn:name":"Borgo Scubla",
    "gn:population":32,
    "gn:timezone":"Europe/Rome",
    "iso:country":"IT",
    "wof:name":"Borgo Scubla",
    "wof:placetype":"locality",
    "wof:population":32
},
  "geometry": {"coordinates":[13.35343,46.159],"type":"Point"}
}