{
  "type": "Feature",
  "properties": {
    "gn:admin1_code":"5.0",
    "gn:admin2_code":"RN",
    "gn:admin3_code":"99004.0",
    "gn:asciiname":"Monte Farneto",
    "gn:country_code":"IT",
    "gn:dem":283,
    "gn:feature_class":"P",
    "gn:feature_code":"PPL",
    "gn:name":"Monte Farneto",
    "gn:population":13,
    "gn:timezone":"Europe/Rome",
    "iso:country":"IT",
    "wof:name":"Monte Farneto",
    "wof:placetype":"locality",
    "wof:population":13
},
  "geometry": {"coordinates":[12.58181,43.89409000000001],"type":"Point"}
}