{
  "type": "Feature",
  "properties": {
    "gn:admin1_code":"4",
    "gn:admin2_code":"SA",
    "gn:admin3_code":"65050.0",
    "gn:asciiname":"Cuccaro",
    "gn:country_code":"IT",
    "gn:dem":183,
    "gn:feature_class":"P",
    "gn:feature_code":"PPL",
    "gn:name":"Cuccaro",
    "gn:population":30,
    "gn:timezone":"Europe/Rome",
    "iso:country":"IT",
    "name:deu_x_preferred":[
        "Cuccaro"
    ],
    "name:fra_x_preferred":[
        "Cuccaro"
    ],
    "name:ita_x_preferred":[
        "Cuccaro"
    ],
    "name:srp_x_preferred":[
        "Kukaro"
    ],
    "wof:name":"Cuccaro",
    "wof:placetype":"locality",
    "wof:population":30
},
  "geometry": {"coordinates":[15.02068,40.6449],"type":"Point"}
}