{
  "type": "Feature",
  "properties": {
    "gn:admin1_code":"7",
    "gn:admin2_code":"RM",
    "gn:admin3_code":"58112.0",
    "gn:asciiname":"Villaggio Acea",
    "gn:country_code":"IT",
    "gn:dem":251,
    "gn:feature_class":"P",
    "gn:feature_code":"PPL",
    "gn:name":"Villaggio Acea",
    "gn:population":59,
    "gn:timezone":"Europe/Rome",
    "iso:country":"IT",
    "wof:name":"Villaggio Acea",
    "wof:placetype":"locality",
    "wof:population":59
},
  "geometry": {"coordinates":[12.86283,41.98523],"type":"Point"}
}