{
  "type": "Feature",
  "properties": {
    "gn:admin1_code":"9",
    "gn:admin2_code":"BS",
    "gn:admin3_code":"17045.0",
    "gn:asciiname":"Campagna",
    "gn:country_code":"IT",
    "gn:dem":121,
    "gn:feature_class":"P",
    "gn:feature_code":"PPL",
    "gn:name":"Campagna",
    "gn:population":53,
    "gn:timezone":"Europe/Rome",
    "iso:country":"IT",
    "wof:name":"Campagna",
    "wof:placetype":"locality",
    "wof:population":53
},
  "geometry": {"coordinates":[10.0059,45.50441],"type":"Point"}
}