{
  "type": "Feature",
  "properties": {
    "gn:admin1_code":"5",
    "gn:admin2_code":"BO",
    "gn:admin3_code":"37032.0",
    "gn:asciiname":"La Bargellina",
    "gn:country_code":"IT",
    "gn:dem":182,
    "gn:feature_class":"P",
    "gn:feature_code":"PPL",
    "gn:name":"La Bargellina",
    "gn:population":14,
    "gn:timezone":"Europe/Rome",
    "iso:country":"IT",
    "wof:name":"La Bargellina",
    "wof:placetype":"locality",
    "wof:population":14
},
  "geometry": {"coordinates":[11.71018,44.31933],"type":"Point"}
}