{
  "type": "Feature",
  "properties": {
    "gn:admin1_code":"10",
    "gn:admin2_code":"AP",
    "gn:admin3_code":"44034.0",
    "gn:asciiname":"Croce Rossa",
    "gn:country_code":"IT",
    "gn:dem":437,
    "gn:feature_class":"P",
    "gn:feature_code":"PPL",
    "gn:name":"Croce Rossa",
    "gn:population":235,
    "gn:timezone":"Europe/Rome",
    "iso:country":"IT",
    "name:fra_x_preferred":[
        "Croix Rousse"
    ],
    "name:ita_x_preferred":[
        "Croce Rossa"
    ],
    "name:nno_x_preferred":[
        "Croce Rossa"
    ],
    "name:pol_x_preferred":[
        "Croce Rossa"
    ],
    "wof:name":"Croce Rossa",
    "wof:placetype":"locality",
    "wof:population":235
},
  "geometry": {"coordinates":[13.56312,42.97419],"type":"Point"}
}