{
  "type": "Feature",
  "properties": {
    "gn:admin1_code":"9",
    "gn:admin2_code":"BS",
    "gn:admin3_code":"17088.0",
    "gn:asciiname":"Feniletto",
    "gn:country_code":"IT",
    "gn:dem":60,
    "gn:feature_class":"P",
    "gn:feature_code":"PPL",
    "gn:name":"Feniletto",
    "gn:population":23,
    "gn:timezone":"Europe/Rome",
    "iso:country":"IT",
    "wof:name":"Feniletto",
    "wof:placetype":"locality",
    "wof:population":23
},
  "geometry": {"coordinates":[10.22982,45.34455],"type":"Point"}
}