{
  "type": "Feature",
  "properties": {
    "gn:admin1_code":"6.0",
    "gn:admin2_code":"UD",
    "gn:admin3_code":"30102.0",
    "gn:asciiname":"Codromaz",
    "gn:country_code":"IT",
    "gn:dem":561,
    "gn:feature_class":"P",
    "gn:feature_code":"PPL",
    "gn:name":"C\u00f2dromaz",
    "gn:population":0,
    "gn:timezone":"Europe/Rome",
    "iso:country":"IT",
    "wof:name":"Codromaz",
    "wof:placetype":"locality"
},
  "geometry": {"coordinates":[13.55028,46.10333],"type":"Point"}
}