{
  "type": "Feature",
  "properties": {
    "gn:admin1_code":"3",
    "gn:admin2_code":"CZ",
    "gn:admin3_code":"79023.0",
    "gn:asciiname":"Guglia",
    "gn:country_code":"IT",
    "gn:dem":71,
    "gn:feature_class":"P",
    "gn:feature_code":"PPL",
    "gn:name":"Guglia",
    "gn:population":137,
    "gn:timezone":"Europe/Rome",
    "iso:country":"IT",
    "wof:name":"Guglia",
    "wof:placetype":"locality",
    "wof:population":137
},
  "geometry": {"coordinates":[16.62074,38.87315],"type":"Point"}
}