{
  "type": "Feature",
  "properties": {
    "gn:admin1_code":"16.0",
    "gn:admin2_code":"FI",
    "gn:admin3_code":"48002.0",
    "gn:asciiname":"Bovecchio",
    "gn:country_code":"IT",
    "gn:dem":424,
    "gn:elevation":"634.0",
    "gn:feature_class":"P",
    "gn:feature_code":"PPL",
    "gn:name":"Bovecchio",
    "gn:population":23,
    "gn:timezone":"Europe/Rome",
    "iso:country":"IT",
    "wof:name":"Bovecchio",
    "wof:placetype":"locality",
    "wof:population":23
},
  "geometry": {"coordinates":[11.18846,43.98083],"type":"Point"}
}