{
  "type": "Feature",
  "properties": {
    "gn:admin1_code":"16.0",
    "gn:admin2_code":"FI",
    "gn:admin3_code":"48024.0",
    "gn:asciiname":"Marliano",
    "gn:country_code":"IT",
    "gn:dem":172,
    "gn:elevation":"170.0",
    "gn:feature_class":"P",
    "gn:feature_code":"PPL",
    "gn:name":"Marliano",
    "gn:population":78,
    "gn:timezone":"Europe/Rome",
    "iso:country":"IT",
    "wof:name":"Marliano",
    "wof:placetype":"locality",
    "wof:population":78
},
  "geometry": {"coordinates":[11.09592,43.73544],"type":"Point"}
}