{
  "type": "Feature",
  "properties": {
    "gn:admin1_code":"20",
    "gn:admin2_code":"TV",
    "gn:admin3_code":"26052.0",
    "gn:asciiname":"Bidoggia",
    "gn:country_code":"IT",
    "gn:dem":13,
    "gn:feature_class":"P",
    "gn:feature_code":"PPL",
    "gn:name":"Bidoggia",
    "gn:population":112,
    "gn:timezone":"Europe/Rome",
    "iso:country":"IT",
    "wof:name":"Bidoggia",
    "wof:placetype":"locality",
    "wof:population":112
},
  "geometry": {"coordinates":[12.42567,45.75881],"type":"Point"}
}