{
  "type": "Feature",
  "properties": {
    "gn:admin1_code":"5.0",
    "gn:admin2_code":"FE",
    "gn:admin3_code":"38008.0",
    "gn:asciiname":"La Sammartina",
    "gn:country_code":"IT",
    "gn:dem":8,
    "gn:feature_class":"P",
    "gn:feature_code":"PPL",
    "gn:name":"La Sammartina",
    "gn:population":416,
    "gn:timezone":"Europe/Rome",
    "iso:country":"IT",
    "wof:name":"La Sammartina",
    "wof:placetype":"locality",
    "wof:population":416
},
  "geometry": {"coordinates":[11.5932,44.80231],"type":"Point"}
}