{
  "type": "Feature",
  "properties": {
    "gn:admin1_code":"9",
    "gn:admin2_code":"MI",
    "gn:admin3_code":"15222.0",
    "gn:asciiname":"San Barbaziano",
    "gn:country_code":"IT",
    "gn:dem":94,
    "gn:feature_class":"P",
    "gn:feature_code":"PPL",
    "gn:name":"San Barbaziano",
    "gn:population":12,
    "gn:timezone":"Europe/Rome",
    "iso:country":"IT",
    "wof:name":"San Barbaziano",
    "wof:placetype":"locality",
    "wof:population":12
},
  "geometry": {"coordinates":[9.36959,45.39859000000001],"type":"Point"}
}