{
  "type": "Feature",
  "properties": {
    "gn:admin1_code":"17",
    "gn:admin2_code":"BZ",
    "gn:admin3_code":"21108.0",
    "gn:asciiname":"Steger Aue",
    "gn:country_code":"IT",
    "gn:dem":1028,
    "gn:feature_class":"P",
    "gn:feature_code":"PPL",
    "gn:name":"Steger Aue",
    "gn:population":59,
    "gn:timezone":"Europe/Rome",
    "iso:country":"IT",
    "wof:name":"Steger Aue",
    "wof:placetype":"locality",
    "wof:population":59
},
  "geometry": {"coordinates":[11.95486,46.98637],"type":"Point"}
}