{
  "type": "Feature",
  "properties": {
    "gn:admin1_code":"4.0",
    "gn:admin2_code":"BN",
    "gn:admin3_code":"62017.0",
    "gn:asciiname":"Sant'Angelo Radiginosa",
    "gn:country_code":"IT",
    "gn:dem":870,
    "gn:feature_class":"P",
    "gn:feature_code":"PPL",
    "gn:name":"Sant'Angelo Radiginosa",
    "gn:population":0,
    "gn:timezone":"Europe/Rome",
    "iso:country":"IT",
    "wof:name":"Sant'Angelo Radiginosa",
    "wof:placetype":"locality"
},
  "geometry": {"coordinates":[14.76667,41.41667],"type":"Point"}
}