{
  "type": "Feature",
  "properties": {
    "gn:admin1_code":"16.0",
    "gn:admin2_code":"FI",
    "gn:admin3_code":"48021.0",
    "gn:asciiname":"Poggio Alla Croce",
    "gn:country_code":"IT",
    "gn:dem":494,
    "gn:feature_class":"P",
    "gn:feature_code":"PPL",
    "gn:name":"Poggio Alla Croce",
    "gn:population":0,
    "gn:timezone":"Europe/Rome",
    "iso:country":"IT",
    "wof:name":"Poggio Alla Croce",
    "wof:placetype":"locality"
},
  "geometry": {"coordinates":[11.39402,43.65139],"type":"Point"}
}