{
  "type": "Feature",
  "properties": {
    "gn:admin1_code":"7",
    "gn:admin2_code":"VT",
    "gn:admin3_code":"56048.0",
    "gn:asciiname":"Selvarella",
    "gn:country_code":"IT",
    "gn:dem":354,
    "gn:feature_class":"P",
    "gn:feature_code":"PPL",
    "gn:name":"Selvarella",
    "gn:population":111,
    "gn:timezone":"Europe/Rome",
    "iso:country":"IT",
    "wof:name":"Selvarella",
    "wof:placetype":"locality",
    "wof:population":111
},
  "geometry": {"coordinates":[12.23649,42.43535],"type":"Point"}
}