{
  "type": "Feature",
  "properties": {
    "gn:admin1_code":"12",
    "gn:admin2_code":"TO",
    "gn:admin3_code":"1067.0",
    "gn:asciiname":"Cicolelio",
    "gn:country_code":"IT",
    "gn:dem":813,
    "gn:feature_class":"P",
    "gn:feature_code":"PPL",
    "gn:name":"Cicolelio",
    "gn:population":14,
    "gn:timezone":"Europe/Rome",
    "iso:country":"IT",
    "wof:name":"Cicolelio",
    "wof:placetype":"locality",
    "wof:population":14
},
  "geometry": {"coordinates":[7.69213,45.44241],"type":"Point"}
}