{
  "type": "Feature",
  "properties": {
    "gn:admin1_code":"16",
    "gn:admin2_code":"MS",
    "gn:admin3_code":"45008.0",
    "gn:asciiname":"Paghezzana",
    "gn:country_code":"IT",
    "gn:dem":188,
    "gn:feature_class":"P",
    "gn:feature_code":"PPL",
    "gn:name":"Paghezzana",
    "gn:population":46,
    "gn:timezone":"Europe/Rome",
    "iso:country":"IT",
    "wof:name":"Paghezzana",
    "wof:placetype":"locality",
    "wof:population":46
},
  "geometry": {"coordinates":[9.98434,44.12685],"type":"Point"}
}