{
  "type": "Feature",
  "properties": {
    "gn:admin1_code":"9",
    "gn:admin2_code":"BS",
    "gn:admin3_code":"17189.0",
    "gn:asciiname":"Fucine",
    "gn:country_code":"IT",
    "gn:dem":556,
    "gn:feature_class":"P",
    "gn:feature_code":"PPL",
    "gn:name":"Fucine",
    "gn:population":14,
    "gn:timezone":"Europe/Rome",
    "iso:country":"IT",
    "wof:name":"Fucine",
    "wof:placetype":"locality",
    "wof:population":14
},
  "geometry": {"coordinates":[10.75369,45.79021],"type":"Point"}
}