{
  "type": "Feature",
  "properties": {
    "gn:admin1_code":"10",
    "gn:admin2_code":"MC",
    "gn:admin3_code":"43007.0",
    "gn:asciiname":"Sellano",
    "gn:country_code":"IT",
    "gn:dem":517,
    "gn:feature_class":"P",
    "gn:feature_code":"PPL",
    "gn:name":"Sellano",
    "gn:population":29,
    "gn:timezone":"Europe/Rome",
    "iso:country":"IT",
    "name:ara_x_preferred":[
        "\u0633\u064a\u0644\u0627\u0646\u0648"
    ],
    "name:azb_x_preferred":[
        "\u0633\u0644\u0627\u0646\u0648"
    ],
    "name:bel_x_preferred":[
        "\u0421\u0435\u043b\u0430\u043d\u0430"
    ],
    "name:bul_x_preferred":[
        "\u0421\u0435\u043b\u0430\u043d\u043e"
    ],
    "name:cat_x_preferred":[
        "Sellano"
    ],
    "name:ceb_x_preferred":[
        "Sellano"
    ],
    "name:deu_x_preferred":[
        "Sellano"
    ],
    "name:epo_x_preferred":[
        "Sellano"
    ],
    "name:eus_x_preferred":[
        "Sellano"
    ],
    "name:fas_x_preferred":[
        "\u0633\u0644\u0627\u0646\u0648"
    ],
    "name:fra_x_preferred":[
        "Sellano"
    ],
    "name:hun_x_preferred":[
        "Sellano"
    ],
    "name:hye_x_preferred":[
        "\u054d\u0565\u056c\u0561\u0576\u0578"
    ],
    "name:ind_x_preferred":[
        "Sellano"
    ],
    "name:ita_x_preferred":[
        "Sellano"
    ],
    "name:jpn_x_preferred":[
        "\u30bb\u30c3\u30e9\u30fc\u30ce"
    ],
    "name:kaz_x_preferred":[
        "\u0421\u0435\u043b\u043b\u0430\u043d\u043e"
    ],
    "name:kor_x_preferred":[
        "\uc140\ub77c\ub178"
    ],
    "name:lat_x_preferred":[
        "Syllanum"
    ],
    "name:lmo_x_preferred":[
        "Sellano"
    ],
    "name:ltz_x_preferred":[
        "Sellano"
    ],
    "name:msa_x_preferred":[
        "Sellano"
    ],
    "name:nap_x_preferred":[
        "Sellano"
    ],
    "name:nld_x_preferred":[
        "Sellano"
    ],
    "name:pms_x_preferred":[
        "Sellano"
    ],
    "name:pol_x_preferred":[
        "Sellano"
    ],
    "name:por_x_preferred":[
        "Sellano"
    ],
    "name:ron_x_preferred":[
        "Sellano"
    ],
    "name:rus_x_preferred":[
        "\u0421\u0435\u043b\u043b\u0430\u043d\u043e"
    ],
    "name:scn_x_preferred":[
        "Sellanu"
    ],
    "name:spa_x_preferred":[
        "Sellano"
    ],
    "name:srp_x_preferred":[
        "\u0421\u0435\u043b\u0430\u043d\u043e"
    ],
    "name:tgl_x_preferred":[
        "Sellano"
    ],
    "name:tur_x_preferred":[
        "Sellano"
    ],
    "name:ukr_x_preferred":[
        "\u0421\u0435\u043b\u043b\u0430\u043d\u043e"
    ],
    "name:uzb_x_preferred":[
        "Sellano"
    ],
    "name:vie_x_preferred":[
        "Sellano"
    ],
    "name:vol_x_preferred":[
        "Sellano"
    ],
    "name:war_x_preferred":[
        "Sellano"
    ],
    "name:zho_x_preferred":[
        "\u585e\u62c9\u8bfa"
    ],
    "wof:name":"Sellano",
    "wof:placetype":"locality",
    "wof:population":29
},
  "geometry": {"coordinates":[13.01402,43.1542],"type":"Point"}
}