{
  "type": "Feature",
  "properties": {
    "gn:admin1_code":"10",
    "gn:admin2_code":"MC",
    "gn:admin3_code":"43007.0",
    "gn:asciiname":"Sellano",
    "gn:country_code":"IT",
    "gn:dem":517,
    "gn:feature_class":"P",
    "gn:feature_code":"PPL",
    "gn:name":"Sellano",
    "gn:population":29,
    "gn:timezone":"Europe/Rome",
    "iso:country":"IT",
    "wof:name":"Sellano",
    "wof:placetype":"locality",
    "wof:population":29
},
  "geometry": {"coordinates":[13.01402,43.1542],"type":"Point"}
}