{
  "type": "Feature",
  "properties": {
    "gn:admin1_code":"6.0",
    "gn:admin2_code":"UD",
    "gn:admin3_code":"30007.0",
    "gn:asciiname":"Zona Industriale di Attimis",
    "gn:country_code":"IT",
    "gn:dem":175,
    "gn:feature_class":"P",
    "gn:feature_code":"PPL",
    "gn:name":"Zona Industriale di Attimis",
    "gn:population":15,
    "gn:timezone":"Europe/Rome",
    "iso:country":"IT",
    "wof:name":"Zona Industriale di Attimis",
    "wof:placetype":"locality",
    "wof:population":15
},
  "geometry": {"coordinates":[13.29738,46.18192],"type":"Point"}
}