{
  "type": "Feature",
  "properties": {
    "gn:admin1_code":"20.0",
    "gn:admin2_code":"VE",
    "gn:admin3_code":"27031.0",
    "gn:asciiname":"Trepalade",
    "gn:country_code":"IT",
    "gn:dem":2,
    "gn:elevation":"2.0",
    "gn:feature_class":"P",
    "gn:feature_code":"PPL",
    "gn:name":"Trepalade",
    "gn:population":53,
    "gn:timezone":"Europe/Rome",
    "iso:country":"IT",
    "wof:name":"Trepalade",
    "wof:placetype":"locality",
    "wof:population":53
},
  "geometry": {"coordinates":[12.41088,45.56317],"type":"Point"}
}