{
  "type": "Feature",
  "properties": {
    "gn:admin1_code":"10",
    "gn:admin2_code":"MC",
    "gn:admin3_code":"43024.0",
    "gn:asciiname":"Vinano",
    "gn:country_code":"IT",
    "gn:dem":509,
    "gn:feature_class":"P",
    "gn:feature_code":"PPLL",
    "gn:name":"Vinano",
    "gn:population":10,
    "gn:timezone":"Europe/Rome",
    "iso:country":"IT",
    "wof:name":"Vinano",
    "wof:placetype":"locality",
    "wof:population":10
},
  "geometry": {"coordinates":[13.04342,43.28644],"type":"Point"}
}