{
  "type": "Feature",
  "properties": {
    "gn:admin1_code":"1.0",
    "gn:admin2_code":"TE",
    "gn:admin3_code":"67008.0",
    "gn:asciiname":"Castelnuovo",
    "gn:country_code":"IT",
    "gn:dem":364,
    "gn:feature_class":"P",
    "gn:feature_code":"PPL",
    "gn:name":"Castelnuovo",
    "gn:population":738,
    "gn:timezone":"Europe/Rome",
    "iso:country":"IT",
    "wof:name":"Castelnuovo",
    "wof:placetype":"locality",
    "wof:population":738
},
  "geometry": {"coordinates":[13.69604,42.72987],"type":"Point"}
}