{
  "type": "Feature",
  "properties": {
    "gn:admin1_code":"10",
    "gn:admin2_code":"PU",
    "gn:admin3_code":"41069.0",
    "gn:asciiname":"Pozzuolo",
    "gn:country_code":"IT",
    "gn:dem":307,
    "gn:feature_class":"P",
    "gn:feature_code":"PPL",
    "gn:name":"Pozzuolo",
    "gn:population":33,
    "gn:timezone":"Europe/Rome",
    "iso:country":"IT",
    "name:ceb_x_preferred":[
        "Pozzuolo"
    ],
    "name:ita_x_preferred":[
        "Pozzuolo"
    ],
    "name:nld_x_preferred":[
        "Pozzuolo"
    ],
    "name:srp_x_preferred":[
        "\u041f\u043e\u0446\u0443\u043e\u043b\u043e"
    ],
    "wof:name":"Pozzuolo",
    "wof:placetype":"locality",
    "wof:population":33
},
  "geometry": {"coordinates":[12.84862,43.76475],"type":"Point"}
}