{
  "type": "Feature",
  "properties": {
    "gn:admin1_code":"10.0",
    "gn:admin2_code":"AP",
    "gn:admin3_code":"44006.0",
    "gn:asciiname":"Faete",
    "gn:country_code":"IT",
    "gn:dem":764,
    "gn:elevation":"756.0",
    "gn:feature_class":"P",
    "gn:feature_code":"PPL",
    "gn:name":"Faete",
    "gn:population":76,
    "gn:timezone":"Europe/Rome",
    "iso:country":"IT",
    "wof:name":"Faete",
    "wof:placetype":"locality",
    "wof:population":76
},
  "geometry": {"coordinates":[13.30663,42.76986],"type":"Point"}
}