{
  "type": "Feature",
  "properties": {
    "gn:admin1_code":"13",
    "gn:admin2_code":"BA",
    "gn:admin3_code":"72019.0",
    "gn:asciiname":"Frantoio Pietre",
    "gn:country_code":"IT",
    "gn:dem":187,
    "gn:feature_class":"P",
    "gn:feature_code":"PPL",
    "gn:name":"Frantoio Pietre",
    "gn:population":24,
    "gn:timezone":"Europe/Rome",
    "iso:country":"IT",
    "wof:name":"Frantoio Pietre",
    "wof:placetype":"locality",
    "wof:population":24
},
  "geometry": {"coordinates":[17.09979,40.97842],"type":"Point"}
}