{
  "type": "Feature",
  "properties": {
    "gn:admin1_code":"5.0",
    "gn:admin2_code":"RN",
    "gn:admin3_code":"99015.0",
    "gn:asciiname":"Pedreto",
    "gn:cc2":"IT",
    "gn:country_code":"IT",
    "gn:dem":285,
    "gn:feature_class":"P",
    "gn:feature_code":"PPL",
    "gn:name":"Pedreto",
    "gn:population":16,
    "gn:timezone":"Europe/Rome",
    "iso:country":"IT",
    "name:und_x_variant":[
        "Cerreto",
        "Cereto"
    ],
    "wof:name":"Pedreto",
    "wof:placetype":"locality",
    "wof:population":16
},
  "geometry": {"coordinates":[12.63702,43.85251],"type":"Point"}
}