{
  "type": "Feature",
  "properties": {
    "gn:admin1_code":"7.0",
    "gn:admin2_code":"VT",
    "gn:admin3_code":"56042.0",
    "gn:asciiname":"Stazione di Bassano in Teverina",
    "gn:country_code":"IT",
    "gn:dem":70,
    "gn:feature_class":"P",
    "gn:feature_code":"PPL",
    "gn:name":"Stazione di Bassano in Teverina",
    "gn:population":5,
    "gn:timezone":"Europe/Rome",
    "iso:country":"IT",
    "wof:name":"Stazione di Bassano in Teverina",
    "wof:placetype":"locality",
    "wof:population":5
},
  "geometry": {"coordinates":[12.3325,42.4836],"type":"Point"}
}