{
  "type": "Feature",
  "properties": {
    "gn:admin1_code":"6",
    "gn:admin2_code":"UD",
    "gn:admin3_code":"30036.0",
    "gn:asciiname":"Borgo Stremiz",
    "gn:country_code":"IT",
    "gn:dem":324,
    "gn:feature_class":"P",
    "gn:feature_code":"PPL",
    "gn:name":"Borgo Stremiz",
    "gn:population":33,
    "gn:timezone":"Europe/Rome",
    "iso:country":"IT",
    "wof:name":"Borgo Stremiz",
    "wof:placetype":"locality",
    "wof:population":33
},
  "geometry": {"coordinates":[13.37553,46.17172],"type":"Point"}
}