{
  "type": "Feature",
  "properties": {
    "gn:admin1_code":"5",
    "gn:admin2_code":"RE",
    "gn:admin3_code":"35027.0",
    "gn:asciiname":"Spadarotta",
    "gn:country_code":"IT",
    "gn:dem":62,
    "gn:feature_class":"P",
    "gn:feature_code":"PPL",
    "gn:name":"Spadarotta",
    "gn:population":18,
    "gn:timezone":"Europe/Rome",
    "iso:country":"IT",
    "wof:name":"Spadarotta",
    "wof:placetype":"locality",
    "wof:population":18
},
  "geometry": {"coordinates":[10.48916,44.72667],"type":"Point"}
}