{
  "type": "Feature",
  "properties": {
    "gn:admin1_code":"12",
    "gn:admin2_code":"TO",
    "gn:admin3_code":"1262.0",
    "gn:asciiname":"Tetti Bavento",
    "gn:country_code":"IT",
    "gn:dem":436,
    "gn:feature_class":"P",
    "gn:feature_code":"PPL",
    "gn:name":"Tetti Bavento",
    "gn:population":59,
    "gn:timezone":"Europe/Rome",
    "iso:country":"IT",
    "wof:name":"Tetti Bavento",
    "wof:placetype":"locality",
    "wof:population":59
},
  "geometry": {"coordinates":[7.85578,45.09694],"type":"Point"}
}