{
  "type": "Feature",
  "properties": {
    "gn:admin1_code":"5",
    "gn:admin2_code":"BO",
    "gn:admin3_code":"37062.0",
    "gn:asciiname":"Lucaiola",
    "gn:country_code":"IT",
    "gn:dem":536,
    "gn:feature_class":"P",
    "gn:feature_code":"PPLL",
    "gn:name":"Lucaiola",
    "gn:population":9,
    "gn:timezone":"Europe/Rome",
    "iso:country":"IT",
    "wof:name":"Lucaiola",
    "wof:placetype":"locality",
    "wof:population":9
},
  "geometry": {"coordinates":[10.97979,44.14111],"type":"Point"}
}