{
  "type": "Feature",
  "properties": {
    "gn:admin1_code":"9",
    "gn:admin2_code":"BG",
    "gn:admin3_code":"16116.0",
    "gn:asciiname":"Fondo Ripa",
    "gn:country_code":"IT",
    "gn:dem":521,
    "gn:feature_class":"P",
    "gn:feature_code":"PPL",
    "gn:name":"Fondo Ripa",
    "gn:population":76,
    "gn:timezone":"Europe/Rome",
    "iso:country":"IT",
    "wof:name":"Fondo Ripa",
    "wof:placetype":"locality",
    "wof:population":76
},
  "geometry": {"coordinates":[9.85077,45.85839],"type":"Point"}
}