{
  "type": "Feature",
  "properties": {
    "gn:admin1_code":"5",
    "gn:admin2_code":"FC",
    "gn:admin3_code":"40012.0",
    "gn:asciiname":"Giulianini Pantoli",
    "gn:country_code":"IT",
    "gn:dem":11,
    "gn:feature_class":"P",
    "gn:feature_code":"PPL",
    "gn:name":"Giulianini Pantoli",
    "gn:population":15,
    "gn:timezone":"Europe/Rome",
    "iso:country":"IT",
    "wof:name":"Giulianini Pantoli",
    "wof:placetype":"locality",
    "wof:population":15
},
  "geometry": {"coordinates":[12.03677,44.31628],"type":"Point"}
}