{
  "type": "Feature",
  "properties": {
    "gn:admin1_code":"1",
    "gn:admin2_code":"CH",
    "gn:admin3_code":"69064.0",
    "gn:asciiname":"Capolegrotti",
    "gn:country_code":"IT",
    "gn:dem":470,
    "gn:feature_class":"P",
    "gn:feature_code":"PPL",
    "gn:name":"Capolegrotti",
    "gn:population":48,
    "gn:timezone":"Europe/Rome",
    "iso:country":"IT",
    "wof:name":"Capolegrotti",
    "wof:placetype":"locality",
    "wof:population":48
},
  "geometry": {"coordinates":[14.2041,42.15215],"type":"Point"}
}