{
  "type": "Feature",
  "properties": {
    "gn:admin1_code":"19.0",
    "gn:admin2_code":"AO",
    "gn:admin3_code":"7054.0",
    "gn:asciiname":"Ville Sur Nus",
    "gn:country_code":"IT",
    "gn:dem":1130,
    "gn:feature_class":"P",
    "gn:feature_code":"PPL",
    "gn:name":"Ville Sur Nus",
    "gn:population":91,
    "gn:timezone":"Europe/Rome",
    "iso:country":"IT",
    "wof:name":"Ville Sur Nus",
    "wof:placetype":"locality",
    "wof:population":91
},
  "geometry": {"coordinates":[7.45084,45.7605],"type":"Point"}
}