{
  "type": "Feature",
  "properties": {
    "gn:admin1_code":"16",
    "gn:admin2_code":"LU",
    "gn:admin3_code":"46015.0",
    "gn:asciiname":"Colle Aginaia",
    "gn:country_code":"IT",
    "gn:dem":161,
    "gn:feature_class":"P",
    "gn:feature_code":"PPL",
    "gn:name":"Colle Aginaia",
    "gn:population":47,
    "gn:timezone":"Europe/Rome",
    "iso:country":"IT",
    "wof:name":"Colle Aginaia",
    "wof:placetype":"locality",
    "wof:population":47
},
  "geometry": {"coordinates":[10.48456,44.03615],"type":"Point"}
}