{
  "type": "Feature",
  "properties": {
    "gn:admin1_code":"5",
    "gn:admin2_code":"RE",
    "gn:admin3_code":"35043.0",
    "gn:asciiname":"Pedergnano",
    "gn:country_code":"IT",
    "gn:dem":341,
    "gn:feature_class":"P",
    "gn:feature_code":"PPL",
    "gn:name":"Pedergnano",
    "gn:population":17,
    "gn:timezone":"Europe/Rome",
    "iso:country":"IT",
    "wof:name":"Pedergnano",
    "wof:placetype":"locality",
    "wof:population":17
},
  "geometry": {"coordinates":[10.51323,44.58225],"type":"Point"}
}