{
  "type": "Feature",
  "properties": {
    "gn:admin1_code":"1",
    "gn:admin2_code":"PE",
    "gn:admin3_code":"68041.0",
    "gn:asciiname":"Di Zio",
    "gn:country_code":"IT",
    "gn:dem":19,
    "gn:feature_class":"P",
    "gn:feature_code":"PPL",
    "gn:name":"Di Zio",
    "gn:population":45,
    "gn:timezone":"Europe/Rome",
    "iso:country":"IT",
    "wof:name":"Di Zio",
    "wof:placetype":"locality",
    "wof:population":45
},
  "geometry": {"coordinates":[14.15387,42.41834],"type":"Point"}
}