{
  "type": "Feature",
  "properties": {
    "gn:admin1_code":"1",
    "gn:admin2_code":"CH",
    "gn:admin3_code":"69073.0",
    "gn:asciiname":"Liberati",
    "gn:country_code":"IT",
    "gn:dem":290,
    "gn:feature_class":"P",
    "gn:feature_code":"PPL",
    "gn:name":"Liberati",
    "gn:population":31,
    "gn:timezone":"Europe/Rome",
    "iso:country":"IT",
    "name:swe_x_preferred":[
        "Liberati"
    ],
    "name:ukr_x_preferred":[
        "\u041b\u0456\u0431\u0435\u0440\u0430\u0442\u0456"
    ],
    "wof:name":"Liberati",
    "wof:placetype":"locality",
    "wof:population":31
},
  "geometry": {"coordinates":[14.11768,42.25874],"type":"Point"}
}