{
  "type": "Feature",
  "properties": {
    "gn:elevation":454,
    "gn:population":590,
    "iso:country":"IT",
    "name:azb_x_preferred":[
        "\u0645\u0648\u0686\u06cc\u0627"
    ],
    "name:bel_x_preferred":[
        "\u041c\u0443\u0447\u0430"
    ],
    "name:bul_x_preferred":[
        "\u041c\u0443\u0447\u0430"
    ],
    "name:cat_x_preferred":[
        "Muccia"
    ],
    "name:ceb_x_preferred":[
        "Muccia"
    ],
    "name:deu_x_preferred":[
        "Muccia"
    ],
    "name:eng_x_preferred":[
        "Muccia"
    ],
    "name:epo_x_preferred":[
        "Muccia"
    ],
    "name:eus_x_preferred":[
        "Muccia"
    ],
    "name:fas_x_preferred":[
        "\u0645\u0648\u0686\u06cc\u0627"
    ],
    "name:fra_x_preferred":[
        "Muccia"
    ],
    "name:hbs_x_preferred":[
        "Muccia"
    ],
    "name:hun_x_preferred":[
        "Muccia"
    ],
    "name:hye_x_preferred":[
        "\u0544\u0578\u0582\u0579\u0561"
    ],
    "name:ina_x_preferred":[
        "Muccia"
    ],
    "name:ita_x_colloquial":[
        "Muccia Vallicchio"
    ],
    "name:ita_x_preferred":[
        "Muccia"
    ],
    "name:ita_x_variant":[
        "M\u00faccia Vallicchio"
    ],
    "name:jpn_x_preferred":[
        "\u30e0\u30c3\u30c1\u30e3"
    ],
    "name:kaz_x_preferred":[
        "\u041c\u0443\u0447\u0447\u0430"
    ],
    "name:lat_x_preferred":[
        "Mutia"
    ],
    "name:lmo_x_preferred":[
        "Muccia"
    ],
    "name:msa_x_preferred":[
        "Muccia"
    ],
    "name:nan_x_preferred":[
        "Muccia"
    ],
    "name:nap_x_preferred":[
        "Muccia"
    ],
    "name:nld_x_preferred":[
        "Muccia"
    ],
    "name:oci_x_preferred":[
        "Muccia"
    ],
    "name:pms_x_preferred":[
        "Muccia"
    ],
    "name:pol_x_preferred":[
        "Muccia"
    ],
    "name:por_x_preferred":[
        "Muccia"
    ],
    "name:ron_x_preferred":[
        "Muccia"
    ],
    "name:rus_x_preferred":[
        "\u041c\u0443\u0447\u0447\u0430"
    ],
    "name:spa_x_preferred":[
        "Muccia"
    ],
    "name:srp_x_preferred":[
        "\u041c\u0443\u0447\u0430"
    ],
    "name:srp_x_variant":[
        "Muccia"
    ],
    "name:tgl_x_preferred":[
        "Muccia"
    ],
    "name:ukr_x_preferred":[
        "\u041c\u0443\u0447\u0447\u0430"
    ],
    "name:uzb_x_preferred":[
        "Muccia"
    ],
    "name:vie_x_preferred":[
        "Muccia"
    ],
    "name:vol_x_preferred":[
        "Muccia"
    ],
    "name:war_x_preferred":[
        "Muccia"
    ],
    "name:zho_min_nan_x_preferred":[
        "Muccia"
    ],
    "name:zho_x_preferred":[
        "\u7a46\u6070"
    ],
    "qs:a0":"Italia",
    "qs:a1":"*Macerata",
    "qs:a1r":"0Marche",
    "qs:adm0":"Italia",
    "qs:la_lc":"*",
    "qs:level":"locality",
    "qs:loc":"Muccia",
    "qs:loc_alt":"Muccia",
    "qs:pop":0,
    "qs:type":"buffered point",
    "wd:wordcount":107,
    "wof:name":"Muccia",
    "wof:placetype":"locality",
    "wof:population":590
},
  "geometry": {"coordinates":[13.04444,43.081939],"type":"Point"}
}