{
  "type": "Feature",
  "properties": {
    "gn:admin1_code":"12",
    "gn:admin2_code":"VC",
    "gn:admin3_code":"2163.0",
    "gn:asciiname":"San Marco",
    "gn:country_code":"IT",
    "gn:dem":174,
    "gn:feature_class":"P",
    "gn:feature_code":"PPL",
    "gn:name":"San Marco",
    "gn:population":120,
    "gn:timezone":"Europe/Rome",
    "iso:country":"IT",
    "wof:name":"San Marco",
    "wof:placetype":"locality",
    "wof:population":120
},
  "geometry": {"coordinates":[8.33026,45.45871],"type":"Point"}
}