{
  "type": "Feature",
  "properties": {
    "gn:admin1_code":"10",
    "gn:admin2_code":"AN",
    "gn:admin3_code":"42045.0",
    "gn:asciiname":"Vasari",
    "gn:country_code":"IT",
    "gn:dem":142,
    "gn:feature_class":"P",
    "gn:feature_code":"PPL",
    "gn:name":"Vasari",
    "gn:population":254,
    "gn:timezone":"Europe/Rome",
    "iso:country":"IT",
    "wof:name":"Vasari",
    "wof:placetype":"locality",
    "wof:population":254
},
  "geometry": {"coordinates":[13.23712,43.65527],"type":"Point"}
}