{
  "type": "Feature",
  "properties": {
    "iso:country":"IT",
    "name:ita_x_colloquial":[
        "Citta Nuova"
    ],
    "name:ita_x_preferred":[
        "Citt\u00e0 Nuova"
    ],
    "qs:gn_adm0_cc":"IT",
    "qs:gn_fcode":"PPLX",
    "qs:gn_local":3165926,
    "qs:gn_nam_loc":"Taranto, Taranto, Taranto, Puglia, IT",
    "qs:gn_namadm1":"13",
    "qs:gn_name":"Citt\u00e0 Nuova",
    "qs:local_max":3126,
    "qs:local_sum":4487,
    "qs:localhoods":3,
    "qs:name":"Citt\u00e0 Nuova",
    "qs:name_adm0":"Italia",
    "qs:name_adm1":"Puglia",
    "qs:name_adm2":"Taranto",
    "qs:name_lau":"Taranto",
    "qs:name_local":"Taranto",
    "qs:photo_max":195,
    "qs:photo_sum":1161,
    "qs:placetype":"Suburb",
    "qs:quad_count":66,
    "qs:woe_adm0":23424853,
    "qs:woe_adm1":7153342,
    "qs:woe_adm2":12591895,
    "qs:woe_lau":20076972,
    "qs:woe_local":724706,
    "qs:woe_ver":"7.10.0",
    "wof:lang":[
        "ita"
    ],
    "wof:name":"Citt\u00e0 Nuova",
    "wof:placetype":"neighbourhood"
},
  "geometry": {"coordinates":[17.250222,40.465656],"type":"Point"}
}