{
  "type": "Feature",
  "properties": {
    "gn:admin1_code":"9.0",
    "gn:admin2_code":"BS",
    "gn:admin3_code":"17125.0",
    "gn:asciiname":"Pudiano",
    "gn:country_code":"IT",
    "gn:dem":81,
    "gn:feature_class":"P",
    "gn:feature_code":"PPL",
    "gn:name":"Pudiano",
    "gn:population":35,
    "gn:timezone":"Europe/Rome",
    "iso:country":"IT",
    "wof:name":"Pudiano",
    "wof:placetype":"locality",
    "wof:population":35
},
  "geometry": {"coordinates":[10.00966,45.39926],"type":"Point"}
}