{
  "type": "Feature",
  "properties": {
    "gn:admin1_code":"10",
    "gn:admin2_code":"MC",
    "gn:admin3_code":"43007.0",
    "gn:asciiname":"Morro",
    "gn:country_code":"IT",
    "gn:dem":560,
    "gn:feature_class":"P",
    "gn:feature_code":"PPL",
    "gn:name":"Morro",
    "gn:population":59,
    "gn:timezone":"Europe/Rome",
    "iso:country":"IT",
    "wof:name":"Morro",
    "wof:placetype":"locality",
    "wof:population":59
},
  "geometry": {"coordinates":[13.02903,43.11459],"type":"Point"}
}