{
  "type": "Feature",
  "properties": {
    "gn:admin1_code":"20",
    "gn:admin2_code":"VR",
    "gn:admin3_code":"23053.0",
    "gn:asciiname":"Motta",
    "gn:country_code":"IT",
    "gn:dem":22,
    "gn:feature_class":"P",
    "gn:feature_code":"PPL",
    "gn:name":"Motta",
    "gn:population":25,
    "gn:timezone":"Europe/Rome",
    "iso:country":"IT",
    "wof:name":"Motta",
    "wof:placetype":"locality",
    "wof:population":25
},
  "geometry": {"coordinates":[11.03699,45.21185],"type":"Point"}
}