{
  "type": "Feature",
  "properties": {
    "gn:admin1_code":"5",
    "gn:admin2_code":"PR",
    "gn:admin3_code":"34009.0",
    "gn:asciiname":"Villanuova",
    "gn:country_code":"IT",
    "gn:dem":129,
    "gn:feature_class":"P",
    "gn:feature_code":"PPL",
    "gn:name":"Villanuova",
    "gn:population":20,
    "gn:timezone":"Europe/Rome",
    "iso:country":"IT",
    "wof:name":"Villanuova",
    "wof:placetype":"locality",
    "wof:population":20
},
  "geometry": {"coordinates":[10.15338,44.71758],"type":"Point"}
}