{
  "type": "Feature",
  "properties": {
    "gn:admin1_code":"17.0",
    "gn:admin2_code":"TN",
    "gn:admin3_code":"22039.0",
    "gn:asciiname":"Lorenz",
    "gn:country_code":"IT",
    "gn:dem":1611,
    "gn:elevation":"1626.0",
    "gn:feature_class":"P",
    "gn:feature_code":"PPL",
    "gn:name":"Lorenz",
    "gn:population":0,
    "gn:timezone":"Europe/Rome",
    "iso:country":"IT",
    "wof:name":"Lorenz",
    "wof:placetype":"locality"
},
  "geometry": {"coordinates":[11.80346,46.46031],"type":"Point"}
}