{
  "type": "Feature",
  "properties": {
    "gn:admin1_code":"17.0",
    "gn:admin2_code":"TN",
    "gn:admin3_code":"22039.0",
    "gn:asciiname":"Lorenz",
    "gn:country_code":"IT",
    "gn:dem":1611,
    "gn:elevation":"1626.0",
    "gn:feature_class":"P",
    "gn:feature_code":"PPL",
    "gn:name":"Lorenz",
    "gn:population":0,
    "gn:timezone":"Europe/Rome",
    "iso:country":"IT",
    "name:bel_x_preferred":[
        "\u041b\u043e\u0440\u044d\u043d\u0446"
    ],
    "name:bul_x_preferred":[
        "\u041b\u043e\u0440\u0435\u043d\u0446"
    ],
    "name:ces_x_preferred":[
        "Lorenz"
    ],
    "name:deu_x_preferred":[
        "Lorenz"
    ],
    "name:fin_x_preferred":[
        "Lorenz"
    ],
    "name:fra_x_preferred":[
        "Lorenz"
    ],
    "name:heb_x_preferred":[
        "\u05dc\u05d5\u05e8\u05e0\u05e5"
    ],
    "name:ita_x_preferred":[
        "Lorenz"
    ],
    "name:jpn_x_preferred":[
        "\u30ed\u30fc\u30ec\u30f3\u30c4"
    ],
    "name:kor_x_preferred":[
        "\ub85c\ub80c\uce20"
    ],
    "name:lav_x_preferred":[
        "Lorencs"
    ],
    "name:nld_x_preferred":[
        "Lorenz"
    ],
    "name:rus_x_preferred":[
        "\u041b\u043e\u0440\u0435\u043d\u0446"
    ],
    "name:slv_x_preferred":[
        "Lorenz"
    ],
    "name:spa_x_preferred":[
        "Lorenz"
    ],
    "name:ukr_x_preferred":[
        "\u041b\u043e\u0440\u0435\u043d\u0446"
    ],
    "name:zho_x_preferred":[
        "\u6d1b\u4f26\u5179"
    ],
    "wof:name":"Lorenz",
    "wof:placetype":"locality"
},
  "geometry": {"coordinates":[11.80346,46.46031],"type":"Point"}
}