{
  "type": "Feature",
  "properties": {
    "gn:admin1_code":"20.0",
    "gn:admin2_code":"VR",
    "gn:admin3_code":"23096.0",
    "gn:asciiname":"Casette del Chiodo",
    "gn:country_code":"IT",
    "gn:dem":45,
    "gn:feature_class":"P",
    "gn:feature_code":"PPL",
    "gn:name":"Casette del Chiodo",
    "gn:population":14,
    "gn:timezone":"Europe/Rome",
    "iso:country":"IT",
    "wof:name":"Casette del Chiodo",
    "wof:placetype":"locality",
    "wof:population":14
},
  "geometry": {"coordinates":[10.93501,45.36857],"type":"Point"}
}