{
  "type": "Feature",
  "properties": {
    "gn:admin1_code":"12",
    "gn:admin2_code":"AT",
    "gn:admin3_code":"5108.0",
    "gn:asciiname":"Besusso",
    "gn:country_code":"IT",
    "gn:dem":255,
    "gn:feature_class":"P",
    "gn:feature_code":"PPL",
    "gn:name":"Besusso",
    "gn:population":21,
    "gn:timezone":"Europe/Rome",
    "iso:country":"IT",
    "wof:name":"Besusso",
    "wof:placetype":"locality",
    "wof:population":21
},
  "geometry": {"coordinates":[8.06517,44.88976],"type":"Point"}
}