{
  "type": "Feature",
  "properties": {
    "gn:admin1_code":"10",
    "gn:admin2_code":"PU",
    "gn:admin3_code":"41006.0",
    "gn:asciiname":"Palazzo Mucci",
    "gn:country_code":"IT",
    "gn:dem":612,
    "gn:feature_class":"P",
    "gn:feature_code":"PPLL",
    "gn:name":"Palazzo Mucci",
    "gn:population":9,
    "gn:timezone":"Europe/Rome",
    "iso:country":"IT",
    "wof:name":"Palazzo Mucci",
    "wof:placetype":"locality",
    "wof:population":9
},
  "geometry": {"coordinates":[12.24736,43.65449],"type":"Point"}
}