{
  "type": "Feature",
  "properties": {
    "gn:admin1_code":"20",
    "gn:admin2_code":"VI",
    "gn:admin3_code":"24017.0",
    "gn:asciiname":"Marzari",
    "gn:country_code":"IT",
    "gn:dem":400,
    "gn:feature_class":"P",
    "gn:feature_code":"PPL",
    "gn:name":"Marzari",
    "gn:population":22,
    "gn:timezone":"Europe/Rome",
    "iso:country":"IT",
    "wof:name":"Marzari",
    "wof:placetype":"locality",
    "wof:population":22
},
  "geometry": {"coordinates":[11.33727,45.58855],"type":"Point"}
}