{
  "type": "Feature",
  "properties": {
    "gn:admin1_code":"18.0",
    "gn:admin2_code":"PG",
    "gn:admin3_code":"54018.0",
    "gn:asciiname":"Sostino",
    "gn:country_code":"IT",
    "gn:dem":703,
    "gn:elevation":"656.0",
    "gn:feature_class":"P",
    "gn:feature_code":"PPL",
    "gn:name":"Sostino",
    "gn:population":41,
    "gn:timezone":"Europe/Rome",
    "iso:country":"IT",
    "wof:name":"Sostino",
    "wof:placetype":"locality",
    "wof:population":41
},
  "geometry": {"coordinates":[12.80004,42.99146],"type":"Point"}
}