{
  "type": "Feature",
  "properties": {
    "gn:admin1_code":"16.0",
    "gn:admin2_code":"FI",
    "gn:admin3_code":"48018.0",
    "gn:asciiname":"Cornacchiaia",
    "gn:country_code":"IT",
    "gn:dem":492,
    "gn:elevation":"507.0",
    "gn:feature_class":"P",
    "gn:feature_code":"PPL",
    "gn:name":"Cornacchiaia",
    "gn:population":167,
    "gn:timezone":"Europe/Rome",
    "iso:country":"IT",
    "wof:name":"Cornacchiaia",
    "wof:placetype":"locality",
    "wof:population":167
},
  "geometry": {"coordinates":[11.33662,44.10277],"type":"Point"}
}