{
  "type": "Feature",
  "properties": {
    "gn:admin1_code":"20",
    "gn:admin2_code":"TV",
    "gn:admin3_code":"26036.0",
    "gn:asciiname":"Manzolino",
    "gn:country_code":"IT",
    "gn:dem":72,
    "gn:feature_class":"P",
    "gn:feature_code":"PPL",
    "gn:name":"Manzolino",
    "gn:population":52,
    "gn:timezone":"Europe/Rome",
    "iso:country":"IT",
    "wof:name":"Manzolino",
    "wof:placetype":"locality",
    "wof:population":52
},
  "geometry": {"coordinates":[11.86599,45.74237],"type":"Point"}
}