{
  "type": "Feature",
  "properties": {
    "gn:admin1_code":"13",
    "gn:admin2_code":"BA",
    "gn:admin3_code":"72021.0",
    "gn:asciiname":"Termosud",
    "gn:country_code":"IT",
    "gn:dem":361,
    "gn:feature_class":"P",
    "gn:feature_code":"PPL",
    "gn:name":"Termosud",
    "gn:population":12,
    "gn:timezone":"Europe/Rome",
    "iso:country":"IT",
    "wof:name":"Termosud",
    "wof:placetype":"locality",
    "wof:population":12
},
  "geometry": {"coordinates":[16.90968,40.81268],"type":"Point"}
}