{
  "type": "Feature",
  "properties": {
    "gn:admin1_code":"10.0",
    "gn:admin2_code":"PU",
    "gn:admin3_code":"41070.0",
    "gn:asciiname":"Schieppe Angelica",
    "gn:country_code":"IT",
    "gn:dem":74,
    "gn:feature_class":"P",
    "gn:feature_code":"PPLL",
    "gn:name":"Schieppe Angelica",
    "gn:population":5,
    "gn:timezone":"Europe/Rome",
    "iso:country":"IT",
    "wof:name":"Schieppe Angelica",
    "wof:placetype":"locality",
    "wof:population":5
},
  "geometry": {"coordinates":[12.90063,43.71847],"type":"Point"}
}