{
  "type": "Feature",
  "properties": {
    "iso:country":"IT",
    "name:eng_x_preferred":[
        "Palmaro di Pra"
    ],
    "name:ita_x_preferred":[
        "Palmaro"
    ],
    "qs:gn_adm0_cc":"IT",
    "qs:gn_fcode":"PPLX",
    "qs:gn_local":3176219,
    "qs:gn_nam_loc":"Genova, Genova, Genova, Liguria, IT",
    "qs:gn_namadm1":"08",
    "qs:gn_name":"Palmaro",
    "qs:local_max":6569,
    "qs:local_sum":41267,
    "qs:localhoods":37,
    "qs:name":"Palmaro",
    "qs:name_adm0":"Italia",
    "qs:name_adm1":"Liguria",
    "qs:name_adm2":"Genova",
    "qs:name_en":"Palmaro di Pra",
    "qs:name_lau":"Genova",
    "qs:name_local":"Genova",
    "qs:photo_max":108,
    "qs:photo_sum":394,
    "qs:placetype":"Suburb",
    "qs:quad_count":27,
    "qs:woe_adm0":23424853,
    "qs:woe_adm1":7153337,
    "qs:woe_adm2":12591832,
    "qs:woe_lau":12675811,
    "qs:woe_local":716085,
    "qs:woe_ver":"7.10.0",
    "wof:lang":[
        "ita"
    ],
    "wof:name":"Palmaro",
    "wof:placetype":"neighbourhood"
},
  "geometry": {"coordinates":[8.772359,44.42892],"type":"Point"}
}