{
  "type": "Feature",
  "properties": {
    "gn:admin1_code":"10",
    "gn:admin2_code":"MC",
    "gn:admin3_code":"43046.0",
    "gn:asciiname":"Colle",
    "gn:country_code":"IT",
    "gn:dem":507,
    "gn:feature_class":"P",
    "gn:feature_code":"PPL",
    "gn:name":"Colle",
    "gn:population":25,
    "gn:timezone":"Europe/Rome",
    "iso:country":"IT",
    "wof:name":"Colle",
    "wof:placetype":"locality",
    "wof:population":25
},
  "geometry": {"coordinates":[13.28082,43.07204],"type":"Point"}
}