{
  "type": "Feature",
  "properties": {
    "gn:admin1_code":"16.0",
    "gn:admin2_code":"FI",
    "gn:admin3_code":"48025.0",
    "gn:asciiname":"Fornace",
    "gn:country_code":"IT",
    "gn:dem":539,
    "gn:elevation":"525.0",
    "gn:feature_class":"P",
    "gn:feature_code":"PPL",
    "gn:name":"Fornace",
    "gn:population":19,
    "gn:timezone":"Europe/Rome",
    "iso:country":"IT",
    "wof:name":"Fornace",
    "wof:placetype":"locality",
    "wof:population":19
},
  "geometry": {"coordinates":[11.61175,43.8559],"type":"Point"}
}