{
  "type": "Feature",
  "properties": {
    "gn:admin1_code":"5",
    "gn:admin2_code":"FC",
    "gn:admin3_code":"40012.0",
    "gn:asciiname":"Ca' Mirri",
    "gn:country_code":"IT",
    "gn:dem":64,
    "gn:feature_class":"P",
    "gn:feature_code":"PPL",
    "gn:name":"Ca' Mirri",
    "gn:population":24,
    "gn:timezone":"Europe/Rome",
    "iso:country":"IT",
    "wof:name":"Ca' Mirri",
    "wof:placetype":"locality",
    "wof:population":24
},
  "geometry": {"coordinates":[12.05154,44.1659],"type":"Point"}
}