{
  "type": "Feature",
  "properties": {
    "gn:admin1_code":"9",
    "gn:admin2_code":"PV",
    "gn:admin3_code":"18036.0",
    "gn:asciiname":"Ca' dei Cristina",
    "gn:country_code":"IT",
    "gn:dem":301,
    "gn:feature_class":"P",
    "gn:feature_code":"PPL",
    "gn:name":"Ca' dei Cristina",
    "gn:population":33,
    "gn:timezone":"Europe/Rome",
    "iso:country":"IT",
    "wof:name":"Ca' dei Cristina",
    "wof:placetype":"locality",
    "wof:population":33
},
  "geometry": {"coordinates":[9.2773,45.01155],"type":"Point"}
}