{
  "type": "Feature",
  "properties": {
    "gn:admin1_code":"4.0",
    "gn:admin2_code":"SA",
    "gn:admin3_code":"65034.0",
    "gn:asciiname":"Lanzara",
    "gn:country_code":"IT",
    "gn:dem":74,
    "gn:feature_class":"P",
    "gn:feature_code":"PPL",
    "gn:name":"Lanzara",
    "gn:population":5673,
    "gn:timezone":"Europe/Rome",
    "iso:country":"IT",
    "wof:name":"Lanzara",
    "wof:placetype":"locality",
    "wof:population":5673
},
  "geometry": {"coordinates":[14.67619,40.77473],"type":"Point"}
}