{
  "type": "Feature",
  "properties": {
    "gn:admin1_code":"20",
    "gn:admin2_code":"PD",
    "gn:admin3_code":"28098.0",
    "gn:asciiname":"Calcatonega",
    "gn:country_code":"IT",
    "gn:dem":5,
    "gn:feature_class":"P",
    "gn:feature_code":"PPL",
    "gn:name":"Calcatonega",
    "gn:population":70,
    "gn:timezone":"Europe/Rome",
    "iso:country":"IT",
    "wof:name":"Calcatonega",
    "wof:placetype":"locality",
    "wof:population":70
},
  "geometry": {"coordinates":[11.64102,45.18212],"type":"Point"}
}