{
  "type": "Feature",
  "properties": {
    "gn:admin1_code":"5.0",
    "gn:admin2_code":"MO",
    "gn:admin3_code":"36016.0",
    "gn:asciiname":"Spervara di Sotto",
    "gn:country_code":"IT",
    "gn:dem":870,
    "gn:feature_class":"P",
    "gn:feature_code":"PPL",
    "gn:name":"Spervara di Sotto",
    "gn:population":29,
    "gn:timezone":"Europe/Rome",
    "iso:country":"IT",
    "wof:name":"Spervara di Sotto",
    "wof:placetype":"locality",
    "wof:population":29
},
  "geometry": {"coordinates":[10.58246,44.28146],"type":"Point"}
}