{
  "type": "Feature",
  "properties": {
    "gn:admin1_code":"12",
    "gn:admin2_code":"TO",
    "gn:admin3_code":"1094.0",
    "gn:asciiname":"Cudine",
    "gn:country_code":"IT",
    "gn:dem":738,
    "gn:feature_class":"P",
    "gn:feature_code":"PPL",
    "gn:name":"Cudine",
    "gn:population":13,
    "gn:timezone":"Europe/Rome",
    "iso:country":"IT",
    "wof:name":"Cudine",
    "wof:placetype":"locality",
    "wof:population":13
},
  "geometry": {"coordinates":[7.50681,45.30114],"type":"Point"}
}