{
  "type": "Feature",
  "properties": {
    "gn:admin1_code":"17",
    "gn:admin2_code":"BZ",
    "gn:admin3_code":"21107.0",
    "gn:asciiname":"Palu",
    "gn:country_code":"IT",
    "gn:dem":944,
    "gn:feature_class":"P",
    "gn:feature_code":"PPL",
    "gn:name":"Pal\u00f9",
    "gn:population":77,
    "gn:timezone":"Europe/Rome",
    "iso:country":"IT",
    "name:und_x_variant":[
        "Pal\u00f9"
    ],
    "wof:name":"Palu",
    "wof:placetype":"locality",
    "wof:population":77
},
  "geometry": {"coordinates":[11.45128,46.9012],"type":"Point"}
}