{
  "type": "Feature",
  "properties": {
    "gn:admin1_code":"8.0",
    "gn:admin2_code":"SP",
    "gn:admin3_code":"11015.0",
    "gn:asciiname":"Termo de La Spezia",
    "gn:country_code":"IT",
    "gn:dem":29,
    "gn:feature_class":"P",
    "gn:feature_code":"PPL",
    "gn:name":"Termo de La Spezia",
    "gn:population":0,
    "gn:timezone":"Europe/Rome",
    "iso:country":"IT",
    "wof:name":"Termo de La Spezia",
    "wof:placetype":"locality"
},
  "geometry": {"coordinates":[9.88272,44.11822],"type":"Point"}
}