{
  "type": "Feature",
  "properties": {
    "gn:admin1_code":"17",
    "gn:admin2_code":"TN",
    "gn:admin3_code":"22027.0",
    "gn:asciiname":"Carnalez",
    "gn:country_code":"IT",
    "gn:dem":978,
    "gn:feature_class":"P",
    "gn:feature_code":"PPL",
    "gn:name":"Carnalez",
    "gn:population":23,
    "gn:timezone":"Europe/Rome",
    "iso:country":"IT",
    "wof:name":"Carnalez",
    "wof:placetype":"locality",
    "wof:population":23
},
  "geometry": {"coordinates":[11.10184,46.44196],"type":"Point"}
}