{
  "type": "Feature",
  "properties": {
    "gn:admin1_code":"6",
    "gn:admin2_code":"UD",
    "gn:admin3_code":"30033.0",
    "gn:asciiname":"Vidali",
    "gn:country_code":"IT",
    "gn:dem":421,
    "gn:feature_class":"P",
    "gn:feature_code":"PPLL",
    "gn:name":"Vidali",
    "gn:population":8,
    "gn:timezone":"Europe/Rome",
    "iso:country":"IT",
    "name:slv_x_preferred":[
        "Vidali"
    ],
    "wof:name":"Vidali",
    "wof:placetype":"locality",
    "wof:population":8
},
  "geometry": {"coordinates":[13.3089,46.43911],"type":"Point"}
}