{
  "type": "Feature",
  "properties": {
    "gn:admin1_code":"7",
    "gn:admin2_code":"LT",
    "gn:admin3_code":"59003.0",
    "gn:asciiname":"Taverna",
    "gn:country_code":"IT",
    "gn:dem":395,
    "gn:feature_class":"P",
    "gn:feature_code":"PPL",
    "gn:name":"Taverna",
    "gn:population":268,
    "gn:timezone":"Europe/Rome",
    "iso:country":"IT",
    "name:ell_x_preferred":[
        "\u03a4\u03b1\u03b2\u03ad\u03c1\u03bd\u03b1"
    ],
    "name:heb_x_preferred":[
        "\u05d8\u05d1\u05e8\u05e0\u05d4"
    ],
    "name:jpn_x_preferred":[
        "\u30bf\u30f4\u30a7\u30eb\u30ca"
    ],
    "name:nld_x_preferred":[
        "Griekse taverna"
    ],
    "name:spa_x_preferred":[
        "Taverna"
    ],
    "name:ukr_x_preferred":[
        "\u0413\u0440\u0435\u0446\u044c\u043a\u0430 \u0442\u0430\u0432\u0435\u0440\u043d\u0430"
    ],
    "wof:name":"Taverna",
    "wof:placetype":"locality",
    "wof:population":268
},
  "geometry": {"coordinates":[13.52021,41.39275],"type":"Point"}
}