{
  "type": "Feature",
  "properties": {
    "gn:admin1_code":"7",
    "gn:admin2_code":"LT",
    "gn:admin3_code":"59003.0",
    "gn:asciiname":"Taverna",
    "gn:country_code":"IT",
    "gn:dem":395,
    "gn:feature_class":"P",
    "gn:feature_code":"PPL",
    "gn:name":"Taverna",
    "gn:population":268,
    "gn:timezone":"Europe/Rome",
    "iso:country":"IT",
    "wof:name":"Taverna",
    "wof:placetype":"locality",
    "wof:population":268
},
  "geometry": {"coordinates":[13.52021,41.39275],"type":"Point"}
}