{
  "type": "Feature",
  "properties": {
    "gn:admin1_code":"5",
    "gn:admin2_code":"BO",
    "gn:admin3_code":"37044.0",
    "gn:asciiname":"Trasasso",
    "gn:country_code":"IT",
    "gn:dem":667,
    "gn:feature_class":"P",
    "gn:feature_code":"PPL",
    "gn:name":"Trasasso",
    "gn:population":69,
    "gn:timezone":"Europe/Rome",
    "iso:country":"IT",
    "wof:name":"Trasasso",
    "wof:placetype":"locality",
    "wof:population":69
},
  "geometry": {"coordinates":[11.27365,44.25576],"type":"Point"}
}