{
  "type": "Feature",
  "properties": {
    "gn:admin1_code":"3",
    "gn:admin2_code":"RC",
    "gn:admin3_code":"80091.0",
    "gn:asciiname":"Sala",
    "gn:country_code":"IT",
    "gn:dem":41,
    "gn:feature_class":"P",
    "gn:feature_code":"PPL",
    "gn:name":"Sala",
    "gn:population":78,
    "gn:timezone":"Europe/Rome",
    "iso:country":"IT",
    "name:arg_x_preferred":[
        "Sala"
    ],
    "name:bre_x_preferred":[
        "Sala"
    ],
    "name:cat_x_preferred":[
        "Sala"
    ],
    "name:ceb_x_preferred":[
        "Sala"
    ],
    "name:ces_x_preferred":[
        "Sala"
    ],
    "name:dan_x_preferred":[
        "Sala"
    ],
    "name:deu_x_preferred":[
        "Sala"
    ],
    "name:epo_x_preferred":[
        "Sala"
    ],
    "name:fin_x_preferred":[
        "Sala"
    ],
    "name:fra_x_preferred":[
        "Sala"
    ],
    "name:glg_x_preferred":[
        "Sala"
    ],
    "name:hun_x_preferred":[
        "Sala"
    ],
    "name:ind_x_preferred":[
        "Sala"
    ],
    "name:ita_x_preferred":[
        "Sala"
    ],
    "name:jpn_x_preferred":[
        "\u30b5\u30fc\u30e9"
    ],
    "name:lat_x_preferred":[
        "Sala"
    ],
    "name:lav_x_preferred":[
        "Sala"
    ],
    "name:lit_x_preferred":[
        "Sala"
    ],
    "name:nld_x_preferred":[
        "Sala"
    ],
    "name:pol_x_preferred":[
        "Sala"
    ],
    "name:por_x_preferred":[
        "Sala"
    ],
    "name:rus_x_preferred":[
        "\u0421\u0430\u043b\u0430"
    ],
    "name:scn_x_preferred":[
        "Sala"
    ],
    "name:sco_x_preferred":[
        "Sala"
    ],
    "name:spa_x_preferred":[
        "Sala"
    ],
    "name:srp_x_preferred":[
        "Sala"
    ],
    "name:swe_x_preferred":[
        "Sala"
    ],
    "name:tgl_x_preferred":[
        "Sala"
    ],
    "name:ukr_x_preferred":[
        "\u0421\u0430\u043b\u0430"
    ],
    "wof:name":"Sala",
    "wof:placetype":"locality",
    "wof:population":78
},
  "geometry": {"coordinates":[16.47458,38.3722],"type":"Point"}
}