{
  "type": "Feature",
  "properties": {
    "gn:admin1_code":"3",
    "gn:admin2_code":"RC",
    "gn:admin3_code":"80091.0",
    "gn:asciiname":"Sala",
    "gn:country_code":"IT",
    "gn:dem":41,
    "gn:feature_class":"P",
    "gn:feature_code":"PPL",
    "gn:name":"Sala",
    "gn:population":78,
    "gn:timezone":"Europe/Rome",
    "iso:country":"IT",
    "wof:name":"Sala",
    "wof:placetype":"locality",
    "wof:population":78
},
  "geometry": {"coordinates":[16.47458,38.3722],"type":"Point"}
}