{
  "type": "Feature",
  "properties": {
    "gn:admin1_code":"16",
    "gn:admin2_code":"MS",
    "gn:admin3_code":"45017.0",
    "gn:asciiname":"Chioso",
    "gn:country_code":"IT",
    "gn:dem":765,
    "gn:feature_class":"P",
    "gn:feature_code":"PPL",
    "gn:name":"Chioso",
    "gn:population":17,
    "gn:timezone":"Europe/Rome",
    "iso:country":"IT",
    "wof:name":"Chioso",
    "wof:placetype":"locality",
    "wof:population":17
},
  "geometry": {"coordinates":[9.78107,44.32686],"type":"Point"}
}