{
  "type": "Feature",
  "properties": {
    "gn:admin1_code":"8.0",
    "gn:admin2_code":"SP",
    "gn:admin3_code":"11029.0",
    "gn:asciiname":"Scauggia",
    "gn:country_code":"IT",
    "gn:dem":523,
    "gn:elevation":"524.0",
    "gn:feature_class":"P",
    "gn:feature_code":"PPL",
    "gn:name":"Scauggia",
    "gn:population":17,
    "gn:timezone":"Europe/Rome",
    "iso:country":"IT",
    "wof:name":"Scauggia",
    "wof:placetype":"locality",
    "wof:population":17
},
  "geometry": {"coordinates":[9.51479,44.37805],"type":"Point"}
}