{
  "type": "Feature",
  "properties": {
    "gn:admin1_code":"8.0",
    "gn:admin2_code":"SP",
    "gn:admin3_code":"11016.0",
    "gn:asciiname":"Pugliola",
    "gn:country_code":"IT",
    "gn:dem":78,
    "gn:feature_class":"P",
    "gn:feature_code":"PPL",
    "gn:name":"Pugliola",
    "gn:population":0,
    "gn:timezone":"Europe/Rome",
    "iso:country":"IT",
    "wof:name":"Pugliola",
    "wof:placetype":"locality"
},
  "geometry": {"coordinates":[9.91293,44.08722],"type":"Point"}
}