{
  "type": "Feature",
  "properties": {
    "gn:admin1_code":"18",
    "gn:admin2_code":"PG",
    "gn:admin3_code":"54048.0",
    "gn:asciiname":"Colle",
    "gn:country_code":"IT",
    "gn:dem":600,
    "gn:feature_class":"P",
    "gn:feature_code":"PPL",
    "gn:name":"Colle",
    "gn:population":19,
    "gn:timezone":"Europe/Rome",
    "iso:country":"IT",
    "wof:name":"Colle",
    "wof:placetype":"locality",
    "wof:population":19
},
  "geometry": {"coordinates":[12.92169,42.86997],"type":"Point"}
}