{
  "type": "Feature",
  "properties": {
    "gn:admin1_code":"7",
    "gn:admin2_code":"FR",
    "gn:admin3_code":"60043.0",
    "gn:asciiname":"Staccone",
    "gn:country_code":"IT",
    "gn:dem":265,
    "gn:feature_class":"P",
    "gn:feature_code":"PPL",
    "gn:name":"Staccone",
    "gn:population":60,
    "gn:timezone":"Europe/Rome",
    "iso:country":"IT",
    "wof:name":"Staccone",
    "wof:placetype":"locality",
    "wof:population":60
},
  "geometry": {"coordinates":[13.55086,41.69192],"type":"Point"}
}