{
  "type": "Feature",
  "properties": {
    "gn:admin1_code":"20",
    "gn:admin2_code":"VI",
    "gn:admin3_code":"24061.0",
    "gn:asciiname":"Carbonara",
    "gn:country_code":"IT",
    "gn:dem":83,
    "gn:feature_class":"P",
    "gn:feature_code":"PPL",
    "gn:name":"Carbonara",
    "gn:population":36,
    "gn:timezone":"Europe/Rome",
    "iso:country":"IT",
    "name:ara_x_preferred":[
        "\u0643\u0627\u0631\u0628\u0648\u0646\u0627\u0631\u0627"
    ],
    "name:ast_x_preferred":[
        "Carbonara"
    ],
    "name:bul_x_preferred":[
        "\u041f\u0430\u0441\u0442\u0430 \u041a\u0430\u0440\u0431\u043e\u043d\u0430\u0440\u0430"
    ],
    "name:cat_x_preferred":[
        "Carbonara"
    ],
    "name:ces_x_preferred":[
        "Carbonara"
    ],
    "name:cym_x_preferred":[
        "Carbonara"
    ],
    "name:dan_x_preferred":[
        "Spaghetti carbonara"
    ],
    "name:deu_x_preferred":[
        "Carbonara"
    ],
    "name:ell_x_preferred":[
        "\u039a\u03b1\u03c1\u03bc\u03c0\u03bf\u03bd\u03ac\u03c1\u03b1"
    ],
    "name:fas_x_preferred":[
        "\u06a9\u0627\u0631\u0628\u0648\u0646\u0627\u0631\u0627"
    ],
    "name:fin_x_preferred":[
        "Carbonara"
    ],
    "name:ind_x_preferred":[
        "Carbonara"
    ],
    "name:jpn_x_preferred":[
        "\u30ab\u30eb\u30dc\u30ca\u30fc\u30e9"
    ],
    "name:kor_x_preferred":[
        "\uce74\ub974\ubcf4\ub098\ub77c"
    ],
    "name:msa_x_preferred":[
        "Carbonara"
    ],
    "name:nld_x_preferred":[
        "Carbonara"
    ],
    "name:pol_x_preferred":[
        "Carbonara"
    ],
    "name:por_x_preferred":[
        "Carbonara"
    ],
    "name:rus_x_preferred":[
        "\u041a\u0430\u0440\u0431\u043e\u043d\u0430\u0440\u0430"
    ],
    "name:spa_x_preferred":[
        "Carbonara"
    ],
    "name:tha_x_preferred":[
        "\u0e01\u0e32\u0e23\u0e4c\u0e42\u0e1a\u0e19\u0e32\u0e23\u0e32"
    ],
    "name:ukr_x_preferred":[
        "\u041a\u0430\u0440\u0431\u043e\u043d\u0430\u0440\u0430"
    ],
    "name:zho_x_preferred":[
        "\u57f9\u6839\u86cb\u9eb5"
    ],
    "wof:name":"Carbonara",
    "wof:placetype":"locality",
    "wof:population":36
},
  "geometry": {"coordinates":[11.40356,45.52606],"type":"Point"}
}