{
  "type": "Feature",
  "properties": {
    "gn:admin1_code":"20",
    "gn:admin2_code":"VI",
    "gn:admin3_code":"24061.0",
    "gn:asciiname":"Carbonara",
    "gn:country_code":"IT",
    "gn:dem":83,
    "gn:feature_class":"P",
    "gn:feature_code":"PPL",
    "gn:name":"Carbonara",
    "gn:population":36,
    "gn:timezone":"Europe/Rome",
    "iso:country":"IT",
    "wof:name":"Carbonara",
    "wof:placetype":"locality",
    "wof:population":36
},
  "geometry": {"coordinates":[11.40356,45.52606],"type":"Point"}
}