{
  "type": "Feature",
  "properties": {
    "gn:admin1_code":"12.0",
    "gn:admin2_code":"TO",
    "gn:admin3_code":"1076.0",
    "gn:asciiname":"Grangia",
    "gn:country_code":"IT",
    "gn:dem":456,
    "gn:feature_class":"P",
    "gn:feature_code":"PPL",
    "gn:name":"Grangia",
    "gn:population":647,
    "gn:timezone":"Europe/Rome",
    "iso:country":"IT",
    "wof:name":"Grangia",
    "wof:placetype":"locality",
    "wof:population":647
},
  "geometry": {"coordinates":[7.16252,45.14244],"type":"Point"}
}