{
  "type": "Feature",
  "properties": {
    "gn:admin1_code":"12.0",
    "gn:admin2_code":"TO",
    "gn:admin3_code":"1018.0",
    "gn:asciiname":"Rivodora",
    "gn:country_code":"IT",
    "gn:dem":321,
    "gn:feature_class":"P",
    "gn:feature_code":"PPL",
    "gn:name":"Rivodora",
    "gn:population":460,
    "gn:timezone":"Europe/Rome",
    "iso:country":"IT",
    "wof:name":"Rivodora",
    "wof:placetype":"locality",
    "wof:population":460
},
  "geometry": {"coordinates":[7.78691,45.08888],"type":"Point"}
}