{
  "type": "Feature",
  "properties": {
    "gn:admin1_code":"5",
    "gn:admin2_code":"RE",
    "gn:admin3_code":"35011.0",
    "gn:asciiname":"Pontone",
    "gn:country_code":"IT",
    "gn:dem":621,
    "gn:feature_class":"P",
    "gn:feature_code":"PPLL",
    "gn:name":"Pontone",
    "gn:population":9,
    "gn:timezone":"Europe/Rome",
    "iso:country":"IT",
    "wof:name":"Pontone",
    "wof:placetype":"locality",
    "wof:population":9
},
  "geometry": {"coordinates":[10.48938,44.425],"type":"Point"}
}