{
  "type": "Feature",
  "properties": {
    "gn:admin1_code":"15",
    "gn:admin2_code":"TP",
    "gn:admin3_code":"81011.0",
    "gn:asciiname":"Marchittati",
    "gn:country_code":"IT",
    "gn:dem":23,
    "gn:feature_class":"P",
    "gn:feature_code":"PPL",
    "gn:name":"Marchittati",
    "gn:population":20,
    "gn:timezone":"Europe/Rome",
    "iso:country":"IT",
    "wof:name":"Marchittati",
    "wof:placetype":"locality",
    "wof:population":20
},
  "geometry": {"coordinates":[12.53674,37.73152],"type":"Point"}
}