{
  "type": "Feature",
  "properties": {
    "gn:admin1_code":"11",
    "gn:admin2_code":"CB",
    "gn:admin3_code":"70031.0",
    "gn:asciiname":"Travaglini",
    "gn:country_code":"IT",
    "gn:dem":195,
    "gn:feature_class":"P",
    "gn:feature_code":"PPL",
    "gn:name":"Travaglini",
    "gn:population":17,
    "gn:timezone":"Europe/Rome",
    "iso:country":"IT",
    "wof:name":"Travaglini",
    "wof:placetype":"locality",
    "wof:population":17
},
  "geometry": {"coordinates":[14.95798,41.817],"type":"Point"}
}