{
  "type": "Feature",
  "properties": {
    "gn:admin1_code":"16.0",
    "gn:admin2_code":"FI",
    "gn:admin3_code":"48041.0",
    "gn:asciiname":"San Michele a Torri",
    "gn:country_code":"IT",
    "gn:dem":179,
    "gn:elevation":"180.0",
    "gn:feature_class":"P",
    "gn:feature_code":"PPL",
    "gn:name":"San Michele a Torri",
    "gn:population":45,
    "gn:timezone":"Europe/Rome",
    "iso:country":"IT",
    "wof:name":"San Michele a Torri",
    "wof:placetype":"locality",
    "wof:population":45
},
  "geometry": {"coordinates":[11.12855,43.701],"type":"Point"}
}