{
  "type": "Feature",
  "properties": {
    "gn:admin1_code":"12",
    "gn:admin2_code":"CN",
    "gn:admin3_code":"4175.0",
    "gn:asciiname":"Campetto",
    "gn:country_code":"IT",
    "gn:dem":583,
    "gn:feature_class":"P",
    "gn:feature_code":"PPL",
    "gn:name":"Campetto",
    "gn:population":24,
    "gn:timezone":"Europe/Rome",
    "iso:country":"IT",
    "wof:name":"Campetto",
    "wof:placetype":"locality",
    "wof:population":24
},
  "geometry": {"coordinates":[8.10148,44.36613],"type":"Point"}
}