{
  "type": "Feature",
  "properties": {
    "gn:admin1_code":"16.0",
    "gn:admin2_code":"PT",
    "gn:admin3_code":"47024.0",
    "gn:asciiname":"Veccialone",
    "gn:country_code":"IT",
    "gn:dem":532,
    "gn:feature_class":"P",
    "gn:feature_code":"PPL",
    "gn:name":"Veccialone",
    "gn:population":0,
    "gn:timezone":"Europe/Rome",
    "iso:country":"IT",
    "wof:name":"Veccialone",
    "wof:placetype":"locality"
},
  "geometry": {"coordinates":[10.76667,44.08333],"type":"Point"}
}