{
  "type": "Feature",
  "properties": {
    "gn:admin1_code":"12",
    "gn:admin2_code":"BI",
    "gn:admin3_code":"96071.0",
    "gn:asciiname":"Benone",
    "gn:country_code":"IT",
    "gn:dem":272,
    "gn:feature_class":"P",
    "gn:feature_code":"PPL",
    "gn:name":"Benone",
    "gn:population":57,
    "gn:timezone":"Europe/Rome",
    "iso:country":"IT",
    "name:eus_x_preferred":[
        "Benone"
    ],
    "wof:name":"Benone",
    "wof:placetype":"locality",
    "wof:population":57
},
  "geometry": {"coordinates":[8.14058,45.55767],"type":"Point"}
}