{
  "type": "Feature",
  "properties": {
    "gn:admin1_code":"14",
    "gn:admin2_code":"SU",
    "gn:admin3_code":"111015.0",
    "gn:asciiname":"Eden Rock",
    "gn:country_code":"IT",
    "gn:dem":90,
    "gn:feature_class":"P",
    "gn:feature_code":"PPL",
    "gn:name":"Eden Rock",
    "gn:population":24,
    "gn:timezone":"Europe/Rome",
    "iso:country":"IT",
    "wof:name":"Eden Rock",
    "wof:placetype":"locality",
    "wof:population":24
},
  "geometry": {"coordinates":[8.90564,38.93099],"type":"Point"}
}