{
  "type": "Feature",
  "properties": {
    "gn:admin1_code":"5",
    "gn:admin2_code":"PR",
    "gn:admin3_code":"34006.0",
    "gn:asciiname":"Baselica",
    "gn:country_code":"IT",
    "gn:dem":589,
    "gn:feature_class":"P",
    "gn:feature_code":"PPL",
    "gn:name":"Baselica",
    "gn:population":22,
    "gn:timezone":"Europe/Rome",
    "iso:country":"IT",
    "wof:name":"Baselica",
    "wof:placetype":"locality",
    "wof:population":22
},
  "geometry": {"coordinates":[9.84508,44.5027],"type":"Point"}
}