{
  "type": "Feature",
  "properties": {
    "gn:admin1_code":"3.0",
    "gn:admin2_code":"RC",
    "gn:admin3_code":"80063.0",
    "gn:asciiname":"Pavigliana",
    "gn:country_code":"IT",
    "gn:dem":531,
    "gn:elevation":"416.0",
    "gn:feature_class":"P",
    "gn:feature_code":"PPL",
    "gn:name":"Pavigliana",
    "gn:population":1088,
    "gn:timezone":"Europe/Rome",
    "iso:country":"IT",
    "wof:name":"Pavigliana",
    "wof:placetype":"locality",
    "wof:population":1088
},
  "geometry": {"coordinates":[15.72108,38.10721],"type":"Point"}
}