{
  "type": "Feature",
  "properties": {
    "gn:admin1_code":"6.0",
    "gn:admin2_code":"UD",
    "gn:admin3_code":"30100.0",
    "gn:asciiname":"Galli",
    "gn:country_code":"IT",
    "gn:dem":4,
    "gn:elevation":"6.0",
    "gn:feature_class":"P",
    "gn:feature_code":"PPL",
    "gn:name":"Galli",
    "gn:population":106,
    "gn:timezone":"Europe/Rome",
    "iso:country":"IT",
    "name:cat_x_preferred":[
        "Gallus"
    ],
    "name:deu_x_preferred":[
        "Galloi"
    ],
    "name:ell_x_preferred":[
        "\u0393\u03ac\u03bb\u03bb\u03bf\u03b9"
    ],
    "name:fra_x_preferred":[
        "Galle"
    ],
    "name:ita_x_preferred":[
        "Gallo"
    ],
    "name:jpn_x_preferred":[
        "\u30ac\u30c3\u30e9\u30a4"
    ],
    "name:kor_x_preferred":[
        "\uac08\ub8e8\uc2a4"
    ],
    "name:lat_x_preferred":[
        "Galli"
    ],
    "name:nld_x_preferred":[
        "Galli"
    ],
    "name:por_x_preferred":[
        "Galo"
    ],
    "name:rus_x_preferred":[
        "\u0413\u0430\u043b\u043b"
    ],
    "name:spa_x_preferred":[
        "Gallo"
    ],
    "name:srp_x_preferred":[
        "\u0413\u0430\u043b\u0438"
    ],
    "name:swe_x_preferred":[
        "Gallus"
    ],
    "wof:name":"Galli",
    "wof:placetype":"locality",
    "wof:population":106
},
  "geometry": {"coordinates":[13.19046,45.82762],"type":"Point"}
}