{
  "type": "Feature",
  "properties": {
    "gn:admin1_code":"6.0",
    "gn:admin2_code":"UD",
    "gn:admin3_code":"30100.0",
    "gn:asciiname":"Galli",
    "gn:country_code":"IT",
    "gn:dem":4,
    "gn:elevation":"6.0",
    "gn:feature_class":"P",
    "gn:feature_code":"PPL",
    "gn:name":"Galli",
    "gn:population":106,
    "gn:timezone":"Europe/Rome",
    "iso:country":"IT",
    "wof:name":"Galli",
    "wof:placetype":"locality",
    "wof:population":106
},
  "geometry": {"coordinates":[13.19046,45.82762],"type":"Point"}
}