{
  "type": "Feature",
  "properties": {
    "gn:admin1_code":"20.0",
    "gn:admin2_code":"VI",
    "gn:admin3_code":"24006.0",
    "gn:asciiname":"Tormeno",
    "gn:country_code":"IT",
    "gn:dem":30,
    "gn:elevation":"30.0",
    "gn:feature_class":"P",
    "gn:feature_code":"PPL",
    "gn:name":"Tormeno",
    "gn:population":522,
    "gn:timezone":"Europe/Rome",
    "iso:country":"IT",
    "wof:name":"Tormeno",
    "wof:placetype":"locality",
    "wof:population":522
},
  "geometry": {"coordinates":[11.55194,45.50415],"type":"Point"}
}