{
  "type": "Feature",
  "properties": {
    "gn:gn_country":"IT",
    "gn:gn_fcode":"PPLA3",
    "gn:gn_pop":369,
    "gn:population":93,
    "iso:country":"IT",
    "name:bel_x_preferred":[
        "\u0424\u0440\u0430\u043d\u0446\u0456\u043d\u0430"
    ],
    "name:bul_x_preferred":[
        "\u0424\u0440\u043e\u043d\u0442\u0438\u043d\u043e"
    ],
    "name:deu_x_preferred":[
        "Frontino"
    ],
    "name:eng_x_preferred":[
        "Frontino"
    ],
    "name:epo_x_preferred":[
        "Frontino"
    ],
    "name:eus_x_preferred":[
        "Frontino"
    ],
    "name:fas_x_preferred":[
        "\u0641\u0631\u0648\u0646\u062a\u06cc\u0646\u0648"
    ],
    "name:fra_x_preferred":[
        "Frontino"
    ],
    "name:hun_x_preferred":[
        "Frontino"
    ],
    "name:hye_x_preferred":[
        "\u0556\u0580\u0578\u0576\u057f\u056b\u0576\u0578"
    ],
    "name:ina_x_preferred":[
        "Frontino"
    ],
    "name:ita_x_preferred":[
        "Frontino"
    ],
    "name:jpn_x_preferred":[
        "\u30d5\u30ed\u30f3\u30c6\u30a3\u30fc\u30ce"
    ],
    "name:kaz_x_preferred":[
        "\u0424\u0440\u043e\u043d\u0442\u0438\u043d\u043e"
    ],
    "name:lat_x_preferred":[
        "Castrum Frontini"
    ],
    "name:lmo_x_preferred":[
        "Frontino"
    ],
    "name:msa_x_preferred":[
        "Frontino"
    ],
    "name:nan_x_preferred":[
        "Frontino"
    ],
    "name:nap_x_preferred":[
        "Frontino"
    ],
    "name:nld_x_preferred":[
        "Frontino"
    ],
    "name:pms_x_preferred":[
        "Frontino"
    ],
    "name:pol_x_preferred":[
        "Frontino"
    ],
    "name:por_x_preferred":[
        "Frontino"
    ],
    "name:ron_x_preferred":[
        "Frontino"
    ],
    "name:rus_x_preferred":[
        "\u0424\u0440\u043e\u043d\u0442\u0438\u043d\u043e"
    ],
    "name:spa_x_preferred":[
        "Frontino"
    ],
    "name:srp_x_preferred":[
        "Frontino"
    ],
    "name:tgl_x_preferred":[
        "Frontino"
    ],
    "name:ukr_x_preferred":[
        "\u0424\u0440\u043e\u043d\u0442\u0456\u043d\u043e"
    ],
    "name:uzb_x_preferred":[
        "Frontino"
    ],
    "name:vie_x_preferred":[
        "Frontino"
    ],
    "name:vol_x_preferred":[
        "Frontino"
    ],
    "name:war_x_preferred":[
        "Frontino"
    ],
    "name:zho_x_preferred":[
        "\u5f17\u9f99\u8482\u8bfa"
    ],
    "qs_pg:aaroncc":"IT",
    "qs_pg:gn_country":"IT",
    "qs_pg:gn_fcode":"PPLA3",
    "qs_pg:gn_pop":369,
    "qs_pg:name":"Frontino",
    "qs_pg:name_adm0":"Italia",
    "qs_pg:name_adm1":"Marche",
    "qs_pg:photos_9k":1,
    "qs_pg:photos_9r":1,
    "qs_pg:photos_all":1,
    "qs_pg:photos_sr":0,
    "qs_pg:pop_sr":2,
    "qs_pg:qs_pg_placetype":"locality",
    "qs_pg:qs_pg_placetype_gp":"Town",
    "qs_pg:woe_adm0":23424853,
    "woe:adm0_id":23424853,
    "woe:name_adm0":"Italia",
    "woe:name_adm1":"Marche",
    "woe:placetype":"Town",
    "wof:name":"Frontino",
    "wof:placetype":"locality",
    "wof:population":93
},
  "geometry": {"coordinates":[12.37675,43.76456],"type":"Point"}
}