{
  "type": "Feature",
  "properties": {
    "gn:admin1_code":"9",
    "gn:admin2_code":"PV",
    "gn:admin3_code":"18059.0",
    "gn:asciiname":"Celpenchio",
    "gn:country_code":"IT",
    "gn:dem":109,
    "gn:feature_class":"P",
    "gn:feature_code":"PPL",
    "gn:name":"Celpenchio",
    "gn:population":76,
    "gn:timezone":"Europe/Rome",
    "iso:country":"IT",
    "wof:name":"Celpenchio",
    "wof:placetype":"locality",
    "wof:population":76
},
  "geometry": {"coordinates":[8.60187,45.22759],"type":"Point"}
}