{
  "type": "Feature",
  "properties": {
    "gn:admin1_code":"11",
    "gn:admin2_code":"CB",
    "gn:admin3_code":"70057.0",
    "gn:asciiname":"Loie",
    "gn:country_code":"IT",
    "gn:dem":760,
    "gn:feature_class":"P",
    "gn:feature_code":"PPL",
    "gn:name":"Loie",
    "gn:population":22,
    "gn:timezone":"Europe/Rome",
    "iso:country":"IT",
    "wof:name":"Loie",
    "wof:placetype":"locality",
    "wof:population":22
},
  "geometry": {"coordinates":[14.86185,41.45954],"type":"Point"}
}