{
  "type": "Feature",
  "properties": {
    "gn:admin1_code":"12",
    "gn:admin2_code":"AT",
    "gn:admin3_code":"5031.0",
    "gn:asciiname":"Freis",
    "gn:country_code":"IT",
    "gn:dem":270,
    "gn:feature_class":"P",
    "gn:feature_code":"PPL",
    "gn:name":"Freis",
    "gn:population":31,
    "gn:timezone":"Europe/Rome",
    "iso:country":"IT",
    "name:deu_x_preferred":[
        "Freis"
    ],
    "wof:name":"Freis",
    "wof:placetype":"locality",
    "wof:population":31
},
  "geometry": {"coordinates":[7.95409,45.0513],"type":"Point"}
}