{
  "type": "Feature",
  "properties": {
    "gn:admin1_code":"10.0",
    "gn:admin2_code":"MC",
    "gn:admin3_code":"43011.0",
    "gn:asciiname":"Le Case",
    "gn:country_code":"IT",
    "gn:dem":419,
    "gn:feature_class":"P",
    "gn:feature_code":"PPL",
    "gn:name":"Le Case",
    "gn:population":20,
    "gn:timezone":"Europe/Rome",
    "iso:country":"IT",
    "wof:name":"Le Case",
    "wof:placetype":"locality",
    "wof:population":20
},
  "geometry": {"coordinates":[13.2541,43.11694],"type":"Point"}
}