{
  "type": "Feature",
  "properties": {
    "gn:admin1_code":"1.0",
    "gn:admin2_code":"AQ",
    "gn:admin3_code":"66095.0",
    "gn:asciiname":"Vigliano",
    "gn:country_code":"IT",
    "gn:dem":933,
    "gn:elevation":"950.0",
    "gn:feature_class":"P",
    "gn:feature_code":"PPL",
    "gn:name":"Vigliano",
    "gn:population":121,
    "gn:timezone":"Europe/Rome",
    "iso:country":"IT",
    "wof:name":"Vigliano",
    "wof:placetype":"locality",
    "wof:population":121
},
  "geometry": {"coordinates":[13.21876,42.3492],"type":"Point"}
}