{
  "type": "Feature",
  "properties": {
    "iso:country":"IT",
    "name:ceb_x_preferred":[
        "Crocetta"
    ],
    "name:deu_x_preferred":[
        "Crocetta"
    ],
    "name:fra_x_preferred":[
        "Crocetta"
    ],
    "name:ita_x_preferred":[
        "Crocetta"
    ],
    "name:srp_x_preferred":[
        "Kro\u010deta"
    ],
    "name:swe_x_preferred":[
        "Crocetta"
    ],
    "wof:name":"Crocetta",
    "wof:placetype":"neighbourhood"
},
  "geometry": {"coordinates":[7.66741975415053,45.05731485017481],"type":"Point"}
}