{
  "type": "Feature",
  "properties": {
    "gn:admin1_code":"4.0",
    "gn:admin2_code":"SA",
    "gn:admin3_code":"65106.0",
    "gn:asciiname":"Fonte II",
    "gn:country_code":"IT",
    "gn:dem":53,
    "gn:feature_class":"P",
    "gn:feature_code":"PPL",
    "gn:name":"Fonte II",
    "gn:population":166,
    "gn:timezone":"Europe/Rome",
    "iso:country":"IT",
    "wof:name":"Fonte II",
    "wof:placetype":"locality",
    "wof:population":166
},
  "geometry": {"coordinates":[15.09323,40.46133],"type":"Point"}
}