{
  "type": "Feature",
  "properties": {
    "gn:admin1_code":"20.0",
    "gn:admin2_code":"RO",
    "gn:admin3_code":"29051.0",
    "gn:asciiname":"Ponte",
    "gn:country_code":"IT",
    "gn:dem":0,
    "gn:feature_class":"P",
    "gn:feature_code":"PPL",
    "gn:name":"Ponte",
    "gn:population":62,
    "gn:timezone":"Europe/Rome",
    "iso:country":"IT",
    "wof:name":"Ponte",
    "wof:placetype":"locality",
    "wof:population":62
},
  "geometry": {"coordinates":[11.95913,44.99427],"type":"Point"}
}