{
  "type": "Feature",
  "properties": {
    "gn:admin1_code":"4",
    "gn:admin2_code":"AV",
    "gn:admin3_code":"64034.0",
    "gn:asciiname":"Casal di Creta",
    "gn:country_code":"IT",
    "gn:dem":423,
    "gn:feature_class":"P",
    "gn:feature_code":"PPL",
    "gn:name":"Casal di Creta",
    "gn:population":51,
    "gn:timezone":"Europe/Rome",
    "iso:country":"IT",
    "wof:name":"Casal di Creta",
    "wof:placetype":"locality",
    "wof:population":51
},
  "geometry": {"coordinates":[14.74379,40.86265],"type":"Point"}
}