{
  "type": "Feature",
  "properties": {
    "gn:admin1_code":"16",
    "gn:admin2_code":"LU",
    "gn:admin3_code":"46037.0",
    "gn:asciiname":"Brica",
    "gn:country_code":"IT",
    "gn:dem":915,
    "gn:feature_class":"P",
    "gn:feature_code":"PPL",
    "gn:name":"Brica",
    "gn:population":26,
    "gn:timezone":"Europe/Rome",
    "iso:country":"IT",
    "wof:name":"Brica",
    "wof:placetype":"locality",
    "wof:population":26
},
  "geometry": {"coordinates":[10.34239,44.23795],"type":"Point"}
}