{
  "type": "Feature",
  "properties": {
    "gn:admin1_code":"20.0",
    "gn:admin2_code":"VR",
    "gn:admin3_code":"23001.0",
    "gn:asciiname":"Casetta",
    "gn:country_code":"IT",
    "gn:dem":244,
    "gn:feature_class":"P",
    "gn:feature_code":"PPL",
    "gn:name":"Casetta",
    "gn:population":22,
    "gn:timezone":"Europe/Rome",
    "iso:country":"IT",
    "wof:name":"Casetta",
    "wof:placetype":"locality",
    "wof:population":22
},
  "geometry": {"coordinates":[10.74887,45.55116],"type":"Point"}
}