{
  "type": "Feature",
  "properties": {
    "gn:admin1_code":"13.0",
    "gn:admin2_code":"BA",
    "gn:admin3_code":"72032.0",
    "gn:asciiname":"Parco Scizzo-Parchitello",
    "gn:country_code":"IT",
    "gn:dem":39,
    "gn:feature_class":"P",
    "gn:feature_code":"PPL",
    "gn:name":"Parco Scizzo-Parchitello",
    "gn:population":3705,
    "gn:timezone":"Europe/Rome",
    "iso:country":"IT",
    "wof:name":"Parco Scizzo-Parchitello",
    "wof:placetype":"locality",
    "wof:population":3705
},
  "geometry": {"coordinates":[16.99329,41.07457],"type":"Point"}
}