{
  "type": "Feature",
  "properties": {
    "gn:admin1_code":"6",
    "gn:admin2_code":"UD",
    "gn:admin3_code":"30122.0",
    "gn:asciiname":"Casali Costa",
    "gn:country_code":"IT",
    "gn:dem":287,
    "gn:feature_class":"P",
    "gn:feature_code":"PPL",
    "gn:name":"Casali Costa",
    "gn:population":24,
    "gn:timezone":"Europe/Rome",
    "iso:country":"IT",
    "wof:name":"Casali Costa",
    "wof:placetype":"locality",
    "wof:population":24
},
  "geometry": {"coordinates":[13.44453,46.14787000000001],"type":"Point"}
}