{
  "type": "Feature",
  "properties": {
    "gn:admin1_code":"16.0",
    "gn:admin2_code":"LI",
    "gn:admin3_code":"49017.0",
    "gn:asciiname":"Castiglioncello",
    "gn:country_code":"IT",
    "gn:dem":21,
    "gn:feature_class":"P",
    "gn:feature_code":"PPL",
    "gn:name":"Castiglioncello",
    "gn:population":0,
    "gn:timezone":"Europe/Rome",
    "iso:country":"IT",
    "name:bos_x_preferred":[
        "Castiglioncello"
    ],
    "name:bre_x_preferred":[
        "Castiglioncello"
    ],
    "name:ceb_x_preferred":[
        "Castiglioncello"
    ],
    "name:deu_x_preferred":[
        "Rosignano Marittimo#Castiglioncello"
    ],
    "name:est_x_preferred":[
        "Castiglioncello"
    ],
    "name:fas_x_preferred":[
        "\u06a9\u0627\u0633\u06cc\u0644\u06cc\u0648\u0646\u0686\u0644\u0648"
    ],
    "name:fra_x_preferred":[
        "Castiglioncello"
    ],
    "name:ita_x_preferred":[
        "Castiglioncello"
    ],
    "name:lat_x_preferred":[
        "Castellioncellum"
    ],
    "name:nld_x_preferred":[
        "Castiglioncello"
    ],
    "name:rus_x_preferred":[
        "\u041a\u0430\u0441\u0442\u0438\u043b\u044c\u043e\u043d\u0447\u0435\u043b\u043b\u043e"
    ],
    "name:spa_x_preferred":[
        "Castiglioncello"
    ],
    "name:swe_x_preferred":[
        "Castiglioncello"
    ],
    "wof:name":"Castiglioncello",
    "wof:placetype":"locality"
},
  "geometry": {"coordinates":[10.42165,43.40517],"type":"Point"}
}