{
  "type": "Feature",
  "properties": {
    "gn:admin1_code":"6",
    "gn:admin2_code":"GO",
    "gn:admin3_code":"31019.0",
    "gn:asciiname":"Groina",
    "gn:country_code":"IT",
    "gn:dem":75,
    "gn:feature_class":"P",
    "gn:feature_code":"PPL",
    "gn:name":"Groina",
    "gn:population":19,
    "gn:timezone":"Europe/Rome",
    "iso:country":"IT",
    "wof:name":"Groina",
    "wof:placetype":"locality",
    "wof:population":19
},
  "geometry": {"coordinates":[13.59563,45.95999000000001],"type":"Point"}
}