{
  "type": "Feature",
  "properties": {
    "gn:admin1_code":"5",
    "gn:admin2_code":"MO",
    "gn:admin3_code":"36025.0",
    "gn:asciiname":"Farneta",
    "gn:country_code":"IT",
    "gn:dem":701,
    "gn:feature_class":"P",
    "gn:feature_code":"PPL",
    "gn:name":"Farneta",
    "gn:population":213,
    "gn:timezone":"Europe/Rome",
    "iso:country":"IT",
    "wof:name":"Farneta",
    "wof:placetype":"locality",
    "wof:population":213
},
  "geometry": {"coordinates":[10.57062,44.34918],"type":"Point"}
}