{
  "type": "Feature",
  "properties": {
    "gn:admin1_code":"20.0",
    "gn:admin2_code":"TV",
    "gn:admin3_code":"26086.0",
    "gn:asciiname":"Canizzano",
    "gn:country_code":"IT",
    "gn:dem":14,
    "gn:elevation":"15.0",
    "gn:feature_class":"P",
    "gn:feature_code":"PPL",
    "gn:name":"Canizzano",
    "gn:population":42,
    "gn:timezone":"Europe/Rome",
    "iso:country":"IT",
    "wof:name":"Canizzano",
    "wof:placetype":"locality",
    "wof:population":42
},
  "geometry": {"coordinates":[12.18746,45.63677],"type":"Point"}
}