{
  "type": "Feature",
  "properties": {
    "iso:country":"IT",
    "name:cat_x_preferred":[
        "Vettign\u00e8"
    ],
    "name:ceb_x_preferred":[
        "Vettign\u00e8"
    ],
    "name:ces_x_preferred":[
        "Vettign\u00e8"
    ],
    "name:che_x_preferred":[
        "\u0412\u0435\u0442\u0438\u043d\u044c\u0435"
    ],
    "name:dan_x_preferred":[
        "Vettign\u00e8"
    ],
    "name:eng_x_preferred":[
        "Vettign\u00e8"
    ],
    "name:eus_x_preferred":[
        "Vettign\u00e8"
    ],
    "name:fin_x_preferred":[
        "Vettign\u00e8"
    ],
    "name:fra_x_preferred":[
        "Vettign\u00e8"
    ],
    "name:ind_x_preferred":[
        "Vettign\u00e8"
    ],
    "name:ita_x_preferred":[
        "Vettign\u00e8"
    ],
    "name:nld_x_preferred":[
        "Vettign\u00e8"
    ],
    "name:nno_x_preferred":[
        "Vettign\u00e8"
    ],
    "name:nob_x_preferred":[
        "Vettign\u00e8"
    ],
    "name:oci_x_preferred":[
        "Vettign\u00e8"
    ],
    "name:pol_x_preferred":[
        "Vettign\u00e8"
    ],
    "name:por_x_preferred":[
        "Vettign\u00e8"
    ],
    "name:ron_x_preferred":[
        "Vettign\u00e8"
    ],
    "name:slk_x_preferred":[
        "Vettign\u00e8"
    ],
    "name:slv_x_preferred":[
        "Vettign\u00e8"
    ],
    "name:spa_x_preferred":[
        "Vettign\u00e8"
    ],
    "name:srp_x_preferred":[
        "Vettign\u00e8"
    ],
    "name:swe_x_preferred":[
        "Vettign\u00e8"
    ],
    "name:tat_x_preferred":[
        "\u0412\u0435\u0442\u0438\u043d\u044c\u0435"
    ],
    "name:tgl_x_preferred":[
        "Vettign\u00e8"
    ],
    "name:tur_x_preferred":[
        "Vettign\u00e8"
    ],
    "name:war_x_preferred":[
        "Vettign\u00e8"
    ],
    "qs_pg:aaroncc":"IT",
    "qs_pg:name":"Vettign\u00e8",
    "qs_pg:name_adm0":"Italia",
    "qs_pg:name_adm1":"Piemonte",
    "qs_pg:photos":34,
    "qs_pg:photos_1k":7,
    "qs_pg:photos_9k":1,
    "qs_pg:photos_9r":2,
    "qs_pg:photos_all":34,
    "qs_pg:photos_sr":2,
    "qs_pg:pop_sr":0,
    "qs_pg:qs_pg_placetype":"locality",
    "qs_pg:qs_pg_placetype_gp":"Town",
    "qs_pg:woe_adm0":23424853,
    "woe:adm0_id":23424853,
    "woe:name_adm0":"Italia",
    "woe:name_adm1":"Piemonte",
    "woe:placetype":"Town",
    "wof:name":"Vettign\u00e8",
    "wof:placetype":"locality"
},
  "geometry": {"coordinates":[8.24026,45.39338],"type":"Point"}
}