{
  "type": "Feature",
  "properties": {
    "gn:admin1_code":"1.0",
    "gn:admin2_code":"PE",
    "gn:admin3_code":"68034.0",
    "gn:asciiname":"Piano delle Castagne",
    "gn:country_code":"IT",
    "gn:dem":531,
    "gn:feature_class":"P",
    "gn:feature_code":"PPL",
    "gn:name":"Piano delle Castagne",
    "gn:population":410,
    "gn:timezone":"Europe/Rome",
    "iso:country":"IT",
    "wof:name":"Piano delle Castagne",
    "wof:placetype":"locality",
    "wof:population":410
},
  "geometry": {"coordinates":[14.0312,42.21623],"type":"Point"}
}