{
  "type": "Feature",
  "properties": {
    "gn:admin1_code":"20",
    "gn:admin2_code":"BL",
    "gn:admin3_code":"25004.0",
    "gn:asciiname":"Duri",
    "gn:country_code":"IT",
    "gn:dem":374,
    "gn:feature_class":"P",
    "gn:feature_code":"PPL",
    "gn:name":"Duri",
    "gn:population":25,
    "gn:timezone":"Europe/Rome",
    "iso:country":"IT",
    "wof:name":"Duri",
    "wof:placetype":"locality",
    "wof:population":25
},
  "geometry": {"coordinates":[11.71968,45.95685],"type":"Point"}
}