{
  "type": "Feature",
  "properties": {
    "gn:admin1_code":"12",
    "gn:admin2_code":"AL",
    "gn:admin3_code":"6002.0",
    "gn:asciiname":"Santa Maria",
    "gn:country_code":"IT",
    "gn:dem":538,
    "gn:feature_class":"P",
    "gn:feature_code":"PPL",
    "gn:name":"Santa Maria",
    "gn:population":15,
    "gn:timezone":"Europe/Rome",
    "iso:country":"IT",
    "wof:name":"Santa Maria",
    "wof:placetype":"locality",
    "wof:population":15
},
  "geometry": {"coordinates":[9.08166,44.71128],"type":"Point"}
}