{
  "type": "Feature",
  "properties": {
    "gn:admin1_code":"10",
    "gn:admin2_code":"MC",
    "gn:admin3_code":"43030.0",
    "gn:asciiname":"Fonte Vecchia",
    "gn:country_code":"IT",
    "gn:dem":204,
    "gn:feature_class":"P",
    "gn:feature_code":"PPL",
    "gn:name":"Fonte Vecchia",
    "gn:population":18,
    "gn:timezone":"Europe/Rome",
    "iso:country":"IT",
    "wof:name":"Fonte Vecchia",
    "wof:placetype":"locality",
    "wof:population":18
},
  "geometry": {"coordinates":[13.58017,43.33853],"type":"Point"}
}