{
  "type": "Feature",
  "properties": {
    "gn:admin1_code":"12",
    "gn:admin2_code":"TO",
    "gn:admin3_code":"1287.0",
    "gn:asciiname":"Braidacroce",
    "gn:country_code":"IT",
    "gn:dem":355,
    "gn:feature_class":"P",
    "gn:feature_code":"PPL",
    "gn:name":"Braidacroce",
    "gn:population":33,
    "gn:timezone":"Europe/Rome",
    "iso:country":"IT",
    "wof:name":"Braidacroce",
    "wof:placetype":"locality",
    "wof:population":33
},
  "geometry": {"coordinates":[7.66972,45.35871],"type":"Point"}
}