{
  "type": "Feature",
  "properties": {
    "gn:admin1_code":"6",
    "gn:admin2_code":"GO",
    "gn:admin3_code":"31018.0",
    "gn:asciiname":"Marcorina I",
    "gn:country_code":"IT",
    "gn:dem":4,
    "gn:feature_class":"P",
    "gn:feature_code":"PPL",
    "gn:name":"Marcorina I",
    "gn:population":26,
    "gn:timezone":"Europe/Rome",
    "iso:country":"IT",
    "wof:name":"Marcorina I",
    "wof:placetype":"locality",
    "wof:population":26
},
  "geometry": {"coordinates":[13.45483,45.79289],"type":"Point"}
}