{
  "type": "Feature",
  "properties": {
    "iso:country":"IT",
    "wof:name":"Nasche",
    "wof:placetype":"neighbourhood"
},
  "geometry": {"coordinates":[8.9960923000752,44.41574010030965],"type":"Point"}
}