{
  "type": "Feature",
  "properties": {
    "gn:admin1_code":"16.0",
    "gn:admin2_code":"FI",
    "gn:admin3_code":"48001.0",
    "gn:asciiname":"Capannuccia",
    "gn:country_code":"IT",
    "gn:dem":114,
    "gn:feature_class":"P",
    "gn:feature_code":"PPL",
    "gn:name":"Capannuccia",
    "gn:population":223,
    "gn:timezone":"Europe/Rome",
    "iso:country":"IT",
    "wof:name":"Capannuccia",
    "wof:placetype":"locality",
    "wof:population":223
},
  "geometry": {"coordinates":[11.3092,43.70145],"type":"Point"}
}