{
  "type": "Feature",
  "properties": {
    "gn:admin1_code":"5",
    "gn:admin2_code":"PC",
    "gn:admin3_code":"33015.0",
    "gn:asciiname":"Ponte Organasco",
    "gn:country_code":"IT",
    "gn:dem":476,
    "gn:feature_class":"P",
    "gn:feature_code":"PPL",
    "gn:name":"Ponte Organasco",
    "gn:population":27,
    "gn:timezone":"Europe/Rome",
    "iso:country":"IT",
    "wof:name":"Ponte Organasco",
    "wof:placetype":"locality",
    "wof:population":27
},
  "geometry": {"coordinates":[9.30658,44.68487],"type":"Point"}
}