{
  "type": "Feature",
  "properties": {
    "gn:admin1_code":"6",
    "gn:admin2_code":"UD",
    "gn:admin3_code":"30065.0",
    "gn:asciiname":"Borgo di Mezzo",
    "gn:country_code":"IT",
    "gn:dem":612,
    "gn:feature_class":"P",
    "gn:feature_code":"PPL",
    "gn:name":"Borgo di Mezzo",
    "gn:population":30,
    "gn:timezone":"Europe/Rome",
    "iso:country":"IT",
    "wof:name":"Borgo di Mezzo",
    "wof:placetype":"locality",
    "wof:population":30
},
  "geometry": {"coordinates":[13.27905,46.23867],"type":"Point"}
}