{
  "type": "Feature",
  "properties": {
    "gn:admin1_code":"20.0",
    "gn:admin2_code":"VR",
    "gn:admin3_code":"23044.0",
    "gn:asciiname":"Gallese",
    "gn:country_code":"IT",
    "gn:dem":14,
    "gn:feature_class":"P",
    "gn:feature_code":"PPL",
    "gn:name":"Gallese",
    "gn:population":504,
    "gn:timezone":"Europe/Rome",
    "iso:country":"IT",
    "wof:name":"Gallese",
    "wof:placetype":"locality",
    "wof:population":504
},
  "geometry": {"coordinates":[11.33154,45.2245],"type":"Point"}
}