{
  "type": "Feature",
  "properties": {
    "gn:admin1_code":"20.0",
    "gn:admin2_code":"VR",
    "gn:admin3_code":"23044.0",
    "gn:asciiname":"Gallese",
    "gn:country_code":"IT",
    "gn:dem":14,
    "gn:feature_class":"P",
    "gn:feature_code":"PPL",
    "gn:name":"Gallese",
    "gn:population":504,
    "gn:timezone":"Europe/Rome",
    "iso:country":"IT",
    "name:ast_x_preferred":[
        "Gallese"
    ],
    "name:azb_x_preferred":[
        "\u0642\u0627\u0644\u0647\u200c\u0633\u0647"
    ],
    "name:bcl_x_preferred":[
        "Gallese"
    ],
    "name:bel_x_preferred":[
        "\u0413\u0430\u043b\u0435\u0437\u044d"
    ],
    "name:bul_x_preferred":[
        "\u0413\u0430\u043b\u0435\u0437\u0435"
    ],
    "name:ceb_x_preferred":[
        "Gallese"
    ],
    "name:deu_x_preferred":[
        "Gallese"
    ],
    "name:epo_x_preferred":[
        "Gallese"
    ],
    "name:eus_x_preferred":[
        "Gallese"
    ],
    "name:fas_x_preferred":[
        "\u06af\u0627\u0644\u0647\u200c\u0633\u0647"
    ],
    "name:fra_x_preferred":[
        "Gallese"
    ],
    "name:hun_x_preferred":[
        "Gallese"
    ],
    "name:hye_x_preferred":[
        "\u0533\u0561\u056c\u056c\u0565\u057d\u0565"
    ],
    "name:ina_x_preferred":[
        "Gallese"
    ],
    "name:ita_x_preferred":[
        "Gallese"
    ],
    "name:jpn_x_preferred":[
        "\u30ac\u30c3\u30ec\u30fc\u30bc"
    ],
    "name:kaz_x_preferred":[
        "\u0413\u0430\u043b\u043b\u0435\u0437\u0435"
    ],
    "name:kor_x_preferred":[
        "\uac08\ub808\uc138"
    ],
    "name:lat_x_preferred":[
        "Gallesium"
    ],
    "name:lmo_x_preferred":[
        "Gallese"
    ],
    "name:msa_x_preferred":[
        "Gallese"
    ],
    "name:nap_x_preferred":[
        "Gallese"
    ],
    "name:nld_x_preferred":[
        "Gallese"
    ],
    "name:pms_x_preferred":[
        "Gallese"
    ],
    "name:pol_x_preferred":[
        "Gallese"
    ],
    "name:por_x_preferred":[
        "Gallese"
    ],
    "name:ron_x_preferred":[
        "Gallese"
    ],
    "name:rus_x_preferred":[
        "\u0413\u0430\u043b\u043b\u0435\u0437\u0435"
    ],
    "name:scn_x_preferred":[
        "Gallesi"
    ],
    "name:spa_x_preferred":[
        "Gallese"
    ],
    "name:srp_x_preferred":[
        "\u0413\u0430\u043b\u0435\u0437\u0435"
    ],
    "name:swe_x_preferred":[
        "Gallese"
    ],
    "name:szl_x_preferred":[
        "Gallese"
    ],
    "name:ukr_x_preferred":[
        "\u0413\u0430\u043b\u043b\u0435\u0437\u0435"
    ],
    "name:uzb_x_preferred":[
        "Gallese"
    ],
    "name:vie_x_preferred":[
        "Gallese"
    ],
    "name:vol_x_preferred":[
        "Gallese"
    ],
    "name:war_x_preferred":[
        "Gallese"
    ],
    "name:zho_x_preferred":[
        "\u52a0\u83b1\u585e"
    ],
    "wof:name":"Gallese",
    "wof:placetype":"locality",
    "wof:population":504
},
  "geometry": {"coordinates":[11.33154,45.2245],"type":"Point"}
}