{
  "type": "Feature",
  "properties": {
    "gn:admin1_code":"14.0",
    "gn:admin2_code":"SU",
    "gn:admin3_code":"111001.0",
    "gn:asciiname":"Torre di Flumentorgiu",
    "gn:country_code":"IT",
    "gn:dem":67,
    "gn:feature_class":"P",
    "gn:feature_code":"PPL",
    "gn:name":"Torre di Flumentorgiu",
    "gn:population":0,
    "gn:timezone":"Europe/Rome",
    "iso:country":"IT",
    "wof:name":"Torre di Flumentorgiu",
    "wof:placetype":"locality"
},
  "geometry": {"coordinates":[8.45037,39.68196],"type":"Point"}
}