{
  "type": "Feature",
  "properties": {
    "gn:gn_country":"IT",
    "gn:gn_fcode":"PPLA3",
    "gn:gn_pop":253,
    "gn:population":180,
    "iso:country":"IT",
    "name:azb_x_preferred":[
        "\u0628\u0644\u0633\u0627\u0646\u06cc\u0648"
    ],
    "name:bel_x_preferred":[
        "\u0411\u043b\u0435\u0441\u0430\u043d\u044c\u0451"
    ],
    "name:ceb_x_preferred":[
        "Blessagno"
    ],
    "name:deu_x_preferred":[
        "Blessagno"
    ],
    "name:eng_x_preferred":[
        "Blessagno"
    ],
    "name:epo_x_preferred":[
        "Blessagno"
    ],
    "name:eus_x_preferred":[
        "Blessagno"
    ],
    "name:fas_x_preferred":[
        "\u0628\u0644\u0633\u0627\u0646\u06cc\u0648"
    ],
    "name:fra_x_preferred":[
        "Blessagno"
    ],
    "name:hun_x_preferred":[
        "Blessagno"
    ],
    "name:hye_x_preferred":[
        "\u0532\u056c\u0565\u057d\u0561\u0576\u0578"
    ],
    "name:ita_x_preferred":[
        "Blessagno"
    ],
    "name:jpn_x_preferred":[
        "\u30d6\u30ec\u30c3\u30b5\u30fc\u30cb\u30e7"
    ],
    "name:kaz_x_preferred":[
        "\u0411\u043b\u0435\u0441\u0441\u0430\u043d\u044c\u043e"
    ],
    "name:lat_x_preferred":[
        "Blexum"
    ],
    "name:lmo_x_preferred":[
        "Blessagn"
    ],
    "name:msa_x_preferred":[
        "Blessagno"
    ],
    "name:nap_x_preferred":[
        "Blessagno"
    ],
    "name:nld_x_preferred":[
        "Blessagno"
    ],
    "name:pms_x_preferred":[
        "Blessagno"
    ],
    "name:pol_x_preferred":[
        "Blessagno"
    ],
    "name:por_x_preferred":[
        "Blessagno"
    ],
    "name:ron_x_preferred":[
        "Blessagno"
    ],
    "name:rus_x_preferred":[
        "\u0411\u043b\u0435\u0441\u0441\u0430\u043d\u044c\u043e"
    ],
    "name:scn_x_preferred":[
        "Blessagno"
    ],
    "name:spa_x_preferred":[
        "Blessagno"
    ],
    "name:srp_x_preferred":[
        "Blessagno"
    ],
    "name:tgl_x_preferred":[
        "Blessagno"
    ],
    "name:ukr_x_preferred":[
        "\u0411\u043b\u0435\u0441\u0441\u0430\u043d\u044c\u043e"
    ],
    "name:uzb_x_preferred":[
        "Blessagno"
    ],
    "name:vie_x_preferred":[
        "Blessagno"
    ],
    "name:vol_x_preferred":[
        "Blessagno"
    ],
    "name:war_x_preferred":[
        "Blessagno"
    ],
    "name:zho_x_preferred":[
        "\u5e03\u83b1\u8428\u5c3c\u5965"
    ],
    "qs_pg:aaroncc":"IT",
    "qs_pg:gn_country":"IT",
    "qs_pg:gn_fcode":"PPLA3",
    "qs_pg:gn_pop":253,
    "qs_pg:name":"Blessagno",
    "qs_pg:name_adm0":"Italia",
    "qs_pg:name_adm1":"Lombardia",
    "qs_pg:photos_9r":0,
    "qs_pg:photos_sr":0,
    "qs_pg:pop_sr":2,
    "qs_pg:qs_pg_placetype":"locality",
    "qs_pg:qs_pg_placetype_gp":"Town",
    "qs_pg:woe_adm0":23424853,
    "woe:adm0_id":23424853,
    "woe:name_adm0":"Italia",
    "woe:name_adm1":"Lombardia",
    "woe:placetype":"Town",
    "wof:name":"Blessagno",
    "wof:placetype":"locality",
    "wof:population":180
},
  "geometry": {"coordinates":[9.09754,45.95908],"type":"Point"}
}