{
  "type": "Feature",
  "properties": {
    "gn:admin1_code":"20",
    "gn:admin2_code":"TV",
    "gn:admin3_code":"26049.0",
    "gn:asciiname":"Redigole",
    "gn:country_code":"IT",
    "gn:dem":4,
    "gn:feature_class":"P",
    "gn:feature_code":"PPL",
    "gn:name":"Redigole",
    "gn:population":109,
    "gn:timezone":"Europe/Rome",
    "iso:country":"IT",
    "wof:name":"Redigole",
    "wof:placetype":"locality",
    "wof:population":109
},
  "geometry": {"coordinates":[12.58826,45.76394000000001],"type":"Point"}
}