{
  "type": "Feature",
  "properties": {
    "gn:admin1_code":"20.0",
    "gn:admin2_code":"TV",
    "gn:admin3_code":"26003.0",
    "gn:asciiname":"Ca' Falier",
    "gn:country_code":"IT",
    "gn:dem":88,
    "gn:feature_class":"P",
    "gn:feature_code":"PPL",
    "gn:name":"Ca' Falier",
    "gn:population":50,
    "gn:timezone":"Europe/Rome",
    "iso:country":"IT",
    "wof:name":"Ca' Falier",
    "wof:placetype":"locality",
    "wof:population":50
},
  "geometry": {"coordinates":[11.899,45.7803],"type":"Point"}
}