{
  "type": "Feature",
  "properties": {
    "gn:admin1_code":"5.0",
    "gn:admin2_code":"RE",
    "gn:admin3_code":"35038.0",
    "gn:asciiname":"Grassano Chiesa",
    "gn:country_code":"IT",
    "gn:dem":480,
    "gn:feature_class":"P",
    "gn:feature_code":"PPL",
    "gn:name":"Grassano Chiesa",
    "gn:population":10,
    "gn:timezone":"Europe/Rome",
    "iso:country":"IT",
    "wof:name":"Grassano Chiesa",
    "wof:placetype":"locality",
    "wof:population":10
},
  "geometry": {"coordinates":[10.45057,44.59337],"type":"Point"}
}