{
  "type": "Feature",
  "properties": {
    "gn:admin1_code":"20",
    "gn:admin2_code":"RO",
    "gn:admin3_code":"29051.0",
    "gn:asciiname":"Anconetta",
    "gn:country_code":"IT",
    "gn:dem":1,
    "gn:feature_class":"P",
    "gn:feature_code":"PPL",
    "gn:name":"Anconetta",
    "gn:population":32,
    "gn:timezone":"Europe/Rome",
    "iso:country":"IT",
    "wof:name":"Anconetta",
    "wof:placetype":"locality",
    "wof:population":32
},
  "geometry": {"coordinates":[11.95009,44.99756],"type":"Point"}
}