{
  "type": "Feature",
  "properties": {
    "gn:admin1_code":"5",
    "gn:admin2_code":"RE",
    "gn:admin3_code":"35013.0",
    "gn:asciiname":"Bocco",
    "gn:country_code":"IT",
    "gn:dem":367,
    "gn:feature_class":"P",
    "gn:feature_code":"PPL",
    "gn:name":"Bocco",
    "gn:population":178,
    "gn:timezone":"Europe/Rome",
    "iso:country":"IT",
    "wof:name":"Bocco",
    "wof:placetype":"locality",
    "wof:population":178
},
  "geometry": {"coordinates":[10.51811,44.53413],"type":"Point"}
}