{
  "type": "Feature",
  "properties": {
    "gn:admin1_code":"6.0",
    "gn:admin2_code":"UD",
    "gn:admin3_code":"30009.0",
    "gn:asciiname":"Basiliano-Vissandone",
    "gn:country_code":"IT",
    "gn:dem":78,
    "gn:feature_class":"P",
    "gn:feature_code":"PPLA3",
    "gn:name":"Basiliano-Vissandone",
    "gn:population":2096,
    "gn:timezone":"Europe/Rome",
    "iso:country":"IT",
    "wof:name":"Basiliano-Vissandone",
    "wof:placetype":"locality",
    "wof:population":2096
},
  "geometry": {"coordinates":[13.09306,46.02278],"type":"Point"}
}