{
  "type": "Feature",
  "properties": {
    "gn:admin1_code":"20",
    "gn:admin2_code":"VE",
    "gn:admin3_code":"27039.0",
    "gn:asciiname":"Case Giantin",
    "gn:country_code":"IT",
    "gn:dem":2,
    "gn:feature_class":"P",
    "gn:feature_code":"PPL",
    "gn:name":"Case Giantin",
    "gn:population":55,
    "gn:timezone":"Europe/Rome",
    "iso:country":"IT",
    "wof:name":"Case Giantin",
    "wof:placetype":"locality",
    "wof:population":55
},
  "geometry": {"coordinates":[12.02427,45.39797],"type":"Point"}
}