{
  "type": "Feature",
  "properties": {
    "gn:admin1_code":"7",
    "gn:admin2_code":"RM",
    "gn:admin3_code":"58002.0",
    "gn:asciiname":"Vasca",
    "gn:country_code":"IT",
    "gn:dem":357,
    "gn:feature_class":"P",
    "gn:feature_code":"PPL",
    "gn:name":"Vasca",
    "gn:population":34,
    "gn:timezone":"Europe/Rome",
    "iso:country":"IT",
    "wof:name":"Vasca",
    "wof:placetype":"locality",
    "wof:population":34
},
  "geometry": {"coordinates":[13.04739,41.96557],"type":"Point"}
}