{
  "type": "Feature",
  "properties": {
    "gn:admin1_code":"16",
    "gn:admin2_code":"MS",
    "gn:admin3_code":"45012.0",
    "gn:asciiname":"Cassana",
    "gn:country_code":"IT",
    "gn:dem":371,
    "gn:feature_class":"P",
    "gn:feature_code":"PPL",
    "gn:name":"Cassana",
    "gn:population":13,
    "gn:timezone":"Europe/Rome",
    "iso:country":"IT",
    "wof:name":"Cassana",
    "wof:placetype":"locality",
    "wof:population":13
},
  "geometry": {"coordinates":[9.88611,44.32695],"type":"Point"}
}