{
  "type": "Feature",
  "properties": {
    "gn:admin1_code":"12",
    "gn:admin2_code":"AL",
    "gn:admin3_code":"6149.0",
    "gn:asciiname":"Cascina Varacca",
    "gn:country_code":"IT",
    "gn:dem":148,
    "gn:feature_class":"P",
    "gn:feature_code":"PPL",
    "gn:name":"Cascina Varacca",
    "gn:population":25,
    "gn:timezone":"Europe/Rome",
    "iso:country":"IT",
    "wof:name":"Cascina Varacca",
    "wof:placetype":"locality",
    "wof:population":25
},
  "geometry": {"coordinates":[8.43076,45.06049],"type":"Point"}
}