{
  "type": "Feature",
  "properties": {
    "gn:admin1_code":"8.0",
    "gn:admin2_code":"IM",
    "gn:admin3_code":"8034.0",
    "gn:asciiname":"Secate",
    "gn:country_code":"IT",
    "gn:dem":1261,
    "gn:feature_class":"P",
    "gn:feature_code":"PPLL",
    "gn:name":"Secate",
    "gn:population":4,
    "gn:timezone":"Europe/Rome",
    "iso:country":"IT",
    "wof:name":"Secate",
    "wof:placetype":"locality",
    "wof:population":4
},
  "geometry": {"coordinates":[7.75203,44.09204],"type":"Point"}
}