{
  "type": "Feature",
  "properties": {
    "gn:admin1_code":"9",
    "gn:admin2_code":"BG",
    "gn:admin3_code":"16012.0",
    "gn:asciiname":"Bani",
    "gn:country_code":"IT",
    "gn:dem":1008,
    "gn:feature_class":"P",
    "gn:feature_code":"PPL",
    "gn:name":"Bani",
    "gn:population":102,
    "gn:timezone":"Europe/Rome",
    "iso:country":"IT",
    "name:cat_x_preferred":[
        "Bani"
    ],
    "name:ceb_x_preferred":[
        "Bani"
    ],
    "name:ces_x_preferred":[
        "Bani"
    ],
    "name:deu_x_preferred":[
        "Bani"
    ],
    "name:fas_x_preferred":[
        "\u0628\u0627\u0646\u06cc"
    ],
    "name:fra_x_preferred":[
        "Bani"
    ],
    "name:ita_x_preferred":[
        "Bani"
    ],
    "name:kat_x_preferred":[
        "\u10d1\u10d0\u10dc\u10d8"
    ],
    "name:nld_x_preferred":[
        "Bani"
    ],
    "name:por_x_preferred":[
        "Bani"
    ],
    "name:rus_x_preferred":[
        "\u0411\u0430\u043d\u0438"
    ],
    "name:spa_x_preferred":[
        "Bani"
    ],
    "name:swe_x_preferred":[
        "Bani"
    ],
    "name:war_x_preferred":[
        "Bani"
    ],
    "wof:name":"Bani",
    "wof:placetype":"locality",
    "wof:population":102
},
  "geometry": {"coordinates":[9.90521,45.95274000000001],"type":"Point"}
}