{
  "type": "Feature",
  "properties": {
    "gn:admin1_code":"1.0",
    "gn:admin2_code":"CH",
    "gn:admin3_code":"69005.0",
    "gn:asciiname":"Monte Marcone",
    "gn:country_code":"IT",
    "gn:dem":101,
    "gn:feature_class":"P",
    "gn:feature_code":"PPL",
    "gn:name":"Monte Marcone",
    "gn:population":765,
    "gn:timezone":"Europe/Rome",
    "iso:country":"IT",
    "wof:name":"Monte Marcone",
    "wof:placetype":"locality",
    "wof:population":765
},
  "geometry": {"coordinates":[14.43243,42.12346],"type":"Point"}
}