{
  "type": "Feature",
  "properties": {
    "gn:admin1_code":"16",
    "gn:admin2_code":"SI",
    "gn:admin3_code":"52022.0",
    "gn:asciiname":"Castiglioni",
    "gn:country_code":"IT",
    "gn:dem":166,
    "gn:feature_class":"P",
    "gn:feature_code":"PPL",
    "gn:name":"Castiglioni",
    "gn:population":187,
    "gn:timezone":"Europe/Rome",
    "iso:country":"IT",
    "wof:name":"Castiglioni",
    "wof:placetype":"locality",
    "wof:population":187
},
  "geometry": {"coordinates":[11.13761,43.43329],"type":"Point"}
}