{
  "type": "Feature",
  "properties": {
    "gn:admin1_code":"12.0",
    "gn:admin2_code":"AL",
    "gn:admin3_code":"6136.0",
    "gn:asciiname":"Ponzone",
    "gn:country_code":"IT",
    "gn:dem":602,
    "gn:elevation":"629.0",
    "gn:feature_class":"P",
    "gn:feature_code":"PPLA3",
    "gn:name":"Ponzone",
    "gn:population":150,
    "gn:timezone":"Europe/Rome",
    "iso:country":"IT",
    "name:deu_x_preferred":[
        "Ponzone"
    ],
    "name:eng_x_preferred":[
        "Ponzone"
    ],
    "name:epo_x_preferred":[
        "Ponzone"
    ],
    "name:fra_x_preferred":[
        "Ponzone"
    ],
    "name:ita_x_preferred":[
        "Ponzone"
    ],
    "name:nap_x_preferred":[
        "Ponzone"
    ],
    "name:nld_x_preferred":[
        "Ponzone"
    ],
    "name:pol_x_preferred":[
        "Ponzone"
    ],
    "name:por_x_preferred":[
        "Ponzone"
    ],
    "wof:name":"Ponzone",
    "wof:placetype":"locality",
    "wof:population":150
},
  "geometry": {"coordinates":[8.45935,44.58814],"type":"Point"}
}