{
  "type": "Feature",
  "properties": {
    "gn:admin1_code":"12.0",
    "gn:admin2_code":"AL",
    "gn:admin3_code":"6136.0",
    "gn:asciiname":"Ponzone",
    "gn:country_code":"IT",
    "gn:dem":602,
    "gn:elevation":"629.0",
    "gn:feature_class":"P",
    "gn:feature_code":"PPLA3",
    "gn:name":"Ponzone",
    "gn:population":150,
    "gn:timezone":"Europe/Rome",
    "iso:country":"IT",
    "name:ara_x_preferred":[
        "\u0628\u0648\u0646\u0632\u0648\u0646\u064a"
    ],
    "name:azb_x_preferred":[
        "\u067e\u0648\u0646\u062a\u0632\u0648\u0646\u0647"
    ],
    "name:bel_x_preferred":[
        "\u041f\u0430\u043d\u0446\u043e\u043d\u044d"
    ],
    "name:bul_x_preferred":[
        "\u041f\u043e\u043d\u0446\u043e\u043d\u0435"
    ],
    "name:cat_x_preferred":[
        "Ponzone"
    ],
    "name:ceb_x_preferred":[
        "Ponzone"
    ],
    "name:deu_x_preferred":[
        "Ponzone"
    ],
    "name:eng_x_preferred":[
        "Ponzone"
    ],
    "name:epo_x_preferred":[
        "Ponzone"
    ],
    "name:eus_x_preferred":[
        "Ponzone"
    ],
    "name:fas_x_preferred":[
        "\u067e\u0648\u0646\u062a\u0632\u0648\u0646\u0647"
    ],
    "name:fra_x_preferred":[
        "Ponzone"
    ],
    "name:hun_x_preferred":[
        "Ponzone"
    ],
    "name:hye_x_preferred":[
        "\u054a\u0578\u0576\u0581\u0578\u0576\u0565"
    ],
    "name:ind_x_preferred":[
        "Ponzone"
    ],
    "name:ita_x_preferred":[
        "Ponzone"
    ],
    "name:jpn_x_preferred":[
        "\u30dd\u30f3\u30c4\u30a9\u30fc\u30cd"
    ],
    "name:kaz_x_preferred":[
        "\u041f\u043e\u043d\u0446\u043e\u043d\u0435"
    ],
    "name:lat_x_preferred":[
        "Poncionum"
    ],
    "name:lmo_x_preferred":[
        "Ponzone"
    ],
    "name:msa_x_preferred":[
        "Ponzone"
    ],
    "name:nap_x_preferred":[
        "Ponzone"
    ],
    "name:nld_x_preferred":[
        "Ponzone"
    ],
    "name:pms_x_preferred":[
        "Ponson"
    ],
    "name:pol_x_preferred":[
        "Ponzone"
    ],
    "name:por_x_preferred":[
        "Ponzone"
    ],
    "name:ron_x_preferred":[
        "Ponzone"
    ],
    "name:rus_x_preferred":[
        "\u041f\u043e\u043d\u0446\u043e\u043d\u0435"
    ],
    "name:scn_x_preferred":[
        "Ponzone"
    ],
    "name:spa_x_preferred":[
        "Ponzone"
    ],
    "name:srp_x_preferred":[
        "\u041f\u043e\u043d\u0446\u043e\u043d\u0435"
    ],
    "name:tgl_x_preferred":[
        "Ponzone"
    ],
    "name:tur_x_preferred":[
        "Ponzone"
    ],
    "name:ukr_x_preferred":[
        "\u041f\u043e\u043d\u0446\u043e\u043d\u0435"
    ],
    "name:uzb_x_preferred":[
        "Ponzone"
    ],
    "name:vie_x_preferred":[
        "Ponzone"
    ],
    "name:vol_x_preferred":[
        "Ponzone"
    ],
    "name:war_x_preferred":[
        "Ponzone"
    ],
    "name:zho_x_preferred":[
        "\u84ec\u4f50\u5185"
    ],
    "wof:name":"Ponzone",
    "wof:placetype":"locality",
    "wof:population":150
},
  "geometry": {"coordinates":[8.45935,44.58814],"type":"Point"}
}