{
  "type": "Feature",
  "properties": {
    "gn:admin1_code":"4",
    "gn:admin2_code":"BN",
    "gn:admin3_code":"62059.0",
    "gn:asciiname":"Sant'Andrea",
    "gn:country_code":"IT",
    "gn:dem":555,
    "gn:feature_class":"P",
    "gn:feature_code":"PPL",
    "gn:name":"Sant'Andrea",
    "gn:population":34,
    "gn:timezone":"Europe/Rome",
    "iso:country":"IT",
    "name:ceb_x_preferred":[
        "Sant'Andrea"
    ],
    "name:deu_x_preferred":[
        "Sant\u2019Andrea"
    ],
    "name:fra_x_preferred":[
        "Sant'Andrea"
    ],
    "name:ita_x_preferred":[
        "Sant'Andrea"
    ],
    "name:por_x_preferred":[
        "Sant'Andrea"
    ],
    "name:sco_x_preferred":[
        "Sant'Andrea"
    ],
    "name:slv_x_preferred":[
        "Sant'Andrea"
    ],
    "name:srp_x_preferred":[
        "Sant'Andrea"
    ],
    "name:swe_x_preferred":[
        "Sant'Andrea"
    ],
    "wof:name":"Sant'Andrea",
    "wof:placetype":"locality",
    "wof:population":34
},
  "geometry": {"coordinates":[14.93688,41.26375],"type":"Point"}
}