{
  "type": "Feature",
  "properties": {
    "gn:admin1_code":"4",
    "gn:admin2_code":"BN",
    "gn:admin3_code":"62076.0",
    "gn:asciiname":"Iardino",
    "gn:country_code":"IT",
    "gn:dem":129,
    "gn:feature_class":"P",
    "gn:feature_code":"PPL",
    "gn:name":"Iardino",
    "gn:population":30,
    "gn:timezone":"Europe/Rome",
    "iso:country":"IT",
    "wof:name":"Iardino",
    "wof:placetype":"locality",
    "wof:population":30
},
  "geometry": {"coordinates":[14.72041,41.1835],"type":"Point"}
}