{
  "type": "Feature",
  "properties": {
    "gn:admin1_code":"5.0",
    "gn:admin2_code":"PR",
    "gn:admin3_code":"34038.0",
    "gn:asciiname":"Boschi di Bardone",
    "gn:cc2":"IT",
    "gn:country_code":"IT",
    "gn:dem":592,
    "gn:elevation":"594.0",
    "gn:feature_class":"P",
    "gn:feature_code":"PPL",
    "gn:name":"Boschi di Bardone",
    "gn:population":62,
    "gn:timezone":"Europe/Rome",
    "iso:country":"IT",
    "name:und_x_variant":[
        "Boschi di Bord",
        "Boschi di Bardone"
    ],
    "wof:name":"Boschi di Bardone",
    "wof:placetype":"locality",
    "wof:population":62
},
  "geometry": {"coordinates":[10.07929,44.63447],"type":"Point"}
}