{
  "type": "Feature",
  "properties": {
    "gn:admin1_code":"19",
    "gn:admin2_code":"AO",
    "gn:admin3_code":"7006.0",
    "gn:asciiname":"Charbonniere",
    "gn:country_code":"IT",
    "gn:dem":1273,
    "gn:feature_class":"P",
    "gn:feature_code":"PPL",
    "gn:name":"Charbonniere",
    "gn:population":20,
    "gn:timezone":"Europe/Rome",
    "iso:country":"IT",
    "wof:name":"Charbonniere",
    "wof:placetype":"locality",
    "wof:population":20
},
  "geometry": {"coordinates":[7.1509,45.71639],"type":"Point"}
}