{
  "type": "Feature",
  "properties": {
    "gn:admin1_code":"4",
    "gn:admin2_code":"AV",
    "gn:admin3_code":"64048.0",
    "gn:asciiname":"Murge",
    "gn:country_code":"IT",
    "gn:dem":290,
    "gn:feature_class":"P",
    "gn:feature_code":"PPL",
    "gn:name":"Murge",
    "gn:population":21,
    "gn:timezone":"Europe/Rome",
    "iso:country":"IT",
    "wof:name":"Murge",
    "wof:placetype":"locality",
    "wof:population":21
},
  "geometry": {"coordinates":[15.02769,41.1031],"type":"Point"}
}