{
  "type": "Feature",
  "properties": {
    "gn:admin1_code":"10.0",
    "gn:admin2_code":"AN",
    "gn:admin3_code":"42044.0",
    "gn:asciiname":"Coldellanoce",
    "gn:country_code":"IT",
    "gn:dem":391,
    "gn:elevation":"392.0",
    "gn:feature_class":"P",
    "gn:feature_code":"PPL",
    "gn:name":"Coldellanoce",
    "gn:population":48,
    "gn:timezone":"Europe/Rome",
    "iso:country":"IT",
    "wof:name":"Coldellanoce",
    "wof:placetype":"locality",
    "wof:population":48
},
  "geometry": {"coordinates":[12.82447,43.39763],"type":"Point"}
}