{
  "type": "Feature",
  "properties": {
    "gn:admin1_code":"9.0",
    "gn:admin2_code":"MI",
    "gn:admin3_code":"15150.0",
    "gn:asciiname":"Zona Industr. di Frazione Caselle",
    "gn:country_code":"IT",
    "gn:dem":113,
    "gn:feature_class":"P",
    "gn:feature_code":"PPL",
    "gn:name":"Zona Industr. di Frazione Caselle",
    "gn:population":0,
    "gn:timezone":"Europe/Rome",
    "iso:country":"IT",
    "wof:name":"Zona Industr. di Frazione Caselle",
    "wof:placetype":"locality"
},
  "geometry": {"coordinates":[8.94833,45.36857],"type":"Point"}
}