{
  "type": "Feature",
  "properties": {
    "gn:admin1_code":"20.0",
    "gn:admin2_code":"TV",
    "gn:admin3_code":"26078.0",
    "gn:asciiname":"Localita Col dei Buoi",
    "gn:country_code":"IT",
    "gn:dem":959,
    "gn:feature_class":"P",
    "gn:feature_code":"PPLL",
    "gn:name":"Localit\u00e0 Col dei Buoi",
    "gn:population":0,
    "gn:timezone":"Europe/Rome",
    "iso:country":"IT",
    "name:und_x_variant":[
        "Localit\u00e0 Col dei Buoi"
    ],
    "wof:name":"Localita Col dei Buoi",
    "wof:placetype":"locality"
},
  "geometry": {"coordinates":[12.39576,46.01445],"type":"Point"}
}