{
  "type": "Feature",
  "properties": {
    "gn:admin1_code":"16",
    "gn:admin2_code":"SI",
    "gn:admin3_code":"52012.0",
    "gn:asciiname":"Scarna",
    "gn:country_code":"IT",
    "gn:dem":224,
    "gn:feature_class":"P",
    "gn:feature_code":"PPL",
    "gn:name":"Scarna",
    "gn:population":56,
    "gn:timezone":"Europe/Rome",
    "iso:country":"IT",
    "wof:name":"Scarna",
    "wof:placetype":"locality",
    "wof:population":56
},
  "geometry": {"coordinates":[11.16158,43.39466],"type":"Point"}
}