{
  "type": "Feature",
  "properties": {
    "gn:admin1_code":"7",
    "gn:admin2_code":"FR",
    "gn:admin3_code":"60022.0",
    "gn:asciiname":"Il Circolo",
    "gn:country_code":"IT",
    "gn:dem":116,
    "gn:feature_class":"P",
    "gn:feature_code":"PPL",
    "gn:name":"Il Circolo",
    "gn:population":16,
    "gn:timezone":"Europe/Rome",
    "iso:country":"IT",
    "wof:name":"Il Circolo",
    "wof:placetype":"locality",
    "wof:population":16
},
  "geometry": {"coordinates":[13.66639,41.50135],"type":"Point"}
}