{
  "type": "Feature",
  "properties": {
    "gn:admin1_code":"20",
    "gn:admin2_code":"VI",
    "gn:admin3_code":"24052.0",
    "gn:asciiname":"Casette",
    "gn:country_code":"IT",
    "gn:dem":38,
    "gn:feature_class":"P",
    "gn:feature_code":"PPL",
    "gn:name":"Casette",
    "gn:population":40,
    "gn:timezone":"Europe/Rome",
    "iso:country":"IT",
    "wof:name":"Casette",
    "wof:placetype":"locality",
    "wof:population":40
},
  "geometry": {"coordinates":[11.36564,45.42923],"type":"Point"}
}