{
  "type": "Feature",
  "properties": {
    "gn:admin1_code":"16.0",
    "gn:admin2_code":"LI",
    "gn:admin3_code":"49016.0",
    "gn:asciiname":"Bagnaia",
    "gn:country_code":"IT",
    "gn:dem":6,
    "gn:elevation":"3.0",
    "gn:feature_class":"P",
    "gn:feature_code":"PPL",
    "gn:name":"Bagnaia",
    "gn:population":231,
    "gn:timezone":"Europe/Rome",
    "iso:country":"IT",
    "wof:name":"Bagnaia",
    "wof:placetype":"locality",
    "wof:population":231
},
  "geometry": {"coordinates":[10.36371,42.8114],"type":"Point"}
}