{
  "type": "Feature",
  "properties": {
    "gn:gn_country":"IT",
    "gn:gn_fcode":"PPL",
    "gn:gn_pop":0,
    "iso:country":"IT",
    "name:eng_x_preferred":[
        "Mortola Inferiore"
    ],
    "name:fra_x_preferred":[
        "Mortola Inferiore"
    ],
    "name:hun_x_preferred":[
        "Mortola Inferiore"
    ],
    "name:ita_x_preferred":[
        "mortola Inferiore"
    ],
    "name:nld_x_preferred":[
        "Mortola Inferiore"
    ],
    "qs_pg:aaroncc":"IT",
    "qs_pg:gn_country":"IT",
    "qs_pg:gn_fcode":"PPL",
    "qs_pg:gn_pop":0,
    "qs_pg:name":"Mortola Inferiore",
    "qs_pg:name_adm0":"Italia",
    "qs_pg:name_adm1":"Liguria",
    "qs_pg:photos":649,
    "qs_pg:photos_1k":132,
    "qs_pg:photos_9k":3,
    "qs_pg:photos_9r":5,
    "qs_pg:photos_all":649,
    "qs_pg:photos_sr":8,
    "qs_pg:pop_sr":0,
    "qs_pg:qs_pg_placetype":"locality",
    "qs_pg:qs_pg_placetype_gp":"Town",
    "qs_pg:woe_adm0":23424853,
    "woe:adm0_id":23424853,
    "woe:name_adm0":"Italia",
    "woe:name_adm1":"Liguria",
    "woe:placetype":"Town",
    "wof:name":"Mortola Inferiore",
    "wof:placetype":"locality"
},
  "geometry": {"coordinates":[7.55396,43.78566],"type":"Point"}
}