{
  "type": "Feature",
  "properties": {
    "gn:admin1_code":"5.0",
    "gn:admin2_code":"PR",
    "gn:admin3_code":"34038.0",
    "gn:asciiname":"Palmia",
    "gn:country_code":"IT",
    "gn:dem":360,
    "gn:feature_class":"P",
    "gn:feature_code":"PPL",
    "gn:name":"Palmia",
    "gn:population":71,
    "gn:timezone":"Europe/Rome",
    "iso:country":"IT",
    "name:ceb_x_preferred":[
        "Palmia"
    ],
    "name:nld_x_preferred":[
        "Palmia"
    ],
    "name:por_x_preferred":[
        "Palmia"
    ],
    "name:swe_x_preferred":[
        "Palmia"
    ],
    "name:vie_x_preferred":[
        "Palmia"
    ],
    "name:war_x_preferred":[
        "Palmia"
    ],
    "wof:name":"Palmia",
    "wof:placetype":"locality",
    "wof:population":71
},
  "geometry": {"coordinates":[10.12909,44.64288],"type":"Point"}
}