{
  "type": "Feature",
  "properties": {
    "gn:admin1_code":"16",
    "gn:admin2_code":"FI",
    "gn:admin3_code":"48027.0",
    "gn:asciiname":"Casastrada",
    "gn:country_code":"IT",
    "gn:dem":60,
    "gn:feature_class":"P",
    "gn:feature_code":"PPLL",
    "gn:name":"Casastrada",
    "gn:population":10,
    "gn:timezone":"Europe/Rome",
    "iso:country":"IT",
    "wof:name":"Casastrada",
    "wof:placetype":"locality",
    "wof:population":10
},
  "geometry": {"coordinates":[10.87635,43.61554],"type":"Point"}
}