{
  "type": "Feature",
  "properties": {
    "gn:admin1_code":"8",
    "gn:admin2_code":"GE",
    "gn:admin3_code":"10012.0",
    "gn:asciiname":"Stazione",
    "gn:country_code":"IT",
    "gn:dem":403,
    "gn:feature_class":"P",
    "gn:feature_code":"PPL",
    "gn:name":"Stazione",
    "gn:population":25,
    "gn:timezone":"Europe/Rome",
    "iso:country":"IT",
    "wof:name":"Stazione",
    "wof:placetype":"locality",
    "wof:population":25
},
  "geometry": {"coordinates":[8.9953,44.52951],"type":"Point"}
}