{
  "type": "Feature",
  "properties": {
    "gn:admin1_code":"1",
    "gn:admin2_code":"AQ",
    "gn:admin3_code":"66096.0",
    "gn:asciiname":"Area Indust. Artig. e Commerc. II",
    "gn:country_code":"IT",
    "gn:dem":716,
    "gn:feature_class":"P",
    "gn:feature_code":"PPL",
    "gn:name":"Area Indust. Artig. e Commerc. II",
    "gn:population":59,
    "gn:timezone":"Europe/Rome",
    "iso:country":"IT",
    "wof:name":"Area Indust. Artig. e Commerc. II",
    "wof:placetype":"locality",
    "wof:population":59
},
  "geometry": {"coordinates":[13.40107,42.05086],"type":"Point"}
}