{
  "type": "Feature",
  "properties": {
    "gn:admin1_code":"6.0",
    "gn:admin2_code":"UD",
    "gn:admin3_code":"30090.0",
    "gn:asciiname":"Ribis",
    "gn:country_code":"IT",
    "gn:dem":150,
    "gn:feature_class":"P",
    "gn:feature_code":"PPL",
    "gn:name":"Ribis",
    "gn:population":0,
    "gn:timezone":"Europe/Rome",
    "iso:country":"IT",
    "wof:name":"Ribis",
    "wof:placetype":"locality"
},
  "geometry": {"coordinates":[13.23056,46.13028],"type":"Point"}
}