{
  "type": "Feature",
  "properties": {
    "gn:admin1_code":"16",
    "gn:admin2_code":"FI",
    "gn:admin3_code":"48021.0",
    "gn:asciiname":"Case Poggio",
    "gn:country_code":"IT",
    "gn:dem":549,
    "gn:feature_class":"P",
    "gn:feature_code":"PPL",
    "gn:name":"Case Poggio",
    "gn:population":37,
    "gn:timezone":"Europe/Rome",
    "iso:country":"IT",
    "wof:name":"Case Poggio",
    "wof:placetype":"locality",
    "wof:population":37
},
  "geometry": {"coordinates":[11.35585,43.54515],"type":"Point"}
}