{
  "type": "Feature",
  "properties": {
    "gn:admin1_code":"16",
    "gn:admin2_code":"FI",
    "gn:admin3_code":"48046.0",
    "gn:asciiname":"Ferraglia",
    "gn:country_code":"IT",
    "gn:dem":447,
    "gn:feature_class":"P",
    "gn:feature_code":"PPL",
    "gn:name":"Ferraglia",
    "gn:population":27,
    "gn:timezone":"Europe/Rome",
    "iso:country":"IT",
    "wof:name":"Ferraglia",
    "wof:placetype":"locality",
    "wof:population":27
},
  "geometry": {"coordinates":[11.29437,43.88293],"type":"Point"}
}