{
  "type": "Feature",
  "properties": {
    "gn:admin1_code":"8.0",
    "gn:admin2_code":"IM",
    "gn:admin3_code":"8024.0",
    "gn:asciiname":"Piani Paorelli",
    "gn:country_code":"IT",
    "gn:dem":57,
    "gn:feature_class":"P",
    "gn:feature_code":"PPL",
    "gn:name":"Piani Paorelli",
    "gn:population":215,
    "gn:timezone":"Europe/Rome",
    "iso:country":"IT",
    "wof:name":"Piani Paorelli",
    "wof:placetype":"locality",
    "wof:population":215
},
  "geometry": {"coordinates":[7.9489,43.84985],"type":"Point"}
}