{
  "type": "Feature",
  "properties": {
    "gn:admin1_code":"20",
    "gn:admin2_code":"PD",
    "gn:admin3_code":"28045.0",
    "gn:asciiname":"Benetello",
    "gn:country_code":"IT",
    "gn:dem":16,
    "gn:feature_class":"P",
    "gn:feature_code":"PPL",
    "gn:name":"Benetello",
    "gn:population":38,
    "gn:timezone":"Europe/Rome",
    "iso:country":"IT",
    "wof:name":"Benetello",
    "wof:placetype":"locality",
    "wof:population":38
},
  "geometry": {"coordinates":[11.82183,45.48232],"type":"Point"}
}