{
  "type": "Feature",
  "properties": {
    "iso:country":"IT",
    "name:ita_x_preferred":[
        "Centro Congressi"
    ],
    "qs:gn_adm0_cc":"IT",
    "qs:gn_local":3176219,
    "qs:gn_nam_loc":"Genova, Genova, Genova, Liguria, IT",
    "qs:gn_namadm1":"08",
    "qs:local_max":6569,
    "qs:local_sum":41267,
    "qs:localhoods":37,
    "qs:name":"Centro Congressi",
    "qs:name_adm0":"Italia",
    "qs:name_adm1":"Liguria",
    "qs:name_adm2":"Genova",
    "qs:name_lau":"Genova",
    "qs:name_local":"Genova",
    "qs:photo_max":892,
    "qs:photo_sum":6569,
    "qs:placetype":"Suburb",
    "qs:quad_count":77,
    "qs:woe_adm0":23424853,
    "qs:woe_adm1":7153337,
    "qs:woe_adm2":12591832,
    "qs:woe_lau":12675811,
    "qs:woe_local":716085,
    "qs:woe_ver":"7.10.0",
    "wof:name":"Centro Congressi",
    "wof:placetype":"neighbourhood"
},
  "geometry": {"coordinates":[8.929721,44.409308],"type":"Point"}
}