{
  "type": "Feature",
  "properties": {
    "gn:admin1_code":"3",
    "gn:admin2_code":"VV",
    "gn:admin3_code":"102020.0",
    "gn:asciiname":"Piano Insediamenti Produttivi",
    "gn:country_code":"IT",
    "gn:dem":378,
    "gn:feature_class":"P",
    "gn:feature_code":"PPL",
    "gn:name":"Piano Insediamenti Produttivi",
    "gn:population":22,
    "gn:timezone":"Europe/Rome",
    "iso:country":"IT",
    "wof:name":"Piano Insediamenti Produttivi",
    "wof:placetype":"locality",
    "wof:population":22
},
  "geometry": {"coordinates":[16.16106,38.71108],"type":"Point"}
}