{
  "type": "Feature",
  "properties": {
    "gn:admin1_code":"16.0",
    "gn:admin2_code":"PI",
    "gn:admin3_code":"50034.0",
    "gn:asciiname":"Casa Sant'Andrea",
    "gn:country_code":"IT",
    "gn:dem":53,
    "gn:feature_class":"P",
    "gn:feature_code":"PPL",
    "gn:name":"Casa Sant'Andrea",
    "gn:population":0,
    "gn:timezone":"Europe/Rome",
    "iso:country":"IT",
    "wof:name":"Casa Sant'Andrea",
    "wof:placetype":"locality"
},
  "geometry": {"coordinates":[10.51667,43.43333],"type":"Point"}
}