{
  "type": "Feature",
  "properties": {
    "gn:admin1_code":"12",
    "gn:admin2_code":"TO",
    "gn:admin3_code":"1302.0",
    "gn:asciiname":"Roncaglia",
    "gn:country_code":"IT",
    "gn:dem":367,
    "gn:feature_class":"P",
    "gn:feature_code":"PPL",
    "gn:name":"Roncaglia",
    "gn:population":82,
    "gn:timezone":"Europe/Rome",
    "iso:country":"IT",
    "wof:name":"Roncaglia",
    "wof:placetype":"locality",
    "wof:population":82
},
  "geometry": {"coordinates":[7.49022,45.04296],"type":"Point"}
}