{
  "type": "Feature",
  "properties": {
    "gn:admin1_code":"10.0",
    "gn:admin2_code":"AP",
    "gn:admin3_code":"44014.0",
    "gn:asciiname":"Zona Artigianale Via della Stazione",
    "gn:country_code":"IT",
    "gn:dem":54,
    "gn:feature_class":"P",
    "gn:feature_code":"PPLL",
    "gn:name":"Zona Artigianale Via della Stazione",
    "gn:population":0,
    "gn:timezone":"Europe/Rome",
    "iso:country":"IT",
    "wof:name":"Zona Artigianale Via della Stazione",
    "wof:placetype":"locality"
},
  "geometry": {"coordinates":[13.75747,42.87028],"type":"Point"}
}