{
  "type": "Feature",
  "properties": {
    "gn:admin1_code":"15",
    "gn:admin2_code":"SR",
    "gn:admin3_code":"89001.0",
    "gn:asciiname":"Cozzo Filonero-Balate",
    "gn:country_code":"IT",
    "gn:dem":9,
    "gn:feature_class":"P",
    "gn:feature_code":"PPL",
    "gn:name":"Cozzo Filonero-Balate",
    "gn:population":134,
    "gn:timezone":"Europe/Rome",
    "iso:country":"IT",
    "wof:name":"Cozzo Filonero-Balate",
    "wof:placetype":"locality",
    "wof:population":134
},
  "geometry": {"coordinates":[15.2108,37.25251],"type":"Point"}
}