{
  "type": "Feature",
  "properties": {
    "gn:gn_country":"IT",
    "gn:gn_fcode":"PPL",
    "gn:gn_pop":0,
    "gn:population":707,
    "iso:country":"IT",
    "name:azb_x_preferred":[
        "\u0631\u0627\u0642\u0648\u0646\u06cc\u0627"
    ],
    "name:bel_x_preferred":[
        "\u0420\u0430\u0433\u043e\u043d'\u044f"
    ],
    "name:bul_x_preferred":[
        "\u0420\u0430\u0433\u043e\u043d\u044f"
    ],
    "name:cat_x_preferred":[
        "Ragogna"
    ],
    "name:ceb_x_preferred":[
        "Ragogna"
    ],
    "name:deu_x_preferred":[
        "Ragogna"
    ],
    "name:eng_x_preferred":[
        "Ragogna"
    ],
    "name:epo_x_preferred":[
        "Ragogna"
    ],
    "name:eus_x_preferred":[
        "Ragogna"
    ],
    "name:fas_x_preferred":[
        "\u0631\u0627\u06af\u0648\u0646\u06cc\u0627"
    ],
    "name:fra_x_preferred":[
        "Ragogna"
    ],
    "name:fur_x_preferred":[
        "Ruvigne"
    ],
    "name:hun_x_preferred":[
        "Ragogna"
    ],
    "name:hye_x_preferred":[
        "\u054c\u0561\u0563\u0578\u0576\u0575\u0561"
    ],
    "name:ina_x_preferred":[
        "Ragogna"
    ],
    "name:ind_x_preferred":[
        "Ragogna"
    ],
    "name:ita_x_preferred":[
        "Ragogna"
    ],
    "name:jpn_x_preferred":[
        "\u30e9\u30b4\u30fc\u30cb\u30e3"
    ],
    "name:kaz_x_preferred":[
        "\u0420\u0430\u0433\u043e\u043d\u044c\u044f"
    ],
    "name:lat_x_preferred":[
        "Reunia"
    ],
    "name:lmo_x_preferred":[
        "Ragogna"
    ],
    "name:msa_x_preferred":[
        "Ragogna"
    ],
    "name:nan_x_preferred":[
        "Ragogna"
    ],
    "name:nap_x_preferred":[
        "Ragogna"
    ],
    "name:nld_x_preferred":[
        "Ragogna"
    ],
    "name:oci_x_preferred":[
        "Ragogna"
    ],
    "name:pms_x_preferred":[
        "Ragogna"
    ],
    "name:pol_x_preferred":[
        "Ragogna"
    ],
    "name:por_x_preferred":[
        "Ragogna"
    ],
    "name:ron_x_preferred":[
        "Ragogna"
    ],
    "name:rus_x_preferred":[
        "\u0420\u0430\u0433\u043e\u043d\u044c\u044f"
    ],
    "name:scn_x_preferred":[
        "Ragogna"
    ],
    "name:spa_x_preferred":[
        "Ragogna"
    ],
    "name:srp_x_preferred":[
        "Ragogna"
    ],
    "name:ukr_x_preferred":[
        "\u0420\u0430\u0433\u043e\u043d\u044c\u044f"
    ],
    "name:uzb_x_preferred":[
        "Ragogna"
    ],
    "name:vie_x_preferred":[
        "Ragogna"
    ],
    "name:vol_x_preferred":[
        "Ragogna"
    ],
    "name:war_x_preferred":[
        "Ragogna"
    ],
    "name:zho_x_preferred":[
        "\u62c9\u6208\u5c3c\u4e9a"
    ],
    "qs_pg:aaroncc":"IT",
    "qs_pg:gn_country":"IT",
    "qs_pg:gn_fcode":"PPL",
    "qs_pg:gn_pop":0,
    "qs_pg:name":"Muris",
    "qs_pg:name_adm0":"Italia",
    "qs_pg:name_adm1":"Friuli-Venezia Giulia",
    "qs_pg:photos":89,
    "qs_pg:photos_1k":18,
    "qs_pg:photos_9k":1,
    "qs_pg:photos_9r":3,
    "qs_pg:photos_all":89,
    "qs_pg:photos_sr":3,
    "qs_pg:pop_sr":0,
    "qs_pg:qs_pg_placetype":"locality",
    "qs_pg:qs_pg_placetype_gp":"Town",
    "qs_pg:woe_adm0":23424853,
    "woe:adm0_id":23424853,
    "woe:name_adm0":"Italia",
    "woe:name_adm1":"Friuli-Venezia Giulia",
    "woe:placetype":"Town",
    "wof:name":"Muris",
    "wof:placetype":"locality",
    "wof:population":707
},
  "geometry": {"coordinates":[13.00333,46.19278],"type":"Point"}
}