{
  "type": "Feature",
  "properties": {
    "gn:admin1_code":"8.0",
    "gn:admin2_code":"GE",
    "gn:admin3_code":"10013.0",
    "gn:asciiname":"San Pietro Frascati",
    "gn:country_code":"IT",
    "gn:dem":222,
    "gn:feature_class":"P",
    "gn:feature_code":"PPL",
    "gn:name":"San Pietro Frascati",
    "gn:population":119,
    "gn:timezone":"Europe/Rome",
    "iso:country":"IT",
    "wof:name":"San Pietro Frascati",
    "wof:placetype":"locality",
    "wof:population":119
},
  "geometry": {"coordinates":[9.50287,44.27529000000001],"type":"Point"}
}