{
  "type": "Feature",
  "properties": {
    "gn:admin1_code":"5",
    "gn:admin2_code":"PR",
    "gn:admin3_code":"34027.0",
    "gn:asciiname":"Ravadese",
    "gn:country_code":"IT",
    "gn:dem":33,
    "gn:feature_class":"P",
    "gn:feature_code":"PPL",
    "gn:name":"Ravadese",
    "gn:population":100,
    "gn:timezone":"Europe/Rome",
    "iso:country":"IT",
    "wof:name":"Ravadese",
    "wof:placetype":"locality",
    "wof:population":100
},
  "geometry": {"coordinates":[10.37322,44.85836],"type":"Point"}
}