{
  "type": "Feature",
  "properties": {
    "gn:admin1_code":"20.0",
    "gn:admin2_code":"PD",
    "gn:admin3_code":"28077.0",
    "gn:asciiname":"Pila",
    "gn:country_code":"IT",
    "gn:dem":32,
    "gn:feature_class":"P",
    "gn:feature_code":"PPL",
    "gn:name":"Pila",
    "gn:population":20,
    "gn:timezone":"Europe/Rome",
    "iso:country":"IT",
    "wof:name":"Pila",
    "wof:placetype":"locality",
    "wof:population":20
},
  "geometry": {"coordinates":[11.85259,45.62379],"type":"Point"}
}