{
  "type": "Feature",
  "properties": {
    "gn:admin1_code":"9",
    "gn:admin2_code":"BG",
    "gn:admin3_code":"16084.0",
    "gn:asciiname":"Villa Landri",
    "gn:country_code":"IT",
    "gn:dem":215,
    "gn:feature_class":"P",
    "gn:feature_code":"PPL",
    "gn:name":"Villa Landri",
    "gn:population":70,
    "gn:timezone":"Europe/Rome",
    "iso:country":"IT",
    "wof:name":"Villa Landri",
    "wof:placetype":"locality",
    "wof:population":70
},
  "geometry": {"coordinates":[9.80466,45.65258],"type":"Point"}
}