{
  "type": "Feature",
  "properties": {
    "gn:admin1_code":"9.0",
    "gn:admin2_code":"VA",
    "gn:admin3_code":"12020.0",
    "gn:asciiname":"Bedero",
    "gn:country_code":"IT",
    "gn:dem":344,
    "gn:feature_class":"P",
    "gn:feature_code":"PPLA3",
    "gn:name":"Bedero",
    "gn:population":639,
    "gn:timezone":"Europe/Rome",
    "iso:country":"IT",
    "wof:name":"Bedero",
    "wof:placetype":"locality",
    "wof:population":639
},
  "geometry": {"coordinates":[8.71852,45.97776],"type":"Point"}
}