{
  "type": "Feature",
  "properties": {
    "gn:admin1_code":"20",
    "gn:admin2_code":"VR",
    "gn:admin3_code":"23070.0",
    "gn:asciiname":"Fusa",
    "gn:country_code":"IT",
    "gn:dem":257,
    "gn:feature_class":"P",
    "gn:feature_code":"PPL",
    "gn:name":"Fusa",
    "gn:population":26,
    "gn:timezone":"Europe/Rome",
    "iso:country":"IT",
    "name:bpy_x_preferred":[
        "\u09ab\u09c1\u09b8\u09be"
    ],
    "name:cat_x_preferred":[
        "Fusa"
    ],
    "name:ceb_x_preferred":[
        "Fusa"
    ],
    "name:dan_x_preferred":[
        "Fusa"
    ],
    "name:deu_x_preferred":[
        "Fusa"
    ],
    "name:epo_x_preferred":[
        "Fusa"
    ],
    "name:eus_x_preferred":[
        "Fusa"
    ],
    "name:fin_x_preferred":[
        "Fusa"
    ],
    "name:fra_x_preferred":[
        "Fusa"
    ],
    "name:ita_x_preferred":[
        "Fusa"
    ],
    "name:jav_x_preferred":[
        "Fusa"
    ],
    "name:lat_x_preferred":[
        "Fusa"
    ],
    "name:lim_x_preferred":[
        "Fusa"
    ],
    "name:msa_x_preferred":[
        "Fusa"
    ],
    "name:nds_x_preferred":[
        "Kommun Fusa"
    ],
    "name:nld_x_preferred":[
        "Fusa"
    ],
    "name:nno_x_preferred":[
        "Fusa kommune"
    ],
    "name:nor_x_preferred":[
        "Fusa"
    ],
    "name:pol_x_preferred":[
        "Fusa"
    ],
    "name:por_x_preferred":[
        "Fusa"
    ],
    "name:ron_x_preferred":[
        "Fusa"
    ],
    "name:rus_x_preferred":[
        "\u0424\u0443\u0441\u0430"
    ],
    "name:slv_x_preferred":[
        "Fusa"
    ],
    "name:sme_x_preferred":[
        "Fusa"
    ],
    "name:spa_x_preferred":[
        "Fusa"
    ],
    "name:sqi_x_preferred":[
        "Fusa"
    ],
    "name:swe_x_preferred":[
        "Fusa kommun"
    ],
    "name:vie_x_preferred":[
        "Fusa"
    ],
    "name:war_x_preferred":[
        "Fusa"
    ],
    "wof:name":"Fusa",
    "wof:placetype":"locality",
    "wof:population":26
},
  "geometry": {"coordinates":[11.23337,45.53823],"type":"Point"}
}