{
  "type": "Feature",
  "properties": {
    "gn:admin1_code":"16",
    "gn:admin2_code":"PI",
    "gn:admin3_code":"50032.0",
    "gn:asciiname":"Bottega Genovini",
    "gn:country_code":"IT",
    "gn:dem":44,
    "gn:feature_class":"P",
    "gn:feature_code":"PPL",
    "gn:name":"Bottega Genovini",
    "gn:population":27,
    "gn:timezone":"Europe/Rome",
    "iso:country":"IT",
    "wof:name":"Bottega Genovini",
    "wof:placetype":"locality",
    "wof:population":27
},
  "geometry": {"coordinates":[10.83452,43.64364000000001],"type":"Point"}
}