{
  "type": "Feature",
  "properties": {
    "gn:admin1_code":"9",
    "gn:admin2_code":"PV",
    "gn:admin3_code":"18164.0",
    "gn:asciiname":"Roventino",
    "gn:country_code":"IT",
    "gn:dem":99,
    "gn:feature_class":"P",
    "gn:feature_code":"PPL",
    "gn:name":"Roventino",
    "gn:population":15,
    "gn:timezone":"Europe/Rome",
    "iso:country":"IT",
    "wof:name":"Roventino",
    "wof:placetype":"locality",
    "wof:population":15
},
  "geometry": {"coordinates":[8.83282,45.22078],"type":"Point"}
}