{
  "type": "Feature",
  "properties": {
    "gn:admin1_code":"20",
    "gn:admin2_code":"PD",
    "gn:admin3_code":"28044.0",
    "gn:asciiname":"Ribon",
    "gn:country_code":"IT",
    "gn:dem":3,
    "gn:feature_class":"P",
    "gn:feature_code":"PPL",
    "gn:name":"Ribon",
    "gn:population":29,
    "gn:timezone":"Europe/Rome",
    "iso:country":"IT",
    "name:ara_x_preferred":[
        "\u0631\u064a\u0628\u0648\u0646"
    ],
    "name:ast_x_preferred":[
        "Ribon"
    ],
    "name:deu_x_preferred":[
        "Ribon"
    ],
    "name:fin_x_preferred":[
        "Ribon"
    ],
    "name:fra_x_preferred":[
        "Ribon"
    ],
    "name:ita_x_preferred":[
        "Ribon"
    ],
    "name:jpn_x_preferred":[
        "\u308a\u307c\u3093"
    ],
    "name:kor_x_preferred":[
        "\ub9ac\ubcf8"
    ],
    "name:nld_x_preferred":[
        "Ribon"
    ],
    "name:pol_x_preferred":[
        "Ribon"
    ],
    "name:por_x_preferred":[
        "Ribon"
    ],
    "name:rus_x_preferred":[
        "Ribon"
    ],
    "name:spa_x_preferred":[
        "Ribon"
    ],
    "name:tur_x_preferred":[
        "Ribon"
    ],
    "name:zho_x_preferred":[
        "Ribon"
    ],
    "wof:name":"Ribon",
    "wof:placetype":"locality",
    "wof:population":29
},
  "geometry": {"coordinates":[11.97957,45.33994000000001],"type":"Point"}
}