{
  "type": "Feature",
  "properties": {
    "gn:admin1_code":"4",
    "gn:admin2_code":"CE",
    "gn:admin3_code":"61051.0",
    "gn:asciiname":"Casa la Selva",
    "gn:country_code":"IT",
    "gn:dem":122,
    "gn:feature_class":"P",
    "gn:feature_code":"PPL",
    "gn:name":"Casa la Selva",
    "gn:population":52,
    "gn:timezone":"Europe/Rome",
    "iso:country":"IT",
    "wof:name":"Casa la Selva",
    "wof:placetype":"locality",
    "wof:population":52
},
  "geometry": {"coordinates":[13.95891,41.41374],"type":"Point"}
}