{
  "type": "Feature",
  "properties": {
    "gn:admin1_code":"20.0",
    "gn:admin2_code":"VR",
    "gn:admin3_code":"23087.0",
    "gn:asciiname":"Carbonari",
    "gn:country_code":"IT",
    "gn:dem":528,
    "gn:feature_class":"P",
    "gn:feature_code":"PPL",
    "gn:name":"Carbonari",
    "gn:population":0,
    "gn:timezone":"Europe/Rome",
    "iso:country":"IT",
    "name:ara_x_preferred":[
        "\u0643\u0627\u0631\u0628\u0648\u0646\u064a\u0631\u064a\u0627"
    ],
    "name:bel_x_preferred":[
        "\u041a\u0430\u0440\u0431\u0430\u043d\u0430\u0440\u044b\u0439"
    ],
    "name:cat_x_preferred":[
        "Carbonaris"
    ],
    "name:ckb_x_preferred":[
        "\u06a9\u0627\u0631\u0628\u06c6\u0646\u0627\u0631\u06cc"
    ],
    "name:deu_x_preferred":[
        "Carbonari"
    ],
    "name:ell_x_preferred":[
        "\u039a\u03b1\u03c1\u03bc\u03c0\u03bf\u03bd\u03ac\u03c1\u03bf\u03b9"
    ],
    "name:eus_x_preferred":[
        "Karbonari"
    ],
    "name:fin_x_preferred":[
        "Carbonari"
    ],
    "name:fra_x_preferred":[
        "Carbonarisme"
    ],
    "name:heb_x_preferred":[
        "\u05e7\u05e8\u05d1\u05d5\u05e0\u05d0\u05e8\u05d9"
    ],
    "name:hin_x_preferred":[
        "\u0915\u093e\u0930\u094d\u092c\u094b\u0928\u0930\u0940"
    ],
    "name:hun_x_preferred":[
        "Carbonari mozgalom"
    ],
    "name:hye_x_preferred":[
        "\u053f\u0561\u0580\u0562\u0578\u0576\u0561\u0580\u0576\u0565\u0580"
    ],
    "name:ido_x_preferred":[
        "Karbonaro"
    ],
    "name:ita_x_preferred":[
        "Carboneria"
    ],
    "name:jpn_x_preferred":[
        "\u30ab\u30eb\u30dc\u30ca\u30ea"
    ],
    "name:kat_x_preferred":[
        "\u10d9\u10d0\u10e0\u10d1\u10dd\u10dc\u10d0\u10e0\u10d4\u10d1\u10d8"
    ],
    "name:kaz_x_preferred":[
        "\u041a\u0430\u0440\u0431\u043e\u043d\u0430\u0440\u0438\u043b\u0435\u0440"
    ],
    "name:lit_x_preferred":[
        "Karbonarai"
    ],
    "name:nld_x_preferred":[
        "Carbonari"
    ],
    "name:nor_x_preferred":[
        "Carbonariene"
    ],
    "name:pol_x_preferred":[
        "Karbonariusze"
    ],
    "name:por_x_preferred":[
        "Carbon\u00e1ria"
    ],
    "name:rus_x_preferred":[
        "\u041a\u0430\u0440\u0431\u043e\u043d\u0430\u0440\u0438\u0438"
    ],
    "name:slv_x_preferred":[
        "Karbonarji"
    ],
    "name:spa_x_preferred":[
        "Carbonarios"
    ],
    "name:srp_x_preferred":[
        "\u041a\u0430\u0440\u0431\u043e\u043d\u0430\u0440\u0438"
    ],
    "name:swe_x_preferred":[
        "Carbonari"
    ],
    "name:tha_x_preferred":[
        "\u0e2a\u0e21\u0e32\u0e04\u0e21\u0e04\u0e32\u0e23\u0e4c\u0e42\u0e1a\u0e19\u0e32\u0e23\u0e35"
    ],
    "name:ukr_x_preferred":[
        "\u041a\u0430\u0440\u0431\u043e\u043d\u0430\u0440\u0456\u0457"
    ],
    "name:zho_x_preferred":[
        "\u70e7\u70ad\u515a"
    ],
    "wof:name":"Carbonari",
    "wof:placetype":"locality"
},
  "geometry": {"coordinates":[11.16667,45.55],"type":"Point"}
}