{
  "type": "Feature",
  "properties": {
    "gn:admin1_code":"20.0",
    "gn:admin2_code":"VR",
    "gn:admin3_code":"23087.0",
    "gn:asciiname":"Carbonari",
    "gn:country_code":"IT",
    "gn:dem":528,
    "gn:feature_class":"P",
    "gn:feature_code":"PPL",
    "gn:name":"Carbonari",
    "gn:population":0,
    "gn:timezone":"Europe/Rome",
    "iso:country":"IT",
    "wof:name":"Carbonari",
    "wof:placetype":"locality"
},
  "geometry": {"coordinates":[11.16667,45.55],"type":"Point"}
}