{
  "type": "Feature",
  "properties": {
    "gn:admin1_code":"9.0",
    "gn:admin2_code":"SO",
    "gn:admin3_code":"14024.0",
    "gn:asciiname":"Tagliate I",
    "gn:country_code":"IT",
    "gn:dem":1353,
    "gn:feature_class":"P",
    "gn:feature_code":"PPLL",
    "gn:name":"Tagliate I",
    "gn:population":0,
    "gn:timezone":"Europe/Rome",
    "iso:country":"IT",
    "wof:name":"Tagliate I",
    "wof:placetype":"locality"
},
  "geometry": {"coordinates":[9.53139,46.11161],"type":"Point"}
}