{
  "type": "Feature",
  "properties": {
    "gn:admin1_code":"8.0",
    "gn:admin2_code":"SV",
    "gn:admin3_code":"9060.0",
    "gn:asciiname":"Poggio",
    "gn:country_code":"IT",
    "gn:dem":423,
    "gn:feature_class":"P",
    "gn:feature_code":"PPL",
    "gn:name":"Poggio",
    "gn:population":11,
    "gn:timezone":"Europe/Rome",
    "iso:country":"IT",
    "wof:name":"Poggio",
    "wof:placetype":"locality",
    "wof:population":11
},
  "geometry": {"coordinates":[8.01604,44.00921],"type":"Point"}
}