{
  "type": "Feature",
  "properties": {
    "gn:admin1_code":"16.0",
    "gn:admin2_code":"LI",
    "gn:admin3_code":"49015.0",
    "gn:asciiname":"Punta di Rialbano",
    "gn:cc2":"IT",
    "gn:country_code":"IT",
    "gn:dem":7,
    "gn:feature_class":"P",
    "gn:feature_code":"PPL",
    "gn:name":"Punta di Rialbano",
    "gn:population":0,
    "gn:timezone":"Europe/Rome",
    "iso:country":"IT",
    "name:und_x_variant":[
        "Rio Albano"
    ],
    "wof:name":"Punta di Rialbano",
    "wof:placetype":"locality"
},
  "geometry": {"coordinates":[10.44302,42.84652],"type":"Point"}
}