{
  "type": "Feature",
  "properties": {
    "gn:admin1_code":"4",
    "gn:admin3_code":"63006.0",
    "gn:asciiname":"Scalandrone",
    "gn:country_code":"IT",
    "gn:dem":82,
    "gn:feature_class":"P",
    "gn:feature_code":"PPL",
    "gn:name":"Scalandrone",
    "gn:population":61,
    "gn:timezone":"Europe/Rome",
    "iso:country":"IT",
    "wof:name":"Scalandrone",
    "wof:placetype":"locality",
    "wof:population":61
},
  "geometry": {"coordinates":[14.06649,40.84379000000001],"type":"Point"}
}