{
  "type": "Feature",
  "properties": {
    "gn:admin1_code":"9",
    "gn:admin2_code":"PV",
    "gn:admin3_code":"18073.0",
    "gn:asciiname":"Bertignana",
    "gn:country_code":"IT",
    "gn:dem":201,
    "gn:feature_class":"P",
    "gn:feature_code":"PPL",
    "gn:name":"Bertignana",
    "gn:population":24,
    "gn:timezone":"Europe/Rome",
    "iso:country":"IT",
    "wof:name":"Bertignana",
    "wof:placetype":"locality",
    "wof:population":24
},
  "geometry": {"coordinates":[9.06024,44.88871],"type":"Point"}
}