{
  "type": "Feature",
  "properties": {
    "gn:admin1_code":"12",
    "gn:admin2_code":"CN",
    "gn:admin3_code":"4080.0",
    "gn:asciiname":"Carzello",
    "gn:country_code":"IT",
    "gn:dem":247,
    "gn:feature_class":"P",
    "gn:feature_code":"PPL",
    "gn:name":"Carzello",
    "gn:population":47,
    "gn:timezone":"Europe/Rome",
    "iso:country":"IT",
    "wof:name":"Carzello",
    "wof:placetype":"locality",
    "wof:population":47
},
  "geometry": {"coordinates":[8.0118,44.65431],"type":"Point"}
}