{
  "type": "Feature",
  "properties": {
    "gn:admin1_code":"4.0",
    "gn:admin2_code":"SA",
    "gn:admin3_code":"65067.0",
    "gn:asciiname":"Acquarola",
    "gn:country_code":"IT",
    "gn:dem":170,
    "gn:feature_class":"P",
    "gn:feature_code":"PPL",
    "gn:name":"Acquarola",
    "gn:population":677,
    "gn:timezone":"Europe/Rome",
    "iso:country":"IT",
    "wof:name":"Acquarola",
    "wof:placetype":"locality",
    "wof:population":677
},
  "geometry": {"coordinates":[14.72527,40.76872],"type":"Point"}
}