{
  "type": "Feature",
  "properties": {
    "gn:admin1_code":"8",
    "gn:admin2_code":"GE",
    "gn:admin3_code":"10025.0",
    "gn:asciiname":"Cartagenova",
    "gn:country_code":"IT",
    "gn:dem":219,
    "gn:feature_class":"P",
    "gn:feature_code":"PPL",
    "gn:name":"Cartagenova",
    "gn:population":149,
    "gn:timezone":"Europe/Rome",
    "iso:country":"IT",
    "wof:name":"Cartagenova",
    "wof:placetype":"locality",
    "wof:population":149
},
  "geometry": {"coordinates":[8.99266,44.46518],"type":"Point"}
}