{
  "type": "Feature",
  "properties": {
    "gn:admin1_code":"9",
    "gn:admin2_code":"BG",
    "gn:admin3_code":"16224.0",
    "gn:asciiname":"Arca Vuota",
    "gn:country_code":"IT",
    "gn:dem":272,
    "gn:feature_class":"P",
    "gn:feature_code":"PPL",
    "gn:name":"Arca Vuota",
    "gn:population":15,
    "gn:timezone":"Europe/Rome",
    "iso:country":"IT",
    "wof:name":"Arca Vuota",
    "wof:placetype":"locality",
    "wof:population":15
},
  "geometry": {"coordinates":[9.61661,45.72203],"type":"Point"}
}