{
  "type": "Feature",
  "properties": {
    "gn:admin1_code":"8",
    "gn:admin2_code":"SV",
    "gn:admin3_code":"9052.0",
    "gn:asciiname":"Faia",
    "gn:country_code":"IT",
    "gn:dem":319,
    "gn:feature_class":"P",
    "gn:feature_code":"PPL",
    "gn:name":"Faia",
    "gn:population":26,
    "gn:timezone":"Europe/Rome",
    "iso:country":"IT",
    "wof:name":"Faia",
    "wof:placetype":"locality",
    "wof:population":26
},
  "geometry": {"coordinates":[8.37543,44.27341],"type":"Point"}
}