{
  "type": "Feature",
  "properties": {
    "gn:admin1_code":"12",
    "gn:admin2_code":"TO",
    "gn:admin3_code":"1066.0",
    "gn:asciiname":"Case Spina",
    "gn:country_code":"IT",
    "gn:dem":351,
    "gn:feature_class":"P",
    "gn:feature_code":"PPL",
    "gn:name":"Case Spina",
    "gn:population":41,
    "gn:timezone":"Europe/Rome",
    "iso:country":"IT",
    "wof:name":"Case Spina",
    "wof:placetype":"locality",
    "wof:population":41
},
  "geometry": {"coordinates":[7.73043,45.39547],"type":"Point"}
}