{
  "type": "Feature",
  "properties": {
    "iso:country":"IT",
    "name:dut_x_preferred":[
        "Favrio"
    ],
    "name:eng_x_preferred":[
        "Favrio"
    ],
    "name:fin_x_preferred":[
        "Favrio"
    ],
    "name:fre_x_preferred":[
        "Favrio"
    ],
    "name:ger_x_preferred":[
        "Favrio"
    ],
    "name:hun_x_preferred":[
        "Favrio"
    ],
    "name:ita_x_preferred":[
        "Favrio"
    ],
    "name:srp_x_preferred":[
        "Favrio"
    ],
    "qs_pg:aaroncc":"IT",
    "qs_pg:name":"Favrio",
    "qs_pg:name_adm0":"Italia",
    "qs_pg:name_adm1":"Trentino-Alto Adige",
    "qs_pg:photos":30,
    "qs_pg:photos_1k":6,
    "qs_pg:photos_9k":1,
    "qs_pg:photos_9r":2,
    "qs_pg:photos_all":30,
    "qs_pg:photos_sr":2,
    "qs_pg:pop_sr":0,
    "qs_pg:qs_pg_placetype":"locality",
    "qs_pg:qs_pg_placetype_gp":"Town",
    "qs_pg:woe_adm0":23424853,
    "woe:adm0_id":23424853,
    "woe:name_adm0":"Italia",
    "woe:name_adm1":"Trentino-Alto Adige",
    "woe:placetype":"Town",
    "wof:name":"Favrio",
    "wof:placetype":"locality"
},
  "geometry": {"coordinates":[10.85741,45.999793],"type":"Point"}
}