{
  "type": "Feature",
  "properties": {
    "gn:admin1_code":"3",
    "gn:admin2_code":"RC",
    "gn:admin3_code":"80059.0",
    "gn:asciiname":"Titi",
    "gn:country_code":"IT",
    "gn:dem":517,
    "gn:feature_class":"P",
    "gn:feature_code":"PPL",
    "gn:name":"Titi",
    "gn:population":151,
    "gn:timezone":"Europe/Rome",
    "iso:country":"IT",
    "name:cat_x_preferred":[
        "Tit\u00ed"
    ],
    "name:deu_x_preferred":[
        "Springaffen"
    ],
    "name:eus_x_preferred":[
        "Titi"
    ],
    "name:fas_x_preferred":[
        "\u062a\u06cc\u200c\u062a\u06cc"
    ],
    "name:fra_x_preferred":[
        "Callicebinae"
    ],
    "name:pol_x_preferred":[
        "Titi"
    ],
    "name:rus_x_preferred":[
        "Callicebinae"
    ],
    "name:spa_x_preferred":[
        "Callicebinae"
    ],
    "wof:name":"Titi",
    "wof:placetype":"locality",
    "wof:population":151
},
  "geometry": {"coordinates":[16.43233,38.44417],"type":"Point"}
}