{
  "type": "Feature",
  "properties": {
    "gn:admin1_code":"17.0",
    "gn:admin2_code":"TN",
    "gn:admin3_code":"22050.0",
    "gn:asciiname":"Masi di Cavalese",
    "gn:country_code":"IT",
    "gn:dem":887,
    "gn:feature_class":"P",
    "gn:feature_code":"PPL",
    "gn:name":"Masi di Cavalese",
    "gn:population":527,
    "gn:timezone":"Europe/Rome",
    "iso:country":"IT",
    "wof:name":"Masi di Cavalese",
    "wof:placetype":"locality",
    "wof:population":527
},
  "geometry": {"coordinates":[11.48441,46.28195],"type":"Point"}
}