{
  "type": "Feature",
  "properties": {
    "gn:admin1_code":"3.0",
    "gn:admin2_code":"CS",
    "gn:admin3_code":"78034.0",
    "gn:asciiname":"La Matina",
    "gn:cc2":"IT",
    "gn:country_code":"IT",
    "gn:dem":1136,
    "gn:feature_class":"P",
    "gn:feature_code":"PPL",
    "gn:name":"La Matina",
    "gn:population":0,
    "gn:timezone":"Europe/Rome",
    "iso:country":"IT",
    "name:und_x_variant":[
        "Casa la Mattina",
        "La Matina"
    ],
    "wof:name":"La Matina",
    "wof:placetype":"locality"
},
  "geometry": {"coordinates":[16.51667,39.41667],"type":"Point"}
}