{
  "type": "Feature",
  "properties": {
    "gn:admin1_code":"4.0",
    "gn:admin2_code":"SA",
    "gn:admin3_code":"65040.0",
    "gn:asciiname":"San Biase",
    "gn:cc2":"IT",
    "gn:country_code":"IT",
    "gn:dem":495,
    "gn:elevation":"475.0",
    "gn:feature_class":"P",
    "gn:feature_code":"PPL",
    "gn:name":"San Biase",
    "gn:population":283,
    "gn:timezone":"Europe/Rome",
    "iso:country":"IT",
    "name:azb_x_preferred":[
        "\u0633\u0646 \u0628\u06cc\u0627\u0632\u0647"
    ],
    "name:bel_x_preferred":[
        "\u0421\u0430\u043d-\u0411\u2019\u044f\u0437\u044d"
    ],
    "name:bul_x_preferred":[
        "\u0421\u0430\u043d \u0411\u0438\u0430\u0437\u0435"
    ],
    "name:ceb_x_preferred":[
        "San Biase"
    ],
    "name:deu_x_preferred":[
        "San Biase"
    ],
    "name:epo_x_preferred":[
        "San Biase"
    ],
    "name:est_x_preferred":[
        "San Biase"
    ],
    "name:eus_x_preferred":[
        "San Biase"
    ],
    "name:fas_x_preferred":[
        "\u0633\u0646 \u0628\u06cc\u0627\u0632\u0647"
    ],
    "name:fra_x_preferred":[
        "San Biase"
    ],
    "name:hun_x_preferred":[
        "San Biase"
    ],
    "name:hye_x_preferred":[
        "\u054d\u0561\u0576 \u0532\u056b\u0561\u0566\u0565"
    ],
    "name:ina_x_preferred":[
        "San Biase"
    ],
    "name:ita_x_preferred":[
        "San Biase"
    ],
    "name:jpn_x_preferred":[
        "\u30b5\u30f3\u30fb\u30d3\u30a2\u30fc\u30bc"
    ],
    "name:kaz_x_preferred":[
        "\u0421\u0430\u043d-\u0411\u044c\u044f\u0437\u0435"
    ],
    "name:kor_x_preferred":[
        "\uc0b0\ube44\uc544\uc138"
    ],
    "name:lat_x_preferred":[
        "Fanum Sancti Blasii"
    ],
    "name:lmo_x_preferred":[
        "San Biase"
    ],
    "name:msa_x_preferred":[
        "San Biase"
    ],
    "name:nap_x_preferred":[
        "San Biase"
    ],
    "name:nld_x_preferred":[
        "San Biase"
    ],
    "name:pms_x_preferred":[
        "San Biase"
    ],
    "name:pol_x_preferred":[
        "San Biase"
    ],
    "name:por_x_preferred":[
        "San Biase"
    ],
    "name:ron_x_preferred":[
        "San Biase"
    ],
    "name:rus_x_preferred":[
        "\u0421\u0430\u043d-\u0411\u044c\u044f\u0437\u0435"
    ],
    "name:scn_x_preferred":[
        "San Biasi"
    ],
    "name:spa_x_preferred":[
        "San Biase"
    ],
    "name:srp_x_preferred":[
        "\u0421\u0430\u043d \u0411\u0458\u0430\u0437\u0435"
    ],
    "name:tgl_x_preferred":[
        "San Biase"
    ],
    "name:ukr_x_preferred":[
        "\u0421\u0430\u043d-\u0411'\u044f\u0437\u0435"
    ],
    "name:und_x_variant":[
        "San Blase",
        "San Biase"
    ],
    "name:uzb_x_preferred":[
        "San Biase"
    ],
    "name:vie_x_preferred":[
        "San Biase"
    ],
    "name:vol_x_preferred":[
        "San Biase"
    ],
    "name:war_x_preferred":[
        "San Biase"
    ],
    "name:zho_x_preferred":[
        "\u5723\u6bd4\u4e9a\u585e"
    ],
    "wof:name":"San Biase",
    "wof:placetype":"locality",
    "wof:population":283
},
  "geometry": {"coordinates":[15.28197,40.20338],"type":"Point"}
}