{
  "type": "Feature",
  "properties": {
    "gn:admin1_code":"4.0",
    "gn:admin2_code":"SA",
    "gn:admin3_code":"65040.0",
    "gn:asciiname":"San Biase",
    "gn:cc2":"IT",
    "gn:country_code":"IT",
    "gn:dem":495,
    "gn:elevation":"475.0",
    "gn:feature_class":"P",
    "gn:feature_code":"PPL",
    "gn:name":"San Biase",
    "gn:population":283,
    "gn:timezone":"Europe/Rome",
    "iso:country":"IT",
    "name:und_x_variant":[
        "San Blase",
        "San Biase"
    ],
    "wof:name":"San Biase",
    "wof:placetype":"locality",
    "wof:population":283
},
  "geometry": {"coordinates":[15.28197,40.20338],"type":"Point"}
}