{
  "type": "Feature",
  "properties": {
    "gn:admin1_code":"16",
    "gn:admin2_code":"AR",
    "gn:admin3_code":"51013.0",
    "gn:asciiname":"Nardi",
    "gn:country_code":"IT",
    "gn:dem":279,
    "gn:feature_class":"P",
    "gn:feature_code":"PPL",
    "gn:name":"Nardi",
    "gn:population":294,
    "gn:timezone":"Europe/Rome",
    "iso:country":"IT",
    "name:ita_x_preferred":[
        "Nardi"
    ],
    "wof:name":"Nardi",
    "wof:placetype":"locality",
    "wof:population":294
},
  "geometry": {"coordinates":[11.49776,43.52941],"type":"Point"}
}