{
  "type": "Feature",
  "properties": {
    "gn:admin1_code":"1",
    "gn:admin2_code":"CH",
    "gn:admin3_code":"69050.0",
    "gn:asciiname":"Renzetto",
    "gn:country_code":"IT",
    "gn:dem":150,
    "gn:feature_class":"P",
    "gn:feature_code":"PPL",
    "gn:name":"Renzetto",
    "gn:population":163,
    "gn:timezone":"Europe/Rome",
    "iso:country":"IT",
    "wof:name":"Renzetto",
    "wof:placetype":"locality",
    "wof:population":163
},
  "geometry": {"coordinates":[14.2662,42.32941],"type":"Point"}
}