{
  "type": "Feature",
  "properties": {
    "gn:country":"IT",
    "gn:fcode":"PPL",
    "gn:population":0,
    "iso:country":"IT",
    "name:eng_x_preferred":[
        "Ingurtosu"
    ],
    "name:fra_x_preferred":[
        "Ingurtosu"
    ],
    "name:hun_x_preferred":[
        "Ingurtosu"
    ],
    "name:ita_x_preferred":[
        "Ingurtosu"
    ],
    "name:nld_x_preferred":[
        "Ingurtosu"
    ],
    "name:und_x_variant":[
        "Miniera Ingurtosu"
    ],
    "qs_pg:aaroncc":"IT",
    "qs_pg:gn_country":"IT",
    "qs_pg:gn_fcode":"PPL",
    "qs_pg:gn_pop":0,
    "qs_pg:name":"Ingurtosu",
    "qs_pg:name_adm0":"Italia",
    "qs_pg:name_adm1":"Sardegna",
    "qs_pg:photos":331,
    "qs_pg:photos_1k":67,
    "qs_pg:photos_9k":1,
    "qs_pg:photos_9r":5,
    "qs_pg:photos_all":331,
    "qs_pg:photos_sr":5,
    "qs_pg:pop_sr":0,
    "qs_pg:qs_pg_placetype":"locality",
    "qs_pg:qs_pg_placetype_gp":"Town",
    "qs_pg:woe_adm0":23424853,
    "woe:adm0_id":23424853,
    "woe:name_adm0":"Italia",
    "woe:name_adm1":"Sardegna",
    "woe:placetype":"Town",
    "wof:name":"Ingurtosu",
    "wof:placetype":"locality"
},
  "geometry": {"coordinates":[8.5075,39.51972],"type":"Point"}
}