{
  "type": "Feature",
  "properties": {
    "gn:admin1_code":"7.0",
    "gn:admin2_code":"LT",
    "gn:admin3_code":"59011.0",
    "gn:asciiname":"Tor Tre Ponti",
    "gn:country_code":"IT",
    "gn:dem":15,
    "gn:feature_class":"P",
    "gn:feature_code":"PPL",
    "gn:name":"Tor Tre Ponti",
    "gn:population":235,
    "gn:timezone":"Europe/Rome",
    "iso:country":"IT",
    "wof:name":"Tor Tre Ponti",
    "wof:placetype":"locality",
    "wof:population":235
},
  "geometry": {"coordinates":[12.94516,41.50742],"type":"Point"}
}