{
  "type": "Feature",
  "properties": {
    "gn:admin1_code":"4.0",
    "gn:admin2_code":"AV",
    "gn:admin3_code":"64121.0",
    "gn:asciiname":"Pozzillo",
    "gn:country_code":"IT",
    "gn:dem":273,
    "gn:feature_class":"P",
    "gn:feature_code":"PPL",
    "gn:name":"Pozzillo",
    "gn:population":11,
    "gn:timezone":"Europe/Rome",
    "iso:country":"IT",
    "wof:name":"Pozzillo",
    "wof:placetype":"locality",
    "wof:population":11
},
  "geometry": {"coordinates":[14.80944,40.8298],"type":"Point"}
}