{
  "type": "Feature",
  "properties": {
    "gn:admin1_code":"3",
    "gn:admin2_code":"CS",
    "gn:admin3_code":"78091.0",
    "gn:asciiname":"San Giuliano",
    "gn:country_code":"IT",
    "gn:dem":24,
    "gn:feature_class":"P",
    "gn:feature_code":"PPL",
    "gn:name":"San Giuliano",
    "gn:population":53,
    "gn:timezone":"Europe/Rome",
    "iso:country":"IT",
    "wof:name":"San Giuliano",
    "wof:placetype":"locality",
    "wof:population":53
},
  "geometry": {"coordinates":[16.02303,39.3848],"type":"Point"}
}