{
  "type": "Feature",
  "properties": {
    "gn:admin1_code":"16",
    "gn:admin2_code":"LU",
    "gn:admin3_code":"46024.0",
    "gn:asciiname":"Saponiera",
    "gn:country_code":"IT",
    "gn:dem":1,
    "gn:feature_class":"P",
    "gn:feature_code":"PPL",
    "gn:name":"Saponiera",
    "gn:population":50,
    "gn:timezone":"Europe/Rome",
    "iso:country":"IT",
    "wof:name":"Saponiera",
    "wof:placetype":"locality",
    "wof:population":50
},
  "geometry": {"coordinates":[10.22087,43.93807],"type":"Point"}
}