{
  "type": "Feature",
  "properties": {
    "gn:admin1_code":"12",
    "gn:admin2_code":"TO",
    "gn:admin3_code":"1294.0",
    "gn:asciiname":"Rocca",
    "gn:country_code":"IT",
    "gn:dem":192,
    "gn:feature_class":"P",
    "gn:feature_code":"PPLL",
    "gn:name":"Rocca",
    "gn:population":10,
    "gn:timezone":"Europe/Rome",
    "iso:country":"IT",
    "name:bre_x_preferred":[
        "Rocca"
    ],
    "name:ceb_x_preferred":[
        "Rocca"
    ],
    "name:ces_x_preferred":[
        "Rocca"
    ],
    "name:deu_x_preferred":[
        "Rocca"
    ],
    "name:fra_x_preferred":[
        "Rocca"
    ],
    "name:ita_x_preferred":[
        "Rocca"
    ],
    "name:jpn_x_preferred":[
        "\u30ed\u30c3\u30ab"
    ],
    "name:lat_x_preferred":[
        "Rocca"
    ],
    "name:por_x_preferred":[
        "Rocca"
    ],
    "name:rus_x_preferred":[
        "\u0420\u043e\u043a\u043a\u0430"
    ],
    "name:sco_x_preferred":[
        "Rocca"
    ],
    "name:spa_x_preferred":[
        "Rocca"
    ],
    "name:srp_x_preferred":[
        "Roka"
    ],
    "name:swe_x_preferred":[
        "Rocca"
    ],
    "wof:name":"Rocca",
    "wof:placetype":"locality",
    "wof:population":10
},
  "geometry": {"coordinates":[8.09878,45.17441],"type":"Point"}
}