{
  "type": "Feature",
  "properties": {
    "gn:admin1_code":"16",
    "gn:admin2_code":"LU",
    "gn:admin3_code":"46030.0",
    "gn:asciiname":"Gallena",
    "gn:country_code":"IT",
    "gn:dem":351,
    "gn:feature_class":"P",
    "gn:feature_code":"PPL",
    "gn:name":"Gallena",
    "gn:population":68,
    "gn:timezone":"Europe/Rome",
    "iso:country":"IT",
    "wof:name":"Gallena",
    "wof:placetype":"locality",
    "wof:population":68
},
  "geometry": {"coordinates":[10.25164,43.99083],"type":"Point"}
}