{
  "type": "Feature",
  "properties": {
    "gn:admin1_code":"12",
    "gn:admin2_code":"CN",
    "gn:admin3_code":"4218.0",
    "gn:asciiname":"Ornato",
    "gn:country_code":"IT",
    "gn:dem":379,
    "gn:feature_class":"P",
    "gn:feature_code":"PPL",
    "gn:name":"Ornato",
    "gn:population":28,
    "gn:timezone":"Europe/Rome",
    "iso:country":"IT",
    "wof:name":"Ornato",
    "wof:placetype":"locality",
    "wof:population":28
},
  "geometry": {"coordinates":[8.00088,44.60018],"type":"Point"}
}