{
  "type": "Feature",
  "properties": {
    "gn:admin1_code":"12",
    "gn:admin2_code":"CN",
    "gn:admin3_code":"4061.0",
    "gn:asciiname":"Roata Boerino",
    "gn:country_code":"IT",
    "gn:dem":429,
    "gn:feature_class":"P",
    "gn:feature_code":"PPL",
    "gn:name":"Roata Boerino",
    "gn:population":15,
    "gn:timezone":"Europe/Rome",
    "iso:country":"IT",
    "wof:name":"Roata Boerino",
    "wof:placetype":"locality",
    "wof:population":15
},
  "geometry": {"coordinates":[7.60241,44.47562],"type":"Point"}
}