{
  "type": "Feature",
  "properties": {
    "gn:admin1_code":"9",
    "gn:admin2_code":"BS",
    "gn:admin3_code":"17088.0",
    "gn:asciiname":"Pluda",
    "gn:country_code":"IT",
    "gn:dem":65,
    "gn:feature_class":"P",
    "gn:feature_code":"PPL",
    "gn:name":"Pluda",
    "gn:population":23,
    "gn:timezone":"Europe/Rome",
    "iso:country":"IT",
    "wof:name":"Pluda",
    "wof:placetype":"locality",
    "wof:population":23
},
  "geometry": {"coordinates":[10.24462,45.35637],"type":"Point"}
}