{
  "type": "Feature",
  "properties": {
    "gn:admin1_code":"9",
    "gn:admin2_code":"BG",
    "gn:admin3_code":"16164.0",
    "gn:asciiname":"Castello",
    "gn:country_code":"IT",
    "gn:dem":542,
    "gn:feature_class":"P",
    "gn:feature_code":"PPL",
    "gn:name":"Castello",
    "gn:population":17,
    "gn:timezone":"Europe/Rome",
    "iso:country":"IT",
    "wof:name":"Castello",
    "wof:placetype":"locality",
    "wof:population":17
},
  "geometry": {"coordinates":[9.67054,45.94373],"type":"Point"}
}