{
  "type": "Feature",
  "properties": {
    "gn:admin1_code":"16",
    "gn:admin2_code":"AR",
    "gn:admin3_code":"51017.0",
    "gn:asciiname":"San Marco in Villa",
    "gn:country_code":"IT",
    "gn:dem":271,
    "gn:feature_class":"P",
    "gn:feature_code":"PPL",
    "gn:name":"San Marco in Villa",
    "gn:population":28,
    "gn:timezone":"Europe/Rome",
    "iso:country":"IT",
    "wof:name":"San Marco in Villa",
    "wof:placetype":"locality",
    "wof:population":28
},
  "geometry": {"coordinates":[11.99956,43.25761],"type":"Point"}
}