{
  "type": "Feature",
  "properties": {
    "gn:admin1_code":"1",
    "gn:admin2_code":"CH",
    "gn:admin3_code":"69058.0",
    "gn:asciiname":"Colombo",
    "gn:country_code":"IT",
    "gn:dem":128,
    "gn:feature_class":"P",
    "gn:feature_code":"PPL",
    "gn:name":"Colombo",
    "gn:population":36,
    "gn:timezone":"Europe/Rome",
    "iso:country":"IT",
    "wof:name":"Colombo",
    "wof:placetype":"locality",
    "wof:population":36
},
  "geometry": {"coordinates":[14.34411,42.34827],"type":"Point"}
}