{
  "type": "Feature",
  "properties": {
    "gn:admin1_code":"1",
    "gn:admin2_code":"TE",
    "gn:admin3_code":"67037.0",
    "gn:asciiname":"Villa Maise",
    "gn:country_code":"IT",
    "gn:dem":76,
    "gn:feature_class":"P",
    "gn:feature_code":"PPL",
    "gn:name":"Villa Mais\u00e8",
    "gn:population":29,
    "gn:timezone":"Europe/Rome",
    "iso:country":"IT",
    "name:und_x_variant":[
        "Villa Mais\u00e8"
    ],
    "wof:name":"Villa Maise",
    "wof:placetype":"locality",
    "wof:population":29
},
  "geometry": {"coordinates":[13.9563,42.70744000000001],"type":"Point"}
}