{
  "type": "Feature",
  "properties": {
    "gn:admin1_code":"12",
    "gn:admin2_code":"CN",
    "gn:admin3_code":"4059.0",
    "gn:asciiname":"Mana",
    "gn:country_code":"IT",
    "gn:dem":294,
    "gn:feature_class":"P",
    "gn:feature_code":"PPL",
    "gn:name":"Mana",
    "gn:population":27,
    "gn:timezone":"Europe/Rome",
    "iso:country":"IT",
    "wof:name":"Mana",
    "wof:placetype":"locality",
    "wof:population":27
},
  "geometry": {"coordinates":[7.73553,44.69924],"type":"Point"}
}