{
  "type": "Feature",
  "properties": {
    "gn:admin1_code":"9",
    "gn:admin2_code":"PV",
    "gn:admin3_code":"18100.0",
    "gn:asciiname":"Molinazzo",
    "gn:country_code":"IT",
    "gn:dem":127,
    "gn:feature_class":"P",
    "gn:feature_code":"PPLL",
    "gn:name":"Molinazzo",
    "gn:population":9,
    "gn:timezone":"Europe/Rome",
    "iso:country":"IT",
    "wof:name":"Molinazzo",
    "wof:placetype":"locality",
    "wof:population":9
},
  "geometry": {"coordinates":[9.30054,45.02339],"type":"Point"}
}