{
  "type": "Feature",
  "properties": {
    "gn:admin1_code":"5",
    "gn:admin2_code":"RE",
    "gn:admin3_code":"35032.0",
    "gn:asciiname":"Caselli",
    "gn:country_code":"IT",
    "gn:dem":20,
    "gn:feature_class":"P",
    "gn:feature_code":"PPL",
    "gn:name":"Caselli",
    "gn:population":59,
    "gn:timezone":"Europe/Rome",
    "iso:country":"IT",
    "wof:name":"Caselli",
    "wof:placetype":"locality",
    "wof:population":59
},
  "geometry": {"coordinates":[10.81545,44.92943],"type":"Point"}
}