{
  "type": "Feature",
  "properties": {
    "gn:admin1_code":"5",
    "gn:admin2_code":"MO",
    "gn:admin3_code":"36031.0",
    "gn:asciiname":"Casa Quattro",
    "gn:country_code":"IT",
    "gn:dem":1091,
    "gn:feature_class":"P",
    "gn:feature_code":"PPL",
    "gn:name":"Casa Quattro",
    "gn:population":18,
    "gn:timezone":"Europe/Rome",
    "iso:country":"IT",
    "wof:name":"Casa Quattro",
    "wof:placetype":"locality",
    "wof:population":18
},
  "geometry": {"coordinates":[10.60475,44.22578],"type":"Point"}
}