{
  "type": "Feature",
  "properties": {
    "gn:admin1_code":"9",
    "gn:admin2_code":"PV",
    "gn:admin3_code":"18171.0",
    "gn:asciiname":"Albareto",
    "gn:country_code":"IT",
    "gn:dem":557,
    "gn:feature_class":"P",
    "gn:feature_code":"PPL",
    "gn:name":"Albareto",
    "gn:population":23,
    "gn:timezone":"Europe/Rome",
    "iso:country":"IT",
    "name:ara_x_preferred":[
        "\u0623\u0644\u0628\u0627\u0631\u064a\u062a\u0648"
    ],
    "name:azb_x_preferred":[
        "\u0627\u0644\u0628\u0627\u0631\u062a\u0648"
    ],
    "name:bel_x_preferred":[
        "\u0410\u043b\u044c\u0431\u0430\u0440\u044d\u0442\u0430"
    ],
    "name:bul_x_preferred":[
        "\u0410\u043b\u0431\u0430\u0440\u0435\u0442\u043e"
    ],
    "name:cat_x_preferred":[
        "Albareto"
    ],
    "name:ceb_x_preferred":[
        "Albareto"
    ],
    "name:deu_x_preferred":[
        "Albareto"
    ],
    "name:eml_x_preferred":[
        "Albar\u00e8in"
    ],
    "name:epo_x_preferred":[
        "Albareto"
    ],
    "name:eus_x_preferred":[
        "Albareto"
    ],
    "name:fas_x_preferred":[
        "\u0627\u0644\u0628\u0627\u0631\u062a\u0648"
    ],
    "name:fra_x_preferred":[
        "Albareto"
    ],
    "name:hun_x_preferred":[
        "Albareto"
    ],
    "name:hye_x_preferred":[
        "\u0531\u056c\u0562\u0561\u0580\u0565\u057f\u0578"
    ],
    "name:ina_x_preferred":[
        "Albareto"
    ],
    "name:ita_x_preferred":[
        "Albareto"
    ],
    "name:jpn_x_preferred":[
        "\u30a2\u30eb\u30d0\u30ec\u30fc\u30c8"
    ],
    "name:kaz_x_preferred":[
        "\u0410\u043b\u044c\u0431\u0430\u0440\u0435\u0442\u043e"
    ],
    "name:lat_x_preferred":[
        "Albaretum"
    ],
    "name:lmo_x_preferred":[
        "Albareto"
    ],
    "name:msa_x_preferred":[
        "Albareto"
    ],
    "name:nap_x_preferred":[
        "Albareto"
    ],
    "name:nld_x_preferred":[
        "Albareto"
    ],
    "name:pms_x_preferred":[
        "Albareto"
    ],
    "name:pol_x_preferred":[
        "Albareto"
    ],
    "name:por_x_preferred":[
        "Albareto"
    ],
    "name:ron_x_preferred":[
        "Albareto"
    ],
    "name:rus_x_preferred":[
        "\u0410\u043b\u044c\u0431\u0430\u0440\u0435\u0442\u043e"
    ],
    "name:spa_x_preferred":[
        "Albareto"
    ],
    "name:srp_x_preferred":[
        "\u0410\u043b\u0431\u0430\u0440\u0435\u0442\u043e"
    ],
    "name:ukr_x_preferred":[
        "\u0410\u043b\u044c\u0431\u0430\u0440\u0435\u0442\u043e"
    ],
    "name:uzb_x_preferred":[
        "Albareto"
    ],
    "name:vie_x_preferred":[
        "Albareto"
    ],
    "name:vol_x_preferred":[
        "Albareto"
    ],
    "name:war_x_preferred":[
        "Albareto"
    ],
    "name:zho_x_preferred":[
        "\u963f\u5c14\u5df4\u96f7\u6258"
    ],
    "wof:name":"Albareto",
    "wof:placetype":"locality",
    "wof:population":23
},
  "geometry": {"coordinates":[9.19103,44.83583],"type":"Point"}
}