{
  "type": "Feature",
  "properties": {
    "gn:admin1_code":"12.0",
    "gn:admin2_code":"CN",
    "gn:admin3_code":"4034.0",
    "gn:asciiname":"San Chiaffredo",
    "gn:country_code":"IT",
    "gn:dem":495,
    "gn:feature_class":"P",
    "gn:feature_code":"PPL",
    "gn:name":"San Chiaffredo",
    "gn:population":818,
    "gn:timezone":"Europe/Rome",
    "iso:country":"IT",
    "wof:name":"San Chiaffredo",
    "wof:placetype":"locality",
    "wof:population":818
},
  "geometry": {"coordinates":[7.50204,44.47959],"type":"Point"}
}