{
  "type": "Feature",
  "properties": {
    "gn:admin1_code":"9.0",
    "gn:admin2_code":"PV",
    "gn:admin3_code":"18096.0",
    "gn:asciiname":"Versa",
    "gn:country_code":"IT",
    "gn:dem":259,
    "gn:feature_class":"P",
    "gn:feature_code":"PPL",
    "gn:name":"Versa",
    "gn:population":25,
    "gn:timezone":"Europe/Rome",
    "iso:country":"IT",
    "name:ceb_x_preferred":[
        "Versa"
    ],
    "name:deu_x_preferred":[
        "Versa"
    ],
    "name:ita_x_preferred":[
        "Versa"
    ],
    "name:pol_x_preferred":[
        "Versa"
    ],
    "name:spa_x_preferred":[
        "Versa"
    ],
    "name:srp_x_preferred":[
        "Versa"
    ],
    "name:swe_x_preferred":[
        "Versa"
    ],
    "wof:name":"Versa",
    "wof:placetype":"locality",
    "wof:population":25
},
  "geometry": {"coordinates":[9.2902,44.96465],"type":"Point"}
}