{
  "type": "Feature",
  "properties": {
    "gn:admin1_code":"15",
    "gn:admin2_code":"ME",
    "gn:admin3_code":"83027.0",
    "gn:asciiname":"Grotte",
    "gn:country_code":"IT",
    "gn:dem":115,
    "gn:feature_class":"P",
    "gn:feature_code":"PPL",
    "gn:name":"Grotte",
    "gn:population":177,
    "gn:timezone":"Europe/Rome",
    "iso:country":"IT",
    "wof:name":"Grotte",
    "wof:placetype":"locality",
    "wof:population":177
},
  "geometry": {"coordinates":[15.36215,37.96558],"type":"Point"}
}