{
  "type": "Feature",
  "properties": {
    "gn:admin1_code":"5.0",
    "gn:admin2_code":"FE",
    "gn:admin3_code":"38012.0",
    "gn:asciiname":"Ex Fornace",
    "gn:country_code":"IT",
    "gn:dem":-1,
    "gn:feature_class":"P",
    "gn:feature_code":"PPLL",
    "gn:name":"Ex Fornace",
    "gn:population":0,
    "gn:timezone":"Europe/Rome",
    "iso:country":"IT",
    "wof:name":"Ex Fornace",
    "wof:placetype":"locality"
},
  "geometry": {"coordinates":[11.79296,44.75773],"type":"Point"}
}