{
  "type": "Feature",
  "properties": {
    "gn:admin1_code":"16.0",
    "gn:admin2_code":"PI",
    "gn:admin3_code":"50031.0",
    "gn:asciiname":"Mezzana",
    "gn:country_code":"IT",
    "gn:dem":1,
    "gn:feature_class":"P",
    "gn:feature_code":"PPL",
    "gn:name":"Mezzana",
    "gn:population":0,
    "gn:timezone":"Europe/Rome",
    "iso:country":"IT",
    "name:ceb_x_preferred":[
        "Mezzana"
    ],
    "name:deu_x_preferred":[
        "Mezzana"
    ],
    "name:ita_x_preferred":[
        "Mezzana"
    ],
    "name:lat_x_preferred":[
        "Mediana"
    ],
    "name:lmo_x_preferred":[
        "Mezzana"
    ],
    "name:pms_x_preferred":[
        "Mezzana"
    ],
    "name:por_x_preferred":[
        "Mezzana"
    ],
    "name:srp_x_preferred":[
        "Mecana"
    ],
    "name:swe_x_preferred":[
        "Mezzana"
    ],
    "wof:name":"Mezzana",
    "wof:placetype":"locality"
},
  "geometry": {"coordinates":[10.46667,43.73333],"type":"Point"}
}