{
  "type": "Feature",
  "properties": {
    "gn:admin1_code":"16.0",
    "gn:admin2_code":"AR",
    "gn:admin3_code":"51005.0",
    "gn:asciiname":"Pietraviva",
    "gn:country_code":"IT",
    "gn:dem":285,
    "gn:elevation":"267.0",
    "gn:feature_class":"P",
    "gn:feature_code":"PPL",
    "gn:name":"Pietraviva",
    "gn:population":273,
    "gn:timezone":"Europe/Rome",
    "iso:country":"IT",
    "wof:name":"Pietraviva",
    "wof:placetype":"locality",
    "wof:population":273
},
  "geometry": {"coordinates":[11.58362,43.39457],"type":"Point"}
}