{
  "type": "Feature",
  "properties": {
    "gn:admin1_code":"16.0",
    "gn:admin2_code":"GR",
    "gn:admin3_code":"53014.0",
    "gn:asciiname":"Terme di Saturnia",
    "gn:country_code":"IT",
    "gn:dem":157,
    "gn:feature_class":"P",
    "gn:feature_code":"PPL",
    "gn:name":"Terme di Saturnia",
    "gn:population":0,
    "gn:timezone":"Europe/Rome",
    "iso:country":"IT",
    "wof:name":"Terme di Saturnia",
    "wof:placetype":"locality"
},
  "geometry": {"coordinates":[11.51882,42.65817],"type":"Point"}
}