{
  "type": "Feature",
  "properties": {
    "gn:admin1_code":"12",
    "gn:admin2_code":"CN",
    "gn:admin3_code":"4205.0",
    "gn:asciiname":"Cayre",
    "gn:country_code":"IT",
    "gn:dem":1005,
    "gn:feature_class":"P",
    "gn:feature_code":"PPL",
    "gn:name":"Cayre",
    "gn:population":16,
    "gn:timezone":"Europe/Rome",
    "iso:country":"IT",
    "wof:name":"Cayre",
    "wof:placetype":"locality",
    "wof:population":16
},
  "geometry": {"coordinates":[7.17077,44.57882],"type":"Point"}
}