{
  "type": "Feature",
  "properties": {
    "gn:admin1_code":"9",
    "gn:admin2_code":"BG",
    "gn:admin3_code":"16183.0",
    "gn:asciiname":"I Morti del Roccolo",
    "gn:country_code":"IT",
    "gn:dem":117,
    "gn:feature_class":"P",
    "gn:feature_code":"PPL",
    "gn:name":"I Morti del Roccolo",
    "gn:population":44,
    "gn:timezone":"Europe/Rome",
    "iso:country":"IT",
    "wof:name":"I Morti del Roccolo",
    "wof:placetype":"locality",
    "wof:population":44
},
  "geometry": {"coordinates":[9.73663,45.51816],"type":"Point"}
}