{
  "type": "Feature",
  "properties": {
    "gn:admin1_code":"12",
    "gn:admin2_code":"TO",
    "gn:admin3_code":"1232.0",
    "gn:asciiname":"Rival",
    "gn:country_code":"IT",
    "gn:dem":1039,
    "gn:feature_class":"P",
    "gn:feature_code":"PPLL",
    "gn:name":"Rival",
    "gn:population":8,
    "gn:timezone":"Europe/Rome",
    "iso:country":"IT",
    "wof:name":"Rival",
    "wof:placetype":"locality",
    "wof:population":8
},
  "geometry": {"coordinates":[6.86235,45.05932],"type":"Point"}
}