{
  "type": "Feature",
  "properties": {
    "gn:admin1_code":"1.0",
    "gn:admin2_code":"TE",
    "gn:admin3_code":"67026.0",
    "gn:asciiname":"Colliberti",
    "gn:country_code":"IT",
    "gn:dem":464,
    "gn:elevation":"457.0",
    "gn:feature_class":"P",
    "gn:feature_code":"PPL",
    "gn:name":"Colliberti",
    "gn:population":164,
    "gn:timezone":"Europe/Rome",
    "iso:country":"IT",
    "wof:name":"Colliberti",
    "wof:placetype":"locality",
    "wof:population":164
},
  "geometry": {"coordinates":[13.67061,42.50851],"type":"Point"}
}