{
  "type": "Feature",
  "properties": {
    "gn:admin1_code":"20",
    "gn:admin2_code":"PD",
    "gn:admin3_code":"28080.0",
    "gn:asciiname":"Toffano",
    "gn:country_code":"IT",
    "gn:dem":23,
    "gn:feature_class":"P",
    "gn:feature_code":"PPL",
    "gn:name":"Toffano",
    "gn:population":23,
    "gn:timezone":"Europe/Rome",
    "iso:country":"IT",
    "wof:name":"Toffano",
    "wof:placetype":"locality",
    "wof:population":23
},
  "geometry": {"coordinates":[11.87971,45.55882],"type":"Point"}
}