{
  "type": "Feature",
  "properties": {
    "gn:admin1_code":"16.0",
    "gn:admin2_code":"SI",
    "gn:admin3_code":"52004.0",
    "gn:asciiname":"Cavallano",
    "gn:country_code":"IT",
    "gn:dem":320,
    "gn:feature_class":"P",
    "gn:feature_code":"PPL",
    "gn:name":"Cavallano",
    "gn:population":421,
    "gn:timezone":"Europe/Rome",
    "iso:country":"IT",
    "wof:name":"Cavallano",
    "wof:placetype":"locality",
    "wof:population":421
},
  "geometry": {"coordinates":[11.03849,43.36356],"type":"Point"}
}