{
  "type": "Feature",
  "properties": {
    "gn:admin1_code":"9",
    "gn:admin2_code":"PV",
    "gn:admin3_code":"18084.0",
    "gn:asciiname":"Molino Lauzi",
    "gn:country_code":"IT",
    "gn:dem":76,
    "gn:feature_class":"P",
    "gn:feature_code":"PPL",
    "gn:name":"Molino Lauzi",
    "gn:population":29,
    "gn:timezone":"Europe/Rome",
    "iso:country":"IT",
    "wof:name":"Molino Lauzi",
    "wof:placetype":"locality",
    "wof:population":29
},
  "geometry": {"coordinates":[9.0927,45.03087],"type":"Point"}
}