{
  "type": "Feature",
  "properties": {
    "gn:admin1_code":"9",
    "gn:admin2_code":"BS",
    "gn:admin3_code":"17014.0",
    "gn:asciiname":"Fenilazzo",
    "gn:country_code":"IT",
    "gn:dem":148,
    "gn:feature_class":"P",
    "gn:feature_code":"PPL",
    "gn:name":"Fenilazzo",
    "gn:population":58,
    "gn:timezone":"Europe/Rome",
    "iso:country":"IT",
    "wof:name":"Fenilazzo",
    "wof:placetype":"locality",
    "wof:population":58
},
  "geometry": {"coordinates":[10.38206,45.48936],"type":"Point"}
}