{
  "type": "Feature",
  "properties": {
    "gn:admin1_code":"8.0",
    "gn:admin2_code":"SP",
    "gn:admin3_code":"11029.0",
    "gn:asciiname":"Codivilla",
    "gn:country_code":"IT",
    "gn:dem":778,
    "gn:elevation":"776.0",
    "gn:feature_class":"P",
    "gn:feature_code":"PPL",
    "gn:name":"Codivilla",
    "gn:population":8,
    "gn:timezone":"Europe/Rome",
    "iso:country":"IT",
    "wof:name":"Codivilla",
    "wof:placetype":"locality",
    "wof:population":8
},
  "geometry": {"coordinates":[9.49702,44.38918],"type":"Point"}
}