{
  "type": "Feature",
  "properties": {
    "gn:admin1_code":"5.0",
    "gn:admin2_code":"PR",
    "gn:admin3_code":"34013.0",
    "gn:asciiname":"Poggio",
    "gn:country_code":"IT",
    "gn:dem":264,
    "gn:elevation":"262.0",
    "gn:feature_class":"P",
    "gn:feature_code":"PPL",
    "gn:name":"Poggio",
    "gn:population":323,
    "gn:timezone":"Europe/Rome",
    "iso:country":"IT",
    "wof:name":"Poggio",
    "wof:placetype":"locality",
    "wof:population":323
},
  "geometry": {"coordinates":[10.19697,44.66043],"type":"Point"}
}