{
  "type": "Feature",
  "properties": {
    "gn:admin1_code":"12.0",
    "gn:admin2_code":"TO",
    "gn:admin3_code":"1017.0",
    "gn:asciiname":"Cascina Spina",
    "gn:country_code":"IT",
    "gn:dem":351,
    "gn:feature_class":"P",
    "gn:feature_code":"PPL",
    "gn:name":"Cascina Spina",
    "gn:population":26,
    "gn:timezone":"Europe/Rome",
    "iso:country":"IT",
    "wof:name":"Cascina Spina",
    "wof:placetype":"locality",
    "wof:population":26
},
  "geometry": {"coordinates":[7.73408,45.39577],"type":"Point"}
}