{
  "type": "Feature",
  "properties": {
    "gn:admin1_code":"16.0",
    "gn:admin2_code":"AR",
    "gn:admin3_code":"51012.0",
    "gn:asciiname":"Poggiolo",
    "gn:country_code":"IT",
    "gn:dem":275,
    "gn:elevation":"276.0",
    "gn:feature_class":"P",
    "gn:feature_code":"PPL",
    "gn:name":"Poggiolo",
    "gn:population":38,
    "gn:timezone":"Europe/Rome",
    "iso:country":"IT",
    "wof:name":"Poggiolo",
    "wof:placetype":"locality",
    "wof:population":38
},
  "geometry": {"coordinates":[11.93732,43.3277],"type":"Point"}
}