{
  "type": "Feature",
  "properties": {
    "gn:admin1_code":"16.0",
    "gn:admin2_code":"AR",
    "gn:admin3_code":"51012.0",
    "gn:asciiname":"Poggiolo",
    "gn:country_code":"IT",
    "gn:dem":275,
    "gn:elevation":"276.0",
    "gn:feature_class":"P",
    "gn:feature_code":"PPL",
    "gn:name":"Poggiolo",
    "gn:population":38,
    "gn:timezone":"Europe/Rome",
    "iso:country":"IT",
    "name:cat_x_preferred":[
        "Poggiolo"
    ],
    "name:ceb_x_preferred":[
        "Poggiolo"
    ],
    "name:cos_x_preferred":[
        "U Pighjolu"
    ],
    "name:deu_x_preferred":[
        "Poggiolo"
    ],
    "name:eus_x_preferred":[
        "Poggiolo"
    ],
    "name:fra_x_preferred":[
        "Poggiolo"
    ],
    "name:hun_x_preferred":[
        "Poggiolo"
    ],
    "name:hye_x_preferred":[
        "\u054a\u0578\u057b\u0578\u056c\u0578"
    ],
    "name:ind_x_preferred":[
        "Poggiolo"
    ],
    "name:ita_x_preferred":[
        "Poggiolo"
    ],
    "name:kaz_x_preferred":[
        "\u041f\u043e\u0434\u0436\u043e\u043b\u043e"
    ],
    "name:lat_x_preferred":[
        "Poggiolo"
    ],
    "name:lmo_x_preferred":[
        "Poggiolo"
    ],
    "name:msa_x_preferred":[
        "Poggiolo"
    ],
    "name:nld_x_preferred":[
        "Poggiolo"
    ],
    "name:nor_x_preferred":[
        "Poggiolo"
    ],
    "name:oci_x_preferred":[
        "Poggiolo"
    ],
    "name:pol_x_preferred":[
        "Poggiolo"
    ],
    "name:por_x_preferred":[
        "Poggiolo"
    ],
    "name:rus_x_preferred":[
        "\u041f\u043e\u0434\u0436\u043e\u043b\u043e"
    ],
    "name:slk_x_preferred":[
        "Poggiolo"
    ],
    "name:slv_x_preferred":[
        "Poggiolo"
    ],
    "name:spa_x_preferred":[
        "Poggiolo"
    ],
    "name:swe_x_preferred":[
        "Poggiolo"
    ],
    "name:ukr_x_preferred":[
        "\u041f\u043e\u0434\u0436\u043e\u043b\u043e"
    ],
    "name:vie_x_preferred":[
        "Poggiolo"
    ],
    "name:vol_x_preferred":[
        "Poggiolo"
    ],
    "name:war_x_preferred":[
        "Poggiolo"
    ],
    "wof:name":"Poggiolo",
    "wof:placetype":"locality",
    "wof:population":38
},
  "geometry": {"coordinates":[11.93732,43.3277],"type":"Point"}
}