{
  "type": "Feature",
  "properties": {
    "gn:admin1_code":"12",
    "gn:admin2_code":"VB",
    "gn:admin3_code":"103046.0",
    "gn:asciiname":"Naviledo",
    "gn:country_code":"IT",
    "gn:dem":602,
    "gn:feature_class":"P",
    "gn:feature_code":"PPL",
    "gn:name":"Naviledo",
    "gn:population":23,
    "gn:timezone":"Europe/Rome",
    "iso:country":"IT",
    "wof:name":"Naviledo",
    "wof:placetype":"locality",
    "wof:population":23
},
  "geometry": {"coordinates":[8.34131,46.16026],"type":"Point"}
}