{
  "type": "Feature",
  "properties": {
    "gn:admin1_code":"16",
    "gn:admin2_code":"AR",
    "gn:admin3_code":"51037.0",
    "gn:asciiname":"Poggio d'Acona",
    "gn:country_code":"IT",
    "gn:dem":494,
    "gn:feature_class":"P",
    "gn:feature_code":"PPL",
    "gn:name":"Poggio d'Acona",
    "gn:population":36,
    "gn:timezone":"Europe/Rome",
    "iso:country":"IT",
    "wof:name":"Poggio d'Acona",
    "wof:placetype":"locality",
    "wof:population":36
},
  "geometry": {"coordinates":[11.8755,43.63429],"type":"Point"}
}