{
  "type": "Feature",
  "properties": {
    "iso:country":"IT",
    "wof:name":"Romagnolo",
    "wof:placetype":"neighbourhood"
},
  "geometry": {"coordinates":[13.39022901176322,38.10364450455697],"type":"Point"}
}