{
  "type": "Feature",
  "properties": {
    "gn:admin1_code":"13",
    "gn:admin2_code":"LE",
    "gn:admin3_code":"75094.0",
    "gn:asciiname":"Zona Industriale",
    "gn:country_code":"IT",
    "gn:dem":76,
    "gn:feature_class":"P",
    "gn:feature_code":"PPL",
    "gn:name":"Zona Industriale",
    "gn:population":22,
    "gn:timezone":"Europe/Rome",
    "iso:country":"IT",
    "name:deu_x_preferred":[
        "Zona Industriale"
    ],
    "name:fra_x_preferred":[
        "Zona Industriale"
    ],
    "name:ita_x_preferred":[
        "Zona Industriale"
    ],
    "name:nap_x_preferred":[
        "Zona Nnustriale"
    ],
    "wof:name":"Zona Industriale",
    "wof:placetype":"locality",
    "wof:population":22
},
  "geometry": {"coordinates":[18.24087,40.21026],"type":"Point"}
}