{
  "type": "Feature",
  "properties": {
    "gn:admin1_code":"20.0",
    "gn:admin2_code":"VE",
    "gn:admin3_code":"27001.0",
    "gn:asciiname":"Loncon",
    "gn:country_code":"IT",
    "gn:dem":2,
    "gn:feature_class":"P",
    "gn:feature_code":"PPL",
    "gn:name":"Loncon",
    "gn:population":0,
    "gn:timezone":"Europe/Rome",
    "iso:country":"IT",
    "wof:name":"Loncon",
    "wof:placetype":"locality"
},
  "geometry": {"coordinates":[12.71306,45.76667],"type":"Point"}
}