{
  "type": "Feature",
  "properties": {
    "gn:admin1_code":"20.0",
    "gn:admin2_code":"VI",
    "gn:admin3_code":"24019.0",
    "gn:asciiname":"Sieresara",
    "gn:country_code":"IT",
    "gn:dem":223,
    "gn:feature_class":"P",
    "gn:feature_code":"PPLL",
    "gn:name":"Sieresara",
    "gn:population":0,
    "gn:timezone":"Europe/Rome",
    "iso:country":"IT",
    "wof:name":"Sieresara",
    "wof:placetype":"locality"
},
  "geometry": {"coordinates":[11.48234,45.76484],"type":"Point"}
}