{
  "type": "Feature",
  "properties": {
    "gn:admin1_code":"19",
    "gn:admin2_code":"AO",
    "gn:admin3_code":"7015.0",
    "gn:asciiname":"Parleaz",
    "gn:country_code":"IT",
    "gn:dem":468,
    "gn:feature_class":"P",
    "gn:feature_code":"PPL",
    "gn:name":"Parleaz",
    "gn:population":21,
    "gn:timezone":"Europe/Rome",
    "iso:country":"IT",
    "wof:name":"Parleaz",
    "wof:placetype":"locality",
    "wof:population":21
},
  "geometry": {"coordinates":[7.57011,45.74601],"type":"Point"}
}