{
  "type": "Feature",
  "properties": {
    "gn:admin1_code":"15.0",
    "gn:admin2_code":"RG",
    "gn:admin3_code":"88006.0",
    "gn:asciiname":"Musebbi II",
    "gn:country_code":"IT",
    "gn:dem":421,
    "gn:feature_class":"P",
    "gn:feature_code":"PPL",
    "gn:name":"Musebbi II",
    "gn:population":35,
    "gn:timezone":"Europe/Rome",
    "iso:country":"IT",
    "wof:name":"Musebbi II",
    "wof:placetype":"locality",
    "wof:population":35
},
  "geometry": {"coordinates":[14.80448,36.83574],"type":"Point"}
}