{
  "type": "Feature",
  "properties": {
    "gn:admin1_code":"12",
    "gn:admin2_code":"VC",
    "gn:admin3_code":"2025.0",
    "gn:asciiname":"Rusa",
    "gn:country_code":"IT",
    "gn:dem":882,
    "gn:feature_class":"P",
    "gn:feature_code":"PPLL",
    "gn:name":"Rusa",
    "gn:population":5,
    "gn:timezone":"Europe/Rome",
    "iso:country":"IT",
    "name:cat_x_preferred":[
        "Rusa"
    ],
    "name:ceb_x_preferred":[
        "Rusa"
    ],
    "name:deu_x_preferred":[
        "Rusa"
    ],
    "name:fin_x_preferred":[
        "Rusa"
    ],
    "name:fra_x_preferred":[
        "Rusa"
    ],
    "name:hun_x_preferred":[
        "Rusza"
    ],
    "name:pol_x_preferred":[
        "Rusa"
    ],
    "name:swe_x_preferred":[
        "Rusa"
    ],
    "wof:name":"Rusa",
    "wof:placetype":"locality",
    "wof:population":5
},
  "geometry": {"coordinates":[8.02934,45.80886],"type":"Point"}
}