{
  "type": "Feature",
  "properties": {
    "gn:elevation":23,
    "gn:population":1207,
    "iso:country":"IT",
    "name:bul_x_preferred":[
        "\u041a\u0430\u043c\u043f\u043e\u0434\u043e\u0440\u043e"
    ],
    "name:cat_x_preferred":[
        "Campodoro"
    ],
    "name:deu_x_preferred":[
        "Campodoro"
    ],
    "name:eng_x_preferred":[
        "Campodoro"
    ],
    "name:epo_x_preferred":[
        "Campodoro"
    ],
    "name:eus_x_preferred":[
        "Campodoro"
    ],
    "name:fas_x_preferred":[
        "\u06a9\u0627\u0645\u067e\u0648\u062f\u0648\u0631\u0648"
    ],
    "name:fin_x_preferred":[
        "Campodoro"
    ],
    "name:fra_x_preferred":[
        "Campodoro"
    ],
    "name:fra_x_variant":[
        "campodoro"
    ],
    "name:hbs_x_preferred":[
        "Campodoro"
    ],
    "name:hun_x_preferred":[
        "Campodoro"
    ],
    "name:hye_x_preferred":[
        "\u053f\u0561\u0574\u057a\u0578\u0564\u0578\u0580\u0578"
    ],
    "name:ind_x_preferred":[
        "Campodoro"
    ],
    "name:ita_x_preferred":[
        "Campodoro"
    ],
    "name:jpn_x_preferred":[
        "\u30ab\u30f3\u30dd\u30c9\u30fc\u30ed"
    ],
    "name:kaz_x_preferred":[
        "\u041a\u0430\u043c\u043f\u043e\u0434\u043e\u0440\u043e"
    ],
    "name:lat_x_preferred":[
        "Campus Longus Minor"
    ],
    "name:lmo_x_preferred":[
        "Campodoro"
    ],
    "name:msa_x_preferred":[
        "Campodoro"
    ],
    "name:nan_x_preferred":[
        "Campodoro"
    ],
    "name:nap_x_preferred":[
        "Campodoro"
    ],
    "name:nld_x_preferred":[
        "Campodoro"
    ],
    "name:oci_x_preferred":[
        "Campodoro"
    ],
    "name:pms_x_preferred":[
        "Campodoro"
    ],
    "name:pol_x_preferred":[
        "Campodoro"
    ],
    "name:por_x_preferred":[
        "Campodoro"
    ],
    "name:ron_x_preferred":[
        "Campodoro"
    ],
    "name:rus_x_preferred":[
        "\u041a\u0430\u043c\u043f\u043e\u0434\u043e\u0440\u043e"
    ],
    "name:scn_x_preferred":[
        "Campodoro"
    ],
    "name:spa_x_preferred":[
        "Campodoro"
    ],
    "name:srp_x_preferred":[
        "\u041a\u0430\u043c\u043f\u043e\u0434\u043e\u0440\u043e"
    ],
    "name:tgl_x_preferred":[
        "Campodoro"
    ],
    "name:ukr_x_preferred":[
        "\u041a\u0430\u043c\u043f\u043e\u0434\u043e\u0440\u043e"
    ],
    "name:uzb_x_preferred":[
        "Campodoro"
    ],
    "name:vec_x_preferred":[
        "Canpod\u00f2ro"
    ],
    "name:vie_x_preferred":[
        "Campodoro"
    ],
    "name:vol_x_preferred":[
        "Campodoro"
    ],
    "name:war_x_preferred":[
        "Campodoro"
    ],
    "name:zho_min_nan_x_preferred":[
        "Campodoro"
    ],
    "name:zho_x_preferred":[
        "\u574e\u6ce2\u591a\u7f57"
    ],
    "qs:a0":"Italia",
    "qs:a1":"*Padova",
    "qs:a1r":"0Veneto",
    "qs:adm0":"Italia",
    "qs:la_lc":"*",
    "qs:level":"locality",
    "qs:loc":"Campodoro",
    "qs:loc_alt":"Campodoro",
    "qs:pop":0,
    "qs:type":"buffered point",
    "wd:wordcount":108,
    "wof:lang":[
        "ita"
    ],
    "wof:name":"Campodoro",
    "wof:placetype":"locality",
    "wof:population":1207
},
  "geometry": {"coordinates":[11.75278,45.491112],"type":"Point"}
}