{
  "type": "Feature",
  "properties": {
    "gn:admin1_code":"20.0",
    "gn:admin2_code":"VR",
    "gn:admin3_code":"23070.0",
    "gn:asciiname":"Ranchetti",
    "gn:country_code":"IT",
    "gn:dem":474,
    "gn:feature_class":"P",
    "gn:feature_code":"PPL",
    "gn:name":"Ranchetti",
    "gn:population":19,
    "gn:timezone":"Europe/Rome",
    "iso:country":"IT",
    "wof:name":"Ranchetti",
    "wof:placetype":"locality",
    "wof:population":19
},
  "geometry": {"coordinates":[11.23806,45.5467],"type":"Point"}
}