{
  "type": "Feature",
  "properties": {
    "gn:admin1_code":"10.0",
    "gn:admin2_code":"MC",
    "gn:admin3_code":"43002.0",
    "gn:asciiname":"Sant'Andrea",
    "gn:country_code":"IT",
    "gn:dem":389,
    "gn:elevation":"432.0",
    "gn:feature_class":"P",
    "gn:feature_code":"PPL",
    "gn:name":"Sant'Andrea",
    "gn:population":14,
    "gn:timezone":"Europe/Rome",
    "iso:country":"IT",
    "name:ceb_x_preferred":[
        "Sant'Andrea"
    ],
    "name:deu_x_preferred":[
        "Sant\u2019Andrea"
    ],
    "name:fra_x_preferred":[
        "Sant'Andrea"
    ],
    "name:ita_x_preferred":[
        "Sant'Andrea"
    ],
    "name:por_x_preferred":[
        "Sant'Andrea"
    ],
    "name:sco_x_preferred":[
        "Sant'Andrea"
    ],
    "name:slv_x_preferred":[
        "Sant'Andrea"
    ],
    "name:srp_x_preferred":[
        "Sant'Andrea"
    ],
    "name:swe_x_preferred":[
        "Sant'Andrea"
    ],
    "wof:name":"Sant'Andrea",
    "wof:placetype":"locality",
    "wof:population":14
},
  "geometry": {"coordinates":[13.11373,43.40276],"type":"Point"}
}