{
  "type": "Feature",
  "properties": {
    "gn:admin1_code":"9",
    "gn:admin2_code":"CR",
    "gn:admin3_code":"19026.0",
    "gn:asciiname":"Cavallara",
    "gn:country_code":"IT",
    "gn:dem":58,
    "gn:feature_class":"P",
    "gn:feature_code":"PPL",
    "gn:name":"Cavallara",
    "gn:population":11,
    "gn:timezone":"Europe/Rome",
    "iso:country":"IT",
    "wof:name":"Cavallara",
    "wof:placetype":"locality",
    "wof:population":11
},
  "geometry": {"coordinates":[9.98961,45.2257],"type":"Point"}
}