{
  "type": "Feature",
  "properties": {
    "gn:admin1_code":"5",
    "gn:admin2_code":"PC",
    "gn:admin3_code":"33004.0",
    "gn:asciiname":"Case Camia",
    "gn:country_code":"IT",
    "gn:dem":412,
    "gn:feature_class":"P",
    "gn:feature_code":"PPL",
    "gn:name":"Case Camia",
    "gn:population":23,
    "gn:timezone":"Europe/Rome",
    "iso:country":"IT",
    "wof:name":"Case Camia",
    "wof:placetype":"locality",
    "wof:population":23
},
  "geometry": {"coordinates":[9.59269,44.75323],"type":"Point"}
}