{
  "type": "Feature",
  "properties": {
    "gn:admin1_code":"5",
    "gn:admin2_code":"MO",
    "gn:admin3_code":"36031.0",
    "gn:asciiname":"Casa Cagnarino",
    "gn:country_code":"IT",
    "gn:dem":1157,
    "gn:feature_class":"P",
    "gn:feature_code":"PPL",
    "gn:name":"Casa Cagnarino",
    "gn:population":17,
    "gn:timezone":"Europe/Rome",
    "iso:country":"IT",
    "wof:name":"Casa Cagnarino",
    "wof:placetype":"locality",
    "wof:population":17
},
  "geometry": {"coordinates":[10.57053,44.20702],"type":"Point"}
}