{
  "type": "Feature",
  "properties": {
    "gn:admin1_code":"1",
    "gn:admin2_code":"TE",
    "gn:admin3_code":"67044.0",
    "gn:asciiname":"Di Febo",
    "gn:country_code":"IT",
    "gn:dem":126,
    "gn:feature_class":"P",
    "gn:feature_code":"PPL",
    "gn:name":"Di Febo",
    "gn:population":29,
    "gn:timezone":"Europe/Rome",
    "iso:country":"IT",
    "wof:name":"Di Febo",
    "wof:placetype":"locality",
    "wof:population":29
},
  "geometry": {"coordinates":[13.88488,42.80141],"type":"Point"}
}