{
  "type": "Feature",
  "properties": {
    "gn:admin1_code":"20",
    "gn:admin2_code":"VI",
    "gn:admin3_code":"24106.0",
    "gn:asciiname":"Pettina",
    "gn:country_code":"IT",
    "gn:dem":1092,
    "gn:feature_class":"P",
    "gn:feature_code":"PPL",
    "gn:name":"Pettin\u00e0",
    "gn:population":35,
    "gn:timezone":"Europe/Rome",
    "iso:country":"IT",
    "name:und_x_variant":[
        "Pettin\u00e0"
    ],
    "wof:name":"Pettina",
    "wof:placetype":"locality",
    "wof:population":35
},
  "geometry": {"coordinates":[11.33694,45.85796],"type":"Point"}
}