{
  "type": "Feature",
  "properties": {
    "gn:admin1_code":"6.0",
    "gn:admin2_code":"TS",
    "gn:admin3_code":"32003.0",
    "gn:asciiname":"San Bartolomeo",
    "gn:country_code":"IT",
    "gn:dem":13,
    "gn:feature_class":"P",
    "gn:feature_code":"PPL",
    "gn:name":"San Bartolomeo",
    "gn:population":0,
    "gn:timezone":"Europe/Rome",
    "iso:country":"IT",
    "name:ceb_x_preferred":[
        "San Bartolomeo"
    ],
    "name:deu_x_preferred":[
        "San Bartolomeo"
    ],
    "name:epo_x_preferred":[
        "San Bartolomeo"
    ],
    "name:hun_x_preferred":[
        "San Bartolomeo"
    ],
    "name:ita_x_preferred":[
        "San Bartolomeo"
    ],
    "name:por_x_preferred":[
        "San Bartolomeo"
    ],
    "name:srp_x_preferred":[
        "San Bartolomeo"
    ],
    "name:swe_x_preferred":[
        "San Bartolomeo"
    ],
    "name:war_x_preferred":[
        "San Bartolomeo"
    ],
    "wof:name":"San Bartolomeo",
    "wof:placetype":"locality"
},
  "geometry": {"coordinates":[13.72284,45.60047],"type":"Point"}
}