{
  "type": "Feature",
  "properties": {
    "gn:admin1_code":"16",
    "gn:admin2_code":"LU",
    "gn:admin3_code":"46022.0",
    "gn:asciiname":"Vetrianello",
    "gn:country_code":"IT",
    "gn:dem":371,
    "gn:feature_class":"P",
    "gn:feature_code":"PPL",
    "gn:name":"Vetrianello",
    "gn:population":29,
    "gn:timezone":"Europe/Rome",
    "iso:country":"IT",
    "wof:name":"Vetrianello",
    "wof:placetype":"locality",
    "wof:population":29
},
  "geometry": {"coordinates":[10.43276,43.93855],"type":"Point"}
}