{
  "type": "Feature",
  "properties": {
    "gn:admin1_code":"20.0",
    "gn:admin2_code":"VE",
    "gn:admin3_code":"27029.0",
    "gn:asciiname":"Torresella",
    "gn:country_code":"IT",
    "gn:dem":3,
    "gn:elevation":"4.0",
    "gn:feature_class":"P",
    "gn:feature_code":"PPL",
    "gn:name":"Torresella",
    "gn:population":159,
    "gn:timezone":"Europe/Rome",
    "iso:country":"IT",
    "wof:name":"Torresella",
    "wof:placetype":"locality",
    "wof:population":159
},
  "geometry": {"coordinates":[12.89128,45.75439],"type":"Point"}
}