{
  "type": "Feature",
  "properties": {
    "gn:admin1_code":"4",
    "gn:admin2_code":"SA",
    "gn:admin3_code":"65106.0",
    "gn:asciiname":"Seude",
    "gn:country_code":"IT",
    "gn:dem":112,
    "gn:feature_class":"P",
    "gn:feature_code":"PPL",
    "gn:name":"Seude",
    "gn:population":35,
    "gn:timezone":"Europe/Rome",
    "iso:country":"IT",
    "wof:name":"Seude",
    "wof:placetype":"locality",
    "wof:population":35
},
  "geometry": {"coordinates":[15.07683,40.45533],"type":"Point"}
}