{
  "type": "Feature",
  "properties": {
    "iso:country":"IT",
    "qs_pg:aaroncc":"IT",
    "qs_pg:name":"Rocca",
    "qs_pg:name_adm0":"Italia",
    "qs_pg:name_adm1":"Emilia Romagna",
    "qs_pg:photos":1,
    "qs_pg:photos_1k":1,
    "qs_pg:photos_9k":1,
    "qs_pg:photos_9r":1,
    "qs_pg:photos_all":1,
    "qs_pg:photos_sr":1,
    "qs_pg:pop_sr":0,
    "qs_pg:qs_pg_placetype":"locality",
    "qs_pg:qs_pg_placetype_gp":"Town",
    "qs_pg:woe_adm0":23424853,
    "woe:adm0_id":23424853,
    "woe:name_adm0":"Italia",
    "woe:name_adm1":"Emilia Romagna",
    "woe:placetype":"Town",
    "wof:name":"Rocca",
    "wof:placetype":"locality"
},
  "geometry": {"coordinates":[9.518795,44.62435],"type":"Point"}
}