{
  "type": "Feature",
  "properties": {
    "gn:population":154,
    "iso:country":"IT",
    "name:bcl_x_preferred":[
        "Vergemoli"
    ],
    "name:bel_x_preferred":[
        "\u0412\u0435\u0440\u0434\u0436\u044d\u043c\u043e\u043b\u0456"
    ],
    "name:bul_x_preferred":[
        "\u0412\u0435\u0440\u0434\u0436\u0435\u043c\u043e\u043b\u0438"
    ],
    "name:deu_x_preferred":[
        "Vergemoli"
    ],
    "name:eng_x_preferred":[
        "Vergemoli"
    ],
    "name:epo_x_preferred":[
        "Vergemoli"
    ],
    "name:eus_x_preferred":[
        "Vergemoli"
    ],
    "name:fas_x_preferred":[
        "\u0648\u0631\u06af\u0645\u0644\u06cc"
    ],
    "name:fra_x_preferred":[
        "Vergemoli"
    ],
    "name:hbs_x_preferred":[
        "Vergemoli"
    ],
    "name:hun_x_preferred":[
        "Vergemoli"
    ],
    "name:hye_x_preferred":[
        "\u054e\u0565\u0580\u057b\u0565\u0574\u0578\u056c\u056b"
    ],
    "name:ita_x_preferred":[
        "Vergemoli"
    ],
    "name:jpn_x_preferred":[
        "\u30f4\u30a7\u30eb\u30b8\u30a7\u30fc\u30e2\u30ea"
    ],
    "name:kaz_x_preferred":[
        "\u0412\u0435\u0440\u0434\u0436\u0435\u043c\u043e\u043b\u0438"
    ],
    "name:kor_x_preferred":[
        "\ubca0\ub974\uc81c\ubab0\ub9ac"
    ],
    "name:lat_x_preferred":[
        "Virgemulis"
    ],
    "name:lmo_x_preferred":[
        "Vergemoli"
    ],
    "name:msa_x_preferred":[
        "Vergemoli"
    ],
    "name:nap_x_preferred":[
        "Vergemoli"
    ],
    "name:nld_x_preferred":[
        "Vergemoli"
    ],
    "name:nob_x_preferred":[
        "Vergemoli"
    ],
    "name:nor_x_preferred":[
        "Vergemoli"
    ],
    "name:pms_x_preferred":[
        "Vergemoli"
    ],
    "name:pol_x_preferred":[
        "Vergemoli"
    ],
    "name:por_x_preferred":[
        "Vergemoli"
    ],
    "name:ron_x_preferred":[
        "Vergemoli"
    ],
    "name:rus_x_preferred":[
        "\u0412\u0435\u0440\u0434\u0436\u0435\u043c\u043e\u043b\u0438"
    ],
    "name:scn_x_preferred":[
        "Vergemoli"
    ],
    "name:spa_x_preferred":[
        "Vergemoli"
    ],
    "name:srp_x_preferred":[
        "\u0412\u0435\u0440\u0452\u0435\u043c\u043e\u043b\u0438"
    ],
    "name:tgl_x_preferred":[
        "Vergemoli"
    ],
    "name:ukr_x_preferred":[
        "\u0412\u0435\u0440\u0434\u0436\u0435\u043c\u043e\u043b\u0456"
    ],
    "name:uzb_x_preferred":[
        "Vergemoli"
    ],
    "name:vie_x_preferred":[
        "Vergemoli"
    ],
    "name:vol_x_preferred":[
        "Vergemoli"
    ],
    "name:war_x_preferred":[
        "Vergemoli"
    ],
    "name:zho_x_preferred":[
        "\u97e6\u5c14\u6770\u83ab\u5229"
    ],
    "qs:a0":"Italia",
    "qs:a1":"*Lucca",
    "qs:a1r":"0Toscana",
    "qs:adm0":"Italia",
    "qs:la_lc":"*",
    "qs:level":"locality",
    "qs:loc":"Vergemoli",
    "qs:loc_alt":"Vergemoli",
    "qs:pop":0,
    "qs:type":"buffered point",
    "wd:wordcount":54,
    "wof:lang":[
        "ita"
    ],
    "wof:name":"Vergemoli",
    "wof:placetype":"locality",
    "wof:population":154
},
  "geometry": {"coordinates":[10.383139,44.05209],"type":"Point"}
}