{
  "type": "Feature",
  "properties": {
    "gn:admin1_code":"3.0",
    "gn:admin2_code":"RC",
    "gn:admin3_code":"80046.0",
    "gn:asciiname":"Tritanti",
    "gn:country_code":"IT",
    "gn:dem":266,
    "gn:elevation":"263.0",
    "gn:feature_class":"P",
    "gn:feature_code":"PPL",
    "gn:name":"Tritanti",
    "gn:population":519,
    "gn:timezone":"Europe/Rome",
    "iso:country":"IT",
    "wof:name":"Tritanti",
    "wof:placetype":"locality",
    "wof:population":519
},
  "geometry": {"coordinates":[16.1014,38.44872],"type":"Point"}
}