{
  "type": "Feature",
  "properties": {
    "gn:admin1_code":"1",
    "gn:admin2_code":"PE",
    "gn:admin3_code":"68025.0",
    "gn:asciiname":"Valle Molino",
    "gn:country_code":"IT",
    "gn:dem":57,
    "gn:feature_class":"P",
    "gn:feature_code":"PPL",
    "gn:name":"Valle Molino",
    "gn:population":223,
    "gn:timezone":"Europe/Rome",
    "iso:country":"IT",
    "wof:name":"Valle Molino",
    "wof:placetype":"locality",
    "wof:population":223
},
  "geometry": {"coordinates":[14.0809,42.45603],"type":"Point"}
}