{
  "type": "Feature",
  "properties": {
    "gn:admin1_code":"7",
    "gn:admin2_code":"LT",
    "gn:admin3_code":"59011.0",
    "gn:asciiname":"Litoranea",
    "gn:country_code":"IT",
    "gn:dem":4,
    "gn:feature_class":"P",
    "gn:feature_code":"PPL",
    "gn:name":"Litoranea",
    "gn:population":78,
    "gn:timezone":"Europe/Rome",
    "iso:country":"IT",
    "wof:name":"Litoranea",
    "wof:placetype":"locality",
    "wof:population":78
},
  "geometry": {"coordinates":[12.87135,41.42412],"type":"Point"}
}