{
  "type": "Feature",
  "properties": {
    "gn:admin1_code":"12",
    "gn:admin2_code":"BI",
    "gn:admin3_code":"96002.0",
    "gn:asciiname":"Cerruti",
    "gn:country_code":"IT",
    "gn:dem":645,
    "gn:feature_class":"P",
    "gn:feature_code":"PPL",
    "gn:name":"Cerruti",
    "gn:population":45,
    "gn:timezone":"Europe/Rome",
    "iso:country":"IT",
    "wof:name":"Cerruti",
    "wof:placetype":"locality",
    "wof:population":45
},
  "geometry": {"coordinates":[8.06913,45.61805],"type":"Point"}
}