{
  "type": "Feature",
  "properties": {
    "gn:admin1_code":"9.0",
    "gn:admin2_code":"PV",
    "gn:admin3_code":"18159.0",
    "gn:asciiname":"Cascina Carpana",
    "gn:country_code":"IT",
    "gn:dem":88,
    "gn:feature_class":"P",
    "gn:feature_code":"PPL",
    "gn:name":"Cascina Carpana",
    "gn:population":58,
    "gn:timezone":"Europe/Rome",
    "iso:country":"IT",
    "wof:name":"Cascina Carpana",
    "wof:placetype":"locality",
    "wof:population":58
},
  "geometry": {"coordinates":[9.07127,45.2362],"type":"Point"}
}