{
  "type": "Feature",
  "properties": {
    "gn:admin1_code":"4",
    "gn:admin2_code":"CE",
    "gn:admin3_code":"61052.0",
    "gn:asciiname":"Pineta Nuova",
    "gn:country_code":"IT",
    "gn:dem":0,
    "gn:feature_class":"P",
    "gn:feature_code":"PPL",
    "gn:name":"Pineta Nuova",
    "gn:population":93,
    "gn:timezone":"Europe/Rome",
    "iso:country":"IT",
    "wof:name":"Pineta Nuova",
    "wof:placetype":"locality",
    "wof:population":93
},
  "geometry": {"coordinates":[13.92594,41.06824],"type":"Point"}
}