{
  "type": "Feature",
  "properties": {
    "gn:admin1_code":"20.0",
    "gn:admin2_code":"VE",
    "gn:admin3_code":"27006.0",
    "gn:asciiname":"Buoro",
    "gn:country_code":"IT",
    "gn:dem":-3,
    "gn:feature_class":"P",
    "gn:feature_code":"PPL",
    "gn:name":"Buoro",
    "gn:population":0,
    "gn:timezone":"Europe/Rome",
    "iso:country":"IT",
    "wof:name":"Buoro",
    "wof:placetype":"locality"
},
  "geometry": {"coordinates":[12.13972,45.13611],"type":"Point"}
}