{
  "type": "Feature",
  "properties": {
    "gn:admin1_code":"10",
    "gn:admin2_code":"MC",
    "gn:admin3_code":"43038.0",
    "gn:asciiname":"Capriglia",
    "gn:country_code":"IT",
    "gn:dem":578,
    "gn:feature_class":"P",
    "gn:feature_code":"PPL",
    "gn:name":"Capriglia",
    "gn:population":15,
    "gn:timezone":"Europe/Rome",
    "iso:country":"IT",
    "wof:name":"Capriglia",
    "wof:placetype":"locality",
    "wof:population":15
},
  "geometry": {"coordinates":[13.04685,43.01312],"type":"Point"}
}