{
  "type": "Feature",
  "properties": {
    "gn:admin1_code":"18",
    "gn:admin2_code":"TR",
    "gn:admin3_code":"55032.0",
    "gn:asciiname":"Perticara",
    "gn:country_code":"IT",
    "gn:dem":313,
    "gn:feature_class":"P",
    "gn:feature_code":"PPL",
    "gn:name":"Perticara",
    "gn:population":109,
    "gn:timezone":"Europe/Rome",
    "iso:country":"IT",
    "wof:name":"Perticara",
    "wof:placetype":"locality",
    "wof:population":109
},
  "geometry": {"coordinates":[12.65622,42.53034],"type":"Point"}
}