{
  "type": "Feature",
  "properties": {
    "gn:admin1_code":"5",
    "gn:admin2_code":"FC",
    "gn:admin3_code":"40007.0",
    "gn:asciiname":"Celletta",
    "gn:country_code":"IT",
    "gn:dem":61,
    "gn:feature_class":"P",
    "gn:feature_code":"PPL",
    "gn:name":"Celletta",
    "gn:population":94,
    "gn:timezone":"Europe/Rome",
    "iso:country":"IT",
    "wof:name":"Celletta",
    "wof:placetype":"locality",
    "wof:population":94
},
  "geometry": {"coordinates":[12.18741,44.12055],"type":"Point"}
}