{
  "type": "Feature",
  "properties": {
    "gn:admin1_code":"5",
    "gn:admin2_code":"FE",
    "gn:admin3_code":"38010.0",
    "gn:asciiname":"Bonaglina",
    "gn:country_code":"IT",
    "gn:dem":-4,
    "gn:feature_class":"P",
    "gn:feature_code":"PPL",
    "gn:name":"Bonaglina",
    "gn:population":24,
    "gn:timezone":"Europe/Rome",
    "iso:country":"IT",
    "wof:name":"Bonaglina",
    "wof:placetype":"locality",
    "wof:population":24
},
  "geometry": {"coordinates":[11.98986,44.90864000000001],"type":"Point"}
}