{
  "type": "Feature",
  "properties": {
    "gn:admin1_code":"4.0",
    "gn:admin2_code":"SA",
    "gn:admin3_code":"65146.0",
    "gn:asciiname":"San Marco",
    "gn:country_code":"IT",
    "gn:dem":518,
    "gn:feature_class":"P",
    "gn:feature_code":"PPL",
    "gn:name":"San Marco",
    "gn:population":411,
    "gn:timezone":"Europe/Rome",
    "iso:country":"IT",
    "wof:name":"San Marco",
    "wof:placetype":"locality",
    "wof:population":411
},
  "geometry": {"coordinates":[15.50335,40.38432],"type":"Point"}
}