{
  "type": "Feature",
  "properties": {
    "gn:admin1_code":"1.0",
    "gn:admin2_code":"TE",
    "gn:admin3_code":"67017.0",
    "gn:asciiname":"Bivio Risteccio",
    "gn:country_code":"IT",
    "gn:dem":444,
    "gn:elevation":"444.0",
    "gn:feature_class":"P",
    "gn:feature_code":"PPL",
    "gn:name":"Bivio Risteccio",
    "gn:population":55,
    "gn:timezone":"Europe/Rome",
    "iso:country":"IT",
    "wof:name":"Bivio Risteccio",
    "wof:placetype":"locality",
    "wof:population":55
},
  "geometry": {"coordinates":[13.65335,42.76667],"type":"Point"}
}