{
  "type": "Feature",
  "properties": {
    "gn:admin1_code":"4",
    "gn:admin2_code":"AV",
    "gn:admin3_code":"64084.0",
    "gn:asciiname":"Madonna delle Grazie",
    "gn:country_code":"IT",
    "gn:dem":346,
    "gn:feature_class":"P",
    "gn:feature_code":"PPL",
    "gn:name":"Madonna delle Grazie",
    "gn:population":273,
    "gn:timezone":"Europe/Rome",
    "iso:country":"IT",
    "wof:name":"Madonna delle Grazie",
    "wof:placetype":"locality",
    "wof:population":273
},
  "geometry": {"coordinates":[14.84894,40.87779000000001],"type":"Point"}
}