{
  "type": "Feature",
  "properties": {
    "gn:admin1_code":"16",
    "gn:admin2_code":"AR",
    "gn:admin3_code":"51021.0",
    "gn:asciiname":"Scerpella-Sentenze",
    "gn:country_code":"IT",
    "gn:dem":270,
    "gn:feature_class":"P",
    "gn:feature_code":"PPL",
    "gn:name":"Scerpella-Sentenze",
    "gn:population":46,
    "gn:timezone":"Europe/Rome",
    "iso:country":"IT",
    "wof:name":"Scerpella-Sentenze",
    "wof:placetype":"locality",
    "wof:population":46
},
  "geometry": {"coordinates":[11.76239,43.27906],"type":"Point"}
}