{
  "type": "Feature",
  "properties": {
    "gn:admin1_code":"10.0",
    "gn:admin2_code":"AP",
    "gn:admin3_code":"44038.0",
    "gn:asciiname":"Piano",
    "gn:country_code":"IT",
    "gn:dem":715,
    "gn:elevation":"717.0",
    "gn:feature_class":"P",
    "gn:feature_code":"PPL",
    "gn:name":"Piano",
    "gn:population":23,
    "gn:timezone":"Europe/Rome",
    "iso:country":"IT",
    "wof:name":"Piano",
    "wof:placetype":"locality",
    "wof:population":23
},
  "geometry": {"coordinates":[13.33903,42.85486],"type":"Point"}
}