{
  "type": "Feature",
  "properties": {
    "gn:admin1_code":"13",
    "gn:admin2_code":"LE",
    "gn:admin3_code":"75048.0",
    "gn:asciiname":"Via Carducci",
    "gn:country_code":"IT",
    "gn:dem":34,
    "gn:feature_class":"P",
    "gn:feature_code":"PPL",
    "gn:name":"Via Carducci",
    "gn:population":25,
    "gn:timezone":"Europe/Rome",
    "iso:country":"IT",
    "wof:name":"Via Carducci",
    "wof:placetype":"locality",
    "wof:population":25
},
  "geometry": {"coordinates":[18.08179,40.32802],"type":"Point"}
}