{
  "type": "Feature",
  "properties": {
    "gn:admin1_code":"15.0",
    "gn:admin2_code":"ME",
    "gn:admin3_code":"83088.0",
    "gn:asciiname":"Contura",
    "gn:country_code":"IT",
    "gn:dem":566,
    "gn:elevation":"588.0",
    "gn:feature_class":"P",
    "gn:feature_code":"PPL",
    "gn:name":"Contura",
    "gn:population":169,
    "gn:timezone":"Europe/Rome",
    "iso:country":"IT",
    "wof:name":"Contura",
    "wof:placetype":"locality",
    "wof:population":169
},
  "geometry": {"coordinates":[14.89726,38.10447],"type":"Point"}
}