{
  "type": "Feature",
  "properties": {
    "gn:admin1_code":"10",
    "gn:admin2_code":"AN",
    "gn:admin3_code":"42050.0",
    "gn:asciiname":"Rocchetta",
    "gn:country_code":"IT",
    "gn:dem":141,
    "gn:feature_class":"P",
    "gn:feature_code":"PPL",
    "gn:name":"Rocchetta",
    "gn:population":30,
    "gn:timezone":"Europe/Rome",
    "iso:country":"IT",
    "name:ceb_x_preferred":[
        "Rocchetta"
    ],
    "name:deu_x_preferred":[
        "Rocchetta"
    ],
    "name:fra_x_preferred":[
        "Rocchetta"
    ],
    "name:ita_x_preferred":[
        "Rocchetta"
    ],
    "name:por_x_preferred":[
        "Rocchetta"
    ],
    "name:srp_x_preferred":[
        "Roketa"
    ],
    "name:swe_x_preferred":[
        "Rocchetta"
    ],
    "wof:name":"Rocchetta",
    "wof:placetype":"locality",
    "wof:population":30
},
  "geometry": {"coordinates":[13.11993,43.67466],"type":"Point"}
}