{
  "type": "Feature",
  "properties": {
    "gn:admin1_code":"20.0",
    "gn:admin2_code":"BL",
    "gn:admin3_code":"25060.0",
    "gn:asciiname":"Valdenogher",
    "gn:country_code":"IT",
    "gn:dem":854,
    "gn:elevation":"852.0",
    "gn:feature_class":"P",
    "gn:feature_code":"PPL",
    "gn:name":"Valdenogher",
    "gn:population":145,
    "gn:timezone":"Europe/Rome",
    "iso:country":"IT",
    "wof:name":"Valdenogher",
    "wof:placetype":"locality",
    "wof:population":145
},
  "geometry": {"coordinates":[12.38803,46.12328],"type":"Point"}
}