{
  "type": "Feature",
  "properties": {
    "gn:admin1_code":"1",
    "gn:admin2_code":"PE",
    "gn:admin3_code":"68017.0",
    "gn:asciiname":"Frattali l'Incotta",
    "gn:country_code":"IT",
    "gn:dem":236,
    "gn:feature_class":"P",
    "gn:feature_code":"PPL",
    "gn:name":"Frattali l'Incotta",
    "gn:population":15,
    "gn:timezone":"Europe/Rome",
    "iso:country":"IT",
    "wof:name":"Frattali l'Incotta",
    "wof:placetype":"locality",
    "wof:population":15
},
  "geometry": {"coordinates":[13.9499,42.30997],"type":"Point"}
}