{
  "type": "Feature",
  "properties": {
    "gn:admin1_code":"5",
    "gn:admin2_code":"BO",
    "gn:admin3_code":"37001.0",
    "gn:asciiname":"Ponte Asse",
    "gn:country_code":"IT",
    "gn:dem":43,
    "gn:feature_class":"P",
    "gn:feature_code":"PPL",
    "gn:name":"Ponte Asse",
    "gn:population":19,
    "gn:timezone":"Europe/Rome",
    "iso:country":"IT",
    "wof:name":"Ponte Asse",
    "wof:placetype":"locality",
    "wof:population":19
},
  "geometry": {"coordinates":[11.17978,44.53583],"type":"Point"}
}