{
  "type": "Feature",
  "properties": {
    "gn:admin1_code":"16",
    "gn:admin2_code":"PT",
    "gn:admin3_code":"47016.0",
    "gn:asciiname":"Volta",
    "gn:country_code":"IT",
    "gn:dem":16,
    "gn:feature_class":"P",
    "gn:feature_code":"PPL",
    "gn:name":"Volta",
    "gn:population":26,
    "gn:timezone":"Europe/Rome",
    "iso:country":"IT",
    "wof:name":"Volta",
    "wof:placetype":"locality",
    "wof:population":26
},
  "geometry": {"coordinates":[10.76018,43.83803],"type":"Point"}
}