{
  "type": "Feature",
  "properties": {
    "gn:admin1_code":"16",
    "gn:admin2_code":"PT",
    "gn:admin3_code":"47016.0",
    "gn:asciiname":"Volta",
    "gn:country_code":"IT",
    "gn:dem":16,
    "gn:feature_class":"P",
    "gn:feature_code":"PPL",
    "gn:name":"Volta",
    "gn:population":26,
    "gn:timezone":"Europe/Rome",
    "iso:country":"IT",
    "name:bel_x_preferred":[
        "\u0412\u043e\u043b\u044c\u0442\u0430"
    ],
    "name:bul_x_preferred":[
        "\u0412\u043e\u043b\u0442\u0430"
    ],
    "name:cat_x_preferred":[
        "Volta"
    ],
    "name:ceb_x_preferred":[
        "Volta"
    ],
    "name:ces_x_preferred":[
        "Volta"
    ],
    "name:dan_x_preferred":[
        "Volta"
    ],
    "name:deu_x_preferred":[
        "Volta"
    ],
    "name:est_x_preferred":[
        "Volta"
    ],
    "name:eus_x_preferred":[
        "Volta"
    ],
    "name:fas_x_preferred":[
        "\u0648\u0644\u062a\u0627"
    ],
    "name:fin_x_preferred":[
        "Volta"
    ],
    "name:fra_x_preferred":[
        "Volta"
    ],
    "name:heb_x_preferred":[
        "\u05d5\u05d5\u05dc\u05d8\u05d4"
    ],
    "name:hrv_x_preferred":[
        "Volta"
    ],
    "name:ita_x_preferred":[
        "Volta"
    ],
    "name:jpn_x_preferred":[
        "\u30dc\u30eb\u30bf"
    ],
    "name:kat_x_preferred":[
        "\u10d5\u10dd\u10da\u10e2\u10d0"
    ],
    "name:lat_x_preferred":[
        "Volta"
    ],
    "name:nld_x_preferred":[
        "Volta"
    ],
    "name:nno_x_preferred":[
        "Volta"
    ],
    "name:nor_x_preferred":[
        "Volta"
    ],
    "name:pol_x_preferred":[
        "Volta"
    ],
    "name:por_x_preferred":[
        "Volta"
    ],
    "name:ron_x_preferred":[
        "Volta"
    ],
    "name:rus_x_preferred":[
        "\u0412\u043e\u043b\u044c\u0442\u0430"
    ],
    "name:slv_x_preferred":[
        "Volta"
    ],
    "name:spa_x_preferred":[
        "Volta"
    ],
    "name:srp_x_preferred":[
        "\u0412\u043e\u043b\u0442\u0430"
    ],
    "name:swe_x_preferred":[
        "Volta"
    ],
    "name:tgl_x_preferred":[
        "Volta"
    ],
    "name:ukr_x_preferred":[
        "\u0412\u043e\u043b\u044c\u0442\u0430"
    ],
    "name:uzb_x_preferred":[
        "Volta"
    ],
    "wof:name":"Volta",
    "wof:placetype":"locality",
    "wof:population":26
},
  "geometry": {"coordinates":[10.76018,43.83803],"type":"Point"}
}