{
  "type": "Feature",
  "properties": {
    "gn:country":"IT",
    "gn:fcode":"PPL",
    "gn:population":0,
    "iso:country":"IT",
    "name:eng_x_preferred":[
        "Equi Terme"
    ],
    "name:fra_x_preferred":[
        "Equi Terme"
    ],
    "name:ita_x_preferred":[
        "Equi Terme"
    ],
    "name:nld_x_preferred":[
        "Equi Terme"
    ],
    "name:srp_x_preferred":[
        "Equi Terme"
    ],
    "name:und_x_variant":[
        "Equi"
    ],
    "qs_pg:aaroncc":"IT",
    "qs_pg:gn_country":"IT",
    "qs_pg:gn_fcode":"PPL",
    "qs_pg:gn_pop":0,
    "qs_pg:name":"Equi Terme",
    "qs_pg:name_adm0":"Italia",
    "qs_pg:name_adm1":"Toscana",
    "qs_pg:photos":59,
    "qs_pg:photos_1k":12,
    "qs_pg:photos_9k":1,
    "qs_pg:photos_9r":2,
    "qs_pg:photos_all":59,
    "qs_pg:photos_sr":2,
    "qs_pg:pop_sr":0,
    "qs_pg:qs_pg_placetype":"locality",
    "qs_pg:qs_pg_placetype_gp":"Town",
    "qs_pg:woe_adm0":23424853,
    "woe:adm0_id":23424853,
    "woe:name_adm0":"Italia",
    "woe:name_adm1":"Toscana",
    "woe:placetype":"Town",
    "wof:name":"Equi Terme",
    "wof:placetype":"locality",
    "wof:population":67
},
  "geometry": {"coordinates":[10.15489,44.16995],"type":"Point"}
}