{
  "type": "Feature",
  "properties": {
    "gn:admin1_code":"16",
    "gn:admin2_code":"FI",
    "gn:admin3_code":"48049.0",
    "gn:asciiname":"Ricavo",
    "gn:country_code":"IT",
    "gn:dem":267,
    "gn:feature_class":"P",
    "gn:feature_code":"PPLL",
    "gn:name":"Ricavo",
    "gn:population":7,
    "gn:timezone":"Europe/Rome",
    "iso:country":"IT",
    "wof:name":"Ricavo",
    "wof:placetype":"locality",
    "wof:population":7
},
  "geometry": {"coordinates":[11.50929,43.92699],"type":"Point"}
}