{
  "type": "Feature",
  "properties": {
    "gn:admin1_code":"16",
    "gn:admin2_code":"AR",
    "gn:admin3_code":"51017.0",
    "gn:asciiname":"Gabbiano",
    "gn:country_code":"IT",
    "gn:dem":322,
    "gn:feature_class":"P",
    "gn:feature_code":"PPL",
    "gn:name":"Gabbiano",
    "gn:population":15,
    "gn:timezone":"Europe/Rome",
    "iso:country":"IT",
    "name:ita_x_preferred":[
        "Gabbiano"
    ],
    "name:srp_x_preferred":[
        "Gabbiano"
    ],
    "wof:name":"Gabbiano",
    "wof:placetype":"locality",
    "wof:population":15
},
  "geometry": {"coordinates":[11.91346,43.17718],"type":"Point"}
}