{
  "type": "Feature",
  "properties": {
    "gn:admin1_code":"2.0",
    "gn:admin2_code":"PZ",
    "gn:admin3_code":"76078.0",
    "gn:asciiname":"Mancini",
    "gn:cc2":"IT",
    "gn:country_code":"IT",
    "gn:dem":928,
    "gn:elevation":"932.0",
    "gn:feature_class":"P",
    "gn:feature_code":"PPL",
    "gn:name":"Mancini",
    "gn:population":40,
    "gn:timezone":"Europe/Rome",
    "iso:country":"IT",
    "name:und_x_variant":[
        "Mancine"
    ],
    "wof:name":"Mancini",
    "wof:placetype":"locality",
    "wof:population":40
},
  "geometry": {"coordinates":[16.17659,40.02506],"type":"Point"}
}