{
  "type": "Feature",
  "properties": {
    "gn:admin1_code":"3.0",
    "gn:admin2_code":"CS",
    "gn:admin3_code":"78012.0",
    "gn:asciiname":"Torre di Ponte Soprano",
    "gn:cc2":"IT",
    "gn:country_code":"IT",
    "gn:dem":1282,
    "gn:feature_class":"P",
    "gn:feature_code":"PPL",
    "gn:name":"Torre di Ponte Soprano",
    "gn:population":0,
    "gn:timezone":"Europe/Rome",
    "iso:country":"IT",
    "name:und_x_variant":[
        "Torre di Ponte Zurle",
        "Torre di Ponte Soprano"
    ],
    "wof:name":"Torre di Ponte Soprano",
    "wof:placetype":"locality"
},
  "geometry": {"coordinates":[16.58333,39.18333],"type":"Point"}
}