{
  "type": "Feature",
  "properties": {
    "gn:admin1_code":"7",
    "gn:admin2_code":"FR",
    "gn:admin3_code":"60009.0",
    "gn:asciiname":"Risari",
    "gn:country_code":"IT",
    "gn:dem":158,
    "gn:feature_class":"P",
    "gn:feature_code":"PPL",
    "gn:name":"Risari",
    "gn:population":53,
    "gn:timezone":"Europe/Rome",
    "iso:country":"IT",
    "wof:name":"Risari",
    "wof:placetype":"locality",
    "wof:population":53
},
  "geometry": {"coordinates":[13.37755,41.57038],"type":"Point"}
}