{
  "type": "Feature",
  "properties": {
    "gn:country":"IT",
    "iso:country":"IT",
    "qs_pg:aaroncc":"IT",
    "qs_pg:gn_country":"IT",
    "qs_pg:name":"Saturo",
    "qs_pg:name_adm0":"Italia",
    "qs_pg:name_adm1":"Puglia",
    "qs_pg:photos":74,
    "qs_pg:photos_1k":15,
    "qs_pg:photos_9k":1,
    "qs_pg:photos_9r":2,
    "qs_pg:photos_all":74,
    "qs_pg:photos_sr":2,
    "qs_pg:pop_sr":0,
    "qs_pg:qs_pg_placetype":"locality",
    "qs_pg:qs_pg_placetype_gp":"Town",
    "qs_pg:woe_adm0":23424853,
    "woe:adm0_id":23424853,
    "woe:name_adm0":"Italia",
    "woe:name_adm1":"Puglia",
    "woe:placetype":"Town",
    "wof:name":"Saturo",
    "wof:placetype":"locality"
},
  "geometry": {"coordinates":[17.304915,40.374415],"type":"Point"}
}