{
  "type": "Feature",
  "properties": {
    "gn:admin1_code":"16",
    "gn:admin2_code":"MS",
    "gn:admin3_code":"45005.0",
    "gn:asciiname":"Crespiano",
    "gn:country_code":"IT",
    "gn:dem":355,
    "gn:feature_class":"P",
    "gn:feature_code":"PPL",
    "gn:name":"Crespiano",
    "gn:population":113,
    "gn:timezone":"Europe/Rome",
    "iso:country":"IT",
    "wof:name":"Crespiano",
    "wof:placetype":"locality",
    "wof:population":113
},
  "geometry": {"coordinates":[10.09772,44.28803],"type":"Point"}
}