{
  "type": "Feature",
  "properties": {
    "gn:admin1_code":"7",
    "gn:admin2_code":"LT",
    "gn:admin3_code":"59015.0",
    "gn:asciiname":"Col del Fico",
    "gn:country_code":"IT",
    "gn:dem":19,
    "gn:feature_class":"P",
    "gn:feature_code":"PPL",
    "gn:name":"Col del Fico",
    "gn:population":90,
    "gn:timezone":"Europe/Rome",
    "iso:country":"IT",
    "wof:name":"Col del Fico",
    "wof:placetype":"locality",
    "wof:population":90
},
  "geometry": {"coordinates":[13.31616,41.34319],"type":"Point"}
}