{
  "type": "Feature",
  "properties": {
    "gn:country":"IT",
    "gn:fcode":"PPLA3",
    "gn:population":350,
    "iso:country":"IT",
    "name:bel_x_preferred":[
        "\u0426\u0443\u043a\u043b\u0430"
    ],
    "name:cat_x_preferred":[
        "Zuclo"
    ],
    "name:ceb_x_preferred":[
        "Zuclo"
    ],
    "name:deu_x_preferred":[
        "Zuclo"
    ],
    "name:eng_x_preferred":[
        "Zuclo"
    ],
    "name:epo_x_preferred":[
        "Zuclo"
    ],
    "name:eus_x_preferred":[
        "Zuclo"
    ],
    "name:fas_x_preferred":[
        "\u062a\u0632\u0648\u06a9\u0644\u0648"
    ],
    "name:fra_x_preferred":[
        "Zuclo"
    ],
    "name:hun_x_preferred":[
        "Zuclo"
    ],
    "name:hye_x_preferred":[
        "\u0541\u0578\u0582\u056f\u056c\u0578"
    ],
    "name:ind_x_preferred":[
        "Zuclo"
    ],
    "name:ita_x_preferred":[
        "Zuclo"
    ],
    "name:jpn_x_preferred":[
        "\u30ba\u30af\u30ed"
    ],
    "name:kaz_x_preferred":[
        "\u0426\u0443\u043a\u043b\u043e"
    ],
    "name:lat_x_preferred":[
        "Zuclum"
    ],
    "name:lmo_x_preferred":[
        "Zucol"
    ],
    "name:msa_x_preferred":[
        "Zuclo"
    ],
    "name:nap_x_preferred":[
        "Zuclo"
    ],
    "name:nld_x_preferred":[
        "Zuclo"
    ],
    "name:pms_x_preferred":[
        "Zuclo"
    ],
    "name:pol_x_preferred":[
        "Zuclo"
    ],
    "name:por_x_preferred":[
        "Zuclo"
    ],
    "name:ron_x_preferred":[
        "Zuclo"
    ],
    "name:rus_x_preferred":[
        "\u0426\u0443\u043a\u043b\u043e"
    ],
    "name:scn_x_preferred":[
        "Zuclo"
    ],
    "name:spa_x_preferred":[
        "Zuclo"
    ],
    "name:srp_x_preferred":[
        "Zuclo"
    ],
    "name:tgl_x_preferred":[
        "Zuclo"
    ],
    "name:ukr_x_preferred":[
        "\u0426\u0443\u043a\u043b\u043e"
    ],
    "name:uzb_x_preferred":[
        "Zuclo"
    ],
    "name:vie_x_preferred":[
        "Zuclo"
    ],
    "name:vol_x_preferred":[
        "Zuclo"
    ],
    "name:war_x_preferred":[
        "Zuclo"
    ],
    "name:zho_x_preferred":[
        "\u7956\u514b\u6d1b"
    ],
    "qs_pg:aaroncc":"IT",
    "qs_pg:gn_country":"IT",
    "qs_pg:gn_fcode":"PPLA3",
    "qs_pg:gn_pop":350,
    "qs_pg:name":"Zuclo",
    "qs_pg:name_adm0":"Italia",
    "qs_pg:name_adm1":"Trentino-Alto Adige",
    "qs_pg:photos_9r":0,
    "qs_pg:photos_sr":0,
    "qs_pg:pop_sr":2,
    "qs_pg:qs_pg_placetype":"locality",
    "qs_pg:qs_pg_placetype_gp":"Town",
    "qs_pg:woe_adm0":23424853,
    "woe:adm0_id":23424853,
    "woe:name_adm0":"Italia",
    "woe:name_adm1":"Trentino-Alto Adige",
    "woe:placetype":"Town",
    "wof:name":"Zuclo",
    "wof:placetype":"locality",
    "wof:population":326
},
  "geometry": {"coordinates":[10.75107,46.0343],"type":"Point"}
}