{
  "type": "Feature",
  "properties": {
    "gn:admin1_code":"12",
    "gn:admin2_code":"CN",
    "gn:admin3_code":"4116.0",
    "gn:asciiname":"Cascinetta",
    "gn:country_code":"IT",
    "gn:dem":391,
    "gn:feature_class":"P",
    "gn:feature_code":"PPL",
    "gn:name":"Cascinetta",
    "gn:population":14,
    "gn:timezone":"Europe/Rome",
    "iso:country":"IT",
    "wof:name":"Cascinetta",
    "wof:placetype":"locality",
    "wof:population":14
},
  "geometry": {"coordinates":[7.49403,44.61297],"type":"Point"}
}