{
  "type": "Feature",
  "properties": {
    "gn:admin1_code":"6.0",
    "gn:admin2_code":"PN",
    "gn:admin3_code":"93051.0",
    "gn:asciiname":"S.S. N.13 Pontebbana",
    "gn:country_code":"IT",
    "gn:dem":33,
    "gn:feature_class":"P",
    "gn:feature_code":"PPLL",
    "gn:name":"S.S. N.13 Pontebbana",
    "gn:population":0,
    "gn:timezone":"Europe/Rome",
    "iso:country":"IT",
    "wof:name":"S.S. N.13 Pontebbana",
    "wof:placetype":"locality"
},
  "geometry": {"coordinates":[12.80215,45.95327],"type":"Point"}
}