{
  "type": "Feature",
  "properties": {
    "gn:admin1_code":"8.0",
    "gn:admin2_code":"GE",
    "gn:admin3_code":"10021.0",
    "gn:asciiname":"Moranego",
    "gn:country_code":"IT",
    "gn:dem":593,
    "gn:elevation":"588.0",
    "gn:feature_class":"P",
    "gn:feature_code":"PPL",
    "gn:name":"Moranego",
    "gn:population":184,
    "gn:timezone":"Europe/Rome",
    "iso:country":"IT",
    "wof:name":"Moranego",
    "wof:placetype":"locality",
    "wof:population":184
},
  "geometry": {"coordinates":[9.10307,44.4775],"type":"Point"}
}