{
  "type": "Feature",
  "properties": {
    "gn:admin1_code":"9",
    "gn:admin2_code":"BG",
    "gn:admin3_code":"16044.0",
    "gn:asciiname":"Cascina Ribolla",
    "gn:country_code":"IT",
    "gn:dem":116,
    "gn:feature_class":"P",
    "gn:feature_code":"PPL",
    "gn:name":"Cascina Ribolla",
    "gn:population":26,
    "gn:timezone":"Europe/Rome",
    "iso:country":"IT",
    "wof:name":"Cascina Ribolla",
    "wof:placetype":"locality",
    "wof:population":26
},
  "geometry": {"coordinates":[9.84792,45.49441],"type":"Point"}
}