{
  "type": "Feature",
  "properties": {
    "gn:admin1_code":"20",
    "gn:admin2_code":"VI",
    "gn:admin3_code":"24097.0",
    "gn:asciiname":"Duomo",
    "gn:country_code":"IT",
    "gn:dem":102,
    "gn:feature_class":"P",
    "gn:feature_code":"PPL",
    "gn:name":"Duomo",
    "gn:population":25,
    "gn:timezone":"Europe/Rome",
    "iso:country":"IT",
    "wof:name":"Duomo",
    "wof:placetype":"locality",
    "wof:population":25
},
  "geometry": {"coordinates":[11.54795,45.69101],"type":"Point"}
}