{
  "type": "Feature",
  "properties": {
    "gn:admin1_code":"20",
    "gn:admin2_code":"VI",
    "gn:admin3_code":"24097.0",
    "gn:asciiname":"Duomo",
    "gn:country_code":"IT",
    "gn:dem":102,
    "gn:feature_class":"P",
    "gn:feature_code":"PPL",
    "gn:name":"Duomo",
    "gn:population":25,
    "gn:timezone":"Europe/Rome",
    "iso:country":"IT",
    "name:cat_x_preferred":[
        "Duomo"
    ],
    "name:deu_x_preferred":[
        "Dom"
    ],
    "name:epo_x_preferred":[
        "Duomo"
    ],
    "name:eus_x_preferred":[
        "Duomo"
    ],
    "name:fra_x_preferred":[
        "D\u00f4me"
    ],
    "name:fur_x_preferred":[
        "Domo"
    ],
    "name:ita_x_preferred":[
        "Duomo"
    ],
    "name:jpn_x_preferred":[
        "\u30c9\u30a5\u30aa\u30fc\u30e2"
    ],
    "name:kor_x_preferred":[
        "\ub450\uc624\ubaa8"
    ],
    "name:nds_x_preferred":[
        "Doom"
    ],
    "name:pol_x_preferred":[
        "Tum"
    ],
    "name:rus_x_preferred":[
        "\u0414\u0443\u043e\u043c\u043e"
    ],
    "name:spa_x_preferred":[
        "Duomo"
    ],
    "wof:name":"Duomo",
    "wof:placetype":"locality",
    "wof:population":25
},
  "geometry": {"coordinates":[11.54795,45.69101],"type":"Point"}
}