{
  "type": "Feature",
  "properties": {
    "iso:country":"IT",
    "name:bul_x_preferred":[
        "\u0421\u0430\u043c\u0431\u0443\u0433\u0445\u0435"
    ],
    "name:dut_x_preferred":[
        "Sambugh\u00e8"
    ],
    "name:eng_x_preferred":[
        "Sambugh\u00e8"
    ],
    "name:fre_x_preferred":[
        "Sambugh\u00e8"
    ],
    "name:hun_x_preferred":[
        "Sambugh\u00e8"
    ],
    "name:ita_x_preferred":[
        "Sambugh\u00e8"
    ],
    "name:srp_x_preferred":[
        "Sambughe"
    ],
    "name:vec_x_preferred":[
        "Sambugh\u00e8"
    ],
    "qs:a0":"Italia",
    "qs:a1":"*Treviso",
    "qs:a1r":"0Veneto",
    "qs:adm0":"Italia",
    "qs:la_lc":"*",
    "qs:level":"locality",
    "qs:loc":"Sambughe",
    "qs:loc_alt":"Sambughe",
    "qs:pop":0,
    "qs:type":"buffered point",
    "wof:name":"Sambughe",
    "wof:placetype":"locality"
},
  "geometry": {"coordinates":[12.215211,45.587791],"type":"Point"}
}