{
  "type": "Feature",
  "properties": {
    "gn:admin1_code":"20",
    "gn:admin2_code":"VI",
    "gn:admin3_code":"24068.0",
    "gn:asciiname":"Pantiere",
    "gn:country_code":"IT",
    "gn:dem":106,
    "gn:feature_class":"P",
    "gn:feature_code":"PPL",
    "gn:name":"Pantiere",
    "gn:population":72,
    "gn:timezone":"Europe/Rome",
    "iso:country":"IT",
    "wof:name":"Pantiere",
    "wof:placetype":"locality",
    "wof:population":72
},
  "geometry": {"coordinates":[11.35043,45.49282],"type":"Point"}
}