{
  "type": "Feature",
  "properties": {
    "gn:admin1_code":"18.0",
    "gn:admin2_code":"TR",
    "gn:admin3_code":"55032.0",
    "gn:asciiname":"L. P. Papigno",
    "gn:country_code":"IT",
    "gn:dem":180,
    "gn:feature_class":"P",
    "gn:feature_code":"PPL",
    "gn:name":"L. P. Papigno",
    "gn:population":50,
    "gn:timezone":"Europe/Rome",
    "iso:country":"IT",
    "wof:name":"L. P. Papigno",
    "wof:placetype":"locality",
    "wof:population":50
},
  "geometry": {"coordinates":[12.6928,42.55305],"type":"Point"}
}