{
  "type": "Feature",
  "properties": {
    "gn:admin1_code":"7.0",
    "gn:admin2_code":"RI",
    "gn:admin3_code":"57003.0",
    "gn:asciiname":"Vignola",
    "gn:country_code":"IT",
    "gn:dem":792,
    "gn:elevation":"808.0",
    "gn:feature_class":"P",
    "gn:feature_code":"PPL",
    "gn:name":"Vignola",
    "gn:population":6,
    "gn:timezone":"Europe/Rome",
    "iso:country":"IT",
    "wof:name":"Vignola",
    "wof:placetype":"locality",
    "wof:population":6
},
  "geometry": {"coordinates":[13.12514,42.40711],"type":"Point"}
}