{
  "type": "Feature",
  "properties": {
    "gn:admin1_code":"5.0",
    "gn:admin2_code":"PR",
    "gn:admin3_code":"34027.0",
    "gn:asciiname":"Case Cocconi",
    "gn:cc2":"IT",
    "gn:country_code":"IT",
    "gn:dem":44,
    "gn:feature_class":"P",
    "gn:feature_code":"PPL",
    "gn:name":"Case Cocconi",
    "gn:population":36,
    "gn:timezone":"Europe/Rome",
    "iso:country":"IT",
    "name:und_x_variant":[
        "Casa Cocconi",
        "Cocconi"
    ],
    "wof:name":"Case Cocconi",
    "wof:placetype":"locality",
    "wof:population":36
},
  "geometry": {"coordinates":[10.25986,44.84861],"type":"Point"}
}