{
  "type": "Feature",
  "properties": {
    "gn:admin1_code":"3.0",
    "gn:admin2_code":"CS",
    "gn:admin3_code":"78040.0",
    "gn:asciiname":"Borgo San Marco",
    "gn:country_code":"IT",
    "gn:dem":4,
    "gn:feature_class":"P",
    "gn:feature_code":"PPL",
    "gn:name":"Borgo San Marco",
    "gn:population":0,
    "gn:timezone":"Europe/Rome",
    "iso:country":"IT",
    "wof:name":"Borgo San Marco",
    "wof:placetype":"locality"
},
  "geometry": {"coordinates":[15.93333,39.51667],"type":"Point"}
}