{
  "type": "Feature",
  "properties": {
    "gn:admin1_code":"7.0",
    "gn:admin2_code":"FR",
    "gn:admin3_code":"60013.0",
    "gn:asciiname":"Capodichina I",
    "gn:country_code":"IT",
    "gn:dem":526,
    "gn:feature_class":"P",
    "gn:feature_code":"PPL",
    "gn:name":"Capodichina I",
    "gn:population":24,
    "gn:timezone":"Europe/Rome",
    "iso:country":"IT",
    "wof:name":"Capodichina I",
    "wof:placetype":"locality",
    "wof:population":24
},
  "geometry": {"coordinates":[13.80389,41.59638],"type":"Point"}
}