{
  "type": "Feature",
  "properties": {
    "gn:admin1_code":"5",
    "gn:admin2_code":"BO",
    "gn:admin3_code":"37062.0",
    "gn:asciiname":"Borgo Capanne",
    "gn:country_code":"IT",
    "gn:dem":615,
    "gn:feature_class":"P",
    "gn:feature_code":"PPL",
    "gn:name":"Borgo Capanne",
    "gn:population":94,
    "gn:timezone":"Europe/Rome",
    "iso:country":"IT",
    "wof:name":"Borgo Capanne",
    "wof:placetype":"locality",
    "wof:population":94
},
  "geometry": {"coordinates":[10.97397,44.13295],"type":"Point"}
}