{
  "type": "Feature",
  "properties": {
    "gn:admin1_code":"17",
    "gn:admin2_code":"TN",
    "gn:admin3_code":"22006.0",
    "gn:asciiname":"Grotta",
    "gn:country_code":"IT",
    "gn:dem":78,
    "gn:feature_class":"P",
    "gn:feature_code":"PPL",
    "gn:name":"Grotta",
    "gn:population":68,
    "gn:timezone":"Europe/Rome",
    "iso:country":"IT",
    "wof:name":"Grotta",
    "wof:placetype":"locality",
    "wof:population":68
},
  "geometry": {"coordinates":[10.86702,45.89339],"type":"Point"}
}