{
  "type": "Feature",
  "properties": {
    "gn:admin1_code":"3",
    "gn:admin2_code":"CS",
    "gn:admin3_code":"78092.0",
    "gn:asciiname":"Nuppolara",
    "gn:country_code":"IT",
    "gn:dem":424,
    "gn:feature_class":"P",
    "gn:feature_code":"PPL",
    "gn:name":"Nuppolara",
    "gn:population":51,
    "gn:timezone":"Europe/Rome",
    "iso:country":"IT",
    "wof:name":"Nuppolara",
    "wof:placetype":"locality",
    "wof:population":51
},
  "geometry": {"coordinates":[15.93366,39.90419],"type":"Point"}
}