{
  "type": "Feature",
  "properties": {
    "gn:admin1_code":"5",
    "gn:admin2_code":"RE",
    "gn:admin3_code":"35021.0",
    "gn:asciiname":"Rifugio",
    "gn:country_code":"IT",
    "gn:dem":19,
    "gn:feature_class":"P",
    "gn:feature_code":"PPL",
    "gn:name":"Rifugio",
    "gn:population":21,
    "gn:timezone":"Europe/Rome",
    "iso:country":"IT",
    "wof:name":"Rifugio",
    "wof:placetype":"locality",
    "wof:population":21
},
  "geometry": {"coordinates":[10.82393,44.88216],"type":"Point"}
}