{
  "type": "Feature",
  "properties": {
    "gn:admin1_code":"5.0",
    "gn:admin2_code":"RE",
    "gn:admin3_code":"35003.0",
    "gn:asciiname":"Villa",
    "gn:country_code":"IT",
    "gn:dem":433,
    "gn:feature_class":"P",
    "gn:feature_code":"PPL",
    "gn:name":"Villa",
    "gn:population":20,
    "gn:timezone":"Europe/Rome",
    "iso:country":"IT",
    "wof:name":"Villa",
    "wof:placetype":"locality",
    "wof:population":20
},
  "geometry": {"coordinates":[10.62376,44.48856],"type":"Point"}
}