{
  "type": "Feature",
  "properties": {
    "gn:admin1_code":"1",
    "gn:admin2_code":"TE",
    "gn:admin3_code":"67041.0",
    "gn:asciiname":"Garrano Basso",
    "gn:country_code":"IT",
    "gn:dem":476,
    "gn:feature_class":"P",
    "gn:feature_code":"PPL",
    "gn:name":"Garrano Basso",
    "gn:population":109,
    "gn:timezone":"Europe/Rome",
    "iso:country":"IT",
    "name:ceb_x_preferred":[
        "Garrano Basso"
    ],
    "name:srp_x_preferred":[
        "\u0413\u0430\u0440\u0430\u043d\u043e \u0411\u0430\u0441\u043e"
    ],
    "wof:name":"Garrano Basso",
    "wof:placetype":"locality",
    "wof:population":109
},
  "geometry": {"coordinates":[13.66218,42.69803],"type":"Point"}
}