{
  "type": "Feature",
  "properties": {
    "gn:admin1_code":"12",
    "gn:admin2_code":"CN",
    "gn:admin3_code":"4133.0",
    "gn:asciiname":"Badoni",
    "gn:country_code":"IT",
    "gn:dem":356,
    "gn:feature_class":"P",
    "gn:feature_code":"PPL",
    "gn:name":"Badoni",
    "gn:population":33,
    "gn:timezone":"Europe/Rome",
    "iso:country":"IT",
    "wof:name":"Badoni",
    "wof:placetype":"locality",
    "wof:population":33
},
  "geometry": {"coordinates":[7.97701,44.83537000000001],"type":"Point"}
}