{
  "type": "Feature",
  "properties": {
    "iso:country":"IT",
    "name:baq_x_preferred":[
        "Le Farine"
    ],
    "name:cat_x_preferred":[
        "Le Farine"
    ],
    "name:cze_x_preferred":[
        "Le Farine"
    ],
    "name:dan_x_preferred":[
        "Le Farine"
    ],
    "name:dut_x_preferred":[
        "Le Farine"
    ],
    "name:eng_x_preferred":[
        "Le Farine"
    ],
    "name:fin_x_preferred":[
        "Le Farine"
    ],
    "name:fre_x_preferred":[
        "Le Farine"
    ],
    "name:ind_x_preferred":[
        "Le Farine"
    ],
    "name:ita_x_preferred":[
        "Le Farine"
    ],
    "name:nno_x_preferred":[
        "Le Farine"
    ],
    "name:nob_x_preferred":[
        "Le Farine"
    ],
    "name:oci_x_preferred":[
        "Le Farine"
    ],
    "name:pol_x_preferred":[
        "Le Farine"
    ],
    "name:por_x_preferred":[
        "Le Farine"
    ],
    "name:rum_x_preferred":[
        "Le Farine"
    ],
    "name:slo_x_preferred":[
        "Le Farine"
    ],
    "name:slv_x_preferred":[
        "Le Farine"
    ],
    "name:spa_x_preferred":[
        "Le Farine"
    ],
    "name:srp_x_preferred":[
        "Le Farine"
    ],
    "name:swe_x_preferred":[
        "Le Farine"
    ],
    "name:tgl_x_preferred":[
        "Le Farine"
    ],
    "name:tur_x_preferred":[
        "Le Farine"
    ],
    "name:war_x_preferred":[
        "Le Farine"
    ],
    "qs_pg:aaroncc":"IT",
    "qs_pg:name":"Le Farine",
    "qs_pg:name_adm0":"Italia",
    "qs_pg:name_adm1":"Lazio",
    "qs_pg:photos":2,
    "qs_pg:photos_1k":1,
    "qs_pg:photos_9k":1,
    "qs_pg:photos_9r":1,
    "qs_pg:photos_all":2,
    "qs_pg:photos_sr":1,
    "qs_pg:pop_sr":0,
    "qs_pg:qs_pg_placetype":"locality",
    "qs_pg:qs_pg_placetype_gp":"Town",
    "qs_pg:woe_adm0":23424853,
    "woe:adm0_id":23424853,
    "woe:name_adm0":"Italia",
    "woe:name_adm1":"Lazio",
    "woe:placetype":"Town",
    "wof:name":"Le Farine",
    "wof:placetype":"locality"
},
  "geometry": {"coordinates":[12.1025235,42.406905],"type":"Point"}
}