{
  "type": "Feature",
  "properties": {
    "gn:admin1_code":"14",
    "gn:admin2_code":"SS",
    "gn:admin3_code":"90052.0",
    "gn:asciiname":"Fraigas",
    "gn:country_code":"IT",
    "gn:dem":202,
    "gn:feature_class":"P",
    "gn:feature_code":"PPL",
    "gn:name":"Fraigas",
    "gn:population":40,
    "gn:timezone":"Europe/Rome",
    "iso:country":"IT",
    "wof:name":"Fraigas",
    "wof:placetype":"locality",
    "wof:population":40
},
  "geometry": {"coordinates":[8.98691,40.62754],"type":"Point"}
}