{
  "type": "Feature",
  "properties": {
    "gn:admin1_code":"7",
    "gn:admin2_code":"VT",
    "gn:admin3_code":"56059.0",
    "gn:asciiname":"Terme",
    "gn:country_code":"IT",
    "gn:dem":261,
    "gn:feature_class":"P",
    "gn:feature_code":"PPL",
    "gn:name":"Terme",
    "gn:population":13,
    "gn:timezone":"Europe/Rome",
    "iso:country":"IT",
    "wof:name":"Terme",
    "wof:placetype":"locality",
    "wof:population":13
},
  "geometry": {"coordinates":[12.06502,42.41425],"type":"Point"}
}