{
  "type": "Feature",
  "properties": {
    "gn:admin1_code":"7",
    "gn:admin2_code":"VT",
    "gn:admin3_code":"56059.0",
    "gn:asciiname":"Terme",
    "gn:country_code":"IT",
    "gn:dem":261,
    "gn:feature_class":"P",
    "gn:feature_code":"PPL",
    "gn:name":"Terme",
    "gn:population":13,
    "gn:timezone":"Europe/Rome",
    "iso:country":"IT",
    "name:ceb_x_preferred":[
        "Terme"
    ],
    "name:deu_x_preferred":[
        "Terme"
    ],
    "name:fas_x_preferred":[
        "\u062a\u0631\u0645\u0647"
    ],
    "name:ita_x_preferred":[
        "Terme"
    ],
    "name:min_x_preferred":[
        "Terme"
    ],
    "name:nld_x_preferred":[
        "Terme"
    ],
    "name:nno_x_preferred":[
        "Terme"
    ],
    "name:vie_x_preferred":[
        "Terme"
    ],
    "name:zho_x_preferred":[
        "\u6cf0\u723e\u6885"
    ],
    "wof:name":"Terme",
    "wof:placetype":"locality",
    "wof:population":13
},
  "geometry": {"coordinates":[12.06502,42.41425],"type":"Point"}
}