{
  "type": "Feature",
  "properties": {
    "gn:admin1_code":"7",
    "gn:admin2_code":"RI",
    "gn:admin3_code":"57027.0",
    "gn:asciiname":"Stallone",
    "gn:country_code":"IT",
    "gn:dem":156,
    "gn:feature_class":"P",
    "gn:feature_code":"PPL",
    "gn:name":"Stallone",
    "gn:population":168,
    "gn:timezone":"Europe/Rome",
    "iso:country":"IT",
    "name:kor_x_preferred":[
        "\uc2a4\ud0e4\ub860"
    ],
    "wof:name":"Stallone",
    "wof:placetype":"locality",
    "wof:population":168
},
  "geometry": {"coordinates":[12.67455,42.19783],"type":"Point"}
}