{
  "type": "Feature",
  "properties": {
    "gn:admin1_code":"20.0",
    "gn:admin2_code":"PD",
    "gn:admin3_code":"28055.0",
    "gn:asciiname":"Santa Cosma I",
    "gn:country_code":"IT",
    "gn:dem":6,
    "gn:feature_class":"P",
    "gn:feature_code":"PPL",
    "gn:name":"Santa Cosma I",
    "gn:population":15,
    "gn:timezone":"Europe/Rome",
    "iso:country":"IT",
    "wof:name":"Santa Cosma I",
    "wof:placetype":"locality",
    "wof:population":15
},
  "geometry": {"coordinates":[11.7769,45.23219],"type":"Point"}
}