{
  "type": "Feature",
  "properties": {
    "gn:admin1_code":"9",
    "gn:admin2_code":"VA",
    "gn:admin3_code":"12075.0",
    "gn:asciiname":"Cascina Inglesina",
    "gn:country_code":"IT",
    "gn:dem":221,
    "gn:feature_class":"P",
    "gn:feature_code":"PPL",
    "gn:name":"Cascina Inglesina",
    "gn:population":26,
    "gn:timezone":"Europe/Rome",
    "iso:country":"IT",
    "wof:name":"Cascina Inglesina",
    "wof:placetype":"locality",
    "wof:population":26
},
  "geometry": {"coordinates":[8.97911,45.63292],"type":"Point"}
}