{
  "type": "Feature",
  "properties": {
    "gn:admin1_code":"20",
    "gn:admin2_code":"PD",
    "gn:admin3_code":"28033.0",
    "gn:asciiname":"Botti",
    "gn:country_code":"IT",
    "gn:dem":0,
    "gn:feature_class":"P",
    "gn:feature_code":"PPL",
    "gn:name":"Botti",
    "gn:population":42,
    "gn:timezone":"Europe/Rome",
    "iso:country":"IT",
    "wof:name":"Botti",
    "wof:placetype":"locality",
    "wof:population":42
},
  "geometry": {"coordinates":[12.09957,45.25265],"type":"Point"}
}