{
  "type": "Feature",
  "properties": {
    "gn:admin1_code":"14.0",
    "gn:admin2_code":"SS",
    "gn:admin3_code":"90064.0",
    "gn:asciiname":"L.P. Truncu Reale",
    "gn:country_code":"IT",
    "gn:dem":63,
    "gn:feature_class":"P",
    "gn:feature_code":"PPL",
    "gn:name":"L.P. Truncu Reale",
    "gn:population":82,
    "gn:timezone":"Europe/Rome",
    "iso:country":"IT",
    "wof:name":"L.P. Truncu Reale",
    "wof:placetype":"locality",
    "wof:population":82
},
  "geometry": {"coordinates":[8.44076,40.77186],"type":"Point"}
}