{
  "type": "Feature",
  "properties": {
    "gn:admin1_code":"6.0",
    "gn:admin2_code":"UD",
    "gn:admin3_code":"30048.0",
    "gn:asciiname":"Nespoledo-Villacaccia",
    "gn:country_code":"IT",
    "gn:dem":53,
    "gn:feature_class":"P",
    "gn:feature_code":"PPL",
    "gn:name":"Nespoledo-Villacaccia",
    "gn:population":858,
    "gn:timezone":"Europe/Rome",
    "iso:country":"IT",
    "wof:name":"Nespoledo-Villacaccia",
    "wof:placetype":"locality",
    "wof:population":858
},
  "geometry": {"coordinates":[13.09083,45.98306],"type":"Point"}
}