{
  "type": "Feature",
  "properties": {
    "gn:admin1_code":"16.0",
    "gn:admin2_code":"GR",
    "gn:admin3_code":"53020.0",
    "gn:asciiname":"Triana",
    "gn:country_code":"IT",
    "gn:dem":758,
    "gn:elevation":"769.0",
    "gn:feature_class":"P",
    "gn:feature_code":"PPL",
    "gn:name":"Triana",
    "gn:population":14,
    "gn:timezone":"Europe/Rome",
    "iso:country":"IT",
    "wof:name":"Triana",
    "wof:placetype":"locality",
    "wof:population":14
},
  "geometry": {"coordinates":[11.54894,42.78837],"type":"Point"}
}