{
  "type": "Feature",
  "properties": {
    "gn:admin1_code":"3.0",
    "gn:admin2_code":"RC",
    "gn:admin3_code":"80025.0",
    "gn:asciiname":"Campoli Cerasara",
    "gn:country_code":"IT",
    "gn:dem":733,
    "gn:feature_class":"P",
    "gn:feature_code":"PPL",
    "gn:name":"Campoli Cerasara",
    "gn:population":145,
    "gn:timezone":"Europe/Rome",
    "iso:country":"IT",
    "wof:name":"Campoli Cerasara",
    "wof:placetype":"locality",
    "wof:population":145
},
  "geometry": {"coordinates":[16.3911,38.45191],"type":"Point"}
}