{
  "type": "Feature",
  "properties": {
    "gn:admin1_code":"6.0",
    "gn:admin2_code":"TS",
    "gn:admin3_code":"32001.0",
    "gn:asciiname":"Precenico Superiore",
    "gn:country_code":"IT",
    "gn:dem":219,
    "gn:feature_class":"P",
    "gn:feature_code":"PPL",
    "gn:name":"Precenico Superiore",
    "gn:population":48,
    "gn:timezone":"Europe/Rome",
    "iso:country":"IT",
    "wof:name":"Precenico Superiore",
    "wof:placetype":"locality",
    "wof:population":48
},
  "geometry": {"coordinates":[13.68098,45.77923],"type":"Point"}
}