{
  "type": "Feature",
  "properties": {
    "gn:admin1_code":"16",
    "gn:admin2_code":"MS",
    "gn:admin3_code":"45016.0",
    "gn:asciiname":"Il Bosco",
    "gn:country_code":"IT",
    "gn:dem":139,
    "gn:feature_class":"P",
    "gn:feature_code":"PPL",
    "gn:name":"Il Bosco",
    "gn:population":16,
    "gn:timezone":"Europe/Rome",
    "iso:country":"IT",
    "wof:name":"Il Bosco",
    "wof:placetype":"locality",
    "wof:population":16
},
  "geometry": {"coordinates":[9.95545,44.2571],"type":"Point"}
}