{
  "type": "Feature",
  "properties": {
    "gn:admin1_code":"4",
    "gn:admin2_code":"SA",
    "gn:admin3_code":"65052.0",
    "gn:asciiname":"Curteri",
    "gn:country_code":"IT",
    "gn:dem":422,
    "gn:feature_class":"P",
    "gn:feature_code":"PPL",
    "gn:name":"Curteri",
    "gn:population":134,
    "gn:timezone":"Europe/Rome",
    "iso:country":"IT",
    "wof:name":"Curteri",
    "wof:placetype":"locality",
    "wof:population":134
},
  "geometry": {"coordinates":[14.81437,40.77818],"type":"Point"}
}