{
  "type": "Feature",
  "properties": {
    "gn:admin1_code":"18",
    "gn:admin2_code":"PG",
    "gn:admin3_code":"54026.0",
    "gn:asciiname":"La Valle",
    "gn:country_code":"IT",
    "gn:dem":239,
    "gn:feature_class":"P",
    "gn:feature_code":"PPL",
    "gn:name":"La Valle",
    "gn:population":77,
    "gn:timezone":"Europe/Rome",
    "iso:country":"IT",
    "wof:name":"La Valle",
    "wof:placetype":"locality",
    "wof:population":77
},
  "geometry": {"coordinates":[12.23287,43.12369],"type":"Point"}
}