{
  "type": "Feature",
  "properties": {
    "gn:admin1_code":"1.0",
    "gn:admin2_code":"TE",
    "gn:admin3_code":"67008.0",
    "gn:asciiname":"Molviano Basso (La Madonna)",
    "gn:country_code":"IT",
    "gn:dem":218,
    "gn:feature_class":"P",
    "gn:feature_code":"PPL",
    "gn:name":"Molviano Basso (La Madonna)",
    "gn:population":21,
    "gn:timezone":"Europe/Rome",
    "iso:country":"IT",
    "wof:name":"Molviano Basso (La Madonna)",
    "wof:placetype":"locality",
    "wof:population":21
},
  "geometry": {"coordinates":[13.72336,42.76172],"type":"Point"}
}