{
  "type": "Feature",
  "properties": {
    "gn:admin1_code":"13",
    "gn:admin2_code":"TA",
    "gn:admin3_code":"73027.0",
    "gn:asciiname":"Torretta Mare",
    "gn:country_code":"IT",
    "gn:dem":3,
    "gn:feature_class":"P",
    "gn:feature_code":"PPLL",
    "gn:name":"Torretta Mare",
    "gn:population":6,
    "gn:timezone":"Europe/Rome",
    "iso:country":"IT",
    "wof:name":"Torretta Mare",
    "wof:placetype":"locality",
    "wof:population":6
},
  "geometry": {"coordinates":[17.41282,40.3328],"type":"Point"}
}