{
  "type": "Feature",
  "properties": {
    "gn:admin1_code":"12",
    "gn:admin2_code":"TO",
    "gn:admin3_code":"1299.0",
    "gn:asciiname":"Gunia Alta",
    "gn:country_code":"IT",
    "gn:dem":255,
    "gn:feature_class":"P",
    "gn:feature_code":"PPL",
    "gn:name":"Gunia Alta",
    "gn:population":21,
    "gn:timezone":"Europe/Rome",
    "iso:country":"IT",
    "wof:name":"Gunia Alta",
    "wof:placetype":"locality",
    "wof:population":21
},
  "geometry": {"coordinates":[7.52222,44.82871],"type":"Point"}
}