{
  "type": "Feature",
  "properties": {
    "gn:admin1_code":"13",
    "gn:admin2_code":"BR",
    "gn:admin3_code":"74005.0",
    "gn:asciiname":"Masseria Piccola",
    "gn:country_code":"IT",
    "gn:dem":311,
    "gn:feature_class":"P",
    "gn:feature_code":"PPL",
    "gn:name":"Masseria Piccola",
    "gn:population":33,
    "gn:timezone":"Europe/Rome",
    "iso:country":"IT",
    "wof:name":"Masseria Piccola",
    "wof:placetype":"locality",
    "wof:population":33
},
  "geometry": {"coordinates":[17.45986,40.73969],"type":"Point"}
}