{
  "type": "Feature",
  "properties": {
    "gn:admin1_code":"20",
    "gn:admin2_code":"VI",
    "gn:admin3_code":"24020.0",
    "gn:asciiname":"Bissoli",
    "gn:country_code":"IT",
    "gn:dem":157,
    "gn:feature_class":"P",
    "gn:feature_code":"PPL",
    "gn:name":"Bissoli",
    "gn:population":67,
    "gn:timezone":"Europe/Rome",
    "iso:country":"IT",
    "wof:name":"Bissoli",
    "wof:placetype":"locality",
    "wof:population":67
},
  "geometry": {"coordinates":[11.51451,45.75864],"type":"Point"}
}