{
  "type": "Feature",
  "properties": {
    "gn:admin1_code":"11",
    "gn:admin2_code":"CB",
    "gn:admin3_code":"70067.0",
    "gn:asciiname":"Acquasalsa",
    "gn:country_code":"IT",
    "gn:dem":557,
    "gn:feature_class":"P",
    "gn:feature_code":"PPL",
    "gn:name":"Acquasalsa",
    "gn:population":43,
    "gn:timezone":"Europe/Rome",
    "iso:country":"IT",
    "wof:name":"Acquasalsa",
    "wof:placetype":"locality",
    "wof:population":43
},
  "geometry": {"coordinates":[14.62599,41.45352000000001],"type":"Point"}
}