{
  "type": "Feature",
  "properties": {
    "gn:elevation":2,
    "gn:population":2658,
    "iso:country":"IT",
    "name:cat_x_preferred":[
        "Burano"
    ],
    "name:ceb_x_preferred":[
        "Burano"
    ],
    "name:ces_x_preferred":[
        "Burano"
    ],
    "name:dan_x_preferred":[
        "Burano"
    ],
    "name:eng_x_preferred":[
        "Burano"
    ],
    "name:eus_x_preferred":[
        "Burano"
    ],
    "name:fin_x_preferred":[
        "Burano"
    ],
    "name:fra_x_preferred":[
        "Burano"
    ],
    "name:ind_x_preferred":[
        "Burano"
    ],
    "name:ita_x_preferred":[
        "Burano"
    ],
    "name:nld_x_preferred":[
        "Burano"
    ],
    "name:nno_x_preferred":[
        "Burano"
    ],
    "name:nob_x_preferred":[
        "Burano"
    ],
    "name:oci_x_preferred":[
        "Burano"
    ],
    "name:pol_x_preferred":[
        "Burano"
    ],
    "name:por_x_preferred":[
        "Burano"
    ],
    "name:ron_x_preferred":[
        "Burano"
    ],
    "name:slk_x_preferred":[
        "Burano"
    ],
    "name:slv_x_preferred":[
        "Burano"
    ],
    "name:spa_x_preferred":[
        "Burano"
    ],
    "name:srp_x_preferred":[
        "Burano"
    ],
    "name:swe_x_preferred":[
        "Burano"
    ],
    "name:tgl_x_preferred":[
        "Burano"
    ],
    "name:tur_x_preferred":[
        "Burano"
    ],
    "name:war_x_preferred":[
        "Burano"
    ],
    "qs:a0":"Italia",
    "qs:a1":"*Venezia",
    "qs:a1r":"0Veneto",
    "qs:adm0":"Italia",
    "qs:la_lc":"*",
    "qs:level":"locality",
    "qs:loc":"Burano",
    "qs:loc_alt":"Burano",
    "qs:pop":0,
    "qs:type":"buffered point",
    "wof:name":"Burano",
    "wof:placetype":"locality",
    "wof:population":2658
},
  "geometry": {"coordinates":[12.41363,45.472698],"type":"Point"}
}