{
  "type": "Feature",
  "properties": {
    "gn:admin1_code":"10",
    "gn:admin2_code":"MC",
    "gn:admin3_code":"43019.0",
    "gn:asciiname":"Castagna",
    "gn:country_code":"IT",
    "gn:dem":473,
    "gn:feature_class":"P",
    "gn:feature_code":"PPL",
    "gn:name":"Castagna",
    "gn:population":43,
    "gn:timezone":"Europe/Rome",
    "iso:country":"IT",
    "name:deu_x_preferred":[
        "Castagna"
    ],
    "name:ita_x_preferred":[
        "Castagna"
    ],
    "name:nld_x_preferred":[
        "Castagna"
    ],
    "name:srp_x_preferred":[
        "Kastanja"
    ],
    "wof:name":"Castagna",
    "wof:placetype":"locality",
    "wof:population":43
},
  "geometry": {"coordinates":[12.91297,43.19326],"type":"Point"}
}