{
  "type": "Feature",
  "properties": {
    "gn:admin1_code":"3.0",
    "gn:admin2_code":"CS",
    "gn:admin3_code":"78108.0",
    "gn:asciiname":"Casa Oliveto",
    "gn:cc2":"IT",
    "gn:country_code":"IT",
    "gn:dem":72,
    "gn:feature_class":"P",
    "gn:feature_code":"PPL",
    "gn:name":"Casa Oliveto",
    "gn:population":0,
    "gn:timezone":"Europe/Rome",
    "iso:country":"IT",
    "name:und_x_variant":[
        "Oliveto",
        "Casa Oliveto"
    ],
    "wof:name":"Casa Oliveto",
    "wof:placetype":"locality"
},
  "geometry": {"coordinates":[16.66667,39.58333],"type":"Point"}
}