{
  "type": "Feature",
  "properties": {
    "gn:admin1_code":"18.0",
    "gn:admin2_code":"PG",
    "gn:admin3_code":"54048.0",
    "gn:asciiname":"Setri",
    "gn:country_code":"IT",
    "gn:dem":783,
    "gn:elevation":"801.0",
    "gn:feature_class":"P",
    "gn:feature_code":"PPL",
    "gn:name":"Setri",
    "gn:population":19,
    "gn:timezone":"Europe/Rome",
    "iso:country":"IT",
    "wof:name":"Setri",
    "wof:placetype":"locality",
    "wof:population":19
},
  "geometry": {"coordinates":[12.94808,42.90703],"type":"Point"}
}