{
  "type": "Feature",
  "properties": {
    "gn:admin1_code":"9",
    "gn:admin2_code":"BS",
    "gn:admin3_code":"17058.0",
    "gn:asciiname":"Cavada Dalaidi",
    "gn:country_code":"IT",
    "gn:dem":895,
    "gn:feature_class":"P",
    "gn:feature_code":"PPL",
    "gn:name":"Cavada Dalaidi",
    "gn:population":43,
    "gn:timezone":"Europe/Rome",
    "iso:country":"IT",
    "wof:name":"Cavada Dalaidi",
    "wof:placetype":"locality",
    "wof:population":43
},
  "geometry": {"coordinates":[10.35887,45.80853],"type":"Point"}
}