{
  "type": "Feature",
  "properties": {
    "gn:admin1_code":"19",
    "gn:admin2_code":"AO",
    "gn:admin3_code":"7007.0",
    "gn:asciiname":"Cuneaz",
    "gn:country_code":"IT",
    "gn:dem":2069,
    "gn:feature_class":"P",
    "gn:feature_code":"PPLL",
    "gn:name":"Cuneaz",
    "gn:population":9,
    "gn:timezone":"Europe/Rome",
    "iso:country":"IT",
    "wof:name":"Cuneaz",
    "wof:placetype":"locality",
    "wof:population":9
},
  "geometry": {"coordinates":[7.75214,45.82812],"type":"Point"}
}