{
  "type": "Feature",
  "properties": {
    "gn:admin1_code":"6",
    "gn:admin2_code":"TS",
    "gn:admin3_code":"32003.0",
    "gn:asciiname":"Farnei",
    "gn:country_code":"IT",
    "gn:dem":6,
    "gn:feature_class":"P",
    "gn:feature_code":"PPL",
    "gn:name":"Farnei",
    "gn:population":57,
    "gn:timezone":"Europe/Rome",
    "iso:country":"IT",
    "wof:name":"Farnei",
    "wof:placetype":"locality",
    "wof:population":57
},
  "geometry": {"coordinates":[13.79701,45.59016],"type":"Point"}
}