{
  "type": "Feature",
  "properties": {
    "gn:admin1_code":"20",
    "gn:admin2_code":"VI",
    "gn:admin3_code":"24052.0",
    "gn:asciiname":"Villaraspa",
    "gn:country_code":"IT",
    "gn:dem":24,
    "gn:feature_class":"P",
    "gn:feature_code":"PPL",
    "gn:name":"Villaraspa",
    "gn:population":29,
    "gn:timezone":"Europe/Rome",
    "iso:country":"IT",
    "wof:name":"Villaraspa",
    "wof:placetype":"locality",
    "wof:population":29
},
  "geometry": {"coordinates":[11.34371,45.38823],"type":"Point"}
}