{
  "type": "Feature",
  "properties": {
    "gn:admin1_code":"8",
    "gn:admin2_code":"GE",
    "gn:admin3_code":"10060.0",
    "gn:asciiname":"Teriasca",
    "gn:country_code":"IT",
    "gn:dem":298,
    "gn:feature_class":"P",
    "gn:feature_code":"PPL",
    "gn:name":"Teriasca",
    "gn:population":316,
    "gn:timezone":"Europe/Rome",
    "iso:country":"IT",
    "wof:name":"Teriasca",
    "wof:placetype":"locality",
    "wof:population":316
},
  "geometry": {"coordinates":[9.09734,44.39454],"type":"Point"}
}