{
  "type": "Feature",
  "properties": {
    "gn:admin1_code":"5.0",
    "gn:admin2_code":"MO",
    "gn:admin3_code":"36006.0",
    "gn:asciiname":"Casale Sant'Antonio",
    "gn:country_code":"IT",
    "gn:dem":35,
    "gn:feature_class":"P",
    "gn:feature_code":"PPL",
    "gn:name":"Casale Sant'Antonio",
    "gn:population":59,
    "gn:timezone":"Europe/Rome",
    "iso:country":"IT",
    "wof:name":"Casale Sant'Antonio",
    "wof:placetype":"locality",
    "wof:population":59
},
  "geometry": {"coordinates":[11.02235,44.61907],"type":"Point"}
}