{
  "type": "Feature",
  "properties": {
    "gn:admin1_code":"12",
    "gn:admin2_code":"TO",
    "gn:admin3_code":"1131.0",
    "gn:asciiname":"Saletta",
    "gn:country_code":"IT",
    "gn:dem":1054,
    "gn:feature_class":"P",
    "gn:feature_code":"PPLL",
    "gn:name":"Saletta",
    "gn:population":10,
    "gn:timezone":"Europe/Rome",
    "iso:country":"IT",
    "wof:name":"Saletta",
    "wof:placetype":"locality",
    "wof:population":10
},
  "geometry": {"coordinates":[7.26528,45.22615],"type":"Point"}
}