{
  "type": "Feature",
  "properties": {
    "gn:admin1_code":"5",
    "gn:admin2_code":"FC",
    "gn:admin3_code":"40050.0",
    "gn:asciiname":"Capanne",
    "gn:country_code":"IT",
    "gn:dem":892,
    "gn:feature_class":"P",
    "gn:feature_code":"PPL",
    "gn:name":"Capanne",
    "gn:population":43,
    "gn:timezone":"Europe/Rome",
    "iso:country":"IT",
    "name:deu_x_preferred":[
        "Capanne"
    ],
    "name:ltz_x_preferred":[
        "Capanne"
    ],
    "name:srp_x_preferred":[
        "Kapane"
    ],
    "wof:name":"Capanne",
    "wof:placetype":"locality",
    "wof:population":43
},
  "geometry": {"coordinates":[12.10802,43.81],"type":"Point"}
}