{
  "type": "Feature",
  "properties": {
    "gn:admin1_code":"20",
    "gn:admin2_code":"TV",
    "gn:admin3_code":"26075.0",
    "gn:asciiname":"Case Brisotto",
    "gn:country_code":"IT",
    "gn:dem":53,
    "gn:feature_class":"P",
    "gn:feature_code":"PPL",
    "gn:name":"Case Brisotto",
    "gn:population":22,
    "gn:timezone":"Europe/Rome",
    "iso:country":"IT",
    "wof:name":"Case Brisotto",
    "wof:placetype":"locality",
    "wof:population":22
},
  "geometry": {"coordinates":[12.28542,45.8363],"type":"Point"}
}