{
  "type": "Feature",
  "properties": {
    "gn:admin1_code":"9",
    "gn:admin2_code":"BG",
    "gn:admin3_code":"16082.0",
    "gn:asciiname":"Calcinone",
    "gn:country_code":"IT",
    "gn:dem":678,
    "gn:feature_class":"P",
    "gn:feature_code":"PPL",
    "gn:name":"Calcinone",
    "gn:population":52,
    "gn:timezone":"Europe/Rome",
    "iso:country":"IT",
    "wof:name":"Calcinone",
    "wof:placetype":"locality",
    "wof:population":52
},
  "geometry": {"coordinates":[9.54309,45.83915],"type":"Point"}
}