{
  "type": "Feature",
  "properties": {
    "gn:admin1_code":"10",
    "gn:admin2_code":"PU",
    "gn:admin3_code":"41059.0",
    "gn:asciiname":"La Celletta",
    "gn:country_code":"IT",
    "gn:dem":167,
    "gn:feature_class":"P",
    "gn:feature_code":"PPL",
    "gn:name":"La Celletta",
    "gn:population":106,
    "gn:timezone":"Europe/Rome",
    "iso:country":"IT",
    "wof:name":"La Celletta",
    "wof:placetype":"locality",
    "wof:population":106
},
  "geometry": {"coordinates":[12.52865,43.81178],"type":"Point"}
}