{
  "type": "Feature",
  "properties": {
    "gn:admin1_code":"12.0",
    "gn:admin2_code":"CN",
    "gn:admin3_code":"4205.0",
    "gn:asciiname":"Sant'Anna",
    "gn:country_code":"IT",
    "gn:dem":1421,
    "gn:feature_class":"P",
    "gn:feature_code":"PPLL",
    "gn:name":"Sant'Anna",
    "gn:population":3,
    "gn:timezone":"Europe/Rome",
    "iso:country":"IT",
    "wof:name":"Sant'Anna",
    "wof:placetype":"locality",
    "wof:population":3
},
  "geometry": {"coordinates":[7.17109,44.56572],"type":"Point"}
}