{
  "type": "Feature",
  "properties": {
    "gn:admin1_code":"20",
    "gn:admin2_code":"PD",
    "gn:admin3_code":"28055.0",
    "gn:asciiname":"Scuola",
    "gn:country_code":"IT",
    "gn:dem":7,
    "gn:feature_class":"P",
    "gn:feature_code":"PPL",
    "gn:name":"Scuola",
    "gn:population":63,
    "gn:timezone":"Europe/Rome",
    "iso:country":"IT",
    "wof:name":"Scuola",
    "wof:placetype":"locality",
    "wof:population":63
},
  "geometry": {"coordinates":[11.71975,45.22413],"type":"Point"}
}