{
  "type": "Feature",
  "properties": {
    "gn:admin1_code":"5.0",
    "gn:admin2_code":"BO",
    "gn:admin3_code":"37005.0",
    "gn:asciiname":"Santa Maria in Duno",
    "gn:country_code":"IT",
    "gn:dem":18,
    "gn:feature_class":"P",
    "gn:feature_code":"PPL",
    "gn:name":"Santa Maria in Duno",
    "gn:population":726,
    "gn:timezone":"Europe/Rome",
    "iso:country":"IT",
    "wof:name":"Santa Maria in Duno",
    "wof:placetype":"locality",
    "wof:population":726
},
  "geometry": {"coordinates":[11.39823,44.62862],"type":"Point"}
}