{
  "type": "Feature",
  "properties": {
    "gn:admin1_code":"20",
    "gn:admin2_code":"PD",
    "gn:admin3_code":"28104.0",
    "gn:asciiname":"Ampezzon",
    "gn:country_code":"IT",
    "gn:dem":10,
    "gn:feature_class":"P",
    "gn:feature_code":"PPL",
    "gn:name":"Ampezzon",
    "gn:population":19,
    "gn:timezone":"Europe/Rome",
    "iso:country":"IT",
    "wof:name":"Ampezzon",
    "wof:placetype":"locality",
    "wof:population":19
},
  "geometry": {"coordinates":[11.9655,45.48119000000001],"type":"Point"}
}