{
  "type": "Feature",
  "properties": {
    "gn:admin1_code":"9.0",
    "gn:admin2_code":"PV",
    "gn:admin3_code":"18036.0",
    "gn:asciiname":"Loglio",
    "gn:country_code":"IT",
    "gn:dem":140,
    "gn:feature_class":"P",
    "gn:feature_code":"PPL",
    "gn:name":"Loglio",
    "gn:population":12,
    "gn:timezone":"Europe/Rome",
    "iso:country":"IT",
    "wof:name":"Loglio",
    "wof:placetype":"locality",
    "wof:population":12
},
  "geometry": {"coordinates":[9.29783,45.01819],"type":"Point"}
}