{
  "type": "Feature",
  "properties": {
    "gn:admin1_code":"9",
    "gn:admin2_code":"BG",
    "gn:admin3_code":"16134.0",
    "gn:asciiname":"Soliva",
    "gn:country_code":"IT",
    "gn:dem":950,
    "gn:feature_class":"P",
    "gn:feature_code":"PPL",
    "gn:name":"Soliva",
    "gn:population":12,
    "gn:timezone":"Europe/Rome",
    "iso:country":"IT",
    "wof:name":"Soliva",
    "wof:placetype":"locality",
    "wof:population":12
},
  "geometry": {"coordinates":[9.66625,46.00222],"type":"Point"}
}