{
  "type": "Feature",
  "properties": {
    "gn:admin1_code":"12",
    "gn:admin2_code":"AL",
    "gn:admin3_code":"6076.0",
    "gn:asciiname":"Cascine Fornace",
    "gn:country_code":"IT",
    "gn:dem":145,
    "gn:feature_class":"P",
    "gn:feature_code":"PPL",
    "gn:name":"Cascine Fornace",
    "gn:population":30,
    "gn:timezone":"Europe/Rome",
    "iso:country":"IT",
    "wof:name":"Cascine Fornace",
    "wof:placetype":"locality",
    "wof:population":30
},
  "geometry": {"coordinates":[8.43499,44.95118],"type":"Point"}
}