{
  "type": "Feature",
  "properties": {
    "gn:admin1_code":"5",
    "gn:admin2_code":"MO",
    "gn:admin3_code":"36015.0",
    "gn:asciiname":"Cartiera",
    "gn:country_code":"IT",
    "gn:dem":72,
    "gn:feature_class":"P",
    "gn:feature_code":"PPL",
    "gn:name":"Cartiera",
    "gn:population":30,
    "gn:timezone":"Europe/Rome",
    "iso:country":"IT",
    "wof:name":"Cartiera",
    "wof:placetype":"locality",
    "wof:population":30
},
  "geometry": {"coordinates":[10.85387,44.58746],"type":"Point"}
}