{
  "type": "Feature",
  "properties": {
    "gn:admin1_code":"12.0",
    "gn:admin2_code":"TO",
    "gn:admin3_code":"1181.0",
    "gn:asciiname":"Dossi San Bernardo",
    "gn:country_code":"IT",
    "gn:dem":237,
    "gn:feature_class":"P",
    "gn:feature_code":"PPL",
    "gn:name":"Dossi San Bernardo",
    "gn:population":358,
    "gn:timezone":"Europe/Rome",
    "iso:country":"IT",
    "wof:name":"Dossi San Bernardo",
    "wof:placetype":"locality",
    "wof:population":358
},
  "geometry": {"coordinates":[7.87886,45.42614],"type":"Point"}
}