{
  "type": "Feature",
  "properties": {
    "gn:admin1_code":"20",
    "gn:admin2_code":"TV",
    "gn:admin3_code":"26064.0",
    "gn:asciiname":"Boiago",
    "gn:country_code":"IT",
    "gn:dem":17,
    "gn:feature_class":"P",
    "gn:feature_code":"PPL",
    "gn:name":"Boiago",
    "gn:population":97,
    "gn:timezone":"Europe/Rome",
    "iso:country":"IT",
    "wof:name":"Boiago",
    "wof:placetype":"locality",
    "wof:population":97
},
  "geometry": {"coordinates":[12.17678,45.65917],"type":"Point"}
}