{
  "type": "Feature",
  "properties": {
    "gn:admin1_code":"12",
    "gn:admin2_code":"CN",
    "gn:admin3_code":"4182.0",
    "gn:asciiname":"Tetto Pollino",
    "gn:country_code":"IT",
    "gn:dem":1060,
    "gn:feature_class":"P",
    "gn:feature_code":"PPLL",
    "gn:name":"Tetto Pollino",
    "gn:population":8,
    "gn:timezone":"Europe/Rome",
    "iso:country":"IT",
    "wof:name":"Tetto Pollino",
    "wof:placetype":"locality",
    "wof:population":8
},
  "geometry": {"coordinates":[7.37169,44.36171],"type":"Point"}
}