{
  "type": "Feature",
  "properties": {
    "gn:admin1_code":"5",
    "gn:admin2_code":"FE",
    "gn:admin3_code":"38008.0",
    "gn:asciiname":"Il Castello",
    "gn:country_code":"IT",
    "gn:dem":7,
    "gn:feature_class":"P",
    "gn:feature_code":"PPL",
    "gn:name":"Il Castello",
    "gn:population":15,
    "gn:timezone":"Europe/Rome",
    "iso:country":"IT",
    "wof:name":"Il Castello",
    "wof:placetype":"locality",
    "wof:population":15
},
  "geometry": {"coordinates":[11.64618,44.72925],"type":"Point"}
}