{
  "type": "Feature",
  "properties": {
    "gn:admin1_code":"19",
    "gn:admin2_code":"AO",
    "gn:admin3_code":"7054.0",
    "gn:asciiname":"Avisod",
    "gn:country_code":"IT",
    "gn:dem":1385,
    "gn:feature_class":"P",
    "gn:feature_code":"PPL",
    "gn:name":"Avisod",
    "gn:population":21,
    "gn:timezone":"Europe/Rome",
    "iso:country":"IT",
    "wof:name":"Avisod",
    "wof:placetype":"locality",
    "wof:population":21
},
  "geometry": {"coordinates":[7.43235,45.75988],"type":"Point"}
}