{
  "type": "Feature",
  "properties": {
    "gn:admin1_code":"6",
    "gn:admin2_code":"UD",
    "gn:admin3_code":"30116.0",
    "gn:asciiname":"Borgne",
    "gn:country_code":"IT",
    "gn:dem":280,
    "gn:feature_class":"P",
    "gn:feature_code":"PPL",
    "gn:name":"Borgne",
    "gn:population":19,
    "gn:timezone":"Europe/Rome",
    "iso:country":"IT",
    "wof:name":"Borgne",
    "wof:placetype":"locality",
    "wof:population":19
},
  "geometry": {"coordinates":[13.23114,46.23282],"type":"Point"}
}