{
  "type": "Feature",
  "properties": {
    "gn:admin1_code":"6",
    "gn:admin2_code":"UD",
    "gn:admin3_code":"30116.0",
    "gn:asciiname":"Borgne",
    "gn:country_code":"IT",
    "gn:dem":280,
    "gn:feature_class":"P",
    "gn:feature_code":"PPL",
    "gn:name":"Borgne",
    "gn:population":19,
    "gn:timezone":"Europe/Rome",
    "iso:country":"IT",
    "name:ara_x_preferred":[
        "\u0628\u0648\u0631\u0646\u064a"
    ],
    "name:ceb_x_preferred":[
        "Borgne"
    ],
    "name:fra_x_preferred":[
        "Borgne"
    ],
    "name:hat_x_preferred":[
        "Ob\u00f2y"
    ],
    "name:ita_x_preferred":[
        "Borgne"
    ],
    "name:nld_x_preferred":[
        "Borgne"
    ],
    "name:por_x_preferred":[
        "Borgne"
    ],
    "name:ron_x_preferred":[
        "Borgne"
    ],
    "name:spa_x_preferred":[
        "Borgne"
    ],
    "name:swe_x_preferred":[
        "Borgne"
    ],
    "wof:name":"Borgne",
    "wof:placetype":"locality",
    "wof:population":19
},
  "geometry": {"coordinates":[13.23114,46.23282],"type":"Point"}
}