{
  "type": "Feature",
  "properties": {
    "gn:admin1_code":"7",
    "gn:admin2_code":"FR",
    "gn:admin3_code":"60046.0",
    "gn:asciiname":"Zancati Vecchio",
    "gn:country_code":"IT",
    "gn:dem":299,
    "gn:feature_class":"P",
    "gn:feature_code":"PPL",
    "gn:name":"Zancati Vecchio",
    "gn:population":29,
    "gn:timezone":"Europe/Rome",
    "iso:country":"IT",
    "wof:name":"Zancati Vecchio",
    "wof:placetype":"locality",
    "wof:population":29
},
  "geometry": {"coordinates":[13.05706,41.77541],"type":"Point"}
}