{
  "type": "Feature",
  "properties": {
    "gn:admin1_code":"16",
    "gn:admin2_code":"PI",
    "gn:admin3_code":"50033.0",
    "gn:asciiname":"Bocciardi",
    "gn:country_code":"IT",
    "gn:dem":35,
    "gn:feature_class":"P",
    "gn:feature_code":"PPL",
    "gn:name":"Bocciardi",
    "gn:population":60,
    "gn:timezone":"Europe/Rome",
    "iso:country":"IT",
    "wof:name":"Bocciardi",
    "wof:placetype":"locality",
    "wof:population":60
},
  "geometry": {"coordinates":[10.71213,43.76235],"type":"Point"}
}