{
  "type": "Feature",
  "properties": {
    "gn:admin1_code":"20",
    "gn:admin2_code":"VR",
    "gn:admin3_code":"23089.0",
    "gn:asciiname":"Vantini",
    "gn:country_code":"IT",
    "gn:dem":75,
    "gn:feature_class":"P",
    "gn:feature_code":"PPL",
    "gn:name":"Vantini",
    "gn:population":28,
    "gn:timezone":"Europe/Rome",
    "iso:country":"IT",
    "wof:name":"Vantini",
    "wof:placetype":"locality",
    "wof:population":28
},
  "geometry": {"coordinates":[10.77902,45.37948],"type":"Point"}
}