{
  "type": "Feature",
  "properties": {
    "gn:admin1_code":"4.0",
    "gn:admin2_code":"CE",
    "gn:admin3_code":"61017.0",
    "gn:asciiname":"San Donato",
    "gn:country_code":"IT",
    "gn:dem":94,
    "gn:elevation":"102.0",
    "gn:feature_class":"P",
    "gn:feature_code":"PPL",
    "gn:name":"San Donato",
    "gn:population":190,
    "gn:timezone":"Europe/Rome",
    "iso:country":"IT",
    "name:ceb_x_preferred":[
        "San Donato"
    ],
    "name:deu_x_preferred":[
        "San Donato"
    ],
    "name:fra_x_preferred":[
        "San Donato"
    ],
    "name:glg_x_preferred":[
        "San Donato"
    ],
    "name:ita_x_preferred":[
        "San Donato"
    ],
    "name:lmo_x_preferred":[
        "San Donaa"
    ],
    "name:nld_x_preferred":[
        "San Donato"
    ],
    "name:pms_x_preferred":[
        "San Donato"
    ],
    "name:por_x_preferred":[
        "San Donato"
    ],
    "name:rus_x_preferred":[
        "\u0421\u0430\u043d-\u0414\u043e\u043d\u0430\u0442\u043e"
    ],
    "name:spa_x_preferred":[
        "San Donato"
    ],
    "name:srp_x_preferred":[
        "\u0421\u0430\u043d \u0414\u043e\u043d\u0430\u0442\u043e"
    ],
    "name:swe_x_preferred":[
        "San Donato"
    ],
    "wof:name":"San Donato",
    "wof:placetype":"locality",
    "wof:population":190
},
  "geometry": {"coordinates":[13.99382,41.20017],"type":"Point"}
}