{
  "type": "Feature",
  "properties": {
    "gn:admin1_code":"4.0",
    "gn:admin2_code":"CE",
    "gn:admin3_code":"61017.0",
    "gn:asciiname":"San Donato",
    "gn:country_code":"IT",
    "gn:dem":94,
    "gn:elevation":"102.0",
    "gn:feature_class":"P",
    "gn:feature_code":"PPL",
    "gn:name":"San Donato",
    "gn:population":190,
    "gn:timezone":"Europe/Rome",
    "iso:country":"IT",
    "wof:name":"San Donato",
    "wof:placetype":"locality",
    "wof:population":190
},
  "geometry": {"coordinates":[13.99382,41.20017],"type":"Point"}
}