{
  "type": "Feature",
  "properties": {
    "gn:admin1_code":"9",
    "gn:admin2_code":"BG",
    "gn:admin3_code":"16208.0",
    "gn:asciiname":"Mezzasco",
    "gn:country_code":"IT",
    "gn:dem":337,
    "gn:feature_class":"P",
    "gn:feature_code":"PPL",
    "gn:name":"Mezzasco",
    "gn:population":28,
    "gn:timezone":"Europe/Rome",
    "iso:country":"IT",
    "wof:name":"Mezzasco",
    "wof:placetype":"locality",
    "wof:population":28
},
  "geometry": {"coordinates":[9.57676,45.7805],"type":"Point"}
}