{
  "type": "Feature",
  "properties": {
    "gn:admin1_code":"1",
    "gn:admin2_code":"CH",
    "gn:admin3_code":"69065.0",
    "gn:asciiname":"San Pastore",
    "gn:country_code":"IT",
    "gn:dem":234,
    "gn:feature_class":"P",
    "gn:feature_code":"PPL",
    "gn:name":"San Pastore",
    "gn:population":58,
    "gn:timezone":"Europe/Rome",
    "iso:country":"IT",
    "wof:name":"San Pastore",
    "wof:placetype":"locality",
    "wof:population":58
},
  "geometry": {"coordinates":[14.40445,42.1019],"type":"Point"}
}