{
  "type": "Feature",
  "properties": {
    "gn:admin1_code":"2.0",
    "gn:admin2_code":"MT",
    "gn:admin3_code":"77003.0",
    "gn:asciiname":"Santa Palagina II",
    "gn:country_code":"IT",
    "gn:dem":2,
    "gn:feature_class":"P",
    "gn:feature_code":"PPL",
    "gn:name":"Santa Palagina II",
    "gn:population":0,
    "gn:timezone":"Europe/Rome",
    "iso:country":"IT",
    "wof:name":"Santa Palagina II",
    "wof:placetype":"locality"
},
  "geometry": {"coordinates":[16.82917999999999,40.36535],"type":"Point"}
}