{
  "type": "Feature",
  "properties": {
    "gn:admin1_code":"5",
    "gn:admin2_code":"RE",
    "gn:admin3_code":"35013.0",
    "gn:asciiname":"Brugna",
    "gn:country_code":"IT",
    "gn:dem":257,
    "gn:feature_class":"P",
    "gn:feature_code":"PPL",
    "gn:name":"Brugna",
    "gn:population":125,
    "gn:timezone":"Europe/Rome",
    "iso:country":"IT",
    "wof:name":"Brugna",
    "wof:placetype":"locality",
    "wof:population":125
},
  "geometry": {"coordinates":[10.52717,44.55911],"type":"Point"}
}