{
  "type": "Feature",
  "properties": {
    "gn:admin1_code":"5",
    "gn:admin2_code":"BO",
    "gn:admin3_code":"37057.0",
    "gn:asciiname":"Cinque Cerri",
    "gn:country_code":"IT",
    "gn:dem":121,
    "gn:feature_class":"P",
    "gn:feature_code":"PPL",
    "gn:name":"Cinque Cerri",
    "gn:population":82,
    "gn:timezone":"Europe/Rome",
    "iso:country":"IT",
    "wof:name":"Cinque Cerri",
    "wof:placetype":"locality",
    "wof:population":82
},
  "geometry": {"coordinates":[11.26355,44.35923],"type":"Point"}
}