{
  "type": "Feature",
  "properties": {
    "gn:admin1_code":"12.0",
    "gn:admin2_code":"CN",
    "gn:admin3_code":"4139.0",
    "gn:asciiname":"Alborne",
    "gn:country_code":"IT",
    "gn:dem":1290,
    "gn:feature_class":"P",
    "gn:feature_code":"PPLL",
    "gn:name":"Alborn\u00e8",
    "gn:population":2,
    "gn:timezone":"Europe/Rome",
    "iso:country":"IT",
    "name:und_x_variant":[
        "Alborn\u00e8"
    ],
    "wof:name":"Alborne",
    "wof:placetype":"locality",
    "wof:population":2
},
  "geometry": {"coordinates":[7.29089,44.37723],"type":"Point"}
}