{
  "type": "Feature",
  "properties": {
    "gn:admin1_code":"10.0",
    "gn:admin2_code":"MC",
    "gn:admin3_code":"43021.0",
    "gn:asciiname":"San Girolamo di Sopra",
    "gn:cc2":"IT",
    "gn:country_code":"IT",
    "gn:dem":451,
    "gn:feature_class":"P",
    "gn:feature_code":"PPL",
    "gn:name":"San Girolamo di Sopra",
    "gn:population":0,
    "gn:timezone":"Europe/Rome",
    "iso:country":"IT",
    "name:und_x_variant":[
        "San Gir\u00f3lamo",
        "San Girolamo di Sopra"
    ],
    "wof:name":"San Girolamo di Sopra",
    "wof:placetype":"locality"
},
  "geometry": {"coordinates":[13.36667,43.05],"type":"Point"}
}